Protoss_Gateway 2 6407
Protoss_Assimilator 2 3682
Protoss_Cybernetics_Core 1 4905
Protoss_Dragoon 8 10615
Protoss_Zealot 3 9551
Protoss_Robotics_Facility 1 9119
Protoss_Shuttle 1 9953
Protoss_Robotics_Support_Bay 1 9557
Protoss_Observatory 1 10412
Protoss_Reaver 1 11579
11579
