Protoss_Gateway 2 5962
Protoss_Assimilator 1 3148
Protoss_Cybernetics_Core 1 4272
Protoss_Dragoon 10 11066
Protoss_Nexus 2 11278
Protoss_Robotics_Facility 1 9365
Protoss_Observatory 1 9473
Protoss_Observer 2 10938
11278
