Protoss_Nexus 2 11531
Protoss_Gateway 3 7896
Protoss_Assimilator 2 10098
Protoss_Cybernetics_Core 1 5518
Protoss_Dragoon 10 10171
Protoss_Robotics_Facility 1 9833
Protoss_Citadel_of_Adun 1 10189
Protoss_Observatory 1 9953
Protoss_Shuttle 1 10816
Protoss_Zealot 1 10816
11531
