Protoss_Gateway 2 7755
Protoss_Assimilator 1 3387
Protoss_Cybernetics_Core 1 4478
Protoss_Dragoon 10 11133
Protoss_Nexus 2 10978
Protoss_Robotics_Facility 1 10704
Protoss_Zealot 1 10291
11133
