Protoss_Gateway 3 11245
Protoss_Assimilator 1 3246
Protoss_Cybernetics_Core 1 4377
Protoss_Dragoon 6 10931
Protoss_Robotics_Facility 1 6297
Protoss_Shuttle 1 7246
Protoss_Zealot 2 7835
Protoss_Observatory 2 8929
Protoss_Robotics_Support_Bay 1 7507
Protoss_Reaver 1 9011
Protoss_Nexus 1 11748
Protoss_Scarab 4 9958
11748
