Protoss_Gateway 2 7283
Protoss_Assimilator 1 2283
Protoss_Cybernetics_Core 1 2988
Protoss_Dragoon 5 8336
Protoss_Robotics_Facility 1 4562
Protoss_Shuttle 1 5896
Protoss_Robotics_Support_Bay 1 6128
Protoss_Citadel_of_Adun 1 6403
Protoss_Reaver 2 8776
Protoss_Templar_Archives 1 7643
Protoss_Scarab 3 9028
Protoss_Dark_Templar 3 9661
9661
