Protoss_Gateway 3 10385
Protoss_Zealot 5 5626
Protoss_Assimilator 1 5869
Protoss_Cybernetics_Core 1 6718
Protoss_Dragoon 6 10571
Protoss_Robotics_Facility 1 9163
Protoss_Observatory 1 9548
Protoss_Observer 1 10651
10651
