Protoss_Gateway 2 7201
Protoss_Assimilator 1 3236
Protoss_Cybernetics_Core 1 4469
Protoss_Dragoon 9 10147
Protoss_Nexus 1 9781
Protoss_Robotics_Facility 1 10037
Protoss_Zealot 2 10957
Protoss_Shuttle 1 10941
10957
