Protoss_Gateway 5 10998
Protoss_Assimilator 1 3221
Protoss_Zealot 1 3856
Protoss_Cybernetics_Core 1 5170
Protoss_Dragoon 11 11161
Protoss_Nexus 1 9669
Protoss_Robotics_Facility 1 10218
Protoss_Observatory 1 10349
11161
