Protoss_Gateway 2 7532
Protoss_Assimilator 1 3438
Protoss_Cybernetics_Core 1 4498
Protoss_Dragoon 8 10071
Protoss_Nexus 2 12283
Protoss_Stargate 1 9908
Protoss_Forge 1 9747
Protoss_Photon_Cannon 1 11003
Protoss_Scout 1 11841
12283
