Protoss_Gateway 2 4874
Protoss_Assimilator 1 3177
Protoss_Cybernetics_Core 1 4289
Protoss_Dragoon 8 10679
Protoss_Citadel_of_Adun 1 7371
Protoss_Zealot 2 7499
Protoss_Templar_Archives 1 8727
Protoss_Dark_Templar 2 9529
Protoss_Nexus 1 12163
12163
