Protoss_Gateway 4 10011
Protoss_Assimilator 1 3199
Protoss_Cybernetics_Core 1 4374
Protoss_Dragoon 6 8057
Protoss_Citadel_of_Adun 2 9522
Protoss_Nexus 1 10696
Protoss_Robotics_Facility 1 9939
Protoss_Templar_Archives 1 10531
Protoss_Shuttle 1 10763
Protoss_Observatory 1 10183
10763
