Protoss_Gateway 2 8541
Protoss_Assimilator 2 5364
Protoss_Zealot 5 6403
Protoss_Cybernetics_Core 1 6758
Protoss_Dragoon 5 10771
Protoss_Citadel_of_Adun 1 7987
Protoss_Templar_Archives 1 9051
Protoss_Dark_Templar 2 10505
10771
