Protoss_Assimilator 1 2751
Protoss_Gateway 4 11342
Protoss_Cybernetics_Core 1 4854
Protoss_Zealot 3 10498
Protoss_Robotics_Facility 1 6443
Protoss_Dragoon 7 9986
Protoss_Observatory 1 6678
Protoss_Observer 3 8891
Protoss_Citadel_of_Adun 1 9950
11342
