Protoss_Gateway 2 6323
Protoss_Assimilator 1 3250
Protoss_Cybernetics_Core 1 4301
Protoss_Dragoon 10 11051
Protoss_Zealot 5 10046
Protoss_Robotics_Facility 1 10302
Protoss_Nexus 1 12323
12323
