Protoss_Gateway 2 7963
Protoss_Assimilator 1 3245
Protoss_Zealot 1 3801
Protoss_Cybernetics_Core 1 4577
Protoss_Dragoon 10 11117
Protoss_Robotics_Facility 1 7549
Protoss_Observatory 1 7701
Protoss_Observer 2 9291
Protoss_Nexus 1 11272
Protoss_Citadel_of_Adun 1 10152
11272
