Protoss_Gateway 4 10707
Protoss_Assimilator 1 3421
Protoss_Cybernetics_Core 1 4727
Protoss_Dragoon 6 10981
Protoss_Robotics_Facility 1 7536
Protoss_Nexus 1 9556
Protoss_Citadel_of_Adun 1 8593
Protoss_Shuttle 1 9091
Protoss_Observatory 1 8776
Protoss_Observer 1 10317
10981
