Protoss_Gateway 4 10748
Protoss_Assimilator 1 3508
Protoss_Cybernetics_Core 1 5109
Protoss_Dragoon 10 10971
Protoss_Robotics_Facility 1 7703
Protoss_Observatory 1 7852
Protoss_Observer 2 9268
Protoss_Nexus 1 11681
11681
