Protoss_Gateway 2 6008
Protoss_Assimilator 1 3224
Protoss_Cybernetics_Core 1 4330
Protoss_Dragoon 10 9637
Protoss_Zealot 3 10641
Protoss_Robotics_Facility 1 9081
Protoss_Shuttle 1 9889
Protoss_Robotics_Support_Bay 1 9513
Protoss_Reaver 1 11237
11237
