Protoss_Gateway 2 7715
Protoss_Assimilator 1 3473
Protoss_Cybernetics_Core 1 4528
Protoss_Dragoon 10 11165
Protoss_Robotics_Facility 1 6646
Protoss_Observatory 1 6801
Protoss_Observer 2 9071
Protoss_Zealot 1 7831
Protoss_Shuttle 1 10781
11165
