Protoss_Gateway 3 11378
Protoss_Assimilator 1 3268
Protoss_Cybernetics_Core 1 4580
Protoss_Dragoon 9 10341
Protoss_Nexus 1 9811
Protoss_Robotics_Facility 1 10233
Protoss_Zealot 2 9786
Protoss_Observatory 1 10383
11378
