Protoss_Gateway 3 11034
Protoss_Assimilator 1 3488
Protoss_Cybernetics_Core 1 4678
Protoss_Dragoon 11 10875
Protoss_Robotics_Facility 1 7718
Protoss_Observatory 1 7856
Protoss_Observer 2 10496
Protoss_Nexus 1 11938
11938
