Protoss_Gateway 3 8378
Protoss_Assimilator 1 3163
Protoss_Cybernetics_Core 1 4328
Protoss_Dragoon 9 10933
Protoss_Nexus 1 8916
Protoss_Robotics_Facility 1 9754
Protoss_Zealot 3 9161
Protoss_Observatory 1 9848
10933
