Protoss_Gateway 2 7770
Protoss_Assimilator 1 3139
Protoss_Cybernetics_Core 1 4269
Protoss_Dragoon 5 11015
Protoss_Citadel_of_Adun 1 6890
Protoss_Robotics_Facility 1 7927
Protoss_Templar_Archives 1 8221
Protoss_Shuttle 2 11295
Protoss_Dark_Templar 3 10177
Protoss_Nexus 1 11764
11764
