Protoss_Gateway 2 7668
Protoss_Assimilator 1 3362
Protoss_Cybernetics_Core 1 4460
Protoss_Dragoon 8 10301
Protoss_Robotics_Facility 1 7323
Protoss_Observatory 1 7697
Protoss_Observer 1 8579
Protoss_Nexus 1 10707
Protoss_Shuttle 1 9795
Protoss_Robotics_Support_Bay 1 9392
Protoss_Reaver 1 11013
Protoss_Zealot 2 10813
11013
