Protoss_Assimilator 2 5438
Protoss_Gateway 3 11063
Protoss_Cybernetics_Core 1 4722
Protoss_Robotics_Facility 1 6226
Protoss_Dragoon 9 10721
Protoss_Observatory 1 6470
Protoss_Observer 2 7888
Protoss_Shuttle 2 9996
Protoss_Zealot 2 9503
11063
