Protoss_Nexus 1 5644
Protoss_Gateway 4 10425
Protoss_Assimilator 1 4364
Protoss_Cybernetics_Core 1 5548
Protoss_Zealot 4 10916
Protoss_Dragoon 7 11181
Protoss_Robotics_Facility 1 8015
Protoss_Shuttle 1 8871
Protoss_Robotics_Support_Bay 1 8369
Protoss_Observatory 1 8463
Protoss_Observer 1 10141
11181
