Protoss_Gateway 3 9938
Protoss_Assimilator 2 10557
Protoss_Cybernetics_Core 1 4379
Protoss_Dragoon 10 10771
Protoss_Nexus 1 8904
Protoss_Robotics_Facility 1 8993
Protoss_Observatory 1 9350
Protoss_Robotics_Support_Bay 1 9970
Protoss_Observer 1 10256
10771
