Protoss_Gateway 1 3417
Protoss_Assimilator 1 3258
Protoss_Cybernetics_Core 1 4537
Protoss_Zealot 4 6528
Protoss_Robotics_Facility 1 6124
Protoss_Shuttle 1 6931
Protoss_Robotics_Support_Bay 1 6718
Protoss_Reaver 2 10563
Protoss_Dragoon 3 10971
Protoss_Observatory 1 8005
Protoss_Observer 1 9241
Protoss_Shield_Battery 1 9968
10971
