Protoss_Gateway 2 5070
Protoss_Assimilator 2 8751
Protoss_Cybernetics_Core 1 4427
Protoss_Dragoon 6 11073
Protoss_Nexus 1 9179
Protoss_Citadel_of_Adun 1 8474
Protoss_Robotics_Facility 1 9423
Protoss_Templar_Archives 1 9464
Protoss_Shuttle 1 10263
Protoss_Dark_Templar 3 10985
Protoss_Stargate 1 11244
11244
