Protoss_Gateway 3 7901
Protoss_Zealot 7 10495
Protoss_Assimilator 1 4459
Protoss_Cybernetics_Core 1 5467
Protoss_Dragoon 8 9695
Protoss_Robotics_Facility 1 9404
Protoss_Shuttle 1 10203
Protoss_Robotics_Support_Bay 1 9957
Protoss_Reaver 1 11447
11447
