Protoss_Gateway 2 5399
Protoss_Assimilator 1 3723
Protoss_Zealot 6 10253
Protoss_Cybernetics_Core 1 4961
Protoss_Dragoon 11 11125
Protoss_Robotics_Facility 1 9093
Protoss_Shuttle 1 10003
Protoss_Robotics_Support_Bay 1 9690
Protoss_Reaver 1 11405
11405
