Protoss_Nexus 1 5518
Protoss_Gateway 4 9988
Protoss_Assimilator 2 7584
Protoss_Cybernetics_Core 1 5670
Protoss_Zealot 3 10249
Protoss_Dragoon 14 11182
Protoss_Robotics_Facility 1 8443
Protoss_Shield_Battery 1 7753
Protoss_Observatory 1 9677
Protoss_Observer 1 10481
Protoss_Citadel_of_Adun 1 11065
11182
