Protoss_Nexus 1 5674
Protoss_Gateway 2 7795
Protoss_Assimilator 2 7620
Protoss_Cybernetics_Core 1 5755
Protoss_Forge 1 5585
Protoss_Photon_Cannon 2 8696
Protoss_Dragoon 2 7305
Protoss_Citadel_of_Adun 1 6967
Protoss_Templar_Archives 1 7994
Protoss_Zealot 1 7817
Protoss_Dark_Templar 3 9529
Protoss_Robotics_Facility 1 9654
Protoss_Shuttle 1 10561
Protoss_High_Templar 2 10635
10635
