Protoss_Gateway 2 8276
Protoss_Assimilator 1 3528
Protoss_Cybernetics_Core 1 4631
Protoss_Dragoon 6 10341
Protoss_Robotics_Facility 1 6745
Protoss_Observatory 1 6973
Protoss_Observer 3 10208
10341
