Protoss_Gateway 2 7489
Protoss_Assimilator 1 3286
Protoss_Cybernetics_Core 1 4416
Protoss_Dragoon 6 10605
Protoss_Robotics_Facility 1 7605
Protoss_Observatory 1 7709
Protoss_Nexus 1 10345
Protoss_Shuttle 1 9093
Protoss_Robotics_Support_Bay 1 8545
Protoss_Reaver 1 10289
Protoss_Zealot 2 9663
Protoss_Observer 1 10621
10621
