Protoss_Gateway 4 10777
Protoss_Assimilator 1 3225
Protoss_Cybernetics_Core 1 4463
Protoss_Zealot 1 4781
Protoss_Dragoon 8 10805
Protoss_Nexus 1 9057
Protoss_Robotics_Facility 1 8513
Protoss_Shuttle 1 9393
Protoss_Robotics_Support_Bay 1 8904
Protoss_Reaver 1 10535
Protoss_Observatory 1 9698
Protoss_Observer 1 10867
10867
