Protoss_Gateway 4 10339
Protoss_Assimilator 1 3309
Protoss_Cybernetics_Core 1 4386
Protoss_Dragoon 9 10605
Protoss_Robotics_Facility 1 7371
Protoss_Observatory 1 7561
Protoss_Nexus 2 11512
Protoss_Observer 3 10219
11512
