Protoss_Gateway 1 3393
Protoss_Assimilator 1 3458
Protoss_Cybernetics_Core 1 4473
Protoss_Dragoon 7 10886
Protoss_Robotics_Facility 1 7786
Protoss_Shuttle 1 8591
Protoss_Robotics_Support_Bay 1 8001
Protoss_Reaver 1 9771
Protoss_Observatory 1 8861
Protoss_Observer 2 10705
Protoss_Zealot 1 10608
10886
