Protoss_Gateway 3 11014
Protoss_Assimilator 1 3530
Protoss_Cybernetics_Core 1 4720
Protoss_Dragoon 6 8251
Protoss_Citadel_of_Adun 1 7794
Protoss_Templar_Archives 1 8788
Protoss_Dark_Templar 5 11146
Protoss_Nexus 1 12103
12103
