Protoss_Gateway 2 6953
Protoss_Zealot 4 8785
Protoss_Assimilator 1 4045
Protoss_Cybernetics_Core 1 5290
Protoss_Dragoon 7 10185
Protoss_Robotics_Facility 1 8121
Protoss_Nexus 1 10353
Protoss_Observatory 1 8327
Protoss_Observer 1 9103
Protoss_Shuttle 1 10194
Protoss_Robotics_Support_Bay 1 10050
Protoss_Reaver 1 11541
11541
