Protoss_Gateway 2 7140
Protoss_Assimilator 1 3271
Protoss_Cybernetics_Core 1 4365
Protoss_Dragoon 10 10453
Protoss_Robotics_Facility 1 7330
Protoss_Observatory 1 7428
Protoss_Observer 2 9273
Protoss_Nexus 1 10976
Protoss_Shuttle 1 11099
11099
