Protoss_Gateway 2 11200
Protoss_Assimilator 1 3469
Protoss_Cybernetics_Core 1 4643
Protoss_Dragoon 8 11083
Protoss_Robotics_Facility 1 7489
Protoss_Shuttle 1 8289
Protoss_Robotics_Support_Bay 1 7973
Protoss_Reaver 1 9467
Protoss_Nexus 1 11990
Protoss_Observatory 1 9979
Protoss_Observer 1 10747
11990
