Protoss_Gateway 2 8423
Protoss_Assimilator 1 3366
Protoss_Cybernetics_Core 1 4488
Protoss_Dragoon 11 11048
Protoss_Robotics_Facility 1 6943
Protoss_Observatory 1 7084
Protoss_Observer 2 8473
11048
