Protoss_Gateway 2 6661
Protoss_Assimilator 1 3793
Protoss_Cybernetics_Core 1 5221
Protoss_Dragoon 8 10089
Protoss_Nexus 1 10242
Protoss_Robotics_Facility 1 10038
Protoss_Shuttle 1 10859
Protoss_Robotics_Support_Bay 1 10636
10859
