Protoss_Gateway 2 5982
Protoss_Assimilator 1 3318
Protoss_Cybernetics_Core 1 4508
Protoss_Dragoon 4 8656
Protoss_Zealot 3 6661
Protoss_Citadel_of_Adun 1 7842
Protoss_Templar_Archives 1 9014
Protoss_Dark_Templar 4 10586
Protoss_Nexus 1 11778
11778
