Protoss_Gateway 2 7862
Protoss_Assimilator 1 3413
Protoss_Cybernetics_Core 1 4548
Protoss_Zealot 1 4671
Protoss_Dragoon 7 9618
Protoss_Robotics_Facility 1 8755
Protoss_Forge 1 8877
Protoss_Observatory 1 8953
Protoss_Observer 1 9736
Protoss_Nexus 1 12853
12853
