Protoss_Gateway 2 6007
Protoss_Assimilator 2 9918
Protoss_Cybernetics_Core 1 4408
Protoss_Dragoon 7 10591
Protoss_Robotics_Facility 1 8017
Protoss_Zealot 3 10176
Protoss_Shuttle 1 9066
Protoss_Observatory 1 8608
Protoss_Nexus 1 11123
Protoss_Citadel_of_Adun 1 10055
Protoss_Observer 2 10178
Protoss_Templar_Archives 1 11370
11370
