Protoss_Gateway 2 8056
Protoss_Assimilator 1 3360
Protoss_Cybernetics_Core 1 4413
Protoss_Dragoon 7 10526
Protoss_Citadel_of_Adun 1 7165
Protoss_Templar_Archives 1 8168
Protoss_Dark_Templar 3 9698
Protoss_Nexus 1 12147
Protoss_Robotics_Facility 1 11773
12147
