Protoss_Gateway 4 11083
Protoss_Assimilator 1 3269
Protoss_Cybernetics_Core 1 4468
Protoss_Dragoon 9 10266
Protoss_Nexus 2 11538
Protoss_Robotics_Facility 1 9428
Protoss_Observatory 1 9532
Protoss_Observer 2 10923
11538
