Protoss_Gateway 3 8765
Protoss_Assimilator 1 3229
Protoss_Cybernetics_Core 1 4424
Protoss_Dragoon 8 11147
Protoss_Citadel_of_Adun 1 8199
Protoss_Zealot 10 9959
Protoss_Robotics_Facility 1 11344
Protoss_Templar_Archives 1 10998
11344
