Protoss_Gateway 2 7691
Protoss_Assimilator 1 3197
Protoss_Zealot 6 9657
Protoss_Cybernetics_Core 1 5219
Protoss_Dragoon 6 10569
Protoss_Robotics_Facility 1 7630
Protoss_Observatory 1 7723
Protoss_Shuttle 1 8605
Protoss_Robotics_Support_Bay 1 8426
Protoss_Observer 2 10681
Protoss_Reaver 1 10349
Protoss_Nexus 1 12074
12074
