Protoss_Gateway 2 9821
Protoss_Assimilator 1 3207
Protoss_Cybernetics_Core 1 4440
Protoss_Robotics_Facility 1 6191
Protoss_Dragoon 3 9716
Protoss_Shuttle 1 7001
Protoss_Robotics_Support_Bay 1 6563
Protoss_Observatory 1 6993
Protoss_Zealot 2 7996
Protoss_Reaver 2 11666
Protoss_Observer 2 9601
Protoss_Nexus 1 10898
Protoss_Scarab 3 9833
11666
