Protoss_Gateway 3 7625
Protoss_Forge 1 3908
Protoss_Zealot 7 9296
Protoss_Photon_Cannon 4 8248
Protoss_Assimilator 1 8162
Protoss_Cybernetics_Core 1 9209
Protoss_Nexus 1 11907
Protoss_Dragoon 2 10386
Protoss_Citadel_of_Adun 1 11226
11907
