Protoss_Nexus 1 5758
Protoss_Gateway 2 6518
Protoss_Assimilator 2 10493
Protoss_Cybernetics_Core 1 5778
Protoss_Zealot 3 10536
Protoss_Dragoon 8 9692
Protoss_Forge 1 8133
Protoss_Photon_Cannon 2 10335
Protoss_Robotics_Facility 1 11748
11748
