Protoss_Gateway 2 8540
Protoss_Assimilator 1 3483
Protoss_Cybernetics_Core 1 4505
Protoss_Robotics_Facility 1 6228
Protoss_Dragoon 9 10935
Protoss_Observatory 1 6429
Protoss_Observer 3 10175
Protoss_Nexus 1 12497
12497
