Protoss_Gateway 4 11053
Protoss_Assimilator 1 3384
Protoss_Cybernetics_Core 1 4393
Protoss_Dragoon 11 11171
Protoss_Robotics_Facility 1 8724
Protoss_Nexus 1 10472
Protoss_Zealot 1 8871
Protoss_Observatory 1 8873
Protoss_Observer 2 10403
11171
