Protoss_Gateway 3 11353
Protoss_Assimilator 1 3243
Protoss_Cybernetics_Core 1 4349
Protoss_Dragoon 7 10636
Protoss_Robotics_Facility 1 7203
Protoss_Observatory 1 7376
Protoss_Observer 2 10206
Protoss_Nexus 1 10578
Protoss_Shuttle 1 9381
11353
