Protoss_Gateway 2 7338
Protoss_Assimilator 1 3291
Protoss_Cybernetics_Core 1 4484
Protoss_Dragoon 9 11008
Protoss_Citadel_of_Adun 1 6468
Protoss_Templar_Archives 1 7463
Protoss_Dark_Templar 2 8297
Protoss_Nexus 1 10429
Protoss_Robotics_Facility 1 10440
11008
