Protoss_Gateway 3 9573
Protoss_Assimilator 1 4005
Protoss_Zealot 2 5239
Protoss_Cybernetics_Core 1 5361
Protoss_Dragoon 8 10435
Protoss_Nexus 1 9551
Protoss_Robotics_Facility 1 9468
Protoss_Observatory 1 9614
Protoss_Observer 1 10421
10435
