Protoss_Assimilator 1 2758
Protoss_Gateway 3 9459
Protoss_Cybernetics_Core 1 4792
Protoss_Dragoon 12 11058
Protoss_Robotics_Facility 1 6700
Protoss_Observatory 1 6893
Protoss_Observer 3 10301
Protoss_Forge 1 10242
11058
