Protoss_Gateway 2 7243
Protoss_Assimilator 1 3182
Protoss_Cybernetics_Core 1 4285
Protoss_Dragoon 12 10468
Protoss_Robotics_Facility 1 7248
Protoss_Observatory 1 7354
Protoss_Observer 3 10586
Protoss_Nexus 1 12398
12398
