Protoss_Gateway 2 7182
Protoss_Assimilator 1 3194
Protoss_Cybernetics_Core 1 4289
Protoss_Dragoon 8 10939
Protoss_Robotics_Facility 1 7399
Protoss_Shuttle 1 8239
Protoss_Robotics_Support_Bay 1 7587
Protoss_Zealot 2 8261
Protoss_Reaver 1 9381
Protoss_Observatory 1 8730
Protoss_Nexus 1 11284
Protoss_Observer 1 9757
11284
