Protoss_Gateway 4 10509
Protoss_Assimilator 2 9471
Protoss_Cybernetics_Core 1 4523
Protoss_Dragoon 6 9593
Protoss_Citadel_of_Adun 1 6835
Protoss_Templar_Archives 1 7833
Protoss_Nexus 1 10376
Protoss_Robotics_Facility 1 9908
Protoss_Observatory 1 10053
Protoss_Observer 1 10825
10825
