Protoss_Gateway 3 7498
Protoss_Assimilator 1 3473
Protoss_Cybernetics_Core 1 4616
Protoss_Robotics_Facility 1 6271
Protoss_Dragoon 5 8851
Protoss_Observatory 1 6530
Protoss_Observer 2 8446
Protoss_Shuttle 1 9528
Protoss_Zealot 3 9371
Protoss_Nexus 2 12775
12775
