Protoss_Assimilator 1 2578
Protoss_Gateway 3 7693
Protoss_Cybernetics_Core 1 4713
Protoss_Robotics_Facility 1 6228
Protoss_Dragoon 4 10366
Protoss_Observatory 1 6344
Protoss_Observer 2 7728
Protoss_Shuttle 2 9712
Protoss_Zealot 6 9331
Protoss_Robotics_Support_Bay 1 9693
Protoss_Reaver 1 11211
Protoss_Citadel_of_Adun 1 11273
11273
