Protoss_Gateway 2 7122
Protoss_Assimilator 1 3454
Protoss_Cybernetics_Core 1 4566
Protoss_Dragoon 7 8835
Protoss_Robotics_Facility 1 7404
Protoss_Observatory 1 7503
Protoss_Observer 3 9517
Protoss_Nexus 1 11057
Protoss_Robotics_Support_Bay 1 9823
Protoss_Shuttle 1 10599
Protoss_Zealot 2 10603
11057
