Protoss_Gateway 2 10011
Protoss_Assimilator 1 3491
Protoss_Cybernetics_Core 1 4339
Protoss_Dragoon 6 9691
Protoss_Robotics_Facility 1 7561
Protoss_Shuttle 1 8403
Protoss_Robotics_Support_Bay 1 7833
Protoss_Nexus 2 12129
Protoss_Reaver 1 9667
Protoss_Observatory 1 9175
Protoss_Observer 2 10953
12129
