Protoss_Gateway 3 9734
Protoss_Nexus 1 6096
Protoss_Assimilator 2 10333
Protoss_Cybernetics_Core 1 5373
Protoss_Dragoon 12 10795
Protoss_Robotics_Facility 1 9082
Protoss_Observatory 1 9317
Protoss_Observer 1 10451
10795
