Protoss_Gateway 2 7741
Protoss_Assimilator 1 3364
Protoss_Zealot 2 4509
Protoss_Cybernetics_Core 1 4569
Protoss_Dragoon 4 7793
Protoss_Citadel_of_Adun 1 6208
Protoss_Templar_Archives 1 7565
Protoss_Dark_Templar 6 10313
Protoss_Nexus 1 11287
11287
