Protoss_Gateway 3 7148
Protoss_Assimilator 1 3235
Protoss_Cybernetics_Core 1 4557
Protoss_Dragoon 11 10525
Protoss_Zealot 2 9126
Protoss_Nexus 1 11651
Protoss_Citadel_of_Adun 1 10885
Protoss_Robotics_Facility 1 11655
11655
