Protoss_Gateway 2 7576
Protoss_Assimilator 1 3493
Protoss_Cybernetics_Core 1 4577
Protoss_Dragoon 11 10976
Protoss_Robotics_Facility 1 6674
Protoss_Observatory 1 7419
Protoss_Observer 3 10371
Protoss_Nexus 1 12098
12098
