Protoss_Gateway 3 11312
Protoss_Assimilator 1 3384
Protoss_Zealot 2 4841
Protoss_Cybernetics_Core 1 5098
Protoss_Citadel_of_Adun 1 6133
Protoss_Dragoon 5 10983
Protoss_Templar_Archives 1 7553
Protoss_Nexus 2 12043
Protoss_Dark_Templar 2 8335
Protoss_Stargate 1 11464
12043
