Protoss_Gateway 3 10254
Protoss_Assimilator 1 3329
Protoss_Cybernetics_Core 1 4538
Protoss_Dragoon 9 11011
Protoss_Nexus 1 9464
Protoss_Robotics_Facility 1 9578
Protoss_Zealot 2 10376
Protoss_Shuttle 1 10596
Protoss_Observatory 1 10491
Protoss_Citadel_of_Adun 1 11397
11397
