Protoss_Gateway 3 9988
Protoss_Assimilator 2 10639
Protoss_Cybernetics_Core 1 4621
Protoss_Dragoon 7 10001
Protoss_Robotics_Facility 1 6564
Protoss_Nexus 1 9113
Protoss_Observatory 1 7150
Protoss_Observer 3 10711
Protoss_Citadel_of_Adun 1 11153
11153
