Protoss_Nexus 1 5606
Protoss_Gateway 4 9378
Protoss_Assimilator 2 8595
Protoss_Cybernetics_Core 1 5549
Protoss_Dragoon 7 11149
Protoss_Robotics_Facility 1 9104
Protoss_Shuttle 1 10369
Protoss_Observatory 1 9768
Protoss_Zealot 4 10633
Protoss_Observer 1 10906
11149
