Protoss_Gateway 2 5182
Protoss_Assimilator 1 3206
Protoss_Cybernetics_Core 1 4355
Protoss_Dragoon 3 6219
Protoss_Citadel_of_Adun 1 7216
Protoss_Robotics_Facility 1 8052
Protoss_Zealot 2 7719
Protoss_Templar_Archives 1 8268
Protoss_Shuttle 1 8893
Protoss_Dark_Templar 6 11073
Protoss_Nexus 1 12139
12139
