Protoss_Gateway 3 9618
Protoss_Assimilator 1 3224
Protoss_Cybernetics_Core 1 4314
Protoss_Dragoon 11 10725
Protoss_Nexus 1 9447
Protoss_Robotics_Facility 1 9125
Protoss_Observatory 1 9258
Protoss_Observer 2 10658
10725
