Protoss_Assimilator 1 2578
Protoss_Gateway 3 11345
Protoss_Cybernetics_Core 1 4638
Protoss_Zealot 6 7401
Protoss_Citadel_of_Adun 1 6796
Protoss_Templar_Archives 1 7805
Protoss_Dark_Templar 4 9546
Protoss_Nexus 1 10798
Protoss_Dragoon 2 10951
11345
