Protoss_Gateway 3 7558
Protoss_Assimilator 2 10946
Protoss_Cybernetics_Core 1 4287
Protoss_Dragoon 12 10985
Protoss_Nexus 1 8467
Protoss_Robotics_Facility 1 8721
Protoss_Zealot 1 8703
Protoss_Observatory 1 8966
Protoss_Shuttle 1 9985
Protoss_Observer 1 10407
10985
