Protoss_Gateway 2 7255
Protoss_Assimilator 1 3316
Protoss_Cybernetics_Core 1 4464
Protoss_Dragoon 11 10615
Protoss_Robotics_Facility 1 7634
Protoss_Observatory 1 7785
Protoss_Observer 2 9219
Protoss_Nexus 1 11622
Protoss_Shuttle 1 10465
11622
