Protoss_Gateway 2 5959
Protoss_Assimilator 2 10314
Protoss_Cybernetics_Core 1 4626
Protoss_Dragoon 14 11199
Protoss_Nexus 3 12708
Protoss_Robotics_Facility 1 10375
Protoss_Observatory 1 10473
12708
