Protoss_Gateway 2 10361
Protoss_Assimilator 2 3584
Protoss_Cybernetics_Core 1 4994
Protoss_Forge 1 5523
Protoss_Robotics_Facility 1 7240
Protoss_Photon_Cannon 2 7428
Protoss_Robotics_Support_Bay 1 7414
Protoss_Shuttle 1 8606
Protoss_Reaver 1 9748
Protoss_Citadel_of_Adun 1 10265
Protoss_Scarab 1 9763
10361
