Protoss_Gateway 2 8572
Protoss_Assimilator 1 3289
Protoss_Cybernetics_Core 1 4581
Protoss_Dragoon 4 10476
Protoss_Stargate 1 6696
Protoss_Citadel_of_Adun 1 7277
Protoss_Scout 1 8231
Protoss_Templar_Archives 1 8737
Protoss_Dark_Templar 4 10516
10516
