Protoss_Gateway 3 9790
Protoss_Assimilator 1 3321
Protoss_Cybernetics_Core 1 4435
Protoss_Dragoon 9 10743
Protoss_Robotics_Facility 1 7243
Protoss_Observatory 1 7371
Protoss_Nexus 2 12249
Protoss_Observer 3 9609
Protoss_Shuttle 1 11403
12249
