Protoss_Gateway 1 3495
Protoss_Assimilator 1 3695
Protoss_Cybernetics_Core 1 4751
Protoss_Dragoon 8 11085
Protoss_Robotics_Facility 1 8397
Protoss_Shuttle 1 9431
Protoss_Robotics_Support_Bay 1 8759
Protoss_Reaver 1 10573
Protoss_Observatory 1 10025
Protoss_Nexus 1 12537
12537
