Protoss_Gateway 1 3385
Protoss_Assimilator 1 3382
Protoss_Cybernetics_Core 1 4488
Protoss_Dragoon 6 10711
Protoss_Robotics_Facility 1 6488
Protoss_Shuttle 1 7551
Protoss_Observatory 1 7505
Protoss_Zealot 2 9658
Protoss_Observer 1 8331
Protoss_Robotics_Support_Bay 1 8309
Protoss_Reaver 1 9831
10711
