Protoss_Gateway 2 5903
Protoss_Assimilator 1 3257
Protoss_Cybernetics_Core 1 4357
Protoss_Dragoon 10 9648
Protoss_Citadel_of_Adun 1 7292
Protoss_Templar_Archives 1 8383
Protoss_Robotics_Facility 1 10638
Protoss_Nexus 1 12083
Protoss_Dark_Templar 2 10801
12083
