Protoss_Gateway 2 9110
Protoss_Assimilator 1 3377
Protoss_Cybernetics_Core 1 4693
Protoss_Dragoon 5 10716
Protoss_Robotics_Facility 1 6983
Protoss_Robotics_Support_Bay 1 7093
Protoss_Shuttle 1 7951
Protoss_Reaver 1 9093
Protoss_Observatory 1 8249
Protoss_Observer 1 9425
Protoss_Scarab 6 9554
10716
