Protoss_Gateway 5 11263
Protoss_Nexus 2 9637
Protoss_Assimilator 2 10102
Protoss_Zealot 2 5016
Protoss_Cybernetics_Core 1 5318
Protoss_Dragoon 9 10406
Protoss_Robotics_Facility 1 9859
Protoss_Observatory 1 10264
11263
