Protoss_Gateway 3 10351
Protoss_Zealot 5 10861
Protoss_Assimilator 1 5122
Protoss_Cybernetics_Core 1 6108
Protoss_Dragoon 7 10908
Protoss_Nexus 1 10659
Protoss_Robotics_Facility 1 10206
10908
