Protoss_Gateway 2 6793
Protoss_Assimilator 2 10660
Protoss_Cybernetics_Core 1 4325
Protoss_Dragoon 9 10547
Protoss_Nexus 2 11281
Protoss_Robotics_Facility 1 9229
Protoss_Observatory 1 9403
Protoss_Observer 2 10799
Protoss_Citadel_of_Adun 1 10760
11281
