Protoss_Gateway 3 7781
Protoss_Assimilator 1 3124
Protoss_Cybernetics_Core 1 4275
Protoss_Dragoon 11 10677
Protoss_Nexus 1 8469
Protoss_Robotics_Facility 1 8790
Protoss_Zealot 3 9721
Protoss_Observatory 1 8875
Protoss_Observer 2 10403
10677
