Protoss_Gateway 3 7833
Protoss_Assimilator 1 3341
Protoss_Cybernetics_Core 1 4438
Protoss_Dragoon 11 10721
Protoss_Nexus 1 7993
Protoss_Robotics_Facility 1 10378
Protoss_Citadel_of_Adun 1 10745
Protoss_Observatory 1 10635
10745
