Protoss_Gateway 3 9790
Protoss_Assimilator 1 2449
Protoss_Cybernetics_Core 1 3154
Protoss_Robotics_Facility 1 4380
Protoss_Dragoon 4 9331
Protoss_Zealot 2 6073
Protoss_Shuttle 1 5666
Protoss_Robotics_Support_Bay 1 5923
Protoss_Reaver 2 7836
Protoss_Observatory 1 7786
Protoss_Scarab 1 8449
Protoss_Observer 2 9801
Protoss_Nexus 1 9453
9801
