Protoss_Gateway 2 6849
Protoss_Assimilator 1 3404
Protoss_Cybernetics_Core 1 4473
Protoss_Dragoon 5 10969
Protoss_Citadel_of_Adun 1 7037
Protoss_Robotics_Facility 1 7845
Protoss_Templar_Archives 1 8048
Protoss_Shuttle 1 8653
Protoss_Dark_Templar 4 9817
Protoss_Nexus 1 11386
11386
