Protoss_Gateway 1 3409
Protoss_Assimilator 1 3281
Protoss_Cybernetics_Core 1 4610
Protoss_Robotics_Facility 1 6128
Protoss_Dragoon 4 9831
Protoss_Zealot 4 7437
Protoss_Shuttle 1 8136
9831
