Protoss_Gateway 3 10018
Protoss_Assimilator 1 3463
Protoss_Cybernetics_Core 1 4697
Protoss_Dragoon 9 10048
Protoss_Robotics_Facility 1 6593
Protoss_Observatory 1 6796
Protoss_Observer 2 9076
Protoss_Shuttle 2 11006
Protoss_Zealot 3 10560
11006
