Protoss_Gateway 2 4989
Protoss_Assimilator 1 3569
Protoss_Cybernetics_Core 1 4576
Protoss_Dragoon 7 10526
Protoss_Citadel_of_Adun 1 6870
Protoss_Zealot 2 7258
Protoss_Templar_Archives 1 8013
Protoss_Dark_Templar 1 8806
Protoss_Nexus 2 11995
Protoss_Robotics_Facility 1 10465
11995
