Protoss_Assimilator 1 2723
Protoss_Gateway 2 10620
Protoss_Cybernetics_Core 1 4778
Protoss_Zealot 4 7071
Protoss_Robotics_Facility 1 6408
Protoss_Shuttle 1 7361
Protoss_Robotics_Support_Bay 1 7208
Protoss_Reaver 1 8786
Protoss_Observatory 1 7961
Protoss_Dragoon 3 10551
Protoss_Observer 3 10538
10620
