Protoss_Gateway 2 9089
Protoss_Assimilator 2 10438
Protoss_Cybernetics_Core 1 4424
Protoss_Dragoon 8 10421
Protoss_Robotics_Facility 1 7319
Protoss_Observatory 1 7523
Protoss_Nexus 1 9798
Protoss_Observer 2 9193
Protoss_Robotics_Support_Bay 1 8662
Protoss_Shuttle 1 10331
Protoss_Reaver 1 11513
11513
