Protoss_Gateway 2 4086
Protoss_Zealot 5 5685
Protoss_Assimilator 1 4825
Protoss_Cybernetics_Core 1 6734
Protoss_Forge 1 6864
Protoss_Dragoon 1 7625
Protoss_Photon_Cannon 2 8346
8346
