Protoss_Nexus 2 12350
Protoss_Gateway 3 9819
Protoss_Assimilator 2 6563
Protoss_Cybernetics_Core 1 5580
Protoss_Zealot 3 9861
Protoss_Dragoon 10 10983
Protoss_Robotics_Facility 1 8681
Protoss_Shuttle 1 9507
Protoss_Robotics_Support_Bay 1 8833
Protoss_Observatory 1 8861
Protoss_Reaver 1 10649
Protoss_Citadel_of_Adun 1 11426
12350
