Protoss_Gateway 2 7958
Protoss_Zealot 3 5191
Protoss_Assimilator 1 4011
Protoss_Cybernetics_Core 1 5373
Protoss_Dragoon 7 10281
Protoss_Robotics_Facility 1 8723
Protoss_Nexus 1 11098
Protoss_Shuttle 1 9926
Protoss_Robotics_Support_Bay 1 9578
Protoss_Reaver 1 11086
11098
