Protoss_Gateway 4 10828
Protoss_Assimilator 1 3323
Protoss_Cybernetics_Core 1 4628
Protoss_Zealot 1 4621
Protoss_Dragoon 8 10916
Protoss_Robotics_Facility 1 8283
Protoss_Nexus 1 11078
Protoss_Observatory 1 9035
Protoss_Observer 2 10477
11078
