Protoss_Gateway 2 8318
Protoss_Zealot 3 5016
Protoss_Assimilator 1 3976
Protoss_Cybernetics_Core 1 5283
Protoss_Dragoon 7 10193
Protoss_Robotics_Facility 1 7825
Protoss_Shuttle 1 8641
Protoss_Robotics_Support_Bay 1 8078
Protoss_Reaver 2 10916
10916
