Protoss_Gateway 2 7700
Protoss_Assimilator 2 3863
Protoss_Cybernetics_Core 1 4966
Protoss_Dragoon 1 5731
Protoss_Citadel_of_Adun 1 6198
Protoss_Templar_Archives 1 7321
Protoss_Dark_Templar 7 10916
Protoss_Forge 1 8486
Protoss_Nexus 1 11886
11886
