Protoss_Gateway 3 11338
Protoss_Assimilator 1 3176
Protoss_Cybernetics_Core 1 4306
Protoss_Dragoon 10 10585
Protoss_Robotics_Facility 1 7438
Protoss_Observatory 1 7735
Protoss_Nexus 1 10065
Protoss_Observer 3 10751
11338
