Protoss_Gateway 3 9511
Protoss_Assimilator 1 3493
Protoss_Cybernetics_Core 1 4528
Protoss_Dragoon 6 10336
Protoss_Citadel_of_Adun 1 6611
Protoss_Zealot 1 6540
Protoss_Templar_Archives 1 8163
Protoss_Dark_Templar 3 10806
Protoss_Nexus 1 11291
11291
