Protoss_Gateway 2 8064
Protoss_Assimilator 1 3366
Protoss_Cybernetics_Core 1 4557
Protoss_Robotics_Facility 1 6253
Protoss_Dragoon 5 10804
Protoss_Observatory 1 6738
Protoss_Observer 1 7741
10804
