Protoss_Gateway 2 7336
Protoss_Assimilator 1 3318
Protoss_Cybernetics_Core 1 4390
Protoss_Dragoon 12 10533
Protoss_Robotics_Facility 1 7682
Protoss_Observatory 1 7819
Protoss_Observer 2 9198
Protoss_Nexus 1 11148
Protoss_Robotics_Support_Bay 1 10363
Protoss_Shuttle 1 11246
11246
