Protoss_Gateway 2 7924
Protoss_Assimilator 1 3443
Protoss_Cybernetics_Core 1 4538
Protoss_Zealot 5 10880
Protoss_Dragoon 8 9613
Protoss_Robotics_Facility 1 7881
Protoss_Shuttle 1 8796
Protoss_Observatory 1 8147
Protoss_Observer 3 10596
10880
