Protoss_Gateway 3 8029
Protoss_Assimilator 1 3250
Protoss_Zealot 5 9441
Protoss_Cybernetics_Core 1 4639
Protoss_Dragoon 7 11163
Protoss_Citadel_of_Adun 1 6469
Protoss_Templar_Archives 1 7637
Protoss_Dark_Templar 3 8853
11163
