Protoss_Nexus 2 7031
Protoss_Assimilator 2 5533
Protoss_Gateway 3 9156
Protoss_Cybernetics_Core 1 7250
Protoss_Robotics_Facility 2 9433
Protoss_Dragoon 8 10609
Protoss_Shuttle 1 9613
Protoss_Observatory 1 8948
Protoss_Robotics_Support_Bay 1 9821
10609
