Protoss_Gateway 2 7026
Protoss_Assimilator 1 3403
Protoss_Cybernetics_Core 1 4659
Protoss_Dragoon 8 9801
Protoss_Robotics_Facility 1 7133
Protoss_Observatory 1 7259
Protoss_Observer 3 9505
Protoss_Nexus 1 12404
Protoss_Shuttle 1 11033
12404
