Protoss_Gateway 2 11440
Protoss_Assimilator 1 3518
Protoss_Cybernetics_Core 1 4743
Protoss_Robotics_Facility 1 6378
Protoss_Dragoon 4 10612
Protoss_Zealot 3 8266
Protoss_Shuttle 2 11346
Protoss_Robotics_Support_Bay 1 6938
Protoss_Reaver 1 8541
Protoss_Observatory 1 8243
Protoss_Observer 2 9648
Protoss_Scarab 6 9291
11440
