Protoss_Gateway 3 11243
Protoss_Assimilator 1 3417
Protoss_Cybernetics_Core 1 4423
Protoss_Dragoon 12 10495
Protoss_Robotics_Facility 1 8733
Protoss_Observatory 1 8843
Protoss_Nexus 1 11653
Protoss_Observer 1 10076
11653
