Protoss_Nexus 1 5908
Protoss_Gateway 4 10322
Protoss_Assimilator 1 4998
Protoss_Cybernetics_Core 1 6278
Protoss_Dragoon 9 10661
Protoss_Robotics_Facility 1 9148
Protoss_Zealot 3 10871
Protoss_Shuttle 1 10001
Protoss_Observatory 1 9702
Protoss_Observer 1 10591
Protoss_Citadel_of_Adun 1 11358
11358
