Protoss_Gateway 2 8501
Protoss_Assimilator 2 10668
Protoss_Cybernetics_Core 1 4337
Protoss_Dragoon 7 9897
Protoss_Nexus 1 8959
Protoss_Robotics_Facility 1 8660
Protoss_Shuttle 1 9501
Protoss_Robotics_Support_Bay 1 9192
Protoss_Stargate 1 10613
Protoss_Reaver 1 10743
Protoss_Zealot 2 10409
10743
