Protoss_Gateway 2 6693
Protoss_Assimilator 1 3388
Protoss_Cybernetics_Core 1 4518
Protoss_Dragoon 6 8308
Protoss_Robotics_Facility 1 7948
Protoss_Shuttle 1 8771
Protoss_Observatory 1 8250
Protoss_Zealot 4 9430
Protoss_Observer 2 10561
Protoss_Nexus 2 12298
12298
