Protoss_Gateway 3 11388
Protoss_Assimilator 1 3478
Protoss_Cybernetics_Core 1 4913
Protoss_Robotics_Facility 1 6630
Protoss_Dragoon 5 10866
Protoss_Robotics_Support_Bay 1 6738
Protoss_Shuttle 2 11298
Protoss_Zealot 3 8201
Protoss_Reaver 2 10486
Protoss_Observatory 1 10599
11388
