Protoss_Gateway 3 9418
Protoss_Assimilator 1 3542
Protoss_Cybernetics_Core 1 4753
Protoss_Dragoon 10 10786
Protoss_Robotics_Facility 1 7631
Protoss_Observatory 1 7791
Protoss_Observer 1 8586
10786
