Protoss_Gateway 1 3467
Protoss_Assimilator 1 3823
Protoss_Cybernetics_Core 1 4713
Protoss_Zealot 2 9451
Protoss_Dragoon 3 8031
Protoss_Robotics_Facility 1 7700
Protoss_Robotics_Support_Bay 1 7946
Protoss_Shuttle 1 8686
Protoss_Reaver 2 10880
Protoss_Scarab 2 9922
10880
