Protoss_Gateway 3 9116
Protoss_Assimilator 1 3214
Protoss_Cybernetics_Core 1 4349
Protoss_Dragoon 11 10909
Protoss_Nexus 1 8853
Protoss_Robotics_Facility 1 8544
Protoss_Observatory 1 8669
Protoss_Observer 1 9753
10909
