Protoss_Nexus 1 5875
Protoss_Gateway 3 8961
Protoss_Assimilator 2 8798
Protoss_Cybernetics_Core 1 5785
Protoss_Dragoon 9 10930
Protoss_Robotics_Facility 1 7847
Protoss_Forge 1 7832
Protoss_Observatory 1 8009
Protoss_Photon_Cannon 2 10656
Protoss_Observer 2 9461
10930
