Protoss_Gateway 5 10897
Protoss_Assimilator 1 3210
Protoss_Cybernetics_Core 1 4514
Protoss_Dragoon 11 11153
Protoss_Nexus 1 8839
Protoss_Robotics_Facility 1 8816
Protoss_Observatory 1 8980
Protoss_Observer 2 10353
Protoss_Citadel_of_Adun 1 10601
11153
