Protoss_Gateway 4 10704
Protoss_Assimilator 1 3203
Protoss_Cybernetics_Core 1 4311
Protoss_Dragoon 12 11057
Protoss_Robotics_Facility 1 7173
Protoss_Observatory 1 7307
Protoss_Observer 1 8361
Protoss_Nexus 1 10595
Protoss_Citadel_of_Adun 1 11139
11139
