Protoss_Gateway 3 9285
Protoss_Assimilator 1 3200
Protoss_Cybernetics_Core 1 4379
Protoss_Dragoon 9 10245
Protoss_Nexus 1 8944
Protoss_Robotics_Facility 1 8841
Protoss_Observatory 1 9250
Protoss_Observer 1 10267
Protoss_Robotics_Support_Bay 1 10454
Protoss_Shuttle 1 11349
11349
