Protoss_Gateway 3 10182
Protoss_Assimilator 1 3275
Protoss_Zealot 2 4901
Protoss_Cybernetics_Core 1 5174
Protoss_Dragoon 11 11103
Protoss_Nexus 1 10386
Protoss_Robotics_Facility 1 9967
Protoss_Shuttle 1 10773
Protoss_Observatory 1 10172
11103
