Protoss_Gateway 3 8663
Protoss_Assimilator 1 3329
Protoss_Cybernetics_Core 1 4537
Protoss_Dragoon 6 9911
Protoss_Robotics_Facility 1 6533
Protoss_Observatory 1 6715
Protoss_Observer 1 7556
Protoss_Zealot 4 8896
Protoss_Shuttle 1 9021
Protoss_Nexus 1 12563
12563
