Protoss_Gateway 3 11413
Protoss_Assimilator 1 3334
Protoss_Cybernetics_Core 1 4447
Protoss_Dragoon 9 11001
Protoss_Nexus 2 12265
Protoss_Robotics_Facility 1 8055
Protoss_Observatory 1 9139
Protoss_Observer 2 10619
12265
