Protoss_Gateway 4 11124
Protoss_Assimilator 1 3387
Protoss_Cybernetics_Core 1 4377
Protoss_Citadel_of_Adun 1 5410
Protoss_Dragoon 9 10393
Protoss_Nexus 1 9344
Protoss_Zealot 4 10157
Protoss_Robotics_Facility 1 9157
Protoss_Shuttle 1 10025
Protoss_Observatory 1 10185
11124
