Protoss_Nexus 1 5819
Protoss_Forge 1 4203
Protoss_Gateway 4 11233
Protoss_Photon_Cannon 1 5383
Protoss_Assimilator 2 7288
Protoss_Zealot 2 6775
Protoss_Cybernetics_Core 1 6973
Protoss_Dragoon 8 10783
Protoss_Robotics_Facility 1 9206
Protoss_Observatory 1 9351
Protoss_Observer 2 10805
11233
