Protoss_Gateway 3 10547
Protoss_Assimilator 1 3211
Protoss_Cybernetics_Core 1 4449
Protoss_Dragoon 10 10481
Protoss_Robotics_Facility 1 7408
Protoss_Observatory 1 7583
Protoss_Observer 3 9853
Protoss_Nexus 1 11166
11166
