Protoss_Gateway 4 11058
Protoss_Assimilator 1 3163
Protoss_Cybernetics_Core 1 4328
Protoss_Dragoon 12 11141
Protoss_Nexus 1 9518
Protoss_Robotics_Facility 1 9748
Protoss_Observatory 1 10183
11141
