Protoss_Gateway 1 1926
Protoss_Assimilator 1 2214
Protoss_Cybernetics_Core 1 2990
Protoss_Dragoon 8 9477
Protoss_Robotics_Facility 1 5162
Protoss_Shuttle 1 6439
Protoss_Robotics_Support_Bay 1 7000
Protoss_Zealot 1 7331
Protoss_Reaver 2 8583
Protoss_Observatory 1 8371
Protoss_Observer 1 9635
Protoss_Scarab 1 9725
Protoss_Nexus 1 9956
9956
