Protoss_Assimilator 2 4817
Protoss_Nexus 1 6077
Protoss_Gateway 3 8615
Protoss_Cybernetics_Core 2 8251
Protoss_Zealot 3 6995
Protoss_Dragoon 5 10527
Protoss_Robotics_Facility 1 11338
11338
