Protoss_Gateway 2 6220
Protoss_Assimilator 1 3378
Protoss_Cybernetics_Core 1 4519
Protoss_Dragoon 3 6959
Protoss_Citadel_of_Adun 1 7367
Protoss_Zealot 3 8329
Protoss_Robotics_Facility 1 8599
Protoss_Templar_Archives 1 8607
Protoss_Shuttle 1 9397
Protoss_Dark_Templar 5 10943
Protoss_Nexus 1 12675
12675
