Protoss_Gateway 3 9851
Protoss_Assimilator 1 3810
Protoss_Zealot 4 10376
Protoss_Cybernetics_Core 1 5451
Protoss_Dragoon 10 10866
Protoss_Nexus 1 9601
Protoss_Robotics_Facility 1 9595
Protoss_Observatory 1 9753
Protoss_Observer 1 10531
10866
