Protoss_Gateway 4 11363
Protoss_Assimilator 1 3212
Protoss_Cybernetics_Core 1 4429
Protoss_Dragoon 13 10863
Protoss_Nexus 1 9675
Protoss_Robotics_Facility 1 9495
Protoss_Observatory 1 9835
Protoss_Observer 1 10613
11363
