Protoss_Gateway 2 6393
Protoss_Zealot 2 4373
Protoss_Assimilator 1 4019
Protoss_Cybernetics_Core 1 5396
Protoss_Dragoon 10 10561
Protoss_Robotics_Facility 1 8507
Protoss_Robotics_Support_Bay 1 9157
Protoss_Shuttle 1 10026
Protoss_Observatory 1 9476
Protoss_Observer 1 10551
10561
