Protoss_Gateway 2 7327
Protoss_Assimilator 1 3149
Protoss_Cybernetics_Core 1 4389
Protoss_Dragoon 9 10523
Protoss_Robotics_Facility 1 7203
Protoss_Observatory 1 7374
Protoss_Observer 2 8855
Protoss_Nexus 1 10585
Protoss_Shuttle 1 9937
Protoss_Robotics_Support_Bay 1 9581
Protoss_Reaver 1 11279
11279
