Protoss_Gateway 2 6017
Protoss_Assimilator 1 3156
Protoss_Cybernetics_Core 1 4287
Protoss_Zealot 1 4075
Protoss_Dragoon 10 10701
Protoss_Nexus 1 9565
Protoss_Robotics_Facility 1 9412
Protoss_Shuttle 1 10213
Protoss_Observatory 1 9751
Protoss_Robotics_Support_Bay 1 10363
Protoss_Observer 1 10635
10701
