Protoss_Gateway 3 8716
Protoss_Zealot 3 6691
Protoss_Nexus 2 8349
Protoss_Assimilator 2 10909
Protoss_Cybernetics_Core 1 7784
Protoss_Dragoon 7 10786
Protoss_Robotics_Facility 1 11718
11718
