Protoss_Nexus 1 5539
Protoss_Gateway 3 8352
Protoss_Assimilator 1 4484
Protoss_Cybernetics_Core 1 5822
Protoss_Zealot 4 9561
Protoss_Dragoon 8 11155
Protoss_Robotics_Facility 1 8643
Protoss_Observatory 1 8917
Protoss_Observer 1 9741
Protoss_Shuttle 1 10823
Protoss_Robotics_Support_Bay 1 10202
11155
