Protoss_Gateway 2 6057
Protoss_Assimilator 1 3421
Protoss_Cybernetics_Core 1 4455
Protoss_Dragoon 7 9019
Protoss_Nexus 2 12868
Protoss_Robotics_Facility 1 9388
Protoss_Shuttle 1 10237
Protoss_Zealot 2 9899
Protoss_Observatory 1 9731
Protoss_Robotics_Support_Bay 1 10171
Protoss_Observer 1 10659
12868
