Protoss_Gateway 3 10138
Protoss_Zealot 1 3863
Protoss_Nexus 1 6659
Protoss_Assimilator 2 9317
Protoss_Cybernetics_Core 1 5982
Protoss_Dragoon 11 10687
Protoss_Robotics_Facility 1 10340
Protoss_Shuttle 1 11257
Protoss_Observatory 1 10651
11257
