Protoss_Gateway 2 9885
Protoss_Assimilator 1 3338
Protoss_Cybernetics_Core 1 4601
Protoss_Dragoon 7 10295
Protoss_Robotics_Facility 1 6618
Protoss_Shuttle 1 7616
Protoss_Observatory 1 7071
Protoss_Robotics_Support_Bay 1 7308
Protoss_Observer 2 10661
Protoss_Reaver 1 9558
Protoss_Nexus 1 12276
12276
