Protoss_Gateway 2 7494
Protoss_Assimilator 1 3336
Protoss_Cybernetics_Core 1 4422
Protoss_Dragoon 9 11096
Protoss_Robotics_Facility 1 7620
Protoss_Shuttle 1 8436
Protoss_Zealot 4 9000
Protoss_Observatory 1 8169
Protoss_Observer 2 9548
11096
