Protoss_Gateway 3 9978
Protoss_Assimilator 1 3373
Protoss_Cybernetics_Core 1 4697
Protoss_Dragoon 9 10201
Protoss_Robotics_Facility 1 6738
Protoss_Observatory 1 6901
Protoss_Observer 4 10751
Protoss_Nexus 1 10816
Protoss_Citadel_of_Adun 1 10959
10959
