Protoss_Gateway 3 6827
Protoss_Assimilator 1 3387
Protoss_Cybernetics_Core 1 4506
Protoss_Dragoon 9 11166
Protoss_Nexus 2 11737
Protoss_Robotics_Facility 1 10362
Protoss_Observatory 2 10548
11737
