Protoss_Gateway 2 3789
Protoss_Zealot 6 5821
Protoss_Assimilator 2 10740
Protoss_Cybernetics_Core 1 6523
Protoss_Dragoon 8 10993
Protoss_Nexus 1 10334
Protoss_Robotics_Facility 1 10429
Protoss_Forge 1 10160
10993
