Protoss_Gateway 2 5733
Protoss_Assimilator 2 3869
Protoss_Cybernetics_Core 1 4865
Protoss_Dragoon 13 10618
Protoss_Citadel_of_Adun 1 10059
Protoss_Nexus 1 12488
Protoss_Templar_Archives 1 11360
12488
