Protoss_Gateway 1 3397
Protoss_Assimilator 2 10784
Protoss_Cybernetics_Core 1 4685
Protoss_Dragoon 6 10283
Protoss_Robotics_Facility 1 7553
Protoss_Shuttle 1 8361
Protoss_Robotics_Support_Bay 1 7706
Protoss_Reaver 2 10863
Protoss_Observatory 1 10345
Protoss_Nexus 1 12620
12620
