Protoss_Gateway 2 6780
Protoss_Assimilator 1 3333
Protoss_Cybernetics_Core 1 4493
Protoss_Robotics_Facility 1 6225
Protoss_Dragoon 6 10839
Protoss_Observatory 1 6985
Protoss_Observer 4 9779
Protoss_Nexus 2 11663
11663
