Protoss_Assimilator 1 3480
Protoss_Gateway 2 8661
Protoss_Cybernetics_Core 1 5136
Protoss_Robotics_Facility 1 6732
Protoss_Dragoon 2 9669
Protoss_Robotics_Support_Bay 1 6840
Protoss_Shuttle 1 7879
Protoss_Citadel_of_Adun 1 8378
Protoss_Reaver 2 10543
Protoss_Templar_Archives 1 9367
Protoss_Dark_Templar 2 10919
10919
