Protoss_Gateway 2 6297
Protoss_Assimilator 1 3390
Protoss_Zealot 3 5383
Protoss_Cybernetics_Core 1 5141
Protoss_Dragoon 5 8411
Protoss_Citadel_of_Adun 1 7054
Protoss_Templar_Archives 1 8215
Protoss_Dark_Templar 2 9225
Protoss_Nexus 1 12321
12321
