Protoss_Gateway 2 7353
Protoss_Assimilator 1 3174
Protoss_Cybernetics_Core 1 4303
Protoss_Dragoon 5 10799
Protoss_Citadel_of_Adun 1 6238
Protoss_Templar_Archives 1 7227
Protoss_Robotics_Facility 1 8451
Protoss_Dark_Templar 5 9641
Protoss_Shuttle 1 9303
Protoss_Nexus 1 11775
11775
