Protoss_Gateway 2 8289
Protoss_Assimilator 1 3494
Protoss_Cybernetics_Core 1 4608
Protoss_Dragoon 10 10966
Protoss_Robotics_Facility 1 7612
Protoss_Observatory 1 8008
Protoss_Observer 2 9598
Protoss_Nexus 1 12244
12244
