Protoss_Gateway 2 6874
Protoss_Zealot 3 6127
Protoss_Nexus 1 7064
Protoss_Assimilator 2 8204
Protoss_Cybernetics_Core 1 6465
Protoss_Dragoon 9 10815
Protoss_Robotics_Facility 1 10093
Protoss_Shuttle 1 10953
Protoss_Robotics_Support_Bay 1 10263
10953
