Protoss_Gateway 3 10872
Protoss_Assimilator 1 3161
Protoss_Cybernetics_Core 1 4315
Protoss_Dragoon 10 11079
Protoss_Zealot 1 6544
Protoss_Nexus 2 11365
Protoss_Robotics_Facility 1 10777
11365
