Protoss_Gateway 3 7624
Protoss_Assimilator 1 3508
Protoss_Cybernetics_Core 1 4709
Protoss_Robotics_Facility 1 6338
Protoss_Dragoon 9 10736
Protoss_Observatory 1 6651
Protoss_Observer 4 10408
Protoss_Nexus 1 11568
11568
