Protoss_Gateway 2 9374
Protoss_Assimilator 1 3273
Protoss_Cybernetics_Core 1 4396
Protoss_Zealot 1 4131
Protoss_Dragoon 8 10176
Protoss_Nexus 1 9728
Protoss_Robotics_Facility 1 10293
Protoss_Shuttle 1 11181
11181
