Protoss_Gateway 2 5566
Protoss_Assimilator 1 3335
Protoss_Zealot 1 3821
Protoss_Cybernetics_Core 1 5063
Protoss_Dragoon 10 10091
Protoss_Nexus 1 9813
Protoss_Robotics_Facility 1 10258
Protoss_Observatory 1 10513
10513
