Protoss_Gateway 2 8270
Protoss_Assimilator 1 3178
Protoss_Cybernetics_Core 1 4331
Protoss_Dragoon 11 10973
Protoss_Nexus 2 12079
Protoss_Robotics_Facility 1 7923
Protoss_Shuttle 1 9511
Protoss_Robotics_Support_Bay 1 9754
Protoss_Reaver 1 11251
Protoss_Observatory 1 10683
12079
