Protoss_Gateway 2 5000
Protoss_Assimilator 1 3428
Protoss_Cybernetics_Core 1 4589
Protoss_Dragoon 11 10278
Protoss_Nexus 1 10838
Protoss_Citadel_of_Adun 1 9468
Protoss_Zealot 2 10091
Protoss_Templar_Archives 1 10614
10838
