Protoss_Gateway 2 7369
Protoss_Assimilator 1 3365
Protoss_Cybernetics_Core 1 4457
Protoss_Dragoon 8 9815
Protoss_Robotics_Facility 1 7306
Protoss_Observatory 1 7499
Protoss_Shuttle 1 8569
Protoss_Robotics_Support_Bay 1 8468
Protoss_Zealot 3 10509
Protoss_Observer 1 8991
Protoss_Reaver 2 11673
11673
