Protoss_Gateway 4 11429
Protoss_Assimilator 1 3218
Protoss_Cybernetics_Core 1 4515
Protoss_Dragoon 9 10549
Protoss_Robotics_Facility 1 8311
Protoss_Observatory 1 8420
Protoss_Nexus 2 11841
Protoss_Observer 2 10701
11841
