Protoss_Gateway 2 6104
Protoss_Assimilator 1 3292
Protoss_Cybernetics_Core 1 4409
Protoss_Zealot 1 4736
Protoss_Dragoon 6 7666
Protoss_Citadel_of_Adun 1 8288
Protoss_Robotics_Facility 1 9457
Protoss_Templar_Archives 1 9701
Protoss_Shuttle 1 10606
Protoss_Dark_Templar 2 10461
Protoss_Observatory 1 10406
10606
