Protoss_Gateway 3 11044
Protoss_Assimilator 1 3401
Protoss_Cybernetics_Core 1 4448
Protoss_Dragoon 6 10815
Protoss_Citadel_of_Adun 1 6348
Protoss_Robotics_Facility 1 7173
Protoss_Zealot 1 6801
Protoss_Templar_Archives 1 7603
Protoss_Shuttle 1 8191
Protoss_Dark_Templar 2 8371
Protoss_Nexus 1 11392
Protoss_Observatory 1 10398
11392
