Protoss_Gateway 2 9149
Protoss_Assimilator 1 3268
Protoss_Cybernetics_Core 1 4417
Protoss_Dragoon 8 10478
Protoss_Nexus 1 8723
Protoss_Robotics_Facility 1 8479
Protoss_Observatory 1 8717
Protoss_Shuttle 1 9583
Protoss_Robotics_Support_Bay 1 9373
Protoss_Observer 1 10005
Protoss_Reaver 1 11327
Protoss_Zealot 1 10825
11327
