Protoss_Gateway 3 9439
Protoss_Assimilator 1 3280
Protoss_Cybernetics_Core 1 4433
Protoss_Robotics_Facility 1 6088
Protoss_Dragoon 11 11046
Protoss_Observatory 1 6248
Protoss_Observer 2 8471
Protoss_Nexus 1 10283
11046
