Protoss_Gateway 5 9158
Protoss_Zealot 4 10673
Protoss_Assimilator 1 4663
Protoss_Cybernetics_Core 1 6894
Protoss_Dragoon 4 11189
Protoss_Robotics_Facility 1 8561
Protoss_Robotics_Support_Bay 1 8725
Protoss_Shuttle 1 9475
Protoss_Reaver 1 10617
Protoss_Nexus 1 12439
Protoss_Observatory 1 10612
12439
