Protoss_Gateway 2 5068
Protoss_Assimilator 1 3360
Protoss_Cybernetics_Core 1 4397
Protoss_Dragoon 7 8406
Protoss_Robotics_Facility 1 8293
Protoss_Observatory 1 8486
Protoss_Nexus 1 11127
Protoss_Observer 1 9301
Protoss_Robotics_Support_Bay 1 9400
Protoss_Shuttle 1 10501
Protoss_Reaver 1 11643
11643
