Protoss_Gateway 2 9052
Protoss_Zealot 2 4746
Protoss_Assimilator 1 4249
Protoss_Cybernetics_Core 1 5638
Protoss_Dragoon 6 9886
Protoss_Nexus 1 8973
Protoss_Citadel_of_Adun 1 9498
Protoss_Robotics_Facility 1 10528
Protoss_Templar_Archives 1 10556
Protoss_Shuttle 1 11336
11336
