Protoss_Gateway 1 1857
Protoss_Assimilator 1 2338
Protoss_Cybernetics_Core 1 2931
Protoss_Dragoon 6 9543
Protoss_Robotics_Facility 1 4399
Protoss_Shuttle 1 5681
Protoss_Robotics_Support_Bay 1 5858
Protoss_Zealot 2 7035
Protoss_Reaver 1 6871
Protoss_Observatory 1 7152
Protoss_Nexus 1 7798
Protoss_Observer 2 8587
Protoss_Scarab 7 9882
9882
