Protoss_Gateway 4 11340
Protoss_Assimilator 2 9116
Protoss_Cybernetics_Core 1 4319
Protoss_Dragoon 9 9865
Protoss_Nexus 2 12529
Protoss_Citadel_of_Adun 1 8342
Protoss_Robotics_Facility 1 9127
Protoss_Observatory 1 9280
Protoss_Observer 2 10679
12529
