Protoss_Gateway 2 8977
Protoss_Assimilator 1 3353
Protoss_Cybernetics_Core 1 4884
Protoss_Dragoon 6 10204
Protoss_Robotics_Facility 1 7706
Protoss_Observatory 1 7969
Protoss_Observer 3 10566
Protoss_Zealot 1 10391
10566
