Protoss_Gateway 2 7668
Protoss_Assimilator 1 3422
Protoss_Cybernetics_Core 1 4623
Protoss_Dragoon 1 5496
Protoss_Robotics_Facility 1 6477
Protoss_Citadel_of_Adun 1 6980
Protoss_Shuttle 1 7301
Protoss_Templar_Archives 1 7973
Protoss_Dark_Templar 4 9493
Protoss_Nexus 2 12498
Protoss_Forge 1 10769
12498
