Protoss_Gateway 2 9383
Protoss_Assimilator 2 9695
Protoss_Cybernetics_Core 1 4463
Protoss_Dragoon 7 11153
Protoss_Nexus 1 8947
Protoss_Citadel_of_Adun 1 8235
Protoss_Robotics_Facility 1 9257
Protoss_Templar_Archives 1 9509
Protoss_Shuttle 1 10269
Protoss_Dark_Templar 3 11035
Protoss_Observatory 1 10087
Protoss_Observer 1 10921
11153
