Protoss_Gateway 3 10186
Protoss_Assimilator 1 3236
Protoss_Cybernetics_Core 1 4662
Protoss_Dragoon 7 10949
Protoss_Robotics_Facility 1 6887
Protoss_Nexus 1 8884
Protoss_Observatory 1 7020
Protoss_Observer 2 8643
10949
