Protoss_Gateway 2 3816
Protoss_Zealot 13 10601
Protoss_Forge 1 5086
Protoss_Photon_Cannon 4 7783
Protoss_Assimilator 1 7758
Protoss_Cybernetics_Core 1 9072
Protoss_Citadel_of_Adun 1 10410
Protoss_Dragoon 2 10931
Protoss_Templar_Archives 1 11397
11397
