Protoss_Assimilator 3 9995
Protoss_Gateway 4 11440
Protoss_Zealot 11 10827
Protoss_Nexus 1 7657
Protoss_Cybernetics_Core 1 7295
Protoss_Forge 1 7271
Protoss_Photon_Cannon 2 8968
Protoss_Citadel_of_Adun 1 9565
Protoss_Templar_Archives 1 11196
11440
