Protoss_Gateway 2 5731
Protoss_Assimilator 1 3418
Protoss_Zealot 1 3956
Protoss_Cybernetics_Core 1 4903
Protoss_Dragoon 5 7911
Protoss_Citadel_of_Adun 1 7657
Protoss_Templar_Archives 1 8785
Protoss_Nexus 1 11044
Protoss_Dark_Templar 4 10351
11044
