Protoss_Gateway 3 9047
Protoss_Assimilator 2 4365
Protoss_Zealot 3 5375
Protoss_Cybernetics_Core 1 5641
Protoss_Dragoon 3 8021
Protoss_Citadel_of_Adun 1 7370
Protoss_Forge 1 7979
Protoss_Templar_Archives 1 8485
Protoss_Dark_Templar 4 10624
Protoss_Photon_Cannon 1 9589
10624
