Protoss_Gateway 2 4921
Protoss_Assimilator 1 3168
Protoss_Cybernetics_Core 1 4343
Protoss_Dragoon 8 9755
Protoss_Nexus 1 9660
Protoss_Robotics_Facility 1 9012
Protoss_Shuttle 1 9833
Protoss_Robotics_Support_Bay 1 9649
Protoss_Reaver 1 11145
Protoss_Observatory 1 10311
11145
