Protoss_Gateway 1 3438
Protoss_Forge 1 3491
Protoss_Zealot 6 10746
Protoss_Photon_Cannon 10 9913
Protoss_Assimilator 1 7969
Protoss_Nexus 1 10112
Protoss_Cybernetics_Core 1 9584
10746
