Protoss_Gateway 3 11255
Protoss_Assimilator 1 3451
Protoss_Cybernetics_Core 1 4538
Protoss_Dragoon 8 10837
Protoss_Nexus 1 9283
Protoss_Robotics_Facility 1 8963
Protoss_Observatory 1 9447
Protoss_Observer 1 10467
11255
