Protoss_Gateway 1 3382
Protoss_Assimilator 1 3279
Protoss_Cybernetics_Core 1 4424
Protoss_Dragoon 3 6971
Protoss_Robotics_Facility 1 7373
Protoss_Citadel_of_Adun 1 7658
Protoss_Shuttle 1 8196
Protoss_Robotics_Support_Bay 1 7791
Protoss_Zealot 2 9421
Protoss_Reaver 2 11421
Protoss_Templar_Archives 1 9538
Protoss_Nexus 1 12093
Protoss_Dark_Templar 1 10541
12093
