Protoss_Gateway 2 6399
Protoss_Assimilator 1 3438
Protoss_Cybernetics_Core 1 4653
Protoss_Dragoon 8 9280
Protoss_Robotics_Facility 1 8227
Protoss_Observatory 1 8998
Protoss_Nexus 1 11513
Protoss_Zealot 4 10711
Protoss_Observer 1 9791
Protoss_Shuttle 1 10936
11513
