Protoss_Gateway 2 8019
Protoss_Assimilator 1 3393
Protoss_Cybernetics_Core 1 4533
Protoss_Dragoon 11 10668
Protoss_Nexus 1 9039
Protoss_Robotics_Facility 1 9290
Protoss_Observatory 1 9771
Protoss_Shuttle 1 10747
Protoss_Robotics_Support_Bay 1 10657
10747
