Protoss_Gateway 2 9246
Protoss_Assimilator 1 3294
Protoss_Cybernetics_Core 1 4436
Protoss_Dragoon 5 8359
Protoss_Nexus 1 8911
Protoss_Robotics_Facility 2 9447
Protoss_Shuttle 1 9633
Protoss_Robotics_Support_Bay 1 9162
Protoss_Zealot 4 10571
Protoss_Reaver 2 10853
10853
