Protoss_Gateway 2 6390
Protoss_Assimilator 1 3378
Protoss_Cybernetics_Core 1 4503
Protoss_Zealot 3 10823
Protoss_Dragoon 8 10043
Protoss_Nexus 1 9545
Protoss_Robotics_Facility 1 9010
Protoss_Shuttle 1 9839
Protoss_Robotics_Support_Bay 1 9225
Protoss_Reaver 1 11089
11089
