Protoss_Gateway 3 8792
Protoss_Assimilator 1 3329
Protoss_Cybernetics_Core 1 4453
Protoss_Dragoon 10 10667
Protoss_Zealot 1 6534
Protoss_Nexus 1 8791
Protoss_Robotics_Facility 1 8165
Protoss_Observatory 1 8274
Protoss_Observer 2 9691
Protoss_Shuttle 1 11255
11255
