Protoss_Gateway 2 6022
Protoss_Assimilator 1 3278
Protoss_Cybernetics_Core 1 4378
Protoss_Dragoon 6 8781
Protoss_Nexus 1 9657
Protoss_Robotics_Facility 1 9055
Protoss_Shuttle 1 9867
Protoss_Robotics_Support_Bay 1 9680
Protoss_Zealot 2 10333
Protoss_Observatory 1 10275
Protoss_Reaver 1 11277
11277
