Protoss_Gateway 3 7452
Protoss_Assimilator 1 3273
Protoss_Cybernetics_Core 1 4511
Protoss_Robotics_Facility 1 6029
Protoss_Dragoon 9 10073
Protoss_Observatory 1 6247
Protoss_Observer 3 8325
Protoss_Nexus 1 12479
12479
