Protoss_Gateway 4 10947
Protoss_Assimilator 1 3289
Protoss_Cybernetics_Core 1 4502
Protoss_Dragoon 13 11145
Protoss_Nexus 1 9132
Protoss_Zealot 1 8289
Protoss_Robotics_Facility 1 10599
11145
