Protoss_Nexus 2 11598
Protoss_Gateway 3 10112
Protoss_Assimilator 2 8747
Protoss_Cybernetics_Core 1 5748
Protoss_Zealot 1 5636
Protoss_Dragoon 3 7781
Protoss_Citadel_of_Adun 1 8213
Protoss_Robotics_Facility 1 9235
Protoss_Templar_Archives 1 9573
Protoss_Shuttle 1 10306
Protoss_Dark_Templar 3 10866
Protoss_Forge 1 10273
Protoss_Observatory 1 10371
11598
