Protoss_Gateway 3 11276
Protoss_Assimilator 1 3514
Protoss_Cybernetics_Core 1 4618
Protoss_Dragoon 9 10641
Protoss_Robotics_Facility 1 6608
Protoss_Observatory 1 6888
Protoss_Observer 4 10393
Protoss_Nexus 2 12273
12273
