Protoss_Gateway 2 6368
Protoss_Zealot 1 4217
Protoss_Nexus 1 6600
Protoss_Assimilator 2 7087
Protoss_Cybernetics_Core 1 6181
Protoss_Dragoon 7 11055
Protoss_Citadel_of_Adun 1 8082
Protoss_Forge 1 8225
Protoss_Templar_Archives 1 9116
Protoss_Robotics_Facility 1 9759
Protoss_Photon_Cannon 2 9586
Protoss_Dark_Templar 2 10099
Protoss_Stargate 1 10746
Protoss_Shuttle 1 10633
Protoss_Observatory 1 10014
11055
