Protoss_Gateway 2 8049
Protoss_Assimilator 1 3288
Protoss_Cybernetics_Core 1 4330
Protoss_Zealot 1 4191
Protoss_Dragoon 9 11161
Protoss_Robotics_Facility 1 7888
Protoss_Shuttle 1 8706
Protoss_Robotics_Support_Bay 1 8221
Protoss_Reaver 1 10101
Protoss_Nexus 1 11828
Protoss_Observatory 1 10301
11828
