Protoss_Gateway 1 3255
Protoss_Assimilator 1 3157
Protoss_Cybernetics_Core 1 4244
Protoss_Dragoon 7 11147
Protoss_Robotics_Facility 1 7609
Protoss_Shuttle 1 8409
Protoss_Zealot 2 8695
Protoss_Robotics_Support_Bay 1 7975
Protoss_Reaver 1 9645
Protoss_Observatory 1 8872
Protoss_Nexus 2 12351
Protoss_Observer 2 10579
Protoss_Scarab 1 9805
12351
