Protoss_Gateway 2 9962
Protoss_Assimilator 2 9415
Protoss_Cybernetics_Core 1 4337
Protoss_Dragoon 4 7581
Protoss_Citadel_of_Adun 1 6592
Protoss_Templar_Archives 1 7641
Protoss_Nexus 1 9993
Protoss_Dark_Templar 4 10743
Protoss_Stargate 1 9920
Protoss_Arbiter_Tribunal 1 11437
11437
