Protoss_Gateway 4 11391
Protoss_Zealot 1 3881
Protoss_Assimilator 1 4323
Protoss_Cybernetics_Core 1 5154
Protoss_Nexus 2 11930
Protoss_Dragoon 9 10723
Protoss_Robotics_Facility 1 8204
Protoss_Observatory 1 8430
Protoss_Observer 2 9805
11930
