Protoss_Gateway 2 7347
Protoss_Zealot 2 4445
Protoss_Assimilator 1 4115
Protoss_Cybernetics_Core 1 5376
Protoss_Dragoon 9 10287
Protoss_Robotics_Facility 1 8037
Protoss_Shuttle 1 8835
Protoss_Robotics_Support_Bay 1 9020
Protoss_Reaver 1 10661
Protoss_Observatory 1 10117
10661
