Protoss_Gateway 2 6788
Protoss_Assimilator 2 4115
Protoss_Zealot 2 5087
Protoss_Cybernetics_Core 1 5348
Protoss_Dragoon 6 9179
Protoss_Robotics_Facility 1 8985
Protoss_Robotics_Support_Bay 1 9261
Protoss_Shuttle 1 9985
Protoss_Nexus 1 12224
Protoss_Reaver 1 11323
12224
