Protoss_Gateway 4 10502
Protoss_Assimilator 1 3383
Protoss_Cybernetics_Core 1 4413
Protoss_Dragoon 6 10837
Protoss_Citadel_of_Adun 1 7102
Protoss_Templar_Archives 1 8089
Protoss_Zealot 1 7959
Protoss_Dark_Templar 4 9903
Protoss_Nexus 1 10875
10875
