Protoss_Gateway 6 10839
Protoss_Assimilator 1 3172
Protoss_Cybernetics_Core 1 4378
Protoss_Dragoon 8 11005
Protoss_Nexus 2 11408
Protoss_Robotics_Facility 1 8964
Protoss_Observatory 1 9145
Protoss_Observer 2 10645
11408
