Protoss_Gateway 3 10889
Protoss_Assimilator 2 3546
Protoss_Cybernetics_Core 1 4436
Protoss_Dragoon 6 10911
Protoss_Robotics_Facility 1 7571
Protoss_Observatory 1 7876
Protoss_Nexus 1 10037
Protoss_Observer 2 10741
Protoss_Shuttle 1 9221
Protoss_Robotics_Support_Bay 1 8904
Protoss_Zealot 2 9929
Protoss_Reaver 1 10409
10911
