Protoss_Gateway 2 9295
Protoss_Assimilator 1 3607
Protoss_Cybernetics_Core 1 4531
Protoss_Dragoon 8 10049
Protoss_Nexus 2 12519
Protoss_Robotics_Facility 1 9571
Protoss_Shuttle 1 10391
Protoss_Robotics_Support_Bay 1 9833
Protoss_Reaver 1 11632
12519
