Protoss_Gateway 5 11260
Protoss_Assimilator 1 3277
Protoss_Cybernetics_Core 1 4608
Protoss_Dragoon 9 10615
Protoss_Nexus 2 11988
Protoss_Robotics_Facility 1 8813
Protoss_Observatory 1 9026
Protoss_Observer 1 10575
11988
