Protoss_Nexus 2 10583
Protoss_Gateway 4 11088
Protoss_Assimilator 1 4328
Protoss_Zealot 3 8755
Protoss_Cybernetics_Core 1 5643
Protoss_Dragoon 12 11195
Protoss_Robotics_Facility 1 10375
11195
