Protoss_Gateway 2 7421
Protoss_Assimilator 1 3226
Protoss_Cybernetics_Core 1 4333
Protoss_Dragoon 8 10537
Protoss_Robotics_Facility 2 7569
Protoss_Observatory 1 7694
Protoss_Nexus 1 10097
Protoss_Observer 1 8467
Protoss_Shuttle 1 9831
Protoss_Robotics_Support_Bay 1 9432
Protoss_Reaver 1 10973
10973
