Protoss_Gateway 1 3390
Protoss_Assimilator 2 9838
Protoss_Cybernetics_Core 1 4445
Protoss_Dragoon 5 10741
Protoss_Robotics_Facility 1 7646
Protoss_Shuttle 1 8465
Protoss_Robotics_Support_Bay 1 7790
Protoss_Zealot 2 8919
Protoss_Reaver 1 9607
Protoss_Nexus 2 12713
Protoss_Observatory 1 9967
Protoss_Observer 1 10885
12713
