Protoss_Gateway 2 8088
Protoss_Assimilator 1 3438
Protoss_Cybernetics_Core 1 4546
Protoss_Dragoon 7 10206
Protoss_Robotics_Facility 1 7958
Protoss_Observatory 1 8213
Protoss_Shuttle 1 9066
Protoss_Zealot 2 9188
Protoss_Observer 1 9599
10206
