Protoss_Gateway 2 6362
Protoss_Assimilator 2 9605
Protoss_Cybernetics_Core 1 4317
Protoss_Dragoon 9 10493
Protoss_Nexus 1 8651
Protoss_Robotics_Facility 1 8134
Protoss_Observatory 1 8394
Protoss_Stargate 2 11626
Protoss_Observer 1 9165
Protoss_Fleet_Beacon 1 10751
11626
