Protoss_Gateway 2 8614
Protoss_Assimilator 1 3318
Protoss_Cybernetics_Core 1 4637
Protoss_Dragoon 7 10886
Protoss_Robotics_Facility 1 7493
Protoss_Observatory 1 7709
Protoss_Nexus 1 10893
Protoss_Observer 1 9436
Protoss_Shuttle 1 10518
10893
