Protoss_Gateway 3 10875
Protoss_Assimilator 1 3243
Protoss_Cybernetics_Core 1 4311
Protoss_Dragoon 5 8717
Protoss_Robotics_Facility 1 7323
Protoss_Observatory 1 7457
Protoss_Nexus 1 9828
Protoss_Shuttle 1 8639
Protoss_Robotics_Support_Bay 1 8689
Protoss_Observer 2 10769
Protoss_Zealot 2 10119
Protoss_Reaver 1 10437
10875
