Protoss_Gateway 3 10588
Protoss_Zealot 1 3841
Protoss_Assimilator 2 9773
Protoss_Cybernetics_Core 1 6309
Protoss_Nexus 1 8540
Protoss_Citadel_of_Adun 1 7386
Protoss_Templar_Archives 1 8426
Protoss_Dark_Templar 3 10710
10710
