Protoss_Gateway 3 11423
Protoss_Assimilator 1 3575
Protoss_Cybernetics_Core 1 4725
Protoss_Dragoon 10 10081
Protoss_Robotics_Facility 1 8170
Protoss_Observatory 1 8422
Protoss_Observer 2 10091
Protoss_Nexus 1 12495
12495
