Protoss_Gateway 3 9284
Protoss_Assimilator 1 3428
Protoss_Cybernetics_Core 1 4502
Protoss_Dragoon 7 9387
Protoss_Robotics_Facility 1 7518
Protoss_Observatory 1 7654
Protoss_Observer 2 9038
Protoss_Zealot 3 10581
Protoss_Citadel_of_Adun 1 10277
Protoss_Shuttle 1 10351
10581
