Protoss_Gateway 4 10401
Protoss_Assimilator 1 3258
Protoss_Cybernetics_Core 1 4380
Protoss_Dragoon 7 10606
Protoss_Nexus 1 8868
Protoss_Robotics_Facility 1 8789
Protoss_Observatory 1 8898
Protoss_Zealot 2 10361
Protoss_Observer 2 10431
10606
