Protoss_Gateway 2 7398
Protoss_Assimilator 1 3227
Protoss_Cybernetics_Core 1 4379
Protoss_Dragoon 10 10506
Protoss_Robotics_Facility 1 7321
Protoss_Observatory 1 7657
Protoss_Observer 3 9781
Protoss_Nexus 1 10893
10893
