Protoss_Gateway 2 7693
Protoss_Assimilator 1 3504
Protoss_Cybernetics_Core 1 4481
Protoss_Dragoon 4 9581
Protoss_Citadel_of_Adun 1 6735
Protoss_Robotics_Facility 1 7927
Protoss_Templar_Archives 1 7863
Protoss_Dark_Templar 4 10541
Protoss_Shuttle 1 8955
Protoss_Zealot 1 9329
Protoss_Nexus 1 12836
12836
