Protoss_Gateway 3 10383
Protoss_Assimilator 1 3315
Protoss_Cybernetics_Core 1 4329
Protoss_Dragoon 8 10715
Protoss_Citadel_of_Adun 1 7457
Protoss_Templar_Archives 1 8614
Protoss_Nexus 1 10881
Protoss_Dark_Templar 2 9607
Protoss_Robotics_Facility 1 11127
11127
