Protoss_Gateway 2 10359
Protoss_Assimilator 1 3333
Protoss_Cybernetics_Core 1 4406
Protoss_Dragoon 7 10429
Protoss_Robotics_Facility 1 7331
Protoss_Shuttle 1 8239
Protoss_Robotics_Support_Bay 1 7603
Protoss_Reaver 1 9381
Protoss_Nexus 1 11141
Protoss_Observatory 1 9395
Protoss_Observer 1 10237
Protoss_Citadel_of_Adun 1 11283
11283
