Protoss_Gateway 4 10396
Protoss_Assimilator 1 3129
Protoss_Cybernetics_Core 1 4367
Protoss_Zealot 5 10903
Protoss_Dragoon 10 9969
Protoss_Robotics_Facility 1 7567
Protoss_Observatory 1 7667
Protoss_Observer 3 10381
Protoss_Shuttle 1 11203
11203
