Protoss_Gateway 3 11155
Protoss_Assimilator 1 3459
Protoss_Cybernetics_Core 1 4647
Protoss_Dragoon 7 10095
Protoss_Nexus 2 12326
Protoss_Zealot 3 10705
Protoss_Robotics_Facility 1 9262
Protoss_Observatory 1 9865
Protoss_Observer 1 10687
12326
