Protoss_Gateway 3 9400
Protoss_Assimilator 1 3211
Protoss_Cybernetics_Core 1 4325
Protoss_Dragoon 8 10601
Protoss_Robotics_Facility 1 7258
Protoss_Observatory 1 7364
Protoss_Nexus 1 10099
Protoss_Observer 2 8849
Protoss_Shuttle 1 9931
Protoss_Robotics_Support_Bay 1 9626
Protoss_Reaver 1 11259
11259
