Protoss_Gateway 3 6824
Protoss_Zealot 5 9793
Protoss_Nexus 1 6863
Protoss_Assimilator 1 5132
Protoss_Cybernetics_Core 1 6249
Protoss_Dragoon 8 9281
Protoss_Robotics_Facility 1 11161
11161
