Protoss_Gateway 2 9009
Protoss_Assimilator 1 3378
Protoss_Cybernetics_Core 1 4500
Protoss_Dragoon 8 9977
Protoss_Nexus 1 9033
Protoss_Robotics_Facility 1 9205
Protoss_Shuttle 1 10061
Protoss_Robotics_Support_Bay 1 9701
Protoss_Zealot 2 10489
Protoss_Reaver 1 11253
11253
