Protoss_Gateway 2 4140
Protoss_Zealot 6 7083
Protoss_Assimilator 1 4779
Protoss_Cybernetics_Core 1 5691
Protoss_Dragoon 11 10659
Protoss_Forge 1 6646
Protoss_Shield_Battery 1 8017
10659
