Protoss_Gateway 2 6147
Protoss_Assimilator 1 3213
Protoss_Cybernetics_Core 1 4448
Protoss_Dragoon 9 11063
Protoss_Citadel_of_Adun 1 7217
Protoss_Templar_Archives 1 8216
Protoss_Zealot 1 7969
Protoss_Dark_Templar 2 9439
Protoss_Nexus 1 11187
Protoss_Robotics_Facility 1 10809
11187
