Protoss_Gateway 2 7578
Protoss_Assimilator 1 3428
Protoss_Cybernetics_Core 1 4443
Protoss_Dragoon 5 10526
Protoss_Robotics_Facility 1 7480
Protoss_Observatory 1 7585
Protoss_Shuttle 1 8526
Protoss_Zealot 2 10311
Protoss_Robotics_Support_Bay 1 8313
Protoss_Observer 1 8948
Protoss_Nexus 1 11288
Protoss_Reaver 1 10381
11288
