Protoss_Gateway 4 10613
Protoss_Assimilator 1 3201
Protoss_Cybernetics_Core 1 4341
Protoss_Dragoon 10 10443
Protoss_Nexus 1 9377
Protoss_Robotics_Facility 1 9608
Protoss_Observatory 1 9711
Protoss_Observer 1 10819
10819
