Protoss_Gateway 3 8304
Protoss_Assimilator 1 3399
Protoss_Cybernetics_Core 1 4537
Protoss_Dragoon 4 9529
Protoss_Citadel_of_Adun 1 7619
Protoss_Templar_Archives 1 8609
Protoss_Dark_Templar 5 10869
Protoss_Nexus 1 11133
11133
