Protoss_Gateway 2 5058
Protoss_Assimilator 2 10931
Protoss_Cybernetics_Core 1 4455
Protoss_Dragoon 9 10709
Protoss_Nexus 1 9348
Protoss_Robotics_Facility 1 9796
Protoss_Shuttle 1 10637
Protoss_Robotics_Support_Bay 1 10360
10931
