Protoss_Assimilator 2 3681
Protoss_Gateway 6 11299
Protoss_Cybernetics_Core 1 4853
Protoss_Dragoon 5 9577
Protoss_Nexus 2 9996
Protoss_Robotics_Facility 1 9795
Protoss_Shuttle 1 10663
Protoss_Robotics_Support_Bay 1 10381
11299
