Protoss_Nexus 2 11507
Protoss_Gateway 4 11406
Protoss_Assimilator 1 4377
Protoss_Cybernetics_Core 1 5549
Protoss_Zealot 1 5551
Protoss_Dragoon 12 11069
Protoss_Robotics_Facility 1 9373
Protoss_Observatory 1 9884
11507
