Protoss_Gateway 4 10246
Protoss_Assimilator 1 3318
Protoss_Cybernetics_Core 1 4455
Protoss_Dragoon 7 10523
Protoss_Zealot 4 8953
Protoss_Nexus 1 10579
Protoss_Robotics_Facility 1 10253
Protoss_Shuttle 1 11355
Protoss_Robotics_Support_Bay 1 10717
11355
