Protoss_Gateway 2 9717
Protoss_Assimilator 1 3332
Protoss_Cybernetics_Core 1 4575
Protoss_Dragoon 8 11153
Protoss_Robotics_Facility 1 7417
Protoss_Observatory 1 7505
Protoss_Nexus 1 9963
Protoss_Observer 2 10215
Protoss_Shuttle 1 9401
Protoss_Robotics_Support_Bay 2 9484
Protoss_Reaver 1 11537
11537
