Protoss_Gateway 2 6539
Protoss_Assimilator 1 3379
Protoss_Zealot 2 4441
Protoss_Cybernetics_Core 1 4579
Protoss_Dragoon 9 10565
Protoss_Citadel_of_Adun 1 6227
Protoss_Templar_Archives 1 7229
Protoss_Dark_Templar 2 7997
Protoss_Nexus 1 12451
12451
