Protoss_Gateway 2 7585
Protoss_Assimilator 3 10443
Protoss_Zealot 3 6611
Protoss_Nexus 2 10753
Protoss_Cybernetics_Core 1 6825
Protoss_Dragoon 5 10457
Protoss_Robotics_Facility 1 8875
Protoss_Shuttle 1 9889
Protoss_Robotics_Support_Bay 1 9587
Protoss_Reaver 1 11181
11181
