Protoss_Gateway 2 10237
Protoss_Zealot 5 6721
Protoss_Forge 1 4225
Protoss_Photon_Cannon 2 5863
Protoss_Assimilator 1 6162
Protoss_Cybernetics_Core 1 7070
Protoss_Nexus 1 9392
Protoss_Robotics_Facility 1 8940
Protoss_Dragoon 5 11055
Protoss_Robotics_Support_Bay 1 9430
Protoss_Reaver 1 11039
11055
