Protoss_Gateway 2 6246
Protoss_Zealot 4 9261
Protoss_Nexus 2 11699
Protoss_Assimilator 1 5144
Protoss_Cybernetics_Core 1 6137
Protoss_Dragoon 8 10257
Protoss_Robotics_Facility 1 10161
11699
