Protoss_Gateway 2 10224
Protoss_Assimilator 1 3152
Protoss_Cybernetics_Core 1 4294
Protoss_Dragoon 7 10971
Protoss_Robotics_Facility 1 7195
Protoss_Shuttle 1 7991
Protoss_Robotics_Support_Bay 1 7440
Protoss_Reaver 1 9211
Protoss_Zealot 2 9127
Protoss_Observatory 1 8605
Protoss_Nexus 1 10905
Protoss_Observer 2 10169
10971
