Protoss_Gateway 2 9325
Protoss_Assimilator 1 3258
Protoss_Cybernetics_Core 1 4448
Protoss_Robotics_Facility 1 6083
Protoss_Dragoon 9 11006
Protoss_Observatory 1 6306
Protoss_Observer 1 7171
Protoss_Nexus 1 9997
Protoss_Shuttle 1 9046
Protoss_Robotics_Support_Bay 1 9368
11006
