Protoss_Gateway 1 3275
Protoss_Assimilator 1 3313
Protoss_Cybernetics_Core 1 4334
Protoss_Dragoon 5 10685
Protoss_Robotics_Facility 1 6303
Protoss_Shuttle 1 7111
Protoss_Robotics_Support_Bay 1 7064
Protoss_Nexus 2 12047
Protoss_Zealot 2 8813
Protoss_Reaver 1 9137
Protoss_Observatory 1 8545
Protoss_Observer 2 10155
Protoss_Scarab 3 9859
12047
