Protoss_Nexus 2 11901
Protoss_Gateway 3 11234
Protoss_Assimilator 1 4368
Protoss_Cybernetics_Core 1 5595
Protoss_Zealot 1 5571
Protoss_Dragoon 8 10595
Protoss_Robotics_Facility 1 11260
11901
