Protoss_Gateway 2 10046
Protoss_Assimilator 2 10748
Protoss_Cybernetics_Core 1 4649
Protoss_Dragoon 9 11117
Protoss_Nexus 2 10297
Protoss_Robotics_Facility 1 9801
Protoss_Citadel_of_Adun 1 10181
Protoss_Observatory 1 10421
Protoss_Templar_Archives 1 11233
11233
