Protoss_Gateway 2 7768
Protoss_Assimilator 1 3170
Protoss_Cybernetics_Core 1 4399
Protoss_Dragoon 7 10159
Protoss_Robotics_Facility 1 7374
Protoss_Observatory 1 7523
Protoss_Nexus 1 10758
Protoss_Observer 1 8863
Protoss_Robotics_Support_Bay 1 8826
Protoss_Shuttle 1 9945
Protoss_Reaver 1 11087
11087
