Protoss_Gateway 3 11321
Protoss_Assimilator 1 3581
Protoss_Cybernetics_Core 1 4655
Protoss_Dragoon 9 10873
Protoss_Robotics_Facility 1 7830
Protoss_Observatory 1 7928
Protoss_Nexus 1 10525
Protoss_Observer 3 10955
Protoss_Forge 1 10110
11321
