Protoss_Gateway 2 8908
Protoss_Assimilator 1 3374
Protoss_Cybernetics_Core 1 4538
Protoss_Dragoon 5 9195
Protoss_Robotics_Facility 1 6513
Protoss_Nexus 1 8873
Protoss_Observatory 1 6912
Protoss_Observer 3 10918
Protoss_Shuttle 1 10496
10918
