Protoss_Gateway 2 6635
Protoss_Assimilator 1 3627
Protoss_Cybernetics_Core 1 4706
Protoss_Dragoon 11 10917
Protoss_Robotics_Facility 1 8150
Protoss_Observatory 1 8513
Protoss_Observer 2 9937
Protoss_Nexus 1 12791
12791
