Protoss_Gateway 2 7509
Protoss_Assimilator 1 3283
Protoss_Cybernetics_Core 1 4584
Protoss_Dragoon 7 10251
Protoss_Robotics_Facility 1 7714
Protoss_Shuttle 1 8831
Protoss_Observatory 1 8232
Protoss_Zealot 2 9352
Protoss_Nexus 2 12839
Protoss_Observer 1 9616
12839
