Protoss_Gateway 3 10939
Protoss_Assimilator 1 3736
Protoss_Zealot 4 9691
Protoss_Cybernetics_Core 1 4850
Protoss_Dragoon 7 10809
Protoss_Nexus 1 9169
Protoss_Robotics_Facility 1 8408
Protoss_Shuttle 1 9207
Protoss_Robotics_Support_Bay 1 8827
Protoss_Observatory 1 9109
Protoss_Reaver 1 10495
Protoss_Observer 1 10827
10939
