Protoss_Gateway 2 10597
Protoss_Assimilator 2 4287
Protoss_Zealot 3 5447
Protoss_Cybernetics_Core 1 5660
Protoss_Citadel_of_Adun 1 6806
Protoss_Dragoon 5 11195
Protoss_Templar_Archives 1 7830
Protoss_Nexus 1 10021
Protoss_Dark_Templar 2 9329
Protoss_Forge 1 8716
Protoss_Photon_Cannon 1 9706
Protoss_Robotics_Facility 1 11353
11353
