Protoss_Gateway 2 8221
Protoss_Assimilator 1 3252
Protoss_Cybernetics_Core 1 4385
Protoss_Dragoon 4 10749
Protoss_Citadel_of_Adun 1 5692
Protoss_Templar_Archives 1 6897
Protoss_Nexus 1 9305
Protoss_Dark_Templar 4 9511
Protoss_Zealot 1 8157
Protoss_Robotics_Facility 1 10799
10799
