Protoss_Assimilator 1 2848
Protoss_Gateway 2 10785
Protoss_Cybernetics_Core 1 4823
Protoss_Dragoon 6 10468
Protoss_Robotics_Facility 1 6563
Protoss_Shuttle 2 11366
Protoss_Observatory 1 7823
Protoss_Nexus 1 10749
Protoss_Observer 2 9543
Protoss_Forge 1 9096
Protoss_Photon_Cannon 1 10442
11366
