Protoss_Gateway 2 9633
Protoss_Assimilator 1 3513
Protoss_Cybernetics_Core 1 4658
Protoss_Robotics_Facility 1 6193
Protoss_Dragoon 6 10965
Protoss_Zealot 2 6860
Protoss_Shuttle 1 7006
Protoss_Robotics_Support_Bay 1 6954
Protoss_Reaver 2 10951
Protoss_Scarab 5 9852
10965
