Protoss_Gateway 4 11249
Protoss_Assimilator 1 3439
Protoss_Cybernetics_Core 1 4792
Protoss_Dragoon 7 9715
Protoss_Nexus 1 9057
Protoss_Robotics_Facility 1 9186
Protoss_Observatory 1 9395
Protoss_Observer 2 10857
Protoss_Zealot 2 10313
Protoss_Shuttle 1 11437
11437
