Protoss_Gateway 1 3436
Protoss_Assimilator 1 3317
Protoss_Zealot 2 4548
Protoss_Cybernetics_Core 1 4733
Protoss_Dragoon 8 11157
Protoss_Robotics_Facility 1 7711
Protoss_Robotics_Support_Bay 1 7847
Protoss_Shuttle 1 8886
Protoss_Reaver 1 10111
Protoss_Nexus 1 12385
12385
