Protoss_Gateway 2 8818
Protoss_Assimilator 2 9663
Protoss_Cybernetics_Core 1 4483
Protoss_Dragoon 10 10719
Protoss_Nexus 1 8977
Protoss_Robotics_Facility 1 8907
Protoss_Observatory 1 9040
Protoss_Observer 1 9963
Protoss_Shuttle 1 11283
Protoss_Robotics_Support_Bay 1 10634
11283
