Protoss_Nexus 2 11698
Protoss_Gateway 3 11387
Protoss_Assimilator 2 8369
Protoss_Cybernetics_Core 1 5683
Protoss_Zealot 1 5375
Protoss_Dragoon 10 11090
Protoss_Robotics_Facility 1 9230
Protoss_Observatory 1 9674
Protoss_Observer 1 10465
Protoss_Citadel_of_Adun 1 11233
11698
