Protoss_Nexus 3 11197
Protoss_Gateway 4 11381
Protoss_Assimilator 2 9682
Protoss_Zealot 1 5015
Protoss_Cybernetics_Core 1 5778
Protoss_Citadel_of_Adun 1 6804
Protoss_Dragoon 3 10511
Protoss_Forge 1 7014
Protoss_Templar_Archives 1 7875
Protoss_Photon_Cannon 1 8519
Protoss_Dark_Templar 1 8655
Protoss_Robotics_Facility 1 10707
11381
