Protoss_Gateway 4 11113
Protoss_Assimilator 4 8878
Protoss_Zealot 3 5113
Protoss_Nexus 1 7853
Protoss_Cybernetics_Core 1 7283
Protoss_Dragoon 7 10493
Protoss_Robotics_Facility 1 11079
11113
