Protoss_Gateway 2 6453
Protoss_Zealot 4 9997
Protoss_Nexus 1 7068
Protoss_Assimilator 2 8715
Protoss_Cybernetics_Core 1 6133
Protoss_Dragoon 6 10957
Protoss_Robotics_Facility 1 9225
Protoss_Shuttle 1 10035
Protoss_Robotics_Support_Bay 1 9335
Protoss_Stargate 1 10676
Protoss_Reaver 1 11177
Protoss_Observatory 1 10366
11177
