Protoss_Gateway 2 8648
Protoss_Assimilator 1 3318
Protoss_Cybernetics_Core 1 4446
Protoss_Dragoon 2 6396
Protoss_Robotics_Facility 1 6582
Protoss_Observatory 1 6765
Protoss_Citadel_of_Adun 1 7584
Protoss_Zealot 4 9516
Protoss_Observer 2 8221
Protoss_Shuttle 2 10816
10816
