Protoss_Gateway 4 9779
Protoss_Assimilator 2 10801
Protoss_Cybernetics_Core 1 4471
Protoss_Nexus 1 7051
Protoss_Dragoon 8 9203
Protoss_Zealot 7 10427
Protoss_Citadel_of_Adun 1 8825
Protoss_Robotics_Facility 1 11592
11592
