Protoss_Gateway 4 10825
Protoss_Assimilator 2 8983
Protoss_Cybernetics_Core 1 4306
Protoss_Dragoon 5 10193
Protoss_Citadel_of_Adun 1 6705
Protoss_Templar_Archives 1 7694
Protoss_Nexus 1 10066
Protoss_Dark_Templar 1 8443
Protoss_Stargate 1 9206
Protoss_Arbiter_Tribunal 1 10199
Protoss_Arbiter 1 13581
13581
