Protoss_Gateway 2 9959
Protoss_Assimilator 1 3291
Protoss_Cybernetics_Core 1 4588
Protoss_Dragoon 8 11091
Protoss_Robotics_Facility 1 7297
Protoss_Shuttle 1 8163
Protoss_Robotics_Support_Bay 1 7579
Protoss_Reaver 2 11061
Protoss_Nexus 1 10877
Protoss_Observatory 1 9355
Protoss_Scarab 2 9245
11091
