Protoss_Gateway 1 3345
Protoss_Assimilator 1 3344
Protoss_Cybernetics_Core 1 4423
Protoss_Robotics_Facility 1 6109
Protoss_Dragoon 6 10825
Protoss_Shuttle 1 6907
Protoss_Robotics_Support_Bay 1 6935
Protoss_Zealot 2 9147
Protoss_Reaver 2 11435
Protoss_Observatory 1 8353
Protoss_Nexus 2 12689
Protoss_Scarab 3 9476
12689
