Protoss_Gateway 2 8674
Protoss_Assimilator 1 3205
Protoss_Cybernetics_Core 1 4327
Protoss_Dragoon 10 10743
Protoss_Nexus 1 9110
Protoss_Robotics_Facility 1 8617
Protoss_Shuttle 1 9527
Protoss_Observatory 1 8931
Protoss_Observer 1 9949
Protoss_Robotics_Support_Bay 1 9922
10743
