Protoss_Gateway 2 9971
Protoss_Assimilator 1 3280
Protoss_Cybernetics_Core 1 4377
Protoss_Dragoon 7 10719
Protoss_Nexus 1 8847
Protoss_Robotics_Facility 1 8938
Protoss_Shuttle 1 9743
Protoss_Robotics_Support_Bay 1 9080
Protoss_Zealot 2 10309
Protoss_Observatory 1 9920
Protoss_Reaver 1 10885
10885
