Protoss_Gateway 2 5528
Protoss_Zealot 3 10651
Protoss_Assimilator 2 9882
Protoss_Cybernetics_Core 1 4905
Protoss_Dragoon 7 8855
Protoss_Nexus 1 9003
Protoss_Robotics_Facility 1 9222
Protoss_Shuttle 1 10149
Protoss_Robotics_Support_Bay 1 9470
Protoss_Stargate 1 10845
Protoss_Observatory 1 9994
Protoss_Reaver 1 11291
11291
