Protoss_Gateway 2 11111
Protoss_Assimilator 1 3358
Protoss_Cybernetics_Core 1 4411
Protoss_Dragoon 7 10429
Protoss_Robotics_Facility 1 7326
Protoss_Observatory 1 7518
Protoss_Nexus 1 9755
Protoss_Observer 1 8305
Protoss_Shuttle 1 9387
Protoss_Robotics_Support_Bay 1 8814
Protoss_Reaver 1 10667
11111
