Protoss_Gateway 2 3837
Protoss_Zealot 8 8673
Protoss_Assimilator 1 5208
Protoss_Cybernetics_Core 1 6703
Protoss_Dragoon 6 10323
Protoss_Robotics_Facility 1 9465
Protoss_Observatory 1 9551
Protoss_Observer 1 10685
10685
