Protoss_Gateway 2 3999
Protoss_Zealot 8 6699
Protoss_Assimilator 1 5566
Protoss_Cybernetics_Core 1 7038
Protoss_Dragoon 7 10365
Protoss_Nexus 2 12865
Protoss_Robotics_Facility 1 10869
12865
