Protoss_Gateway 4 11309
Protoss_Forge 1 4127
Protoss_Zealot 3 9017
Protoss_Photon_Cannon 2 6201
Protoss_Assimilator 1 5834
Protoss_Cybernetics_Core 1 6728
Protoss_Dragoon 8 10783
Protoss_Nexus 1 11651
11651
