Protoss_Gateway 1 3297
Protoss_Assimilator 1 3209
Protoss_Cybernetics_Core 1 4315
Protoss_Dragoon 7 11171
Protoss_Nexus 2 11729
Protoss_Robotics_Facility 1 8129
Protoss_Shuttle 1 8933
Protoss_Robotics_Support_Bay 1 8265
Protoss_Reaver 2 11303
Protoss_Observatory 1 9768
11729
