Protoss_Gateway 3 10895
Protoss_Zealot 4 5999
Protoss_Forge 1 4279
Protoss_Photon_Cannon 3 7686
Protoss_Assimilator 1 6193
Protoss_Cybernetics_Core 1 7209
Protoss_Dragoon 8 11145
Protoss_Citadel_of_Adun 1 11180
11180
