Protoss_Gateway 2 7473
Protoss_Assimilator 1 3336
Protoss_Cybernetics_Core 1 4458
Protoss_Dragoon 11 11167
Protoss_Robotics_Facility 1 7599
Protoss_Shuttle 1 8459
Protoss_Observatory 1 8047
Protoss_Observer 2 10635
Protoss_Robotics_Support_Bay 1 8653
Protoss_Reaver 1 10303
Protoss_Zealot 2 10047
11167
