Protoss_Gateway 2 9238
Protoss_Assimilator 1 2223
Protoss_Cybernetics_Core 1 2945
Protoss_Zealot 3 7939
Protoss_Dragoon 6 9293
Protoss_Robotics_Facility 1 5460
Protoss_Shuttle 1 6787
Protoss_Robotics_Support_Bay 1 6888
Protoss_Reaver 1 7761
Protoss_Observatory 1 8002
Protoss_Observer 2 9415
Protoss_Scarab 1 9049
9415
