Protoss_Gateway 4 10913
Protoss_Assimilator 2 9468
Protoss_Cybernetics_Core 1 4377
Protoss_Dragoon 5 8229
Protoss_Robotics_Facility 1 7530
Protoss_Observatory 1 7727
Protoss_Nexus 2 11977
Protoss_Observer 2 9841
Protoss_Zealot 1 8869
Protoss_Citadel_of_Adun 1 9899
Protoss_Templar_Archives 1 11264
11977
