Protoss_Gateway 3 11085
Protoss_Assimilator 1 3297
Protoss_Cybernetics_Core 1 4458
Protoss_Dragoon 8 11157
Protoss_Nexus 1 8759
Protoss_Robotics_Facility 1 8803
Protoss_Shuttle 1 9749
Protoss_Robotics_Support_Bay 1 9210
Protoss_Observatory 1 9562
Protoss_Reaver 1 10891
Protoss_Zealot 2 10315
11157
