Protoss_Gateway 3 8811
Protoss_Assimilator 1 3381
Protoss_Cybernetics_Core 1 4485
Protoss_Dragoon 10 10979
Protoss_Robotics_Facility 1 6357
Protoss_Shuttle 1 7183
Protoss_Zealot 2 7885
Protoss_Robotics_Support_Bay 1 6935
Protoss_Reaver 1 8429
Protoss_Observatory 1 7963
Protoss_Observer 1 8807
Protoss_Scarab 6 9686
10979
