Protoss_Gateway 3 10774
Protoss_Assimilator 1 3413
Protoss_Cybernetics_Core 1 4570
Protoss_Dragoon 8 10959
Protoss_Robotics_Facility 1 7887
Protoss_Nexus 2 10390
Protoss_Observatory 1 8005
Protoss_Observer 2 9869
10959
