Protoss_Gateway 2 6160
Protoss_Assimilator 1 3660
Protoss_Cybernetics_Core 1 5233
Protoss_Dragoon 11 11195
Protoss_Robotics_Facility 1 9676
Protoss_Nexus 1 11905
Protoss_Observatory 1 9830
11905
