Protoss_Nexus 1 5871
Protoss_Gateway 4 11153
Protoss_Assimilator 2 9950
Protoss_Cybernetics_Core 1 5977
Protoss_Zealot 6 10373
Protoss_Dragoon 8 10658
Protoss_Robotics_Facility 1 10183
Protoss_Observatory 1 10553
Protoss_Shuttle 1 11351
11351
