Protoss_Gateway 2 7602
Protoss_Assimilator 1 3330
Protoss_Cybernetics_Core 1 4427
Protoss_Dragoon 3 9775
Protoss_Citadel_of_Adun 1 6776
Protoss_Robotics_Facility 1 7990
Protoss_Templar_Archives 1 7890
Protoss_Shuttle 1 8795
Protoss_Dark_Templar 2 8639
Protoss_Nexus 1 10983
Protoss_Stargate 1 10022
10983
