Protoss_Gateway 7 10677
Protoss_Assimilator 2 5087
Protoss_Zealot 6 10911
Protoss_Cybernetics_Core 1 7206
Protoss_Dragoon 2 8003
Protoss_Citadel_of_Adun 1 8295
Protoss_Templar_Archives 1 9290
Protoss_Nexus 1 10967
Protoss_Dark_Templar 2 10033
10967
