Protoss_Gateway 2 6179
Protoss_Assimilator 2 10310
Protoss_Cybernetics_Core 1 4475
Protoss_Dragoon 6 9465
Protoss_Nexus 2 10818
Protoss_Citadel_of_Adun 1 8739
Protoss_Templar_Archives 1 9793
Protoss_Dark_Templar 2 10549
Protoss_Stargate 1 11620
11620
