Protoss_Gateway 2 6674
Protoss_Assimilator 1 3287
Protoss_Cybernetics_Core 1 4474
Protoss_Robotics_Facility 1 6035
Protoss_Dragoon 9 11176
Protoss_Observatory 1 6238
Protoss_Observer 2 10809
Protoss_Shuttle 1 8783
11176
