Protoss_Gateway 2 5571
Protoss_Assimilator 1 3357
Protoss_Cybernetics_Core 1 4445
Protoss_Zealot 1 4277
Protoss_Dragoon 3 6395
Protoss_Stargate 2 8392
Protoss_Fleet_Beacon 1 7728
Protoss_Carrier 2 12155
Protoss_Forge 1 8974
Protoss_Photon_Cannon 2 10328
12155
