Protoss_Gateway 2 4953
Protoss_Assimilator 1 3489
Protoss_Cybernetics_Core 1 4482
Protoss_Dragoon 8 10985
Protoss_Citadel_of_Adun 1 7409
Protoss_Templar_Archives 1 8395
Protoss_Zealot 2 8401
Protoss_Dark_Templar 4 10101
Protoss_Nexus 1 11364
11364
