Protoss_Gateway 3 10491
Protoss_Assimilator 1 3215
Protoss_Cybernetics_Core 1 4390
Protoss_Dragoon 9 10889
Protoss_Nexus 2 12545
Protoss_Robotics_Facility 1 7933
Protoss_Observatory 1 8080
Protoss_Observer 2 10629
Protoss_Shuttle 1 10017
12545
