Protoss_Assimilator 1 2667
Protoss_Gateway 3 10049
Protoss_Cybernetics_Core 1 4621
Protoss_Dragoon 6 11191
Protoss_Citadel_of_Adun 1 6959
Protoss_Robotics_Facility 1 8137
Protoss_Templar_Archives 1 7945
Protoss_Dark_Templar 4 11021
Protoss_Shuttle 1 9003
Protoss_Observatory 1 8479
Protoss_Observer 1 9939
Protoss_Zealot 2 10729
11191
