Protoss_Gateway 3 11269
Protoss_Assimilator 1 3385
Protoss_Cybernetics_Core 1 4499
Protoss_Dragoon 11 10921
Protoss_Robotics_Facility 1 8003
Protoss_Observatory 1 8212
Protoss_Nexus 1 10804
Protoss_Observer 2 9641
11269
