Protoss_Gateway 1 3309
Protoss_Assimilator 1 3291
Protoss_Cybernetics_Core 1 4420
Protoss_Robotics_Facility 1 6131
Protoss_Dragoon 3 10357
Protoss_Shuttle 2 11245
Protoss_Robotics_Support_Bay 1 6459
Protoss_Zealot 2 7623
Protoss_Reaver 2 10433
Protoss_Nexus 2 12185
Protoss_Observatory 1 8519
Protoss_Scarab 4 8605
12185
