Protoss_Gateway 4 11296
Protoss_Assimilator 1 3151
Protoss_Cybernetics_Core 1 4282
Protoss_Dragoon 11 11129
Protoss_Nexus 2 12156
Protoss_Robotics_Facility 1 8444
Protoss_Observatory 1 8665
Protoss_Observer 3 10893
12156
