Protoss_Gateway 2 10014
Protoss_Assimilator 1 3361
Protoss_Cybernetics_Core 1 4397
Protoss_Dragoon 7 10803
Protoss_Nexus 2 12867
Protoss_Robotics_Facility 1 8847
Protoss_Shuttle 1 9651
Protoss_Robotics_Support_Bay 1 9075
Protoss_Zealot 2 10477
Protoss_Reaver 1 10793
12867
