Protoss_Gateway 4 8891
Protoss_Zealot 8 9451
Protoss_Assimilator 4 9856
Protoss_Forge 1 5540
Protoss_Photon_Cannon 2 8873
Protoss_Nexus 1 9333
Protoss_Cybernetics_Core 1 9461
Protoss_Dragoon 2 10319
10319
