Protoss_Gateway 2 6903
Protoss_Assimilator 1 3165
Protoss_Cybernetics_Core 1 4501
Protoss_Dragoon 5 10733
Protoss_Citadel_of_Adun 1 5635
Protoss_Robotics_Facility 1 6838
Protoss_Templar_Archives 1 7264
Protoss_Shuttle 1 7641
Protoss_Dark_Templar 2 8021
Protoss_Nexus 1 10594
10733
