Protoss_Gateway 2 10754
Protoss_Assimilator 2 10849
Protoss_Cybernetics_Core 1 4548
Protoss_Dragoon 7 11086
Protoss_Nexus 2 11318
Protoss_Robotics_Facility 1 9263
Protoss_Observatory 1 9665
Protoss_Citadel_of_Adun 1 10868
Protoss_Observer 1 10506
11318
