Protoss_Gateway 3 11096
Protoss_Assimilator 2 3878
Protoss_Zealot 6 7031
Protoss_Cybernetics_Core 1 7081
Protoss_Dragoon 7 10665
Protoss_Robotics_Facility 1 9512
Protoss_Observatory 1 9729
Protoss_Observer 1 10506
11096
