Protoss_Gateway 3 11292
Protoss_Zealot 2 4947
Protoss_Assimilator 1 4242
Protoss_Cybernetics_Core 1 5184
Protoss_Dragoon 5 9033
Protoss_Nexus 2 11833
Protoss_Robotics_Facility 1 9887
Protoss_Observatory 1 10128
11833
