Protoss_Gateway 2 9130
Protoss_Assimilator 1 3294
Protoss_Cybernetics_Core 1 4335
Protoss_Dragoon 10 10655
Protoss_Robotics_Facility 1 7269
Protoss_Nexus 2 11943
Protoss_Observatory 1 8016
Protoss_Observer 3 10269
11943
