Protoss_Assimilator 1 2594
Protoss_Gateway 2 7216
Protoss_Cybernetics_Core 1 4635
Protoss_Dragoon 4 10645
Protoss_Citadel_of_Adun 1 6393
Protoss_Robotics_Facility 1 6972
Protoss_Templar_Archives 1 7459
Protoss_Shuttle 1 7949
Protoss_Dark_Templar 2 8221
Protoss_Nexus 1 10961
Protoss_High_Templar 2 9365
Protoss_Zealot 2 10203
10961
