Protoss_Gateway 2 3711
Protoss_Zealot 6 5595
Protoss_Forge 1 5363
Protoss_Photon_Cannon 3 8477
Protoss_Assimilator 2 10649
Protoss_Cybernetics_Core 1 7550
Protoss_Citadel_of_Adun 1 8943
Protoss_Nexus 1 11273
Protoss_Templar_Archives 1 10121
Protoss_Robotics_Facility 1 11475
Protoss_Dark_Templar 1 10973
11475
