Protoss_Gateway 2 7280
Protoss_Assimilator 1 3294
Protoss_Cybernetics_Core 1 4446
Protoss_Dragoon 8 9693
Protoss_Robotics_Facility 1 7203
Protoss_Observatory 1 7372
Protoss_Nexus 1 9816
Protoss_Observer 1 8449
Protoss_Shuttle 1 9689
Protoss_Robotics_Support_Bay 1 9064
Protoss_Reaver 1 10849
Protoss_Zealot 2 10773
10849
