Protoss_Gateway 3 9753
Protoss_Assimilator 1 3279
Protoss_Cybernetics_Core 1 4325
Protoss_Zealot 1 4173
Protoss_Dragoon 11 10833
Protoss_Robotics_Facility 1 7537
Protoss_Observatory 1 7625
Protoss_Observer 2 9597
Protoss_Nexus 1 10577
10833
