Protoss_Gateway 2 6089
Protoss_Assimilator 1 3179
Protoss_Cybernetics_Core 1 4360
Protoss_Dragoon 8 10869
Protoss_Citadel_of_Adun 1 7351
Protoss_Zealot 2 7761
Protoss_Templar_Archives 1 8335
Protoss_Dark_Templar 2 9249
Protoss_Nexus 1 11223
11223
