Protoss_Gateway 1 3345
Protoss_Zealot 3 5059
Protoss_Assimilator 1 4058
Protoss_Cybernetics_Core 1 5426
Protoss_Robotics_Facility 1 6950
Protoss_Dragoon 6 10615
Protoss_Shuttle 1 7785
Protoss_Robotics_Support_Bay 1 7293
Protoss_Reaver 1 8927
Protoss_Observatory 1 8495
Protoss_Observer 1 9583
Protoss_Nexus 1 12683
12683
