Protoss_Gateway 2 8363
Protoss_Zealot 3 5419
Protoss_Assimilator 2 8374
Protoss_Cybernetics_Core 1 5740
Protoss_Nexus 1 8401
Protoss_Dragoon 8 10755
Protoss_Robotics_Facility 1 9826
Protoss_Robotics_Support_Bay 1 9993
Protoss_Observatory 1 10177
10755
