Protoss_Gateway 2 10721
Protoss_Assimilator 1 3226
Protoss_Cybernetics_Core 1 4305
Protoss_Dragoon 6 10625
Protoss_Robotics_Facility 1 7145
Protoss_Shuttle 1 7951
Protoss_Robotics_Support_Bay 1 7313
Protoss_Zealot 2 8551
Protoss_Observatory 1 8108
Protoss_Reaver 1 9109
Protoss_Nexus 1 11161
Protoss_Observer 2 10335
11161
