Protoss_Gateway 4 10927
Protoss_Nexus 1 6211
Protoss_Zealot 2 5831
Protoss_Assimilator 1 4976
Protoss_Cybernetics_Core 1 5985
Protoss_Dragoon 8 10493
Protoss_Robotics_Facility 1 11652
11652
