Protoss_Gateway 1 3319
Protoss_Assimilator 1 3325
Protoss_Zealot 9 9301
Protoss_Forge 1 4979
Protoss_Photon_Cannon 2 6345
Protoss_Cybernetics_Core 1 8109
Protoss_Nexus 2 11625
Protoss_Robotics_Facility 1 9787
Protoss_Shuttle 1 10709
Protoss_Robotics_Support_Bay 1 10369
11625
