Protoss_Gateway 2 7711
Protoss_Assimilator 1 3465
Protoss_Cybernetics_Core 1 4590
Protoss_Dragoon 7 10296
Protoss_Robotics_Facility 1 6598
Protoss_Observatory 1 6693
Protoss_Observer 3 9911
Protoss_Nexus 1 11597
11597
