Protoss_Gateway 2 10957
Protoss_Assimilator 2 3691
Protoss_Zealot 2 4381
Protoss_Cybernetics_Core 1 4525
Protoss_Dragoon 7 10667
Protoss_Robotics_Facility 1 6691
Protoss_Shuttle 1 7533
Protoss_Robotics_Support_Bay 1 7372
Protoss_Reaver 1 8885
Protoss_Observatory 1 8417
Protoss_Scarab 7 9990
Protoss_Observer 3 10777
Protoss_Nexus 1 12175
12175
