Protoss_Gateway 4 11031
Protoss_Assimilator 1 3271
Protoss_Zealot 2 4867
Protoss_Cybernetics_Core 1 5041
Protoss_Dragoon 8 9567
Protoss_Citadel_of_Adun 1 8510
Protoss_Templar_Archives 1 9618
Protoss_Nexus 1 11624
Protoss_Dark_Templar 4 11183
11624
