Protoss_Gateway 3 10616
Protoss_Assimilator 1 3401
Protoss_Cybernetics_Core 1 4529
Protoss_Zealot 3 10019
Protoss_Dragoon 8 11053
Protoss_Robotics_Facility 1 7458
Protoss_Nexus 1 9478
Protoss_Shuttle 1 8355
Protoss_Observatory 1 7786
Protoss_Robotics_Support_Bay 1 8629
Protoss_Observer 2 10595
Protoss_Reaver 1 10263
11053
