Protoss_Gateway 2 8293
Protoss_Assimilator 1 3413
Protoss_Cybernetics_Core 1 4478
Protoss_Dragoon 9 10961
Protoss_Robotics_Facility 1 7712
Protoss_Observatory 1 7924
Protoss_Nexus 1 10863
Protoss_Observer 3 10806
10961
