Protoss_Gateway 1 3392
Protoss_Assimilator 1 3396
Protoss_Cybernetics_Core 1 4524
Protoss_Zealot 1 4227
Protoss_Dragoon 6 9621
Protoss_Robotics_Facility 1 7479
Protoss_Observatory 1 7566
Protoss_Nexus 1 10145
Protoss_Observer 2 9023
Protoss_Shuttle 1 10105
Protoss_Robotics_Support_Bay 1 9901
Protoss_Reaver 1 11403
11403
