Protoss_Nexus 1 5555
Protoss_Gateway 3 10167
Protoss_Assimilator 1 4251
Protoss_Cybernetics_Core 1 5445
Protoss_Zealot 2 10689
Protoss_Dragoon 10 11185
Protoss_Robotics_Facility 1 10191
Protoss_Shuttle 1 10999
Protoss_Observatory 1 10358
11185
