Protoss_Gateway 2 6851
Protoss_Assimilator 1 3313
Protoss_Cybernetics_Core 1 4391
Protoss_Dragoon 9 9243
Protoss_Robotics_Facility 1 7758
Protoss_Shuttle 1 8753
Protoss_Robotics_Support_Bay 1 8091
Protoss_Reaver 1 10061
Protoss_Nexus 1 12125
Protoss_Zealot 2 10371
Protoss_Observatory 1 10417
12125
