Protoss_Gateway 2 3907
Protoss_Zealot 7 9833
Protoss_Assimilator 1 5404
Protoss_Cybernetics_Core 1 6523
Protoss_Dragoon 8 10999
Protoss_Citadel_of_Adun 1 9835
Protoss_Forge 1 10295
Protoss_Templar_Archives 1 11108
11108
