Protoss_Gateway 2 6264
Protoss_Assimilator 3 5219
Protoss_Cybernetics_Core 1 4802
Protoss_Dragoon 7 8513
Protoss_Robotics_Facility 1 8820
Protoss_Shuttle 1 9653
Protoss_Robotics_Support_Bay 1 9438
Protoss_Zealot 2 9959
Protoss_Reaver 1 10935
Protoss_Observatory 1 10404
Protoss_Nexus 1 12725
12725
