Protoss_Nexus 2 12283
Protoss_Gateway 2 5749
Protoss_Assimilator 2 9335
Protoss_Cybernetics_Core 1 5408
Protoss_Zealot 1 5731
Protoss_Dragoon 10 10689
Protoss_Robotics_Facility 1 8630
Protoss_Observatory 1 9023
Protoss_Shuttle 1 9895
Protoss_Robotics_Support_Bay 1 9552
Protoss_Observer 1 10391
12283
