Protoss_Gateway 2 9970
Protoss_Assimilator 1 3909
Protoss_Cybernetics_Core 1 4452
Protoss_Dragoon 6 10913
Protoss_Nexus 2 12383
Protoss_Robotics_Facility 1 7903
Protoss_Shuttle 1 8707
Protoss_Robotics_Support_Bay 1 8239
Protoss_Zealot 2 9229
Protoss_Reaver 1 9925
Protoss_Observatory 1 9359
Protoss_Observer 2 10859
12383
