Protoss_Gateway 3 10556
Protoss_Assimilator 2 3691
Protoss_Cybernetics_Core 1 4840
Protoss_Zealot 1 4931
Protoss_Dragoon 5 10925
Protoss_Shield_Battery 1 6522
Protoss_Citadel_of_Adun 1 8040
Protoss_Nexus 1 10247
Protoss_Templar_Archives 1 9167
Protoss_Dark_Templar 2 9939
10925
