Protoss_Gateway 2 7942
Protoss_Assimilator 1 3165
Protoss_Cybernetics_Core 1 4308
Protoss_Zealot 1 4143
Protoss_Dragoon 9 10529
Protoss_Robotics_Facility 1 7231
Protoss_Shuttle 1 8173
Protoss_Robotics_Support_Bay 1 7571
Protoss_Reaver 1 9947
Protoss_Nexus 1 11811
Protoss_Observatory 1 9845
Protoss_Observer 1 10645
11811
