Protoss_Gateway 2 11088
Protoss_Assimilator 1 3548
Protoss_Cybernetics_Core 1 4830
Protoss_Zealot 1 4621
Protoss_Dragoon 4 9250
Protoss_Nexus 1 11528
Protoss_Citadel_of_Adun 1 11189
11528
