Protoss_Gateway 2 8735
Protoss_Assimilator 1 3445
Protoss_Zealot 2 4851
Protoss_Cybernetics_Core 1 5171
Protoss_Dragoon 4 10451
Protoss_Nexus 2 12822
Protoss_Citadel_of_Adun 1 7866
Protoss_Robotics_Facility 1 8802
Protoss_Templar_Archives 1 8951
Protoss_Shuttle 1 9623
Protoss_Dark_Templar 3 10447
Protoss_Observatory 1 9636
Protoss_Observer 1 10421
12822
