Protoss_Gateway 4 11062
Protoss_Assimilator 1 3165
Protoss_Cybernetics_Core 1 4320
Protoss_Zealot 1 4481
Protoss_Dragoon 4 7589
Protoss_Citadel_of_Adun 1 6787
Protoss_Templar_Archives 1 7791
Protoss_Dark_Templar 4 10473
Protoss_Nexus 1 10293
11062
