Protoss_Gateway 1 3445
Protoss_Assimilator 1 3614
Protoss_Cybernetics_Core 1 4566
Protoss_Dragoon 6 10409
Protoss_Robotics_Facility 1 7573
Protoss_Shuttle 1 8419
Protoss_Observatory 1 7747
Protoss_Robotics_Support_Bay 1 7946
Protoss_Zealot 1 8521
Protoss_Reaver 2 10652
Protoss_Nexus 1 12833
12833
