Protoss_Gateway 2 7021
Protoss_Assimilator 1 3501
Protoss_Cybernetics_Core 1 4694
Protoss_Dragoon 11 11149
Protoss_Robotics_Facility 1 8165
Protoss_Observatory 1 8264
Protoss_Observer 2 9655
Protoss_Shuttle 1 10737
Protoss_Nexus 1 12517
12517
