Protoss_Gateway 2 6903
Protoss_Assimilator 1 3282
Protoss_Zealot 2 4939
Protoss_Cybernetics_Core 1 5107
Protoss_Dragoon 8 10585
Protoss_Nexus 2 12661
Protoss_Robotics_Facility 1 9960
Protoss_Shuttle 1 10867
Protoss_Observatory 1 10358
12661
