Protoss_Gateway 2 4774
Protoss_Zealot 2 5313
Protoss_Assimilator 1 4344
Protoss_Cybernetics_Core 1 5757
Protoss_Dragoon 6 10559
Protoss_Nexus 2 11871
Protoss_Robotics_Facility 1 10122
Protoss_Shuttle 1 11127
Protoss_Observatory 1 10560
11871
