Protoss_Gateway 3 9742
Protoss_Assimilator 3 8223
Protoss_Zealot 7 8689
Protoss_Nexus 1 8224
Protoss_Cybernetics_Core 1 7270
Protoss_Citadel_of_Adun 1 8793
Protoss_Dragoon 4 10125
Protoss_Templar_Archives 1 9979
Protoss_Dark_Templar 3 10877
10877
