Protoss_Gateway 4 10634
Protoss_Zealot 4 5811
Protoss_Assimilator 1 3895
Protoss_Cybernetics_Core 1 5435
Protoss_Dragoon 7 10975
Protoss_Robotics_Facility 1 8626
Protoss_Nexus 1 10659
Protoss_Observatory 1 9200
Protoss_Observer 2 10711
10975
