Protoss_Gateway 1 3293
Protoss_Assimilator 1 3166
Protoss_Cybernetics_Core 1 4283
Protoss_Zealot 1 4129
Protoss_Dragoon 8 10821
Protoss_Robotics_Facility 1 7327
Protoss_Shuttle 1 8161
Protoss_Robotics_Support_Bay 1 7737
Protoss_Reaver 2 11237
Protoss_Scarab 4 9831
Protoss_Nexus 1 12529
12529
