Protoss_Gateway 3 10990
Protoss_Assimilator 1 3394
Protoss_Cybernetics_Core 1 4424
Protoss_Dragoon 2 6847
Protoss_Citadel_of_Adun 1 5711
Protoss_Templar_Archives 1 6750
Protoss_Dark_Templar 4 8399
Protoss_Nexus 1 10387
Protoss_Robotics_Facility 1 10166
Protoss_Zealot 2 9769
Protoss_Shuttle 1 10975
Protoss_Observatory 1 10367
10990
