Protoss_Nexus 2 11321
Protoss_Gateway 3 8709
Protoss_Assimilator 1 4356
Protoss_Cybernetics_Core 1 5710
Protoss_Zealot 1 5707
Protoss_Dragoon 10 11031
Protoss_Robotics_Facility 1 8515
Protoss_Observatory 1 8734
Protoss_Observer 2 10597
11321
