Protoss_Gateway 3 9388
Protoss_Assimilator 1 3324
Protoss_Cybernetics_Core 1 4372
Protoss_Dragoon 9 9666
Protoss_Robotics_Facility 1 7963
Protoss_Observatory 1 8131
Protoss_Observer 2 9543
Protoss_Shuttle 1 10625
Protoss_Nexus 1 12403
Protoss_Citadel_of_Adun 1 11435
12403
