Protoss_Assimilator 2 3972
Protoss_Gateway 2 6667
Protoss_Cybernetics_Core 1 5024
Protoss_Dragoon 7 11146
Protoss_Citadel_of_Adun 1 7323
Protoss_Templar_Archives 1 8323
Protoss_Dark_Templar 2 9171
Protoss_Robotics_Facility 1 11378
11378
