Protoss_Gateway 2 7459
Protoss_Assimilator 1 3316
Protoss_Cybernetics_Core 1 4415
Protoss_Dragoon 9 11089
Protoss_Robotics_Facility 1 7303
Protoss_Observatory 1 7418
Protoss_Observer 1 8203
Protoss_Shuttle 1 9285
Protoss_Zealot 4 9477
Protoss_Nexus 1 12233
Protoss_Citadel_of_Adun 1 11224
12233
