Protoss_Gateway 2 3691
Protoss_Zealot 6 5535
Protoss_Assimilator 1 4662
Protoss_Cybernetics_Core 1 5569
Protoss_Dragoon 8 10643
Protoss_Citadel_of_Adun 1 9338
Protoss_Templar_Archives 1 10535
10643
