Protoss_Gateway 3 11333
Protoss_Assimilator 1 3297
Protoss_Cybernetics_Core 1 4411
Protoss_Dragoon 10 11093
Protoss_Robotics_Facility 1 7343
Protoss_Observatory 1 7712
Protoss_Observer 2 9085
Protoss_Nexus 2 12041
12041
