Protoss_Gateway 2 8016
Protoss_Assimilator 1 3293
Protoss_Cybernetics_Core 1 4465
Protoss_Dragoon 9 10757
Protoss_Robotics_Facility 1 8386
Protoss_Observatory 1 8619
Protoss_Nexus 1 10934
Protoss_Observer 2 10635
Protoss_Zealot 2 9605
10934
