Protoss_Gateway 2 6204
Protoss_Assimilator 1 3414
Protoss_Cybernetics_Core 1 4573
Protoss_Dragoon 10 10517
Protoss_Nexus 1 10219
Protoss_Citadel_of_Adun 1 9070
Protoss_Templar_Archives 1 10841
Protoss_Robotics_Facility 1 11386
11386
