Protoss_Gateway 2 8886
Protoss_Assimilator 1 3135
Protoss_Cybernetics_Core 1 4296
Protoss_Zealot 3 10343
Protoss_Dragoon 5 8893
Protoss_Robotics_Facility 1 7188
Protoss_Nexus 2 12815
Protoss_Observatory 1 7403
Protoss_Observer 1 8211
Protoss_Shuttle 1 9355
Protoss_Robotics_Support_Bay 1 9292
Protoss_Reaver 1 10829
12815
