Protoss_Gateway 2 11151
Protoss_Assimilator 1 3553
Protoss_Cybernetics_Core 1 4664
Protoss_Dragoon 4 9818
Protoss_Robotics_Facility 1 6578
Protoss_Shuttle 1 7391
Protoss_Robotics_Support_Bay 1 6903
Protoss_Zealot 3 10451
Protoss_Reaver 1 8666
Protoss_Observatory 1 8339
Protoss_Observer 2 10646
Protoss_Scarab 4 9311
11151
