Protoss_Gateway 4 11266
Protoss_Assimilator 1 3252
Protoss_Cybernetics_Core 1 4329
Protoss_Dragoon 10 10699
Protoss_Nexus 1 9685
Protoss_Robotics_Facility 1 9502
Protoss_Observatory 1 9600
Protoss_Observer 1 10369
11266
