Protoss_Gateway 4 10747
Protoss_Assimilator 1 3316
Protoss_Cybernetics_Core 1 4368
Protoss_Dragoon 9 10931
Protoss_Nexus 2 11827
Protoss_Robotics_Facility 1 8817
Protoss_Observatory 1 8928
Protoss_Observer 2 10359
11827
