Protoss_Gateway 2 7337
Protoss_Zealot 2 6143
Protoss_Nexus 1 6953
Protoss_Assimilator 2 8063
Protoss_Cybernetics_Core 1 6270
Protoss_Dragoon 6 10479
Protoss_Robotics_Facility 1 8419
Protoss_Shuttle 1 9233
Protoss_Robotics_Support_Bay 1 8660
Protoss_Reaver 1 10787
10787
