Protoss_Gateway 3 9574
Protoss_Assimilator 1 3393
Protoss_Cybernetics_Core 1 4620
Protoss_Dragoon 10 10621
Protoss_Nexus 1 10178
Protoss_Robotics_Facility 1 10160
Protoss_Zealot 1 10397
Protoss_Observatory 1 10432
10621
