Protoss_Gateway 3 10773
Protoss_Assimilator 2 9545
Protoss_Cybernetics_Core 1 4350
Protoss_Zealot 1 4181
Protoss_Dragoon 4 7701
Protoss_Nexus 2 10419
Protoss_Citadel_of_Adun 1 8341
Protoss_Templar_Archives 1 9327
Protoss_Dark_Templar 2 10527
10773
