Protoss_Gateway 4 10604
Protoss_Assimilator 2 3839
Protoss_Cybernetics_Core 1 4906
Protoss_Dragoon 4 10879
Protoss_Citadel_of_Adun 1 6686
Protoss_Templar_Archives 1 7901
Protoss_Zealot 1 7431
Protoss_Dark_Templar 4 9629
Protoss_Nexus 1 10992
Protoss_Robotics_Facility 1 11449
11449
