Protoss_Gateway 2 10048
Protoss_Assimilator 1 3208
Protoss_Cybernetics_Core 1 4321
Protoss_Robotics_Facility 1 5926
Protoss_Dragoon 8 10949
Protoss_Observatory 1 6170
Protoss_Observer 1 7181
Protoss_Nexus 1 10059
Protoss_Shuttle 1 9789
Protoss_Robotics_Support_Bay 1 9288
Protoss_Zealot 2 10663
Protoss_Reaver 1 10931
10949
