Protoss_Nexus 1 5880
Protoss_Gateway 2 5910
Protoss_Assimilator 1 4533
Protoss_Cybernetics_Core 1 5759
Protoss_Zealot 2 10775
Protoss_Dragoon 9 11063
Protoss_Robotics_Facility 1 10987
11063
