Protoss_Gateway 3 8685
Protoss_Zealot 6 6826
Protoss_Shield_Battery 1 4468
Protoss_Assimilator 1 5836
Protoss_Cybernetics_Core 1 7223
Protoss_Dragoon 9 10466
Protoss_Robotics_Facility 1 11634
11634
