Protoss_Gateway 2 5950
Protoss_Assimilator 1 3228
Protoss_Cybernetics_Core 1 4555
Protoss_Dragoon 10 10483
Protoss_Nexus 1 8607
Protoss_Zealot 2 7823
Protoss_Robotics_Facility 1 10265
Protoss_Shuttle 1 11179
Protoss_Robotics_Support_Bay 1 10556
11179
