Protoss_Gateway 1 3339
Protoss_Assimilator 2 10318
Protoss_Cybernetics_Core 1 4509
Protoss_Zealot 1 4219
Protoss_Dragoon 6 10757
Protoss_Nexus 1 9155
Protoss_Robotics_Facility 1 8945
Protoss_Shuttle 1 9747
Protoss_Robotics_Support_Bay 1 9242
Protoss_Reaver 1 10889
Protoss_Stargate 1 10972
Protoss_Observatory 1 10393
10972
