Protoss_Gateway 3 11081
Protoss_Assimilator 1 3356
Protoss_Cybernetics_Core 1 4306
Protoss_Dragoon 8 10634
Protoss_Robotics_Facility 1 7302
Protoss_Observatory 1 7418
Protoss_Nexus 2 11556
Protoss_Observer 3 10029
11556
