Protoss_Assimilator 3 8697
Protoss_Gateway 2 8191
Protoss_Zealot 3 5589
Protoss_Nexus 2 12665
Protoss_Forge 1 6065
Protoss_Photon_Cannon 1 6995
Protoss_Cybernetics_Core 1 7552
Protoss_Dragoon 5 10363
Protoss_Robotics_Facility 1 9407
Protoss_Shuttle 1 10217
Protoss_Robotics_Support_Bay 1 9617
Protoss_Reaver 1 11465
12665
