Protoss_Gateway 2 8716
Protoss_Zealot 2 5067
Protoss_Assimilator 1 4119
Protoss_Cybernetics_Core 1 5095
Protoss_Dragoon 9 10635
Protoss_Robotics_Facility 1 8398
Protoss_Observatory 1 8549
Protoss_Observer 2 9921
Protoss_Nexus 1 12547
Protoss_Shuttle 1 11411
12547
