Protoss_Gateway 2 9165
Protoss_Assimilator 1 3337
Protoss_Zealot 2 4533
Protoss_Cybernetics_Core 1 5547
Protoss_Dragoon 8 10693
Protoss_Nexus 1 9311
Protoss_Robotics_Facility 1 9031
Protoss_Observatory 1 9234
Protoss_Observer 2 10679
10693
