Protoss_Nexus 1 5637
Protoss_Gateway 2 5649
Protoss_Assimilator 2 8202
Protoss_Cybernetics_Core 1 5455
Protoss_Zealot 1 5623
Protoss_Dragoon 10 10319
Protoss_Robotics_Facility 1 9138
Protoss_Observatory 1 9233
Protoss_Citadel_of_Adun 1 9961
Protoss_Observer 2 10631
Protoss_Templar_Archives 1 10947
10947
