Protoss_Gateway 2 8792
Protoss_Assimilator 1 3298
Protoss_Cybernetics_Core 1 4435
Protoss_Dragoon 9 10281
Protoss_Nexus 1 8867
Protoss_Robotics_Facility 1 8481
Protoss_Robotics_Support_Bay 1 8687
Protoss_Shuttle 1 9539
Protoss_Reaver 1 11157
11157
