Protoss_Gateway 2 2303
Protoss_Zealot 8 6591
Protoss_Forge 1 4062
Protoss_Photon_Cannon 3 7814
Protoss_Assimilator 1 6018
Protoss_Cybernetics_Core 1 7038
Protoss_Dragoon 1 8136
8136
