Protoss_Gateway 2 10817
Protoss_Assimilator 1 3164
Protoss_Cybernetics_Core 1 4424
Protoss_Dragoon 7 11143
Protoss_Robotics_Facility 1 6323
Protoss_Observatory 1 6433
Protoss_Observer 2 7821
Protoss_Nexus 1 10345
Protoss_Shuttle 1 9345
Protoss_Robotics_Support_Bay 1 8952
Protoss_Reaver 1 10531
11143
