Protoss_Gateway 2 8228
Protoss_Assimilator 1 3358
Protoss_Cybernetics_Core 1 4419
Protoss_Dragoon 8 11036
Protoss_Robotics_Facility 1 7548
Protoss_Observatory 1 7750
Protoss_Nexus 1 10767
Protoss_Observer 3 10090
Protoss_Shuttle 1 11186
11186
