Protoss_Gateway 5 10943
Protoss_Assimilator 1 3175
Protoss_Cybernetics_Core 1 4364
Protoss_Zealot 1 4301
Protoss_Dragoon 7 10945
Protoss_Nexus 2 11032
Protoss_Robotics_Facility 1 8661
Protoss_Observatory 1 8949
Protoss_Observer 2 10397
Protoss_Citadel_of_Adun 1 11096
11096
