Protoss_Gateway 1 3283
Protoss_Assimilator 2 9035
Protoss_Cybernetics_Core 1 4429
Protoss_Dragoon 8 10558
Protoss_Nexus 1 9042
Protoss_Robotics_Facility 1 8911
Protoss_Shuttle 1 9709
Protoss_Robotics_Support_Bay 1 9413
Protoss_Reaver 1 10901
Protoss_Stargate 2 11540
Protoss_Observatory 2 10709
11540
