Protoss_Nexus 1 5579
Protoss_Gateway 4 10130
Protoss_Assimilator 2 8291
Protoss_Cybernetics_Core 1 5550
Protoss_Zealot 1 5741
Protoss_Dragoon 10 10439
Protoss_Robotics_Facility 1 9485
Protoss_Shuttle 1 10281
Protoss_Robotics_Support_Bay 1 9724
Protoss_Reaver 1 11563
11563
