Protoss_Gateway 2 9286
Protoss_Assimilator 1 2370
Protoss_Cybernetics_Core 1 3014
Protoss_Dragoon 7 9668
Protoss_Robotics_Facility 1 4463
Protoss_Shuttle 1 5786
Protoss_Robotics_Support_Bay 1 5933
Protoss_Reaver 2 7938
Protoss_Observatory 1 8087
Protoss_Scarab 4 9938
Protoss_Observer 1 8990
9938
