Protoss_Nexus 2 12336
Protoss_Gateway 3 8697
Protoss_Assimilator 1 4253
Protoss_Cybernetics_Core 1 5501
Protoss_Zealot 6 10885
Protoss_Dragoon 11 11115
Protoss_Robotics_Facility 1 8407
Protoss_Observatory 1 8566
Protoss_Shuttle 1 9547
Protoss_Robotics_Support_Bay 1 9143
Protoss_Observer 1 10293
12336
