Protoss_Gateway 2 6939
Protoss_Assimilator 1 3363
Protoss_Zealot 3 5305
Protoss_Cybernetics_Core 1 5334
Protoss_Dragoon 8 10855
Protoss_Nexus 2 12182
Protoss_Robotics_Facility 1 9575
Protoss_Observatory 1 9663
Protoss_Observer 1 10431
12182
