Protoss_Assimilator 2 3737
Protoss_Gateway 4 10891
Protoss_Cybernetics_Core 1 4913
Protoss_Dragoon 9 11141
Protoss_Nexus 2 10498
Protoss_Robotics_Facility 1 10219
Protoss_Observatory 1 10485
11141
