Protoss_Gateway 3 9439
Protoss_Assimilator 2 10320
Protoss_Cybernetics_Core 1 4305
Protoss_Dragoon 7 10283
Protoss_Citadel_of_Adun 1 6473
Protoss_Templar_Archives 1 7566
Protoss_Nexus 2 12707
Protoss_Dark_Templar 1 8363
Protoss_Robotics_Facility 1 9545
Protoss_Observatory 1 9730
Protoss_Observer 1 10521
12707
