Protoss_Gateway 2 9161
Protoss_Assimilator 1 3447
Protoss_Cybernetics_Core 1 4653
Protoss_Dragoon 5 11190
Protoss_Robotics_Facility 1 6797
Protoss_Zealot 2 8166
Protoss_Shuttle 1 7641
Protoss_Robotics_Support_Bay 1 6957
Protoss_Reaver 1 8783
Protoss_Observatory 1 8016
Protoss_Observer 2 10728
11190
