Protoss_Assimilator 1 2687
Protoss_Gateway 4 10543
Protoss_Cybernetics_Core 1 4757
Protoss_Robotics_Facility 1 6239
Protoss_Dragoon 8 10973
Protoss_Shuttle 2 8855
Protoss_Observatory 1 8317
Protoss_Observer 2 9879
Protoss_Nexus 1 12472
12472
