Protoss_Gateway 1 3327
Protoss_Assimilator 1 3160
Protoss_Cybernetics_Core 1 4392
Protoss_Zealot 2 7249
Protoss_Robotics_Facility 1 5910
Protoss_Dragoon 5 8883
Protoss_Shuttle 1 6719
Protoss_Robotics_Support_Bay 1 6413
Protoss_Reaver 1 7909
Protoss_Observatory 1 7376
Protoss_Observer 3 9609
Protoss_Scarab 6 9983
Protoss_Nexus 2 12151
12151
