Protoss_Nexus 3 12817
Protoss_Gateway 2 5759
Protoss_Assimilator 1 4190
Protoss_Cybernetics_Core 1 5353
Protoss_Zealot 1 5545
Protoss_Dragoon 12 10997
Protoss_Robotics_Facility 1 8720
Protoss_Observatory 1 8970
Protoss_Observer 2 10929
12817
