Protoss_Gateway 2 8635
Protoss_Assimilator 2 8987
Protoss_Cybernetics_Core 1 4674
Protoss_Dragoon 7 10667
Protoss_Nexus 1 8781
Protoss_Citadel_of_Adun 1 7888
Protoss_Templar_Archives 1 8993
Protoss_Dark_Templar 4 10833
Protoss_Robotics_Facility 1 10962
10962
