Protoss_Gateway 3 11362
Protoss_Assimilator 1 3398
Protoss_Cybernetics_Core 1 4618
Protoss_Zealot 1 4396
Protoss_Robotics_Facility 1 6453
Protoss_Dragoon 7 11145
Protoss_Observatory 1 6696
Protoss_Observer 3 9561
Protoss_Nexus 1 11113
11362
