Protoss_Gateway 2 7032
Protoss_Assimilator 1 3412
Protoss_Cybernetics_Core 1 4413
Protoss_Dragoon 7 11181
Protoss_Robotics_Facility 1 6493
Protoss_Zealot 3 10501
Protoss_Shuttle 2 8801
Protoss_Observatory 1 7283
Protoss_Robotics_Support_Bay 1 7695
Protoss_Reaver 1 10191
Protoss_Observer 1 10911
11181
