Protoss_Gateway 2 7658
Protoss_Assimilator 1 3405
Protoss_Zealot 3 9707
Protoss_Cybernetics_Core 1 5181
Protoss_Dragoon 9 10549
Protoss_Robotics_Facility 1 7801
Protoss_Observatory 1 7932
Protoss_Observer 1 8743
Protoss_Shuttle 1 10143
Protoss_Nexus 1 12735
12735
