Protoss_Gateway 1 3427
Protoss_Assimilator 2 9273
Protoss_Cybernetics_Core 1 4417
Protoss_Dragoon 8 11151
Protoss_Nexus 1 9525
Protoss_Stargate 2 10741
Protoss_Fleet_Beacon 1 9449
Protoss_Carrier 1 12379
12379
