Protoss_Gateway 3 9472
Protoss_Assimilator 1 3413
Protoss_Cybernetics_Core 1 4436
Protoss_Dragoon 11 11161
Protoss_Robotics_Facility 1 7337
Protoss_Nexus 1 9458
Protoss_Observatory 1 7482
Protoss_Observer 3 9573
11161
