Protoss_Gateway 4 10868
Protoss_Assimilator 1 3492
Protoss_Cybernetics_Core 1 4576
Protoss_Dragoon 4 8316
Protoss_Robotics_Facility 1 6555
Protoss_Observatory 1 6728
Protoss_Observer 2 8686
Protoss_Nexus 1 11144
Protoss_Citadel_of_Adun 1 9939
Protoss_Shuttle 1 10561
Protoss_Templar_Archives 1 11033
11144
