Protoss_Gateway 1 1893
Protoss_Assimilator 1 2214
Protoss_Cybernetics_Core 1 2898
Protoss_Zealot 1 3151
Protoss_Robotics_Facility 1 4089
Protoss_Dragoon 5 9887
Protoss_Shuttle 1 5369
Protoss_Robotics_Support_Bay 1 5592
Protoss_Reaver 2 7857
Protoss_Observatory 1 6697
Protoss_Scarab 3 9986
Protoss_Nexus 1 8389
Protoss_Observer 2 9785
9986
