Protoss_Gateway 2 4273
Protoss_Assimilator 3 9346
Protoss_Zealot 12 10465
Protoss_Nexus 1 8234
Protoss_Forge 1 6587
Protoss_Photon_Cannon 2 7681
Protoss_Cybernetics_Core 1 8867
Protoss_Citadel_of_Adun 1 9881
Protoss_Robotics_Facility 1 10933
Protoss_Templar_Archives 1 11175
11175
