Protoss_Gateway 3 8099
Protoss_Assimilator 1 3515
Protoss_Cybernetics_Core 1 4647
Protoss_Dragoon 7 9217
Protoss_Robotics_Facility 1 6901
Protoss_Observatory 1 7007
Protoss_Observer 4 10477
Protoss_Nexus 2 12645
12645
