Protoss_Gateway 2 8723
Protoss_Assimilator 1 3352
Protoss_Cybernetics_Core 1 4557
Protoss_Robotics_Facility 1 6068
Protoss_Dragoon 9 11153
Protoss_Shuttle 1 7071
Protoss_Observatory 1 6718
Protoss_Observer 2 8563
Protoss_Nexus 1 11400
11400
