Protoss_Gateway 2 7435
Protoss_Zealot 4 10575
Protoss_Assimilator 1 4149
Protoss_Cybernetics_Core 1 5111
Protoss_Dragoon 5 9149
Protoss_Nexus 1 10145
Protoss_Robotics_Facility 1 9580
Protoss_Shuttle 1 10401
Protoss_Robotics_Support_Bay 1 10117
Protoss_Observatory 1 10243
Protoss_Reaver 1 11645
11645
