Protoss_Gateway 2 5207
Protoss_Assimilator 1 3483
Protoss_Cybernetics_Core 1 4819
Protoss_Dragoon 8 10621
Protoss_Robotics_Facility 1 7803
Protoss_Observatory 1 7974
Protoss_Nexus 2 12645
Protoss_Observer 3 10351
Protoss_Zealot 1 10281
12645
