Protoss_Gateway 2 7967
Protoss_Assimilator 1 3765
Protoss_Cybernetics_Core 1 4853
Protoss_Dragoon 9 11056
Protoss_Robotics_Facility 1 7773
Protoss_Observatory 1 7916
Protoss_Observer 1 9061
Protoss_Nexus 2 12308
12308
