Protoss_Gateway 4 11215
Protoss_Assimilator 1 3135
Protoss_Cybernetics_Core 1 4324
Protoss_Dragoon 9 10457
Protoss_Nexus 2 10825
Protoss_Robotics_Facility 1 9277
Protoss_Observatory 1 9403
Protoss_Observer 1 10199
11215
