Protoss_Gateway 2 6768
Protoss_Assimilator 1 3243
Protoss_Cybernetics_Core 1 4378
Protoss_Dragoon 6 8870
Protoss_Robotics_Facility 1 7989
Protoss_Zealot 4 10626
Protoss_Shuttle 1 9591
Protoss_Robotics_Support_Bay 1 9173
Protoss_Observatory 1 9238
Protoss_Citadel_of_Adun 1 10244
Protoss_Reaver 1 10733
10733
