Protoss_Gateway 3 11244
Protoss_Assimilator 1 3485
Protoss_Cybernetics_Core 1 4518
Protoss_Dragoon 9 10816
Protoss_Robotics_Facility 1 6633
Protoss_Observatory 1 7152
Protoss_Observer 2 8681
Protoss_Nexus 1 11855
11855
