Protoss_Gateway 2 7976
Protoss_Assimilator 1 3488
Protoss_Zealot 1 3981
Protoss_Cybernetics_Core 1 5005
Protoss_Dragoon 10 10494
Protoss_Robotics_Facility 1 6649
Protoss_Observatory 1 6793
Protoss_Observer 2 8301
Protoss_Citadel_of_Adun 1 10678
Protoss_Nexus 1 12278
12278
