Protoss_Gateway 3 9458
Protoss_Assimilator 1 3337
Protoss_Cybernetics_Core 1 4457
Protoss_Dragoon 8 9491
Protoss_Robotics_Facility 1 7285
Protoss_Observatory 1 7625
Protoss_Observer 1 8585
Protoss_Citadel_of_Adun 1 9279
Protoss_Zealot 4 10215
Protoss_Shuttle 1 11147
11147
