Protoss_Gateway 2 7384
Protoss_Assimilator 1 3326
Protoss_Cybernetics_Core 1 4434
Protoss_Dragoon 11 10743
Protoss_Robotics_Facility 1 7575
Protoss_Observatory 1 7707
Protoss_Observer 2 9335
Protoss_Nexus 1 11008
Protoss_Shuttle 1 10417
Protoss_Robotics_Support_Bay 1 10429
Protoss_Zealot 1 10833
11008
