Protoss_Gateway 2 8015
Protoss_Assimilator 2 9618
Protoss_Cybernetics_Core 1 5145
Protoss_Dragoon 3 7949
Protoss_Citadel_of_Adun 1 6925
Protoss_Templar_Archives 1 7915
Protoss_Dark_Templar 4 10895
Protoss_Nexus 1 10974
Protoss_Stargate 1 11155
11155
