Protoss_Gateway 2 8059
Protoss_Assimilator 1 3610
Protoss_Cybernetics_Core 1 4474
Protoss_Dragoon 9 10921
Protoss_Robotics_Facility 1 7908
Protoss_Observatory 1 8003
Protoss_Zealot 1 8606
Protoss_Observer 2 9388
Protoss_Nexus 1 12864
12864
