Protoss_Gateway 2 6334
Protoss_Assimilator 1 3453
Protoss_Cybernetics_Core 1 4559
Protoss_Robotics_Facility 1 6215
Protoss_Shuttle 1 7136
Protoss_Dragoon 6 9273
Protoss_Observatory 1 7165
Protoss_Observer 2 8766
Protoss_Forge 1 8198
Protoss_Photon_Cannon 1 9443
Protoss_Nexus 1 12492
12492
