Protoss_Gateway 3 9894
Protoss_Assimilator 1 3328
Protoss_Zealot 1 3927
Protoss_Cybernetics_Core 1 5093
Protoss_Dragoon 9 11115
Protoss_Robotics_Facility 1 7874
Protoss_Nexus 1 9731
Protoss_Observatory 1 8724
Protoss_Observer 2 10159
11115
