Protoss_Gateway 2 9637
Protoss_Assimilator 1 3382
Protoss_Cybernetics_Core 1 4553
Protoss_Zealot 1 4279
Protoss_Dragoon 9 11139
Protoss_Robotics_Facility 1 8162
Protoss_Observatory 1 8513
Protoss_Nexus 1 10757
Protoss_Observer 2 9909
11139
