Protoss_Gateway 2 7507
Protoss_Assimilator 1 3428
Protoss_Cybernetics_Core 1 4838
Protoss_Dragoon 8 10076
Protoss_Robotics_Facility 1 7606
Protoss_Observatory 1 8088
Protoss_Observer 2 9463
Protoss_Shuttle 1 10545
Protoss_Zealot 2 10596
10596
