Protoss_Gateway 3 11401
Protoss_Assimilator 1 3420
Protoss_Zealot 2 4467
Protoss_Cybernetics_Core 1 4695
Protoss_Dragoon 8 11053
Protoss_Nexus 1 9635
Protoss_Citadel_of_Adun 1 10754
11401
