Protoss_Gateway 4 10506
Protoss_Assimilator 3 3913
Protoss_Cybernetics_Core 1 4765
Protoss_Dragoon 9 10836
Protoss_Nexus 1 9289
Protoss_Robotics_Facility 1 9258
Protoss_Observatory 1 9420
Protoss_Observer 2 10798
10836
