Protoss_Gateway 2 10629
Protoss_Zealot 3 5257
Protoss_Assimilator 1 4467
Protoss_Cybernetics_Core 1 5618
Protoss_Dragoon 6 10893
Protoss_Nexus 1 9149
Protoss_Robotics_Facility 1 8831
Protoss_Shuttle 1 9661
Protoss_Robotics_Support_Bay 1 9375
Protoss_Reaver 1 10891
10893
