Protoss_Gateway 1 3507
Protoss_Assimilator 1 3568
Protoss_Cybernetics_Core 1 4629
Protoss_Dragoon 6 11067
Protoss_Robotics_Facility 1 6808
Protoss_Zealot 2 7381
Protoss_Shuttle 1 7651
Protoss_Robotics_Support_Bay 1 7071
Protoss_Reaver 2 10241
Protoss_Scarab 9 9520
Protoss_Observatory 1 10399
11067
