Protoss_Gateway 2 6807
Protoss_Assimilator 1 3346
Protoss_Cybernetics_Core 1 4337
Protoss_Dragoon 9 9697
Protoss_Nexus 2 12862
Protoss_Robotics_Facility 1 9036
Protoss_Shuttle 1 9877
Protoss_Robotics_Support_Bay 1 9646
Protoss_Reaver 1 11167
Protoss_Observatory 1 10365
12862
