Protoss_Gateway 1 3251
Protoss_Assimilator 1 3143
Protoss_Cybernetics_Core 1 4247
Protoss_Zealot 1 4039
Protoss_Dragoon 7 10945
Protoss_Forge 1 5573
Protoss_Photon_Cannon 2 6805
Protoss_Stargate 2 8727
Protoss_Scout 4 11471
11471
