Protoss_Gateway 2 9041
Protoss_Assimilator 1 3289
Protoss_Cybernetics_Core 1 4389
Protoss_Dragoon 9 10865
Protoss_Nexus 2 10105
Protoss_Robotics_Facility 1 10416
Protoss_Shuttle 1 11231
Protoss_Robotics_Support_Bay 1 10521
11231
