Protoss_Gateway 4 10991
Protoss_Assimilator 1 3252
Protoss_Cybernetics_Core 1 4536
Protoss_Dragoon 11 11086
Protoss_Robotics_Facility 1 6999
Protoss_Observatory 1 7249
Protoss_Observer 3 9435
Protoss_Nexus 1 11568
11568
