Protoss_Gateway 2 7028
Protoss_Assimilator 1 3528
Protoss_Cybernetics_Core 1 4754
Protoss_Dragoon 8 10156
Protoss_Robotics_Facility 1 8241
Protoss_Observatory 1 8388
Protoss_Nexus 1 11035
Protoss_Observer 2 9788
Protoss_Robotics_Support_Bay 1 10078
Protoss_Zealot 2 10901
11035
