Protoss_Gateway 2 7827
Protoss_Assimilator 1 3354
Protoss_Cybernetics_Core 1 4629
Protoss_Zealot 1 4493
Protoss_Dragoon 6 8593
Protoss_Citadel_of_Adun 1 7261
Protoss_Templar_Archives 1 8347
Protoss_Dark_Templar 4 10939
Protoss_Nexus 1 11852
Protoss_Robotics_Facility 1 11183
11852
