Protoss_Gateway 4 10698
Protoss_Assimilator 1 3448
Protoss_Cybernetics_Core 1 4373
Protoss_Dragoon 11 11026
Protoss_Zealot 2 7266
Protoss_Nexus 1 9743
Protoss_Robotics_Facility 1 9538
Protoss_Observatory 1 9897
11026
