Protoss_Gateway 2 7401
Protoss_Assimilator 2 9653
Protoss_Cybernetics_Core 1 4613
Protoss_Dragoon 9 11051
Protoss_Robotics_Facility 1 7221
Protoss_Nexus 2 11081
Protoss_Observatory 1 7395
Protoss_Observer 5 10893
Protoss_Citadel_of_Adun 1 10666
11081
