Protoss_Gateway 3 9239
Protoss_Assimilator 1 3201
Protoss_Cybernetics_Core 1 4393
Protoss_Dragoon 11 11181
Protoss_Nexus 2 12379
Protoss_Robotics_Facility 1 8751
Protoss_Observatory 1 9091
Protoss_Observer 2 10517
12379
