Protoss_Gateway 3 11173
Protoss_Assimilator 2 10319
Protoss_Cybernetics_Core 1 4333
Protoss_Dragoon 7 9509
Protoss_Nexus 2 12111
Protoss_Robotics_Facility 1 8760
Protoss_Observatory 1 9479
Protoss_Observer 1 10401
12111
