Protoss_Gateway 5 11059
Protoss_Assimilator 3 9473
Protoss_Zealot 7 7605
Protoss_Nexus 1 8145
Protoss_Cybernetics_Core 1 7715
Protoss_Forge 1 8041
Protoss_Photon_Cannon 2 9237
Protoss_Citadel_of_Adun 1 9387
Protoss_Templar_Archives 1 10395
Protoss_Dark_Templar 1 11197
11197
