Protoss_Gateway 2 8627
Protoss_Assimilator 2 10202
Protoss_Cybernetics_Core 1 4428
Protoss_Dragoon 11 10945
Protoss_Nexus 1 9028
Protoss_Robotics_Facility 1 8819
Protoss_Observatory 1 8927
Protoss_Observer 3 10905
10945
