Protoss_Gateway 4 10888
Protoss_Assimilator 1 3326
Protoss_Cybernetics_Core 1 4487
Protoss_Dragoon 10 11055
Protoss_Nexus 1 8124
Protoss_Robotics_Facility 1 8605
Protoss_Observatory 1 9426
Protoss_Observer 1 10369
11055
