Protoss_Gateway 5 11378
Protoss_Assimilator 1 3438
Protoss_Cybernetics_Core 1 4513
Protoss_Dragoon 6 10831
Protoss_Nexus 2 12098
Protoss_Robotics_Facility 1 9158
Protoss_Observatory 1 9638
Protoss_Observer 1 10516
12098
