Protoss_Gateway 3 8953
Protoss_Assimilator 2 9265
Protoss_Cybernetics_Core 1 4395
Protoss_Dragoon 6 9935
Protoss_Robotics_Facility 1 6334
Protoss_Observatory 3 7169
Protoss_Nexus 1 9602
Protoss_Observer 3 10189
Protoss_Citadel_of_Adun 1 9885
Protoss_Zealot 2 9957
Protoss_Templar_Archives 1 11060
11060
