Protoss_Gateway 2 7848
Protoss_Assimilator 1 3413
Protoss_Cybernetics_Core 1 4548
Protoss_Dragoon 7 11016
Protoss_Robotics_Facility 1 8138
Protoss_Observatory 1 8278
Protoss_Shuttle 1 9261
Protoss_Zealot 2 9176
11016
