Protoss_Gateway 2 9477
Protoss_Assimilator 2 2699
Protoss_Cybernetics_Core 1 3269
Protoss_Dragoon 7 9379
Protoss_Robotics_Facility 1 5428
Protoss_Shuttle 1 6773
Protoss_Robotics_Support_Bay 1 7064
Protoss_Reaver 1 7675
Protoss_Observatory 1 8557
Protoss_Nexus 1 9033
Protoss_Scarab 3 9995
9995
