Protoss_Gateway 1 3223
Protoss_Assimilator 1 3109
Protoss_Cybernetics_Core 1 4241
Protoss_Zealot 1 4067
Protoss_Dragoon 7 10329
Protoss_Nexus 2 10869
Protoss_Robotics_Facility 1 8855
Protoss_Shuttle 1 9803
Protoss_Robotics_Support_Bay 1 9473
Protoss_Reaver 1 11067
Protoss_Observatory 1 10255
11067
