Protoss_Gateway 2 6705
Protoss_Assimilator 1 3366
Protoss_Cybernetics_Core 1 4655
Protoss_Dragoon 9 10205
Protoss_Robotics_Facility 1 6728
Protoss_Observatory 1 6823
Protoss_Observer 2 8203
Protoss_Shuttle 1 10791
Protoss_Zealot 2 10717
10791
