Protoss_Gateway 3 8527
Protoss_Assimilator 1 3630
Protoss_Cybernetics_Core 1 4739
Protoss_Dragoon 8 10701
Protoss_Robotics_Facility 1 7762
Protoss_Observatory 1 8002
Protoss_Shuttle 1 8891
Protoss_Observer 1 9313
Protoss_Robotics_Support_Bay 1 9108
Protoss_Zealot 1 10765
10765
