Protoss_Gateway 2 8971
Protoss_Assimilator 1 2413
Protoss_Cybernetics_Core 1 3085
Protoss_Dragoon 4 9663
Protoss_Robotics_Facility 1 4717
Protoss_Shuttle 1 5995
Protoss_Robotics_Support_Bay 1 6071
Protoss_Zealot 2 7019
Protoss_Reaver 1 6897
Protoss_Observatory 1 7246
Protoss_Observer 2 8551
Protoss_Nexus 1 8416
Protoss_Scarab 8 9982
9982
