Protoss_Gateway 3 10921
Protoss_Assimilator 1 3355
Protoss_Cybernetics_Core 1 4364
Protoss_Dragoon 8 10678
Protoss_Nexus 2 10353
Protoss_Robotics_Facility 1 10238
Protoss_Shuttle 1 11131
11131
