Protoss_Gateway 2 7546
Protoss_Assimilator 1 3487
Protoss_Cybernetics_Core 1 4533
Protoss_Dragoon 9 11101
Protoss_Citadel_of_Adun 1 6568
Protoss_Templar_Archives 1 7693
Protoss_Zealot 1 7741
Protoss_Dark_Templar 2 8583
Protoss_Nexus 1 11498
Protoss_Robotics_Facility 1 11368
11498
