Protoss_Gateway 1 3645
Protoss_Assimilator 1 3478
Protoss_Cybernetics_Core 1 4653
Protoss_Dragoon 5 10421
Protoss_Robotics_Facility 1 7602
Protoss_Shuttle 1 8521
Protoss_Robotics_Support_Bay 1 8152
Protoss_Reaver 1 9736
Protoss_Zealot 1 9146
Protoss_Observatory 1 9518
Protoss_Observer 2 10913
10913
