Protoss_Gateway 2 8384
Protoss_Assimilator 3 8005
Protoss_Zealot 4 6745
Protoss_Nexus 2 12038
Protoss_Forge 1 5848
Protoss_Photon_Cannon 1 6875
Protoss_Cybernetics_Core 1 7921
Protoss_Dragoon 5 10639
Protoss_Robotics_Facility 1 10424
Protoss_Observatory 1 10655
12038
