Protoss_Gateway 2 8711
Protoss_Assimilator 2 10230
Protoss_Cybernetics_Core 1 4521
Protoss_Dragoon 9 10973
Protoss_Nexus 2 12019
Protoss_Robotics_Facility 1 8361
Protoss_Observatory 1 8633
Protoss_Shuttle 1 9777
Protoss_Observer 3 10645
12019
