Protoss_Gateway 3 11115
Protoss_Assimilator 1 3465
Protoss_Cybernetics_Core 1 4409
Protoss_Dragoon 6 10779
Protoss_Citadel_of_Adun 1 6625
Protoss_Templar_Archives 1 7645
Protoss_Nexus 2 11366
Protoss_Dark_Templar 3 10279
11366
