Protoss_Gateway 5 11163
Protoss_Assimilator 1 3202
Protoss_Cybernetics_Core 1 4345
Protoss_Dragoon 6 11109
Protoss_Nexus 2 10374
Protoss_Robotics_Facility 1 8373
Protoss_Shuttle 1 9453
Protoss_Zealot 1 9371
Protoss_Robotics_Support_Bay 1 9281
Protoss_Reaver 1 10881
Protoss_Observatory 1 10585
11163
