Protoss_Gateway 2 7894
Protoss_Assimilator 2 10624
Protoss_Cybernetics_Core 1 4457
Protoss_Dragoon 6 10727
Protoss_Robotics_Facility 1 8152
Protoss_Nexus 2 11151
Protoss_Observatory 1 8500
Protoss_Observer 3 10623
Protoss_Citadel_of_Adun 1 10241
Protoss_Templar_Archives 1 11415
11415
