Protoss_Assimilator 3 10797
Protoss_Gateway 2 10752
Protoss_Cybernetics_Core 1 4862
Protoss_Dragoon 6 10281
Protoss_Nexus 1 9106
Protoss_Robotics_Facility 1 8721
Protoss_Shuttle 1 9685
Protoss_Robotics_Support_Bay 1 9683
Protoss_Reaver 1 11281
Protoss_Zealot 1 10793
11281
