Protoss_Gateway 2 8026
Protoss_Assimilator 2 10187
Protoss_Zealot 2 7805
Protoss_Cybernetics_Core 1 4615
Protoss_Citadel_of_Adun 2 6830
Protoss_Dragoon 4 10171
Protoss_Robotics_Facility 1 6790
Protoss_Templar_Archives 1 7829
Protoss_Nexus 1 10155
Protoss_Shuttle 1 8993
Protoss_Dark_Templar 2 9127
Protoss_Observatory 1 8768
Protoss_Observer 1 10437
10437
