Protoss_Gateway 2 9713
Protoss_Assimilator 1 3247
Protoss_Cybernetics_Core 1 4454
Protoss_Dragoon 8 10597
Protoss_Robotics_Facility 1 7347
Protoss_Nexus 2 11327
Protoss_Observatory 1 7513
Protoss_Observer 2 8901
Protoss_Shuttle 1 10227
Protoss_Robotics_Support_Bay 1 9875
Protoss_Reaver 1 11381
Protoss_Zealot 1 10799
11381
