Protoss_Gateway 2 3949
Protoss_Zealot 5 5471
Protoss_Assimilator 1 4788
Protoss_Cybernetics_Core 1 5633
Protoss_Dragoon 12 11141
Protoss_Nexus 1 11728
Protoss_Robotics_Facility 1 11609
11728
