Protoss_Gateway 1 1830
Protoss_Assimilator 1 2313
Protoss_Cybernetics_Core 1 2829
Protoss_Dragoon 4 8375
Protoss_Robotics_Facility 2 7629
Protoss_Shuttle 2 8241
Protoss_Robotics_Support_Bay 1 6201
Protoss_Zealot 2 7659
Protoss_Reaver 3 9585
Protoss_Scarab 2 9936
9936
