Protoss_Gateway 3 10130
Protoss_Forge 1 3527
Protoss_Assimilator 1 3709
Protoss_Cybernetics_Core 1 4598
Protoss_Dragoon 13 11146
Protoss_Zealot 1 6056
Protoss_Robotics_Facility 1 9023
Protoss_Observatory 1 9298
Protoss_Observer 1 10211
Protoss_Nexus 1 12317
12317
