Protoss_Gateway 3 8561
Protoss_Assimilator 1 3173
Protoss_Cybernetics_Core 1 4405
Protoss_Dragoon 9 10481
Protoss_Citadel_of_Adun 1 7161
Protoss_Robotics_Facility 1 7953
Protoss_Observatory 1 8055
Protoss_Observer 3 10139
Protoss_Nexus 1 12423
12423
