Protoss_Gateway 3 9073
Protoss_Assimilator 2 10939
Protoss_Cybernetics_Core 1 4549
Protoss_Dragoon 10 10819
Protoss_Nexus 1 8651
Protoss_Robotics_Facility 1 8587
Protoss_Observatory 1 8944
Protoss_Observer 3 10923
10939
