Protoss_Gateway 2 6811
Protoss_Assimilator 1 3351
Protoss_Cybernetics_Core 1 4451
Protoss_Zealot 3 9142
Protoss_Dragoon 9 10977
Protoss_Robotics_Facility 1 8767
Protoss_Observatory 1 8925
Protoss_Shuttle 1 9861
Protoss_Nexus 1 12239
Protoss_Observer 1 10351
12239
