Protoss_Gateway 2 7998
Protoss_Assimilator 1 3438
Protoss_Cybernetics_Core 1 4403
Protoss_Zealot 2 10511
Protoss_Dragoon 8 10676
Protoss_Robotics_Facility 1 7788
Protoss_Observatory 1 8008
Protoss_Observer 2 9471
Protoss_Nexus 1 12123
12123
