Protoss_Gateway 4 9753
Protoss_Assimilator 1 3275
Protoss_Cybernetics_Core 1 4337
Protoss_Dragoon 11 10429
Protoss_Nexus 2 12703
Protoss_Robotics_Facility 1 9264
Protoss_Zealot 1 9431
Protoss_Observatory 1 9404
Protoss_Observer 2 10891
12703
