Protoss_Gateway 2 9158
Protoss_Assimilator 1 3418
Protoss_Cybernetics_Core 1 4575
Protoss_Zealot 1 4357
Protoss_Robotics_Facility 1 6335
Protoss_Dragoon 9 11147
Protoss_Nexus 1 9646
Protoss_Observatory 1 7697
Protoss_Observer 2 9067
Protoss_Shuttle 1 10149
Protoss_Robotics_Support_Bay 1 9430
11147
