Protoss_Gateway 4 11399
Protoss_Assimilator 1 3303
Protoss_Cybernetics_Core 1 4395
Protoss_Dragoon 8 10641
Protoss_Robotics_Facility 1 7210
Protoss_Observatory 1 7370
Protoss_Observer 2 8813
Protoss_Nexus 1 10667
Protoss_Shuttle 1 9649
Protoss_Robotics_Support_Bay 1 9287
Protoss_Reaver 1 10791
Protoss_Zealot 2 10845
11399
