Protoss_Gateway 3 9270
Protoss_Assimilator 2 10379
Protoss_Cybernetics_Core 1 4366
Protoss_Dragoon 7 9281
Protoss_Nexus 1 9671
Protoss_Robotics_Facility 1 9290
Protoss_Shuttle 1 10181
Protoss_Robotics_Support_Bay 1 9922
Protoss_Observatory 1 9952
Protoss_Observer 1 10803
10803
