Protoss_Gateway 3 10901
Protoss_Assimilator 1 3533
Protoss_Cybernetics_Core 1 4584
Protoss_Dragoon 10 10931
Protoss_Robotics_Facility 1 6712
Protoss_Observatory 1 7106
Protoss_Observer 3 9308
Protoss_Nexus 1 11503
11503
