Protoss_Gateway 2 6551
Protoss_Assimilator 1 3329
Protoss_Cybernetics_Core 1 4451
Protoss_Dragoon 12 10009
Protoss_Robotics_Facility 1 8179
Protoss_Observatory 1 8287
Protoss_Observer 2 9815
Protoss_Nexus 1 12565
12565
