Protoss_Gateway 2 8026
Protoss_Assimilator 1 3632
Protoss_Cybernetics_Core 1 4704
Protoss_Dragoon 10 10846
Protoss_Robotics_Facility 1 8058
Protoss_Observatory 1 8251
Protoss_Observer 2 10351
Protoss_Nexus 1 11878
11878
