Protoss_Gateway 3 8822
Protoss_Assimilator 2 9911
Protoss_Cybernetics_Core 1 4246
Protoss_Dragoon 9 9815
Protoss_Nexus 1 8493
Protoss_Robotics_Facility 1 8435
Protoss_Observatory 1 8680
Protoss_Observer 1 10095
10095
