Protoss_Gateway 3 7705
Protoss_Zealot 4 10313
Protoss_Nexus 1 7353
Protoss_Assimilator 1 5655
Protoss_Cybernetics_Core 1 6501
Protoss_Dragoon 7 10449
Protoss_Robotics_Facility 1 10559
Protoss_Observatory 1 10684
10684
