Protoss_Gateway 2 7536
Protoss_Assimilator 1 3385
Protoss_Cybernetics_Core 1 4494
Protoss_Dragoon 7 9309
Protoss_Robotics_Facility 1 7468
Protoss_Observatory 1 7627
Protoss_Observer 3 10219
Protoss_Nexus 2 12006
Protoss_Citadel_of_Adun 1 11116
12006
