Protoss_Gateway 3 10232
Protoss_Assimilator 1 3446
Protoss_Cybernetics_Core 1 4427
Protoss_Dragoon 8 11117
Protoss_Nexus 1 8552
Protoss_Robotics_Facility 1 8185
Protoss_Shuttle 1 9027
Protoss_Robotics_Support_Bay 1 8605
Protoss_Zealot 2 9197
Protoss_Reaver 1 10169
Protoss_Observatory 1 9360
Protoss_Scarab 1 9765
11117
