Protoss_Gateway 3 11325
Protoss_Assimilator 1 3311
Protoss_Cybernetics_Core 1 4315
Protoss_Dragoon 8 10183
Protoss_Nexus 2 11547
Protoss_Robotics_Facility 1 8521
Protoss_Observatory 1 8658
Protoss_Observer 3 10641
11547
