Protoss_Gateway 3 11343
Protoss_Assimilator 1 3246
Protoss_Cybernetics_Core 2 4336
Protoss_Dragoon 7 10829
Protoss_Robotics_Facility 1 7505
Protoss_Shuttle 1 8311
Protoss_Robotics_Support_Bay 1 8103
Protoss_Zealot 2 9235
Protoss_Reaver 1 9609
Protoss_Observatory 1 8984
Protoss_Observer 2 10543
Protoss_Nexus 1 12061
12061
