Protoss_Gateway 6 11391
Protoss_Assimilator 1 3200
Protoss_Cybernetics_Core 1 4291
Protoss_Dragoon 5 9363
Protoss_Robotics_Facility 1 7223
Protoss_Shuttle 1 8053
Protoss_Nexus 2 11759
Protoss_Robotics_Support_Bay 1 7993
Protoss_Reaver 1 9517
Protoss_Observatory 1 8873
Protoss_Observer 2 10451
11759
