Protoss_Gateway 2 11342
Protoss_Assimilator 1 3273
Protoss_Cybernetics_Core 1 4407
Protoss_Dragoon 5 11079
Protoss_Robotics_Facility 1 7060
Protoss_Nexus 2 11653
Protoss_Shuttle 1 7917
Protoss_Robotics_Support_Bay 1 7577
Protoss_Zealot 2 8555
Protoss_Reaver 1 9065
Protoss_Stargate 1 11125
Protoss_Observatory 1 10646
11653
