Protoss_Gateway 3 10622
Protoss_Assimilator 1 3422
Protoss_Cybernetics_Core 1 4497
Protoss_Zealot 4 6360
Protoss_Dragoon 7 10301
Protoss_Robotics_Facility 1 9381
Protoss_Observatory 1 10100
Protoss_Observer 1 10951
Protoss_Nexus 1 12880
12880
