Protoss_Gateway 4 11387
Protoss_Assimilator 3 9758
Protoss_Zealot 1 4037
Protoss_Cybernetics_Core 1 4734
Protoss_Dragoon 9 10865
Protoss_Nexus 1 9351
Protoss_Robotics_Facility 1 9795
Protoss_Observatory 1 9949
11387
