Protoss_Gateway 2 6193
Protoss_Assimilator 2 4683
Protoss_Cybernetics_Core 1 4538
Protoss_Dragoon 8 10291
Protoss_Forge 1 6211
Protoss_Robotics_Facility 1 8643
Protoss_Photon_Cannon 1 8828
Protoss_Observatory 1 8931
Protoss_Robotics_Support_Bay 1 9378
Protoss_Shuttle 1 10806
10806
