Protoss_Assimilator 2 3966
Protoss_Gateway 1 3835
Protoss_Zealot 3 5785
Protoss_Cybernetics_Core 1 5363
Protoss_Robotics_Facility 1 7179
Protoss_Dragoon 3 7883
Protoss_Shuttle 1 7983
Protoss_Robotics_Support_Bay 1 7467
Protoss_Reaver 2 10863
Protoss_Scarab 2 8649
10863
