Protoss_Nexus 2 10321
Protoss_Gateway 4 10977
Protoss_Assimilator 1 4265
Protoss_Cybernetics_Core 1 5473
Protoss_Dragoon 13 11141
Protoss_Robotics_Facility 1 10155
Protoss_Observatory 1 10334
11141
