Protoss_Gateway 2 7074
Protoss_Assimilator 1 3145
Protoss_Zealot 3 5388
Protoss_Cybernetics_Core 1 5038
Protoss_Robotics_Facility 1 6709
Protoss_Dragoon 3 11026
Protoss_Shuttle 1 8536
Protoss_Robotics_Support_Bay 1 8179
Protoss_Observatory 1 8808
Protoss_Reaver 1 10036
Protoss_Nexus 1 12048
Protoss_Observer 1 10368
Protoss_Citadel_of_Adun 1 11158
12048
