Protoss_Gateway 3 11193
Protoss_Assimilator 1 3041
Protoss_Cybernetics_Core 1 4459
Protoss_Dragoon 9 9335
Protoss_Robotics_Facility 1 6304
Protoss_Observatory 1 6407
Protoss_Observer 2 7987
Protoss_Shuttle 1 10021
Protoss_Nexus 1 12027
Protoss_Zealot 3 10843
12027
