Protoss_Gateway 4 11429
Protoss_Assimilator 1 3547
Protoss_Cybernetics_Core 1 4597
Protoss_Robotics_Facility 1 6311
Protoss_Dragoon 6 9414
Protoss_Observatory 1 6429
Protoss_Observer 4 10215
Protoss_Nexus 2 11955
11955
