Protoss_Gateway 2 7523
Protoss_Assimilator 1 3484
Protoss_Cybernetics_Core 1 4633
Protoss_Robotics_Facility 1 6366
Protoss_Dragoon 7 10916
Protoss_Observatory 1 6668
Protoss_Observer 3 10728
Protoss_Nexus 2 11974
Protoss_Shuttle 1 10306
Protoss_Citadel_of_Adun 1 10794
11974
