Protoss_Gateway 2 8779
Protoss_Assimilator 2 9823
Protoss_Cybernetics_Core 1 4508
Protoss_Dragoon 6 10767
Protoss_Citadel_of_Adun 1 6776
Protoss_Nexus 1 9231
Protoss_Templar_Archives 1 8005
Protoss_Dark_Templar 2 9623
Protoss_Robotics_Facility 1 10124
10767
