Protoss_Gateway 1 3300
Protoss_Assimilator 1 3475
Protoss_Zealot 5 10053
Protoss_Cybernetics_Core 1 5249
Protoss_Dragoon 5 10895
Protoss_Robotics_Facility 1 7329
Protoss_Shuttle 1 8455
Protoss_Observatory 1 8284
Protoss_Observer 1 9093
Protoss_Robotics_Support_Bay 1 9060
Protoss_Reaver 1 10565
Protoss_Nexus 1 11979
11979
