Protoss_Gateway 2 10924
Protoss_Assimilator 1 3483
Protoss_Cybernetics_Core 1 4579
Protoss_Dragoon 6 11041
Protoss_Robotics_Facility 1 6562
Protoss_Shuttle 1 7451
Protoss_Observatory 1 7270
Protoss_Robotics_Support_Bay 1 7528
Protoss_Observer 2 10146
Protoss_Reaver 1 9421
Protoss_Nexus 1 11308
Protoss_Scarab 7 9959
11308
