Protoss_Assimilator 1 2874
Protoss_Gateway 1 3833
Protoss_Cybernetics_Core 1 4858
Protoss_Robotics_Facility 1 6382
Protoss_Dragoon 6 10758
Protoss_Robotics_Support_Bay 1 6509
Protoss_Observatory 1 6566
Protoss_Observer 1 7501
Protoss_Shuttle 2 10843
Protoss_Reaver 1 10031
10843
