Protoss_Gateway 3 10929
Protoss_Assimilator 2 9259
Protoss_Cybernetics_Core 1 4527
Protoss_Dragoon 7 9985
Protoss_Nexus 1 8549
Protoss_Robotics_Facility 1 8277
Protoss_Shuttle 1 9409
Protoss_Observatory 1 8737
Protoss_Observer 1 9831
Protoss_Robotics_Support_Bay 1 9641
Protoss_Citadel_of_Adun 1 10834
Protoss_Reaver 1 11327
11327
