Protoss_Gateway 3 8004
Protoss_Assimilator 1 3346
Protoss_Cybernetics_Core 1 4376
Protoss_Dragoon 7 10423
Protoss_Robotics_Facility 1 7469
Protoss_Observatory 1 7702
Protoss_Zealot 6 10411
Protoss_Observer 2 9098
Protoss_Shuttle 1 10391
10423
