Protoss_Gateway 3 9720
Protoss_Assimilator 1 3553
Protoss_Cybernetics_Core 1 4630
Protoss_Dragoon 9 10821
Protoss_Citadel_of_Adun 1 7027
Protoss_Templar_Archives 1 8087
Protoss_Dark_Templar 2 9016
Protoss_Nexus 1 11007
Protoss_Robotics_Facility 1 10863
11007
