Protoss_Gateway 3 10013
Protoss_Assimilator 1 3306
Protoss_Cybernetics_Core 1 4388
Protoss_Zealot 3 10696
Protoss_Dragoon 6 9246
Protoss_Nexus 1 10111
Protoss_Robotics_Facility 1 9560
Protoss_Shuttle 1 10586
Protoss_Observatory 1 10046
Protoss_Robotics_Support_Bay 1 10143
10696
