Protoss_Nexus 2 11737
Protoss_Gateway 3 9133
Protoss_Assimilator 2 8934
Protoss_Cybernetics_Core 1 5639
Protoss_Zealot 2 9229
Protoss_Dragoon 11 10913
Protoss_Robotics_Facility 1 8391
Protoss_Observatory 1 8533
Protoss_Observer 3 10739
Protoss_Citadel_of_Adun 1 11320
11737
