Protoss_Gateway 2 6938
Protoss_Assimilator 1 3483
Protoss_Cybernetics_Core 1 4511
Protoss_Dragoon 10 10839
Protoss_Robotics_Facility 1 8292
Protoss_Zealot 2 8435
Protoss_Observatory 1 8443
Protoss_Observer 2 10441
Protoss_Nexus 1 12726
12726
