Protoss_Gateway 2 7355
Protoss_Assimilator 1 3144
Protoss_Cybernetics_Core 1 4251
Protoss_Dragoon 10 9699
Protoss_Robotics_Facility 1 7465
Protoss_Observatory 1 7614
Protoss_Observer 2 10521
Protoss_Nexus 2 12599
12599
