Protoss_Gateway 2 7511
Protoss_Assimilator 1 3526
Protoss_Cybernetics_Core 1 4551
Protoss_Dragoon 10 10875
Protoss_Robotics_Facility 1 7672
Protoss_Observatory 1 7815
Protoss_Nexus 1 10487
Protoss_Observer 1 8671
Protoss_Shuttle 1 10168
Protoss_Robotics_Support_Bay 1 10281
10875
