Protoss_Assimilator 1 2991
Protoss_Gateway 1 3873
Protoss_Cybernetics_Core 1 4926
Protoss_Robotics_Facility 1 6490
Protoss_Dragoon 6 10656
Protoss_Shuttle 3 11106
Protoss_Observatory 1 7192
Protoss_Observer 2 8676
Protoss_Robotics_Support_Bay 1 8199
Protoss_Nexus 1 12751
12751
