Protoss_Gateway 3 11102
Protoss_Assimilator 1 3304
Protoss_Cybernetics_Core 1 4366
Protoss_Dragoon 10 11089
Protoss_Nexus 2 11537
Protoss_Zealot 1 8007
Protoss_Robotics_Facility 1 10383
Protoss_Observatory 1 10481
11537
