Protoss_Gateway 3 9634
Protoss_Assimilator 1 3414
Protoss_Cybernetics_Core 1 4573
Protoss_Dragoon 11 11153
Protoss_Nexus 1 9168
Protoss_Robotics_Facility 1 8933
Protoss_Observatory 1 9164
Protoss_Observer 2 10603
11153
