Protoss_Gateway 2 6218
Protoss_Assimilator 2 3801
Protoss_Cybernetics_Core 1 4933
Protoss_Dragoon 11 10847
Protoss_Nexus 1 9919
Protoss_Robotics_Facility 1 9393
Protoss_Shuttle 1 10231
Protoss_Robotics_Support_Bay 1 10318
10847
