Protoss_Nexus 2 12468
Protoss_Gateway 2 5257
Protoss_Assimilator 2 9653
Protoss_Cybernetics_Core 1 5732
Protoss_Dragoon 7 11025
Protoss_Robotics_Facility 1 10487
Protoss_Observatory 1 10672
12468
