Protoss_Gateway 2 10718
Protoss_Assimilator 1 3498
Protoss_Cybernetics_Core 1 4422
Protoss_Zealot 1 4211
Protoss_Dragoon 6 10376
Protoss_Robotics_Facility 1 6593
Protoss_Shuttle 1 7436
Protoss_Robotics_Support_Bay 1 7053
Protoss_Reaver 1 8856
Protoss_Observatory 1 8933
Protoss_Scarab 2 9028
Protoss_Observer 1 10316
10718
