Protoss_Gateway 2 6967
Protoss_Assimilator 1 3171
Protoss_Zealot 1 3859
Protoss_Cybernetics_Core 1 4693
Protoss_Dragoon 8 10259
Protoss_Robotics_Facility 1 9104
Protoss_Observatory 1 9355
Protoss_Nexus 1 11635
Protoss_Observer 2 10785
Protoss_Robotics_Support_Bay 1 10185
Protoss_Shuttle 1 11391
11635
