Protoss_Gateway 2 8015
Protoss_Assimilator 2 9476
Protoss_Zealot 1 3769
Protoss_Cybernetics_Core 1 5101
Protoss_Dragoon 8 9773
Protoss_Nexus 1 8819
Protoss_Citadel_of_Adun 1 8317
Protoss_Templar_Archives 1 9367
Protoss_Dark_Templar 2 10525
Protoss_Robotics_Facility 1 11427
11427
