Protoss_Gateway 2 9243
Protoss_Assimilator 1 3294
Protoss_Cybernetics_Core 1 4409
Protoss_Dragoon 7 10923
Protoss_Citadel_of_Adun 1 6647
Protoss_Templar_Archives 1 7652
Protoss_Dark_Templar 2 9145
Protoss_Nexus 1 10299
Protoss_Stargate 1 11039
11039
