Protoss_Gateway 4 10114
Protoss_Assimilator 2 3572
Protoss_Cybernetics_Core 1 4685
Protoss_Dragoon 9 10873
Protoss_Nexus 1 10113
Protoss_Robotics_Facility 1 9513
Protoss_Observatory 1 9716
Protoss_Observer 1 10507
10873
