Protoss_Gateway 4 11126
Protoss_Zealot 1 3631
Protoss_Assimilator 1 3854
Protoss_Cybernetics_Core 1 4895
Protoss_Dragoon 5 7465
Protoss_Nexus 2 10921
Protoss_Robotics_Facility 1 10463
Protoss_Observatory 1 10578
Protoss_Shuttle 1 11373
11373
