Protoss_Gateway 2 8278
Protoss_Assimilator 1 3443
Protoss_Cybernetics_Core 1 4606
Protoss_Dragoon 9 9867
Protoss_Robotics_Facility 1 7342
Protoss_Observatory 1 7448
Protoss_Observer 2 8893
Protoss_Shuttle 1 10751
Protoss_Nexus 1 12503
Protoss_Zealot 2 10906
12503
