Protoss_Gateway 2 7699
Protoss_Assimilator 1 3352
Protoss_Cybernetics_Core 1 4391
Protoss_Zealot 2 9491
Protoss_Dragoon 8 10583
Protoss_Robotics_Facility 1 7533
Protoss_Shuttle 1 8405
Protoss_Observatory 1 8080
Protoss_Robotics_Support_Bay 1 8613
Protoss_Reaver 1 10109
Protoss_Nexus 1 11825
Protoss_Observer 1 10567
11825
