Protoss_Gateway 4 11159
Protoss_Assimilator 2 10395
Protoss_Cybernetics_Core 1 4399
Protoss_Dragoon 5 11175
Protoss_Citadel_of_Adun 1 5643
Protoss_Templar_Archives 1 6733
Protoss_Nexus 2 10520
Protoss_Dark_Templar 3 9065
Protoss_Robotics_Facility 1 10796
11175
