Protoss_Gateway 2 4785
Protoss_Assimilator 1 3235
Protoss_Cybernetics_Core 1 4269
Protoss_Dragoon 6 11093
Protoss_Nexus 2 12705
Protoss_Robotics_Facility 1 8903
Protoss_Shuttle 1 9719
Protoss_Robotics_Support_Bay 1 9133
Protoss_Observatory 1 9854
Protoss_Reaver 1 10861
Protoss_Zealot 2 10227
12705
