Protoss_Gateway 2 8054
Protoss_Assimilator 1 3214
Protoss_Cybernetics_Core 1 4403
Protoss_Dragoon 11 10455
Protoss_Robotics_Facility 1 7441
Protoss_Observatory 1 7603
Protoss_Observer 2 10803
Protoss_Nexus 2 12656
Protoss_Citadel_of_Adun 1 11296
12656
