Protoss_Gateway 2 11162
Protoss_Assimilator 1 3399
Protoss_Cybernetics_Core 1 4489
Protoss_Dragoon 8 11051
Protoss_Robotics_Facility 1 7482
Protoss_Shuttle 1 8287
Protoss_Robotics_Support_Bay 1 8086
Protoss_Reaver 1 9577
Protoss_Observatory 1 8999
Protoss_Nexus 1 11758
Protoss_Observer 1 10499
Protoss_Scarab 2 9835
11758
