Protoss_Gateway 1 3434
Protoss_Assimilator 1 3434
Protoss_Cybernetics_Core 1 4711
Protoss_Zealot 1 4261
Protoss_Dragoon 7 10793
Protoss_Robotics_Facility 1 7815
Protoss_Shuttle 1 8879
Protoss_Robotics_Support_Bay 1 8190
Protoss_Reaver 1 10175
Protoss_Nexus 1 11959
Protoss_Observatory 1 10009
Protoss_Observer 1 10803
11959
