Protoss_Gateway 2 6708
Protoss_Assimilator 1 3167
Protoss_Cybernetics_Core 1 4411
Protoss_Dragoon 11 11117
Protoss_Nexus 1 9797
Protoss_Robotics_Facility 1 9351
Protoss_Observatory 1 9552
Protoss_Observer 2 10949
11117
