Protoss_Gateway 3 10766
Protoss_Assimilator 2 8967
Protoss_Cybernetics_Core 1 4370
Protoss_Dragoon 9 10803
Protoss_Nexus 1 9101
Protoss_Robotics_Facility 1 8829
Protoss_Citadel_of_Adun 1 9388
Protoss_Observatory 1 9108
Protoss_Observer 1 9889
Protoss_Templar_Archives 1 10603
Protoss_Shuttle 1 11277
11277
