Protoss_Nexus 1 5559
Protoss_Gateway 2 7479
Protoss_Assimilator 1 4217
Protoss_Cybernetics_Core 1 5563
Protoss_Zealot 1 5413
Protoss_Dragoon 10 10715
Protoss_Forge 1 7909
Protoss_Photon_Cannon 2 9082
Protoss_Robotics_Facility 1 10253
Protoss_Observatory 1 10420
Protoss_Shuttle 1 11269
11269
