Protoss_Gateway 2 8013
Protoss_Assimilator 2 3859
Protoss_Zealot 2 5071
Protoss_Cybernetics_Core 1 5367
Protoss_Dragoon 5 10775
Protoss_Citadel_of_Adun 1 7815
Protoss_Robotics_Facility 1 8939
Protoss_Templar_Archives 1 8877
Protoss_Nexus 1 10893
Protoss_Shuttle 1 9739
Protoss_Dark_Templar 2 9789
Protoss_Observatory 1 9785
Protoss_Observer 1 10827
10893
