Protoss_Gateway 2 9960
Protoss_Assimilator 1 2400
Protoss_Cybernetics_Core 1 3089
Protoss_Dragoon 5 9586
Protoss_Robotics_Facility 1 4539
Protoss_Shuttle 1 5893
Protoss_Robotics_Support_Bay 1 6269
Protoss_Zealot 2 7169
Protoss_Reaver 2 9175
Protoss_Observatory 1 7629
Protoss_Observer 1 8225
Protoss_Scarab 2 9172
9960
