Protoss_Gateway 2 8759
Protoss_Assimilator 1 3667
Protoss_Zealot 1 4145
Protoss_Cybernetics_Core 1 5197
Protoss_Dragoon 8 10841
Protoss_Nexus 2 11165
Protoss_Robotics_Facility 1 11189
11189
