Protoss_Gateway 3 9443
Protoss_Assimilator 1 3716
Protoss_Cybernetics_Core 1 4825
Protoss_Dragoon 13 11176
Protoss_Robotics_Facility 1 7467
Protoss_Observatory 1 7653
Protoss_Observer 2 10661
11176
