Protoss_Gateway 2 7429
Protoss_Assimilator 1 3461
Protoss_Cybernetics_Core 1 4522
Protoss_Zealot 1 4763
Protoss_Dragoon 11 10443
Protoss_Robotics_Facility 1 9979
Protoss_Observatory 1 10126
Protoss_Observer 1 10915
10915
