Protoss_Gateway 2 10668
Protoss_Assimilator 1 3333
Protoss_Zealot 1 3829
Protoss_Cybernetics_Core 1 5087
Protoss_Dragoon 6 10359
Protoss_Robotics_Facility 2 8043
Protoss_Robotics_Support_Bay 1 7332
Protoss_Shuttle 1 8405
Protoss_Reaver 2 9799
Protoss_Scarab 3 9964
10668
