Protoss_Gateway 2 6301
Protoss_Assimilator 1 3461
Protoss_Cybernetics_Core 1 4607
Protoss_Dragoon 11 10335
Protoss_Robotics_Facility 1 8121
Protoss_Shuttle 1 9031
Protoss_Observatory 1 8811
Protoss_Observer 1 9605
Protoss_Robotics_Support_Bay 1 9539
Protoss_Reaver 1 11123
11123
