Protoss_Gateway 2 8632
Protoss_Assimilator 1 3183
Protoss_Cybernetics_Core 1 4440
Protoss_Zealot 1 4223
Protoss_Dragoon 9 10405
Protoss_Nexus 1 9496
Protoss_Robotics_Facility 1 8838
Protoss_Observatory 1 8996
Protoss_Observer 1 9771
Protoss_Shuttle 1 11080
Protoss_Robotics_Support_Bay 1 10574
11080
