Protoss_Gateway 2 6159
Protoss_Assimilator 1 3618
Protoss_Cybernetics_Core 1 4852
Protoss_Dragoon 11 10846
Protoss_Nexus 1 9703
Protoss_Robotics_Facility 1 9578
Protoss_Observatory 1 9843
Protoss_Observer 1 10856
10856
