Protoss_Gateway 3 11042
Protoss_Assimilator 1 3383
Protoss_Cybernetics_Core 1 4633
Protoss_Robotics_Facility 1 6183
Protoss_Dragoon 9 10466
Protoss_Observatory 1 6368
Protoss_Observer 3 9963
Protoss_Nexus 1 10895
Protoss_Shuttle 1 11351
11351
