Protoss_Gateway 2 9430
Protoss_Assimilator 1 3350
Protoss_Cybernetics_Core 1 4440
Protoss_Zealot 1 4287
Protoss_Dragoon 9 10921
Protoss_Robotics_Facility 1 7965
Protoss_Shuttle 1 8769
Protoss_Robotics_Support_Bay 1 8186
Protoss_Reaver 1 9911
Protoss_Observatory 1 9205
Protoss_Observer 2 10887
10921
