Protoss_Gateway 2 6863
Protoss_Assimilator 2 4054
Protoss_Zealot 4 6145
Protoss_Cybernetics_Core 1 5678
Protoss_Dragoon 9 10941
Protoss_Citadel_of_Adun 1 8993
Protoss_Templar_Archives 1 10933
10941
