Protoss_Gateway 2 10156
Protoss_Assimilator 2 9699
Protoss_Cybernetics_Core 1 4389
Protoss_Zealot 1 4095
Protoss_Dragoon 7 10797
Protoss_Robotics_Facility 1 6416
Protoss_Observatory 1 6776
Protoss_Observer 3 10411
Protoss_Nexus 1 10267
Protoss_Citadel_of_Adun 1 9447
Protoss_Templar_Archives 1 10599
10797
