Protoss_Assimilator 3 4399
Protoss_Gateway 2 11037
Protoss_Zealot 2 5151
Protoss_Cybernetics_Core 1 6038
Protoss_Dragoon 6 10605
Protoss_Robotics_Facility 1 7901
Protoss_Shuttle 1 8711
Protoss_Robotics_Support_Bay 1 8304
Protoss_Reaver 1 9867
Protoss_Nexus 1 11258
11258
