Protoss_Gateway 2 7176
Protoss_Assimilator 2 10663
Protoss_Cybernetics_Core 1 4535
Protoss_Dragoon 4 10281
Protoss_Citadel_of_Adun 1 6874
Protoss_Templar_Archives 1 7913
Protoss_Robotics_Facility 1 9222
Protoss_Dark_Templar 2 8671
Protoss_Nexus 1 11093
Protoss_Observatory 1 9424
Protoss_Stargate 1 10768
Protoss_Observer 1 10211
11093
