Protoss_Gateway 3 9583
Protoss_Assimilator 1 3618
Protoss_Cybernetics_Core 1 4673
Protoss_Dragoon 8 9708
Protoss_Robotics_Facility 1 7605
Protoss_Observatory 1 7744
Protoss_Observer 2 9423
Protoss_Shuttle 1 10346
Protoss_Robotics_Support_Bay 1 9778
Protoss_Reaver 1 11488
11488
