Protoss_Gateway 3 9860
Protoss_Assimilator 2 9031
Protoss_Cybernetics_Core 1 4241
Protoss_Dragoon 10 11187
Protoss_Nexus 1 8815
Protoss_Stargate 1 9514
Protoss_Fleet_Beacon 1 10570
Protoss_Zealot 1 10959
11187
