Protoss_Gateway 3 8765
Protoss_Zealot 4 5795
Protoss_Forge 1 3803
Protoss_Assimilator 1 4571
Protoss_Cybernetics_Core 1 5553
Protoss_Dragoon 9 10719
Protoss_Robotics_Facility 1 9551
Protoss_Observatory 1 9987
Protoss_Observer 1 10805
10805
