Protoss_Gateway 2 8926
Protoss_Assimilator 2 10112
Protoss_Cybernetics_Core 1 4492
Protoss_Zealot 1 4319
Protoss_Dragoon 7 10045
Protoss_Robotics_Facility 1 7563
Protoss_Nexus 1 9858
Protoss_Observatory 1 7849
Protoss_Observer 2 9297
Protoss_Citadel_of_Adun 1 9865
Protoss_Templar_Archives 1 10978
Protoss_Stargate 1 11625
11625
