Protoss_Gateway 3 10548
Protoss_Assimilator 1 3313
Protoss_Cybernetics_Core 1 4424
Protoss_Dragoon 4 10786
Protoss_Robotics_Facility 1 7333
Protoss_Zealot 3 9316
Protoss_Robotics_Support_Bay 1 7836
Protoss_Shuttle 1 8596
Protoss_Observatory 1 8035
Protoss_Reaver 1 9738
Protoss_Nexus 1 11378
Protoss_Observer 1 10070
11378
