Protoss_Gateway 2 8878
Protoss_Assimilator 1 3598
Protoss_Cybernetics_Core 1 4820
Protoss_Dragoon 8 11141
Protoss_Robotics_Facility 1 6536
Protoss_Observatory 1 6677
Protoss_Observer 3 10761
Protoss_Shuttle 1 9591
Protoss_Zealot 2 10151
11141
