Protoss_Gateway 2 7549
Protoss_Assimilator 1 3329
Protoss_Cybernetics_Core 1 4546
Protoss_Dragoon 11 11093
Protoss_Robotics_Facility 1 7361
Protoss_Observatory 1 7475
Protoss_Observer 2 9055
Protoss_Nexus 1 11549
Protoss_Zealot 1 10943
11549
