Protoss_Gateway 2 6954
Protoss_Assimilator 1 3293
Protoss_Cybernetics_Core 1 4315
Protoss_Dragoon 4 10685
Protoss_Citadel_of_Adun 1 5851
Protoss_Templar_Archives 1 6837
Protoss_Dark_Templar 5 9603
Protoss_Nexus 1 10657
Protoss_Robotics_Facility 1 11913
11913
