Protoss_Gateway 2 7377
Protoss_Assimilator 1 3332
Protoss_Cybernetics_Core 1 4385
Protoss_Dragoon 10 10087
Protoss_Robotics_Facility 1 7405
Protoss_Observatory 1 7747
Protoss_Observer 2 9621
Protoss_Nexus 2 12251
12251
