Protoss_Gateway 3 10610
Protoss_Assimilator 1 3542
Protoss_Cybernetics_Core 1 4823
Protoss_Robotics_Facility 1 6400
Protoss_Dragoon 6 9741
Protoss_Observatory 1 6601
Protoss_Observer 3 9151
Protoss_Nexus 1 11215
Protoss_Citadel_of_Adun 1 10205
11215
