Protoss_Gateway 2 6976
Protoss_Assimilator 1 3241
Protoss_Cybernetics_Core 1 4451
Protoss_Dragoon 5 10083
Protoss_Citadel_of_Adun 1 6670
Protoss_Templar_Archives 1 7723
Protoss_Nexus 1 9543
Protoss_Dark_Templar 4 9231
10083
