Protoss_Nexus 2 11956
Protoss_Gateway 3 11373
Protoss_Assimilator 2 7618
Protoss_Cybernetics_Core 1 5418
Protoss_Zealot 1 5457
Protoss_Dragoon 12 10881
Protoss_Robotics_Facility 1 9327
Protoss_Observatory 1 9419
Protoss_Observer 2 10815
Protoss_Citadel_of_Adun 1 11320
11956
