Protoss_Gateway 2 7913
Protoss_Assimilator 1 3794
Protoss_Zealot 2 4701
Protoss_Cybernetics_Core 1 4973
Protoss_Dragoon 7 10291
Protoss_Nexus 1 11693
Protoss_Robotics_Facility 1 11544
11693
