Protoss_Gateway 3 11143
Protoss_Assimilator 1 3473
Protoss_Cybernetics_Core 1 4710
Protoss_Dragoon 10 10793
Protoss_Robotics_Facility 1 7535
Protoss_Observatory 1 7641
Protoss_Observer 2 9101
Protoss_Nexus 1 11000
Protoss_Shuttle 1 10603
Protoss_Zealot 1 10609
11143
