Protoss_Gateway 2 7947
Protoss_Assimilator 1 3358
Protoss_Cybernetics_Core 1 4413
Protoss_Dragoon 7 10761
Protoss_Robotics_Facility 1 7458
Protoss_Observatory 1 7598
Protoss_Observer 1 8451
Protoss_Nexus 1 10664
Protoss_Shuttle 1 10216
Protoss_Zealot 2 9876
10761
