Protoss_Gateway 3 9393
Protoss_Assimilator 1 3779
Protoss_Zealot 4 9966
Protoss_Cybernetics_Core 1 5421
Protoss_Dragoon 7 11146
Protoss_Robotics_Facility 1 8113
Protoss_Observatory 1 8310
Protoss_Shuttle 1 9266
11146
