Protoss_Gateway 4 10808
Protoss_Assimilator 1 3433
Protoss_Cybernetics_Core 1 4478
Protoss_Robotics_Facility 1 6227
Protoss_Dragoon 6 11171
Protoss_Observatory 1 6558
Protoss_Observer 2 8901
Protoss_Nexus 2 11610
11610
