Protoss_Gateway 3 7640
Protoss_Assimilator 1 3313
Protoss_Cybernetics_Core 1 4424
Protoss_Dragoon 5 9775
Protoss_Robotics_Facility 1 7349
Protoss_Citadel_of_Adun 1 7661
Protoss_Zealot 9 10406
Protoss_Nexus 1 12207
12207
