Protoss_Gateway 3 11028
Protoss_Assimilator 1 3219
Protoss_Cybernetics_Core 1 4339
Protoss_Dragoon 9 10527
Protoss_Robotics_Facility 1 7632
Protoss_Observatory 1 7795
Protoss_Nexus 1 10311
Protoss_Observer 3 9821
11028
