Protoss_Gateway 2 9925
Protoss_Assimilator 1 3185
Protoss_Cybernetics_Core 1 4471
Protoss_Zealot 2 8405
Protoss_Robotics_Facility 1 6133
Protoss_Dragoon 4 10679
Protoss_Shuttle 1 7061
Protoss_Robotics_Support_Bay 1 6382
Protoss_Reaver 1 8251
Protoss_Observatory 1 7915
Protoss_Observer 1 9323
Protoss_Nexus 1 12737
12737
