Protoss_Gateway 1 3376
Protoss_Assimilator 1 3366
Protoss_Cybernetics_Core 1 4471
Protoss_Dragoon 8 10743
Protoss_Robotics_Facility 1 7343
Protoss_Observatory 1 7458
Protoss_Nexus 1 9966
Protoss_Observer 1 8615
Protoss_Shuttle 1 9697
Protoss_Robotics_Support_Bay 1 9289
Protoss_Reaver 1 10839
Protoss_Citadel_of_Adun 1 10955
10955
