Protoss_Gateway 2 6409
Protoss_Assimilator 1 3239
Protoss_Cybernetics_Core 1 4312
Protoss_Dragoon 9 10893
Protoss_Robotics_Facility 1 7459
Protoss_Shuttle 1 8459
Protoss_Robotics_Support_Bay 1 7878
Protoss_Zealot 2 8603
Protoss_Reaver 2 11043
Protoss_Nexus 1 11461
Protoss_Scarab 5 9954
11461
