Protoss_Gateway 2 7897
Protoss_Assimilator 1 3199
Protoss_Cybernetics_Core 1 4331
Protoss_Dragoon 9 10637
Protoss_Robotics_Facility 1 7149
Protoss_Observatory 1 7269
Protoss_Observer 1 8223
Protoss_Shuttle 1 9333
Protoss_Nexus 1 11431
Protoss_Robotics_Support_Bay 1 9701
Protoss_Reaver 1 11409
11431
