Protoss_Gateway 2 10313
Protoss_Zealot 3 5617
Protoss_Assimilator 1 4968
Protoss_Cybernetics_Core 1 6021
Protoss_Dragoon 7 11133
Protoss_Nexus 1 10672
Protoss_Robotics_Facility 1 10192
Protoss_Shuttle 1 11151
Protoss_Robotics_Support_Bay 1 10540
11151
