Protoss_Gateway 2 6899
Protoss_Assimilator 1 3262
Protoss_Cybernetics_Core 1 4425
Protoss_Dragoon 10 10991
Protoss_Robotics_Facility 1 8503
Protoss_Observatory 1 8717
Protoss_Observer 3 10725
Protoss_Nexus 2 12367
12367
