Protoss_Gateway 2 8985
Protoss_Assimilator 2 9135
Protoss_Cybernetics_Core 1 4401
Protoss_Dragoon 9 10625
Protoss_Robotics_Facility 1 7567
Protoss_Nexus 1 9825
Protoss_Observatory 1 7827
Protoss_Observer 3 10165
Protoss_Citadel_of_Adun 1 9473
Protoss_Stargate 1 11235
Protoss_Templar_Archives 1 11417
11417
