Protoss_Gateway 4 10699
Protoss_Zealot 1 3799
Protoss_Nexus 1 6739
Protoss_Assimilator 2 7774
Protoss_Cybernetics_Core 1 6042
Protoss_Dragoon 9 10271
Protoss_Robotics_Facility 1 9619
Protoss_Observatory 1 9753
Protoss_Observer 1 10521
Protoss_Citadel_of_Adun 1 11331
11331
