Protoss_Gateway 4 10709
Protoss_Assimilator 1 3226
Protoss_Cybernetics_Core 1 4315
Protoss_Dragoon 10 10883
Protoss_Robotics_Facility 1 7253
Protoss_Observatory 1 7565
Protoss_Robotics_Support_Bay 1 7609
Protoss_Observer 3 10943
Protoss_Nexus 2 11759
11759
