Protoss_Gateway 3 10862
Protoss_Assimilator 1 3149
Protoss_Cybernetics_Core 1 4273
Protoss_Dragoon 4 6665
Protoss_Citadel_of_Adun 1 6724
Protoss_Zealot 1 7195
Protoss_Templar_Archives 1 7795
Protoss_Dark_Templar 5 10746
Protoss_Nexus 1 10944
Protoss_Robotics_Facility 1 11797
11797
