Protoss_Gateway 3 9718
Protoss_Assimilator 1 3558
Protoss_Cybernetics_Core 1 4583
Protoss_Dragoon 11 10758
Protoss_Nexus 1 10928
Protoss_Robotics_Facility 1 11203
Protoss_Zealot 1 10846
11203
