Protoss_Gateway 2 6929
Protoss_Assimilator 1 3383
Protoss_Cybernetics_Core 1 4591
Protoss_Dragoon 9 10901
Protoss_Citadel_of_Adun 1 7497
Protoss_Forge 1 7363
Protoss_Templar_Archives 1 8583
Protoss_Photon_Cannon 1 9374
Protoss_Dark_Templar 2 9386
Protoss_Nexus 1 12143
12143
