Protoss_Gateway 2 8544
Protoss_Assimilator 2 9977
Protoss_Cybernetics_Core 1 4355
Protoss_Zealot 1 4119
Protoss_Dragoon 3 9647
Protoss_Citadel_of_Adun 1 5698
Protoss_Templar_Archives 1 6764
Protoss_Dark_Templar 2 8337
Protoss_Nexus 2 12854
Protoss_Stargate 1 8543
Protoss_Arbiter_Tribunal 1 9828
Protoss_Arbiter 1 13707
13707
