Protoss_Gateway 2 5875
Protoss_Assimilator 1 3341
Protoss_Cybernetics_Core 1 4455
Protoss_Dragoon 12 10617
Protoss_Nexus 1 9551
Protoss_Robotics_Facility 1 9807
Protoss_Observatory 1 10063
Protoss_Observer 1 10953
10953
