Protoss_Gateway 1 3273
Protoss_Assimilator 2 10741
Protoss_Cybernetics_Core 1 4271
Protoss_Robotics_Facility 2 11029
Protoss_Dragoon 3 11017
Protoss_Shuttle 2 10051
Protoss_Robotics_Support_Bay 1 6132
Protoss_Reaver 3 11599
Protoss_Nexus 1 10693
Protoss_Scarab 4 9993
Protoss_Observatory 1 10281
11599
