Protoss_Gateway 1 1885
Protoss_Assimilator 1 2325
Protoss_Cybernetics_Core 1 2873
Protoss_Zealot 2 5267
Protoss_Dragoon 4 9001
Protoss_Robotics_Facility 1 4349
Protoss_Shuttle 2 9097
Protoss_Robotics_Support_Bay 1 6141
Protoss_Reaver 3 9999
Protoss_Observatory 1 8128
Protoss_Nexus 1 8531
Protoss_Scarab 4 9525
9999
