Protoss_Gateway 2 3612
Protoss_Zealot 3 4391
Protoss_Assimilator 1 5021
Protoss_Cybernetics_Core 1 5963
Protoss_Dragoon 8 10506
Protoss_Nexus 1 11149
Protoss_Robotics_Facility 1 10878
11149
