Protoss_Assimilator 3 9401
Protoss_Gateway 2 7225
Protoss_Cybernetics_Core 1 4814
Protoss_Dragoon 7 10923
Protoss_Robotics_Facility 1 6955
Protoss_Zealot 2 7807
Protoss_Shuttle 1 7777
Protoss_Robotics_Support_Bay 1 7151
Protoss_Reaver 1 8919
Protoss_Nexus 1 10722
Protoss_Observatory 1 9293
Protoss_Citadel_of_Adun 1 10048
Protoss_Scarab 8 9984
10923
