Protoss_Gateway 2 7727
Protoss_Assimilator 1 3332
Protoss_Cybernetics_Core 1 4321
Protoss_Dragoon 10 10845
Protoss_Nexus 1 8962
Protoss_Robotics_Facility 1 9037
Protoss_Shuttle 1 9959
Protoss_Robotics_Support_Bay 1 9755
Protoss_Reaver 1 11321
11321
