Protoss_Gateway 3 9825
Protoss_Assimilator 1 3175
Protoss_Cybernetics_Core 1 4330
Protoss_Dragoon 10 11073
Protoss_Robotics_Facility 1 7736
Protoss_Nexus 1 9891
Protoss_Observatory 1 7889
Protoss_Observer 4 10461
11073
