Protoss_Gateway 4 11190
Protoss_Assimilator 4 5158
Protoss_Cybernetics_Core 1 4607
Protoss_Zealot 1 4711
Protoss_Dragoon 8 10783
Protoss_Nexus 1 11170
Protoss_Robotics_Facility 1 11023
11190
