Protoss_Gateway 2 9222
Protoss_Assimilator 1 3286
Protoss_Cybernetics_Core 1 4314
Protoss_Dragoon 9 10719
Protoss_Robotics_Facility 1 6307
Protoss_Shuttle 1 7113
Protoss_Robotics_Support_Bay 1 6833
Protoss_Reaver 1 8517
Protoss_Observatory 1 8609
Protoss_Zealot 1 8983
Protoss_Observer 1 9689
10719
