Protoss_Gateway 2 8837
Protoss_Assimilator 1 3211
Protoss_Cybernetics_Core 1 4395
Protoss_Dragoon 5 8175
Protoss_Nexus 1 8833
Protoss_Citadel_of_Adun 1 7981
Protoss_Robotics_Facility 1 9438
Protoss_Templar_Archives 1 9023
Protoss_Zealot 1 8941
Protoss_Dark_Templar 4 10625
Protoss_Shuttle 1 10261
Protoss_High_Templar 2 10755
Protoss_Forge 1 10641
10755
