Protoss_Gateway 2 8697
Protoss_Assimilator 1 3231
Protoss_Cybernetics_Core 1 4475
Protoss_Dragoon 10 11039
Protoss_Robotics_Facility 1 6474
Protoss_Shuttle 1 7271
Protoss_Robotics_Support_Bay 1 6953
Protoss_Reaver 1 8445
Protoss_Observatory 1 8283
Protoss_Observer 1 9053
Protoss_Scarab 6 9963
11039
