Protoss_Gateway 4 11012
Protoss_Assimilator 1 3355
Protoss_Cybernetics_Core 1 4512
Protoss_Dragoon 5 11121
Protoss_Citadel_of_Adun 1 5820
Protoss_Templar_Archives 1 6926
Protoss_Dark_Templar 5 9783
Protoss_Nexus 1 10365
Protoss_Robotics_Facility 1 11554
11554
