Protoss_Gateway 2 11255
Protoss_Assimilator 2 9742
Protoss_Cybernetics_Core 1 4401
Protoss_Dragoon 6 9421
Protoss_Nexus 1 8901
Protoss_Robotics_Facility 2 9117
Protoss_Observatory 1 8924
Protoss_Robotics_Support_Bay 1 9247
Protoss_Observer 1 9735
Protoss_Shuttle 1 10339
Protoss_Reaver 2 11669
11669
