Protoss_Gateway 2 5981
Protoss_Assimilator 2 10416
Protoss_Cybernetics_Core 1 4394
Protoss_Dragoon 8 10397
Protoss_Nexus 2 10769
Protoss_Citadel_of_Adun 1 8757
Protoss_Templar_Archives 1 10205
Protoss_Dark_Templar 1 11143
11143
