Protoss_Gateway 2 8722
Protoss_Assimilator 1 3422
Protoss_Cybernetics_Core 1 4631
Protoss_Dragoon 11 11179
Protoss_Robotics_Facility 1 7464
Protoss_Nexus 1 9785
Protoss_Observatory 1 7721
Protoss_Observer 3 10635
11179
