Protoss_Gateway 2 9608
Protoss_Assimilator 1 3478
Protoss_Cybernetics_Core 1 4558
Protoss_Zealot 2 8901
Protoss_Dragoon 7 11166
Protoss_Robotics_Facility 1 7788
Protoss_Shuttle 1 8931
Protoss_Robotics_Support_Bay 1 8376
Protoss_Reaver 1 10136
Protoss_Observatory 1 9977
Protoss_Observer 1 10871
11166
