Protoss_Gateway 4 8757
Protoss_Assimilator 3 5469
Protoss_Zealot 6 6937
Protoss_Cybernetics_Core 1 6506
Protoss_Dragoon 10 11123
Protoss_Robotics_Facility 1 10340
Protoss_Shuttle 1 11145
11145
