Protoss_Gateway 3 8618
Protoss_Assimilator 1 3438
Protoss_Cybernetics_Core 1 4495
Protoss_Dragoon 8 9831
Protoss_Robotics_Facility 1 7488
Protoss_Observatory 1 7583
Protoss_Observer 2 9031
Protoss_Shuttle 1 10686
Protoss_Zealot 2 10611
10686
