Protoss_Gateway 3 7873
Protoss_Assimilator 2 4187
Protoss_Zealot 5 10626
Protoss_Cybernetics_Core 1 6318
Protoss_Dragoon 6 9473
Protoss_Citadel_of_Adun 1 8688
Protoss_Robotics_Facility 1 10793
Protoss_Templar_Archives 1 11208
11208
