Protoss_Gateway 2 7404
Protoss_Assimilator 1 3574
Protoss_Zealot 2 9593
Protoss_Cybernetics_Core 1 5001
Protoss_Dragoon 8 10581
Protoss_Robotics_Facility 1 8648
Protoss_Shuttle 1 9601
Protoss_Observatory 1 9282
Protoss_Observer 1 10356
10581
