Protoss_Gateway 4 10513
Protoss_Assimilator 1 3359
Protoss_Cybernetics_Core 1 4382
Protoss_Dragoon 11 10859
Protoss_Zealot 1 7563
Protoss_Nexus 1 10384
Protoss_Robotics_Facility 1 9526
Protoss_Observatory 1 9621
Protoss_Observer 1 10397
10859
