Protoss_Assimilator 1 3013
Protoss_Gateway 4 10134
Protoss_Cybernetics_Core 1 4888
Protoss_Dragoon 9 10315
Protoss_Robotics_Facility 1 8252
Protoss_Nexus 1 10096
Protoss_Observatory 1 8844
Protoss_Observer 2 10229
Protoss_Shuttle 1 11311
11311
