Protoss_Gateway 2 5281
Protoss_Assimilator 1 3458
Protoss_Cybernetics_Core 1 4587
Protoss_Dragoon 10 10991
Protoss_Nexus 2 12446
Protoss_Robotics_Facility 1 9643
Protoss_Observatory 1 9887
Protoss_Observer 1 10691
12446
