Protoss_Gateway 3 10143
Protoss_Assimilator 1 3302
Protoss_Cybernetics_Core 1 4359
Protoss_Dragoon 10 10907
Protoss_Robotics_Facility 1 7265
Protoss_Observatory 1 7367
Protoss_Observer 2 9315
Protoss_Nexus 1 10595
Protoss_Shuttle 1 10397
Protoss_Zealot 3 10791
10907
