Protoss_Gateway 2 10953
Protoss_Assimilator 2 4348
Protoss_Zealot 1 3923
Protoss_Cybernetics_Core 1 5544
Protoss_Dragoon 6 10419
Protoss_Robotics_Facility 1 8521
Protoss_Shuttle 1 9357
Protoss_Robotics_Support_Bay 1 8661
Protoss_Reaver 2 11659
11659
