Protoss_Gateway 3 10302
Protoss_Assimilator 1 3307
Protoss_Cybernetics_Core 1 4285
Protoss_Dragoon 10 10611
Protoss_Robotics_Facility 1 7145
Protoss_Observatory 1 7277
Protoss_Observer 3 9669
Protoss_Nexus 1 10063
10611
