Protoss_Gateway 2 7970
Protoss_Assimilator 1 3419
Protoss_Cybernetics_Core 1 4575
Protoss_Dragoon 5 11181
Protoss_Robotics_Facility 1 6603
Protoss_Citadel_of_Adun 1 6858
Protoss_Observatory 1 6721
Protoss_Observer 1 7501
Protoss_Templar_Archives 1 8585
Protoss_Shuttle 1 8696
Protoss_Dark_Templar 2 9376
11181
