Protoss_Gateway 2 6989
Protoss_Assimilator 1 3155
Protoss_Cybernetics_Core 1 4405
Protoss_Dragoon 11 11117
Protoss_Robotics_Facility 1 8528
Protoss_Nexus 1 10319
Protoss_Observatory 1 9072
Protoss_Observer 1 9857
Protoss_Shuttle 1 10939
11117
