Protoss_Gateway 3 9661
Protoss_Assimilator 1 3240
Protoss_Cybernetics_Core 1 4352
Protoss_Dragoon 9 10735
Protoss_Robotics_Facility 1 7199
Protoss_Observatory 1 7325
Protoss_Nexus 1 9879
Protoss_Observer 2 8705
Protoss_Shuttle 1 10009
Protoss_Robotics_Support_Bay 1 10010
Protoss_Reaver 1 11677
11677
