Protoss_Gateway 3 9355
Protoss_Assimilator 2 6235
Protoss_Zealot 4 7047
Protoss_Nexus 1 7134
Protoss_Cybernetics_Core 1 7268
Protoss_Shield_Battery 1 7548
Protoss_Dragoon 6 11007
Protoss_Robotics_Facility 1 10783
11007
