Protoss_Gateway 2 9536
Protoss_Assimilator 2 8652
Protoss_Cybernetics_Core 1 4409
Protoss_Dragoon 9 10759
Protoss_Robotics_Facility 1 7681
Protoss_Nexus 1 9717
Protoss_Observatory 1 7892
Protoss_Citadel_of_Adun 1 9610
Protoss_Observer 3 10913
Protoss_Stargate 1 10865
Protoss_Templar_Archives 1 10799
10913
