Protoss_Gateway 2 7527
Protoss_Assimilator 2 10527
Protoss_Cybernetics_Core 1 4400
Protoss_Dragoon 10 10967
Protoss_Robotics_Facility 1 7751
Protoss_Observatory 1 7881
Protoss_Nexus 2 11467
Protoss_Observer 2 10657
11467
