Protoss_Nexus 1 5719
Protoss_Gateway 3 9570
Protoss_Assimilator 2 8863
Protoss_Cybernetics_Core 1 5851
Protoss_Zealot 2 10073
Protoss_Dragoon 9 9877
Protoss_Robotics_Facility 1 9273
Protoss_Shuttle 1 10247
Protoss_Robotics_Support_Bay 1 9853
10247
