Protoss_Gateway 3 11112
Protoss_Assimilator 2 10654
Protoss_Cybernetics_Core 1 4545
Protoss_Dragoon 11 11151
Protoss_Nexus 2 12030
Protoss_Robotics_Facility 1 8203
Protoss_Observatory 1 8517
Protoss_Observer 3 10732
12030
