Protoss_Assimilator 5 4955
Protoss_Gateway 2 6717
Protoss_Cybernetics_Core 1 5009
Protoss_Robotics_Facility 1 6633
Protoss_Dragoon 6 10507
Protoss_Zealot 2 8105
Protoss_Shuttle 1 7467
Protoss_Robotics_Support_Bay 1 7233
Protoss_Reaver 1 8757
Protoss_Citadel_of_Adun 1 9199
Protoss_Templar_Archives 1 10545
10545
