Protoss_Gateway 2 6168
Protoss_Assimilator 1 3543
Protoss_Zealot 1 4131
Protoss_Cybernetics_Core 1 4938
Protoss_Dragoon 9 11076
Protoss_Nexus 1 11935
Protoss_Stargate 1 11085
Protoss_Robotics_Facility 1 11644
11935
