Protoss_Gateway 2 6105
Protoss_Zealot 5 9615
Protoss_Assimilator 1 4152
Protoss_Cybernetics_Core 1 5343
Protoss_Dragoon 8 10623
Protoss_Robotics_Facility 1 8946
Protoss_Shuttle 1 9989
Protoss_Robotics_Support_Bay 1 9643
10623
