Protoss_Nexus 1 5721
Protoss_Gateway 3 7834
Protoss_Assimilator 2 9829
Protoss_Cybernetics_Core 1 5507
Protoss_Zealot 2 10425
Protoss_Dragoon 12 10983
Protoss_Robotics_Facility 1 10584
Protoss_Observatory 1 10715
10983
