Protoss_Gateway 2 10445
Protoss_Assimilator 1 3295
Protoss_Cybernetics_Core 1 4315
Protoss_Zealot 1 4165
Protoss_Dragoon 6 10445
Protoss_Robotics_Facility 1 7643
Protoss_Shuttle 1 8451
Protoss_Nexus 1 10263
Protoss_Robotics_Support_Bay 1 8368
Protoss_Reaver 1 9857
Protoss_Observatory 1 10375
10445
