Protoss_Gateway 2 6469
Protoss_Assimilator 1 3199
Protoss_Cybernetics_Core 1 4446
Protoss_Dragoon 9 10249
Protoss_Robotics_Facility 1 7439
Protoss_Shuttle 1 8239
Protoss_Robotics_Support_Bay 1 7732
Protoss_Reaver 1 9381
Protoss_Observatory 1 8835
Protoss_Scarab 4 9467
10249
