Protoss_Gateway 3 10369
Protoss_Assimilator 1 3406
Protoss_Zealot 1 3876
Protoss_Cybernetics_Core 1 4478
Protoss_Dragoon 11 11136
Protoss_Robotics_Facility 1 7574
Protoss_Observatory 1 7673
Protoss_Observer 4 10257
Protoss_Nexus 1 10903
Protoss_Shuttle 1 11146
11146
