Protoss_Gateway 2 8603
Protoss_Assimilator 1 3212
Protoss_Cybernetics_Core 1 4439
Protoss_Dragoon 9 10439
Protoss_Nexus 1 9079
Protoss_Robotics_Facility 1 9336
Protoss_Observatory 1 9589
Protoss_Observer 1 10359
10439
