Protoss_Gateway 2 7035
Protoss_Assimilator 1 3406
Protoss_Cybernetics_Core 1 4531
Protoss_Dragoon 7 11131
Protoss_Citadel_of_Adun 1 6840
Protoss_Templar_Archives 1 7823
Protoss_Zealot 2 7603
Protoss_Dark_Templar 4 9387
Protoss_Nexus 1 11457
11457
