Protoss_Gateway 1 1886
Protoss_Assimilator 1 2340
Protoss_Cybernetics_Core 1 2978
Protoss_Robotics_Facility 2 9605
Protoss_Dragoon 3 9545
Protoss_Shuttle 1 5485
Protoss_Robotics_Support_Bay 1 5949
Protoss_Zealot 2 6823
Protoss_Reaver 3 9185
Protoss_Nexus 1 7841
Protoss_Observatory 1 8249
Protoss_Scarab 11 9779
9779
