Protoss_Gateway 2 10036
Protoss_Assimilator 1 3135
Protoss_Zealot 1 3795
Protoss_Cybernetics_Core 1 4557
Protoss_Dragoon 9 10803
Protoss_Nexus 2 10848
Protoss_Robotics_Facility 1 10003
Protoss_Shuttle 1 10819
Protoss_Robotics_Support_Bay 1 10167
10848
