Protoss_Assimilator 2 3744
Protoss_Gateway 2 5187
Protoss_Zealot 2 5287
Protoss_Cybernetics_Core 1 5642
Protoss_Dragoon 7 8803
Protoss_Citadel_of_Adun 1 8779
Protoss_Templar_Archives 1 9819
Protoss_Nexus 1 11595
Protoss_Dark_Templar 2 10601
Protoss_Robotics_Facility 1 11821
11821
