Protoss_Gateway 3 9504
Protoss_Assimilator 1 3155
Protoss_Cybernetics_Core 1 4417
Protoss_Dragoon 10 10999
Protoss_Nexus 1 9295
Protoss_Robotics_Facility 1 9861
Protoss_Zealot 2 10001
Protoss_Observatory 1 10521
10999
