Protoss_Gateway 2 7169
Protoss_Assimilator 1 3288
Protoss_Cybernetics_Core 1 4368
Protoss_Dragoon 10 11007
Protoss_Robotics_Facility 1 7407
Protoss_Observatory 1 7681
Protoss_Nexus 1 9949
Protoss_Observer 2 9269
Protoss_Robotics_Support_Bay 1 9420
Protoss_Shuttle 1 10477
11007
