Protoss_Nexus 1 5497
Protoss_Gateway 2 5655
Protoss_Assimilator 2 7247
Protoss_Cybernetics_Core 1 5474
Protoss_Dragoon 10 9827
Protoss_Citadel_of_Adun 1 8274
Protoss_Templar_Archives 1 9874
Protoss_Stargate 1 10750
10750
