Protoss_Gateway 2 7771
Protoss_Assimilator 1 3135
Protoss_Cybernetics_Core 1 4255
Protoss_Dragoon 5 10385
Protoss_Citadel_of_Adun 2 6536
Protoss_Robotics_Facility 1 7923
Protoss_Templar_Archives 1 7695
Protoss_Zealot 1 7469
Protoss_Dark_Templar 3 9411
Protoss_Shuttle 1 8877
Protoss_Observatory 1 8494
Protoss_Nexus 1 11501
11501
