Protoss_Gateway 2 10295
Protoss_Assimilator 1 3273
Protoss_Zealot 2 7979
Protoss_Cybernetics_Core 1 5028
Protoss_Dragoon 7 11119
Protoss_Robotics_Facility 1 7578
Protoss_Shuttle 1 8395
Protoss_Robotics_Support_Bay 1 7831
Protoss_Reaver 1 9537
Protoss_Nexus 1 11247
Protoss_Observatory 1 9473
Protoss_Scarab 1 9386
Protoss_Observer 1 10579
11247
