Protoss_Gateway 2 6708
Protoss_Assimilator 1 3319
Protoss_Cybernetics_Core 1 4423
Protoss_Dragoon 9 10059
Protoss_Nexus 2 10245
Protoss_Robotics_Facility 1 10014
Protoss_Shuttle 1 10835
Protoss_Zealot 2 10597
Protoss_Observatory 1 10382
10835
