Protoss_Gateway 2 9753
Protoss_Assimilator 1 3389
Protoss_Cybernetics_Core 1 4668
Protoss_Zealot 1 4371
Protoss_Dragoon 6 10936
Protoss_Robotics_Facility 1 7608
Protoss_Observatory 1 7835
Protoss_Nexus 1 10039
Protoss_Observer 3 9913
Protoss_Shuttle 1 10995
10995
