Protoss_Gateway 3 8445
Protoss_Assimilator 1 2371
Protoss_Cybernetics_Core 1 2933
Protoss_Zealot 3 6645
Protoss_Robotics_Facility 1 4127
Protoss_Dragoon 4 9183
Protoss_Shuttle 1 5405
Protoss_Robotics_Support_Bay 1 5578
Protoss_Reaver 2 9151
Protoss_Observatory 1 7191
Protoss_Nexus 1 7619
Protoss_Observer 2 8549
Protoss_Scarab 6 9886
9886
