Protoss_Gateway 2 6568
Protoss_Assimilator 2 10867
Protoss_Cybernetics_Core 1 4327
Protoss_Dragoon 8 10447
Protoss_Nexus 2 12402
Protoss_Robotics_Facility 1 9435
Protoss_Citadel_of_Adun 1 9581
Protoss_Templar_Archives 1 10630
12402
