Protoss_Nexus 2 11487
Protoss_Gateway 2 5689
Protoss_Assimilator 1 4223
Protoss_Cybernetics_Core 1 5449
Protoss_Zealot 3 10705
Protoss_Dragoon 6 8699
Protoss_Robotics_Facility 1 8610
Protoss_Shuttle 1 9503
Protoss_Robotics_Support_Bay 1 9537
Protoss_Reaver 1 11025
11487
