Protoss_Gateway 1 3457
Protoss_Assimilator 1 3575
Protoss_Zealot 3 5315
Protoss_Cybernetics_Core 1 4957
Protoss_Dragoon 6 10993
Protoss_Robotics_Facility 1 7706
Protoss_Robotics_Support_Bay 1 7822
Protoss_Reaver 2 10655
10993
