Protoss_Gateway 2 7235
Protoss_Assimilator 1 3184
Protoss_Cybernetics_Core 1 4278
Protoss_Dragoon 6 8569
Protoss_Robotics_Facility 1 7548
Protoss_Observatory 1 7809
Protoss_Nexus 2 11547
Protoss_Observer 1 8589
Protoss_Shuttle 1 9759
Protoss_Robotics_Support_Bay 1 9619
Protoss_Reaver 1 11115
Protoss_Zealot 2 10621
11547
