Protoss_Nexus 1 5638
Protoss_Gateway 4 9813
Protoss_Assimilator 2 8780
Protoss_Cybernetics_Core 1 5685
Protoss_Zealot 5 10325
Protoss_Dragoon 9 11151
Protoss_Robotics_Facility 1 9015
Protoss_Observatory 1 9227
Protoss_Shuttle 1 10109
Protoss_Observer 1 10531
11151
