Protoss_Gateway 2 11164
Protoss_Assimilator 1 3446
Protoss_Cybernetics_Core 1 4631
Protoss_Dragoon 7 10541
Protoss_Robotics_Facility 1 7582
Protoss_Shuttle 1 8536
Protoss_Robotics_Support_Bay 1 7884
Protoss_Observatory 2 8934
Protoss_Reaver 1 9696
Protoss_Nexus 1 12148
Protoss_Observer 2 10953
12148
