Protoss_Gateway 3 10750
Protoss_Assimilator 1 3297
Protoss_Cybernetics_Core 1 4400
Protoss_Dragoon 6 10217
Protoss_Robotics_Facility 1 6247
Protoss_Shuttle 1 7315
Protoss_Zealot 2 8555
Protoss_Observatory 1 7389
Protoss_Observer 2 10429
Protoss_Robotics_Support_Bay 1 8042
Protoss_Reaver 1 9673
Protoss_Nexus 1 11469
11469
