Protoss_Gateway 2 8309
Protoss_Assimilator 3 10465
Protoss_Cybernetics_Core 1 4874
Protoss_Dragoon 10 11051
Protoss_Nexus 2 12567
Protoss_Robotics_Facility 1 8523
Protoss_Observatory 1 8793
Protoss_Observer 3 10913
12567
