Protoss_Gateway 4 10070
Protoss_Assimilator 1 3201
Protoss_Cybernetics_Core 1 4373
Protoss_Dragoon 12 11153
Protoss_Nexus 2 9949
Protoss_Robotics_Facility 1 9826
Protoss_Observatory 1 10320
11153
