Protoss_Gateway 2 9233
Protoss_Forge 1 3630
Protoss_Zealot 3 6120
Protoss_Assimilator 1 5999
Protoss_Photon_Cannon 3 10928
Protoss_Cybernetics_Core 1 7016
Protoss_Dragoon 2 10606
Protoss_Citadel_of_Adun 1 8683
Protoss_Robotics_Facility 1 9528
Protoss_Templar_Archives 1 10032
Protoss_Shuttle 1 10351
10928
