Protoss_Gateway 2 7423
Protoss_Assimilator 1 3352
Protoss_Cybernetics_Core 1 4417
Protoss_Dragoon 10 9999
Protoss_Robotics_Facility 1 7309
Protoss_Observatory 1 7682
Protoss_Observer 2 9341
Protoss_Nexus 2 12401
Protoss_Citadel_of_Adun 1 11421
12401
