Protoss_Gateway 2 5699
Protoss_Assimilator 2 8942
Protoss_Zealot 13 10631
Protoss_Forge 1 7924
Protoss_Nexus 1 10382
Protoss_Photon_Cannon 2 11085
Protoss_Cybernetics_Core 1 9957
Protoss_Robotics_Facility 1 11685
11685
