Protoss_Gateway 2 5873
Protoss_Assimilator 1 3290
Protoss_Cybernetics_Core 1 4351
Protoss_Dragoon 12 11195
Protoss_Robotics_Facility 1 7272
Protoss_Observatory 1 7578
Protoss_Nexus 1 10009
Protoss_Observer 2 9033
11195
