Protoss_Gateway 2 5831
Protoss_Assimilator 1 3286
Protoss_Cybernetics_Core 1 4291
Protoss_Dragoon 12 10991
Protoss_Nexus 1 9605
Protoss_Robotics_Facility 1 9492
Protoss_Observatory 1 9638
Protoss_Observer 1 10407
10991
