Protoss_Gateway 2 6535
Protoss_Assimilator 1 3313
Protoss_Cybernetics_Core 1 4485
Protoss_Dragoon 5 9703
Protoss_Citadel_of_Adun 1 6786
Protoss_Templar_Archives 1 7900
Protoss_Dark_Templar 4 10859
Protoss_Nexus 1 11029
11029
