Protoss_Gateway 2 7106
Protoss_Assimilator 1 3473
Protoss_Cybernetics_Core 1 4565
Protoss_Dragoon 5 10383
Protoss_Citadel_of_Adun 1 6610
Protoss_Templar_Archives 1 7599
Protoss_Zealot 2 7731
Protoss_Dark_Templar 4 9347
Protoss_Nexus 1 12551
12551
