Protoss_Gateway 2 7937
Protoss_Assimilator 2 10606
Protoss_Cybernetics_Core 1 4297
Protoss_Dragoon 8 10511
Protoss_Citadel_of_Adun 1 6875
Protoss_Templar_Archives 1 7879
Protoss_Dark_Templar 2 8687
Protoss_Nexus 2 12825
Protoss_Stargate 1 10702
12825
