Protoss_Gateway 3 10946
Protoss_Assimilator 1 3208
Protoss_Cybernetics_Core 1 4461
Protoss_Dragoon 8 10527
Protoss_Robotics_Facility 1 8131
Protoss_Shuttle 1 8995
Protoss_Robotics_Support_Bay 1 8796
Protoss_Nexus 1 11073
Protoss_Reaver 2 11603
11603
