Protoss_Gateway 2 9129
Protoss_Assimilator 1 3714
Protoss_Cybernetics_Core 1 5088
Protoss_Zealot 1 4859
Protoss_Dragoon 9 10965
Protoss_Nexus 2 12837
Protoss_Robotics_Facility 1 9125
Protoss_Observatory 1 9207
Protoss_Observer 2 10819
12837
