Protoss_Gateway 2 7315
Protoss_Assimilator 1 3310
Protoss_Cybernetics_Core 1 4351
Protoss_Dragoon 12 10935
Protoss_Robotics_Facility 1 7205
Protoss_Shuttle 1 8025
Protoss_Robotics_Support_Bay 1 7595
Protoss_Reaver 1 9259
Protoss_Scarab 8 9706
10935
