Protoss_Gateway 2 9653
Protoss_Assimilator 1 3382
Protoss_Cybernetics_Core 1 4390
Protoss_Dragoon 7 11195
Protoss_Robotics_Facility 1 7233
Protoss_Shuttle 1 8115
Protoss_Observatory 1 7580
Protoss_Robotics_Support_Bay 1 7679
Protoss_Zealot 2 8715
Protoss_Reaver 1 9426
Protoss_Observer 1 9900
Protoss_Scarab 5 9914
Protoss_Nexus 1 12453
12453
