Protoss_Gateway 4 11259
Protoss_Assimilator 1 3327
Protoss_Cybernetics_Core 1 4446
Protoss_Dragoon 8 10527
Protoss_Robotics_Facility 1 7229
Protoss_Observatory 1 7579
Protoss_Observer 1 8387
Protoss_Zealot 4 9399
Protoss_Shuttle 1 9489
Protoss_Nexus 1 11431
Protoss_Robotics_Support_Bay 1 10207
11431
