Protoss_Gateway 1 3321
Protoss_Assimilator 1 3263
Protoss_Cybernetics_Core 1 4399
Protoss_Dragoon 7 10483
Protoss_Robotics_Facility 1 7951
Protoss_Shuttle 1 8821
Protoss_Robotics_Support_Bay 1 8115
Protoss_Reaver 2 11015
Protoss_Nexus 2 12873
12873
