Protoss_Gateway 3 10103
Protoss_Assimilator 1 3401
Protoss_Cybernetics_Core 1 4583
Protoss_Dragoon 12 10729
Protoss_Nexus 1 9124
Protoss_Robotics_Facility 1 9772
Protoss_Shuttle 1 10935
Protoss_Observatory 1 10432
Protoss_Robotics_Support_Bay 1 10711
10935
