Protoss_Gateway 4 10998
Protoss_Assimilator 1 3318
Protoss_Cybernetics_Core 1 4314
Protoss_Dragoon 6 9561
Protoss_Nexus 2 10949
Protoss_Robotics_Facility 1 9231
Protoss_Observatory 1 9501
Protoss_Observer 1 10299
10998
