Protoss_Gateway 2 6633
Protoss_Zealot 1 3793
Protoss_Nexus 1 6712
Protoss_Assimilator 2 6917
Protoss_Cybernetics_Core 1 6391
Protoss_Dragoon 6 11035
Protoss_Citadel_of_Adun 1 8159
Protoss_Robotics_Facility 1 9615
Protoss_Templar_Archives 1 9237
Protoss_Dark_Templar 2 9979
Protoss_Stargate 1 10521
Protoss_Shuttle 1 10413
Protoss_Observatory 1 10529
11035
