Protoss_Gateway 3 10725
Protoss_Assimilator 1 3186
Protoss_Cybernetics_Core 1 4384
Protoss_Dragoon 10 10415
Protoss_Nexus 1 10327
Protoss_Robotics_Facility 1 10308
Protoss_Observatory 1 10431
10725
