Protoss_Gateway 4 11315
Protoss_Assimilator 1 3191
Protoss_Cybernetics_Core 1 4317
Protoss_Zealot 2 8503
Protoss_Dragoon 3 9500
Protoss_Robotics_Facility 1 7255
Protoss_Nexus 2 12093
Protoss_Shuttle 1 8199
Protoss_Robotics_Support_Bay 1 7947
Protoss_Reaver 1 9467
Protoss_Observatory 1 8776
Protoss_Observer 2 10810
Protoss_Scarab 2 9943
12093
