Protoss_Gateway 3 11175
Protoss_Assimilator 2 3619
Protoss_Zealot 2 8729
Protoss_Cybernetics_Core 1 5016
Protoss_Dragoon 5 10721
Protoss_Robotics_Facility 1 8006
Protoss_Shuttle 1 8837
Protoss_Robotics_Support_Bay 1 8437
Protoss_Reaver 1 9989
Protoss_Nexus 1 11919
Protoss_Observatory 1 10067
Protoss_Observer 1 10865
11919
