Protoss_Gateway 3 11259
Protoss_Assimilator 1 3431
Protoss_Cybernetics_Core 1 4414
Protoss_Dragoon 8 11195
Protoss_Robotics_Facility 1 6462
Protoss_Zealot 1 6539
Protoss_Shuttle 1 7321
Protoss_Observatory 1 7531
Protoss_Robotics_Support_Bay 1 7955
Protoss_Observer 2 10725
Protoss_Reaver 1 9837
Protoss_Nexus 1 11977
11977
