Protoss_Gateway 2 8817
Protoss_Assimilator 2 10813
Protoss_Cybernetics_Core 1 4579
Protoss_Zealot 1 4299
Protoss_Dragoon 8 10759
Protoss_Nexus 1 9200
Protoss_Robotics_Facility 1 8734
Protoss_Shuttle 1 10013
Protoss_Observatory 1 9439
Protoss_Robotics_Support_Bay 1 9977
Protoss_Observer 1 10435
10813
