Protoss_Gateway 3 8939
Protoss_Assimilator 2 10351
Protoss_Cybernetics_Core 1 4345
Protoss_Dragoon 9 9983
Protoss_Nexus 1 9276
Protoss_Robotics_Facility 1 8631
Protoss_Citadel_of_Adun 1 9222
Protoss_Observatory 1 8972
Protoss_Observer 1 9811
Protoss_Templar_Archives 1 10737
10737
