Protoss_Gateway 2 7385
Protoss_Assimilator 1 3188
Protoss_Cybernetics_Core 1 4343
Protoss_Dragoon 10 10199
Protoss_Robotics_Facility 1 7332
Protoss_Observatory 1 7483
Protoss_Observer 1 8297
Protoss_Nexus 1 10565
Protoss_Shuttle 1 10377
Protoss_Robotics_Support_Bay 1 9996
Protoss_Reaver 1 11519
11519
