Protoss_Nexus 1 5649
Protoss_Gateway 3 9499
Protoss_Assimilator 2 6938
Protoss_Cybernetics_Core 1 5641
Protoss_Zealot 1 5601
Protoss_Dragoon 14 11137
Protoss_Robotics_Facility 1 9206
Protoss_Observatory 1 9308
Protoss_Observer 2 10799
11137
