Protoss_Nexus 2 8805
Protoss_Gateway 5 11163
Protoss_Assimilator 2 7792
Protoss_Cybernetics_Core 1 5676
Protoss_Dragoon 7 10605
Protoss_Citadel_of_Adun 1 8101
Protoss_Templar_Archives 1 9093
Protoss_Stargate 1 10162
Protoss_Dark_Templar 2 9843
Protoss_Forge 1 10311
11163
