Protoss_Gateway 3 10380
Protoss_Zealot 1 3801
Protoss_Nexus 1 6144
Protoss_Assimilator 2 6583
Protoss_Cybernetics_Core 1 5751
Protoss_Dragoon 12 11123
Protoss_Robotics_Facility 1 8649
Protoss_Observatory 1 8867
Protoss_Observer 2 10239
11123
