Protoss_Gateway 3 11176
Protoss_Zealot 4 8315
Protoss_Assimilator 1 4083
Protoss_Cybernetics_Core 1 5560
Protoss_Dragoon 10 10627
Protoss_Nexus 1 10963
Protoss_Robotics_Facility 1 10678
11176
