Protoss_Gateway 2 5703
Protoss_Zealot 2 4329
Protoss_Assimilator 2 9473
Protoss_Cybernetics_Core 1 5271
Protoss_Dragoon 5 7775
Protoss_Nexus 1 10187
Protoss_Citadel_of_Adun 1 9063
Protoss_Robotics_Facility 1 9947
Protoss_Templar_Archives 1 10125
Protoss_Shuttle 1 10975
Protoss_Dark_Templar 2 10901
Protoss_Observatory 1 10619
10975
