Protoss_Gateway 2 8748
Protoss_Assimilator 1 2191
Protoss_Cybernetics_Core 1 2817
Protoss_Robotics_Facility 1 4075
Protoss_Dragoon 8 9783
Protoss_Shuttle 1 5359
Protoss_Robotics_Support_Bay 1 5740
Protoss_Reaver 2 8873
Protoss_Scarab 14 9621
Protoss_Observatory 1 8876
Protoss_Observer 1 9925
9925
