Protoss_Nexus 1 5603
Protoss_Gateway 4 11321
Protoss_Assimilator 2 9165
Protoss_Cybernetics_Core 1 5523
Protoss_Zealot 1 5655
Protoss_Dragoon 12 10977
Protoss_Robotics_Facility 1 9201
Protoss_Observatory 1 9321
Protoss_Observer 1 10093
11321
