Protoss_Gateway 3 11427
Protoss_Assimilator 2 4835
Protoss_Zealot 2 5233
Protoss_Cybernetics_Core 1 6215
Protoss_Dragoon 7 10419
Protoss_Nexus 1 10549
Protoss_Robotics_Facility 1 10415
Protoss_Observatory 1 10526
11427
