Protoss_Gateway 4 10598
Protoss_Assimilator 1 3320
Protoss_Cybernetics_Core 1 4431
Protoss_Dragoon 8 11075
Protoss_Nexus 2 10865
Protoss_Robotics_Facility 1 8645
Protoss_Observatory 1 8781
Protoss_Observer 3 10851
Protoss_Shuttle 1 11407
11407
