Protoss_Gateway 3 10524
Protoss_Assimilator 1 3314
Protoss_Cybernetics_Core 1 4423
Protoss_Dragoon 11 10881
Protoss_Robotics_Facility 1 6252
Protoss_Observatory 1 6435
Protoss_Observer 4 10767
Protoss_Nexus 1 9821
Protoss_Citadel_of_Adun 1 10879
10881
