Protoss_Gateway 2 7135
Protoss_Zealot 3 5173
Protoss_Assimilator 1 4001
Protoss_Cybernetics_Core 1 5400
Protoss_Dragoon 10 10917
Protoss_Robotics_Facility 1 9120
Protoss_Observatory 1 9325
Protoss_Nexus 1 12044
Protoss_Observer 2 10909
12044
