Protoss_Gateway 3 10866
Protoss_Assimilator 1 3328
Protoss_Cybernetics_Core 1 4689
Protoss_Dragoon 1 5471
Protoss_Citadel_of_Adun 1 5994
Protoss_Templar_Archives 1 7066
Protoss_Dark_Templar 9 11126
Protoss_Forge 1 8333
Protoss_Photon_Cannon 1 10493
11126
