Protoss_Gateway 3 9028
Protoss_Assimilator 1 3367
Protoss_Cybernetics_Core 1 4385
Protoss_Dragoon 11 10195
Protoss_Robotics_Facility 1 7327
Protoss_Observatory 1 7505
Protoss_Observer 1 8451
Protoss_Robotics_Support_Bay 1 10118
Protoss_Zealot 1 10569
Protoss_Shuttle 1 11069
11069
