Protoss_Gateway 4 11247
Protoss_Assimilator 1 3171
Protoss_Cybernetics_Core 1 4339
Protoss_Dragoon 11 10307
Protoss_Nexus 1 9887
Protoss_Robotics_Facility 1 10065
Protoss_Observatory 1 10197
11247
