Protoss_Gateway 2 7182
Protoss_Assimilator 2 10851
Protoss_Cybernetics_Core 1 4431
Protoss_Dragoon 8 9269
Protoss_Robotics_Facility 1 7403
Protoss_Observatory 1 7647
Protoss_Observer 2 9077
Protoss_Nexus 2 12283
Protoss_Citadel_of_Adun 1 10165
Protoss_Templar_Archives 1 11206
12283
