Protoss_Gateway 5 9678
Protoss_Assimilator 1 3405
Protoss_Cybernetics_Core 1 4563
Protoss_Dragoon 6 9976
Protoss_Nexus 1 9093
Protoss_Robotics_Facility 1 8923
Protoss_Observatory 1 9110
Protoss_Shuttle 1 10036
Protoss_Zealot 6 10646
10646
