Protoss_Gateway 2 9028
Protoss_Assimilator 1 3627
Protoss_Cybernetics_Core 1 4694
Protoss_Zealot 1 4406
Protoss_Dragoon 9 10939
Protoss_Robotics_Facility 1 7712
Protoss_Observatory 1 7843
Protoss_Observer 2 9641
Protoss_Nexus 1 12048
12048
