Protoss_Gateway 3 9408
Protoss_Assimilator 1 3468
Protoss_Cybernetics_Core 1 4523
Protoss_Dragoon 9 11121
Protoss_Robotics_Facility 1 6577
Protoss_Observatory 1 6714
Protoss_Observer 2 8156
Protoss_Nexus 1 12068
12068
