Protoss_Assimilator 2 3755
Protoss_Gateway 3 7843
Protoss_Zealot 2 9181
Protoss_Cybernetics_Core 1 5512
Protoss_Dragoon 6 10755
Protoss_Robotics_Facility 1 7647
Protoss_Shuttle 1 8447
Protoss_Robotics_Support_Bay 1 8239
Protoss_Reaver 1 9789
Protoss_Nexus 1 11743
Protoss_Observatory 1 9837
Protoss_Observer 1 10637
11743
