Protoss_Gateway 4 11111
Protoss_Assimilator 1 3443
Protoss_Cybernetics_Core 1 4483
Protoss_Dragoon 9 11009
Protoss_Robotics_Facility 1 7431
Protoss_Nexus 2 11452
Protoss_Observatory 1 7880
Protoss_Observer 4 10905
11452
