Protoss_Gateway 3 11278
Protoss_Assimilator 1 3216
Protoss_Cybernetics_Core 1 4365
Protoss_Dragoon 11 10633
Protoss_Robotics_Facility 1 8199
Protoss_Observatory 1 8331
Protoss_Observer 3 10697
Protoss_Nexus 1 11518
11518
