Protoss_Gateway 2 7857
Protoss_Assimilator 1 3392
Protoss_Cybernetics_Core 1 4687
Protoss_Dragoon 11 11018
Protoss_Robotics_Facility 1 7685
Protoss_Observatory 1 7876
Protoss_Observer 3 9955
Protoss_Nexus 1 11606
11606
