Protoss_Gateway 4 10724
Protoss_Assimilator 2 3663
Protoss_Cybernetics_Core 1 4801
Protoss_Dragoon 9 11069
Protoss_Nexus 1 10319
Protoss_Robotics_Facility 1 9778
Protoss_Shuttle 1 10599
Protoss_Observatory 1 10336
11069
