Protoss_Gateway 2 6037
Protoss_Assimilator 1 3368
Protoss_Cybernetics_Core 1 4406
Protoss_Dragoon 11 10625
Protoss_Robotics_Facility 1 8203
Protoss_Nexus 2 12127
Protoss_Observatory 1 8320
Protoss_Observer 2 9701
12127
