Protoss_Gateway 3 7383
Protoss_Assimilator 1 3477
Protoss_Cybernetics_Core 1 4903
Protoss_Dragoon 4 11176
Protoss_Citadel_of_Adun 1 6198
Protoss_Templar_Archives 1 7588
Protoss_Dark_Templar 6 10571
Protoss_Nexus 1 12078
12078
