Protoss_Gateway 2 8317
Protoss_Assimilator 2 9686
Protoss_Cybernetics_Core 1 4471
Protoss_Zealot 3 10517
Protoss_Dragoon 6 9099
Protoss_Nexus 1 9209
Protoss_Robotics_Facility 1 9081
Protoss_Citadel_of_Adun 1 9290
Protoss_Observatory 1 9251
Protoss_Templar_Archives 1 10302
Protoss_Observer 1 10037
Protoss_Stargate 1 11431
Protoss_Shuttle 1 11271
Protoss_Dark_Templar 2 11093
11431
