Protoss_Gateway 2 8565
Protoss_Assimilator 1 3589
Protoss_Cybernetics_Core 1 4668
Protoss_Zealot 2 9181
Protoss_Dragoon 4 8591
Protoss_Robotics_Facility 1 7935
Protoss_Citadel_of_Adun 1 8630
Protoss_Observatory 1 8033
Protoss_Observer 1 8811
Protoss_Templar_Archives 1 9873
Protoss_Shuttle 1 10566
Protoss_Nexus 1 12283
Protoss_Dark_Templar 2 10806
12283
