Protoss_Gateway 5 5860
Protoss_Assimilator 1 5625
Protoss_Cybernetics_Core 1 6852
Protoss_Zealot 2 6951
Protoss_Dragoon 8 10557
Protoss_Robotics_Facility 1 10514
Protoss_Shuttle 1 11409
11409
