Protoss_Gateway 4 9706
Protoss_Assimilator 1 3149
Protoss_Cybernetics_Core 1 4411
Protoss_Robotics_Facility 1 5898
Protoss_Dragoon 13 11041
Protoss_Observatory 1 6165
Protoss_Observer 4 10603
Protoss_Nexus 1 10009
11041
