Protoss_Gateway 3 10977
Protoss_Assimilator 1 3445
Protoss_Cybernetics_Core 1 4581
Protoss_Dragoon 8 10101
Protoss_Robotics_Facility 1 6528
Protoss_Observatory 1 6735
Protoss_Observer 1 7536
Protoss_Nexus 1 10371
Protoss_Shuttle 1 9611
Protoss_Citadel_of_Adun 1 10437
Protoss_Zealot 2 10613
10977
