Protoss_Gateway 3 9456
Protoss_Assimilator 1 3177
Protoss_Cybernetics_Core 1 4324
Protoss_Dragoon 10 10691
Protoss_Nexus 1 8996
Protoss_Robotics_Facility 1 8779
Protoss_Observatory 1 8973
Protoss_Observer 1 9863
Protoss_Zealot 2 10733
10733
