Protoss_Gateway 2 5122
Protoss_Assimilator 2 3452
Protoss_Cybernetics_Core 1 4640
Protoss_Dragoon 5 7391
Protoss_Citadel_of_Adun 1 7433
Protoss_Templar_Archives 1 8653
Protoss_Robotics_Facility 1 9577
Protoss_Dark_Templar 4 10739
Protoss_Shuttle 1 10413
Protoss_Nexus 1 12513
12513
