Protoss_Gateway 2 8765
Protoss_Assimilator 2 9756
Protoss_Cybernetics_Core 1 4665
Protoss_Zealot 1 4639
Protoss_Dragoon 6 9625
Protoss_Nexus 1 9319
Protoss_Robotics_Facility 1 8754
Protoss_Citadel_of_Adun 1 8455
Protoss_Templar_Archives 1 9465
Protoss_Observatory 1 8887
Protoss_Shuttle 1 10141
Protoss_Dark_Templar 2 10249
Protoss_Observer 1 10605
Protoss_Stargate 1 11578
11578
