Protoss_Gateway 3 8450
Protoss_Zealot 1 3803
Protoss_Nexus 1 6643
Protoss_Assimilator 2 6828
Protoss_Cybernetics_Core 1 5959
Protoss_Dragoon 9 10645
Protoss_Robotics_Facility 1 9090
Protoss_Observatory 1 9247
Protoss_Shuttle 1 10069
Protoss_Observer 1 10491
10645
