Protoss_Gateway 3 10419
Protoss_Assimilator 2 8993
Protoss_Cybernetics_Core 1 4433
Protoss_Nexus 1 7037
Protoss_Dragoon 10 9821
Protoss_Robotics_Facility 1 9191
Protoss_Observatory 1 9295
Protoss_Shuttle 1 10257
Protoss_Zealot 2 10333
Protoss_Observer 1 10679
10679
