Protoss_Nexus 1 5509
Protoss_Gateway 5 10944
Protoss_Assimilator 2 8150
Protoss_Cybernetics_Core 1 5390
Protoss_Zealot 3 10885
Protoss_Dragoon 12 10545
Protoss_Robotics_Facility 1 9694
Protoss_Citadel_of_Adun 1 10625
Protoss_Observatory 1 10003
Protoss_Observer 1 10843
10944
