Protoss_Gateway 2 7820
Protoss_Assimilator 1 3331
Protoss_Cybernetics_Core 1 4505
Protoss_Zealot 1 4289
Protoss_Dragoon 8 10975
Protoss_Citadel_of_Adun 1 7471
Protoss_Templar_Archives 1 8695
Protoss_Dark_Templar 4 10573
Protoss_Nexus 1 12425
Protoss_Robotics_Facility 1 11909
12425
