Protoss_Gateway 4 11059
Protoss_Assimilator 1 3410
Protoss_Cybernetics_Core 1 4572
Protoss_Dragoon 8 10167
Protoss_Robotics_Facility 1 7407
Protoss_Observatory 1 7529
Protoss_Observer 4 10189
Protoss_Nexus 2 11377
11377
