Protoss_Gateway 2 7919
Protoss_Assimilator 2 9722
Protoss_Cybernetics_Core 1 4559
Protoss_Dragoon 5 8725
Protoss_Nexus 1 8842
Protoss_Robotics_Facility 1 8773
Protoss_Shuttle 1 9575
Protoss_Robotics_Support_Bay 1 8936
Protoss_Observatory 1 9309
Protoss_Reaver 1 10717
Protoss_Zealot 4 10927
10927
