Protoss_Gateway 4 10980
Protoss_Assimilator 1 3241
Protoss_Cybernetics_Core 1 4339
Protoss_Zealot 1 4217
Protoss_Dragoon 7 10479
Protoss_Citadel_of_Adun 1 6261
Protoss_Templar_Archives 1 7269
Protoss_Dark_Templar 2 8223
Protoss_Nexus 1 10910
Protoss_Robotics_Facility 1 10979
10980
