Protoss_Gateway 2 7607
Protoss_Assimilator 1 3179
Protoss_Cybernetics_Core 1 4529
Protoss_Dragoon 8 11133
Protoss_Robotics_Facility 1 7453
Protoss_Zealot 5 8609
Protoss_Shuttle 1 8261
Protoss_Observatory 1 7675
Protoss_Observer 2 9583
Protoss_Nexus 1 11039
11133
