Protoss_Gateway 2 7575
Protoss_Assimilator 1 3295
Protoss_Cybernetics_Core 1 4629
Protoss_Dragoon 11 10727
Protoss_Robotics_Facility 1 7823
Protoss_Observatory 1 7978
Protoss_Observer 1 8745
Protoss_Citadel_of_Adun 1 10604
10727
