Protoss_Gateway 3 10612
Protoss_Nexus 1 6383
Protoss_Zealot 2 5587
Protoss_Assimilator 2 7672
Protoss_Cybernetics_Core 1 5816
Protoss_Dragoon 8 10397
Protoss_Stargate 2 11164
Protoss_Robotics_Facility 1 9758
Protoss_Citadel_of_Adun 1 9428
Protoss_Fleet_Beacon 1 10279
Protoss_Carrier 1 13207
13207
