Protoss_Gateway 2 10199
Protoss_Assimilator 1 3204
Protoss_Cybernetics_Core 1 4468
Protoss_Zealot 2 9413
Protoss_Dragoon 8 11018
Protoss_Robotics_Facility 1 7327
Protoss_Shuttle 1 8135
Protoss_Robotics_Support_Bay 1 8050
Protoss_Reaver 1 9539
Protoss_Nexus 1 11183
Protoss_Observatory 1 9565
Protoss_Observer 1 10413
11183
