Protoss_Assimilator 3 7737
Protoss_Gateway 2 7771
Protoss_Zealot 4 6717
Protoss_Nexus 2 12407
Protoss_Cybernetics_Core 1 6973
Protoss_Dragoon 7 10454
Protoss_Robotics_Facility 1 9934
Protoss_Observatory 1 10042
Protoss_Observer 1 10819
Protoss_Robotics_Support_Bay 1 10719
12407
