Protoss_Gateway 3 9512
Protoss_Assimilator 1 3126
Protoss_Cybernetics_Core 1 4368
Protoss_Zealot 1 4125
Protoss_Dragoon 11 11005
Protoss_Nexus 1 8957
Protoss_Robotics_Facility 1 8835
Protoss_Observatory 1 9087
Protoss_Observer 2 10527
11005
