Protoss_Nexus 1 5553
Protoss_Gateway 5 9443
Protoss_Assimilator 2 7815
Protoss_Cybernetics_Core 1 5612
Protoss_Dragoon 10 10281
Protoss_Robotics_Facility 1 9139
Protoss_Shuttle 1 10127
Protoss_Observatory 1 9455
Protoss_Observer 1 10549
Protoss_Zealot 4 10793
10793
