Protoss_Nexus 1 5601
Protoss_Gateway 3 10481
Protoss_Assimilator 2 7168
Protoss_Cybernetics_Core 1 5563
Protoss_Zealot 1 5575
Protoss_Dragoon 10 10817
Protoss_Robotics_Facility 1 9345
Protoss_Citadel_of_Adun 1 10115
Protoss_Observatory 1 9548
Protoss_Observer 1 10331
Protoss_Templar_Archives 1 11392
11392
