Protoss_Gateway 3 9512
Protoss_Assimilator 2 10608
Protoss_Cybernetics_Core 1 4327
Protoss_Dragoon 10 10399
Protoss_Robotics_Facility 1 7597
Protoss_Nexus 1 9787
Protoss_Observatory 1 7785
Protoss_Observer 3 10779
Protoss_Citadel_of_Adun 1 10950
10950
