Protoss_Nexus 1 5621
Protoss_Gateway 3 10006
Protoss_Assimilator 2 8142
Protoss_Cybernetics_Core 1 5659
Protoss_Zealot 1 5427
Protoss_Dragoon 7 9833
Protoss_Citadel_of_Adun 1 8233
Protoss_Templar_Archives 1 9221
Protoss_Robotics_Facility 1 10341
Protoss_Dark_Templar 4 10721
Protoss_Forge 1 10414
Protoss_Observatory 1 10611
10721
