Protoss_Gateway 2 10796
Protoss_Assimilator 2 3580
Protoss_Cybernetics_Core 1 4503
Protoss_Zealot 3 9027
Protoss_Dragoon 6 10235
Protoss_Robotics_Facility 1 7975
Protoss_Shuttle 1 9089
Protoss_Robotics_Support_Bay 1 8412
Protoss_Reaver 1 10231
Protoss_Observatory 1 10668
10796
