Protoss_Gateway 2 5971
Protoss_Assimilator 1 3213
Protoss_Cybernetics_Core 1 4425
Protoss_Zealot 1 4155
Protoss_Citadel_of_Adun 1 5677
Protoss_Templar_Archives 1 6667
Protoss_Dark_Templar 4 8209
Protoss_Nexus 2 10909
Protoss_Stargate 1 10291
10909
