Protoss_Gateway 6 10923
Protoss_Assimilator 1 3438
Protoss_Cybernetics_Core 1 4603
Protoss_Dragoon 8 9761
Protoss_Robotics_Facility 1 6504
Protoss_Observatory 1 6763
Protoss_Observer 4 10361
Protoss_Nexus 1 11228
11228
