Protoss_Gateway 4 10228
Protoss_Assimilator 1 3463
Protoss_Cybernetics_Core 1 4537
Protoss_Dragoon 11 11031
Protoss_Robotics_Facility 1 7513
Protoss_Observatory 1 7644
Protoss_Observer 2 9171
Protoss_Nexus 1 10778
11031
