Protoss_Nexus 1 5606
Protoss_Gateway 2 5890
Protoss_Assimilator 2 8951
Protoss_Zealot 3 9427
Protoss_Cybernetics_Core 1 5565
Protoss_Dragoon 7 9679
Protoss_Citadel_of_Adun 1 8095
Protoss_Templar_Archives 1 9386
Protoss_Forge 1 9521
Protoss_Dark_Templar 2 10433
Protoss_Photon_Cannon 1 10578
Protoss_Stargate 1 11209
11209
