Protoss_Nexus 1 5683
Protoss_Gateway 5 11156
Protoss_Assimilator 2 6762
Protoss_Zealot 1 5355
Protoss_Cybernetics_Core 1 5897
Protoss_Dragoon 13 11149
Protoss_Robotics_Facility 1 9084
Protoss_Observatory 1 9269
Protoss_Citadel_of_Adun 1 10371
Protoss_Observer 2 10775
11156
