Protoss_Nexus 3 12399
Protoss_Gateway 2 5312
Protoss_Assimilator 2 6550
Protoss_Cybernetics_Core 1 5641
Protoss_Dragoon 6 7945
Protoss_Citadel_of_Adun 1 8387
Protoss_Templar_Archives 1 9630
Protoss_Stargate 2 11673
Protoss_Dark_Templar 2 10519
Protoss_Arbiter_Tribunal 1 11356
12399
