Protoss_Gateway 4 11162
Protoss_Assimilator 1 3347
Protoss_Cybernetics_Core 1 4431
Protoss_Dragoon 8 11097
Protoss_Robotics_Facility 1 7378
Protoss_Observatory 1 7515
Protoss_Nexus 2 11441
Protoss_Observer 3 10399
11441
