Protoss_Gateway 4 11361
Protoss_Assimilator 1 3151
Protoss_Cybernetics_Core 1 4280
Protoss_Dragoon 8 10605
Protoss_Robotics_Facility 1 7526
Protoss_Observatory 1 7619
Protoss_Nexus 2 11145
Protoss_Observer 4 10355
11361
