Protoss_Gateway 2 9091
Protoss_Assimilator 2 9677
Protoss_Cybernetics_Core 1 4355
Protoss_Zealot 1 4179
Protoss_Dragoon 8 10171
Protoss_Nexus 1 9423
Protoss_Citadel_of_Adun 1 8667
Protoss_Templar_Archives 1 9763
Protoss_Robotics_Facility 1 10342
Protoss_Dark_Templar 2 10939
Protoss_Shuttle 1 11147
Protoss_Observatory 1 10672
11147
