Protoss_Gateway 2 7341
Protoss_Assimilator 1 3362
Protoss_Cybernetics_Core 1 4430
Protoss_Dragoon 8 9649
Protoss_Robotics_Facility 1 6865
Protoss_Robotics_Support_Bay 1 7049
Protoss_Shuttle 1 8003
Protoss_Observatory 1 7868
Protoss_Reaver 2 10799
Protoss_Observer 1 9477
Protoss_Scarab 1 8987
Protoss_Nexus 1 12792
12792
