Protoss_Gateway 2 7571
Protoss_Assimilator 1 3387
Protoss_Cybernetics_Core 1 4342
Protoss_Dragoon 8 10837
Protoss_Robotics_Facility 1 7587
Protoss_Observatory 1 7681
Protoss_Observer 2 10083
Protoss_Nexus 1 10575
Protoss_Shuttle 1 9661
Protoss_Robotics_Support_Bay 1 9446
Protoss_Reaver 1 11043
11043
