Protoss_Gateway 3 10678
Protoss_Assimilator 1 3183
Protoss_Cybernetics_Core 1 4269
Protoss_Dragoon 6 10659
Protoss_Robotics_Facility 1 7181
Protoss_Shuttle 1 7991
Protoss_Robotics_Support_Bay 1 7772
Protoss_Reaver 1 9513
Protoss_Zealot 2 10377
Protoss_Nexus 1 11035
Protoss_Observatory 1 9255
Protoss_Observer 2 10649
11035
