Protoss_Gateway 2 6881
Protoss_Zealot 2 4479
Protoss_Nexus 2 12523
Protoss_Assimilator 2 6745
Protoss_Cybernetics_Core 1 6321
Protoss_Dragoon 7 10181
Protoss_Robotics_Facility 1 8483
Protoss_Observatory 1 8609
Protoss_Shuttle 1 9851
Protoss_Observer 2 10001
Protoss_Robotics_Support_Bay 1 9314
Protoss_Reaver 1 11491
12523
