Protoss_Gateway 4 11236
Protoss_Assimilator 1 3365
Protoss_Cybernetics_Core 1 4353
Protoss_Dragoon 11 11199
Protoss_Nexus 1 8956
Protoss_Robotics_Facility 1 9059
Protoss_Observatory 1 9609
Protoss_Observer 1 10745
11236
