Protoss_Gateway 2 7724
Protoss_Assimilator 1 3551
Protoss_Cybernetics_Core 1 4521
Protoss_Zealot 5 9861
Protoss_Dragoon 6 8741
Protoss_Robotics_Facility 1 7677
Protoss_Robotics_Support_Bay 1 8358
Protoss_Shuttle 1 9535
Protoss_Reaver 1 11101
Protoss_Nexus 1 12565
12565
