Protoss_Gateway 2 9690
Protoss_Assimilator 1 2281
Protoss_Cybernetics_Core 1 2931
Protoss_Dragoon 7 9333
Protoss_Robotics_Facility 1 4433
Protoss_Shuttle 1 6045
Protoss_Zealot 1 6465
Protoss_Observatory 1 6489
Protoss_Observer 2 9267
Protoss_Robotics_Support_Bay 1 7178
Protoss_Reaver 1 7767
Protoss_Nexus 1 8971
Protoss_Scarab 2 9838
9838
