Protoss_Assimilator 2 3751
Protoss_Gateway 2 6541
Protoss_Cybernetics_Core 1 4752
Protoss_Zealot 1 4593
Protoss_Dragoon 8 9737
Protoss_Nexus 1 9899
Protoss_Citadel_of_Adun 1 9377
Protoss_Templar_Archives 1 10435
Protoss_Stargate 1 10895
Protoss_Dark_Templar 2 11181
11181
