Protoss_Gateway 3 10442
Protoss_Assimilator 2 10367
Protoss_Cybernetics_Core 1 4917
Protoss_Dragoon 10 10991
Protoss_Robotics_Facility 1 7662
Protoss_Observatory 1 7753
Protoss_Nexus 1 10034
Protoss_Observer 3 10767
10991
