Protoss_Gateway 4 10791
Protoss_Assimilator 1 3208
Protoss_Cybernetics_Core 1 4379
Protoss_Dragoon 9 11135
Protoss_Citadel_of_Adun 1 7202
Protoss_Nexus 1 10352
Protoss_Templar_Archives 1 9012
Protoss_Dark_Templar 2 9923
Protoss_Robotics_Facility 1 11138
11138
