Protoss_Gateway 3 10390
Protoss_Assimilator 1 3124
Protoss_Cybernetics_Core 1 4265
Protoss_Zealot 1 4059
Protoss_Dragoon 8 11145
Protoss_Robotics_Facility 1 6219
Protoss_Shuttle 1 7017
Protoss_Robotics_Support_Bay 1 6485
Protoss_Reaver 1 8159
Protoss_Nexus 1 10267
Protoss_Observatory 1 8437
Protoss_Observer 2 10083
Protoss_Scarab 7 9934
11145
