Protoss_Gateway 2 6716
Protoss_Assimilator 1 3382
Protoss_Cybernetics_Core 1 4539
Protoss_Dragoon 5 7741
Protoss_Robotics_Facility 1 7780
Protoss_Shuttle 1 8681
Protoss_Zealot 4 9115
Protoss_Observatory 1 8395
Protoss_Observer 3 10446
Protoss_Nexus 2 12121
12121
