Protoss_Nexus 2 10683
Protoss_Gateway 8 11305
Protoss_Assimilator 2 9942
Protoss_Cybernetics_Core 1 5549
Protoss_Dragoon 10 10197
Protoss_Robotics_Facility 1 9263
Protoss_Observatory 1 9450
Protoss_Observer 1 10277
11305
