Protoss_Gateway 3 10524
Protoss_Assimilator 1 3316
Protoss_Cybernetics_Core 1 4328
Protoss_Dragoon 12 10890
Protoss_Robotics_Facility 1 6356
Protoss_Observatory 1 6766
Protoss_Observer 5 10696
Protoss_Nexus 1 10593
10890
