Protoss_Nexus 1 5945
Protoss_Gateway 2 8119
Protoss_Forge 1 5316
Protoss_Zealot 2 6143
Protoss_Photon_Cannon 4 10228
Protoss_Assimilator 1 6843
Protoss_Cybernetics_Core 1 7693
Protoss_Dragoon 7 10803
10803
