Protoss_Gateway 3 8866
Protoss_Assimilator 1 3505
Protoss_Cybernetics_Core 1 4927
Protoss_Zealot 1 4783
Protoss_Dragoon 8 10907
Protoss_Robotics_Facility 1 7811
Protoss_Nexus 1 10043
Protoss_Observatory 1 8016
Protoss_Observer 1 8793
Protoss_Robotics_Support_Bay 1 8902
Protoss_Shuttle 1 10325
Protoss_Reaver 1 11549
11549
