Protoss_Gateway 5 11341
Protoss_Assimilator 2 3602
Protoss_Cybernetics_Core 1 4681
Protoss_Dragoon 7 10589
Protoss_Nexus 2 10636
Protoss_Robotics_Facility 1 10251
Protoss_Observatory 1 10363
11341
