Protoss_Gateway 1 3408
Protoss_Assimilator 1 3423
Protoss_Cybernetics_Core 1 4462
Protoss_Stargate 1 5708
Protoss_Dragoon 6 10873
Protoss_Scout 1 7186
Protoss_Robotics_Facility 1 9013
Protoss_Observatory 1 9281
Protoss_Nexus 1 11654
Protoss_Observer 2 10823
11654
