Protoss_Gateway 3 10524
Protoss_Assimilator 1 3167
Protoss_Cybernetics_Core 1 4338
Protoss_Dragoon 12 11035
Protoss_Robotics_Facility 1 7334
Protoss_Nexus 1 9074
Protoss_Observatory 1 7427
Protoss_Robotics_Support_Bay 1 8107
Protoss_Reaver 1 10173
Protoss_Observer 1 10505
11035
