Protoss_Gateway 2 6356
Protoss_Assimilator 1 3409
Protoss_Cybernetics_Core 1 4463
Protoss_Zealot 1 4211
Protoss_Dragoon 4 11116
Protoss_Citadel_of_Adun 1 7281
Protoss_Robotics_Facility 1 8668
Protoss_Templar_Archives 1 8292
Protoss_Dark_Templar 4 9813
Protoss_Shuttle 1 9476
Protoss_Forge 2 10240
Protoss_Observatory 1 10316
11116
