Protoss_Nexus 2 11607
Protoss_Gateway 2 5605
Protoss_Assimilator 2 7448
Protoss_Cybernetics_Core 1 5793
Protoss_Zealot 1 5733
Protoss_Dragoon 8 10393
Protoss_Robotics_Facility 1 8908
Protoss_Shuttle 1 9817
Protoss_Robotics_Support_Bay 1 9693
Protoss_Reaver 1 11241
11607
