Protoss_Gateway 2 7865
Protoss_Assimilator 1 3403
Protoss_Cybernetics_Core 1 4525
Protoss_Dragoon 10 10127
Protoss_Robotics_Facility 1 7830
Protoss_Observatory 1 7921
Protoss_Observer 2 9293
Protoss_Nexus 1 12262
Protoss_Shuttle 1 10903
Protoss_Zealot 2 10657
Protoss_Robotics_Support_Bay 1 10673
12262
