Protoss_Gateway 2 4013
Protoss_Zealot 10 7731
Protoss_Forge 1 4778
Protoss_Photon_Cannon 3 10561
Protoss_Assimilator 1 6036
Protoss_Cybernetics_Core 1 8855
Protoss_Robotics_Facility 1 10328
Protoss_Shuttle 1 11136
Protoss_Robotics_Support_Bay 1 10528
11136
