Protoss_Gateway 1 1907
Protoss_Assimilator 1 2271
Protoss_Cybernetics_Core 1 2937
Protoss_Zealot 2 6841
Protoss_Robotics_Facility 1 4172
Protoss_Dragoon 2 9701
Protoss_Shuttle 1 5485
Protoss_Robotics_Support_Bay 1 5753
Protoss_Reaver 1 6453
Protoss_Observatory 1 6634
Protoss_Observer 3 8774
Protoss_Nexus 1 7801
Protoss_Scarab 16 9682
9701
