Protoss_Gateway 2 4949
Protoss_Assimilator 1 3403
Protoss_Cybernetics_Core 1 4389
Protoss_Dragoon 5 10821
Protoss_Citadel_of_Adun 1 6825
Protoss_Robotics_Facility 1 7705
Protoss_Templar_Archives 1 7813
Protoss_Shuttle 1 8511
Protoss_Dark_Templar 4 9439
Protoss_Nexus 1 11892
11892
