Protoss_Gateway 4 11045
Protoss_Assimilator 1 3433
Protoss_Cybernetics_Core 1 4549
Protoss_Dragoon 7 10363
Protoss_Nexus 1 8942
Protoss_Robotics_Facility 1 8851
Protoss_Shuttle 1 9709
Protoss_Robotics_Support_Bay 1 9059
Protoss_Reaver 1 10946
11045
