Protoss_Nexus 2 10638
Protoss_Gateway 2 5757
Protoss_Assimilator 1 4425
Protoss_Cybernetics_Core 1 5605
Protoss_Zealot 3 10413
Protoss_Dragoon 6 9631
Protoss_Robotics_Facility 1 8217
Protoss_Robotics_Support_Bay 1 8332
Protoss_Shuttle 1 9357
Protoss_Observatory 1 9247
Protoss_Reaver 1 10499
Protoss_Air_Weapons_1 1 9825
Protoss_Observer 1 10831
10831
