Protoss_Nexus 2 11881
Protoss_Gateway 3 11374
Protoss_Assimilator 1 4423
Protoss_Cybernetics_Core 1 5887
Protoss_Zealot 1 5791
Protoss_Dragoon 10 10511
Protoss_Robotics_Facility 1 9095
Protoss_Observatory 1 10117
Protoss_Observer 1 10893
11881
