Protoss_Gateway 3 10202
Protoss_Assimilator 1 3283
Protoss_Cybernetics_Core 1 4372
Protoss_Dragoon 10 11031
Protoss_Robotics_Facility 1 6709
Protoss_Observatory 1 6804
Protoss_Observer 3 8893
Protoss_Nexus 1 10117
Protoss_Shuttle 1 10681
11031
