Protoss_Gateway 4 10943
Protoss_Assimilator 1 3338
Protoss_Cybernetics_Core 1 4834
Protoss_Dragoon 7 11171
Protoss_Citadel_of_Adun 1 6257
Protoss_Templar_Archives 1 7457
Protoss_Dark_Templar 2 8853
Protoss_Nexus 1 10244
Protoss_Robotics_Facility 1 10443
11171
