Protoss_Gateway 2 8774
Protoss_Assimilator 2 9792
Protoss_Cybernetics_Core 1 4620
Protoss_Dragoon 9 10345
Protoss_Robotics_Facility 1 7751
Protoss_Nexus 1 9881
Protoss_Observatory 1 7952
Protoss_Observer 2 10603
Protoss_Citadel_of_Adun 1 10762
10762
