Protoss_Nexus 1 5657
Protoss_Gateway 4 11167
Protoss_Assimilator 2 7460
Protoss_Cybernetics_Core 1 5533
Protoss_Zealot 1 5617
Protoss_Dragoon 10 10219
Protoss_Robotics_Facility 1 8811
Protoss_Shuttle 1 9801
Protoss_Robotics_Support_Bay 1 9282
Protoss_Reaver 1 10943
Protoss_Observatory 1 10473
11167
