Protoss_Gateway 2 8063
Protoss_Assimilator 1 3413
Protoss_Zealot 6 9339
Protoss_Cybernetics_Core 1 5183
Protoss_Dragoon 7 11093
Protoss_Robotics_Facility 1 8027
Protoss_Observatory 1 8135
Protoss_Shuttle 1 8895
Protoss_Observer 2 9919
Protoss_Nexus 1 12461
12461
