Protoss_Gateway 2 7306
Protoss_Assimilator 1 3463
Protoss_Cybernetics_Core 1 4593
Protoss_Dragoon 9 10301
Protoss_Robotics_Facility 1 7947
Protoss_Observatory 1 8038
Protoss_Observer 3 10211
Protoss_Nexus 1 11098
11098
