Protoss_Gateway 5 9971
Protoss_Zealot 2 4851
Protoss_Nexus 1 3725
Protoss_Assimilator 2 5413
Protoss_Cybernetics_Core 1 4633
Protoss_Dragoon 7 9603
Protoss_Robotics_Facility 1 6143
Protoss_Shuttle 1 7429
Protoss_Robotics_Support_Bay 1 7900
Protoss_Reaver 1 8429
Protoss_Observatory 1 8770
Protoss_Observer 1 9481
Protoss_Scarab 1 9987
9987
