Protoss_Gateway 3 11226
Protoss_Assimilator 1 3145
Protoss_Cybernetics_Core 1 4367
Protoss_Zealot 3 9437
Protoss_Dragoon 7 10463
Protoss_Nexus 1 8493
Protoss_Robotics_Facility 1 8328
Protoss_Shuttle 1 9173
Protoss_Robotics_Support_Bay 1 9031
Protoss_Reaver 1 10537
Protoss_Observatory 1 10250
11226
