Protoss_Gateway 2 4113
Protoss_Zealot 11 10016
Protoss_Assimilator 1 4942
Protoss_Forge 1 5432
Protoss_Photon_Cannon 2 6540
Protoss_Cybernetics_Core 1 7773
Protoss_Citadel_of_Adun 1 9022
Protoss_Dragoon 2 9086
Protoss_Templar_Archives 1 10116
Protoss_High_Templar 1 10886
10886
