Protoss_Gateway 3 11320
Protoss_Assimilator 2 9227
Protoss_Cybernetics_Core 1 4370
Protoss_Zealot 1 4115
Protoss_Dragoon 7 10893
Protoss_Citadel_of_Adun 1 6613
Protoss_Templar_Archives 1 7612
Protoss_Nexus 1 9945
Protoss_Dark_Templar 1 8487
Protoss_Robotics_Facility 1 9689
Protoss_Observatory 1 10182
Protoss_Stargate 1 11620
Protoss_Observer 1 10957
11620
