Protoss_Gateway 2 9950
Protoss_Assimilator 1 3129
Protoss_Cybernetics_Core 1 4367
Protoss_Dragoon 8 10901
Protoss_Robotics_Facility 1 7027
Protoss_Shuttle 1 7827
Protoss_Robotics_Support_Bay 1 7195
Protoss_Zealot 1 7443
Protoss_Reaver 2 10035
Protoss_Observatory 1 8413
Protoss_Scarab 8 9791
Protoss_Observer 1 10367
10901
