Protoss_Gateway 2 9691
Protoss_Assimilator 1 3360
Protoss_Cybernetics_Core 1 4308
Protoss_Zealot 2 9513
Protoss_Dragoon 8 11187
Protoss_Nexus 2 12645
Protoss_Robotics_Facility 1 7787
Protoss_Shuttle 1 8641
Protoss_Robotics_Support_Bay 1 8373
Protoss_Reaver 1 9861
Protoss_Observatory 1 9330
Protoss_Observer 2 10855
12645
