Protoss_Nexus 1 5633
Protoss_Gateway 2 5859
Protoss_Assimilator 2 7336
Protoss_Cybernetics_Core 1 5611
Protoss_Dragoon 6 9359
Protoss_Citadel_of_Adun 1 8106
Protoss_Robotics_Facility 1 9221
Protoss_Templar_Archives 1 9246
Protoss_Shuttle 1 10083
Protoss_Dark_Templar 2 10111
Protoss_Stargate 1 10891
Protoss_Observatory 1 9997
Protoss_Observer 1 10775
10891
