Protoss_Gateway 3 10389
Protoss_Assimilator 1 3420
Protoss_Cybernetics_Core 1 4359
Protoss_Dragoon 9 10631
Protoss_Nexus 1 9221
Protoss_Robotics_Facility 1 9624
Protoss_Observatory 1 9953
Protoss_Observer 1 10775
10775
