Protoss_Gateway 2 7700
Protoss_Assimilator 3 10881
Protoss_Cybernetics_Core 1 4649
Protoss_Zealot 1 4623
Protoss_Dragoon 6 9365
Protoss_Robotics_Facility 1 7710
Protoss_Observatory 1 7913
Protoss_Nexus 1 10527
Protoss_Observer 1 8879
Protoss_Shuttle 1 10027
Protoss_Robotics_Support_Bay 1 9479
Protoss_Reaver 1 11169
11169
