Protoss_Gateway 2 4880
Protoss_Assimilator 1 3158
Protoss_Cybernetics_Core 1 4261
Protoss_Dragoon 9 10901
Protoss_Citadel_of_Adun 1 7420
Protoss_Templar_Archives 1 8792
Protoss_Nexus 2 12090
Protoss_Dark_Templar 2 9633
12090
