Protoss_Nexus 2 10894
Protoss_Gateway 2 5997
Protoss_Assimilator 2 9761
Protoss_Cybernetics_Core 1 5807
Protoss_Zealot 1 5349
Protoss_Dragoon 8 10435
Protoss_Citadel_of_Adun 1 9805
Protoss_Robotics_Facility 1 10628
Protoss_Templar_Archives 1 11039
11039
