Protoss_Gateway 2 8605
Protoss_Assimilator 2 9721
Protoss_Cybernetics_Core 1 4355
Protoss_Zealot 1 4027
Protoss_Dragoon 7 9803
Protoss_Robotics_Facility 1 7249
Protoss_Observatory 1 7335
Protoss_Nexus 2 12809
Protoss_Observer 2 8867
Protoss_Citadel_of_Adun 1 9969
Protoss_Templar_Archives 1 10964
12809
