Protoss_Gateway 3 9765
Protoss_Assimilator 1 3257
Protoss_Cybernetics_Core 1 4335
Protoss_Dragoon 7 9169
Protoss_Nexus 1 9857
Protoss_Robotics_Facility 1 9471
Protoss_Shuttle 1 10305
Protoss_Robotics_Support_Bay 1 9914
Protoss_Reaver 1 11449
11449
