Protoss_Gateway 2 9814
Protoss_Assimilator 1 3366
Protoss_Cybernetics_Core 1 4396
Protoss_Zealot 2 9653
Protoss_Dragoon 6 10761
Protoss_Robotics_Facility 1 7569
Protoss_Shuttle 1 8375
Protoss_Nexus 1 10249
Protoss_Robotics_Support_Bay 1 8277
Protoss_Reaver 1 9895
Protoss_Observatory 1 9634
Protoss_Observer 1 10441
10761
