Protoss_Gateway 2 4899
Protoss_Assimilator 2 9826
Protoss_Cybernetics_Core 1 4344
Protoss_Dragoon 9 10659
Protoss_Nexus 1 9119
Protoss_Robotics_Facility 1 8769
Protoss_Observatory 1 9163
Protoss_Citadel_of_Adun 1 10203
Protoss_Observer 1 10361
Protoss_Templar_Archives 1 11379
Protoss_Stargate 1 11675
11675
