Protoss_Gateway 2 7930
Protoss_Assimilator 1 3481
Protoss_Cybernetics_Core 1 4623
Protoss_Dragoon 4 10471
Protoss_Robotics_Facility 1 6815
Protoss_Observatory 1 7047
Protoss_Robotics_Support_Bay 1 7599
Protoss_Observer 1 7876
Protoss_Shuttle 1 8971
Protoss_Reaver 1 10113
Protoss_Zealot 2 9406
10471
