Protoss_Gateway 2 6029
Protoss_Assimilator 1 3277
Protoss_Cybernetics_Core 1 4285
Protoss_Zealot 1 4149
Protoss_Dragoon 10 10611
Protoss_Nexus 1 10171
Protoss_Robotics_Facility 1 9757
Protoss_Shuttle 1 10555
Protoss_Observatory 1 9907
Protoss_Robotics_Support_Bay 1 10539
10611
