Protoss_Gateway 3 10288
Protoss_Assimilator 1 3447
Protoss_Cybernetics_Core 1 4507
Protoss_Dragoon 10 10466
Protoss_Robotics_Facility 1 7417
Protoss_Observatory 1 7538
Protoss_Observer 2 9081
Protoss_Nexus 1 11348
11348
