Protoss_Gateway 2 7453
Protoss_Assimilator 2 10581
Protoss_Cybernetics_Core 1 4328
Protoss_Dragoon 6 10935
Protoss_Citadel_of_Adun 1 6508
Protoss_Robotics_Facility 1 7590
Protoss_Templar_Archives 1 7557
Protoss_Zealot 1 7207
Protoss_Shuttle 1 8425
Protoss_Dark_Templar 2 8491
Protoss_Observatory 1 8290
Protoss_Observer 3 10747
Protoss_Nexus 1 11043
11043
