Protoss_Gateway 3 9966
Protoss_Assimilator 1 3553
Protoss_Cybernetics_Core 1 4588
Protoss_Dragoon 9 10926
Protoss_Zealot 5 10609
Protoss_Robotics_Facility 1 8188
Protoss_Observatory 1 8338
Protoss_Observer 1 9436
Protoss_Shuttle 1 10651
10926
