Protoss_Gateway 3 11310
Protoss_Assimilator 1 3579
Protoss_Cybernetics_Core 1 4723
Protoss_Dragoon 7 10211
Protoss_Citadel_of_Adun 1 6344
Protoss_Templar_Archives 1 7397
Protoss_Dark_Templar 2 8191
Protoss_Nexus 1 11148
Protoss_Robotics_Facility 1 10801
11310
