Protoss_Gateway 2 7798
Protoss_Assimilator 1 3304
Protoss_Cybernetics_Core 1 4427
Protoss_Dragoon 7 9391
Protoss_Robotics_Facility 1 7393
Protoss_Observatory 1 7601
Protoss_Observer 2 9007
Protoss_Nexus 1 10653
Protoss_Shuttle 1 10089
Protoss_Robotics_Support_Bay 1 9565
Protoss_Zealot 2 10447
Protoss_Reaver 1 11324
11324
