Protoss_Gateway 2 7612
Protoss_Assimilator 1 3213
Protoss_Cybernetics_Core 1 4402
Protoss_Dragoon 9 10975
Protoss_Robotics_Facility 1 7525
Protoss_Observatory 1 7787
Protoss_Observer 2 9277
Protoss_Robotics_Support_Bay 1 9127
Protoss_Nexus 1 11655
Protoss_Zealot 2 9975
Protoss_Shuttle 1 11155
11655
