Protoss_Gateway 2 7007
Protoss_Assimilator 1 3417
Protoss_Cybernetics_Core 1 4549
Protoss_Dragoon 8 11165
Protoss_Citadel_of_Adun 1 6541
Protoss_Templar_Archives 1 7535
Protoss_Nexus 1 9818
Protoss_Dark_Templar 3 9099
11165
