Protoss_Gateway 3 10095
Protoss_Assimilator 2 10565
Protoss_Cybernetics_Core 1 4357
Protoss_Dragoon 8 11045
Protoss_Robotics_Facility 1 7297
Protoss_Shuttle 1 8137
Protoss_Nexus 1 10097
Protoss_Robotics_Support_Bay 1 8150
Protoss_Reaver 1 9649
Protoss_Observatory 1 9066
Protoss_Observer 2 10623
11045
