Protoss_Gateway 3 11326
Protoss_Assimilator 1 3538
Protoss_Cybernetics_Core 1 4588
Protoss_Dragoon 7 9811
Protoss_Robotics_Facility 1 7695
Protoss_Observatory 1 7868
Protoss_Observer 2 9258
Protoss_Nexus 2 12669
12669
