Protoss_Gateway 3 10636
Protoss_Zealot 13 9793
Protoss_Forge 1 5191
Protoss_Photon_Cannon 3 7766
Protoss_Assimilator 1 8926
Protoss_Cybernetics_Core 1 9819
Protoss_Dragoon 2 10635
10636
