Protoss_Gateway 2 10605
Protoss_Assimilator 1 3269
Protoss_Cybernetics_Core 1 4406
Protoss_Dragoon 6 11007
Protoss_Robotics_Facility 1 6286
Protoss_Shuttle 1 7389
Protoss_Observatory 1 7015
Protoss_Observer 1 7811
Protoss_Robotics_Support_Bay 1 7848
Protoss_Zealot 2 9077
Protoss_Reaver 1 9403
Protoss_Nexus 1 11513
11513
