Protoss_Gateway 2 8827
Protoss_Assimilator 1 3463
Protoss_Cybernetics_Core 1 4721
Protoss_Zealot 1 4463
Protoss_Dragoon 9 10515
Protoss_Nexus 2 12625
Protoss_Robotics_Facility 1 8939
Protoss_Observatory 1 9100
Protoss_Observer 1 9971
12625
