Protoss_Nexus 2 10939
Protoss_Gateway 2 7469
Protoss_Assimilator 1 4427
Protoss_Cybernetics_Core 1 5653
Protoss_Dragoon 9 10735
Protoss_Robotics_Facility 1 7481
Protoss_Observatory 1 7613
Protoss_Observer 1 8655
Protoss_Shuttle 1 9357
10939
