Protoss_Gateway 2 7761
Protoss_Assimilator 1 3469
Protoss_Cybernetics_Core 1 4481
Protoss_Dragoon 8 10983
Protoss_Citadel_of_Adun 2 7254
Protoss_Nexus 1 9463
Protoss_Templar_Archives 1 8318
Protoss_Dark_Templar 2 9226
Protoss_Robotics_Facility 1 10281
10983
