Protoss_Gateway 2 10215
Protoss_Assimilator 1 3341
Protoss_Cybernetics_Core 1 4331
Protoss_Dragoon 8 11131
Protoss_Robotics_Facility 1 7219
Protoss_Shuttle 2 11381
Protoss_Robotics_Support_Bay 1 7624
Protoss_Zealot 2 8639
Protoss_Reaver 1 9434
Protoss_Nexus 1 11031
Protoss_Observatory 1 9168
Protoss_Observer 1 10255
Protoss_Scarab 2 9750
11381
