Protoss_Assimilator 2 10173
Protoss_Gateway 2 6190
Protoss_Cybernetics_Core 1 4765
Protoss_Robotics_Facility 1 6254
Protoss_Shuttle 1 7057
Protoss_Observatory 1 6689
Protoss_Dragoon 8 10087
Protoss_Observer 2 8223
Protoss_Nexus 1 11328
Protoss_Citadel_of_Adun 1 10725
Protoss_Zealot 2 10849
11328
