Protoss_Gateway 2 4894
Protoss_Assimilator 2 10760
Protoss_Cybernetics_Core 1 4337
Protoss_Dragoon 10 10081
Protoss_Nexus 1 9871
Protoss_Robotics_Facility 1 9817
Protoss_Observatory 1 9943
Protoss_Shuttle 1 10707
Protoss_Robotics_Support_Bay 1 10705
10760
