Protoss_Gateway 2 6586
Protoss_Assimilator 1 3282
Protoss_Cybernetics_Core 1 4509
Protoss_Dragoon 10 10893
Protoss_Nexus 1 8808
Protoss_Robotics_Facility 1 8702
Protoss_Shuttle 1 9515
Protoss_Robotics_Support_Bay 1 9225
Protoss_Reaver 1 10793
Protoss_Observatory 1 9897
10893
