Protoss_Gateway 1 3721
Protoss_Assimilator 1 3585
Protoss_Cybernetics_Core 1 4838
Protoss_Dragoon 5 8675
Protoss_Robotics_Facility 1 8273
Protoss_Shuttle 1 9256
Protoss_Robotics_Support_Bay 1 8773
Protoss_Zealot 2 10446
Protoss_Reaver 2 11453
11453
