Protoss_Gateway 2 7224
Protoss_Assimilator 2 10112
Protoss_Cybernetics_Core 1 4395
Protoss_Dragoon 12 10667
Protoss_Nexus 1 9539
Protoss_Robotics_Facility 1 9484
Protoss_Observatory 1 9619
Protoss_Observer 1 10395
Protoss_Citadel_of_Adun 1 11373
11373
