Protoss_Gateway 2 7178
Protoss_Assimilator 1 3122
Protoss_Cybernetics_Core 1 4251
Protoss_Dragoon 7 11107
Protoss_Citadel_of_Adun 1 6425
Protoss_Robotics_Facility 1 7160
Protoss_Templar_Archives 1 7479
Protoss_Shuttle 1 8065
Protoss_Dark_Templar 3 8973
Protoss_Nexus 1 11091
Protoss_Observatory 1 10065
11107
