Protoss_Gateway 2 5236
Protoss_Assimilator 1 3419
Protoss_Cybernetics_Core 1 4521
Protoss_Dragoon 10 9703
Protoss_Robotics_Facility 1 8230
Protoss_Shuttle 1 9255
Protoss_Robotics_Support_Bay 1 8799
Protoss_Reaver 1 10407
Protoss_Zealot 2 10215
10407
