Protoss_Nexus 2 12309
Protoss_Gateway 3 8996
Protoss_Assimilator 2 7907
Protoss_Zealot 1 4971
Protoss_Cybernetics_Core 1 5603
Protoss_Dragoon 13 10819
Protoss_Robotics_Facility 1 10409
12309
