Protoss_Gateway 3 11440
Protoss_Assimilator 1 3583
Protoss_Cybernetics_Core 1 4508
Protoss_Dragoon 3 7101
Protoss_Citadel_of_Adun 2 6998
Protoss_Templar_Archives 1 8066
Protoss_Dark_Templar 6 10691
Protoss_Nexus 1 11958
11958
