Protoss_Gateway 1 1921
Protoss_Assimilator 1 2382
Protoss_Cybernetics_Core 1 2993
Protoss_Dragoon 5 9203
Protoss_Robotics_Facility 1 5636
Protoss_Zealot 2 7413
Protoss_Shuttle 1 6955
Protoss_Robotics_Support_Bay 1 7350
Protoss_Reaver 1 7897
Protoss_Nexus 1 8783
Protoss_Observatory 1 8841
Protoss_Scarab 3 9451
9451
