Protoss_Gateway 2 9075
Protoss_Assimilator 2 9590
Protoss_Cybernetics_Core 1 4367
Protoss_Zealot 1 4063
Protoss_Dragoon 10 11163
Protoss_Robotics_Facility 1 7380
Protoss_Observatory 1 7557
Protoss_Nexus 1 9927
Protoss_Observer 4 10883
Protoss_Citadel_of_Adun 1 9979
Protoss_Stargate 1 11347
11347
