Protoss_Gateway 4 10814
Protoss_Assimilator 1 3285
Protoss_Cybernetics_Core 1 4376
Protoss_Dragoon 6 10659
Protoss_Citadel_of_Adun 1 6492
Protoss_Templar_Archives 1 7521
Protoss_Nexus 1 9509
Protoss_Dark_Templar 1 8277
Protoss_Robotics_Facility 1 9144
Protoss_Observatory 1 9710
Protoss_Observer 1 10682
10814
