Protoss_Nexus 1 5681
Protoss_Gateway 2 5814
Protoss_Assimilator 1 4496
Protoss_Cybernetics_Core 1 5697
Protoss_Zealot 2 9797
Protoss_Dragoon 8 10699
Protoss_Robotics_Facility 1 8507
Protoss_Observatory 1 8821
Protoss_Observer 2 10439
10699
