Protoss_Gateway 2 7861
Protoss_Assimilator 2 10421
Protoss_Cybernetics_Core 1 4295
Protoss_Dragoon 9 9735
Protoss_Nexus 2 8847
Protoss_Robotics_Facility 1 8877
Protoss_Observatory 1 9266
Protoss_Shuttle 1 10103
Protoss_Observer 1 10525
Protoss_Robotics_Support_Bay 1 10345
Protoss_Zealot 2 10787
Protoss_Citadel_of_Adun 1 11408
11408
