Protoss_Nexus 1 5518
Protoss_Gateway 2 5783
Protoss_Assimilator 1 4303
Protoss_Cybernetics_Core 1 5495
Protoss_Zealot 2 10251
Protoss_Dragoon 10 10497
Protoss_Robotics_Facility 1 8737
Protoss_Shuttle 1 9611
Protoss_Robotics_Support_Bay 1 9031
Protoss_Reaver 1 10753
Protoss_Observatory 1 10126
10753
