Protoss_Gateway 2 5274
Protoss_Assimilator 1 3411
Protoss_Cybernetics_Core 1 4509
Protoss_Dragoon 6 8579
Protoss_Citadel_of_Adun 1 7091
Protoss_Templar_Archives 1 8285
Protoss_Zealot 1 8327
Protoss_Dark_Templar 4 10565
Protoss_Nexus 2 12713
12713
