Protoss_Gateway 2 4757
Protoss_Assimilator 2 8937
Protoss_Cybernetics_Core 1 4281
Protoss_Dragoon 4 6473
Protoss_Nexus 1 9555
Protoss_Citadel_of_Adun 1 8227
Protoss_Robotics_Facility 1 9351
Protoss_Templar_Archives 1 9235
Protoss_Shuttle 1 10279
Protoss_Dark_Templar 4 10891
Protoss_Stargate 1 11050
11050
