Protoss_Gateway 3 9744
Protoss_Assimilator 1 3532
Protoss_Cybernetics_Core 1 4742
Protoss_Robotics_Facility 1 6261
Protoss_Dragoon 9 10767
Protoss_Shuttle 2 8207
Protoss_Nexus 1 10193
Protoss_Observatory 1 8577
Protoss_Observer 1 10569
10767
