Protoss_Assimilator 1 2649
Protoss_Gateway 3 11161
Protoss_Cybernetics_Core 1 4563
Protoss_Dragoon 6 11145
Protoss_Citadel_of_Adun 1 6357
Protoss_Robotics_Facility 1 7523
Protoss_Templar_Archives 1 7715
Protoss_Shuttle 1 8499
Protoss_Dark_Templar 4 9641
Protoss_Nexus 1 11012
11161
