Protoss_Gateway 2 7299
Protoss_Assimilator 1 3216
Protoss_Cybernetics_Core 1 4352
Protoss_Zealot 1 4115
Protoss_Dragoon 4 10445
Protoss_Citadel_of_Adun 1 6541
Protoss_Robotics_Facility 1 7598
Protoss_Templar_Archives 1 7525
Protoss_Shuttle 2 11339
Protoss_Dark_Templar 2 8391
Protoss_Observatory 1 8632
Protoss_Nexus 1 11193
Protoss_Observer 2 10021
Protoss_Robotics_Support_Bay 1 10661
11339
