Protoss_Gateway 3 11428
Protoss_Assimilator 1 3333
Protoss_Cybernetics_Core 1 4548
Protoss_Dragoon 9 10818
Protoss_Robotics_Facility 1 6700
Protoss_Zealot 1 7018
Protoss_Shuttle 1 7511
Protoss_Robotics_Support_Bay 1 6993
Protoss_Reaver 1 8653
Protoss_Observatory 1 9361
Protoss_Observer 2 10748
Protoss_Scarab 1 9799
11428
