Protoss_Gateway 2 7021
Protoss_Assimilator 1 3454
Protoss_Cybernetics_Core 1 4665
Protoss_Dragoon 5 8281
Protoss_Robotics_Facility 1 8508
Protoss_Citadel_of_Adun 1 9088
Protoss_Observatory 1 8656
Protoss_Zealot 7 10606
Protoss_Observer 2 10108
10606
