Protoss_Gateway 6 10836
Protoss_Assimilator 1 3607
Protoss_Cybernetics_Core 1 4417
Protoss_Dragoon 8 11171
Protoss_Nexus 2 9341
Protoss_Robotics_Facility 1 9421
Protoss_Observatory 1 9813
Protoss_Observer 1 10585
11171
