Protoss_Nexus 2 11883
Protoss_Gateway 4 10938
Protoss_Assimilator 1 4238
Protoss_Cybernetics_Core 1 5431
Protoss_Zealot 3 10185
Protoss_Dragoon 12 11159
Protoss_Robotics_Facility 1 9199
Protoss_Observatory 1 9371
Protoss_Observer 2 10929
11883
