Protoss_Gateway 3 8650
Protoss_Assimilator 1 3528
Protoss_Cybernetics_Core 1 4633
Protoss_Dragoon 3 7286
Protoss_Robotics_Facility 1 7667
Protoss_Nexus 1 9532
Protoss_Observatory 1 8181
Protoss_Citadel_of_Adun 1 9228
Protoss_Observer 2 10436
Protoss_Zealot 7 10906
10906
