Protoss_Nexus 3 11331
Protoss_Gateway 2 5750
Protoss_Assimilator 1 4223
Protoss_Cybernetics_Core 1 5513
Protoss_Zealot 1 5445
Protoss_Dragoon 6 10133
Protoss_Robotics_Facility 1 9677
Protoss_Observatory 1 9945
Protoss_Citadel_of_Adun 1 10999
Protoss_Observer 1 10729
11331
