Protoss_Nexus 2 9783
Protoss_Gateway 3 11270
Protoss_Assimilator 2 9083
Protoss_Cybernetics_Core 1 5565
Protoss_Dragoon 10 10421
Protoss_Robotics_Facility 1 9523
Protoss_Citadel_of_Adun 1 9404
Protoss_Shuttle 1 10547
Protoss_Observatory 1 10447
11270
