Protoss_Nexus 1 5592
Protoss_Gateway 2 9492
Protoss_Assimilator 2 9183
Protoss_Cybernetics_Core 1 5662
Protoss_Zealot 1 5267
Protoss_Dragoon 8 11181
Protoss_Robotics_Facility 1 10351
Protoss_Observatory 1 10445
11181
