Protoss_Gateway 2 9160
Protoss_Assimilator 2 9486
Protoss_Cybernetics_Core 1 4353
Protoss_Zealot 1 4213
Protoss_Dragoon 10 10973
Protoss_Nexus 1 9144
Protoss_Robotics_Facility 1 9365
Protoss_Citadel_of_Adun 1 9411
Protoss_Observatory 1 9471
Protoss_Observer 1 10261
Protoss_Templar_Archives 1 10867
10973
