Protoss_Gateway 5 10949
Protoss_Assimilator 1 3129
Protoss_Cybernetics_Core 1 4253
Protoss_Zealot 1 3923
Protoss_Dragoon 10 11195
Protoss_Nexus 2 10630
Protoss_Robotics_Facility 1 10799
11195
