Protoss_Gateway 3 10741
Protoss_Assimilator 1 3488
Protoss_Zealot 2 4579
Protoss_Cybernetics_Core 1 5465
Protoss_Dragoon 5 9909
Protoss_Robotics_Facility 1 7941
Protoss_Nexus 1 9401
Protoss_Shuttle 1 8747
Protoss_Robotics_Support_Bay 1 8153
Protoss_Reaver 1 9909
Protoss_Observatory 1 10205
Protoss_Scarab 2 9893
10741
