Protoss_Gateway 2 7883
Protoss_Assimilator 1 3176
Protoss_Cybernetics_Core 1 4297
Protoss_Dragoon 10 10629
Protoss_Nexus 1 8954
Protoss_Robotics_Facility 1 9334
Protoss_Zealot 1 8860
Protoss_Shuttle 1 10595
Protoss_Robotics_Support_Bay 1 10006
10629
