Protoss_Nexus 1 5530
Protoss_Gateway 2 5693
Protoss_Assimilator 1 4323
Protoss_Cybernetics_Core 1 5645
Protoss_Zealot 1 5621
Protoss_Dragoon 8 10431
Protoss_Robotics_Facility 1 9311
Protoss_Shuttle 1 10141
Protoss_Robotics_Support_Bay 1 9481
Protoss_Reaver 1 11283
11283
