Protoss_Nexus 1 5599
Protoss_Gateway 3 9399
Protoss_Assimilator 2 7204
Protoss_Cybernetics_Core 1 5623
Protoss_Dragoon 5 11121
Protoss_Citadel_of_Adun 1 7775
Protoss_Forge 1 7824
Protoss_Templar_Archives 1 8844
Protoss_Robotics_Facility 1 9427
Protoss_Photon_Cannon 2 9230
Protoss_Shuttle 1 10233
Protoss_Stargate 1 10530
Protoss_Dark_Templar 3 10205
Protoss_Observatory 1 10251
11121
