Protoss_Gateway 3 8923
Protoss_Assimilator 1 3293
Protoss_Cybernetics_Core 1 4293
Protoss_Zealot 1 4053
Protoss_Dragoon 12 10661
Protoss_Nexus 1 9037
Protoss_Robotics_Facility 1 8720
Protoss_Observatory 1 8939
Protoss_Observer 3 10954
10954
