Protoss_Assimilator 2 3565
Protoss_Gateway 1 3653
Protoss_Cybernetics_Core 1 4722
Protoss_Zealot 3 10865
Protoss_Dragoon 5 9079
Protoss_Robotics_Facility 1 7633
Protoss_Observatory 1 7719
Protoss_Observer 1 8511
Protoss_Nexus 1 10587
Protoss_Shuttle 1 9699
Protoss_Robotics_Support_Bay 1 9290
Protoss_Reaver 1 10873
10873
