Protoss_Gateway 3 10644
Protoss_Assimilator 1 3183
Protoss_Cybernetics_Core 1 4329
Protoss_Dragoon 10 11187
Protoss_Nexus 1 9603
Protoss_Robotics_Facility 1 9921
Protoss_Shuttle 1 10835
Protoss_Robotics_Support_Bay 1 10598
11187
