Protoss_Gateway 1 1823
Protoss_Assimilator 1 2335
Protoss_Cybernetics_Core 1 2840
Protoss_Dragoon 9 9937
Protoss_Robotics_Facility 1 5617
Protoss_Shuttle 1 6957
Protoss_Robotics_Support_Bay 1 7011
Protoss_Reaver 1 7883
Protoss_Observatory 1 8473
Protoss_Nexus 2 9897
Protoss_Observer 2 9985
Protoss_Scarab 2 9718
9985
