Protoss_Gateway 2 4854
Protoss_Assimilator 1 3330
Protoss_Cybernetics_Core 1 4431
Protoss_Dragoon 6 8759
Protoss_Nexus 2 12855
Protoss_Robotics_Facility 1 8411
Protoss_Shuttle 1 9217
Protoss_Robotics_Support_Bay 1 8957
Protoss_Reaver 1 10539
Protoss_Observatory 1 9967
Protoss_Zealot 2 10373
Protoss_Observer 1 10871
12855
