Protoss_Gateway 2 4833
Protoss_Assimilator 1 3202
Protoss_Cybernetics_Core 1 4309
Protoss_Dragoon 6 7867
Protoss_Citadel_of_Adun 1 6504
Protoss_Zealot 1 6403
Protoss_Templar_Archives 1 7670
Protoss_Dark_Templar 2 8709
Protoss_Nexus 2 12351
Protoss_Robotics_Facility 1 11742
12351
