Protoss_Gateway 2 9427
Protoss_Zealot 6 7480
Protoss_Nexus 2 12699
Protoss_Assimilator 2 9076
Protoss_Cybernetics_Core 1 7305
Protoss_Forge 1 7470
Protoss_Citadel_of_Adun 1 8436
Protoss_Dragoon 2 9511
Protoss_Templar_Archives 1 9531
Protoss_Photon_Cannon 1 9961
Protoss_Dark_Templar 3 11183
Protoss_Stargate 1 11030
12699
