Protoss_Nexus 1 5493
Protoss_Gateway 2 5703
Protoss_Assimilator 2 7929
Protoss_Cybernetics_Core 1 5507
Protoss_Zealot 2 10849
Protoss_Dragoon 11 11101
Protoss_Stargate 2 10209
Protoss_Fleet_Beacon 1 9749
Protoss_Carrier 1 12877
12877
