Protoss_Gateway 2 6035
Protoss_Assimilator 1 3523
Protoss_Cybernetics_Core 1 4690
Protoss_Dragoon 9 10621
Protoss_Robotics_Facility 1 8891
Protoss_Observatory 1 9028
Protoss_Observer 1 9876
Protoss_Citadel_of_Adun 1 11023
Protoss_Shuttle 1 11176
Protoss_Zealot 2 10751
11176
