Protoss_Gateway 1 3588
Protoss_Assimilator 1 3593
Protoss_Cybernetics_Core 1 4840
Protoss_Dragoon 5 9701
Protoss_Robotics_Facility 1 7948
Protoss_Shuttle 1 8761
Protoss_Robotics_Support_Bay 1 8068
Protoss_Zealot 2 10213
Protoss_Reaver 1 9903
Protoss_Observatory 1 9926
Protoss_Scarab 4 9953
10213
