Protoss_Gateway 3 8867
Protoss_Zealot 4 5944
Protoss_Assimilator 1 4619
Protoss_Cybernetics_Core 1 6147
Protoss_Dragoon 10 11093
Protoss_Robotics_Facility 1 9854
Protoss_Observatory 1 9941
Protoss_Observer 1 10711
11093
