Protoss_Gateway 2 7831
Protoss_Assimilator 1 2237
Protoss_Cybernetics_Core 1 2941
Protoss_Dragoon 8 9701
Protoss_Robotics_Facility 1 5333
Protoss_Shuttle 1 6643
Protoss_Robotics_Support_Bay 1 6771
Protoss_Observatory 1 6967
Protoss_Reaver 2 9299
Protoss_Nexus 1 8489
Protoss_Observer 1 8607
Protoss_Scarab 1 8842
9701
