Protoss_Gateway 3 9615
Protoss_Assimilator 2 9680
Protoss_Cybernetics_Core 1 4233
Protoss_Dragoon 10 10521
Protoss_Nexus 1 8579
Protoss_Robotics_Facility 1 7963
Protoss_Observatory 1 8078
Protoss_Observer 2 9453
Protoss_Citadel_of_Adun 1 11071
11071
