Protoss_Gateway 2 9711
Protoss_Assimilator 2 9472
Protoss_Cybernetics_Core 1 4301
Protoss_Dragoon 9 10615
Protoss_Robotics_Facility 1 7406
Protoss_Observatory 1 7532
Protoss_Nexus 1 10279
Protoss_Observer 2 9259
Protoss_Citadel_of_Adun 1 9430
10615
