Protoss_Gateway 3 10416
Protoss_Assimilator 1 3468
Protoss_Cybernetics_Core 1 4608
Protoss_Dragoon 8 10761
Protoss_Robotics_Facility 1 7478
Protoss_Shuttle 1 8406
Protoss_Robotics_Support_Bay 1 7773
Protoss_Reaver 1 9621
Protoss_Scarab 8 9907
10761
