Protoss_Gateway 3 9147
Protoss_Assimilator 2 9552
Protoss_Cybernetics_Core 1 4438
Protoss_Dragoon 4 8927
Protoss_Robotics_Facility 1 7195
Protoss_Nexus 2 12051
Protoss_Observatory 1 7279
Protoss_Observer 3 9523
Protoss_Citadel_of_Adun 1 9636
Protoss_Stargate 1 11302
Protoss_Templar_Archives 1 11086
12051
