Protoss_Gateway 2 9329
Protoss_Assimilator 1 3361
Protoss_Zealot 3 5164
Protoss_Cybernetics_Core 1 5293
Protoss_Dragoon 7 10433
Protoss_Nexus 1 9591
Protoss_Robotics_Facility 1 9133
Protoss_Shuttle 1 9945
Protoss_Robotics_Support_Bay 1 9758
Protoss_Reaver 1 11277
Protoss_Observatory 1 10331
11277
