Protoss_Assimilator 2 3639
Protoss_Gateway 2 10721
Protoss_Cybernetics_Core 1 5017
Protoss_Zealot 1 4859
Protoss_Dragoon 4 10055
Protoss_Robotics_Facility 1 7013
Protoss_Shuttle 1 7829
Protoss_Robotics_Support_Bay 1 7725
Protoss_Reaver 1 9217
Protoss_Observatory 1 8659
Protoss_Observer 1 9549
Protoss_Nexus 1 11493
Protoss_Scarab 2 9499
11493
