Protoss_Gateway 2 8634
Protoss_Assimilator 1 3317
Protoss_Cybernetics_Core 1 4410
Protoss_Dragoon 6 10837
Protoss_Robotics_Facility 1 7889
Protoss_Nexus 2 12691
Protoss_Shuttle 1 9303
Protoss_Observatory 1 8654
Protoss_Zealot 3 9867
Protoss_Observer 1 9725
12691
