Protoss_Gateway 3 8765
Protoss_Assimilator 1 3341
Protoss_Cybernetics_Core 1 4344
Protoss_Dragoon 9 10783
Protoss_Robotics_Facility 1 8333
Protoss_Zealot 4 9525
Protoss_Observatory 1 8568
Protoss_Shuttle 1 9623
Protoss_Observer 1 10045
10783
