Protoss_Nexus 2 10101
Protoss_Gateway 4 9909
Protoss_Assimilator 1 4372
Protoss_Cybernetics_Core 1 5590
Protoss_Zealot 1 5599
Protoss_Dragoon 10 10891
Protoss_Robotics_Facility 1 9455
Protoss_Observatory 1 9583
Protoss_Observer 1 10505
10891
