Protoss_Gateway 3 9071
Protoss_Assimilator 2 9211
Protoss_Cybernetics_Core 1 4386
Protoss_Zealot 1 4109
Protoss_Dragoon 8 10187
Protoss_Nexus 1 8820
Protoss_Robotics_Facility 1 8699
Protoss_Observatory 1 8861
Protoss_Citadel_of_Adun 1 10079
Protoss_Observer 2 10235
Protoss_Templar_Archives 1 11177
Protoss_Stargate 1 11450
11450
