Protoss_Gateway 4 11191
Protoss_Assimilator 1 3328
Protoss_Cybernetics_Core 1 4406
Protoss_Zealot 1 4089
Protoss_Dragoon 5 8311
Protoss_Nexus 2 11553
Protoss_Citadel_of_Adun 1 8799
Protoss_Templar_Archives 1 9783
Protoss_Dark_Templar 2 10531
Protoss_Robotics_Facility 1 11335
11553
