Protoss_Gateway 2 10246
Protoss_Assimilator 1 3325
Protoss_Cybernetics_Core 1 4370
Protoss_Dragoon 8 11057
Protoss_Nexus 2 12667
Protoss_Robotics_Facility 1 8779
Protoss_Shuttle 1 9647
Protoss_Robotics_Support_Bay 1 9410
Protoss_Reaver 1 10915
12667
