Protoss_Gateway 3 8921
Protoss_Assimilator 2 10843
Protoss_Cybernetics_Core 1 4449
Protoss_Dragoon 10 10937
Protoss_Nexus 2 11787
Protoss_Robotics_Facility 1 8813
Protoss_Observatory 1 9003
Protoss_Observer 2 10598
Protoss_Citadel_of_Adun 1 10922
11787
