Protoss_Gateway 2 9783
Protoss_Assimilator 1 3316
Protoss_Zealot 2 4499
Protoss_Cybernetics_Core 1 5235
Protoss_Dragoon 8 10897
Protoss_Robotics_Facility 1 6935
Protoss_Observatory 1 7038
Protoss_Observer 2 8411
Protoss_Nexus 2 12113
12113
