Protoss_Gateway 2 9532
Protoss_Assimilator 1 3368
Protoss_Cybernetics_Core 1 4383
Protoss_Dragoon 9 10729
Protoss_Robotics_Facility 1 7860
Protoss_Observatory 1 8104
Protoss_Observer 4 10897
Protoss_Nexus 1 12820
12820
