Protoss_Gateway 1 3279
Protoss_Assimilator 1 3180
Protoss_Cybernetics_Core 1 4278
Protoss_Dragoon 5 10561
Protoss_Robotics_Facility 1 7194
Protoss_Shuttle 1 7999
Protoss_Observatory 1 7351
Protoss_Nexus 2 12483
Protoss_Robotics_Support_Bay 1 8125
Protoss_Observer 3 10773
Protoss_Zealot 2 9481
Protoss_Reaver 1 9839
12483
