Protoss_Gateway 4 11021
Protoss_Assimilator 1 3340
Protoss_Cybernetics_Core 1 4342
Protoss_Dragoon 9 10861
Protoss_Robotics_Facility 1 7239
Protoss_Observatory 1 7342
Protoss_Observer 3 10649
Protoss_Nexus 2 11161
11161
