Protoss_Gateway 4 11167
Protoss_Assimilator 1 3305
Protoss_Cybernetics_Core 1 4395
Protoss_Dragoon 6 10489
Protoss_Robotics_Facility 1 6276
Protoss_Shuttle 1 7335
Protoss_Zealot 2 7905
Protoss_Observatory 1 7087
Protoss_Robotics_Support_Bay 1 7545
Protoss_Observer 1 7913
Protoss_Nexus 1 10897
Protoss_Reaver 1 9925
11167
