Protoss_Nexus 1 5669
Protoss_Gateway 2 5809
Protoss_Assimilator 2 6891
Protoss_Cybernetics_Core 1 5562
Protoss_Zealot 1 5639
Protoss_Dragoon 6 11029
Protoss_Citadel_of_Adun 1 7843
Protoss_Robotics_Facility 1 9174
Protoss_Templar_Archives 1 8900
Protoss_Shuttle 1 10031
Protoss_Dark_Templar 2 9835
Protoss_Forge 1 9709
Protoss_Observatory 1 9920
Protoss_Stargate 1 11109
Protoss_Photon_Cannon 1 10876
Protoss_Observer 1 10697
11109
