Protoss_Gateway 2 8867
Protoss_Assimilator 2 9145
Protoss_Cybernetics_Core 1 4985
Protoss_Zealot 1 4603
Protoss_Dragoon 9 10653
Protoss_Nexus 1 9011
Protoss_Robotics_Facility 1 9121
Protoss_Observatory 1 9415
Protoss_Shuttle 1 10431
Protoss_Robotics_Support_Bay 1 9843
Protoss_Citadel_of_Adun 1 11139
Protoss_Observer 1 10853
11139
