Protoss_Gateway 2 4858
Protoss_Assimilator 1 3140
Protoss_Cybernetics_Core 1 4287
Protoss_Dragoon 9 9855
Protoss_Robotics_Facility 1 7537
Protoss_Shuttle 1 8351
Protoss_Robotics_Support_Bay 1 8011
Protoss_Zealot 2 8513
Protoss_Reaver 1 9515
Protoss_Nexus 1 12779
12779
