Protoss_Gateway 2 9720
Protoss_Assimilator 1 3214
Protoss_Cybernetics_Core 1 4323
Protoss_Zealot 1 4169
Protoss_Dragoon 9 11105
Protoss_Robotics_Facility 2 11330
Protoss_Robotics_Support_Bay 1 7161
Protoss_Shuttle 1 8089
Protoss_Reaver 1 9591
Protoss_Nexus 1 11801
11801
