Protoss_Gateway 4 10399
Protoss_Assimilator 1 3270
Protoss_Cybernetics_Core 1 4266
Protoss_Dragoon 7 8805
Protoss_Nexus 1 9623
Protoss_Citadel_of_Adun 1 9503
Protoss_Robotics_Facility 1 10530
Protoss_Templar_Archives 1 10799
Protoss_Shuttle 1 11333
11333
