Protoss_Assimilator 1 2789
Protoss_Gateway 4 11122
Protoss_Cybernetics_Core 1 4707
Protoss_Dragoon 7 9753
Protoss_Robotics_Facility 1 7828
Protoss_Zealot 1 7099
Protoss_Nexus 2 12112
Protoss_Observatory 1 8261
Protoss_Observer 3 10557
12112
