Protoss_Assimilator 3 8359
Protoss_Gateway 3 10594
Protoss_Nexus 1 6711
Protoss_Zealot 7 8959
Protoss_Cybernetics_Core 1 6530
Protoss_Dragoon 3 10981
Protoss_Robotics_Facility 2 10343
Protoss_Shuttle 1 10655
Protoss_Robotics_Support_Bay 1 10040
Protoss_Reaver 1 11627
11627
