Protoss_Gateway 2 7701
Protoss_Assimilator 2 10468
Protoss_Cybernetics_Core 1 4567
Protoss_Dragoon 9 10891
Protoss_Nexus 1 8591
Protoss_Robotics_Facility 1 8571
Protoss_Shuttle 1 9385
Protoss_Robotics_Support_Bay 1 9364
Protoss_Zealot 2 9963
Protoss_Reaver 1 10947
Protoss_Observatory 1 10545
10947
