Protoss_Gateway 3 9374
Protoss_Assimilator 1 3547
Protoss_Cybernetics_Core 1 4527
Protoss_Dragoon 13 11106
Protoss_Robotics_Facility 1 6549
Protoss_Observatory 1 6703
Protoss_Observer 2 8118
11106
