Protoss_Gateway 3 9059
Protoss_Assimilator 1 3300
Protoss_Cybernetics_Core 1 4301
Protoss_Zealot 1 4123
Protoss_Dragoon 9 9901
Protoss_Nexus 1 8875
Protoss_Robotics_Facility 1 8765
Protoss_Observatory 1 8901
Protoss_Observer 2 10281
Protoss_Shuttle 1 11363
Protoss_Robotics_Support_Bay 1 10702
11363
