Protoss_Gateway 4 10653
Protoss_Assimilator 1 3561
Protoss_Cybernetics_Core 1 4633
Protoss_Dragoon 10 10840
Protoss_Nexus 1 9671
Protoss_Robotics_Facility 1 9574
Protoss_Observatory 1 9725
Protoss_Observer 1 10671
Protoss_Zealot 1 10716
10840
