Protoss_Gateway 2 7932
Protoss_Assimilator 2 10313
Protoss_Cybernetics_Core 1 4515
Protoss_Dragoon 11 11149
Protoss_Nexus 1 8955
Protoss_Robotics_Facility 1 9144
Protoss_Observatory 1 9316
Protoss_Observer 2 10799
Protoss_Citadel_of_Adun 1 10655
11149
