Protoss_Nexus 2 12264
Protoss_Gateway 4 11107
Protoss_Assimilator 2 7421
Protoss_Cybernetics_Core 1 5599
Protoss_Dragoon 7 10911
Protoss_Robotics_Facility 1 7709
Protoss_Zealot 2 8119
Protoss_Observatory 1 7946
Protoss_Observer 3 10519
12264
