Protoss_Gateway 2 8614
Protoss_Assimilator 2 9327
Protoss_Cybernetics_Core 1 4387
Protoss_Zealot 1 4593
Protoss_Nexus 1 7616
Protoss_Dragoon 7 10831
Protoss_Citadel_of_Adun 1 8391
Protoss_Templar_Archives 1 9540
Protoss_Stargate 1 9981
Protoss_Arbiter_Tribunal 1 10879
Protoss_Dark_Templar 1 10821
10879
