Protoss_Gateway 2 8651
Protoss_Assimilator 1 3313
Protoss_Cybernetics_Core 1 4360
Protoss_Dragoon 11 10961
Protoss_Nexus 1 9356
Protoss_Robotics_Facility 1 8858
Protoss_Observatory 1 9026
Protoss_Observer 2 10407
10961
