Protoss_Gateway 2 7863
Protoss_Assimilator 2 10261
Protoss_Cybernetics_Core 1 4493
Protoss_Dragoon 10 11059
Protoss_Nexus 1 8819
Protoss_Robotics_Facility 1 9167
Protoss_Shuttle 1 9973
Protoss_Observatory 1 9547
Protoss_Zealot 2 10707
Protoss_Robotics_Support_Bay 1 10004
Protoss_Observer 1 10527
11059
