Protoss_Gateway 3 11257
Protoss_Assimilator 2 10920
Protoss_Cybernetics_Core 1 4338
Protoss_Zealot 1 4069
Protoss_Dragoon 7 10351
Protoss_Nexus 2 11671
Protoss_Robotics_Facility 1 8985
Protoss_Observatory 1 9076
Protoss_Observer 2 10515
11671
