Protoss_Gateway 2 8643
Protoss_Assimilator 1 3313
Protoss_Cybernetics_Core 1 4632
Protoss_Dragoon 8 11128
Protoss_Robotics_Facility 1 7602
Protoss_Robotics_Support_Bay 1 7724
Protoss_Shuttle 1 8901
Protoss_Observatory 1 8869
Protoss_Reaver 1 10116
Protoss_Observer 1 10448
11128
