Protoss_Gateway 2 9690
Protoss_Assimilator 2 9407
Protoss_Cybernetics_Core 1 4317
Protoss_Zealot 1 4059
Protoss_Dragoon 7 10837
Protoss_Citadel_of_Adun 1 6493
Protoss_Templar_Archives 1 7583
Protoss_Nexus 1 10072
Protoss_Dark_Templar 2 9163
Protoss_Stargate 1 9583
Protoss_Arbiter_Tribunal 1 10616
10837
