Protoss_Nexus 1 5549
Protoss_Gateway 3 8266
Protoss_Assimilator 2 8994
Protoss_Cybernetics_Core 1 5493
Protoss_Zealot 3 9923
Protoss_Dragoon 12 10765
Protoss_Robotics_Facility 1 8675
Protoss_Shuttle 1 9899
Protoss_Robotics_Support_Bay 1 9939
Protoss_Reaver 1 11451
11451
