Protoss_Gateway 2 7658
Protoss_Assimilator 1 3413
Protoss_Cybernetics_Core 1 4684
Protoss_Dragoon 7 9026
Protoss_Robotics_Facility 1 7427
Protoss_Observatory 2 9169
Protoss_Robotics_Support_Bay 1 7818
Protoss_Reaver 1 9431
Protoss_Shuttle 1 10431
Protoss_Nexus 1 12513
Protoss_Observer 1 10853
12513
