Protoss_Assimilator 3 4212
Protoss_Gateway 4 10413
Protoss_Cybernetics_Core 1 5065
Protoss_Dragoon 10 11115
Protoss_Nexus 1 10621
Protoss_Robotics_Facility 1 9954
Protoss_Observatory 1 10585
11115
