Protoss_Gateway 2 7727
Protoss_Assimilator 1 3561
Protoss_Cybernetics_Core 1 4725
Protoss_Dragoon 8 10781
Protoss_Robotics_Facility 1 7535
Protoss_Shuttle 1 8415
Protoss_Observatory 1 7837
Protoss_Robotics_Support_Bay 1 8448
Protoss_Observer 1 8879
Protoss_Zealot 2 8933
Protoss_Reaver 1 10201
Protoss_Nexus 2 12861
12861
