Protoss_Gateway 2 10287
Protoss_Assimilator 2 10274
Protoss_Cybernetics_Core 1 4413
Protoss_Dragoon 9 11045
Protoss_Robotics_Facility 1 7265
Protoss_Nexus 1 9517
Protoss_Shuttle 1 8619
Protoss_Robotics_Support_Bay 1 8375
Protoss_Reaver 1 9977
Protoss_Observatory 1 9959
Protoss_Observer 1 10725
11045
