Protoss_Gateway 2 8690
Protoss_Assimilator 2 10639
Protoss_Cybernetics_Core 1 4593
Protoss_Dragoon 6 10623
Protoss_Nexus 1 8601
Protoss_Citadel_of_Adun 1 7888
Protoss_Robotics_Facility 1 8757
Protoss_Templar_Archives 1 8919
Protoss_Shuttle 1 9563
Protoss_Dark_Templar 2 9693
Protoss_Observatory 1 9479
Protoss_Observer 1 10411
10639
