Protoss_Nexus 1 5493
Protoss_Gateway 3 8783
Protoss_Assimilator 1 4363
Protoss_Cybernetics_Core 1 5621
Protoss_Zealot 1 5409
Protoss_Dragoon 10 10927
Protoss_Robotics_Facility 1 9755
Protoss_Observatory 1 9894
Protoss_Observer 1 10729
10927
