Protoss_Gateway 2 7022
Protoss_Assimilator 2 10133
Protoss_Cybernetics_Core 1 4475
Protoss_Dragoon 7 10839
Protoss_Robotics_Facility 1 7398
Protoss_Nexus 2 11241
Protoss_Observatory 1 7737
Protoss_Observer 2 9111
Protoss_Citadel_of_Adun 1 10511
11241
