Protoss_Gateway 3 8119
Protoss_Assimilator 1 3438
Protoss_Cybernetics_Core 1 4642
Protoss_Dragoon 8 10701
Protoss_Citadel_of_Adun 1 6893
Protoss_Templar_Archives 1 7939
Protoss_Dark_Templar 2 10156
Protoss_Robotics_Facility 1 11783
11783
