Protoss_Nexus 2 10499
Protoss_Gateway 6 10903
Protoss_Assimilator 2 10122
Protoss_Cybernetics_Core 1 5701
Protoss_Dragoon 6 10205
Protoss_Citadel_of_Adun 1 7315
Protoss_Templar_Archives 1 8702
Protoss_Dark_Templar 2 9453
10903
