Protoss_Gateway 1 3384
Protoss_Assimilator 1 3466
Protoss_Zealot 1 4071
Protoss_Cybernetics_Core 1 5355
Protoss_Dragoon 2 8836
Protoss_Citadel_of_Adun 1 6453
Protoss_Forge 1 10378
10378
