Protoss_Nexus 1 5805
Protoss_Gateway 2 6121
Protoss_Assimilator 1 4637
Protoss_Cybernetics_Core 1 5814
Protoss_Zealot 1 5783
Protoss_Dragoon 12 11103
Protoss_Robotics_Facility 1 11415
11415
