Protoss_Nexus 1 5377
Protoss_Gateway 2 5109
Protoss_Assimilator 2 8169
Protoss_Zealot 3 5759
Protoss_Cybernetics_Core 1 5655
Protoss_Dragoon 10 11041
Protoss_Citadel_of_Adun 1 8664
Protoss_Templar_Archives 1 9665
Protoss_Stargate 1 9991
Protoss_Robotics_Facility 1 11175
Protoss_Arbiter_Tribunal 1 10923
11175
