Protoss_Gateway 4 11328
Protoss_Assimilator 1 3103
Protoss_Cybernetics_Core 1 4251
Protoss_Dragoon 10 10415
Protoss_Robotics_Facility 1 6985
Protoss_Observatory 1 7095
Protoss_Nexus 2 11460
Protoss_Observer 3 10321
11460
