Protoss_Gateway 2 10767
Protoss_Assimilator 2 9908
Protoss_Cybernetics_Core 1 4415
Protoss_Dragoon 7 10107
Protoss_Robotics_Facility 1 7279
Protoss_Observatory 1 7459
Protoss_Nexus 1 9915
Protoss_Observer 3 9941
Protoss_Citadel_of_Adun 1 9575
Protoss_Templar_Archives 1 11174
11174
