Protoss_Gateway 2 7426
Protoss_Assimilator 1 3144
Protoss_Cybernetics_Core 1 4264
Protoss_Zealot 1 4135
Protoss_Dragoon 12 10609
Protoss_Robotics_Facility 1 7254
Protoss_Observatory 1 7339
Protoss_Observer 2 8749
Protoss_Nexus 1 10291
Protoss_Shuttle 1 10041
Protoss_Robotics_Support_Bay 1 9528
Protoss_Reaver 1 11391
11391
