Protoss_Gateway 3 11163
Protoss_Assimilator 1 3491
Protoss_Cybernetics_Core 1 4673
Protoss_Dragoon 5 8871
Protoss_Robotics_Facility 1 7805
Protoss_Shuttle 1 8611
Protoss_Robotics_Support_Bay 1 8364
Protoss_Reaver 1 9871
Protoss_Observatory 1 8999
Protoss_Zealot 2 9908
Protoss_Nexus 1 11698
Protoss_Observer 1 10306
11698
