Protoss_Gateway 2 6073
Protoss_Assimilator 1 3283
Protoss_Cybernetics_Core 1 4468
Protoss_Dragoon 11 10773
Protoss_Robotics_Facility 1 8571
Protoss_Zealot 2 8829
Protoss_Shuttle 1 9385
Protoss_Robotics_Support_Bay 1 8820
Protoss_Reaver 1 10569
Protoss_Observatory 1 10127
10773
