Protoss_Gateway 2 10368
Protoss_Assimilator 2 10097
Protoss_Cybernetics_Core 1 4307
Protoss_Zealot 1 4115
Protoss_Dragoon 6 10667
Protoss_Citadel_of_Adun 1 6786
Protoss_Templar_Archives 1 7871
Protoss_Nexus 1 10313
Protoss_Dark_Templar 1 8661
Protoss_Robotics_Facility 1 10385
Protoss_Shuttle 1 11439
11439
