Protoss_Gateway 1 3367
Protoss_Assimilator 1 3279
Protoss_Cybernetics_Core 1 4417
Protoss_Dragoon 6 9651
Protoss_Robotics_Facility 1 7341
Protoss_Observatory 1 7625
Protoss_Nexus 2 10179
Protoss_Observer 3 10799
Protoss_Shuttle 1 10377
Protoss_Robotics_Support_Bay 1 9689
Protoss_Zealot 2 10905
10905
