Protoss_Gateway 3 7525
Protoss_Assimilator 1 3192
Protoss_Cybernetics_Core 1 4385
Protoss_Dragoon 11 10745
Protoss_Robotics_Facility 1 7221
Protoss_Observatory 1 7332
Protoss_Observer 1 8099
Protoss_Shuttle 1 9371
Protoss_Robotics_Support_Bay 1 8931
Protoss_Zealot 3 9903
Protoss_Reaver 1 10537
10745
