Protoss_Gateway 3 11178
Protoss_Assimilator 1 3166
Protoss_Cybernetics_Core 1 4343
Protoss_Dragoon 5 8377
Protoss_Robotics_Facility 1 7306
Protoss_Shuttle 1 8473
Protoss_Observatory 1 8083
Protoss_Robotics_Support_Bay 1 8230
Protoss_Observer 1 9001
Protoss_Nexus 1 11227
Protoss_Zealot 1 9473
Protoss_Reaver 1 10475
11227
