Protoss_Gateway 1 3303
Protoss_Assimilator 1 3391
Protoss_Cybernetics_Core 1 4375
Protoss_Zealot 2 7793
Protoss_Dragoon 6 10721
Protoss_Robotics_Facility 1 6329
Protoss_Shuttle 2 10817
Protoss_Robotics_Support_Bay 1 6803
Protoss_Reaver 1 8471
Protoss_Observatory 1 8055
Protoss_Observer 2 9467
Protoss_Nexus 1 11259
11259
