Protoss_Gateway 3 9325
Protoss_Assimilator 2 9822
Protoss_Cybernetics_Core 1 4353
Protoss_Zealot 3 10913
Protoss_Dragoon 7 10871
Protoss_Nexus 1 8905
Protoss_Robotics_Facility 1 8814
Protoss_Observatory 1 8949
Protoss_Citadel_of_Adun 1 9909
Protoss_Observer 2 10347
Protoss_Templar_Archives 1 10903
Protoss_Stargate 1 11225
11225
