Protoss_Gateway 4 10174
Protoss_Assimilator 1 3175
Protoss_Cybernetics_Core 1 4361
Protoss_Dragoon 8 10999
Protoss_Robotics_Facility 1 7754
Protoss_Observatory 1 7868
Protoss_Nexus 1 10412
Protoss_Observer 2 9857
10999
