Protoss_Gateway 2 7490
Protoss_Assimilator 1 3277
Protoss_Cybernetics_Core 1 4260
Protoss_Dragoon 7 10961
Protoss_Citadel_of_Adun 1 6368
Protoss_Templar_Archives 1 7399
Protoss_Zealot 1 7345
Protoss_Dark_Templar 3 10163
Protoss_Nexus 1 10565
10961
