Protoss_Gateway 4 11148
Protoss_Assimilator 1 3428
Protoss_Cybernetics_Core 1 4737
Protoss_Dragoon 4 9411
Protoss_Robotics_Facility 1 7101
Protoss_Robotics_Support_Bay 1 7209
Protoss_Shuttle 1 7936
Protoss_Zealot 2 8193
Protoss_Reaver 1 9078
Protoss_Observatory 1 8381
Protoss_Observer 2 10096
Protoss_Nexus 1 11829
11829
