Protoss_Gateway 2 7655
Protoss_Assimilator 1 3315
Protoss_Cybernetics_Core 1 4496
Protoss_Dragoon 7 10713
Protoss_Robotics_Facility 1 7159
Protoss_Citadel_of_Adun 1 6827
Protoss_Templar_Archives 1 7884
Protoss_Shuttle 1 8019
Protoss_Dark_Templar 2 8637
Protoss_Observatory 1 9395
Protoss_Nexus 1 11937
11937
