Protoss_Gateway 2 6133
Protoss_Assimilator 1 3306
Protoss_Cybernetics_Core 1 4275
Protoss_Zealot 2 10239
Protoss_Citadel_of_Adun 1 5389
Protoss_Dragoon 8 10363
Protoss_Templar_Archives 1 6460
Protoss_Dark_Templar 2 7205
Protoss_Nexus 1 11759
Protoss_Robotics_Facility 1 11179
11759
