Protoss_Gateway 2 10453
Protoss_Assimilator 1 3318
Protoss_Cybernetics_Core 1 4423
Protoss_Zealot 1 4157
Protoss_Dragoon 7 10749
Protoss_Robotics_Facility 1 7482
Protoss_Shuttle 1 8301
Protoss_Robotics_Support_Bay 1 7779
Protoss_Reaver 1 9443
Protoss_Nexus 1 11011
Protoss_Observatory 1 8977
Protoss_Observer 2 10377
11011
