Protoss_Gateway 2 7372
Protoss_Assimilator 1 3187
Protoss_Cybernetics_Core 1 4436
Protoss_Dragoon 12 10695
Protoss_Robotics_Facility 1 7582
Protoss_Observatory 1 8022
Protoss_Observer 2 10799
Protoss_Nexus 1 11723
Protoss_Citadel_of_Adun 1 10618
11723
