Protoss_Gateway 2 10509
Protoss_Assimilator 1 3233
Protoss_Cybernetics_Core 1 4410
Protoss_Zealot 2 9669
Protoss_Dragoon 7 10511
Protoss_Robotics_Facility 1 6963
Protoss_Robotics_Support_Bay 1 7069
Protoss_Shuttle 1 8127
Protoss_Reaver 2 10378
Protoss_Scarab 8 9996
10511
