Protoss_Gateway 4 11206
Protoss_Assimilator 1 3297
Protoss_Cybernetics_Core 1 4285
Protoss_Dragoon 9 10577
Protoss_Nexus 2 11910
Protoss_Robotics_Facility 1 8459
Protoss_Observatory 1 8662
Protoss_Observer 3 10649
11910
