Protoss_Nexus 1 5465
Protoss_Gateway 2 5518
Protoss_Assimilator 1 4388
Protoss_Cybernetics_Core 1 5447
Protoss_Zealot 1 5277
Protoss_Dragoon 8 9985
Protoss_Robotics_Facility 1 10278
Protoss_Shuttle 1 11077
11077
