Protoss_Gateway 2 11170
Protoss_Assimilator 1 3301
Protoss_Cybernetics_Core 1 4411
Protoss_Dragoon 3 7567
Protoss_Robotics_Facility 1 6271
Protoss_Zealot 4 10477
Protoss_Shuttle 1 7071
Protoss_Robotics_Support_Bay 1 6623
Protoss_Reaver 1 8597
Protoss_Nexus 1 11173
Protoss_Scarab 12 9831
11173
