Protoss_Gateway 2 9784
Protoss_Assimilator 2 9211
Protoss_Zealot 1 4081
Protoss_Cybernetics_Core 1 5249
Protoss_Dragoon 6 10593
Protoss_Robotics_Facility 1 7727
Protoss_Nexus 1 9628
Protoss_Observatory 1 8104
Protoss_Observer 3 10865
Protoss_Citadel_of_Adun 1 9592
Protoss_Templar_Archives 1 10924
10924
