Protoss_Gateway 2 8638
Protoss_Assimilator 2 9818
Protoss_Cybernetics_Core 1 4432
Protoss_Dragoon 11 11009
Protoss_Robotics_Facility 1 7402
Protoss_Observatory 1 7494
Protoss_Nexus 1 9744
Protoss_Observer 2 8875
Protoss_Citadel_of_Adun 1 10206
11009
