Protoss_Gateway 3 9949
Protoss_Assimilator 1 3358
Protoss_Cybernetics_Core 1 4577
Protoss_Zealot 1 4271
Protoss_Dragoon 10 11041
Protoss_Nexus 1 10174
Protoss_Robotics_Facility 1 9428
Protoss_Observatory 1 9593
Protoss_Observer 1 10371
11041
