Protoss_Gateway 4 10770
Protoss_Assimilator 2 8504
Protoss_Nexus 1 6643
Protoss_Cybernetics_Core 1 5633
Protoss_Zealot 1 5443
Protoss_Dragoon 10 10751
Protoss_Robotics_Facility 1 8597
Protoss_Observatory 1 8851
Protoss_Observer 3 10873
10873
