Protoss_Gateway 2 8920
Protoss_Assimilator 1 3187
Protoss_Cybernetics_Core 1 4299
Protoss_Dragoon 8 10669
Protoss_Robotics_Facility 1 7517
Protoss_Nexus 1 9757
Protoss_Observatory 1 7796
Protoss_Observer 1 8977
Protoss_Robotics_Support_Bay 1 9087
Protoss_Shuttle 1 10188
Protoss_Zealot 2 9747
Protoss_Reaver 1 11345
11345
