Protoss_Gateway 3 9493
Protoss_Assimilator 1 3533
Protoss_Cybernetics_Core 1 4896
Protoss_Dragoon 12 10533
Protoss_Nexus 1 10111
Protoss_Shield_Battery 1 9335
Protoss_Robotics_Facility 1 11565
Protoss_Zealot 1 10783
11565
