Protoss_Gateway 4 10256
Protoss_Assimilator 2 3555
Protoss_Cybernetics_Core 1 4911
Protoss_Nexus 1 7753
Protoss_Dragoon 11 11179
Protoss_Robotics_Facility 1 9528
Protoss_Observatory 1 9619
Protoss_Observer 1 10391
11179
