Protoss_Gateway 2 7847
Protoss_Assimilator 1 3327
Protoss_Cybernetics_Core 1 4459
Protoss_Dragoon 10 10819
Protoss_Robotics_Facility 1 7501
Protoss_Observatory 1 7620
Protoss_Nexus 2 11400
Protoss_Observer 3 10053
11400
