Protoss_Gateway 2 7426
Protoss_Assimilator 1 3191
Protoss_Cybernetics_Core 1 4452
Protoss_Dragoon 10 10627
Protoss_Robotics_Facility 1 7181
Protoss_Observatory 1 7416
Protoss_Nexus 2 11691
Protoss_Observer 3 9471
11691
