Protoss_Gateway 1 3491
Protoss_Assimilator 1 3576
Protoss_Cybernetics_Core 1 4761
Protoss_Dragoon 6 10812
Protoss_Citadel_of_Adun 1 6208
Protoss_Nexus 1 9683
Protoss_Robotics_Facility 1 11523
11523
