Protoss_Gateway 3 11435
Protoss_Zealot 2 4485
Protoss_Assimilator 2 10279
Protoss_Cybernetics_Core 1 5443
Protoss_Dragoon 8 10963
Protoss_Nexus 2 11987
Protoss_Robotics_Facility 1 9072
Protoss_Observatory 1 9280
Protoss_Observer 2 10913
Protoss_Citadel_of_Adun 1 10897
11987
