Protoss_Gateway 2 7693
Protoss_Assimilator 1 3428
Protoss_Cybernetics_Core 1 4481
Protoss_Dragoon 12 10935
Protoss_Robotics_Facility 1 7726
Protoss_Observatory 1 8029
Protoss_Observer 1 8831
Protoss_Shuttle 1 10173
Protoss_Robotics_Support_Bay 1 9537
Protoss_Nexus 1 12736
12736
