Protoss_Gateway 4 10557
Protoss_Assimilator 2 9540
Protoss_Cybernetics_Core 1 4685
Protoss_Nexus 2 11295
Protoss_Dragoon 9 10723
Protoss_Robotics_Facility 1 9308
Protoss_Observatory 1 9453
Protoss_Observer 1 10307
11295
