Protoss_Gateway 2 8763
Protoss_Assimilator 2 10344
Protoss_Cybernetics_Core 1 4356
Protoss_Zealot 1 4241
Protoss_Dragoon 8 11036
Protoss_Nexus 2 11858
Protoss_Robotics_Facility 1 8926
Protoss_Observatory 1 9241
Protoss_Observer 2 10828
11858
