Protoss_Gateway 7 11237
Protoss_Zealot 4 8915
Protoss_Nexus 2 11247
Protoss_Assimilator 2 7983
Protoss_Cybernetics_Core 1 6241
Protoss_Dragoon 6 10837
Protoss_Robotics_Facility 1 9496
Protoss_Observatory 2 9629
Protoss_Observer 1 10409
11247
