Protoss_Nexus 2 11165
Protoss_Gateway 4 11055
Protoss_Assimilator 2 8539
Protoss_Cybernetics_Core 1 5591
Protoss_Zealot 1 5599
Protoss_Dragoon 8 10197
Protoss_Robotics_Facility 1 9206
Protoss_Observatory 1 9510
Protoss_Observer 2 10883
11165
