Protoss_Nexus 1 5463
Protoss_Gateway 3 11376
Protoss_Assimilator 1 4365
Protoss_Cybernetics_Core 1 5425
Protoss_Zealot 3 9957
Protoss_Dragoon 8 9445
Protoss_Robotics_Facility 1 10736
11376
