Protoss_Gateway 2 10200
Protoss_Assimilator 1 3243
Protoss_Cybernetics_Core 1 4433
Protoss_Dragoon 8 10487
Protoss_Robotics_Facility 1 7524
Protoss_Observatory 1 7628
Protoss_Observer 3 10651
Protoss_Nexus 1 10678
10678
