Protoss_Gateway 2 6859
Protoss_Assimilator 3 5125
Protoss_Zealot 5 9263
Protoss_Cybernetics_Core 1 6102
Protoss_Dragoon 5 8779
Protoss_Citadel_of_Adun 1 7842
Protoss_Templar_Archives 1 9509
Protoss_Dark_Templar 4 11167
11167
