Protoss_Nexus 2 12691
Protoss_Gateway 2 5975
Protoss_Assimilator 2 8540
Protoss_Cybernetics_Core 1 5690
Protoss_Dragoon 10 10567
Protoss_Robotics_Facility 1 9695
Protoss_Zealot 2 8883
Protoss_Citadel_of_Adun 1 10279
Protoss_Observatory 1 9962
12691
