Protoss_Gateway 3 8938
Protoss_Assimilator 1 3314
Protoss_Cybernetics_Core 1 4415
Protoss_Dragoon 13 11129
Protoss_Nexus 1 8509
Protoss_Robotics_Facility 1 8495
Protoss_Observatory 1 8673
Protoss_Observer 1 9453
11129
