Protoss_Gateway 2 4810
Protoss_Assimilator 1 3159
Protoss_Cybernetics_Core 1 4305
Protoss_Dragoon 7 10685
Protoss_Nexus 2 11049
Protoss_Robotics_Facility 1 9383
Protoss_Shuttle 1 10187
Protoss_Robotics_Support_Bay 1 9747
Protoss_Reaver 1 11369
11369
