Protoss_Gateway 4 11141
Protoss_Assimilator 2 9864
Protoss_Cybernetics_Core 1 4315
Protoss_Zealot 1 4023
Protoss_Citadel_of_Adun 1 5337
Protoss_Dragoon 7 10819
Protoss_Templar_Archives 1 6321
Protoss_Dark_Templar 7 9235
Protoss_Nexus 1 9000
Protoss_Robotics_Facility 1 10890
11141
