Protoss_Gateway 1 3295
Protoss_Assimilator 1 3315
Protoss_Cybernetics_Core 1 4413
Protoss_Dragoon 7 10871
Protoss_Robotics_Facility 1 6449
Protoss_Shuttle 1 7247
Protoss_Zealot 1 7223
Protoss_Robotics_Support_Bay 1 7100
Protoss_Reaver 2 11345
Protoss_Observatory 1 8064
Protoss_Observer 2 9563
Protoss_Nexus 1 11373
Protoss_Scarab 6 9967
11373
