Protoss_Gateway 4 11400
Protoss_Assimilator 1 3266
Protoss_Cybernetics_Core 1 4387
Protoss_Dragoon 6 10839
Protoss_Robotics_Facility 1 6264
Protoss_Zealot 4 9732
Protoss_Shuttle 1 7077
Protoss_Robotics_Support_Bay 1 6749
Protoss_Reaver 1 8417
Protoss_Nexus 1 11201
11400
