Protoss_Nexus 1 5523
Protoss_Gateway 3 10170
Protoss_Assimilator 2 9247
Protoss_Cybernetics_Core 1 5491
Protoss_Zealot 1 5199
Protoss_Dragoon 13 10983
Protoss_Robotics_Facility 1 9491
Protoss_Observatory 1 9904
Protoss_Observer 1 10755
Protoss_Citadel_of_Adun 1 11319
11319
