Protoss_Gateway 2 8527
Protoss_Assimilator 1 3665
Protoss_Cybernetics_Core 1 4763
Protoss_Dragoon 7 9281
Protoss_Robotics_Facility 1 6712
Protoss_Observatory 1 6844
Protoss_Observer 3 9063
Protoss_Nexus 2 12288
12288
