Protoss_Gateway 2 7294
Protoss_Assimilator 2 9717
Protoss_Cybernetics_Core 1 4385
Protoss_Dragoon 9 10677
Protoss_Robotics_Facility 1 6333
Protoss_Zealot 1 6409
Protoss_Observatory 1 6445
Protoss_Observer 2 8027
Protoss_Nexus 1 9695
Protoss_Citadel_of_Adun 1 9467
Protoss_Templar_Archives 1 10511
10677
