Protoss_Gateway 2 7279
Protoss_Assimilator 1 3291
Protoss_Cybernetics_Core 1 4379
Protoss_Dragoon 9 10865
Protoss_Robotics_Facility 1 7248
Protoss_Observatory 1 7349
Protoss_Observer 1 8121
Protoss_Nexus 1 10393
Protoss_Shuttle 1 9785
Protoss_Robotics_Support_Bay 1 9797
Protoss_Reaver 1 11559
11559
