Protoss_Gateway 2 11122
Protoss_Assimilator 1 3390
Protoss_Cybernetics_Core 1 4489
Protoss_Zealot 1 4141
Protoss_Dragoon 7 10714
Protoss_Robotics_Facility 1 7403
Protoss_Shuttle 1 8229
Protoss_Robotics_Support_Bay 1 7587
Protoss_Reaver 1 9371
Protoss_Observatory 1 8606
Protoss_Observer 2 10474
Protoss_Nexus 1 12632
12632
