Protoss_Gateway 3 9830
Protoss_Assimilator 2 10581
Protoss_Cybernetics_Core 1 4427
Protoss_Dragoon 12 11075
Protoss_Nexus 1 9289
Protoss_Robotics_Facility 1 8784
Protoss_Observatory 1 8961
Protoss_Observer 2 10379
Protoss_Zealot 1 10403
Protoss_Citadel_of_Adun 1 11149
11149
