Protoss_Gateway 4 9277
Protoss_Zealot 4 10575
Protoss_Nexus 2 7337
Protoss_Assimilator 2 9168
Protoss_Cybernetics_Core 1 6508
Protoss_Dragoon 8 10809
Protoss_Robotics_Facility 1 9576
Protoss_Observatory 1 10451
10809
