Protoss_Gateway 1 3439
Protoss_Assimilator 1 3433
Protoss_Cybernetics_Core 1 4591
Protoss_Dragoon 4 10626
Protoss_Robotics_Facility 1 6531
Protoss_Zealot 2 7016
Protoss_Shuttle 1 7356
Protoss_Robotics_Support_Bay 1 6695
Protoss_Reaver 3 11436
Protoss_Scarab 5 9650
Protoss_Shield_Battery 1 9138
11436
