Protoss_Gateway 2 8703
Protoss_Assimilator 2 9257
Protoss_Cybernetics_Core 1 4369
Protoss_Dragoon 11 11117
Protoss_Robotics_Facility 1 6197
Protoss_Zealot 1 6385
Protoss_Observatory 1 6415
Protoss_Observer 3 9399
Protoss_Nexus 1 9790
Protoss_Citadel_of_Adun 1 9347
Protoss_Templar_Archives 1 10938
11117
