Protoss_Gateway 3 10090
Protoss_Assimilator 1 3318
Protoss_Cybernetics_Core 1 4393
Protoss_Dragoon 8 10913
Protoss_Robotics_Facility 1 6505
Protoss_Observatory 1 6744
Protoss_Observer 1 7853
Protoss_Nexus 1 10040
Protoss_Shuttle 1 11033
Protoss_Citadel_of_Adun 1 11062
11062
