Protoss_Gateway 3 10959
Protoss_Assimilator 1 3273
Protoss_Cybernetics_Core 1 4330
Protoss_Dragoon 9 11031
Protoss_Robotics_Facility 1 7924
Protoss_Nexus 2 11204
Protoss_Observatory 1 8177
Protoss_Observer 3 10247
Protoss_Shuttle 1 11329
11329
