Protoss_Gateway 2 5540
Protoss_Assimilator 1 3307
Protoss_Zealot 1 3771
Protoss_Cybernetics_Core 1 5057
Protoss_Dragoon 10 10051
Protoss_Nexus 1 9024
Protoss_Robotics_Facility 1 8835
Protoss_Observatory 1 8985
Protoss_Observer 1 9825
Protoss_Robotics_Support_Bay 1 10173
Protoss_Shuttle 1 10907
10907
