Protoss_Nexus 2 11755
Protoss_Gateway 4 10665
Protoss_Assimilator 2 9278
Protoss_Cybernetics_Core 1 5506
Protoss_Zealot 3 9917
Protoss_Dragoon 10 11009
Protoss_Robotics_Facility 1 8709
Protoss_Observatory 1 8959
Protoss_Observer 2 10329
11755
