Protoss_Gateway 3 7605
Protoss_Zealot 4 5535
Protoss_Assimilator 1 4471
Protoss_Cybernetics_Core 1 6008
Protoss_Dragoon 9 10685
Protoss_Robotics_Facility 1 9403
Protoss_Observatory 1 9489
Protoss_Observer 2 10871
10871
