Protoss_Nexus 2 10249
Protoss_Gateway 3 11207
Protoss_Assimilator 2 9703
Protoss_Cybernetics_Core 1 5327
Protoss_Zealot 1 4957
Protoss_Dragoon 12 10982
Protoss_Robotics_Facility 1 9951
Protoss_Citadel_of_Adun 1 10112
Protoss_Observatory 1 10433
Protoss_Forge 1 10909
11207
