Protoss_Nexus 2 10522
Protoss_Gateway 4 10497
Protoss_Assimilator 2 9418
Protoss_Cybernetics_Core 1 5617
Protoss_Zealot 1 5581
Protoss_Dragoon 10 11183
Protoss_Citadel_of_Adun 1 9783
Protoss_Templar_Archives 1 10867
Protoss_Stargate 1 11156
11183
