Protoss_Gateway 3 11138
Protoss_Assimilator 1 3277
Protoss_Cybernetics_Core 1 4459
Protoss_Dragoon 7 11087
Protoss_Robotics_Facility 1 6419
Protoss_Zealot 2 7117
Protoss_Shuttle 1 7259
Protoss_Observatory 1 6978
Protoss_Observer 2 10277
Protoss_Robotics_Support_Bay 1 7847
Protoss_Reaver 1 9359
Protoss_Nexus 1 11749
11749
