Protoss_Gateway 2 8910
Protoss_Assimilator 1 3173
Protoss_Cybernetics_Core 1 4347
Protoss_Zealot 1 4127
Protoss_Dragoon 10 10697
Protoss_Nexus 2 12592
Protoss_Robotics_Facility 1 8939
Protoss_Observatory 1 10141
Protoss_Observer 1 10911
12592
