Protoss_Gateway 4 11393
Protoss_Assimilator 1 3217
Protoss_Cybernetics_Core 1 4286
Protoss_Dragoon 9 10923
Protoss_Nexus 2 11956
Protoss_Robotics_Facility 1 8208
Protoss_Observatory 1 8367
Protoss_Observer 3 10383
11956
