Protoss_Nexus 1 5509
Protoss_Gateway 4 10033
Protoss_Assimilator 2 10108
Protoss_Zealot 3 10317
Protoss_Cybernetics_Core 1 5886
Protoss_Dragoon 12 11191
Protoss_Robotics_Facility 1 9683
Protoss_Observatory 1 9989
11191
