Protoss_Gateway 2 7627
Protoss_Assimilator 1 3231
Protoss_Cybernetics_Core 1 4522
Protoss_Dragoon 8 10413
Protoss_Citadel_of_Adun 1 6502
Protoss_Templar_Archives 1 7499
Protoss_Zealot 1 7609
Protoss_Dark_Templar 2 8647
Protoss_Nexus 1 10851
Protoss_Robotics_Facility 1 9959
Protoss_Shuttle 1 10783
Protoss_Robotics_Support_Bay 1 10199
Protoss_Observatory 1 10560
10851
