Protoss_Gateway 2 4929
Protoss_Assimilator 2 3563
Protoss_Zealot 5 7226
Protoss_Cybernetics_Core 1 6803
Protoss_Robotics_Facility 1 8618
Protoss_Dragoon 5 11166
Protoss_Robotics_Support_Bay 1 9623
Protoss_Citadel_of_Adun 1 10582
11166
