Protoss_Gateway 1 3321
Protoss_Assimilator 1 3328
Protoss_Cybernetics_Core 1 4389
Protoss_Dragoon 6 9787
Protoss_Robotics_Facility 1 6270
Protoss_Zealot 1 6435
Protoss_Shuttle 1 7167
Protoss_Robotics_Support_Bay 1 6841
Protoss_Reaver 1 8331
Protoss_Observatory 1 8232
Protoss_Observer 1 9059
Protoss_Scarab 2 9039
Protoss_Nexus 1 12204
12204
