Protoss_Gateway 1 3360
Protoss_Assimilator 1 3187
Protoss_Cybernetics_Core 1 4370
Protoss_Dragoon 7 10529
Protoss_Robotics_Facility 1 6281
Protoss_Shuttle 1 7081
Protoss_Robotics_Support_Bay 1 6994
Protoss_Reaver 1 8545
Protoss_Observatory 1 8779
Protoss_Scarab 2 9933
Protoss_Nexus 1 12037
Protoss_Observer 1 10225
12037
