Protoss_Gateway 3 9011
Protoss_Assimilator 1 3158
Protoss_Cybernetics_Core 1 4331
Protoss_Zealot 1 4119
Protoss_Dragoon 8 10955
Protoss_Robotics_Facility 1 7591
Protoss_Nexus 2 12131
Protoss_Observatory 1 7719
Protoss_Observer 3 9803
12131
