Protoss_Gateway 1 3301
Protoss_Assimilator 2 8509
Protoss_Cybernetics_Core 1 4387
Protoss_Zealot 1 4219
Protoss_Dragoon 4 10113
Protoss_Citadel_of_Adun 1 5669
Protoss_Templar_Archives 1 6659
Protoss_Dark_Templar 3 11051
Protoss_Nexus 1 9548
Protoss_Stargate 1 9067
Protoss_Arbiter_Tribunal 1 10367
11051
