Protoss_Gateway 2 10859
Protoss_Assimilator 1 3270
Protoss_Cybernetics_Core 1 4369
Protoss_Dragoon 6 10493
Protoss_Robotics_Facility 1 6201
Protoss_Zealot 2 7093
Protoss_Shuttle 1 7007
Protoss_Robotics_Support_Bay 1 6679
Protoss_Reaver 1 8337
Protoss_Nexus 1 10990
Protoss_Scarab 13 9795
10990
