Protoss_Gateway 2 4967
Protoss_Assimilator 2 9696
Protoss_Cybernetics_Core 1 4515
Protoss_Dragoon 10 10479
Protoss_Nexus 1 10069
Protoss_Robotics_Facility 1 10405
Protoss_Observatory 1 10559
10559
