Protoss_Gateway 5 11410
Protoss_Assimilator 1 3308
Protoss_Cybernetics_Core 1 4291
Protoss_Dragoon 9 10981
Protoss_Robotics_Facility 1 6237
Protoss_Zealot 1 6326
Protoss_Nexus 2 11617
Protoss_Observatory 1 7417
Protoss_Observer 4 10015
Protoss_Citadel_of_Adun 1 10678
11617
