Protoss_Gateway 2 8892
Protoss_Assimilator 1 3221
Protoss_Cybernetics_Core 1 4300
Protoss_Zealot 3 10317
Protoss_Dragoon 9 11181
Protoss_Nexus 1 8980
Protoss_Robotics_Facility 1 8879
Protoss_Shuttle 1 9679
Protoss_Robotics_Support_Bay 1 9069
Protoss_Reaver 1 10821
Protoss_Observatory 1 10042
11181
