Protoss_Gateway 5 10326
Protoss_Assimilator 1 3301
Protoss_Cybernetics_Core 1 4363
Protoss_Dragoon 10 11043
Protoss_Nexus 1 8489
Protoss_Robotics_Facility 1 8022
Protoss_Shuttle 1 8975
Protoss_Observatory 1 8619
Protoss_Observer 1 9659
Protoss_Robotics_Support_Bay 1 9849
Protoss_Zealot 3 10513
11043
