Protoss_Gateway 2 7425
Protoss_Assimilator 1 3234
Protoss_Zealot 3 5097
Protoss_Cybernetics_Core 1 5229
Protoss_Dragoon 10 10823
Protoss_Robotics_Facility 1 7775
Protoss_Observatory 1 8022
Protoss_Observer 1 9203
Protoss_Nexus 1 11186
Protoss_Citadel_of_Adun 1 10273
11186
