Protoss_Gateway 2 7427
Protoss_Assimilator 1 3337
Protoss_Cybernetics_Core 1 4373
Protoss_Dragoon 12 10921
Protoss_Robotics_Facility 1 7503
Protoss_Observatory 1 7702
Protoss_Nexus 1 10662
Protoss_Observer 3 10483
10921
