Protoss_Assimilator 3 4342
Protoss_Gateway 2 5809
Protoss_Zealot 2 5503
Protoss_Cybernetics_Core 1 5379
Protoss_Dragoon 8 10935
Protoss_Nexus 1 9881
Protoss_Robotics_Facility 1 11378
11378
