Protoss_Gateway 2 9086
Protoss_Assimilator 1 3539
Protoss_Zealot 1 3957
Protoss_Cybernetics_Core 1 5029
Protoss_Dragoon 7 10139
Protoss_Nexus 1 8927
Protoss_Robotics_Facility 1 9090
Protoss_Forge 1 9311
Protoss_Observatory 1 9555
Protoss_Citadel_of_Adun 1 11323
11323
