Protoss_Gateway 4 10619
Protoss_Assimilator 1 3279
Protoss_Cybernetics_Core 1 4332
Protoss_Dragoon 8 10789
Protoss_Nexus 2 9993
Protoss_Robotics_Facility 1 9327
Protoss_Citadel_of_Adun 1 9831
Protoss_Observatory 1 9612
Protoss_Observer 1 10585
Protoss_Templar_Archives 1 11096
Protoss_Stargate 1 11606
11606
