Protoss_Gateway 3 10953
Protoss_Assimilator 1 3508
Protoss_Cybernetics_Core 1 4718
Protoss_Dragoon 8 10081
Protoss_Nexus 1 10808
Protoss_Robotics_Facility 1 10551
Protoss_Zealot 2 10686
10953
