Protoss_Gateway 1 3286
Protoss_Assimilator 1 3206
Protoss_Cybernetics_Core 1 4351
Protoss_Zealot 1 4157
Protoss_Dragoon 8 10969
Protoss_Robotics_Facility 1 7640
Protoss_Shuttle 1 8739
Protoss_Robotics_Support_Bay 1 8636
Protoss_Nexus 1 11390
Protoss_Reaver 1 10215
Protoss_Observatory 1 9369
Protoss_Observer 1 10547
11390
