Protoss_Gateway 2 7528
Protoss_Assimilator 1 3349
Protoss_Cybernetics_Core 1 4477
Protoss_Dragoon 9 10775
Protoss_Robotics_Facility 1 6414
Protoss_Zealot 1 6627
Protoss_Observatory 1 6575
Protoss_Observer 3 10323
Protoss_Nexus 1 11536
Protoss_Citadel_of_Adun 1 10705
11536
