Protoss_Gateway 4 10891
Protoss_Assimilator 1 3087
Protoss_Zealot 2 4807
Protoss_Cybernetics_Core 1 5077
Protoss_Dragoon 10 10433
Protoss_Nexus 2 12457
Protoss_Robotics_Facility 1 8261
Protoss_Observatory 1 8589
Protoss_Observer 3 10813
Protoss_Citadel_of_Adun 1 10767
12457
