Protoss_Gateway 3 9810
Protoss_Assimilator 1 3146
Protoss_Cybernetics_Core 1 4253
Protoss_Dragoon 11 10999
Protoss_Robotics_Facility 1 7103
Protoss_Observatory 1 7453
Protoss_Nexus 1 10223
Protoss_Observer 3 9519
Protoss_Citadel_of_Adun 1 9943
10999
