Protoss_Gateway 3 9048
Protoss_Assimilator 2 10368
Protoss_Cybernetics_Core 1 4280
Protoss_Zealot 1 4055
Protoss_Dragoon 10 11119
Protoss_Robotics_Facility 1 7286
Protoss_Observatory 1 7386
Protoss_Nexus 1 9560
Protoss_Observer 4 10498
Protoss_Citadel_of_Adun 1 10758
11119
