Protoss_Gateway 4 10534
Protoss_Assimilator 1 3252
Protoss_Cybernetics_Core 1 4562
Protoss_Dragoon 7 10987
Protoss_Nexus 2 9791
Protoss_Robotics_Facility 1 9895
Protoss_Observatory 1 9987
10987
