Protoss_Gateway 3 10445
Protoss_Assimilator 2 10248
Protoss_Cybernetics_Core 1 4328
Protoss_Dragoon 11 10499
Protoss_Robotics_Facility 1 7459
Protoss_Observatory 1 7615
Protoss_Observer 2 10563
Protoss_Nexus 1 10685
Protoss_Citadel_of_Adun 1 10825
10825
