Protoss_Gateway 3 11298
Protoss_Zealot 1 3769
Protoss_Assimilator 1 4093
Protoss_Cybernetics_Core 1 5431
Protoss_Dragoon 7 10431
Protoss_Nexus 2 11365
Protoss_Robotics_Facility 1 9887
Protoss_Observatory 1 10198
11365
