Protoss_Gateway 2 9547
Protoss_Assimilator 2 9707
Protoss_Cybernetics_Core 1 4265
Protoss_Zealot 1 4055
Protoss_Dragoon 9 11125
Protoss_Citadel_of_Adun 1 6693
Protoss_Templar_Archives 1 7710
Protoss_Dark_Templar 1 8493
Protoss_Nexus 1 10809
Protoss_Robotics_Facility 1 9858
Protoss_Observatory 1 10090
Protoss_Observer 1 10891
11125
