Protoss_Gateway 2 5138
Protoss_Assimilator 2 9999
Protoss_Cybernetics_Core 1 4609
Protoss_Dragoon 8 10589
Protoss_Nexus 1 10213
Protoss_Robotics_Facility 1 9711
Protoss_Observatory 1 10065
Protoss_Citadel_of_Adun 1 11125
Protoss_Observer 1 10873
11125
