Protoss_Gateway 2 8794
Protoss_Assimilator 1 3236
Protoss_Cybernetics_Core 1 4445
Protoss_Zealot 1 4443
Protoss_Dragoon 9 11075
Protoss_Nexus 1 9089
Protoss_Robotics_Facility 1 8843
Protoss_Observatory 1 9028
Protoss_Shuttle 1 10095
Protoss_Robotics_Support_Bay 1 10254
Protoss_Observer 1 10517
11075
