Protoss_Gateway 3 11117
Protoss_Assimilator 1 3324
Protoss_Cybernetics_Core 1 4425
Protoss_Dragoon 7 11133
Protoss_Robotics_Facility 1 6247
Protoss_Shuttle 1 7219
Protoss_Zealot 2 7813
Protoss_Robotics_Support_Bay 1 7199
Protoss_Reaver 1 8769
Protoss_Nexus 1 10890
Protoss_Observatory 1 9338
Protoss_Observer 1 10137
Protoss_Citadel_of_Adun 1 11424
11424
