Protoss_Gateway 2 9203
Protoss_Assimilator 2 10806
Protoss_Cybernetics_Core 1 4395
Protoss_Dragoon 9 11145
Protoss_Robotics_Facility 1 6336
Protoss_Zealot 1 6431
Protoss_Observatory 1 6581
Protoss_Observer 3 9515
Protoss_Nexus 2 11598
Protoss_Citadel_of_Adun 1 10853
11598
