Protoss_Nexus 1 5621
Protoss_Gateway 3 11022
Protoss_Assimilator 1 4519
Protoss_Cybernetics_Core 1 5633
Protoss_Zealot 1 5357
Protoss_Dragoon 7 9923
Protoss_Robotics_Facility 1 9440
Protoss_Shuttle 1 10277
Protoss_Robotics_Support_Bay 1 9964
Protoss_Reaver 1 11551
11551
