Protoss_Gateway 2 8677
Protoss_Assimilator 2 9445
Protoss_Cybernetics_Core 1 4346
Protoss_Dragoon 9 10703
Protoss_Robotics_Facility 1 6205
Protoss_Zealot 1 6351
Protoss_Observatory 1 6400
Protoss_Observer 2 7945
Protoss_Nexus 1 9580
Protoss_Citadel_of_Adun 1 9161
Protoss_Templar_Archives 1 10465
Protoss_Shuttle 1 11197
11197
