Protoss_Nexus 1 5561
Protoss_Gateway 2 5502
Protoss_Assimilator 2 10865
Protoss_Cybernetics_Core 1 5579
Protoss_Zealot 4 8693
Protoss_Dragoon 9 11145
Protoss_Robotics_Facility 1 11395
11395
