Protoss_Gateway 2 7090
Protoss_Assimilator 1 3479
Protoss_Cybernetics_Core 1 4691
Protoss_Zealot 1 4361
Protoss_Dragoon 12 10977
Protoss_Robotics_Facility 1 8812
Protoss_Shuttle 1 9621
Protoss_Robotics_Support_Bay 1 9111
Protoss_Reaver 1 10865
10977
