Protoss_Gateway 2 8028
Protoss_Assimilator 2 10499
Protoss_Cybernetics_Core 1 4417
Protoss_Dragoon 9 11009
Protoss_Robotics_Facility 1 6337
Protoss_Observatory 1 6689
Protoss_Zealot 1 7253
Protoss_Observer 2 8063
Protoss_Nexus 2 11916
Protoss_Citadel_of_Adun 1 9418
Protoss_Templar_Archives 1 10673
11916
