Protoss_Gateway 2 6667
Protoss_Assimilator 1 3439
Protoss_Cybernetics_Core 1 4505
Protoss_Dragoon 13 10653
Protoss_Robotics_Facility 1 8747
Protoss_Shuttle 1 9547
Protoss_Robotics_Support_Bay 1 9463
10653
