Protoss_Nexus 1 5464
Protoss_Gateway 2 5582
Protoss_Assimilator 2 9689
Protoss_Cybernetics_Core 1 5327
Protoss_Zealot 1 5429
Protoss_Dragoon 12 10753
Protoss_Robotics_Facility 1 8844
Protoss_Observatory 1 9048
Protoss_Observer 2 10645
10753
