Protoss_Gateway 4 9864
Protoss_Assimilator 1 3253
Protoss_Cybernetics_Core 1 4406
Protoss_Dragoon 10 10567
Protoss_Robotics_Facility 1 6330
Protoss_Zealot 1 6413
Protoss_Observatory 1 6544
Protoss_Observer 2 7931
Protoss_Nexus 1 9959
Protoss_Shuttle 1 11287
11287
