Protoss_Gateway 2 7705
Protoss_Assimilator 2 9948
Protoss_Cybernetics_Core 1 4393
Protoss_Dragoon 7 10991
Protoss_Robotics_Facility 1 6237
Protoss_Zealot 2 10795
Protoss_Observatory 1 6441
Protoss_Observer 2 7875
Protoss_Nexus 1 10380
Protoss_Citadel_of_Adun 1 9361
Protoss_Templar_Archives 1 10449
Protoss_Shuttle 1 10961
Protoss_Stargate 1 11211
11211
