Protoss_Gateway 5 11223
Protoss_Assimilator 1 3275
Protoss_Cybernetics_Core 1 4452
Protoss_Dragoon 7 11105
Protoss_Robotics_Facility 1 6394
Protoss_Zealot 4 9903
Protoss_Observatory 1 6605
Protoss_Observer 2 7991
Protoss_Nexus 1 10248
Protoss_Shuttle 1 10313
Protoss_Citadel_of_Adun 1 10602
11223
