Protoss_Gateway 3 7428
Protoss_Assimilator 1 3319
Protoss_Cybernetics_Core 1 4320
Protoss_Dragoon 8 9349
Protoss_Zealot 2 8131
Protoss_Robotics_Facility 1 6696
Protoss_Observatory 1 6915
Protoss_Observer 1 8011
Protoss_Nexus 2 12321
12321
