Protoss_Gateway 2 9319
Protoss_Assimilator 1 2294
Protoss_Cybernetics_Core 1 2908
Protoss_Dragoon 6 9245
Protoss_Robotics_Facility 1 4325
Protoss_Zealot 1 5437
Protoss_Shuttle 1 5729
Protoss_Robotics_Support_Bay 1 6391
Protoss_Reaver 1 6921
Protoss_Observatory 1 7488
Protoss_Observer 2 9381
Protoss_Nexus 1 8502
Protoss_Scarab 5 9121
Protoss_Citadel_of_Adun 1 9691
9691
