Protoss_Gateway 2 7321
Protoss_Assimilator 3 10919
Protoss_Zealot 2 6975
Protoss_Nexus 1 7831
Protoss_Cybernetics_Core 1 6763
Protoss_Dragoon 9 10929
Protoss_Robotics_Facility 1 11586
11586
