Protoss_Gateway 3 8088
Protoss_Assimilator 1 3141
Protoss_Cybernetics_Core 1 4285
Protoss_Dragoon 13 10859
Protoss_Robotics_Facility 1 7635
Protoss_Zealot 3 10005
Protoss_Observatory 1 7813
Protoss_Shuttle 1 8965
Protoss_Observer 1 9387
10859
