Protoss_Gateway 3 9553
Protoss_Assimilator 2 10031
Protoss_Cybernetics_Core 1 4352
Protoss_Dragoon 10 10847
Protoss_Nexus 1 8679
Protoss_Robotics_Facility 1 9042
Protoss_Zealot 1 9343
Protoss_Citadel_of_Adun 1 10238
Protoss_Observatory 1 9573
Protoss_Observer 1 10345
Protoss_Templar_Archives 1 11411
11411
