Protoss_Gateway 4 10640
Protoss_Assimilator 2 10574
Protoss_Cybernetics_Core 1 4709
Protoss_Zealot 1 4581
Protoss_Dragoon 7 11051
Protoss_Citadel_of_Adun 1 6505
Protoss_Templar_Archives 1 7517
Protoss_Nexus 2 9737
Protoss_Dark_Templar 2 9159
Protoss_Robotics_Facility 1 9765
Protoss_Observatory 1 10097
Protoss_Observer 1 10869
11051
