Protoss_Nexus 1 5507
Protoss_Gateway 2 5597
Protoss_Assimilator 2 9663
Protoss_Cybernetics_Core 1 5409
Protoss_Zealot 2 6996
Protoss_Dragoon 10 10751
Protoss_Robotics_Facility 1 9920
Protoss_Observatory 1 10086
Protoss_Citadel_of_Adun 1 10861
Protoss_Observer 1 10909
10909
