Protoss_Gateway 3 9578
Protoss_Assimilator 1 3420
Protoss_Cybernetics_Core 1 4377
Protoss_Zealot 1 4351
Protoss_Dragoon 11 11179
Protoss_Robotics_Facility 1 6608
Protoss_Observatory 1 6915
Protoss_Observer 1 7757
Protoss_Nexus 2 11537
11537
