Protoss_Gateway 1 3277
Protoss_Assimilator 1 3191
Protoss_Cybernetics_Core 1 4342
Protoss_Zealot 1 4021
Protoss_Dragoon 8 10461
Protoss_Robotics_Facility 1 7833
Protoss_Shuttle 1 8747
Protoss_Robotics_Support_Bay 1 8082
Protoss_Reaver 1 9889
Protoss_Nexus 1 12492
Protoss_Observatory 1 10496
12492
