Protoss_Assimilator 1 2617
Protoss_Gateway 2 10066
Protoss_Cybernetics_Core 1 4770
Protoss_Zealot 4 6821
Protoss_Robotics_Facility 1 6274
Protoss_Shuttle 3 11052
Protoss_Robotics_Support_Bay 1 7063
Protoss_Observatory 1 7143
Protoss_Dragoon 5 10991
Protoss_Reaver 1 8736
Protoss_Observer 1 9970
11052
