Protoss_Nexus 2 9374
Protoss_Gateway 2 9165
Protoss_Assimilator 2 9783
Protoss_Zealot 2 5881
Protoss_Cybernetics_Core 1 5688
Protoss_Dragoon 7 10941
Protoss_Robotics_Facility 1 9863
Protoss_Citadel_of_Adun 1 9843
Protoss_Observatory 1 10029
Protoss_Templar_Archives 1 10882
Protoss_Shuttle 1 10985
10985
