Protoss_Gateway 3 9220
Protoss_Assimilator 2 10044
Protoss_Cybernetics_Core 1 4459
Protoss_Dragoon 11 11121
Protoss_Nexus 1 8793
Protoss_Robotics_Facility 1 9115
Protoss_Observatory 1 9237
Protoss_Citadel_of_Adun 1 10249
Protoss_Observer 1 10583
Protoss_Templar_Archives 1 11283
11283
