Protoss_Gateway 2 8228
Protoss_Assimilator 1 3329
Protoss_Cybernetics_Core 1 4603
Protoss_Dragoon 7 10380
Protoss_Robotics_Facility 1 7734
Protoss_Shuttle 1 8546
Protoss_Zealot 4 9393
Protoss_Observatory 1 8071
Protoss_Observer 2 9976
Protoss_Robotics_Support_Bay 1 10487
10487
