Protoss_Nexus 1 5453
Protoss_Gateway 4 11277
Protoss_Assimilator 2 7306
Protoss_Cybernetics_Core 1 5586
Protoss_Zealot 1 5471
Protoss_Dragoon 7 11173
Protoss_Citadel_of_Adun 1 8256
Protoss_Robotics_Facility 1 9134
Protoss_Templar_Archives 1 9241
Protoss_Shuttle 2 10225
Protoss_Observatory 1 9458
Protoss_Dark_Templar 2 10075
Protoss_Forge 1 10548
Protoss_Observer 1 10647
11277
