Protoss_Gateway 4 10045
Protoss_Assimilator 1 3349
Protoss_Cybernetics_Core 1 4333
Protoss_Zealot 1 4045
Protoss_Dragoon 11 10903
Protoss_Nexus 1 8932
Protoss_Robotics_Facility 1 8873
Protoss_Observatory 1 9115
Protoss_Observer 2 10915
Protoss_Citadel_of_Adun 1 11396
11396
