Protoss_Assimilator 2 9087
Protoss_Gateway 2 8401
Protoss_Cybernetics_Core 1 4713
Protoss_Zealot 1 4521
Protoss_Dragoon 6 11057
Protoss_Nexus 1 8916
Protoss_Citadel_of_Adun 1 7905
Protoss_Robotics_Facility 1 9299
Protoss_Templar_Archives 1 9027
Protoss_Shuttle 1 10105
Protoss_Dark_Templar 2 10047
Protoss_Observatory 2 10183
Protoss_Stargate 1 11098
Protoss_Observer 1 10527
11098
