Protoss_Gateway 4 10195
Protoss_Assimilator 2 10242
Protoss_Cybernetics_Core 1 4299
Protoss_Zealot 1 4005
Protoss_Dragoon 11 11157
Protoss_Nexus 1 8850
Protoss_Robotics_Facility 1 8781
Protoss_Observatory 1 8999
Protoss_Observer 2 10761
11157
