Protoss_Gateway 2 8558
Protoss_Assimilator 1 3305
Protoss_Cybernetics_Core 1 4428
Protoss_Zealot 1 4101
Protoss_Dragoon 10 10823
Protoss_Nexus 1 9405
Protoss_Robotics_Facility 1 9444
Protoss_Observatory 1 10261
10823
