Protoss_Assimilator 2 10773
Protoss_Gateway 4 10862
Protoss_Cybernetics_Core 1 4703
Protoss_Zealot 1 4513
Protoss_Dragoon 6 10859
Protoss_Citadel_of_Adun 1 6397
Protoss_Robotics_Facility 1 7382
Protoss_Templar_Archives 1 7389
Protoss_Shuttle 1 8189
Protoss_Dark_Templar 4 8917
Protoss_Nexus 1 10869
Protoss_Observatory 1 8995
Protoss_Observer 1 9955
10869
