Protoss_Gateway 2 6615
Protoss_Assimilator 1 3491
Protoss_Zealot 2 4655
Protoss_Cybernetics_Core 1 4965
Protoss_Dragoon 10 10389
Protoss_Nexus 2 12634
Protoss_Robotics_Facility 1 10547
12634
