Protoss_Gateway 2 9186
Protoss_Assimilator 1 3144
Protoss_Cybernetics_Core 1 4283
Protoss_Dragoon 9 10951
Protoss_Zealot 1 5697
Protoss_Robotics_Facility 1 6791
Protoss_Observatory 1 6933
Protoss_Observer 3 9183
Protoss_Nexus 1 9817
10951
