Protoss_Gateway 4 11063
Protoss_Assimilator 1 3184
Protoss_Zealot 1 3821
Protoss_Cybernetics_Core 1 5089
Protoss_Dragoon 9 11053
Protoss_Nexus 2 10395
Protoss_Robotics_Facility 1 9753
Protoss_Observatory 1 9947
Protoss_Observer 1 10883
11063
