Protoss_Gateway 3 9043
Protoss_Assimilator 2 9365
Protoss_Cybernetics_Core 1 4375
Protoss_Dragoon 10 10835
Protoss_Nexus 1 8706
Protoss_Robotics_Facility 1 9014
Protoss_Observatory 1 9195
Protoss_Citadel_of_Adun 1 9940
Protoss_Observer 1 10059
Protoss_Templar_Archives 1 11159
Protoss_Zealot 1 10745
11159
