Protoss_Assimilator 1 2753
Protoss_Gateway 2 7479
Protoss_Cybernetics_Core 1 4753
Protoss_Robotics_Facility 1 6338
Protoss_Dragoon 6 10241
Protoss_Observatory 1 6516
Protoss_Observer 3 9518
Protoss_Shuttle 1 9096
Protoss_Forge 1 9063
Protoss_Robotics_Support_Bay 1 9112
Protoss_Photon_Cannon 1 10130
Protoss_Reaver 1 10840
10840
