Protoss_Gateway 4 10917
Protoss_Assimilator 2 9080
Protoss_Cybernetics_Core 1 4389
Protoss_Dragoon 8 10809
Protoss_Nexus 1 8974
Protoss_Robotics_Facility 1 8202
Protoss_Observatory 1 8293
Protoss_Citadel_of_Adun 1 9385
Protoss_Observer 2 10453
Protoss_Stargate 1 10623
Protoss_Templar_Archives 1 10599
10917
