Protoss_Gateway 2 7357
Protoss_Assimilator 1 3363
Protoss_Cybernetics_Core 1 4616
Protoss_Robotics_Facility 1 6153
Protoss_Dragoon 7 10586
Protoss_Observatory 1 6323
Protoss_Observer 2 7713
Protoss_Zealot 2 8023
Protoss_Shuttle 1 9051
Protoss_Robotics_Support_Bay 1 9288
10586
