Protoss_Gateway 4 10328
Protoss_Assimilator 1 3183
Protoss_Cybernetics_Core 1 4282
Protoss_Robotics_Facility 1 5938
Protoss_Dragoon 8 11183
Protoss_Observatory 1 6108
Protoss_Observer 4 10581
Protoss_Nexus 2 11287
11287
