Protoss_Gateway 2 6223
Protoss_Assimilator 2 10245
Protoss_Cybernetics_Core 1 4617
Protoss_Nexus 1 6991
Protoss_Dragoon 13 10739
Protoss_Robotics_Facility 1 9493
Protoss_Observatory 1 9951
Protoss_Shuttle 1 10745
10745
