Protoss_Gateway 2 7382
Protoss_Assimilator 1 3173
Protoss_Zealot 1 3927
Protoss_Cybernetics_Core 1 5021
Protoss_Dragoon 13 11199
Protoss_Robotics_Facility 1 7581
Protoss_Observatory 1 7759
Protoss_Observer 2 10237
Protoss_Nexus 1 12777
12777
