Protoss_Gateway 2 9597
Protoss_Assimilator 1 3381
Protoss_Cybernetics_Core 1 4419
Protoss_Zealot 2 9545
Protoss_Dragoon 6 10437
Protoss_Nexus 1 8331
Protoss_Robotics_Facility 1 7798
Protoss_Shuttle 1 8767
Protoss_Robotics_Support_Bay 1 8499
Protoss_Reaver 1 9987
Protoss_Observatory 1 9435
Protoss_Observer 1 10319
10437
