Protoss_Gateway 3 8905
Protoss_Assimilator 2 10252
Protoss_Cybernetics_Core 1 4285
Protoss_Dragoon 11 10495
Protoss_Nexus 2 12699
Protoss_Robotics_Facility 1 8821
Protoss_Observatory 1 9053
Protoss_Observer 2 10431
12699
