Protoss_Gateway 2 5554
Protoss_Assimilator 1 3334
Protoss_Zealot 4 9677
Protoss_Cybernetics_Core 1 5110
Protoss_Dragoon 8 10519
Protoss_Nexus 1 9839
Protoss_Robotics_Facility 1 9359
Protoss_Shuttle 1 10325
Protoss_Robotics_Support_Bay 1 9857
Protoss_Reaver 1 11467
11467
