Protoss_Gateway 4 10455
Protoss_Assimilator 2 9509
Protoss_Cybernetics_Core 1 4267
Protoss_Zealot 1 4039
Protoss_Citadel_of_Adun 1 5267
Protoss_Dragoon 7 10719
Protoss_Templar_Archives 1 6284
Protoss_Dark_Templar 1 7027
Protoss_Nexus 1 9019
Protoss_Robotics_Facility 1 8639
Protoss_Observatory 1 8804
Protoss_Observer 2 10397
10719
