Protoss_Gateway 1 3559
Protoss_Assimilator 1 3620
Protoss_Zealot 2 5761
Protoss_Cybernetics_Core 1 5639
Protoss_Robotics_Facility 1 7378
Protoss_Dragoon 2 8301
Protoss_Observatory 1 7478
Protoss_Shuttle 1 8211
Protoss_Forge 1 7852
Protoss_Observer 1 8633
Protoss_Robotics_Support_Bay 1 8443
Protoss_Reaver 1 9986
Protoss_Photon_Cannon 1 9940
9986
