Protoss_Gateway 4 9708
Protoss_Assimilator 1 3125
Protoss_Cybernetics_Core 1 4239
Protoss_Dragoon 10 10951
Protoss_Robotics_Facility 1 7490
Protoss_Nexus 1 9740
Protoss_Observatory 1 7623
Protoss_Observer 1 8473
Protoss_Shuttle 1 10469
10951
