Protoss_Gateway 3 10268
Protoss_Assimilator 1 3499
Protoss_Cybernetics_Core 1 4628
Protoss_Robotics_Facility 1 6278
Protoss_Dragoon 8 11021
Protoss_Observatory 1 6566
Protoss_Nexus 1 9235
Protoss_Observer 3 9051
11021
