Protoss_Gateway 2 11353
Protoss_Assimilator 1 3446
Protoss_Cybernetics_Core 1 4457
Protoss_Zealot 1 4259
Protoss_Robotics_Facility 1 6296
Protoss_Dragoon 6 11095
Protoss_Shuttle 1 7107
Protoss_Robotics_Support_Bay 1 6742
Protoss_Reaver 1 8551
Protoss_Observatory 1 8294
Protoss_Observer 2 10159
Protoss_Nexus 1 12250
12250
