Protoss_Gateway 4 11117
Protoss_Assimilator 1 3302
Protoss_Cybernetics_Core 1 4330
Protoss_Zealot 1 4153
Protoss_Citadel_of_Adun 1 5399
Protoss_Dragoon 7 10329
Protoss_Templar_Archives 1 6445
Protoss_Dark_Templar 2 7197
Protoss_Nexus 1 9581
Protoss_Robotics_Facility 1 9735
Protoss_Observatory 1 10103
11117
