Protoss_Gateway 1 2178
Protoss_Assimilator 1 2608
Protoss_Cybernetics_Core 1 3299
Protoss_Dragoon 3 6148
Protoss_Robotics_Facility 1 4842
Protoss_Zealot 1 7731
Protoss_Shuttle 1 7791
7791
