Protoss_Gateway 2 7164
Protoss_Assimilator 1 3582
Protoss_Cybernetics_Core 1 4796
Protoss_Dragoon 9 11166
Protoss_Robotics_Facility 1 7184
Protoss_Observatory 1 7571
Protoss_Observer 2 9161
Protoss_Shuttle 1 10243
Protoss_Nexus 1 12238
12238
