Protoss_Gateway 5 10894
Protoss_Assimilator 2 9207
Protoss_Cybernetics_Core 1 4377
Protoss_Dragoon 7 9807
Protoss_Nexus 1 8631
Protoss_Robotics_Facility 1 7969
Protoss_Observatory 1 8203
Protoss_Citadel_of_Adun 1 9267
Protoss_Observer 1 9115
Protoss_Templar_Archives 1 10689
Protoss_Zealot 3 10933
10933
