Protoss_Gateway 2 7297
Protoss_Assimilator 1 3801
Protoss_Cybernetics_Core 1 4696
Protoss_Zealot 1 4546
Protoss_Dragoon 5 8806
Protoss_Citadel_of_Adun 1 7733
Protoss_Templar_Archives 1 8792
Protoss_Nexus 1 11401
Protoss_Dark_Templar 3 10941
Protoss_Robotics_Facility 1 11428
11428
