Protoss_Gateway 2 6255
Protoss_Nexus 2 10210
Protoss_Zealot 1 4087
Protoss_Assimilator 2 8010
Protoss_Cybernetics_Core 1 5578
Protoss_Dragoon 7 9996
Protoss_Robotics_Facility 1 8745
Protoss_Observatory 1 8995
Protoss_Observer 2 10391
Protoss_Citadel_of_Adun 1 10469
Protoss_Forge 1 10056
Protoss_Stargate 1 11388
Protoss_Photon_Cannon 1 11196
11388
