Protoss_Nexus 1 5499
Protoss_Gateway 2 5707
Protoss_Assimilator 2 8485
Protoss_Cybernetics_Core 1 5533
Protoss_Zealot 1 5483
Protoss_Dragoon 11 10447
Protoss_Robotics_Facility 1 8973
Protoss_Citadel_of_Adun 1 9797
Protoss_Shuttle 1 9849
Protoss_Robotics_Support_Bay 1 9833
Protoss_Templar_Archives 1 10835
Protoss_Stargate 1 11209
Protoss_Reaver 1 11329
11329
