Protoss_Gateway 2 6918
Protoss_Assimilator 1 3320
Protoss_Zealot 2 4921
Protoss_Cybernetics_Core 1 5049
Protoss_Dragoon 10 10357
Protoss_Nexus 1 9966
Protoss_Robotics_Facility 1 10442
10442
