Protoss_Gateway 4 10867
Protoss_Assimilator 1 3393
Protoss_Cybernetics_Core 1 4666
Protoss_Robotics_Facility 1 6209
Protoss_Observatory 1 6336
Protoss_Dragoon 8 10727
Protoss_Observer 3 9485
Protoss_Shuttle 1 8461
Protoss_Nexus 1 11135
11135
