Protoss_Gateway 2 8878
Protoss_Assimilator 1 3393
Protoss_Cybernetics_Core 1 4339
Protoss_Zealot 2 10443
Protoss_Dragoon 9 11129
Protoss_Nexus 1 9127
Protoss_Robotics_Facility 1 9019
Protoss_Shuttle 1 9843
Protoss_Robotics_Support_Bay 1 9498
Protoss_Reaver 1 11125
Protoss_Observatory 1 10553
11129
