Protoss_Assimilator 3 8924
Protoss_Gateway 2 7053
Protoss_Zealot 3 5873
Protoss_Nexus 1 7683
Protoss_Cybernetics_Core 1 6743
Protoss_Dragoon 8 10057
Protoss_Stargate 2 11589
Protoss_Fleet_Beacon 1 11027
11589
