Protoss_Gateway 2 7632
Protoss_Assimilator 1 3548
Protoss_Cybernetics_Core 1 4514
Protoss_Dragoon 4 10211
Protoss_Citadel_of_Adun 1 6468
Protoss_Templar_Archives 1 7463
Protoss_Robotics_Facility 1 8485
Protoss_Dark_Templar 3 8963
Protoss_Shuttle 1 9386
Protoss_Observatory 1 9098
Protoss_Observer 1 9921
Protoss_Nexus 1 12436
12436
