Protoss_Gateway 3 8249
Protoss_Assimilator 1 3207
Protoss_Cybernetics_Core 1 4410
Protoss_Zealot 1 4147
Protoss_Dragoon 13 10843
Protoss_Robotics_Facility 1 8042
Protoss_Observatory 1 8405
Protoss_Observer 2 9903
10843
