Protoss_Gateway 3 11318
Protoss_Assimilator 1 3310
Protoss_Cybernetics_Core 1 4697
Protoss_Zealot 2 8571
Protoss_Dragoon 7 11116
Protoss_Robotics_Facility 1 7588
Protoss_Shuttle 1 8421
Protoss_Robotics_Support_Bay 1 8103
Protoss_Reaver 1 9646
Protoss_Observatory 1 9396
Protoss_Observer 1 10176
11318
