Protoss_Gateway 2 9995
Protoss_Assimilator 1 3477
Protoss_Cybernetics_Core 1 4672
Protoss_Dragoon 7 11046
Protoss_Robotics_Facility 1 6780
Protoss_Shuttle 2 11431
Protoss_Robotics_Support_Bay 1 7103
Protoss_Reaver 1 8733
Protoss_Observatory 1 7896
Protoss_Observer 1 9336
Protoss_Scarab 7 9615
11431
