Protoss_Gateway 2 8245
Protoss_Assimilator 1 3322
Protoss_Cybernetics_Core 1 4524
Protoss_Dragoon 10 11076
Protoss_Robotics_Facility 1 7218
Protoss_Observatory 1 7341
Protoss_Observer 3 10558
Protoss_Shuttle 1 10136
Protoss_Nexus 1 12323
12323
