Protoss_Gateway 2 7298
Protoss_Assimilator 1 3512
Protoss_Cybernetics_Core 1 4488
Protoss_Dragoon 6 10566
Protoss_Robotics_Facility 1 7275
Protoss_Shuttle 1 8081
Protoss_Robotics_Support_Bay 1 7517
Protoss_Reaver 1 9306
Protoss_Observatory 1 8957
Protoss_Zealot 1 9336
Protoss_Observer 1 9756
Protoss_Scarab 2 9766
10566
