Protoss_Gateway 3 11058
Protoss_Assimilator 2 10929
Protoss_Cybernetics_Core 1 4643
Protoss_Dragoon 5 9556
Protoss_Citadel_of_Adun 1 6059
Protoss_Templar_Archives 1 7120
Protoss_Dark_Templar 4 10526
Protoss_Robotics_Facility 1 9422
Protoss_Nexus 1 12522
12522
