Protoss_Nexus 1 5593
Protoss_Gateway 4 11038
Protoss_Assimilator 2 7709
Protoss_Cybernetics_Core 1 5511
Protoss_Zealot 1 5719
Protoss_Dragoon 12 10967
Protoss_Robotics_Facility 1 9443
Protoss_Observatory 1 9759
Protoss_Citadel_of_Adun 1 10579
Protoss_Observer 1 10683
11038
