Protoss_Gateway 4 11418
Protoss_Assimilator 1 3666
Protoss_Zealot 1 4041
Protoss_Cybernetics_Core 1 4843
Protoss_Dragoon 7 10891
Protoss_Robotics_Facility 1 8077
Protoss_Observatory 1 8208
Protoss_Observer 2 9696
Protoss_Nexus 1 11822
Protoss_Shuttle 1 10876
11822
