Protoss_Gateway 4 10601
Protoss_Assimilator 2 9237
Protoss_Cybernetics_Core 1 4531
Protoss_Dragoon 5 10501
Protoss_Nexus 1 8866
Protoss_Citadel_of_Adun 1 7626
Protoss_Templar_Archives 1 8682
Protoss_Stargate 1 9184
Protoss_Dark_Templar 1 9563
Protoss_Arbiter_Tribunal 1 10132
10601
