Protoss_Gateway 3 10202
Protoss_Assimilator 2 10271
Protoss_Cybernetics_Core 1 4426
Protoss_Dragoon 9 10089
Protoss_Nexus 1 10255
Protoss_Robotics_Facility 1 9893
Protoss_Citadel_of_Adun 1 10666
Protoss_Observatory 1 10125
10666
