Protoss_Gateway 3 8042
Protoss_Assimilator 1 3436
Protoss_Cybernetics_Core 1 4517
Protoss_Nexus 1 7444
Protoss_Dragoon 9 9929
Protoss_Zealot 4 10441
Protoss_Robotics_Facility 1 11102
11102
