Protoss_Nexus 2 11687
Protoss_Gateway 2 5579
Protoss_Assimilator 1 4325
Protoss_Cybernetics_Core 1 5490
Protoss_Zealot 2 9468
Protoss_Dragoon 10 10585
Protoss_Robotics_Facility 1 10230
Protoss_Shuttle 1 11055
11687
