Protoss_Gateway 1 3393
Protoss_Assimilator 1 3490
Protoss_Cybernetics_Core 1 4530
Protoss_Robotics_Facility 1 6168
Protoss_Dragoon 4 11013
Protoss_Shuttle 1 7051
Protoss_Robotics_Support_Bay 1 6948
Protoss_Reaver 2 10321
Protoss_Zealot 3 10171
Protoss_Scarab 3 9083
Protoss_Nexus 1 12769
Protoss_Observatory 1 10611
12769
