Protoss_Gateway 2 5641
Protoss_Assimilator 1 3345
Protoss_Cybernetics_Core 1 5069
Protoss_Dragoon 6 10439
Protoss_Citadel_of_Adun 1 8089
Protoss_Robotics_Facility 1 8916
Protoss_Observatory 1 9042
Protoss_Zealot 2 9523
Protoss_Observer 2 10465
Protoss_Forge 1 10396
10465
