Protoss_Gateway 2 7562
Protoss_Assimilator 1 3693
Protoss_Cybernetics_Core 1 4738
Protoss_Dragoon 8 11151
Protoss_Robotics_Facility 1 7678
Protoss_Shuttle 1 8486
Protoss_Observatory 1 7846
Protoss_Observer 2 9626
Protoss_Citadel_of_Adun 1 9533
Protoss_Nexus 1 12316
12316
