Protoss_Gateway 2 6299
Protoss_Assimilator 1 3335
Protoss_Cybernetics_Core 1 4455
Protoss_Dragoon 6 8159
Protoss_Citadel_of_Adun 1 6958
Protoss_Templar_Archives 1 8193
Protoss_Dark_Templar 3 9693
Protoss_Nexus 1 11285
Protoss_Robotics_Facility 1 11423
11423
