Protoss_Nexus 1 5437
Protoss_Gateway 2 8669
Protoss_Assimilator 2 6566
Protoss_Cybernetics_Core 1 5427
Protoss_Zealot 2 6063
Protoss_Dragoon 10 11137
Protoss_Citadel_of_Adun 1 8366
Protoss_Robotics_Facility 1 9595
Protoss_Templar_Archives 1 9535
Protoss_Stargate 1 9858
Protoss_Observatory 1 9777
Protoss_Dark_Templar 1 10385
Protoss_Arbiter_Tribunal 1 10797
Protoss_Observer 1 10605
11137
