Protoss_Gateway 3 11083
Protoss_Assimilator 1 3225
Protoss_Cybernetics_Core 1 4661
Protoss_Dragoon 9 10173
Protoss_Nexus 1 9893
Protoss_Robotics_Facility 1 10022
Protoss_Observatory 1 10174
Protoss_Citadel_of_Adun 1 11367
11367
