Protoss_Nexus 2 10783
Protoss_Gateway 3 9690
Protoss_Assimilator 3 6910
Protoss_Cybernetics_Core 1 5563
Protoss_Dragoon 7 11075
Protoss_Citadel_of_Adun 1 6865
Protoss_Robotics_Facility 1 11173
Protoss_Templar_Archives 1 10869
Protoss_Stargate 1 11208
11208
