Protoss_Nexus 1 5527
Protoss_Gateway 5 10619
Protoss_Assimilator 2 5697
Protoss_Cybernetics_Core 1 5651
Protoss_Dragoon 8 10693
Protoss_Robotics_Facility 1 8141
Protoss_Citadel_of_Adun 1 8269
Protoss_Observatory 1 8265
Protoss_Templar_Archives 1 9329
Protoss_Observer 4 10863
Protoss_Stargate 1 9782
Protoss_Dark_Templar 2 10447
10863
