Protoss_Gateway 2 5024
Protoss_Assimilator 1 3229
Protoss_Cybernetics_Core 1 4379
Protoss_Dragoon 10 10285
Protoss_Robotics_Facility 1 8671
Protoss_Observatory 1 8892
Protoss_Zealot 2 9443
Protoss_Observer 1 9935
Protoss_Nexus 1 12490
Protoss_Robotics_Support_Bay 1 10591
12490
