Protoss_Gateway 3 6881
Protoss_Assimilator 2 4910
Protoss_Cybernetics_Core 1 4324
Protoss_Dragoon 5 7651
Protoss_Nexus 2 11961
Protoss_Robotics_Facility 1 9755
Protoss_Citadel_of_Adun 1 9950
Protoss_Shuttle 1 10557
Protoss_Robotics_Support_Bay 1 10204
Protoss_Templar_Archives 1 11178
11961
