Protoss_Gateway 1 2031
Protoss_Assimilator 1 2601
Protoss_Cybernetics_Core 1 3198
Protoss_Dragoon 4 9726
Protoss_Robotics_Facility 1 4743
Protoss_Shuttle 1 6726
Protoss_Robotics_Support_Bay 1 6798
Protoss_Nexus 1 7123
Protoss_Reaver 3 9735
Protoss_Scarab 5 9979
9979
