Protoss_Gateway 4 11435
Protoss_Assimilator 2 10535
Protoss_Cybernetics_Core 1 4487
Protoss_Dragoon 8 9451
Protoss_Nexus 1 8925
Protoss_Citadel_of_Adun 1 9273
Protoss_Templar_Archives 1 10589
11435
