Protoss_Gateway 2 8181
Protoss_Assimilator 1 3433
Protoss_Cybernetics_Core 1 4463
Protoss_Dragoon 10 10931
Protoss_Nexus 2 11953
Protoss_Robotics_Facility 1 8501
Protoss_Observatory 1 8791
Protoss_Observer 2 10907
Protoss_Citadel_of_Adun 1 11350
11953
