Protoss_Gateway 3 8071
Protoss_Assimilator 1 3448
Protoss_Cybernetics_Core 1 4556
Protoss_Dragoon 9 10781
Protoss_Robotics_Facility 1 7469
Protoss_Observatory 1 7663
Protoss_Zealot 4 8991
Protoss_Observer 2 10546
Protoss_Shuttle 1 9821
10781
