Protoss_Gateway 3 8883
Protoss_Assimilator 1 3456
Protoss_Cybernetics_Core 1 4817
Protoss_Dragoon 10 10651
Protoss_Robotics_Facility 1 8112
Protoss_Nexus 1 10061
Protoss_Observatory 1 8267
Protoss_Observer 2 9693
Protoss_Robotics_Support_Bay 1 9571
Protoss_Zealot 2 10655
Protoss_Reaver 1 11205
11205
