Protoss_Gateway 2 9311
Protoss_Assimilator 2 9823
Protoss_Cybernetics_Core 1 4411
Protoss_Zealot 1 4089
Protoss_Dragoon 7 10803
Protoss_Citadel_of_Adun 1 6783
Protoss_Templar_Archives 1 7838
Protoss_Dark_Templar 1 8627
Protoss_Nexus 1 10471
Protoss_Stargate 1 10481
10803
