Protoss_Gateway 2 6441
Protoss_Assimilator 1 3449
Protoss_Cybernetics_Core 1 4419
Protoss_Dragoon 5 8767
Protoss_Nexus 1 9198
Protoss_Zealot 2 7567
Protoss_Robotics_Facility 1 9001
Protoss_Robotics_Support_Bay 1 9116
Protoss_Shuttle 1 10107
Protoss_Observatory 1 9652
Protoss_Reaver 1 11249
11249
