Protoss_Gateway 3 11278
Protoss_Assimilator 2 8486
Protoss_Cybernetics_Core 1 4447
Protoss_Dragoon 9 10701
Protoss_Nexus 1 9337
Protoss_Citadel_of_Adun 1 9046
Protoss_Robotics_Facility 1 10283
Protoss_Templar_Archives 1 10618
Protoss_Stargate 1 11327
Protoss_Observatory 1 10490
11327
