Protoss_Gateway 3 11179
Protoss_Assimilator 1 3140
Protoss_Cybernetics_Core 1 4274
Protoss_Dragoon 11 11177
Protoss_Nexus 2 10759
Protoss_Robotics_Facility 1 9229
Protoss_Observatory 1 9465
Protoss_Observer 2 10867
11179
