Protoss_Gateway 1 3551
Protoss_Assimilator 1 3318
Protoss_Cybernetics_Core 1 4568
Protoss_Dragoon 6 10529
Protoss_Robotics_Facility 1 7295
Protoss_Zealot 2 8049
Protoss_Shuttle 1 8095
Protoss_Observatory 1 7461
Protoss_Robotics_Support_Bay 1 8150
Protoss_Observer 2 10457
Protoss_Reaver 1 9930
Protoss_Nexus 1 12057
12057
