Protoss_Gateway 2 6901
Protoss_Assimilator 3 10935
Protoss_Cybernetics_Core 1 4727
Protoss_Dragoon 8 10529
Protoss_Nexus 2 11673
Protoss_Robotics_Facility 1 9550
Protoss_Observatory 1 9727
Protoss_Observer 1 10569
Protoss_Citadel_of_Adun 1 11248
11673
