Protoss_Gateway 2 6872
Protoss_Assimilator 1 3721
Protoss_Zealot 3 5325
Protoss_Cybernetics_Core 1 5125
Protoss_Dragoon 10 10891
Protoss_Robotics_Facility 2 9469
Protoss_Nexus 1 10081
Protoss_Observatory 1 9647
Protoss_Observer 1 10465
10891
