Protoss_Gateway 2 3903
Protoss_Zealot 8 6471
Protoss_Forge 1 5158
Protoss_Photon_Cannon 4 9294
Protoss_Nexus 1 9937
Protoss_Assimilator 1 8331
Protoss_Cybernetics_Core 1 9971
Protoss_Citadel_of_Adun 1 11260
11260
