Protoss_Gateway 1 3259
Protoss_Assimilator 1 3157
Protoss_Cybernetics_Core 1 4285
Protoss_Dragoon 6 10623
Protoss_Robotics_Facility 1 7227
Protoss_Observatory 1 7362
Protoss_Nexus 1 9940
Protoss_Observer 2 8737
Protoss_Robotics_Support_Bay 1 8517
Protoss_Zealot 2 9539
Protoss_Shuttle 1 9833
Protoss_Reaver 1 10975
10975
