Protoss_Gateway 2 6785
Protoss_Assimilator 2 10113
Protoss_Zealot 1 3890
Protoss_Cybernetics_Core 1 5258
Protoss_Dragoon 9 10696
Protoss_Nexus 1 10187
Protoss_Robotics_Facility 1 9377
Protoss_Stargate 1 10461
Protoss_Observatory 1 9542
Protoss_Observer 2 10925
10925
