Protoss_Gateway 2 8492
Protoss_Assimilator 1 3508
Protoss_Zealot 1 4011
Protoss_Cybernetics_Core 1 4724
Protoss_Dragoon 6 11041
Protoss_Robotics_Facility 1 6658
Protoss_Shuttle 1 7491
Protoss_Robotics_Support_Bay 1 6833
Protoss_Reaver 2 10296
Protoss_Observatory 1 8253
Protoss_Observer 1 10766
11041
