Protoss_Gateway 2 5853
Protoss_Assimilator 1 2333
Protoss_Cybernetics_Core 1 2983
Protoss_Dragoon 6 8356
Protoss_Robotics_Facility 1 4726
Protoss_Zealot 1 5911
Protoss_Shuttle 1 6201
Protoss_Observatory 1 6460
Protoss_Robotics_Support_Bay 1 6889
Protoss_Reaver 2 8801
Protoss_Scarab 4 9958
9958
