Protoss_Gateway 2 10391
Protoss_Assimilator 1 3260
Protoss_Cybernetics_Core 1 4293
Protoss_Dragoon 8 11137
Protoss_Robotics_Facility 1 6791
Protoss_Shuttle 1 7621
Protoss_Robotics_Support_Bay 1 7010
Protoss_Reaver 2 11043
Protoss_Observatory 1 10194
11137
