Protoss_Gateway 2 8760
Protoss_Assimilator 1 3428
Protoss_Cybernetics_Core 1 4608
Protoss_Dragoon 7 9561
Protoss_Robotics_Facility 1 6650
Protoss_Observatory 1 6868
Protoss_Observer 3 10011
Protoss_Nexus 1 11710
Protoss_Zealot 2 10586
Protoss_Shuttle 1 11396
11710
