Protoss_Gateway 4 10747
Protoss_Assimilator 2 9743
Protoss_Zealot 2 4445
Protoss_Cybernetics_Core 1 5098
Protoss_Dragoon 7 11095
Protoss_Nexus 1 9111
Protoss_Robotics_Facility 1 8515
Protoss_Citadel_of_Adun 1 8849
Protoss_Observatory 1 8636
Protoss_Observer 2 10533
Protoss_Templar_Archives 1 10469
11095
