Protoss_Gateway 6 11325
Protoss_Assimilator 1 3213
Protoss_Cybernetics_Core 1 4475
Protoss_Dragoon 9 11129
Protoss_Nexus 2 9491
Protoss_Robotics_Facility 1 9276
Protoss_Observatory 1 9506
Protoss_Observer 1 10315
Protoss_Citadel_of_Adun 1 11148
11325
