Protoss_Nexus 2 11368
Protoss_Gateway 4 10645
Protoss_Assimilator 1 4257
Protoss_Cybernetics_Core 1 5492
Protoss_Zealot 1 5303
Protoss_Dragoon 9 10813
Protoss_Robotics_Facility 1 8322
Protoss_Observatory 1 8495
Protoss_Observer 3 10645
11368
