Protoss_Gateway 2 7497
Protoss_Assimilator 1 3391
Protoss_Cybernetics_Core 1 4505
Protoss_Dragoon 12 10761
Protoss_Robotics_Facility 1 7297
Protoss_Observatory 1 7485
Protoss_Observer 1 8373
Protoss_Nexus 1 11972
11972
