Protoss_Gateway 2 7586
Protoss_Assimilator 1 3620
Protoss_Cybernetics_Core 1 4538
Protoss_Dragoon 4 8446
Protoss_Robotics_Facility 1 7448
Protoss_Robotics_Support_Bay 1 7593
Protoss_Shuttle 1 8341
Protoss_Observatory 1 9247
9247
