Protoss_Gateway 4 10823
Protoss_Assimilator 1 3235
Protoss_Cybernetics_Core 1 4252
Protoss_Nexus 2 11321
Protoss_Dragoon 8 9081
Protoss_Robotics_Facility 1 8688
Protoss_Observatory 1 8982
Protoss_Observer 2 10375
Protoss_Citadel_of_Adun 1 11380
11380
