Protoss_Gateway 2 6222
Protoss_Assimilator 1 3293
Protoss_Cybernetics_Core 1 4477
Protoss_Robotics_Facility 1 5950
Protoss_Dragoon 11 10545
Protoss_Observatory 1 6087
Protoss_Observer 3 9825
Protoss_Shuttle 1 7999
Protoss_Nexus 1 11659
11659
