Protoss_Gateway 2 10939
Protoss_Assimilator 1 3434
Protoss_Cybernetics_Core 1 4570
Protoss_Dragoon 2 10521
Protoss_Robotics_Facility 1 6453
Protoss_Shuttle 1 7526
Protoss_Robotics_Support_Bay 1 6879
Protoss_Zealot 2 8396
Protoss_Reaver 2 10151
Protoss_Observatory 1 8360
Protoss_Nexus 1 11108
11108
