Protoss_Gateway 3 10112
Protoss_Assimilator 1 3390
Protoss_Cybernetics_Core 1 4436
Protoss_Dragoon 8 10456
Protoss_Robotics_Facility 1 8208
Protoss_Zealot 4 9552
Protoss_Shuttle 1 9106
Protoss_Observatory 1 8706
Protoss_Observer 3 10732
10732
