Protoss_Gateway 2 10292
Protoss_Assimilator 1 3459
Protoss_Cybernetics_Core 1 4489
Protoss_Dragoon 3 10458
Protoss_Robotics_Facility 1 6568
Protoss_Shuttle 1 7486
Protoss_Robotics_Support_Bay 1 6958
Protoss_Reaver 2 9728
Protoss_Observatory 1 8670
Protoss_Observer 2 10948
10948
