Protoss_Gateway 3 10571
Protoss_Assimilator 1 3123
Protoss_Zealot 2 4740
Protoss_Cybernetics_Core 1 5243
Protoss_Dragoon 9 9767
Protoss_Robotics_Facility 1 8587
Protoss_Observatory 1 8688
Protoss_Observer 2 10295
Protoss_Nexus 1 11709
11709
