Protoss_Gateway 2 8298
Protoss_Assimilator 1 3489
Protoss_Cybernetics_Core 1 4608
Protoss_Dragoon 6 10773
Protoss_Robotics_Facility 1 6672
Protoss_Observatory 1 6836
Protoss_Observer 3 9081
Protoss_Nexus 1 12140
12140
