Protoss_Gateway 4 11109
Protoss_Assimilator 1 3204
Protoss_Cybernetics_Core 1 4315
Protoss_Dragoon 12 10129
Protoss_Nexus 1 10363
Protoss_Robotics_Facility 1 9601
Protoss_Observatory 1 9747
Protoss_Observer 1 10519
11109
