Protoss_Gateway 2 7743
Protoss_Assimilator 1 3397
Protoss_Cybernetics_Core 1 4458
Protoss_Dragoon 8 10311
Protoss_Robotics_Facility 1 7662
Protoss_Observatory 1 7779
Protoss_Observer 2 9213
Protoss_Nexus 1 11583
11583
