Protoss_Gateway 1 3428
Protoss_Assimilator 1 3291
Protoss_Cybernetics_Core 1 4454
Protoss_Dragoon 7 10213
Protoss_Robotics_Facility 2 7816
Protoss_Shuttle 1 8801
Protoss_Robotics_Support_Bay 1 8261
Protoss_Reaver 2 10995
Protoss_Nexus 1 12691
12691
