Protoss_Gateway 4 11135
Protoss_Assimilator 1 3254
Protoss_Cybernetics_Core 1 4351
Protoss_Dragoon 9 9473
Protoss_Nexus 1 9057
Protoss_Robotics_Facility 1 9070
Protoss_Shuttle 1 9891
Protoss_Zealot 2 10320
Protoss_Observatory 1 9981
Protoss_Citadel_of_Adun 1 11328
11328
