Protoss_Assimilator 1 2873
Protoss_Gateway 3 11133
Protoss_Cybernetics_Core 1 4868
Protoss_Citadel_of_Adun 1 5888
Protoss_Robotics_Facility 1 6598
Protoss_Dragoon 3 10441
Protoss_Templar_Archives 1 7048
Protoss_Shuttle 1 7641
Protoss_Dark_Templar 3 8553
Protoss_Observatory 1 7911
Protoss_Observer 1 8926
Protoss_Nexus 1 11345
11345
