Protoss_Gateway 3 7983
Protoss_Assimilator 2 9162
Protoss_Cybernetics_Core 1 4403
Protoss_Dragoon 9 10639
Protoss_Nexus 1 8574
Protoss_Robotics_Facility 1 7911
Protoss_Observatory 1 8242
Protoss_Observer 3 10823
Protoss_Citadel_of_Adun 1 9860
Protoss_Templar_Archives 1 10946
Protoss_Stargate 1 11311
11311
