Protoss_Gateway 2 8974
Protoss_Assimilator 1 3270
Protoss_Cybernetics_Core 1 4413
Protoss_Dragoon 6 10876
Protoss_Robotics_Facility 1 6473
Protoss_Shuttle 1 7281
Protoss_Observatory 1 6666
Protoss_Robotics_Support_Bay 1 6910
Protoss_Observer 1 7703
Protoss_Reaver 2 10241
Protoss_Scarab 4 9519
10876
