Protoss_Gateway 3 7493
Protoss_Assimilator 1 3460
Protoss_Cybernetics_Core 1 4527
Protoss_Dragoon 6 10585
Protoss_Citadel_of_Adun 1 6743
Protoss_Templar_Archives 1 7729
Protoss_Dark_Templar 5 9713
Protoss_Nexus 1 10999
10999
