Protoss_Assimilator 3 4423
Protoss_Gateway 2 7288
Protoss_Zealot 1 4456
Protoss_Cybernetics_Core 1 5820
Protoss_Dragoon 10 10996
Protoss_Robotics_Facility 1 9203
Protoss_Shuttle 1 10156
Protoss_Robotics_Support_Bay 1 9713
Protoss_Reaver 1 11298
11298
