Protoss_Assimilator 1 2594
Protoss_Gateway 2 7034
Protoss_Cybernetics_Core 1 4697
Protoss_Citadel_of_Adun 1 5723
Protoss_Robotics_Facility 1 6635
Protoss_Templar_Archives 1 6730
Protoss_Dragoon 6 10719
Protoss_Shuttle 1 7723
Protoss_Dark_Templar 2 7929
Protoss_Observatory 1 7685
Protoss_Observer 3 10561
Protoss_Nexus 1 12137
12137
