Protoss_Gateway 2 4909
Protoss_Assimilator 2 3966
Protoss_Zealot 10 7926
Protoss_Cybernetics_Core 1 8658
Protoss_Robotics_Facility 1 10262
Protoss_Dragoon 4 10606
Protoss_Shuttle 1 11081
11081
