Protoss_Gateway 2 7292
Protoss_Assimilator 1 3362
Protoss_Cybernetics_Core 1 4603
Protoss_Robotics_Facility 1 6121
Protoss_Zealot 3 9671
Protoss_Observatory 1 6218
Protoss_Dragoon 8 10841
Protoss_Observer 4 9121
Protoss_Shuttle 1 10203
Protoss_Nexus 1 12399
12399
