Protoss_Gateway 3 9335
Protoss_Assimilator 1 3238
Protoss_Cybernetics_Core 1 4592
Protoss_Robotics_Facility 1 6068
Protoss_Dragoon 8 10125
Protoss_Shuttle 1 6896
Protoss_Observatory 1 6506
Protoss_Observer 4 9264
Protoss_Zealot 3 10637
10637
