Protoss_Gateway 2 7093
Protoss_Assimilator 2 10387
Protoss_Cybernetics_Core 1 4473
Protoss_Dragoon 10 10707
Protoss_Nexus 1 9471
Protoss_Robotics_Facility 1 9593
Protoss_Zealot 2 9769
Protoss_Observatory 1 9723
Protoss_Shuttle 1 10623
Protoss_Observer 1 10583
10707
