Protoss_Gateway 2 6812
Protoss_Assimilator 1 3336
Protoss_Cybernetics_Core 1 4437
Protoss_Dragoon 11 10917
Protoss_Nexus 1 7989
Protoss_Robotics_Facility 1 8691
Protoss_Observatory 1 8797
Protoss_Observer 1 9565
10917
