Protoss_Gateway 1 3698
Protoss_Assimilator 1 3495
Protoss_Cybernetics_Core 1 4785
Protoss_Dragoon 5 11151
Protoss_Robotics_Facility 1 7763
Protoss_Shuttle 1 8641
Protoss_Zealot 1 8355
Protoss_Robotics_Support_Bay 1 8128
Protoss_Reaver 1 9783
Protoss_Nexus 2 12451
Protoss_Observatory 1 10489
12451
