Protoss_Gateway 3 7943
Protoss_Assimilator 1 3579
Protoss_Cybernetics_Core 1 5009
Protoss_Dragoon 10 9951
Protoss_Citadel_of_Adun 1 9374
Protoss_Templar_Archives 1 10393
Protoss_Zealot 3 10584
10584
