Protoss_Gateway 2 7368
Protoss_Assimilator 2 3769
Protoss_Cybernetics_Core 1 4804
Protoss_Citadel_of_Adun 1 5893
Protoss_Dragoon 2 11091
Protoss_Templar_Archives 1 6981
Protoss_Dark_Templar 5 10691
Protoss_Robotics_Facility 1 8843
Protoss_Zealot 1 7941
Protoss_Nexus 1 11993
Protoss_Shuttle 1 10721
11993
