Protoss_Gateway 3 10558
Protoss_Assimilator 1 3358
Protoss_Cybernetics_Core 1 4403
Protoss_Dragoon 10 9903
Protoss_Nexus 1 10553
Protoss_Robotics_Facility 1 10572
Protoss_Zealot 4 10648
Protoss_Observatory 1 10677
10677
