Protoss_Gateway 3 11180
Protoss_Assimilator 1 3197
Protoss_Cybernetics_Core 1 4523
Protoss_Dragoon 10 11161
Protoss_Robotics_Facility 1 8405
Protoss_Nexus 2 12336
Protoss_Observatory 1 8502
Protoss_Observer 2 10231
12336
