Protoss_Gateway 3 11297
Protoss_Assimilator 2 3583
Protoss_Cybernetics_Core 1 4781
Protoss_Dragoon 9 10711
Protoss_Robotics_Facility 1 8038
Protoss_Observatory 1 8425
Protoss_Observer 3 10931
Protoss_Nexus 1 11583
11583
