Protoss_Gateway 3 11398
Protoss_Assimilator 1 3387
Protoss_Zealot 2 9211
Protoss_Cybernetics_Core 1 5645
Protoss_Dragoon 4 8657
Protoss_Stargate 1 7730
Protoss_Citadel_of_Adun 1 8195
Protoss_Scout 1 9116
Protoss_Templar_Archives 1 9372
Protoss_Dark_Templar 3 10906
Protoss_Nexus 1 12438
12438
