Protoss_Gateway 3 10089
Protoss_Assimilator 1 3175
Protoss_Cybernetics_Core 1 4388
Protoss_Dragoon 8 11161
Protoss_Robotics_Facility 1 6404
Protoss_Zealot 2 7091
Protoss_Shuttle 1 7211
Protoss_Robotics_Support_Bay 1 6643
Protoss_Reaver 1 8386
Protoss_Observatory 1 8132
Protoss_Observer 1 9261
Protoss_Scarab 2 8947
Protoss_Citadel_of_Adun 1 11100
11161
