Protoss_Gateway 3 9212
Protoss_Assimilator 1 3489
Protoss_Cybernetics_Core 1 4826
Protoss_Dragoon 7 10426
Protoss_Citadel_of_Adun 1 6000
Protoss_Robotics_Facility 1 7248
Protoss_Nexus 2 11938
Protoss_Observatory 1 7380
Protoss_Observer 4 10448
11938
