Protoss_Gateway 2 4910
Protoss_Assimilator 2 10856
Protoss_Cybernetics_Core 1 4466
Protoss_Dragoon 12 10701
Protoss_Nexus 1 9728
Protoss_Robotics_Facility 1 9240
Protoss_Observatory 1 9347
Protoss_Observer 2 10848
10856
