Protoss_Gateway 3 8637
Protoss_Assimilator 1 3528
Protoss_Cybernetics_Core 1 4579
Protoss_Dragoon 11 10896
Protoss_Robotics_Facility 1 7619
Protoss_Observatory 1 8240
Protoss_Observer 2 9848
Protoss_Nexus 1 12219
12219
