Protoss_Gateway 5 11418
Protoss_Assimilator 1 3372
Protoss_Cybernetics_Core 1 4508
Protoss_Dragoon 8 10761
Protoss_Nexus 1 10203
Protoss_Robotics_Facility 1 9755
Protoss_Observatory 1 9961
Protoss_Observer 1 10756
11418
