Protoss_Gateway 3 10208
Protoss_Assimilator 1 3353
Protoss_Cybernetics_Core 1 4585
Protoss_Dragoon 11 10606
Protoss_Nexus 1 10528
Protoss_Robotics_Facility 1 9818
Protoss_Observatory 1 10218
10606
