Protoss_Gateway 2 7027
Protoss_Assimilator 1 3496
Protoss_Cybernetics_Core 1 4679
Protoss_Dragoon 10 11121
Protoss_Citadel_of_Adun 1 6374
Protoss_Nexus 1 9548
Protoss_Robotics_Facility 1 11515
11515
