Protoss_Gateway 2 6253
Protoss_Assimilator 3 4973
Protoss_Cybernetics_Core 1 4675
Protoss_Dragoon 8 8957
Protoss_Citadel_of_Adun 1 8477
Protoss_Templar_Archives 1 9499
Protoss_Dark_Templar 2 10403
Protoss_Nexus 1 11988
Protoss_Robotics_Facility 1 11621
11988
