Protoss_Gateway 2 7623
Protoss_Assimilator 1 3497
Protoss_Cybernetics_Core 1 4535
Protoss_Dragoon 7 10836
Protoss_Robotics_Facility 1 7479
Protoss_Shuttle 1 8291
Protoss_Robotics_Support_Bay 1 8213
Protoss_Reaver 1 9711
Protoss_Zealot 2 9651
Protoss_Observatory 1 9371
Protoss_Observer 1 10186
Protoss_Scarab 1 9500
10836
