Protoss_Gateway 2 7552
Protoss_Assimilator 1 3304
Protoss_Cybernetics_Core 1 4444
Protoss_Dragoon 11 11178
Protoss_Robotics_Facility 1 7383
Protoss_Observatory 1 7644
Protoss_Observer 2 9626
Protoss_Nexus 1 11944
11944
