Protoss_Gateway 2 7459
Protoss_Assimilator 1 3319
Protoss_Cybernetics_Core 1 4333
Protoss_Dragoon 8 9916
Protoss_Robotics_Facility 1 7648
Protoss_Observatory 1 7795
Protoss_Observer 3 10313
Protoss_Nexus 2 12643
12643
