Protoss_Gateway 3 9814
Protoss_Assimilator 2 10331
Protoss_Cybernetics_Core 1 4820
Protoss_Dragoon 8 11078
Protoss_Citadel_of_Adun 1 7693
Protoss_Templar_Archives 1 8688
Protoss_Nexus 1 10498
Protoss_Dark_Templar 2 9451
Protoss_Stargate 1 11183
Protoss_Zealot 1 10828
11183
