Protoss_Gateway 2 11358
Protoss_Assimilator 2 10564
Protoss_Cybernetics_Core 1 4268
Protoss_Dragoon 5 8189
Protoss_Nexus 1 9059
Protoss_Stargate 2 9533
Protoss_Zealot 2 9383
Protoss_Fleet_Beacon 1 10210
Protoss_Carrier 2 13226
13226
