Protoss_Gateway 2 7993
Protoss_Assimilator 1 3418
Protoss_Cybernetics_Core 1 4523
Protoss_Dragoon 10 10736
Protoss_Robotics_Facility 1 7840
Protoss_Observatory 1 8016
Protoss_Nexus 1 11083
Protoss_Observer 2 10753
11083
