Protoss_Gateway 2 5043
Protoss_Assimilator 1 3458
Protoss_Cybernetics_Core 1 4662
Protoss_Dragoon 10 9293
Protoss_Robotics_Facility 1 8693
Protoss_Observatory 1 8923
Protoss_Shuttle 1 9926
Protoss_Zealot 4 10873
Protoss_Robotics_Support_Bay 1 9989
Protoss_Observer 1 10348
10873
