Protoss_Gateway 2 7338
Protoss_Assimilator 1 3265
Protoss_Cybernetics_Core 1 4530
Protoss_Dragoon 9 9803
Protoss_Robotics_Facility 1 6427
Protoss_Observatory 1 6990
Protoss_Observer 1 7771
Protoss_Nexus 1 12080
Protoss_Stargate 2 11103
12080
