Protoss_Gateway 3 9209
Protoss_Assimilator 1 3643
Protoss_Cybernetics_Core 1 4739
Protoss_Dragoon 9 10836
Protoss_Nexus 1 9223
Protoss_Robotics_Facility 1 10472
Protoss_Observatory 1 10660
10836
