Protoss_Gateway 2 7191
Protoss_Assimilator 1 3553
Protoss_Cybernetics_Core 1 4418
Protoss_Dragoon 7 10668
Protoss_Robotics_Facility 1 6708
Protoss_Shuttle 1 7736
Protoss_Robotics_Support_Bay 1 7513
Protoss_Zealot 2 8126
Protoss_Reaver 1 9081
Protoss_Observatory 1 8829
Protoss_Observer 1 9611
Protoss_Scarab 6 9859
10668
