Protoss_Gateway 2 7393
Protoss_Assimilator 1 3278
Protoss_Cybernetics_Core 1 4608
Protoss_Dragoon 7 9871
Protoss_Robotics_Facility 1 6673
Protoss_Observatory 1 7133
Protoss_Observer 2 10821
Protoss_Nexus 1 11088
11088
