Protoss_Gateway 3 8920
Protoss_Assimilator 1 3279
Protoss_Cybernetics_Core 1 4448
Protoss_Dragoon 11 9983
Protoss_Robotics_Facility 1 7450
Protoss_Observatory 1 7598
Protoss_Observer 1 8431
Protoss_Shuttle 1 10856
Protoss_Zealot 3 10586
10856
