Protoss_Gateway 2 7032
Protoss_Assimilator 1 3398
Protoss_Cybernetics_Core 1 4598
Protoss_Dragoon 10 10688
Protoss_Robotics_Facility 1 6504
Protoss_Observatory 1 6703
Protoss_Observer 2 9226
Protoss_Nexus 1 11089
Protoss_Shuttle 1 11151
11151
