Protoss_Gateway 4 11283
Protoss_Assimilator 1 3425
Protoss_Cybernetics_Core 1 4445
Protoss_Dragoon 9 9756
Protoss_Nexus 2 12056
Protoss_Robotics_Facility 1 9842
Protoss_Observatory 1 10009
Protoss_Observer 1 10936
12056
