Protoss_Gateway 2 7477
Protoss_Assimilator 1 3609
Protoss_Cybernetics_Core 1 4695
Protoss_Robotics_Facility 1 6274
Protoss_Dragoon 6 10399
Protoss_Observatory 1 6365
Protoss_Observer 1 7283
Protoss_Shuttle 2 9477
Protoss_Nexus 1 12618
12618
