Protoss_Gateway 2 7316
Protoss_Assimilator 1 3233
Protoss_Cybernetics_Core 1 4417
Protoss_Dragoon 7 9511
Protoss_Robotics_Facility 1 7000
Protoss_Observatory 1 7096
Protoss_Observer 2 9311
Protoss_Nexus 1 10667
Protoss_Zealot 4 10625
Protoss_Shuttle 1 10731
10731
