Protoss_Gateway 4 11339
Protoss_Assimilator 1 3268
Protoss_Cybernetics_Core 1 4387
Protoss_Dragoon 12 10988
Protoss_Nexus 1 9089
Protoss_Zealot 1 8211
Protoss_Robotics_Facility 1 10617
11339
