Protoss_Gateway 1 3419
Protoss_Assimilator 1 3471
Protoss_Cybernetics_Core 1 4683
Protoss_Robotics_Facility 1 6320
Protoss_Zealot 1 5486
Protoss_Dragoon 6 11195
Protoss_Robotics_Support_Bay 1 6428
Protoss_Reaver 1 8046
Protoss_Shuttle 2 11426
Protoss_Observatory 1 8885
Protoss_Nexus 1 12548
12548
