Protoss_Gateway 2 7055
Protoss_Assimilator 1 3493
Protoss_Zealot 4 8367
Protoss_Cybernetics_Core 1 4672
Protoss_Dragoon 9 11183
Protoss_Robotics_Facility 1 6727
Protoss_Observatory 1 6817
Protoss_Observer 3 10059
Protoss_Shuttle 1 8921
Protoss_Forge 1 9757
Protoss_Citadel_of_Adun 1 11274
11274
