Protoss_Gateway 2 6710
Protoss_Assimilator 1 3417
Protoss_Cybernetics_Core 1 4358
Protoss_Dragoon 8 10076
Protoss_Nexus 1 9085
Protoss_Zealot 5 10588
Protoss_Robotics_Facility 1 8963
Protoss_Observatory 1 9289
10588
