Protoss_Nexus 1 5958
Protoss_Gateway 3 7808
Protoss_Assimilator 1 5050
Protoss_Cybernetics_Core 1 6118
Protoss_Zealot 6 10291
Protoss_Dragoon 7 10546
Protoss_Robotics_Facility 1 10243
Protoss_Observatory 1 10613
10613
