Protoss_Gateway 2 5901
Protoss_Assimilator 1 3418
Protoss_Zealot 2 4991
Protoss_Cybernetics_Core 1 5268
Protoss_Dragoon 11 10375
Protoss_Robotics_Facility 1 8910
Protoss_Observatory 1 9200
Protoss_Observer 2 10623
Protoss_Nexus 1 12743
12743
