Protoss_Gateway 2 5938
Protoss_Assimilator 1 3483
Protoss_Cybernetics_Core 1 4526
Protoss_Dragoon 8 9111
Protoss_Citadel_of_Adun 2 8386
Protoss_Templar_Archives 1 9418
Protoss_Nexus 1 11551
Protoss_Dark_Templar 2 10246
Protoss_Zealot 2 10856
11551
