Protoss_Gateway 3 10024
Protoss_Assimilator 1 3291
Protoss_Cybernetics_Core 1 4590
Protoss_Robotics_Facility 1 6127
Protoss_Dragoon 9 11025
Protoss_Observatory 1 6233
Protoss_Observer 3 9937
Protoss_Shuttle 1 8139
Protoss_Nexus 1 10833
Protoss_Robotics_Support_Bay 1 10316
11025
