Protoss_Gateway 4 10953
Protoss_Assimilator 2 10275
Protoss_Cybernetics_Core 1 4423
Protoss_Dragoon 5 10963
Protoss_Zealot 1 5678
Protoss_Citadel_of_Adun 1 6355
Protoss_Templar_Archives 1 7608
Protoss_Dark_Templar 5 10211
Protoss_Nexus 1 10303
10963
