Protoss_Gateway 2 8343
Protoss_Assimilator 1 3528
Protoss_Cybernetics_Core 1 4619
Protoss_Zealot 1 4456
Protoss_Dragoon 9 10391
Protoss_Robotics_Facility 1 8228
Protoss_Observatory 1 8328
Protoss_Observer 2 10596
10596
