Protoss_Gateway 3 10962
Protoss_Assimilator 1 3438
Protoss_Cybernetics_Core 1 4561
Protoss_Dragoon 10 10811
Protoss_Robotics_Facility 1 8944
Protoss_Observatory 1 9235
Protoss_Nexus 1 11513
Protoss_Observer 2 10676
11513
