Protoss_Gateway 4 11273
Protoss_Assimilator 1 3560
Protoss_Cybernetics_Core 1 4421
Protoss_Dragoon 11 10370
Protoss_Nexus 1 7858
Protoss_Robotics_Facility 1 10490
Protoss_Observatory 1 10667
Protoss_Zealot 1 10956
11273
