Protoss_Gateway 3 9873
Protoss_Assimilator 1 3489
Protoss_Cybernetics_Core 1 4673
Protoss_Dragoon 9 11037
Protoss_Robotics_Facility 1 6693
Protoss_Observatory 1 6845
Protoss_Observer 2 8299
Protoss_Shuttle 1 10545
11037
