Protoss_Gateway 2 8801
Protoss_Assimilator 1 3192
Protoss_Cybernetics_Core 1 4328
Protoss_Dragoon 7 10806
Protoss_Robotics_Facility 1 6499
Protoss_Zealot 2 7336
Protoss_Shuttle 1 7426
Protoss_Robotics_Support_Bay 1 6830
Protoss_Reaver 2 10376
Protoss_Observatory 1 8643
Protoss_Scarab 1 8403
Protoss_Observer 2 10546
10806
