Protoss_Gateway 4 11265
Protoss_Assimilator 1 3534
Protoss_Cybernetics_Core 1 4803
Protoss_Dragoon 8 10071
Protoss_Zealot 2 7816
Protoss_Nexus 1 11133
Protoss_Citadel_of_Adun 1 9972
Protoss_Robotics_Facility 1 11183
11265
