Protoss_Gateway 2 7030
Protoss_Assimilator 1 3533
Protoss_Cybernetics_Core 1 4601
Protoss_Dragoon 7 10886
Protoss_Citadel_of_Adun 1 8546
Protoss_Templar_Archives 1 9648
Protoss_Stargate 1 9988
Protoss_Nexus 1 11530
Protoss_Arbiter_Tribunal 1 11045
11530
