Protoss_Gateway 2 9730
Protoss_Assimilator 1 3435
Protoss_Cybernetics_Core 1 4508
Protoss_Dragoon 4 9286
Protoss_Robotics_Facility 1 6373
Protoss_Zealot 2 8441
Protoss_Shuttle 1 7256
Protoss_Observatory 1 6655
Protoss_Robotics_Support_Bay 1 7203
Protoss_Observer 2 9333
Protoss_Reaver 1 9001
Protoss_Nexus 1 12203
12203
