Protoss_Gateway 2 9844
Protoss_Assimilator 1 3541
Protoss_Cybernetics_Core 1 4841
Protoss_Dragoon 7 11181
Protoss_Robotics_Facility 1 6681
Protoss_Shuttle 1 7525
Protoss_Observatory 1 7009
Protoss_Observer 2 8549
Protoss_Robotics_Support_Bay 1 7841
Protoss_Reaver 2 11150
Protoss_Nexus 1 12363
12363
