Protoss_Gateway 2 5008
Protoss_Assimilator 1 3348
Protoss_Cybernetics_Core 1 4489
Protoss_Dragoon 3 6171
Protoss_Citadel_of_Adun 1 6977
Protoss_Robotics_Facility 1 8143
Protoss_Templar_Archives 1 8008
Protoss_Shuttle 1 8981
Protoss_Dark_Templar 6 10936
10936
