Protoss_Gateway 2 5953
Protoss_Assimilator 1 3213
Protoss_Cybernetics_Core 1 4368
Protoss_Dragoon 11 11155
Protoss_Robotics_Facility 1 8408
Protoss_Shuttle 1 9401
Protoss_Nexus 1 11111
Protoss_Robotics_Support_Bay 1 9079
Protoss_Reaver 1 10576
Protoss_Observatory 1 10221
11155
