Protoss_Gateway 3 9329
Protoss_Assimilator 1 3594
Protoss_Cybernetics_Core 1 4897
Protoss_Dragoon 10 10776
Protoss_Nexus 1 9071
Protoss_Robotics_Facility 1 8528
Protoss_Observatory 1 8744
Protoss_Observer 2 10221
Protoss_Citadel_of_Adun 1 10588
10776
