Protoss_Gateway 5 10923
Protoss_Assimilator 1 3479
Protoss_Cybernetics_Core 1 4504
Protoss_Dragoon 9 10986
Protoss_Nexus 1 9236
Protoss_Zealot 2 10806
Protoss_Robotics_Facility 1 9433
Protoss_Observatory 1 9558
Protoss_Citadel_of_Adun 1 10777
Protoss_Observer 1 10701
10986
