Protoss_Gateway 1 3584
Protoss_Assimilator 1 3668
Protoss_Cybernetics_Core 1 4903
Protoss_Dragoon 5 10549
Protoss_Nexus 1 10043
Protoss_Citadel_of_Adun 1 9906
Protoss_Templar_Archives 1 11086
11086
