Protoss_Gateway 2 8494
Protoss_Assimilator 1 3489
Protoss_Cybernetics_Core 1 4687
Protoss_Robotics_Facility 1 6281
Protoss_Dragoon 7 10055
Protoss_Shuttle 1 7085
Protoss_Observatory 1 6568
Protoss_Observer 3 9263
10055
