Protoss_Gateway 2 5369
Protoss_Assimilator 1 3205
Protoss_Cybernetics_Core 1 4416
Protoss_Dragoon 7 8386
Protoss_Citadel_of_Adun 1 7005
Protoss_Templar_Archives 1 8208
Protoss_Dark_Templar 4 10570
Protoss_Zealot 1 9728
Protoss_Nexus 1 12418
Protoss_Robotics_Facility 1 11838
12418
