Protoss_Gateway 2 7253
Protoss_Assimilator 1 3494
Protoss_Cybernetics_Core 1 4599
Protoss_Dragoon 6 10963
Protoss_Citadel_of_Adun 1 6995
Protoss_Templar_Archives 1 8048
Protoss_Zealot 1 8006
Protoss_Dark_Templar 4 10211
Protoss_Nexus 1 11607
11607
