Protoss_Gateway 3 9523
Protoss_Assimilator 1 3283
Protoss_Cybernetics_Core 1 4433
Protoss_Dragoon 7 10761
Protoss_Citadel_of_Adun 1 6893
Protoss_Templar_Archives 1 7959
Protoss_Zealot 1 7671
Protoss_Dark_Templar 3 9676
Protoss_Robotics_Facility 1 9868
Protoss_Shuttle 1 11116
11116
