Protoss_Gateway 2 4919
Protoss_Assimilator 1 3407
Protoss_Cybernetics_Core 1 4388
Protoss_Dragoon 7 8066
Protoss_Zealot 3 8666
Protoss_Citadel_of_Adun 1 7693
Protoss_Templar_Archives 1 8763
Protoss_Dark_Templar 2 9601
Protoss_Nexus 1 11978
11978
