Protoss_Gateway 2 7191
Protoss_Assimilator 1 3541
Protoss_Cybernetics_Core 1 4551
Protoss_Zealot 1 4406
Protoss_Dragoon 11 10426
Protoss_Robotics_Facility 1 9813
Protoss_Observatory 1 9913
Protoss_Observer 1 10691
10691
