Protoss_Gateway 3 10979
Protoss_Assimilator 1 3498
Protoss_Zealot 1 4326
Protoss_Cybernetics_Core 1 4888
Protoss_Dragoon 6 10556
Protoss_Robotics_Facility 1 7840
Protoss_Shuttle 1 8761
Protoss_Robotics_Support_Bay 1 8751
Protoss_Nexus 1 11983
Protoss_Reaver 1 11026
Protoss_Observatory 1 10404
11983
