Protoss_Assimilator 1 2743
Protoss_Gateway 2 9880
Protoss_Cybernetics_Core 1 4711
Protoss_Robotics_Facility 1 6230
Protoss_Dragoon 8 10876
Protoss_Shuttle 1 7051
Protoss_Observatory 1 6648
Protoss_Observer 2 8075
Protoss_Nexus 1 11054
Protoss_Forge 1 9743
11054
