Protoss_Gateway 3 10262
Protoss_Assimilator 1 3513
Protoss_Cybernetics_Core 1 4543
Protoss_Dragoon 10 11148
Protoss_Nexus 1 9473
Protoss_Shield_Battery 1 8176
Protoss_Robotics_Facility 1 9928
Protoss_Observatory 1 10127
Protoss_Observer 1 10936
11148
