Protoss_Gateway 2 7638
Protoss_Assimilator 1 3348
Protoss_Zealot 2 4453
Protoss_Cybernetics_Core 1 4566
Protoss_Dragoon 9 10976
Protoss_Citadel_of_Adun 2 7922
Protoss_Templar_Archives 1 8953
Protoss_Dark_Templar 2 9721
Protoss_Nexus 1 11996
11996
