Protoss_Gateway 3 10575
Protoss_Assimilator 1 3540
Protoss_Cybernetics_Core 1 4721
Protoss_Dragoon 11 11176
Protoss_Robotics_Facility 1 6804
Protoss_Observatory 1 7168
Protoss_Observer 2 9236
Protoss_Nexus 1 11038
11176
