Protoss_Gateway 2 7724
Protoss_Assimilator 2 2676
Protoss_Cybernetics_Core 1 3288
Protoss_Dragoon 5 9741
Protoss_Robotics_Facility 1 4753
Protoss_Shuttle 1 6096
Protoss_Robotics_Support_Bay 1 6326
Protoss_Reaver 1 6998
Protoss_Observatory 1 7671
Protoss_Scarab 1 8548
Protoss_Nexus 1 8888
Protoss_Observer 1 9046
Protoss_Forge 1 9277
9741
