Protoss_Assimilator 1 3027
Protoss_Gateway 2 7487
Protoss_Cybernetics_Core 1 5084
Protoss_Dragoon 4 8145
Protoss_Robotics_Facility 1 7107
Protoss_Observatory 1 7335
Protoss_Zealot 1 8137
Protoss_Observer 3 10893
Protoss_Citadel_of_Adun 1 8727
Protoss_Shuttle 1 9313
Protoss_Templar_Archives 1 9758
Protoss_Forge 1 9477
Protoss_Dark_Templar 2 10543
Protoss_Nexus 1 12663
12663
