Protoss_Assimilator 1 2351
Protoss_Gateway 2 7755
Protoss_Cybernetics_Core 1 4876
Protoss_Dragoon 6 10811
Protoss_Citadel_of_Adun 1 7324
Protoss_Templar_Archives 1 8348
Protoss_Dark_Templar 2 9268
Protoss_Nexus 1 11238
Protoss_Robotics_Facility 1 10879
11238
