Protoss_Gateway 2 7167
Protoss_Assimilator 1 3278
Protoss_Cybernetics_Core 1 4418
Protoss_Dragoon 8 10648
Protoss_Citadel_of_Adun 1 6959
Protoss_Templar_Archives 1 8103
Protoss_Zealot 1 7771
Protoss_Dark_Templar 2 8951
Protoss_Nexus 1 11158
Protoss_Stargate 1 11322
11322
