Protoss_Gateway 3 9350
Protoss_Assimilator 1 3390
Protoss_Cybernetics_Core 1 4499
Protoss_Dragoon 9 10459
Protoss_Robotics_Facility 1 6505
Protoss_Shuttle 1 7581
Protoss_Observatory 1 7055
Protoss_Observer 3 10379
Protoss_Nexus 1 12696
12696
