Protoss_Gateway 4 10618
Protoss_Assimilator 1 3373
Protoss_Cybernetics_Core 1 4478
Protoss_Dragoon 10 10007
Protoss_Nexus 1 10180
Protoss_Robotics_Facility 1 10001
Protoss_Observatory 1 10216
10618
