Protoss_Gateway 2 8556
Protoss_Assimilator 2 2629
Protoss_Cybernetics_Core 1 3309
Protoss_Dragoon 6 9329
Protoss_Robotics_Facility 1 5152
Protoss_Robotics_Support_Bay 1 6511
Protoss_Shuttle 1 6597
Protoss_Reaver 1 7615
Protoss_Observatory 1 9340
Protoss_Scarab 7 9964
9964
