Protoss_Gateway 4 11320
Protoss_Assimilator 1 3280
Protoss_Cybernetics_Core 1 4696
Protoss_Dragoon 10 10737
Protoss_Nexus 1 9921
Protoss_Robotics_Facility 1 9749
Protoss_Observatory 1 9977
Protoss_Observer 1 10827
11320
