Protoss_Gateway 4 10803
Protoss_Assimilator 1 3170
Protoss_Shield_Battery 1 3643
Protoss_Cybernetics_Core 1 4448
Protoss_Dragoon 10 10281
Protoss_Robotics_Facility 1 7214
Protoss_Observatory 1 7417
Protoss_Observer 2 8853
Protoss_Nexus 1 10693
Protoss_Zealot 2 10946
10946
