Protoss_Gateway 3 10946
Protoss_Assimilator 1 3410
Protoss_Cybernetics_Core 1 4740
Protoss_Dragoon 12 11001
Protoss_Robotics_Facility 1 6873
Protoss_Observatory 1 6988
Protoss_Observer 2 8388
Protoss_Nexus 1 11313
11313
