Protoss_Gateway 2 7003
Protoss_Assimilator 1 3385
Protoss_Cybernetics_Core 1 4524
Protoss_Dragoon 8 10706
Protoss_Citadel_of_Adun 1 6696
Protoss_Templar_Archives 1 7793
Protoss_Zealot 1 7681
Protoss_Dark_Templar 2 8611
Protoss_Nexus 1 10973
Protoss_Robotics_Facility 1 11087
11087
