Protoss_Gateway 2 4043
Protoss_Zealot 6 8571
Protoss_Assimilator 1 4649
Protoss_Cybernetics_Core 1 5655
Protoss_Dragoon 5 8816
Protoss_Citadel_of_Adun 1 8210
Protoss_Templar_Archives 1 9416
Protoss_Dark_Templar 2 10171
Protoss_Robotics_Facility 1 11695
11695
