Protoss_Gateway 4 11245
Protoss_Assimilator 1 3435
Protoss_Cybernetics_Core 1 4731
Protoss_Dragoon 8 10707
Protoss_Robotics_Facility 1 6539
Protoss_Observatory 1 7235
Protoss_Nexus 2 11501
Protoss_Observer 2 8763
11501
