Protoss_Nexus 1 5605
Protoss_Gateway 3 7523
Protoss_Assimilator 1 4349
Protoss_Cybernetics_Core 1 5651
Protoss_Zealot 2 8187
Protoss_Dragoon 9 9357
Protoss_Robotics_Facility 1 8926
Protoss_Observatory 1 9525
Protoss_Observer 1 10657
10657
