Protoss_Gateway 3 10592
Protoss_Assimilator 1 3483
Protoss_Cybernetics_Core 1 4463
Protoss_Zealot 2 9948
Protoss_Dragoon 4 9166
Protoss_Citadel_of_Adun 1 7576
Protoss_Robotics_Facility 1 8718
Protoss_Templar_Archives 1 8672
Protoss_Observatory 1 8851
Protoss_Dark_Templar 3 11066
Protoss_Observer 2 10243
Protoss_Nexus 1 12214
Protoss_Shuttle 1 11026
12214
