Protoss_Gateway 2 6683
Protoss_Assimilator 1 3386
Protoss_Cybernetics_Core 1 4748
Protoss_Dragoon 7 10811
Protoss_Robotics_Facility 1 6827
Protoss_Observatory 1 6990
Protoss_Observer 2 8383
Protoss_Zealot 4 9797
Protoss_Shuttle 1 9531
Protoss_Nexus 1 12341
12341
