Protoss_Gateway 2 4843
Protoss_Assimilator 1 3324
Protoss_Cybernetics_Core 1 4363
Protoss_Dragoon 8 10566
Protoss_Zealot 2 10166
Protoss_Robotics_Facility 1 8168
Protoss_Shuttle 1 8986
Protoss_Nexus 1 11048
Protoss_Robotics_Support_Bay 1 9106
Protoss_Reaver 1 10671
Protoss_Observatory 1 10013
11048
