Protoss_Gateway 2 7076
Protoss_Assimilator 1 3474
Protoss_Cybernetics_Core 1 4667
Protoss_Dragoon 8 10911
Protoss_Robotics_Facility 1 6908
Protoss_Observatory 1 7017
Protoss_Observer 2 8398
Protoss_Nexus 1 11637
Protoss_Citadel_of_Adun 1 11276
11637
