Protoss_Gateway 2 7268
Protoss_Assimilator 1 3359
Protoss_Zealot 1 3856
Protoss_Cybernetics_Core 1 5183
Protoss_Citadel_of_Adun 1 6225
Protoss_Dragoon 6 10456
Protoss_Templar_Archives 1 7228
Protoss_Dark_Templar 2 8016
Protoss_Nexus 1 10716
Protoss_Robotics_Facility 1 9917
Protoss_Shuttle 1 10801
Protoss_Robotics_Support_Bay 1 10683
10801
