Protoss_Gateway 2 11044
Protoss_Assimilator 1 3413
Protoss_Cybernetics_Core 1 4587
Protoss_Zealot 2 7651
Protoss_Dragoon 6 10608
Protoss_Robotics_Facility 1 6579
Protoss_Shuttle 1 7516
Protoss_Robotics_Support_Bay 1 6998
Protoss_Reaver 1 8658
Protoss_Observatory 1 8134
Protoss_Observer 2 10636
Protoss_Nexus 1 11853
11853
