Protoss_Assimilator 1 2722
Protoss_Gateway 2 6517
Protoss_Cybernetics_Core 1 4511
Protoss_Dragoon 6 11175
Protoss_Citadel_of_Adun 1 5666
Protoss_Robotics_Facility 1 6594
Protoss_Templar_Archives 1 6858
Protoss_Shuttle 1 7497
Protoss_Dark_Templar 3 8417
Protoss_Observatory 1 7664
Protoss_Observer 1 8717
Protoss_Nexus 1 11505
11505
