Protoss_Gateway 2 7563
Protoss_Assimilator 1 3579
Protoss_Zealot 3 5276
Protoss_Cybernetics_Core 1 6157
Protoss_Dragoon 8 10340
Protoss_Robotics_Facility 1 10545
Protoss_Observatory 1 10654
10654
