Protoss_Gateway 2 6604
Protoss_Assimilator 1 2392
Protoss_Cybernetics_Core 1 2853
Protoss_Dragoon 8 9823
Protoss_Robotics_Facility 1 5437
Protoss_Shuttle 1 6741
Protoss_Robotics_Support_Bay 1 7188
Protoss_Reaver 1 7751
Protoss_Observatory 1 8221
Protoss_Nexus 1 8770
Protoss_Observer 1 8946
Protoss_Scarab 1 9973
9973
