Protoss_Gateway 2 9478
Protoss_Assimilator 2 3792
Protoss_Cybernetics_Core 1 4863
Protoss_Zealot 4 8711
Protoss_Robotics_Facility 1 6693
Protoss_Robotics_Support_Bay 1 6832
Protoss_Shuttle 1 7631
Protoss_Observatory 1 7378
Protoss_Reaver 1 9011
Protoss_Observer 1 9351
Protoss_Dragoon 3 10758
10758
