Protoss_Gateway 3 11366
Protoss_Assimilator 1 3473
Protoss_Cybernetics_Core 1 4552
Protoss_Dragoon 6 8993
Protoss_Robotics_Facility 1 6603
Protoss_Observatory 1 6796
Protoss_Observer 4 10508
Protoss_Nexus 2 12685
12685
