Protoss_Gateway 3 11103
Protoss_Assimilator 1 3685
Protoss_Cybernetics_Core 1 4692
Protoss_Dragoon 7 9293
Protoss_Robotics_Facility 1 6878
Protoss_Observatory 1 7375
Protoss_Observer 2 9806
Protoss_Nexus 1 11444
Protoss_Citadel_of_Adun 1 10574
11444
