Protoss_Gateway 1 2083
Protoss_Assimilator 1 2618
Protoss_Cybernetics_Core 1 3760
Protoss_Zealot 1 4386
Protoss_Robotics_Facility 1 5001
Protoss_Dragoon 7 9630
Protoss_Shuttle 1 6311
Protoss_Robotics_Support_Bay 1 7088
Protoss_Reaver 2 9951
Protoss_Observatory 1 8267
Protoss_Observer 1 8961
Protoss_Scarab 3 9873
9951
