Protoss_Gateway 2 11026
Protoss_Assimilator 1 3523
Protoss_Cybernetics_Core 1 4642
Protoss_Dragoon 5 10591
Protoss_Robotics_Facility 1 7908
Protoss_Robotics_Support_Bay 1 8013
Protoss_Shuttle 1 8741
Protoss_Zealot 2 9246
Protoss_Reaver 1 9883
Protoss_Nexus 1 11738
Protoss_Observatory 1 9828
Protoss_Observer 1 10616
11738
