Protoss_Gateway 3 10057
Protoss_Assimilator 1 3578
Protoss_Cybernetics_Core 1 4602
Protoss_Dragoon 7 11026
Protoss_Citadel_of_Adun 1 6996
Protoss_Templar_Archives 1 7988
Protoss_Nexus 1 10318
Protoss_Dark_Templar 2 9666
11026
