Protoss_Gateway 2 7307
Protoss_Assimilator 1 3410
Protoss_Cybernetics_Core 1 4601
Protoss_Dragoon 8 11200
Protoss_Robotics_Facility 1 6723
Protoss_Observatory 1 7132
Protoss_Observer 1 8057
Protoss_Nexus 1 12624
12624
