Protoss_Assimilator 1 2856
Protoss_Gateway 2 9445
Protoss_Cybernetics_Core 1 4878
Protoss_Zealot 4 7040
Protoss_Robotics_Facility 1 6393
Protoss_Shuttle 3 11036
Protoss_Citadel_of_Adun 1 7826
Protoss_Observatory 1 7178
Protoss_Observer 2 8698
Protoss_Dragoon 1 8411
Protoss_Templar_Archives 1 8906
Protoss_Forge 1 8452
Protoss_Dark_Templar 2 10476
Protoss_Photon_Cannon 1 10803
11036
