Protoss_Gateway 2 6725
Protoss_Assimilator 1 3549
Protoss_Zealot 6 10448
Protoss_Cybernetics_Core 1 5870
Protoss_Dragoon 5 9936
Protoss_Robotics_Facility 1 8748
Protoss_Shuttle 1 9756
Protoss_Robotics_Support_Bay 1 9291
Protoss_Reaver 1 11156
11156
