Protoss_Nexus 2 12130
Protoss_Gateway 3 10536
Protoss_Assimilator 1 4661
Protoss_Cybernetics_Core 1 5873
Protoss_Zealot 3 10291
Protoss_Dragoon 5 8796
Protoss_Forge 1 7438
Protoss_Photon_Cannon 3 11192
Protoss_Robotics_Facility 1 10694
12130
