Protoss_Gateway 1 3393
Protoss_Assimilator 1 3428
Protoss_Cybernetics_Core 1 4499
Protoss_Zealot 1 4221
Protoss_Dragoon 6 9491
Protoss_Robotics_Facility 1 8068
Protoss_Shuttle 1 9141
Protoss_Robotics_Support_Bay 1 8424
Protoss_Reaver 2 11335
11335
