Protoss_Gateway 2 6218
Protoss_Assimilator 1 3438
Protoss_Cybernetics_Core 1 4533
Protoss_Dragoon 7 11181
Protoss_Citadel_of_Adun 1 7653
Protoss_Robotics_Facility 1 8593
Protoss_Zealot 1 8556
Protoss_Templar_Archives 1 9424
Protoss_Shuttle 1 10021
Protoss_Observatory 1 9451
Protoss_Dark_Templar 2 10281
Protoss_Nexus 1 12549
Protoss_Observer 1 10741
12549
