Protoss_Gateway 4 10716
Protoss_Assimilator 1 3415
Protoss_Cybernetics_Core 1 4616
Protoss_Dragoon 13 10906
Protoss_Nexus 1 9213
Protoss_Robotics_Facility 1 9021
Protoss_Observatory 1 9218
Protoss_Observer 2 10756
10906
