Protoss_Gateway 4 10599
Protoss_Assimilator 1 3445
Protoss_Cybernetics_Core 1 4499
Protoss_Dragoon 8 9907
Protoss_Robotics_Facility 1 7587
Protoss_Observatory 1 7759
Protoss_Observer 3 9801
Protoss_Nexus 1 10849
Protoss_Shuttle 1 10883
10883
