Protoss_Gateway 4 10749
Protoss_Assimilator 1 3536
Protoss_Cybernetics_Core 1 4725
Protoss_Dragoon 10 10851
Protoss_Robotics_Facility 1 7816
Protoss_Shuttle 1 8626
Protoss_Robotics_Support_Bay 1 7937
Protoss_Observatory 1 7998
Protoss_Reaver 1 9871
Protoss_Observer 2 10916
10916
