Protoss_Gateway 3 10163
Protoss_Assimilator 1 3505
Protoss_Cybernetics_Core 1 4555
Protoss_Dragoon 12 10966
Protoss_Nexus 1 10079
Protoss_Robotics_Facility 1 9396
Protoss_Observatory 1 9505
Protoss_Observer 1 10476
10966
