Protoss_Gateway 2 7834
Protoss_Assimilator 1 3490
Protoss_Zealot 5 10768
Protoss_Cybernetics_Core 1 5513
Protoss_Dragoon 2 7151
Protoss_Citadel_of_Adun 1 6949
Protoss_Robotics_Facility 1 8002
Protoss_Templar_Archives 1 8061
Protoss_Shuttle 1 8816
Protoss_Dark_Templar 5 11001
Protoss_Nexus 1 11733
11733
