Protoss_Gateway 2 5814
Protoss_Assimilator 1 2533
Protoss_Cybernetics_Core 1 3248
Protoss_Dragoon 7 9483
Protoss_Robotics_Facility 1 5696
Protoss_Shuttle 1 7131
Protoss_Robotics_Support_Bay 1 7646
Protoss_Zealot 2 7716
Protoss_Reaver 1 8356
Protoss_Observatory 1 9106
Protoss_Scarab 2 9968
9968
