Protoss_Gateway 4 10762
Protoss_Assimilator 1 3507
Protoss_Cybernetics_Core 1 4538
Protoss_Dragoon 10 10786
Protoss_Nexus 1 10788
Protoss_Zealot 1 9316
Protoss_Robotics_Facility 1 10783
10788
