Protoss_Gateway 3 10218
Protoss_Assimilator 1 3376
Protoss_Cybernetics_Core 1 4526
Protoss_Dragoon 13 11001
Protoss_Nexus 1 10783
Protoss_Robotics_Facility 1 10104
Protoss_Observatory 1 10321
11001
