Protoss_Gateway 2 7074
Protoss_Assimilator 2 3493
Protoss_Cybernetics_Core 1 4633
Protoss_Zealot 1 4461
Protoss_Dragoon 6 8741
Protoss_Citadel_of_Adun 1 7658
Protoss_Templar_Archives 1 8664
Protoss_Dark_Templar 4 10491
Protoss_Nexus 1 12288
12288
