Protoss_Gateway 3 9013
Protoss_Assimilator 1 3465
Protoss_Cybernetics_Core 1 4593
Protoss_Dragoon 6 10576
Protoss_Robotics_Facility 1 7297
Protoss_Observatory 1 7491
Protoss_Observer 1 8856
Protoss_Zealot 4 10706
Protoss_Shuttle 1 9938
10706
