Protoss_Gateway 4 11219
Protoss_Assimilator 2 3662
Protoss_Zealot 2 5156
Protoss_Cybernetics_Core 1 5288
Protoss_Dragoon 9 11181
Protoss_Nexus 1 10800
Protoss_Robotics_Facility 1 11010
11219
