Protoss_Gateway 3 9467
Protoss_Assimilator 1 3573
Protoss_Cybernetics_Core 1 4751
Protoss_Dragoon 9 10435
Protoss_Citadel_of_Adun 1 6950
Protoss_Nexus 2 12664
Protoss_Robotics_Facility 1 8778
Protoss_Observatory 1 9100
Protoss_Observer 1 9916
12664
