Protoss_Gateway 2 4029
Protoss_Zealot 6 9546
Protoss_Assimilator 1 5584
Protoss_Cybernetics_Core 1 6268
Protoss_Dragoon 8 11140
Protoss_Nexus 1 10174
Protoss_Robotics_Facility 1 10289
Protoss_Observatory 1 10591
11140
