Protoss_Gateway 2 7329
Protoss_Zealot 3 6227
Protoss_Assimilator 1 5123
Protoss_Cybernetics_Core 1 6423
Protoss_Dragoon 7 10947
Protoss_Robotics_Facility 1 10152
Protoss_Nexus 1 11971
Protoss_Observatory 1 10270
11971
