Protoss_Nexus 2 10558
Protoss_Gateway 3 10663
Protoss_Assimilator 1 4308
Protoss_Cybernetics_Core 1 5492
Protoss_Zealot 1 5646
Protoss_Dragoon 7 10701
Protoss_Robotics_Facility 1 10453
Protoss_Observatory 1 10578
10701
