Protoss_Gateway 1 3338
Protoss_Assimilator 1 3387
Protoss_Cybernetics_Core 1 4478
Protoss_Dragoon 6 10631
Protoss_Robotics_Facility 1 6223
Protoss_Shuttle 1 7041
Protoss_Robotics_Support_Bay 1 6575
Protoss_Reaver 2 9608
Protoss_Zealot 2 9376
Protoss_Observatory 1 8858
Protoss_Nexus 1 11808
Protoss_Observer 2 10681
11808
