Protoss_Gateway 5 9828
Protoss_Assimilator 1 3448
Protoss_Cybernetics_Core 1 4465
Protoss_Dragoon 10 10861
Protoss_Nexus 1 10183
Protoss_Robotics_Facility 1 9514
Protoss_Observatory 1 9631
Protoss_Observer 1 10501
Protoss_Citadel_of_Adun 1 11328
11328
