Protoss_Gateway 3 8113
Protoss_Assimilator 1 3589
Protoss_Cybernetics_Core 1 4924
Protoss_Dragoon 11 10796
Protoss_Robotics_Facility 1 7698
Protoss_Observatory 1 7904
Protoss_Observer 3 10171
Protoss_Nexus 1 11863
11863
