Protoss_Gateway 2 8204
Protoss_Assimilator 3 4723
Protoss_Zealot 2 5066
Protoss_Cybernetics_Core 1 6393
Protoss_Citadel_of_Adun 1 7428
Protoss_Dragoon 2 10786
Protoss_Templar_Archives 1 8788
Protoss_Dark_Templar 2 9601
Protoss_Nexus 1 12013
12013
