Protoss_Gateway 3 11180
Protoss_Assimilator 1 3273
Protoss_Cybernetics_Core 1 4429
Protoss_Dragoon 4 10858
Protoss_Citadel_of_Adun 1 6203
Protoss_Templar_Archives 1 7304
Protoss_Dark_Templar 5 10094
Protoss_Nexus 1 10298
Protoss_Robotics_Facility 1 11600
11600
