Protoss_Gateway 3 9569
Protoss_Assimilator 1 3413
Protoss_Cybernetics_Core 1 4483
Protoss_Dragoon 13 11186
Protoss_Nexus 1 9970
Protoss_Robotics_Facility 1 9653
Protoss_Observatory 1 10376
11186
