Protoss_Gateway 2 8035
Protoss_Assimilator 1 3447
Protoss_Cybernetics_Core 1 4624
Protoss_Dragoon 9 10816
Protoss_Robotics_Facility 1 7118
Protoss_Observatory 1 7224
Protoss_Observer 5 10656
10816
