Protoss_Assimilator 1 1801
Protoss_Gateway 1 2213
Protoss_Cybernetics_Core 1 3201
Protoss_Robotics_Facility 1 4256
Protoss_Dragoon 3 9051
Protoss_Shuttle 1 5535
Protoss_Robotics_Support_Bay 1 5675
Protoss_Observatory 1 5796
Protoss_Observer 3 9028
Protoss_Nexus 1 6850
Protoss_Reaver 1 7976
Protoss_Scarab 4 9715
9715
