Protoss_Gateway 2 7249
Protoss_Assimilator 1 3234
Protoss_Cybernetics_Core 1 4357
Protoss_Dragoon 7 10622
Protoss_Robotics_Facility 1 6393
Protoss_Observatory 1 6645
Protoss_Observer 1 7451
Protoss_Shuttle 1 8991
Protoss_Zealot 4 9780
Protoss_Nexus 1 11791
11791
