Protoss_Gateway 3 11290
Protoss_Assimilator 1 3331
Protoss_Cybernetics_Core 1 4411
Protoss_Dragoon 8 10525
Protoss_Robotics_Facility 1 6329
Protoss_Observatory 1 6518
Protoss_Observer 3 9287
Protoss_Nexus 1 9602
11290
