Protoss_Gateway 3 10084
Protoss_Assimilator 2 10413
Protoss_Cybernetics_Core 1 4478
Protoss_Dragoon 11 10331
Protoss_Nexus 1 8708
Protoss_Robotics_Facility 1 8996
Protoss_Observatory 1 9229
Protoss_Observer 2 10613
10613
