Protoss_Gateway 3 8893
Protoss_Assimilator 1 3318
Protoss_Cybernetics_Core 1 4511
Protoss_Zealot 2 8006
Protoss_Dragoon 9 10816
Protoss_Robotics_Facility 1 7038
Protoss_Observatory 1 7167
Protoss_Observer 2 8883
Protoss_Nexus 1 11998
11998
