Protoss_Gateway 2 6964
Protoss_Assimilator 1 3203
Protoss_Cybernetics_Core 1 4411
Protoss_Dragoon 8 9591
Protoss_Nexus 1 9181
Protoss_Zealot 3 10511
Protoss_Robotics_Facility 1 9216
Protoss_Shuttle 1 10051
Protoss_Observatory 1 9419
Protoss_Robotics_Support_Bay 1 9703
Protoss_Reaver 1 11195
11195
