Protoss_Gateway 4 11399
Protoss_Assimilator 1 3388
Protoss_Cybernetics_Core 1 4385
Protoss_Dragoon 8 10965
Protoss_Nexus 1 9341
Protoss_Zealot 1 8023
Protoss_Robotics_Facility 1 9137
Protoss_Shuttle 1 9963
Protoss_Robotics_Support_Bay 1 9597
Protoss_Observatory 1 9860
Protoss_Observer 1 10645
11399
