Protoss_Gateway 3 11218
Protoss_Assimilator 1 3417
Protoss_Cybernetics_Core 1 4515
Protoss_Dragoon 9 10511
Protoss_Nexus 1 10201
Protoss_Zealot 3 10731
Protoss_Robotics_Facility 1 10119
Protoss_Observatory 1 10251
11218
