Protoss_Gateway 2 7249
Protoss_Assimilator 1 3457
Protoss_Cybernetics_Core 1 4453
Protoss_Dragoon 10 10783
Protoss_Nexus 1 9606
Protoss_Zealot 1 8049
Protoss_Robotics_Facility 1 10313
10783
