Protoss_Gateway 4 10734
Protoss_Assimilator 1 3464
Protoss_Cybernetics_Core 1 4463
Protoss_Dragoon 11 10976
Protoss_Nexus 1 9046
Protoss_Robotics_Facility 1 9358
Protoss_Observatory 1 9563
Protoss_Observer 1 10411
Protoss_Citadel_of_Adun 1 10981
10981
