Protoss_Assimilator 1 1788
Protoss_Gateway 1 2115
Protoss_Cybernetics_Core 1 3113
Protoss_Dragoon 8 9981
Protoss_Robotics_Facility 1 4591
Protoss_Shuttle 1 5936
Protoss_Robotics_Support_Bay 1 6273
Protoss_Reaver 2 7928
Protoss_Nexus 1 8823
Protoss_Scarab 8 9850
Protoss_Observatory 1 9873
9981
