Protoss_Gateway 2 7283
Protoss_Assimilator 1 3216
Protoss_Cybernetics_Core 1 4349
Protoss_Dragoon 9 10937
Protoss_Nexus 1 8149
Protoss_Forge 1 6985
Protoss_Photon_Cannon 2 9408
Protoss_Zealot 2 10689
Protoss_Robotics_Facility 1 11217
11217
