Protoss_Gateway 2 7528
Protoss_Assimilator 1 3446
Protoss_Cybernetics_Core 1 4541
Protoss_Dragoon 5 10293
Protoss_Citadel_of_Adun 1 6992
Protoss_Robotics_Facility 1 7770
Protoss_Templar_Archives 1 7998
Protoss_Shuttle 1 8569
Protoss_Dark_Templar 4 9503
Protoss_Nexus 1 12647
12647
