Protoss_Gateway 2 5958
Protoss_Assimilator 1 3518
Protoss_Cybernetics_Core 1 4588
Protoss_Zealot 3 9761
Protoss_Dragoon 6 8506
Protoss_Robotics_Facility 1 8636
Protoss_Robotics_Support_Bay 1 8818
Protoss_Shuttle 1 9591
Protoss_Reaver 1 10733
Protoss_Nexus 1 12582
12582
