Protoss_Gateway 4 11424
Protoss_Assimilator 1 3199
Protoss_Cybernetics_Core 1 4453
Protoss_Dragoon 10 10421
Protoss_Nexus 1 9072
Protoss_Robotics_Facility 1 10508
Protoss_Observatory 1 10598
11424
