Protoss_Gateway 3 8565
Protoss_Assimilator 1 3286
Protoss_Cybernetics_Core 1 4351
Protoss_Citadel_of_Adun 1 5432
Protoss_Dragoon 1 5259
Protoss_Templar_Archives 1 6418
Protoss_Dark_Templar 11 11117
Protoss_Nexus 1 11821
Protoss_Forge 1 10316
11821
