Protoss_Assimilator 1 2582
Protoss_Gateway 3 8268
Protoss_Cybernetics_Core 1 4688
Protoss_Dragoon 6 11099
Protoss_Robotics_Facility 1 6365
Protoss_Observatory 1 6485
Protoss_Citadel_of_Adun 1 7242
Protoss_Observer 1 7375
Protoss_Shuttle 3 10549
Protoss_Zealot 6 9809
Protoss_Robotics_Support_Bay 1 9291
11099
