Protoss_Gateway 2 7619
Protoss_Assimilator 1 3487
Protoss_Cybernetics_Core 1 4790
Protoss_Dragoon 8 10179
Protoss_Citadel_of_Adun 2 10250
Protoss_Robotics_Facility 1 8728
Protoss_Observatory 1 8959
Protoss_Shuttle 1 9701
10250
