Protoss_Gateway 4 10557
Protoss_Assimilator 1 3474
Protoss_Cybernetics_Core 1 4591
Protoss_Dragoon 10 9848
Protoss_Nexus 1 10580
Protoss_Zealot 2 10360
Protoss_Robotics_Facility 1 11533
11533
