Protoss_Gateway 2 10009
Protoss_Assimilator 1 3546
Protoss_Cybernetics_Core 1 4590
Protoss_Dragoon 6 10907
Protoss_Robotics_Facility 1 6760
Protoss_Zealot 2 6875
Protoss_Shuttle 2 9717
Protoss_Robotics_Support_Bay 1 7415
Protoss_Reaver 1 8905
Protoss_Observatory 1 9619
Protoss_Observer 1 10445
10907
