Protoss_Gateway 2 6992
Protoss_Assimilator 1 3434
Protoss_Zealot 1 3901
Protoss_Cybernetics_Core 1 4677
Protoss_Dragoon 11 10759
Protoss_Robotics_Facility 1 9084
Protoss_Observatory 1 9337
Protoss_Nexus 1 11876
Protoss_Observer 2 10733
11876
