Protoss_Gateway 3 9939
Protoss_Assimilator 1 3299
Protoss_Cybernetics_Core 1 4443
Protoss_Dragoon 12 11178
Protoss_Robotics_Facility 1 7401
Protoss_Observatory 1 7499
Protoss_Observer 2 8883
Protoss_Nexus 1 11573
Protoss_Zealot 1 10943
11573
