Protoss_Gateway 3 11255
Protoss_Assimilator 1 3153
Protoss_Cybernetics_Core 1 4328
Protoss_Dragoon 8 10751
Protoss_Robotics_Facility 1 7453
Protoss_Observatory 1 7543
Protoss_Observer 2 10656
Protoss_Nexus 1 10512
Protoss_Zealot 4 9591
Protoss_Shuttle 1 9736
11255
