Protoss_Gateway 2 4889
Protoss_Assimilator 2 10473
Protoss_Cybernetics_Core 1 4379
Protoss_Dragoon 7 10249
Protoss_Citadel_of_Adun 1 6898
Protoss_Templar_Archives 1 7996
Protoss_Nexus 1 11023
Protoss_Dark_Templar 1 9497
11023
