Protoss_Gateway 3 7473
Protoss_Assimilator 1 3628
Protoss_Zealot 3 7965
Protoss_Cybernetics_Core 1 5438
Protoss_Dragoon 5 10197
Protoss_Citadel_of_Adun 1 6811
Protoss_Templar_Archives 1 8001
Protoss_Dark_Templar 3 8973
Protoss_Nexus 1 12455
12455
