Protoss_Gateway 2 11279
Protoss_Assimilator 1 3550
Protoss_Cybernetics_Core 1 4763
Protoss_Dragoon 5 11051
Protoss_Robotics_Facility 1 6771
Protoss_Shuttle 1 7696
Protoss_Zealot 2 8216
Protoss_Robotics_Support_Bay 1 7518
Protoss_Reaver 1 9041
Protoss_Observatory 1 8466
Protoss_Observer 2 9975
Protoss_Nexus 1 11878
11878
