Protoss_Gateway 2 6549
Protoss_Assimilator 1 3547
Protoss_Cybernetics_Core 1 4660
Protoss_Robotics_Facility 1 6313
Protoss_Dragoon 11 10836
Protoss_Observatory 1 6543
Protoss_Observer 3 10076
Protoss_Nexus 1 11629
11629
