Protoss_Gateway 2 9868
Protoss_Assimilator 1 3598
Protoss_Zealot 1 4071
Protoss_Cybernetics_Core 1 4930
Protoss_Dragoon 7 10765
Protoss_Robotics_Facility 1 7188
Protoss_Shuttle 1 8531
Protoss_Robotics_Support_Bay 1 7908
Protoss_Reaver 1 9673
Protoss_Observatory 1 9984
10765
