Protoss_Gateway 3 11169
Protoss_Assimilator 1 3352
Protoss_Cybernetics_Core 1 4504
Protoss_Dragoon 7 10991
Protoss_Robotics_Facility 1 7303
Protoss_Shuttle 1 8116
Protoss_Robotics_Support_Bay 1 7608
Protoss_Zealot 2 8871
Protoss_Reaver 1 9312
Protoss_Observatory 1 9041
Protoss_Observer 1 10191
11169
