Protoss_Gateway 1 3477
Protoss_Assimilator 1 3408
Protoss_Cybernetics_Core 1 4524
Protoss_Zealot 2 8051
Protoss_Robotics_Facility 1 6468
Protoss_Dragoon 4 9916
Protoss_Robotics_Support_Bay 1 6563
Protoss_Shield_Battery 1 6724
Protoss_Shuttle 2 9635
Protoss_Reaver 2 11416
Protoss_Nexus 1 12423
12423
