Protoss_Gateway 3 10944
Protoss_Assimilator 1 3418
Protoss_Cybernetics_Core 1 4623
Protoss_Dragoon 2 6291
Protoss_Citadel_of_Adun 1 5935
Protoss_Templar_Archives 1 6987
Protoss_Dark_Templar 8 10546
Protoss_Nexus 1 10953
10953
