Protoss_Gateway 3 11115
Protoss_Assimilator 1 3422
Protoss_Zealot 1 3873
Protoss_Cybernetics_Core 1 5301
Protoss_Dragoon 11 11079
Protoss_Nexus 1 10357
Protoss_Robotics_Facility 2 10609
Protoss_Observatory 1 10243
11115
