Protoss_Gateway 2 7774
Protoss_Assimilator 2 3733
Protoss_Cybernetics_Core 1 4743
Protoss_Dragoon 4 9926
Protoss_Citadel_of_Adun 1 6597
Protoss_Templar_Archives 1 7588
Protoss_Dark_Templar 4 10786
Protoss_Nexus 1 10888
Protoss_Robotics_Facility 1 10234
10888
