Protoss_Gateway 3 9243
Protoss_Assimilator 1 3448
Protoss_Cybernetics_Core 1 4689
Protoss_Dragoon 9 10206
Protoss_Robotics_Facility 1 9059
Protoss_Zealot 2 9316
Protoss_Observatory 1 9167
Protoss_Observer 1 10336
Protoss_Nexus 1 12653
12653
