Protoss_Gateway 3 9730
Protoss_Assimilator 1 3302
Protoss_Cybernetics_Core 1 4415
Protoss_Robotics_Facility 1 6139
Protoss_Dragoon 9 11175
Protoss_Shuttle 3 10311
Protoss_Observatory 1 6760
Protoss_Nexus 1 9901
Protoss_Observer 2 10809
11175
