Protoss_Gateway 2 7153
Protoss_Assimilator 1 3178
Protoss_Cybernetics_Core 1 4321
Protoss_Dragoon 12 11131
Protoss_Robotics_Facility 1 6863
Protoss_Observatory 1 7029
Protoss_Observer 4 10381
Protoss_Nexus 1 11283
11283
