Protoss_Gateway 3 7423
Protoss_Assimilator 1 3447
Protoss_Cybernetics_Core 1 4517
Protoss_Dragoon 8 9639
Protoss_Zealot 4 9267
Protoss_Citadel_of_Adun 1 9429
Protoss_Templar_Archives 1 10432
Protoss_Nexus 1 12247
Protoss_Dark_Templar 2 11177
12247
