Protoss_Gateway 3 9016
Protoss_Assimilator 2 9771
Protoss_Cybernetics_Core 1 4523
Protoss_Dragoon 11 11095
Protoss_Nexus 1 9025
Protoss_Robotics_Facility 1 9785
Protoss_Zealot 1 8919
Protoss_Stargate 1 11202
Protoss_Observatory 1 10409
11202
