Protoss_Gateway 2 6105
Protoss_Assimilator 1 3468
Protoss_Cybernetics_Core 1 4532
Protoss_Dragoon 10 10451
Protoss_Citadel_of_Adun 1 7496
Protoss_Nexus 2 12581
Protoss_Robotics_Facility 1 10240
Protoss_Observatory 1 10480
12581
