Protoss_Gateway 2 9147
Protoss_Assimilator 1 3344
Protoss_Cybernetics_Core 1 4381
Protoss_Dragoon 8 11181
Protoss_Robotics_Facility 1 6293
Protoss_Shuttle 1 7099
Protoss_Robotics_Support_Bay 1 6473
Protoss_Reaver 1 8277
Protoss_Observatory 1 8201
Protoss_Observer 1 9045
Protoss_Nexus 1 12322
12322
