Protoss_Gateway 3 9547
Protoss_Assimilator 1 3145
Protoss_Cybernetics_Core 1 4257
Protoss_Dragoon 9 9401
Protoss_Nexus 1 10124
Protoss_Zealot 5 10233
Protoss_Citadel_of_Adun 1 11037
11037
