Protoss_Gateway 2 4866
Protoss_Assimilator 1 3186
Protoss_Cybernetics_Core 1 4401
Protoss_Dragoon 9 9923
Protoss_Robotics_Facility 1 8011
Protoss_Zealot 2 7899
Protoss_Robotics_Support_Bay 1 9009
Protoss_Shuttle 1 9875
Protoss_Reaver 1 11017
Protoss_Observatory 1 10332
11017
