Protoss_Gateway 2 7437
Protoss_Assimilator 1 3393
Protoss_Cybernetics_Core 1 4488
Protoss_Dragoon 9 10062
Protoss_Robotics_Facility 1 7638
Protoss_Zealot 3 10656
Protoss_Observatory 1 8143
Protoss_Observer 1 9076
Protoss_Citadel_of_Adun 1 9564
Protoss_Shuttle 1 10581
Protoss_Templar_Archives 2 10883
10883
