Protoss_Gateway 2 8783
Protoss_Assimilator 1 3395
Protoss_Cybernetics_Core 1 4561
Protoss_Dragoon 10 10637
Protoss_Robotics_Facility 1 7860
Protoss_Observatory 1 7997
Protoss_Observer 3 10595
Protoss_Nexus 1 12023
12023
