Protoss_Gateway 2 8778
Protoss_Assimilator 1 3510
Protoss_Cybernetics_Core 1 4523
Protoss_Dragoon 6 11066
Protoss_Robotics_Facility 1 6568
Protoss_Shuttle 1 7376
Protoss_Robotics_Support_Bay 1 7048
Protoss_Reaver 2 9806
Protoss_Scarab 8 9299
Protoss_Nexus 1 12574
12574
