Protoss_Gateway 3 9776
Protoss_Assimilator 1 3493
Protoss_Cybernetics_Core 1 4536
Protoss_Zealot 1 4816
Protoss_Dragoon 10 10771
Protoss_Robotics_Facility 1 7693
Protoss_Observatory 1 7889
Protoss_Observer 2 9661
Protoss_Shuttle 1 10743
10771
