Protoss_Gateway 1 3358
Protoss_Assimilator 1 3418
Protoss_Cybernetics_Core 1 4543
Protoss_Dragoon 2 7621
Protoss_Robotics_Facility 1 6959
Protoss_Citadel_of_Adun 1 6720
Protoss_Templar_Archives 1 7841
Protoss_Shuttle 1 8226
Protoss_Observatory 1 8217
Protoss_Dark_Templar 2 10581
Protoss_Observer 1 9246
10581
