Protoss_Gateway 2 8455
Protoss_Assimilator 1 3488
Protoss_Cybernetics_Core 1 4688
Protoss_Dragoon 7 9958
Protoss_Robotics_Facility 1 6918
Protoss_Zealot 1 6421
Protoss_Observatory 1 7064
Protoss_Observer 3 10876
Protoss_Shuttle 1 10216
Protoss_Nexus 2 12863
12863
