Protoss_Nexus 1 5553
Protoss_Gateway 3 10863
Protoss_Assimilator 2 8941
Protoss_Cybernetics_Core 1 5615
Protoss_Zealot 4 10271
Protoss_Dragoon 10 11156
Protoss_Stargate 2 11017
Protoss_Fleet_Beacon 1 10608
11156
