Protoss_Gateway 2 5007
Protoss_Assimilator 1 3335
Protoss_Cybernetics_Core 1 4353
Protoss_Dragoon 8 11116
Protoss_Nexus 2 11733
Protoss_Robotics_Facility 1 9970
Protoss_Shuttle 1 11156
Protoss_Robotics_Support_Bay 1 10484
11733
