Protoss_Gateway 2 7328
Protoss_Assimilator 1 3219
Protoss_Cybernetics_Core 1 4389
Protoss_Dragoon 9 10516
Protoss_Robotics_Facility 1 7404
Protoss_Observatory 1 7553
Protoss_Observer 3 10461
Protoss_Nexus 2 10539
10539
