Protoss_Gateway 4 11388
Protoss_Assimilator 1 3508
Protoss_Cybernetics_Core 1 4452
Protoss_Dragoon 9 10653
Protoss_Nexus 1 9416
Protoss_Robotics_Facility 1 9318
Protoss_Observatory 1 9563
Protoss_Observer 1 10536
11388
