Protoss_Gateway 2 5097
Protoss_Assimilator 1 3257
Protoss_Cybernetics_Core 1 4475
Protoss_Dragoon 5 7695
Protoss_Citadel_of_Adun 1 7447
Protoss_Templar_Archives 1 8739
Protoss_Robotics_Facility 1 9403
Protoss_Zealot 2 9159
Protoss_Nexus 1 11183
Protoss_Shuttle 1 10213
Protoss_Dark_Templar 2 10257
Protoss_Observatory 1 10190
Protoss_Observer 1 10959
11183
