Protoss_Gateway 1 3313
Protoss_Assimilator 1 3203
Protoss_Cybernetics_Core 1 4363
Protoss_Zealot 2 6381
Protoss_Robotics_Facility 1 5972
Protoss_Dragoon 5 10623
Protoss_Shuttle 3 11421
Protoss_Robotics_Support_Bay 1 6408
Protoss_Reaver 2 9078
Protoss_Observatory 1 9498
Protoss_Observer 1 10321
11421
