Protoss_Gateway 3 10498
Protoss_Assimilator 1 3334
Protoss_Cybernetics_Core 1 4519
Protoss_Dragoon 9 10427
Protoss_Robotics_Facility 1 8540
Protoss_Nexus 2 12645
Protoss_Observatory 1 8625
Protoss_Observer 2 10085
12645
