Protoss_Gateway 3 10666
Protoss_Assimilator 1 3281
Protoss_Cybernetics_Core 1 4385
Protoss_Dragoon 8 9625
Protoss_Robotics_Facility 1 8264
Protoss_Observatory 1 8397
Protoss_Observer 2 10783
Protoss_Nexus 1 11520
Protoss_Citadel_of_Adun 1 10648
11520
