Protoss_Gateway 2 9603
Protoss_Assimilator 1 3423
Protoss_Cybernetics_Core 1 4651
Protoss_Zealot 1 4591
Protoss_Dragoon 8 10861
Protoss_Robotics_Facility 1 8418
Protoss_Nexus 1 10353
Protoss_Observatory 1 8643
Protoss_Observer 1 9471
10861
