Protoss_Gateway 2 7569
Protoss_Assimilator 1 3520
Protoss_Cybernetics_Core 1 4638
Protoss_Dragoon 10 11066
Protoss_Robotics_Facility 1 9109
Protoss_Observatory 1 9323
Protoss_Nexus 1 11803
Protoss_Observer 1 10111
11803
