Protoss_Gateway 2 6211
Protoss_Assimilator 1 3384
Protoss_Cybernetics_Core 1 4425
Protoss_Dragoon 12 10699
Protoss_Nexus 2 11860
Protoss_Robotics_Facility 1 9831
Protoss_Observatory 1 10108
Protoss_Observer 1 10885
11860
