Protoss_Gateway 2 10437
Protoss_Assimilator 1 3319
Protoss_Cybernetics_Core 1 4675
Protoss_Robotics_Facility 1 6544
Protoss_Dragoon 5 10438
Protoss_Robotics_Support_Bay 1 6710
Protoss_Reaver 3 11512
Protoss_Shuttle 1 9028
Protoss_Scarab 8 8744
11512
