Protoss_Gateway 2 4837
Protoss_Assimilator 1 3523
Protoss_Cybernetics_Core 1 4422
Protoss_Dragoon 12 10515
Protoss_Nexus 1 10405
Protoss_Robotics_Facility 1 10267
Protoss_Observatory 1 10706
10706
