Protoss_Gateway 2 6216
Protoss_Assimilator 1 3250
Protoss_Cybernetics_Core 1 4515
Protoss_Dragoon 8 8799
Protoss_Robotics_Facility 1 8237
Protoss_Observatory 1 8407
Protoss_Shuttle 1 9371
Protoss_Zealot 6 10539
Protoss_Observer 1 9793
10539
