Protoss_Gateway 2 8207
Protoss_Assimilator 2 3835
Protoss_Zealot 5 9446
Protoss_Cybernetics_Core 1 5118
Protoss_Dragoon 2 6623
Protoss_Robotics_Facility 1 7853
Protoss_Shuttle 1 8666
Protoss_Observatory 1 8115
Protoss_Robotics_Support_Bay 1 8877
Protoss_Reaver 2 11488
11488
