Protoss_Gateway 3 11203
Protoss_Assimilator 1 3283
Protoss_Cybernetics_Core 1 4443
Protoss_Zealot 2 6581
Protoss_Robotics_Facility 1 6028
Protoss_Dragoon 5 10546
Protoss_Shuttle 1 6856
Protoss_Robotics_Support_Bay 1 7397
Protoss_Reaver 1 9161
Protoss_Observatory 1 9256
Protoss_Observer 1 10821
11203
