Protoss_Gateway 1 3313
Protoss_Assimilator 2 9689
Protoss_Cybernetics_Core 1 4472
Protoss_Dragoon 3 6937
Protoss_Stargate 2 10061
Protoss_Scout 2 9459
Protoss_Nexus 1 10221
Protoss_Air_Weapons_1 1 8291
Protoss_Fleet_Beacon 1 9997
Protoss_Carrier 2 13293
13293
