Protoss_Gateway 2 10169
Protoss_Assimilator 1 3407
Protoss_Cybernetics_Core 1 4528
Protoss_Dragoon 6 10155
Protoss_Robotics_Facility 1 6888
Protoss_Shuttle 1 7721
Protoss_Robotics_Support_Bay 1 7103
Protoss_Observatory 1 7178
Protoss_Reaver 1 8863
Protoss_Observer 1 9195
Protoss_Scarab 2 9748
10169
