Protoss_Gateway 2 7716
Protoss_Assimilator 1 3496
Protoss_Cybernetics_Core 1 4668
Protoss_Dragoon 6 11127
Protoss_Citadel_of_Adun 1 7070
Protoss_Templar_Archives 1 8068
Protoss_Dark_Templar 4 9731
Protoss_Nexus 1 10868
11127
