Protoss_Gateway 2 5161
Protoss_Assimilator 1 3427
Protoss_Cybernetics_Core 1 4538
Protoss_Dragoon 11 10979
Protoss_Citadel_of_Adun 1 7639
Protoss_Zealot 1 7933
Protoss_Templar_Archives 1 8625
Protoss_Dark_Templar 2 9835
10979
