Protoss_Assimilator 2 3852
Protoss_Gateway 3 10879
Protoss_Cybernetics_Core 1 4973
Protoss_Dragoon 6 8488
Protoss_Shield_Battery 2 7813
Protoss_Citadel_of_Adun 1 8103
Protoss_Templar_Archives 1 9207
Protoss_Dark_Templar 4 10788
Protoss_Forge 1 10024
10879
