Protoss_Gateway 2 10113
Protoss_Assimilator 1 3452
Protoss_Zealot 4 6102
Protoss_Cybernetics_Core 1 5800
Protoss_Dragoon 5 10541
Protoss_Robotics_Facility 1 7799
Protoss_Shuttle 2 9871
Protoss_Robotics_Support_Bay 1 8227
Protoss_Reaver 2 11381
Protoss_Shield_Battery 1 9512
Protoss_Observatory 1 10663
11381
