Protoss_Gateway 2 7213
Protoss_Assimilator 1 3716
Protoss_Cybernetics_Core 1 4748
Protoss_Dragoon 2 6341
Protoss_Citadel_of_Adun 1 6183
Protoss_Templar_Archives 1 7553
Protoss_Dark_Templar 4 9068
Protoss_Nexus 1 11516
Protoss_Robotics_Facility 1 11286
11516
