Protoss_Gateway 2 7444
Protoss_Assimilator 1 3309
Protoss_Cybernetics_Core 1 4360
Protoss_Dragoon 10 10465
Protoss_Robotics_Facility 1 7609
Protoss_Observatory 1 7785
Protoss_Observer 4 10903
Protoss_Nexus 2 11625
11625
