Protoss_Gateway 2 7589
Protoss_Assimilator 1 3381
Protoss_Cybernetics_Core 1 4579
Protoss_Dragoon 8 9649
Protoss_Robotics_Facility 1 7651
Protoss_Observatory 1 7741
Protoss_Observer 2 9239
Protoss_Nexus 2 12137
Protoss_Zealot 2 10521
Protoss_Shuttle 1 11389
12137
