Protoss_Gateway 3 9031
Protoss_Assimilator 1 3289
Protoss_Cybernetics_Core 1 4269
Protoss_Dragoon 8 10938
Protoss_Robotics_Facility 1 6298
Protoss_Shuttle 1 7191
Protoss_Observatory 1 6945
Protoss_Observer 2 10401
Protoss_Nexus 1 11168
11168
