Protoss_Gateway 1 2011
Protoss_Assimilator 1 2404
Protoss_Cybernetics_Core 1 3003
Protoss_Zealot 4 8729
Protoss_Robotics_Facility 1 4431
Protoss_Dragoon 3 6657
Protoss_Shuttle 1 5969
Protoss_Robotics_Support_Bay 1 6423
Protoss_Reaver 3 9343
Protoss_Scarab 13 9986
9986
