Protoss_Gateway 1 3283
Protoss_Assimilator 1 3209
Protoss_Cybernetics_Core 1 4428
Protoss_Robotics_Facility 1 5978
Protoss_Dragoon 4 8791
Protoss_Shuttle 1 6856
Protoss_Observatory 1 7628
Protoss_Observer 1 8456
8791
