Protoss_Gateway 2 11352
Protoss_Assimilator 1 3389
Protoss_Cybernetics_Core 1 4603
Protoss_Dragoon 3 7453
Protoss_Robotics_Facility 1 7495
Protoss_Forge 1 7229
Protoss_Shuttle 1 8356
Protoss_Photon_Cannon 1 8183
Protoss_Robotics_Support_Bay 1 7965
Protoss_Reaver 2 10550
11352
