Protoss_Gateway 1 3419
Protoss_Assimilator 1 3420
Protoss_Cybernetics_Core 1 4538
Protoss_Dragoon 7 11076
Protoss_Zealot 1 6671
Protoss_Robotics_Facility 1 7783
Protoss_Shuttle 1 8611
Protoss_Robotics_Support_Bay 1 8110
Protoss_Reaver 1 9753
Protoss_Nexus 1 11448
Protoss_Observatory 1 9441
Protoss_Observer 1 10796
11448
