Protoss_Gateway 3 11108
Protoss_Assimilator 1 3834
Protoss_Cybernetics_Core 1 4788
Protoss_Dragoon 9 10823
Protoss_Robotics_Facility 1 7624
Protoss_Observatory 1 7958
Protoss_Observer 4 10672
Protoss_Nexus 1 11198
11198
