Protoss_Gateway 1 3346
Protoss_Assimilator 1 3683
Protoss_Zealot 2 7575
Protoss_Cybernetics_Core 1 5025
Protoss_Robotics_Facility 1 6499
Protoss_Dragoon 5 11161
Protoss_Shuttle 1 7327
Protoss_Robotics_Support_Bay 1 7165
Protoss_Reaver 1 8677
Protoss_Observatory 1 8090
Protoss_Observer 2 9611
Protoss_Nexus 2 12690
12690
