Protoss_Gateway 2 6937
Protoss_Assimilator 1 3584
Protoss_Zealot 1 3951
Protoss_Cybernetics_Core 1 5418
Protoss_Dragoon 8 10086
Protoss_Nexus 1 10940
Protoss_Robotics_Facility 1 10513
Protoss_Shuttle 1 11411
11411
