Protoss_Gateway 3 10194
Protoss_Assimilator 1 3294
Protoss_Cybernetics_Core 1 4450
Protoss_Dragoon 9 10017
Protoss_Nexus 1 10253
Protoss_Robotics_Facility 1 10117
Protoss_Shuttle 1 11175
Protoss_Robotics_Support_Bay 1 10629
11175
