Protoss_Gateway 2 6953
Protoss_Assimilator 2 3893
Protoss_Zealot 2 5231
Protoss_Cybernetics_Core 1 5331
Protoss_Dragoon 10 10961
Protoss_Nexus 1 11123
Protoss_Robotics_Facility 1 10723
11123
