Protoss_Gateway 2 6103
Protoss_Assimilator 2 10550
Protoss_Cybernetics_Core 1 4437
Protoss_Dragoon 5 7966
Protoss_Citadel_of_Adun 1 7793
Protoss_Zealot 1 7541
Protoss_Robotics_Facility 2 11889
Protoss_Templar_Archives 1 8823
Protoss_Nexus 1 10794
Protoss_Dark_Templar 1 9696
Protoss_Stargate 1 10688
11889
