Protoss_Gateway 2 7577
Protoss_Assimilator 1 3530
Protoss_Cybernetics_Core 1 4666
Protoss_Dragoon 6 9083
Protoss_Robotics_Facility 1 7423
Protoss_Observatory 1 7649
Protoss_Observer 3 10716
Protoss_Nexus 2 12611
Protoss_Shuttle 1 10135
Protoss_Zealot 2 9931
12611
