Protoss_Gateway 2 6168
Protoss_Assimilator 1 3380
Protoss_Cybernetics_Core 1 4455
Protoss_Dragoon 7 10291
Protoss_Robotics_Facility 1 8447
Protoss_Zealot 4 9016
Protoss_Shuttle 1 9386
Protoss_Observatory 1 8926
Protoss_Observer 1 9808
Protoss_Nexus 1 12308
12308
