Protoss_Gateway 4 11075
Protoss_Assimilator 1 3453
Protoss_Cybernetics_Core 1 4588
Protoss_Dragoon 8 11001
Protoss_Robotics_Facility 1 6563
Protoss_Observatory 1 6838
Protoss_Observer 5 10608
Protoss_Nexus 1 11778
11778
