Protoss_Gateway 3 10427
Protoss_Assimilator 2 10162
Protoss_Cybernetics_Core 1 4448
Protoss_Dragoon 7 9831
Protoss_Robotics_Facility 1 8506
Protoss_Zealot 2 7871
Protoss_Nexus 1 10668
Protoss_Observatory 1 8660
Protoss_Observer 2 10121
10668
