Protoss_Gateway 2 8726
Protoss_Assimilator 1 3201
Protoss_Cybernetics_Core 1 4568
Protoss_Robotics_Facility 1 6076
Protoss_Dragoon 2 6288
Protoss_Shuttle 1 6886
Protoss_Robotics_Support_Bay 1 6468
Protoss_Zealot 2 7771
Protoss_Reaver 2 9126
Protoss_Citadel_of_Adun 1 8136
Protoss_Templar_Archives 1 9558
Protoss_Scarab 16 9702
Protoss_Dark_Templar 1 10696
10696
