Protoss_Gateway 1 1946
Protoss_Assimilator 1 2470
Protoss_Cybernetics_Core 1 3153
Protoss_Dragoon 7 9216
Protoss_Robotics_Facility 1 4578
Protoss_Shuttle 1 5876
Protoss_Robotics_Support_Bay 1 6233
Protoss_Reaver 3 9151
Protoss_Observatory 1 8224
Protoss_Scarab 5 8974
9216
