Protoss_Gateway 2 4041
Protoss_Zealot 3 4631
Protoss_Assimilator 1 4783
Protoss_Cybernetics_Core 1 5848
Protoss_Dragoon 7 11196
Protoss_Nexus 1 10422
Protoss_Robotics_Facility 1 9893
Protoss_Shuttle 1 10716
Protoss_Robotics_Support_Bay 1 10018
11196
