Protoss_Gateway 2 5658
Protoss_Assimilator 1 3455
Protoss_Zealot 2 4806
Protoss_Cybernetics_Core 1 5063
Protoss_Dragoon 11 10316
Protoss_Nexus 1 10711
Protoss_Robotics_Facility 1 10423
Protoss_Observatory 1 10692
10711
