Protoss_Nexus 1 6058
Protoss_Gateway 3 8968
Protoss_Assimilator 2 8737
Protoss_Zealot 9 10753
Protoss_Cybernetics_Core 1 6228
Protoss_Dragoon 4 8971
Protoss_Citadel_of_Adun 1 8478
Protoss_Templar_Archives 1 9518
Protoss_Dark_Templar 2 11155
11155
