Protoss_Gateway 2 7787
Protoss_Assimilator 1 3415
Protoss_Cybernetics_Core 1 4636
Protoss_Dragoon 8 9541
Protoss_Robotics_Facility 1 7732
Protoss_Observatory 1 8028
Protoss_Observer 3 10291
Protoss_Nexus 2 12740
12740
