Protoss_Gateway 3 11252
Protoss_Assimilator 1 3155
Protoss_Cybernetics_Core 1 4273
Protoss_Dragoon 10 10637
Protoss_Nexus 2 11451
Protoss_Robotics_Facility 1 9498
Protoss_Observatory 1 9614
Protoss_Shuttle 1 10525
11451
