Protoss_Gateway 2 7618
Protoss_Assimilator 1 3337
Protoss_Cybernetics_Core 1 4309
Protoss_Dragoon 9 11027
Protoss_Robotics_Facility 1 7373
Protoss_Observatory 1 7536
Protoss_Nexus 3 12809
Protoss_Observer 1 8621
Protoss_Shuttle 1 10525
Protoss_Robotics_Support_Bay 1 9999
12809
