Protoss_Gateway 3 10323
Protoss_Assimilator 1 3514
Protoss_Cybernetics_Core 1 4688
Protoss_Dragoon 11 11126
Protoss_Robotics_Facility 1 7656
Protoss_Observatory 1 7773
Protoss_Observer 4 10853
Protoss_Nexus 1 11192
11192
