Protoss_Nexus 2 11422
Protoss_Gateway 5 11133
Protoss_Zealot 8 7753
Protoss_Assimilator 1 5849
Protoss_Cybernetics_Core 1 7117
Protoss_Dragoon 6 10248
Protoss_Robotics_Facility 1 11078
Protoss_Citadel_of_Adun 1 10803
11422
