Protoss_Gateway 2 9683
Protoss_Assimilator 1 3441
Protoss_Cybernetics_Core 1 4513
Protoss_Dragoon 4 11006
Protoss_Robotics_Facility 1 6550
Protoss_Shuttle 1 7371
Protoss_Observatory 1 6789
Protoss_Robotics_Support_Bay 1 6858
Protoss_Observer 2 10615
Protoss_Reaver 2 10283
11006
