Protoss_Gateway 2 10815
Protoss_Assimilator 1 3408
Protoss_Cybernetics_Core 1 4478
Protoss_Dragoon 8 10898
Protoss_Robotics_Facility 1 7703
Protoss_Observatory 1 7840
Protoss_Nexus 1 10194
Protoss_Observer 1 8791
Protoss_Robotics_Support_Bay 1 8913
Protoss_Shuttle 1 9873
Protoss_Reaver 1 11015
11015
