Protoss_Gateway 2 6958
Protoss_Assimilator 1 3513
Protoss_Cybernetics_Core 1 4808
Protoss_Dragoon 8 9311
Protoss_Robotics_Facility 1 7996
Protoss_Observatory 1 8289
Protoss_Observer 3 10526
Protoss_Nexus 1 11403
11403
