Protoss_Gateway 4 10429
Protoss_Assimilator 1 3323
Protoss_Cybernetics_Core 1 4428
Protoss_Dragoon 11 10027
Protoss_Robotics_Facility 1 8730
Protoss_Nexus 1 10828
Protoss_Observatory 1 8865
Protoss_Observer 1 9646
Protoss_Shuttle 1 10871
Protoss_Zealot 2 10706
10871
