Protoss_Gateway 3 9318
Protoss_Assimilator 1 3588
Protoss_Zealot 2 5291
Protoss_Cybernetics_Core 1 5318
Protoss_Dragoon 10 10933
Protoss_Robotics_Facility 1 7468
Protoss_Observatory 1 7608
Protoss_Observer 2 9153
10933
