Protoss_Gateway 3 10323
Protoss_Assimilator 1 3503
Protoss_Cybernetics_Core 1 4673
Protoss_Dragoon 9 11151
Protoss_Robotics_Facility 1 7957
Protoss_Observatory 1 8160
Protoss_Nexus 1 11009
Protoss_Observer 3 10546
11151
