Protoss_Gateway 2 5128
Protoss_Assimilator 1 3448
Protoss_Cybernetics_Core 1 4608
Protoss_Dragoon 8 10826
Protoss_Zealot 1 7181
Protoss_Nexus 2 11638
Protoss_Robotics_Facility 1 11063
11638
