Protoss_Gateway 3 10927
Protoss_Assimilator 1 3366
Protoss_Cybernetics_Core 1 4356
Protoss_Dragoon 9 10347
Protoss_Robotics_Facility 1 6391
Protoss_Observatory 1 6525
Protoss_Observer 2 10205
Protoss_Nexus 2 11782
Protoss_Shuttle 1 11381
11782
