Protoss_Nexus 2 12059
Protoss_Gateway 3 11176
Protoss_Assimilator 2 6438
Protoss_Cybernetics_Core 1 5535
Protoss_Zealot 3 9723
Protoss_Citadel_of_Adun 1 6561
Protoss_Dragoon 5 10735
Protoss_Robotics_Facility 1 7640
Protoss_Shuttle 1 8575
Protoss_Robotics_Support_Bay 1 8245
Protoss_Reaver 1 9903
Protoss_Observatory 1 9005
12059
