Protoss_Gateway 2 7651
Protoss_Assimilator 1 3245
Protoss_Cybernetics_Core 1 4378
Protoss_Dragoon 12 11031
Protoss_Robotics_Facility 1 7193
Protoss_Observatory 1 7363
Protoss_Observer 2 9481
Protoss_Nexus 1 12596
12596
