Protoss_Gateway 2 4869
Protoss_Assimilator 1 3224
Protoss_Cybernetics_Core 1 4295
Protoss_Dragoon 9 10917
Protoss_Citadel_of_Adun 1 7275
Protoss_Templar_Archives 1 8305
Protoss_Zealot 2 8241
Protoss_Dark_Templar 2 9083
Protoss_Nexus 1 11308
11308
