Protoss_Gateway 3 10242
Protoss_Assimilator 1 3343
Protoss_Cybernetics_Core 1 5017
Protoss_Zealot 2 6736
Protoss_Robotics_Facility 1 6583
Protoss_Dragoon 8 11001
Protoss_Robotics_Support_Bay 1 6738
Protoss_Shuttle 1 7581
Protoss_Reaver 1 8723
11001
