Protoss_Gateway 3 8250
Protoss_Assimilator 1 3143
Protoss_Cybernetics_Core 1 4449
Protoss_Dragoon 12 11056
Protoss_Nexus 2 12648
Protoss_Robotics_Facility 1 9427
Protoss_Observatory 1 9523
Protoss_Observer 2 10898
12648
