Protoss_Gateway 3 8173
Protoss_Assimilator 1 3323
Protoss_Cybernetics_Core 1 4448
Protoss_Dragoon 11 10386
Protoss_Nexus 2 12781
Protoss_Robotics_Facility 1 9976
Protoss_Observatory 1 10272
12781
