Protoss_Gateway 6 11173
Protoss_Assimilator 1 3404
Protoss_Cybernetics_Core 1 4426
Protoss_Dragoon 9 9836
Protoss_Nexus 1 9279
Protoss_Robotics_Facility 1 9146
Protoss_Observatory 1 9342
Protoss_Observer 2 10743
11173
