Protoss_Gateway 3 10094
Protoss_Assimilator 1 3505
Protoss_Cybernetics_Core 1 4623
Protoss_Dragoon 11 11011
Protoss_Robotics_Facility 1 7816
Protoss_Nexus 1 10266
Protoss_Observatory 1 8289
Protoss_Observer 3 10395
11011
