Protoss_Gateway 3 8463
Protoss_Assimilator 1 3438
Protoss_Zealot 3 9056
Protoss_Cybernetics_Core 1 5365
Protoss_Dragoon 10 11088
Protoss_Nexus 1 9003
Protoss_Robotics_Facility 1 9588
Protoss_Observatory 1 9712
Protoss_Observer 1 10771
11088
