Protoss_Gateway 2 11074
Protoss_Assimilator 1 3441
Protoss_Cybernetics_Core 1 4528
Protoss_Zealot 1 4201
Protoss_Dragoon 7 10576
Protoss_Robotics_Facility 1 7773
Protoss_Shuttle 1 8586
Protoss_Robotics_Support_Bay 1 7968
Protoss_Reaver 1 9728
Protoss_Observatory 1 9396
Protoss_Observer 2 10908
11074
