Protoss_Gateway 1 3516
Protoss_Assimilator 1 3550
Protoss_Cybernetics_Core 1 5012
Protoss_Dragoon 3 7310
Protoss_Robotics_Facility 1 7572
Protoss_Shuttle 1 8456
Protoss_Robotics_Support_Bay 2 8028
Protoss_Reaver 2 11093
Protoss_Nexus 1 12528
12528
