Protoss_Gateway 2 4849
Protoss_Assimilator 1 3240
Protoss_Cybernetics_Core 1 4378
Protoss_Dragoon 9 10891
Protoss_Robotics_Facility 1 7912
Protoss_Shuttle 2 9676
Protoss_Robotics_Support_Bay 1 8342
Protoss_Reaver 1 9951
Protoss_Observatory 1 9233
Protoss_Nexus 1 12023
Protoss_Observer 1 10283
12023
