Protoss_Assimilator 2 7549
Protoss_Gateway 2 9730
Protoss_Zealot 7 9565
Protoss_Nexus 1 8857
Protoss_Forge 1 7476
Protoss_Photon_Cannon 5 10498
Protoss_Cybernetics_Core 1 9003
Protoss_Dragoon 3 10725
10725
