Protoss_Gateway 2 7038
Protoss_Assimilator 1 3282
Protoss_Cybernetics_Core 1 4353
Protoss_Dragoon 12 10898
Protoss_Robotics_Facility 1 6324
Protoss_Observatory 1 6470
Protoss_Shuttle 1 7631
Protoss_Nexus 1 10648
Protoss_Robotics_Support_Bay 1 9389
Protoss_Reaver 1 11591
11591
