Protoss_Gateway 4 11365
Protoss_Assimilator 1 3411
Protoss_Cybernetics_Core 1 4541
Protoss_Dragoon 2 8059
Protoss_Robotics_Facility 1 6767
Protoss_Citadel_of_Adun 1 7145
Protoss_Observatory 1 6884
Protoss_Templar_Archives 1 8135
Protoss_Observer 2 10083
Protoss_Shuttle 1 8761
Protoss_Dark_Templar 4 9883
Protoss_Nexus 1 11941
11941
