Protoss_Gateway 3 9298
Protoss_Assimilator 2 10805
Protoss_Cybernetics_Core 1 4513
Protoss_Dragoon 8 10466
Protoss_Nexus 1 8574
Protoss_Robotics_Facility 1 8438
Protoss_Observatory 1 10355
10805
