Protoss_Gateway 2 4468
Protoss_Zealot 4 7986
Protoss_Assimilator 1 4577
Protoss_Cybernetics_Core 1 6329
Protoss_Dragoon 6 10481
Protoss_Robotics_Facility 1 8973
Protoss_Nexus 1 10838
Protoss_Observatory 1 9927
Protoss_Shuttle 1 10811
10838
