Protoss_Gateway 3 10109
Protoss_Assimilator 1 3358
Protoss_Cybernetics_Core 1 4507
Protoss_Dragoon 8 9571
Protoss_Robotics_Facility 1 7342
Protoss_Observatory 1 7474
Protoss_Observer 2 9105
Protoss_Nexus 1 10740
Protoss_Zealot 5 10685
10740
