Protoss_Nexus 1 5621
Protoss_Gateway 4 10244
Protoss_Assimilator 1 4378
Protoss_Cybernetics_Core 1 5669
Protoss_Zealot 1 5745
Protoss_Dragoon 11 10983
Protoss_Robotics_Facility 1 9193
Protoss_Shuttle 1 10067
10983
