Protoss_Gateway 2 6638
Protoss_Assimilator 1 3210
Protoss_Cybernetics_Core 1 4497
Protoss_Dragoon 9 10041
Protoss_Nexus 2 12435
Protoss_Robotics_Facility 1 10002
Protoss_Shuttle 1 10957
Protoss_Robotics_Support_Bay 1 10622
12435
