Protoss_Gateway 1 1968
Protoss_Assimilator 1 2533
Protoss_Cybernetics_Core 1 3263
Protoss_Robotics_Facility 1 4467
Protoss_Dragoon 2 9976
Protoss_Zealot 3 8396
Protoss_Shuttle 1 5986
Protoss_Robotics_Support_Bay 1 6129
Protoss_Reaver 3 9996
Protoss_Scarab 8 9886
Protoss_Nexus 1 9486
9996
