Protoss_Gateway 4 10715
Protoss_Assimilator 1 3333
Protoss_Cybernetics_Core 1 4463
Protoss_Dragoon 8 9866
Protoss_Robotics_Facility 1 7338
Protoss_Observatory 1 7428
Protoss_Observer 2 9646
Protoss_Nexus 1 10763
Protoss_Shuttle 1 10961
Protoss_Zealot 2 10641
10961
