Protoss_Gateway 3 10003
Protoss_Assimilator 1 3343
Protoss_Cybernetics_Core 1 4423
Protoss_Dragoon 14 11076
Protoss_Robotics_Facility 1 7862
Protoss_Observatory 1 8380
Protoss_Observer 2 9828
11076
