Protoss_Gateway 4 10223
Protoss_Assimilator 1 3173
Protoss_Cybernetics_Core 1 4323
Protoss_Dragoon 8 11131
Protoss_Nexus 2 10695
Protoss_Robotics_Facility 1 8324
Protoss_Observatory 1 8418
Protoss_Observer 3 10911
Protoss_Citadel_of_Adun 1 9793
Protoss_Zealot 1 10061
11131
