Protoss_Gateway 2 6347
Protoss_Assimilator 1 3574
Protoss_Cybernetics_Core 1 4831
Protoss_Dragoon 8 10885
Protoss_Nexus 2 11287
Protoss_Zealot 1 9865
Protoss_Robotics_Facility 1 11255
11287
