Protoss_Nexus 2 12474
Protoss_Gateway 4 8978
Protoss_Assimilator 2 9863
Protoss_Cybernetics_Core 1 5683
Protoss_Dragoon 12 11111
Protoss_Zealot 1 7003
Protoss_Robotics_Facility 1 9107
Protoss_Observatory 1 9291
Protoss_Observer 1 10676
12474
