Protoss_Gateway 4 11351
Protoss_Assimilator 1 3343
Protoss_Cybernetics_Core 1 4426
Protoss_Dragoon 8 11055
Protoss_Zealot 2 5815
Protoss_Nexus 2 11030
Protoss_Robotics_Facility 1 10937
11351
