Protoss_Gateway 3 10025
Protoss_Assimilator 1 3514
Protoss_Cybernetics_Core 1 4649
Protoss_Dragoon 7 9220
Protoss_Robotics_Facility 1 8318
Protoss_Observatory 1 8537
Protoss_Observer 1 9436
Protoss_Zealot 5 10926
Protoss_Shuttle 1 10518
Protoss_Shield_Battery 1 10025
Protoss_Citadel_of_Adun 1 11307
11307
