Protoss_Gateway 3 10684
Protoss_Assimilator 1 3198
Protoss_Cybernetics_Core 1 4438
Protoss_Dragoon 8 10741
Protoss_Robotics_Facility 1 7243
Protoss_Observatory 1 7466
Protoss_Observer 1 8246
Protoss_Nexus 1 10653
Protoss_Zealot 4 9711
Protoss_Shuttle 1 9906
10741
