Protoss_Gateway 2 5269
Protoss_Assimilator 1 3440
Protoss_Cybernetics_Core 1 4452
Protoss_Dragoon 7 9136
Protoss_Zealot 4 9736
Protoss_Nexus 1 10305
Protoss_Citadel_of_Adun 1 10043
Protoss_Robotics_Facility 1 11217
Protoss_Templar_Archives 1 11250
11250
