Protoss_Gateway 3 11372
Protoss_Assimilator 1 3413
Protoss_Cybernetics_Core 1 4379
Protoss_Zealot 1 4079
Protoss_Dragoon 10 10953
Protoss_Nexus 1 10061
Protoss_Robotics_Facility 1 10118
Protoss_Observatory 1 10428
11372
