Protoss_Gateway 4 10775
Protoss_Assimilator 1 3428
Protoss_Cybernetics_Core 1 4568
Protoss_Dragoon 10 10996
Protoss_Nexus 1 9180
Protoss_Robotics_Facility 1 8753
Protoss_Observatory 1 9133
Protoss_Zealot 1 9531
Protoss_Observer 2 10591
10996
