Protoss_Gateway 2 4138
Protoss_Zealot 4 7668
Protoss_Assimilator 1 5023
Protoss_Cybernetics_Core 1 6348
Protoss_Dragoon 10 10993
Protoss_Nexus 1 10388
Protoss_Robotics_Facility 1 10583
10993
