Protoss_Gateway 3 9811
Protoss_Assimilator 1 3175
Protoss_Cybernetics_Core 1 4426
Protoss_Dragoon 11 10115
Protoss_Nexus 1 8893
Protoss_Robotics_Facility 1 8823
Protoss_Observatory 1 10049
10115
