Protoss_Gateway 4 10265
Protoss_Assimilator 1 3428
Protoss_Cybernetics_Core 1 4466
Protoss_Dragoon 7 9831
Protoss_Nexus 1 8783
Protoss_Zealot 7 10551
Protoss_Citadel_of_Adun 1 9677
10551
