Protoss_Gateway 2 6123
Protoss_Assimilator 1 3338
Protoss_Cybernetics_Core 1 4399
Protoss_Dragoon 4 7056
Protoss_Citadel_of_Adun 1 6872
Protoss_Templar_Archives 1 7911
Protoss_Zealot 3 9213
Protoss_Dark_Templar 5 10346
Protoss_Nexus 1 12127
Protoss_Robotics_Facility 1 11843
12127
