Protoss_Gateway 2 7216
Protoss_Assimilator 1 3534
Protoss_Cybernetics_Core 1 4640
Protoss_Dragoon 6 11061
Protoss_Citadel_of_Adun 1 6288
Protoss_Templar_Archives 1 7498
Protoss_Dark_Templar 4 9256
Protoss_Robotics_Facility 1 9426
Protoss_Shuttle 1 10366
Protoss_Nexus 1 12183
Protoss_Observatory 1 10380
12183
