Protoss_Gateway 1 3573
Protoss_Assimilator 1 3258
Protoss_Cybernetics_Core 1 4590
Protoss_Dragoon 5 11166
Protoss_Robotics_Facility 1 6366
Protoss_Zealot 2 6611
Protoss_Shuttle 1 7181
Protoss_Robotics_Support_Bay 1 6643
Protoss_Reaver 2 9375
Protoss_Scarab 17 9615
Protoss_Observatory 1 9749
Protoss_Nexus 1 12340
Protoss_Observer 1 10916
12340
