Protoss_Gateway 4 10388
Protoss_Assimilator 2 9256
Protoss_Cybernetics_Core 1 4423
Protoss_Dragoon 8 9856
Protoss_Citadel_of_Adun 1 6979
Protoss_Stargate 1 7933
Protoss_Templar_Archives 1 8137
Protoss_Nexus 1 9868
Protoss_Arbiter_Tribunal 1 9303
Protoss_Arbiter 1 13041
Protoss_Zealot 3 10691
13041
