Protoss_Assimilator 1 2783
Protoss_Gateway 5 11268
Protoss_Cybernetics_Core 1 4733
Protoss_Robotics_Facility 1 6208
Protoss_Dragoon 7 10518
Protoss_Shuttle 1 7176
Protoss_Observatory 1 6532
Protoss_Observer 3 8802
Protoss_Nexus 1 11320
Protoss_Citadel_of_Adun 1 10339
11320
