Protoss_Gateway 4 9723
Protoss_Assimilator 2 10524
Protoss_Cybernetics_Core 1 4396
Protoss_Dragoon 9 11147
Protoss_Robotics_Facility 1 7360
Protoss_Nexus 2 12632
Protoss_Observatory 1 7657
Protoss_Observer 3 9667
Protoss_Zealot 1 10811
12632
