Protoss_Gateway 2 6447
Protoss_Assimilator 1 3376
Protoss_Cybernetics_Core 1 4403
Protoss_Dragoon 14 10954
Protoss_Robotics_Facility 1 9615
Protoss_Observatory 1 9699
Protoss_Observer 1 10481
10954
