Protoss_Gateway 3 10931
Protoss_Assimilator 1 3449
Protoss_Cybernetics_Core 1 4559
Protoss_Dragoon 6 9196
Protoss_Nexus 1 8933
Protoss_Robotics_Facility 1 9215
Protoss_Shuttle 1 10186
Protoss_Robotics_Support_Bay 1 9656
Protoss_Reaver 1 11328
11328
