Protoss_Gateway 3 9418
Protoss_Assimilator 2 9800
Protoss_Cybernetics_Core 1 4291
Protoss_Dragoon 5 6817
Protoss_Nexus 1 9811
Protoss_Citadel_of_Adun 1 8679
Protoss_Robotics_Facility 1 9850
Protoss_Templar_Archives 1 9671
Protoss_Shuttle 1 10653
Protoss_Dark_Templar 3 10471
Protoss_Observatory 1 10327
10653
