Protoss_Gateway 4 11282
Protoss_Assimilator 1 3298
Protoss_Cybernetics_Core 1 4267
Protoss_Dragoon 8 9601
Protoss_Robotics_Facility 1 6574
Protoss_Observatory 1 7063
Protoss_Observer 1 8007
Protoss_Nexus 2 12252
12252
