Protoss_Gateway 2 5233
Protoss_Assimilator 1 3346
Protoss_Cybernetics_Core 1 4673
Protoss_Dragoon 5 7233
Protoss_Robotics_Facility 1 8893
Protoss_Zealot 4 8929
Protoss_Shuttle 1 9697
Protoss_Robotics_Support_Bay 1 9120
Protoss_Reaver 1 10839
10839
