Protoss_Gateway 4 10336
Protoss_Assimilator 2 8411
Protoss_Cybernetics_Core 1 4320
Protoss_Dragoon 7 9051
Protoss_Nexus 1 8902
Protoss_Robotics_Facility 1 8714
Protoss_Citadel_of_Adun 1 8618
Protoss_Templar_Archives 1 9883
Protoss_Shuttle 1 10561
Protoss_Dark_Templar 3 10921
Protoss_Stargate 1 11266
11266
