Protoss_Gateway 3 11219
Protoss_Assimilator 1 3317
Protoss_Cybernetics_Core 1 4392
Protoss_Dragoon 6 10517
Protoss_Robotics_Facility 1 7468
Protoss_Zealot 2 9675
Protoss_Shuttle 1 8473
Protoss_Robotics_Support_Bay 1 7796
Protoss_Reaver 1 9615
Protoss_Observatory 1 9122
Protoss_Observer 2 10897
Protoss_Nexus 1 12477
12477
