Protoss_Gateway 3 9541
Protoss_Assimilator 1 3359
Protoss_Cybernetics_Core 1 4511
Protoss_Zealot 5 9561
Protoss_Dragoon 7 10563
Protoss_Robotics_Facility 1 7948
Protoss_Observatory 1 8073
Protoss_Shuttle 1 8999
Protoss_Observer 2 10641
10641
