Protoss_Gateway 1 1880
Protoss_Assimilator 1 2342
Protoss_Cybernetics_Core 1 2964
Protoss_Robotics_Facility 1 4088
Protoss_Zealot 1 4253
Protoss_Dragoon 5 9803
Protoss_Shuttle 1 5367
Protoss_Robotics_Support_Bay 1 5509
Protoss_Reaver 2 7321
Protoss_Scarab 12 9911
Protoss_Observatory 1 7898
Protoss_Observer 1 8853
9911
