Protoss_Gateway 3 10937
Protoss_Assimilator 1 3295
Protoss_Cybernetics_Core 1 4406
Protoss_Zealot 3 8157
Protoss_Dragoon 5 10351
Protoss_Citadel_of_Adun 2 7167
Protoss_Templar_Archives 1 8189
Protoss_Dark_Templar 2 9073
Protoss_Robotics_Facility 1 10215
Protoss_Nexus 1 11797
Protoss_Observatory 1 10531
11797
