Protoss_Gateway 2 9177
Protoss_Assimilator 1 3508
Protoss_Cybernetics_Core 1 4793
Protoss_Dragoon 7 10036
Protoss_Robotics_Facility 1 7544
Protoss_Shuttle 1 8406
Protoss_Observatory 1 7798
Protoss_Observer 2 9596
Protoss_Robotics_Support_Bay 1 8908
Protoss_Reaver 1 11126
11126
