Protoss_Gateway 5 11218
Protoss_Assimilator 1 3244
Protoss_Cybernetics_Core 1 4314
Protoss_Dragoon 11 10596
Protoss_Nexus 2 11991
Protoss_Robotics_Facility 1 9658
Protoss_Observatory 1 9754
Protoss_Observer 1 10561
11991
