Protoss_Gateway 2 9985
Protoss_Assimilator 1 3402
Protoss_Cybernetics_Core 1 4505
Protoss_Zealot 2 8403
Protoss_Dragoon 6 10861
Protoss_Robotics_Facility 1 6551
Protoss_Observatory 1 6681
Protoss_Shuttle 1 7703
Protoss_Robotics_Support_Bay 1 7571
Protoss_Observer 2 10387
Protoss_Reaver 1 9907
Protoss_Nexus 1 12247
12247
