Protoss_Gateway 2 9107
Protoss_Assimilator 1 3474
Protoss_Cybernetics_Core 1 4373
Protoss_Robotics_Facility 1 6368
Protoss_Forge 1 5701
Protoss_Dragoon 8 10678
Protoss_Shuttle 2 10801
Protoss_Observatory 1 6570
Protoss_Observer 2 8296
Protoss_Photon_Cannon 5 11113
Protoss_Nexus 1 12400
12400
