Protoss_Gateway 2 5207
Protoss_Assimilator 1 3243
Protoss_Cybernetics_Core 1 4355
Protoss_Dragoon 10 10571
Protoss_Zealot 3 8246
Protoss_Nexus 2 11658
Protoss_Robotics_Facility 1 11088
11658
