Protoss_Nexus 2 11913
Protoss_Gateway 3 7777
Protoss_Assimilator 1 4283
Protoss_Cybernetics_Core 1 5558
Protoss_Dragoon 8 10666
Protoss_Robotics_Facility 1 8850
Protoss_Zealot 2 8126
Protoss_Shuttle 1 9706
Protoss_Robotics_Support_Bay 1 9295
Protoss_Reaver 1 10901
Protoss_Observatory 1 10459
11913
