Protoss_Gateway 2 7512
Protoss_Assimilator 1 3179
Protoss_Cybernetics_Core 1 4313
Protoss_Dragoon 6 11061
Protoss_Citadel_of_Adun 1 6658
Protoss_Templar_Archives 1 7658
Protoss_Dark_Templar 6 10326
Protoss_Nexus 2 12368
12368
