Protoss_Gateway 3 10739
Protoss_Assimilator 1 3155
Protoss_Cybernetics_Core 1 4329
Protoss_Dragoon 10 10765
Protoss_Robotics_Facility 1 7421
Protoss_Observatory 1 7590
Protoss_Observer 4 10689
Protoss_Nexus 1 11367
11367
