Protoss_Gateway 3 10473
Protoss_Assimilator 1 3187
Protoss_Cybernetics_Core 1 4424
Protoss_Dragoon 8 9885
Protoss_Robotics_Facility 1 7897
Protoss_Shuttle 1 8939
Protoss_Robotics_Support_Bay 1 8243
Protoss_Zealot 4 10859
Protoss_Reaver 2 11151
11151
