Protoss_Gateway 2 8577
Protoss_Assimilator 1 3564
Protoss_Cybernetics_Core 1 4797
Protoss_Dragoon 7 10875
Protoss_Robotics_Facility 1 6592
Protoss_Zealot 2 6665
Protoss_Shuttle 1 7401
Protoss_Robotics_Support_Bay 1 6803
Protoss_Reaver 1 8543
Protoss_Observatory 1 8053
Protoss_Observer 1 8996
Protoss_Scarab 3 9954
10875
