Protoss_Gateway 2 7179
Protoss_Assimilator 1 3393
Protoss_Cybernetics_Core 1 4518
Protoss_Dragoon 9 11185
Protoss_Citadel_of_Adun 1 5959
Protoss_Templar_Archives 1 6945
Protoss_Zealot 2 9417
Protoss_Dark_Templar 2 7945
11185
