Protoss_Assimilator 1 2841
Protoss_Gateway 2 8750
Protoss_Cybernetics_Core 1 5105
Protoss_Dragoon 3 10295
Protoss_Robotics_Facility 1 6927
Protoss_Citadel_of_Adun 1 7343
Protoss_Shuttle 1 7785
Protoss_Templar_Archives 1 8506
Protoss_Dark_Templar 2 10825
10825
