Protoss_Assimilator 1 2693
Protoss_Gateway 2 7822
Protoss_Cybernetics_Core 1 4549
Protoss_Dragoon 2 6701
Protoss_Robotics_Facility 1 6658
Protoss_Citadel_of_Adun 1 6618
Protoss_Templar_Archives 1 7775
Protoss_Observatory 1 7377
Protoss_Zealot 3 9896
Protoss_Observer 1 8156
Protoss_Dark_Templar 1 8636
Protoss_Shuttle 1 9238
Protoss_High_Templar 1 9361
9896
