Protoss_Gateway 2 10032
Protoss_Assimilator 1 3363
Protoss_Cybernetics_Core 1 4573
Protoss_Dragoon 6 10851
Protoss_Robotics_Facility 1 7314
Protoss_Observatory 1 7588
Protoss_Shuttle 1 8516
Protoss_Observer 3 10493
Protoss_Nexus 1 11171
11171
