Protoss_Gateway 2 4952
Protoss_Assimilator 1 3395
Protoss_Cybernetics_Core 1 4403
Protoss_Dragoon 8 10726
Protoss_Robotics_Facility 1 7769
Protoss_Zealot 6 9884
Protoss_Shuttle 1 8696
Protoss_Nexus 1 12808
12808
