Protoss_Gateway 3 9499
Protoss_Assimilator 1 3392
Protoss_Cybernetics_Core 1 4378
Protoss_Dragoon 13 11156
Protoss_Nexus 1 9785
Protoss_Robotics_Facility 1 9481
Protoss_Observatory 1 9760
Protoss_Observer 1 10541
11156
