Protoss_Gateway 2 10888
Protoss_Assimilator 1 3533
Protoss_Cybernetics_Core 1 4696
Protoss_Dragoon 8 10730
Protoss_Robotics_Facility 1 7283
Protoss_Observatory 1 7398
Protoss_Observer 3 10841
Protoss_Nexus 1 11888
11888
