Protoss_Gateway 4 10817
Protoss_Assimilator 1 3335
Protoss_Cybernetics_Core 1 4393
Protoss_Dragoon 10 10371
Protoss_Nexus 1 9279
Protoss_Robotics_Facility 1 9072
Protoss_Observatory 1 9335
Protoss_Observer 1 10479
Protoss_Citadel_of_Adun 1 11055
11055
