Protoss_Gateway 2 6784
Protoss_Assimilator 2 3834
Protoss_Cybernetics_Core 1 5119
Protoss_Dragoon 6 8741
Protoss_Citadel_of_Adun 1 8139
Protoss_Templar_Archives 1 9223
Protoss_Dark_Templar 4 10746
10746
