Protoss_Gateway 4 9258
Protoss_Assimilator 1 3158
Protoss_Cybernetics_Core 1 4323
Protoss_Robotics_Facility 1 5884
Protoss_Citadel_of_Adun 1 5893
Protoss_Shuttle 1 6696
Protoss_Templar_Archives 1 6943
Protoss_Dark_Templar 4 10166
Protoss_Dragoon 3 9891
Protoss_Observatory 1 9957
Protoss_Nexus 1 12418
12418
