Protoss_Gateway 3 11175
Protoss_Assimilator 1 3176
Protoss_Cybernetics_Core 1 4393
Protoss_Dragoon 10 10561
Protoss_Robotics_Facility 1 7456
Protoss_Observatory 1 7543
Protoss_Observer 3 9623
Protoss_Nexus 2 12097
12097
