Protoss_Gateway 2 7474
Protoss_Assimilator 1 3193
Protoss_Cybernetics_Core 1 4331
Protoss_Dragoon 10 10359
Protoss_Robotics_Facility 1 7273
Protoss_Observatory 1 7387
Protoss_Observer 2 8761
Protoss_Nexus 1 10865
10865
