Protoss_Gateway 2 4873
Protoss_Assimilator 1 3200
Protoss_Cybernetics_Core 1 4308
Protoss_Dragoon 7 9909
Protoss_Citadel_of_Adun 1 6559
Protoss_Zealot 1 6563
Protoss_Templar_Archives 1 7629
Protoss_Dark_Templar 5 10857
10857
