Protoss_Gateway 2 7039
Protoss_Nexus 1 6363
Protoss_Assimilator 1 4587
Protoss_Cybernetics_Core 1 5914
Protoss_Zealot 9 10681
Protoss_Dragoon 7 11181
Protoss_Shield_Battery 1 7073
11181
