Protoss_Gateway 1 3327
Protoss_Assimilator 1 3231
Protoss_Cybernetics_Core 1 4447
Protoss_Dragoon 6 10855
Protoss_Robotics_Facility 1 6543
Protoss_Shuttle 1 7403
Protoss_Robotics_Support_Bay 1 6903
Protoss_Zealot 2 8223
Protoss_Reaver 2 9680
10855
