Protoss_Gateway 3 9977
Protoss_Assimilator 1 3340
Protoss_Cybernetics_Core 1 4575
Protoss_Dragoon 11 10837
Protoss_Robotics_Facility 1 7673
Protoss_Observatory 1 7778
Protoss_Nexus 1 10346
Protoss_Observer 2 9367
Protoss_Shuttle 1 10805
Protoss_Robotics_Support_Bay 1 10160
10837
