Protoss_Nexus 1 5645
Protoss_Gateway 2 6178
Protoss_Assimilator 2 9120
Protoss_Cybernetics_Core 1 5499
Protoss_Dragoon 8 9331
Protoss_Robotics_Facility 1 9579
Protoss_Stargate 1 10170
Protoss_Observatory 1 9736
Protoss_Fleet_Beacon 1 11092
11092
