Protoss_Gateway 4 11429
Protoss_Assimilator 1 3188
Protoss_Cybernetics_Core 1 4425
Protoss_Zealot 1 4066
Protoss_Dragoon 11 11113
Protoss_Robotics_Facility 1 8018
Protoss_Observatory 1 8133
Protoss_Nexus 2 11798
Protoss_Observer 2 9513
11798
