Protoss_Gateway 3 10662
Protoss_Assimilator 1 3317
Protoss_Cybernetics_Core 1 4293
Protoss_Dragoon 9 10633
Protoss_Nexus 2 11218
Protoss_Robotics_Facility 1 10665
Protoss_Citadel_of_Adun 1 10617
11218
