Protoss_Gateway 3 8547
Protoss_Assimilator 1 3443
Protoss_Cybernetics_Core 1 4674
Protoss_Robotics_Facility 1 6248
Protoss_Dragoon 8 10631
Protoss_Observatory 1 6494
Protoss_Observer 3 8701
Protoss_Citadel_of_Adun 1 9970
Protoss_Templar_Archives 1 11203
Protoss_Shuttle 1 11416
11416
