Protoss_Nexus 1 2706
Protoss_Gateway 6 9673
Protoss_Assimilator 2 8486
Protoss_Cybernetics_Core 1 4233
Protoss_Zealot 5 9266
Protoss_Dragoon 7 8338
Protoss_Robotics_Facility 1 7058
Protoss_Observatory 1 8353
Protoss_Observer 2 9493
Protoss_Citadel_of_Adun 1 9612
9673
