Protoss_Gateway 2 4750
Protoss_Assimilator 1 3203
Protoss_Cybernetics_Core 1 4309
Protoss_Dragoon 5 7217
Protoss_Citadel_of_Adun 1 7031
Protoss_Zealot 1 6777
Protoss_Templar_Archives 1 8044
Protoss_Dark_Templar 4 10497
Protoss_Nexus 1 11225
Protoss_Robotics_Facility 1 10633
Protoss_Shuttle 1 11433
11433
