Protoss_Nexus 2 11773
Protoss_Gateway 3 7651
Protoss_Assimilator 2 10031
Protoss_Cybernetics_Core 1 5643
Protoss_Zealot 5 9130
Protoss_Dragoon 6 8618
Protoss_Robotics_Facility 1 9087
Protoss_Shuttle 1 10211
Protoss_Robotics_Support_Bay 1 9516
Protoss_Citadel_of_Adun 1 11012
Protoss_Reaver 1 11626
11773
