Protoss_Gateway 2 5785
Protoss_Assimilator 1 3317
Protoss_Cybernetics_Core 1 4375
Protoss_Dragoon 4 9975
Protoss_Citadel_of_Adun 1 7223
Protoss_Robotics_Facility 1 8077
Protoss_Templar_Archives 1 8295
Protoss_Shuttle 1 8995
Protoss_Dark_Templar 3 9793
Protoss_Nexus 1 11287
11287
