Protoss_Gateway 3 9844
Protoss_Assimilator 1 3203
Protoss_Cybernetics_Core 1 4353
Protoss_Zealot 1 4076
Protoss_Dragoon 8 10751
Protoss_Nexus 2 11823
Protoss_Robotics_Facility 1 9013
Protoss_Observatory 1 9181
Protoss_Observer 1 10121
11823
