Protoss_Gateway 2 8065
Protoss_Assimilator 1 3353
Protoss_Cybernetics_Core 1 4576
Protoss_Zealot 1 4321
Protoss_Dragoon 6 10046
Protoss_Robotics_Facility 1 7935
Protoss_Shield_Battery 1 8153
10046
