Protoss_Gateway 1 3428
Protoss_Assimilator 1 3373
Protoss_Cybernetics_Core 1 4548
Protoss_Zealot 1 4301
Protoss_Dragoon 6 9458
Protoss_Robotics_Facility 1 7693
Protoss_Shuttle 1 8756
Protoss_Observatory 1 8441
Protoss_Robotics_Support_Bay 1 8563
Protoss_Reaver 1 10221
10221
