Protoss_Assimilator 1 2733
Protoss_Gateway 3 10852
Protoss_Cybernetics_Core 1 4785
Protoss_Stargate 1 6037
Protoss_Robotics_Facility 1 7053
Protoss_Corsair 3 7751
Protoss_Dragoon 2 8516
Protoss_Shuttle 1 7946
Protoss_Robotics_Support_Bay 1 7813
Protoss_Reaver 2 10363
Protoss_Citadel_of_Adun 1 10368
Protoss_Scarab 5 9972
10852
