Protoss_Nexus 2 11462
Protoss_Gateway 4 11413
Protoss_Assimilator 2 10096
Protoss_Zealot 2 5841
Protoss_Cybernetics_Core 1 6146
Protoss_Dragoon 13 10896
Protoss_Citadel_of_Adun 1 10367
11462
