Protoss_Gateway 2 5137
Protoss_Assimilator 1 3411
Protoss_Cybernetics_Core 1 4537
Protoss_Dragoon 10 11003
Protoss_Nexus 2 11189
Protoss_Robotics_Facility 1 10453
Protoss_Shuttle 1 11305
Protoss_Robotics_Support_Bay 1 10689
11305
