Protoss_Nexus 1 5768
Protoss_Gateway 3 7943
Protoss_Assimilator 2 10244
Protoss_Cybernetics_Core 1 5823
Protoss_Zealot 5 10376
Protoss_Dragoon 8 10401
Protoss_Robotics_Facility 1 7948
Protoss_Shield_Battery 1 8008
Protoss_Shuttle 1 10331
Protoss_Robotics_Support_Bay 1 9743
Protoss_Reaver 1 11473
11473
