Protoss_Gateway 2 9569
Protoss_Assimilator 1 3297
Protoss_Cybernetics_Core 1 4399
Protoss_Zealot 4 10109
Protoss_Dragoon 7 10951
Protoss_Nexus 1 9283
Protoss_Robotics_Facility 1 8671
Protoss_Observatory 1 8811
Protoss_Observer 2 10183
10951
