Protoss_Gateway 4 10703
Protoss_Assimilator 1 3344
Protoss_Cybernetics_Core 1 4453
Protoss_Zealot 1 4313
Protoss_Dragoon 6 9669
Protoss_Robotics_Facility 1 6797
Protoss_Observatory 1 6957
Protoss_Observer 3 10461
Protoss_Nexus 1 10671
10703
