Protoss_Gateway 2 6827
Protoss_Assimilator 1 3525
Protoss_Cybernetics_Core 1 4686
Protoss_Dragoon 9 11187
Protoss_Robotics_Facility 1 6965
Protoss_Observatory 1 7106
Protoss_Observer 2 8715
Protoss_Nexus 1 11817
Protoss_Citadel_of_Adun 1 11015
11817
