Protoss_Assimilator 3 4751
Protoss_Gateway 2 6800
Protoss_Cybernetics_Core 1 4993
Protoss_Dragoon 10 11025
Protoss_Nexus 1 10149
Protoss_Robotics_Facility 1 9952
Protoss_Observatory 1 10063
11025
