Protoss_Gateway 3 11413
Protoss_Assimilator 1 3378
Protoss_Cybernetics_Core 1 4545
Protoss_Dragoon 8 10651
Protoss_Robotics_Facility 1 9043
Protoss_Nexus 1 11023
Protoss_Shuttle 1 10006
Protoss_Robotics_Support_Bay 1 9613
Protoss_Observatory 1 9658
Protoss_Zealot 2 10536
Protoss_Reaver 1 11361
11413
