Protoss_Gateway 4 11256
Protoss_Assimilator 1 3394
Protoss_Cybernetics_Core 1 4513
Protoss_Dragoon 10 10446
Protoss_Nexus 1 9120
Protoss_Robotics_Facility 1 9493
Protoss_Observatory 1 9766
Protoss_Observer 1 10621
11256
