Protoss_Gateway 2 7478
Protoss_Assimilator 1 3563
Protoss_Cybernetics_Core 1 4847
Protoss_Citadel_of_Adun 1 6000
Protoss_Dragoon 5 10911
Protoss_Templar_Archives 1 7270
Protoss_Dark_Templar 4 8993
Protoss_Nexus 1 11903
Protoss_Robotics_Facility 1 11283
11903
