Protoss_Gateway 1 3385
Protoss_Assimilator 1 3308
Protoss_Cybernetics_Core 1 4503
Protoss_Dragoon 3 10911
Protoss_Robotics_Facility 1 6213
Protoss_Shuttle 1 7016
Protoss_Robotics_Support_Bay 1 6618
Protoss_Reaver 2 9348
Protoss_Zealot 1 7826
Protoss_Nexus 1 11623
Protoss_Stargate 1 11271
11623
