Protoss_Gateway 3 9637
Protoss_Assimilator 1 3456
Protoss_Cybernetics_Core 1 4483
Protoss_Dragoon 9 11121
Protoss_Citadel_of_Adun 1 7393
Protoss_Templar_Archives 1 8603
Protoss_Dark_Templar 2 9406
Protoss_Nexus 1 12369
12369
