Protoss_Gateway 1 3462
Protoss_Assimilator 1 3458
Protoss_Cybernetics_Core 1 4613
Protoss_Dragoon 8 10815
Protoss_Robotics_Facility 1 7920
Protoss_Nexus 1 10293
Protoss_Observatory 1 8221
10815
