Protoss_Gateway 3 8639
Protoss_Assimilator 1 3403
Protoss_Zealot 7 10956
Protoss_Cybernetics_Core 1 5418
Protoss_Dragoon 11 10423
Protoss_Robotics_Facility 1 8138
Protoss_Observatory 1 8247
Protoss_Observer 2 9776
Protoss_Shuttle 1 11041
11041
