Protoss_Gateway 3 11312
Protoss_Assimilator 1 3358
Protoss_Cybernetics_Core 1 4527
Protoss_Dragoon 7 10646
Protoss_Robotics_Facility 1 8213
Protoss_Nexus 3 11158
Protoss_Observatory 1 9093
Protoss_Observer 2 10853
11312
