Protoss_Gateway 4 11424
Protoss_Assimilator 2 10293
Protoss_Cybernetics_Core 1 4428
Protoss_Dragoon 9 10766
Protoss_Nexus 2 11521
Protoss_Robotics_Facility 1 8983
Protoss_Observatory 1 9179
Protoss_Observer 2 10628
11521
