Protoss_Gateway 4 11036
Protoss_Assimilator 1 3403
Protoss_Cybernetics_Core 1 4570
Protoss_Dragoon 7 10235
Protoss_Nexus 1 8973
Protoss_Robotics_Facility 1 9033
Protoss_Zealot 5 10941
Protoss_Observatory 1 9296
Protoss_Citadel_of_Adun 1 10170
Protoss_Observer 2 10688
Protoss_Templar_Archives 1 11343
11343
