Protoss_Gateway 5 11021
Protoss_Assimilator 1 3299
Protoss_Cybernetics_Core 1 4403
Protoss_Dragoon 10 9915
Protoss_Robotics_Facility 1 7573
Protoss_Observatory 1 7738
Protoss_Observer 2 9118
Protoss_Citadel_of_Adun 1 10853
Protoss_Zealot 2 10481
11021
