Protoss_Gateway 2 8283
Protoss_Assimilator 1 3233
Protoss_Cybernetics_Core 1 4561
Protoss_Dragoon 3 7211
Protoss_Robotics_Facility 1 6686
Protoss_Citadel_of_Adun 1 7402
Protoss_Templar_Archives 1 8433
Protoss_Dark_Templar 4 9953
Protoss_Shuttle 1 9521
Protoss_Nexus 1 12283
Protoss_Observatory 1 10498
12283
