Protoss_Gateway 1 3324
Protoss_Assimilator 1 3193
Protoss_Cybernetics_Core 1 4361
Protoss_Dragoon 7 10843
Protoss_Robotics_Facility 1 7378
Protoss_Shuttle 1 8191
Protoss_Observatory 1 7543
Protoss_Observer 2 9215
Protoss_Nexus 1 11078
11078
