Protoss_Gateway 3 10631
Protoss_Assimilator 1 3374
Protoss_Cybernetics_Core 1 4362
Protoss_Dragoon 9 10975
Protoss_Nexus 2 11580
Protoss_Robotics_Facility 1 8273
Protoss_Observatory 1 9036
Protoss_Observer 2 10409
Protoss_Citadel_of_Adun 1 11334
11580
