Protoss_Gateway 3 10283
Protoss_Assimilator 1 3259
Protoss_Cybernetics_Core 1 4373
Protoss_Dragoon 11 11051
Protoss_Nexus 2 12353
Protoss_Robotics_Facility 1 10122
Protoss_Observatory 1 10270
12353
