Protoss_Gateway 3 10025
Protoss_Assimilator 1 3163
Protoss_Cybernetics_Core 1 4268
Protoss_Dragoon 9 10809
Protoss_Zealot 2 7497
Protoss_Citadel_of_Adun 1 7199
Protoss_Templar_Archives 1 8203
Protoss_Dark_Templar 2 9125
Protoss_Nexus 1 11065
11065
