Protoss_Gateway 3 10205
Protoss_Assimilator 1 3273
Protoss_Cybernetics_Core 1 4382
Protoss_Dragoon 13 10951
Protoss_Robotics_Facility 1 9171
Protoss_Nexus 1 10418
Protoss_Observatory 1 9312
Protoss_Observer 2 10708
10951
