Protoss_Gateway 2 3824
Protoss_Zealot 14 8856
Protoss_Forge 1 4726
Protoss_Photon_Cannon 4 6543
Protoss_Assimilator 1 7809
Protoss_Cybernetics_Core 1 9063
Protoss_Dragoon 4 10911
10911
