Protoss_Gateway 2 6588
Protoss_Assimilator 1 3488
Protoss_Cybernetics_Core 1 4758
Protoss_Dragoon 8 10943
Protoss_Robotics_Facility 1 6619
Protoss_Observatory 1 6761
Protoss_Observer 3 10708
Protoss_Nexus 1 11708
Protoss_Shuttle 1 10286
11708
