Protoss_Gateway 4 8018
Protoss_Assimilator 1 3466
Protoss_Cybernetics_Core 1 4609
Protoss_Dragoon 3 8766
Protoss_Citadel_of_Adun 1 5785
Protoss_Templar_Archives 1 6794
Protoss_Dark_Templar 4 9826
Protoss_Robotics_Facility 1 8913
Protoss_Shuttle 1 9951
9951
