Protoss_Assimilator 1 2805
Protoss_Gateway 4 11020
Protoss_Cybernetics_Core 1 4748
Protoss_Dragoon 11 11161
Protoss_Robotics_Facility 1 6419
Protoss_Observatory 1 6836
Protoss_Observer 3 10601
Protoss_Nexus 1 11575
11575
