Protoss_Gateway 3 11128
Protoss_Assimilator 1 3518
Protoss_Cybernetics_Core 1 4673
Protoss_Dragoon 10 10318
Protoss_Robotics_Facility 1 7973
Protoss_Observatory 1 8129
Protoss_Observer 2 9508
Protoss_Nexus 1 12163
12163
