Protoss_Gateway 2 10950
Protoss_Assimilator 1 3273
Protoss_Cybernetics_Core 1 4422
Protoss_Dragoon 5 10501
Protoss_Robotics_Facility 1 6462
Protoss_Zealot 3 7517
Protoss_Shuttle 1 7265
Protoss_Robotics_Support_Bay 1 6770
Protoss_Reaver 1 8459
Protoss_Nexus 1 10857
Protoss_Observatory 1 9479
Protoss_Scarab 2 9312
Protoss_Observer 1 10461
10950
