Protoss_Gateway 3 9764
Protoss_Assimilator 1 3551
Protoss_Cybernetics_Core 1 4732
Protoss_Zealot 1 5155
Protoss_Dragoon 9 10635
Protoss_Robotics_Facility 1 7963
Protoss_Nexus 2 12651
Protoss_Observatory 1 8139
Protoss_Observer 1 8931
12651
