Protoss_Gateway 4 11021
Protoss_Assimilator 1 3226
Protoss_Cybernetics_Core 1 4354
Protoss_Dragoon 8 10026
Protoss_Nexus 2 11067
Protoss_Robotics_Facility 1 9238
Protoss_Observatory 1 9348
Protoss_Observer 1 10726
11067
