Protoss_Gateway 4 10262
Protoss_Zealot 2 5329
Protoss_Nexus 2 10519
Protoss_Assimilator 2 9149
Protoss_Forge 1 5975
Protoss_Cybernetics_Core 1 7121
Protoss_Photon_Cannon 1 7225
Protoss_Dragoon 4 11021
Protoss_Citadel_of_Adun 1 8323
Protoss_Templar_Archives 1 9503
Protoss_Dark_Templar 2 10551
11021
