Protoss_Gateway 3 8748
Protoss_Assimilator 1 3363
Protoss_Cybernetics_Core 1 4723
Protoss_Dragoon 11 10410
Protoss_Nexus 1 9059
Protoss_Robotics_Facility 1 8331
Protoss_Observatory 1 9175
Protoss_Observer 2 10553
10553
