Protoss_Gateway 3 11134
Protoss_Assimilator 1 3203
Protoss_Cybernetics_Core 1 4618
Protoss_Dragoon 12 11077
Protoss_Robotics_Facility 1 7273
Protoss_Observatory 1 7397
Protoss_Observer 2 8791
Protoss_Nexus 1 11115
Protoss_Shuttle 1 11051
11134
