Protoss_Gateway 2 7719
Protoss_Assimilator 1 3458
Protoss_Cybernetics_Core 1 4563
Protoss_Dragoon 11 10886
Protoss_Robotics_Facility 1 7529
Protoss_Observatory 1 7800
Protoss_Observer 3 10271
Protoss_Nexus 1 12048
12048
