Protoss_Gateway 3 9785
Protoss_Assimilator 1 3221
Protoss_Cybernetics_Core 1 4438
Protoss_Dragoon 10 10287
Protoss_Robotics_Facility 1 7699
Protoss_Observatory 1 7852
Protoss_Observer 2 10761
Protoss_Nexus 1 12687
12687
