Protoss_Gateway 4 9497
Protoss_Assimilator 1 3429
Protoss_Cybernetics_Core 1 4590
Protoss_Dragoon 7 9811
Protoss_Robotics_Facility 1 6443
Protoss_Observatory 1 6612
Protoss_Observer 2 10756
Protoss_Citadel_of_Adun 1 9105
Protoss_Zealot 2 10026
Protoss_Nexus 1 12548
12548
