Protoss_Gateway 3 10786
Protoss_Assimilator 1 3513
Protoss_Cybernetics_Core 1 4554
Protoss_Dragoon 10 10721
Protoss_Robotics_Facility 1 6768
Protoss_Observatory 1 6863
Protoss_Observer 2 8294
Protoss_Shuttle 1 10721
Protoss_Zealot 1 10471
10786
