Protoss_Gateway 3 4953
Protoss_Assimilator 1 3358
Protoss_Cybernetics_Core 1 4428
Protoss_Dragoon 8 10658
Protoss_Nexus 1 8963
Protoss_Robotics_Facility 1 9443
Protoss_Zealot 3 10898
Protoss_Observatory 1 9724
Protoss_Observer 1 10636
10898
