Protoss_Gateway 1 3267
Protoss_Assimilator 3 8533
Protoss_Zealot 6 7151
Protoss_Nexus 1 8050
Protoss_Forge 1 6629
Protoss_Photon_Cannon 1 7740
Protoss_Cybernetics_Core 1 9244
Protoss_Robotics_Facility 1 10874
Protoss_Dragoon 2 11097
11097
