Protoss_Gateway 2 6243
Protoss_Zealot 3 9353
Protoss_Nexus 1 6433
Protoss_Cybernetics_Core 1 5555
Protoss_Assimilator 2 7778
Protoss_Dragoon 8 10663
Protoss_Robotics_Facility 1 10167
10663
