Protoss_Gateway 3 9693
Protoss_Assimilator 2 10177
Protoss_Cybernetics_Core 1 4294
Protoss_Dragoon 8 11051
Protoss_Robotics_Facility 1 7261
Protoss_Shuttle 1 8141
Protoss_Robotics_Support_Bay 1 7554
Protoss_Nexus 1 10117
Protoss_Reaver 1 9283
Protoss_Observatory 1 9173
Protoss_Observer 1 10003
11051
