Protoss_Assimilator 1 2761
Protoss_Gateway 3 8017
Protoss_Cybernetics_Core 1 4625
Protoss_Dragoon 11 9891
Protoss_Robotics_Facility 1 7163
Protoss_Observatory 1 7401
Protoss_Observer 1 8273
Protoss_Citadel_of_Adun 1 8815
Protoss_Nexus 1 11968
Protoss_Templar_Archives 1 10738
11968
