Protoss_Gateway 3 9173
Protoss_Zealot 1 3899
Protoss_Assimilator 2 10071
Protoss_Cybernetics_Core 1 5095
Protoss_Dragoon 9 10785
Protoss_Nexus 1 9693
Protoss_Robotics_Facility 1 10202
10785
