Protoss_Gateway 4 10494
Protoss_Assimilator 1 3463
Protoss_Cybernetics_Core 1 4639
Protoss_Dragoon 4 9276
Protoss_Robotics_Facility 1 6778
Protoss_Observatory 1 7018
Protoss_Observer 3 9746
Protoss_Nexus 1 10018
Protoss_Zealot 3 10441
Protoss_Shuttle 1 10828
10828
