Protoss_Gateway 4 10000
Protoss_Nexus 1 6139
Protoss_Assimilator 2 10757
Protoss_Cybernetics_Core 1 5407
Protoss_Zealot 1 5317
Protoss_Dragoon 9 10929
Protoss_Robotics_Facility 1 9204
Protoss_Observatory 1 9412
Protoss_Shuttle 1 10137
Protoss_Robotics_Support_Bay 1 10190
Protoss_Observer 1 10559
10929
