Protoss_Gateway 2 7627
Protoss_Assimilator 2 8598
Protoss_Cybernetics_Core 1 4309
Protoss_Dragoon 6 11059
Protoss_Nexus 1 8529
Protoss_Robotics_Facility 1 8475
Protoss_Shuttle 1 9317
Protoss_Robotics_Support_Bay 1 8902
Protoss_Zealot 3 10277
Protoss_Reaver 1 10619
Protoss_Observatory 1 10352
11059
