Protoss_Nexus 1 5676
Protoss_Gateway 3 8153
Protoss_Assimilator 1 4368
Protoss_Zealot 1 5181
Protoss_Cybernetics_Core 1 5731
Protoss_Dragoon 13 11141
Protoss_Robotics_Facility 1 9606
Protoss_Citadel_of_Adun 1 9445
11141
