Protoss_Gateway 2 9520
Protoss_Assimilator 1 3418
Protoss_Cybernetics_Core 1 4487
Protoss_Dragoon 7 11056
Protoss_Robotics_Facility 1 6803
Protoss_Shuttle 1 7621
Protoss_Robotics_Support_Bay 1 6972
Protoss_Observatory 1 7239
Protoss_Reaver 1 8763
Protoss_Citadel_of_Adun 1 9214
Protoss_Observer 3 10377
Protoss_Scarab 7 9912
11056
