Protoss_Gateway 3 7613
Protoss_Assimilator 1 3392
Protoss_Cybernetics_Core 1 4521
Protoss_Dragoon 13 10881
Protoss_Robotics_Facility 1 7459
Protoss_Observatory 1 7622
Protoss_Observer 1 9063
Protoss_Nexus 1 12125
12125
