Protoss_Gateway 3 10453
Protoss_Assimilator 1 3352
Protoss_Cybernetics_Core 1 4417
Protoss_Dragoon 11 10521
Protoss_Citadel_of_Adun 1 6738
Protoss_Robotics_Facility 1 7583
Protoss_Observatory 1 8035
Protoss_Observer 3 10078
Protoss_Nexus 2 11952
11952
