Protoss_Gateway 2 7693
Protoss_Assimilator 1 3349
Protoss_Cybernetics_Core 1 4463
Protoss_Dragoon 4 11175
Protoss_Robotics_Facility 1 7439
Protoss_Nexus 2 12679
Protoss_Observatory 1 7651
Protoss_Shuttle 1 9033
Protoss_Robotics_Support_Bay 1 8724
Protoss_Reaver 1 10267
Protoss_Zealot 2 10029
Protoss_Observer 1 10599
12679
