Protoss_Gateway 2 8100
Protoss_Assimilator 1 3401
Protoss_Cybernetics_Core 1 4543
Protoss_Dragoon 9 10336
Protoss_Robotics_Facility 1 7988
Protoss_Observatory 1 8503
Protoss_Nexus 1 11598
Protoss_Observer 1 9726
Protoss_Shuttle 1 11016
Protoss_Zealot 2 10848
11598
