Protoss_Gateway 2 7173
Protoss_Assimilator 1 3411
Protoss_Cybernetics_Core 1 4444
Protoss_Dragoon 6 10801
Protoss_Citadel_of_Adun 1 5773
Protoss_Templar_Archives 1 6783
Protoss_Dark_Templar 3 8693
Protoss_Zealot 1 8053
Protoss_Nexus 1 11078
Protoss_Forge 1 10942
11078
