Protoss_Gateway 2 9719
Protoss_Assimilator 1 3306
Protoss_Cybernetics_Core 1 4383
Protoss_Dragoon 8 10628
Protoss_Robotics_Facility 1 7793
Protoss_Citadel_of_Adun 1 8732
Protoss_Observatory 1 8177
Protoss_Shuttle 1 9361
Protoss_Observer 1 9783
Protoss_Nexus 1 12218
12218
