Protoss_Nexus 2 11247
Protoss_Gateway 5 11032
Protoss_Assimilator 1 4604
Protoss_Cybernetics_Core 1 6082
Protoss_Dragoon 7 9861
Protoss_Robotics_Facility 1 8893
Protoss_Observatory 1 9219
Protoss_Shuttle 1 10486
Protoss_Forge 1 10638
Protoss_Citadel_of_Adun 1 11233
11247
