Protoss_Gateway 2 10100
Protoss_Zealot 6 6522
Protoss_Assimilator 1 4779
Protoss_Cybernetics_Core 1 6378
Protoss_Citadel_of_Adun 1 7544
Protoss_Dragoon 3 8781
Protoss_Templar_Archives 1 8700
Protoss_Nexus 1 11076
Protoss_Dark_Templar 2 10285
Protoss_Stargate 1 10982
11076
