Protoss_Gateway 2 5061
Protoss_Assimilator 1 3435
Protoss_Cybernetics_Core 1 4517
Protoss_Dragoon 9 9861
Protoss_Zealot 2 7491
Protoss_Robotics_Facility 1 9653
Protoss_Shuttle 1 10523
Protoss_Robotics_Support_Bay 1 9913
10523
