Protoss_Gateway 3 9980
Protoss_Assimilator 1 3363
Protoss_Cybernetics_Core 1 4488
Protoss_Dragoon 9 11121
Protoss_Robotics_Facility 1 6541
Protoss_Observatory 1 6661
Protoss_Observer 2 8391
Protoss_Nexus 1 10055
Protoss_Shuttle 1 10566
11121
