Protoss_Gateway 4 11343
Protoss_Assimilator 1 3377
Protoss_Cybernetics_Core 1 4443
Protoss_Dragoon 7 9629
Protoss_Robotics_Facility 1 7792
Protoss_Observatory 1 7879
Protoss_Nexus 2 12287
Protoss_Observer 2 9309
12287
