Protoss_Gateway 2 4885
Protoss_Assimilator 1 3210
Protoss_Cybernetics_Core 1 4387
Protoss_Dragoon 10 10509
Protoss_Zealot 2 8525
Protoss_Nexus 1 10285
Protoss_Robotics_Facility 1 9867
Protoss_Shuttle 1 10899
Protoss_Robotics_Support_Bay 1 10402
10899
