Protoss_Gateway 3 8347
Protoss_Assimilator 1 3208
Protoss_Cybernetics_Core 1 4352
Protoss_Dragoon 11 10637
Protoss_Nexus 1 8805
Protoss_Robotics_Facility 1 9713
Protoss_Zealot 1 10411
Protoss_Shuttle 1 10919
Protoss_Observatory 1 10219
10919
