Protoss_Gateway 4 11317
Protoss_Assimilator 1 3378
Protoss_Cybernetics_Core 1 4566
Protoss_Dragoon 8 9825
Protoss_Robotics_Facility 1 7284
Protoss_Observatory 1 7403
Protoss_Observer 5 10713
Protoss_Nexus 2 12039
Protoss_Citadel_of_Adun 1 11397
12039
