Protoss_Gateway 2 4785
Protoss_Assimilator 1 3330
Protoss_Cybernetics_Core 1 4309
Protoss_Dragoon 5 9779
Protoss_Robotics_Facility 1 7763
Protoss_Zealot 5 8467
Protoss_Shuttle 1 8565
Protoss_Robotics_Support_Bay 1 8130
Protoss_Reaver 1 9779
Protoss_Nexus 1 12220
12220
