Protoss_Gateway 2 9353
Protoss_Assimilator 1 3345
Protoss_Cybernetics_Core 1 4606
Protoss_Dragoon 7 10361
Protoss_Robotics_Facility 1 6633
Protoss_Shuttle 1 7466
Protoss_Observatory 1 7253
Protoss_Nexus 2 12318
Protoss_Observer 1 8946
12318
