Protoss_Gateway 5 11159
Protoss_Assimilator 1 3416
Protoss_Cybernetics_Core 1 4469
Protoss_Dragoon 8 11101
Protoss_Robotics_Facility 1 7600
Protoss_Observatory 1 7713
Protoss_Observer 3 9711
Protoss_Nexus 2 11849
11849
