Protoss_Gateway 2 7486
Protoss_Assimilator 1 3370
Protoss_Cybernetics_Core 1 4483
Protoss_Dragoon 10 10649
Protoss_Robotics_Facility 1 7393
Protoss_Observatory 1 7541
Protoss_Observer 2 10301
Protoss_Nexus 1 10929
10929
