Protoss_Gateway 2 5773
Protoss_Assimilator 1 3335
Protoss_Cybernetics_Core 1 4649
Protoss_Dragoon 2 6741
Protoss_Citadel_of_Adun 1 6623
Protoss_Robotics_Facility 1 7798
Protoss_Templar_Archives 1 7653
Protoss_Shuttle 1 8606
Protoss_Dark_Templar 8 11191
11191
