Protoss_Gateway 3 11053
Protoss_Assimilator 2 4692
Protoss_Zealot 2 5453
Protoss_Cybernetics_Core 1 5734
Protoss_Dragoon 7 10631
Protoss_Robotics_Facility 1 7671
Protoss_Shuttle 1 8583
Protoss_Robotics_Support_Bay 1 8208
Protoss_Reaver 1 9767
Protoss_Observatory 1 10095
11053
