Protoss_Gateway 2 5168
Protoss_Assimilator 1 3185
Protoss_Cybernetics_Core 1 4267
Protoss_Dragoon 11 9941
Protoss_Zealot 2 7191
Protoss_Robotics_Facility 1 9601
Protoss_Shuttle 1 10441
Protoss_Robotics_Support_Bay 1 10084
Protoss_Observatory 1 10402
Protoss_Reaver 1 11583
11583
