Protoss_Gateway 3 8097
Protoss_Assimilator 1 3392
Protoss_Cybernetics_Core 1 4487
Protoss_Dragoon 10 11113
Protoss_Nexus 1 8985
Protoss_Zealot 3 9959
Protoss_Robotics_Facility 1 10171
Protoss_Observatory 1 10321
11113
