Protoss_Nexus 1 5531
Protoss_Gateway 4 10840
Protoss_Assimilator 2 9136
Protoss_Cybernetics_Core 1 5541
Protoss_Zealot 5 10267
Protoss_Dragoon 10 9725
Protoss_Robotics_Facility 1 9050
Protoss_Observatory 1 9596
10840
