Protoss_Gateway 2 5853
Protoss_Assimilator 1 3203
Protoss_Cybernetics_Core 1 4413
Protoss_Dragoon 8 9676
Protoss_Robotics_Facility 1 8063
Protoss_Shuttle 1 8871
Protoss_Robotics_Support_Bay 1 8353
Protoss_Reaver 2 11551
Protoss_Zealot 2 10506
11551
