Protoss_Gateway 3 9762
Protoss_Assimilator 1 3479
Protoss_Cybernetics_Core 1 4618
Protoss_Dragoon 7 11070
Protoss_Robotics_Facility 1 7888
Protoss_Shuttle 1 8971
Protoss_Observatory 1 8561
Protoss_Observer 2 10156
Protoss_Zealot 4 10325
11070
