Protoss_Gateway 2 8664
Protoss_Assimilator 1 3372
Protoss_Cybernetics_Core 1 4223
Protoss_Dragoon 6 10311
Protoss_Robotics_Facility 1 7826
Protoss_Zealot 6 10823
Protoss_Shuttle 1 8726
Protoss_Robotics_Support_Bay 1 8392
Protoss_Citadel_of_Adun 1 9999
Protoss_Reaver 1 10636
Protoss_Templar_Archives 1 11103
11103
