Protoss_Gateway 4 10485
Protoss_Assimilator 1 3426
Protoss_Cybernetics_Core 1 4544
Protoss_Dragoon 8 9481
Protoss_Nexus 1 8793
Protoss_Robotics_Facility 1 9351
Protoss_Shuttle 1 10199
Protoss_Robotics_Support_Bay 1 9803
Protoss_Reaver 1 11341
11341
