Protoss_Assimilator 2 10869
Protoss_Gateway 2 7458
Protoss_Cybernetics_Core 1 4761
Protoss_Dragoon 5 10623
Protoss_Robotics_Facility 1 7321
Protoss_Citadel_of_Adun 1 6989
Protoss_Templar_Archives 1 7977
Protoss_Shuttle 1 8315
Protoss_Dark_Templar 3 9485
Protoss_Observatory 1 8853
Protoss_Nexus 1 11579
Protoss_Observer 1 9733
11579
