Protoss_Gateway 2 8522
Protoss_Assimilator 1 3193
Protoss_Cybernetics_Core 1 4411
Protoss_Dragoon 6 9765
Protoss_Nexus 2 12499
Protoss_Robotics_Facility 1 8483
Protoss_Shuttle 1 9281
Protoss_Observatory 1 8594
Protoss_Robotics_Support_Bay 1 8738
Protoss_Observer 1 9703
Protoss_Reaver 1 11072
Protoss_Zealot 2 10795
12499
