Protoss_Gateway 2 9696
Protoss_Assimilator 1 3302
Protoss_Cybernetics_Core 1 4565
Protoss_Dragoon 7 10766
Protoss_Robotics_Facility 1 6584
Protoss_Shuttle 1 7401
Protoss_Observatory 1 7188
Protoss_Robotics_Support_Bay 1 7652
Protoss_Observer 2 10777
Protoss_Reaver 2 10445
10777
