Protoss_Gateway 5 10978
Protoss_Assimilator 1 3273
Protoss_Cybernetics_Core 1 4508
Protoss_Dragoon 7 11076
Protoss_Zealot 1 7723
Protoss_Nexus 2 11221
Protoss_Robotics_Facility 1 10553
11221
