Protoss_Gateway 5 11395
Protoss_Assimilator 2 9866
Protoss_Cybernetics_Core 1 4297
Protoss_Dragoon 4 7297
Protoss_Citadel_of_Adun 1 6648
Protoss_Templar_Archives 1 7667
Protoss_Nexus 2 11341
Protoss_Dark_Templar 2 9211
Protoss_Robotics_Facility 1 9513
Protoss_Observatory 1 10016
11395
