Protoss_Gateway 2 4839
Protoss_Assimilator 1 3292
Protoss_Cybernetics_Core 1 4257
Protoss_Dragoon 8 10901
Protoss_Nexus 1 9131
Protoss_Robotics_Facility 1 8651
Protoss_Shuttle 1 9547
Protoss_Robotics_Support_Bay 1 8909
Protoss_Reaver 1 10799
Protoss_Observatory 1 10686
10901
