Protoss_Gateway 2 7355
Protoss_Assimilator 1 3201
Protoss_Cybernetics_Core 1 4475
Protoss_Dragoon 8 8973
Protoss_Robotics_Facility 1 7178
Protoss_Observatory 1 7299
Protoss_Observer 1 8083
Protoss_Nexus 1 10947
Protoss_Shuttle 1 9769
Protoss_Robotics_Support_Bay 1 9461
Protoss_Reaver 1 11065
Protoss_Zealot 2 10613
11065
