Protoss_Gateway 2 5103
Protoss_Assimilator 1 3165
Protoss_Cybernetics_Core 1 4494
Protoss_Dragoon 9 10521
Protoss_Nexus 1 9532
Protoss_Robotics_Facility 1 9267
Protoss_Citadel_of_Adun 1 9199
Protoss_Forge 1 9599
Protoss_Observatory 1 9834
Protoss_Observer 1 10623
10623
