Protoss_Gateway 2 6994
Protoss_Assimilator 2 10323
Protoss_Cybernetics_Core 1 4342
Protoss_Dragoon 9 11041
Protoss_Citadel_of_Adun 1 6425
Protoss_Templar_Archives 1 7434
Protoss_Dark_Templar 2 8191
Protoss_Nexus 1 10192
Protoss_Robotics_Facility 1 11118
11118
