Protoss_Gateway 2 6233
Protoss_Assimilator 1 3176
Protoss_Cybernetics_Core 1 4362
Protoss_Dragoon 9 9919
Protoss_Robotics_Facility 1 7684
Protoss_Shuttle 1 8523
Protoss_Robotics_Support_Bay 1 7853
Protoss_Observatory 1 8716
Protoss_Reaver 1 9851
Protoss_Nexus 1 12092
Protoss_Observer 1 10441
12092
