Protoss_Assimilator 2 7059
Protoss_Gateway 4 11038
Protoss_Zealot 3 8657
Protoss_Forge 1 5087
Protoss_Photon_Cannon 5 11175
Protoss_Nexus 2 9727
Protoss_Cybernetics_Core 1 8711
Protoss_Citadel_of_Adun 1 9814
Protoss_Dragoon 1 9615
Protoss_Templar_Archives 1 11148
11175
