Protoss_Gateway 2 10770
Protoss_Assimilator 2 9409
Protoss_Cybernetics_Core 1 4375
Protoss_Dragoon 5 9069
Protoss_Nexus 2 12836
Protoss_Robotics_Facility 1 8037
Protoss_Shuttle 1 9033
Protoss_Robotics_Support_Bay 1 8355
Protoss_Reaver 1 10413
Protoss_Observatory 1 9709
Protoss_Zealot 1 10335
Protoss_Observer 1 10745
12836
