Protoss_Gateway 2 5557
Protoss_Assimilator 1 3773
Protoss_Zealot 5 10479
Protoss_Cybernetics_Core 1 5212
Protoss_Dragoon 10 9727
Protoss_Nexus 1 11787
Protoss_Citadel_of_Adun 1 10892
11787
