Protoss_Gateway 4 11185
Protoss_Assimilator 2 10436
Protoss_Cybernetics_Core 1 4346
Protoss_Dragoon 10 10083
Protoss_Nexus 1 8757
Protoss_Robotics_Facility 1 8504
Protoss_Observatory 1 8605
Protoss_Observer 1 9375
11185
