Protoss_Gateway 1 2022
Protoss_Assimilator 1 2399
Protoss_Cybernetics_Core 1 3037
Protoss_Zealot 2 6665
Protoss_Robotics_Facility 1 4154
Protoss_Dragoon 5 9973
Protoss_Shuttle 1 5531
Protoss_Robotics_Support_Bay 1 5711
Protoss_Reaver 1 6433
Protoss_Observatory 1 7873
Protoss_Observer 3 9609
Protoss_Scarab 5 9606
Protoss_Nexus 1 9383
9973
