Protoss_Gateway 4 10978
Protoss_Assimilator 1 3167
Protoss_Cybernetics_Core 1 4359
Protoss_Zealot 1 4133
Protoss_Dragoon 9 11053
Protoss_Robotics_Facility 1 7685
Protoss_Observatory 1 7824
Protoss_Nexus 2 12826
Protoss_Observer 2 9539
12826
