Protoss_Gateway 4 10981
Protoss_Assimilator 1 3161
Protoss_Cybernetics_Core 1 4317
Protoss_Dragoon 11 11045
Protoss_Nexus 1 9994
Protoss_Robotics_Facility 1 9514
Protoss_Observatory 1 9607
Protoss_Observer 1 10379
11045
