Protoss_Gateway 2 7216
Protoss_Assimilator 1 3141
Protoss_Cybernetics_Core 1 4261
Protoss_Dragoon 10 10837
Protoss_Robotics_Facility 1 7142
Protoss_Observatory 1 7262
Protoss_Nexus 2 11491
Protoss_Observer 3 10653
11491
