Protoss_Nexus 2 10802
Protoss_Gateway 2 6233
Protoss_Assimilator 2 9902
Protoss_Cybernetics_Core 1 5671
Protoss_Dragoon 9 10479
Protoss_Robotics_Facility 1 9322
Protoss_Citadel_of_Adun 1 10292
Protoss_Observatory 1 9583
10802
