Protoss_Gateway 4 10576
Protoss_Assimilator 1 3193
Protoss_Cybernetics_Core 1 4295
Protoss_Zealot 2 6865
Protoss_Dragoon 6 10733
Protoss_Robotics_Facility 1 5914
Protoss_Shuttle 1 6759
Protoss_Robotics_Support_Bay 1 6276
Protoss_Reaver 1 7941
Protoss_Nexus 1 10544
Protoss_Observatory 1 8517
Protoss_Scarab 10 9967
Protoss_Observer 1 10235
10733
