Protoss_Nexus 1 5517
Protoss_Gateway 4 10375
Protoss_Assimilator 2 8586
Protoss_Cybernetics_Core 1 5487
Protoss_Zealot 1 5477
Protoss_Dragoon 12 10513
Protoss_Robotics_Facility 1 10051
Protoss_Observatory 1 10208
10513
