Protoss_Gateway 2 7369
Protoss_Assimilator 2 9928
Protoss_Cybernetics_Core 1 4387
Protoss_Zealot 3 9569
Protoss_Citadel_of_Adun 2 6445
Protoss_Dragoon 4 10493
Protoss_Templar_Archives 1 7556
Protoss_Dark_Templar 2 8469
Protoss_Nexus 1 10643
Protoss_Stargate 1 9937
Protoss_Arbiter_Tribunal 1 11043
11043
