Protoss_Gateway 2 5469
Protoss_Assimilator 1 3428
Protoss_Cybernetics_Core 1 4488
Protoss_Dragoon 7 10915
Protoss_Robotics_Facility 1 8036
Protoss_Nexus 1 9795
Protoss_Shuttle 1 8835
Protoss_Robotics_Support_Bay 1 8285
Protoss_Reaver 1 10473
Protoss_Zealot 2 9883
Protoss_Observatory 1 9724
Protoss_Observer 1 10805
10915
