Protoss_Assimilator 5 8915
Protoss_Gateway 3 11301
Protoss_Cybernetics_Core 1 4971
Protoss_Dragoon 9 10647
Protoss_Nexus 1 9299
Protoss_Robotics_Facility 1 9548
Protoss_Observatory 1 9711
Protoss_Citadel_of_Adun 1 10491
Protoss_Observer 1 10515
11301
