Protoss_Nexus 1 5523
Protoss_Gateway 5 9908
Protoss_Assimilator 1 4407
Protoss_Cybernetics_Core 1 5533
Protoss_Dragoon 16 11189
Protoss_Robotics_Facility 1 9049
Protoss_Zealot 2 10067
11189
