Protoss_Nexus 2 12109
Protoss_Gateway 2 6271
Protoss_Assimilator 1 4476
Protoss_Cybernetics_Core 1 5665
Protoss_Zealot 5 10257
Protoss_Dragoon 8 11155
Protoss_Robotics_Facility 1 10130
Protoss_Observatory 1 10420
12109
