Protoss_Gateway 2 8082
Protoss_Assimilator 1 3198
Protoss_Cybernetics_Core 1 4492
Protoss_Zealot 1 4191
Protoss_Dragoon 9 10617
Protoss_Nexus 1 9379
Protoss_Robotics_Facility 1 9666
Protoss_Observatory 1 9957
Protoss_Shuttle 1 10961
Protoss_Robotics_Support_Bay 1 10611
10961
