Protoss_Gateway 4 11216
Protoss_Assimilator 1 3330
Protoss_Cybernetics_Core 1 4453
Protoss_Dragoon 9 10455
Protoss_Nexus 1 9743
Protoss_Robotics_Facility 1 9340
Protoss_Observatory 1 9487
Protoss_Observer 2 10869
11216
