Protoss_Gateway 3 8909
Protoss_Assimilator 2 10280
Protoss_Cybernetics_Core 1 4295
Protoss_Dragoon 12 10903
Protoss_Nexus 1 8631
Protoss_Robotics_Facility 1 8843
Protoss_Observatory 1 8987
Protoss_Observer 2 10361
Protoss_Citadel_of_Adun 1 10693
10903
