Protoss_Nexus 2 12325
Protoss_Gateway 2 6317
Protoss_Assimilator 1 4292
Protoss_Cybernetics_Core 1 5521
Protoss_Zealot 2 6013
Protoss_Dragoon 9 10961
Protoss_Robotics_Facility 1 10395
Protoss_Observatory 1 10593
12325
