Protoss_Gateway 4 11012
Protoss_Assimilator 1 3319
Protoss_Zealot 2 4713
Protoss_Cybernetics_Core 1 5015
Protoss_Dragoon 11 10987
Protoss_Nexus 1 9466
Protoss_Robotics_Facility 1 8825
Protoss_Observatory 1 8939
Protoss_Observer 2 10895
11012
