Protoss_Gateway 3 7813
Protoss_Assimilator 1 3269
Protoss_Cybernetics_Core 1 4377
Protoss_Dragoon 9 9735
Protoss_Nexus 1 8527
Protoss_Robotics_Facility 1 7796
Protoss_Observatory 1 8067
Protoss_Observer 2 9703
Protoss_Zealot 3 10247
Protoss_Shuttle 1 10893
10893
