Protoss_Gateway 2 9230
Protoss_Assimilator 1 3447
Protoss_Cybernetics_Core 1 4516
Protoss_Zealot 1 4215
Protoss_Dragoon 9 10981
Protoss_Robotics_Facility 1 7435
Protoss_Observatory 1 7521
Protoss_Nexus 1 10119
Protoss_Observer 2 9169
Protoss_Robotics_Support_Bay 1 9064
Protoss_Shuttle 1 10461
10981
