Protoss_Gateway 2 9169
Protoss_Assimilator 1 3161
Protoss_Cybernetics_Core 1 4308
Protoss_Zealot 1 4545
Protoss_Robotics_Facility 1 6185
Protoss_Dragoon 6 11197
Protoss_Shuttle 2 10979
Protoss_Robotics_Support_Bay 1 6322
Protoss_Reaver 1 8231
Protoss_Observatory 1 8963
Protoss_Nexus 1 11494
Protoss_Observer 1 9739
Protoss_Scarab 3 9443
11494
