Protoss_Nexus 1 5557
Protoss_Gateway 4 9590
Protoss_Assimilator 2 7343
Protoss_Cybernetics_Core 1 5537
Protoss_Dragoon 12 10467
Protoss_Robotics_Facility 1 9251
Protoss_Observatory 1 9441
Protoss_Observer 2 10907
10907
