Protoss_Gateway 4 10233
Protoss_Assimilator 2 10537
Protoss_Zealot 2 4743
Protoss_Cybernetics_Core 1 4919
Protoss_Dragoon 8 10405
Protoss_Robotics_Facility 1 7629
Protoss_Observatory 1 7747
Protoss_Observer 3 10813
Protoss_Nexus 1 10501
10813
