Protoss_Gateway 4 10696
Protoss_Assimilator 2 8989
Protoss_Cybernetics_Core 1 4261
Protoss_Dragoon 8 9983
Protoss_Nexus 2 10871
Protoss_Robotics_Facility 1 10087
Protoss_Citadel_of_Adun 1 10051
Protoss_Observatory 1 10189
Protoss_Observer 1 10957
10957
