Protoss_Gateway 2 9507
Protoss_Zealot 5 8843
Protoss_Assimilator 1 3902
Protoss_Cybernetics_Core 1 5162
Protoss_Dragoon 6 10949
Protoss_Robotics_Facility 1 7262
Protoss_Shuttle 1 8095
Protoss_Robotics_Support_Bay 1 7689
Protoss_Reaver 1 9273
Protoss_Observatory 1 8856
Protoss_Observer 1 9629
Protoss_Nexus 1 12265
Protoss_Scarab 2 9875
12265
