Protoss_Gateway 2 4134
Protoss_Zealot 11 9453
Protoss_Forge 1 5805
Protoss_Assimilator 1 7118
Protoss_Photon_Cannon 4 9745
Protoss_Cybernetics_Core 1 9716
Protoss_Dragoon 2 10519
10519
