Protoss_Nexus 2 12738
Protoss_Gateway 5 10274
Protoss_Assimilator 2 7418
Protoss_Cybernetics_Core 1 5572
Protoss_Zealot 4 10035
Protoss_Dragoon 5 8740
Protoss_Robotics_Facility 1 8141
Protoss_Shuttle 1 9123
Protoss_Observatory 2 10166
Protoss_Observer 1 10949
12738
