Protoss_Gateway 1 3320
Protoss_Assimilator 1 3313
Protoss_Cybernetics_Core 1 4422
Protoss_Dragoon 6 10045
Protoss_Nexus 2 10624
Protoss_Robotics_Facility 1 8719
Protoss_Shuttle 1 9863
Protoss_Robotics_Support_Bay 1 9792
Protoss_Zealot 1 10557
Protoss_Reaver 1 11305
Protoss_Observatory 1 10618
11305
