Protoss_Gateway 4 10652
Protoss_Assimilator 1 3245
Protoss_Zealot 1 3891
Protoss_Nexus 2 10810
Protoss_Cybernetics_Core 1 5687
Protoss_Dragoon 11 11199
Protoss_Robotics_Facility 1 10298
Protoss_Forge 1 10933
11199
