Protoss_Gateway 3 11127
Protoss_Assimilator 1 3232
Protoss_Zealot 2 4665
Protoss_Cybernetics_Core 1 4907
Protoss_Dragoon 8 11059
Protoss_Robotics_Facility 1 8098
Protoss_Nexus 1 10162
Protoss_Observatory 1 8185
Protoss_Observer 2 9949
Protoss_Citadel_of_Adun 1 9507
Protoss_Templar_Archives 1 11073
11127
