Protoss_Gateway 2 9161
Protoss_Assimilator 2 10478
Protoss_Cybernetics_Core 1 4294
Protoss_Dragoon 4 8719
Protoss_Nexus 2 11873
Protoss_Robotics_Facility 1 8142
Protoss_Citadel_of_Adun 1 8235
Protoss_Observatory 1 8320
Protoss_Templar_Archives 1 9603
Protoss_Observer 1 9391
Protoss_Shuttle 1 10061
Protoss_Dark_Templar 2 10399
11873
