Protoss_Gateway 3 5793
Protoss_Assimilator 2 4621
Protoss_Zealot 6 7143
Protoss_Cybernetics_Core 1 7090
Protoss_Citadel_of_Adun 1 8117
Protoss_Robotics_Facility 1 8753
Protoss_Dragoon 2 8347
Protoss_Templar_Archives 1 9223
Protoss_Shuttle 1 9673
Protoss_Dark_Templar 4 10795
Protoss_Nexus 1 12127
12127
