Protoss_Gateway 2 5638
Protoss_Assimilator 1 2409
Protoss_Cybernetics_Core 1 2983
Protoss_Dragoon 7 9187
Protoss_Robotics_Facility 1 5372
Protoss_Shuttle 1 6671
Protoss_Robotics_Support_Bay 1 6700
Protoss_Zealot 1 6713
Protoss_Reaver 1 7573
Protoss_Nexus 1 8299
Protoss_Observatory 1 8564
Protoss_Observer 1 9099
Protoss_Scarab 1 9836
9836
