Protoss_Gateway 4 11393
Protoss_Assimilator 2 9631
Protoss_Cybernetics_Core 1 4365
Protoss_Dragoon 9 10885
Protoss_Robotics_Facility 1 7611
Protoss_Nexus 1 9439
Protoss_Observatory 1 7824
Protoss_Observer 3 9819
Protoss_Citadel_of_Adun 1 9220
Protoss_Templar_Archives 1 10805
11393
