Protoss_Gateway 2 7659
Protoss_Assimilator 1 3436
Protoss_Cybernetics_Core 1 4521
Protoss_Zealot 1 4209
Protoss_Dragoon 10 10715
Protoss_Robotics_Facility 1 8001
Protoss_Shuttle 1 8895
Protoss_Robotics_Support_Bay 1 9073
Protoss_Observatory 1 9391
Protoss_Reaver 1 10595
Protoss_Observer 1 10927
10927
