Protoss_Gateway 2 7305
Protoss_Zealot 7 7811
Protoss_Forge 1 4289
Protoss_Photon_Cannon 3 6281
Protoss_Assimilator 1 6163
Protoss_Cybernetics_Core 1 7961
Protoss_Dragoon 4 10091
Protoss_Citadel_of_Adun 1 10389
10389
