Protoss_Gateway 2 9072
Protoss_Assimilator 2 8682
Protoss_Cybernetics_Core 1 4273
Protoss_Dragoon 5 10347
Protoss_Citadel_of_Adun 1 6483
Protoss_Templar_Archives 1 7520
Protoss_Nexus 1 9447
Protoss_Dark_Templar 1 8263
Protoss_Stargate 2 10787
Protoss_Fleet_Beacon 1 9997
Protoss_Carrier 1 13145
13145
