Protoss_Gateway 2 8267
Protoss_Assimilator 2 10649
Protoss_Cybernetics_Core 1 4299
Protoss_Dragoon 10 11073
Protoss_Robotics_Facility 1 7165
Protoss_Nexus 2 11597
Protoss_Observatory 1 7464
Protoss_Observer 4 10463
11597
