Protoss_Gateway 3 9808
Protoss_Assimilator 1 3325
Protoss_Cybernetics_Core 1 4461
Protoss_Dragoon 11 11057
Protoss_Zealot 2 6909
Protoss_Nexus 1 9517
Protoss_Robotics_Facility 1 9605
Protoss_Observatory 1 10203
11057
