Protoss_Gateway 2 9354
Protoss_Assimilator 1 3260
Protoss_Cybernetics_Core 1 4279
Protoss_Zealot 1 4093
Protoss_Dragoon 8 10193
Protoss_Robotics_Facility 1 7313
Protoss_Observatory 1 7444
Protoss_Nexus 2 12609
Protoss_Observer 5 10769
12609
