Protoss_Gateway 3 10321
Protoss_Assimilator 1 3393
Protoss_Cybernetics_Core 1 4415
Protoss_Dragoon 5 11125
Protoss_Robotics_Facility 1 6373
Protoss_Shuttle 1 7191
Protoss_Robotics_Support_Bay 1 6605
Protoss_Zealot 2 8059
Protoss_Reaver 2 9539
Protoss_Observatory 1 9952
Protoss_Nexus 1 12583
Protoss_Observer 1 10819
12583
