Protoss_Gateway 3 10907
Protoss_Assimilator 1 3432
Protoss_Cybernetics_Core 1 4614
Protoss_Dragoon 4 11107
Protoss_Citadel_of_Adun 1 6874
Protoss_Templar_Archives 1 7885
Protoss_Zealot 1 7557
Protoss_Dark_Templar 7 11065
Protoss_Nexus 1 11779
11779
