Protoss_Gateway 2 9003
Protoss_Assimilator 1 3133
Protoss_Zealot 3 4957
Protoss_Cybernetics_Core 1 5276
Protoss_Dragoon 9 10841
Protoss_Nexus 1 9023
Protoss_Robotics_Facility 1 8783
Protoss_Shuttle 1 10423
Protoss_Robotics_Support_Bay 1 10014
Protoss_Reaver 1 11565
Protoss_Observatory 1 10713
11565
