Protoss_Gateway 3 9709
Protoss_Assimilator 2 8896
Protoss_Cybernetics_Core 1 4350
Protoss_Nexus 1 7942
Protoss_Dragoon 9 10669
Protoss_Robotics_Facility 1 7685
Protoss_Observatory 1 8028
Protoss_Observer 3 10859
Protoss_Citadel_of_Adun 1 10324
Protoss_Zealot 1 10841
10859
