Protoss_Gateway 3 9021
Protoss_Assimilator 1 3167
Protoss_Cybernetics_Core 1 4311
Protoss_Zealot 1 4107
Protoss_Dragoon 8 9769
Protoss_Nexus 2 12213
Protoss_Robotics_Facility 1 8922
Protoss_Observatory 1 9349
Protoss_Observer 2 10745
12213
