Protoss_Gateway 3 11315
Protoss_Assimilator 1 3139
Protoss_Cybernetics_Core 1 4347
Protoss_Zealot 1 4043
Protoss_Dragoon 10 11179
Protoss_Robotics_Facility 1 7107
Protoss_Observatory 1 7192
Protoss_Nexus 1 9817
Protoss_Observer 2 8623
Protoss_Shuttle 1 9705
Protoss_Robotics_Support_Bay 1 9484
Protoss_Reaver 1 11105
11315
