Protoss_Gateway 2 7829
Protoss_Assimilator 2 9127
Protoss_Cybernetics_Core 1 4273
Protoss_Dragoon 7 10615
Protoss_Nexus 1 8521
Protoss_Robotics_Facility 1 7891
Protoss_Shuttle 1 8855
Protoss_Robotics_Support_Bay 1 8601
Protoss_Reaver 1 10115
Protoss_Zealot 2 9523
Protoss_Observatory 1 9399
Protoss_Citadel_of_Adun 1 10563
Protoss_Observer 1 10447
Protoss_Stargate 1 11579
11579
