Protoss_Gateway 2 8196
Protoss_Assimilator 1 3366
Protoss_Zealot 1 3949
Protoss_Cybernetics_Core 1 4840
Protoss_Dragoon 6 10511
Protoss_Citadel_of_Adun 1 7045
Protoss_Robotics_Facility 1 8410
Protoss_Templar_Archives 1 8079
Protoss_Dark_Templar 3 9759
Protoss_Shuttle 1 9423
Protoss_Observatory 1 8860
Protoss_Observer 2 10681
10681
