Protoss_Nexus 2 11222
Protoss_Gateway 5 11411
Protoss_Assimilator 2 6840
Protoss_Cybernetics_Core 1 5667
Protoss_Zealot 2 10345
Protoss_Dragoon 8 11151
Protoss_Robotics_Facility 1 8603
Protoss_Observatory 1 8729
Protoss_Observer 1 10057
Protoss_Citadel_of_Adun 1 10604
Protoss_Forge 1 10196
Protoss_Shuttle 1 11139
11411
