Protoss_Gateway 3 11250
Protoss_Assimilator 1 3203
Protoss_Cybernetics_Core 1 4343
Protoss_Dragoon 9 10963
Protoss_Nexus 2 11667
Protoss_Robotics_Facility 1 8867
Protoss_Observatory 1 9274
Protoss_Observer 2 10807
11667
