Protoss_Gateway 4 9153
Protoss_Assimilator 1 3312
Protoss_Cybernetics_Core 1 4411
Protoss_Dragoon 10 11003
Protoss_Robotics_Facility 1 7615
Protoss_Nexus 1 9495
Protoss_Observatory 1 7747
Protoss_Observer 4 10519
Protoss_Zealot 2 10729
11003
