Protoss_Gateway 3 10225
Protoss_Assimilator 1 3364
Protoss_Cybernetics_Core 1 4464
Protoss_Nexus 1 8183
Protoss_Dragoon 8 9817
Protoss_Robotics_Facility 1 9774
Protoss_Zealot 2 10547
Protoss_Shuttle 1 11039
Protoss_Observatory 1 10399
11039
