Protoss_Gateway 2 8571
Protoss_Assimilator 1 3162
Protoss_Cybernetics_Core 1 4193
Protoss_Dragoon 7 9371
Protoss_Robotics_Facility 1 7099
Protoss_Observatory 1 7277
Protoss_Nexus 1 9783
Protoss_Observer 2 9030
Protoss_Shuttle 1 10214
Protoss_Robotics_Support_Bay 1 9619
Protoss_Reaver 1 11398
Protoss_Zealot 2 10711
11398
