Protoss_Gateway 4 10749
Protoss_Assimilator 1 3182
Protoss_Cybernetics_Core 1 4301
Protoss_Dragoon 12 10673
Protoss_Nexus 1 7374
Protoss_Zealot 1 8525
Protoss_Robotics_Facility 1 9971
Protoss_Shuttle 1 11159
11159
