Protoss_Gateway 2 4873
Protoss_Assimilator 1 3181
Protoss_Cybernetics_Core 1 4297
Protoss_Dragoon 9 9585
Protoss_Robotics_Facility 1 8743
Protoss_Shuttle 1 9545
Protoss_Robotics_Support_Bay 1 8847
Protoss_Zealot 3 10111
Protoss_Reaver 1 10689
Protoss_Observatory 1 10269
Protoss_Nexus 1 12879
12879
