Protoss_Gateway 4 11303
Protoss_Assimilator 2 10090
Protoss_Cybernetics_Core 1 4317
Protoss_Dragoon 11 10753
Protoss_Nexus 1 9741
Protoss_Robotics_Facility 1 9479
Protoss_Observatory 1 9701
Protoss_Citadel_of_Adun 1 10506
Protoss_Observer 1 10473
11303
