Protoss_Gateway 2 9702
Protoss_Assimilator 1 3265
Protoss_Cybernetics_Core 1 4377
Protoss_Zealot 1 4153
Protoss_Dragoon 9 10797
Protoss_Nexus 1 8981
Protoss_Robotics_Facility 1 8979
Protoss_Shuttle 1 10181
Protoss_Robotics_Support_Bay 1 10262
10797
