Protoss_Gateway 2 8851
Protoss_Assimilator 1 2315
Protoss_Cybernetics_Core 1 2971
Protoss_Zealot 1 3245
Protoss_Robotics_Facility 1 4146
Protoss_Dragoon 4 9717
Protoss_Robotics_Support_Bay 1 5455
Protoss_Shuttle 1 5899
Protoss_Reaver 1 6801
Protoss_Observatory 1 7685
Protoss_Observer 1 8399
Protoss_Scarab 6 9508
Protoss_Nexus 1 9846
9846
