Protoss_Gateway 2 9017
Protoss_Assimilator 1 2373
Protoss_Cybernetics_Core 1 2943
Protoss_Dragoon 6 9629
Protoss_Robotics_Facility 1 5419
Protoss_Shuttle 1 6735
Protoss_Robotics_Support_Bay 1 7112
Protoss_Nexus 1 7485
Protoss_Reaver 1 7755
Protoss_Observatory 1 8187
Protoss_Observer 2 9699
Protoss_Scarab 2 9871
9871
