Protoss_Gateway 2 8085
Protoss_Assimilator 1 3199
Protoss_Cybernetics_Core 1 4280
Protoss_Zealot 2 8863
Protoss_Dragoon 8 10821
Protoss_Nexus 1 8119
Protoss_Robotics_Facility 1 7633
Protoss_Shuttle 1 8555
Protoss_Robotics_Support_Bay 1 8422
Protoss_Reaver 1 9913
Protoss_Observatory 1 9422
Protoss_Observer 1 10331
Protoss_Scarab 3 9914
10821
