Protoss_Nexus 2 12227
Protoss_Gateway 2 5757
Protoss_Assimilator 1 4315
Protoss_Cybernetics_Core 1 5603
Protoss_Zealot 1 5609
Protoss_Dragoon 8 9829
Protoss_Robotics_Facility 1 9951
Protoss_Shuttle 1 11173
12227
