Protoss_Gateway 2 8605
Protoss_Assimilator 2 9515
Protoss_Cybernetics_Core 1 4625
Protoss_Dragoon 10 11109
Protoss_Nexus 1 9157
Protoss_Robotics_Facility 1 9707
Protoss_Stargate 1 10654
Protoss_Observatory 1 9961
Protoss_Observer 1 10751
11109
