Protoss_Gateway 3 11082
Protoss_Assimilator 1 3381
Protoss_Cybernetics_Core 1 4402
Protoss_Nexus 2 8784
Protoss_Dragoon 9 10457
Protoss_Robotics_Facility 1 10071
Protoss_Observatory 1 10271
11082
