Protoss_Gateway 2 6707
Protoss_Assimilator 1 3370
Protoss_Cybernetics_Core 1 4467
Protoss_Dragoon 11 10709
Protoss_Nexus 1 9991
Protoss_Robotics_Facility 1 10156
Protoss_Citadel_of_Adun 1 9788
10709
