Protoss_Gateway 2 10221
Protoss_Assimilator 2 10670
Protoss_Cybernetics_Core 1 4258
Protoss_Zealot 1 4127
Protoss_Dragoon 7 10309
Protoss_Robotics_Facility 1 7902
Protoss_Observatory 1 8297
Protoss_Nexus 1 10496
Protoss_Observer 2 9669
Protoss_Citadel_of_Adun 1 9779
Protoss_Templar_Archives 1 10769
Protoss_Shuttle 1 10843
10843
