Protoss_Gateway 2 9404
Protoss_Assimilator 2 9498
Protoss_Cybernetics_Core 1 4430
Protoss_Dragoon 10 11199
Protoss_Robotics_Facility 1 7365
Protoss_Nexus 1 9933
Protoss_Observatory 1 7857
Protoss_Observer 3 10131
Protoss_Citadel_of_Adun 1 9816
11199
