Protoss_Gateway 1 3500
Protoss_Assimilator 1 3454
Protoss_Cybernetics_Core 1 4540
Protoss_Zealot 2 7253
Protoss_Robotics_Facility 1 6356
Protoss_Dragoon 5 10533
Protoss_Shuttle 1 7271
Protoss_Robotics_Support_Bay 1 6732
Protoss_Reaver 1 8413
Protoss_Nexus 1 10997
Protoss_Observatory 1 10543
10997
