Protoss_Gateway 1 3267
Protoss_Assimilator 1 3255
Protoss_Cybernetics_Core 1 4298
Protoss_Zealot 4 10263
Protoss_Dragoon 6 9149
Protoss_Robotics_Facility 1 7477
Protoss_Shuttle 1 8283
Protoss_Robotics_Support_Bay 1 7605
Protoss_Reaver 2 10477
Protoss_Observatory 1 9857
Protoss_Nexus 1 12510
Protoss_Observer 1 10809
12510
