Protoss_Gateway 2 8446
Protoss_Assimilator 2 10380
Protoss_Cybernetics_Core 1 4259
Protoss_Zealot 2 9201
Protoss_Dragoon 8 11145
Protoss_Nexus 1 8833
Protoss_Robotics_Facility 1 8553
Protoss_Shuttle 1 9355
Protoss_Robotics_Support_Bay 1 9165
Protoss_Observatory 1 9643
Protoss_Reaver 1 10663
Protoss_Citadel_of_Adun 1 10948
11145
