Protoss_Gateway 2 4985
Protoss_Assimilator 1 3225
Protoss_Cybernetics_Core 1 4463
Protoss_Dragoon 7 8375
Protoss_Citadel_of_Adun 1 7929
Protoss_Robotics_Facility 1 9809
Protoss_Templar_Archives 1 9424
Protoss_Dark_Templar 3 11191
Protoss_Nexus 1 12298
Protoss_Shuttle 1 11115
12298
