Protoss_Gateway 2 10175
Protoss_Assimilator 2 9539
Protoss_Cybernetics_Core 1 4467
Protoss_Zealot 1 4371
Protoss_Dragoon 5 9275
Protoss_Nexus 2 12704
Protoss_Robotics_Facility 1 8382
Protoss_Citadel_of_Adun 1 8632
Protoss_Shuttle 1 9349
Protoss_Templar_Archives 1 9866
Protoss_Dark_Templar 1 10625
12704
