Protoss_Gateway 2 8024
Protoss_Assimilator 2 10320
Protoss_Cybernetics_Core 1 4501
Protoss_Dragoon 8 10385
Protoss_Nexus 1 9088
Protoss_Citadel_of_Adun 1 8522
Protoss_Robotics_Facility 1 9639
Protoss_Templar_Archives 1 9923
Protoss_Observatory 1 9867
Protoss_Dark_Templar 1 10695
Protoss_Observer 1 10651
10695
