Protoss_Gateway 3 11357
Protoss_Assimilator 1 3125
Protoss_Cybernetics_Core 1 4289
Protoss_Dragoon 10 10821
Protoss_Robotics_Facility 1 7069
Protoss_Observatory 1 7169
Protoss_Nexus 1 9607
Protoss_Observer 2 8559
Protoss_Shuttle 1 9691
Protoss_Robotics_Support_Bay 1 9075
Protoss_Reaver 1 10883
11357
