Protoss_Gateway 2 7099
Protoss_Assimilator 1 3189
Protoss_Cybernetics_Core 1 4289
Protoss_Zealot 1 4135
Protoss_Dragoon 13 11153
Protoss_Robotics_Facility 1 7396
Protoss_Observatory 1 7535
Protoss_Observer 2 10841
Protoss_Nexus 1 12027
12027
