Protoss_Gateway 1 3311
Protoss_Assimilator 1 3204
Protoss_Zealot 2 4497
Protoss_Cybernetics_Core 1 4574
Protoss_Dragoon 8 11078
Protoss_Nexus 1 9378
Protoss_Robotics_Facility 1 10018
Protoss_Shuttle 1 10990
11078
