Protoss_Gateway 2 6571
Protoss_Assimilator 1 3385
Protoss_Cybernetics_Core 1 4412
Protoss_Dragoon 11 10679
Protoss_Robotics_Facility 1 8399
Protoss_Robotics_Support_Bay 1 8783
Protoss_Zealot 2 9085
Protoss_Shuttle 1 9965
Protoss_Reaver 1 11107
11107
