Protoss_Nexus 1 5388
Protoss_Gateway 2 11314
Protoss_Assimilator 1 4175
Protoss_Cybernetics_Core 1 5304
Protoss_Zealot 1 4935
Protoss_Dragoon 6 10490
Protoss_Robotics_Facility 1 10981
11314
