Protoss_Gateway 3 9554
Protoss_Assimilator 1 3201
Protoss_Cybernetics_Core 1 4295
Protoss_Dragoon 6 10723
Protoss_Citadel_of_Adun 1 6228
Protoss_Robotics_Facility 1 7221
Protoss_Templar_Archives 1 7539
Protoss_Zealot 1 7323
Protoss_Shuttle 1 8125
Protoss_Dark_Templar 3 9065
Protoss_Nexus 1 11933
Protoss_Observatory 1 10438
11933
