Protoss_Gateway 6 10871
Protoss_Assimilator 1 3215
Protoss_Cybernetics_Core 1 4397
Protoss_Dragoon 6 10755
Protoss_Nexus 2 11174
Protoss_Robotics_Facility 1 8441
Protoss_Shuttle 1 9257
Protoss_Robotics_Support_Bay 1 8783
Protoss_Reaver 1 10399
Protoss_Observatory 1 10287
11174
