Protoss_Gateway 2 7031
Protoss_Zealot 3 5157
Protoss_Assimilator 1 3923
Protoss_Cybernetics_Core 1 5171
Protoss_Dragoon 11 11091
Protoss_Nexus 1 10267
Protoss_Robotics_Facility 1 9859
Protoss_Shuttle 1 10693
Protoss_Robotics_Support_Bay 1 10245
11091
