Protoss_Gateway 4 10792
Protoss_Assimilator 1 3351
Protoss_Cybernetics_Core 1 4503
Protoss_Dragoon 9 10859
Protoss_Citadel_of_Adun 1 7167
Protoss_Templar_Archives 1 8154
Protoss_Nexus 1 10310
Protoss_Dark_Templar 2 8913
Protoss_Stargate 1 11575
11575
