Protoss_Gateway 2 9333
Protoss_Assimilator 1 2501
Protoss_Cybernetics_Core 1 3163
Protoss_Dragoon 4 9081
Protoss_Robotics_Facility 1 5025
Protoss_Shuttle 1 6375
Protoss_Robotics_Support_Bay 1 6397
Protoss_Reaver 2 8329
Protoss_Zealot 1 7543
Protoss_Observatory 1 8266
Protoss_Nexus 1 8833
Protoss_Observer 1 9381
Protoss_Scarab 4 9934
9934
