Protoss_Gateway 2 11227
Protoss_Assimilator 1 3507
Protoss_Cybernetics_Core 1 4703
Protoss_Dragoon 6 10959
Protoss_Robotics_Facility 1 7571
Protoss_Nexus 1 9510
Protoss_Shuttle 1 8387
Protoss_Robotics_Support_Bay 1 8025
Protoss_Zealot 2 9759
Protoss_Reaver 2 10905
11227
