Protoss_Gateway 2 6772
Protoss_Assimilator 1 3396
Protoss_Cybernetics_Core 1 4380
Protoss_Dragoon 10 10091
Protoss_Robotics_Facility 1 7849
Protoss_Observatory 1 8419
Protoss_Zealot 1 8959
Protoss_Observer 2 10153
Protoss_Nexus 1 11893
11893
