Protoss_Nexus 2 11328
Protoss_Gateway 4 11372
Protoss_Assimilator 2 9019
Protoss_Cybernetics_Core 1 5511
Protoss_Zealot 1 5177
Protoss_Dragoon 10 10627
Protoss_Citadel_of_Adun 1 8967
Protoss_Robotics_Facility 1 10609
Protoss_Templar_Archives 1 10478
11372
