Protoss_Gateway 2 9161
Protoss_Assimilator 1 3157
Protoss_Zealot 1 3815
Protoss_Cybernetics_Core 1 4524
Protoss_Dragoon 7 10837
Protoss_Citadel_of_Adun 1 5747
Protoss_Templar_Archives 1 6776
Protoss_Dark_Templar 2 8371
Protoss_Nexus 1 9741
Protoss_Robotics_Facility 1 10914
10914
