Protoss_Gateway 2 8033
Protoss_Assimilator 3 4091
Protoss_Zealot 2 5023
Protoss_Cybernetics_Core 1 5173
Protoss_Nexus 1 7833
Protoss_Dragoon 10 11085
Protoss_Robotics_Facility 1 9973
Protoss_Forge 1 9808
11085
