Protoss_Assimilator 3 8586
Protoss_Gateway 4 10694
Protoss_Zealot 3 6593
Protoss_Nexus 1 7435
Protoss_Cybernetics_Core 1 6865
Protoss_Dragoon 9 10913
Protoss_Robotics_Facility 1 10957
Protoss_Citadel_of_Adun 1 11117
11117
