Protoss_Gateway 1 3253
Protoss_Assimilator 1 3305
Protoss_Cybernetics_Core 1 4316
Protoss_Zealot 1 4135
Protoss_Dragoon 6 10693
Protoss_Robotics_Facility 1 7321
Protoss_Shuttle 1 8117
Protoss_Robotics_Support_Bay 1 7873
Protoss_Reaver 1 9363
Protoss_Nexus 1 11061
Protoss_Observatory 1 8979
Protoss_Observer 2 10401
Protoss_Scarab 1 9971
11061
