Protoss_Gateway 3 11337
Protoss_Assimilator 2 10099
Protoss_Cybernetics_Core 1 4388
Protoss_Zealot 3 10631
Protoss_Dragoon 6 9831
Protoss_Nexus 1 9163
Protoss_Robotics_Facility 1 8773
Protoss_Citadel_of_Adun 1 9417
Protoss_Observatory 1 8917
Protoss_Observer 2 10337
Protoss_Templar_Archives 1 10441
Protoss_Stargate 1 11151
11337
