Protoss_Gateway 2 10268
Protoss_Assimilator 2 9429
Protoss_Cybernetics_Core 1 4581
Protoss_Dragoon 4 8341
Protoss_Nexus 1 9126
Protoss_Citadel_of_Adun 1 8218
Protoss_Robotics_Facility 1 8989
Protoss_Templar_Archives 1 9408
Protoss_Observatory 1 9134
Protoss_Shuttle 1 10106
Protoss_Dark_Templar 3 11026
Protoss_Observer 1 10528
11026
