Protoss_Gateway 4 10241
Protoss_Assimilator 1 3160
Protoss_Cybernetics_Core 1 4289
Protoss_Zealot 1 4027
Protoss_Dragoon 12 11155
Protoss_Nexus 1 9443
Protoss_Robotics_Facility 1 9197
Protoss_Observatory 1 9426
Protoss_Observer 2 10807
11155
