Protoss_Gateway 2 6138
Protoss_Zealot 2 4331
Protoss_Assimilator 1 4079
Protoss_Cybernetics_Core 1 5613
Protoss_Dragoon 6 10246
Protoss_Nexus 1 10938
Protoss_Citadel_of_Adun 1 9723
Protoss_Templar_Archives 1 10740
Protoss_Robotics_Facility 1 11852
11852
