Protoss_Gateway 3 10779
Protoss_Assimilator 2 9157
Protoss_Cybernetics_Core 1 4323
Protoss_Dragoon 11 10772
Protoss_Robotics_Facility 1 7216
Protoss_Nexus 1 9077
Protoss_Observatory 1 7399
Protoss_Observer 2 8823
10779
