Protoss_Nexus 1 5476
Protoss_Gateway 2 5733
Protoss_Assimilator 2 10079
Protoss_Cybernetics_Core 1 5577
Protoss_Zealot 3 10715
Protoss_Dragoon 7 10203
Protoss_Robotics_Facility 1 8994
Protoss_Shuttle 1 9869
Protoss_Observatory 1 9327
Protoss_Robotics_Support_Bay 1 9385
Protoss_Observer 1 10425
10715
