Protoss_Gateway 3 8649
Protoss_Assimilator 1 3295
Protoss_Cybernetics_Core 1 4278
Protoss_Dragoon 12 10597
Protoss_Nexus 1 8263
Protoss_Robotics_Facility 1 8301
Protoss_Observatory 1 8441
Protoss_Observer 2 10651
10651
