Protoss_Gateway 2 10011
Protoss_Assimilator 1 3602
Protoss_Zealot 4 9087
Protoss_Cybernetics_Core 1 5106
Protoss_Dragoon 7 11063
Protoss_Robotics_Facility 1 7400
Protoss_Shuttle 1 8203
Protoss_Robotics_Support_Bay 1 7951
Protoss_Reaver 1 9449
Protoss_Nexus 1 10909
Protoss_Observatory 1 10226
11063
