Protoss_Gateway 2 8058
Protoss_Assimilator 1 3556
Protoss_Zealot 3 5075
Protoss_Cybernetics_Core 1 5385
Protoss_Dragoon 3 7651
Protoss_Citadel_of_Adun 1 7463
Protoss_Templar_Archives 1 8511
Protoss_Robotics_Facility 1 9040
Protoss_Dark_Templar 4 10064
Protoss_Shuttle 1 9845
Protoss_Observatory 1 10055
Protoss_Observer 1 10871
10871
