Protoss_Assimilator 3 8616
Protoss_Gateway 4 10690
Protoss_Nexus 1 6593
Protoss_Cybernetics_Core 1 6032
Protoss_Zealot 2 8293
Protoss_Dragoon 11 11113
Protoss_Citadel_of_Adun 1 8109
Protoss_Robotics_Facility 1 11405
11405
