Protoss_Gateway 4 10028
Protoss_Assimilator 2 9717
Protoss_Cybernetics_Core 1 4427
Protoss_Dragoon 6 10353
Protoss_Citadel_of_Adun 1 6564
Protoss_Templar_Archives 1 7679
Protoss_Nexus 1 9357
Protoss_Dark_Templar 2 10223
Protoss_Robotics_Facility 1 9953
Protoss_Observatory 1 10625
10625
