Protoss_Gateway 1 3260
Protoss_Assimilator 1 3119
Protoss_Cybernetics_Core 1 4245
Protoss_Zealot 2 9147
Protoss_Dragoon 6 10805
Protoss_Robotics_Facility 1 7318
Protoss_Shuttle 1 8117
Protoss_Robotics_Support_Bay 1 7738
Protoss_Nexus 1 10273
Protoss_Reaver 1 9351
Protoss_Observatory 1 9248
Protoss_Observer 2 10697
Protoss_Scarab 2 9976
10805
