Protoss_Gateway 2 10720
Protoss_Assimilator 1 3289
Protoss_Cybernetics_Core 1 4315
Protoss_Dragoon 6 10791
Protoss_Robotics_Facility 1 7261
Protoss_Nexus 1 9695
Protoss_Shuttle 1 8673
Protoss_Robotics_Support_Bay 1 8442
Protoss_Zealot 2 9717
Protoss_Reaver 1 10087
Protoss_Observatory 1 10223
10791
