Protoss_Nexus 1 5503
Protoss_Gateway 4 9317
Protoss_Assimilator 2 7048
Protoss_Cybernetics_Core 1 5687
Protoss_Zealot 3 10425
Protoss_Dragoon 10 10516
Protoss_Robotics_Facility 1 8785
Protoss_Observatory 1 8918
Protoss_Shuttle 1 10063
Protoss_Observer 1 10485
10516
