Protoss_Gateway 2 6313
Protoss_Zealot 2 5299
Protoss_Nexus 2 12144
Protoss_Assimilator 2 7594
Protoss_Cybernetics_Core 1 5597
Protoss_Dragoon 9 10795
Protoss_Robotics_Facility 1 8957
Protoss_Observatory 1 9171
Protoss_Observer 2 10801
Protoss_Citadel_of_Adun 1 10823
12144
