Protoss_Gateway 2 4751
Protoss_Assimilator 1 3203
Protoss_Cybernetics_Core 1 4353
Protoss_Dragoon 11 11049
Protoss_Nexus 1 9009
Protoss_Robotics_Facility 1 10531
Protoss_Observatory 1 10652
11049
