Protoss_Assimilator 1 2806
Protoss_Gateway 2 8054
Protoss_Cybernetics_Core 1 4771
Protoss_Zealot 1 4601
Protoss_Dragoon 10 10397
Protoss_Nexus 1 8699
Protoss_Robotics_Facility 1 8953
Protoss_Observatory 1 9261
Protoss_Observer 2 10645
10645
