Protoss_Gateway 1 1877
Protoss_Assimilator 1 2246
Protoss_Cybernetics_Core 1 2891
Protoss_Dragoon 6 9621
Protoss_Robotics_Facility 1 5382
Protoss_Shuttle 1 6665
Protoss_Robotics_Support_Bay 1 6879
Protoss_Reaver 1 7567
Protoss_Zealot 1 7723
Protoss_Observatory 1 7830
Protoss_Nexus 1 8409
Protoss_Observer 2 9221
Protoss_Scarab 6 9976
9976
