Protoss_Gateway 2 6624
Protoss_Assimilator 2 4693
Protoss_Cybernetics_Core 1 4422
Protoss_Dragoon 11 10472
Protoss_Nexus 2 12531
Protoss_Robotics_Facility 1 9825
Protoss_Observatory 1 10009
Protoss_Observer 1 10921
12531
