Protoss_Gateway 1 3337
Protoss_Assimilator 1 3304
Protoss_Cybernetics_Core 1 4338
Protoss_Zealot 2 8989
Protoss_Dragoon 6 11069
Protoss_Robotics_Facility 1 7561
Protoss_Shuttle 1 8361
Protoss_Robotics_Support_Bay 1 7969
Protoss_Reaver 1 9615
Protoss_Observatory 2 9737
Protoss_Observer 2 10805
Protoss_Scarab 1 9955
11069
