Protoss_Gateway 4 9973
Protoss_Assimilator 2 10229
Protoss_Cybernetics_Core 1 4261
Protoss_Zealot 1 4083
Protoss_Dragoon 9 10255
Protoss_Nexus 1 8830
Protoss_Robotics_Facility 1 8565
Protoss_Observatory 1 8682
Protoss_Observer 2 10101
Protoss_Citadel_of_Adun 1 10833
Protoss_Shuttle 1 11273
11273
