Protoss_Nexus 2 12233
Protoss_Gateway 2 5889
Protoss_Assimilator 1 4237
Protoss_Cybernetics_Core 1 5637
Protoss_Zealot 1 5677
Protoss_Dragoon 10 10907
Protoss_Robotics_Facility 1 11743
12233
