Protoss_Gateway 2 6022
Protoss_Assimilator 1 3143
Protoss_Cybernetics_Core 1 4245
Protoss_Zealot 3 10869
Protoss_Dragoon 10 10347
Protoss_Nexus 1 10169
Protoss_Robotics_Facility 1 9883
Protoss_Shuttle 1 10779
Protoss_Robotics_Support_Bay 1 10191
10869
