Protoss_Gateway 2 8854
Protoss_Assimilator 2 8461
Protoss_Cybernetics_Core 1 4267
Protoss_Zealot 1 4031
Protoss_Dragoon 9 10859
Protoss_Nexus 1 8127
Protoss_Robotics_Facility 1 8433
Protoss_Observatory 1 8765
Protoss_Observer 2 10197
Protoss_Citadel_of_Adun 1 10255
Protoss_Stargate 1 11164
Protoss_Templar_Archives 1 11266
11266
