Protoss_Gateway 2 7199
Protoss_Assimilator 2 9879
Protoss_Cybernetics_Core 1 4306
Protoss_Robotics_Facility 1 6061
Protoss_Dragoon 8 10881
Protoss_Observatory 1 6299
Protoss_Zealot 1 6861
Protoss_Observer 2 8251
Protoss_Nexus 1 10521
Protoss_Citadel_of_Adun 1 9480
Protoss_Templar_Archives 1 10488
10881
