Protoss_Gateway 2 7438
Protoss_Assimilator 2 10147
Protoss_Cybernetics_Core 1 4363
Protoss_Dragoon 7 11033
Protoss_Robotics_Facility 1 6709
Protoss_Citadel_of_Adun 1 6759
Protoss_Templar_Archives 1 7749
Protoss_Shuttle 1 8071
Protoss_Dark_Templar 4 9467
Protoss_Nexus 1 10831
Protoss_Stargate 1 10302
11033
