Protoss_Gateway 2 9118
Protoss_Assimilator 1 3095
Protoss_Cybernetics_Core 1 4256
Protoss_Zealot 3 9287
Protoss_Dragoon 5 11007
Protoss_Robotics_Facility 1 7295
Protoss_Shuttle 1 8097
Protoss_Robotics_Support_Bay 1 8276
Protoss_Observatory 1 8328
Protoss_Reaver 1 9769
Protoss_Nexus 2 12645
Protoss_Observer 1 10101
Protoss_Scarab 2 9975
12645
