Protoss_Assimilator 1 2809
Protoss_Gateway 3 9558
Protoss_Cybernetics_Core 1 4588
Protoss_Robotics_Facility 1 6553
Protoss_Dragoon 10 11198
Protoss_Shuttle 2 10906
Protoss_Observatory 1 7569
Protoss_Observer 3 9675
Protoss_Robotics_Support_Bay 1 8420
11198
