Protoss_Gateway 3 9224
Protoss_Assimilator 1 3385
Protoss_Cybernetics_Core 1 4409
Protoss_Zealot 1 4153
Protoss_Dragoon 10 10165
Protoss_Nexus 1 9157
Protoss_Robotics_Facility 1 11298
11298
