Protoss_Gateway 2 7343
Protoss_Assimilator 1 3333
Protoss_Cybernetics_Core 1 4427
Protoss_Dragoon 8 9525
Protoss_Robotics_Facility 1 7415
Protoss_Observatory 1 7960
Protoss_Observer 1 9195
Protoss_Nexus 2 12179
Protoss_Shuttle 1 10277
Protoss_Robotics_Support_Bay 1 10379
Protoss_Zealot 2 10853
12179
