Protoss_Gateway 3 10121
Protoss_Assimilator 2 9056
Protoss_Cybernetics_Core 1 4562
Protoss_Dragoon 6 11061
Protoss_Citadel_of_Adun 1 7002
Protoss_Nexus 1 9509
Protoss_Templar_Archives 1 8319
Protoss_Robotics_Facility 1 9658
Protoss_Dark_Templar 3 10833
Protoss_Observatory 1 9883
Protoss_Stargate 1 11072
Protoss_Observer 1 10783
11072
