Protoss_Gateway 3 9624
Protoss_Assimilator 1 3217
Protoss_Cybernetics_Core 1 4341
Protoss_Dragoon 10 11153
Protoss_Robotics_Facility 1 6338
Protoss_Observatory 1 6624
Protoss_Observer 4 10181
Protoss_Nexus 2 11879
11879
