Protoss_Gateway 3 10443
Protoss_Assimilator 2 3854
Protoss_Zealot 2 5096
Protoss_Cybernetics_Core 1 5273
Protoss_Dragoon 6 10686
Protoss_Robotics_Facility 1 8398
Protoss_Nexus 1 10439
Protoss_Observatory 1 8494
Protoss_Observer 2 10093
10686
