Protoss_Gateway 2 11040
Protoss_Assimilator 4 4621
Protoss_Cybernetics_Core 1 4785
Protoss_Dragoon 4 10603
Protoss_Robotics_Facility 1 7692
Protoss_Shuttle 1 8633
Protoss_Robotics_Support_Bay 1 8295
Protoss_Reaver 1 9827
Protoss_Zealot 2 9761
Protoss_Observatory 1 9482
Protoss_Observer 1 10707
11040
