Protoss_Nexus 2 11629
Protoss_Gateway 4 11050
Protoss_Assimilator 1 4269
Protoss_Cybernetics_Core 1 5405
Protoss_Zealot 1 5459
Protoss_Dragoon 3 7423
Protoss_Citadel_of_Adun 1 7971
Protoss_Robotics_Facility 1 9436
Protoss_Templar_Archives 1 8972
Protoss_Dark_Templar 2 9851
Protoss_Shuttle 1 10249
Protoss_Observatory 1 9848
Protoss_Observer 1 10671
11629
