Protoss_Nexus 1 5561
Protoss_Gateway 3 10335
Protoss_Assimilator 2 8761
Protoss_Cybernetics_Core 1 5574
Protoss_Zealot 1 5365
Protoss_Dragoon 10 10317
Protoss_Robotics_Facility 1 9092
Protoss_Observatory 1 9493
Protoss_Observer 2 10907
Protoss_Citadel_of_Adun 1 11072
11072
