Protoss_Gateway 2 7081
Protoss_Assimilator 3 7373
Protoss_Zealot 3 6319
Protoss_Nexus 2 12078
Protoss_Cybernetics_Core 1 6590
Protoss_Dragoon 5 9283
Protoss_Robotics_Facility 1 8885
Protoss_Shuttle 1 9717
Protoss_Observatory 1 9129
Protoss_Robotics_Support_Bay 1 9453
Protoss_Observer 1 10139
Protoss_Reaver 1 11519
12078
