Protoss_Gateway 2 9165
Protoss_Assimilator 1 3209
Protoss_Cybernetics_Core 1 4229
Protoss_Zealot 1 4011
Protoss_Dragoon 6 9249
Protoss_Robotics_Facility 1 7139
Protoss_Observatory 1 7227
Protoss_Nexus 1 9893
Protoss_Observer 2 8603
Protoss_Shuttle 1 9823
Protoss_Robotics_Support_Bay 1 9458
Protoss_Reaver 1 10999
10999
