Protoss_Gateway 2 9119
Protoss_Assimilator 1 3279
Protoss_Cybernetics_Core 1 4403
Protoss_Dragoon 10 10761
Protoss_Robotics_Facility 1 7679
Protoss_Nexus 1 9873
Protoss_Observatory 1 7843
Protoss_Observer 3 10017
10761
