Protoss_Nexus 1 5557
Protoss_Gateway 4 9045
Protoss_Assimilator 2 7884
Protoss_Cybernetics_Core 1 5519
Protoss_Dragoon 11 10163
Protoss_Robotics_Facility 1 8714
Protoss_Zealot 1 8183
Protoss_Observatory 1 8853
Protoss_Observer 2 10251
Protoss_Robotics_Support_Bay 1 10073
10251
