Protoss_Nexus 1 5602
Protoss_Gateway 2 10413
Protoss_Assimilator 2 6734
Protoss_Cybernetics_Core 1 5618
Protoss_Stargate 2 7293
Protoss_Forge 1 7054
Protoss_Corsair 4 8591
Protoss_Photon_Cannon 3 9060
Protoss_Dragoon 2 10296
Protoss_Robotics_Facility 1 10398
Protoss_Robotics_Support_Bay 1 10534
Protoss_Shuttle 1 11331
11331
