Protoss_Gateway 2 7683
Protoss_Assimilator 2 9105
Protoss_Cybernetics_Core 1 4457
Protoss_Dragoon 8 10647
Protoss_Nexus 1 8536
Protoss_Robotics_Facility 1 8489
Protoss_Citadel_of_Adun 1 9321
Protoss_Observatory 1 8665
Protoss_Observer 2 10039
Protoss_Templar_Archives 1 11422
11422
