Protoss_Gateway 9 7507
Protoss_Assimilator 1 5419
Protoss_Cybernetics_Core 1 6781
Protoss_Dragoon 2 8287
Protoss_Zealot 2 9081
Protoss_Citadel_of_Adun 1 9048
Protoss_Robotics_Facility 1 9848
Protoss_Nexus 1 11599
Protoss_Templar_Archives 1 10283
Protoss_Shuttle 1 10749
Protoss_Dark_Templar 2 11039
11599
