Protoss_Gateway 2 7269
Protoss_Assimilator 2 10166
Protoss_Cybernetics_Core 1 4299
Protoss_Zealot 1 4079
Protoss_Dragoon 8 10741
Protoss_Citadel_of_Adun 1 6456
Protoss_Robotics_Facility 1 7604
Protoss_Templar_Archives 1 7457
Protoss_Shuttle 1 8409
Protoss_Dark_Templar 3 9807
Protoss_Nexus 1 11109
Protoss_Observatory 1 9397
Protoss_Observer 1 10625
11109
