Protoss_Gateway 2 7276
Protoss_Assimilator 1 3155
Protoss_Cybernetics_Core 1 4299
Protoss_Zealot 1 3997
Protoss_Dragoon 6 11163
Protoss_Citadel_of_Adun 1 6026
Protoss_Robotics_Facility 1 7408
Protoss_Templar_Archives 1 7519
Protoss_Shuttle 2 10951
Protoss_Dark_Templar 3 10411
Protoss_Observatory 1 8273
Protoss_Observer 1 9071
Protoss_Nexus 1 11490
11490
