Protoss_Gateway 3 10789
Protoss_Assimilator 1 3248
Protoss_Cybernetics_Core 1 4538
Protoss_Dragoon 4 9021
Protoss_Robotics_Facility 1 6531
Protoss_Observatory 1 6796
Protoss_Citadel_of_Adun 1 7547
Protoss_Observer 2 8606
Protoss_Nexus 1 10265
Protoss_Templar_Archives 1 8903
Protoss_Dark_Templar 3 10801
10801
