Protoss_Gateway 4 10940
Protoss_Assimilator 1 3157
Protoss_Cybernetics_Core 1 4266
Protoss_Dragoon 7 10773
Protoss_Nexus 2 11146
Protoss_Robotics_Facility 1 8817
Protoss_Observatory 1 8945
Protoss_Observer 2 10317
11146
