Protoss_Gateway 2 8964
Protoss_Assimilator 1 3774
Protoss_Cybernetics_Core 1 4607
Protoss_Zealot 5 10206
Protoss_Dragoon 5 8640
Protoss_Robotics_Facility 1 8462
Protoss_Observatory 1 8614
Protoss_Observer 1 9571
Protoss_Nexus 1 11759
Protoss_Shuttle 1 10751
11759
