Protoss_Gateway 3 9804
Protoss_Assimilator 1 2424
Protoss_Cybernetics_Core 1 2998
Protoss_Dragoon 6 9977
Protoss_Robotics_Facility 1 4399
Protoss_Zealot 2 6257
Protoss_Shuttle 1 5683
Protoss_Robotics_Support_Bay 1 5837
Protoss_Reaver 1 6951
Protoss_Observatory 1 7977
Protoss_Scarab 5 9869
Protoss_Observer 2 9743
Protoss_Nexus 1 9501
9977
