Protoss_Gateway 2 6517
Protoss_Assimilator 2 10290
Protoss_Cybernetics_Core 1 4415
Protoss_Citadel_of_Adun 1 5505
Protoss_Dragoon 8 11139
Protoss_Templar_Archives 1 6891
Protoss_Dark_Templar 3 10263
Protoss_Nexus 1 11841
Protoss_Stargate 1 11236
11841
