Protoss_Gateway 3 10561
Protoss_Assimilator 1 3251
Protoss_Cybernetics_Core 1 4401
Protoss_Dragoon 10 10920
Protoss_Robotics_Facility 1 6708
Protoss_Robotics_Support_Bay 1 6738
Protoss_Shuttle 1 7476
Protoss_Reaver 1 8591
Protoss_Scarab 2 8317
Protoss_Observatory 1 9720
Protoss_Nexus 2 12503
Protoss_Observer 1 10796
12503
