Protoss_Nexus 2 12457
Protoss_Gateway 4 8833
Protoss_Assimilator 2 7710
Protoss_Zealot 2 6026
Protoss_Cybernetics_Core 1 6209
Protoss_Dragoon 9 11196
Protoss_Robotics_Facility 1 9863
Protoss_Observatory 1 10466
12457
