Protoss_Gateway 2 6261
Protoss_Assimilator 1 3377
Protoss_Zealot 3 5687
Protoss_Cybernetics_Core 1 5281
Protoss_Dragoon 10 11129
Protoss_Robotics_Facility 1 9100
Protoss_Observatory 1 9310
Protoss_Nexus 2 12607
Protoss_Observer 2 10941
12607
