Protoss_Gateway 2 4860
Protoss_Assimilator 1 3303
Protoss_Cybernetics_Core 1 4373
Protoss_Dragoon 15 11179
Protoss_Robotics_Facility 1 10095
Protoss_Nexus 1 11820
Protoss_Observatory 1 10259
11820
