Protoss_Gateway 2 7383
Protoss_Assimilator 1 3329
Protoss_Zealot 3 5189
Protoss_Cybernetics_Core 1 5363
Protoss_Dragoon 9 10361
Protoss_Nexus 2 12712
Protoss_Robotics_Facility 1 10583
12712
