Protoss_Gateway 3 11021
Protoss_Assimilator 2 3680
Protoss_Cybernetics_Core 1 4717
Protoss_Zealot 1 5147
Protoss_Dragoon 7 9939
Protoss_Nexus 1 10393
Protoss_Robotics_Facility 1 10133
Protoss_Shuttle 1 11151
Protoss_Robotics_Support_Bay 1 10623
11151
