Protoss_Gateway 4 10177
Protoss_Assimilator 1 3324
Protoss_Cybernetics_Core 1 4343
Protoss_Dragoon 12 11021
Protoss_Nexus 1 9119
Protoss_Robotics_Facility 1 9448
Protoss_Observatory 1 9628
Protoss_Observer 1 10623
11021
