Protoss_Gateway 1 3437
Protoss_Assimilator 1 3273
Protoss_Cybernetics_Core 1 4453
Protoss_Robotics_Facility 1 6105
Protoss_Dragoon 4 10476
Protoss_Shuttle 1 6921
Protoss_Robotics_Support_Bay 1 6436
Protoss_Reaver 2 9115
Protoss_Observatory 1 8922
Protoss_Observer 1 9746
Protoss_Nexus 1 11913
Protoss_Scarab 8 9973
11913
