Protoss_Gateway 2 8700
Protoss_Assimilator 1 3207
Protoss_Cybernetics_Core 1 4380
Protoss_Robotics_Facility 1 6092
Protoss_Dragoon 8 10577
Protoss_Observatory 1 6444
Protoss_Observer 2 7907
Protoss_Nexus 1 9519
Protoss_Shuttle 1 9145
Protoss_Robotics_Support_Bay 1 8891
Protoss_Reaver 1 10545
10577
