Protoss_Gateway 2 9199
Protoss_Assimilator 3 9544
Protoss_Cybernetics_Core 1 4643
Protoss_Dragoon 5 9117
Protoss_Nexus 1 9849
Protoss_Robotics_Facility 1 9415
Protoss_Citadel_of_Adun 1 10014
Protoss_Stargate 1 10871
Protoss_Observatory 1 10149
Protoss_Observer 1 10921
10921
