Protoss_Gateway 4 9846
Protoss_Assimilator 2 10070
Protoss_Cybernetics_Core 1 4313
Protoss_Dragoon 12 10606
Protoss_Nexus 1 9313
Protoss_Robotics_Facility 1 9413
Protoss_Observatory 1 9700
Protoss_Citadel_of_Adun 1 10655
Protoss_Observer 1 10696
10696
