Protoss_Gateway 2 10575
Protoss_Assimilator 1 3425
Protoss_Cybernetics_Core 1 5149
Protoss_Zealot 2 9461
Protoss_Dragoon 4 11061
Protoss_Robotics_Facility 1 7623
Protoss_Shuttle 1 8433
Protoss_Robotics_Support_Bay 1 8067
Protoss_Reaver 1 9575
Protoss_Nexus 2 12795
Protoss_Observatory 1 9528
Protoss_Observer 2 10899
12795
