Protoss_Gateway 3 10337
Protoss_Assimilator 2 10082
Protoss_Cybernetics_Core 1 4442
Protoss_Dragoon 7 11091
Protoss_Citadel_of_Adun 1 5718
Protoss_Templar_Archives 1 6743
Protoss_Dark_Templar 4 8498
Protoss_Nexus 1 10465
11091
