Protoss_Gateway 3 9100
Protoss_Assimilator 2 10072
Protoss_Cybernetics_Core 1 4509
Protoss_Dragoon 11 10973
Protoss_Nexus 1 8971
Protoss_Robotics_Facility 1 8927
Protoss_Observatory 1 9133
Protoss_Observer 2 10681
Protoss_Citadel_of_Adun 1 10523
10973
