Protoss_Gateway 2 6618
Protoss_Zealot 4 6011
Protoss_Assimilator 1 4324
Protoss_Cybernetics_Core 1 5913
Protoss_Dragoon 9 10583
Protoss_Nexus 1 11240
Protoss_Robotics_Facility 1 11488
11488
