Protoss_Gateway 2 7728
Protoss_Assimilator 1 3486
Protoss_Cybernetics_Core 1 4463
Protoss_Zealot 1 4273
Protoss_Dragoon 10 10915
Protoss_Robotics_Facility 1 7516
Protoss_Observatory 1 7911
Protoss_Observer 2 9283
Protoss_Robotics_Support_Bay 1 9387
Protoss_Shuttle 1 10365
Protoss_Reaver 1 11507
11507
