Protoss_Gateway 2 8875
Protoss_Assimilator 1 3291
Protoss_Zealot 3 5140
Protoss_Cybernetics_Core 1 6103
Protoss_Dragoon 4 10901
Protoss_Robotics_Facility 1 7947
Protoss_Citadel_of_Adun 1 7768
Protoss_Templar_Archives 1 8778
Protoss_Shuttle 1 8886
Protoss_Observatory 1 8981
Protoss_Dark_Templar 3 10408
Protoss_Observer 1 9896
Protoss_Forge 1 10581
10901
