Protoss_Gateway 4 9995
Protoss_Assimilator 2 10825
Protoss_Cybernetics_Core 1 4636
Protoss_Dragoon 8 10496
Protoss_Nexus 1 9320
Protoss_Robotics_Facility 1 9249
Protoss_Observatory 1 9486
Protoss_Shuttle 1 10361
Protoss_Robotics_Support_Bay 1 10414
Protoss_Zealot 1 10731
Protoss_Observer 1 10783
10825
