Protoss_Gateway 2 4830
Protoss_Assimilator 1 3141
Protoss_Cybernetics_Core 1 4259
Protoss_Dragoon 13 10955
Protoss_Robotics_Facility 1 7585
Protoss_Shuttle 1 8385
Protoss_Robotics_Support_Bay 1 8329
Protoss_Zealot 2 8973
Protoss_Reaver 1 9839
10955
