Protoss_Gateway 1 3325
Protoss_Assimilator 1 3327
Protoss_Cybernetics_Core 1 4329
Protoss_Zealot 3 9599
Protoss_Dragoon 4 7496
Protoss_Robotics_Facility 1 7791
Protoss_Nexus 2 12686
Protoss_Shuttle 1 9001
Protoss_Robotics_Support_Bay 1 8461
Protoss_Reaver 1 10304
Protoss_Observatory 1 9753
Protoss_Observer 1 10636
12686
