Protoss_Gateway 3 11419
Protoss_Assimilator 1 3169
Protoss_Cybernetics_Core 1 4351
Protoss_Dragoon 7 11141
Protoss_Nexus 2 11813
Protoss_Robotics_Facility 1 8228
Protoss_Robotics_Support_Bay 1 8365
Protoss_Shuttle 1 9545
Protoss_Zealot 2 9335
Protoss_Reaver 1 10795
Protoss_Observatory 1 10520
11813
