Protoss_Gateway 2 6362
Protoss_Assimilator 1 3321
Protoss_Cybernetics_Core 1 4441
Protoss_Dragoon 4 10597
Protoss_Citadel_of_Adun 1 5724
Protoss_Templar_Archives 1 6715
Protoss_Zealot 1 6561
Protoss_Dark_Templar 5 9133
Protoss_Nexus 1 11499
Protoss_Robotics_Facility 1 11156
11499
