Protoss_Gateway 2 9135
Protoss_Assimilator 1 3287
Protoss_Cybernetics_Core 1 4413
Protoss_Dragoon 8 11185
Protoss_Robotics_Facility 1 6311
Protoss_Shuttle 1 7107
Protoss_Robotics_Support_Bay 1 6519
Protoss_Zealot 2 7917
Protoss_Reaver 1 8466
Protoss_Observatory 1 7940
Protoss_Observer 2 9400
Protoss_Scarab 4 8785
Protoss_Nexus 1 12799
12799
