Protoss_Gateway 3 8785
Protoss_Assimilator 2 9697
Protoss_Cybernetics_Core 1 4305
Protoss_Dragoon 13 11021
Protoss_Nexus 1 8457
Protoss_Robotics_Facility 1 8149
Protoss_Observatory 1 8444
Protoss_Observer 2 9987
11021
