Protoss_Gateway 3 9534
Protoss_Nexus 1 6298
Protoss_Assimilator 2 7720
Protoss_Cybernetics_Core 1 5691
Protoss_Forge 1 5814
Protoss_Dragoon 4 11096
Protoss_Photon_Cannon 1 6988
Protoss_Citadel_of_Adun 1 7851
Protoss_Templar_Archives 1 8876
Protoss_Dark_Templar 3 10701
Protoss_Robotics_Facility 1 10732
Protoss_Stargate 1 10810
11096
