Protoss_Gateway 3 8905
Protoss_Assimilator 1 3174
Protoss_Cybernetics_Core 1 4515
Protoss_Zealot 4 10359
Protoss_Dragoon 9 9847
Protoss_Robotics_Facility 1 7810
Protoss_Observatory 1 8067
Protoss_Observer 2 10699
Protoss_Shuttle 1 10277
10699
