Protoss_Gateway 4 11173
Protoss_Assimilator 1 3420
Protoss_Cybernetics_Core 1 4497
Protoss_Dragoon 5 10478
Protoss_Citadel_of_Adun 2 6548
Protoss_Zealot 1 6796
Protoss_Templar_Archives 1 7538
Protoss_Dark_Templar 3 10483
Protoss_Nexus 1 10283
Protoss_Robotics_Facility 1 10911
11173
