Protoss_Gateway 3 11339
Protoss_Assimilator 1 3239
Protoss_Cybernetics_Core 1 4452
Protoss_Dragoon 9 10643
Protoss_Robotics_Facility 1 7506
Protoss_Observatory 1 7654
Protoss_Observer 3 10333
Protoss_Nexus 2 11964
11964
