Protoss_Gateway 3 10015
Protoss_Assimilator 1 3111
Protoss_Cybernetics_Core 1 4219
Protoss_Zealot 1 4031
Protoss_Dragoon 11 10753
Protoss_Nexus 1 9041
Protoss_Robotics_Facility 1 9068
Protoss_Observatory 1 9169
Protoss_Observer 2 10545
10753
