Protoss_Zealot 23 10851
Protoss_Gateway 2 8993
Protoss_Assimilator 1 3428
Protoss_Cybernetics_Core 1 4563
Protoss_Dragoon 6 9786
Protoss_Robotics_Facility 1 7923
Protoss_Observatory 1 8642
Protoss_Observer 1 9586
10851
