Protoss_Gateway 3 10190
Protoss_Zealot 15 8940
Protoss_Forge 1 5914
Protoss_Photon_Cannon 2 10514
Protoss_Assimilator 1 8938
Protoss_Cybernetics_Core 1 9649
Protoss_Citadel_of_Adun 1 10663
Protoss_Dragoon 1 10835
10835
