Protoss_Gateway 2 6215
Protoss_Assimilator 1 3633
Protoss_Cybernetics_Core 1 4713
Protoss_Dragoon 12 10856
Protoss_Citadel_of_Adun 1 7442
Protoss_Templar_Archives 1 8467
Protoss_Nexus 1 11002
Protoss_Robotics_Facility 1 10951
11002
