Protoss_Gateway 2 7134
Protoss_Assimilator 1 3578
Protoss_Cybernetics_Core 1 4729
Protoss_Dragoon 9 10071
Protoss_Robotics_Facility 1 8248
Protoss_Observatory 1 8432
Protoss_Observer 2 9853
Protoss_Shuttle 1 10935
10935
