Protoss_Gateway 7 11438
Protoss_Assimilator 1 3286
Protoss_Cybernetics_Core 1 4401
Protoss_Dragoon 6 9799
Protoss_Robotics_Facility 1 7243
Protoss_Nexus 1 9327
Protoss_Shuttle 1 8155
Protoss_Robotics_Support_Bay 1 8366
Protoss_Reaver 2 10913
Protoss_Shield_Battery 1 10479
11438
