Protoss_Gateway 4 10505
Protoss_Assimilator 1 3273
Protoss_Cybernetics_Core 1 4282
Protoss_Dragoon 10 10587
Protoss_Nexus 2 12864
Protoss_Robotics_Facility 1 8822
Protoss_Observatory 1 8907
Protoss_Observer 2 10283
12864
