Protoss_Gateway 2 8833
Protoss_Assimilator 1 3372
Protoss_Cybernetics_Core 1 4387
Protoss_Dragoon 8 9939
Protoss_Nexus 1 8951
Protoss_Robotics_Facility 1 8773
Protoss_Shuttle 1 9781
Protoss_Robotics_Support_Bay 1 9663
Protoss_Observatory 1 10172
Protoss_Zealot 2 10759
Protoss_Reaver 1 11487
11487
