Protoss_Gateway 1 3373
Protoss_Zealot 3 5111
Protoss_Assimilator 1 4038
Protoss_Cybernetics_Core 1 5233
Protoss_Dragoon 6 11126
Protoss_Robotics_Facility 1 7073
Protoss_Shuttle 1 7956
Protoss_Robotics_Support_Bay 1 7438
Protoss_Reaver 3 11255
Protoss_Nexus 1 12175
Protoss_Observatory 1 10239
12175
