Protoss_Gateway 3 11369
Protoss_Assimilator 1 3267
Protoss_Cybernetics_Core 1 4395
Protoss_Dragoon 6 10765
Protoss_Robotics_Facility 1 6279
Protoss_Shuttle 2 11301
Protoss_Zealot 2 7851
Protoss_Observatory 1 6946
Protoss_Observer 1 7721
Protoss_Robotics_Support_Bay 1 7581
Protoss_Reaver 1 9173
Protoss_Nexus 1 11388
11388
