Protoss_Gateway 2 9773
Protoss_Assimilator 1 3282
Protoss_Cybernetics_Core 1 4529
Protoss_Dragoon 9 11009
Protoss_Nexus 1 9354
Protoss_Robotics_Facility 1 10081
Protoss_Observatory 1 10202
11009
