Protoss_Gateway 3 11400
Protoss_Assimilator 1 3267
Protoss_Cybernetics_Core 1 4574
Protoss_Dragoon 6 8927
Protoss_Nexus 2 11985
Protoss_Robotics_Facility 1 9138
Protoss_Shuttle 1 9963
Protoss_Observatory 1 9291
Protoss_Robotics_Support_Bay 1 9512
Protoss_Reaver 1 11105
Protoss_Zealot 2 10713
11985
