Protoss_Gateway 2 7606
Protoss_Assimilator 1 3395
Protoss_Cybernetics_Core 1 4561
Protoss_Dragoon 7 9737
Protoss_Robotics_Facility 1 7458
Protoss_Observatory 1 7805
Protoss_Observer 1 8625
Protoss_Nexus 1 11373
Protoss_Shuttle 1 10163
Protoss_Robotics_Support_Bay 1 9988
Protoss_Reaver 1 11483
Protoss_Zealot 1 10849
11483
