Protoss_Gateway 3 10796
Protoss_Assimilator 1 3382
Protoss_Cybernetics_Core 1 4656
Protoss_Dragoon 10 10790
Protoss_Citadel_of_Adun 1 7234
Protoss_Templar_Archives 1 8276
Protoss_Dark_Templar 2 9286
Protoss_Nexus 1 12073
12073
