Protoss_Gateway 2 4430
Protoss_Zealot 11 10760
Protoss_Assimilator 1 5479
Protoss_Cybernetics_Core 1 7426
Protoss_Dragoon 6 10323
Protoss_Robotics_Facility 1 9712
Protoss_Shuttle 1 10711
10760
