Protoss_Gateway 3 11238
Protoss_Assimilator 1 3321
Protoss_Cybernetics_Core 1 4449
Protoss_Dragoon 10 11007
Protoss_Nexus 2 11580
Protoss_Robotics_Facility 1 9879
Protoss_Observatory 1 10319
Protoss_Citadel_of_Adun 1 11053
11580
