Protoss_Gateway 2 6972
Protoss_Assimilator 1 3267
Protoss_Zealot 2 5007
Protoss_Cybernetics_Core 1 5329
Protoss_Dragoon 12 11129
Protoss_Robotics_Facility 1 10224
Protoss_Nexus 1 11529
Protoss_Observatory 1 10665
11529
