Protoss_Gateway 2 11395
Protoss_Assimilator 1 3327
Protoss_Cybernetics_Core 1 4455
Protoss_Dragoon 6 11013
Protoss_Robotics_Facility 1 6610
Protoss_Shuttle 1 7417
Protoss_Robotics_Support_Bay 1 6833
Protoss_Nexus 1 9715
Protoss_Reaver 2 10573
Protoss_Observatory 1 8062
Protoss_Observer 2 10905
11395
