Protoss_Gateway 2 5953
Protoss_Assimilator 1 3300
Protoss_Cybernetics_Core 1 4495
Protoss_Dragoon 6 7781
Protoss_Citadel_of_Adun 1 7505
Protoss_Templar_Archives 1 8533
Protoss_Zealot 2 8471
Protoss_Dark_Templar 4 10711
Protoss_Nexus 1 11603
11603
