Protoss_Gateway 4 10829
Protoss_Assimilator 1 3347
Protoss_Cybernetics_Core 1 4465
Protoss_Dragoon 6 11113
Protoss_Robotics_Facility 1 7468
Protoss_Shuttle 1 8359
Protoss_Robotics_Support_Bay 1 7791
Protoss_Zealot 1 8291
Protoss_Reaver 1 9501
Protoss_Nexus 1 11083
Protoss_Observatory 1 9099
Protoss_Observer 2 10499
11113
