Protoss_Gateway 3 8593
Protoss_Assimilator 1 3449
Protoss_Cybernetics_Core 1 4454
Protoss_Dragoon 14 11010
Protoss_Robotics_Facility 1 7453
Protoss_Observatory 1 7563
Protoss_Observer 3 9701
11010
