Protoss_Gateway 3 11037
Protoss_Assimilator 2 9957
Protoss_Cybernetics_Core 1 4581
Protoss_Dragoon 6 11017
Protoss_Citadel_of_Adun 1 6843
Protoss_Robotics_Facility 1 8015
Protoss_Templar_Archives 1 7843
Protoss_Nexus 1 9833
Protoss_Dark_Templar 2 8591
Protoss_Shuttle 1 8967
Protoss_Observatory 1 8791
Protoss_Observer 1 10525
11037
