Protoss_Gateway 2 3755
Protoss_Zealot 2 4333
Protoss_Assimilator 1 4664
Protoss_Cybernetics_Core 1 5621
Protoss_Dragoon 10 10809
Protoss_Nexus 1 9972
Protoss_Robotics_Facility 1 10908
10908
