Protoss_Gateway 4 10051
Protoss_Assimilator 1 3541
Protoss_Cybernetics_Core 1 4763
Protoss_Robotics_Facility 1 6321
Protoss_Dragoon 9 10187
Protoss_Observatory 1 6442
Protoss_Observer 1 7281
Protoss_Shuttle 1 8471
10187
