Protoss_Gateway 4 11235
Protoss_Assimilator 1 3165
Protoss_Cybernetics_Core 1 4273
Protoss_Dragoon 7 8593
Protoss_Nexus 1 9543
Protoss_Robotics_Facility 1 9159
Protoss_Citadel_of_Adun 1 9389
Protoss_Zealot 4 10211
Protoss_Shuttle 1 10253
Protoss_Templar_Archives 2 10611
Protoss_Observatory 1 10107
Protoss_Observer 1 10887
11235
