Protoss_Gateway 3 11036
Protoss_Assimilator 1 3381
Protoss_Cybernetics_Core 1 4383
Protoss_Dragoon 7 11087
Protoss_Zealot 2 6955
Protoss_Citadel_of_Adun 1 6647
Protoss_Templar_Archives 1 7681
Protoss_Dark_Templar 4 9577
Protoss_Nexus 1 10893
11087
