Protoss_Nexus 2 11555
Protoss_Gateway 2 6212
Protoss_Assimilator 2 8183
Protoss_Cybernetics_Core 1 5521
Protoss_Dragoon 3 7493
Protoss_Citadel_of_Adun 2 7390
Protoss_Zealot 2 8005
Protoss_Templar_Archives 1 8553
Protoss_Dark_Templar 5 10811
Protoss_Robotics_Facility 1 11034
11555
