Protoss_Gateway 4 11417
Protoss_Assimilator 1 3179
Protoss_Cybernetics_Core 1 4373
Protoss_Dragoon 5 11131
Protoss_Robotics_Facility 1 7187
Protoss_Shuttle 1 8251
Protoss_Robotics_Support_Bay 1 7610
Protoss_Zealot 2 8673
Protoss_Reaver 1 9543
Protoss_Nexus 1 11609
Protoss_Observatory 1 9659
Protoss_Observer 1 10935
11609
