Protoss_Gateway 3 11427
Protoss_Assimilator 1 3177
Protoss_Cybernetics_Core 1 4271
Protoss_Dragoon 6 9401
Protoss_Nexus 1 9515
Protoss_Robotics_Facility 1 8931
Protoss_Shuttle 1 10051
Protoss_Robotics_Support_Bay 1 9744
Protoss_Zealot 2 10483
Protoss_Reaver 1 11263
11427
