Protoss_Nexus 1 5642
Protoss_Gateway 4 10809
Protoss_Assimilator 2 7388
Protoss_Cybernetics_Core 1 5471
Protoss_Zealot 1 5601
Protoss_Dragoon 4 7751
Protoss_Citadel_of_Adun 1 7355
Protoss_Templar_Archives 1 8365
Protoss_Stargate 1 9494
Protoss_Dark_Templar 4 10095
Protoss_Arbiter_Tribunal 1 10509
10809
