Protoss_Gateway 2 8491
Protoss_Assimilator 1 3405
Protoss_Cybernetics_Core 1 4465
Protoss_Dragoon 10 10967
Protoss_Robotics_Facility 1 7556
Protoss_Observatory 1 7647
Protoss_Observer 3 10339
Protoss_Shuttle 1 9917
Protoss_Robotics_Support_Bay 1 10204
10967
