Protoss_Gateway 2 7655
Protoss_Assimilator 2 4430
Protoss_Zealot 2 4567
Protoss_Cybernetics_Core 1 5670
Protoss_Dragoon 7 11033
Protoss_Nexus 2 12387
Protoss_Citadel_of_Adun 1 8489
Protoss_Templar_Archives 1 9487
Protoss_Robotics_Facility 1 10691
Protoss_Dark_Templar 2 10237
12387
