Protoss_Gateway 3 10777
Protoss_Assimilator 1 3376
Protoss_Zealot 3 5187
Protoss_Cybernetics_Core 1 5285
Protoss_Dragoon 9 10701
Protoss_Nexus 2 10545
Protoss_Robotics_Facility 1 10277
Protoss_Observatory 1 10631
10777
