Protoss_Gateway 3 11093
Protoss_Assimilator 1 3287
Protoss_Cybernetics_Core 1 4310
Protoss_Dragoon 12 10531
Protoss_Nexus 1 11307
Protoss_Citadel_of_Adun 1 10600
Protoss_Robotics_Facility 1 11385
11385
