Protoss_Gateway 3 9096
Protoss_Assimilator 1 3250
Protoss_Cybernetics_Core 1 4400
Protoss_Dragoon 13 11199
Protoss_Nexus 1 9349
Protoss_Shield_Battery 1 9812
Protoss_Robotics_Facility 1 11405
11405
