Protoss_Gateway 4 11421
Protoss_Assimilator 1 3503
Protoss_Zealot 1 3923
Protoss_Cybernetics_Core 1 5155
Protoss_Dragoon 9 11085
Protoss_Nexus 2 12075
Protoss_Robotics_Facility 1 8867
Protoss_Observatory 1 9141
Protoss_Observer 2 10777
12075
