Protoss_Gateway 3 9805
Protoss_Assimilator 1 3375
Protoss_Cybernetics_Core 1 4563
Protoss_Dragoon 7 9951
Protoss_Nexus 2 12144
Protoss_Robotics_Facility 1 8208
Protoss_Observatory 1 8428
Protoss_Observer 2 10397
Protoss_Zealot 2 10551
12144
