Protoss_Gateway 3 10264
Protoss_Assimilator 1 3303
Protoss_Cybernetics_Core 1 4442
Protoss_Dragoon 8 9783
Protoss_Robotics_Facility 1 7399
Protoss_Observatory 1 7493
Protoss_Nexus 1 10100
Protoss_Observer 2 8923
Protoss_Citadel_of_Adun 1 9566
Protoss_Zealot 3 10953
10953
