Protoss_Gateway 2 4875
Protoss_Assimilator 2 10556
Protoss_Cybernetics_Core 1 5489
Protoss_Zealot 1 5151
Protoss_Dragoon 6 9391
Protoss_Nexus 1 10427
Protoss_Citadel_of_Adun 1 9366
Protoss_Templar_Archives 1 10449
Protoss_Dark_Templar 2 11197
11197
