Protoss_Gateway 3 11285
Protoss_Assimilator 1 3182
Protoss_Cybernetics_Core 1 4297
Protoss_Dragoon 9 10413
Protoss_Nexus 2 10539
Protoss_Robotics_Facility 1 9993
Protoss_Observatory 1 10204
11285
