Protoss_Nexus 1 5533
Protoss_Gateway 4 9481
Protoss_Assimilator 2 8146
Protoss_Cybernetics_Core 1 5530
Protoss_Zealot 2 9251
Protoss_Dragoon 9 10665
Protoss_Robotics_Facility 1 8828
Protoss_Observatory 1 8926
Protoss_Shuttle 1 9661
Protoss_Robotics_Support_Bay 1 9802
Protoss_Observer 1 10083
Protoss_Stargate 1 11134
Protoss_Reaver 1 11405
11405
