Protoss_Gateway 2 7040
Protoss_Assimilator 1 3259
Protoss_Cybernetics_Core 1 4447
Protoss_Dragoon 11 10651
Protoss_Robotics_Facility 1 9019
Protoss_Robotics_Support_Bay 1 9268
Protoss_Reaver 1 10956
10956
