Protoss_Gateway 2 3693
Protoss_Zealot 11 8909
Protoss_Assimilator 1 5692
Protoss_Forge 1 5740
Protoss_Cybernetics_Core 1 7312
Protoss_Photon_Cannon 4 8719
Protoss_Dragoon 4 10787
Protoss_Robotics_Facility 1 10955
Protoss_Nexus 1 12208
12208
