Protoss_Nexus 1 6240
Protoss_Assimilator 1 4624
Protoss_Gateway 6 11060
Protoss_Cybernetics_Core 2 10581
Protoss_Zealot 3 8311
Protoss_Dragoon 4 9153
Protoss_Citadel_of_Adun 1 7958
Protoss_Templar_Archives 1 9149
Protoss_Shield_Battery 1 8766
Protoss_Dark_Templar 4 10888
11060
