Protoss_Gateway 2 5003
Protoss_Assimilator 1 3301
Protoss_Cybernetics_Core 1 4427
Protoss_Dragoon 8 9697
Protoss_Nexus 1 10405
Protoss_Citadel_of_Adun 1 9253
Protoss_Robotics_Facility 1 10122
Protoss_Templar_Archives 1 10314
Protoss_Shuttle 1 11043
Protoss_Dark_Templar 1 11087
11087
