Protoss_Gateway 5 11274
Protoss_Assimilator 2 9404
Protoss_Cybernetics_Core 1 4504
Protoss_Dragoon 9 10146
Protoss_Nexus 1 10498
Protoss_Robotics_Facility 1 10040
Protoss_Observatory 1 10171
Protoss_Citadel_of_Adun 1 11120
Protoss_Observer 1 10951
11274
