Protoss_Gateway 4 10678
Protoss_Assimilator 1 3193
Protoss_Cybernetics_Core 1 4293
Protoss_Dragoon 8 9095
Protoss_Robotics_Facility 1 7280
Protoss_Observatory 1 7441
Protoss_Observer 1 8313
Protoss_Citadel_of_Adun 1 9590
Protoss_Nexus 1 11455
Protoss_Templar_Archives 1 10612
Protoss_Shuttle 1 10927
11455
