Protoss_Gateway 2 4829
Protoss_Assimilator 2 10025
Protoss_Cybernetics_Core 1 4348
Protoss_Dragoon 6 8653
Protoss_Nexus 1 9128
Protoss_Citadel_of_Adun 1 7969
Protoss_Robotics_Facility 1 8939
Protoss_Templar_Archives 1 9167
Protoss_Shuttle 1 9883
Protoss_Dark_Templar 4 10737
Protoss_Observatory 1 10614
10737
