Protoss_Gateway 2 4735
Protoss_Assimilator 3 8748
Protoss_Zealot 7 7607
Protoss_Nexus 1 8127
Protoss_Cybernetics_Core 1 7677
Protoss_Dragoon 6 10573
Protoss_Robotics_Facility 1 10909
10909
