Protoss_Gateway 3 11038
Protoss_Nexus 1 6867
Protoss_Zealot 2 5577
Protoss_Assimilator 2 7084
Protoss_Cybernetics_Core 1 6710
Protoss_Dragoon 9 10567
Protoss_Robotics_Facility 1 9791
Protoss_Observatory 1 9941
11038
