Protoss_Nexus 2 10765
Protoss_Gateway 4 10411
Protoss_Assimilator 1 4233
Protoss_Cybernetics_Core 1 5533
Protoss_Zealot 1 5497
Protoss_Dragoon 11 11165
Protoss_Robotics_Facility 1 10198
Protoss_Observatory 1 10323
11165
