Protoss_Assimilator 2 5296
Protoss_Gateway 2 7386
Protoss_Zealot 2 5609
Protoss_Nexus 1 7044
Protoss_Cybernetics_Core 1 6572
Protoss_Dragoon 6 9861
Protoss_Shield_Battery 1 7777
Protoss_Robotics_Facility 1 9764
Protoss_Shuttle 1 10595
Protoss_Robotics_Support_Bay 1 10188
10595
