Protoss_Gateway 1 3301
Protoss_Assimilator 1 3214
Protoss_Cybernetics_Core 1 4432
Protoss_Dragoon 6 9647
Protoss_Robotics_Facility 1 7463
Protoss_Observatory 1 7578
Protoss_Nexus 2 12217
Protoss_Observer 3 9665
Protoss_Forge 2 10420
Protoss_Citadel_of_Adun 1 11274
12217
