Protoss_Gateway 1 3436
Protoss_Assimilator 1 3419
Protoss_Zealot 2 8165
Protoss_Cybernetics_Core 1 5392
Protoss_Dragoon 5 10743
Protoss_Robotics_Facility 1 7759
Protoss_Robotics_Support_Bay 1 7849
Protoss_Shuttle 1 8819
Protoss_Reaver 2 11013
11013
