Protoss_Gateway 2 7601
Protoss_Assimilator 1 3148
Protoss_Cybernetics_Core 1 4436
Protoss_Dragoon 8 10623
Protoss_Robotics_Facility 1 6828
Protoss_Shuttle 1 7857
Protoss_Observatory 1 7381
Protoss_Robotics_Support_Bay 1 7939
Protoss_Observer 1 8279
Protoss_Reaver 1 9601
Protoss_Nexus 1 11557
11557
