Protoss_Gateway 2 6217
Protoss_Nexus 2 11733
Protoss_Assimilator 2 7796
Protoss_Cybernetics_Core 1 5679
Protoss_Zealot 1 6027
Protoss_Dragoon 9 10489
Protoss_Robotics_Facility 1 8921
Protoss_Observatory 1 9037
Protoss_Observer 2 10511
11733
