Protoss_Assimilator 2 9167
Protoss_Gateway 2 8723
Protoss_Cybernetics_Core 1 4731
Protoss_Dragoon 5 8971
Protoss_Nexus 2 12753
Protoss_Citadel_of_Adun 1 7760
Protoss_Robotics_Facility 1 8960
Protoss_Templar_Archives 1 8959
Protoss_Shuttle 1 9879
Protoss_High_Templar 4 11177
12753
