Protoss_Assimilator 3 7085
Protoss_Gateway 4 10053
Protoss_Zealot 6 10369
Protoss_Nexus 2 12537
Protoss_Cybernetics_Core 1 7039
Protoss_Dragoon 4 10669
Protoss_Citadel_of_Adun 1 8820
Protoss_Templar_Archives 1 10518
12537
