Protoss_Gateway 3 7713
Protoss_Zealot 4 4936
Protoss_Assimilator 2 9597
Protoss_Cybernetics_Core 1 6291
Protoss_Nexus 1 8218
Protoss_Dragoon 12 10803
Protoss_Shield_Battery 1 9182
10803
