Protoss_Gateway 4 10546
Protoss_Assimilator 1 3191
Protoss_Cybernetics_Core 1 4335
Protoss_Dragoon 8 10931
Protoss_Nexus 2 9450
Protoss_Robotics_Facility 1 8847
Protoss_Observatory 1 8957
Protoss_Observer 1 10045
10931
