Protoss_Gateway 3 10143
Protoss_Assimilator 1 3312
Protoss_Zealot 1 3773
Protoss_Cybernetics_Core 1 4709
Protoss_Dragoon 8 10929
Protoss_Robotics_Facility 1 7487
Protoss_Nexus 1 9695
Protoss_Shuttle 1 8809
Protoss_Robotics_Support_Bay 1 8415
Protoss_Reaver 1 9951
Protoss_Observatory 1 9484
Protoss_Observer 1 10489
10929
