Protoss_Gateway 5 10669
Protoss_Assimilator 1 3280
Protoss_Cybernetics_Core 1 4285
Protoss_Dragoon 8 10737
Protoss_Nexus 2 11447
Protoss_Robotics_Facility 1 9070
Protoss_Observatory 1 9190
Protoss_Zealot 3 10509
Protoss_Observer 2 10565
Protoss_Citadel_of_Adun 1 11221
11447
