Protoss_Gateway 2 7094
Protoss_Assimilator 1 3201
Protoss_Cybernetics_Core 1 4308
Protoss_Zealot 1 4143
Protoss_Dragoon 4 10907
Protoss_Citadel_of_Adun 1 5867
Protoss_Robotics_Facility 1 6979
Protoss_Templar_Archives 1 7462
Protoss_Shuttle 1 8153
Protoss_Dark_Templar 3 9005
Protoss_Observatory 1 8223
Protoss_Nexus 2 12267
Protoss_Observer 2 10917
12267
