Protoss_Nexus 1 5687
Protoss_Gateway 2 5292
Protoss_Assimilator 2 8958
Protoss_Cybernetics_Core 1 5829
Protoss_Zealot 1 5679
Protoss_Dragoon 10 10541
Protoss_Robotics_Facility 1 9247
Protoss_Observatory 1 9483
Protoss_Observer 1 10313
Protoss_Stargate 1 11357
11357
