Protoss_Gateway 2 6817
Protoss_Assimilator 1 3228
Protoss_Cybernetics_Core 1 4370
Protoss_Dragoon 8 10625
Protoss_Robotics_Facility 1 6829
Protoss_Observatory 1 6938
Protoss_Observer 2 8593
Protoss_Nexus 2 12818
Protoss_Shuttle 1 10037
Protoss_Robotics_Support_Bay 1 9888
12818
