Protoss_Gateway 2 7579
Protoss_Assimilator 1 3325
Protoss_Zealot 4 10729
Protoss_Cybernetics_Core 1 5310
Protoss_Dragoon 6 9969
Protoss_Robotics_Facility 1 6931
Protoss_Observatory 1 7084
Protoss_Observer 3 9075
Protoss_Nexus 1 10772
Protoss_Shuttle 1 10577
Protoss_Robotics_Support_Bay 1 9965
10772
