Protoss_Gateway 2 7931
Protoss_Assimilator 1 3348
Protoss_Cybernetics_Core 1 4455
Protoss_Dragoon 9 10139
Protoss_Robotics_Facility 1 7666
Protoss_Shuttle 1 8533
Protoss_Observatory 1 8173
Protoss_Observer 2 10777
Protoss_Robotics_Support_Bay 1 8819
Protoss_Reaver 1 10445
Protoss_Nexus 1 12567
12567
