Protoss_Gateway 3 11369
Protoss_Assimilator 1 3285
Protoss_Cybernetics_Core 1 4444
Protoss_Zealot 1 4199
Protoss_Citadel_of_Adun 1 5742
Protoss_Dragoon 6 10857
Protoss_Templar_Archives 1 6729
Protoss_Dark_Templar 2 8219
Protoss_Nexus 1 9695
Protoss_Robotics_Facility 1 9460
Protoss_Shuttle 1 10569
Protoss_Observatory 1 10345
11369
