Protoss_Assimilator 3 9997
Protoss_Gateway 2 6676
Protoss_Zealot 2 5121
Protoss_Cybernetics_Core 1 6008
Protoss_Nexus 2 11375
Protoss_Dragoon 7 10077
Protoss_Robotics_Facility 1 10889
11375
