Protoss_Gateway 4 11315
Protoss_Assimilator 2 9764
Protoss_Cybernetics_Core 1 4497
Protoss_Dragoon 6 10905
Protoss_Nexus 2 12014
Protoss_Citadel_of_Adun 1 7795
Protoss_Zealot 2 8437
Protoss_Templar_Archives 1 9041
Protoss_Dark_Templar 2 10153
12014
