Protoss_Nexus 2 11215
Protoss_Gateway 2 6118
Protoss_Assimilator 1 4552
Protoss_Cybernetics_Core 1 5647
Protoss_Dragoon 9 10631
Protoss_Zealot 2 9517
Protoss_Robotics_Facility 1 10843
11215
