Protoss_Gateway 3 10956
Protoss_Assimilator 1 3118
Protoss_Cybernetics_Core 1 4254
Protoss_Dragoon 9 11117
Protoss_Nexus 1 9414
Protoss_Robotics_Facility 1 8836
Protoss_Shuttle 1 9645
Protoss_Robotics_Support_Bay 1 9307
Protoss_Reaver 1 10923
Protoss_Observatory 1 10437
11117
