Protoss_Nexus 2 10731
Protoss_Gateway 2 5797
Protoss_Assimilator 2 10282
Protoss_Cybernetics_Core 1 5585
Protoss_Zealot 1 5595
Protoss_Dragoon 10 10285
Protoss_Robotics_Facility 1 9913
Protoss_Shuttle 1 10723
Protoss_Robotics_Support_Bay 1 10227
Protoss_Observatory 1 10685
10731
