Protoss_Gateway 2 10570
Protoss_Assimilator 1 3366
Protoss_Cybernetics_Core 1 4498
Protoss_Dragoon 7 10935
Protoss_Robotics_Facility 1 7303
Protoss_Zealot 2 7769
Protoss_Shuttle 1 8105
Protoss_Robotics_Support_Bay 1 7421
Protoss_Reaver 1 9247
Protoss_Nexus 1 10955
Protoss_Observatory 1 9126
Protoss_Observer 1 10633
10955
