Protoss_Gateway 2 9453
Protoss_Assimilator 2 9514
Protoss_Cybernetics_Core 1 4743
Protoss_Dragoon 7 10947
Protoss_Nexus 2 12579
Protoss_Citadel_of_Adun 1 7791
Protoss_Templar_Archives 1 8829
Protoss_Stargate 1 10032
Protoss_Dark_Templar 1 9575
12579
