Protoss_Forge 1 3334
Protoss_Photon_Cannon 6 9208
Protoss_Gateway 2 10790
Protoss_Assimilator 2 10190
Protoss_Cybernetics_Core 1 7354
Protoss_Nexus 1 9435
Protoss_Zealot 1 7601
Protoss_Citadel_of_Adun 1 8778
Protoss_Dragoon 2 9356
Protoss_Templar_Archives 1 10073
10790
