Protoss_Gateway 2 3853
Protoss_Zealot 14 9929
Protoss_Forge 1 4461
Protoss_Photon_Cannon 4 8765
Protoss_Assimilator 1 8919
Protoss_Cybernetics_Core 1 9974
Protoss_Dragoon 2 10881
10881
