Protoss_Gateway 2 7439
Protoss_Assimilator 1 3379
Protoss_Cybernetics_Core 1 4408
Protoss_Zealot 1 4163
Protoss_Dragoon 10 10927
Protoss_Robotics_Facility 1 7433
Protoss_Observatory 1 7589
Protoss_Observer 2 9211
Protoss_Nexus 1 11999
Protoss_Shuttle 1 10711
Protoss_Robotics_Support_Bay 1 10697
11999
