Protoss_Gateway 2 11075
Protoss_Assimilator 1 3571
Protoss_Zealot 2 8293
Protoss_Cybernetics_Core 1 5465
Protoss_Dragoon 6 10917
Protoss_Robotics_Facility 1 7414
Protoss_Shuttle 1 8245
Protoss_Robotics_Support_Bay 1 7627
Protoss_Reaver 2 11517
Protoss_Observatory 1 9352
Protoss_Nexus 1 12001
Protoss_Observer 1 10127
Protoss_Scarab 1 9640
12001
