Protoss_Gateway 2 6309
Protoss_Assimilator 1 3185
Protoss_Cybernetics_Core 1 4350
Protoss_Dragoon 8 10715
Protoss_Robotics_Facility 1 6268
Protoss_Observatory 1 6984
Protoss_Observer 2 10805
Protoss_Shuttle 1 8873
Protoss_Robotics_Support_Bay 1 8819
Protoss_Zealot 2 9429
Protoss_Reaver 1 10473
Protoss_Nexus 1 12001
Protoss_Citadel_of_Adun 1 11186
12001
