Protoss_Gateway 2 8032
Protoss_Assimilator 1 3318
Protoss_Cybernetics_Core 1 4458
Protoss_Dragoon 9 9915
Protoss_Robotics_Facility 1 7735
Protoss_Shuttle 1 8539
Protoss_Observatory 1 8237
Protoss_Observer 1 9013
Protoss_Robotics_Support_Bay 1 9233
Protoss_Reaver 1 10725
Protoss_Zealot 1 10479
Protoss_Nexus 1 12856
12856
