Protoss_Gateway 2 9757
Protoss_Assimilator 1 3327
Protoss_Cybernetics_Core 1 4448
Protoss_Dragoon 8 10679
Protoss_Robotics_Facility 1 7324
Protoss_Observatory 1 7425
Protoss_Nexus 1 10020
Protoss_Observer 1 8209
Protoss_Robotics_Support_Bay 1 8228
Protoss_Shuttle 1 10429
Protoss_Reaver 1 11579
11579
