Protoss_Gateway 2 11163
Protoss_Assimilator 1 3288
Protoss_Cybernetics_Core 1 4531
Protoss_Dragoon 8 11021
Protoss_Robotics_Facility 1 6434
Protoss_Shuttle 1 7243
Protoss_Robotics_Support_Bay 1 6663
Protoss_Reaver 1 8547
Protoss_Observatory 1 8047
Protoss_Observer 2 9481
Protoss_Nexus 1 12099
12099
