Protoss_Gateway 1 3445
Protoss_Assimilator 1 3455
Protoss_Cybernetics_Core 1 4528
Protoss_Dragoon 8 11073
Protoss_Robotics_Facility 1 8287
Protoss_Shuttle 1 9216
Protoss_Robotics_Support_Bay 1 8568
Protoss_Reaver 1 10396
Protoss_Observatory 1 10530
11073
