Protoss_Gateway 2 7405
Protoss_Assimilator 1 3395
Protoss_Cybernetics_Core 1 4524
Protoss_Dragoon 12 11017
Protoss_Robotics_Facility 1 7388
Protoss_Shuttle 1 8251
Protoss_Observatory 1 7664
Protoss_Observer 2 10483
Protoss_Nexus 1 12038
Protoss_Forge 1 10492
12038
