Protoss_Gateway 4 10849
Protoss_Assimilator 1 3382
Protoss_Cybernetics_Core 1 4447
Protoss_Dragoon 9 10101
Protoss_Robotics_Facility 1 7532
Protoss_Observatory 1 7686
Protoss_Nexus 1 10052
Protoss_Observer 3 10601
Protoss_Shuttle 1 11249
11249
