Protoss_Gateway 4 11124
Protoss_Assimilator 1 3284
Protoss_Cybernetics_Core 1 4368
Protoss_Dragoon 5 10715
Protoss_Robotics_Facility 1 7252
Protoss_Observatory 1 7339
Protoss_Nexus 1 9830
Protoss_Observer 2 10669
Protoss_Robotics_Support_Bay 1 7991
Protoss_Shuttle 1 9193
Protoss_Zealot 2 9829
Protoss_Reaver 1 10335
11124
