Protoss_Gateway 2 6960
Protoss_Assimilator 1 3504
Protoss_Cybernetics_Core 1 4603
Protoss_Dragoon 8 9220
Protoss_Robotics_Facility 1 8275
Protoss_Observatory 1 9180
Protoss_Nexus 1 12073
Protoss_Zealot 4 10803
Protoss_Observer 1 10226
Protoss_Shuttle 1 11308
12073
