Protoss_Gateway 2 7456
Protoss_Assimilator 1 3352
Protoss_Cybernetics_Core 1 4451
Protoss_Dragoon 11 11033
Protoss_Robotics_Facility 1 7640
Protoss_Shuttle 1 8441
Protoss_Robotics_Support_Bay 1 8313
Protoss_Reaver 2 11101
Protoss_Scarab 1 9473
11101
