Protoss_Gateway 2 6223
Protoss_Assimilator 2 10551
Protoss_Cybernetics_Core 1 4456
Protoss_Citadel_of_Adun 1 5475
Protoss_Dragoon 6 10971
Protoss_Templar_Archives 1 6580
Protoss_Dark_Templar 4 8349
Protoss_Nexus 1 10435
Protoss_Stargate 1 10071
10971
