Protoss_Gateway 2 4035
Protoss_Zealot 5 5261
Protoss_Assimilator 2 10906
Protoss_Cybernetics_Core 1 6095
Protoss_Dragoon 8 10955
Protoss_Robotics_Facility 1 8701
Protoss_Nexus 1 10479
Protoss_Observatory 1 8824
Protoss_Observer 2 10261
10955
