Protoss_Gateway 3 10620
Protoss_Assimilator 1 3536
Protoss_Cybernetics_Core 1 4885
Protoss_Dragoon 9 10826
Protoss_Robotics_Facility 1 8561
Protoss_Observatory 1 8814
Protoss_Nexus 1 11414
Protoss_Observer 2 10723
Protoss_Forge 1 10761
11414
