Protoss_Gateway 3 9520
Protoss_Assimilator 1 3363
Protoss_Cybernetics_Core 1 4500
Protoss_Dragoon 12 11071
Protoss_Nexus 1 8893
Protoss_Robotics_Facility 1 8879
Protoss_Observatory 1 9591
Protoss_Observer 1 10365
11071
