Protoss_Gateway 3 9702
Protoss_Assimilator 1 3190
Protoss_Cybernetics_Core 1 4417
Protoss_Dragoon 8 10607
Protoss_Robotics_Facility 1 7192
Protoss_Observatory 1 7334
Protoss_Nexus 1 10527
Protoss_Observer 3 10119
Protoss_Shuttle 1 10049
10607
