Protoss_Nexus 2 12341
Protoss_Gateway 3 10272
Protoss_Assimilator 1 4237
Protoss_Cybernetics_Core 1 5515
Protoss_Zealot 1 5433
Protoss_Dragoon 6 8739
Protoss_Citadel_of_Adun 1 8449
Protoss_Templar_Archives 1 9439
Protoss_Dark_Templar 1 11031
12341
