Protoss_Gateway 3 10298
Protoss_Assimilator 2 10352
Protoss_Zealot 1 3877
Protoss_Cybernetics_Core 1 5178
Protoss_Dragoon 9 11199
Protoss_Citadel_of_Adun 1 6243
Protoss_Templar_Archives 1 7234
Protoss_Nexus 1 9175
Protoss_Dark_Templar 1 7973
Protoss_Robotics_Facility 1 9296
Protoss_Observatory 1 9423
Protoss_Observer 1 10195
11199
