Protoss_Gateway 1 3267
Protoss_Assimilator 1 3301
Protoss_Cybernetics_Core 1 4421
Protoss_Dragoon 5 10899
Protoss_Robotics_Facility 1 6530
Protoss_Zealot 2 7683
Protoss_Shuttle 1 7333
Protoss_Robotics_Support_Bay 1 6841
Protoss_Reaver 1 8475
Protoss_Nexus 1 10515
Protoss_Observatory 1 8825
Protoss_Observer 1 9599
Protoss_Scarab 14 9997
10899
