Protoss_Gateway 4 10565
Protoss_Assimilator 2 10345
Protoss_Cybernetics_Core 1 4500
Protoss_Zealot 1 4527
Protoss_Dragoon 6 10929
Protoss_Citadel_of_Adun 2 10703
Protoss_Nexus 2 11481
Protoss_Robotics_Facility 1 8821
Protoss_Observatory 1 8933
Protoss_Observer 2 10361
11481
