Protoss_Gateway 2 8340
Protoss_Assimilator 1 3294
Protoss_Zealot 2 4981
Protoss_Cybernetics_Core 1 5293
Protoss_Dragoon 5 9329
Protoss_Nexus 2 12792
Protoss_Citadel_of_Adun 1 7669
Protoss_Robotics_Facility 1 9224
Protoss_Templar_Archives 1 9114
Protoss_Dark_Templar 2 10081
Protoss_Shuttle 1 10425
Protoss_Observatory 1 9772
Protoss_Observer 1 10847
12792
