Protoss_Gateway 2 5564
Protoss_Assimilator 1 3434
Protoss_Cybernetics_Core 1 4628
Protoss_Dragoon 7 8636
Protoss_Robotics_Facility 1 8994
Protoss_Observatory 1 9268
Protoss_Nexus 1 11488
Protoss_Zealot 2 9946
Protoss_Observer 1 10061
Protoss_Shuttle 1 11236
11488
