Protoss_Gateway 1 3496
Protoss_Assimilator 2 3803
Protoss_Cybernetics_Core 1 4993
Protoss_Robotics_Facility 1 6663
Protoss_Dragoon 1 6316
Protoss_Shuttle 1 7486
Protoss_Robotics_Support_Bay 1 7028
Protoss_Reaver 3 10861
Protoss_Zealot 1 8296
Protoss_Citadel_of_Adun 1 11163
11163
