Protoss_Gateway 2 9997
Protoss_Assimilator 1 2362
Protoss_Zealot 3 7631
Protoss_Cybernetics_Core 1 3703
Protoss_Dragoon 6 9981
Protoss_Robotics_Facility 1 5323
Protoss_Shuttle 2 9949
Protoss_Robotics_Support_Bay 1 6799
Protoss_Reaver 1 7519
Protoss_Observatory 1 8162
Protoss_Nexus 1 8557
Protoss_Observer 1 8935
Protoss_Scarab 3 9641
9997
