Protoss_Gateway 2 6253
Protoss_Assimilator 1 3364
Protoss_Cybernetics_Core 1 4490
Protoss_Dragoon 8 10915
Protoss_Citadel_of_Adun 1 5698
Protoss_Templar_Archives 1 6747
Protoss_Dark_Templar 2 7495
Protoss_Nexus 2 11975
11975
