Protoss_Gateway 2 4881
Protoss_Assimilator 2 10676
Protoss_Cybernetics_Core 1 4327
Protoss_Zealot 1 4581
Protoss_Dragoon 8 11121
Protoss_Nexus 2 10867
Protoss_Robotics_Facility 1 8691
Protoss_Observatory 1 8943
Protoss_Observer 2 10313
Protoss_Robotics_Support_Bay 1 10291
11121
