Protoss_Gateway 1 3267
Protoss_Assimilator 1 3298
Protoss_Cybernetics_Core 1 4421
Protoss_Dragoon 7 9889
Protoss_Robotics_Facility 1 7468
Protoss_Observatory 1 7683
Protoss_Robotics_Support_Bay 1 7795
Protoss_Observer 1 8479
Protoss_Nexus 2 12571
Protoss_Shuttle 1 10287
Protoss_Zealot 1 10401
12571
