Protoss_Gateway 2 6983
Protoss_Assimilator 1 3503
Protoss_Cybernetics_Core 1 4458
Protoss_Robotics_Facility 1 6272
Protoss_Dragoon 10 11146
Protoss_Observatory 1 6433
Protoss_Shuttle 1 7296
Protoss_Observer 2 8320
11146
