Protoss_Gateway 4 10581
Protoss_Assimilator 1 3446
Protoss_Cybernetics_Core 1 4528
Protoss_Nexus 2 10699
Protoss_Dragoon 10 10613
Protoss_Robotics_Facility 1 10122
Protoss_Observatory 1 10342
10699
