Protoss_Nexus 2 10311
Protoss_Gateway 6 10883
Protoss_Assimilator 1 4306
Protoss_Cybernetics_Core 1 5465
Protoss_Zealot 1 5427
Protoss_Dragoon 10 10471
Protoss_Robotics_Facility 1 10179
Protoss_Observatory 1 10487
10883
