Protoss_Gateway 3 8645
Protoss_Zealot 2 5557
Protoss_Assimilator 1 4547
Protoss_Cybernetics_Core 1 5986
Protoss_Dragoon 7 10359
Protoss_Robotics_Facility 1 8819
Protoss_Observatory 1 8907
Protoss_Nexus 1 11635
Protoss_Observer 2 10329
Protoss_Shuttle 1 10981
Protoss_Robotics_Support_Bay 1 10485
11635
