Protoss_Gateway 2 9506
Protoss_Assimilator 1 3300
Protoss_Cybernetics_Core 1 4433
Protoss_Dragoon 7 10819
Protoss_Robotics_Facility 1 7417
Protoss_Nexus 1 9689
Protoss_Observatory 1 7748
Protoss_Observer 1 8539
Protoss_Robotics_Support_Bay 1 8917
Protoss_Shuttle 1 10089
Protoss_Reaver 1 11231
11231
