Protoss_Gateway 3 11309
Protoss_Assimilator 2 10747
Protoss_Cybernetics_Core 1 4473
Protoss_Dragoon 9 10645
Protoss_Nexus 1 9156
Protoss_Robotics_Facility 1 9124
Protoss_Observatory 1 9463
Protoss_Shuttle 1 10435
Protoss_Observer 2 10863
11309
