Protoss_Gateway 3 10435
Protoss_Assimilator 1 3210
Protoss_Cybernetics_Core 1 4387
Protoss_Dragoon 11 10809
Protoss_Robotics_Facility 1 7221
Protoss_Observatory 1 7457
Protoss_Observer 1 8701
Protoss_Nexus 1 10893
10893
