Protoss_Gateway 3 7795
Protoss_Assimilator 1 3425
Protoss_Cybernetics_Core 1 4523
Protoss_Dragoon 8 10816
Protoss_Robotics_Facility 1 7177
Protoss_Observatory 1 7520
Protoss_Observer 2 10371
Protoss_Zealot 4 9681
Protoss_Shuttle 1 9503
10816
