Protoss_Gateway 2 7839
Protoss_Assimilator 1 3214
Protoss_Cybernetics_Core 1 4439
Protoss_Dragoon 6 10391
Protoss_Citadel_of_Adun 1 7103
Protoss_Robotics_Facility 1 7996
Protoss_Templar_Archives 1 8743
Protoss_Shuttle 1 9315
Protoss_Dark_Templar 2 9629
Protoss_Observatory 1 9652
Protoss_Zealot 1 10077
Protoss_Observer 1 10473
Protoss_Nexus 1 12781
12781
