Protoss_Gateway 3 5620
Protoss_Assimilator 1 4771
Protoss_Cybernetics_Core 1 6527
Protoss_Zealot 2 6137
Protoss_Dragoon 8 10821
Protoss_Nexus 1 11047
Protoss_Robotics_Facility 1 11222
Protoss_Stargate 1 11655
11655
