Protoss_Gateway 2 11439
Protoss_Assimilator 1 3363
Protoss_Cybernetics_Core 1 4595
Protoss_Dragoon 6 10549
Protoss_Robotics_Facility 1 7478
Protoss_Shuttle 1 8289
Protoss_Robotics_Support_Bay 1 7842
Protoss_Zealot 2 9003
Protoss_Reaver 2 10655
Protoss_Observatory 1 8784
Protoss_Nexus 1 11583
Protoss_Scarab 2 9700
11583
