Protoss_Gateway 4 11181
Protoss_Assimilator 1 3255
Protoss_Cybernetics_Core 1 4358
Protoss_Dragoon 9 11067
Protoss_Nexus 2 12253
Protoss_Citadel_of_Adun 1 7485
Protoss_Robotics_Facility 1 8773
Protoss_Templar_Archives 1 8690
Protoss_Shuttle 1 9617
Protoss_Dark_Templar 2 9643
Protoss_Observatory 1 9318
Protoss_Observer 1 10397
12253
