Protoss_Gateway 3 9956
Protoss_Assimilator 1 3327
Protoss_Cybernetics_Core 1 4518
Protoss_Dragoon 9 10726
Protoss_Robotics_Facility 1 7859
Protoss_Observatory 1 8000
Protoss_Observer 1 8806
Protoss_Shuttle 1 9976
Protoss_Zealot 2 9791
10726
