Protoss_Gateway 3 11331
Protoss_Assimilator 1 3203
Protoss_Cybernetics_Core 1 4292
Protoss_Dragoon 4 9217
Protoss_Robotics_Facility 1 7119
Protoss_Citadel_of_Adun 1 7641
Protoss_Observatory 1 7255
Protoss_Nexus 1 9811
Protoss_Zealot 1 8013
Protoss_Observer 1 8141
Protoss_Templar_Archives 1 9145
Protoss_Shuttle 1 9877
Protoss_Dark_Templar 4 11057
11331
