Protoss_Gateway 2 8094
Protoss_Assimilator 1 3187
Protoss_Zealot 2 4955
Protoss_Cybernetics_Core 1 5123
Protoss_Dragoon 6 9789
Protoss_Robotics_Facility 1 7789
Protoss_Observatory 1 7901
Protoss_Observer 2 9273
Protoss_Nexus 1 10996
Protoss_Shuttle 1 10355
Protoss_Robotics_Support_Bay 1 9959
Protoss_Reaver 1 11497
11497
