Protoss_Gateway 3 8944
Protoss_Assimilator 1 3312
Protoss_Cybernetics_Core 1 4503
Protoss_Dragoon 6 10146
Protoss_Robotics_Facility 1 7497
Protoss_Observatory 1 7771
Protoss_Observer 1 8546
Protoss_Zealot 4 9721
Protoss_Shuttle 1 9628
10146
