Protoss_Gateway 2 9319
Protoss_Assimilator 2 3540
Protoss_Cybernetics_Core 1 4773
Protoss_Dragoon 9 10901
Protoss_Nexus 1 9191
Protoss_Robotics_Facility 1 9112
Protoss_Observatory 1 9747
Protoss_Observer 1 10523
10901
