Protoss_Gateway 4 11389
Protoss_Assimilator 1 3067
Protoss_Cybernetics_Core 1 4307
Protoss_Dragoon 10 10923
Protoss_Nexus 2 11343
Protoss_Robotics_Facility 1 7961
Protoss_Observatory 1 8217
Protoss_Observer 3 10473
11389
