Protoss_Nexus 1 5682
Protoss_Gateway 2 5718
Protoss_Assimilator 1 4289
Protoss_Cybernetics_Core 1 5574
Protoss_Zealot 4 10803
Protoss_Dragoon 9 10851
Protoss_Robotics_Facility 1 8477
Protoss_Shuttle 1 9279
Protoss_Robotics_Support_Bay 1 8815
Protoss_Reaver 1 10471
Protoss_Observatory 1 9848
10851
