Protoss_Gateway 3 10728
Protoss_Assimilator 2 9129
Protoss_Cybernetics_Core 1 4674
Protoss_Dragoon 6 10857
Protoss_Nexus 1 8569
Protoss_Robotics_Facility 1 8305
Protoss_Shuttle 1 9189
Protoss_Observatory 1 8687
Protoss_Robotics_Support_Bay 1 8769
Protoss_Zealot 2 9969
Protoss_Reaver 1 10679
10857
