Protoss_Gateway 3 9200
Protoss_Assimilator 1 3468
Protoss_Cybernetics_Core 1 4628
Protoss_Dragoon 5 8920
Protoss_Robotics_Facility 2 8492
Protoss_Observatory 1 8602
Protoss_Observer 1 9586
Protoss_Zealot 3 10201
Protoss_Shuttle 1 10696
10696
