Protoss_Gateway 2 9068
Protoss_Assimilator 1 3153
Protoss_Cybernetics_Core 1 4460
Protoss_Dragoon 8 10677
Protoss_Robotics_Facility 1 7212
Protoss_Observatory 1 7333
Protoss_Observer 1 8129
Protoss_Nexus 1 10253
Protoss_Shuttle 1 9385
Protoss_Robotics_Support_Bay 1 9109
Protoss_Zealot 1 9669
Protoss_Reaver 1 10773
10773
