Protoss_Gateway 4 11264
Protoss_Assimilator 1 3466
Protoss_Cybernetics_Core 1 4547
Protoss_Dragoon 8 9333
Protoss_Robotics_Facility 1 7579
Protoss_Observatory 1 7884
Protoss_Observer 1 8701
Protoss_Shuttle 1 10003
Protoss_Nexus 1 11717
Protoss_Robotics_Support_Bay 1 9757
Protoss_Zealot 2 10215
Protoss_Reaver 1 11643
11717
