Protoss_Gateway 2 7185
Protoss_Assimilator 2 9788
Protoss_Cybernetics_Core 1 4571
Protoss_Dragoon 4 8197
Protoss_Citadel_of_Adun 1 6937
Protoss_Templar_Archives 1 7963
Protoss_Zealot 1 7573
Protoss_Dark_Templar 2 8949
Protoss_Nexus 2 12694
12694
