Protoss_Nexus 2 12409
Protoss_Gateway 3 9673
Protoss_Assimilator 2 8303
Protoss_Cybernetics_Core 1 5368
Protoss_Zealot 3 9243
Protoss_Dragoon 8 10085
Protoss_Robotics_Facility 2 9476
Protoss_Shuttle 1 10423
Protoss_Robotics_Support_Bay 1 9786
Protoss_Reaver 1 11565
12409
