Protoss_Gateway 2 5995
Protoss_Assimilator 2 10541
Protoss_Cybernetics_Core 1 4295
Protoss_Dragoon 10 10653
Protoss_Nexus 1 9507
Protoss_Robotics_Facility 1 9763
Protoss_Citadel_of_Adun 1 9867
Protoss_Shuttle 1 10639
Protoss_Robotics_Support_Bay 1 10449
Protoss_Templar_Archives 1 11338
11338
