Protoss_Gateway 6 11367
Protoss_Assimilator 1 3339
Protoss_Cybernetics_Core 1 4349
Protoss_Dragoon 6 10239
Protoss_Robotics_Facility 1 7373
Protoss_Observatory 1 7485
Protoss_Nexus 2 11151
Protoss_Observer 3 9503
11367
