Protoss_Gateway 1 3369
Protoss_Assimilator 1 3316
Protoss_Cybernetics_Core 1 4586
Protoss_Dragoon 6 9991
Protoss_Robotics_Facility 1 7379
Protoss_Shuttle 1 8237
Protoss_Observatory 1 7895
Protoss_Robotics_Support_Bay 1 8237
Protoss_Observer 2 10527
Protoss_Reaver 1 10011
Protoss_Zealot 1 10503
10527
