Protoss_Gateway 2 4828
Protoss_Assimilator 1 3288
Protoss_Cybernetics_Core 1 4393
Protoss_Dragoon 8 10961
Protoss_Nexus 1 9529
Protoss_Robotics_Facility 1 8943
Protoss_Shuttle 1 10121
Protoss_Observatory 1 9842
Protoss_Observer 1 10626
10961
