Protoss_Gateway 2 7450
Protoss_Assimilator 1 3425
Protoss_Cybernetics_Core 1 4581
Protoss_Dragoon 10 10811
Protoss_Robotics_Facility 1 7599
Protoss_Observatory 1 7730
Protoss_Observer 2 9241
Protoss_Nexus 1 10775
Protoss_Shuttle 1 10447
Protoss_Robotics_Support_Bay 1 9815
Protoss_Reaver 1 11593
11593
