Protoss_Gateway 2 9380
Protoss_Assimilator 1 3211
Protoss_Cybernetics_Core 1 4258
Protoss_Dragoon 10 10895
Protoss_Robotics_Facility 1 7315
Protoss_Nexus 1 9617
Protoss_Observatory 1 7506
Protoss_Observer 2 8877
Protoss_Shuttle 1 9959
Protoss_Robotics_Support_Bay 1 9679
Protoss_Reaver 1 11193
11193
