Protoss_Gateway 3 7773
Protoss_Assimilator 1 3529
Protoss_Zealot 10 9587
Protoss_Cybernetics_Core 1 5459
Protoss_Dragoon 2 9967
Protoss_Citadel_of_Adun 1 6716
Protoss_Templar_Archives 1 9802
Protoss_Dark_Templar 3 10719
10719
