Protoss_Gateway 2 5565
Protoss_Assimilator 1 3739
Protoss_Cybernetics_Core 1 4729
Protoss_Dragoon 7 10043
Protoss_Nexus 2 10592
Protoss_Forge 2 9224
Protoss_Robotics_Facility 1 11553
11553
