Protoss_Gateway 2 7345
Protoss_Assimilator 1 3438
Protoss_Cybernetics_Core 1 4577
Protoss_Dragoon 10 10886
Protoss_Robotics_Facility 1 6563
Protoss_Observatory 1 6730
Protoss_Observer 2 8476
Protoss_Nexus 1 11418
11418
