Protoss_Gateway 2 7284
Protoss_Assimilator 1 3225
Protoss_Cybernetics_Core 1 4392
Protoss_Dragoon 8 10697
Protoss_Robotics_Facility 1 7237
Protoss_Observatory 1 7429
Protoss_Nexus 2 11704
Protoss_Observer 2 9073
Protoss_Shuttle 1 10155
Protoss_Robotics_Support_Bay 1 9761
Protoss_Reaver 1 11297
Protoss_Zealot 2 10833
11704
