Protoss_Gateway 5 11075
Protoss_Assimilator 1 3276
Protoss_Cybernetics_Core 1 4242
Protoss_Dragoon 6 7081
Protoss_Nexus 2 10317
Protoss_Citadel_of_Adun 1 9341
Protoss_Templar_Archives 1 10412
11075
