Protoss_Gateway 3 11141
Protoss_Assimilator 2 9777
Protoss_Cybernetics_Core 1 4503
Protoss_Dragoon 10 10945
Protoss_Nexus 1 7610
Protoss_Robotics_Facility 1 8347
Protoss_Observatory 1 8437
Protoss_Observer 2 9987
Protoss_Shuttle 1 11097
Protoss_Robotics_Support_Bay 1 10427
Protoss_Zealot 2 10847
11141
