Protoss_Gateway 2 7655
Protoss_Assimilator 2 8766
Protoss_Cybernetics_Core 1 2735
Protoss_Dragoon 10 9915
Protoss_Robotics_Facility 1 5394
Protoss_Shuttle 1 6675
Protoss_Robotics_Support_Bay 1 6901
Protoss_Observatory 1 7216
Protoss_Reaver 1 7577
Protoss_Observer 3 9892
Protoss_Nexus 1 9853
Protoss_Scarab 1 9974
9974
