Protoss_Nexus 1 5557
Protoss_Gateway 2 5806
Protoss_Assimilator 2 7784
Protoss_Cybernetics_Core 1 5539
Protoss_Dragoon 11 10511
Protoss_Robotics_Facility 1 8771
Protoss_Shuttle 1 9611
Protoss_Observatory 2 10186
Protoss_Robotics_Support_Bay 1 9049
Protoss_Reaver 1 10753
10753
