Protoss_Gateway 3 8763
Protoss_Assimilator 1 3258
Protoss_Cybernetics_Core 1 4490
Protoss_Dragoon 10 10265
Protoss_Nexus 1 8678
Protoss_Robotics_Facility 1 8237
Protoss_Observatory 1 8355
Protoss_Observer 2 9729
10265
