Protoss_Nexus 1 5647
Protoss_Gateway 3 10727
Protoss_Assimilator 2 8487
Protoss_Cybernetics_Core 1 5505
Protoss_Zealot 1 5715
Protoss_Dragoon 12 10705
Protoss_Robotics_Facility 1 8802
Protoss_Shuttle 1 9625
Protoss_Robotics_Support_Bay 1 9563
Protoss_Reaver 1 11273
Protoss_Stargate 1 11610
11610
