Protoss_Gateway 2 8794
Protoss_Assimilator 1 3145
Protoss_Cybernetics_Core 1 4306
Protoss_Dragoon 10 10552
Protoss_Nexus 1 8849
Protoss_Robotics_Facility 1 8543
Protoss_Observatory 1 8811
Protoss_Observer 3 10914
10914
