Protoss_Gateway 2 7490
Protoss_Assimilator 1 3309
Protoss_Cybernetics_Core 1 4266
Protoss_Dragoon 3 6877
Protoss_Robotics_Facility 1 7365
Protoss_Citadel_of_Adun 1 7000
Protoss_Templar_Archives 1 8011
Protoss_Shuttle 1 8191
Protoss_Robotics_Support_Bay 1 7560
Protoss_Dark_Templar 4 10217
Protoss_Reaver 2 10755
Protoss_Nexus 1 11779
11779
