Protoss_Nexus 1 5729
Protoss_Gateway 5 11090
Protoss_Assimilator 1 4488
Protoss_Cybernetics_Core 1 5989
Protoss_Zealot 4 10807
Protoss_Dragoon 13 10901
Protoss_Robotics_Facility 1 9493
Protoss_Shuttle 1 10501
Protoss_Observatory 1 10548
11090
