Protoss_Gateway 2 5936
Protoss_Assimilator 1 3384
Protoss_Cybernetics_Core 1 4500
Protoss_Dragoon 10 10905
Protoss_Nexus 1 9011
Protoss_Robotics_Facility 1 8406
Protoss_Shuttle 1 9219
Protoss_Robotics_Support_Bay 1 9188
Protoss_Observatory 1 9990
10905
