Protoss_Gateway 2 6143
Protoss_Assimilator 1 3383
Protoss_Cybernetics_Core 1 4432
Protoss_Dragoon 12 10905
Protoss_Nexus 1 9703
Protoss_Robotics_Facility 1 8952
Protoss_Shuttle 1 9885
Protoss_Robotics_Support_Bay 1 9340
Protoss_Reaver 1 11027
11027
