Protoss_Nexus 1 5479
Protoss_Gateway 2 5583
Protoss_Assimilator 2 8859
Protoss_Cybernetics_Core 1 5463
Protoss_Zealot 2 9453
Protoss_Dragoon 9 10575
Protoss_Robotics_Facility 1 8569
Protoss_Shuttle 1 9385
Protoss_Robotics_Support_Bay 1 8890
Protoss_Reaver 1 10655
10655
