Protoss_Nexus 1 5653
Protoss_Gateway 4 10810
Protoss_Assimilator 2 7568
Protoss_Zealot 2 6063
Protoss_Cybernetics_Core 1 6210
Protoss_Dragoon 9 10939
Protoss_Forge 1 8395
Protoss_Robotics_Facility 1 9595
Protoss_Photon_Cannon 1 9545
Protoss_Citadel_of_Adun 1 10268
Protoss_Observatory 1 9714
Protoss_Observer 1 10509
Protoss_Templar_Archives 1 11327
11327
