Protoss_Gateway 2 9421
Protoss_Assimilator 1 3285
Protoss_Cybernetics_Core 1 4347
Protoss_Dragoon 8 10903
Protoss_Robotics_Facility 1 7288
Protoss_Observatory 1 7379
Protoss_Observer 3 9437
Protoss_Nexus 1 10311
Protoss_Shuttle 1 9937
Protoss_Robotics_Support_Bay 1 9260
Protoss_Reaver 1 11079
11079
