Protoss_Gateway 2 4825
Protoss_Assimilator 1 3256
Protoss_Cybernetics_Core 1 4270
Protoss_Dragoon 11 10193
Protoss_Robotics_Facility 1 9200
Protoss_Nexus 2 12703
Protoss_Observatory 1 9313
Protoss_Observer 1 10679
12703
