Protoss_Gateway 2 8175
Protoss_Assimilator 1 3493
Protoss_Cybernetics_Core 1 4578
Protoss_Robotics_Facility 1 6278
Protoss_Dragoon 6 10861
Protoss_Observatory 1 6439
Protoss_Observer 2 8241
Protoss_Nexus 1 10810
Protoss_Shuttle 1 9686
Protoss_Zealot 1 10941
10941
