Protoss_Gateway 2 11113
Protoss_Assimilator 1 3330
Protoss_Cybernetics_Core 1 4448
Protoss_Dragoon 7 11025
Protoss_Robotics_Facility 1 6275
Protoss_Shuttle 2 10823
Protoss_Robotics_Support_Bay 1 6747
Protoss_Zealot 2 7641
Protoss_Reaver 1 8289
Protoss_Observatory 1 8325
Protoss_Nexus 1 10995
Protoss_Observer 1 9187
Protoss_Scarab 4 9041
11113
