Protoss_Gateway 2 5131
Protoss_Assimilator 1 3421
Protoss_Cybernetics_Core 1 4480
Protoss_Dragoon 7 10305
Protoss_Nexus 2 10348
Protoss_Citadel_of_Adun 1 9349
Protoss_Templar_Archives 1 10582
Protoss_Stargate 1 11058
11058
