Protoss_Gateway 3 9833
Protoss_Assimilator 2 9969
Protoss_Cybernetics_Core 1 4328
Protoss_Dragoon 9 10917
Protoss_Nexus 1 8096
Protoss_Robotics_Facility 1 7970
Protoss_Observatory 1 8271
Protoss_Shuttle 1 9245
Protoss_Observer 1 9667
Protoss_Robotics_Support_Bay 1 9586
Protoss_Reaver 1 11073
Protoss_Zealot 2 10927
11073
