Protoss_Assimilator 1 2716
Protoss_Gateway 3 11103
Protoss_Cybernetics_Core 1 4705
Protoss_Robotics_Facility 1 6206
Protoss_Dragoon 6 10311
Protoss_Shuttle 1 7011
Protoss_Robotics_Support_Bay 1 7676
Protoss_Forge 1 8017
Protoss_Photon_Cannon 1 8978
Protoss_Reaver 1 9961
Protoss_Nexus 1 12045
12045
