Protoss_Gateway 2 7167
Protoss_Assimilator 1 3167
Protoss_Cybernetics_Core 1 4382
Protoss_Dragoon 10 10551
Protoss_Robotics_Facility 1 6877
Protoss_Observatory 1 7022
Protoss_Observer 2 8395
Protoss_Nexus 1 11069
11069
