Protoss_Gateway 2 6107
Protoss_Assimilator 2 8760
Protoss_Cybernetics_Core 1 4717
Protoss_Dragoon 5 10209
Protoss_Nexus 1 8485
Protoss_Robotics_Facility 1 8038
Protoss_Stargate 2 11596
Protoss_Observatory 1 8354
Protoss_Fleet_Beacon 1 9493
Protoss_Zealot 4 10911
Protoss_Observer 1 9981
Protoss_Carrier 1 12775
12775
