Protoss_Gateway 3 10577
Protoss_Assimilator 1 3361
Protoss_Cybernetics_Core 1 4436
Protoss_Dragoon 6 11003
Protoss_Robotics_Facility 1 7344
Protoss_Shuttle 1 8291
Protoss_Robotics_Support_Bay 1 7582
Protoss_Zealot 1 8281
Protoss_Reaver 1 9433
Protoss_Nexus 1 10929
Protoss_Observatory 1 8916
Protoss_Observer 1 10203
11003
