Protoss_Gateway 4 10827
Protoss_Assimilator 1 3217
Protoss_Cybernetics_Core 1 4348
Protoss_Dragoon 7 10159
Protoss_Robotics_Facility 1 6179
Protoss_Observatory 1 6406
Protoss_Nexus 2 11515
Protoss_Observer 3 8525
11515
