Protoss_Assimilator 3 5074
Protoss_Gateway 2 9308
Protoss_Cybernetics_Core 1 4807
Protoss_Dragoon 10 11123
Protoss_Nexus 2 12275
Protoss_Robotics_Facility 1 9083
Protoss_Observatory 1 9202
Protoss_Observer 2 10631
12275
