Protoss_Gateway 2 6767
Protoss_Assimilator 1 3375
Protoss_Cybernetics_Core 1 4479
Protoss_Dragoon 11 10111
Protoss_Robotics_Facility 1 8688
Protoss_Observatory 1 8818
Protoss_Observer 2 10553
Protoss_Nexus 1 12476
12476
