Protoss_Gateway 2 11074
Protoss_Zealot 5 8977
Protoss_Assimilator 2 10252
Protoss_Nexus 1 9612
Protoss_Forge 1 7742
Protoss_Cybernetics_Core 1 8821
Protoss_Photon_Cannon 2 9472
Protoss_Citadel_of_Adun 1 10084
Protoss_Robotics_Facility 1 11117
Protoss_Templar_Archives 1 11217
11217
