Protoss_Gateway 3 8693
Protoss_Assimilator 1 3133
Protoss_Cybernetics_Core 1 4335
Protoss_Robotics_Facility 1 5883
Protoss_Shuttle 1 6691
Protoss_Dragoon 10 11146
Protoss_Observatory 1 8235
Protoss_Observer 2 9618
Protoss_Nexus 1 12023
12023
