Protoss_Gateway 1 3273
Protoss_Assimilator 1 3189
Protoss_Cybernetics_Core 1 4345
Protoss_Zealot 1 4119
Protoss_Dragoon 8 10641
Protoss_Robotics_Facility 1 8298
Protoss_Shuttle 1 9145
Protoss_Robotics_Support_Bay 1 8621
Protoss_Observatory 1 8901
Protoss_Reaver 1 10287
Protoss_Observer 1 10643
10643
