Protoss_Gateway 4 10660
Protoss_Nexus 1 6117
Protoss_Assimilator 2 7459
Protoss_Cybernetics_Core 1 5791
Protoss_Zealot 3 10353
Protoss_Dragoon 8 9839
Protoss_Robotics_Facility 1 9317
Protoss_Observatory 1 9463
Protoss_Stargate 2 11312
Protoss_Observer 1 10241
Protoss_Fleet_Beacon 1 11403
Protoss_Shuttle 1 11425
11425
