Protoss_Gateway 4 10391
Protoss_Zealot 1 3685
Protoss_Assimilator 1 4666
Protoss_Cybernetics_Core 1 6095
Protoss_Dragoon 10 10715
Protoss_Nexus 1 10281
Protoss_Robotics_Facility 1 10626
10715
