Protoss_Gateway 3 10867
Protoss_Assimilator 1 3173
Protoss_Cybernetics_Core 1 4366
Protoss_Dragoon 6 9065
Protoss_Robotics_Facility 1 7412
Protoss_Shuttle 1 8337
Protoss_Robotics_Support_Bay 1 7724
Protoss_Nexus 1 10465
Protoss_Reaver 1 10251
Protoss_Zealot 2 10179
10867
