Protoss_Gateway 3 9683
Protoss_Assimilator 1 3247
Protoss_Zealot 2 9543
Protoss_Cybernetics_Core 1 4575
Protoss_Robotics_Facility 1 6103
Protoss_Dragoon 9 11137
Protoss_Observatory 1 6389
Protoss_Observer 2 8229
Protoss_Nexus 1 9767
11137
