Protoss_Gateway 3 9358
Protoss_Assimilator 1 3478
Protoss_Cybernetics_Core 1 4838
Protoss_Dragoon 9 11086
Protoss_Robotics_Facility 1 7383
Protoss_Nexus 1 9424
Protoss_Robotics_Support_Bay 1 7534
Protoss_Observatory 1 7718
Protoss_Observer 2 9308
Protoss_Shuttle 1 10390
Protoss_Citadel_of_Adun 1 11163
11163
