Protoss_Gateway 3 9316
Protoss_Assimilator 1 3269
Protoss_Cybernetics_Core 1 4302
Protoss_Dragoon 11 11087
Protoss_Zealot 1 5555
Protoss_Robotics_Facility 1 7040
Protoss_Observatory 1 7227
Protoss_Nexus 2 12537
Protoss_Observer 5 10821
12537
