Protoss_Gateway 4 10869
Protoss_Assimilator 1 3327
Protoss_Cybernetics_Core 1 4449
Protoss_Zealot 1 4339
Protoss_Dragoon 9 10987
Protoss_Robotics_Facility 1 7451
Protoss_Nexus 1 10048
Protoss_Observatory 1 8016
Protoss_Observer 4 10775
10987
