Protoss_Gateway 2 11239
Protoss_Assimilator 1 3147
Protoss_Cybernetics_Core 1 4295
Protoss_Dragoon 6 10429
Protoss_Robotics_Facility 1 6132
Protoss_Shuttle 1 6953
Protoss_Robotics_Support_Bay 1 6726
Protoss_Reaver 4 11401
Protoss_Scarab 11 9530
Protoss_Nexus 1 11237
11401
