Protoss_Gateway 2 7526
Protoss_Assimilator 1 3337
Protoss_Cybernetics_Core 1 4447
Protoss_Zealot 3 10725
Protoss_Dragoon 8 9805
Protoss_Robotics_Facility 1 7345
Protoss_Observatory 1 7481
Protoss_Observer 2 9355
Protoss_Nexus 1 11198
Protoss_Shuttle 1 10593
Protoss_Robotics_Support_Bay 1 10363
11198
