Protoss_Nexus 1 6055
Protoss_Gateway 4 11250
Protoss_Assimilator 2 8848
Protoss_Cybernetics_Core 1 5822
Protoss_Zealot 1 5411
Protoss_Dragoon 8 10428
Protoss_Robotics_Facility 1 7923
Protoss_Observatory 1 8100
Protoss_Observer 1 9021
Protoss_Robotics_Support_Bay 1 10591
11250
