Protoss_Gateway 4 11119
Protoss_Assimilator 2 10398
Protoss_Cybernetics_Core 1 4424
Protoss_Dragoon 3 6689
Protoss_Citadel_of_Adun 1 6781
Protoss_Robotics_Facility 1 7327
Protoss_Templar_Archives 1 7834
Protoss_Shuttle 1 8145
Protoss_Dark_Templar 6 10505
Protoss_Nexus 1 10992
11119
