Protoss_Gateway 2 10227
Protoss_Assimilator 2 10047
Protoss_Cybernetics_Core 1 4605
Protoss_Dragoon 8 10635
Protoss_Nexus 1 8883
Protoss_Robotics_Facility 1 9091
Protoss_Observatory 1 9191
Protoss_Robotics_Support_Bay 1 9585
Protoss_Citadel_of_Adun 1 10367
Protoss_Observer 1 9963
Protoss_Shuttle 1 11073
11073
