Protoss_Gateway 2 6025
Protoss_Assimilator 1 3322
Protoss_Cybernetics_Core 1 4429
Protoss_Dragoon 10 10565
Protoss_Nexus 2 10618
Protoss_Robotics_Facility 1 10033
Protoss_Shuttle 1 10921
Protoss_Robotics_Support_Bay 1 10358
Protoss_Observatory 1 10402
10921
