Protoss_Gateway 2 7321
Protoss_Assimilator 1 3325
Protoss_Cybernetics_Core 1 4653
Protoss_Dragoon 12 10817
Protoss_Forge 1 8341
Protoss_Nexus 1 11061
Protoss_Photon_Cannon 2 10706
11061
