Protoss_Gateway 3 10657
Protoss_Assimilator 1 3389
Protoss_Cybernetics_Core 1 4596
Protoss_Dragoon 8 10321
Protoss_Robotics_Facility 1 7896
Protoss_Observatory 1 8178
Protoss_Nexus 1 11458
Protoss_Observer 1 10696
Protoss_Citadel_of_Adun 1 11211
11458
