Protoss_Gateway 3 10885
Protoss_Assimilator 2 10675
Protoss_Cybernetics_Core 1 4491
Protoss_Dragoon 7 10239
Protoss_Robotics_Facility 1 7649
Protoss_Nexus 1 9775
Protoss_Shuttle 1 8677
Protoss_Robotics_Support_Bay 1 8428
Protoss_Reaver 1 10065
Protoss_Observatory 1 9418
Protoss_Observer 1 10397
10885
