Protoss_Gateway 2 7719
Protoss_Assimilator 1 3114
Protoss_Cybernetics_Core 1 4199
Protoss_Dragoon 7 11177
Protoss_Robotics_Facility 1 7434
Protoss_Shuttle 1 8263
Protoss_Nexus 2 12695
Protoss_Robotics_Support_Bay 1 8038
Protoss_Reaver 1 9597
Protoss_Observatory 1 8906
Protoss_Zealot 2 9207
Protoss_Observer 2 10531
12695
