Protoss_Forge 1 3103
Protoss_Photon_Cannon 4 6267
Protoss_Gateway 2 8120
Protoss_Assimilator 2 10951
Protoss_Cybernetics_Core 1 6958
Protoss_Zealot 3 10931
Protoss_Dragoon 6 10419
Protoss_Nexus 1 10839
10951
