Protoss_Assimilator 2 5030
Protoss_Gateway 2 7111
Protoss_Zealot 3 6083
Protoss_Cybernetics_Core 1 5729
Protoss_Nexus 1 7849
Protoss_Dragoon 9 10553
Protoss_Robotics_Facility 1 10765
10765
