Protoss_Gateway 3 8478
Protoss_Assimilator 1 3333
Protoss_Cybernetics_Core 1 4588
Protoss_Dragoon 12 10777
Protoss_Robotics_Facility 1 6231
Protoss_Shuttle 1 7036
Protoss_Observatory 1 6493
Protoss_Observer 3 9426
Protoss_Nexus 1 12560
12560
