Protoss_Gateway 3 7427
Protoss_Assimilator 1 3289
Protoss_Cybernetics_Core 1 4269
Protoss_Zealot 4 10909
Protoss_Dragoon 3 6491
Protoss_Citadel_of_Adun 1 6114
Protoss_Templar_Archives 1 7105
Protoss_Dark_Templar 10 11135
11135
