Protoss_Gateway 2 6981
Protoss_Assimilator 1 3322
Protoss_Cybernetics_Core 1 4474
Protoss_Dragoon 7 8990
Protoss_Robotics_Facility 1 7357
Protoss_Observatory 1 7633
Protoss_Observer 2 9019
Protoss_Nexus 2 11511
Protoss_Shuttle 1 10365
Protoss_Robotics_Support_Bay 1 9837
Protoss_Reaver 1 11507
11511
