Protoss_Gateway 2 8421
Protoss_Assimilator 1 3227
Protoss_Cybernetics_Core 1 4453
Protoss_Dragoon 8 10989
Protoss_Robotics_Facility 1 7149
Protoss_Nexus 2 11645
Protoss_Observatory 1 7367
Protoss_Observer 3 9583
11645
