Protoss_Nexus 2 12285
Protoss_Gateway 2 6357
Protoss_Assimilator 2 9131
Protoss_Cybernetics_Core 1 5531
Protoss_Zealot 2 7795
Protoss_Dragoon 8 9633
Protoss_Robotics_Facility 1 8397
Protoss_Observatory 1 8524
Protoss_Observer 2 10003
12285
