Protoss_Nexus 1 5457
Protoss_Gateway 4 10525
Protoss_Assimilator 2 7388
Protoss_Cybernetics_Core 1 5547
Protoss_Dragoon 13 10763
Protoss_Robotics_Facility 1 9007
Protoss_Observatory 1 9318
Protoss_Observer 2 10769
Protoss_Citadel_of_Adun 1 11430
11430
