Protoss_Gateway 2 9571
Protoss_Assimilator 1 3413
Protoss_Zealot 2 4503
Protoss_Cybernetics_Core 1 4737
Protoss_Dragoon 6 10451
Protoss_Robotics_Facility 1 7679
Protoss_Observatory 1 7769
Protoss_Nexus 1 10287
Protoss_Observer 2 9309
Protoss_Citadel_of_Adun 1 9291
Protoss_Shuttle 1 10219
Protoss_Templar_Archives 1 10327
Protoss_Dark_Templar 1 11123
11123
