Protoss_Gateway 5 11383
Protoss_Assimilator 1 3694
Protoss_Cybernetics_Core 1 4553
Protoss_Dragoon 8 10923
Protoss_Citadel_of_Adun 1 7541
Protoss_Nexus 1 9648
Protoss_Robotics_Facility 1 9491
Protoss_Observatory 1 9661
Protoss_Observer 1 10451
11383
