Protoss_Gateway 2 5619
Protoss_Assimilator 2 9676
Protoss_Cybernetics_Core 1 4270
Protoss_Dragoon 12 10171
Protoss_Nexus 1 10002
Protoss_Citadel_of_Adun 1 9682
Protoss_Templar_Archives 1 11129
Protoss_Robotics_Facility 1 11706
11706
