Protoss_Gateway 2 8996
Protoss_Assimilator 1 3155
Protoss_Cybernetics_Core 1 4295
Protoss_Zealot 1 4075
Protoss_Dragoon 8 9793
Protoss_Robotics_Facility 1 7813
Protoss_Nexus 2 12553
Protoss_Observatory 1 8028
Protoss_Observer 4 10746
12553
