Protoss_Gateway 2 6023
Protoss_Zealot 2 4275
Protoss_Assimilator 1 4694
Protoss_Cybernetics_Core 1 5770
Protoss_Dragoon 7 10577
Protoss_Robotics_Facility 1 9034
Protoss_Nexus 1 11083
Protoss_Observatory 1 9562
Protoss_Observer 1 10457
Protoss_Robotics_Support_Bay 1 10474
11083
