Protoss_Gateway 2 8404
Protoss_Assimilator 1 3630
Protoss_Cybernetics_Core 1 4758
Protoss_Dragoon 6 10146
Protoss_Robotics_Facility 1 8593
Protoss_Nexus 2 12168
Protoss_Shuttle 1 9471
Protoss_Observatory 1 8851
Protoss_Observer 1 10351
12168
