Protoss_Gateway 3 9251
Protoss_Zealot 4 5717
Protoss_Assimilator 1 4619
Protoss_Cybernetics_Core 1 5931
Protoss_Dragoon 9 10949
Protoss_Nexus 1 11223
Protoss_Robotics_Facility 1 10611
Protoss_Observatory 1 10699
11223
