Protoss_Gateway 1 3377
Protoss_Assimilator 1 3316
Protoss_Cybernetics_Core 1 4416
Protoss_Zealot 3 8859
Protoss_Dragoon 6 10453
Protoss_Robotics_Facility 1 7525
Protoss_Shuttle 1 8323
Protoss_Robotics_Support_Bay 1 7874
Protoss_Reaver 1 9465
Protoss_Observatory 1 8604
Protoss_Observer 2 10470
Protoss_Nexus 1 12176
Protoss_Scarab 2 9938
12176
