Protoss_Gateway 2 8603
Protoss_Assimilator 2 9791
Protoss_Zealot 2 4661
Protoss_Cybernetics_Core 1 5074
Protoss_Dragoon 8 10383
Protoss_Nexus 1 9301
Protoss_Robotics_Facility 1 8707
Protoss_Shuttle 1 9537
Protoss_Observatory 1 8867
Protoss_Robotics_Support_Bay 1 9408
Protoss_Observer 1 9959
Protoss_Reaver 1 11647
11647
