Protoss_Assimilator 2 3835
Protoss_Gateway 2 6384
Protoss_Cybernetics_Core 1 5044
Protoss_Dragoon 10 10715
Protoss_Nexus 2 12600
Protoss_Robotics_Facility 1 11720
Protoss_Citadel_of_Adun 1 11426
12600
