Protoss_Gateway 2 10422
Protoss_Assimilator 1 3182
Protoss_Cybernetics_Core 1 4301
Protoss_Dragoon 5 9551
Protoss_Robotics_Facility 1 7374
Protoss_Shuttle 1 8183
Protoss_Robotics_Support_Bay 1 7710
Protoss_Reaver 2 10377
Protoss_Nexus 2 12626
Protoss_Scarab 3 9927
12626
