Protoss_Gateway 3 10049
Protoss_Assimilator 1 3269
Protoss_Cybernetics_Core 1 4436
Protoss_Dragoon 9 10845
Protoss_Robotics_Facility 1 7233
Protoss_Observatory 1 7669
Protoss_Nexus 1 10122
Protoss_Observer 1 8539
10845
