Protoss_Gateway 3 9188
Protoss_Assimilator 1 3373
Protoss_Cybernetics_Core 1 4618
Protoss_Dragoon 6 10831
Protoss_Robotics_Facility 1 7188
Protoss_Nexus 2 11618
Protoss_Observatory 1 7896
Protoss_Observer 4 10767
11618
