Protoss_Gateway 2 10843
Protoss_Assimilator 1 3210
Protoss_Cybernetics_Core 1 4357
Protoss_Dragoon 5 8413
Protoss_Robotics_Facility 1 7485
Protoss_Shuttle 1 8287
Protoss_Robotics_Support_Bay 1 7832
Protoss_Reaver 1 9429
Protoss_Zealot 1 9055
Protoss_Nexus 2 12143
Protoss_Observatory 1 9297
Protoss_Observer 2 10673
12143
