Protoss_Gateway 3 9305
Protoss_Assimilator 1 3343
Protoss_Cybernetics_Core 1 4407
Protoss_Zealot 1 4249
Protoss_Dragoon 7 10445
Protoss_Nexus 2 12593
Protoss_Robotics_Facility 1 8968
Protoss_Observatory 1 9146
Protoss_Observer 2 10557
12593
