Protoss_Gateway 4 10597
Protoss_Assimilator 1 3218
Protoss_Cybernetics_Core 1 4371
Protoss_Dragoon 12 10546
Protoss_Nexus 1 10393
Protoss_Robotics_Facility 1 10273
Protoss_Observatory 1 10404
Protoss_Citadel_of_Adun 1 11416
11416
