Protoss_Gateway 3 11171
Protoss_Zealot 4 9477
Protoss_Assimilator 1 4082
Protoss_Cybernetics_Core 1 5017
Protoss_Dragoon 6 10565
Protoss_Nexus 1 8357
Protoss_Robotics_Facility 1 8097
Protoss_Shuttle 1 8933
Protoss_Robotics_Support_Bay 1 8495
Protoss_Reaver 1 10075
Protoss_Observatory 1 9476
Protoss_Observer 1 10407
11171
