Protoss_Gateway 2 8703
Protoss_Assimilator 2 10301
Protoss_Cybernetics_Core 1 4695
Protoss_Zealot 2 10403
Protoss_Dragoon 7 10629
Protoss_Nexus 1 8949
Protoss_Robotics_Facility 1 8703
Protoss_Shuttle 1 9549
Protoss_Observatory 1 8910
Protoss_Robotics_Support_Bay 1 9659
Protoss_Observer 1 9971
Protoss_Reaver 1 11399
11399
