Protoss_Gateway 2 6319
Protoss_Assimilator 1 3361
Protoss_Zealot 3 5219
Protoss_Cybernetics_Core 1 5465
Protoss_Dragoon 3 7569
Protoss_Robotics_Facility 1 7831
Protoss_Citadel_of_Adun 1 8099
Protoss_Templar_Archives 1 9109
Protoss_Shuttle 1 9129
Protoss_Dark_Templar 4 10611
Protoss_Nexus 1 12485
12485
