Protoss_Gateway 3 11432
Protoss_Assimilator 1 3441
Protoss_Cybernetics_Core 1 4703
Protoss_Zealot 1 4547
Protoss_Dragoon 9 10541
Protoss_Nexus 1 11263
Protoss_Robotics_Facility 1 10401
Protoss_Citadel_of_Adun 1 10182
Protoss_Templar_Archives 1 11197
Protoss_Observatory 1 10539
11432
