Protoss_Gateway 2 9029
Protoss_Assimilator 1 3345
Protoss_Cybernetics_Core 1 4475
Protoss_Dragoon 8 10453
Protoss_Robotics_Facility 1 6370
Protoss_Observatory 1 6709
Protoss_Shuttle 1 7729
Protoss_Observer 3 9355
Protoss_Robotics_Support_Bay 1 9327
Protoss_Nexus 1 11859
11859
