Protoss_Gateway 2 6959
Protoss_Assimilator 2 9647
Protoss_Forge 1 5230
Protoss_Cybernetics_Core 1 5903
Protoss_Dragoon 6 10197
Protoss_Nexus 1 8923
Protoss_Citadel_of_Adun 1 8633
Protoss_Robotics_Facility 1 9505
Protoss_Templar_Archives 1 10029
Protoss_Robotics_Support_Bay 1 10333
Protoss_Shield_Battery 1 10365
Protoss_Dark_Templar 2 11003
11003
