Protoss_Gateway 4 9703
Protoss_Assimilator 3 3862
Protoss_Zealot 1 4081
Protoss_Cybernetics_Core 1 5221
Protoss_Nexus 2 8567
Protoss_Dragoon 12 11141
Protoss_Robotics_Facility 1 11000
11141
