Protoss_Gateway 2 3991
Protoss_Zealot 2 4577
Protoss_Assimilator 1 4754
Protoss_Cybernetics_Core 1 6004
Protoss_Dragoon 8 10485
Protoss_Robotics_Facility 1 10135
Protoss_Nexus 1 11219
Protoss_Robotics_Support_Bay 1 10336
Protoss_Shuttle 1 11311
11311
