Protoss_Gateway 2 6809
Protoss_Assimilator 1 3331
Protoss_Cybernetics_Core 1 4465
Protoss_Zealot 4 10507
Protoss_Dragoon 8 10289
Protoss_Robotics_Facility 1 8145
Protoss_Observatory 1 8426
Protoss_Observer 1 9365
Protoss_Nexus 1 11801
Protoss_Shuttle 1 11025
11801
