Protoss_Gateway 5 10991
Protoss_Assimilator 1 3209
Protoss_Cybernetics_Core 1 4379
Protoss_Robotics_Facility 1 5971
Protoss_Dragoon 8 10733
Protoss_Observatory 1 6481
Protoss_Observer 4 9429
Protoss_Nexus 2 10449
10991
