Protoss_Gateway 2 7810
Protoss_Assimilator 1 3433
Protoss_Cybernetics_Core 1 4599
Protoss_Dragoon 3 10608
Protoss_Robotics_Facility 1 6684
Protoss_Citadel_of_Adun 1 6788
Protoss_Observatory 1 6834
Protoss_Templar_Archives 1 7914
Protoss_Observer 1 7781
Protoss_Shuttle 1 8863
Protoss_Dark_Templar 4 9856
Protoss_Nexus 1 12009
12009
