Protoss_Gateway 2 9388
Protoss_Assimilator 1 3381
Protoss_Cybernetics_Core 1 4471
Protoss_Zealot 3 10039
Protoss_Dragoon 8 11141
Protoss_Nexus 1 9072
Protoss_Robotics_Facility 1 8922
Protoss_Shuttle 1 9835
Protoss_Robotics_Support_Bay 1 9492
Protoss_Reaver 1 11101
11141
