Protoss_Gateway 3 9551
Protoss_Assimilator 1 3383
Protoss_Cybernetics_Core 1 4580
Protoss_Dragoon 11 10826
Protoss_Nexus 1 9695
Protoss_Robotics_Facility 1 9588
Protoss_Observatory 1 10068
Protoss_Forge 1 10907
10907
