Protoss_Gateway 1 3307
Protoss_Assimilator 1 3315
Protoss_Zealot 1 3839
Protoss_Cybernetics_Core 1 4681
Protoss_Robotics_Facility 1 6207
Protoss_Dragoon 6 10441
Protoss_Shuttle 1 7011
Protoss_Robotics_Support_Bay 1 6757
Protoss_Reaver 2 10975
Protoss_Observatory 1 7964
Protoss_Observer 2 9615
Protoss_Nexus 1 12639
12639
