Protoss_Gateway 2 8071
Protoss_Assimilator 1 3431
Protoss_Cybernetics_Core 1 4465
Protoss_Dragoon 10 10715
Protoss_Robotics_Facility 1 7959
Protoss_Observatory 1 8130
Protoss_Observer 2 10567
Protoss_Nexus 1 11042
11042
