Protoss_Assimilator 3 10325
Protoss_Gateway 3 11420
Protoss_Cybernetics_Core 1 5162
Protoss_Dragoon 6 9329
Protoss_Nexus 1 9832
Protoss_Robotics_Facility 1 9487
Protoss_Citadel_of_Adun 1 10179
Protoss_Observatory 1 9831
Protoss_Stargate 1 10863
Protoss_Observer 1 10615
Protoss_Templar_Archives 1 11301
11420
