Protoss_Gateway 2 6648
Protoss_Assimilator 1 3408
Protoss_Cybernetics_Core 1 4463
Protoss_Dragoon 6 8826
Protoss_Citadel_of_Adun 1 7593
Protoss_Templar_Archives 1 8728
Protoss_Dark_Templar 2 9731
Protoss_Nexus 1 12183
Protoss_Robotics_Facility 1 11897
12183
