Protoss_Gateway 5 9930
Protoss_Assimilator 2 10131
Protoss_Cybernetics_Core 1 4563
Protoss_Dragoon 8 10875
Protoss_Robotics_Facility 1 7518
Protoss_Observatory 1 7653
Protoss_Nexus 1 10049
Protoss_Observer 5 10959
10959
