Protoss_Gateway 2 9551
Protoss_Assimilator 1 2389
Protoss_Cybernetics_Core 1 3027
Protoss_Dragoon 5 9955
Protoss_Robotics_Facility 1 5187
Protoss_Shuttle 1 6697
Protoss_Robotics_Support_Bay 1 6840
Protoss_Reaver 1 7599
Protoss_Zealot 1 8283
Protoss_Nexus 1 8607
Protoss_Scarab 10 9799
9955
