Protoss_Gateway 2 8753
Protoss_Assimilator 1 3255
Protoss_Cybernetics_Core 1 4337
Protoss_Zealot 3 10297
Protoss_Dragoon 10 11189
Protoss_Nexus 1 9055
Protoss_Robotics_Facility 1 8757
Protoss_Shuttle 1 9613
Protoss_Robotics_Support_Bay 1 9355
Protoss_Reaver 1 11069
Protoss_Observatory 1 10202
11189
