Protoss_Assimilator 3 8943
Protoss_Gateway 3 11381
Protoss_Zealot 3 6555
Protoss_Nexus 1 7161
Protoss_Cybernetics_Core 1 6797
Protoss_Dragoon 9 10787
Protoss_Robotics_Facility 1 10178
Protoss_Shuttle 1 11005
Protoss_Robotics_Support_Bay 1 10499
11381
