Protoss_Nexus 1 5877
Protoss_Gateway 3 9865
Protoss_Assimilator 1 4789
Protoss_Cybernetics_Core 1 5798
Protoss_Zealot 4 10529
Protoss_Dragoon 7 9815
Protoss_Robotics_Facility 1 9255
Protoss_Robotics_Support_Bay 1 9589
Protoss_Shuttle 1 10647
10647
