Protoss_Gateway 3 9865
Protoss_Assimilator 2 9559
Protoss_Cybernetics_Core 1 4444
Protoss_Dragoon 7 10775
Protoss_Nexus 1 8859
Protoss_Robotics_Facility 1 8882
Protoss_Citadel_of_Adun 1 9497
Protoss_Observatory 1 8983
Protoss_Observer 1 9893
Protoss_Templar_Archives 1 10493
Protoss_Stargate 1 10939
Protoss_Zealot 2 10521
10939
