Protoss_Gateway 4 10336
Protoss_Assimilator 1 3181
Protoss_Cybernetics_Core 1 4332
Protoss_Dragoon 8 11079
Protoss_Nexus 2 10875
Protoss_Robotics_Facility 1 8750
Protoss_Observatory 1 8990
Protoss_Observer 2 10789
11079
