Protoss_Gateway 2 9600
Protoss_Assimilator 1 3437
Protoss_Cybernetics_Core 1 4574
Protoss_Dragoon 6 10849
Protoss_Stargate 1 7179
Protoss_Fleet_Beacon 1 8235
Protoss_Carrier 1 11285
Protoss_Robotics_Facility 1 10567
Protoss_Nexus 1 12787
12787
