Protoss_Gateway 2 7923
Protoss_Assimilator 2 10649
Protoss_Cybernetics_Core 1 4275
Protoss_Dragoon 9 11085
Protoss_Nexus 1 8539
Protoss_Robotics_Facility 1 8009
Protoss_Shuttle 1 8987
Protoss_Robotics_Support_Bay 1 8545
Protoss_Observatory 1 9500
Protoss_Reaver 1 10909
11085
