Protoss_Nexus 2 10846
Protoss_Gateway 4 10092
Protoss_Assimilator 2 9645
Protoss_Cybernetics_Core 1 5615
Protoss_Zealot 1 5601
Protoss_Dragoon 8 10089
Protoss_Robotics_Facility 1 8997
Protoss_Observatory 1 9280
Protoss_Observer 2 10771
10846
