Protoss_Gateway 2 9347
Protoss_Assimilator 1 3493
Protoss_Cybernetics_Core 1 4572
Protoss_Zealot 1 4261
Protoss_Dragoon 6 10711
Protoss_Robotics_Facility 1 7647
Protoss_Observatory 1 7834
Protoss_Nexus 1 10285
Protoss_Observer 2 9551
Protoss_Shuttle 1 10261
Protoss_Robotics_Support_Bay 1 10188
10711
