Protoss_Gateway 3 9664
Protoss_Assimilator 1 3396
Protoss_Cybernetics_Core 1 4778
Protoss_Dragoon 9 10787
Protoss_Robotics_Facility 1 6353
Protoss_Shuttle 1 7286
Protoss_Observatory 1 6690
Protoss_Observer 4 10873
10873
