Protoss_Gateway 3 10988
Protoss_Nexus 1 6280
Protoss_Assimilator 1 4491
Protoss_Cybernetics_Core 1 5368
Protoss_Zealot 1 5406
Protoss_Dragoon 10 10626
Protoss_Robotics_Facility 1 9285
Protoss_Robotics_Support_Bay 1 9483
Protoss_Shuttle 1 10466
Protoss_Reaver 1 11611
11611
