Protoss_Gateway 4 11231
Protoss_Assimilator 1 3303
Protoss_Zealot 5 10411
Protoss_Cybernetics_Core 1 4518
Protoss_Citadel_of_Adun 1 5509
Protoss_Dragoon 1 5373
Protoss_Templar_Archives 1 6614
Protoss_Dark_Templar 7 9691
Protoss_Nexus 1 10467
11231
