Protoss_Gateway 4 11181
Protoss_Assimilator 2 9542
Protoss_Cybernetics_Core 1 4416
Protoss_Dragoon 9 10323
Protoss_Robotics_Facility 1 7484
Protoss_Nexus 1 9774
Protoss_Observatory 1 7680
Protoss_Observer 3 9867
Protoss_Citadel_of_Adun 1 9596
Protoss_Templar_Archives 1 10911
Protoss_Stargate 1 11256
11256
