Protoss_Gateway 5 11395
Protoss_Assimilator 1 3261
Protoss_Cybernetics_Core 1 4479
Protoss_Dragoon 8 10591
Protoss_Robotics_Facility 1 6333
Protoss_Observatory 1 6482
Protoss_Nexus 2 11875
Protoss_Observer 2 7971
11875
