Protoss_Gateway 3 11128
Protoss_Assimilator 1 3287
Protoss_Cybernetics_Core 1 4427
Protoss_Zealot 3 10315
Protoss_Dragoon 8 11157
Protoss_Nexus 1 9115
Protoss_Robotics_Facility 1 8432
Protoss_Shuttle 1 9245
Protoss_Robotics_Support_Bay 1 9042
Protoss_Reaver 1 10601
Protoss_Observatory 1 10217
11157
