Protoss_Gateway 2 6611
Protoss_Assimilator 1 3519
Protoss_Cybernetics_Core 1 4707
Protoss_Zealot 1 4437
Protoss_Dragoon 11 11143
Protoss_Nexus 1 9295
Protoss_Robotics_Facility 1 9583
Protoss_Shuttle 1 11169
Protoss_Robotics_Support_Bay 1 10551
11169
