Protoss_Nexus 1 5429
Protoss_Gateway 2 5591
Protoss_Assimilator 1 4219
Protoss_Cybernetics_Core 1 5353
Protoss_Zealot 1 5451
Protoss_Dragoon 10 10651
Protoss_Robotics_Facility 1 9847
Protoss_Observatory 1 10633
10651
