Protoss_Gateway 1 3322
Protoss_Assimilator 1 3148
Protoss_Cybernetics_Core 1 4311
Protoss_Zealot 2 8263
Protoss_Dragoon 6 10557
Protoss_Robotics_Facility 1 7185
Protoss_Shuttle 1 8005
Protoss_Robotics_Support_Bay 1 7601
Protoss_Reaver 1 9303
Protoss_Observatory 1 9149
Protoss_Nexus 1 11752
Protoss_Scarab 5 9969
Protoss_Observer 1 10425
11752
