Protoss_Gateway 2 6718
Protoss_Assimilator 1 3451
Protoss_Cybernetics_Core 1 4568
Protoss_Dragoon 7 11153
Protoss_Robotics_Facility 1 7882
Protoss_Zealot 4 9101
Protoss_Shuttle 1 8819
Protoss_Observatory 1 8423
Protoss_Observer 2 10107
Protoss_Nexus 2 12327
12327
