Protoss_Gateway 2 7889
Protoss_Assimilator 1 3229
Protoss_Cybernetics_Core 1 4251
Protoss_Dragoon 9 11097
Protoss_Robotics_Facility 1 7485
Protoss_Zealot 4 8969
Protoss_Shuttle 1 8333
Protoss_Observatory 1 8035
Protoss_Observer 1 9483
Protoss_Nexus 1 12471
12471
