Protoss_Gateway 2 5453
Protoss_Assimilator 1 3111
Protoss_Zealot 1 3789
Protoss_Cybernetics_Core 1 5090
Protoss_Dragoon 12 10775
Protoss_Nexus 1 10229
Protoss_Robotics_Facility 1 10315
Protoss_Observatory 1 10509
10775
