Protoss_Gateway 4 10678
Protoss_Assimilator 1 3400
Protoss_Cybernetics_Core 1 4629
Protoss_Dragoon 12 11200
Protoss_Robotics_Facility 1 7421
Protoss_Observatory 1 7538
Protoss_Observer 2 10886
Protoss_Citadel_of_Adun 1 10713
11200
