Protoss_Gateway 4 10633
Protoss_Assimilator 1 3193
Protoss_Cybernetics_Core 1 4303
Protoss_Dragoon 11 10533
Protoss_Nexus 1 8891
Protoss_Zealot 1 8197
Protoss_Robotics_Facility 1 10590
10633
