Protoss_Forge 2 10365
Protoss_Nexus 1 6777
Protoss_Photon_Cannon 4 9001
Protoss_Gateway 3 9868
Protoss_Zealot 7 10841
Protoss_Assimilator 1 8625
Protoss_Cybernetics_Core 1 10318
Protoss_Citadel_of_Adun 1 11391
11391
