Protoss_Gateway 3 11381
Protoss_Assimilator 2 10530
Protoss_Cybernetics_Core 1 4311
Protoss_Dragoon 7 10619
Protoss_Citadel_of_Adun 1 6357
Protoss_Templar_Archives 1 7383
Protoss_Dark_Templar 4 9043
Protoss_Nexus 1 10395
11381
