Protoss_Nexus 1 5414
Protoss_Gateway 4 9360
Protoss_Assimilator 2 7485
Protoss_Cybernetics_Core 1 5397
Protoss_Zealot 3 10207
Protoss_Dragoon 14 11109
Protoss_Robotics_Facility 1 9108
Protoss_Citadel_of_Adun 1 9506
Protoss_Observatory 1 9223
Protoss_Observer 2 10725
Protoss_Stargate 1 10842
Protoss_Templar_Archives 1 10703
11109
