Protoss_Gateway 2 11339
Protoss_Assimilator 1 3223
Protoss_Cybernetics_Core 1 4421
Protoss_Zealot 3 10197
Protoss_Dragoon 6 9443
Protoss_Robotics_Facility 1 7335
Protoss_Observatory 1 7566
Protoss_Nexus 1 10015
Protoss_Observer 1 8451
Protoss_Shuttle 1 9533
Protoss_Robotics_Support_Bay 1 9249
Protoss_Reaver 1 10789
11339
