Protoss_Gateway 3 9091
Protoss_Assimilator 1 3203
Protoss_Cybernetics_Core 1 4423
Protoss_Dragoon 6 8633
Protoss_Robotics_Facility 1 7195
Protoss_Observatory 1 7368
Protoss_Citadel_of_Adun 1 8233
Protoss_Observer 3 10493
Protoss_Zealot 8 10851
10851
