Protoss_Gateway 3 10382
Protoss_Assimilator 1 3610
Protoss_Cybernetics_Core 1 4867
Protoss_Robotics_Facility 1 6381
Protoss_Dragoon 2 7741
Protoss_Shuttle 1 7216
Protoss_Citadel_of_Adun 1 7564
Protoss_Templar_Archives 1 8577
Protoss_Dark_Templar 6 11178
Protoss_Nexus 1 11568
11568
