Protoss_Gateway 2 7972
Protoss_Assimilator 2 10429
Protoss_Zealot 2 4581
Protoss_Cybernetics_Core 1 4803
Protoss_Dragoon 11 11181
Protoss_Robotics_Facility 1 7573
Protoss_Nexus 1 10017
Protoss_Observatory 1 8233
Protoss_Observer 2 9965
Protoss_Citadel_of_Adun 1 9999
11181
