Protoss_Gateway 2 7054
Protoss_Assimilator 2 10182
Protoss_Zealot 3 5087
Protoss_Cybernetics_Core 1 5138
Protoss_Citadel_of_Adun 1 6351
Protoss_Dragoon 9 10967
Protoss_Nexus 1 10143
Protoss_Robotics_Facility 1 9905
Protoss_Observatory 1 10021
10967
