Protoss_Nexus 2 12635
Protoss_Gateway 4 9855
Protoss_Assimilator 2 7333
Protoss_Cybernetics_Core 1 5603
Protoss_Zealot 2 5555
Protoss_Dragoon 8 9897
Protoss_Robotics_Facility 2 10281
Protoss_Citadel_of_Adun 1 9502
Protoss_Observatory 1 10398
12635
