Protoss_Nexus 1 5507
Protoss_Gateway 4 10217
Protoss_Assimilator 2 8520
Protoss_Zealot 5 10291
Protoss_Cybernetics_Core 1 5747
Protoss_Dragoon 7 9779
Protoss_Robotics_Facility 1 8580
Protoss_Observatory 1 8847
Protoss_Observer 3 10819
10819
