Protoss_Gateway 4 10381
Protoss_Assimilator 1 3315
Protoss_Cybernetics_Core 1 4403
Protoss_Dragoon 10 10477
Protoss_Robotics_Facility 1 7266
Protoss_Observatory 1 7351
Protoss_Observer 2 8725
Protoss_Nexus 1 10947
Protoss_Citadel_of_Adun 1 10317
Protoss_Shuttle 1 11065
11065
