Protoss_Gateway 3 8966
Protoss_Assimilator 1 3202
Protoss_Cybernetics_Core 1 4368
Protoss_Zealot 1 4031
Protoss_Dragoon 11 10879
Protoss_Nexus 1 8825
Protoss_Robotics_Facility 1 8597
Protoss_Observatory 1 9012
Protoss_Observer 2 10595
10879
