Protoss_Gateway 2 6815
Protoss_Assimilator 1 3510
Protoss_Cybernetics_Core 1 4594
Protoss_Dragoon 8 9260
Protoss_Robotics_Facility 1 8149
Protoss_Observatory 1 8364
Protoss_Observer 1 9151
Protoss_Zealot 3 10546
Protoss_Shuttle 1 10441
10546
