Protoss_Gateway 2 5234
Protoss_Assimilator 2 10443
Protoss_Cybernetics_Core 1 4349
Protoss_Dragoon 6 10619
Protoss_Citadel_of_Adun 1 6270
Protoss_Zealot 1 6027
Protoss_Robotics_Facility 1 7740
Protoss_Templar_Archives 1 7429
Protoss_Dark_Templar 3 10913
Protoss_Shuttle 1 8553
Protoss_Nexus 1 10295
Protoss_Stargate 1 9616
Protoss_Arbiter_Tribunal 1 11110
11110
