Protoss_Gateway 3 8751
Protoss_Assimilator 1 3203
Protoss_Cybernetics_Core 1 4458
Protoss_Robotics_Facility 1 5947
Protoss_Dragoon 9 10361
Protoss_Observatory 1 6349
Protoss_Observer 3 9213
Protoss_Nexus 1 9210
10361
