Protoss_Gateway 2 8643
Protoss_Assimilator 1 3423
Protoss_Cybernetics_Core 1 4500
Protoss_Zealot 1 4199
Protoss_Dragoon 6 9473
Protoss_Nexus 1 8749
Protoss_Citadel_of_Adun 1 8303
Protoss_Robotics_Facility 1 9587
Protoss_Templar_Archives 1 9407
Protoss_Shuttle 1 10385
Protoss_Dark_Templar 2 10295
10385
