Protoss_Gateway 3 9819
Protoss_Assimilator 1 3342
Protoss_Cybernetics_Core 1 4616
Protoss_Dragoon 8 10851
Protoss_Robotics_Facility 1 8857
Protoss_Observatory 1 8971
Protoss_Zealot 4 10231
Protoss_Shuttle 1 10546
Protoss_Observer 1 10111
10851
