Protoss_Gateway 6 11047
Protoss_Assimilator 1 3129
Protoss_Cybernetics_Core 1 4398
Protoss_Zealot 1 4087
Protoss_Dragoon 9 11139
Protoss_Nexus 1 9794
Protoss_Robotics_Facility 1 9422
Protoss_Observatory 1 9664
Protoss_Observer 1 10569
11139
