Protoss_Nexus 1 5401
Protoss_Gateway 4 11264
Protoss_Assimilator 2 7498
Protoss_Cybernetics_Core 1 5484
Protoss_Zealot 4 10237
Protoss_Dragoon 8 9693
Protoss_Robotics_Facility 1 8655
Protoss_Shuttle 1 9485
Protoss_Robotics_Support_Bay 1 9124
Protoss_Reaver 1 10691
Protoss_Observatory 1 10330
Protoss_Citadel_of_Adun 1 11350
11350
