Protoss_Gateway 3 10607
Protoss_Assimilator 1 3444
Protoss_Cybernetics_Core 1 4606
Protoss_Dragoon 6 9036
Protoss_Robotics_Facility 1 7009
Protoss_Observatory 1 7663
Protoss_Observer 3 9863
Protoss_Nexus 1 11318
Protoss_Zealot 2 10321
11318
