Protoss_Nexus 1 5969
Protoss_Forge 1 4393
Protoss_Photon_Cannon 7 10349
Protoss_Gateway 3 10243
Protoss_Assimilator 2 7981
Protoss_Cybernetics_Core 1 7633
Protoss_Citadel_of_Adun 1 8846
Protoss_Templar_Archives 1 9835
Protoss_Dark_Templar 3 10985
10985
