Protoss_Assimilator 1 3339
Protoss_Gateway 2 10633
Protoss_Cybernetics_Core 1 4813
Protoss_Zealot 1 4463
Protoss_Dragoon 6 11109
Protoss_Nexus 2 10023
Protoss_Robotics_Facility 1 9713
Protoss_Observatory 1 10396
11109
