Protoss_Gateway 4 9489
Protoss_Nexus 1 6042
Protoss_Zealot 4 10825
Protoss_Assimilator 1 4497
Protoss_Cybernetics_Core 1 5737
Protoss_Dragoon 11 10731
Protoss_Robotics_Facility 1 8924
Protoss_Observatory 1 9064
Protoss_Observer 1 9871
10825
