Protoss_Gateway 3 9505
Protoss_Assimilator 1 3306
Protoss_Cybernetics_Core 1 4306
Protoss_Dragoon 10 10981
Protoss_Nexus 1 8523
Protoss_Robotics_Facility 1 8181
Protoss_Observatory 1 8545
Protoss_Observer 2 9919
Protoss_Citadel_of_Adun 1 10589
10981
