Protoss_Gateway 2 10367
Protoss_Assimilator 1 3239
Protoss_Cybernetics_Core 1 4273
Protoss_Zealot 1 4027
Protoss_Dragoon 8 11105
Protoss_Robotics_Facility 1 7393
Protoss_Shuttle 1 8195
Protoss_Robotics_Support_Bay 1 7526
Protoss_Reaver 2 11303
Protoss_Nexus 1 11065
Protoss_Observatory 1 8941
Protoss_Observer 2 10485
11303
