Protoss_Gateway 2 7897
Protoss_Assimilator 1 3494
Protoss_Cybernetics_Core 1 4702
Protoss_Dragoon 8 10606
Protoss_Robotics_Facility 2 11602
Protoss_Citadel_of_Adun 1 7778
Protoss_Templar_Archives 1 8806
Protoss_Dark_Templar 2 9611
11602
