Protoss_Gateway 4 10498
Protoss_Assimilator 1 3177
Protoss_Zealot 1 3819
Protoss_Cybernetics_Core 1 4863
Protoss_Dragoon 11 11031
Protoss_Robotics_Facility 1 7015
Protoss_Nexus 1 9283
Protoss_Observatory 1 7517
Protoss_Observer 3 9741
11031
