Protoss_Gateway 2 11278
Protoss_Assimilator 2 10816
Protoss_Cybernetics_Core 1 4297
Protoss_Dragoon 7 10983
Protoss_Robotics_Facility 1 7137
Protoss_Observatory 1 7225
Protoss_Nexus 1 9763
Protoss_Observer 2 10807
Protoss_Zealot 1 8085
Protoss_Shuttle 1 9105
Protoss_Robotics_Support_Bay 1 8966
Protoss_Reaver 1 10475
11278
