Protoss_Gateway 2 11000
Protoss_Assimilator 1 3503
Protoss_Cybernetics_Core 1 4598
Protoss_Dragoon 5 10531
Protoss_Stargate 1 7746
Protoss_Scout 1 9131
Protoss_Fleet_Beacon 1 9183
Protoss_Carrier 1 12276
Protoss_Shield_Battery 1 10610
12276
