Protoss_Gateway 3 9768
Protoss_Assimilator 1 3339
Protoss_Cybernetics_Core 1 4375
Protoss_Dragoon 10 10937
Protoss_Robotics_Facility 1 7316
Protoss_Observatory 1 7430
Protoss_Nexus 1 9964
Protoss_Observer 3 9427
10937
