Protoss_Gateway 3 6272
Protoss_Assimilator 2 4634
Protoss_Zealot 2 5857
Protoss_Cybernetics_Core 1 6091
Protoss_Dragoon 6 9171
Protoss_Nexus 2 12409
Protoss_Robotics_Facility 1 9477
Protoss_Shuttle 1 10365
Protoss_Robotics_Support_Bay 1 10076
Protoss_Observatory 1 10543
Protoss_Reaver 1 11573
12409
