Protoss_Gateway 4 10794
Protoss_Assimilator 1 3130
Protoss_Cybernetics_Core 1 4346
Protoss_Dragoon 4 8205
Protoss_Nexus 1 8513
Protoss_Robotics_Facility 1 8025
Protoss_Shuttle 1 8979
Protoss_Robotics_Support_Bay 1 8545
Protoss_Zealot 2 9135
Protoss_Reaver 1 10121
Protoss_Observatory 1 9529
Protoss_Citadel_of_Adun 1 10445
Protoss_Observer 1 10453
Protoss_Templar_Archives 1 11429
11429
