Protoss_Gateway 2 7163
Protoss_Assimilator 1 3155
Protoss_Cybernetics_Core 1 4209
Protoss_Dragoon 8 10621
Protoss_Robotics_Facility 1 7025
Protoss_Observatory 1 7228
Protoss_Observer 2 10835
Protoss_Nexus 2 12879
Protoss_Zealot 4 9615
Protoss_Shuttle 1 9863
12879
