Protoss_Nexus 2 12579
Protoss_Gateway 2 6990
Protoss_Assimilator 2 7371
Protoss_Cybernetics_Core 1 5200
Protoss_Zealot 1 4831
Protoss_Dragoon 10 10419
Protoss_Robotics_Facility 1 8859
Protoss_Citadel_of_Adun 1 9266
Protoss_Observatory 1 9031
Protoss_Observer 2 10415
Protoss_Stargate 1 10669
Protoss_Templar_Archives 1 10491
12579
