Protoss_Gateway 2 6001
Protoss_Assimilator 1 3288
Protoss_Cybernetics_Core 1 4320
Protoss_Zealot 3 10019
Protoss_Dragoon 8 11161
Protoss_Nexus 1 8910
Protoss_Robotics_Facility 1 8377
Protoss_Shuttle 1 9361
Protoss_Robotics_Support_Bay 1 9218
Protoss_Reaver 1 10707
Protoss_Observatory 1 9944
11161
