Protoss_Gateway 2 10304
Protoss_Assimilator 1 3336
Protoss_Zealot 3 5239
Protoss_Cybernetics_Core 1 5253
Protoss_Dragoon 7 11175
Protoss_Robotics_Facility 1 8664
Protoss_Nexus 1 10315
Protoss_Observatory 1 8837
Protoss_Observer 1 9631
11175
