Protoss_Gateway 2 6346
Protoss_Assimilator 2 9987
Protoss_Cybernetics_Core 1 4565
Protoss_Zealot 1 4399
Protoss_Dragoon 10 10745
Protoss_Nexus 1 10178
Protoss_Citadel_of_Adun 1 9724
Protoss_Templar_Archives 1 11169
Protoss_Robotics_Facility 1 11869
11869
