Protoss_Gateway 2 9011
Protoss_Assimilator 2 9973
Protoss_Cybernetics_Core 1 4333
Protoss_Zealot 2 9993
Protoss_Dragoon 6 9245
Protoss_Nexus 1 9068
Protoss_Robotics_Facility 1 8899
Protoss_Shuttle 1 9823
Protoss_Robotics_Support_Bay 1 9387
Protoss_Reaver 1 10965
Protoss_Observatory 1 10528
10965
