Protoss_Nexus 2 12615
Protoss_Gateway 2 6035
Protoss_Assimilator 2 7957
Protoss_Cybernetics_Core 1 5670
Protoss_Dragoon 11 10629
Protoss_Robotics_Facility 1 8739
Protoss_Shuttle 1 9549
Protoss_Observatory 1 8955
Protoss_Robotics_Support_Bay 1 9699
Protoss_Observer 2 10853
Protoss_Reaver 1 11605
12615
