Protoss_Assimilator 1 2704
Protoss_Gateway 2 8358
Protoss_Cybernetics_Core 1 4625
Protoss_Dragoon 7 11025
Protoss_Citadel_of_Adun 1 6571
Protoss_Robotics_Facility 1 7775
Protoss_Templar_Archives 1 7923
Protoss_Shuttle 1 8595
Protoss_Dark_Templar 4 11131
Protoss_Nexus 1 11493
Protoss_Observatory 1 9533
Protoss_Observer 1 10933
11493
