Protoss_Gateway 3 10687
Protoss_Assimilator 1 3235
Protoss_Zealot 2 4851
Protoss_Cybernetics_Core 1 4835
Protoss_Dragoon 11 10997
Protoss_Robotics_Facility 1 7550
Protoss_Observatory 1 7633
Protoss_Observer 2 9603
Protoss_Nexus 1 11439
11439
