Protoss_Gateway 3 9139
Protoss_Assimilator 1 3115
Protoss_Cybernetics_Core 1 4332
Protoss_Dragoon 8 10057
Protoss_Robotics_Facility 1 7516
Protoss_Nexus 2 12503
Protoss_Observatory 1 7670
Protoss_Observer 4 10493
12503
