Protoss_Nexus 2 12369
Protoss_Gateway 2 5687
Protoss_Assimilator 2 8041
Protoss_Cybernetics_Core 1 5526
Protoss_Zealot 3 10795
Protoss_Dragoon 8 9669
Protoss_Robotics_Facility 1 8615
Protoss_Shuttle 1 9417
Protoss_Robotics_Support_Bay 2 9097
Protoss_Reaver 1 10597
Protoss_Observatory 1 9718
Protoss_Observer 1 10929
12369
