Protoss_Nexus 1 5473
Protoss_Gateway 4 8553
Protoss_Assimilator 1 4245
Protoss_Cybernetics_Core 1 5459
Protoss_Zealot 1 5635
Protoss_Dragoon 16 10833
Protoss_Robotics_Facility 1 10805
10833
