Protoss_Nexus 2 12094
Protoss_Gateway 2 5667
Protoss_Assimilator 1 4237
Protoss_Cybernetics_Core 1 5401
Protoss_Zealot 2 5533
Protoss_Dragoon 7 9903
Protoss_Robotics_Facility 1 10158
Protoss_Observatory 1 10327
12094
