Protoss_Gateway 1 3415
Protoss_Assimilator 1 3443
Protoss_Cybernetics_Core 1 4616
Protoss_Dragoon 5 11126
Protoss_Stargate 1 7545
Protoss_Fleet_Beacon 1 8463
Protoss_Shield_Battery 1 8151
Protoss_Zealot 1 9876
11126
