Protoss_Gateway 2 8958
Protoss_Assimilator 1 3403
Protoss_Cybernetics_Core 2 10522
Protoss_Zealot 3 10369
Protoss_Robotics_Facility 1 6253
Protoss_Dragoon 2 6943
Protoss_Shuttle 1 7057
Protoss_Robotics_Support_Bay 1 6691
Protoss_Reaver 2 9513
Protoss_Scarab 15 9996
10522
