Protoss_Gateway 2 8227
Protoss_Assimilator 1 3391
Protoss_Cybernetics_Core 1 4462
Protoss_Dragoon 9 10791
Protoss_Robotics_Facility 1 8018
Protoss_Observatory 1 8123
Protoss_Observer 2 10103
Protoss_Shuttle 1 9991
Protoss_Zealot 2 9797
Protoss_Nexus 1 12638
12638
