Protoss_Nexus 1 5429
Protoss_Gateway 4 10549
Protoss_Assimilator 2 8047
Protoss_Cybernetics_Core 1 5457
Protoss_Zealot 1 5385
Protoss_Dragoon 6 8301
Protoss_Citadel_of_Adun 1 8029
Protoss_Robotics_Facility 1 9641
Protoss_Templar_Archives 1 9741
Protoss_Shuttle 1 10519
Protoss_Dark_Templar 2 10493
Protoss_Stargate 1 11015
Protoss_Observatory 1 10111
11015
