Protoss_Gateway 4 11325
Protoss_Assimilator 1 3121
Protoss_Cybernetics_Core 1 4217
Protoss_Dragoon 12 10591
Protoss_Nexus 2 12016
Protoss_Robotics_Facility 1 8691
Protoss_Observatory 1 8907
Protoss_Observer 3 10879
12016
