Protoss_Gateway 2 6097
Protoss_Assimilator 1 3300
Protoss_Cybernetics_Core 1 4363
Protoss_Zealot 1 4103
Protoss_Dragoon 10 10501
Protoss_Nexus 1 10133
Protoss_Robotics_Facility 1 9695
Protoss_Observatory 1 9850
Protoss_Observer 1 10779
10779
