Protoss_Gateway 3 9215
Protoss_Assimilator 2 10949
Protoss_Zealot 1 3755
Protoss_Cybernetics_Core 1 4495
Protoss_Dragoon 12 11075
Protoss_Nexus 1 9461
Protoss_Robotics_Facility 1 8889
Protoss_Observatory 1 9164
Protoss_Observer 2 10543
11075
