Protoss_Nexus 1 5429
Protoss_Gateway 2 5663
Protoss_Assimilator 2 9170
Protoss_Cybernetics_Core 1 5519
Protoss_Zealot 1 5411
Protoss_Dragoon 12 10977
Protoss_Robotics_Facility 1 9743
Protoss_Shuttle 1 10603
Protoss_Robotics_Support_Bay 1 10033
10977
