Protoss_Gateway 3 9781
Protoss_Zealot 2 5285
Protoss_Nexus 1 6479
Protoss_Assimilator 2 7999
Protoss_Cybernetics_Core 1 5571
Protoss_Dragoon 11 10907
Protoss_Robotics_Facility 1 8455
Protoss_Observatory 1 8569
Protoss_Observer 3 10571
Protoss_Citadel_of_Adun 1 10651
10907
