Protoss_Gateway 2 8156
Protoss_Assimilator 1 2268
Protoss_Cybernetics_Core 1 3201
Protoss_Dragoon 6 9421
Protoss_Stargate 1 5612
Protoss_Fleet_Beacon 1 6819
Protoss_Carrier 1 7806
Protoss_Robotics_Facility 1 8568
Protoss_Forge 1 9740
Protoss_Observatory 1 9894
Protoss_Interceptor 1 9946
9946
