Protoss_Gateway 2 8421
Protoss_Assimilator 1 3449
Protoss_Cybernetics_Core 1 4648
Protoss_Dragoon 7 9286
Protoss_Robotics_Facility 1 7927
Protoss_Observatory 1 8044
Protoss_Observer 1 8871
Protoss_Citadel_of_Adun 1 9471
Protoss_Shuttle 1 10051
Protoss_Zealot 4 10428
10428
