Protoss_Gateway 4 9700
Protoss_Assimilator 1 3433
Protoss_Cybernetics_Core 1 4693
Protoss_Dragoon 13 11106
Protoss_Nexus 1 8653
Protoss_Robotics_Facility 1 8104
Protoss_Observatory 1 8360
Protoss_Observer 2 10936
11106
