Protoss_Gateway 2 8579
Protoss_Assimilator 1 3478
Protoss_Cybernetics_Core 1 4580
Protoss_Dragoon 10 10980
Protoss_Robotics_Facility 1 6858
Protoss_Observatory 1 7051
Protoss_Observer 3 9986
Protoss_Shuttle 1 10591
10980
