Protoss_Gateway 2 7703
Protoss_Assimilator 1 3438
Protoss_Cybernetics_Core 1 4527
Protoss_Dragoon 3 10536
Protoss_Robotics_Facility 1 6532
Protoss_Citadel_of_Adun 1 6751
Protoss_Templar_Archives 1 7759
Protoss_Observatory 1 7357
Protoss_Observer 1 8221
Protoss_Dark_Templar 4 9761
Protoss_Shuttle 1 9303
10536
