Protoss_Gateway 3 10623
Protoss_Assimilator 1 3604
Protoss_Cybernetics_Core 1 5138
Protoss_Dragoon 3 8226
Protoss_Robotics_Facility 1 7265
Protoss_Citadel_of_Adun 1 7055
Protoss_Observatory 1 7397
Protoss_Templar_Archives 1 8268
Protoss_Observer 1 8241
Protoss_Zealot 1 8401
Protoss_Shuttle 1 9396
Protoss_Dark_Templar 4 10358
10623
