Protoss_Gateway 3 10592
Protoss_Assimilator 1 3423
Protoss_Cybernetics_Core 1 4473
Protoss_Dragoon 6 11046
Protoss_Stargate 1 7561
Protoss_Fleet_Beacon 1 8586
Protoss_Carrier 1 11496
Protoss_Robotics_Facility 1 10713
11496
