Protoss_Gateway 2 7288
Protoss_Assimilator 1 3369
Protoss_Cybernetics_Core 1 4391
Protoss_Dragoon 6 8793
Protoss_Robotics_Facility 1 6589
Protoss_Observatory 1 6794
Protoss_Observer 2 9978
Protoss_Shuttle 1 9556
Protoss_Zealot 4 10291
10291
