Protoss_Gateway 1 3438
Protoss_Assimilator 1 3522
Protoss_Cybernetics_Core 1 4638
Protoss_Robotics_Facility 1 6474
Protoss_Dragoon 7 11067
Protoss_Shuttle 2 10886
Protoss_Robotics_Support_Bay 1 6803
Protoss_Reaver 1 8831
Protoss_Observatory 1 9245
Protoss_Nexus 1 12324
12324
