Protoss_Gateway 4 11405
Protoss_Assimilator 1 3158
Protoss_Cybernetics_Core 1 4299
Protoss_Robotics_Facility 1 5913
Protoss_Dragoon 9 9738
Protoss_Shuttle 1 6771
Protoss_Observatory 1 6375
Protoss_Observer 3 10091
Protoss_Nexus 1 11868
11868
