Protoss_Gateway 2 9175
Protoss_Assimilator 1 3353
Protoss_Cybernetics_Core 1 4438
Protoss_Dragoon 10 11076
Protoss_Robotics_Facility 1 7236
Protoss_Shuttle 1 8066
Protoss_Robotics_Support_Bay 1 7707
Protoss_Reaver 1 9211
Protoss_Observatory 1 8660
Protoss_Observer 1 9543
11076
