Protoss_Gateway 4 11191
Protoss_Assimilator 1 3370
Protoss_Cybernetics_Core 1 4409
Protoss_Dragoon 9 9411
Protoss_Robotics_Facility 1 10173
Protoss_Nexus 1 11388
Protoss_Citadel_of_Adun 1 10363
Protoss_Zealot 2 10546
Protoss_Observatory 1 10315
11388
