Protoss_Gateway 3 10288
Protoss_Assimilator 1 3248
Protoss_Cybernetics_Core 1 4415
Protoss_Dragoon 6 10479
Protoss_Robotics_Facility 1 7583
Protoss_Observatory 1 7771
Protoss_Nexus 1 10288
Protoss_Observer 1 8566
10479
