Protoss_Gateway 3 10341
Protoss_Assimilator 1 3433
Protoss_Cybernetics_Core 1 4493
Protoss_Dragoon 12 10717
Protoss_Robotics_Facility 1 8538
Protoss_Observatory 1 8708
Protoss_Observer 1 9536
10717
