Protoss_Gateway 3 10218
Protoss_Assimilator 1 3392
Protoss_Cybernetics_Core 1 4358
Protoss_Zealot 1 4231
Protoss_Dragoon 9 11176
Protoss_Robotics_Facility 1 8521
Protoss_Nexus 1 10688
Protoss_Observatory 1 8723
Protoss_Observer 3 10780
11176
