Protoss_Gateway 4 11233
Protoss_Assimilator 1 3459
Protoss_Cybernetics_Core 1 4658
Protoss_Dragoon 7 9613
Protoss_Robotics_Facility 1 7536
Protoss_Observatory 1 7643
Protoss_Zealot 2 10146
11233
