Protoss_Gateway 1 3483
Protoss_Assimilator 1 3483
Protoss_Cybernetics_Core 1 4499
Protoss_Dragoon 4 8206
Protoss_Robotics_Facility 1 6527
Protoss_Observatory 1 6660
Protoss_Observer 2 8386
Protoss_Robotics_Support_Bay 1 8424
Protoss_Shuttle 1 9468
Protoss_Reaver 1 10610
Protoss_Zealot 1 10056
Protoss_Nexus 1 11991
11991
