Protoss_Gateway 2 9497
Protoss_Assimilator 1 3454
Protoss_Cybernetics_Core 1 4691
Protoss_Robotics_Facility 1 6424
Protoss_Zealot 3 10290
Protoss_Dragoon 5 10251
Protoss_Shuttle 1 7236
Protoss_Observatory 1 6672
Protoss_Robotics_Support_Bay 1 7101
Protoss_Observer 1 7658
Protoss_Reaver 1 8980
10290
