Protoss_Gateway 2 7675
Protoss_Assimilator 1 3438
Protoss_Cybernetics_Core 1 4638
Protoss_Dragoon 3 11026
Protoss_Citadel_of_Adun 1 6891
Protoss_Robotics_Facility 1 7958
Protoss_Templar_Archives 1 7913
Protoss_Dark_Templar 1 8841
Protoss_Observatory 1 8469
11026
