Protoss_Gateway 2 7457
Protoss_Assimilator 1 3438
Protoss_Cybernetics_Core 1 4648
Protoss_Robotics_Facility 1 6355
Protoss_Dragoon 9 10541
Protoss_Observatory 1 6530
Protoss_Observer 5 10866
Protoss_Shuttle 1 9725
10866
