Protoss_Gateway 3 10523
Protoss_Assimilator 1 3438
Protoss_Cybernetics_Core 1 4468
Protoss_Dragoon 7 10678
Protoss_Robotics_Facility 1 7972
Protoss_Shuttle 1 9091
Protoss_Nexus 1 10867
Protoss_Observatory 1 9014
Protoss_Observer 1 10061
10867
