Protoss_Gateway 2 9597
Protoss_Assimilator 1 3363
Protoss_Cybernetics_Core 1 4398
Protoss_Dragoon 5 10486
Protoss_Robotics_Facility 1 6462
Protoss_Shuttle 1 7271
Protoss_Robotics_Support_Bay 1 6779
Protoss_Zealot 2 7956
Protoss_Reaver 1 8439
Protoss_Observatory 1 7847
Protoss_Observer 1 8864
Protoss_Scarab 2 9045
Protoss_Nexus 1 12661
12661
