Protoss_Gateway 2 8248
Protoss_Assimilator 1 3428
Protoss_Cybernetics_Core 1 4503
Protoss_Dragoon 11 11068
Protoss_Robotics_Facility 1 7473
Protoss_Observatory 1 7737
Protoss_Observer 1 8531
Protoss_Nexus 1 11453
11453
