Protoss_Gateway 3 8911
Protoss_Assimilator 1 3285
Protoss_Cybernetics_Core 1 4469
Protoss_Dragoon 12 10686
Protoss_Robotics_Facility 1 7721
Protoss_Observatory 1 7884
Protoss_Observer 2 9268
10686
