Protoss_Gateway 3 8598
Protoss_Assimilator 1 3268
Protoss_Cybernetics_Core 1 4419
Protoss_Robotics_Facility 1 6013
Protoss_Dragoon 10 11131
Protoss_Shuttle 1 6821
Protoss_Observatory 1 6436
Protoss_Observer 1 7276
11131
