Protoss_Gateway 3 9190
Protoss_Assimilator 1 3416
Protoss_Cybernetics_Core 1 4505
Protoss_Dragoon 7 9866
Protoss_Robotics_Facility 1 6499
Protoss_Shuttle 1 7306
Protoss_Observatory 1 6804
Protoss_Observer 5 10511
Protoss_Nexus 2 12121
12121
