Protoss_Gateway 2 7405
Protoss_Assimilator 1 3420
Protoss_Cybernetics_Core 1 4598
Protoss_Dragoon 8 9121
Protoss_Robotics_Facility 1 9853
Protoss_Nexus 1 11518
Protoss_Shuttle 1 10736
11518
