Protoss_Gateway 3 10231
Protoss_Assimilator 1 3489
Protoss_Cybernetics_Core 1 4558
Protoss_Dragoon 7 9688
Protoss_Robotics_Facility 1 6638
Protoss_Observatory 1 6733
Protoss_Observer 2 9461
Protoss_Shuttle 1 9146
Protoss_Citadel_of_Adun 1 10267
Protoss_Zealot 2 10200
Protoss_Templar_Archives 1 11318
11318
