Protoss_Gateway 2 10378
Protoss_Assimilator 2 3936
Protoss_Cybernetics_Core 1 4943
Protoss_Dragoon 2 6453
Protoss_Robotics_Facility 1 7663
Protoss_Forge 1 7018
Protoss_Photon_Cannon 1 8070
Protoss_Shuttle 1 8476
Protoss_Zealot 2 9006
Protoss_Robotics_Support_Bay 1 8205
Protoss_Reaver 1 9706
Protoss_Citadel_of_Adun 1 9971
10378
