Protoss_Gateway 2 4998
Protoss_Assimilator 1 3331
Protoss_Cybernetics_Core 1 4703
Protoss_Dragoon 7 8173
Protoss_Citadel_of_Adun 1 7638
Protoss_Templar_Archives 1 8953
Protoss_Nexus 1 11088
Protoss_Dark_Templar 3 11096
Protoss_Robotics_Facility 1 11283
11283
