Protoss_Gateway 4 9916
Protoss_Assimilator 1 3628
Protoss_Cybernetics_Core 1 4899
Protoss_Dragoon 5 10768
Protoss_Robotics_Facility 1 6886
Protoss_Observatory 1 7106
Protoss_Observer 2 8581
10768
