Protoss_Gateway 3 9739
Protoss_Assimilator 1 3403
Protoss_Cybernetics_Core 1 4447
Protoss_Dragoon 7 9681
Protoss_Robotics_Facility 1 6423
Protoss_Observatory 1 6571
Protoss_Nexus 1 9163
Protoss_Observer 3 9591
Protoss_Zealot 3 10356
Protoss_Shuttle 1 10673
10673
