Protoss_Gateway 3 8715
Protoss_Assimilator 1 3436
Protoss_Cybernetics_Core 1 4609
Protoss_Dragoon 12 11071
Protoss_Robotics_Facility 1 8135
Protoss_Observatory 1 8387
Protoss_Observer 2 10284
Protoss_Citadel_of_Adun 1 10809
11071
