Protoss_Nexus 1 5741
Protoss_Gateway 3 6938
Protoss_Assimilator 2 8740
Protoss_Cybernetics_Core 1 5902
Protoss_Zealot 1 5971
Protoss_Dragoon 11 11146
Protoss_Robotics_Facility 1 9157
Protoss_Shuttle 1 10196
11146
