Protoss_Gateway 1 3512
Protoss_Assimilator 1 3428
Protoss_Cybernetics_Core 1 4786
Protoss_Robotics_Facility 1 6683
Protoss_Zealot 1 6091
Protoss_Robotics_Support_Bay 1 7506
Protoss_Dragoon 2 9548
Protoss_Shield_Battery 1 8837
9548
