Protoss_Assimilator 1 2699
Protoss_Gateway 3 9833
Protoss_Cybernetics_Core 1 4668
Protoss_Robotics_Facility 1 6178
Protoss_Dragoon 6 10120
Protoss_Shuttle 1 6986
Protoss_Observatory 1 7738
Protoss_Observer 3 9825
Protoss_Citadel_of_Adun 1 9401
Protoss_Templar_Archives 1 10638
Protoss_Zealot 1 10241
10638
