Protoss_Assimilator 1 2992
Protoss_Gateway 3 10098
Protoss_Cybernetics_Core 1 4578
Protoss_Robotics_Facility 1 6053
Protoss_Shuttle 1 6866
Protoss_Robotics_Support_Bay 1 6189
Protoss_Reaver 2 9060
Protoss_Forge 1 7628
Protoss_Shield_Battery 1 8353
Protoss_Dragoon 6 11142
Protoss_Observatory 1 10254
11142
