Protoss_Gateway 3 10831
Protoss_Assimilator 1 3324
Protoss_Cybernetics_Core 1 4373
Protoss_Dragoon 9 9008
Protoss_Citadel_of_Adun 1 8285
Protoss_Templar_Archives 1 9293
Protoss_Dark_Templar 2 10051
Protoss_Nexus 1 11859
Protoss_Zealot 2 10771
11859
