Protoss_Gateway 2 9309
Protoss_Assimilator 1 3367
Protoss_Cybernetics_Core 1 4603
Protoss_Dragoon 7 10642
Protoss_Robotics_Facility 1 6600
Protoss_Shuttle 1 7411
Protoss_Observatory 1 7243
Protoss_Observer 2 10836
Protoss_Nexus 1 10451
Protoss_Robotics_Support_Bay 1 10194
Protoss_Zealot 1 10703
10836
