Protoss_Gateway 2 4953
Protoss_Assimilator 1 3183
Protoss_Cybernetics_Core 1 4444
Protoss_Dragoon 7 9823
Protoss_Robotics_Facility 1 8223
Protoss_Zealot 4 8981
Protoss_Observatory 1 8333
Protoss_Shuttle 1 9066
Protoss_Observer 1 9488
9823
