Protoss_Gateway 3 9165
Protoss_Assimilator 1 3238
Protoss_Cybernetics_Core 1 4555
Protoss_Dragoon 12 11122
Protoss_Robotics_Facility 1 6848
Protoss_Shuttle 1 7656
Protoss_Observatory 1 6993
Protoss_Observer 1 8078
Protoss_Shield_Battery 1 9394
Protoss_Citadel_of_Adun 1 10769
11122
