Protoss_Gateway 4 11006
Protoss_Assimilator 1 3174
Protoss_Cybernetics_Core 1 4293
Protoss_Dragoon 6 10561
Protoss_Robotics_Facility 1 7718
Protoss_Observatory 1 8076
Protoss_Nexus 2 10983
Protoss_Citadel_of_Adun 1 9198
Protoss_Observer 2 10341
Protoss_Templar_Archives 1 10402
11006
