Protoss_Gateway 2 5833
Protoss_Assimilator 1 3333
Protoss_Cybernetics_Core 1 4498
Protoss_Dragoon 11 10921
Protoss_Nexus 1 10263
Protoss_Robotics_Facility 1 10318
Protoss_Citadel_of_Adun 1 10617
Protoss_Observatory 1 10526
10921
