Protoss_Gateway 3 9282
Protoss_Assimilator 1 3278
Protoss_Cybernetics_Core 1 4514
Protoss_Dragoon 13 11008
Protoss_Robotics_Facility 1 7188
Protoss_Shuttle 1 7996
Protoss_Observatory 1 7345
Protoss_Observer 2 10471
Protoss_Shield_Battery 1 8898
11008
