Protoss_Gateway 3 9741
Protoss_Assimilator 1 3238
Protoss_Cybernetics_Core 1 4303
Protoss_Dragoon 5 10341
Protoss_Citadel_of_Adun 1 5932
Protoss_Templar_Archives 1 7007
Protoss_Dark_Templar 4 8518
Protoss_Robotics_Facility 1 9978
Protoss_Zealot 3 10951
Protoss_Shuttle 1 10926
Protoss_Observatory 1 10359
10951
