Protoss_Gateway 2 5612
Protoss_Assimilator 1 3228
Protoss_Cybernetics_Core 1 4348
Protoss_Dragoon 12 10636
Protoss_Robotics_Facility 1 9143
Protoss_Observatory 1 9384
Protoss_Nexus 1 12118
Protoss_Observer 1 10241
12118
