Protoss_Gateway 3 9478
Protoss_Assimilator 1 3247
Protoss_Cybernetics_Core 1 4378
Protoss_Robotics_Facility 1 6023
Protoss_Dragoon 9 10906
Protoss_Observatory 1 6133
Protoss_Shuttle 1 7021
Protoss_Observer 3 9231
10906
