Protoss_Gateway 2 5813
Protoss_Assimilator 2 3726
Protoss_Cybernetics_Core 1 4999
Protoss_Dragoon 7 10081
Protoss_Citadel_of_Adun 1 7399
Protoss_Templar_Archives 1 8439
Protoss_Dark_Templar 4 11031
11031
