Protoss_Gateway 2 7826
Protoss_Assimilator 1 3421
Protoss_Zealot 1 4075
Protoss_Cybernetics_Core 1 5552
Protoss_Dragoon 7 10037
Protoss_Robotics_Facility 1 8987
Protoss_Observatory 1 9227
Protoss_Shuttle 1 10443
Protoss_Observer 1 10865
10865
