Protoss_Gateway 1 3483
Protoss_Assimilator 1 3597
Protoss_Cybernetics_Core 1 4778
Protoss_Dragoon 3 7261
Protoss_Robotics_Facility 1 6798
Protoss_Shuttle 1 7996
Protoss_Robotics_Support_Bay 1 7461
Protoss_Zealot 2 8923
Protoss_Reaver 2 10261
Protoss_Observatory 1 9384
Protoss_Scarab 5 9968
Protoss_Observer 1 10593
10593
