Protoss_Gateway 2 5082
Protoss_Assimilator 1 3470
Protoss_Cybernetics_Core 1 4495
Protoss_Dragoon 10 10846
Protoss_Zealot 2 7363
Protoss_Robotics_Facility 1 8968
Protoss_Observatory 1 9113
Protoss_Observer 1 10266
Protoss_Nexus 1 12492
12492
