Protoss_Gateway 1 3513
Protoss_Assimilator 1 3365
Protoss_Cybernetics_Core 1 4644
Protoss_Dragoon 2 7511
Protoss_Robotics_Facility 1 6523
Protoss_Shuttle 1 7526
Protoss_Robotics_Support_Bay 1 7632
Protoss_Citadel_of_Adun 1 8698
Protoss_Reaver 1 9236
Protoss_Templar_Archives 1 9786
Protoss_Observatory 1 9123
Protoss_Scarab 4 9595
Protoss_Observer 1 9946
Protoss_Dark_Templar 1 10806
10806
