Protoss_Gateway 1 3577
Protoss_Assimilator 1 3664
Protoss_Cybernetics_Core 1 4741
Protoss_Dragoon 6 10263
Protoss_Robotics_Facility 1 7716
Protoss_Shuttle 1 8701
Protoss_Zealot 2 10775
Protoss_Robotics_Support_Bay 1 8264
Protoss_Reaver 2 11456
11456
