Protoss_Gateway 2 7328
Protoss_Assimilator 1 3512
Protoss_Cybernetics_Core 1 4695
Protoss_Dragoon 7 9304
Protoss_Robotics_Facility 1 6757
Protoss_Observatory 1 7037
Protoss_Observer 2 10171
Protoss_Nexus 2 12411
12411
