Protoss_Gateway 2 7013
Protoss_Assimilator 1 3454
Protoss_Cybernetics_Core 1 4603
Protoss_Dragoon 9 9726
Protoss_Robotics_Facility 1 8176
Protoss_Observatory 1 8507
Protoss_Observer 1 9461
Protoss_Zealot 3 10913
Protoss_Shuttle 1 10543
10913
