Protoss_Gateway 2 10201
Protoss_Assimilator 2 3674
Protoss_Zealot 2 5076
Protoss_Cybernetics_Core 1 5447
Protoss_Dragoon 5 9728
Protoss_Robotics_Facility 1 7075
Protoss_Shuttle 1 7886
Protoss_Robotics_Support_Bay 1 7598
Protoss_Reaver 2 10458
Protoss_Nexus 1 12708
12708
