Protoss_Gateway 2 6763
Protoss_Assimilator 1 3358
Protoss_Cybernetics_Core 1 4688
Protoss_Dragoon 9 9592
Protoss_Robotics_Facility 1 10270
Protoss_Nexus 1 11804
Protoss_Zealot 2 10251
Protoss_Observatory 1 10373
Protoss_Shuttle 1 11236
11804
