Protoss_Gateway 3 8364
Protoss_Assimilator 1 3521
Protoss_Cybernetics_Core 1 4613
Protoss_Dragoon 9 9796
Protoss_Robotics_Facility 1 7066
Protoss_Observatory 1 7356
Protoss_Observer 2 9591
Protoss_Nexus 1 11958
11958
