Protoss_Gateway 2 6708
Protoss_Assimilator 2 3808
Protoss_Cybernetics_Core 1 4893
Protoss_Zealot 2 10501
Protoss_Dragoon 5 10711
Protoss_Nexus 1 10743
Protoss_Robotics_Facility 1 11218
11218
