Protoss_Gateway 2 7227
Protoss_Assimilator 1 3438
Protoss_Cybernetics_Core 1 4538
Protoss_Dragoon 10 10951
Protoss_Robotics_Facility 1 6503
Protoss_Observatory 1 6863
Protoss_Observer 2 9471
Protoss_Shuttle 1 9311
Protoss_Nexus 1 11438
11438
