Protoss_Gateway 4 9794
Protoss_Assimilator 1 3274
Protoss_Cybernetics_Core 1 4413
Protoss_Robotics_Facility 1 6063
Protoss_Dragoon 9 10831
Protoss_Shuttle 1 6881
Protoss_Observatory 1 6278
Protoss_Observer 2 8031
Protoss_Nexus 1 11637
11637
