Protoss_Gateway 2 4308
Protoss_Zealot 3 8006
Protoss_Assimilator 1 4186
Protoss_Cybernetics_Core 1 5243
Protoss_Dragoon 4 9386
Protoss_Robotics_Facility 1 7800
Protoss_Citadel_of_Adun 1 8361
Protoss_Shuttle 1 8671
Protoss_Templar_Archives 1 9401
Protoss_Dark_Templar 4 10933
10933
