Protoss_Gateway 3 9521
Protoss_Assimilator 1 3355
Protoss_Cybernetics_Core 1 4650
Protoss_Dragoon 12 10434
Protoss_Robotics_Facility 1 7213
Protoss_Observatory 1 7380
Protoss_Observer 2 8943
Protoss_Nexus 1 12638
12638
