Protoss_Gateway 2 7610
Protoss_Assimilator 1 3568
Protoss_Cybernetics_Core 1 4637
Protoss_Dragoon 9 10443
Protoss_Robotics_Facility 1 6798
Protoss_Observatory 1 6995
Protoss_Observer 3 10331
Protoss_Nexus 1 12729
12729
