Protoss_Gateway 4 10818
Protoss_Assimilator 1 3481
Protoss_Cybernetics_Core 1 4563
Protoss_Dragoon 9 10373
Protoss_Robotics_Facility 1 6620
Protoss_Observatory 1 6795
Protoss_Observer 4 10808
Protoss_Nexus 1 11563
11563
