Protoss_Gateway 2 7249
Protoss_Assimilator 1 3363
Protoss_Cybernetics_Core 1 4626
Protoss_Dragoon 8 10671
Protoss_Robotics_Facility 1 7349
Protoss_Observatory 1 7534
Protoss_Observer 4 10786
Protoss_Nexus 2 11841
11841
