Protoss_Gateway 2 7000
Protoss_Assimilator 1 3461
Protoss_Cybernetics_Core 1 4559
Protoss_Dragoon 10 10741
Protoss_Citadel_of_Adun 1 6198
Protoss_Nexus 1 10082
Protoss_Robotics_Facility 1 9553
Protoss_Observatory 1 9868
Protoss_Observer 1 10646
10741
