Protoss_Gateway 2 9553
Protoss_Assimilator 1 3528
Protoss_Cybernetics_Core 1 4623
Protoss_Dragoon 8 11178
Protoss_Robotics_Facility 1 6641
Protoss_Shuttle 1 7531
Protoss_Robotics_Support_Bay 1 7291
Protoss_Reaver 2 9886
Protoss_Observatory 1 8621
Protoss_Scarab 5 9850
Protoss_Observer 1 10218
11178
