Protoss_Gateway 1 3393
Protoss_Assimilator 1 3311
Protoss_Cybernetics_Core 1 4549
Protoss_Dragoon 8 10724
Protoss_Robotics_Facility 1 7445
Protoss_Nexus 1 9224
Protoss_Observatory 1 7627
Protoss_Observer 3 10341
10724
