Protoss_Gateway 3 8409
Protoss_Assimilator 1 3369
Protoss_Cybernetics_Core 1 4486
Protoss_Dragoon 9 9605
Protoss_Robotics_Facility 1 7685
Protoss_Observatory 1 7818
Protoss_Observer 3 10227
Protoss_Nexus 1 12057
Protoss_Citadel_of_Adun 1 11209
Protoss_Shuttle 1 11309
12057
