Protoss_Gateway 2 7086
Protoss_Assimilator 1 3406
Protoss_Cybernetics_Core 1 4643
Protoss_Zealot 1 4361
Protoss_Dragoon 5 9696
Protoss_Robotics_Facility 1 6478
Protoss_Robotics_Support_Bay 1 7133
Protoss_Reaver 1 8711
Protoss_Nexus 2 12309
Protoss_Observatory 1 8661
Protoss_Observer 1 10756
12309
