Protoss_Gateway 2 7768
Protoss_Assimilator 1 3183
Protoss_Cybernetics_Core 1 4322
Protoss_Robotics_Facility 1 5893
Protoss_Zealot 5 10771
Protoss_Dragoon 7 9471
Protoss_Observatory 1 5996
Protoss_Observer 3 9811
Protoss_Shuttle 1 8639
Protoss_Nexus 1 12281
Protoss_Citadel_of_Adun 1 11373
12281
