Protoss_Gateway 2 8877
Protoss_Assimilator 1 3424
Protoss_Cybernetics_Core 1 4564
Protoss_Zealot 1 4216
Protoss_Dragoon 9 10801
Protoss_Robotics_Facility 1 8803
Protoss_Shuttle 1 9641
Protoss_Observatory 1 9103
Protoss_Observer 2 10841
Protoss_Robotics_Support_Bay 1 9908
10841
