Protoss_Gateway 2 8265
Protoss_Assimilator 1 3453
Protoss_Cybernetics_Core 1 4590
Protoss_Robotics_Facility 1 6253
Protoss_Dragoon 5 9021
Protoss_Observatory 1 6590
Protoss_Observer 1 7386
Protoss_Shuttle 1 8468
Protoss_Nexus 1 11345
Protoss_Zealot 2 9691
11345
