Protoss_Gateway 3 8361
Protoss_Assimilator 1 3423
Protoss_Cybernetics_Core 1 4548
Protoss_Dragoon 11 11171
Protoss_Robotics_Facility 1 8433
Protoss_Observatory 1 8646
Protoss_Observer 2 10099
Protoss_Nexus 1 12125
12125
