Protoss_Gateway 3 8220
Protoss_Assimilator 1 3274
Protoss_Zealot 1 3916
Protoss_Cybernetics_Core 1 4855
Protoss_Robotics_Facility 1 6548
Protoss_Dragoon 8 10456
Protoss_Observatory 1 6767
Protoss_Observer 4 10238
Protoss_Nexus 1 10498
Protoss_Shuttle 1 11320
11320
