Protoss_Gateway 3 7704
Protoss_Assimilator 1 3396
Protoss_Cybernetics_Core 1 4428
Protoss_Dragoon 6 10308
Protoss_Citadel_of_Adun 1 6273
Protoss_Templar_Archives 1 7374
Protoss_Dark_Templar 3 8456
Protoss_Robotics_Facility 1 11073
Protoss_Zealot 2 10561
11073
