Protoss_Gateway 3 7689
Protoss_Assimilator 1 3477
Protoss_Zealot 6 10643
Protoss_Cybernetics_Core 1 5183
Protoss_Dragoon 6 9213
Protoss_Robotics_Facility 1 6960
Protoss_Observatory 1 7070
Protoss_Shuttle 1 8101
Protoss_Observer 2 9583
Protoss_Nexus 1 11813
11813
