Protoss_Gateway 2 7438
Protoss_Assimilator 1 3305
Protoss_Cybernetics_Core 1 4448
Protoss_Dragoon 7 9097
Protoss_Robotics_Facility 1 6699
Protoss_Observatory 1 6801
Protoss_Observer 2 8201
Protoss_Nexus 2 12249
Protoss_Citadel_of_Adun 1 11153
12249
