Protoss_Gateway 3 7688
Protoss_Assimilator 1 3477
Protoss_Cybernetics_Core 1 4550
Protoss_Dragoon 8 9705
Protoss_Robotics_Facility 1 6565
Protoss_Observatory 1 6803
Protoss_Observer 2 8905
Protoss_Nexus 2 12467
12467
