Protoss_Gateway 3 11190
Protoss_Assimilator 1 3535
Protoss_Cybernetics_Core 1 4748
Protoss_Dragoon 9 10628
Protoss_Robotics_Facility 1 7443
Protoss_Observatory 1 7588
Protoss_Observer 2 9081
Protoss_Nexus 1 11188
11190
