Protoss_Gateway 2 9833
Protoss_Assimilator 1 3482
Protoss_Cybernetics_Core 1 4493
Protoss_Dragoon 8 11036
Protoss_Robotics_Facility 1 6193
Protoss_Zealot 2 6915
Protoss_Shuttle 1 7061
Protoss_Nexus 1 10565
Protoss_Observatory 1 8486
Protoss_Citadel_of_Adun 1 9724
Protoss_Observer 1 9406
Protoss_Templar_Archives 1 11035
11036
