Protoss_Gateway 3 10863
Protoss_Assimilator 1 3533
Protoss_Cybernetics_Core 1 4741
Protoss_Dragoon 10 10785
Protoss_Robotics_Facility 1 7313
Protoss_Observatory 1 7418
Protoss_Observer 2 9546
Protoss_Shuttle 1 11011
11011
