Protoss_Gateway 2 8161
Protoss_Assimilator 1 3438
Protoss_Cybernetics_Core 1 4488
Protoss_Dragoon 6 10521
Protoss_Stargate 1 7636
Protoss_Fleet_Beacon 1 8668
Protoss_Carrier 1 11701
Protoss_Robotics_Facility 1 10889
11701
