Protoss_Gateway 2 7331
Protoss_Assimilator 1 3512
Protoss_Cybernetics_Core 1 4710
Protoss_Dragoon 9 9966
Protoss_Robotics_Facility 1 7463
Protoss_Observatory 1 7675
Protoss_Observer 2 9395
Protoss_Shuttle 1 10243
Protoss_Nexus 1 12203
12203
