Protoss_Gateway 3 11419
Protoss_Assimilator 1 3438
Protoss_Cybernetics_Core 1 4479
Protoss_Zealot 3 10511
Protoss_Dragoon 6 8786
Protoss_Robotics_Facility 1 7694
Protoss_Observatory 1 7863
Protoss_Observer 2 9253
Protoss_Nexus 1 11816
Protoss_Shuttle 1 10776
11816
