Protoss_Gateway 2 7455
Protoss_Assimilator 1 3443
Protoss_Cybernetics_Core 1 4704
Protoss_Dragoon 11 11191
Protoss_Robotics_Facility 1 8168
Protoss_Observatory 1 8528
Protoss_Observer 2 10018
Protoss_Nexus 1 11539
11539
