Protoss_Gateway 2 7808
Protoss_Assimilator 1 3248
Protoss_Cybernetics_Core 1 4474
Protoss_Dragoon 10 10681
Protoss_Robotics_Facility 1 7434
Protoss_Observatory 1 7617
Protoss_Observer 2 9003
10681
