Protoss_Gateway 2 11413
Protoss_Assimilator 1 3560
Protoss_Cybernetics_Core 1 4648
Protoss_Dragoon 4 10881
Protoss_Robotics_Facility 1 6662
Protoss_Shuttle 1 7476
Protoss_Robotics_Support_Bay 1 6978
Protoss_Reaver 2 9736
Protoss_Observatory 1 9123
Protoss_Nexus 1 11823
Protoss_Observer 1 10068
11823
