Protoss_Gateway 1 3586
Protoss_Assimilator 1 3465
Protoss_Cybernetics_Core 1 4588
Protoss_Dragoon 2 8080
Protoss_Robotics_Facility 1 6649
Protoss_Zealot 2 7238
Protoss_Robotics_Support_Bay 1 6824
Protoss_Shuttle 1 7551
Protoss_Reaver 1 8766
8766
