Protoss_Gateway 1 3442
Protoss_Assimilator 1 3430
Protoss_Cybernetics_Core 1 4578
Protoss_Dragoon 7 10761
Protoss_Robotics_Facility 1 6573
Protoss_Zealot 1 5986
Protoss_Observatory 1 6693
Protoss_Observer 2 9017
Protoss_Shuttle 2 11001
Protoss_Nexus 1 12018
12018
