Protoss_Gateway 3 9091
Protoss_Assimilator 1 3378
Protoss_Cybernetics_Core 1 4482
Protoss_Dragoon 9 10416
Protoss_Nexus 2 11731
Protoss_Robotics_Facility 1 11413
Protoss_Citadel_of_Adun 1 11163
11731
