Protoss_Gateway 2 9130
Protoss_Assimilator 1 3677
Protoss_Zealot 5 9891
Protoss_Cybernetics_Core 1 5388
Protoss_Dragoon 3 10816
Protoss_Robotics_Facility 1 7288
Protoss_Shuttle 1 8111
Protoss_Robotics_Support_Bay 1 7632
Protoss_Reaver 2 10305
10816
