Protoss_Gateway 2 10534
Protoss_Assimilator 1 3423
Protoss_Cybernetics_Core 1 4517
Protoss_Robotics_Facility 1 6188
Protoss_Dragoon 5 10217
Protoss_Shuttle 1 7001
Protoss_Robotics_Support_Bay 1 6573
Protoss_Reaver 2 11366
Protoss_Zealot 1 7676
Protoss_Observatory 1 8458
Protoss_Scarab 8 9978
Protoss_Observer 1 9926
11366
