Protoss_Gateway 2 7906
Protoss_Assimilator 1 3315
Protoss_Cybernetics_Core 1 4533
Protoss_Dragoon 7 9490
Protoss_Robotics_Facility 1 6832
Protoss_Observatory 1 7038
Protoss_Observer 2 8661
Protoss_Nexus 1 11603
Protoss_Citadel_of_Adun 1 10551
Protoss_Zealot 2 10336
11603
