Protoss_Gateway 1 3358
Protoss_Assimilator 1 3268
Protoss_Cybernetics_Core 1 4372
Protoss_Zealot 1 4486
Protoss_Dragoon 6 9226
Protoss_Robotics_Facility 1 8513
Protoss_Citadel_of_Adun 1 8531
Protoss_Shuttle 1 9426
Protoss_Templar_Archives 1 9706
Protoss_Dark_Templar 1 10456
Protoss_Robotics_Support_Bay 1 10587
10587
