Protoss_Gateway 2 7270
Protoss_Assimilator 1 3371
Protoss_Cybernetics_Core 1 4407
Protoss_Robotics_Facility 1 6038
Protoss_Dragoon 11 10670
Protoss_Observatory 1 6183
Protoss_Observer 3 10256
Protoss_Nexus 1 11869
11869
