Protoss_Gateway 2 7346
Protoss_Assimilator 1 3394
Protoss_Cybernetics_Core 1 4408
Protoss_Robotics_Facility 1 6138
Protoss_Dragoon 10 11101
Protoss_Observatory 1 6423
Protoss_Observer 4 10431
Protoss_Nexus 2 12264
12264
