Protoss_Gateway 2 7753
Protoss_Assimilator 1 3390
Protoss_Cybernetics_Core 1 4547
Protoss_Dragoon 11 10803
Protoss_Robotics_Facility 1 6420
Protoss_Observatory 1 6605
Protoss_Observer 2 8241
Protoss_Nexus 1 12262
12262
