Protoss_Gateway 2 8966
Protoss_Assimilator 1 3291
Protoss_Cybernetics_Core 1 4404
Protoss_Dragoon 7 9731
Protoss_Robotics_Facility 1 7006
Protoss_Observatory 1 7103
Protoss_Observer 3 10436
Protoss_Nexus 2 12350
Protoss_Citadel_of_Adun 1 10401
Protoss_Zealot 2 10796
12350
