Protoss_Gateway 2 9731
Protoss_Assimilator 1 3406
Protoss_Cybernetics_Core 1 4511
Protoss_Dragoon 3 8996
Protoss_Stargate 2 7072
Protoss_Scout 2 8591
Protoss_Zealot 1 8106
Protoss_Shield_Battery 1 8530
9731
