Protoss_Gateway 3 8852
Protoss_Assimilator 1 3387
Protoss_Cybernetics_Core 1 4393
Protoss_Robotics_Facility 1 6094
Protoss_Dragoon 8 10951
Protoss_Shuttle 1 6901
Protoss_Observatory 1 6308
Protoss_Observer 6 10957
Protoss_Nexus 1 12482
12482
