Protoss_Gateway 4 11301
Protoss_Assimilator 1 3528
Protoss_Cybernetics_Core 1 4623
Protoss_Dragoon 6 9936
Protoss_Robotics_Facility 1 7763
Protoss_Citadel_of_Adun 1 8665
Protoss_Observatory 1 7968
Protoss_Observer 1 8806
Protoss_Nexus 1 11344
Protoss_Templar_Archives 1 10144
Protoss_Shuttle 1 10996
11344
