Protoss_Gateway 2 6198
Protoss_Assimilator 1 3674
Protoss_Cybernetics_Core 1 4698
Protoss_Zealot 1 4391
Protoss_Dragoon 5 10391
Protoss_Citadel_of_Adun 1 5935
Protoss_Templar_Archives 1 7123
Protoss_Dark_Templar 4 9043
Protoss_Robotics_Facility 1 10528
10528
