Protoss_Gateway 2 6218
Protoss_Assimilator 1 2342
Protoss_Cybernetics_Core 1 3168
Protoss_Dragoon 6 9256
Protoss_Robotics_Facility 1 4598
Protoss_Robotics_Support_Bay 1 5988
Protoss_Shuttle 1 6631
Protoss_Reaver 1 7533
Protoss_Nexus 1 8533
Protoss_Observatory 1 9228
Protoss_Scarab 2 9957
9957
