Protoss_Gateway 3 7653
Protoss_Assimilator 1 3367
Protoss_Cybernetics_Core 1 4583
Protoss_Robotics_Facility 1 6143
Protoss_Dragoon 6 9153
Protoss_Observatory 1 6298
Protoss_Observer 4 10376
Protoss_Nexus 2 12593
12593
