Protoss_Gateway 2 9888
Protoss_Assimilator 1 3336
Protoss_Cybernetics_Core 1 4578
Protoss_Zealot 3 10731
Protoss_Dragoon 7 10170
Protoss_Robotics_Facility 1 7913
Protoss_Shuttle 2 11055
Protoss_Robotics_Support_Bay 1 8425
Protoss_Reaver 1 10243
Protoss_Citadel_of_Adun 1 10573
11055
