Protoss_Gateway 2 7223
Protoss_Assimilator 1 3238
Protoss_Cybernetics_Core 1 4506
Protoss_Dragoon 10 11041
Protoss_Robotics_Facility 1 6688
Protoss_Observatory 1 7046
Protoss_Observer 4 10456
Protoss_Nexus 2 12291
12291
