Protoss_Gateway 2 7248
Protoss_Assimilator 1 3195
Protoss_Cybernetics_Core 1 4443
Protoss_Dragoon 7 10777
Protoss_Robotics_Facility 1 6544
Protoss_Observatory 1 6643
Protoss_Observer 3 10221
Protoss_Nexus 1 10997
Protoss_Shuttle 1 11303
11303
