Protoss_Gateway 3 9226
Protoss_Assimilator 1 3475
Protoss_Cybernetics_Core 1 4716
Protoss_Zealot 4 10881
Protoss_Dragoon 8 10151
Protoss_Nexus 1 9578
Protoss_Robotics_Facility 1 9749
Protoss_Observatory 1 10228
Protoss_Shuttle 1 10986
10986
