Protoss_Gateway 2 9057
Protoss_Assimilator 1 3303
Protoss_Cybernetics_Core 1 4489
Protoss_Robotics_Facility 1 6139
Protoss_Dragoon 3 7661
Protoss_Observatory 1 6331
Protoss_Shuttle 1 7266
Protoss_Observer 3 8892
Protoss_Zealot 4 10236
Protoss_Robotics_Support_Bay 1 8874
Protoss_Nexus 1 11643
Protoss_Reaver 1 10926
11643
