Protoss_Gateway 1 3354
Protoss_Assimilator 1 3265
Protoss_Cybernetics_Core 1 4390
Protoss_Robotics_Facility 1 5989
Protoss_Dragoon 4 10269
Protoss_Zealot 2 6767
Protoss_Shuttle 1 6929
Protoss_Robotics_Support_Bay 1 6681
Protoss_Reaver 3 10285
10285
