Protoss_Gateway 3 10923
Protoss_Assimilator 1 3403
Protoss_Cybernetics_Core 1 4695
Protoss_Dragoon 8 10436
Protoss_Robotics_Facility 1 7935
Protoss_Observatory 1 8767
Protoss_Nexus 1 11509
Protoss_Observer 1 9671
Protoss_Shuttle 1 10753
11509
