Protoss_Gateway 3 7223
Protoss_Assimilator 1 3495
Protoss_Zealot 7 10861
Protoss_Cybernetics_Core 1 5325
Protoss_Dragoon 7 8972
Protoss_Citadel_of_Adun 1 9420
Protoss_Templar_Archives 1 10572
Protoss_Robotics_Facility 1 11483
11483
