Protoss_Gateway 2 9093
Protoss_Assimilator 1 3278
Protoss_Cybernetics_Core 1 4621
Protoss_Dragoon 9 10882
Protoss_Robotics_Facility 1 6703
Protoss_Observatory 1 6798
Protoss_Observer 4 10426
Protoss_Nexus 1 10091
10882
