Protoss_Assimilator 2 3943
Protoss_Gateway 3 11298
Protoss_Zealot 2 5426
Protoss_Cybernetics_Core 1 5568
Protoss_Dragoon 1 6326
Protoss_Citadel_of_Adun 1 7453
Protoss_Nexus 1 9503
Protoss_Templar_Archives 1 8498
Protoss_Robotics_Facility 1 9424
Protoss_Dark_Templar 2 10316
Protoss_Shuttle 1 10431
Protoss_Observatory 1 10088
Protoss_Observer 1 10866
11298
