Protoss_Assimilator 1 2705
Protoss_Gateway 2 7897
Protoss_Cybernetics_Core 1 4683
Protoss_Dragoon 4 7981
Protoss_Robotics_Facility 1 6549
Protoss_Observatory 1 6688
Protoss_Citadel_of_Adun 1 7484
Protoss_Observer 2 8078
Protoss_Templar_Archives 1 8587
Protoss_Zealot 1 8476
Protoss_Shuttle 1 9316
Protoss_Dark_Templar 4 10366
Protoss_Nexus 1 12303
12303
