Protoss_Gateway 3 10543
Protoss_Nexus 1 6444
Protoss_Zealot 2 5631
Protoss_Assimilator 1 5238
Protoss_Cybernetics_Core 1 6645
Protoss_Dragoon 8 10518
Protoss_Shield_Battery 1 7829
10543
