Protoss_Gateway 2 7015
Protoss_Assimilator 1 3450
Protoss_Cybernetics_Core 1 4490
Protoss_Zealot 1 4161
Protoss_Dragoon 9 11086
Protoss_Robotics_Facility 1 8566
Protoss_Observatory 1 8805
11086
