Protoss_Gateway 2 6446
Protoss_Assimilator 1 3606
Protoss_Cybernetics_Core 1 4752
Protoss_Zealot 3 8986
Protoss_Dragoon 12 11111
Protoss_Nexus 1 11508
Protoss_Robotics_Facility 1 11474
11508
