Protoss_Gateway 3 9423
Protoss_Assimilator 1 3583
Protoss_Cybernetics_Core 1 4533
Protoss_Dragoon 8 10879
Protoss_Robotics_Facility 1 7998
Protoss_Zealot 4 9751
Protoss_Shuttle 1 9109
Protoss_Observatory 1 8443
Protoss_Observer 1 9604
Protoss_Citadel_of_Adun 1 10345
10879
