Protoss_Gateway 2 8249
Protoss_Assimilator 4 4554
Protoss_Cybernetics_Core 1 4888
Protoss_Dragoon 5 10781
Protoss_Citadel_of_Adun 1 7146
Protoss_Robotics_Facility 1 8470
Protoss_Zealot 1 7971
Protoss_Templar_Archives 1 8948
Protoss_Shuttle 1 9651
Protoss_Dark_Templar 2 9701
Protoss_Observatory 1 9836
Protoss_Nexus 1 12218
12218
