Protoss_Gateway 2 7384
Protoss_Assimilator 1 3595
Protoss_Cybernetics_Core 1 4581
Protoss_Dragoon 4 9351
Protoss_Robotics_Facility 1 6813
Protoss_Observatory 1 6999
Protoss_Observer 1 7781
9351
