Protoss_Gateway 2 6644
Protoss_Assimilator 1 3293
Protoss_Cybernetics_Core 1 4278
Protoss_Zealot 3 10556
Protoss_Dragoon 7 8451
Protoss_Citadel_of_Adun 1 8171
Protoss_Templar_Archives 1 9193
Protoss_Robotics_Facility 1 9803
Protoss_Dark_Templar 2 9981
Protoss_Shuttle 1 10766
10766
