Protoss_Gateway 2 7343
Protoss_Assimilator 1 3449
Protoss_Cybernetics_Core 1 4483
Protoss_Dragoon 3 6868
Protoss_Citadel_of_Adun 1 6696
Protoss_Templar_Archives 1 7740
Protoss_Zealot 1 7380
Protoss_Dark_Templar 6 10561
Protoss_Nexus 1 11051
11051
