Protoss_Gateway 2 5942
Protoss_Assimilator 1 3238
Protoss_Cybernetics_Core 1 4418
Protoss_Dragoon 6 8501
Protoss_Robotics_Facility 1 7133
Protoss_Observatory 1 7298
Protoss_Citadel_of_Adun 1 8290
Protoss_Observer 1 8476
Protoss_Zealot 2 9013
Protoss_Templar_Archives 1 9746
Protoss_Nexus 1 12032
Protoss_Dark_Templar 2 10646
12032
