Protoss_Gateway 2 7748
Protoss_Assimilator 1 3393
Protoss_Cybernetics_Core 1 4492
Protoss_Dragoon 8 10666
Protoss_Robotics_Facility 1 7433
Protoss_Observatory 1 7574
Protoss_Observer 3 10806
Protoss_Nexus 2 11723
11723
