Protoss_Gateway 1 3406
Protoss_Assimilator 1 3496
Protoss_Zealot 2 5081
Protoss_Cybernetics_Core 1 5303
Protoss_Dragoon 6 10701
Protoss_Robotics_Facility 1 7404
Protoss_Shuttle 1 8461
Protoss_Robotics_Support_Bay 1 7942
Protoss_Reaver 2 10728
10728
