Protoss_Gateway 2 5940
Protoss_Assimilator 1 3355
Protoss_Cybernetics_Core 1 4543
Protoss_Dragoon 12 11016
Protoss_Robotics_Facility 1 9473
Protoss_Observatory 1 9609
Protoss_Nexus 1 12013
12013
