Protoss_Gateway 2 10203
Protoss_Assimilator 1 3463
Protoss_Cybernetics_Core 1 4593
Protoss_Dragoon 5 11121
Protoss_Robotics_Facility 1 6548
Protoss_Shuttle 1 7356
Protoss_Robotics_Support_Bay 1 6928
Protoss_Reaver 1 8509
Protoss_Zealot 1 7961
Protoss_Observatory 1 7883
Protoss_Nexus 1 10948
Protoss_Observer 3 10656
11121
