Protoss_Gateway 3 11028
Protoss_Assimilator 1 3443
Protoss_Cybernetics_Core 1 4573
Protoss_Dragoon 12 10815
Protoss_Nexus 1 9348
Protoss_Robotics_Facility 1 8704
Protoss_Observatory 1 8956
Protoss_Observer 1 10136
11028
