Protoss_Gateway 2 7380
Protoss_Assimilator 1 3446
Protoss_Cybernetics_Core 1 4766
Protoss_Dragoon 7 9481
Protoss_Robotics_Facility 1 6708
Protoss_Observatory 1 7140
Protoss_Observer 2 9676
Protoss_Zealot 1 8086
Protoss_Shuttle 1 9098
Protoss_Robotics_Support_Bay 1 8820
Protoss_Reaver 1 10998
Protoss_Nexus 1 12295
12295
