Protoss_Nexus 1 5749
Protoss_Gateway 3 8750
Protoss_Assimilator 1 4893
Protoss_Zealot 8 10931
Protoss_Cybernetics_Core 1 6933
Protoss_Dragoon 2 9326
Protoss_Citadel_of_Adun 1 8814
Protoss_Forge 2 8561
Protoss_Photon_Cannon 3 10543
Protoss_Templar_Archives 1 10078
Protoss_Dark_Templar 1 10856
10931
