Protoss_Gateway 1 3408
Protoss_Assimilator 1 3469
Protoss_Cybernetics_Core 1 4628
Protoss_Dragoon 4 10545
Protoss_Robotics_Facility 1 6578
Protoss_Zealot 2 7028
Protoss_Shuttle 2 11276
Protoss_Robotics_Support_Bay 1 7113
Protoss_Reaver 2 9968
Protoss_Nexus 1 11687
Protoss_Scarab 2 9660
11687
