Protoss_Gateway 5 11314
Protoss_Assimilator 1 3488
Protoss_Cybernetics_Core 1 4645
Protoss_Dragoon 9 11183
Protoss_Robotics_Facility 1 6684
Protoss_Observatory 1 6898
Protoss_Observer 2 8389
Protoss_Nexus 1 10726
Protoss_Shuttle 1 9685
11314
