Protoss_Gateway 2 7778
Protoss_Assimilator 1 3573
Protoss_Cybernetics_Core 1 4689
Protoss_Dragoon 8 10866
Protoss_Robotics_Facility 1 7544
Protoss_Observatory 1 7734
Protoss_Nexus 1 10438
Protoss_Observer 2 9153
Protoss_Shuttle 1 10331
Protoss_Robotics_Support_Bay 1 9838
Protoss_Reaver 1 11473
11473
