Protoss_Gateway 4 11377
Protoss_Assimilator 1 3324
Protoss_Zealot 1 3995
Protoss_Cybernetics_Core 1 4825
Protoss_Dragoon 8 10247
Protoss_Robotics_Facility 1 8779
Protoss_Observatory 1 8955
Protoss_Nexus 1 11321
Protoss_Observer 2 10333
11377
