Protoss_Gateway 2 6695
Protoss_Assimilator 1 3400
Protoss_Cybernetics_Core 1 4448
Protoss_Dragoon 7 8856
Protoss_Robotics_Facility 1 7970
Protoss_Observatory 1 8123
Protoss_Observer 2 9553
Protoss_Nexus 1 11431
Protoss_Shuttle 1 10326
Protoss_Zealot 2 10286
11431
