Protoss_Gateway 4 11131
Protoss_Assimilator 1 3612
Protoss_Zealot 4 10517
Protoss_Cybernetics_Core 1 5252
Protoss_Dragoon 9 10701
Protoss_Robotics_Facility 1 7999
Protoss_Observatory 1 8105
Protoss_Observer 2 9525
Protoss_Nexus 1 11206
11206
