Protoss_Assimilator 1 2746
Protoss_Gateway 1 3588
Protoss_Cybernetics_Core 1 4663
Protoss_Dragoon 5 10158
Protoss_Robotics_Facility 1 6412
Protoss_Shuttle 1 7241
Protoss_Robotics_Support_Bay 1 6718
Protoss_Reaver 3 11130
Protoss_Observatory 1 7634
Protoss_Scarab 7 8971
Protoss_Observer 1 9808
11130
