Protoss_Gateway 3 10073
Protoss_Assimilator 1 3478
Protoss_Cybernetics_Core 1 4603
Protoss_Robotics_Facility 1 6253
Protoss_Shuttle 1 7061
Protoss_Observatory 1 6368
Protoss_Dragoon 8 10906
Protoss_Observer 4 10273
Protoss_Nexus 2 12818
12818
