Protoss_Gateway 3 8476
Protoss_Assimilator 1 3606
Protoss_Zealot 2 4426
Protoss_Cybernetics_Core 1 4700
Protoss_Dragoon 12 10708
Protoss_Citadel_of_Adun 1 10041
Protoss_Templar_Archives 1 11063
11063
