Protoss_Gateway 2 6601
Protoss_Assimilator 1 3389
Protoss_Cybernetics_Core 1 4654
Protoss_Dragoon 4 7390
Protoss_Citadel_of_Adun 1 8009
Protoss_Zealot 4 8866
Protoss_Robotics_Facility 1 9193
Protoss_Templar_Archives 1 9062
Protoss_Shuttle 1 10086
Protoss_Dark_Templar 4 11111
Protoss_Nexus 1 12373
12373
