Protoss_Gateway 2 7778
Protoss_Assimilator 1 3362
Protoss_Cybernetics_Core 1 4478
Protoss_Dragoon 9 10421
Protoss_Citadel_of_Adun 2 11169
Protoss_Robotics_Facility 1 7079
Protoss_Observatory 1 7178
Protoss_Observer 2 9324
Protoss_Nexus 1 11296
11296
