Protoss_Gateway 3 7791
Protoss_Assimilator 1 3443
Protoss_Cybernetics_Core 1 4518
Protoss_Dragoon 9 10089
Protoss_Nexus 1 8856
Protoss_Zealot 1 8167
Protoss_Robotics_Facility 1 11111
Protoss_Citadel_of_Adun 1 11207
11207
