Protoss_Gateway 1 3550
Protoss_Assimilator 1 3517
Protoss_Cybernetics_Core 1 4753
Protoss_Dragoon 6 10506
Protoss_Robotics_Facility 1 7956
Protoss_Shuttle 1 8806
Protoss_Zealot 1 8531
Protoss_Robotics_Support_Bay 1 8548
Protoss_Reaver 1 10111
Protoss_Observatory 1 9427
Protoss_Observer 1 10855
10855
