Protoss_Gateway 2 8217
Protoss_Assimilator 1 3276
Protoss_Cybernetics_Core 1 4537
Protoss_Robotics_Facility 1 6147
Protoss_Dragoon 9 10485
Protoss_Observatory 1 6349
Protoss_Observer 2 9861
10485
