Protoss_Gateway 1 3260
Protoss_Zealot 3 5241
Protoss_Assimilator 1 4008
Protoss_Cybernetics_Core 1 5278
Protoss_Robotics_Facility 1 6973
Protoss_Dragoon 6 10978
Protoss_Robotics_Support_Bay 1 7146
Protoss_Reaver 3 11378
Protoss_Observatory 1 7898
Protoss_Nexus 1 10178
Protoss_Observer 1 8988
Protoss_Scarab 4 9868
11378
