Protoss_Gateway 3 6593
Protoss_Assimilator 1 3509
Protoss_Cybernetics_Core 1 4541
Protoss_Dragoon 12 10543
Protoss_Robotics_Facility 1 8195
Protoss_Observatory 1 8345
Protoss_Nexus 1 10673
Protoss_Observer 2 10447
10673
