Protoss_Gateway 3 11289
Protoss_Assimilator 1 3398
Protoss_Cybernetics_Core 1 4434
Protoss_Dragoon 5 11116
Protoss_Citadel_of_Adun 1 5723
Protoss_Templar_Archives 1 6821
Protoss_Dark_Templar 6 9176
Protoss_Nexus 1 11258
Protoss_Forge 1 9636
11289
