Protoss_Gateway 2 6007
Protoss_Assimilator 1 3236
Protoss_Cybernetics_Core 1 4313
Protoss_Dragoon 11 10819
Protoss_Nexus 1 9904
Protoss_Robotics_Facility 1 9977
Protoss_Observatory 1 10162
10819
