Protoss_Gateway 2 9928
Protoss_Assimilator 1 3403
Protoss_Zealot 1 4031
Protoss_Cybernetics_Core 1 5153
Protoss_Dragoon 7 10871
Protoss_Robotics_Facility 1 6881
Protoss_Shuttle 1 7691
Protoss_Robotics_Support_Bay 1 7368
Protoss_Reaver 2 9918
Protoss_Observatory 1 9383
Protoss_Nexus 1 12152
Protoss_Observer 1 10926
12152
