Protoss_Gateway 3 10893
Protoss_Assimilator 1 3346
Protoss_Cybernetics_Core 1 4514
Protoss_Dragoon 8 10481
Protoss_Zealot 2 7126
Protoss_Nexus 1 9848
Protoss_Robotics_Facility 1 9494
Protoss_Observatory 1 9700
Protoss_Observer 1 10491
10893
