Protoss_Gateway 2 5263
Protoss_Assimilator 1 3358
Protoss_Cybernetics_Core 1 4508
Protoss_Dragoon 10 9616
Protoss_Nexus 1 10371
Protoss_Citadel_of_Adun 1 9812
Protoss_Templar_Archives 1 11325
11325
