Protoss_Gateway 2 7407
Protoss_Assimilator 1 3447
Protoss_Cybernetics_Core 1 4597
Protoss_Dragoon 6 8537
Protoss_Robotics_Facility 1 7407
Protoss_Observatory 1 7563
Protoss_Observer 1 8337
Protoss_Shuttle 1 9569
Protoss_Zealot 2 9247
Protoss_Nexus 2 12879
12879
