Protoss_Gateway 2 6129
Protoss_Assimilator 2 10124
Protoss_Cybernetics_Core 1 4416
Protoss_Dragoon 10 10808
Protoss_Robotics_Facility 1 8456
Protoss_Zealot 1 7781
Protoss_Observatory 1 8662
Protoss_Nexus 1 11228
Protoss_Observer 2 10361
Protoss_Stargate 1 11059
11228
