Protoss_Gateway 2 6957
Protoss_Assimilator 1 3243
Protoss_Cybernetics_Core 1 4650
Protoss_Dragoon 9 10623
Protoss_Robotics_Facility 1 6442
Protoss_Observatory 1 6719
Protoss_Observer 3 10743
Protoss_Nexus 2 12548
12548
