Protoss_Gateway 1 3436
Protoss_Assimilator 1 3668
Protoss_Zealot 7 9573
Protoss_Cybernetics_Core 1 5529
Protoss_Dragoon 3 10651
Protoss_Robotics_Facility 1 7309
Protoss_Shuttle 1 8121
Protoss_Robotics_Support_Bay 1 7764
Protoss_Reaver 2 10413
Protoss_Observatory 1 9681
Protoss_Citadel_of_Adun 1 10608
Protoss_Observer 1 10745
10745
