Protoss_Gateway 1 3428
Protoss_Assimilator 1 3493
Protoss_Cybernetics_Core 1 4632
Protoss_Dragoon 7 10069
Protoss_Robotics_Facility 1 7563
Protoss_Shuttle 1 8376
Protoss_Observatory 1 7780
Protoss_Robotics_Support_Bay 1 8468
Protoss_Observer 1 8798
Protoss_Reaver 2 11253
11253
