Protoss_Gateway 2 3993
Protoss_Zealot 7 6431
Protoss_Assimilator 1 4927
Protoss_Cybernetics_Core 1 6494
Protoss_Dragoon 6 9263
Protoss_Citadel_of_Adun 1 8266
Protoss_Templar_Archives 1 9628
Protoss_Dark_Templar 2 10461
Protoss_Nexus 1 12440
12440
