Protoss_Gateway 2 6399
Protoss_Assimilator 1 3468
Protoss_Zealot 2 10231
Protoss_Cybernetics_Core 1 5394
Protoss_Dragoon 8 10871
Protoss_Robotics_Facility 1 7904
Protoss_Observatory 1 8003
Protoss_Observer 3 10801
Protoss_Nexus 1 11597
11597
