Protoss_Gateway 2 4915
Protoss_Assimilator 1 3319
Protoss_Cybernetics_Core 1 4424
Protoss_Dragoon 11 10457
Protoss_Nexus 1 9296
Protoss_Robotics_Facility 1 9139
Protoss_Observatory 1 9268
Protoss_Observer 2 10749
10749
