Protoss_Gateway 3 9749
Protoss_Assimilator 1 3398
Protoss_Cybernetics_Core 1 4738
Protoss_Robotics_Facility 1 6288
Protoss_Dragoon 7 10501
Protoss_Observatory 1 6391
Protoss_Observer 2 8675
Protoss_Shuttle 2 10816
Protoss_Nexus 1 12817
12817
