Protoss_Gateway 4 10759
Protoss_Assimilator 1 3309
Protoss_Cybernetics_Core 1 4338
Protoss_Dragoon 11 10881
Protoss_Robotics_Facility 1 7358
Protoss_Observatory 1 7453
Protoss_Observer 2 9926
Protoss_Nexus 1 11279
11279
