Protoss_Gateway 3 7885
Protoss_Assimilator 2 9874
Protoss_Cybernetics_Core 1 4305
Protoss_Dragoon 8 11106
Protoss_Robotics_Facility 1 7437
Protoss_Observatory 1 7677
Protoss_Observer 2 9063
Protoss_Nexus 1 10403
Protoss_Zealot 3 9476
Protoss_Shuttle 1 10639
11106
