Protoss_Gateway 4 10903
Protoss_Assimilator 1 3128
Protoss_Cybernetics_Core 1 4374
Protoss_Dragoon 3 5996
Protoss_Robotics_Facility 1 7608
Protoss_Zealot 3 10488
Protoss_Citadel_of_Adun 1 7883
Protoss_Observatory 1 7888
Protoss_Templar_Archives 1 9206
Protoss_Shuttle 1 9371
Protoss_Nexus 1 11166
Protoss_Dark_Templar 3 10718
11166
