Protoss_Gateway 2 6313
Protoss_Assimilator 1 3480
Protoss_Cybernetics_Core 1 4716
Protoss_Dragoon 11 11037
Protoss_Robotics_Facility 1 7741
Protoss_Observatory 1 8011
Protoss_Observer 2 9685
Protoss_Nexus 1 11057
11057
