Protoss_Gateway 2 6302
Protoss_Forge 1 3968
Protoss_Zealot 2 4591
Protoss_Assimilator 1 4621
Protoss_Photon_Cannon 1 4973
Protoss_Cybernetics_Core 1 5833
Protoss_Dragoon 11 10885
Protoss_Robotics_Facility 1 9999
Protoss_Shuttle 1 11169
11169
