Protoss_Gateway 2 9129
Protoss_Assimilator 1 3508
Protoss_Cybernetics_Core 1 4705
Protoss_Dragoon 6 9652
Protoss_Robotics_Facility 1 7962
Protoss_Observatory 1 8237
Protoss_Citadel_of_Adun 1 8985
Protoss_Observer 1 9476
9652
