Protoss_Gateway 2 5853
Protoss_Assimilator 2 10768
Protoss_Cybernetics_Core 1 4399
Protoss_Dragoon 10 10161
Protoss_Zealot 1 8165
Protoss_Nexus 1 10496
Protoss_Robotics_Facility 1 10265
Protoss_Shuttle 1 11396
11396
