Protoss_Gateway 4 10509
Protoss_Assimilator 1 3346
Protoss_Cybernetics_Core 1 4577
Protoss_Dragoon 11 10729
Protoss_Nexus 1 9033
Protoss_Robotics_Facility 1 9371
Protoss_Observatory 1 9556
10729
