Protoss_Gateway 4 10451
Protoss_Assimilator 2 10364
Protoss_Cybernetics_Core 1 4565
Protoss_Dragoon 11 10985
Protoss_Nexus 1 9260
Protoss_Robotics_Facility 1 9044
Protoss_Observatory 1 9249
Protoss_Observer 1 10237
10985
