Protoss_Gateway 2 9156
Protoss_Assimilator 1 3578
Protoss_Cybernetics_Core 1 4653
Protoss_Dragoon 9 11181
Protoss_Robotics_Facility 1 6884
Protoss_Observatory 1 7119
Protoss_Observer 2 8518
Protoss_Shuttle 1 9826
Protoss_Nexus 1 12480
12480
