Protoss_Gateway 2 7327
Protoss_Assimilator 1 3385
Protoss_Cybernetics_Core 1 4487
Protoss_Dragoon 11 11087
Protoss_Robotics_Facility 1 6425
Protoss_Observatory 1 6614
Protoss_Observer 3 10449
Protoss_Nexus 2 12590
12590
