Protoss_Gateway 2 6444
Protoss_Assimilator 1 3438
Protoss_Cybernetics_Core 1 4555
Protoss_Dragoon 5 10488
Protoss_Citadel_of_Adun 1 7083
Protoss_Zealot 3 7663
Protoss_Templar_Archives 1 8189
Protoss_Nexus 1 10394
Protoss_Dark_Templar 4 9798
Protoss_Robotics_Facility 1 11372
11372
