Protoss_Gateway 2 11408
Protoss_Assimilator 1 3453
Protoss_Zealot 4 9406
Protoss_Cybernetics_Core 1 5254
Protoss_Dragoon 5 11021
Protoss_Robotics_Facility 1 7363
Protoss_Shuttle 2 10871
Protoss_Robotics_Support_Bay 1 7849
Protoss_Reaver 1 9533
11408
