Protoss_Gateway 4 11403
Protoss_Zealot 3 7586
Protoss_Assimilator 1 4148
Protoss_Cybernetics_Core 1 5503
Protoss_Dragoon 3 7781
Protoss_Citadel_of_Adun 1 6668
Protoss_Templar_Archives 1 7663
Protoss_Dark_Templar 6 10993
Protoss_Robotics_Facility 1 9861
Protoss_Shuttle 1 11076
11403
