Protoss_Gateway 2 6088
Protoss_Assimilator 1 3359
Protoss_Cybernetics_Core 1 4497
Protoss_Dragoon 4 7113
Protoss_Citadel_of_Adun 1 7725
Protoss_Zealot 2 7625
Protoss_Templar_Archives 1 8760
Protoss_Robotics_Facility 1 9444
Protoss_Dark_Templar 3 10537
Protoss_Nexus 1 11695
Protoss_Shuttle 1 10365
Protoss_Observatory 1 10311
11695
