Protoss_Gateway 2 4052
Protoss_Zealot 9 10907
Protoss_Assimilator 1 4442
Protoss_Cybernetics_Core 1 5733
Protoss_Dragoon 4 7535
Protoss_Citadel_of_Adun 1 8263
Protoss_Templar_Archives 1 9301
Protoss_High_Templar 2 11011
Protoss_Forge 1 10119
11011
