Protoss_Gateway 1 3383
Protoss_Assimilator 1 3618
Protoss_Zealot 3 6036
Protoss_Cybernetics_Core 1 6047
Protoss_Robotics_Facility 1 7554
Protoss_Dragoon 2 7738
Protoss_Citadel_of_Adun 1 7748
Protoss_Robotics_Support_Bay 1 7818
Protoss_Shuttle 1 8541
Protoss_Templar_Archives 1 8943
Protoss_Reaver 2 10735
Protoss_Dark_Templar 2 10713
10735
