Protoss_Gateway 2 6838
Protoss_Assimilator 1 3333
Protoss_Zealot 3 8403
Protoss_Cybernetics_Core 1 4778
Protoss_Dragoon 8 10871
Protoss_Nexus 1 11083
Protoss_Robotics_Facility 1 10835
11083
