Protoss_Gateway 3 8809
Protoss_Assimilator 1 3233
Protoss_Cybernetics_Core 1 4370
Protoss_Dragoon 11 9713
Protoss_Robotics_Facility 1 8635
Protoss_Zealot 5 10909
Protoss_Observatory 1 8782
Protoss_Observer 1 9563
Protoss_Shuttle 1 10809
Protoss_Nexus 1 12569
12569
