Protoss_Gateway 2 4773
Protoss_Assimilator 1 3302
Protoss_Cybernetics_Core 1 4363
Protoss_Dragoon 13 10569
Protoss_Zealot 2 7013
Protoss_Nexus 1 11105
Protoss_Robotics_Facility 1 11341
11341
