Protoss_Gateway 4 10748
Protoss_Assimilator 1 3383
Protoss_Cybernetics_Core 1 4377
Protoss_Dragoon 12 11123
Protoss_Nexus 1 9723
Protoss_Robotics_Facility 1 9071
Protoss_Observatory 1 9213
Protoss_Observer 2 10603
11123
