Protoss_Gateway 2 7558
Protoss_Assimilator 1 3488
Protoss_Cybernetics_Core 1 4703
Protoss_Dragoon 10 10046
Protoss_Robotics_Facility 1 7539
Protoss_Observatory 1 7916
Protoss_Observer 2 9303
Protoss_Nexus 2 12597
12597
