Protoss_Gateway 2 7248
Protoss_Assimilator 1 3440
Protoss_Cybernetics_Core 1 4528
Protoss_Dragoon 8 9893
Protoss_Robotics_Facility 1 7378
Protoss_Observatory 1 7474
Protoss_Observer 2 8888
Protoss_Nexus 1 10428
Protoss_Shuttle 1 9521
Protoss_Robotics_Support_Bay 1 9045
Protoss_Reaver 1 10821
Protoss_Zealot 2 10405
10821
