Protoss_Gateway 3 9603
Protoss_Assimilator 1 3585
Protoss_Cybernetics_Core 1 4783
Protoss_Dragoon 8 10501
Protoss_Nexus 1 9598
Protoss_Robotics_Facility 1 9453
Protoss_Observatory 1 9554
Protoss_Observer 1 10411
10501
