Protoss_Nexus 2 11600
Protoss_Gateway 3 8390
Protoss_Assimilator 2 10939
Protoss_Cybernetics_Core 1 5549
Protoss_Zealot 1 5866
Protoss_Dragoon 8 9446
Protoss_Robotics_Facility 1 9213
Protoss_Shuttle 1 10061
Protoss_Robotics_Support_Bay 1 9538
Protoss_Observatory 1 9876
Protoss_Reaver 1 11203
11600
