Protoss_Gateway 2 6525
Protoss_Zealot 5 10361
Protoss_Assimilator 1 4749
Protoss_Cybernetics_Core 1 5721
Protoss_Dragoon 9 9849
Protoss_Robotics_Facility 1 10003
Protoss_Shuttle 1 10836
Protoss_Robotics_Support_Bay 1 10145
10836
