Protoss_Gateway 2 9464
Protoss_Assimilator 1 3271
Protoss_Cybernetics_Core 1 4646
Protoss_Dragoon 5 10823
Protoss_Robotics_Facility 1 6613
Protoss_Shuttle 1 7417
Protoss_Robotics_Support_Bay 1 6763
Protoss_Zealot 2 8077
Protoss_Reaver 2 9969
Protoss_Nexus 1 12135
Protoss_Observatory 1 10223
12135
