Protoss_Gateway 3 10935
Protoss_Assimilator 1 3365
Protoss_Cybernetics_Core 1 4414
Protoss_Dragoon 7 10683
Protoss_Nexus 2 11962
Protoss_Robotics_Facility 1 9734
Protoss_Observatory 1 10038
11962
