Protoss_Gateway 2 4916
Protoss_Assimilator 1 3331
Protoss_Cybernetics_Core 1 4351
Protoss_Dragoon 9 8949
Protoss_Robotics_Facility 1 8493
Protoss_Shuttle 1 9465
Protoss_Robotics_Support_Bay 1 8927
Protoss_Reaver 1 10607
Protoss_Zealot 2 10249
10607
