Protoss_Nexus 1 5533
Protoss_Gateway 2 6644
Protoss_Assimilator 1 4160
Protoss_Cybernetics_Core 1 5389
Protoss_Zealot 1 5303
Protoss_Dragoon 10 10375
Protoss_Robotics_Facility 1 9091
Protoss_Observatory 1 9397
Protoss_Observer 1 10243
10375
