Protoss_Gateway 3 11432
Protoss_Assimilator 1 3583
Protoss_Cybernetics_Core 1 4758
Protoss_Dragoon 11 10671
Protoss_Robotics_Facility 1 8788
Protoss_Nexus 1 10948
Protoss_Observatory 1 8968
Protoss_Observer 2 10388
11432
