Protoss_Gateway 3 9821
Protoss_Assimilator 2 10447
Protoss_Cybernetics_Core 1 4333
Protoss_Dragoon 11 11065
Protoss_Robotics_Facility 1 7227
Protoss_Observatory 1 7364
Protoss_Observer 4 10661
Protoss_Nexus 1 10129
Protoss_Citadel_of_Adun 1 9719
Protoss_Templar_Archives 1 10954
11065
