Protoss_Gateway 5 9710
Protoss_Assimilator 2 10129
Protoss_Cybernetics_Core 1 4542
Protoss_Dragoon 8 9833
Protoss_Nexus 1 9960
Protoss_Robotics_Facility 1 9749
Protoss_Observatory 1 10049
Protoss_Zealot 3 10563
Protoss_Shuttle 1 11339
11339
