Protoss_Gateway 2 6933
Protoss_Assimilator 2 10353
Protoss_Cybernetics_Core 1 4343
Protoss_Dragoon 7 10383
Protoss_Citadel_of_Adun 1 6489
Protoss_Robotics_Facility 1 7199
Protoss_Templar_Archives 1 7518
Protoss_Zealot 3 10441
Protoss_Shuttle 2 10771
Protoss_Dark_Templar 2 8411
Protoss_Nexus 1 11083
Protoss_Observatory 1 9412
Protoss_Robotics_Support_Bay 1 10243
Protoss_Forge 1 10889
11083
