Protoss_Gateway 2 6021
Protoss_Assimilator 1 3289
Protoss_Cybernetics_Core 1 4363
Protoss_Dragoon 9 10677
Protoss_Robotics_Facility 1 8623
Protoss_Zealot 2 8255
Protoss_Shuttle 1 9473
Protoss_Robotics_Support_Bay 1 8939
Protoss_Reaver 1 10865
10865
