Protoss_Gateway 2 10072
Protoss_Assimilator 1 3435
Protoss_Zealot 3 10823
Protoss_Cybernetics_Core 1 5103
Protoss_Dragoon 6 10339
Protoss_Robotics_Facility 1 7555
Protoss_Observatory 1 7667
Protoss_Nexus 1 10173
Protoss_Observer 2 9049
Protoss_Shuttle 1 10131
Protoss_Robotics_Support_Bay 1 9471
Protoss_Reaver 1 11333
11333
