Protoss_Forge 1 3747
Protoss_Photon_Cannon 6 10099
Protoss_Nexus 2 12623
Protoss_Assimilator 1 6746
Protoss_Gateway 1 7510
Protoss_Cybernetics_Core 1 8579
Protoss_Stargate 2 9895
Protoss_Scout 2 11276
12623
