Protoss_Gateway 2 8298
Protoss_Assimilator 1 3563
Protoss_Cybernetics_Core 1 4713
Protoss_Dragoon 9 11123
Protoss_Robotics_Facility 1 8083
Protoss_Shuttle 1 8961
Protoss_Zealot 4 9408
Protoss_Observatory 1 9029
Protoss_Observer 1 10076
Protoss_Nexus 1 12473
12473
