Protoss_Nexus 1 5586
Protoss_Gateway 6 11113
Protoss_Assimilator 2 9446
Protoss_Cybernetics_Core 1 5673
Protoss_Zealot 5 10226
Protoss_Dragoon 7 9538
Protoss_Robotics_Facility 1 8978
Protoss_Observatory 1 9073
Protoss_Observer 2 10453
Protoss_Citadel_of_Adun 1 11052
11113
