Protoss_Gateway 3 10836
Protoss_Assimilator 1 3434
Protoss_Cybernetics_Core 1 4530
Protoss_Dragoon 1 5281
Protoss_Robotics_Facility 1 6727
Protoss_Nexus 1 8788
Protoss_Observatory 1 6844
Protoss_Observer 1 7656
Protoss_Forge 1 7666
Protoss_Zealot 3 9916
Protoss_Shuttle 1 8764
Protoss_Photon_Cannon 4 10392
10836
