Protoss_Gateway 2 4913
Protoss_Assimilator 1 3368
Protoss_Cybernetics_Core 1 4487
Protoss_Dragoon 12 10466
Protoss_Nexus 1 10725
Protoss_Zealot 2 9221
Protoss_Robotics_Facility 1 10764
10764
