Protoss_Gateway 1 3375
Protoss_Assimilator 1 3435
Protoss_Cybernetics_Core 1 4537
Protoss_Zealot 1 4171
Protoss_Dragoon 7 10532
Protoss_Robotics_Facility 1 6937
Protoss_Observatory 1 7219
Protoss_Observer 2 8633
Protoss_Shuttle 1 9971
Protoss_Nexus 1 12651
Protoss_Citadel_of_Adun 1 11280
12651
