Protoss_Gateway 2 6628
Protoss_Assimilator 1 3297
Protoss_Cybernetics_Core 1 4518
Protoss_Zealot 1 4961
Protoss_Citadel_of_Adun 1 5897
Protoss_Robotics_Facility 1 6886
Protoss_Templar_Archives 1 7073
Protoss_Shuttle 1 7711
Protoss_Dark_Templar 4 9256
Protoss_Forge 1 7900
Protoss_Photon_Cannon 2 10256
Protoss_Dragoon 4 10986
Protoss_Observatory 1 10174
10986
