Protoss_Gateway 2 5833
Protoss_Assimilator 1 3607
Protoss_Zealot 2 4981
Protoss_Cybernetics_Core 1 5158
Protoss_Dragoon 11 11096
Protoss_Nexus 2 11195
Protoss_Robotics_Facility 1 11452
11452
