Protoss_Gateway 2 7939
Protoss_Assimilator 1 3448
Protoss_Cybernetics_Core 1 4524
Protoss_Dragoon 3 10546
Protoss_Robotics_Facility 1 6904
Protoss_Citadel_of_Adun 1 6752
Protoss_Templar_Archives 1 7770
Protoss_Observatory 1 7479
Protoss_Observer 1 8261
Protoss_Dark_Templar 4 9771
Protoss_Shuttle 1 9343
Protoss_Nexus 1 12775
12775
