Protoss_Gateway 2 5842
Protoss_Assimilator 1 3281
Protoss_Zealot 3 5019
Protoss_Cybernetics_Core 1 5479
Protoss_Dragoon 10 10613
Protoss_Nexus 1 10836
Protoss_Robotics_Facility 1 10875
10875
