Protoss_Gateway 3 11370
Protoss_Assimilator 1 3361
Protoss_Cybernetics_Core 1 4383
Protoss_Dragoon 8 11197
Protoss_Robotics_Facility 1 7401
Protoss_Observatory 1 7510
Protoss_Observer 2 8983
Protoss_Nexus 1 10537
Protoss_Zealot 4 9529
Protoss_Shuttle 1 10233
11370
