Protoss_Gateway 3 11246
Protoss_Assimilator 1 3338
Protoss_Cybernetics_Core 1 4461
Protoss_Dragoon 11 10876
Protoss_Robotics_Facility 1 7401
Protoss_Observatory 1 7508
Protoss_Observer 3 10943
Protoss_Nexus 1 11063
Protoss_Shuttle 1 10521
11246
