Protoss_Nexus 2 8379
Protoss_Gateway 4 9941
Protoss_Zealot 6 9005
Protoss_Assimilator 1 4485
Protoss_Cybernetics_Core 1 4875
Protoss_Dragoon 9 9771
Protoss_Robotics_Facility 1 8919
9941
