Protoss_Nexus 2 2883
Protoss_Gateway 4 8887
Protoss_Assimilator 2 8645
Protoss_Cybernetics_Core 1 4537
Protoss_Dragoon 11 9875
Protoss_Robotics_Facility 1 7166
Protoss_Zealot 4 9939
Protoss_Observatory 1 8499
Protoss_Citadel_of_Adun 1 8967
Protoss_Observer 1 9775
9939
