Protoss_Nexus 2 7989
Protoss_Gateway 2 2567
Protoss_Zealot 5 4871
Protoss_Assimilator 1 4429
Protoss_Cybernetics_Core 1 5093
Protoss_Robotics_Facility 1 6188
Protoss_Dragoon 1 6531
Protoss_Shuttle 1 7481
Protoss_Robotics_Support_Bay 1 7513
Protoss_Reaver 1 8383
Protoss_Observatory 1 8778
Protoss_Observer 1 9435
9435
