Protoss_Nexus 2 5363
Protoss_Gateway 2 2531
Protoss_Zealot 7 6639
Protoss_Assimilator 2 8583
Protoss_Cybernetics_Core 1 6480
Protoss_Citadel_of_Adun 1 7523
Protoss_Forge 1 7986
Protoss_Dragoon 2 8233
Protoss_Templar_Archives 1 8721
Protoss_Photon_Cannon 1 8868
Protoss_Dark_Templar 2 9705
9705
