Protoss_Nexus 2 9230
Protoss_Gateway 2 6411
Protoss_Zealot 3 4161
Protoss_Assimilator 1 3130
Protoss_Cybernetics_Core 1 3933
Protoss_Dragoon 8 9997
Protoss_Robotics_Facility 1 6997
Protoss_Observatory 1 8408
Protoss_Observer 2 9541
Protoss_Robotics_Support_Bay 1 9789
9997
