Protoss_Nexus 1 0
Protoss_Gateway 3 6969
Protoss_Assimilator 1 2926
Protoss_Zealot 2 3673
Protoss_Cybernetics_Core 1 4033
Protoss_Dragoon 12 9847
Protoss_Robotics_Facility 1 6035
Protoss_Observatory 1 7389
Protoss_Observer 3 9573
9847
