Protoss_Nexus 1 0
Protoss_Gateway 3 9035
Protoss_Assimilator 1 2534
Protoss_Zealot 3 4373
Protoss_Cybernetics_Core 1 4902
Protoss_Dragoon 7 8768
Protoss_Robotics_Facility 1 6473
Protoss_Observatory 1 7865
Protoss_Observer 2 9303
9303
