Protoss_Nexus 1 0
Protoss_Gateway 2 4327
Protoss_Assimilator 1 2538
Protoss_Zealot 1 2951
Protoss_Cybernetics_Core 1 3688
Protoss_Dragoon 9 9706
Protoss_Robotics_Facility 1 5983
Protoss_Robotics_Support_Bay 1 7374
Protoss_Shuttle 1 7551
Protoss_Reaver 1 8571
9706
