Protoss_Nexus 1 0
Protoss_Gateway 2 5153
Protoss_Zealot 3 4461
Protoss_Assimilator 1 3483
Protoss_Cybernetics_Core 1 4268
Protoss_Dragoon 11 9870
Protoss_Robotics_Facility 1 8133
Protoss_Robotics_Support_Bay 1 9483
Protoss_Shuttle 1 9491
Protoss_Observatory 1 9588
9870
