Protoss_Nexus 3 8036
Protoss_Gateway 3 5338
Protoss_Assimilator 1 4047
Protoss_Cybernetics_Core 1 4351
Protoss_Dragoon 5 8566
Protoss_Zealot 3 9111
Protoss_Robotics_Facility 1 7518
Protoss_Citadel_of_Adun 1 8298
Protoss_Observatory 1 8833
Protoss_Shuttle 1 9106
Protoss_Forge 1 9921
9921
