Protoss_Nexus 1 0
Protoss_Gateway 2 2614
Protoss_Zealot 6 6428
Protoss_Assimilator 1 4761
Protoss_Cybernetics_Core 1 5159
Protoss_Robotics_Facility 1 7714
Protoss_Dragoon 5 9845
Protoss_Robotics_Support_Bay 1 9325
9845
