Protoss_Nexus 1 0
Protoss_Gateway 2 3813
Protoss_Zealot 7 5956
Protoss_Assimilator 1 4649
Protoss_Cybernetics_Core 1 5429
Protoss_Dragoon 10 9668
Protoss_Robotics_Facility 1 9257
9668
