Protoss_Nexus 2 9730
Protoss_Gateway 2 9469
Protoss_Zealot 3 4511
Protoss_Assimilator 1 3458
Protoss_Cybernetics_Core 1 4047
Protoss_Dragoon 6 9931
Protoss_Robotics_Facility 1 5853
Protoss_Shuttle 1 7216
Protoss_Observatory 1 7333
Protoss_Observer 1 8118
Protoss_Robotics_Support_Bay 1 8437
Protoss_Reaver 1 9396
9931
