Protoss_Nexus 1 0
Protoss_Gateway 2 7590
Protoss_Zealot 3 4516
Protoss_Assimilator 1 3272
Protoss_Cybernetics_Core 1 4132
Protoss_Dragoon 8 9663
Protoss_Robotics_Facility 1 6653
Protoss_Observatory 1 8070
Protoss_Observer 1 9016
Protoss_Robotics_Support_Bay 1 9355
9663
