Protoss_Nexus 2 6833
Protoss_Gateway 5 9669
Protoss_Assimilator 1 2533
Protoss_Cybernetics_Core 1 3244
Protoss_Dragoon 8 9413
Protoss_Robotics_Facility 1 5065
Protoss_Observatory 1 6558
Protoss_Observer 2 8261
9669
