Protoss_Nexus 2 9837
Protoss_Gateway 2 5820
Protoss_Assimilator 1 2259
Protoss_Cybernetics_Core 1 3562
Protoss_Zealot 1 3991
Protoss_Dragoon 11 9577
Protoss_Robotics_Facility 1 7450
Protoss_Robotics_Support_Bay 1 9611
9837
