Protoss_Nexus 1 0
Protoss_Gateway 4 7264
Protoss_Assimilator 1 2538
Protoss_Cybernetics_Core 1 3088
Protoss_Dragoon 12 9996
Protoss_Robotics_Facility 1 5173
Protoss_Observatory 1 6463
Protoss_Observer 1 6996
Protoss_Zealot 6 9226
9996
