Protoss_Nexus 1 0
Protoss_Gateway 3 7244
Protoss_Assimilator 1 2406
Protoss_Zealot 3 4467
Protoss_Cybernetics_Core 1 3550
Protoss_Dragoon 12 9899
Protoss_Robotics_Facility 1 7283
Protoss_Observatory 1 8925
9899
