Protoss_Nexus 1 0
Protoss_Gateway 3 6057
Protoss_Zealot 10 8738
Protoss_Assimilator 1 4336
Protoss_Cybernetics_Core 1 5215
Protoss_Dragoon 8 9641
Protoss_Robotics_Facility 1 8986
9641
