Protoss_Nexus 2 9792
Protoss_Gateway 2 3715
Protoss_Assimilator 1 2379
Protoss_Cybernetics_Core 1 2870
Protoss_Zealot 4 5423
Protoss_Dragoon 3 6625
Protoss_Citadel_of_Adun 1 6089
Protoss_Templar_Archives 1 7117
Protoss_Forge 1 7463
Protoss_Dark_Templar 2 8353
Protoss_Photon_Cannon 2 8581
9792
