Protoss_Nexus 3 9265
Protoss_Gateway 2 2531
Protoss_Zealot 11 8547
Protoss_Assimilator 2 7235
Protoss_Cybernetics_Core 1 5760
Protoss_Dragoon 2 6763
Protoss_Citadel_of_Adun 1 7154
Protoss_Templar_Archives 1 8267
Protoss_Forge 1 8279
Protoss_Dark_Templar 2 9501
Protoss_Photon_Cannon 2 9887
9887
