Protoss_Nexus 2 5201
Protoss_Gateway 2 2547
Protoss_Zealot 14 9431
Protoss_Assimilator 1 5848
Protoss_Cybernetics_Core 1 6423
Protoss_Citadel_of_Adun 1 7611
Protoss_Templar_Archives 1 8815
Protoss_Forge 1 8879
Protoss_Shield_Battery 1 9355
9431
