Protoss_Nexus 1 0
Protoss_Gateway 2 5226
Protoss_Assimilator 1 2344
Protoss_Zealot 3 4141
Protoss_Cybernetics_Core 1 3801
Protoss_Dragoon 6 7271
Protoss_Citadel_of_Adun 1 7631
Protoss_Robotics_Facility 1 8400
Protoss_Templar_Archives 1 8615
Protoss_Shuttle 1 9679
Protoss_Dark_Templar 2 9781
Protoss_Observatory 1 9979
9979
