Protoss_Nexus 2 4796
Protoss_Gateway 4 8852
Protoss_Zealot 5 6199
Protoss_Assimilator 2 7743
Protoss_Cybernetics_Core 1 5798
Protoss_Dragoon 5 9393
Protoss_Forge 1 7419
Protoss_Robotics_Facility 1 8442
Protoss_Photon_Cannon 1 9505
Protoss_Shuttle 1 9733
9733
