Protoss_Nexus 3 9651
Protoss_Gateway 4 8437
Protoss_Zealot 5 7055
Protoss_Assimilator 2 6893
Protoss_Cybernetics_Core 1 5764
Protoss_Citadel_of_Adun 1 6865
Protoss_Dragoon 1 6965
Protoss_Templar_Archives 1 7857
Protoss_Robotics_Facility 1 8158
Protoss_Forge 1 8739
Protoss_Dark_Templar 2 8893
Protoss_Observatory 1 9471
Protoss_Photon_Cannon 2 9964
Protoss_High_Templar 2 9749
9964
