Protoss_Nexus 2 8035
Protoss_Gateway 3 5819
Protoss_Zealot 5 6079
Protoss_Assimilator 2 9953
Protoss_Cybernetics_Core 1 4247
Protoss_Dragoon 6 9495
Protoss_Forge 1 7079
Protoss_Photon_Cannon 2 8987
Protoss_Citadel_of_Adun 1 8606
Protoss_Robotics_Facility 1 9272
Protoss_Templar_Archives 1 9715
9953
