Protoss_Nexus 1 0
Protoss_Assimilator 1 1658
Protoss_Gateway 1 2251
Protoss_Cybernetics_Core 1 3329
Protoss_Stargate 1 4341
Protoss_Robotics_Facility 1 4791
Protoss_Corsair 3 6680
Protoss_Shuttle 1 6096
Protoss_Forge 1 6937
Protoss_Dragoon 4 9651
Protoss_Photon_Cannon 2 9324
Protoss_Fleet_Beacon 1 9104
9651
