Protoss_Nexus 2 7323
Protoss_Gateway 3 8620
Protoss_Assimilator 1 2328
Protoss_Cybernetics_Core 1 3095
Protoss_Dragoon 12 9991
Protoss_Robotics_Facility 1 5978
Protoss_Observatory 1 7460
Protoss_Observer 2 8753
9991
