Protoss_Nexus 2 8268
Protoss_Gateway 2 2503
Protoss_Zealot 5 4566
Protoss_Assimilator 1 3818
Protoss_Cybernetics_Core 1 4203
Protoss_Dragoon 9 9918
Protoss_Forge 1 6892
Protoss_Photon_Cannon 2 8823
9918
