Protoss_Nexus 2 4183
Protoss_Gateway 4 8197
Protoss_Zealot 13 9503
Protoss_Assimilator 2 6598
Protoss_Cybernetics_Core 1 6050
Protoss_Dragoon 2 7163
Protoss_Citadel_of_Adun 1 7549
Protoss_Robotics_Facility 1 8814
Protoss_Forge 1 9669
9669
