Protoss_Nexus 2 4870
Protoss_Gateway 4 9745
Protoss_Zealot 5 6213
Protoss_Assimilator 2 6665
Protoss_Cybernetics_Core 1 5531
Protoss_Dragoon 6 9515
Protoss_Citadel_of_Adun 1 7505
Protoss_Robotics_Facility 1 8002
Protoss_Forge 1 8770
Protoss_Templar_Archives 1 8985
Protoss_Observatory 1 9456
Protoss_Photon_Cannon 1 9841
9841
