Protoss_Nexus 1 0
Protoss_Gateway 2 2437
Protoss_Zealot 9 5809
Protoss_Assimilator 1 4711
Protoss_Cybernetics_Core 1 5532
Protoss_Dragoon 10 9903
Protoss_Robotics_Facility 1 8683
9903
