Protoss_Nexus 1 0
Protoss_Assimilator 1 1896
Protoss_Gateway 1 2268
Protoss_Cybernetics_Core 1 3461
Protoss_Robotics_Facility 1 4453
Protoss_Dragoon 4 9403
Protoss_Robotics_Support_Bay 1 5763
Protoss_Shuttle 4 9831
Protoss_Reaver 1 6871
9831
