Protoss_Nexus 2 6678
Protoss_Gateway 3 8362
Protoss_Assimilator 1 2338
Protoss_Cybernetics_Core 1 2854
Protoss_Dragoon 8 8761
Protoss_Robotics_Facility 1 7744
Protoss_Robotics_Support_Bay 1 9376
Protoss_Zealot 2 9561
9561
