Protoss_Nexus 2 6140
Protoss_Gateway 3 7619
Protoss_Assimilator 1 2478
Protoss_Zealot 1 2901
Protoss_Cybernetics_Core 1 3821
Protoss_Dragoon 9 9593
Protoss_Robotics_Facility 1 7011
Protoss_Observatory 1 8352
Protoss_Observer 2 9541
Protoss_Citadel_of_Adun 1 9071
9593
