Protoss_Nexus 2 4475
Protoss_Gateway 2 5728
Protoss_Zealot 3 4085
Protoss_Assimilator 1 4370
Protoss_Cybernetics_Core 1 5096
Protoss_Forge 1 5405
Protoss_Dragoon 7 9879
Protoss_Photon_Cannon 3 9580
Protoss_Robotics_Facility 1 8415
Protoss_Observatory 1 9701
Protoss_Citadel_of_Adun 1 9976
9976
