Protoss_Nexus 1 0
Protoss_Gateway 3 8472
Protoss_Assimilator 1 2587
Protoss_Zealot 2 4139
Protoss_Cybernetics_Core 1 3986
Protoss_Dragoon 10 9769
Protoss_Robotics_Facility 1 7344
Protoss_Shuttle 1 8643
Protoss_Robotics_Support_Bay 1 9069
Protoss_Observatory 1 9187
Protoss_Reaver 1 9609
9769
