Protoss_Nexus 2 4867
Protoss_Gateway 4 9101
Protoss_Zealot 11 9263
Protoss_Assimilator 2 7994
Protoss_Cybernetics_Core 1 6240
Protoss_Citadel_of_Adun 1 7269
Protoss_Dragoon 2 7737
Protoss_Templar_Archives 1 8545
Protoss_Forge 1 9015
Protoss_Dark_Templar 2 9587
Protoss_Photon_Cannon 2 9874
9874
