Protoss_Nexus 2 5204
Protoss_Gateway 2 2659
Protoss_Zealot 10 8585
Protoss_Assimilator 2 7697
Protoss_Cybernetics_Core 1 6583
Protoss_Citadel_of_Adun 1 7588
Protoss_Robotics_Facility 1 8533
Protoss_Templar_Archives 1 9062
Protoss_Forge 1 9756
Protoss_Dragoon 2 9859
Protoss_Observatory 1 9868
9868
