Protoss_Nexus 1 0
Protoss_Gateway 3 9639
Protoss_Zealot 10 7331
Protoss_Assimilator 1 4903
Protoss_Cybernetics_Core 1 6673
Protoss_Dragoon 6 9991
Protoss_Robotics_Facility 1 8827
9991
