Protoss_Nexus 1 0
Protoss_Gateway 2 7171
Protoss_Zealot 2 3883
Protoss_Assimilator 1 3033
Protoss_Cybernetics_Core 1 3557
Protoss_Dragoon 10 9913
Protoss_Robotics_Facility 1 6143
Protoss_Shuttle 1 7421
Protoss_Robotics_Support_Bay 1 7507
Protoss_Reaver 2 9661
Protoss_Observatory 1 9377
9913
