Protoss_Nexus 2 9215
Protoss_Gateway 3 7767
Protoss_Assimilator 1 2413
Protoss_Zealot 2 3955
Protoss_Cybernetics_Core 1 3661
Protoss_Dragoon 11 9611
Protoss_Robotics_Facility 1 5679
Protoss_Observatory 1 7051
Protoss_Observer 3 8863
9611
