Protoss_Nexus 1 0
Protoss_Gateway 2 6950
Protoss_Assimilator 1 2261
Protoss_Zealot 3 4087
Protoss_Cybernetics_Core 1 3747
Protoss_Dragoon 9 8989
Protoss_Robotics_Facility 1 6806
Protoss_Shuttle 1 8121
Protoss_Observatory 1 8188
Protoss_Robotics_Support_Bay 1 8779
Protoss_Observer 1 9023
Protoss_Reaver 1 9625
9625
