Protoss_Nexus 2 8923
Protoss_Gateway 3 9597
Protoss_Assimilator 1 2211
Protoss_Cybernetics_Core 1 2908
Protoss_Zealot 1 3153
Protoss_Dragoon 8 9869
Protoss_Citadel_of_Adun 1 4914
Protoss_Robotics_Facility 1 5056
Protoss_Templar_Archives 1 5999
Protoss_Shuttle 1 6439
Protoss_Dark_Templar 2 7003
9869
