Protoss_Nexus 2 5641
Protoss_Gateway 4 9899
Protoss_Assimilator 2 8627
Protoss_Cybernetics_Core 1 2788
Protoss_Zealot 1 3089
Protoss_Dragoon 12 9659
Protoss_Robotics_Facility 1 7713
Protoss_Observatory 1 9021
Protoss_Observer 1 9553
9899
