Protoss_Nexus 1 0
Protoss_Gateway 3 9563
Protoss_Assimilator 1 2518
Protoss_Zealot 10 7191
Protoss_Cybernetics_Core 1 6563
Protoss_Dragoon 5 9281
Protoss_Robotics_Facility 1 8843
9563
