Protoss_Nexus 2 6867
Protoss_Gateway 3 9969
Protoss_Zealot 3 4763
Protoss_Assimilator 2 9538
Protoss_Cybernetics_Core 1 3566
Protoss_Citadel_of_Adun 1 4618
Protoss_Dragoon 1 5365
Protoss_Templar_Archives 1 5622
Protoss_Forge 1 5784
Protoss_Dark_Templar 2 7619
Protoss_Photon_Cannon 6 9767
Protoss_High_Templar 2 9541
9969
