Protoss_Nexus 1 0
Protoss_Gateway 4 9895
Protoss_Assimilator 1 2317
Protoss_Cybernetics_Core 1 2865
Protoss_Dragoon 14 9821
Protoss_Robotics_Facility 1 6167
Protoss_Observatory 1 7508
Protoss_Observer 2 8655
9895
