Protoss_Nexus 1 0
Protoss_Gateway 2 2245
Protoss_Zealot 12 8341
Protoss_Shield_Battery 2 5585
Protoss_Forge 1 5223
Protoss_Photon_Cannon 4 7892
Protoss_Assimilator 1 7742
Protoss_Cybernetics_Core 1 8734
Protoss_Stargate 1 9873
9873
