Protoss_Nexus 2 5602
Protoss_Gateway 2 2423
Protoss_Zealot 19 9601
Protoss_Assimilator 2 8666
Protoss_Cybernetics_Core 1 6939
Protoss_Citadel_of_Adun 1 8481
Protoss_Templar_Archives 1 9544
9601
