Protoss_Nexus 2 4969
Protoss_Gateway 2 2463
Protoss_Zealot 7 7769
Protoss_Assimilator 2 6388
Protoss_Cybernetics_Core 1 5551
Protoss_Citadel_of_Adun 1 6629
Protoss_Dragoon 2 6795
Protoss_Templar_Archives 1 7667
Protoss_Robotics_Facility 1 8127
Protoss_High_Templar 4 9791
Protoss_Forge 1 8810
Protoss_Shuttle 1 9429
Protoss_Photon_Cannon 2 9736
9791
