Protoss_Nexus 1 0
Protoss_Gateway 4 5466
Protoss_Zealot 12 9761
Protoss_Shield_Battery 1 3934
Protoss_Forge 1 6392
Protoss_Assimilator 1 6929
Protoss_Photon_Cannon 4 9448
Protoss_Cybernetics_Core 1 8011
Protoss_Robotics_Facility 2 9715
9761
