Protoss_Nexus 1 0
Protoss_Gateway 2 3525
Protoss_Assimilator 1 2243
Protoss_Cybernetics_Core 1 2911
Protoss_Dragoon 9 7447
Protoss_Robotics_Facility 1 5951
Protoss_Observatory 1 7297
Protoss_Observer 1 7841
Protoss_Zealot 4 9095
Protoss_Shuttle 1 8447
Protoss_Robotics_Support_Bay 1 8749
Protoss_Reaver 1 9399
9399
