Protoss_Nexus 2 4956
Protoss_Gateway 4 9631
Protoss_Zealot 6 7305
Protoss_Assimilator 2 7641
Protoss_Cybernetics_Core 1 5594
Protoss_Dragoon 1 6793
Protoss_Citadel_of_Adun 1 7035
Protoss_Forge 1 7739
Protoss_Templar_Archives 1 8133
Protoss_Photon_Cannon 1 9001
Protoss_Dark_Templar 2 9119
Protoss_Robotics_Facility 1 9458
9631
