Protoss_Nexus 3 8661
Protoss_Gateway 2 2340
Protoss_Zealot 6 5545
Protoss_Assimilator 1 4028
Protoss_Cybernetics_Core 1 4723
Protoss_Dragoon 7 9881
Protoss_Robotics_Facility 1 8947
9881
