Protoss_Nexus 3 8951
Protoss_Gateway 2 7438
Protoss_Assimilator 1 2283
Protoss_Cybernetics_Core 1 2938
Protoss_Dragoon 6 9721
Protoss_Citadel_of_Adun 1 5035
Protoss_Templar_Archives 1 6127
Protoss_Dark_Templar 2 7891
Protoss_High_Templar 2 8643
Protoss_Forge 1 9506
9721
