Protoss_Nexus 2 6007
Protoss_Gateway 2 2447
Protoss_Zealot 19 9255
Protoss_Assimilator 2 8849
Protoss_Cybernetics_Core 1 7415
Protoss_Citadel_of_Adun 1 8710
Protoss_Robotics_Facility 1 9641
Protoss_Forge 1 9983
9983
