Protoss_Nexus 2 9059
Protoss_Gateway 1 1815
Protoss_Assimilator 1 2215
Protoss_Cybernetics_Core 1 2916
Protoss_Dragoon 6 9941
Protoss_Robotics_Facility 1 5472
Protoss_Shuttle 1 6751
Protoss_Robotics_Support_Bay 1 6865
Protoss_Reaver 1 7689
Protoss_Observatory 1 8763
Protoss_Observer 1 9555
9941
