Protoss_Nexus 2 6931
Protoss_Gateway 3 9690
Protoss_Zealot 3 4617
Protoss_Assimilator 1 3144
Protoss_Cybernetics_Core 1 4071
Protoss_Dragoon 6 9763
Protoss_Robotics_Facility 1 7168
Protoss_Observatory 1 8509
Protoss_Observer 1 9203
9763
