Protoss_Nexus 2 9436
Protoss_Gateway 2 3981
Protoss_Zealot 1 2827
Protoss_Assimilator 1 2977
Protoss_Cybernetics_Core 1 3579
Protoss_Dragoon 12 9789
Protoss_Robotics_Facility 1 7295
Protoss_Shuttle 1 8857
Protoss_Observatory 1 8930
Protoss_Observer 1 9513
Protoss_Robotics_Support_Bay 1 9657
9789
