Protoss_Nexus 2 6987
Protoss_Gateway 2 8812
Protoss_Assimilator 2 9418
Protoss_Zealot 2 3933
Protoss_Cybernetics_Core 1 3667
Protoss_Dragoon 6 9811
Protoss_Citadel_of_Adun 1 5097
Protoss_Templar_Archives 1 6117
Protoss_Dark_Templar 2 8005
Protoss_Robotics_Facility 1 8550
9811
