Protoss_Nexus 2 7741
Protoss_Gateway 1 2009
Protoss_Assimilator 1 2364
Protoss_Cybernetics_Core 1 3039
Protoss_Robotics_Facility 1 4431
Protoss_Dragoon 5 9173
Protoss_Shuttle 1 5771
Protoss_Observatory 1 5845
Protoss_Observer 2 7275
Protoss_Zealot 1 8043
9173
