Protoss_Nexus 1 0
Protoss_Gateway 3 8829
Protoss_Zealot 2 4181
Protoss_Assimilator 1 3293
Protoss_Cybernetics_Core 1 4095
Protoss_Dragoon 8 9906
Protoss_Robotics_Facility 1 5298
Protoss_Shuttle 1 6591
Protoss_Observatory 1 6761
Protoss_Robotics_Support_Bay 1 7330
Protoss_Observer 1 7501
Protoss_Reaver 2 9166
9906
