Protoss_Nexus 2 9677
Protoss_Gateway 2 4608
Protoss_Assimilator 2 2697
Protoss_Cybernetics_Core 1 3343
Protoss_Zealot 1 3559
Protoss_Dragoon 9 8789
Protoss_Citadel_of_Adun 1 7403
Protoss_Templar_Archives 1 8994
Protoss_Forge 1 8997
9677
