Protoss_Nexus 1 0
Protoss_Gateway 2 8696
Protoss_Assimilator 1 2468
Protoss_Cybernetics_Core 1 3119
Protoss_Zealot 3 9811
Protoss_Dragoon 2 5451
Protoss_Robotics_Facility 1 5899
Protoss_Citadel_of_Adun 1 6701
Protoss_Observatory 1 7232
Protoss_Forge 1 7257
Protoss_Templar_Archives 1 7699
Protoss_Observer 1 7946
Protoss_Photon_Cannon 1 8803
Protoss_High_Templar 2 9683
Protoss_Shuttle 1 9156
9811
