Protoss_Nexus 3 9502
Protoss_Gateway 1 1871
Protoss_Zealot 2 3927
Protoss_Assimilator 1 3292
Protoss_Cybernetics_Core 1 3609
Protoss_Dragoon 7 9729
Protoss_Robotics_Facility 1 5761
Protoss_Shuttle 1 7041
Protoss_Observatory 1 7652
Protoss_Observer 1 8185
Protoss_Robotics_Support_Bay 1 8553
Protoss_Reaver 1 9903
9903
