Protoss_Nexus 1 0
Protoss_Gateway 1 1893
Protoss_Assimilator 1 2271
Protoss_Cybernetics_Core 1 2957
Protoss_Robotics_Facility 2 8926
Protoss_Zealot 2 4873
Protoss_Shuttle 2 8927
Protoss_Dragoon 5 9185
Protoss_Robotics_Support_Bay 1 5862
Protoss_Reaver 2 7829
Protoss_Scarab 4 8734
Protoss_Observatory 1 9600
9600
