Protoss_Nexus 2 8571
Protoss_Gateway 2 2474
Protoss_Zealot 10 6606
Protoss_Shield_Battery 1 5066
Protoss_Assimilator 1 9004
Protoss_Forge 1 9118
Protoss_Photon_Cannon 1 9993
9993
