Protoss_Nexus 2 7315
Protoss_Gateway 3 8977
Protoss_Assimilator 1 2560
Protoss_Zealot 2 3981
Protoss_Cybernetics_Core 1 3725
Protoss_Dragoon 10 9355
Protoss_Robotics_Facility 1 7571
Protoss_Observatory 1 8883
Protoss_Observer 1 9431
9431
