Protoss_Nexus 2 9529
Protoss_Gateway 2 4161
Protoss_Assimilator 1 2323
Protoss_Zealot 1 2903
Protoss_Cybernetics_Core 1 3747
Protoss_Dragoon 9 9829
Protoss_Citadel_of_Adun 1 5852
Protoss_Templar_Archives 1 6865
Protoss_Forge 1 7318
Protoss_Dark_Templar 3 8607
Protoss_Photon_Cannon 1 8222
9829
