Protoss_Nexus 2 6386
Protoss_Gateway 2 7571
Protoss_Assimilator 2 8938
Protoss_Zealot 2 4075
Protoss_Cybernetics_Core 1 3757
Protoss_Dragoon 8 9485
Protoss_Robotics_Facility 1 7303
Protoss_Observatory 1 8605
Protoss_Citadel_of_Adun 1 8879
Protoss_Observer 2 9821
Protoss_Templar_Archives 1 9892
Protoss_Forge 1 9997
9997
