Protoss_Nexus 2 7468
Protoss_Gateway 3 8533
Protoss_Assimilator 1 3038
Protoss_Zealot 3 9541
Protoss_Cybernetics_Core 1 3767
Protoss_Dragoon 8 9936
Protoss_Robotics_Facility 1 6126
Protoss_Observatory 1 7609
Protoss_Observer 1 8211
Protoss_Shuttle 1 9391
9936
