Protoss_Nexus 2 6540
Protoss_Gateway 3 9342
Protoss_Zealot 3 4129
Protoss_Assimilator 2 8808
Protoss_Cybernetics_Core 1 3820
Protoss_Dragoon 10 9759
Protoss_Robotics_Facility 1 7445
Protoss_Observatory 1 8742
Protoss_Observer 2 9879
Protoss_Citadel_of_Adun 1 9541
9879
