Protoss_Nexus 2 5050
Protoss_Gateway 4 8755
Protoss_Zealot 7 9857
Protoss_Assimilator 2 7743
Protoss_Cybernetics_Core 1 6227
Protoss_Dragoon 1 7385
Protoss_Forge 1 8028
Protoss_Robotics_Facility 1 8323
Protoss_Citadel_of_Adun 1 8752
Protoss_Photon_Cannon 2 9235
Protoss_Observatory 1 9647
Protoss_Templar_Archives 1 9812
9857
