Protoss_Nexus 1 0
Protoss_Gateway 3 7669
Protoss_Zealot 3 5739
Protoss_Assimilator 1 4155
Protoss_Cybernetics_Core 1 5582
Protoss_Dragoon 8 9119
Protoss_Robotics_Facility 1 7996
Protoss_Observatory 1 9387
Protoss_Observer 1 9923
9923
