Protoss_Nexus 2 6087
Protoss_Gateway 2 6616
Protoss_Assimilator 1 2460
Protoss_Zealot 1 2999
Protoss_Cybernetics_Core 1 3167
Protoss_Dragoon 10 9833
Protoss_Robotics_Facility 1 7323
Protoss_Citadel_of_Adun 1 8566
Protoss_Observatory 1 9532
9833
