Protoss_Nexus 2 8647
Protoss_Gateway 2 7273
Protoss_Assimilator 1 2428
Protoss_Zealot 2 3671
Protoss_Cybernetics_Core 1 3991
Protoss_Dragoon 7 9731
Protoss_Robotics_Facility 1 6498
Protoss_Observatory 1 7837
Protoss_Observer 3 9581
9731
