Protoss_Nexus 1 0
Protoss_Gateway 2 5912
Protoss_Zealot 7 8825
Protoss_Assimilator 1 4305
Protoss_Cybernetics_Core 1 5355
Protoss_Robotics_Facility 1 6383
Protoss_Dragoon 5 9621
Protoss_Shuttle 1 7671
Protoss_Robotics_Support_Bay 1 7727
Protoss_Reaver 1 8573
Protoss_Observatory 1 9568
9621
