Protoss_Nexus 2 4798
Protoss_Gateway 3 9018
Protoss_Zealot 8 8503
Protoss_Assimilator 2 7155
Protoss_Cybernetics_Core 1 6268
Protoss_Dragoon 1 7269
Protoss_Citadel_of_Adun 1 7360
Protoss_Robotics_Facility 1 7981
Protoss_Templar_Archives 1 8521
Protoss_Forge 1 8734
Protoss_Shuttle 1 9261
Protoss_Observatory 1 9314
Protoss_Dark_Templar 2 9547
Protoss_Photon_Cannon 2 9793
9793
