Protoss_Nexus 1 0
Protoss_Gateway 2 4549
Protoss_Assimilator 1 2211
Protoss_Cybernetics_Core 1 3091
Protoss_Zealot 1 3653
Protoss_Dragoon 12 9831
Protoss_Robotics_Facility 1 5694
Protoss_Shuttle 1 7019
Protoss_Robotics_Support_Bay 1 7636
Protoss_Reaver 2 9495
Protoss_Observatory 1 8605
9831
