Protoss_Nexus 2 4725
Protoss_Gateway 3 9131
Protoss_Zealot 10 7905
Protoss_Assimilator 2 7351
Protoss_Cybernetics_Core 1 6041
Protoss_Citadel_of_Adun 1 7111
Protoss_Dragoon 1 7713
Protoss_Templar_Archives 1 8242
Protoss_Forge 1 8619
Protoss_Dark_Templar 2 9229
Protoss_Photon_Cannon 3 9735
9735
