Protoss_Nexus 1 0
Protoss_Gateway 2 6618
Protoss_Assimilator 1 2346
Protoss_Zealot 2 3853
Protoss_Cybernetics_Core 1 3545
Protoss_Dragoon 9 9259
Protoss_Robotics_Facility 1 5817
Protoss_Shuttle 1 7101
Protoss_Observatory 1 7597
Protoss_Robotics_Support_Bay 1 7954
Protoss_Observer 1 8175
Protoss_Reaver 1 8873
9259
