Protoss_Nexus 2 8423
Protoss_Gateway 3 9521
Protoss_Assimilator 1 2425
Protoss_Zealot 3 4217
Protoss_Cybernetics_Core 1 3828
Protoss_Dragoon 8 9733
Protoss_Robotics_Facility 1 6010
Protoss_Shuttle 1 7347
Protoss_Observatory 1 7449
Protoss_Robotics_Support_Bay 1 8039
Protoss_Observer 1 8249
Protoss_Reaver 2 9903
9903
