Protoss_Nexus 2 6513
Protoss_Gateway 3 8432
Protoss_Zealot 2 3907
Protoss_Assimilator 2 9965
Protoss_Cybernetics_Core 1 3577
Protoss_Dragoon 9 9661
Protoss_Robotics_Facility 1 6885
Protoss_Observatory 1 8269
Protoss_Observer 2 9811
Protoss_Citadel_of_Adun 1 9240
9965
