Protoss_Nexus 2 7277
Protoss_Gateway 3 8517
Protoss_Assimilator 1 2436
Protoss_Zealot 6 8731
Protoss_Cybernetics_Core 1 3687
Protoss_Dragoon 6 9637
Protoss_Robotics_Facility 1 7754
Protoss_Observatory 1 9135
Protoss_Observer 1 9681
9681
