Protoss_Nexus 2 7370
Protoss_Assimilator 1 1678
Protoss_Gateway 2 7764
Protoss_Cybernetics_Core 1 3441
Protoss_Robotics_Facility 1 4469
Protoss_Dragoon 9 9515
Protoss_Shuttle 2 8356
Protoss_Observatory 1 7586
Protoss_Robotics_Support_Bay 1 8644
Protoss_Observer 1 9591
9591
