Protoss_Nexus 1 0
Protoss_Gateway 2 8792
Protoss_Assimilator 1 2235
Protoss_Cybernetics_Core 1 2883
Protoss_Robotics_Facility 1 4109
Protoss_Dragoon 3 9796
Protoss_Shuttle 1 5416
Protoss_Zealot 3 6993
Protoss_Robotics_Support_Bay 1 5998
Protoss_Reaver 2 8290
Protoss_Scarab 5 8489
Protoss_Forge 1 8734
Protoss_Photon_Cannon 3 9965
9965
