Protoss_Nexus 2 6078
Protoss_Gateway 2 7657
Protoss_Assimilator 1 2352
Protoss_Zealot 1 2839
Protoss_Cybernetics_Core 1 3751
Protoss_Dragoon 7 8985
Protoss_Robotics_Facility 1 7101
Protoss_Observatory 1 8393
Protoss_Observer 1 8947
8985
