Protoss_Nexus 1 0
Protoss_Gateway 3 7959
Protoss_Assimilator 1 2445
Protoss_Cybernetics_Core 1 2993
Protoss_Zealot 1 3411
Protoss_Dragoon 13 9825
Protoss_Citadel_of_Adun 1 5771
Protoss_Templar_Archives 1 6761
Protoss_Dark_Templar 2 8229
9825
