Protoss_Nexus 1 0
Protoss_Gateway 2 2771
Protoss_Zealot 11 7216
Protoss_Assimilator 1 4973
Protoss_Cybernetics_Core 1 7433
Protoss_Citadel_of_Adun 1 8530
Protoss_Dragoon 4 9583
Protoss_Templar_Archives 1 9548
9583
