Protoss_Nexus 2 5160
Protoss_Gateway 4 9537
Protoss_Zealot 5 5441
Protoss_Assimilator 2 7625
Protoss_Cybernetics_Core 1 6061
Protoss_Dragoon 8 9837
Protoss_Citadel_of_Adun 1 7841
Protoss_Robotics_Facility 1 8967
Protoss_Templar_Archives 1 9503
9837
