Protoss_Nexus 1 0
Protoss_Gateway 3 8312
Protoss_Assimilator 1 2231
Protoss_Cybernetics_Core 1 2920
Protoss_Dragoon 14 9757
Protoss_Robotics_Facility 1 6978
Protoss_Observatory 1 8281
Protoss_Zealot 2 9041
Protoss_Observer 2 9694
9757
