Protoss_Nexus 2 8103
Protoss_Gateway 2 5588
Protoss_Assimilator 1 2271
Protoss_Zealot 2 3539
Protoss_Cybernetics_Core 1 3287
Protoss_Dragoon 11 9387
Protoss_Robotics_Facility 1 7108
Protoss_Observatory 1 8600
Protoss_Observer 1 9153
9387
