Protoss_Nexus 2 9646
Protoss_Gateway 2 6769
Protoss_Zealot 3 4143
Protoss_Assimilator 1 2955
Protoss_Cybernetics_Core 1 3892
Protoss_Dragoon 9 9775
Protoss_Citadel_of_Adun 1 5117
Protoss_Templar_Archives 1 6141
Protoss_Dark_Templar 1 7155
9775
