Protoss_Nexus 1 0
Protoss_Gateway 2 2528
Protoss_Zealot 10 7011
Protoss_Assimilator 1 4605
Protoss_Cybernetics_Core 1 6927
Protoss_Dragoon 6 9738
Protoss_Robotics_Facility 1 8465
9738
