Protoss_Nexus 2 7355
Protoss_Gateway 2 2513
Protoss_Zealot 9 5801
Protoss_Assimilator 1 4448
Protoss_Cybernetics_Core 1 5291
Protoss_Dragoon 8 9341
Protoss_Robotics_Facility 1 8861
9341
