Protoss_Nexus 1 0
Protoss_Gateway 2 4960
Protoss_Assimilator 1 2578
Protoss_Zealot 3 4366
Protoss_Cybernetics_Core 1 3992
Protoss_Dragoon 4 8441
Protoss_Citadel_of_Adun 1 5619
Protoss_Templar_Archives 1 6666
Protoss_Dark_Templar 2 7666
Protoss_Robotics_Facility 1 8834
Protoss_Forge 1 9412
9412
