Protoss_Nexus 1 0
Protoss_Gateway 1 1976
Protoss_Assimilator 1 2508
Protoss_Cybernetics_Core 1 3051
Protoss_Zealot 1 3381
Protoss_Dragoon 2 5406
Protoss_Shield_Battery 1 4796
5406
