Protoss_Nexus 2 8851
Protoss_Gateway 3 9954
Protoss_Assimilator 2 9813
Protoss_Cybernetics_Core 1 3078
Protoss_Dragoon 5 6837
Protoss_Citadel_of_Adun 1 5655
Protoss_Templar_Archives 1 6669
Protoss_Forge 1 7461
Protoss_Dark_Templar 2 7661
Protoss_Photon_Cannon 2 8245
Protoss_High_Templar 2 8965
9954
