Protoss_Nexus 2 6235
Protoss_Gateway 3 9447
Protoss_Assimilator 1 2323
Protoss_Cybernetics_Core 1 2841
Protoss_Zealot 1 3393
Protoss_Dragoon 10 9635
Protoss_Robotics_Facility 1 7704
Protoss_Observatory 1 9077
Protoss_Observer 1 9605
9635
