Protoss_Nexus 1 0
Protoss_Gateway 3 6447
Protoss_Assimilator 1 2411
Protoss_Cybernetics_Core 1 2925
Protoss_Zealot 1 3463
Protoss_Dragoon 16 9805
Protoss_Robotics_Facility 1 7926
Protoss_Shuttle 1 9641
Protoss_Robotics_Support_Bay 1 9653
9805
