Protoss_Nexus 2 9578
Protoss_Gateway 2 5143
Protoss_Assimilator 1 2371
Protoss_Zealot 3 6375
Protoss_Cybernetics_Core 1 3605
Protoss_Dragoon 7 8615
Protoss_Robotics_Facility 1 6153
Protoss_Shuttle 1 7437
Protoss_Observatory 1 7787
Protoss_Robotics_Support_Bay 1 7923
Protoss_Observer 1 8359
Protoss_Reaver 1 9297
9578
