Protoss_Nexus 2 9107
Protoss_Gateway 3 9824
Protoss_Assimilator 1 2310
Protoss_Zealot 2 3979
Protoss_Cybernetics_Core 1 3683
Protoss_Dragoon 9 9501
Protoss_Robotics_Facility 1 6295
Protoss_Observatory 1 7615
Protoss_Robotics_Support_Bay 1 8063
Protoss_Observer 1 8171
Protoss_Reaver 1 8983
9824
