Protoss_Nexus 1 0
Protoss_Gateway 2 7239
Protoss_Assimilator 1 2479
Protoss_Zealot 2 4273
Protoss_Cybernetics_Core 1 3905
Protoss_Dragoon 10 9983
Protoss_Robotics_Facility 1 6371
Protoss_Observatory 1 7681
Protoss_Observer 2 8827
Protoss_Shuttle 1 9429
Protoss_Robotics_Support_Bay 1 9547
9983
