Protoss_Nexus 1 0
Protoss_Gateway 4 9397
Protoss_Assimilator 1 2478
Protoss_Zealot 1 2951
Protoss_Cybernetics_Core 1 3848
Protoss_Dragoon 10 9276
Protoss_Robotics_Facility 1 7678
Protoss_Observatory 1 8996
Protoss_Observer 1 9536
9536
