Protoss_Nexus 2 8009
Protoss_Gateway 4 8951
Protoss_Assimilator 1 2318
Protoss_Cybernetics_Core 1 2853
Protoss_Zealot 2 6787
Protoss_Dragoon 9 9935
Protoss_Citadel_of_Adun 1 5275
Protoss_Templar_Archives 1 6328
Protoss_Dark_Templar 2 7459
9935
