Protoss_Nexus 1 0
Protoss_Gateway 1 1885
Protoss_Assimilator 1 2380
Protoss_Cybernetics_Core 1 3106
Protoss_Zealot 2 7245
Protoss_Dragoon 7 9670
Protoss_Robotics_Facility 1 5481
Protoss_Shuttle 1 6801
Protoss_Observatory 1 6806
Protoss_Robotics_Support_Bay 1 7586
Protoss_Observer 2 9357
Protoss_Reaver 2 9959
9959
