Protoss_Nexus 2 7003
Protoss_Gateway 2 8930
Protoss_Assimilator 1 2354
Protoss_Cybernetics_Core 1 2882
Protoss_Zealot 1 3455
Protoss_Dragoon 8 9847
Protoss_Robotics_Facility 1 5910
Protoss_Shuttle 1 7561
Protoss_Robotics_Support_Bay 1 7849
Protoss_Reaver 2 9853
Protoss_Observatory 1 9433
9853
