Protoss_Nexus 1 0
Protoss_Gateway 2 6648
Protoss_Assimilator 1 2488
Protoss_Zealot 5 9521
Protoss_Cybernetics_Core 1 4334
Protoss_Dragoon 2 6121
Protoss_Citadel_of_Adun 1 5960
Protoss_Robotics_Facility 1 6403
Protoss_Templar_Archives 1 7048
Protoss_Observatory 1 7813
Protoss_Shuttle 2 9338
Protoss_Dark_Templar 3 8818
Protoss_Observer 1 8736
Protoss_Forge 1 9182
9521
