Protoss_Nexus 2 7911
Protoss_Gateway 4 8783
Protoss_Assimilator 1 2209
Protoss_Zealot 2 3727
Protoss_Cybernetics_Core 1 3680
Protoss_Dragoon 8 9155
Protoss_Citadel_of_Adun 1 6240
Protoss_Templar_Archives 1 7225
Protoss_Dark_Templar 2 8357
9155
