Protoss_Nexus 2 5075
Protoss_Gateway 4 9113
Protoss_Assimilator 1 2399
Protoss_Cybernetics_Core 1 3028
Protoss_Zealot 1 3327
Protoss_Dragoon 8 9287
Protoss_Robotics_Facility 1 6044
Protoss_Observatory 1 7396
Protoss_Observer 1 7963
Protoss_Shuttle 1 8565
Protoss_Robotics_Support_Bay 1 8780
Protoss_Reaver 1 9533
9533
