Protoss_Nexus 2 9721
Protoss_Gateway 2 6726
Protoss_Assimilator 1 2333
Protoss_Zealot 2 3933
Protoss_Cybernetics_Core 1 3633
Protoss_Dragoon 8 8869
Protoss_Robotics_Facility 1 5862
Protoss_Shuttle 1 7197
Protoss_Observatory 1 7368
Protoss_Observer 2 9753
Protoss_Robotics_Support_Bay 1 8105
Protoss_Reaver 1 8701
9753
