Protoss_Nexus 3 9708
Protoss_Gateway 2 7078
Protoss_Assimilator 1 2309
Protoss_Cybernetics_Core 1 3124
Protoss_Robotics_Facility 1 4189
Protoss_Dragoon 8 8818
Protoss_Observatory 1 5614
Protoss_Observer 2 8091
Protoss_Forge 1 8267
Protoss_Photon_Cannon 1 9184
9708
