Protoss_Nexus 1 0
Protoss_Gateway 2 6697
Protoss_Assimilator 1 2378
Protoss_Zealot 2 3937
Protoss_Cybernetics_Core 1 3629
Protoss_Dragoon 9 8899
Protoss_Robotics_Facility 1 5839
Protoss_Shuttle 1 7221
Protoss_Observatory 1 7356
Protoss_Robotics_Support_Bay 1 8119
Protoss_Observer 2 9777
Protoss_Reaver 1 8725
9777
