Protoss_Nexus 2 7160
Protoss_Gateway 4 8017
Protoss_Assimilator 1 2215
Protoss_Cybernetics_Core 1 2875
Protoss_Zealot 1 3133
Protoss_Dragoon 13 9793
Protoss_Citadel_of_Adun 1 4754
9793
