Protoss_Nexus 2 4999
Protoss_Gateway 4 8393
Protoss_Zealot 11 8777
Protoss_Assimilator 2 7484
Protoss_Cybernetics_Core 1 6281
Protoss_Citadel_of_Adun 1 7414
Protoss_Templar_Archives 1 8449
Protoss_Dark_Templar 4 9633
Protoss_Forge 1 9871
9871
