Protoss_Nexus 2 5780
Protoss_Gateway 2 2391
Protoss_Zealot 11 8377
Protoss_Assimilator 2 8753
Protoss_Cybernetics_Core 1 6210
Protoss_Dragoon 2 7625
Protoss_Citadel_of_Adun 1 8208
Protoss_Robotics_Facility 1 9048
Protoss_Templar_Archives 1 9348
Protoss_Forge 1 9624
9624
