Protoss_Nexus 1 0
Protoss_Gateway 4 9756
Protoss_Zealot 17 9531
Protoss_Shield_Battery 1 3703
Protoss_Forge 1 7793
Protoss_Photon_Cannon 2 9072
Protoss_Assimilator 1 9233
9756
