Protoss_Nexus 1 0
Protoss_Gateway 2 6953
Protoss_Assimilator 1 2480
Protoss_Zealot 2 4095
Protoss_Cybernetics_Core 1 3797
Protoss_Dragoon 10 9785
Protoss_Robotics_Facility 1 6539
Protoss_Shuttle 1 7821
Protoss_Observatory 1 7900
Protoss_Robotics_Support_Bay 1 8546
Protoss_Observer 1 8723
Protoss_Reaver 1 9325
9785
