Protoss_Nexus 2 6119
Protoss_Gateway 3 8600
Protoss_Assimilator 1 2382
Protoss_Zealot 4 9299
Protoss_Cybernetics_Core 1 4545
Protoss_Dragoon 6 9599
Protoss_Robotics_Facility 1 7635
Protoss_Observatory 1 9039
Protoss_Robotics_Support_Bay 1 9402
9599
