Protoss_Nexus 1 0
Protoss_Gateway 2 6317
Protoss_Assimilator 1 2363
Protoss_Zealot 2 3939
Protoss_Cybernetics_Core 1 3661
Protoss_Dragoon 9 9755
Protoss_Robotics_Facility 1 5971
Protoss_Observatory 1 7375
Protoss_Shuttle 1 7605
Protoss_Robotics_Support_Bay 1 8313
Protoss_Observer 1 8507
Protoss_Reaver 1 9109
9755
