Protoss_Nexus 1 0
Protoss_Gateway 2 2445
Protoss_Assimilator 1 2757
Protoss_Cybernetics_Core 1 3691
Protoss_Zealot 2 4299
Protoss_Dragoon 13 9669
Protoss_Robotics_Facility 1 7631
Protoss_Observatory 1 9024
Protoss_Robotics_Support_Bay 1 9066
9669
