Protoss_Nexus 1 0
Protoss_Gateway 2 2508
Protoss_Zealot 13 9011
Protoss_Forge 1 5535
Protoss_Photon_Cannon 4 8581
Protoss_Assimilator 1 7815
Protoss_Cybernetics_Core 1 8921
Protoss_Robotics_Facility 1 9970
9970
