Protoss_Nexus 2 4945
Protoss_Gateway 4 8945
Protoss_Zealot 6 6221
Protoss_Assimilator 1 5036
Protoss_Cybernetics_Core 1 5506
Protoss_Dragoon 8 9983
Protoss_Robotics_Facility 1 7965
Protoss_Shuttle 1 9721
Protoss_Observatory 1 9805
9983
