Protoss_Nexus 2 8803
Protoss_Gateway 3 9709
Protoss_Assimilator 1 2345
Protoss_Zealot 2 4057
Protoss_Cybernetics_Core 1 3723
Protoss_Dragoon 7 9363
Protoss_Citadel_of_Adun 1 5345
Protoss_Templar_Archives 1 6384
Protoss_Forge 1 6967
Protoss_Dark_Templar 2 7369
Protoss_Photon_Cannon 1 7809
9709
