Protoss_Nexus 2 6297
Protoss_Gateway 3 9877
Protoss_Assimilator 2 8898
Protoss_Zealot 1 2979
Protoss_Cybernetics_Core 1 3912
Protoss_Dragoon 9 9439
Protoss_Robotics_Facility 1 6813
Protoss_Observatory 1 8306
Protoss_Observer 2 9969
Protoss_Citadel_of_Adun 1 9500
9969
