Protoss_Nexus 2 4778
Protoss_Gateway 4 9824
Protoss_Zealot 8 6529
Protoss_Assimilator 2 7085
Protoss_Cybernetics_Core 1 6111
Protoss_Dragoon 9 9955
Protoss_Robotics_Facility 1 8143
Protoss_Shuttle 1 9427
Protoss_Observatory 1 9509
9955
