Protoss_Nexus 2 8181
Protoss_Gateway 2 5147
Protoss_Assimilator 1 2376
Protoss_Cybernetics_Core 1 3273
Protoss_Zealot 5 9533
Protoss_Dragoon 9 9309
Protoss_Robotics_Facility 1 5711
Protoss_Observatory 1 7117
Protoss_Observer 2 8937
Protoss_Citadel_of_Adun 1 8436
Protoss_Templar_Archives 1 9483
9533
