Protoss_Nexus 2 9571
Protoss_Gateway 2 4963
Protoss_Assimilator 1 2344
Protoss_Zealot 2 3899
Protoss_Cybernetics_Core 1 3553
Protoss_Dragoon 11 9691
Protoss_Robotics_Facility 1 6819
Protoss_Observatory 1 8124
Protoss_Observer 2 9273
9691
