Protoss_Nexus 2 9003
Protoss_Gateway 2 9476
Protoss_Assimilator 1 2385
Protoss_Cybernetics_Core 1 2981
Protoss_Zealot 1 3253
Protoss_Dragoon 7 9203
Protoss_Robotics_Facility 1 5399
Protoss_Shuttle 1 6715
Protoss_Robotics_Support_Bay 1 6788
Protoss_Reaver 1 7617
Protoss_Observatory 1 7734
Protoss_Observer 2 9271
Protoss_Scarab 3 9933
9933
