Protoss_Nexus 2 7241
Protoss_Gateway 2 9682
Protoss_Assimilator 1 2220
Protoss_Cybernetics_Core 1 2889
Protoss_Dragoon 7 9591
Protoss_Robotics_Facility 1 4141
Protoss_Shuttle 1 5505
Protoss_Observatory 1 5994
Protoss_Observer 2 8095
Protoss_Forge 1 9173
Protoss_Photon_Cannon 1 9966
9966
