Protoss_Nexus 1 0
Protoss_Gateway 1 1930
Protoss_Assimilator 1 2309
Protoss_Cybernetics_Core 1 2938
Protoss_Robotics_Facility 1 4111
Protoss_Dragoon 7 9275
Protoss_Observatory 1 5708
Protoss_Observer 2 6888
Protoss_Shuttle 1 7490
Protoss_Robotics_Support_Bay 1 7947
Protoss_Reaver 2 9748
9748
