Protoss_Nexus 2 6497
Protoss_Gateway 3 8053
Protoss_Assimilator 1 2163
Protoss_Cybernetics_Core 1 2936
Protoss_Zealot 1 3077
Protoss_Dragoon 10 9855
Protoss_Robotics_Facility 1 5268
Protoss_Observatory 1 6681
Protoss_Observer 3 8907
Protoss_Citadel_of_Adun 1 8655
9855
