Protoss_Nexus 1 0
Protoss_Gateway 1 2298
Protoss_Assimilator 1 2528
Protoss_Zealot 3 4606
Protoss_Cybernetics_Core 1 4408
Protoss_Dragoon 2 9536
Protoss_Robotics_Facility 2 6454
Protoss_Observatory 1 7429
Protoss_Shuttle 1 7441
Protoss_Robotics_Support_Bay 1 7783
Protoss_Observer 2 8343
Protoss_Reaver 2 9131
9536
