Protoss_Nexus 1 0
Protoss_Gateway 2 6355
Protoss_Assimilator 1 2382
Protoss_Zealot 2 3945
Protoss_Cybernetics_Core 1 3669
Protoss_Dragoon 9 8651
Protoss_Robotics_Facility 1 5671
Protoss_Shuttle 1 7003
Protoss_Observatory 1 7291
Protoss_Observer 1 7905
Protoss_Robotics_Support_Bay 1 8285
Protoss_Reaver 1 8905
Protoss_Citadel_of_Adun 1 9420
9420
