Protoss_Nexus 2 6687
Protoss_Gateway 3 9967
Protoss_Zealot 2 3443
Protoss_Assimilator 1 2949
Protoss_Cybernetics_Core 1 3625
Protoss_Dragoon 11 9979
Protoss_Robotics_Facility 1 6062
Protoss_Observatory 1 7371
Protoss_Observer 2 8503
9979
