Protoss_Nexus 2 7382
Protoss_Gateway 1 1918
Protoss_Assimilator 1 2399
Protoss_Zealot 2 4185
Protoss_Cybernetics_Core 1 3923
Protoss_Dragoon 7 9711
Protoss_Robotics_Facility 1 5509
Protoss_Robotics_Support_Bay 1 6795
Protoss_Reaver 1 7459
Protoss_Observatory 1 7852
Protoss_Observer 1 8511
Protoss_Shuttle 1 9131
9711
