Protoss_Nexus 2 6429
Protoss_Gateway 3 7731
Protoss_Assimilator 2 8380
Protoss_Zealot 2 3857
Protoss_Cybernetics_Core 1 3558
Protoss_Dragoon 8 9103
Protoss_Robotics_Facility 1 6808
Protoss_Observatory 1 8124
Protoss_Citadel_of_Adun 1 8534
Protoss_Observer 2 9551
Protoss_Templar_Archives 1 9597
Protoss_Forge 1 9801
9801
