Protoss_Nexus 1 0
Protoss_Gateway 2 4343
Protoss_Assimilator 1 2392
Protoss_Zealot 3 9657
Protoss_Cybernetics_Core 1 3990
Protoss_Dragoon 10 8905
Protoss_Robotics_Facility 1 6663
Protoss_Robotics_Support_Bay 1 8003
Protoss_Shield_Battery 1 8225
Protoss_Reaver 1 8695
Protoss_Observatory 1 9051
Protoss_Observer 1 9789
9789
