Protoss_Nexus 2 8063
Protoss_Gateway 3 8757
Protoss_Assimilator 1 2946
Protoss_Cybernetics_Core 1 3331
Protoss_Zealot 3 7621
Protoss_Dragoon 12 9929
Protoss_Robotics_Facility 1 5613
Protoss_Observatory 1 7139
Protoss_Observer 2 8389
9929
