Protoss_Nexus 2 6479
Protoss_Gateway 2 7181
Protoss_Assimilator 2 9164
Protoss_Cybernetics_Core 1 2883
Protoss_Zealot 1 3133
Protoss_Dragoon 9 9467
Protoss_Robotics_Facility 1 7527
Protoss_Observatory 1 8955
Protoss_Observer 1 9483
9483
