Protoss_Nexus 2 7083
Protoss_Gateway 2 5777
Protoss_Assimilator 2 9547
Protoss_Zealot 2 4121
Protoss_Cybernetics_Core 1 3843
Protoss_Dragoon 8 9817
Protoss_Robotics_Facility 1 8088
Protoss_Citadel_of_Adun 1 9298
Protoss_Observatory 1 9411
Protoss_Observer 1 9987
9987
