Protoss_Nexus 2 7405
Protoss_Gateway 3 9612
Protoss_Assimilator 2 9053
Protoss_Zealot 2 4199
Protoss_Cybernetics_Core 1 3801
Protoss_Dragoon 4 7057
Protoss_Citadel_of_Adun 1 5693
Protoss_Templar_Archives 1 6707
Protoss_Forge 1 7750
Protoss_Dark_Templar 1 7809
Protoss_Photon_Cannon 2 8893
Protoss_High_Templar 2 9341
9612
