Protoss_Nexus 2 7901
Protoss_Gateway 2 9393
Protoss_Assimilator 1 2231
Protoss_Zealot 2 4275
Protoss_Cybernetics_Core 1 3693
Protoss_Citadel_of_Adun 1 4733
Protoss_Dragoon 2 5965
Protoss_Templar_Archives 1 5723
Protoss_Forge 1 6303
Protoss_Dark_Templar 1 6717
Protoss_Photon_Cannon 3 8975
Protoss_High_Templar 3 8987
9393
