Protoss_Nexus 2 9777
Protoss_Gateway 2 6587
Protoss_Assimilator 1 2270
Protoss_Zealot 2 4029
Protoss_Cybernetics_Core 1 3727
Protoss_Dragoon 7 8757
Protoss_Robotics_Facility 1 5811
Protoss_Shuttle 1 7187
Protoss_Observatory 1 7314
Protoss_Observer 1 8125
Protoss_Robotics_Support_Bay 1 8358
Protoss_Reaver 1 8987
9777
