Protoss_Nexus 2 9369
Protoss_Gateway 2 6580
Protoss_Assimilator 1 2305
Protoss_Zealot 2 3871
Protoss_Cybernetics_Core 1 3552
Protoss_Dragoon 8 8827
Protoss_Robotics_Facility 1 5627
Protoss_Shuttle 1 7025
Protoss_Observatory 1 7061
Protoss_Observer 1 7927
Protoss_Robotics_Support_Bay 1 7982
Protoss_Reaver 2 9791
9791
