Protoss_Nexus 1 0
Protoss_Gateway 1 1883
Protoss_Assimilator 1 2504
Protoss_Cybernetics_Core 1 3138
Protoss_Dragoon 7 8902
Protoss_Robotics_Facility 1 5512
Protoss_Observatory 1 6967
Protoss_Observer 2 9458
Protoss_Shuttle 1 8556
9458
