Protoss_Nexus 1 0
Protoss_Gateway 2 5210
Protoss_Assimilator 1 2337
Protoss_Cybernetics_Core 1 2967
Protoss_Zealot 1 3205
Protoss_Dragoon 11 9757
Protoss_Robotics_Facility 1 5877
Protoss_Shuttle 1 7221
Protoss_Observatory 1 7297
Protoss_Robotics_Support_Bay 1 7549
Protoss_Observer 2 9121
9757
