Protoss_Nexus 2 9670
Protoss_Gateway 2 6501
Protoss_Assimilator 1 2331
Protoss_Zealot 2 4027
Protoss_Cybernetics_Core 1 3952
Protoss_Dragoon 10 9903
Protoss_Robotics_Facility 1 5827
Protoss_Shuttle 1 7105
Protoss_Observatory 1 7695
Protoss_Observer 1 8291
Protoss_Robotics_Support_Bay 1 8370
Protoss_Reaver 1 8919
9903
