Protoss_Nexus 2 9714
Protoss_Gateway 2 6095
Protoss_Assimilator 1 2363
Protoss_Zealot 2 3727
Protoss_Cybernetics_Core 1 3616
Protoss_Dragoon 8 8719
Protoss_Robotics_Facility 1 5314
Protoss_Shuttle 1 6595
Protoss_Observatory 1 6792
Protoss_Observer 1 7497
Protoss_Robotics_Support_Bay 1 7689
Protoss_Reaver 1 8323
9714
