Protoss_Nexus 2 8377
Protoss_Gateway 2 6491
Protoss_Assimilator 1 2193
Protoss_Zealot 2 3863
Protoss_Cybernetics_Core 1 3658
Protoss_Dragoon 10 9967
Protoss_Robotics_Facility 1 5940
Protoss_Observatory 1 7256
Protoss_Observer 2 8397
Protoss_Robotics_Support_Bay 1 8889
Protoss_Reaver 1 9655
9967
