Protoss_Nexus 2 8517
Protoss_Gateway 2 6505
Protoss_Zealot 2 3919
Protoss_Assimilator 2 9110
Protoss_Cybernetics_Core 1 3673
Protoss_Dragoon 8 9481
Protoss_Robotics_Facility 1 6276
Protoss_Observatory 1 7620
Protoss_Observer 2 8759
Protoss_Citadel_of_Adun 1 8894
9481
