Protoss_Nexus 1 0
Protoss_Gateway 2 5575
Protoss_Assimilator 1 2868
Protoss_Zealot 2 4363
Protoss_Cybernetics_Core 1 3827
Protoss_Dragoon 9 9817
Protoss_Robotics_Facility 1 6541
Protoss_Observatory 1 7904
Protoss_Observer 1 8647
Protoss_Shuttle 1 9459
Protoss_Robotics_Support_Bay 1 9813
9817
