Protoss_Nexus 2 8199
Protoss_Gateway 2 9127
Protoss_Assimilator 1 2371
Protoss_Zealot 2 3907
Protoss_Cybernetics_Core 1 3568
Protoss_Dragoon 7 9655
Protoss_Robotics_Facility 1 5550
Protoss_Robotics_Support_Bay 1 6849
Protoss_Shuttle 1 7421
Protoss_Reaver 2 9503
Protoss_Observatory 1 8617
9655
