Protoss_Nexus 2 9655
Protoss_Gateway 2 6139
Protoss_Assimilator 1 2349
Protoss_Zealot 2 3965
Protoss_Cybernetics_Core 1 3763
Protoss_Dragoon 8 9975
Protoss_Robotics_Facility 1 5651
Protoss_Shuttle 1 7033
Protoss_Robotics_Support_Bay 1 7595
Protoss_Observatory 1 7679
Protoss_Reaver 1 8401
Protoss_Observer 1 9453
9975
