Protoss_Nexus 2 6741
Protoss_Gateway 4 9986
Protoss_Assimilator 1 2366
Protoss_Zealot 2 4045
Protoss_Cybernetics_Core 1 3737
Protoss_Dragoon 11 9511
Protoss_Robotics_Facility 1 9118
9986
