Protoss_Nexus 1 0
Protoss_Gateway 2 6651
Protoss_Assimilator 1 2469
Protoss_Cybernetics_Core 1 3083
Protoss_Zealot 1 3287
Protoss_Dragoon 9 9457
Protoss_Robotics_Facility 1 5963
Protoss_Shuttle 1 7257
Protoss_Robotics_Support_Bay 1 7805
Protoss_Observatory 1 7905
Protoss_Observer 1 8435
Protoss_Reaver 1 9407
9457
