Protoss_Nexus 1 0
Protoss_Gateway 2 6169
Protoss_Assimilator 1 2454
Protoss_Zealot 2 4173
Protoss_Cybernetics_Core 1 3819
Protoss_Dragoon 9 9185
Protoss_Robotics_Facility 1 5972
Protoss_Shuttle 1 7329
Protoss_Robotics_Support_Bay 1 7767
Protoss_Reaver 1 8467
Protoss_Observatory 1 8917
Protoss_Forge 1 9541
Protoss_Observer 1 9711
9711
