Protoss_Nexus 1 0
Protoss_Gateway 2 6095
Protoss_Assimilator 1 2470
Protoss_Zealot 2 4133
Protoss_Cybernetics_Core 1 3787
Protoss_Dragoon 11 9719
Protoss_Robotics_Facility 1 5773
Protoss_Shuttle 1 7119
Protoss_Robotics_Support_Bay 1 7757
Protoss_Reaver 1 8295
Protoss_Observatory 1 8698
Protoss_Observer 1 9347
9719
