Protoss_Nexus 2 6355
Protoss_Gateway 4 8453
Protoss_Assimilator 1 2206
Protoss_Cybernetics_Core 1 2842
Protoss_Zealot 1 3001
Protoss_Citadel_of_Adun 1 3833
Protoss_Dragoon 11 9803
Protoss_Templar_Archives 1 4852
Protoss_Dark_Templar 1 5927
Protoss_Robotics_Facility 1 9428
9803
