Protoss_Nexus 2 8095
Protoss_Gateway 2 6443
Protoss_Assimilator 1 2238
Protoss_Zealot 2 3903
Protoss_Cybernetics_Core 1 3634
Protoss_Dragoon 7 9281
Protoss_Robotics_Facility 1 5845
Protoss_Observatory 1 7151
Protoss_Observer 2 8361
Protoss_Robotics_Support_Bay 1 8457
Protoss_Reaver 1 9093
Protoss_Citadel_of_Adun 1 9818
9818
