Protoss_Nexus 1 0
Protoss_Gateway 2 6010
Protoss_Assimilator 1 2421
Protoss_Zealot 2 4063
Protoss_Cybernetics_Core 1 3767
Protoss_Dragoon 11 9911
Protoss_Robotics_Facility 1 5751
Protoss_Shuttle 1 7057
Protoss_Robotics_Support_Bay 1 7465
Protoss_Observatory 1 7987
Protoss_Reaver 1 8269
Protoss_Observer 2 9923
Protoss_Forge 1 9378
9923
