Protoss_Nexus 1 0
Protoss_Gateway 3 9589
Protoss_Zealot 5 6169
Protoss_Assimilator 1 5510
Protoss_Cybernetics_Core 1 5905
Protoss_Dragoon 7 9827
Protoss_Robotics_Facility 1 9645
9827
