Protoss_Nexus 2 8253
Protoss_Gateway 4 9443
Protoss_Assimilator 1 2413
Protoss_Zealot 2 4039
Protoss_Cybernetics_Core 1 3715
Protoss_Dragoon 11 9761
Protoss_Robotics_Facility 1 5656
Protoss_Observatory 1 7025
Protoss_Observer 2 8349
9761
