Protoss_Nexus 1 0
Protoss_Gateway 2 6339
Protoss_Assimilator 1 2470
Protoss_Zealot 2 4351
Protoss_Cybernetics_Core 1 4039
Protoss_Dragoon 9 9353
Protoss_Robotics_Facility 1 6072
Protoss_Shuttle 1 7575
Protoss_Robotics_Support_Bay 1 8007
Protoss_Reaver 1 8551
Protoss_Observatory 1 8954
Protoss_Observer 1 9603
9603
