Protoss_Nexus 2 5406
Protoss_Gateway 3 8548
Protoss_Zealot 6 9579
Protoss_Forge 2 6185
Protoss_Assimilator 2 9439
Protoss_Photon_Cannon 3 7723
Protoss_Cybernetics_Core 1 7437
Protoss_Dragoon 2 9039
Protoss_Robotics_Facility 1 9594
9594
