Protoss_Nexus 2 9739
Protoss_Gateway 3 7979
Protoss_Assimilator 2 3411
Protoss_Zealot 7 7105
Protoss_Cybernetics_Core 1 4753
Protoss_Dragoon 4 9431
Protoss_Citadel_of_Adun 1 6754
Protoss_Forge 1 7630
Protoss_Templar_Archives 1 7893
Protoss_Photon_Cannon 1 8763
Protoss_Dark_Templar 3 9055
Protoss_High_Templar 1 9255
9739
