Protoss_Nexus 1 0
Protoss_Gateway 1 2050
Protoss_Assimilator 1 2334
Protoss_Cybernetics_Core 1 3179
Protoss_Zealot 2 4681
Protoss_Forge 1 4059
Protoss_Photon_Cannon 1 5267
5267
