Protoss_Nexus 1 0
Protoss_Gateway 1 1992
Protoss_Assimilator 1 2460
Protoss_Zealot 2 3801
Protoss_Cybernetics_Core 1 3491
Protoss_Dragoon 5 8207
Protoss_Robotics_Facility 1 5747
Protoss_Observatory 1 7045
Protoss_Robotics_Support_Bay 1 7073
Protoss_Reaver 1 7797
8207
