Protoss_Nexus 2 9667
Protoss_Gateway 2 4443
Protoss_Assimilator 1 2467
Protoss_Zealot 3 4619
Protoss_Cybernetics_Core 1 3671
Protoss_Dragoon 8 8777
Protoss_Robotics_Facility 1 6489
Protoss_Observatory 1 7950
Protoss_Observer 2 9081
Protoss_Robotics_Support_Bay 1 8955
Protoss_Reaver 1 9985
9985
