Protoss_Nexus 2 6775
Protoss_Gateway 2 2424
Protoss_Zealot 6 4795
Protoss_Assimilator 1 5689
Protoss_Cybernetics_Core 1 5927
Protoss_Dragoon 6 9259
Protoss_Forge 1 7918
Protoss_Photon_Cannon 1 8849
Protoss_Robotics_Facility 1 9769
9769
