Protoss_Nexus 2 9081
Protoss_Gateway 2 6715
Protoss_Assimilator 1 2305
Protoss_Zealot 2 3939
Protoss_Cybernetics_Core 1 3575
Protoss_Dragoon 8 9819
Protoss_Robotics_Facility 1 5859
Protoss_Shuttle 1 7223
Protoss_Observatory 1 7516
Protoss_Observer 1 8125
Protoss_Robotics_Support_Bay 1 8485
Protoss_Reaver 1 9465
9819
