Protoss_Nexus 1 0
Protoss_Gateway 3 8401
Protoss_Assimilator 1 2312
Protoss_Zealot 4 9331
Protoss_Cybernetics_Core 1 3439
Protoss_Dragoon 11 9401
Protoss_Robotics_Facility 1 5820
Protoss_Observatory 1 7563
Protoss_Observer 1 8195
Protoss_Robotics_Support_Bay 1 8985
Protoss_Shuttle 1 9851
9851
