Protoss_Nexus 1 0
Protoss_Gateway 3 6469
Protoss_Zealot 6 5415
Protoss_Assimilator 1 4818
Protoss_Cybernetics_Core 1 5823
Protoss_Dragoon 5 8319
Protoss_Citadel_of_Adun 1 7063
Protoss_Templar_Archives 1 8094
Protoss_Forge 1 8621
Protoss_Dark_Templar 2 9201
Protoss_Photon_Cannon 1 9481
9481
