Protoss_Nexus 1 0
Protoss_Gateway 2 2534
Protoss_Zealot 6 9573
Protoss_Assimilator 2 4415
Protoss_Cybernetics_Core 1 5638
Protoss_Dragoon 3 8003
Protoss_Robotics_Facility 1 9215
9573
