Protoss_Nexus 2 9321
Protoss_Gateway 2 5231
Protoss_Assimilator 1 2227
Protoss_Cybernetics_Core 1 2916
Protoss_Dragoon 9 7989
Protoss_Robotics_Facility 1 7687
Protoss_Observatory 1 9018
Protoss_Zealot 1 9103
Protoss_Observer 1 9549
Protoss_Robotics_Support_Bay 1 9714
9714
