Protoss_Nexus 2 8781
Protoss_Gateway 2 4103
Protoss_Assimilator 1 2340
Protoss_Zealot 3 8431
Protoss_Cybernetics_Core 1 3391
Protoss_Dragoon 11 9731
Protoss_Robotics_Facility 1 6533
Protoss_Observatory 1 7821
Protoss_Robotics_Support_Bay 1 8312
Protoss_Observer 1 8413
Protoss_Reaver 1 9245
9731
