Protoss_Nexus 1 0
Protoss_Gateway 4 9539
Protoss_Assimilator 1 2217
Protoss_Zealot 2 3993
Protoss_Cybernetics_Core 1 3701
Protoss_Dragoon 12 9667
Protoss_Robotics_Facility 1 5469
Protoss_Observatory 1 7299
Protoss_Observer 2 8467
9667
