Protoss_Nexus 1 0
Protoss_Gateway 4 9525
Protoss_Forge 1 2617
Protoss_Zealot 9 8333
Protoss_Photon_Cannon 8 6867
Protoss_Assimilator 1 7962
Protoss_Cybernetics_Core 1 8776
Protoss_Dragoon 1 9819
9819
