Protoss_Nexus 2 9339
Protoss_Gateway 3 6821
Protoss_Assimilator 1 2416
Protoss_Cybernetics_Core 1 2999
Protoss_Dragoon 14 9853
Protoss_Robotics_Facility 1 6062
Protoss_Observatory 1 7719
Protoss_Observer 1 8549
9853
