Protoss_Nexus 1 0
Protoss_Gateway 3 8513
Protoss_Assimilator 1 2363
Protoss_Zealot 4 8991
Protoss_Cybernetics_Core 1 3873
Protoss_Dragoon 8 9559
Protoss_Robotics_Facility 1 6057
Protoss_Shuttle 1 7399
Protoss_Observatory 1 7704
Protoss_Robotics_Support_Bay 1 8243
Protoss_Observer 1 8301
Protoss_Reaver 1 9217
9559
