Protoss_Nexus 2 6744
Protoss_Gateway 3 7523
Protoss_Assimilator 1 2561
Protoss_Zealot 3 8799
Protoss_Cybernetics_Core 1 3434
Protoss_Dragoon 11 9653
Protoss_Robotics_Facility 1 8205
Protoss_Observatory 1 9599
9653
