Protoss_Nexus 2 8617
Protoss_Gateway 2 6015
Protoss_Assimilator 1 2255
Protoss_Zealot 2 4075
Protoss_Cybernetics_Core 1 3783
Protoss_Dragoon 9 9597
Protoss_Robotics_Facility 1 5721
Protoss_Observatory 1 7280
Protoss_Observer 1 7833
Protoss_Robotics_Support_Bay 1 8196
Protoss_Reaver 1 8981
9597
