Protoss_Nexus 2 8567
Protoss_Gateway 2 5943
Protoss_Assimilator 1 2407
Protoss_Zealot 2 4027
Protoss_Cybernetics_Core 1 3655
Protoss_Dragoon 10 9599
Protoss_Robotics_Facility 1 5650
Protoss_Shuttle 1 7355
Protoss_Observatory 1 7641
Protoss_Observer 1 8381
Protoss_Robotics_Support_Bay 1 8501
Protoss_Reaver 1 9513
9599
