Protoss_Nexus 2 9072
Protoss_Gateway 2 4465
Protoss_Assimilator 1 2216
Protoss_Zealot 1 2837
Protoss_Cybernetics_Core 1 3779
Protoss_Dragoon 10 9371
Protoss_Robotics_Facility 1 6458
Protoss_Observatory 1 7857
Protoss_Observer 1 8431
Protoss_Shuttle 1 9033
Protoss_Robotics_Support_Bay 1 9208
9371
