Protoss_Nexus 1 0
Protoss_Gateway 2 6001
Protoss_Assimilator 1 2604
Protoss_Zealot 1 3191
Protoss_Cybernetics_Core 1 3809
Protoss_Dragoon 7 9066
Protoss_Robotics_Facility 1 4848
Protoss_Shuttle 1 6166
Protoss_Observatory 1 6258
Protoss_Observer 1 7068
Protoss_Robotics_Support_Bay 1 7623
Protoss_Reaver 2 9551
9551
