Protoss_Nexus 2 6419
Protoss_Gateway 2 3672
Protoss_Assimilator 2 8225
Protoss_Zealot 1 2815
Protoss_Cybernetics_Core 1 3258
Protoss_Dragoon 13 9735
Protoss_Citadel_of_Adun 1 7615
Protoss_Templar_Archives 1 9047
Protoss_Robotics_Facility 1 9886
9886
