Protoss_Nexus 2 7959
Protoss_Gateway 2 5844
Protoss_Assimilator 1 2300
Protoss_Zealot 2 3819
Protoss_Cybernetics_Core 1 3485
Protoss_Citadel_of_Adun 1 4893
Protoss_Dragoon 3 9764
Protoss_Templar_Archives 1 5923
Protoss_Dark_Templar 2 7077
Protoss_Forge 1 7013
Protoss_Photon_Cannon 2 8841
Protoss_High_Templar 2 8989
9764
