Protoss_Nexus 2 8391
Protoss_Gateway 2 6700
Protoss_Assimilator 2 9759
Protoss_Zealot 2 4571
Protoss_Cybernetics_Core 1 4298
Protoss_Dragoon 6 9885
Protoss_Robotics_Facility 1 6229
Protoss_Observatory 1 7515
Protoss_Robotics_Support_Bay 1 7675
Protoss_Observer 1 8053
Protoss_Reaver 1 9379
9885
