Protoss_Nexus 2 3969
Protoss_Gateway 4 7825
Protoss_Zealot 2 4221
Protoss_Assimilator 1 4391
Protoss_Forge 1 4994
Protoss_Cybernetics_Core 1 5319
Protoss_Photon_Cannon 4 9785
Protoss_Dragoon 10 9687
9785
