Protoss_Nexus 1 0
Protoss_Gateway 2 6310
Protoss_Assimilator 1 2348
Protoss_Zealot 2 3935
Protoss_Cybernetics_Core 1 3711
Protoss_Dragoon 6 8205
Protoss_Robotics_Facility 1 5929
Protoss_Shuttle 1 7285
Protoss_Robotics_Support_Bay 1 7828
Protoss_Reaver 1 8361
Protoss_Observatory 1 9393
Protoss_Scarab 1 9834
9834
