Protoss_Nexus 2 9665
Protoss_Gateway 2 6095
Protoss_Assimilator 1 2443
Protoss_Zealot 2 4101
Protoss_Cybernetics_Core 1 3843
Protoss_Dragoon 7 9495
Protoss_Citadel_of_Adun 1 5758
Protoss_Templar_Archives 1 6775
Protoss_Dark_Templar 4 8743
Protoss_Forge 1 7975
9665
