Protoss_Nexus 2 8595
Protoss_Gateway 2 6187
Protoss_Assimilator 1 2383
Protoss_Zealot 2 4051
Protoss_Cybernetics_Core 1 3883
Protoss_Dragoon 7 8391
Protoss_Robotics_Facility 1 5605
Protoss_Shuttle 1 6915
Protoss_Observatory 1 7479
Protoss_Observer 1 8149
Protoss_Robotics_Support_Bay 1 8831
Protoss_Reaver 1 9619
9619
