Protoss_Nexus 2 8639
Protoss_Gateway 2 5322
Protoss_Zealot 2 3989
Protoss_Assimilator 2 9975
Protoss_Cybernetics_Core 1 3994
Protoss_Dragoon 12 9837
Protoss_Robotics_Facility 1 6565
Protoss_Observatory 1 7958
Protoss_Observer 2 9043
Protoss_Citadel_of_Adun 1 9422
9975
