Protoss_Nexus 1 0
Protoss_Gateway 3 8689
Protoss_Assimilator 1 2523
Protoss_Cybernetics_Core 1 3193
Protoss_Dragoon 13 9876
Protoss_Robotics_Facility 1 6233
Protoss_Observatory 1 7530
Protoss_Observer 1 8066
Protoss_Robotics_Support_Bay 1 9981
9981
