Protoss_Nexus 2 8364
Protoss_Gateway 2 2577
Protoss_Assimilator 2 3967
Protoss_Zealot 5 4221
Protoss_Cybernetics_Core 1 4777
Protoss_Dragoon 9 9139
Protoss_Forge 1 7066
9139
