Protoss_Nexus 2 9403
Protoss_Gateway 2 5311
Protoss_Assimilator 1 2213
Protoss_Cybernetics_Core 1 2893
Protoss_Dragoon 13 9687
Protoss_Robotics_Facility 1 6090
Protoss_Observatory 1 7379
Protoss_Observer 3 9703
9703
