Protoss_Nexus 1 0
Protoss_Gateway 2 5525
Protoss_Assimilator 1 2260
Protoss_Zealot 2 4081
Protoss_Cybernetics_Core 1 3787
Protoss_Dragoon 10 9923
Protoss_Shield_Battery 1 6311
9923
