Protoss_Nexus 2 2534
Protoss_Gateway 4 9760
Protoss_Assimilator 2 3656
Protoss_Cybernetics_Core 1 4341
Protoss_Dragoon 9 8548
Protoss_Robotics_Facility 1 7783
Protoss_Zealot 2 8818
Protoss_Observatory 1 9112
Protoss_Observer 1 9756
9760
