Protoss_Nexus 3 7173
Protoss_Gateway 3 9363
Protoss_Assimilator 1 2483
Protoss_Zealot 3 4476
Protoss_Cybernetics_Core 1 4158
Protoss_Dragoon 8 9896
Protoss_Robotics_Facility 1 8283
Protoss_Shield_Battery 1 8453
Protoss_Observatory 1 9782
9896
