Protoss_Nexus 1 0
Protoss_Gateway 2 2583
Protoss_Zealot 7 5931
Protoss_Assimilator 1 4030
Protoss_Cybernetics_Core 1 5255
Protoss_Dragoon 8 9261
Protoss_Robotics_Facility 1 7948
Protoss_Observatory 1 9608
9608
