Protoss_Nexus 1 0
Protoss_Gateway 2 3724
Protoss_Zealot 7 6506
Protoss_Assimilator 1 5113
Protoss_Cybernetics_Core 1 6083
Protoss_Dragoon 7 9676
Protoss_Robotics_Facility 1 8895
9676
