Protoss_Nexus 1 0
Protoss_Gateway 3 9908
Protoss_Zealot 6 5586
Protoss_Assimilator 1 4818
Protoss_Cybernetics_Core 1 6345
Protoss_Citadel_of_Adun 1 7416
Protoss_Dragoon 2 7511
Protoss_Templar_Archives 1 8466
Protoss_Forge 1 9342
Protoss_Dark_Templar 2 9576
9908
