Protoss_Nexus 1 0
Protoss_Gateway 2 4581
Protoss_Assimilator 1 2513
Protoss_Cybernetics_Core 1 3220
Protoss_Zealot 1 3381
Protoss_Dragoon 7 8491
Protoss_Robotics_Facility 1 9428
9428
