Protoss_Nexus 1 0
Protoss_Gateway 2 7384
Protoss_Assimilator 1 3189
Protoss_Zealot 1 3271
Protoss_Cybernetics_Core 1 4307
Protoss_Dragoon 8 9519
Protoss_Robotics_Facility 1 5418
Protoss_Observatory 1 6787
Protoss_Observer 1 7419
Protoss_Shuttle 1 8243
Protoss_Robotics_Support_Bay 1 9047
Protoss_Reaver 1 9589
9589
