Protoss_Nexus 2 9858
Protoss_Gateway 2 6527
Protoss_Assimilator 1 2523
Protoss_Zealot 2 4011
Protoss_Cybernetics_Core 1 3766
Protoss_Dragoon 7 9241
Protoss_Robotics_Facility 1 5405
Protoss_Shuttle 1 6796
Protoss_Robotics_Support_Bay 1 7043
Protoss_Reaver 1 7726
Protoss_Observatory 1 7788
Protoss_Observer 1 8778
9858
