Protoss_Nexus 1 0
Protoss_Gateway 2 6218
Protoss_Assimilator 1 2889
Protoss_Zealot 3 9156
Protoss_Cybernetics_Core 1 3893
Protoss_Dragoon 8 9161
Protoss_Robotics_Facility 1 7608
Protoss_Observatory 1 8913
Protoss_Robotics_Support_Bay 1 9003
Protoss_Observer 1 9451
9451
