Protoss_Nexus 1 0
Protoss_Gateway 2 2603
Protoss_Zealot 7 6096
Protoss_Assimilator 1 3999
Protoss_Cybernetics_Core 1 5397
Protoss_Citadel_of_Adun 1 6616
Protoss_Dragoon 3 9856
Protoss_Robotics_Facility 1 7166
Protoss_Templar_Archives 1 7733
Protoss_Shuttle 1 8456
Protoss_Forge 1 8608
Protoss_Dark_Templar 2 8741
Protoss_Photon_Cannon 2 9373
9856
