Protoss_Nexus 1 0
Protoss_Gateway 2 2559
Protoss_Zealot 8 6201
Protoss_Assimilator 1 5068
Protoss_Cybernetics_Core 1 5719
Protoss_Dragoon 6 9481
Protoss_Robotics_Facility 1 7638
Protoss_Shuttle 1 9061
Protoss_Robotics_Support_Bay 1 9267
Protoss_Forge 1 9361
9481
