Protoss_Nexus 1 0
Protoss_Gateway 3 8966
Protoss_Zealot 5 5071
Protoss_Assimilator 1 4493
Protoss_Cybernetics_Core 1 5469
Protoss_Dragoon 8 9151
Protoss_Robotics_Facility 1 7948
Protoss_Observatory 1 9353
Protoss_Observer 1 9886
9886
