Protoss_Nexus 1 0
Protoss_Gateway 2 5567
Protoss_Assimilator 1 2508
Protoss_Zealot 3 4066
Protoss_Cybernetics_Core 1 3898
Protoss_Dragoon 12 9841
Protoss_Robotics_Facility 1 7708
Protoss_Observatory 1 9103
Protoss_Shuttle 1 9461
9841
