Protoss_Nexus 1 0
Protoss_Gateway 3 9633
Protoss_Zealot 4 6385
Protoss_Assimilator 1 4386
Protoss_Cybernetics_Core 1 5973
Protoss_Citadel_of_Adun 1 7073
Protoss_Dragoon 1 7191
Protoss_Templar_Archives 1 8165
Protoss_Forge 1 8984
Protoss_Dark_Templar 2 9369
Protoss_Photon_Cannon 1 9817
9817
