Protoss_Nexus 2 9955
Protoss_Gateway 2 5668
Protoss_Zealot 7 6739
Protoss_Assimilator 1 4936
Protoss_Cybernetics_Core 1 5704
Protoss_Citadel_of_Adun 1 7147
Protoss_Dragoon 4 8555
Protoss_Templar_Archives 1 8133
Protoss_Forge 1 8419
Protoss_Dark_Templar 2 9307
Protoss_Photon_Cannon 1 9311
9955
