Protoss_Nexus 1 0
Protoss_Gateway 2 4961
Protoss_Zealot 9 9371
Protoss_Assimilator 1 5028
Protoss_Cybernetics_Core 1 5697
Protoss_Dragoon 5 9319
Protoss_Robotics_Facility 1 7728
Protoss_Shuttle 1 9009
Protoss_Observatory 1 9286
Protoss_Robotics_Support_Bay 1 9971
9971
