Protoss_Nexus 2 9383
Protoss_Gateway 3 8043
Protoss_Assimilator 1 2578
Protoss_Zealot 1 3056
Protoss_Cybernetics_Core 1 3989
Protoss_Dragoon 9 9566
Protoss_Robotics_Facility 1 6813
Protoss_Observatory 1 8273
Protoss_Observer 2 9796
9796
