Protoss_Nexus 2 5414
Protoss_Gateway 2 6287
Protoss_Zealot 4 5541
Protoss_Assimilator 2 9655
Protoss_Cybernetics_Core 1 6028
Protoss_Forge 1 6868
Protoss_Dragoon 5 9536
Protoss_Photon_Cannon 2 9833
Protoss_Robotics_Facility 1 8581
Protoss_Observatory 1 9919
9919
