Protoss_Nexus 1 0
Protoss_Gateway 2 3763
Protoss_Zealot 8 6573
Protoss_Assimilator 1 6298
Protoss_Cybernetics_Core 1 7302
Protoss_Forge 1 7775
Protoss_Dragoon 4 9295
Protoss_Photon_Cannon 1 8637
9295
