Protoss_Nexus 1 0
Protoss_Gateway 2 4236
Protoss_Assimilator 1 2365
Protoss_Cybernetics_Core 1 3035
Protoss_Dragoon 12 9613
Protoss_Robotics_Facility 1 7676
Protoss_Observatory 1 8963
Protoss_Observer 1 9661
9661
