Protoss_Nexus 2 7218
Protoss_Gateway 2 5235
Protoss_Assimilator 1 2248
Protoss_Zealot 5 9666
Protoss_Cybernetics_Core 1 3648
Protoss_Citadel_of_Adun 1 4688
Protoss_Dragoon 2 5741
Protoss_Templar_Archives 1 5715
Protoss_Forge 1 6202
Protoss_Dark_Templar 1 6891
Protoss_Photon_Cannon 2 8042
Protoss_High_Templar 3 8911
9666
