Protoss_Nexus 1 0
Protoss_Gateway 2 5196
Protoss_Assimilator 1 2468
Protoss_Zealot 3 4286
Protoss_Cybernetics_Core 1 4678
Protoss_Robotics_Facility 1 5673
Protoss_Dragoon 11 9834
Protoss_Observatory 1 6992
Protoss_Observer 2 8133
Protoss_Shuttle 1 8796
Protoss_Robotics_Support_Bay 1 9719
9834
