Protoss_Nexus 1 0
Protoss_Gateway 2 7451
Protoss_Assimilator 1 2714
Protoss_Zealot 2 4216
Protoss_Cybernetics_Core 1 3782
Protoss_Dragoon 7 9517
Protoss_Robotics_Facility 1 5477
Protoss_Forge 1 5870
Protoss_Observatory 1 6785
Protoss_Observer 2 8901
Protoss_Shuttle 1 9503
Protoss_Robotics_Support_Bay 1 9775
9775
