Protoss_Nexus 2 9498
Protoss_Gateway 2 6315
Protoss_Assimilator 1 2412
Protoss_Zealot 2 3793
Protoss_Cybernetics_Core 1 4002
Protoss_Dragoon 9 9846
Protoss_Robotics_Facility 1 5348
Protoss_Observatory 1 6668
Protoss_Observer 2 7877
Protoss_Robotics_Support_Bay 1 8004
Protoss_Reaver 2 9628
9846
