Protoss_Nexus 2 5263
Protoss_Gateway 2 2822
Protoss_Zealot 8 6823
Protoss_Assimilator 2 8256
Protoss_Cybernetics_Core 1 7125
Protoss_Citadel_of_Adun 1 8139
Protoss_Dragoon 2 8751
Protoss_Forge 1 9115
Protoss_Templar_Archives 1 9700
Protoss_Photon_Cannon 2 9861
9861
