Protoss_Nexus 2 5391
Protoss_Gateway 3 7026
Protoss_Zealot 7 5971
Protoss_Assimilator 2 8627
Protoss_Cybernetics_Core 1 6455
Protoss_Forge 1 7261
Protoss_Dragoon 2 7607
Protoss_Citadel_of_Adun 1 7884
Protoss_Templar_Archives 1 8877
Protoss_Photon_Cannon 2 9616
Protoss_Dark_Templar 2 9877
9877
