Protoss_Nexus 2 5271
Protoss_Gateway 3 8464
Protoss_Zealot 8 6645
Protoss_Assimilator 2 8519
Protoss_Cybernetics_Core 1 6266
Protoss_Dragoon 8 9921
Protoss_Robotics_Facility 1 9537
9921
