Protoss_Nexus 1 0
Protoss_Gateway 1 1905
Protoss_Assimilator 1 2263
Protoss_Cybernetics_Core 1 2909
Protoss_Dragoon 4 8513
Protoss_Robotics_Facility 1 4405
Protoss_Shuttle 1 5691
Protoss_Robotics_Support_Bay 1 5818
Protoss_Citadel_of_Adun 1 6259
Protoss_Reaver 1 6593
Protoss_Stargate 2 8768
Protoss_Scarab 1 8484
Protoss_Fleet_Beacon 1 8568
Protoss_Carrier 1 9556
9556
