Protoss_Nexus 2 4268
Protoss_Gateway 4 8726
Protoss_Zealot 14 9721
Protoss_Assimilator 2 7566
Protoss_Cybernetics_Core 1 6113
Protoss_Citadel_of_Adun 1 8243
Protoss_Forge 1 9237
Protoss_Templar_Archives 1 9373
9721
