Protoss_Nexus 1 0
Protoss_Gateway 3 7772
Protoss_Assimilator 1 2277
Protoss_Cybernetics_Core 1 2919
Protoss_Robotics_Facility 1 4059
Protoss_Dragoon 7 9449
Protoss_Shuttle 1 5341
Protoss_Observatory 1 5667
Protoss_Observer 3 7527
9449
