Protoss_Nexus 2 8493
Protoss_Gateway 2 5775
Protoss_Assimilator 2 3887
Protoss_Cybernetics_Core 1 3062
Protoss_Zealot 1 3521
Protoss_Dragoon 10 9559
Protoss_Robotics_Facility 1 9943
9943
