Protoss_Nexus 2 5114
Protoss_Gateway 3 6937
Protoss_Zealot 11 9377
Protoss_Forge 1 5570
Protoss_Photon_Cannon 7 9753
Protoss_Assimilator 2 8600
Protoss_Cybernetics_Core 1 9403
9753
