Protoss_Nexus 2 7869
Protoss_Gateway 4 9242
Protoss_Assimilator 1 2497
Protoss_Zealot 4 8811
Protoss_Cybernetics_Core 1 3818
Protoss_Dragoon 8 9573
Protoss_Robotics_Facility 1 8601
9573
