Protoss_Nexus 2 8365
Protoss_Gateway 2 4747
Protoss_Zealot 2 3759
Protoss_Assimilator 1 3126
Protoss_Cybernetics_Core 1 4241
Protoss_Dragoon 9 9767
Protoss_Robotics_Facility 1 6876
Protoss_Observatory 1 8509
Protoss_Observer 2 9707
9767
