Protoss_Nexus 2 5218
Protoss_Gateway 2 2503
Protoss_Zealot 10 7658
Protoss_Assimilator 1 5963
Protoss_Cybernetics_Core 1 6866
Protoss_Citadel_of_Adun 1 8309
Protoss_Forge 1 8467
Protoss_Dragoon 4 9703
Protoss_Photon_Cannon 1 9653
Protoss_Templar_Archives 1 9968
9968
