Protoss_Nexus 2 5209
Protoss_Gateway 3 9388
Protoss_Zealot 14 8741
Protoss_Assimilator 1 6541
Protoss_Cybernetics_Core 1 7870
Protoss_Citadel_of_Adun 1 9291
Protoss_Dragoon 2 9343
Protoss_Shield_Battery 1 9869
9869
