Protoss_Nexus 2 3834
Protoss_Gateway 4 7281
Protoss_Zealot 1 2899
Protoss_Assimilator 1 3964
Protoss_Cybernetics_Core 1 4313
Protoss_Dragoon 15 9979
Protoss_Forge 1 9863
9979
