Protoss_Nexus 2 6003
Protoss_Gateway 3 7708
Protoss_Zealot 11 7111
Protoss_Assimilator 2 9208
Protoss_Forge 1 7202
Protoss_Cybernetics_Core 1 7328
Protoss_Photon_Cannon 4 9347
Protoss_Citadel_of_Adun 1 8467
Protoss_Dragoon 2 9091
Protoss_Templar_Archives 1 9488
9488
