Protoss_Nexus 2 7823
Protoss_Gateway 2 3586
Protoss_Assimilator 1 2372
Protoss_Zealot 7 5811
Protoss_Cybernetics_Core 1 5175
Protoss_Dragoon 8 9196
Protoss_Citadel_of_Adun 1 9166
Protoss_Robotics_Facility 1 9460
9460
