Protoss_Nexus 2 5616
Protoss_Gateway 4 9287
Protoss_Zealot 14 8258
Protoss_Assimilator 2 9089
Protoss_Cybernetics_Core 1 7156
Protoss_Citadel_of_Adun 1 8281
Protoss_Robotics_Facility 1 9383
Protoss_Dragoon 1 9746
9746
