Protoss_Nexus 2 7789
Protoss_Gateway 3 9409
Protoss_Assimilator 1 2443
Protoss_Zealot 1 2917
Protoss_Cybernetics_Core 1 3847
Protoss_Dragoon 11 9759
Protoss_Robotics_Facility 1 9215
9759
