Protoss_Nexus 1 0
Protoss_Gateway 3 8186
Protoss_Assimilator 1 2757
Protoss_Zealot 4 9687
Protoss_Cybernetics_Core 1 3625
Protoss_Dragoon 7 7629
Protoss_Citadel_of_Adun 1 6815
Protoss_Templar_Archives 1 7923
Protoss_Forge 1 8901
Protoss_Dark_Templar 2 8935
9687
