Protoss_Nexus 2 8790
Protoss_Gateway 2 7328
Protoss_Assimilator 1 2423
Protoss_Cybernetics_Core 1 3101
Protoss_Dragoon 10 9987
Protoss_Robotics_Facility 1 6377
Protoss_Observatory 1 7710
Protoss_Observer 1 8433
Protoss_Robotics_Support_Bay 1 9615
9987
