Protoss_Nexus 2 9680
Protoss_Gateway 2 7033
Protoss_Assimilator 1 2431
Protoss_Zealot 2 4106
Protoss_Cybernetics_Core 1 3889
Protoss_Dragoon 2 5966
Protoss_Citadel_of_Adun 1 5501
Protoss_Templar_Archives 1 6599
Protoss_Forge 1 7083
Protoss_Dark_Templar 4 8801
Protoss_High_Templar 2 9956
Protoss_Photon_Cannon 2 9430
9956
