Protoss_Nexus 2 6403
Protoss_Gateway 3 8313
Protoss_Zealot 9 5841
Protoss_Forge 1 4571
Protoss_Photon_Cannon 4 7993
Protoss_Assimilator 1 6763
Protoss_Cybernetics_Core 1 7319
Protoss_Dragoon 3 9296
9296
