Protoss_Nexus 2 9848
Protoss_Gateway 2 3421
Protoss_Assimilator 1 2366
Protoss_Cybernetics_Core 1 2963
Protoss_Dragoon 5 6366
Protoss_Robotics_Facility 1 7129
Protoss_Citadel_of_Adun 1 7617
Protoss_Shuttle 1 8421
Protoss_Zealot 1 8531
Protoss_Templar_Archives 1 9267
9848
