Protoss_Nexus 2 4643
Protoss_Gateway 3 5919
Protoss_Assimilator 2 9848
Protoss_Zealot 4 9545
Protoss_Cybernetics_Core 1 4887
Protoss_Dragoon 9 9503
Protoss_Robotics_Facility 1 7037
Protoss_Observatory 1 8497
Protoss_Observer 2 9975
9975
