Protoss_Nexus 2 5768
Protoss_Gateway 3 6872
Protoss_Assimilator 1 2427
Protoss_Zealot 9 9287
Protoss_Cybernetics_Core 1 3646
Protoss_Dragoon 2 6007
Protoss_Citadel_of_Adun 1 7111
Protoss_Forge 1 8800
Protoss_Templar_Archives 1 9519
Protoss_Photon_Cannon 1 9665
9665
