Protoss_Nexus 2 8603
Protoss_Gateway 2 4600
Protoss_Zealot 5 6995
Protoss_Assimilator 1 7084
Protoss_Cybernetics_Core 1 7538
Protoss_Dragoon 3 9521
Protoss_Forge 1 9055
Protoss_Shield_Battery 1 9787
Protoss_Photon_Cannon 1 9834
9834
