Protoss_Nexus 1 0
Protoss_Gateway 3 9764
Protoss_Zealot 8 6981
Protoss_Assimilator 2 4275
Protoss_Cybernetics_Core 1 5959
Protoss_Dragoon 5 9398
Protoss_Citadel_of_Adun 1 7764
Protoss_Templar_Archives 1 8948
Protoss_Dark_Templar 2 9941
9941
