Protoss_Nexus 2 9539
Protoss_Gateway 3 6309
Protoss_Zealot 13 8679
Protoss_Assimilator 1 6668
Protoss_Cybernetics_Core 1 7078
Protoss_Citadel_of_Adun 1 8204
Protoss_Templar_Archives 1 9278
9539
