Protoss_Nexus 1 0
Protoss_Gateway 2 2756
Protoss_Zealot 9 7091
Protoss_Assimilator 1 6209
Protoss_Cybernetics_Core 1 6437
Protoss_Dragoon 6 9425
Protoss_Forge 1 8699
Protoss_Photon_Cannon 1 9753
9753
