Protoss_Nexus 2 6703
Protoss_Gateway 3 7381
Protoss_Assimilator 1 2975
Protoss_Zealot 3 4949
Protoss_Cybernetics_Core 1 4149
Protoss_Dragoon 11 9561
Protoss_Shield_Battery 1 9246
9561
