Protoss_Nexus 1 0
Protoss_Gateway 2 8241
Protoss_Zealot 3 4205
Protoss_Assimilator 1 3143
Protoss_Cybernetics_Core 1 4007
Protoss_Robotics_Facility 1 5230
Protoss_Dragoon 7 9913
Protoss_Shuttle 1 6595
Protoss_Robotics_Support_Bay 1 7097
Protoss_Reaver 2 8679
Protoss_Observatory 1 8196
Protoss_Scarab 7 9969
9969
