Protoss_Nexus 1 0
Protoss_Gateway 2 2438
Protoss_Zealot 9 6211
Protoss_Assimilator 1 4590
Protoss_Cybernetics_Core 1 5611
Protoss_Dragoon 8 9786
Protoss_Robotics_Facility 1 8061
Protoss_Forge 1 8777
Protoss_Observatory 1 9399
Protoss_Observer 1 9956
9956
