Protoss_Nexus 2 4983
Protoss_Gateway 2 5213
Protoss_Zealot 11 9856
Protoss_Assimilator 2 8164
Protoss_Cybernetics_Core 1 7065
Protoss_Forge 1 7975
Protoss_Citadel_of_Adun 1 8094
Protoss_Dragoon 2 8611
Protoss_Photon_Cannon 1 8927
Protoss_Templar_Archives 1 9719
9856
