Protoss_Nexus 1 0
Protoss_Gateway 2 6638
Protoss_Assimilator 1 2208
Protoss_Zealot 2 4396
Protoss_Cybernetics_Core 1 3850
Protoss_Dragoon 8 9941
Protoss_Robotics_Facility 1 5693
Protoss_Shuttle 1 7281
Protoss_Robotics_Support_Bay 1 7537
Protoss_Reaver 1 8516
Protoss_Observatory 1 8623
Protoss_Observer 1 9568
9941
