Protoss_Nexus 2 8723
Protoss_Gateway 2 4257
Protoss_Assimilator 1 2418
Protoss_Zealot 7 6156
Protoss_Cybernetics_Core 1 3761
Protoss_Citadel_of_Adun 1 5339
Protoss_Dragoon 1 6098
Protoss_Templar_Archives 1 6483
Protoss_Dark_Templar 3 8228
Protoss_Forge 1 8636
Protoss_High_Templar 2 9071
Protoss_Photon_Cannon 1 9945
9945
