Protoss_Nexus 2 7452
Protoss_Gateway 3 8157
Protoss_Assimilator 1 2532
Protoss_Zealot 3 9897
Protoss_Cybernetics_Core 1 3745
Protoss_Dragoon 8 9221
Protoss_Robotics_Facility 1 6195
Protoss_Observatory 1 7629
Protoss_Observer 2 9001
9897
