Protoss_Nexus 1 0
Protoss_Gateway 3 9906
Protoss_Zealot 8 6041
Protoss_Assimilator 1 3978
Protoss_Cybernetics_Core 1 5243
Protoss_Dragoon 8 9533
Protoss_Forge 1 7458
Protoss_Photon_Cannon 1 8329
Protoss_Robotics_Facility 1 8623
Protoss_Citadel_of_Adun 1 9548
Protoss_Shuttle 1 9926
9926
