Protoss_Nexus 2 9768
Protoss_Gateway 3 7523
Protoss_Assimilator 1 2233
Protoss_Cybernetics_Core 1 2845
Protoss_Dragoon 13 9253
Protoss_Robotics_Facility 1 5849
Protoss_Observatory 1 7416
Protoss_Observer 1 7965
9768
