Protoss_Nexus 2 9004
Protoss_Gateway 2 5611
Protoss_Zealot 2 3989
Protoss_Assimilator 1 3173
Protoss_Cybernetics_Core 1 3775
Protoss_Dragoon 10 9735
Protoss_Robotics_Facility 1 7214
Protoss_Observatory 1 8542
Protoss_Shuttle 1 8559
Protoss_Robotics_Support_Bay 1 9345
Protoss_Observer 1 9461
9735
