Protoss_Nexus 2 9241
Protoss_Gateway 4 9465
Protoss_Zealot 2 3689
Protoss_Assimilator 1 2925
Protoss_Cybernetics_Core 1 3445
Protoss_Dragoon 12 9801
Protoss_Robotics_Facility 1 7825
9801
