Protoss_Nexus 2 8130
Protoss_Gateway 3 9642
Protoss_Zealot 2 7171
Protoss_Assimilator 1 3067
Protoss_Cybernetics_Core 1 3758
Protoss_Dragoon 10 9331
Protoss_Robotics_Facility 1 7019
Protoss_Observatory 1 8328
Protoss_Observer 1 9031
Protoss_Shuttle 1 9793
9793
