Protoss_Nexus 2 2938
Protoss_Gateway 3 6317
Protoss_Zealot 4 8859
Protoss_Assimilator 2 7388
Protoss_Cybernetics_Core 1 5931
Protoss_Dragoon 6 8203
Protoss_Citadel_of_Adun 1 8631
Protoss_Forge 1 9212
Protoss_Shield_Battery 1 9431
Protoss_Templar_Archives 1 9846
Protoss_Photon_Cannon 1 9933
9933
