Protoss_Nexus 2 9382
Protoss_Gateway 6 7876
Protoss_Forge 1 4793
Protoss_Zealot 7 7243
Protoss_Assimilator 1 5955
Protoss_Cybernetics_Core 2 6787
Protoss_Citadel_of_Adun 1 7223
Protoss_Templar_Archives 1 8297
Protoss_Photon_Cannon 1 8429
Protoss_Dark_Templar 1 9385
9385
