Protoss_Nexus 2 8748
Protoss_Gateway 3 9772
Protoss_Assimilator 1 2428
Protoss_Cybernetics_Core 1 3083
Protoss_Dragoon 12 9421
Protoss_Robotics_Facility 1 6111
Protoss_Observatory 1 7447
Protoss_Observer 1 8331
9772
