Protoss_Nexus 2 2725
Protoss_Gateway 2 4472
Protoss_Assimilator 3 9563
Protoss_Zealot 8 7275
Protoss_Cybernetics_Core 1 8201
Protoss_Forge 1 8537
Protoss_Citadel_of_Adun 1 9281
Protoss_Photon_Cannon 4 9885
9885
