Protoss_Nexus 2 4939
Protoss_Gateway 3 9372
Protoss_Zealot 11 9993
Protoss_Assimilator 2 7266
Protoss_Cybernetics_Core 1 6621
Protoss_Dragoon 6 9241
Protoss_Robotics_Facility 1 8165
Protoss_Observatory 1 9611
Protoss_Shuttle 1 9859
9993
