Protoss_Nexus 1 0
Protoss_Gateway 1 1913
Protoss_Assimilator 1 2845
Protoss_Zealot 4 5396
Protoss_Cybernetics_Core 1 4746
Protoss_Robotics_Facility 1 5989
Protoss_Dragoon 4 9231
Protoss_Shuttle 1 7276
Protoss_Robotics_Support_Bay 1 7559
Protoss_Reaver 2 9296
Protoss_Scarab 4 9948
9948
