Protoss_Nexus 1 0
Protoss_Gateway 2 6045
Protoss_Assimilator 1 2253
Protoss_Zealot 7 6528
Protoss_Cybernetics_Core 1 4745
Protoss_Dragoon 8 9587
Protoss_Robotics_Facility 1 7155
Protoss_Observatory 1 8478
Protoss_Observer 1 9521
9587
