Protoss_Nexus 2 2583
Protoss_Gateway 2 3312
Protoss_Zealot 5 6687
Protoss_Assimilator 2 8903
Protoss_Forge 1 5576
Protoss_Cybernetics_Core 1 5837
Protoss_Photon_Cannon 10 9765
Protoss_Citadel_of_Adun 1 7013
Protoss_Templar_Archives 1 8154
Protoss_Dark_Templar 2 9141
9765
