Protoss_Nexus 2 9325
Protoss_Gateway 3 9918
Protoss_Assimilator 1 2414
Protoss_Zealot 7 9045
Protoss_Cybernetics_Core 1 4127
Protoss_Citadel_of_Adun 1 5135
Protoss_Dragoon 1 5421
Protoss_Templar_Archives 1 6129
Protoss_Dark_Templar 1 7107
Protoss_High_Templar 3 9647
Protoss_Forge 1 8113
Protoss_Photon_Cannon 1 9694
9918
