Protoss_Nexus 2 7857
Protoss_Gateway 2 6857
Protoss_Assimilator 1 2451
Protoss_Zealot 2 4027
Protoss_Cybernetics_Core 1 3739
Protoss_Dragoon 8 9637
Protoss_Robotics_Facility 1 5983
Protoss_Observatory 1 7351
Protoss_Observer 1 7925
Protoss_Robotics_Support_Bay 1 8204
Protoss_Reaver 2 9845
9845
