Protoss_Nexus 1 0
Protoss_Gateway 2 6710
Protoss_Assimilator 1 2981
Protoss_Zealot 2 3945
Protoss_Cybernetics_Core 1 3883
Protoss_Dragoon 8 9131
Protoss_Robotics_Facility 1 5923
Protoss_Shuttle 1 7251
Protoss_Observatory 1 7265
Protoss_Observer 1 8153
Protoss_Robotics_Support_Bay 1 8259
Protoss_Reaver 1 8791
9131
