Protoss_Nexus 2 8927
Protoss_Gateway 2 6647
Protoss_Assimilator 1 2451
Protoss_Cybernetics_Core 1 3150
Protoss_Dragoon 8 9577
Protoss_Robotics_Facility 1 5912
Protoss_Observatory 1 7345
Protoss_Shuttle 1 7509
Protoss_Robotics_Support_Bay 1 8297
Protoss_Observer 1 8411
Protoss_Reaver 1 9199
9577
