Protoss_Nexus 2 9717
Protoss_Gateway 2 4995
Protoss_Assimilator 1 2354
Protoss_Zealot 2 3685
Protoss_Cybernetics_Core 1 4383
Protoss_Dragoon 10 9961
Protoss_Robotics_Facility 1 5997
Protoss_Observatory 1 7283
Protoss_Observer 3 9441
9961
