Protoss_Nexus 1 0
Protoss_Gateway 3 5875
Protoss_Zealot 2 4667
Protoss_Assimilator 1 4302
Protoss_Cybernetics_Core 1 5419
Protoss_Dragoon 7 9733
Protoss_Robotics_Facility 1 6867
Protoss_Shuttle 1 8155
Protoss_Robotics_Support_Bay 1 8769
Protoss_Reaver 1 9299
9733
