Protoss_Nexus 2 8816
Protoss_Gateway 4 9741
Protoss_Assimilator 1 2460
Protoss_Cybernetics_Core 1 3079
Protoss_Dragoon 9 9429
Protoss_Robotics_Facility 1 6673
Protoss_Observatory 1 7969
Protoss_Observer 2 9103
Protoss_Robotics_Support_Bay 1 9916
9916
