Protoss_Nexus 2 4086
Protoss_Gateway 2 2465
Protoss_Zealot 3 5111
Protoss_Assimilator 2 8547
Protoss_Cybernetics_Core 1 4711
Protoss_Dragoon 8 9579
Protoss_Forge 1 6836
Protoss_Citadel_of_Adun 1 7579
Protoss_Photon_Cannon 3 9140
Protoss_Robotics_Facility 1 8071
Protoss_Observatory 1 9363
Protoss_Observer 1 9921
9921
