Protoss_Nexus 2 8373
Protoss_Gateway 4 9614
Protoss_Assimilator 1 2409
Protoss_Zealot 2 4591
Protoss_Cybernetics_Core 1 3816
Protoss_Citadel_of_Adun 1 4803
Protoss_Dragoon 6 9573
Protoss_Templar_Archives 1 5790
Protoss_Dark_Templar 3 7683
Protoss_Robotics_Facility 1 9928
9928
