Protoss_Nexus 2 8459
Protoss_Gateway 2 4174
Protoss_Assimilator 1 2523
Protoss_Zealot 3 9497
Protoss_Cybernetics_Core 1 3565
Protoss_Dragoon 5 6821
Protoss_Citadel_of_Adun 1 5478
Protoss_Forge 1 6419
Protoss_Templar_Archives 1 6469
Protoss_Dark_Templar 2 7573
Protoss_Photon_Cannon 3 9962
Protoss_High_Templar 2 8551
Protoss_Archon 1 9908
9962
