Protoss_Nexus 2 4985
Protoss_Gateway 4 9840
Protoss_Zealot 9 7681
Protoss_Assimilator 2 6887
Protoss_Cybernetics_Core 1 5832
Protoss_Dragoon 4 9351
Protoss_Forge 1 9178
9840
