Protoss_Nexus 2 9197
Protoss_Gateway 4 9859
Protoss_Assimilator 1 2342
Protoss_Zealot 3 4595
Protoss_Cybernetics_Core 1 4111
Protoss_Dragoon 10 9655
Protoss_Robotics_Facility 1 6429
Protoss_Observatory 1 7763
Protoss_Observer 3 9911
9911
