Protoss_Nexus 1 0
Protoss_Gateway 2 3443
Protoss_Assimilator 1 2243
Protoss_Cybernetics_Core 1 2896
Protoss_Dragoon 15 9931
Protoss_Robotics_Facility 1 7190
Protoss_Shuttle 1 8551
Protoss_Observatory 1 8959
Protoss_Observer 1 9501
9931
