Protoss_Nexus 1 0
Protoss_Gateway 3 7409
Protoss_Zealot 4 9328
Protoss_Assimilator 1 3334
Protoss_Cybernetics_Core 1 3958
Protoss_Dragoon 11 9816
Protoss_Robotics_Facility 1 6583
Protoss_Observatory 1 8294
Protoss_Observer 2 9626
9816
