Protoss_Nexus 2 8863
Protoss_Gateway 2 6231
Protoss_Assimilator 1 2242
Protoss_Zealot 3 4305
Protoss_Cybernetics_Core 1 3985
Protoss_Dragoon 4 9981
Protoss_Citadel_of_Adun 1 5599
Protoss_Templar_Archives 1 6748
Protoss_Forge 1 7603
Protoss_Dark_Templar 2 7763
Protoss_Photon_Cannon 3 9391
Protoss_High_Templar 2 9175
9981
