Protoss_Nexus 2 4870
Protoss_Gateway 4 8947
Protoss_Zealot 5 5525
Protoss_Assimilator 2 7479
Protoss_Cybernetics_Core 1 6041
Protoss_Dragoon 8 9985
Protoss_Robotics_Facility 1 8043
Protoss_Forge 1 8070
Protoss_Photon_Cannon 2 9561
Protoss_Observatory 1 9369
9985
