Protoss_Nexus 2 7070
Protoss_Gateway 2 5486
Protoss_Zealot 5 8571
Protoss_Cybernetics_Core 1 4047
Protoss_Assimilator 1 5358
Protoss_Dragoon 7 9925
Protoss_Robotics_Facility 1 8479
9925
