Protoss_Nexus 1 0
Protoss_Gateway 2 7478
Protoss_Assimilator 3 4646
Protoss_Zealot 3 4823
Protoss_Cybernetics_Core 1 4293
Protoss_Dragoon 8 9779
Protoss_Robotics_Facility 1 6777
Protoss_Shuttle 1 8311
Protoss_Robotics_Support_Bay 1 9087
Protoss_Observatory 1 9147
Protoss_Observer 1 9809
9809
