Protoss_Nexus 3 9997
Protoss_Gateway 3 8511
Protoss_Zealot 5 5765
Protoss_Assimilator 2 6923
Protoss_Cybernetics_Core 1 5540
Protoss_Dragoon 9 9503
Protoss_Robotics_Facility 1 7371
Protoss_Shuttle 1 8651
Protoss_Observatory 1 8726
Protoss_Observer 1 9675
9997
