Protoss_Nexus 2 6029
Protoss_Gateway 2 2347
Protoss_Zealot 15 8595
Protoss_Assimilator 2 8811
Protoss_Cybernetics_Core 1 7069
Protoss_Forge 1 8133
Protoss_Citadel_of_Adun 1 8371
Protoss_Photon_Cannon 2 9097
Protoss_Robotics_Facility 1 9331
9331
