Protoss_Nexus 2 6417
Protoss_Gateway 2 2325
Protoss_Zealot 13 7701
Protoss_Assimilator 2 9379
Protoss_Forge 1 6897
Protoss_Cybernetics_Core 1 8054
Protoss_Photon_Cannon 2 9680
Protoss_Citadel_of_Adun 1 9449
Protoss_Robotics_Facility 1 9904
9904
