Protoss_Nexus 2 5249
Protoss_Gateway 2 2442
Protoss_Zealot 7 6647
Protoss_Assimilator 2 7176
Protoss_Cybernetics_Core 1 6374
Protoss_Citadel_of_Adun 1 7520
Protoss_Dragoon 4 8547
Protoss_Templar_Archives 1 8581
Protoss_Forge 1 8645
Protoss_Robotics_Facility 1 9094
Protoss_Photon_Cannon 1 9639
Protoss_Dark_Templar 2 9809
9809
