Protoss_Nexus 1 0
Protoss_Gateway 1 1954
Protoss_Assimilator 1 2343
Protoss_Cybernetics_Core 1 2999
Protoss_Robotics_Facility 1 4131
Protoss_Zealot 2 4838
Protoss_Shuttle 1 5421
Protoss_Dragoon 2 7311
Protoss_Robotics_Support_Bay 1 6363
Protoss_Reaver 1 6901
Protoss_Scarab 1 8165
8165
