Protoss_Nexus 2 6789
Protoss_Gateway 3 8221
Protoss_Assimilator 1 2268
Protoss_Cybernetics_Core 1 2918
Protoss_Robotics_Facility 1 4033
Protoss_Dragoon 9 9583
Protoss_Shuttle 1 5326
Protoss_Observatory 1 5486
Protoss_Observer 3 7432
9583
