Protoss_Nexus 1 0
Protoss_Gateway 1 2025
Protoss_Assimilator 1 2230
Protoss_Cybernetics_Core 1 3061
Protoss_Zealot 2 4281
Protoss_Robotics_Facility 1 4058
Protoss_Shuttle 1 5351
Protoss_Robotics_Support_Bay 1 5601
Protoss_Dragoon 1 5741
Protoss_Reaver 2 8791
Protoss_Shield_Battery 1 8540
8791
