Protoss_Nexus 1 0
Protoss_Gateway 3 7843
Protoss_Assimilator 1 2198
Protoss_Cybernetics_Core 1 3011
Protoss_Citadel_of_Adun 1 4029
Protoss_Robotics_Facility 1 4669
Protoss_Templar_Archives 1 5386
Protoss_Shuttle 1 5956
Protoss_Dark_Templar 2 6656
Protoss_Observatory 1 6817
Protoss_Dragoon 6 9221
Protoss_Observer 1 7366
9221
