Protoss_Nexus 2 6138
Protoss_Gateway 3 7757
Protoss_Zealot 3 4111
Protoss_Assimilator 1 3030
Protoss_Cybernetics_Core 1 3916
Protoss_Dragoon 8 9701
Protoss_Robotics_Facility 1 6978
Protoss_Observatory 1 8296
Protoss_Observer 2 9463
Protoss_Robotics_Support_Bay 1 8985
9701
