Protoss_Nexus 2 9009
Protoss_Gateway 2 6482
Protoss_Assimilator 1 2363
Protoss_Cybernetics_Core 1 3007
Protoss_Zealot 1 3329
Protoss_Dragoon 2 5789
Protoss_Citadel_of_Adun 1 5417
Protoss_Templar_Archives 1 6547
Protoss_Forge 2 7127
Protoss_Dark_Templar 2 7623
Protoss_Photon_Cannon 3 9908
9908
