Protoss_Nexus 3 8535
Protoss_Gateway 4 9807
Protoss_Assimilator 1 2865
Protoss_Cybernetics_Core 1 3172
Protoss_Zealot 1 3721
Protoss_Dragoon 7 9165
Protoss_Robotics_Facility 1 6779
Protoss_Observatory 1 8200
Protoss_Observer 2 9351
Protoss_Robotics_Support_Bay 1 9451
9807
