Protoss_Nexus 1 0
Protoss_Gateway 4 7710
Protoss_Assimilator 1 2473
Protoss_Cybernetics_Core 1 3117
Protoss_Robotics_Facility 1 4360
Protoss_Dragoon 4 9351
Protoss_Citadel_of_Adun 1 5438
Protoss_Shuttle 1 5651
Protoss_Observatory 1 5826
Protoss_Observer 5 9920
Protoss_Zealot 10 9993
9993
