Protoss_Nexus 1 0
Protoss_Gateway 3 5712
Protoss_Assimilator 1 2386
Protoss_Zealot 1 2975
Protoss_Cybernetics_Core 1 4291
Protoss_Dragoon 11 9313
Protoss_Robotics_Facility 1 8425
Protoss_Observatory 1 9765
9765
