Protoss_Nexus 2 5801
Protoss_Gateway 2 2431
Protoss_Zealot 11 7449
Protoss_Assimilator 2 8249
Protoss_Cybernetics_Core 1 6409
Protoss_Citadel_of_Adun 1 7692
Protoss_Dragoon 2 8515
Protoss_Templar_Archives 1 8815
Protoss_Forge 1 9183
Protoss_Dark_Templar 2 9839
9839
