Protoss_Nexus 1 0
Protoss_Gateway 2 5576
Protoss_Assimilator 1 2632
Protoss_Zealot 3 9001
Protoss_Cybernetics_Core 1 3580
Protoss_Dragoon 12 9823
Protoss_Robotics_Facility 1 7151
Protoss_Observatory 1 8447
Protoss_Observer 2 9579
9823
