Protoss_Nexus 2 5130
Protoss_Gateway 2 2425
Protoss_Zealot 9 7089
Protoss_Assimilator 2 8233
Protoss_Cybernetics_Core 1 6663
Protoss_Dragoon 6 9763
Protoss_Robotics_Facility 1 8639
Protoss_Shuttle 1 9995
9995
