Protoss_Nexus 1 0
Protoss_Gateway 2 8913
Protoss_Assimilator 1 2248
Protoss_Cybernetics_Core 1 3039
Protoss_Stargate 1 4051
Protoss_Robotics_Facility 1 4406
Protoss_Dragoon 7 9301
Protoss_Observatory 1 5784
Protoss_Observer 3 9206
Protoss_Shuttle 1 7760
Protoss_Robotics_Support_Bay 1 9146
Protoss_Reaver 1 9808
9808
