Protoss_Nexus 1 0
Protoss_Gateway 2 6845
Protoss_Assimilator 1 2402
Protoss_Zealot 2 4103
Protoss_Cybernetics_Core 1 3688
Protoss_Dragoon 9 9517
Protoss_Robotics_Facility 1 6015
Protoss_Shuttle 1 7425
Protoss_Robotics_Support_Bay 1 7911
Protoss_Reaver 1 8481
Protoss_Observatory 1 9041
Protoss_Scarab 3 9984
9984
