Protoss_Nexus 1 0
Protoss_Gateway 2 3839
Protoss_Assimilator 1 2304
Protoss_Zealot 7 9433
Protoss_Cybernetics_Core 2 4805
Protoss_Dragoon 8 8681
Protoss_Robotics_Facility 1 7329
Protoss_Shuttle 1 8607
Protoss_Robotics_Support_Bay 1 8821
Protoss_Observatory 1 9211
Protoss_Reaver 1 9621
9621
