Protoss_Nexus 1 0
Protoss_Gateway 2 4212
Protoss_Assimilator 1 2560
Protoss_Zealot 7 8291
Protoss_Cybernetics_Core 2 7407
Protoss_Shield_Battery 1 5064
Protoss_Dragoon 1 8601
Protoss_Robotics_Facility 1 9321
9321
