Protoss_Nexus 2 9769
Protoss_Gateway 2 2622
Protoss_Zealot 14 8446
Protoss_Assimilator 1 6743
Protoss_Cybernetics_Core 1 7602
Protoss_Dragoon 2 9241
Protoss_Robotics_Facility 1 9394
9769
