Protoss_Nexus 2 8483
Protoss_Gateway 2 6436
Protoss_Assimilator 2 9393
Protoss_Zealot 2 3901
Protoss_Cybernetics_Core 1 3682
Protoss_Dragoon 3 6167
Protoss_Citadel_of_Adun 1 5558
Protoss_Templar_Archives 1 6677
Protoss_Forge 1 6999
Protoss_Dark_Templar 2 7727
Protoss_Photon_Cannon 1 7820
Protoss_High_Templar 2 9491
9491
