Protoss_Nexus 1 0
Protoss_Gateway 3 7558
Protoss_Zealot 7 4709
Protoss_Assimilator 1 4295
Protoss_Cybernetics_Core 1 5487
Protoss_Dragoon 9 8911
Protoss_Forge 1 9590
9590
