Protoss_Nexus 2 9055
Protoss_Gateway 2 6184
Protoss_Assimilator 1 2385
Protoss_Zealot 2 3763
Protoss_Cybernetics_Core 1 3539
Protoss_Dragoon 10 9579
Protoss_Robotics_Facility 1 5621
Protoss_Observatory 1 6922
Protoss_Observer 2 8821
Protoss_Robotics_Support_Bay 1 9403
9579
