Protoss_Nexus 1 0
Protoss_Gateway 3 9769
Protoss_Zealot 8 8411
Protoss_Assimilator 1 4555
Protoss_Cybernetics_Core 1 5246
Protoss_Robotics_Facility 1 6838
Protoss_Dragoon 5 9466
Protoss_Observatory 1 8753
9769
