Protoss_Nexus 2 9491
Protoss_Gateway 2 5881
Protoss_Assimilator 1 2342
Protoss_Zealot 2 3813
Protoss_Cybernetics_Core 1 3480
Protoss_Dragoon 9 8831
Protoss_Robotics_Facility 1 5635
Protoss_Observatory 1 7045
Protoss_Observer 1 7579
Protoss_Robotics_Support_Bay 1 7687
Protoss_Reaver 1 8665
Protoss_Shuttle 1 9717
9717
