Protoss_Nexus 2 8895
Protoss_Gateway 4 9496
Protoss_Assimilator 1 2443
Protoss_Zealot 2 3877
Protoss_Cybernetics_Core 1 3468
Protoss_Dragoon 6 8455
Protoss_Citadel_of_Adun 1 5567
Protoss_Templar_Archives 1 6607
Protoss_Forge 1 7058
Protoss_Dark_Templar 1 7585
Protoss_Photon_Cannon 1 8081
Protoss_High_Templar 2 9207
9496
