Protoss_Nexus 2 5075
Protoss_Gateway 2 7266
Protoss_Zealot 11 8915
Protoss_Forge 1 5867
Protoss_Photon_Cannon 11 9963
Protoss_Assimilator 1 7613
Protoss_Cybernetics_Core 1 8529
Protoss_Dragoon 2 9655
9963
