Protoss_Nexus 2 8423
Protoss_Gateway 3 9045
Protoss_Assimilator 2 9896
Protoss_Zealot 2 3803
Protoss_Cybernetics_Core 1 3585
Protoss_Dragoon 12 9609
Protoss_Robotics_Facility 1 6482
Protoss_Observatory 1 7913
Protoss_Observer 2 9089
Protoss_Citadel_of_Adun 1 9790
9896
