Protoss_Nexus 2 8228
Protoss_Gateway 2 6771
Protoss_Zealot 2 3501
Protoss_Assimilator 1 3069
Protoss_Cybernetics_Core 1 3969
Protoss_Dragoon 8 9291
Protoss_Robotics_Facility 1 7381
Protoss_Shuttle 1 8669
Protoss_Robotics_Support_Bay 1 8737
Protoss_Reaver 1 9589
Protoss_Observatory 1 9901
9901
