Protoss_Nexus 2 6512
Protoss_Gateway 2 7747
Protoss_Assimilator 1 2477
Protoss_Cybernetics_Core 1 3257
Protoss_Zealot 1 3553
Protoss_Dragoon 9 9929
Protoss_Forge 1 7213
Protoss_Photon_Cannon 2 8987
9929
