Protoss_Nexus 2 9153
Protoss_Gateway 3 9815
Protoss_Assimilator 1 2385
Protoss_Zealot 1 2851
Protoss_Cybernetics_Core 1 3564
Protoss_Dragoon 10 9573
Protoss_Robotics_Facility 1 7331
Protoss_Observatory 1 8685
Protoss_Observer 2 9867
9867
