Protoss_Nexus 2 6630
Protoss_Gateway 3 8078
Protoss_Assimilator 1 2357
Protoss_Zealot 2 3975
Protoss_Cybernetics_Core 1 3714
Protoss_Dragoon 11 9957
Protoss_Robotics_Facility 1 7157
Protoss_Observatory 1 8549
Protoss_Observer 1 9079
Protoss_Robotics_Support_Bay 1 9096
Protoss_Reaver 1 9821
9957
