Protoss_Nexus 2 6513
Protoss_Gateway 2 8229
Protoss_Assimilator 2 9723
Protoss_Zealot 2 3927
Protoss_Cybernetics_Core 1 3633
Protoss_Dragoon 5 7895
Protoss_Citadel_of_Adun 1 7015
Protoss_Forge 1 7525
Protoss_Templar_Archives 1 8231
Protoss_Photon_Cannon 2 8833
Protoss_Dark_Templar 2 9229
Protoss_High_Templar 2 9981
9981
