Protoss_Nexus 2 4751
Protoss_Gateway 2 2528
Protoss_Zealot 3 6055
Protoss_Assimilator 3 6494
Protoss_Cybernetics_Core 1 5234
Protoss_Dragoon 9 9719
Protoss_Robotics_Facility 1 7629
Protoss_Shuttle 1 8975
Protoss_Observatory 1 9069
Protoss_Robotics_Support_Bay 1 9498
Protoss_Observer 1 9893
9893
