Protoss_Nexus 2 7231
Protoss_Gateway 2 5327
Protoss_Assimilator 1 2202
Protoss_Zealot 2 3813
Protoss_Cybernetics_Core 1 3546
Protoss_Dragoon 1 4523
Protoss_Citadel_of_Adun 1 4973
Protoss_Templar_Archives 1 5961
Protoss_Dark_Templar 2 6979
Protoss_Forge 1 7334
Protoss_Photon_Cannon 7 9792
Protoss_High_Templar 3 9337
9792
