Protoss_Nexus 1 0
Protoss_Gateway 3 5935
Protoss_Assimilator 1 2298
Protoss_Zealot 2 3653
Protoss_Cybernetics_Core 1 3426
Protoss_Dragoon 15 9601
Protoss_Robotics_Facility 1 5165
Protoss_Observatory 1 6461
Protoss_Observer 2 7623
Protoss_Shuttle 1 9975
9975
