Protoss_Nexus 1 0
Protoss_Gateway 1 2196
Protoss_Assimilator 1 2523
Protoss_Zealot 1 3511
Protoss_Cybernetics_Core 1 3963
Protoss_Robotics_Facility 2 9780
Protoss_Dragoon 5 9671
Protoss_Shuttle 1 6766
Protoss_Robotics_Support_Bay 1 6907
Protoss_Reaver 2 8720
9780
