Protoss_Nexus 1 0
Protoss_Gateway 1 1948
Protoss_Assimilator 1 2483
Protoss_Zealot 2 3981
Protoss_Cybernetics_Core 1 4400
Protoss_Robotics_Facility 1 5441
Protoss_Dragoon 3 8153
Protoss_Shuttle 1 6901
Protoss_Robotics_Support_Bay 1 6959
Protoss_Citadel_of_Adun 1 7733
Protoss_Reaver 2 8866
Protoss_Forge 1 8298
Protoss_Templar_Archives 1 8729
Protoss_Dark_Templar 1 9751
9751
