Protoss_Nexus 2 8743
Protoss_Assimilator 1 1802
Protoss_Gateway 2 6827
Protoss_Cybernetics_Core 1 3428
Protoss_Stargate 1 4428
Protoss_Citadel_of_Adun 1 4743
Protoss_Robotics_Facility 1 5238
Protoss_Corsair 2 7001
Protoss_Templar_Archives 1 6363
Protoss_Forge 1 6505
Protoss_Shuttle 1 6531
Protoss_Dark_Templar 3 8138
Protoss_Dragoon 4 9938
9938
