Protoss_Nexus 2 5590
Protoss_Gateway 3 6691
Protoss_Assimilator 1 2235
Protoss_Cybernetics_Core 1 2873
Protoss_Dragoon 12 9353
Protoss_Robotics_Facility 2 9788
Protoss_Observatory 1 9880
9880
