Protoss_Nexus 2 9703
Protoss_Gateway 1 2043
Protoss_Assimilator 1 2413
Protoss_Cybernetics_Core 1 3123
Protoss_Dragoon 6 8981
Protoss_Robotics_Facility 1 4480
Protoss_Robotics_Support_Bay 1 5794
Protoss_Shield_Battery 1 6002
Protoss_Reaver 2 9440
Protoss_Observatory 1 7467
Protoss_Shuttle 1 7936
Protoss_Observer 1 8838
9703
