Protoss_Nexus 1 0
Protoss_Assimilator 1 1865
Protoss_Gateway 1 2374
Protoss_Cybernetics_Core 1 3436
Protoss_Robotics_Facility 1 4470
Protoss_Observatory 1 5816
Protoss_Dragoon 5 9211
9211
