Protoss_Nexus 2 9577
Protoss_Gateway 4 8534
Protoss_Zealot 5 5586
Protoss_Assimilator 2 4241
Protoss_Cybernetics_Core 1 4931
Protoss_Dragoon 4 7331
Protoss_Citadel_of_Adun 1 6762
Protoss_Templar_Archives 1 7811
Protoss_Dark_Templar 2 8826
Protoss_Forge 1 9750
9750
