Protoss_Nexus 1 0
Protoss_Gateway 2 3148
Protoss_Assimilator 2 3596
Protoss_Zealot 11 7116
Protoss_Cybernetics_Core 1 6650
Protoss_Citadel_of_Adun 1 7648
Protoss_Templar_Archives 1 8645
Protoss_Forge 1 9138
Protoss_Dark_Templar 2 9646
9646
