Protoss_Nexus 2 9493
Protoss_Gateway 3 9658
Protoss_Zealot 7 6236
Protoss_Assimilator 1 5513
Protoss_Cybernetics_Core 1 5766
Protoss_Dragoon 7 9356
Protoss_Robotics_Facility 1 8943
9658
