Protoss_Nexus 1 0
Protoss_Assimilator 1 1849
Protoss_Gateway 1 2268
Protoss_Cybernetics_Core 1 3268
Protoss_Robotics_Facility 2 5493
Protoss_Zealot 4 6406
Protoss_Observatory 1 6123
Protoss_Robotics_Support_Bay 1 6774
Protoss_Forge 1 8710
Protoss_Photon_Cannon 1 9434
9434
