Protoss_Nexus 1 0
Protoss_Gateway 1 1832
Protoss_Assimilator 1 2203
Protoss_Cybernetics_Core 1 2925
Protoss_Zealot 4 5605
Protoss_Robotics_Facility 2 8984
Protoss_Shuttle 2 9278
Protoss_Robotics_Support_Bay 1 5928
Protoss_Reaver 2 8226
Protoss_Dragoon 4 9656
9656
