Protoss_Nexus 1 0
Protoss_Gateway 2 4070
Protoss_Assimilator 1 2513
Protoss_Zealot 5 5551
Protoss_Shield_Battery 1 4658
Protoss_Cybernetics_Core 1 5768
Protoss_Dragoon 2 7411
7411
