Protoss_Nexus 1 0
Protoss_Gateway 2 4828
Protoss_Assimilator 1 2363
Protoss_Zealot 3 4256
Protoss_Cybernetics_Core 1 3586
Protoss_Shield_Battery 1 4008
Protoss_Dragoon 7 9831
Protoss_Robotics_Facility 1 7114
Protoss_Shuttle 1 8551
Protoss_Robotics_Support_Bay 1 8820
Protoss_Reaver 1 9453
9831
