Protoss_Nexus 2 9623
Protoss_Assimilator 1 1828
Protoss_Gateway 3 9244
Protoss_Cybernetics_Core 1 3318
Protoss_Robotics_Facility 1 4318
Protoss_Shuttle 1 5606
Protoss_Observatory 1 5634
Protoss_Robotics_Support_Bay 1 5724
Protoss_Dragoon 3 9006
Protoss_Observer 1 6508
Protoss_Reaver 2 8986
Protoss_Zealot 1 7721
9623
