Protoss_Nexus 1 0
Protoss_Gateway 2 4895
Protoss_Assimilator 1 2498
Protoss_Zealot 2 3927
Protoss_Cybernetics_Core 1 3750
Protoss_Shield_Battery 1 4395
Protoss_Dragoon 4 9683
Protoss_Robotics_Facility 1 9313
9683
