Protoss_Nexus 2 4869
Protoss_Gateway 4 9952
Protoss_Zealot 7 6823
Protoss_Shield_Battery 1 5338
Protoss_Assimilator 1 5397
Protoss_Forge 1 7127
Protoss_Cybernetics_Core 1 7293
Protoss_Photon_Cannon 2 7956
Protoss_Dragoon 7 9965
9965
