Protoss_Nexus 1 0
Protoss_Gateway 3 4429
Protoss_Zealot 9 6889
Protoss_Forge 2 5226
Protoss_Photon_Cannon 3 7858
Protoss_Assimilator 1 6191
Protoss_Cybernetics_Core 1 6582
Protoss_Dragoon 4 9633
Protoss_Citadel_of_Adun 1 8469
Protoss_Templar_Archives 1 9459
9633
