Protoss_Nexus 1 0
Protoss_Gateway 3 8773
Protoss_Assimilator 1 2466
Protoss_Cybernetics_Core 1 3454
Protoss_Dragoon 3 9923
Protoss_Citadel_of_Adun 1 4610
Protoss_Templar_Archives 1 6003
Protoss_Zealot 4 9791
Protoss_Dark_Templar 2 8950
Protoss_High_Templar 2 7778
Protoss_Archon 1 9026
Protoss_Forge 1 9377
Psionic_Storm 1 9811
9923
