Protoss_Nexus 1 0
Protoss_Assimilator 1 1854
Protoss_Gateway 2 5453
Protoss_Cybernetics_Core 1 3370
Protoss_Citadel_of_Adun 1 4383
Protoss_Forge 1 5299
Protoss_Templar_Archives 1 5600
Protoss_Photon_Cannon 3 7865
Protoss_Dark_Templar 6 8125
Protoss_Dark_Archon 2 8213
Protoss_Robotics_Facility 1 8333
Protoss_Dragoon 2 9541
Protoss_Shuttle 1 9651
9651
