Protoss_Nexus 1 0
Protoss_Gateway 2 2778
Protoss_Zealot 7 6116
Protoss_Assimilator 1 4359
Protoss_Cybernetics_Core 1 5260
Protoss_Dragoon 1 6731
Protoss_Citadel_of_Adun 1 7048
Protoss_Templar_Archives 1 8073
Protoss_Dark_Templar 2 9351
Protoss_Forge 1 9715
9715
