Protoss_Nexus 1 0
Protoss_Gateway 2 5752
Protoss_Zealot 4 5696
Protoss_Assimilator 1 3660
Protoss_Cybernetics_Core 1 4678
Protoss_Robotics_Facility 1 6461
Protoss_Dragoon 6 9098
Protoss_Robotics_Support_Bay 1 7768
Protoss_Reaver 1 8806
Protoss_Shuttle 1 9886
9886
