Protoss_Nexus 3 9359
Protoss_Assimilator 2 5515
Protoss_Gateway 3 8003
Protoss_Cybernetics_Core 1 4633
Protoss_Stargate 1 5708
Protoss_Citadel_of_Adun 1 5846
Protoss_Forge 1 6128
Protoss_Photon_Cannon 3 7473
Protoss_Corsair 2 7641
Protoss_Templar_Archives 1 7228
Protoss_Robotics_Facility 1 8404
Protoss_High_Templar 1 8561
Protoss_Shuttle 1 9726
Protoss_Robotics_Support_Bay 1 9832
9832
