Protoss_Nexus 1 0
Protoss_Gateway 3 9072
Protoss_Zealot 15 8056
Protoss_Assimilator 1 6468
Protoss_Cybernetics_Core 1 6758
Protoss_Citadel_of_Adun 1 8228
Protoss_Forge 1 8438
Protoss_Templar_Archives 1 9591
Protoss_Photon_Cannon 2 9962
9962
