Protoss_Nexus 1 0
Protoss_Gateway 2 3978
Protoss_Assimilator 2 2999
Protoss_Zealot 13 8061
Protoss_Cybernetics_Core 1 7644
Protoss_Dragoon 4 9668
Protoss_Citadel_of_Adun 1 9284
9668
