Protoss_Nexus 2 7093
Protoss_Gateway 2 2688
Protoss_Zealot 11 7531
Protoss_Assimilator 1 7488
Protoss_Forge 1 8453
Protoss_Cybernetics_Core 1 8507
Protoss_Photon_Cannon 2 9442
Protoss_Dragoon 2 9676
9676
