Protoss_Nexus 1 0
Protoss_Assimilator 1 1623
Protoss_Gateway 3 9442
Protoss_Cybernetics_Core 1 3273
Protoss_Robotics_Facility 1 4368
Protoss_Dragoon 7 9546
Protoss_Shuttle 1 5791
Protoss_Observatory 1 6163
Protoss_Observer 1 6971
Protoss_Robotics_Support_Bay 1 7063
Protoss_Reaver 2 8996
9546
