Protoss_Nexus 1 0
Protoss_Assimilator 1 1796
Protoss_Gateway 3 8003
Protoss_Cybernetics_Core 1 3389
Protoss_Robotics_Facility 1 4441
Protoss_Dragoon 12 9936
Protoss_Shuttle 1 5766
Protoss_Observatory 1 5940
Protoss_Observer 2 8146
Protoss_Robotics_Support_Bay 1 8737
9936
