Protoss_Nexus 1 0
Protoss_Gateway 3 8004
Protoss_Zealot 5 5531
Protoss_Assimilator 1 4514
Protoss_Cybernetics_Core 1 5109
Protoss_Dragoon 10 9833
Protoss_Robotics_Facility 1 8528
Protoss_Observatory 1 9932
9932
