Protoss_Nexus 2 9898
Protoss_Gateway 2 4601
Protoss_Assimilator 1 2499
Protoss_Cybernetics_Core 1 3103
Protoss_Zealot 1 3316
Protoss_Dragoon 7 8326
Protoss_Robotics_Facility 1 7705
Protoss_Observatory 1 9073
Protoss_Robotics_Support_Bay 1 9345
Protoss_Observer 1 9636
9898
