Protoss_Nexus 1 0
Protoss_Gateway 3 8951
Protoss_Zealot 11 9877
Protoss_Assimilator 1 5233
Protoss_Cybernetics_Core 1 5845
Protoss_Dragoon 8 9981
Protoss_Robotics_Facility 1 9151
9981
