Protoss_Nexus 2 9340
Protoss_Gateway 3 7273
Protoss_Assimilator 1 2309
Protoss_Zealot 2 4016
Protoss_Cybernetics_Core 1 3729
Protoss_Dragoon 9 9786
Protoss_Robotics_Facility 1 5594
Protoss_Observatory 1 6932
Protoss_Observer 3 8700
Protoss_Robotics_Support_Bay 1 9561
9786
