Protoss_Nexus 1 0
Protoss_Gateway 2 3404
Protoss_Assimilator 1 2459
Protoss_Cybernetics_Core 1 3036
Protoss_Dragoon 11 9821
Protoss_Robotics_Facility 1 5683
Protoss_Observatory 1 6995
Protoss_Observer 3 9441
Protoss_Forge 1 9513
Protoss_Robotics_Support_Bay 1 9969
9969
