Protoss_Nexus 1 0
Protoss_Gateway 2 4658
Protoss_Assimilator 1 2462
Protoss_Zealot 3 4106
Protoss_Cybernetics_Core 1 3892
Protoss_Dragoon 11 9351
Protoss_Robotics_Facility 1 7188
Protoss_Observatory 1 8510
Protoss_Observer 1 9056
9351
