Protoss_Nexus 2 9808
Protoss_Gateway 2 9396
Protoss_Assimilator 1 2347
Protoss_Cybernetics_Core 1 2999
Protoss_Zealot 1 3557
Protoss_Dragoon 7 9503
Protoss_Robotics_Facility 1 4445
Protoss_Shuttle 1 5785
Protoss_Observatory 1 5923
Protoss_Observer 2 7289
Protoss_Forge 1 9886
9886
