Protoss_Nexus 2 8961
Protoss_Gateway 2 4664
Protoss_Assimilator 1 2343
Protoss_Cybernetics_Core 1 3011
Protoss_Dragoon 11 9271
Protoss_Robotics_Facility 1 6399
Protoss_Zealot 1 6659
Protoss_Robotics_Support_Bay 1 7855
Protoss_Reaver 2 9563
9563
