Protoss_Nexus 2 7717
Protoss_Gateway 4 9643
Protoss_Assimilator 2 9228
Protoss_Zealot 2 3767
Protoss_Cybernetics_Core 1 3515
Protoss_Robotics_Facility 1 4611
Protoss_Dragoon 10 9849
Protoss_Observatory 1 5992
Protoss_Observer 4 8700
9849
