Protoss_Nexus 1 0
Protoss_Gateway 3 8958
Protoss_Assimilator 1 2384
Protoss_Zealot 9 8775
Protoss_Shield_Battery 1 3864
Protoss_Cybernetics_Core 1 8366
Protoss_Dragoon 2 9805
9805
