Protoss_Nexus 2 3507
Protoss_Gateway 3 8863
Protoss_Zealot 2 4785
Protoss_Assimilator 2 8824
Protoss_Cybernetics_Core 1 4495
Protoss_Dragoon 11 9677
Protoss_Shield_Battery 1 7428
Protoss_Robotics_Facility 1 8140
Protoss_Observatory 1 9549
Protoss_Forge 1 9770
9770
