Protoss_Nexus 2 9218
Protoss_Gateway 2 6136
Protoss_Assimilator 1 2533
Protoss_Cybernetics_Core 1 3137
Protoss_Dragoon 11 9776
Protoss_Robotics_Facility 1 4754
Protoss_Observatory 1 6699
Protoss_Observer 3 9411
9776
