Protoss_Nexus 2 9283
Protoss_Gateway 2 3434
Protoss_Assimilator 1 2217
Protoss_Cybernetics_Core 1 2849
Protoss_Dragoon 8 9479
Protoss_Citadel_of_Adun 1 5931
Protoss_Zealot 2 6539
Protoss_Templar_Archives 1 7287
Protoss_Dark_Templar 2 8329
9479
