Protoss_Nexus 2 9110
Protoss_Gateway 2 9760
Protoss_Assimilator 1 2509
Protoss_Cybernetics_Core 1 3203
Protoss_Dragoon 8 9883
Protoss_Robotics_Facility 1 5569
Protoss_Shuttle 1 6849
Protoss_Robotics_Support_Bay 1 7253
Protoss_Reaver 1 7787
Protoss_Observatory 1 9259
Protoss_Observer 1 9787
9883
