Protoss_Nexus 2 8801
Protoss_Gateway 4 9308
Protoss_Assimilator 1 2548
Protoss_Cybernetics_Core 1 3669
Protoss_Dragoon 10 9771
Protoss_Robotics_Facility 1 5783
Protoss_Observatory 1 7132
Protoss_Observer 2 8308
9771
