Protoss_Nexus 2 2794
Protoss_Gateway 2 6355
Protoss_Assimilator 2 6660
Protoss_Cybernetics_Core 1 4315
Protoss_Forge 1 4625
Protoss_Photon_Cannon 2 7496
Protoss_Dragoon 2 6105
Protoss_Citadel_of_Adun 1 5527
Protoss_Templar_Archives 1 6554
Protoss_Zealot 1 6857
Protoss_Dark_Templar 3 8329
Protoss_Robotics_Facility 1 7734
Protoss_Shuttle 1 9121
Protoss_High_Templar 2 9435
9435
