Protoss_Nexus 3 8398
Protoss_Gateway 2 4522
Protoss_Assimilator 1 2188
Protoss_Cybernetics_Core 1 2832
Protoss_Dragoon 10 9866
Protoss_Robotics_Facility 1 7445
Protoss_Observatory 1 8753
Protoss_Observer 2 9978
9978
