Protoss_Nexus 2 2726
Protoss_Gateway 4 7938
Protoss_Assimilator 2 7635
Protoss_Cybernetics_Core 1 4109
Protoss_Dragoon 7 9949
Protoss_Robotics_Facility 1 7184
Protoss_Shuttle 1 8929
Protoss_Observatory 1 9048
Protoss_Zealot 4 9673
Protoss_Observer 1 9946
9949
