Protoss_Nexus 2 9259
Protoss_Gateway 2 3742
Protoss_Assimilator 1 2246
Protoss_Cybernetics_Core 1 2915
Protoss_Dragoon 3 5019
Protoss_Citadel_of_Adun 1 5776
Protoss_Robotics_Facility 1 6132
Protoss_Zealot 2 6759
Protoss_Templar_Archives 1 6828
Protoss_Shuttle 1 7453
Protoss_Dark_Templar 6 9873
9873
