Protoss_Nexus 2 9518
Protoss_Gateway 2 5803
Protoss_Assimilator 1 2222
Protoss_Cybernetics_Core 1 2845
Protoss_Dragoon 12 9268
Protoss_Robotics_Facility 1 5328
Protoss_Observatory 1 6634
Protoss_Observer 3 9626
9626
