Protoss_Nexus 2 7827
Protoss_Gateway 2 6228
Protoss_Assimilator 1 2402
Protoss_Cybernetics_Core 1 3020
Protoss_Dragoon 8 9101
Protoss_Robotics_Facility 1 5403
Protoss_Observatory 1 6977
Protoss_Observer 1 7619
Protoss_Shuttle 1 8355
Protoss_Robotics_Support_Bay 1 8672
Protoss_Reaver 1 9333
Protoss_Zealot 2 9853
9853
