Protoss_Nexus 1 0
Protoss_Gateway 2 4967
Protoss_Assimilator 2 2722
Protoss_Cybernetics_Core 1 3465
Protoss_Dragoon 8 9415
Protoss_Zealot 3 8591
Protoss_Robotics_Facility 1 7199
Protoss_Shuttle 1 8513
Protoss_Robotics_Support_Bay 1 8837
Protoss_Observatory 1 9692
Protoss_Reaver 1 9899
9899
