Protoss_Nexus 2 8404
Protoss_Gateway 2 5742
Protoss_Assimilator 1 2234
Protoss_Cybernetics_Core 1 2849
Protoss_Dragoon 8 9739
Protoss_Robotics_Facility 1 5479
Protoss_Shuttle 1 6799
Protoss_Robotics_Support_Bay 1 6867
Protoss_Zealot 2 7301
Protoss_Reaver 1 7701
Protoss_Observatory 1 8010
Protoss_Observer 1 8797
9739
