Protoss_Nexus 1 0
Protoss_Gateway 2 3959
Protoss_Assimilator 1 2763
Protoss_Zealot 6 9293
Protoss_Cybernetics_Core 1 3521
Protoss_Dragoon 11 9925
Protoss_Robotics_Facility 1 7173
Protoss_Shuttle 1 8563
Protoss_Robotics_Support_Bay 1 8970
Protoss_Reaver 1 9725
9925
