Protoss_Nexus 2 3216
Protoss_Gateway 3 8294
Protoss_Assimilator 2 9373
Protoss_Cybernetics_Core 1 3933
Protoss_Dragoon 12 9595
Protoss_Robotics_Facility 1 7162
Protoss_Observatory 1 8597
Protoss_Observer 1 9491
9595
