Protoss_Nexus 2 6584
Protoss_Gateway 3 8814
Protoss_Assimilator 1 2369
Protoss_Cybernetics_Core 1 3098
Protoss_Dragoon 9 9811
Protoss_Robotics_Facility 1 7658
Protoss_Zealot 2 9416
Protoss_Shuttle 1 9156
Protoss_Observatory 1 9771
Protoss_Citadel_of_Adun 1 9957
9957
