Protoss_Nexus 2 9027
Protoss_Gateway 3 6185
Protoss_Forge 1 2948
Protoss_Zealot 7 8336
Protoss_Photon_Cannon 4 7048
Protoss_Assimilator 1 7202
Protoss_Cybernetics_Core 1 7769
Protoss_Dragoon 2 9186
Protoss_Citadel_of_Adun 1 9786
9786
