Protoss_Nexus 2 5587
Protoss_Gateway 3 6118
Protoss_Assimilator 2 9986
Protoss_Cybernetics_Core 1 2847
Protoss_Dragoon 12 9785
Protoss_Robotics_Facility 1 6801
Protoss_Zealot 1 7743
Protoss_Observatory 1 8246
Protoss_Shuttle 1 8545
Protoss_Observer 1 9447
9986
