Protoss_Nexus 1 0
Protoss_Gateway 3 6461
Protoss_Zealot 7 9535
Protoss_Assimilator 1 3499
Protoss_Cybernetics_Core 1 4027
Protoss_Dragoon 8 8495
Protoss_Robotics_Facility 1 7484
Protoss_Shuttle 1 8763
Protoss_Robotics_Support_Bay 1 9237
Protoss_Reaver 1 9767
9767
