Protoss_Nexus 2 9617
Protoss_Gateway 2 7100
Protoss_Assimilator 1 2523
Protoss_Cybernetics_Core 1 3065
Protoss_Robotics_Facility 1 4308
Protoss_Dragoon 9 9735
Protoss_Observatory 1 5709
Protoss_Observer 3 9215
9735
