Protoss_Nexus 2 8771
Protoss_Gateway 3 5708
Protoss_Assimilator 1 2275
Protoss_Cybernetics_Core 1 3117
Protoss_Dragoon 11 9325
Protoss_Zealot 2 8166
Protoss_Citadel_of_Adun 1 9445
Protoss_Robotics_Facility 1 9735
9735
