Protoss_Nexus 2 6789
Protoss_Gateway 5 9558
Protoss_Assimilator 1 2261
Protoss_Zealot 1 2896
Protoss_Cybernetics_Core 1 3730
Protoss_Dragoon 11 9961
Protoss_Robotics_Facility 1 8298
Protoss_Observatory 1 9629
9961
