Protoss_Nexus 2 8742
Protoss_Gateway 2 5815
Protoss_Assimilator 1 2356
Protoss_Cybernetics_Core 1 3024
Protoss_Dragoon 11 9415
Protoss_Robotics_Facility 1 5714
Protoss_Observatory 1 7065
Protoss_Observer 2 8259
Protoss_Shuttle 1 9025
9415
