Protoss_Nexus 1 0
Protoss_Gateway 1 2003
Protoss_Assimilator 1 2393
Protoss_Cybernetics_Core 1 3173
Protoss_Dragoon 7 9278
Protoss_Robotics_Facility 1 5818
Protoss_Observatory 1 7173
9278
