Protoss_Nexus 2 7465
Protoss_Gateway 2 6049
Protoss_Assimilator 1 2326
Protoss_Cybernetics_Core 1 2976
Protoss_Dragoon 6 9405
Protoss_Robotics_Facility 1 5685
Protoss_Observatory 1 6989
Protoss_Shuttle 1 7653
Protoss_Robotics_Support_Bay 1 7825
Protoss_Reaver 1 8609
Protoss_Zealot 2 8703
Protoss_Observer 1 9661
9661
