Protoss_Nexus 1 0
Protoss_Assimilator 1 1791
Protoss_Gateway 4 9902
Protoss_Cybernetics_Core 1 3414
Protoss_Zealot 3 9538
Protoss_Robotics_Facility 1 4523
Protoss_Dragoon 7 8786
Protoss_Observatory 1 5958
Protoss_Observer 3 7931
Protoss_Citadel_of_Adun 1 8510
9902
