Protoss_Nexus 2 7816
Protoss_Gateway 4 8571
Protoss_Assimilator 1 2239
Protoss_Cybernetics_Core 1 2934
Protoss_Dragoon 6 6857
Protoss_Citadel_of_Adun 2 8082
Protoss_Robotics_Facility 1 8019
Protoss_Templar_Archives 1 9091
Protoss_Shuttle 1 9323
Protoss_Observatory 1 9463
9463
