Protoss_Nexus 2 7473
Protoss_Gateway 2 5513
Protoss_Zealot 4 7825
Protoss_Assimilator 1 3085
Protoss_Cybernetics_Core 1 3850
Protoss_Dragoon 7 8985
Protoss_Robotics_Facility 1 6201
Protoss_Observatory 1 7607
Protoss_Observer 1 8143
Protoss_Shuttle 1 8754
Protoss_Robotics_Support_Bay 1 9330
Protoss_Reaver 1 9861
9861
