Protoss_Nexus 1 0
Protoss_Assimilator 2 4478
Protoss_Gateway 3 9623
Protoss_Cybernetics_Core 1 3282
Protoss_Robotics_Facility 1 4306
Protoss_Dragoon 9 9521
Protoss_Observatory 1 5750
Protoss_Observer 2 6928
Protoss_Shuttle 2 8556
Protoss_Zealot 2 8543
9623
