Protoss_Nexus 2 8407
Protoss_Gateway 2 6301
Protoss_Assimilator 1 2404
Protoss_Zealot 2 3549
Protoss_Cybernetics_Core 1 3129
Protoss_Dragoon 4 6593
Protoss_Citadel_of_Adun 1 4768
Protoss_Templar_Archives 1 6125
Protoss_Dark_Templar 6 9113
9113
