Protoss_Nexus 1 0
Protoss_Gateway 2 6983
Protoss_Assimilator 1 2406
Protoss_Cybernetics_Core 1 3048
Protoss_Dragoon 11 9848
Protoss_Robotics_Facility 1 5023
Protoss_Observatory 1 6364
Protoss_Observer 2 7513
9848
