Protoss_Nexus 3 8658
Protoss_Gateway 4 9643
Protoss_Assimilator 1 2309
Protoss_Cybernetics_Core 1 3028
Protoss_Dragoon 9 9066
Protoss_Robotics_Facility 1 7508
Protoss_Observatory 1 8812
Protoss_Observer 2 9963
9963
