Protoss_Nexus 2 6676
Protoss_Gateway 4 9267
Protoss_Assimilator 1 2461
Protoss_Cybernetics_Core 1 3287
Protoss_Dragoon 6 9781
Protoss_Robotics_Facility 1 5616
Protoss_Citadel_of_Adun 1 7153
Protoss_Shuttle 1 7651
Protoss_Observatory 1 8056
Protoss_Observer 1 9357
9781
