Protoss_Nexus 2 8243
Protoss_Gateway 2 4567
Protoss_Assimilator 2 8958
Protoss_Cybernetics_Core 1 2968
Protoss_Dragoon 7 9391
Protoss_Robotics_Facility 1 6097
Protoss_Zealot 3 9216
Protoss_Shuttle 1 7626
Protoss_Observatory 1 7888
Protoss_Citadel_of_Adun 1 8615
Protoss_Observer 2 9218
Protoss_Templar_Archives 1 9930
9930
