Protoss_Nexus 2 6299
Protoss_Gateway 2 3630
Protoss_Assimilator 2 7791
Protoss_Cybernetics_Core 1 2987
Protoss_Dragoon 6 9873
Protoss_Citadel_of_Adun 1 7034
Protoss_Robotics_Facility 1 7503
Protoss_Templar_Archives 1 8024
Protoss_Shuttle 1 8823
Protoss_Dark_Templar 3 9785
Protoss_Stargate 1 9564
9873
