Protoss_Nexus 2 7496
Protoss_Gateway 4 9069
Protoss_Assimilator 2 8511
Protoss_Cybernetics_Core 1 3083
Protoss_Dragoon 6 8393
Protoss_Citadel_of_Adun 1 5395
Protoss_Templar_Archives 1 6393
Protoss_Robotics_Facility 1 7988
Protoss_Observatory 1 9333
Protoss_Observer 1 9865
9865
