Protoss_Nexus 2 8868
Protoss_Gateway 3 9805
Protoss_Assimilator 1 2286
Protoss_Cybernetics_Core 1 2937
Protoss_Dragoon 6 9731
Protoss_Robotics_Facility 1 4377
Protoss_Shuttle 1 5806
Protoss_Zealot 2 6875
Protoss_Observatory 2 8209
Protoss_Robotics_Support_Bay 1 6787
Protoss_Reaver 1 7331
Protoss_Scarab 4 9958
9958
