Protoss_Nexus 1 0
Protoss_Gateway 2 4568
Protoss_Assimilator 1 2264
Protoss_Cybernetics_Core 1 2890
Protoss_Dragoon 10 8437
Protoss_Zealot 3 9681
Protoss_Robotics_Facility 1 7161
Protoss_Shuttle 1 8449
Protoss_Robotics_Support_Bay 1 8793
Protoss_Reaver 1 9557
9681
