Protoss_Nexus 4 9828
Protoss_Gateway 2 4519
Protoss_Assimilator 2 9354
Protoss_Cybernetics_Core 1 3186
Protoss_Dragoon 14 9999
Protoss_Robotics_Facility 1 8455
Protoss_Observatory 1 9753
9999
