Protoss_Nexus 2 8177
Protoss_Gateway 2 5682
Protoss_Assimilator 1 2494
Protoss_Cybernetics_Core 1 3126
Protoss_Dragoon 7 7635
Protoss_Robotics_Facility 1 5484
Protoss_Observatory 1 6783
Protoss_Observer 3 8557
Protoss_Robotics_Support_Bay 1 9103
Protoss_Shuttle 1 9159
Protoss_Zealot 2 9643
9643
