Protoss_Nexus 3 9403
Protoss_Gateway 2 6092
Protoss_Assimilator 1 2478
Protoss_Cybernetics_Core 1 3058
Protoss_Dragoon 8 8871
Protoss_Stargate 1 8228
Protoss_Forge 1 8787
Protoss_Photon_Cannon 1 9803
Protoss_Scout 1 9921
9921
