Protoss_Nexus 2 9443
Protoss_Gateway 2 4883
Protoss_Assimilator 1 2290
Protoss_Cybernetics_Core 1 2861
Protoss_Dragoon 10 9851
Protoss_Zealot 5 9086
Protoss_Robotics_Facility 1 8382
9851
