Protoss_Nexus 1 0
Protoss_Gateway 1 1953
Protoss_Assimilator 1 2498
Protoss_Cybernetics_Core 1 3033
Protoss_Dragoon 7 9686
Protoss_Robotics_Facility 1 5866
Protoss_Shuttle 1 7151
Protoss_Robotics_Support_Bay 1 7281
Protoss_Reaver 1 8091
Protoss_Observatory 1 8141
Protoss_Observer 2 9745
Protoss_Zealot 1 9648
9745
