Protoss_Nexus 2 6671
Protoss_Gateway 3 8133
Protoss_Assimilator 1 3045
Protoss_Zealot 2 4279
Protoss_Cybernetics_Core 1 3921
Protoss_Dragoon 8 9235
Protoss_Robotics_Facility 1 7548
Protoss_Observatory 1 8894
Protoss_Observer 1 9461
9461
