Protoss_Nexus 2 8392
Protoss_Gateway 2 6523
Protoss_Assimilator 1 2285
Protoss_Zealot 1 2841
Protoss_Cybernetics_Core 1 3137
Protoss_Dragoon 10 9917
Protoss_Robotics_Facility 1 5629
Protoss_Observatory 1 6981
Protoss_Observer 2 8331
Protoss_Citadel_of_Adun 1 8712
9917
