Protoss_Nexus 2 8096
Protoss_Gateway 2 5700
Protoss_Assimilator 1 2311
Protoss_Cybernetics_Core 1 2925
Protoss_Dragoon 10 9253
Protoss_Robotics_Facility 1 5410
Protoss_Observatory 1 6708
Protoss_Observer 2 8313
Protoss_Shuttle 1 9659
9659
