Protoss_Nexus 2 9223
Protoss_Gateway 3 9574
Protoss_Assimilator 1 2570
Protoss_Cybernetics_Core 1 3280
Protoss_Dragoon 6 7051
Protoss_Citadel_of_Adun 1 6354
Protoss_Templar_Archives 1 7348
Protoss_Dark_Templar 5 9946
9946
