Protoss_Nexus 1 0
Protoss_Gateway 2 7101
Protoss_Assimilator 2 4404
Protoss_Zealot 5 5443
Protoss_Cybernetics_Core 1 5318
Protoss_Dragoon 5 9571
Protoss_Citadel_of_Adun 1 6547
Protoss_Templar_Archives 1 7611
Protoss_Dark_Templar 2 9305
9571
