Protoss_Nexus 2 2878
Protoss_Gateway 2 5078
Protoss_Assimilator 2 9533
Protoss_Cybernetics_Core 1 4338
Protoss_Zealot 3 9576
Protoss_Dragoon 8 8492
Protoss_Forge 1 7173
Protoss_Photon_Cannon 2 9135
Protoss_Robotics_Facility 1 9828
9828
