Protoss_Nexus 2 7698
Protoss_Gateway 3 9913
Protoss_Assimilator 1 2283
Protoss_Cybernetics_Core 1 2909
Protoss_Dragoon 7 9436
Protoss_Robotics_Facility 1 5283
Protoss_Observatory 1 6656
Protoss_Observer 2 9246
Protoss_Shuttle 1 7941
9913
