Protoss_Nexus 3 9895
Protoss_Gateway 3 6058
Protoss_Assimilator 1 2513
Protoss_Cybernetics_Core 1 3176
Protoss_Robotics_Facility 1 4351
Protoss_Dragoon 5 7651
Protoss_Observatory 1 5810
Protoss_Observer 2 7486
Protoss_Shuttle 1 8088
Protoss_Zealot 3 8411
9895
