Protoss_Nexus 2 9267
Protoss_Gateway 2 6616
Protoss_Assimilator 1 2400
Protoss_Cybernetics_Core 1 2973
Protoss_Dragoon 7 9326
Protoss_Citadel_of_Adun 1 5725
Protoss_Templar_Archives 1 6728
Protoss_Dark_Templar 3 8498
Protoss_Robotics_Facility 1 9853
9853
