Protoss_Nexus 1 0
Protoss_Assimilator 1 1618
Protoss_Gateway 3 6253
Protoss_Cybernetics_Core 1 3273
Protoss_Robotics_Facility 1 4308
Protoss_Dragoon 4 9166
Protoss_Observatory 1 5624
Protoss_Observer 2 6768
Protoss_Shuttle 2 8272
Protoss_Zealot 6 8371
Protoss_Robotics_Support_Bay 1 8973
Protoss_Reaver 1 9531
Protoss_Citadel_of_Adun 1 9833
9833
