Protoss_Nexus 2 9524
Protoss_Gateway 2 5586
Protoss_Assimilator 1 2443
Protoss_Cybernetics_Core 1 3219
Protoss_Dragoon 8 8601
Protoss_Robotics_Facility 1 5213
Protoss_Observatory 1 6539
Protoss_Observer 3 8545
Protoss_Shuttle 1 9593
9593
