Protoss_Nexus 2 9006
Protoss_Gateway 2 6260
Protoss_Assimilator 2 2903
Protoss_Cybernetics_Core 1 3526
Protoss_Dragoon 1 4531
Protoss_Citadel_of_Adun 1 4758
Protoss_Templar_Archives 1 5881
Protoss_Dark_Templar 7 9716
Protoss_Forge 1 7526
9716
