Protoss_Nexus 2 2995
Protoss_Gateway 3 7521
Protoss_Assimilator 2 7838
Protoss_Cybernetics_Core 1 4345
Protoss_Dragoon 9 9730
Protoss_Robotics_Facility 1 5927
Protoss_Forge 1 6872
Protoss_Observatory 1 7289
Protoss_Photon_Cannon 2 9456
Protoss_Observer 2 8501
9730
