Protoss_Nexus 3 9418
Protoss_Gateway 2 5253
Protoss_Assimilator 1 2428
Protoss_Cybernetics_Core 1 3078
Protoss_Dragoon 6 7108
Protoss_Robotics_Facility 1 6028
Protoss_Shuttle 1 7331
Protoss_Observatory 1 7530
Protoss_Zealot 4 8470
Protoss_Observer 2 9601
9601
