Protoss_Nexus 2 8218
Protoss_Gateway 2 6518
Protoss_Zealot 3 4231
Protoss_Assimilator 1 3051
Protoss_Cybernetics_Core 1 3933
Protoss_Dragoon 7 9081
Protoss_Robotics_Facility 1 6803
Protoss_Shuttle 1 8486
Protoss_Robotics_Support_Bay 1 8858
Protoss_Reaver 1 9406
9406
