Protoss_Nexus 3 6757
Protoss_Gateway 5 9823
Protoss_Assimilator 2 9142
Protoss_Zealot 2 4056
Protoss_Cybernetics_Core 1 3878
Protoss_Dragoon 9 9206
Protoss_Robotics_Facility 1 7939
Protoss_Observatory 1 9544
9823
