Protoss_Nexus 1 0
Protoss_Gateway 2 10000
Protoss_Assimilator 1 2558
Protoss_Cybernetics_Core 1 3303
Protoss_Robotics_Facility 1 4458
Protoss_Dragoon 4 9412
Protoss_Zealot 3 7306
Protoss_Shuttle 2 9906
Protoss_Robotics_Support_Bay 1 6218
Protoss_Reaver 1 6861
Protoss_Observatory 1 7523
Protoss_Observer 2 8688
Protoss_Scarab 6 9291
10000
