Protoss_Nexus 2 9203
Protoss_Gateway 2 4463
Protoss_Assimilator 1 2297
Protoss_Cybernetics_Core 1 2917
Protoss_Dragoon 10 8448
Protoss_Citadel_of_Adun 1 5852
Protoss_Templar_Archives 1 6943
Protoss_Robotics_Facility 1 8718
Protoss_Dark_Templar 2 9601
9601
