Protoss_Nexus 1 0
Protoss_Gateway 3 6589
Protoss_Assimilator 1 2290
Protoss_Zealot 5 8481
Protoss_Cybernetics_Core 1 3199
Protoss_Dragoon 7 9963
Protoss_Citadel_of_Adun 1 5029
Protoss_Templar_Archives 1 6197
Protoss_Dark_Templar 3 7653
9963
