Protoss_Nexus 1 0
Protoss_Gateway 1 1969
Protoss_Assimilator 1 2321
Protoss_Cybernetics_Core 1 3170
Protoss_Robotics_Facility 1 4208
Protoss_Dragoon 4 8631
Protoss_Zealot 4 6477
Protoss_Shuttle 1 6696
8631
