Protoss_Nexus 3 8401
Protoss_Gateway 2 5353
Protoss_Assimilator 2 9700
Protoss_Cybernetics_Core 1 2885
Protoss_Dragoon 9 9347
Protoss_Robotics_Facility 1 7309
Protoss_Observatory 1 8683
Protoss_Observer 2 9839
Protoss_Citadel_of_Adun 1 9320
9839
