Protoss_Nexus 2 5589
Protoss_Gateway 3 6341
Protoss_Assimilator 1 2164
Protoss_Cybernetics_Core 1 2835
Protoss_Dragoon 11 9477
Protoss_Robotics_Facility 1 6870
Protoss_Zealot 3 8761
Protoss_Observatory 1 8155
Protoss_Observer 2 9443
9477
