Protoss_Nexus 2 7779
Protoss_Gateway 3 8911
Protoss_Zealot 5 9901
Protoss_Assimilator 1 4162
Protoss_Cybernetics_Core 1 4668
Protoss_Dragoon 7 9708
Protoss_Robotics_Facility 1 8286
9901
