Protoss_Nexus 2 5959
Protoss_Gateway 5 9457
Protoss_Assimilator 1 2250
Protoss_Cybernetics_Core 1 3074
Protoss_Dragoon 11 9953
Protoss_Robotics_Facility 1 6896
Protoss_Observatory 1 8260
Protoss_Observer 2 9393
Protoss_Citadel_of_Adun 1 9161
9953
