Protoss_Nexus 2 8506
Protoss_Gateway 2 5409
Protoss_Assimilator 1 2444
Protoss_Cybernetics_Core 1 3033
Protoss_Dragoon 5 9769
Protoss_Citadel_of_Adun 1 5597
Protoss_Robotics_Facility 1 5925
Protoss_Templar_Archives 1 6608
Protoss_Shuttle 1 7213
Protoss_Dark_Templar 4 8617
9769
