Protoss_Nexus 2 8268
Protoss_Gateway 2 5896
Protoss_Assimilator 1 2358
Protoss_Cybernetics_Core 1 2950
Protoss_Dragoon 12 9333
Protoss_Robotics_Facility 1 5762
Protoss_Observatory 1 7099
Protoss_Observer 2 8238
Protoss_Robotics_Support_Bay 1 9643
Protoss_Shuttle 1 9806
9806
