Protoss_Nexus 2 6918
Protoss_Gateway 2 7649
Protoss_Assimilator 2 9478
Protoss_Cybernetics_Core 1 2984
Protoss_Dragoon 8 9221
Protoss_Robotics_Facility 1 5399
Protoss_Observatory 1 6803
Protoss_Observer 2 8233
Protoss_Robotics_Support_Bay 1 7942
Protoss_Shuttle 1 8891
Protoss_Reaver 1 9833
9833
