Protoss_Nexus 2 8773
Protoss_Gateway 3 9803
Protoss_Assimilator 1 2457
Protoss_Cybernetics_Core 1 2983
Protoss_Dragoon 12 9295
Protoss_Robotics_Facility 1 6813
Protoss_Observatory 1 8123
Protoss_Observer 1 9116
9803
