Protoss_Nexus 1 0
Protoss_Gateway 2 7132
Protoss_Assimilator 1 2329
Protoss_Cybernetics_Core 1 3141
Protoss_Dragoon 4 9276
Protoss_Stargate 1 5016
Protoss_Citadel_of_Adun 1 5837
Protoss_Scout 1 6311
Protoss_Templar_Archives 1 7297
Protoss_Dark_Templar 4 9316
9316
