Protoss_Nexus 2 8198
Protoss_Gateway 4 9388
Protoss_Assimilator 1 2363
Protoss_Cybernetics_Core 1 3188
Protoss_Zealot 1 3661
Protoss_Dragoon 8 9716
Protoss_Robotics_Facility 1 6363
Protoss_Observatory 1 8315
Protoss_Observer 2 9517
9716
