Protoss_Nexus 1 0
Protoss_Gateway 3 8578
Protoss_Assimilator 1 2503
Protoss_Cybernetics_Core 1 3257
Protoss_Dragoon 9 8848
Protoss_Robotics_Facility 1 4673
Protoss_Observatory 1 6076
Protoss_Observer 2 8116
Protoss_Shuttle 2 9566
Protoss_Zealot 3 9600
9600
