Protoss_Nexus 1 0
Protoss_Gateway 3 7978
Protoss_Assimilator 1 2582
Protoss_Cybernetics_Core 1 3313
Protoss_Dragoon 10 9586
Protoss_Robotics_Facility 1 5711
Protoss_Observatory 1 7071
Protoss_Observer 1 7626
9586
