Protoss_Nexus 1 0
Protoss_Gateway 1 2027
Protoss_Assimilator 1 2863
Protoss_Cybernetics_Core 1 3273
Protoss_Zealot 2 8491
Protoss_Dragoon 3 6831
Protoss_Robotics_Facility 1 5780
Protoss_Robotics_Support_Bay 1 7226
Protoss_Shuttle 1 7246
Protoss_Reaver 2 9200
Protoss_Scarab 2 9922
9922
