Protoss_Nexus 1 0
Protoss_Gateway 3 9948
Protoss_Assimilator 1 2518
Protoss_Cybernetics_Core 1 3473
Protoss_Robotics_Facility 1 4710
Protoss_Dragoon 5 9666
Protoss_Robotics_Support_Bay 1 6018
Protoss_Shuttle 2 9858
Protoss_Zealot 3 7241
Protoss_Reaver 2 8806
Protoss_Observatory 1 9879
9948
