Protoss_Nexus 1 0
Protoss_Gateway 2 6878
Protoss_Zealot 3 4056
Protoss_Assimilator 1 3016
Protoss_Cybernetics_Core 1 3843
Protoss_Dragoon 7 8993
Protoss_Robotics_Facility 1 5905
Protoss_Shuttle 1 7201
Protoss_Robotics_Support_Bay 1 7358
Protoss_Reaver 2 9236
9236
