Protoss_Nexus 2 8688
Protoss_Gateway 3 6184
Protoss_Assimilator 1 2548
Protoss_Cybernetics_Core 1 3269
Protoss_Robotics_Facility 1 4418
Protoss_Dragoon 9 9536
Protoss_Observatory 1 5931
Protoss_Observer 4 9448
9536
