Protoss_Nexus 2 7232
Protoss_Gateway 1 1998
Protoss_Forge 1 2531
Protoss_Zealot 6 9786
Protoss_Photon_Cannon 10 8713
Protoss_Assimilator 1 7009
Protoss_Cybernetics_Core 1 8144
9786
