Protoss_Nexus 2 8895
Protoss_Gateway 2 5913
Protoss_Assimilator 1 2214
Protoss_Cybernetics_Core 1 2863
Protoss_Dragoon 5 9599
Protoss_Citadel_of_Adun 1 4798
Protoss_Templar_Archives 1 5787
Protoss_Robotics_Facility 1 6531
Protoss_Dark_Templar 5 8441
Protoss_Shuttle 1 7863
9599
