Protoss_Nexus 2 9795
Protoss_Gateway 2 4780
Protoss_Assimilator 1 2418
Protoss_Cybernetics_Core 1 3079
Protoss_Dragoon 3 5759
Protoss_Citadel_of_Adun 1 5927
Protoss_Zealot 3 7369
Protoss_Robotics_Facility 1 6679
Protoss_Templar_Archives 1 7167
Protoss_Shuttle 1 7957
Protoss_Dark_Templar 5 9743
9795
