Protoss_Nexus 1 0
Protoss_Gateway 1 2047
Protoss_Assimilator 1 2517
Protoss_Cybernetics_Core 1 3110
Protoss_Dragoon 3 9323
Protoss_Robotics_Facility 1 4661
Protoss_Zealot 1 6301
9323
