Protoss_Nexus 2 6252
Protoss_Gateway 4 9507
Protoss_Assimilator 1 2329
Protoss_Cybernetics_Core 1 3062
Protoss_Dragoon 13 9945
Protoss_Zealot 1 7329
Protoss_Robotics_Facility 1 8679
9945
