Protoss_Nexus 2 8633
Protoss_Gateway 2 4959
Protoss_Assimilator 1 2478
Protoss_Cybernetics_Core 1 3213
Protoss_Dragoon 8 8080
Protoss_Robotics_Facility 1 6307
Protoss_Observatory 1 8278
Protoss_Zealot 4 9751
Protoss_Observer 1 8831
Protoss_Shuttle 1 9496
9751
