Protoss_Nexus 2 3720
Protoss_Gateway 2 4928
Protoss_Zealot 1 3257
Protoss_Assimilator 2 6127
Protoss_Cybernetics_Core 1 4741
Protoss_Dragoon 7 9855
Protoss_Citadel_of_Adun 1 6642
Protoss_Forge 1 7265
Protoss_Templar_Archives 1 7676
Protoss_Robotics_Facility 1 7839
Protoss_Photon_Cannon 2 8386
Protoss_Dark_Templar 2 8899
Protoss_Stargate 1 9066
Protoss_Shuttle 1 9193
Protoss_Observatory 1 9294
9855
