Protoss_Nexus 1 0
Protoss_Gateway 2 7537
Protoss_Assimilator 1 2393
Protoss_Cybernetics_Core 1 3444
Protoss_Dragoon 6 9004
Protoss_Robotics_Facility 1 5786
Protoss_Observatory 1 7249
Protoss_Observer 3 9606
Protoss_Zealot 1 9431
9606
