Protoss_Nexus 1 0
Protoss_Assimilator 1 2520
Protoss_Gateway 2 7221
Protoss_Cybernetics_Core 1 3696
Protoss_Robotics_Facility 1 4812
Protoss_Dragoon 2 8469
Protoss_Robotics_Support_Bay 1 6120
Protoss_Shuttle 1 6439
Protoss_Citadel_of_Adun 1 6938
Protoss_Reaver 2 8863
Protoss_Templar_Archives 1 7927
Protoss_Dark_Templar 2 9719
Protoss_Scarab 2 9481
9719
