Protoss_Nexus 3 8961
Protoss_Gateway 4 9989
Protoss_Assimilator 1 2258
Protoss_Cybernetics_Core 1 3075
Protoss_Dragoon 9 9349
Protoss_Robotics_Facility 1 6391
Protoss_Observatory 1 7700
Protoss_Observer 2 9741
9989
