Protoss_Nexus 2 2659
Protoss_Gateway 3 6912
Protoss_Assimilator 1 3524
Protoss_Cybernetics_Core 1 4382
Protoss_Zealot 4 8601
Protoss_Dragoon 8 9955
Protoss_Robotics_Facility 1 6723
Protoss_Observatory 1 8197
Protoss_Observer 1 8781
Protoss_Shuttle 1 9383
Protoss_Robotics_Support_Bay 1 9482
9955
