Protoss_Nexus 2 4184
Protoss_Gateway 2 5434
Protoss_Zealot 3 5167
Protoss_Assimilator 2 7244
Protoss_Cybernetics_Core 1 5025
Protoss_Dragoon 9 9615
Protoss_Robotics_Facility 1 8173
Protoss_Shuttle 1 9513
Protoss_Robotics_Support_Bay 1 9543
9615
