Protoss_Nexus 2 7113
Protoss_Gateway 2 8522
Protoss_Assimilator 2 8455
Protoss_Cybernetics_Core 1 2897
Protoss_Dragoon 4 6381
Protoss_Citadel_of_Adun 1 5152
Protoss_Templar_Archives 1 6201
Protoss_Dark_Templar 4 9543
Protoss_Stargate 1 8240
Protoss_Arbiter_Tribunal 1 9997
9997
