Protoss_Nexus 2 9364
Protoss_Gateway 2 6849
Protoss_Assimilator 1 2534
Protoss_Cybernetics_Core 1 3168
Protoss_Dragoon 10 9766
Protoss_Robotics_Facility 1 5692
Protoss_Observatory 1 7288
Protoss_Observer 2 8638
9766
