Protoss_Nexus 3 8718
Protoss_Gateway 3 8672
Protoss_Assimilator 2 7787
Protoss_Cybernetics_Core 1 4308
Protoss_Zealot 1 4676
Protoss_Dragoon 3 6581
Protoss_Citadel_of_Adun 1 6773
Protoss_Robotics_Facility 1 7315
Protoss_Templar_Archives 1 8133
Protoss_Shuttle 1 8866
Protoss_Dark_Templar 3 9666
Protoss_Forge 1 9313
Protoss_Observatory 1 9651
9666
