Protoss_Nexus 2 3779
Protoss_Gateway 3 8698
Protoss_Zealot 1 2903
Protoss_Assimilator 2 8357
Protoss_Cybernetics_Core 1 4542
Protoss_Dragoon 11 9487
Protoss_Robotics_Facility 1 8420
Protoss_Shuttle 1 9817
Protoss_Observatory 1 9931
9931
