Protoss_Nexus 2 6665
Protoss_Gateway 2 4950
Protoss_Assimilator 1 2418
Protoss_Cybernetics_Core 1 3063
Protoss_Zealot 3 9863
Protoss_Dragoon 8 8843
Protoss_Robotics_Facility 1 7090
Protoss_Shuttle 1 8399
Protoss_Robotics_Support_Bay 1 8505
Protoss_Reaver 1 9409
9863
