Protoss_Nexus 2 8512
Protoss_Gateway 3 9604
Protoss_Assimilator 1 2441
Protoss_Cybernetics_Core 1 3008
Protoss_Dragoon 6 9615
Protoss_Citadel_of_Adun 1 4908
Protoss_Robotics_Facility 1 5253
Protoss_Zealot 1 5841
Protoss_Templar_Archives 1 6163
Protoss_Shuttle 1 6751
Protoss_Dark_Templar 2 7171
Protoss_Observatory 1 9678
9678
