Protoss_Nexus 2 6638
Protoss_Gateway 4 9618
Protoss_Assimilator 1 2203
Protoss_Cybernetics_Core 1 2888
Protoss_Dragoon 12 9941
Protoss_Robotics_Facility 1 7828
Protoss_Observatory 1 9463
9941
