Protoss_Nexus 2 5911
Protoss_Gateway 3 7352
Protoss_Assimilator 1 2369
Protoss_Cybernetics_Core 1 3013
Protoss_Dragoon 10 9467
Protoss_Zealot 1 5574
Protoss_Robotics_Facility 1 6245
Protoss_Observatory 1 7554
Protoss_Observer 2 8731
Protoss_Shuttle 1 9815
9815
