Protoss_Nexus 2 6685
Protoss_Gateway 2 4577
Protoss_Assimilator 1 2196
Protoss_Cybernetics_Core 1 2847
Protoss_Zealot 1 3115
Protoss_Dragoon 10 9501
Protoss_Robotics_Facility 1 7492
Protoss_Shuttle 1 8773
Protoss_Observatory 1 9031
Protoss_Robotics_Support_Bay 1 9643
Protoss_Observer 1 9675
9675
