Protoss_Nexus 2 9683
Protoss_Gateway 3 7223
Protoss_Assimilator 1 2369
Protoss_Cybernetics_Core 1 3097
Protoss_Dragoon 6 8711
Protoss_Robotics_Facility 1 4613
Protoss_Observatory 1 5995
Protoss_Observer 1 6596
Protoss_Zealot 4 7936
Protoss_Shuttle 1 7581
9683
