Protoss_Nexus 2 3197
Protoss_Assimilator 2 3857
Protoss_Gateway 3 7175
Protoss_Cybernetics_Core 2 6811
Protoss_Zealot 3 6035
Protoss_Dragoon 5 9327
Protoss_Robotics_Facility 1 9418
9418
