Protoss_Nexus 3 9988
Protoss_Gateway 2 4617
Protoss_Assimilator 1 2461
Protoss_Cybernetics_Core 1 3015
Protoss_Dragoon 7 7819
Protoss_Robotics_Facility 1 7468
Protoss_Shuttle 1 8797
Protoss_Zealot 2 8939
Protoss_Observatory 1 9011
Protoss_Robotics_Support_Bay 1 9451
Protoss_Observer 1 9699
9988
