Protoss_Nexus 2 7705
Protoss_Gateway 2 5887
Protoss_Assimilator 1 2189
Protoss_Cybernetics_Core 1 2949
Protoss_Dragoon 9 9323
Protoss_Robotics_Facility 1 5283
Protoss_Observatory 1 6654
Protoss_Observer 2 7895
Protoss_Shuttle 1 8497
Protoss_Robotics_Support_Bay 1 8861
Protoss_Reaver 1 9599
9599
