Protoss_Nexus 2 9213
Protoss_Gateway 1 1942
Protoss_Assimilator 1 2319
Protoss_Cybernetics_Core 1 2984
Protoss_Dragoon 3 5771
Protoss_Robotics_Facility 1 5453
Protoss_Citadel_of_Adun 1 6218
Protoss_Shuttle 1 6756
Protoss_Robotics_Support_Bay 1 7071
Protoss_Zealot 2 8461
Protoss_Reaver 2 9741
Protoss_Templar_Archives 1 8098
Protoss_Dark_Templar 1 9341
9741
