Protoss_Assimilator 18 9780
Protoss_Nexus 2 7454
Protoss_Gateway 2 2349
Protoss_Zealot 6 4861
Protoss_Cybernetics_Core 1 5083
Protoss_Dragoon 8 9793
Protoss_Robotics_Facility 1 8509
Protoss_Forge 1 9200
9793
