Protoss_Nexus 2 7715
Protoss_Gateway 4 9264
Protoss_Assimilator 1 2243
Protoss_Cybernetics_Core 1 2871
Protoss_Dragoon 12 9857
Protoss_Robotics_Facility 1 5253
Protoss_Observatory 1 6587
Protoss_Observer 1 7401
Protoss_Citadel_of_Adun 1 9699
9857
