Protoss_Nexus 2 8948
Protoss_Gateway 2 6609
Protoss_Assimilator 1 2328
Protoss_Cybernetics_Core 1 2890
Protoss_Zealot 1 3231
Protoss_Dragoon 9 9961
Protoss_Robotics_Facility 1 5968
Protoss_Shuttle 1 7266
Protoss_Robotics_Support_Bay 1 7501
Protoss_Reaver 1 8421
Protoss_Observatory 1 9581
9961
