Protoss_Nexus 2 6777
Protoss_Gateway 2 4582
Protoss_Assimilator 1 2318
Protoss_Cybernetics_Core 1 2938
Protoss_Dragoon 6 7581
Protoss_Robotics_Facility 1 7135
Protoss_Shuttle 1 8427
Protoss_Robotics_Support_Bay 1 8960
Protoss_Zealot 2 9373
Protoss_Observatory 1 9555
Protoss_Reaver 1 9597
9597
