Protoss_Nexus 2 6004
Protoss_Gateway 3 8746
Protoss_Assimilator 1 2276
Protoss_Cybernetics_Core 1 3222
Protoss_Dragoon 7 9749
Protoss_Robotics_Facility 1 4967
Protoss_Observatory 1 6300
Protoss_Observer 2 7683
9749
