Protoss_Nexus 1 0
Protoss_Gateway 2 4953
Protoss_Zealot 2 3413
Protoss_Assimilator 1 3059
Protoss_Cybernetics_Core 1 3956
Protoss_Dragoon 10 9361
Protoss_Robotics_Facility 1 6587
Protoss_Robotics_Support_Bay 1 8437
Protoss_Shuttle 1 8586
Protoss_Observatory 1 8756
Protoss_Observer 1 9591
9591
