Protoss_Nexus 2 7506
Protoss_Gateway 3 8742
Protoss_Assimilator 1 2315
Protoss_Zealot 2 3941
Protoss_Cybernetics_Core 1 3734
Protoss_Dragoon 11 9903
Protoss_Robotics_Facility 1 8047
Protoss_Shuttle 1 9333
Protoss_Observatory 1 9452
9903
