Protoss_Nexus 2 9441
Protoss_Gateway 2 4857
Protoss_Assimilator 1 2430
Protoss_Zealot 3 4423
Protoss_Cybernetics_Core 1 3701
Protoss_Dragoon 5 7211
Protoss_Citadel_of_Adun 1 5614
Protoss_Templar_Archives 1 6775
Protoss_Dark_Templar 2 8025
9441
