Protoss_Nexus 2 5843
Protoss_Gateway 2 7709
Protoss_Assimilator 1 2308
Protoss_Cybernetics_Core 1 2977
Protoss_Dragoon 8 9278
Protoss_Robotics_Facility 1 6559
Protoss_Observatory 1 7997
Protoss_Shuttle 1 8143
Protoss_Robotics_Support_Bay 1 8653
Protoss_Observer 1 9045
Protoss_Reaver 1 9647
Protoss_Zealot 1 9865
9865
