Protoss_Nexus 2 9559
Protoss_Gateway 5 7718
Protoss_Zealot 4 9713
Protoss_Assimilator 1 3703
Protoss_Cybernetics_Core 1 5454
Protoss_Dragoon 4 9989
Protoss_Robotics_Facility 1 6641
Protoss_Robotics_Support_Bay 1 8005
Protoss_Shuttle 1 8035
Protoss_Reaver 1 8937
Protoss_Observatory 1 9892
9989
