Protoss_Assimilator 17 3819
Protoss_Nexus 1 0
Protoss_Gateway 2 2700
Protoss_Zealot 6 6123
Protoss_Cybernetics_Core 1 4251
Protoss_Dragoon 11 9459
Protoss_Forge 1 5686
Protoss_Shield_Battery 1 7297
9459
