Protoss_Nexus 2 6153
Protoss_Gateway 2 7569
Protoss_Assimilator 1 2418
Protoss_Cybernetics_Core 1 3060
Protoss_Dragoon 8 8777
Protoss_Robotics_Facility 1 7285
Protoss_Shuttle 1 8621
Protoss_Robotics_Support_Bay 1 8981
Protoss_Zealot 2 9529
Protoss_Reaver 1 9573
9573
