Protoss_Nexus 3 7417
Protoss_Gateway 2 8606
Protoss_Assimilator 2 9788
Protoss_Cybernetics_Core 1 3209
Protoss_Dragoon 9 9917
Protoss_Robotics_Facility 1 7881
Protoss_Citadel_of_Adun 1 8741
Protoss_Observatory 1 9701
Protoss_Templar_Archives 1 9793
9917
