Protoss_Nexus 2 5660
Protoss_Gateway 3 9148
Protoss_Zealot 1 2881
Protoss_Assimilator 2 8813
Protoss_Cybernetics_Core 1 4869
Protoss_Citadel_of_Adun 1 5946
Protoss_Templar_Archives 1 6986
Protoss_Dark_Templar 3 9510
9510
