Protoss_Nexus 3 9959
Protoss_Gateway 2 6069
Protoss_Assimilator 1 2323
Protoss_Cybernetics_Core 1 3144
Protoss_Dragoon 7 9051
Protoss_Robotics_Facility 1 5794
Protoss_Shuttle 1 7391
Protoss_Observatory 1 7512
Protoss_Zealot 2 8392
Protoss_Observer 1 8656
9959
