Protoss_Nexus 2 6512
Protoss_Assimilator 17 5202
Protoss_Gateway 2 8797
Protoss_Zealot 5 5761
Protoss_Forge 1 3265
Protoss_Photon_Cannon 2 4663
Protoss_Cybernetics_Core 1 5630
Protoss_Robotics_Facility 1 7020
Protoss_Dragoon 5 9855
Protoss_Robotics_Support_Bay 1 8710
Protoss_Reaver 1 9359
9855
