Protoss_Nexus 2 8013
Protoss_Gateway 2 7174
Protoss_Assimilator 1 2358
Protoss_Cybernetics_Core 1 3197
Protoss_Dragoon 7 9686
Protoss_Robotics_Facility 1 5573
Protoss_Observatory 1 6989
Protoss_Observer 1 8476
Protoss_Shuttle 1 9078
9686
