Protoss_Nexus 2 9615
Protoss_Gateway 3 9983
Protoss_Assimilator 1 2615
Protoss_Cybernetics_Core 1 3285
Protoss_Dragoon 10 8881
Protoss_Robotics_Facility 1 6250
Protoss_Observatory 1 7702
Protoss_Observer 2 9131
9983
