Protoss_Nexus 3 7873
Protoss_Gateway 2 6145
Protoss_Assimilator 3 9483
Protoss_Zealot 3 5651
Protoss_Cybernetics_Core 1 5385
Protoss_Dragoon 5 9257
Protoss_Robotics_Facility 1 6955
Protoss_Shuttle 1 8449
Protoss_Robotics_Support_Bay 1 8867
Protoss_Reaver 1 9501
9501
