Protoss_Nexus 2 9571
Protoss_Gateway 2 5099
Protoss_Assimilator 1 2419
Protoss_Zealot 2 3481
Protoss_Cybernetics_Core 1 3139
Protoss_Dragoon 9 9365
Protoss_Citadel_of_Adun 1 4787
Protoss_Templar_Archives 1 5789
Protoss_Dark_Templar 2 6797
9571
