Protoss_Nexus 2 8013
Protoss_Gateway 2 5958
Protoss_Assimilator 1 2267
Protoss_Cybernetics_Core 1 2939
Protoss_Dragoon 10 9306
Protoss_Robotics_Facility 1 5401
Protoss_Observatory 1 6937
Protoss_Observer 3 8821
9306
