Protoss_Nexus 2 7869
Protoss_Assimilator 1 1888
Protoss_Gateway 2 9345
Protoss_Cybernetics_Core 1 3383
Protoss_Dragoon 6 9268
Protoss_Robotics_Facility 1 4643
Protoss_Shuttle 2 9926
Protoss_Observatory 1 7103
Protoss_Observer 2 8583
Protoss_Forge 1 8136
Protoss_Photon_Cannon 1 9242
9926
