Protoss_Nexus 2 7219
Protoss_Gateway 3 7960
Protoss_Assimilator 1 2251
Protoss_Cybernetics_Core 1 2885
Protoss_Dragoon 8 9401
Protoss_Robotics_Facility 1 5338
Protoss_Observatory 1 6644
Protoss_Observer 2 7889
Protoss_Shuttle 1 8491
Protoss_Robotics_Support_Bay 1 8906
Protoss_Reaver 1 9579
9579
