Protoss_Nexus 3 9021
Protoss_Gateway 3 9794
Protoss_Assimilator 1 3408
Protoss_Cybernetics_Core 1 4155
Protoss_Zealot 1 4611
Protoss_Dragoon 8 9395
Protoss_Robotics_Facility 1 9340
9794
