Protoss_Nexus 3 5988
Protoss_Gateway 4 8961
Protoss_Assimilator 1 2298
Protoss_Cybernetics_Core 1 2940
Protoss_Dragoon 7 9406
Protoss_Robotics_Facility 1 6869
Protoss_Observatory 1 8178
Protoss_Zealot 2 9401
Protoss_Observer 2 9471
9471
