Protoss_Nexus 2 8001
Protoss_Gateway 3 8943
Protoss_Assimilator 1 2355
Protoss_Cybernetics_Core 1 2889
Protoss_Dragoon 8 9515
Protoss_Citadel_of_Adun 1 6017
Protoss_Templar_Archives 1 7174
Protoss_Dark_Templar 2 8407
Protoss_Robotics_Facility 1 9207
9515
