Protoss_Nexus 2 9505
Protoss_Gateway 1 1996
Protoss_Assimilator 1 2357
Protoss_Zealot 2 3588
Protoss_Cybernetics_Core 1 3293
Protoss_Dragoon 8 9957
Protoss_Robotics_Facility 1 5791
Protoss_Robotics_Support_Bay 1 7127
Protoss_Shuttle 1 7446
Protoss_Reaver 1 8431
9957
