Protoss_Nexus 2 8261
Protoss_Gateway 2 8919
Protoss_Assimilator 1 2373
Protoss_Cybernetics_Core 1 2966
Protoss_Dragoon 7 9229
Protoss_Robotics_Facility 1 5411
Protoss_Shuttle 1 6799
Protoss_Robotics_Support_Bay 1 6883
Protoss_Reaver 1 7701
Protoss_Observatory 1 8675
Protoss_Observer 1 9277
Protoss_Scarab 7 9914
Protoss_Citadel_of_Adun 1 9843
9914
