Protoss_Nexus 2 5771
Protoss_Gateway 2 4922
Protoss_Assimilator 2 8645
Protoss_Cybernetics_Core 1 2877
Protoss_Dragoon 9 9293
Protoss_Robotics_Facility 1 6214
Protoss_Observatory 1 7674
Protoss_Stargate 2 9946
Protoss_Observer 1 8205
Protoss_Fleet_Beacon 1 9311
9946
