Protoss_Nexus 1 0
Protoss_Gateway 3 7844
Protoss_Assimilator 1 2468
Protoss_Cybernetics_Core 1 3062
Protoss_Dragoon 7 8187
Protoss_Robotics_Facility 1 5598
Protoss_Observatory 1 6934
Protoss_Observer 2 8078
Protoss_Zealot 3 9621
Protoss_Citadel_of_Adun 1 8837
Protoss_Shuttle 1 8911
9621
