Protoss_Nexus 2 7217
Protoss_Gateway 2 5981
Protoss_Assimilator 1 2266
Protoss_Cybernetics_Core 1 2893
Protoss_Dragoon 8 9337
Protoss_Robotics_Facility 2 5649
Protoss_Observatory 1 6974
Protoss_Observer 1 7507
Protoss_Shuttle 1 8391
Protoss_Robotics_Support_Bay 1 8712
Protoss_Reaver 1 9293
9337
