Protoss_Nexus 2 7117
Protoss_Gateway 2 7885
Protoss_Assimilator 1 2298
Protoss_Cybernetics_Core 1 3008
Protoss_Robotics_Facility 1 4163
Protoss_Dragoon 9 9806
Protoss_Observatory 1 5586
Protoss_Observer 1 6211
Protoss_Shuttle 1 7606
Protoss_Robotics_Support_Bay 1 8648
9806
