Protoss_Nexus 3 8818
Protoss_Gateway 3 9947
Protoss_Assimilator 2 7409
Protoss_Cybernetics_Core 1 4243
Protoss_Zealot 1 4415
Protoss_Dragoon 10 9890
Protoss_Robotics_Facility 1 7310
Protoss_Observatory 1 8954
Protoss_Observer 1 9505
Protoss_Citadel_of_Adun 1 9793
9947
