Protoss_Nexus 3 8528
Protoss_Gateway 6 9399
Protoss_Assimilator 1 2212
Protoss_Cybernetics_Core 1 2938
Protoss_Dragoon 8 9805
Protoss_Robotics_Facility 1 7044
Protoss_Observatory 1 8425
Protoss_Observer 2 9685
9805
