Protoss_Nexus 3 7116
Protoss_Assimilator 2 2721
Protoss_Gateway 6 9859
Protoss_Cybernetics_Core 1 3413
Protoss_Dragoon 5 8377
Protoss_Robotics_Facility 1 7875
Protoss_Shuttle 1 9223
Protoss_Robotics_Support_Bay 1 9661
9859
