Protoss_Nexus 2 6289
Protoss_Gateway 3 9499
Protoss_Assimilator 1 2776
Protoss_Zealot 4 8731
Protoss_Cybernetics_Core 1 3410
Protoss_Dragoon 7 9609
Protoss_Robotics_Facility 1 6488
Protoss_Shuttle 1 7767
Protoss_Robotics_Support_Bay 1 8107
Protoss_Observatory 1 8389
Protoss_Reaver 1 8815
Protoss_Observer 1 9867
9867
