Protoss_Nexus 2 7141
Protoss_Gateway 2 9157
Protoss_Assimilator 2 3327
Protoss_Zealot 3 4487
Protoss_Cybernetics_Core 1 4220
Protoss_Citadel_of_Adun 1 5366
Protoss_Dragoon 5 9995
Protoss_Templar_Archives 1 6390
Protoss_Dark_Templar 2 8129
Protoss_Forge 1 7756
Protoss_Photon_Cannon 1 8506
Protoss_Robotics_Facility 1 9433
9995
