Protoss_Nexus 1 0
Protoss_Gateway 2 8193
Protoss_Assimilator 1 2553
Protoss_Cybernetics_Core 1 3218
Protoss_Robotics_Facility 1 4273
Protoss_Dragoon 6 9765
Protoss_Zealot 2 5900
Protoss_Shuttle 1 5566
Protoss_Robotics_Support_Bay 1 6234
Protoss_Reaver 2 9271
Protoss_Scarab 5 9852
9852
