Protoss_Nexus 2 6097
Protoss_Gateway 2 7378
Protoss_Assimilator 2 8703
Protoss_Cybernetics_Core 1 3043
Protoss_Dragoon 10 9519
Protoss_Robotics_Facility 1 6987
Protoss_Observatory 1 8320
Protoss_Observer 1 9003
Protoss_Shuttle 1 9843
Protoss_Robotics_Support_Bay 1 9914
9914
