Protoss_Nexus 3 8627
Protoss_Gateway 4 9966
Protoss_Assimilator 1 3417
Protoss_Cybernetics_Core 1 4109
Protoss_Zealot 1 4591
Protoss_Dragoon 12 9869
Protoss_Robotics_Facility 1 7453
Protoss_Observatory 1 9164
9966
