Protoss_Nexus 2 8307
Protoss_Gateway 2 4707
Protoss_Assimilator 1 2253
Protoss_Cybernetics_Core 1 3008
Protoss_Dragoon 9 9863
Protoss_Citadel_of_Adun 1 5777
Protoss_Templar_Archives 1 6776
Protoss_Zealot 1 7009
Protoss_Dark_Templar 2 8239
Protoss_Robotics_Facility 1 8889
9863
