Protoss_Nexus 2 7997
Protoss_Gateway 2 8519
Protoss_Assimilator 1 2331
Protoss_Cybernetics_Core 1 3148
Protoss_Dragoon 8 9891
Protoss_Robotics_Facility 1 5377
Protoss_Shuttle 1 6723
Protoss_Robotics_Support_Bay 1 6859
Protoss_Reaver 2 9381
Protoss_Observatory 1 8635
Protoss_Scarab 2 9245
9891
