Protoss_Nexus 1 0
Protoss_Assimilator 1 1707
Protoss_Gateway 3 8609
Protoss_Cybernetics_Core 1 3181
Protoss_Dragoon 6 9991
Protoss_Citadel_of_Adun 1 5519
Protoss_Robotics_Facility 1 6217
Protoss_Templar_Archives 1 6505
Protoss_Dark_Templar 4 9821
Protoss_Shuttle 1 7563
Protoss_Observatory 1 7759
Protoss_Observer 1 8979
Protoss_Zealot 2 9769
9991
