Protoss_Nexus 2 4188
Protoss_Gateway 2 5013
Protoss_Zealot 4 9037
Protoss_Assimilator 2 7755
Protoss_Cybernetics_Core 1 4693
Protoss_Dragoon 6 9757
Protoss_Robotics_Facility 1 7305
Protoss_Shuttle 1 8595
Protoss_Robotics_Support_Bay 1 8615
Protoss_Stargate 1 8996
Protoss_Reaver 1 9497
Protoss_Observatory 1 9646
9757
