Protoss_Nexus 2 7697
Protoss_Gateway 3 8313
Protoss_Assimilator 1 2319
Protoss_Cybernetics_Core 1 2885
Protoss_Zealot 1 3213
Protoss_Dragoon 11 9633
Protoss_Robotics_Facility 1 5617
Protoss_Observatory 1 6905
Protoss_Observer 2 8637
9633
