Protoss_Nexus 2 5967
Protoss_Gateway 2 8531
Protoss_Assimilator 1 2320
Protoss_Cybernetics_Core 1 2937
Protoss_Dragoon 7 9519
Protoss_Robotics_Facility 1 7018
Protoss_Shuttle 1 8303
Protoss_Robotics_Support_Bay 1 8360
Protoss_Zealot 2 9349
Protoss_Observatory 1 9200
Protoss_Reaver 1 9205
9519
