Protoss_Nexus 2 7924
Protoss_Gateway 3 9829
Protoss_Assimilator 1 2425
Protoss_Cybernetics_Core 1 3059
Protoss_Dragoon 11 9721
Protoss_Robotics_Facility 1 6083
Protoss_Observatory 1 7492
Protoss_Observer 2 8681
9829
