Protoss_Nexus 2 6453
Protoss_Gateway 4 7451
Protoss_Zealot 8 8491
Protoss_Assimilator 4 8896
Protoss_Forge 1 4580
Protoss_Photon_Cannon 2 7673
Protoss_Cybernetics_Core 1 8021
Protoss_Dragoon 2 9119
9119
