Protoss_Nexus 3 9985
Protoss_Gateway 2 2559
Protoss_Zealot 8 5739
Protoss_Assimilator 1 4606
Protoss_Cybernetics_Core 1 5598
Protoss_Dragoon 7 9165
Protoss_Robotics_Facility 1 8949
9985
