Protoss_Nexus 1 0
Protoss_Gateway 2 7208
Protoss_Assimilator 1 2358
Protoss_Cybernetics_Core 1 3006
Protoss_Dragoon 2 5196
Protoss_Robotics_Facility 1 4662
Protoss_Observatory 1 6045
Protoss_Citadel_of_Adun 1 6144
Protoss_Zealot 4 8556
Protoss_Observer 2 7261
Protoss_Shuttle 2 9376
9376
