Protoss_Nexus 3 8745
Protoss_Gateway 1 1879
Protoss_Assimilator 1 2365
Protoss_Zealot 9 8341
Protoss_Forge 1 4019
Protoss_Photon_Cannon 2 5145
Protoss_Cybernetics_Core 1 6669
Protoss_Robotics_Facility 1 7867
Protoss_Shuttle 1 9269
Protoss_Robotics_Support_Bay 1 9649
9649
