Protoss_Nexus 3 9063
Protoss_Gateway 2 7690
Protoss_Assimilator 1 2334
Protoss_Cybernetics_Core 1 2895
Protoss_Dragoon 10 9455
Protoss_Robotics_Facility 1 5349
Protoss_Observatory 1 7296
Protoss_Observer 3 9309
9455
