Protoss_Nexus 2 7714
Protoss_Gateway 2 5463
Protoss_Assimilator 1 2205
Protoss_Cybernetics_Core 1 3061
Protoss_Dragoon 5 9533
Protoss_Citadel_of_Adun 1 4195
Protoss_Robotics_Facility 1 4918
Protoss_Templar_Archives 1 5824
Protoss_Shuttle 1 6201
Protoss_Dark_Templar 2 6821
9533
