Protoss_Nexus 3 9097
Protoss_Gateway 4 9473
Protoss_Assimilator 2 8508
Protoss_Cybernetics_Core 1 2937
Protoss_Dragoon 5 7029
Protoss_Robotics_Facility 1 5610
Protoss_Observatory 1 7007
Protoss_Observer 2 8881
Protoss_Zealot 1 7909
Protoss_Citadel_of_Adun 1 8459
Protoss_Templar_Archives 1 9824
9824
