Protoss_Nexus 2 5521
Protoss_Gateway 2 6923
Protoss_Zealot 3 4459
Protoss_Assimilator 2 7414
Protoss_Cybernetics_Core 1 4300
Protoss_Dragoon 8 9555
Protoss_Robotics_Facility 1 7906
Protoss_Robotics_Support_Bay 1 9273
Protoss_Observatory 1 9457
9555
