Protoss_Nexus 2 9295
Protoss_Gateway 2 9517
Protoss_Assimilator 2 2731
Protoss_Zealot 2 3421
Protoss_Cybernetics_Core 1 3085
Protoss_Dragoon 7 9467
Protoss_Robotics_Facility 1 4771
Protoss_Shuttle 1 6093
Protoss_Robotics_Support_Bay 1 6652
Protoss_Reaver 1 7205
Protoss_Observatory 1 7697
Protoss_Scarab 7 9990
Protoss_Observer 3 9817
9990
