Protoss_Assimilator 17 2397
Protoss_Nexus 1 0
Protoss_Gateway 2 4131
Protoss_Cybernetics_Core 1 3005
Protoss_Zealot 1 3317
Protoss_Dragoon 3 5195
Protoss_Stargate 2 6712
Protoss_Fleet_Beacon 1 6288
Protoss_Carrier 2 8795
Protoss_Forge 1 8014
Protoss_Photon_Cannon 2 9128
Protoss_Interceptor 2 9983
9983
