Protoss_Nexus 2 6936
Protoss_Gateway 2 5840
Protoss_Assimilator 1 2334
Protoss_Cybernetics_Core 1 3006
Protoss_Dragoon 8 8493
Protoss_Robotics_Facility 1 5283
Protoss_Observatory 1 6652
Protoss_Observer 1 7489
Protoss_Shuttle 1 8249
Protoss_Robotics_Support_Bay 1 8344
Protoss_Reaver 1 9169
Protoss_Zealot 2 9813
9813
