Protoss_Nexus 3 9665
Protoss_Gateway 3 9051
Protoss_Assimilator 1 2255
Protoss_Cybernetics_Core 1 2950
Protoss_Dragoon 9 9689
Protoss_Robotics_Facility 1 6013
Protoss_Observatory 1 7360
Protoss_Observer 2 9669
Protoss_Shuttle 1 8577
9689
