Protoss_Nexus 1 0
Protoss_Gateway 2 5234
Protoss_Assimilator 1 2327
Protoss_Cybernetics_Core 1 3034
Protoss_Robotics_Facility 1 4115
Protoss_Dragoon 9 9976
Protoss_Observatory 1 5518
Protoss_Observer 2 9849
Protoss_Shuttle 1 7343
9976
