Protoss_Nexus 4 8317
Protoss_Gateway 4 9941
Protoss_Assimilator 2 8722
Protoss_Zealot 1 4055
Protoss_Cybernetics_Core 1 4338
Protoss_Citadel_of_Adun 1 5364
Protoss_Dragoon 3 9311
Protoss_Forge 1 6054
Protoss_Templar_Archives 1 6435
Protoss_Photon_Cannon 1 7319
Protoss_Dark_Templar 1 7455
Protoss_Robotics_Facility 1 8787
9941
