Protoss_Nexus 2 8281
Protoss_Gateway 2 9281
Protoss_Assimilator 1 2266
Protoss_Cybernetics_Core 1 2865
Protoss_Dragoon 6 9425
Protoss_Robotics_Facility 1 5225
Protoss_Shuttle 1 6511
Protoss_Robotics_Support_Bay 1 6593
Protoss_Zealot 2 7591
Protoss_Observatory 1 7388
Protoss_Reaver 1 7429
Protoss_Observer 2 9375
9425
