Protoss_Nexus 3 8953
Protoss_Gateway 3 9852
Protoss_Zealot 2 3987
Protoss_Assimilator 1 3282
Protoss_Cybernetics_Core 1 3744
Protoss_Dragoon 5 7833
Protoss_Robotics_Facility 1 7967
Protoss_Observatory 1 9408
9852
