Protoss_Nexus 2 3331
Protoss_Gateway 4 9487
Protoss_Zealot 2 4871
Protoss_Assimilator 1 4016
Protoss_Cybernetics_Core 1 4545
Protoss_Dragoon 8 9293
Protoss_Robotics_Facility 1 9732
9732
