Protoss_Nexus 2 9803
Protoss_Gateway 1 1905
Protoss_Zealot 3 4099
Protoss_Assimilator 1 3098
Protoss_Cybernetics_Core 1 3986
Protoss_Robotics_Facility 1 5030
Protoss_Dragoon 6 9415
Protoss_Shuttle 1 6345
Protoss_Robotics_Support_Bay 1 6573
Protoss_Reaver 1 7247
Protoss_Observatory 1 7775
Protoss_Observer 1 8623
Protoss_Scarab 4 9944
9944
