Protoss_Nexus 2 2991
Protoss_Gateway 4 9713
Protoss_Assimilator 2 8990
Protoss_Cybernetics_Core 1 4537
Protoss_Zealot 6 9413
Protoss_Dragoon 8 9458
Protoss_Robotics_Facility 1 8263
Protoss_Observatory 1 9833
Protoss_Shuttle 1 9911
9911
