Protoss_Nexus 2 4973
Protoss_Gateway 4 9673
Protoss_Assimilator 4 7918
Protoss_Zealot 3 4153
Protoss_Cybernetics_Core 1 5843
Protoss_Dragoon 7 9293
Protoss_Robotics_Facility 1 9159
9673
