Protoss_Nexus 2 8393
Protoss_Gateway 2 2271
Protoss_Zealot 6 4635
Protoss_Forge 1 4403
Protoss_Photon_Cannon 3 7277
Protoss_Assimilator 2 9689
Protoss_Cybernetics_Core 1 6110
Protoss_Citadel_of_Adun 1 7503
Protoss_Templar_Archives 1 8681
Protoss_Robotics_Facility 1 9555
Protoss_Dark_Templar 1 9773
9773
