Protoss_Nexus 2 8717
Protoss_Gateway 2 6271
Protoss_Assimilator 1 2505
Protoss_Cybernetics_Core 1 3150
Protoss_Dragoon 7 9096
Protoss_Robotics_Facility 1 4678
Protoss_Observatory 1 5973
Protoss_Observer 3 8951
9096
