Protoss_Nexus 3 7938
Protoss_Gateway 2 4739
Protoss_Assimilator 2 9350
Protoss_Cybernetics_Core 1 3035
Protoss_Dragoon 6 8265
Protoss_Citadel_of_Adun 1 7299
Protoss_Templar_Archives 1 8353
Protoss_Dark_Templar 2 9349
Protoss_Stargate 1 9940
9940
