Protoss_Nexus 1 0
Protoss_Gateway 2 2397
Protoss_Zealot 8 7713
Protoss_Assimilator 1 4248
Protoss_Cybernetics_Core 1 5263
Protoss_Dragoon 6 9123
Protoss_Robotics_Facility 1 7545
Protoss_Observatory 1 8831
Protoss_Observer 1 9725
9725
