Protoss_Nexus 2 8484
Protoss_Gateway 2 3513
Protoss_Assimilator 1 2529
Protoss_Cybernetics_Core 1 3042
Protoss_Dragoon 8 9785
Protoss_Citadel_of_Adun 1 5969
Protoss_Templar_Archives 1 6955
Protoss_Zealot 2 7441
Protoss_Dark_Templar 4 8901
9785
