Protoss_Nexus 2 5727
Protoss_Gateway 2 4510
Protoss_Assimilator 1 2268
Protoss_Cybernetics_Core 1 3115
Protoss_Dragoon 10 9283
Protoss_Zealot 2 6863
Protoss_Robotics_Facility 1 8345
Protoss_Shuttle 1 9739
Protoss_Robotics_Support_Bay 1 9836
9836
