Special_Protoss_Temple 30 0
Protoss_Nexus 2 7339
Protoss_Gateway 2 4764
Protoss_Assimilator 1 2454
Protoss_Cybernetics_Core 1 3133
Protoss_Dragoon 10 9317
Protoss_Citadel_of_Adun 1 7630
Protoss_Templar_Archives 1 9401
Protoss_Robotics_Facility 1 9466
9466
