Protoss_Nexus 2 9845
Protoss_Gateway 2 4824
Protoss_Assimilator 3 4259
Protoss_Cybernetics_Core 1 3362
Protoss_Dragoon 7 7313
Protoss_Robotics_Facility 1 6900
Protoss_Shuttle 1 8213
Protoss_Robotics_Support_Bay 1 8718
Protoss_Zealot 2 8999
Protoss_Reaver 1 9255
Protoss_Observatory 1 9684
9845
