Protoss_Nexus 2 6598
Protoss_Gateway 3 9176
Protoss_Assimilator 1 2441
Protoss_Cybernetics_Core 1 3089
Protoss_Zealot 3 9059
Protoss_Dragoon 8 9853
Protoss_Robotics_Facility 1 5538
Protoss_Shuttle 1 6915
Protoss_Observatory 1 7066
Protoss_Robotics_Support_Bay 1 7909
Protoss_Observer 2 9635
Protoss_Reaver 1 8583
9853
