Protoss_Nexus 2 8054
Protoss_Gateway 2 6576
Protoss_Assimilator 1 2333
Protoss_Cybernetics_Core 1 3025
Protoss_Dragoon 9 9557
Protoss_Robotics_Facility 1 6466
Protoss_Observatory 1 7899
Protoss_Observer 2 9675
Protoss_Zealot 2 8645
9675
