Protoss_Nexus 2 9667
Protoss_Gateway 2 7276
Protoss_Zealot 2 4107
Protoss_Assimilator 1 3159
Protoss_Cybernetics_Core 1 3655
Protoss_Dragoon 9 9435
Protoss_Robotics_Facility 1 6478
Protoss_Observatory 1 7829
Protoss_Observer 2 8961
Protoss_Shuttle 1 9971
9971
