Protoss_Nexus 1 0
Protoss_Gateway 2 9711
Protoss_Assimilator 1 2593
Protoss_Cybernetics_Core 1 3224
Protoss_Dragoon 4 8618
Protoss_Robotics_Facility 1 4658
Protoss_Shuttle 1 5951
Protoss_Robotics_Support_Bay 1 6183
Protoss_Zealot 3 9491
Protoss_Reaver 1 6986
Protoss_Observatory 1 7619
Protoss_Observer 2 9686
Protoss_Scarab 4 9311
9711
