Protoss_Nexus 3 7539
Protoss_Gateway 3 9333
Protoss_Assimilator 2 8585
Protoss_Cybernetics_Core 1 2910
Protoss_Zealot 1 3221
Protoss_Dragoon 4 6501
Protoss_Citadel_of_Adun 1 6901
Protoss_Templar_Archives 1 7887
Protoss_Dark_Templar 2 9327
9333
