Special_Protoss_Temple 30 0
Protoss_Nexus 2 3000
Protoss_Gateway 2 4470
Protoss_Assimilator 1 3573
Protoss_Cybernetics_Core 1 4319
Protoss_Zealot 2 9815
Protoss_Dragoon 9 9863
Protoss_Robotics_Facility 1 9067
9863
