Protoss_Nexus 2 7298
Protoss_Gateway 3 8134
Protoss_Assimilator 1 2433
Protoss_Cybernetics_Core 1 3180
Protoss_Dragoon 10 9421
Protoss_Robotics_Facility 1 8240
Protoss_Zealot 1 9437
Protoss_Observatory 1 9712
9712
