Protoss_Nexus 2 5344
Protoss_Gateway 3 8302
Protoss_Assimilator 3 7263
Protoss_Zealot 7 7729
Protoss_Cybernetics_Core 1 5830
Protoss_Citadel_of_Adun 1 7353
Protoss_Dragoon 4 8925
Protoss_Templar_Archives 1 8539
Protoss_Dark_Templar 3 9677
9677
