Protoss_Nexus 2 7465
Protoss_Gateway 2 9377
Protoss_Assimilator 1 2204
Protoss_Cybernetics_Core 1 2984
Protoss_Dragoon 7 9943
Protoss_Robotics_Facility 1 4403
Protoss_Observatory 1 5713
Protoss_Observer 2 6861
Protoss_Shuttle 1 7905
Protoss_Robotics_Support_Bay 1 8232
Protoss_Reaver 1 8851
9943
