Protoss_Nexus 1 0
Protoss_Gateway 2 2251
Protoss_Zealot 6 4575
Protoss_Assimilator 1 3702
Protoss_Cybernetics_Core 1 4129
Protoss_Dragoon 8 9443
Protoss_Citadel_of_Adun 1 7898
Protoss_Templar_Archives 1 9095
9443
