Protoss_Nexus 2 7413
Protoss_Gateway 4 9622
Protoss_Assimilator 1 2205
Protoss_Cybernetics_Core 1 2880
Protoss_Zealot 1 3521
Protoss_Dragoon 4 6389
Protoss_Citadel_of_Adun 1 5347
Protoss_Templar_Archives 1 6351
Protoss_Dark_Templar 4 9273
9622
