Protoss_Nexus 3 9161
Protoss_Gateway 3 9893
Protoss_Assimilator 1 2337
Protoss_Cybernetics_Core 1 2971
Protoss_Dragoon 10 9893
Protoss_Robotics_Facility 1 5423
Protoss_Observatory 1 6992
Protoss_Observer 2 8125
9893
