Protoss_Nexus 1 0
Protoss_Gateway 3 7245
Protoss_Zealot 6 5866
Protoss_Shield_Battery 1 3748
Protoss_Assimilator 1 4876
Protoss_Cybernetics_Core 1 5783
Protoss_Dragoon 9 9266
Protoss_Robotics_Facility 1 9714
9714
