Protoss_Nexus 2 8931
Protoss_Gateway 2 6502
Protoss_Assimilator 1 2205
Protoss_Cybernetics_Core 1 2868
Protoss_Zealot 1 3183
Protoss_Dragoon 9 9329
Protoss_Robotics_Facility 1 5311
Protoss_Shuttle 1 6733
Protoss_Robotics_Support_Bay 1 6851
Protoss_Reaver 1 8267
Protoss_Observatory 1 9125
Protoss_Observer 1 9685
9685
