Protoss_Nexus 3 8441
Protoss_Gateway 3 7269
Protoss_Assimilator 1 3396
Protoss_Cybernetics_Core 1 4270
Protoss_Zealot 1 4747
Protoss_Dragoon 10 9831
Protoss_Robotics_Facility 1 6595
Protoss_Observatory 1 8014
Protoss_Observer 2 9637
9831
