Protoss_Nexus 2 9953
Protoss_Gateway 1 2005
Protoss_Assimilator 1 2654
Protoss_Cybernetics_Core 1 3126
Protoss_Dragoon 6 9209
Protoss_Robotics_Facility 1 5653
Protoss_Shuttle 1 6979
Protoss_Observatory 1 7027
Protoss_Robotics_Support_Bay 1 7226
Protoss_Zealot 1 7561
Protoss_Reaver 2 8972
9953
