Protoss_Nexus 3 8152
Protoss_Gateway 5 9503
Protoss_Assimilator 1 2215
Protoss_Cybernetics_Core 1 2924
Protoss_Zealot 1 3341
Protoss_Dragoon 7 9745
Protoss_Robotics_Facility 1 6741
Protoss_Observatory 1 8229
Protoss_Observer 2 9437
Protoss_Citadel_of_Adun 1 9656
9745
