Protoss_Nexus 3 9827
Protoss_Gateway 3 7999
Protoss_Assimilator 2 9360
Protoss_Cybernetics_Core 1 2865
Protoss_Dragoon 7 9083
Protoss_Citadel_of_Adun 1 5033
Protoss_Templar_Archives 1 6126
Protoss_Dark_Templar 1 7163
Protoss_Robotics_Facility 1 7625
Protoss_Observatory 1 9010
Protoss_Observer 1 9561
9827
