Protoss_Nexus 2 5901
Protoss_Gateway 2 7195
Protoss_Assimilator 2 8027
Protoss_Cybernetics_Core 1 3234
Protoss_Dragoon 7 9467
Protoss_Citadel_of_Adun 1 6448
Protoss_Templar_Archives 1 7553
Protoss_Dark_Templar 4 9633
Protoss_Robotics_Facility 1 9042
9633
