Protoss_Nexus 3 9765
Protoss_Gateway 3 6659
Protoss_Assimilator 1 2555
Protoss_Cybernetics_Core 1 3207
Protoss_Dragoon 7 8017
Protoss_Robotics_Facility 1 4981
Protoss_Observatory 1 6287
Protoss_Observer 4 9517
9765
