Protoss_Nexus 3 7731
Protoss_Assimilator 2 2725
Protoss_Gateway 4 9521
Protoss_Cybernetics_Core 1 3391
Protoss_Zealot 1 3765
Protoss_Dragoon 6 8937
Protoss_Citadel_of_Adun 1 8354
Protoss_Templar_Archives 1 9366
9521
