Protoss_Nexus 2 8264
Protoss_Gateway 4 9428
Protoss_Assimilator 1 2532
Protoss_Cybernetics_Core 1 3136
Protoss_Dragoon 4 7116
Protoss_Robotics_Facility 1 4635
Protoss_Observatory 1 6008
Protoss_Observer 2 7726
Protoss_Citadel_of_Adun 1 8499
Protoss_Shuttle 1 9121
Protoss_Templar_Archives 1 9593
9593
