Protoss_Nexus 2 2699
Protoss_Gateway 4 8690
Protoss_Assimilator 2 7331
Protoss_Cybernetics_Core 1 4110
Protoss_Zealot 1 4781
Protoss_Dragoon 10 9239
Protoss_Robotics_Facility 1 7565
Protoss_Shuttle 1 8841
Protoss_Robotics_Support_Bay 1 9004
Protoss_Reaver 1 9883
9883
