Protoss_Nexus 3 7945
Protoss_Gateway 4 9775
Protoss_Assimilator 1 2175
Protoss_Cybernetics_Core 1 2884
Protoss_Dragoon 9 9257
Protoss_Robotics_Facility 1 7357
Protoss_Observatory 1 8683
Protoss_Observer 1 9239
9775
