Protoss_Nexus 2 8233
Protoss_Gateway 3 9922
Protoss_Assimilator 1 2438
Protoss_Cybernetics_Core 1 3178
Protoss_Zealot 1 3436
Protoss_Robotics_Facility 1 4533
Protoss_Dragoon 7 9945
Protoss_Observatory 1 5976
Protoss_Observer 3 8601
9945
