Protoss_Nexus 3 9765
Protoss_Gateway 2 3767
Protoss_Assimilator 1 2523
Protoss_Cybernetics_Core 1 3379
Protoss_Dragoon 8 9421
Protoss_Robotics_Facility 1 5883
Protoss_Observatory 1 7254
Protoss_Observer 3 9391
Protoss_Zealot 1 9321
9765
