Protoss_Nexus 2 7265
Protoss_Gateway 2 5995
Protoss_Zealot 4 9615
Protoss_Assimilator 1 3189
Protoss_Cybernetics_Core 1 3671
Protoss_Dragoon 5 7949
Protoss_Robotics_Facility 1 7660
Protoss_Shuttle 1 8961
Protoss_Robotics_Support_Bay 1 9397
Protoss_Observatory 1 9523
Protoss_Reaver 1 9965
9965
