Protoss_Nexus 2 6578
Protoss_Gateway 3 8032
Protoss_Assimilator 1 2453
Protoss_Cybernetics_Core 1 2996
Protoss_Dragoon 11 9961
Protoss_Robotics_Facility 1 5417
Protoss_Observatory 1 6762
Protoss_Observer 3 8613
9961
