Protoss_Nexus 1 0
Protoss_Gateway 2 7721
Protoss_Assimilator 1 2487
Protoss_Cybernetics_Core 1 3213
Protoss_Dragoon 5 9990
Protoss_Robotics_Facility 1 4877
Protoss_Zealot 2 7206
Protoss_Shuttle 1 6201
Protoss_Robotics_Support_Bay 1 6237
Protoss_Reaver 1 7103
Protoss_Observatory 1 7296
Protoss_Observer 2 9768
9990
