Protoss_Nexus 3 9302
Protoss_Gateway 2 5499
Protoss_Assimilator 1 2403
Protoss_Zealot 3 4345
Protoss_Cybernetics_Core 1 3894
Protoss_Dragoon 8 9655
Protoss_Robotics_Facility 1 7655
Protoss_Observatory 1 8943
Protoss_Observer 1 9471
9655
