Protoss_Nexus 2 8975
Protoss_Gateway 3 9804
Protoss_Assimilator 1 2525
Protoss_Cybernetics_Core 1 3078
Protoss_Dragoon 9 9616
Protoss_Robotics_Facility 1 4713
Protoss_Observatory 1 6432
Protoss_Observer 2 7721
9804
