Protoss_Nexus 1 0
Protoss_Gateway 2 5592
Protoss_Assimilator 1 2452
Protoss_Cybernetics_Core 1 2973
Protoss_Dragoon 7 9981
Protoss_Robotics_Facility 1 4573
Protoss_Zealot 3 9541
Protoss_Shuttle 2 7361
Protoss_Observatory 1 6563
Protoss_Robotics_Support_Bay 1 6975
Protoss_Reaver 1 8511
Protoss_Observer 1 9951
9981
