Protoss_Nexus 1 0
Protoss_Gateway 3 8018
Protoss_Assimilator 1 2377
Protoss_Cybernetics_Core 1 3017
Protoss_Dragoon 8 8291
Protoss_Robotics_Facility 1 5365
Protoss_Observatory 1 6905
Protoss_Observer 1 7625
Protoss_Citadel_of_Adun 1 7839
Protoss_Zealot 4 9255
Protoss_Shuttle 1 9707
9707
