Protoss_Nexus 2 6755
Protoss_Gateway 3 9961
Protoss_Assimilator 1 2460
Protoss_Zealot 2 3507
Protoss_Cybernetics_Core 1 3255
Protoss_Dragoon 8 9853
Protoss_Citadel_of_Adun 1 9314
9961
