Protoss_Nexus 3 7225
Protoss_Gateway 2 7601
Protoss_Assimilator 1 2329
Protoss_Cybernetics_Core 1 2949
Protoss_Dragoon 9 9665
Protoss_Robotics_Facility 1 8496
Protoss_Shuttle 1 9791
Protoss_Robotics_Support_Bay 1 9801
9801
