Protoss_Nexus 1 0
Protoss_Gateway 1 1811
Protoss_Assimilator 1 2183
Protoss_Cybernetics_Core 1 2807
Protoss_Zealot 1 3079
Protoss_Dragoon 7 9745
Protoss_Forge 1 4613
Protoss_Photon_Cannon 2 5605
Protoss_Stargate 2 7047
Protoss_Scout 4 9551
9745
