Protoss_Nexus 2 9612
Protoss_Gateway 2 4894
Protoss_Assimilator 1 2493
Protoss_Cybernetics_Core 1 3119
Protoss_Robotics_Facility 1 4295
Protoss_Shuttle 1 5696
Protoss_Dragoon 6 8073
Protoss_Observatory 1 6445
Protoss_Observer 2 7806
Protoss_Forge 1 7238
Protoss_Photon_Cannon 1 8243
9612
