Protoss_Nexus 2 8128
Protoss_Gateway 2 5944
Protoss_Assimilator 1 2366
Protoss_Cybernetics_Core 1 2994
Protoss_Dragoon 11 9543
Protoss_Robotics_Facility 1 5655
Protoss_Observatory 1 6987
Protoss_Observer 2 8375
Protoss_Shuttle 1 8977
Protoss_Robotics_Support_Bay 1 9709
Protoss_Zealot 1 9873
9873
