Protoss_Nexus 2 6269
Protoss_Gateway 2 9189
Protoss_Zealot 3 4297
Protoss_Assimilator 1 3507
Protoss_Cybernetics_Core 1 4178
Protoss_Dragoon 6 9693
Protoss_Robotics_Facility 1 6911
Protoss_Shuttle 1 8221
Protoss_Robotics_Support_Bay 1 8655
Protoss_Reaver 1 9211
9693
