Protoss_Nexus 2 9984
Protoss_Gateway 2 6619
Protoss_Assimilator 1 2650
Protoss_Cybernetics_Core 1 3034
Protoss_Dragoon 9 9721
Protoss_Robotics_Facility 1 5988
Protoss_Observatory 1 7283
Protoss_Zealot 1 7646
Protoss_Observer 2 8428
9984
