Protoss_Nexus 2 6851
Protoss_Gateway 3 8454
Protoss_Assimilator 1 2368
Protoss_Zealot 1 2967
Protoss_Cybernetics_Core 1 3653
Protoss_Dragoon 9 9915
Protoss_Robotics_Facility 1 5954
Protoss_Observatory 1 8004
Protoss_Observer 2 9199
9915
