Special_Protoss_Temple 30 0
Protoss_Nexus 3 8271
Protoss_Gateway 2 6454
Protoss_Assimilator 2 9664
Protoss_Cybernetics_Core 1 3017
Protoss_Dragoon 6 9527
Protoss_Robotics_Facility 1 6232
Protoss_Observatory 1 7780
Protoss_Observer 3 9663
Protoss_Citadel_of_Adun 1 8801
Protoss_Templar_Archives 1 9975
9975
