Protoss_Nexus 2 6863
Protoss_Gateway 4 9258
Protoss_Assimilator 1 2488
Protoss_Cybernetics_Core 1 2933
Protoss_Dragoon 11 9826
Protoss_Zealot 2 6306
Protoss_Robotics_Facility 1 7618
Protoss_Observatory 1 9177
9826
