Protoss_Nexus 3 9231
Protoss_Gateway 3 9733
Protoss_Assimilator 2 9359
Protoss_Cybernetics_Core 1 2893
Protoss_Dragoon 7 8309
Protoss_Robotics_Facility 1 6840
Protoss_Observatory 1 8759
Protoss_Observer 1 9441
9733
