Special_Protoss_Temple 30 0
Protoss_Nexus 2 9437
Protoss_Gateway 3 8690
Protoss_Forge 1 2567
Protoss_Assimilator 1 2749
Protoss_Cybernetics_Core 1 3158
Protoss_Dragoon 13 9946
Protoss_Zealot 1 5096
Protoss_Robotics_Facility 1 7103
Protoss_Observatory 1 8578
Protoss_Observer 1 9251
9946
