Special_Protoss_Temple 30 0
Protoss_Nexus 3 8201
Protoss_Gateway 2 5961
Protoss_Assimilator 2 8693
Protoss_Cybernetics_Core 1 3173
Protoss_Dragoon 9 9851
Protoss_Robotics_Facility 1 5301
Protoss_Observatory 1 6675
Protoss_Observer 5 9933
Protoss_Citadel_of_Adun 1 9226
9933
