Protoss_Nexus 3 9139
Protoss_Gateway 2 7271
Protoss_Assimilator 2 9270
Protoss_Cybernetics_Core 1 3081
Protoss_Dragoon 9 9773
Protoss_Robotics_Facility 1 6441
Protoss_Observatory 1 7913
Protoss_Shuttle 1 8337
Protoss_Observer 3 9685
9773
