Protoss_Nexus 3 9499
Protoss_Gateway 3 7799
Protoss_Assimilator 1 2241
Protoss_Cybernetics_Core 1 2953
Protoss_Dragoon 11 9981
Protoss_Robotics_Facility 1 6831
Protoss_Observatory 1 8371
Protoss_Observer 2 9557
9981
