Protoss_Nexus 2 9359
Protoss_Gateway 2 5371
Protoss_Assimilator 1 2391
Protoss_Cybernetics_Core 1 3011
Protoss_Zealot 3 8182
Protoss_Dragoon 9 9777
Protoss_Robotics_Facility 1 6847
Protoss_Observatory 1 8205
Protoss_Shuttle 1 8421
Protoss_Observer 1 9391
9777
