Protoss_Nexus 1 0
Protoss_Gateway 3 7087
Protoss_Assimilator 1 2670
Protoss_Cybernetics_Core 1 3299
Protoss_Dragoon 8 9501
Protoss_Robotics_Facility 1 5842
Protoss_Observatory 1 7282
Protoss_Shuttle 1 7451
Protoss_Observer 1 8353
Protoss_Robotics_Support_Bay 1 8388
Protoss_Zealot 1 9805
9805
