Protoss_Nexus 2 6148
Protoss_Gateway 2 7187
Protoss_Assimilator 2 9242
Protoss_Cybernetics_Core 1 2988
Protoss_Dragoon 11 9745
Protoss_Robotics_Facility 1 6899
Protoss_Observatory 1 8207
Protoss_Observer 3 9945
9945
