Protoss_Nexus 2 9543
Protoss_Gateway 3 7121
Protoss_Assimilator 1 2213
Protoss_Cybernetics_Core 1 2965
Protoss_Dragoon 9 9281
Protoss_Citadel_of_Adun 1 5721
Protoss_Robotics_Facility 1 6033
Protoss_Observatory 1 7335
Protoss_Observer 3 9179
9543
