Protoss_Nexus 2 6722
Protoss_Gateway 3 7513
Protoss_Assimilator 2 8305
Protoss_Cybernetics_Core 1 2955
Protoss_Dragoon 6 8735
Protoss_Robotics_Facility 1 4414
Protoss_Observatory 3 6449
Protoss_Observer 3 9229
Protoss_Citadel_of_Adun 1 8445
Protoss_Zealot 2 8997
Protoss_Templar_Archives 1 9620
9620
