Protoss_Nexus 3 7494
Protoss_Gateway 5 9723
Protoss_Assimilator 1 2242
Protoss_Cybernetics_Core 1 2905
Protoss_Dragoon 6 9909
Protoss_Robotics_Facility 1 6453
Protoss_Shuttle 1 8013
Protoss_Zealot 1 8411
Protoss_Robotics_Support_Bay 1 8561
Protoss_Reaver 1 9201
Protoss_Observatory 1 9865
9909
