Protoss_Nexus 3 7473
Protoss_Gateway 3 9481
Protoss_Assimilator 1 2395
Protoss_Cybernetics_Core 1 2924
Protoss_Dragoon 8 9478
Protoss_Robotics_Facility 1 8318
Protoss_Shuttle 1 9691
9691
