Protoss_Nexus 2 10000
Protoss_Gateway 3 9182
Protoss_Assimilator 1 2462
Protoss_Cybernetics_Core 1 3057
Protoss_Zealot 4 5400
Protoss_Dragoon 7 9101
Protoss_Robotics_Facility 1 7461
Protoss_Observatory 1 9380
Protoss_Observer 1 9991
10000
