Protoss_Nexus 2 8998
Protoss_Gateway 2 6586
Protoss_Assimilator 1 2672
Protoss_Cybernetics_Core 1 3264
Protoss_Dragoon 10 9646
Protoss_Robotics_Facility 1 6138
Protoss_Observatory 1 7531
Protoss_Observer 2 9391
9646
