Protoss_Nexus 2 9871
Protoss_Assimilator 1 2031
Protoss_Gateway 1 2433
Protoss_Cybernetics_Core 1 3486
Protoss_Robotics_Facility 1 4570
Protoss_Dragoon 6 9456
Protoss_Shuttle 3 9666
Protoss_Observatory 1 6472
Protoss_Observer 2 7716
Protoss_Robotics_Support_Bay 1 7479
9871
