Protoss_Nexus 1 0
Protoss_Gateway 1 2085
Protoss_Assimilator 1 2648
Protoss_Cybernetics_Core 1 3297
Protoss_Dragoon 3 6186
Protoss_Robotics_Facility 1 4758
Protoss_Shuttle 1 7371
7371
