Special_Protoss_Temple 30 0
Protoss_Nexus 3 9126
Protoss_Gateway 2 6096
Protoss_Assimilator 1 2425
Protoss_Cybernetics_Core 1 3054
Protoss_Dragoon 7 8109
Protoss_Robotics_Facility 1 5548
Protoss_Observatory 1 6907
Protoss_Observer 3 9259
Protoss_Citadel_of_Adun 1 9676
9676
