Protoss_Nexus 3 8857
Protoss_Gateway 3 7693
Protoss_Assimilator 2 7974
Protoss_Cybernetics_Core 1 4199
Protoss_Zealot 2 8269
Protoss_Dragoon 11 9713
Protoss_Robotics_Facility 1 6471
Protoss_Observatory 1 7813
Protoss_Observer 3 9779
Protoss_Citadel_of_Adun 1 9880
9880
