Special_Protoss_Temple 30 0
Protoss_Nexus 3 9719
Protoss_Gateway 2 5915
Protoss_Assimilator 1 2184
Protoss_Cybernetics_Core 1 2811
Protoss_Dragoon 10 8499
Protoss_Robotics_Facility 1 5545
Protoss_Observatory 1 6894
Protoss_Observer 2 9561
9719
