Protoss_Nexus 2 6351
Protoss_Gateway 2 7339
Protoss_Assimilator 2 8863
Protoss_Cybernetics_Core 1 3068
Protoss_Dragoon 6 9567
Protoss_Citadel_of_Adun 1 5336
Protoss_Templar_Archives 1 6565
Protoss_Dark_Templar 2 8423
Protoss_Robotics_Facility 1 8204
9567
