Protoss_Nexus 2 9147
Protoss_Gateway 3 9753
Protoss_Assimilator 1 2081
Protoss_Cybernetics_Core 1 3019
Protoss_Dragoon 9 8135
Protoss_Robotics_Facility 1 4384
Protoss_Observatory 1 5687
Protoss_Observer 2 7027
Protoss_Shuttle 1 8581
Protoss_Zealot 3 9883
9883
