Protoss_Nexus 2 9168
Protoss_Gateway 2 5634
Protoss_Assimilator 1 2185
Protoss_Zealot 3 4428
Protoss_Cybernetics_Core 1 3598
Protoss_Robotics_Facility 1 4789
Protoss_Dragoon 3 9826
Protoss_Shuttle 1 7096
Protoss_Robotics_Support_Bay 1 7459
Protoss_Observatory 1 8088
Protoss_Reaver 1 8356
Protoss_Observer 1 9408
Protoss_Citadel_of_Adun 1 9718
9826
