Protoss_Nexus 2 9685
Protoss_Gateway 2 5111
Protoss_Assimilator 1 2369
Protoss_Cybernetics_Core 1 3011
Protoss_Dragoon 12 8809
Protoss_Robotics_Facility 1 6259
Protoss_Observatory 1 7567
Protoss_Observer 2 8855
9685
