Protoss_Nexus 3 8657
Protoss_Gateway 3 9662
Protoss_Assimilator 1 2344
Protoss_Cybernetics_Core 1 2926
Protoss_Dragoon 10 9889
Protoss_Zealot 1 7047
Protoss_Robotics_Facility 1 8463
Protoss_Observatory 1 9761
9889
