Protoss_Nexus 3 9094
Protoss_Gateway 2 6083
Protoss_Assimilator 1 2524
Protoss_Cybernetics_Core 1 3193
Protoss_Robotics_Facility 1 4446
Protoss_Dragoon 7 9716
Protoss_Observatory 1 5948
Protoss_Observer 3 9768
Protoss_Shuttle 1 8866
Protoss_Citadel_of_Adun 1 9354
9768
