Protoss_Nexus 2 6471
Protoss_Gateway 4 9947
Protoss_Assimilator 3 8798
Protoss_Zealot 1 3077
Protoss_Cybernetics_Core 1 3294
Protoss_Dragoon 9 9665
Protoss_Robotics_Facility 1 7875
Protoss_Observatory 1 9229
9947
