Protoss_Nexus 2 8127
Protoss_Gateway 3 8280
Protoss_Assimilator 1 2593
Protoss_Cybernetics_Core 1 3190
Protoss_Dragoon 9 9621
Protoss_Citadel_of_Adun 1 5587
Protoss_Templar_Archives 1 6647
Protoss_Dark_Templar 2 7816
Protoss_Robotics_Facility 1 8943
9621
