Protoss_Nexus 3 8773
Protoss_Gateway 2 9902
Protoss_Assimilator 1 2313
Protoss_Cybernetics_Core 1 2967
Protoss_Dragoon 5 9879
Protoss_Robotics_Facility 1 5140
Protoss_Shuttle 1 6477
Protoss_Robotics_Support_Bay 1 6857
Protoss_Zealot 2 7595
Protoss_Reaver 1 7385
Protoss_Stargate 1 9445
Protoss_Observatory 1 9926
9926
