Protoss_Nexus 2 9846
Protoss_Gateway 2 5498
Protoss_Assimilator 1 2523
Protoss_Cybernetics_Core 1 3071
Protoss_Dragoon 10 9639
Protoss_Robotics_Facility 1 6372
Protoss_Zealot 2 7475
Protoss_Observatory 1 7723
Protoss_Observer 2 9481
9846
