Protoss_Nexus 2 5672
Protoss_Gateway 3 8792
Protoss_Assimilator 1 2486
Protoss_Cybernetics_Core 1 2987
Protoss_Dragoon 8 9917
Protoss_Robotics_Facility 1 6265
Protoss_Shuttle 1 7587
Protoss_Robotics_Support_Bay 1 7885
Protoss_Zealot 2 8237
Protoss_Reaver 1 8489
Protoss_Observatory 1 8640
Protoss_Scarab 1 9765
9917
