Protoss_Nexus 1 0
Protoss_Gateway 1 1968
Protoss_Assimilator 1 2456
Protoss_Cybernetics_Core 1 3178
Protoss_Zealot 2 4831
Protoss_Robotics_Facility 1 4666
Protoss_Dragoon 2 6619
6619
