Protoss_Nexus 2 2679
Protoss_Gateway 2 6039
Protoss_Assimilator 1 3257
Protoss_Cybernetics_Core 1 4123
Protoss_Zealot 1 4453
Protoss_Dragoon 10 9515
Protoss_Forge 1 6949
Protoss_Photon_Cannon 2 7882
Protoss_Robotics_Facility 1 8333
Protoss_Observatory 1 9700
Protoss_Shuttle 1 9829
9829
