Special_Protoss_Temple 14 0
Protoss_Nexus 3 8166
Protoss_Gateway 4 9683
Protoss_Assimilator 1 2283
Protoss_Cybernetics_Core 1 2937
Protoss_Dragoon 10 9895
Protoss_Robotics_Facility 1 8801
9895
