Protoss_Nexus 2 8013
Protoss_Gateway 2 6573
Protoss_Assimilator 2 2899
Protoss_Zealot 2 4111
Protoss_Cybernetics_Core 1 3927
Protoss_Dragoon 5 9575
Protoss_Citadel_of_Adun 1 6375
Protoss_Robotics_Facility 1 7019
Protoss_Templar_Archives 1 7437
Protoss_Shuttle 1 8299
Protoss_Dark_Templar 2 8589
Protoss_Observatory 1 9065
Protoss_Observer 1 9867
9867
