Protoss_Nexus 2 9623
Protoss_Gateway 2 6838
Protoss_Assimilator 1 2483
Protoss_Cybernetics_Core 1 3166
Protoss_Dragoon 9 8667
Protoss_Robotics_Facility 1 5422
Protoss_Observatory 1 6728
Protoss_Observer 2 7933
Protoss_Shuttle 1 9311
Protoss_Zealot 2 9946
9946
