Protoss_Nexus 1 0
Protoss_Gateway 2 9278
Protoss_Assimilator 1 2538
Protoss_Cybernetics_Core 1 2982
Protoss_Zealot 1 3251
Protoss_Dragoon 6 9176
Protoss_Robotics_Facility 1 4673
Protoss_Shuttle 1 5996
Protoss_Robotics_Support_Bay 1 6333
Protoss_Reaver 1 7176
Protoss_Observatory 1 8213
Protoss_Scarab 2 9028
Protoss_Observer 1 9356
9356
