Protoss_Nexus 3 8285
Protoss_Gateway 2 7319
Protoss_Assimilator 1 2707
Protoss_Zealot 1 3185
Protoss_Cybernetics_Core 1 3757
Protoss_Dragoon 8 9641
Protoss_Robotics_Facility 1 9269
9641
