Protoss_Nexus 3 9776
Protoss_Gateway 2 6614
Protoss_Assimilator 1 2254
Protoss_Cybernetics_Core 1 2963
Protoss_Dragoon 11 9255
Protoss_Robotics_Facility 1 5521
Protoss_Observatory 1 6883
Protoss_Observer 2 9843
Protoss_Citadel_of_Adun 1 9856
9856
