Protoss_Nexus 3 9588
Protoss_Gateway 2 3817
Protoss_Assimilator 2 8693
Protoss_Cybernetics_Core 1 4292
Protoss_Dragoon 7 9825
Protoss_Robotics_Facility 1 8567
Protoss_Observatory 1 9952
9952
