Special_Protoss_Temple 30 0
Protoss_Nexus 2 5939
Protoss_Gateway 2 6575
Protoss_Assimilator 2 8516
Protoss_Zealot 1 2809
Protoss_Cybernetics_Core 1 3661
Protoss_Dragoon 8 8573
Protoss_Citadel_of_Adun 1 6877
Protoss_Templar_Archives 1 7927
Protoss_Dark_Templar 2 9325
Protoss_Robotics_Facility 1 9507
9507
