Protoss_Nexus 1 0
Protoss_Gateway 2 9228
Protoss_Assimilator 1 2373
Protoss_Zealot 1 2869
Protoss_Cybernetics_Core 1 3647
Protoss_Dragoon 6 9159
Protoss_Robotics_Facility 2 6123
Protoss_Robotics_Support_Bay 1 6612
Protoss_Shuttle 1 6965
Protoss_Reaver 2 8119
Protoss_Scarab 3 9964
9964
