Protoss_Nexus 1 0
Protoss_Gateway 2 5989
Protoss_Assimilator 1 2501
Protoss_Cybernetics_Core 1 3082
Protoss_Zealot 1 3803
Protoss_Dragoon 11 9243
Protoss_Robotics_Facility 1 8059
Protoss_Observatory 1 9406
Protoss_Observer 1 9955
9955
