Protoss_Nexus 2 9327
Protoss_Gateway 3 6200
Protoss_Assimilator 1 2353
Protoss_Cybernetics_Core 1 2984
Protoss_Dragoon 5 8575
Protoss_Robotics_Facility 1 5429
Protoss_Citadel_of_Adun 1 6221
Protoss_Zealot 9 9446
9446
