Protoss_Nexus 2 8120
Protoss_Gateway 3 9703
Protoss_Assimilator 1 2513
Protoss_Cybernetics_Core 1 3270
Protoss_Dragoon 10 9593
Protoss_Robotics_Facility 1 5615
Protoss_Observatory 1 6921
Protoss_Observer 2 8141
Protoss_Shuttle 1 9163
Protoss_Zealot 1 9649
9703
