Protoss_Nexus 2 7784
Protoss_Gateway 2 6507
Protoss_Assimilator 1 2398
Protoss_Cybernetics_Core 1 2973
Protoss_Dragoon 7 9561
Protoss_Robotics_Facility 1 5538
Protoss_Observatory 1 6878
Protoss_Observer 1 7491
Protoss_Shuttle 1 8776
Protoss_Zealot 2 8916
9561
