Protoss_Nexus 2 6823
Protoss_Gateway 2 4719
Protoss_Assimilator 1 2658
Protoss_Cybernetics_Core 1 3412
Protoss_Dragoon 11 9646
Protoss_Robotics_Facility 1 7658
Protoss_Observatory 1 9123
Protoss_Observer 1 9896
9896
