Protoss_Nexus 2 6616
Protoss_Gateway 2 7192
Protoss_Assimilator 1 2223
Protoss_Cybernetics_Core 1 3000
Protoss_Zealot 1 3263
Protoss_Dragoon 9 9205
Protoss_Robotics_Facility 1 6918
Protoss_Observatory 1 8276
Protoss_Observer 1 8811
Protoss_Shuttle 1 9640
Protoss_Robotics_Support_Bay 1 9854
9854
