Protoss_Nexus 2 8498
Protoss_Gateway 3 9108
Protoss_Assimilator 1 2353
Protoss_Cybernetics_Core 1 2984
Protoss_Dragoon 4 9586
Protoss_Robotics_Facility 1 5413
Protoss_Zealot 3 8356
Protoss_Robotics_Support_Bay 1 7116
Protoss_Shuttle 1 7156
Protoss_Observatory 1 7315
Protoss_Reaver 1 8058
Protoss_Observer 1 9110
Protoss_Scarab 3 9865
9865
