Special_Protoss_Temple 30 0
Protoss_Nexus 2 7777
Protoss_Gateway 2 5514
Protoss_Assimilator 1 2333
Protoss_Cybernetics_Core 1 2875
Protoss_Dragoon 4 9485
Protoss_Citadel_of_Adun 1 4411
Protoss_Templar_Archives 1 5397
Protoss_Dark_Templar 5 8403
Protoss_Robotics_Facility 1 9993
9993
