Special_Protoss_Temple 14 0
Protoss_Nexus 1 0
Protoss_Gateway 2 4861
Protoss_Assimilator 1 2501
Protoss_Cybernetics_Core 1 3167
Protoss_Dragoon 11 9135
Protoss_Robotics_Facility 1 6201
Protoss_Shuttle 1 7591
Protoss_Observatory 1 8091
Protoss_Observer 1 8645
Protoss_Robotics_Support_Bay 1 8819
Protoss_Reaver 1 9443
9443
