Protoss_Nexus 1 0
Protoss_Gateway 3 7953
Protoss_Assimilator 1 2819
Protoss_Zealot 4 9006
Protoss_Cybernetics_Core 1 3981
Protoss_Dragoon 7 9946
Protoss_Robotics_Facility 1 6193
Protoss_Observatory 1 7590
Protoss_Shuttle 1 7826
9946
