Special_Protoss_Temple 14 0
Protoss_Nexus 1 0
Protoss_Gateway 2 7990
Protoss_Assimilator 1 2390
Protoss_Cybernetics_Core 1 3000
Protoss_Zealot 1 3327
Protoss_Dragoon 9 9721
Protoss_Robotics_Facility 1 6045
Protoss_Shuttle 1 7329
Protoss_Robotics_Support_Bay 1 7466
Protoss_Reaver 1 8231
Protoss_Observatory 1 8485
Protoss_Observer 2 9927
9927
