Protoss_Nexus 1 0
Protoss_Gateway 3 8143
Protoss_Assimilator 1 2658
Protoss_Cybernetics_Core 1 3233
Protoss_Dragoon 8 8508
Protoss_Robotics_Facility 1 5685
Protoss_Observatory 1 7024
Protoss_Observer 2 8463
Protoss_Shuttle 1 8906
Protoss_Robotics_Support_Bay 1 9058
Protoss_Reaver 1 9808
9808
