Protoss_Nexus 2 8378
Protoss_Assimilator 3 3439
Protoss_Gateway 2 9597
Protoss_Zealot 2 4191
Protoss_Cybernetics_Core 1 4598
Protoss_Dragoon 6 9405
Protoss_Robotics_Facility 1 5981
Protoss_Shuttle 1 7271
Protoss_Robotics_Support_Bay 1 7584
Protoss_Reaver 1 8187
9597
