Protoss_Nexus 3 8730
Protoss_Gateway 4 9368
Protoss_Assimilator 1 2473
Protoss_Cybernetics_Core 1 3038
Protoss_Robotics_Facility 1 4307
Protoss_Dragoon 6 9971
Protoss_Observatory 1 5838
Protoss_Observer 2 7941
9971
