Protoss_Nexus 2 8813
Protoss_Gateway 2 6473
Protoss_Assimilator 1 2834
Protoss_Zealot 2 3741
Protoss_Cybernetics_Core 1 3533
Protoss_Dragoon 7 9091
Protoss_Robotics_Facility 1 9624
9624
