Protoss_Nexus 3 9371
Protoss_Gateway 2 5937
Protoss_Assimilator 1 2372
Protoss_Cybernetics_Core 1 2945
Protoss_Dragoon 10 8887
Protoss_Robotics_Facility 1 5485
Protoss_Observatory 1 7027
Protoss_Observer 2 8661
9371
