Protoss_Nexus 1 0
Protoss_Gateway 2 3349
Protoss_Assimilator 1 2338
Protoss_Cybernetics_Core 1 2874
Protoss_Dragoon 10 8345
Protoss_Zealot 5 9667
Protoss_Robotics_Facility 2 9097
9667
