Protoss_Nexus 1 0
Protoss_Gateway 2 7257
Protoss_Assimilator 1 2271
Protoss_Cybernetics_Core 1 3035
Protoss_Dragoon 10 9839
Protoss_Robotics_Facility 1 4554
Protoss_Shuttle 1 5831
Protoss_Robotics_Support_Bay 1 6233
Protoss_Reaver 1 6765
Protoss_Observatory 1 7563
Protoss_Observer 1 8093
Protoss_Scarab 6 9963
9963
