Protoss_Nexus 2 8048
Protoss_Gateway 3 8278
Protoss_Assimilator 1 2598
Protoss_Cybernetics_Core 1 3143
Protoss_Dragoon 11 9558
Protoss_Robotics_Facility 1 9283
Protoss_Zealot 1 9886
9886
