Protoss_Nexus 2 7504
Protoss_Gateway 4 9073
Protoss_Assimilator 1 2399
Protoss_Cybernetics_Core 1 2942
Protoss_Dragoon 11 9659
Protoss_Zealot 1 6603
Protoss_Robotics_Facility 1 7606
Protoss_Observatory 1 8901
Protoss_Observer 1 9437
9659
