Special_Protoss_Temple 14 0
Protoss_Nexus 2 6945
Protoss_Gateway 2 7545
Protoss_Assimilator 2 8175
Protoss_Cybernetics_Core 1 2961
Protoss_Dragoon 9 9425
Protoss_Robotics_Facility 1 5647
Protoss_Observatory 1 7107
Protoss_Observer 3 9205
Protoss_Citadel_of_Adun 1 8033
Protoss_Stargate 1 9555
Protoss_Templar_Archives 1 9977
9977
