Protoss_Nexus 1 0
Protoss_Gateway 2 5964
Protoss_Assimilator 1 2614
Protoss_Zealot 2 8633
Protoss_Cybernetics_Core 1 3561
Protoss_Dragoon 8 9381
Protoss_Robotics_Facility 1 6728
Protoss_Shuttle 1 8161
Protoss_Observatory 1 8562
Protoss_Observer 1 9396
9396
