Protoss_Nexus 1 0
Protoss_Gateway 3 7178
Protoss_Assimilator 1 2478
Protoss_Cybernetics_Core 1 3055
Protoss_Dragoon 8 8631
Protoss_Robotics_Facility 1 5568
Protoss_Observatory 1 6863
Protoss_Observer 2 8071
Protoss_Shuttle 1 9246
Protoss_Zealot 2 9651
9651
