Protoss_Nexus 2 7792
Protoss_Gateway 2 8873
Protoss_Zealot 3 4657
Protoss_Assimilator 1 4008
Protoss_Cybernetics_Core 1 4581
Protoss_Dragoon 7 9933
Protoss_Robotics_Facility 1 8272
Protoss_Shuttle 1 9711
Protoss_Robotics_Support_Bay 1 9820
9933
