Special_Protoss_Temple 30 0
Protoss_Nexus 2 8064
Protoss_Gateway 3 9422
Protoss_Assimilator 1 2189
Protoss_Cybernetics_Core 1 2833
Protoss_Dragoon 4 5465
Protoss_Citadel_of_Adun 1 5284
Protoss_Zealot 1 6235
Protoss_Templar_Archives 1 6355
Protoss_Dark_Templar 5 9546
Protoss_Robotics_Facility 1 9877
9877
