Protoss_Nexus 1 0
Protoss_Gateway 2 7782
Protoss_Assimilator 1 2326
Protoss_Cybernetics_Core 1 2874
Protoss_Dragoon 9 9519
Protoss_Robotics_Facility 1 4387
Protoss_Shuttle 1 5673
Protoss_Robotics_Support_Bay 1 6113
Protoss_Reaver 1 6837
Protoss_Observatory 1 7889
Protoss_Zealot 1 8023
Protoss_Scarab 7 9127
Protoss_Observer 1 8729
9519
