Protoss_Nexus 2 6905
Protoss_Gateway 2 7282
Protoss_Assimilator 1 2462
Protoss_Cybernetics_Core 1 3191
Protoss_Dragoon 11 9979
Protoss_Robotics_Facility 1 5544
Protoss_Observatory 1 7001
Protoss_Observer 3 9675
9979
