Protoss_Nexus 2 9857
Protoss_Gateway 2 8485
Protoss_Assimilator 1 2225
Protoss_Cybernetics_Core 1 3031
Protoss_Zealot 2 7445
Protoss_Robotics_Facility 1 4213
Protoss_Dragoon 4 9479
Protoss_Shuttle 1 5621
Protoss_Robotics_Support_Bay 1 5662
Protoss_Reaver 1 6571
Protoss_Observatory 1 7195
Protoss_Scarab 11 9950
Protoss_Observer 1 8363
9950
