Protoss_Nexus 2 7485
Protoss_Gateway 4 9572
Protoss_Assimilator 1 2395
Protoss_Cybernetics_Core 1 3072
Protoss_Dragoon 5 9921
Protoss_Citadel_of_Adun 1 4380
Protoss_Templar_Archives 1 5486
Protoss_Dark_Templar 5 8583
Protoss_Robotics_Facility 1 9634
9921
