Protoss_Nexus 2 8581
Protoss_Gateway 2 4969
Protoss_Assimilator 1 2279
Protoss_Cybernetics_Core 1 2872
Protoss_Dragoon 9 9693
Protoss_Robotics_Facility 1 5539
Protoss_Shuttle 1 7019
Protoss_Robotics_Support_Bay 1 7158
Protoss_Zealot 2 7643
Protoss_Reaver 2 9363
Protoss_Scarab 5 9954
9954
