Protoss_Nexus 2 6671
Protoss_Gateway 2 4435
Protoss_Assimilator 1 2381
Protoss_Cybernetics_Core 1 3015
Protoss_Dragoon 12 9417
Protoss_Robotics_Facility 1 7887
Protoss_Observatory 1 9343
Protoss_Observer 1 9993
9993
