Protoss_Nexus 2 7011
Protoss_Gateway 3 8385
Protoss_Assimilator 1 2215
Protoss_Cybernetics_Core 1 2890
Protoss_Dragoon 10 9873
Protoss_Robotics_Facility 1 5816
Protoss_Observatory 1 7169
Protoss_Observer 4 9501
9873
