Protoss_Nexus 3 8879
Protoss_Gateway 4 9269
Protoss_Assimilator 1 2266
Protoss_Cybernetics_Core 1 2875
Protoss_Dragoon 10 9683
Protoss_Robotics_Facility 1 5333
Protoss_Observatory 1 6845
Protoss_Robotics_Support_Bay 1 6889
Protoss_Observer 3 9983
9983
