Protoss_Nexus 2 7086
Protoss_Gateway 1 1936
Protoss_Assimilator 1 2406
Protoss_Cybernetics_Core 1 3031
Protoss_Dragoon 8 9543
Protoss_Robotics_Facility 1 5423
Protoss_Observatory 1 6738
Protoss_Observer 1 7655
Protoss_Shuttle 1 8257
Protoss_Robotics_Support_Bay 1 8569
Protoss_Reaver 1 9159
Protoss_Citadel_of_Adun 1 9515
9543
