Protoss_Nexus 3 9974
Protoss_Gateway 2 7104
Protoss_Assimilator 2 9017
Protoss_Cybernetics_Core 1 2915
Protoss_Zealot 1 3159
Protoss_Dragoon 3 8447
Protoss_Citadel_of_Adun 1 4258
Protoss_Templar_Archives 1 5324
Protoss_Dark_Templar 2 7137
Protoss_Stargate 1 6863
Protoss_Arbiter_Tribunal 1 8388
Protoss_Arbiter 1 9867
9974
