Protoss_Nexus 2 6021
Protoss_Gateway 2 9815
Protoss_Assimilator 2 8782
Protoss_Cybernetics_Core 1 2961
Protoss_Dragoon 6 8221
Protoss_Robotics_Facility 2 7197
Protoss_Observatory 1 8204
Protoss_Robotics_Support_Bay 1 8527
Protoss_Observer 1 8775
Protoss_Shuttle 1 8899
Protoss_Reaver 2 9989
9989
