Protoss_Nexus 2 7715
Protoss_Gateway 3 8703
Protoss_Assimilator 1 2342
Protoss_Cybernetics_Core 1 2919
Protoss_Dragoon 10 9707
Protoss_Robotics_Facility 1 5345
Protoss_Observatory 1 6647
Protoss_Observer 2 8355
Protoss_Shuttle 1 8957
Protoss_Zealot 3 9831
9831
