Protoss_Nexus 3 7889
Special_Protoss_Temple 30 0
Protoss_Gateway 2 4541
Protoss_Assimilator 2 9456
Protoss_Cybernetics_Core 1 2954
Protoss_Dragoon 8 9197
Protoss_Citadel_of_Adun 1 7317
Protoss_Templar_Archives 1 8765
Protoss_Dark_Templar 1 9943
9943
