Protoss_Nexus 1 0
Protoss_Gateway 3 6433
Protoss_Assimilator 2 3227
Protoss_Zealot 5 9666
Protoss_Cybernetics_Core 1 4878
Protoss_Dragoon 6 8273
Protoss_Citadel_of_Adun 1 7248
Protoss_Robotics_Facility 1 8873
Protoss_Templar_Archives 1 9768
9768
