Protoss_Nexus 2 8269
Protoss_Gateway 2 2172
Protoss_Zealot 3 3431
Protoss_Assimilator 1 4061
Protoss_Cybernetics_Core 1 4523
Protoss_Dragoon 8 9306
Protoss_Robotics_Facility 1 8958
9306
