Protoss_Nexus 1 0
Protoss_Gateway 4 7317
Protoss_Assimilator 3 4509
Protoss_Zealot 6 5977
Protoss_Cybernetics_Core 1 5066
Protoss_Dragoon 10 9923
Protoss_Robotics_Facility 1 8420
Protoss_Shuttle 1 9705
9923
