Protoss_Nexus 3 9487
Protoss_Gateway 2 5459
Protoss_Assimilator 1 2302
Protoss_Cybernetics_Core 1 2985
Protoss_Dragoon 10 9791
Protoss_Robotics_Facility 1 6583
Protoss_Observatory 1 7997
Protoss_Observer 3 9765
9791
