Special_Protoss_Temple 14 0
Protoss_Nexus 2 7431
Protoss_Gateway 3 9588
Protoss_Assimilator 1 2259
Protoss_Cybernetics_Core 1 2899
Protoss_Dragoon 9 9327
Protoss_Robotics_Facility 1 5712
Protoss_Observatory 1 7075
Protoss_Observer 3 8861
9588
