Protoss_Nexus 3 7968
Protoss_Gateway 2 8596
Protoss_Assimilator 1 2175
Protoss_Zealot 1 2835
Protoss_Cybernetics_Core 1 3117
Protoss_Dragoon 9 9603
Protoss_Robotics_Facility 1 8083
Protoss_Shuttle 1 9379
Protoss_Robotics_Support_Bay 1 9447
9603
