Protoss_Nexus 3 7365
Protoss_Gateway 2 5268
Protoss_Assimilator 1 2359
Protoss_Cybernetics_Core 1 2983
Protoss_Dragoon 9 8859
Protoss_Robotics_Facility 1 8094
Protoss_Shuttle 1 9395
Protoss_Zealot 2 9637
Protoss_Observatory 1 9662
9662
