Protoss_Nexus 1 0
Protoss_Gateway 2 7793
Protoss_Forge 1 2670
Protoss_Zealot 3 5160
Protoss_Assimilator 1 5039
Protoss_Photon_Cannon 3 9728
Protoss_Cybernetics_Core 1 5576
Protoss_Dragoon 2 9406
Protoss_Citadel_of_Adun 1 7243
Protoss_Robotics_Facility 1 7608
Protoss_Templar_Archives 1 8592
Protoss_Shuttle 1 8911
9728
