Protoss_Nexus 3 9957
Protoss_Gateway 2 7689
Protoss_Assimilator 1 2754
Protoss_Cybernetics_Core 1 3648
Protoss_Zealot 1 3899
Protoss_Dragoon 9 9765
Protoss_Robotics_Facility 1 7205
Protoss_Observatory 1 8487
Protoss_Observer 2 9859
9957
