Protoss_Nexus 2 7383
Protoss_Gateway 2 9005
Protoss_Assimilator 1 2335
Protoss_Cybernetics_Core 1 2875
Protoss_Zealot 1 3205
Protoss_Dragoon 6 9245
Protoss_Robotics_Facility 1 5723
Protoss_Shuttle 1 7011
Protoss_Robotics_Support_Bay 1 7648
Protoss_Reaver 1 8177
Protoss_Observatory 1 9655
9655
