Protoss_Nexus 1 0
Protoss_Gateway 2 4352
Protoss_Assimilator 1 2489
Protoss_Cybernetics_Core 1 3081
Protoss_Zealot 4 5534
Protoss_Dragoon 3 9129
Protoss_Forge 1 6391
9129
