Protoss_Nexus 2 9164
Protoss_Gateway 2 5695
Protoss_Zealot 3 4213
Protoss_Assimilator 1 3041
Protoss_Cybernetics_Core 1 3960
Protoss_Dragoon 10 9717
Protoss_Robotics_Facility 1 7200
Protoss_Observatory 1 8605
Protoss_Observer 2 9949
9949
