Protoss_Nexus 3 7069
Protoss_Gateway 4 8630
Protoss_Assimilator 1 2241
Protoss_Cybernetics_Core 1 2933
Protoss_Dragoon 12 9953
Protoss_Robotics_Facility 1 7906
Protoss_Observatory 1 9600
9953
