Protoss_Nexus 2 7502
Protoss_Gateway 2 4259
Protoss_Assimilator 2 7982
Protoss_Zealot 13 9671
Protoss_Forge 1 6964
Protoss_Photon_Cannon 2 9885
Protoss_Cybernetics_Core 1 8517
Protoss_Robotics_Facility 1 9765
9885
