Protoss_Nexus 2 2769
Protoss_Gateway 3 8059
Protoss_Assimilator 2 5978
Protoss_Cybernetics_Core 1 4201
Protoss_Zealot 1 4641
Protoss_Dragoon 14 9937
Protoss_Robotics_Facility 1 7286
Protoss_Observatory 1 8588
Protoss_Observer 2 9839
9937
