Protoss_Nexus 2 9671
Protoss_Gateway 2 5666
Protoss_Assimilator 1 2513
Protoss_Cybernetics_Core 1 3125
Protoss_Dragoon 5 9183
Protoss_Citadel_of_Adun 1 5170
Protoss_Templar_Archives 1 6159
Protoss_Zealot 2 6771
Protoss_Dark_Templar 4 8147
9671
