Protoss_Nexus 2 7129
Protoss_Gateway 2 4433
Protoss_Assimilator 1 2330
Protoss_Cybernetics_Core 1 2911
Protoss_Dragoon 12 9995
Protoss_Robotics_Facility 1 5352
Protoss_Observatory 1 6858
Protoss_Observer 2 8073
9995
