Special_Protoss_Temple 14 0
Protoss_Nexus 2 2723
Protoss_Gateway 4 9881
Protoss_Assimilator 2 8205
Protoss_Cybernetics_Core 1 4083
Protoss_Zealot 1 4695
Protoss_Dragoon 12 9777
Protoss_Robotics_Facility 1 7281
Protoss_Observatory 1 8601
Protoss_Observer 1 9133
9881
