Protoss_Nexus 1 0
Protoss_Assimilator 5 3995
Protoss_Gateway 2 5277
Protoss_Cybernetics_Core 1 3569
Protoss_Robotics_Facility 1 4713
Protoss_Dragoon 6 9307
Protoss_Zealot 2 7145
Protoss_Shuttle 1 6027
Protoss_Robotics_Support_Bay 1 6513
Protoss_Reaver 1 7077
Protoss_Citadel_of_Adun 1 7759
Protoss_Scarab 7 9993
Protoss_Templar_Archives 1 9105
9993
