Protoss_Nexus 1 0
Protoss_Gateway 3 9426
Protoss_Assimilator 1 2368
Protoss_Cybernetics_Core 1 3249
Protoss_Dragoon 1 4271
Protoss_Citadel_of_Adun 1 4554
Protoss_Templar_Archives 1 5626
Protoss_Dark_Templar 9 9926
Protoss_Forge 1 7373
Protoss_Photon_Cannon 1 9293
9926
