Protoss_Nexus 2 7307
Protoss_Gateway 2 4263
Protoss_Zealot 2 3369
Protoss_Assimilator 2 8513
Protoss_Cybernetics_Core 1 3831
Protoss_Dragoon 5 6575
Protoss_Citadel_of_Adun 1 7623
Protoss_Robotics_Facility 1 8027
Protoss_Templar_Archives 1 8685
Protoss_Shuttle 1 9535
Protoss_Dark_Templar 2 9701
Protoss_Observatory 1 9899
9899
