Protoss_Nexus 2 9573
Protoss_Gateway 2 8213
Protoss_Assimilator 1 2422
Protoss_Cybernetics_Core 1 2950
Protoss_Dragoon 7 9995
Protoss_Robotics_Facility 1 5313
Protoss_Shuttle 1 6675
Protoss_Observatory 1 6860
Protoss_Robotics_Support_Bay 1 6959
Protoss_Zealot 2 7755
Protoss_Reaver 1 7746
Protoss_Observer 1 8940
Protoss_Scarab 5 9914
9995
