Protoss_Nexus 2 8367
Protoss_Gateway 2 8855
Protoss_Assimilator 1 2313
Protoss_Zealot 2 7019
Protoss_Cybernetics_Core 1 3588
Protoss_Dragoon 7 9919
Protoss_Robotics_Facility 1 5658
Protoss_Shuttle 1 6955
Protoss_Robotics_Support_Bay 1 7111
Protoss_Reaver 1 7857
Protoss_Observatory 1 8753
Protoss_Scarab 1 9386
Protoss_Observer 1 9619
9919
