Protoss_Nexus 2 6415
Protoss_Gateway 3 8064
Protoss_Assimilator 1 2195
Protoss_Cybernetics_Core 1 2977
Protoss_Dragoon 10 9799
Protoss_Robotics_Facility 1 7941
Protoss_Zealot 2 9041
Protoss_Observatory 1 9801
9801
