Protoss_Nexus 2 8589
Protoss_Gateway 3 9310
Protoss_Assimilator 1 2337
Protoss_Cybernetics_Core 1 2960
Protoss_Dragoon 6 9017
Protoss_Robotics_Facility 1 4327
Protoss_Shuttle 1 5875
Protoss_Zealot 2 7595
Protoss_Observatory 1 6669
Protoss_Observer 2 9469
Protoss_Robotics_Support_Bay 1 7322
Protoss_Reaver 1 7993
9469
