Protoss_Nexus 2 7685
Protoss_Gateway 2 5945
Protoss_Assimilator 1 2228
Protoss_Cybernetics_Core 1 2903
Protoss_Dragoon 10 8999
Protoss_Robotics_Facility 1 5412
Protoss_Observatory 1 6763
Protoss_Observer 1 7337
Protoss_Shuttle 1 8937
Protoss_Robotics_Support_Bay 1 9276
Protoss_Reaver 1 9839
9839
