Protoss_Nexus 2 6725
Protoss_Gateway 2 4391
Protoss_Assimilator 1 2326
Protoss_Cybernetics_Core 1 2851
Protoss_Dragoon 12 9791
Protoss_Robotics_Facility 1 7572
Protoss_Observatory 1 8918
Protoss_Observer 1 9447
9791
