Protoss_Nexus 1 0
Protoss_Gateway 1 2017
Protoss_Assimilator 1 2615
Protoss_Zealot 3 4355
Protoss_Cybernetics_Core 1 3517
Protoss_Dragoon 6 9793
Protoss_Robotics_Facility 1 5786
Protoss_Robotics_Support_Bay 1 7102
Protoss_Reaver 2 8975
9793
