Protoss_Nexus 2 6320
Protoss_Gateway 2 7377
Protoss_Assimilator 2 9853
Protoss_Cybernetics_Core 1 3139
Protoss_Zealot 1 3339
Protoss_Dragoon 8 9559
Protoss_Robotics_Facility 1 6814
Protoss_Shuttle 1 8573
Protoss_Observatory 1 8719
Protoss_Robotics_Support_Bay 1 9257
Protoss_Observer 1 9475
9853
