Special_Protoss_Temple 14 0
Protoss_Nexus 3 9993
Protoss_Gateway 1 1881
Protoss_Assimilator 1 2303
Protoss_Cybernetics_Core 1 2959
Protoss_Dragoon 7 9283
Protoss_Robotics_Facility 1 6031
Protoss_Shuttle 1 7381
Protoss_Robotics_Support_Bay 1 7395
Protoss_Reaver 2 9335
9993
