Protoss_Nexus 2 8621
Protoss_Gateway 2 6331
Protoss_Assimilator 1 2175
Protoss_Cybernetics_Core 1 2815
Protoss_Dragoon 5 9185
Protoss_Citadel_of_Adun 2 5096
Protoss_Robotics_Facility 1 6003
Protoss_Templar_Archives 1 6255
Protoss_Zealot 1 6509
Protoss_Dark_Templar 3 8211
Protoss_Shuttle 1 7437
Protoss_Observatory 1 7774
9185
