Protoss_Nexus 3 9150
Protoss_Gateway 3 9672
Protoss_Assimilator 2 9694
Protoss_Cybernetics_Core 1 3105
Protoss_Dragoon 11 9951
Protoss_Robotics_Facility 1 6283
Protoss_Observatory 1 7797
Protoss_Observer 3 9772
9951
