Protoss_Nexus 3 9403
Protoss_Gateway 2 5742
Protoss_Assimilator 2 9891
Protoss_Cybernetics_Core 1 2991
Protoss_Dragoon 8 8069
Protoss_Robotics_Facility 1 5483
Protoss_Observatory 1 6927
Protoss_Observer 2 8117
Protoss_Citadel_of_Adun 1 8725
Protoss_Templar_Archives 1 9766
9891
