Protoss_Nexus 3 5925
Protoss_Gateway 5 9723
Protoss_Assimilator 2 6832
Protoss_Cybernetics_Core 1 4236
Protoss_Dragoon 7 9405
Protoss_Citadel_of_Adun 1 6661
Protoss_Templar_Archives 1 7653
Protoss_Stargate 1 8482
Protoss_Dark_Templar 2 8643
Protoss_Forge 1 9351
9723
