Special_Protoss_Temple 14 0
Protoss_Nexus 2 8193
Protoss_Gateway 3 9506
Protoss_Assimilator 1 2248
Protoss_Cybernetics_Core 1 3021
Protoss_Dragoon 8 9327
Protoss_Robotics_Facility 1 6211
Protoss_Shuttle 1 7555
Protoss_Robotics_Support_Bay 1 8076
Protoss_Reaver 2 9923
9923
