Protoss_Nexus 2 4254
Protoss_Gateway 3 7915
Protoss_Assimilator 2 5275
Protoss_Zealot 4 6087
Protoss_Cybernetics_Core 1 5828
Protoss_Shield_Battery 1 6828
Protoss_Dragoon 6 9807
Protoss_Robotics_Facility 1 8863
9807
