Special_Protoss_Temple 30 0
Protoss_Nexus 3 7985
Protoss_Gateway 4 9158
Protoss_Assimilator 1 2360
Protoss_Cybernetics_Core 1 2991
Protoss_Dragoon 8 9875
Protoss_Robotics_Facility 1 6725
Protoss_Observatory 1 8061
Protoss_Observer 3 9891
Protoss_Shuttle 1 9967
9967
