Protoss_Nexus 2 8149
Protoss_Gateway 2 5095
Protoss_Assimilator 1 2353
Protoss_Cybernetics_Core 1 3045
Protoss_Dragoon 5 8503
Protoss_Citadel_of_Adun 1 5346
Protoss_Templar_Archives 1 6460
Protoss_Dark_Templar 4 9659
9659
