Special_Protoss_Temple 30 0
Protoss_Nexus 3 8607
Protoss_Gateway 2 4249
Protoss_Assimilator 1 3263
Protoss_Cybernetics_Core 1 4009
Protoss_Zealot 3 9745
Protoss_Dragoon 6 7499
Protoss_Robotics_Facility 1 6690
Protoss_Shuttle 1 8063
Protoss_Robotics_Support_Bay 1 8817
Protoss_Reaver 1 9345
9745
