Protoss_Nexus 2 8083
Protoss_Gateway 3 9736
Protoss_Zealot 4 7355
Protoss_Assimilator 1 3123
Protoss_Cybernetics_Core 1 4120
Protoss_Dragoon 10 9427
Protoss_Robotics_Facility 1 8758
9736
