Protoss_Nexus 2 2841
Protoss_Gateway 3 6394
Protoss_Assimilator 2 8869
Protoss_Cybernetics_Core 1 4067
Protoss_Zealot 2 9465
Protoss_Dragoon 12 9783
Protoss_Robotics_Facility 1 8664
Protoss_Observatory 1 9995
9995
