Protoss_Nexus 2 9168
Protoss_Gateway 2 7588
Protoss_Assimilator 1 2667
Protoss_Cybernetics_Core 1 3254
Protoss_Zealot 1 3446
Protoss_Dragoon 9 9739
Protoss_Robotics_Facility 1 5792
Protoss_Observatory 1 7123
Protoss_Observer 2 8681
9739
