Protoss_Nexus 3 9945
Protoss_Gateway 2 6497
Protoss_Assimilator 2 9646
Protoss_Cybernetics_Core 1 2857
Protoss_Dragoon 8 9311
Protoss_Citadel_of_Adun 1 5435
Protoss_Templar_Archives 1 6439
Protoss_Dark_Templar 2 7487
Protoss_Stargate 1 9022
9945
