Special_Protoss_Temple 30 0
Protoss_Nexus 3 8069
Protoss_Gateway 4 9558
Protoss_Assimilator 1 2358
Protoss_Cybernetics_Core 1 2874
Protoss_Dragoon 6 8361
Protoss_Robotics_Facility 1 7311
Protoss_Observatory 1 8781
Protoss_Observer 1 9339
9558
