Protoss_Nexus 3 8587
Protoss_Gateway 2 6087
Protoss_Assimilator 2 9567
Protoss_Cybernetics_Core 1 2960
Protoss_Dragoon 10 9767
Protoss_Robotics_Facility 1 5831
Protoss_Observatory 1 7161
Protoss_Observer 2 9697
9767
