Protoss_Nexus 2 6396
Protoss_Gateway 3 7499
Protoss_Assimilator 2 9391
Protoss_Cybernetics_Core 1 2905
Protoss_Dragoon 9 8783
Protoss_Robotics_Facility 1 6711
Protoss_Citadel_of_Adun 1 7782
Protoss_Observatory 1 8252
Protoss_Observer 1 8851
Protoss_Templar_Archives 1 9297
9391
