Protoss_Nexus 2 7183
Protoss_Gateway 3 8862
Protoss_Assimilator 1 2347
Protoss_Cybernetics_Core 1 2845
Protoss_Dragoon 10 9411
Protoss_Robotics_Facility 1 5225
Protoss_Observatory 1 6557
Protoss_Observer 3 8709
9411
