Special_Protoss_Temple 30 0
Protoss_Nexus 2 7447
Protoss_Gateway 3 9285
Protoss_Assimilator 1 2226
Protoss_Cybernetics_Core 1 2944
Protoss_Dragoon 10 9215
Protoss_Robotics_Facility 1 8388
Protoss_Observatory 1 9711
9711
