Protoss_Nexus 2 9039
Protoss_Gateway 3 9735
Protoss_Assimilator 2 2659
Protoss_Zealot 2 7769
Protoss_Cybernetics_Core 1 3576
Protoss_Dragoon 5 9521
Protoss_Robotics_Facility 1 6086
Protoss_Shuttle 1 7397
Protoss_Robotics_Support_Bay 1 7717
Protoss_Reaver 1 8309
Protoss_Observatory 1 9347
Protoss_Observer 1 9905
9905
