Special_Protoss_Temple 30 0
Protoss_Nexus 3 9521
Protoss_Gateway 2 5983
Protoss_Assimilator 1 2392
Protoss_Cybernetics_Core 1 2977
Protoss_Dragoon 10 8799
Protoss_Robotics_Facility 1 5389
Protoss_Observatory 1 6962
Protoss_Observer 2 8381
Protoss_Citadel_of_Adun 1 9981
9981
