Protoss_Nexus 3 8667
Protoss_Gateway 2 5795
Protoss_Assimilator 1 2224
Protoss_Cybernetics_Core 1 2838
Protoss_Dragoon 6 7369
Protoss_Robotics_Facility 1 5628
Protoss_Observatory 1 7089
Protoss_Observer 1 7629
Protoss_Shuttle 1 8319
Protoss_Robotics_Support_Bay 1 8899
Protoss_Reaver 1 9435
Protoss_Zealot 2 9661
9661
