Protoss_Nexus 2 8577
Protoss_Gateway 2 5595
Protoss_Assimilator 1 2446
Protoss_Cybernetics_Core 1 3091
Protoss_Dragoon 7 9931
Protoss_Citadel_of_Adun 1 5400
Protoss_Templar_Archives 1 6383
Protoss_Zealot 2 6643
Protoss_Dark_Templar 4 8187
9931
