Protoss_Nexus 2 8726
Protoss_Gateway 2 6417
Protoss_Assimilator 1 2432
Protoss_Cybernetics_Core 1 3247
Protoss_Dragoon 11 9818
Protoss_Robotics_Facility 1 5765
Protoss_Observatory 1 7156
Protoss_Observer 3 8995
9818
