Protoss_Nexus 2 8348
Protoss_Gateway 6 9483
Protoss_Assimilator 1 2478
Protoss_Cybernetics_Core 1 3163
Protoss_Dragoon 8 8561
Protoss_Robotics_Facility 1 4584
Protoss_Observatory 1 6043
Protoss_Observer 4 9401
9483
