Special_Protoss_Temple 14 0
Protoss_Nexus 3 8572
Protoss_Gateway 4 9671
Protoss_Assimilator 1 2483
Protoss_Cybernetics_Core 1 3043
Protoss_Dragoon 9 9809
Protoss_Robotics_Facility 1 5511
Protoss_Observatory 1 7160
Protoss_Observer 4 9945
9945
