Protoss_Nexus 2 4157
Protoss_Gateway 3 8979
Protoss_Assimilator 2 8033
Protoss_Cybernetics_Core 1 2993
Protoss_Dragoon 10 8621
Protoss_Robotics_Facility 1 7271
Protoss_Observatory 1 8575
Protoss_Shuttle 1 8817
Protoss_Zealot 2 9373
Protoss_Observer 1 9719
9719
