Special_Protoss_Temple 30 0
Protoss_Nexus 3 8265
Protoss_Gateway 4 9921
Protoss_Assimilator 1 2191
Protoss_Cybernetics_Core 1 2840
Protoss_Dragoon 8 9405
Protoss_Robotics_Facility 1 5606
Protoss_Observatory 1 6899
Protoss_Observer 4 9395
9921
