Protoss_Nexus 1 0
Protoss_Gateway 5 4420
Protoss_Assimilator 1 4665
Protoss_Cybernetics_Core 1 5412
Protoss_Zealot 2 5991
Protoss_Dragoon 8 9357
Protoss_Robotics_Facility 1 8594
Protoss_Shuttle 1 9969
9969
