Special_Protoss_Temple 30 0
Protoss_Nexus 2 8638
Protoss_Gateway 3 9838
Protoss_Assimilator 1 2256
Protoss_Cybernetics_Core 1 2925
Protoss_Dragoon 11 9433
Protoss_Robotics_Facility 1 6279
Protoss_Observatory 1 7611
Protoss_Observer 3 9737
9838
