Protoss_Nexus 2 2629
Protoss_Gateway 5 9504
Protoss_Assimilator 2 7190
Protoss_Cybernetics_Core 1 3950
Protoss_Zealot 3 9925
Protoss_Dragoon 12 9345
Protoss_Robotics_Facility 1 7774
Protoss_Citadel_of_Adun 1 9185
Protoss_Observatory 1 9283
Protoss_Observer 1 9883
9925
