Protoss_Nexus 2 2721
Protoss_Gateway 3 9041
Protoss_Assimilator 2 6208
Protoss_Cybernetics_Core 1 4123
Protoss_Zealot 1 4615
Protoss_Dragoon 10 9617
Protoss_Robotics_Facility 1 7425
Protoss_Citadel_of_Adun 1 8675
Protoss_Observatory 1 8828
Protoss_Observer 1 9371
Protoss_Templar_Archives 1 9952
9952
