Protoss_Nexus 4 9519
Protoss_Gateway 2 3872
Protoss_Assimilator 2 5590
Protoss_Cybernetics_Core 1 4201
Protoss_Dragoon 6 6745
Protoss_Citadel_of_Adun 1 6947
Protoss_Templar_Archives 1 8190
Protoss_Stargate 2 9993
Protoss_Dark_Templar 2 9319
Protoss_Arbiter_Tribunal 1 9916
9993
