Protoss_Nexus 2 8030
Protoss_Gateway 4 9540
Protoss_Assimilator 1 2281
Protoss_Cybernetics_Core 1 2899
Protoss_Zealot 1 3257
Protoss_Dragoon 7 9279
Protoss_Citadel_of_Adun 1 4821
Protoss_Templar_Archives 1 5829
Protoss_Dark_Templar 2 7023
Protoss_Robotics_Facility 1 9059
9540
