Special_Protoss_Temple 14 0
Protoss_Nexus 2 7439
Protoss_Gateway 4 9284
Protoss_Assimilator 2 2703
Protoss_Cybernetics_Core 1 3361
Protoss_Dragoon 9 9869
Protoss_Robotics_Facility 1 7858
Protoss_Shuttle 1 9159
Protoss_Observatory 1 9616
9869
