Protoss_Nexus 2 7695
Protoss_Gateway 2 6131
Protoss_Assimilator 1 2427
Protoss_Cybernetics_Core 1 2902
Protoss_Dragoon 8 9637
Protoss_Robotics_Facility 1 5667
Protoss_Observatory 1 6961
Protoss_Observer 2 9123
Protoss_Shuttle 1 8221
Protoss_Robotics_Support_Bay 1 8726
Protoss_Reaver 1 9363
9637
