Protoss_Nexus 2 9198
Protoss_Gateway 3 5943
Protoss_Assimilator 1 2517
Protoss_Cybernetics_Core 1 3463
Protoss_Dragoon 4 9976
Protoss_Citadel_of_Adun 1 4758
Protoss_Templar_Archives 1 6148
Protoss_Dark_Templar 6 9371
9976
