Special_Protoss_Temple 14 0
Protoss_Nexus 2 7711
Protoss_Gateway 2 4595
Protoss_Assimilator 1 2229
Protoss_Cybernetics_Core 1 2911
Protoss_Dragoon 13 9903
Protoss_Robotics_Facility 1 8471
9903
