Protoss_Nexus 2 2741
Protoss_Gateway 3 8566
Protoss_Assimilator 2 7182
Protoss_Cybernetics_Core 1 4219
Protoss_Zealot 1 4467
Protoss_Dragoon 7 8633
Protoss_Citadel_of_Adun 1 6793
Protoss_Templar_Archives 1 7781
Protoss_Robotics_Facility 1 8421
Protoss_Dark_Templar 4 9521
Protoss_Forge 1 9454
Protoss_Observatory 1 9891
9891
