Protoss_Nexus 2 6543
Protoss_Gateway 2 7651
Protoss_Assimilator 2 8717
Protoss_Cybernetics_Core 1 2915
Protoss_Zealot 1 3219
Protoss_Dragoon 8 8971
Protoss_Citadel_of_Adun 1 7227
Protoss_Templar_Archives 1 8323
Protoss_Robotics_Facility 1 8422
Protoss_Dark_Templar 2 9739
Protoss_Shuttle 1 9707
Protoss_Observatory 1 9952
9952
