Protoss_Nexus 2 9188
Protoss_Gateway 3 7968
Protoss_Assimilator 1 2508
Protoss_Cybernetics_Core 1 3083
Protoss_Dragoon 9 9921
Protoss_Robotics_Facility 1 4657
Protoss_Observatory 1 5994
Protoss_Observer 2 7196
9921
