Protoss_Nexus 2 8155
Protoss_Gateway 3 9238
Protoss_Assimilator 1 2223
Protoss_Cybernetics_Core 1 2829
Protoss_Dragoon 6 9459
Protoss_Robotics_Facility 1 5261
Protoss_Shuttle 1 6551
Protoss_Robotics_Support_Bay 1 7052
Protoss_Reaver 1 7833
Protoss_Zealot 2 9417
Protoss_Observatory 1 8535
Protoss_Observer 2 9689
Protoss_Scarab 2 9973
9973
