Protoss_Nexus 2 9403
Protoss_Gateway 2 7125
Protoss_Assimilator 1 2629
Protoss_Cybernetics_Core 1 3228
Protoss_Zealot 2 8221
Protoss_Dragoon 4 7391
Protoss_Robotics_Facility 1 6015
Protoss_Citadel_of_Adun 1 7190
Protoss_Observatory 1 7313
Protoss_Observer 1 7851
Protoss_Templar_Archives 1 8433
Protoss_Shuttle 1 9126
Protoss_Dark_Templar 2 9606
9606
