Special_Protoss_Temple 30 0
Protoss_Nexus 2 9633
Protoss_Gateway 2 3682
Protoss_Assimilator 2 2492
Protoss_Cybernetics_Core 1 3200
Protoss_Dragoon 5 6191
Protoss_Citadel_of_Adun 1 5993
Protoss_Templar_Archives 1 7213
Protoss_Robotics_Facility 1 7657
Protoss_Dark_Templar 4 9539
Protoss_Shuttle 1 8973
9633
