Protoss_Nexus 2 3763
Protoss_Gateway 3 7010
Protoss_Zealot 1 2843
Protoss_Assimilator 2 5868
Protoss_Cybernetics_Core 1 4519
Protoss_Dragoon 9 9445
Protoss_Robotics_Facility 1 7170
Protoss_Observatory 1 8527
Protoss_Shuttle 1 8629
Protoss_Observer 1 9531
9531
