Protoss_Nexus 2 7129
Protoss_Gateway 4 8266
Protoss_Assimilator 1 2189
Protoss_Cybernetics_Core 1 2971
Protoss_Robotics_Facility 1 3978
Protoss_Dragoon 13 9841
Protoss_Observatory 1 5445
Protoss_Observer 4 9643
9841
