Special_Protoss_Temple 14 0
Protoss_Nexus 2 2803
Protoss_Gateway 5 9716
Protoss_Assimilator 2 5802
Protoss_Zealot 1 4395
Protoss_Cybernetics_Core 1 4457
Protoss_Dragoon 13 9949
Protoss_Robotics_Facility 1 7164
Protoss_Observatory 1 8549
Protoss_Citadel_of_Adun 1 8931
Protoss_Observer 2 9815
9949
