Special_Protoss_Temple 14 0
Protoss_Nexus 2 9912
Protoss_Gateway 2 5901
Protoss_Assimilator 1 2402
Protoss_Cybernetics_Core 1 2990
Protoss_Dragoon 8 8449
Protoss_Robotics_Facility 1 4945
Protoss_Robotics_Support_Bay 1 6329
Protoss_Shuttle 1 6563
Protoss_Observatory 1 7148
Protoss_Reaver 2 9119
Protoss_Observer 1 8517
Protoss_Scarab 1 8987
9912
