Protoss_Nexus 2 7898
Protoss_Gateway 4 8788
Protoss_Assimilator 1 2503
Protoss_Cybernetics_Core 1 3097
Protoss_Dragoon 11 9831
Protoss_Robotics_Facility 1 5593
Protoss_Observatory 1 6924
Protoss_Observer 2 8211
9831
