Protoss_Nexus 2 6077
Protoss_Gateway 3 8072
Protoss_Assimilator 1 2166
Protoss_Cybernetics_Core 1 2928
Protoss_Zealot 1 3165
Protoss_Dragoon 11 9805
Protoss_Robotics_Facility 1 6915
Protoss_Observatory 1 8367
Protoss_Observer 2 9567
9805
