Protoss_Nexus 2 8268
Protoss_Gateway 3 9870
Protoss_Assimilator 1 2619
Protoss_Cybernetics_Core 1 3283
Protoss_Dragoon 7 9011
Protoss_Citadel_of_Adun 1 4904
Protoss_Templar_Archives 1 5957
Protoss_Dark_Templar 2 6991
Protoss_Robotics_Facility 1 8881
9870
