Protoss_Nexus 3 8059
Protoss_Gateway 2 6029
Protoss_Assimilator 1 3467
Protoss_Cybernetics_Core 1 4213
Protoss_Dragoon 9 9535
Protoss_Robotics_Facility 1 5561
Protoss_Observatory 1 6893
Protoss_Observer 1 7695
Protoss_Shuttle 1 7917
9535
