Protoss_Nexus 2 8218
Protoss_Gateway 2 5866
Protoss_Assimilator 1 2503
Protoss_Cybernetics_Core 1 3153
Protoss_Dragoon 9 9101
Protoss_Robotics_Facility 1 6027
Protoss_Observatory 1 7318
Protoss_Observer 3 9251
9251
