Protoss_Nexus 2 2753
Protoss_Gateway 2 4419
Protoss_Assimilator 2 6376
Protoss_Cybernetics_Core 1 4171
Protoss_Dragoon 6 8159
Protoss_Citadel_of_Adun 1 6666
Protoss_Robotics_Facility 1 7301
Protoss_Templar_Archives 1 7806
Protoss_Shuttle 1 8643
Protoss_Dark_Templar 2 8911
Protoss_Stargate 1 9211
Protoss_Observatory 1 9277
Protoss_Observer 1 9815
9815
