Protoss_Nexus 2 7163
Protoss_Gateway 3 7426
Protoss_Assimilator 1 2545
Protoss_Cybernetics_Core 1 3487
Protoss_Zealot 1 3823
Protoss_Dragoon 8 9707
Protoss_Robotics_Facility 1 5891
Protoss_Observatory 1 7296
Protoss_Observer 1 7833
Protoss_Robotics_Support_Bay 1 8182
Protoss_Shuttle 1 8885
Protoss_Reaver 1 9869
9869
