Protoss_Nexus 3 7756
Protoss_Gateway 5 9901
Protoss_Assimilator 2 2642
Protoss_Cybernetics_Core 1 3241
Protoss_Dragoon 7 9389
Protoss_Robotics_Facility 1 8331
Protoss_Observatory 1 9643
9901
