Protoss_Nexus 2 5613
Protoss_Gateway 3 9786
Protoss_Assimilator 1 2185
Protoss_Cybernetics_Core 1 2927
Protoss_Zealot 3 8477
Protoss_Dragoon 7 9263
Protoss_Robotics_Facility 1 6408
Protoss_Shuttle 1 7733
Protoss_Robotics_Support_Bay 1 8311
Protoss_Reaver 1 8857
Protoss_Observatory 1 9530
9786
