Protoss_Nexus 3 9001
Protoss_Gateway 3 9934
Protoss_Assimilator 1 3463
Protoss_Cybernetics_Core 1 4447
Protoss_Zealot 1 4831
Protoss_Dragoon 10 9311
Protoss_Robotics_Facility 1 7175
Protoss_Observatory 1 9397
Protoss_Observer 1 9933
9934
