Protoss_Nexus 2 8633
Protoss_Gateway 2 9165
Protoss_Assimilator 1 2309
Protoss_Cybernetics_Core 1 2966
Protoss_Dragoon 6 9807
Protoss_Robotics_Facility 1 4366
Protoss_Shuttle 1 5949
Protoss_Observatory 1 6295
Protoss_Observer 1 6851
Protoss_Robotics_Support_Bay 1 7128
Protoss_Zealot 2 8117
Protoss_Reaver 1 7723
Protoss_Scarab 6 9985
9985
