Protoss_Nexus 2 7217
Protoss_Gateway 3 8655
Protoss_Assimilator 2 9605
Protoss_Cybernetics_Core 1 2917
Protoss_Dragoon 8 9845
Protoss_Robotics_Facility 1 5377
Protoss_Shuttle 1 6697
Protoss_Robotics_Support_Bay 1 7430
Protoss_Reaver 1 7969
Protoss_Observatory 1 8346
Protoss_Observer 2 9663
Protoss_Scarab 2 9950
9950
