Protoss_Nexus 1 0
Protoss_Gateway 2 2573
Protoss_Zealot 10 6771
Protoss_Forge 1 3818
Protoss_Photon_Cannon 3 9361
Protoss_Assimilator 1 5076
Protoss_Cybernetics_Core 1 7415
Protoss_Robotics_Facility 1 8408
Protoss_Shuttle 1 9696
Protoss_Robotics_Support_Bay 1 9808
9808
