Protoss_Nexus 2 7713
Protoss_Gateway 3 9084
Protoss_Assimilator 1 2356
Protoss_Cybernetics_Core 1 2888
Protoss_Dragoon 12 9690
Protoss_Robotics_Facility 1 4436
Protoss_Observatory 1 6046
Protoss_Observer 5 9736
9736
