Protoss_Nexus 2 9581
Protoss_Gateway 2 6623
Protoss_Assimilator 1 2453
Protoss_Zealot 6 8379
Protoss_Cybernetics_Core 1 3743
Protoss_Dragoon 7 9893
Protoss_Robotics_Facility 1 6107
Protoss_Observatory 1 7415
Protoss_Shuttle 1 7455
Protoss_Observer 2 8959
9893
