Special_Protoss_Temple 14 0
Protoss_Nexus 2 7369
Protoss_Gateway 2 8374
Protoss_Assimilator 1 2406
Protoss_Cybernetics_Core 1 2956
Protoss_Zealot 2 8693
Protoss_Dragoon 6 9561
Protoss_Robotics_Facility 1 5649
Protoss_Shuttle 1 6935
Protoss_Robotics_Support_Bay 1 7557
Protoss_Reaver 1 8215
Protoss_Observatory 1 8914
Protoss_Observer 1 9481
9561
