Protoss_Nexus 3 7803
Protoss_Gateway 8 9865
Protoss_Assimilator 2 8982
Protoss_Cybernetics_Core 1 4109
Protoss_Dragoon 10 8997
Protoss_Robotics_Facility 1 7343
Protoss_Observatory 1 8730
Protoss_Observer 1 9317
9865
