Protoss_Nexus 2 9382
Protoss_Gateway 2 6425
Protoss_Assimilator 1 2443
Protoss_Cybernetics_Core 1 3085
Protoss_Dragoon 10 8927
Protoss_Robotics_Facility 1 5910
Protoss_Observatory 1 7201
Protoss_Observer 2 8333
Protoss_Shuttle 1 9463
Protoss_Zealot 2 9697
Protoss_Robotics_Support_Bay 1 9953
9953
