Protoss_Nexus 2 6938
Protoss_Gateway 2 5567
Protoss_Assimilator 1 2457
Protoss_Cybernetics_Core 1 3109
Protoss_Dragoon 8 9965
Protoss_Citadel_of_Adun 1 5101
Protoss_Templar_Archives 1 6095
Protoss_Dark_Templar 3 7899
9965
