Protoss_Nexus 1 0
Protoss_Gateway 3 8526
Protoss_Assimilator 1 2593
Protoss_Cybernetics_Core 1 3148
Protoss_Dragoon 9 9726
Protoss_Zealot 5 9649
Protoss_Robotics_Facility 1 6268
Protoss_Observatory 1 7618
Protoss_Observer 1 8476
Protoss_Shuttle 1 9211
9726
