Protoss_Nexus 1 0
Protoss_Gateway 2 2673
Protoss_Zealot 11 9056
Protoss_Assimilator 1 3982
Protoss_Forge 1 4472
Protoss_Photon_Cannon 2 5340
Protoss_Cybernetics_Core 1 6333
Protoss_Citadel_of_Adun 1 7582
Protoss_Dragoon 2 7886
Protoss_Templar_Archives 1 8676
Protoss_High_Templar 1 9686
9686
