Protoss_Nexus 2 8468
Protoss_Gateway 3 8848
Protoss_Assimilator 1 2487
Protoss_Cybernetics_Core 1 3067
Protoss_Dragoon 10 9266
Protoss_Robotics_Facility 1 5497
Protoss_Observatory 1 6818
Protoss_Observer 2 8121
9266
