Protoss_Nexus 3 9210
Protoss_Gateway 2 3440
Protoss_Assimilator 1 2198
Protoss_Cybernetics_Core 1 2821
Protoss_Dragoon 9 9701
Protoss_Citadel_of_Adun 1 5980
Protoss_Templar_Archives 1 7352
Protoss_Dark_Templar 2 8433
9701
