Special_Protoss_Temple 14 0
Protoss_Nexus 1 0
Protoss_Gateway 3 9196
Protoss_Zealot 13 8833
Protoss_Forge 1 4231
Protoss_Photon_Cannon 3 6566
Protoss_Assimilator 1 7966
Protoss_Cybernetics_Core 1 8379
Protoss_Dragoon 2 9435
9435
