Protoss_Nexus 1 0
Protoss_Gateway 2 8510
Protoss_Assimilator 1 2169
Protoss_Cybernetics_Core 1 2927
Protoss_Dragoon 8 9701
Protoss_Robotics_Facility 1 5107
Protoss_Shuttle 1 6387
Protoss_Robotics_Support_Bay 1 6475
Protoss_Zealot 1 6483
Protoss_Reaver 2 8355
Protoss_Observatory 1 7693
Protoss_Scarab 8 9791
Protoss_Observer 1 9407
9791
