Special_Protoss_Temple 14 0
Protoss_Nexus 2 6521
Protoss_Gateway 3 9301
Protoss_Assimilator 1 2528
Protoss_Zealot 2 3619
Protoss_Cybernetics_Core 1 4025
Protoss_Dragoon 5 8709
Protoss_Robotics_Facility 1 6021
Protoss_Shuttle 1 7307
Protoss_Robotics_Support_Bay 1 7433
Protoss_Reaver 1 8229
Protoss_Observatory 1 9485
Protoss_Scarab 2 9893
9893
