Protoss_Nexus 3 8907
Protoss_Gateway 3 7481
Protoss_Assimilator 2 9883
Protoss_Cybernetics_Core 1 3009
Protoss_Dragoon 10 9737
Protoss_Robotics_Facility 1 6893
Protoss_Observatory 1 8283
Protoss_Observer 2 9638
Protoss_Citadel_of_Adun 1 9482
9883
