Protoss_Nexus 2 6675
Protoss_Gateway 2 3317
Protoss_Assimilator 2 7977
Protoss_Cybernetics_Core 1 2841
Protoss_Dragoon 4 5273
Protoss_Citadel_of_Adun 1 6787
Protoss_Robotics_Facility 1 7431
Protoss_Templar_Archives 1 7795
Protoss_Shuttle 1 8839
Protoss_Dark_Templar 4 9691
Protoss_Stargate 1 9370
9691
