Protoss_Nexus 3 9787
Protoss_Gateway 2 8806
Protoss_Assimilator 1 2365
Protoss_Cybernetics_Core 1 2930
Protoss_Dragoon 8 9857
Protoss_Robotics_Facility 1 6859
Protoss_Shuttle 1 8207
Protoss_Robotics_Support_Bay 1 8690
Protoss_Reaver 1 9235
9857
