Protoss_Nexus 3 6461
Protoss_Gateway 6 9396
Protoss_Assimilator 1 2647
Protoss_Cybernetics_Core 1 2977
Protoss_Dragoon 8 9971
Protoss_Robotics_Facility 1 7501
Protoss_Observatory 1 9093
Protoss_Observer 1 9625
9971
