Protoss_Nexus 3 7221
Protoss_Gateway 4 8469
Protoss_Assimilator 1 3412
Protoss_Cybernetics_Core 1 4150
Protoss_Zealot 1 4639
Protoss_Dragoon 10 9691
Protoss_Robotics_Facility 1 7535
Protoss_Observatory 1 8863
Protoss_Observer 1 9545
9691
