Protoss_Nexus 2 7313
Protoss_Gateway 3 8304
Protoss_Assimilator 1 2572
Protoss_Cybernetics_Core 1 3302
Protoss_Robotics_Facility 1 4341
Protoss_Dragoon 9 9567
Protoss_Shuttle 2 6767
Protoss_Observatory 1 7857
Protoss_Observer 1 9609
9609
