Protoss_Nexus 2 6157
Protoss_Gateway 3 7483
Protoss_Assimilator 1 2333
Protoss_Cybernetics_Core 1 2853
Protoss_Zealot 1 3093
Protoss_Dragoon 12 9461
Protoss_Robotics_Facility 1 6800
Protoss_Observatory 1 8219
Protoss_Observer 3 9994
9994
