Protoss_Nexus 2 6264
Special_Protoss_Temple 14 0
Protoss_Gateway 2 7720
Protoss_Assimilator 2 8526
Protoss_Cybernetics_Core 1 2913
Protoss_Zealot 1 3253
Protoss_Dragoon 10 9773
Protoss_Robotics_Facility 1 7445
Protoss_Citadel_of_Adun 1 7971
Protoss_Observatory 1 8751
Protoss_Observer 1 9301
Protoss_Templar_Archives 1 9427
9773
