Protoss_Nexus 2 8448
Protoss_Assimilator 2 9213
Protoss_Gateway 2 4750
Protoss_Cybernetics_Core 1 3325
Protoss_Robotics_Facility 1 4334
Protoss_Shuttle 1 5617
Protoss_Observatory 1 5969
Protoss_Dragoon 8 8887
Protoss_Observer 2 7263
Protoss_Citadel_of_Adun 1 9285
Protoss_Zealot 2 9889
9889
