Protoss_Nexus 2 7047
Protoss_Gateway 2 7635
Protoss_Assimilator 2 8630
Protoss_Cybernetics_Core 1 2927
Protoss_Zealot 1 3103
Protoss_Dragoon 10 9963
Protoss_Robotics_Facility 1 5460
Protoss_Observatory 1 6837
Protoss_Observer 4 9923
Protoss_Citadel_of_Adun 1 8539
Protoss_Stargate 1 9667
9963
