Protoss_Nexus 1 0
Protoss_Gateway 3 9988
Protoss_Assimilator 1 2373
Protoss_Cybernetics_Core 1 3108
Protoss_Dragoon 9 9618
Protoss_Robotics_Facility 1 4780
Protoss_Zealot 1 6058
Protoss_Shuttle 1 6071
Protoss_Robotics_Support_Bay 1 6273
Protoss_Reaver 1 6973
Protoss_Observatory 1 8641
Protoss_Observer 2 9788
Protoss_Scarab 1 9799
9988
