Protoss_Nexus 3 5967
Protoss_Gateway 2 6421
Protoss_Assimilator 2 9461
Protoss_Cybernetics_Core 1 2855
Protoss_Dragoon 9 8535
Protoss_Robotics_Facility 1 6957
Protoss_Observatory 1 8546
Protoss_Shuttle 1 8663
Protoss_Observer 1 9565
Protoss_Robotics_Support_Bay 1 9625
Protoss_Zealot 2 9827
Protoss_Citadel_of_Adun 1 9968
9968
