Protoss_Nexus 3 7750
Protoss_Gateway 5 9509
Protoss_Assimilator 1 2169
Protoss_Cybernetics_Core 1 2813
Protoss_Zealot 1 2963
Protoss_Dragoon 10 9995
Protoss_Robotics_Facility 1 8879
9995
