Protoss_Nexus 2 2789
Protoss_Gateway 2 4369
Protoss_Assimilator 2 5931
Protoss_Cybernetics_Core 1 4122
Protoss_Zealot 1 4679
Protoss_Dragoon 6 9829
Protoss_Citadel_of_Adun 1 6403
Protoss_Robotics_Facility 1 7254
Protoss_Templar_Archives 1 7460
Protoss_Shuttle 1 8591
Protoss_Dark_Templar 2 8635
Protoss_Forge 1 8749
Protoss_Observatory 1 9200
Protoss_Stargate 1 9429
Protoss_Photon_Cannon 1 9676
Protoss_Observer 1 9737
9829
