Protoss_Nexus 2 2712
Protoss_Gateway 2 8052
Protoss_Assimilator 2 8223
Protoss_Cybernetics_Core 1 4222
Protoss_Zealot 1 4307
Protoss_Dragoon 8 9981
Protoss_Robotics_Facility 1 8431
Protoss_Observatory 1 9725
9981
