Protoss_Nexus 2 6991
Protoss_Gateway 2 3454
Protoss_Assimilator 2 9800
Protoss_Cybernetics_Core 1 2897
Protoss_Dragoon 10 8881
Protoss_Robotics_Facility 1 7897
Protoss_Observatory 1 9223
Protoss_Shuttle 1 9267
Protoss_Robotics_Support_Bay 1 9985
9985
