Special_Protoss_Temple 14 0
Protoss_Nexus 3 9811
Protoss_Gateway 2 7194
Protoss_Assimilator 1 2357
Protoss_Cybernetics_Core 1 2970
Protoss_Dragoon 6 9637
Protoss_Robotics_Facility 1 5969
Protoss_Shuttle 1 7863
Protoss_Observatory 1 7934
Protoss_Zealot 3 8907
Protoss_Observer 1 8765
9811
