Protoss_Nexus 2 9078
Protoss_Gateway 3 10000
Protoss_Assimilator 1 2623
Protoss_Cybernetics_Core 1 3068
Protoss_Dragoon 3 5901
Protoss_Citadel_of_Adun 2 5558
Protoss_Templar_Archives 1 6626
Protoss_Dark_Templar 6 9491
10000
