Protoss_Nexus 4 8451
Protoss_Gateway 2 4310
Protoss_Assimilator 1 3263
Protoss_Cybernetics_Core 1 4073
Protoss_Zealot 1 4485
Protoss_Dragoon 6 8933
Protoss_Robotics_Facility 1 7757
Protoss_Observatory 1 9225
Protoss_Citadel_of_Adun 1 9559
Protoss_Observer 1 9769
9769
