Special_Protoss_Temple 30 0
Protoss_Nexus 3 9471
Protoss_Gateway 2 3393
Protoss_Assimilator 1 2242
Protoss_Cybernetics_Core 1 2869
Protoss_Dragoon 6 6667
Protoss_Citadel_of_Adun 1 5064
Protoss_Zealot 1 5443
Protoss_Templar_Archives 1 6230
Protoss_Dark_Templar 2 7509
Protoss_Robotics_Facility 1 9822
9822
