Protoss_Nexus 3 9233
Protoss_Gateway 2 8343
Protoss_Assimilator 1 2356
Protoss_Zealot 2 3539
Protoss_Cybernetics_Core 1 3795
Protoss_Dragoon 8 9697
Protoss_Robotics_Facility 1 5015
Protoss_Observatory 1 6318
Protoss_Observer 2 7451
9697
