Protoss_Nexus 1 0
Protoss_Gateway 1 2148
Protoss_Assimilator 1 2633
Protoss_Cybernetics_Core 1 3400
Protoss_Dragoon 5 8501
Protoss_Robotics_Facility 1 6028
Protoss_Shuttle 1 7321
Protoss_Robotics_Support_Bay 1 7348
Protoss_Zealot 2 9253
Protoss_Reaver 1 8223
Protoss_Observatory 1 9206
Protoss_Scarab 4 9953
9953
