Protoss_Nexus 3 9003
Protoss_Gateway 4 9498
Protoss_Assimilator 1 3278
Protoss_Cybernetics_Core 1 3991
Protoss_Zealot 3 9225
Protoss_Dragoon 12 9959
Protoss_Robotics_Facility 1 7279
Protoss_Observatory 1 8651
Protoss_Observer 2 9969
9969
