Protoss_Nexus 2 9940
Protoss_Gateway 2 8092
Protoss_Assimilator 1 2408
Protoss_Cybernetics_Core 1 2943
Protoss_Dragoon 9 9529
Protoss_Robotics_Facility 1 5940
Protoss_Observatory 1 7384
Protoss_Observer 4 9937
9940
