Protoss_Nexus 3 9819
Protoss_Gateway 2 7987
Protoss_Zealot 6 6520
Protoss_Assimilator 2 8116
Protoss_Cybernetics_Core 1 5865
Protoss_Forge 1 6510
Protoss_Citadel_of_Adun 1 6996
Protoss_Dragoon 2 8311
Protoss_Templar_Archives 1 8091
Protoss_Photon_Cannon 1 8761
Protoss_Dark_Templar 3 9983
Protoss_Stargate 1 9350
9983
