Protoss_Nexus 2 6476
Protoss_Gateway 2 7211
Protoss_Assimilator 1 2353
Protoss_Cybernetics_Core 1 2920
Protoss_Dragoon 11 9761
Protoss_Robotics_Facility 1 6938
Protoss_Observatory 1 8306
Protoss_Observer 2 9447
9761
