Special_Protoss_Temple 14 0
Protoss_Nexus 2 2925
Protoss_Gateway 2 4681
Protoss_Assimilator 1 3677
Protoss_Cybernetics_Core 1 4374
Protoss_Zealot 1 4823
Protoss_Dragoon 12 9903
Protoss_Robotics_Facility 1 9495
9903
