Special_Protoss_Temple 14 0
Protoss_Nexus 2 6075
Protoss_Gateway 2 6492
Protoss_Assimilator 2 9353
Protoss_Cybernetics_Core 1 3075
Protoss_Dragoon 11 9949
Protoss_Robotics_Facility 1 7224
Protoss_Observatory 1 8596
Protoss_Observer 2 9839
Protoss_Citadel_of_Adun 1 9215
9949
