Special_Protoss_Temple 14 0
Protoss_Nexus 2 8131
Protoss_Gateway 2 9013
Protoss_Assimilator 1 2358
Protoss_Cybernetics_Core 1 2983
Protoss_Zealot 1 3197
Protoss_Dragoon 7 9549
Protoss_Robotics_Facility 1 5562
Protoss_Shuttle 1 6861
Protoss_Robotics_Support_Bay 1 7059
Protoss_Reaver 1 7763
Protoss_Observatory 1 8257
Protoss_Observer 2 9417
9549
