Protoss_Nexus 2 8379
Protoss_Gateway 1 1863
Protoss_Assimilator 1 2431
Protoss_Cybernetics_Core 1 2935
Protoss_Zealot 2 6833
Protoss_Dragoon 6 9521
Protoss_Robotics_Facility 1 4409
Protoss_Shuttle 2 9377
Protoss_Robotics_Support_Bay 1 6083
Protoss_Reaver 1 6791
Protoss_Observatory 1 7335
Protoss_Observer 2 8507
Protoss_Scarab 2 9001
9521
