Protoss_Nexus 2 6791
Protoss_Gateway 4 9213
Protoss_Assimilator 1 2601
Protoss_Cybernetics_Core 1 3193
Protoss_Dragoon 10 9640
Protoss_Robotics_Facility 1 7654
Protoss_Observatory 1 9005
Protoss_Observer 1 9711
Protoss_Zealot 1 9756
9756
