Protoss_Nexus 2 8818
Protoss_Gateway 3 9723
Protoss_Assimilator 1 2531
Protoss_Cybernetics_Core 1 3233
Protoss_Dragoon 5 7671
Protoss_Robotics_Facility 1 5885
Protoss_Shuttle 1 7171
Protoss_Robotics_Support_Bay 1 7644
Protoss_Reaver 1 8191
Protoss_Observatory 1 8279
Protoss_Zealot 2 8948
Protoss_Observer 1 9346
9723
