Special_Protoss_Temple 14 0
Protoss_Nexus 2 7035
Protoss_Gateway 2 9327
Protoss_Assimilator 2 8948
Protoss_Cybernetics_Core 1 2975
Protoss_Dragoon 7 8907
Protoss_Robotics_Facility 1 5359
Protoss_Observatory 1 6739
Protoss_Observer 3 8981
Protoss_Citadel_of_Adun 1 8135
Protoss_Templar_Archives 1 9734
9734
