Protoss_Nexus 2 7685
Protoss_Gateway 2 6050
Protoss_Assimilator 1 2317
Protoss_Cybernetics_Core 1 2820
Protoss_Dragoon 7 9761
Protoss_Citadel_of_Adun 1 4928
Protoss_Templar_Archives 1 5959
Protoss_Zealot 1 6385
Protoss_Dark_Templar 3 8963
9761
