Protoss_Nexus 2 6743
Protoss_Gateway 4 8959
Protoss_Assimilator 1 2310
Protoss_Cybernetics_Core 1 2826
Protoss_Dragoon 7 7605
Protoss_Citadel_of_Adun 1 8063
Protoss_Robotics_Facility 1 8610
Protoss_Templar_Archives 1 9359
Protoss_Shuttle 1 9893
9893
