Protoss_Nexus 2 7411
Protoss_Gateway 2 5986
Protoss_Assimilator 1 2184
Protoss_Cybernetics_Core 1 2824
Protoss_Zealot 1 3175
Protoss_Dragoon 12 9409
Protoss_Robotics_Facility 1 5334
Protoss_Observatory 1 6619
Protoss_Observer 2 7789
Protoss_Shuttle 1 8601
Protoss_Robotics_Support_Bay 1 8808
Protoss_Reaver 1 9711
9711
