Special_Protoss_Temple 14 0
Protoss_Nexus 2 7741
Protoss_Assimilator 3 3252
Protoss_Gateway 4 8973
Protoss_Cybernetics_Core 1 3625
Protoss_Dragoon 10 9915
Protoss_Robotics_Facility 1 8034
Protoss_Observatory 1 9865
9915
