Special_Protoss_Temple 14 0
Protoss_Nexus 2 5711
Protoss_Gateway 2 6261
Protoss_Assimilator 2 9508
Protoss_Cybernetics_Core 1 3127
Protoss_Dragoon 9 9691
Protoss_Robotics_Facility 1 6651
Protoss_Shuttle 1 7945
Protoss_Robotics_Support_Bay 1 8644
Protoss_Zealot 2 9003
Protoss_Reaver 1 9267
Protoss_Observatory 1 9825
9825
