Special_Protoss_Temple 14 0
Protoss_Nexus 2 5939
Protoss_Gateway 2 6423
Protoss_Assimilator 2 9301
Protoss_Cybernetics_Core 1 3053
Protoss_Dragoon 10 9859
Protoss_Robotics_Facility 1 7247
Protoss_Shuttle 1 8533
Protoss_Observatory 1 8827
Protoss_Zealot 2 9747
Protoss_Robotics_Support_Bay 1 9284
Protoss_Observer 1 9567
9859
