Protoss_Nexus 2 5995
Protoss_Gateway 3 7619
Protoss_Assimilator 1 2340
Protoss_Cybernetics_Core 1 2861
Protoss_Zealot 1 3163
Protoss_Dragoon 9 8701
Protoss_Robotics_Facility 1 6845
Protoss_Observatory 1 8181
Protoss_Observer 2 9321
Protoss_Shuttle 1 9923
Protoss_Robotics_Support_Bay 1 9982
9982
