Protoss_Nexus 3 8580
Protoss_Gateway 4 9888
Protoss_Assimilator 1 2143
Protoss_Cybernetics_Core 1 2811
Protoss_Dragoon 10 9215
Protoss_Robotics_Facility 1 5065
Protoss_Observatory 1 6375
Protoss_Observer 3 9361
9888
