Protoss_Nexus 2 8879
Protoss_Gateway 2 4693
Protoss_Assimilator 1 2346
Protoss_Cybernetics_Core 1 2835
Protoss_Zealot 2 9279
Protoss_Citadel_of_Adun 1 3949
Protoss_Dragoon 8 9163
Protoss_Templar_Archives 1 5020
Protoss_Dark_Templar 2 6005
Protoss_Robotics_Facility 1 9259
9279
