Protoss_Nexus 2 6025
Protoss_Gateway 3 7885
Protoss_Assimilator 2 8862
Protoss_Cybernetics_Core 1 2913
Protoss_Zealot 3 9953
Protoss_Dragoon 7 9671
Protoss_Robotics_Facility 1 6894
Protoss_Observatory 1 8229
Protoss_Citadel_of_Adun 1 8469
Protoss_Observer 2 9387
Protoss_Templar_Archives 1 9463
Protoss_Stargate 1 9545
9953
