Protoss_Nexus 3 8361
Protoss_Gateway 2 5582
Protoss_Assimilator 2 9173
Protoss_Cybernetics_Core 1 3035
Protoss_Dragoon 7 9639
Protoss_Robotics_Facility 1 5478
Protoss_Observatory 1 7017
Protoss_Observer 2 8151
Protoss_Citadel_of_Adun 1 9071
9639
