Protoss_Nexus 3 9384
Protoss_Gateway 4 9667
Protoss_Assimilator 2 6461
Protoss_Cybernetics_Core 1 4159
Protoss_Dragoon 7 9711
Protoss_Robotics_Facility 1 5789
Protoss_Zealot 2 7159
Protoss_Observatory 1 7226
Protoss_Observer 3 9559
9711
