Protoss_Nexus 3 7299
Protoss_Gateway 1 1927
Protoss_Assimilator 1 2319
Protoss_Cybernetics_Core 1 2977
Protoss_Dragoon 6 8451
Protoss_Robotics_Facility 1 5421
Protoss_Observatory 1 6905
Protoss_Observer 3 9839
Protoss_Shuttle 1 8937
Protoss_Robotics_Support_Bay 1 8969
Protoss_Zealot 2 9945
9945
