Protoss_Nexus 3 8791
Protoss_Gateway 3 9817
Protoss_Assimilator 2 9960
Protoss_Cybernetics_Core 1 2898
Protoss_Zealot 1 3109
Protoss_Dragoon 7 9151
Protoss_Robotics_Facility 1 7065
Protoss_Observatory 1 8356
Protoss_Observer 2 9555
9960
