Protoss_Nexus 2 2497
Protoss_Gateway 2 3669
Protoss_Assimilator 2 7209
Protoss_Zealot 3 4799
Protoss_Cybernetics_Core 1 4215
Protoss_Dragoon 10 9841
Protoss_Citadel_of_Adun 1 7224
Protoss_Templar_Archives 1 8225
Protoss_Stargate 1 8311
Protoss_Robotics_Facility 1 9255
Protoss_Arbiter_Tribunal 1 9483
9841
