Protoss_Nexus 1 0
Protoss_Gateway 3 6085
Protoss_Assimilator 1 2232
Protoss_Cybernetics_Core 1 2945
Protoss_Dragoon 11 9545
Protoss_Robotics_Facility 1 5301
Protoss_Observatory 1 6612
Protoss_Observer 1 7139
Protoss_Shuttle 1 7931
Protoss_Robotics_Support_Bay 1 8211
Protoss_Zealot 3 8943
Protoss_Reaver 1 8857
9545
