Protoss_Nexus 3 9232
Protoss_Assimilator 1 1829
Protoss_Gateway 4 9682
Protoss_Cybernetics_Core 1 3267
Protoss_Dragoon 7 8553
Protoss_Robotics_Facility 1 5908
Protoss_Zealot 1 6139
Protoss_Observatory 1 7541
Protoss_Observer 3 9597
9682
