Special_Protoss_Temple 14 0
Protoss_Nexus 3 9981
Protoss_Gateway 2 6287
Protoss_Assimilator 1 2601
Protoss_Cybernetics_Core 1 3285
Protoss_Dragoon 8 9581
Protoss_Robotics_Facility 1 5615
Protoss_Shuttle 1 6975
Protoss_Observatory 1 7117
Protoss_Robotics_Support_Bay 1 7728
Protoss_Observer 1 7919
Protoss_Zealot 2 7973
Protoss_Reaver 1 8521
9981
