Protoss_Nexus 2 2583
Protoss_Gateway 3 9936
Protoss_Assimilator 1 3405
Protoss_Cybernetics_Core 1 3985
Protoss_Zealot 3 8997
Protoss_Dragoon 8 8245
Protoss_Robotics_Facility 1 8816
9936
