Protoss_Nexus 2 8293
Protoss_Gateway 2 9730
Protoss_Assimilator 1 2341
Protoss_Cybernetics_Core 1 2971
Protoss_Dragoon 3 6367
Protoss_Robotics_Facility 1 4351
Protoss_Zealot 4 9517
Protoss_Shuttle 1 5631
Protoss_Robotics_Support_Bay 1 5903
Protoss_Reaver 1 6917
Protoss_Scarab 12 9831
9831
