Special_Protoss_Temple 14 0
Protoss_Nexus 2 7231
Protoss_Gateway 3 8053
Protoss_Assimilator 1 2573
Protoss_Cybernetics_Core 1 3456
Protoss_Dragoon 12 9333
Protoss_Shield_Battery 1 8615
Protoss_Robotics_Facility 1 9645
Protoss_Zealot 1 9823
9823
