Protoss_Nexus 2 6864
Protoss_Gateway 2 7198
Protoss_Assimilator 2 8858
Protoss_Cybernetics_Core 1 2992
Protoss_Dragoon 11 9809
Protoss_Robotics_Facility 1 5482
Protoss_Observatory 1 6774
Protoss_Observer 2 7915
Protoss_Citadel_of_Adun 1 8766
9809
