Protoss_Nexus 2 3763
Protoss_Gateway 4 9330
Protoss_Assimilator 2 7544
Protoss_Cybernetics_Core 1 4193
Protoss_Zealot 1 4483
Protoss_Dragoon 10 9551
Protoss_Robotics_Facility 1 6677
Protoss_Observatory 1 8131
Protoss_Observer 3 9913
9913
