Protoss_Nexus 2 6748
Protoss_Gateway 2 8344
Protoss_Assimilator 2 8251
Protoss_Zealot 1 3121
Protoss_Cybernetics_Core 1 3809
Protoss_Dragoon 6 9393
Protoss_Robotics_Facility 1 5807
Protoss_Observatory 1 7384
Protoss_Observer 3 9905
Protoss_Citadel_of_Adun 1 8152
Protoss_Templar_Archives 1 9484
9905
