Protoss_Nexus 3 8367
Protoss_Gateway 7 9797
Protoss_Zealot 4 7955
Protoss_Assimilator 2 7023
Protoss_Cybernetics_Core 1 4801
Protoss_Dragoon 6 9637
Protoss_Robotics_Facility 1 7576
Protoss_Observatory 2 8909
Protoss_Observer 1 9449
9797
