Protoss_Nexus 3 8285
Protoss_Gateway 4 9615
Protoss_Assimilator 2 7579
Protoss_Cybernetics_Core 1 4151
Protoss_Zealot 1 4639
Protoss_Dragoon 8 8997
Protoss_Robotics_Facility 1 7286
Protoss_Observatory 1 8790
Protoss_Observer 2 9923
9923
