Special_Protoss_Temple 14 0
Protoss_Nexus 3 8978
Protoss_Gateway 2 7323
Protoss_Assimilator 2 9384
Protoss_Cybernetics_Core 1 2916
Protoss_Zealot 1 3281
Protoss_Dragoon 8 9836
Protoss_Robotics_Facility 1 7006
Protoss_Observatory 1 8521
Protoss_Observer 2 9868
9868
