Protoss_Nexus 2 7798
Protoss_Gateway 2 8760
Protoss_Assimilator 1 2283
Protoss_Cybernetics_Core 1 2993
Protoss_Dragoon 8 9287
Protoss_Robotics_Facility 1 5604
Protoss_Observatory 1 6908
Protoss_Observer 3 9691
9691
