Protoss_Nexus 2 5629
Protoss_Gateway 3 7498
Protoss_Assimilator 1 2354
Protoss_Cybernetics_Core 1 2975
Protoss_Dragoon 13 9929
Protoss_Robotics_Facility 1 6575
Protoss_Observatory 1 7953
Protoss_Observer 1 8493
9929
