Protoss_Nexus 3 8169
Protoss_Gateway 2 3370
Protoss_Assimilator 1 2199
Protoss_Cybernetics_Core 1 2865
Protoss_Dragoon 7 9485
Protoss_Robotics_Facility 1 7463
Protoss_Shuttle 1 8747
Protoss_Robotics_Support_Bay 1 9027
Protoss_Reaver 1 9689
9689
