Protoss_Nexus 3 9811
Protoss_Gateway 2 4535
Protoss_Assimilator 2 7580
Protoss_Cybernetics_Core 1 4250
Protoss_Dragoon 10 9367
Protoss_Robotics_Facility 1 7775
Protoss_Zealot 2 7923
Protoss_Citadel_of_Adun 1 8839
Protoss_Observatory 1 9242
9811
