Special_Protoss_Temple 30 0
Protoss_Nexus 2 7513
Protoss_Gateway 2 5839
Protoss_Assimilator 1 2331
Protoss_Cybernetics_Core 1 2939
Protoss_Dragoon 9 9665
Protoss_Robotics_Facility 1 5328
Protoss_Observatory 1 6629
Protoss_Observer 1 7161
Protoss_Shuttle 1 8345
Protoss_Robotics_Support_Bay 1 9077
Protoss_Reaver 1 9879
9879
