Protoss_Nexus 1 0
Protoss_Gateway 1 1999
Protoss_Assimilator 1 2473
Protoss_Cybernetics_Core 1 3151
Protoss_Dragoon 4 9426
Protoss_Robotics_Facility 1 4611
Protoss_Zealot 2 6056
Protoss_Shuttle 1 5916
Protoss_Robotics_Support_Bay 1 5975
Protoss_Reaver 3 9756
Protoss_Scarab 5 9650
Protoss_Shield_Battery 1 8418
9756
