Protoss_Nexus 2 6910
Protoss_Gateway 2 7263
Protoss_Assimilator 2 8297
Protoss_Cybernetics_Core 1 2929
Protoss_Dragoon 11 9917
Protoss_Robotics_Facility 1 4277
Protoss_Zealot 1 5425
Protoss_Observatory 1 5695
Protoss_Observer 3 8439
Protoss_Citadel_of_Adun 1 7907
Protoss_Templar_Archives 1 9498
9917
