Protoss_Nexus 2 8869
Protoss_Gateway 3 9698
Protoss_Assimilator 1 2317
Protoss_Cybernetics_Core 1 3019
Protoss_Dragoon 7 9887
Protoss_Robotics_Facility 1 4499
Protoss_Zealot 2 6157
Protoss_Shuttle 1 5819
Protoss_Observatory 1 6258
Protoss_Observer 2 9317
Protoss_Robotics_Support_Bay 1 7127
Protoss_Reaver 1 7679
Protoss_Scarab 2 9731
9887
