Protoss_Nexus 2 9752
Protoss_Gateway 2 9682
Protoss_Assimilator 1 2430
Protoss_Cybernetics_Core 1 3049
Protoss_Zealot 1 3181
Protoss_Dragoon 7 9514
Protoss_Robotics_Facility 1 5483
Protoss_Shuttle 1 6789
Protoss_Robotics_Support_Bay 1 6867
Protoss_Reaver 1 7691
Protoss_Observatory 1 7886
Protoss_Observer 2 9514
9752
