Protoss_Nexus 2 8321
Protoss_Gateway 4 9960
Protoss_Assimilator 1 2306
Protoss_Cybernetics_Core 1 2947
Protoss_Dragoon 6 9639
Protoss_Robotics_Facility 1 4344
Protoss_Zealot 4 8772
Protoss_Shuttle 1 5637
Protoss_Robotics_Support_Bay 1 6029
Protoss_Reaver 1 6737
Protoss_Scarab 7 9726
9960
