Special_Protoss_Temple 30 0
Protoss_Nexus 3 8324
Protoss_Gateway 3 9519
Protoss_Assimilator 1 2313
Protoss_Cybernetics_Core 1 2890
Protoss_Dragoon 9 9831
Protoss_Robotics_Facility 1 6004
Protoss_Observatory 1 7457
Protoss_Observer 3 9287
Protoss_Shuttle 1 9889
9889
