Protoss_Nexus 2 6144
Protoss_Gateway 2 4100
Protoss_Assimilator 1 2347
Protoss_Zealot 1 2811
Protoss_Cybernetics_Core 1 3617
Protoss_Dragoon 10 8851
Protoss_Robotics_Facility 1 6915
Protoss_Observatory 1 8265
Protoss_Observer 1 8865
Protoss_Robotics_Support_Bay 1 9453
Protoss_Shuttle 1 9467
9467
