Protoss_Nexus 2 2643
Protoss_Gateway 3 8730
Protoss_Assimilator 2 8287
Protoss_Cybernetics_Core 1 4051
Protoss_Zealot 1 4239
Protoss_Dragoon 13 9783
Protoss_Robotics_Facility 1 7571
Protoss_Observatory 1 9184
Protoss_Observer 1 9795
Protoss_Citadel_of_Adun 1 9879
9879
