Protoss_Nexus 3 7369
Protoss_Gateway 3 9767
Protoss_Assimilator 2 8743
Protoss_Cybernetics_Core 1 3887
Protoss_Zealot 1 3997
Protoss_Dragoon 12 9782
Protoss_Robotics_Facility 1 8031
Protoss_Citadel_of_Adun 1 8672
Protoss_Observatory 1 9713
Protoss_Forge 1 9949
9949
