Special_Protoss_Temple 30 0
Protoss_Nexus 2 6409
Protoss_Gateway 3 8390
Protoss_Assimilator 2 9621
Protoss_Cybernetics_Core 1 2987
Protoss_Dragoon 12 9875
Protoss_Robotics_Facility 1 6864
Protoss_Observatory 1 8241
Protoss_Observer 2 9419
Protoss_Zealot 1 9443
Protoss_Citadel_of_Adun 1 9709
9875
