Special_Protoss_Temple 30 0
Protoss_Nexus 3 4457
Protoss_Gateway 4 7837
Protoss_Zealot 4 9615
Protoss_Assimilator 2 8208
Protoss_Cybernetics_Core 1 5068
Protoss_Dragoon 8 9609
Protoss_Robotics_Facility 1 7656
Protoss_Observatory 1 9731
9731
