Protoss_Nexus 3 9076
Protoss_Gateway 4 9953
Protoss_Assimilator 1 2257
Protoss_Cybernetics_Core 1 2846
Protoss_Dragoon 9 9723
Protoss_Robotics_Facility 1 6288
Protoss_Observatory 1 7647
Protoss_Observer 3 9423
9953
