Special_Protoss_Temple 14 0
Protoss_Nexus 2 7189
Protoss_Gateway 2 3527
Protoss_Assimilator 2 8736
Protoss_Cybernetics_Core 1 3075
Protoss_Dragoon 10 9279
Protoss_Robotics_Facility 1 8485
Protoss_Observatory 1 9839
9839
