Protoss_Nexus 2 5609
Protoss_Gateway 5 8886
Protoss_Assimilator 1 2341
Protoss_Cybernetics_Core 1 2923
Protoss_Dragoon 10 9843
Protoss_Robotics_Facility 1 6102
Protoss_Shuttle 1 7535
Protoss_Observatory 1 7899
Protoss_Observer 1 8699
Protoss_Robotics_Support_Bay 1 9129
Protoss_Zealot 3 9553
9843
