Protoss_Nexus 1 0
Protoss_Gateway 2 3489
Protoss_Assimilator 2 2603
Protoss_Zealot 5 6266
Protoss_Cybernetics_Core 1 5363
Protoss_Robotics_Facility 1 6698
Protoss_Dragoon 5 9966
Protoss_Robotics_Support_Bay 1 8903
Protoss_Citadel_of_Adun 1 9142
9966
