Protoss_Nexus 2 7929
Protoss_Gateway 2 8107
Protoss_Assimilator 2 8747
Protoss_Cybernetics_Core 1 2825
Protoss_Zealot 1 3095
Protoss_Dragoon 9 9925
Protoss_Citadel_of_Adun 1 5253
Protoss_Templar_Archives 1 6270
Protoss_Dark_Templar 1 7293
Protoss_Robotics_Facility 1 7938
Protoss_Observatory 1 9370
Protoss_Observer 1 9931
9931
