Special_Protoss_Temple 14 0
Protoss_Nexus 2 7333
Protoss_Gateway 2 3698
Protoss_Assimilator 2 9039
Protoss_Cybernetics_Core 1 3169
Protoss_Dragoon 8 9389
Protoss_Robotics_Facility 1 7791
Protoss_Observatory 1 9345
Protoss_Citadel_of_Adun 1 9685
Protoss_Observer 1 9913
9913
