Protoss_Nexus 2 6680
Protoss_Gateway 3 7608
Protoss_Assimilator 2 9408
Protoss_Cybernetics_Core 1 2840
Protoss_Zealot 1 3095
Protoss_Dragoon 10 9919
Protoss_Robotics_Facility 1 5366
Protoss_Observatory 1 6666
Protoss_Observer 4 9538
Protoss_Citadel_of_Adun 1 9318
9919
