Protoss_Nexus 3 9577
Protoss_Gateway 4 9451
Protoss_Assimilator 1 2127
Protoss_Zealot 2 3847
Protoss_Cybernetics_Core 1 3637
Protoss_Dragoon 10 9233
Protoss_Robotics_Facility 1 6341
Protoss_Observatory 1 7869
Protoss_Observer 3 9853
Protoss_Citadel_of_Adun 1 9327
9853
