Protoss_Nexus 2 7782
Protoss_Gateway 2 5987
Protoss_Assimilator 1 2377
Protoss_Cybernetics_Core 1 2933
Protoss_Dragoon 12 9721
Protoss_Robotics_Facility 1 5583
Protoss_Observatory 1 6982
Protoss_Observer 3 9523
9721
