Protoss_Nexus 2 8656
Protoss_Gateway 2 6088
Protoss_Assimilator 1 2389
Protoss_Cybernetics_Core 1 3037
Protoss_Dragoon 9 9575
Protoss_Robotics_Facility 1 4494
Protoss_Zealot 1 5667
Protoss_Observatory 1 5855
Protoss_Observer 3 9363
Protoss_Citadel_of_Adun 1 9265
9575
