Protoss_Nexus 2 6047
Protoss_Gateway 2 7646
Protoss_Assimilator 1 2579
Protoss_Zealot 1 2997
Protoss_Cybernetics_Core 1 3589
Protoss_Dragoon 7 8939
Protoss_Robotics_Facility 1 7170
Protoss_Forge 1 8351
Protoss_Observatory 1 8835
Protoss_Citadel_of_Adun 1 9883
9883
