Protoss_Nexus 3 8485
Protoss_Gateway 3 9858
Protoss_Zealot 1 2809
Protoss_Assimilator 1 3133
Protoss_Cybernetics_Core 1 3991
Protoss_Dragoon 7 9231
Protoss_Robotics_Facility 1 7967
Protoss_Observatory 1 9478
9858
