Protoss_Nexus 2 8510
Protoss_Gateway 1 1846
Protoss_Assimilator 1 2246
Protoss_Cybernetics_Core 1 2911
Protoss_Zealot 1 3197
Protoss_Dragoon 8 9769
Protoss_Robotics_Facility 1 5720
Protoss_Shuttle 1 7299
Protoss_Robotics_Support_Bay 1 7916
Protoss_Reaver 1 8535
Protoss_Observatory 1 8649
Protoss_Observer 1 9587
9769
