Protoss_Nexus 3 7113
Protoss_Gateway 4 9179
Protoss_Assimilator 1 2319
Protoss_Cybernetics_Core 1 2892
Protoss_Dragoon 8 9589
Protoss_Robotics_Facility 1 7407
Protoss_Citadel_of_Adun 1 8391
Protoss_Observatory 1 8892
Protoss_Observer 1 9625
Protoss_Templar_Archives 1 9656
Protoss_Stargate 1 9926
9926
