Protoss_Nexus 2 8306
Protoss_Gateway 2 5985
Protoss_Assimilator 1 2274
Protoss_Zealot 3 4137
Protoss_Cybernetics_Core 1 3789
Protoss_Dragoon 10 9623
Protoss_Robotics_Facility 1 5855
Protoss_Observatory 1 7302
Protoss_Observer 1 8243
Protoss_Citadel_of_Adun 1 8833
9623
