Protoss_Nexus 2 4951
Protoss_Gateway 2 5881
Protoss_Assimilator 3 9959
Protoss_Zealot 2 6015
Protoss_Cybernetics_Core 1 5323
Protoss_Dragoon 9 9729
Protoss_Robotics_Facility 1 9666
9959
