Special_Protoss_Temple 14 0
Protoss_Nexus 1 0
Protoss_Gateway 2 5522
Protoss_Assimilator 1 2386
Protoss_Cybernetics_Core 1 2999
Protoss_Zealot 1 3411
Protoss_Dragoon 5 8169
Protoss_Shield_Battery 1 5414
8169
