Protoss_Nexus 3 9441
Protoss_Gateway 3 5988
Protoss_Assimilator 1 2359
Protoss_Cybernetics_Core 1 2880
Protoss_Dragoon 8 8149
Protoss_Zealot 2 7171
Protoss_Robotics_Facility 1 4776
Protoss_Observatory 1 6195
Protoss_Observer 1 7051
9441
