Protoss_Nexus 1 0
Protoss_Gateway 2 5650
Protoss_Assimilator 1 2519
Protoss_Cybernetics_Core 1 3251
Protoss_Zealot 1 3401
Protoss_Dragoon 12 9777
Protoss_Robotics_Facility 1 6892
Protoss_Shuttle 1 8181
Protoss_Robotics_Support_Bay 1 8391
Protoss_Reaver 1 9185
9777
