Protoss_Nexus 3 6494
Protoss_Gateway 2 7725
Protoss_Assimilator 2 8823
Protoss_Zealot 2 4921
Protoss_Cybernetics_Core 1 4248
Protoss_Dragoon 7 9741
Protoss_Robotics_Facility 1 7943
Protoss_Citadel_of_Adun 1 8403
Protoss_Observatory 1 9309
Protoss_Templar_Archives 1 9442
Protoss_Shuttle 1 9545
9741
