Protoss_Nexus 2 2741
Protoss_Gateway 3 9582
Protoss_Assimilator 1 3559
Protoss_Cybernetics_Core 1 4193
Protoss_Zealot 1 4397
Protoss_Dragoon 7 8723
Protoss_Robotics_Facility 1 7520
Protoss_Shuttle 1 8837
Protoss_Robotics_Support_Bay 1 9244
Protoss_Reaver 1 9871
9871
