Protoss_Nexus 2 9612
Protoss_Gateway 1 1837
Protoss_Assimilator 1 2231
Protoss_Cybernetics_Core 1 2902
Protoss_Zealot 1 3061
Protoss_Dragoon 8 9261
Protoss_Robotics_Facility 1 5913
Protoss_Shuttle 1 7307
Protoss_Robotics_Support_Bay 1 7362
Protoss_Reaver 1 8209
Protoss_Observatory 1 9776
9776
