Special_Protoss_Temple 14 0
Protoss_Nexus 2 5799
Protoss_Gateway 3 8113
Protoss_Assimilator 2 9071
Protoss_Cybernetics_Core 1 2912
Protoss_Dragoon 10 9647
Protoss_Robotics_Facility 1 7122
Protoss_Zealot 1 8383
Protoss_Citadel_of_Adun 1 8798
Protoss_Observatory 1 8853
Protoss_Observer 1 9385
Protoss_Templar_Archives 1 9971
9971
