Protoss_Nexus 2 2627
Protoss_Gateway 2 4157
Protoss_Assimilator 2 8703
Protoss_Cybernetics_Core 1 3969
Protoss_Zealot 2 6036
Protoss_Dragoon 10 9551
Protoss_Robotics_Facility 1 8000
Protoss_Observatory 1 9366
Protoss_Citadel_of_Adun 1 9421
Protoss_Observer 1 9949
9949
