Protoss_Nexus 2 7079
Protoss_Gateway 4 8424
Protoss_Assimilator 1 2293
Protoss_Cybernetics_Core 1 2966
Protoss_Dragoon 10 9367
Protoss_Robotics_Facility 1 4410
Protoss_Zealot 1 5453
Protoss_Observatory 1 5824
Protoss_Observer 2 6971
Protoss_Shuttle 1 9847
9847
