Protoss_Nexus 2 7368
Protoss_Gateway 5 9783
Protoss_Assimilator 1 2315
Protoss_Cybernetics_Core 1 3012
Protoss_Dragoon 7 9905
Protoss_Robotics_Facility 1 4474
Protoss_Zealot 4 8943
Protoss_Observatory 1 5885
Protoss_Observer 2 7031
Protoss_Shuttle 1 8873
Protoss_Citadel_of_Adun 1 9162
9905
