Special_Protoss_Temple 14 0
Protoss_Nexus 2 2681
Protoss_Gateway 2 4062
Protoss_Assimilator 2 9905
Protoss_Cybernetics_Core 1 4139
Protoss_Zealot 4 7733
Protoss_Dragoon 9 9945
Protoss_Robotics_Facility 1 9475
9945
