Protoss_Nexus 2 8010
Protoss_Gateway 3 9677
Protoss_Assimilator 1 2364
Protoss_Cybernetics_Core 1 2985
Protoss_Dragoon 7 9933
Protoss_Robotics_Facility 1 4327
Protoss_Shuttle 1 5779
Protoss_Zealot 2 6853
Protoss_Robotics_Support_Bay 1 6479
Protoss_Reaver 1 7089
Protoss_Observatory 1 8618
Protoss_Observer 1 9177
Protoss_Scarab 2 9571
Protoss_Citadel_of_Adun 1 9984
9984
