Protoss_Nexus 2 6525
Protoss_Gateway 2 7118
Protoss_Assimilator 1 2345
Protoss_Cybernetics_Core 1 2988
Protoss_Zealot 1 3141
Protoss_Dragoon 10 9623
Protoss_Robotics_Facility 1 7524
Protoss_Observatory 1 9541
9623
