Protoss_Nexus 2 6036
Protoss_Assimilator 2 8127
Protoss_Gateway 2 6961
Protoss_Cybernetics_Core 1 3273
Protoss_Zealot 1 3561
Protoss_Dragoon 6 9857
Protoss_Citadel_of_Adun 1 6465
Protoss_Robotics_Facility 1 7379
Protoss_Templar_Archives 1 7587
Protoss_Shuttle 1 8665
Protoss_Dark_Templar 2 8847
Protoss_Observatory 2 9463
Protoss_Stargate 1 9418
Protoss_Observer 1 9567
9857
