Protoss_Nexus 2 6937
Protoss_Gateway 2 7746
Protoss_Assimilator 1 2184
Protoss_Cybernetics_Core 1 2843
Protoss_Dragoon 9 9751
Protoss_Zealot 1 4737
Protoss_Robotics_Facility 1 4871
Protoss_Observatory 1 6213
Protoss_Observer 3 8223
9751
