Protoss_Nexus 3 9754
Protoss_Gateway 2 5175
Protoss_Assimilator 1 2531
Protoss_Zealot 2 3695
Protoss_Cybernetics_Core 1 3525
Protoss_Dragoon 10 9189
Protoss_Robotics_Facility 1 8627
9754
