Protoss_Nexus 2 5826
Protoss_Gateway 3 7603
Protoss_Assimilator 2 8405
Protoss_Cybernetics_Core 1 2935
Protoss_Dragoon 10 9635
Protoss_Robotics_Facility 1 7094
Protoss_Observatory 1 8475
Protoss_Citadel_of_Adun 1 8500
Protoss_Observer 1 9099
Protoss_Templar_Archives 1 9719
Protoss_Zealot 1 9785
9785
