Protoss_Nexus 1 0
Protoss_Gateway 2 5917
Protoss_Assimilator 1 2403
Protoss_Cybernetics_Core 1 3176
Protoss_Robotics_Facility 1 4233
Protoss_Dragoon 7 9386
Protoss_Observatory 1 5603
Protoss_Observer 2 6753
Protoss_Zealot 2 7063
Protoss_Shuttle 1 7611
Protoss_Robotics_Support_Bay 1 8568
9386
