Protoss_Nexus 1 0
Protoss_Assimilator 1 1793
Protoss_Gateway 2 6039
Protoss_Cybernetics_Core 1 3313
Protoss_Robotics_Facility 1 4418
Protoss_Dragoon 6 9041
Protoss_Observatory 1 5796
Protoss_Observer 3 8558
Protoss_Shuttle 1 7656
Protoss_Forge 1 8103
Protoss_Robotics_Support_Bay 1 8392
Protoss_Photon_Cannon 1 8930
Protoss_Reaver 1 9160
9160
