Protoss_Nexus 3 8407
Protoss_Gateway 4 8888
Protoss_Assimilator 1 2223
Protoss_Cybernetics_Core 1 2842
Protoss_Robotics_Facility 1 4018
Protoss_Dragoon 8 9983
Protoss_Observatory 1 5388
Protoss_Observer 4 9621
9983
