Protoss_Nexus 3 9819
Protoss_Gateway 3 7465
Protoss_Assimilator 2 9292
Protoss_Cybernetics_Core 1 2845
Protoss_Dragoon 11 9295
Protoss_Robotics_Facility 1 6901
Protoss_Observatory 1 8333
Protoss_Observer 2 9471
9819
