Special_Protoss_Temple 14 0
Protoss_Nexus 2 5451
Protoss_Gateway 2 8157
Protoss_Assimilator 1 2421
Protoss_Cybernetics_Core 1 2979
Protoss_Zealot 2 8585
Protoss_Dragoon 6 9237
Protoss_Robotics_Facility 1 5878
Protoss_Shuttle 1 7327
Protoss_Robotics_Support_Bay 1 7779
Protoss_Reaver 1 8307
Protoss_Observatory 1 8715
Protoss_Observer 1 9359
9359
