Protoss_Nexus 2 6959
Protoss_Gateway 2 4114
Protoss_Assimilator 1 2374
Protoss_Zealot 4 8717
Protoss_Cybernetics_Core 1 3670
Protoss_Dragoon 8 9319
Protoss_Robotics_Facility 1 7439
Protoss_Shuttle 1 8885
Protoss_Robotics_Support_Bay 1 9137
Protoss_Reaver 1 9787
9787
