Protoss_Nexus 1 0
Protoss_Gateway 1 2119
Protoss_Assimilator 1 2660
Protoss_Zealot 2 4801
Protoss_Cybernetics_Core 1 4199
Protoss_Robotics_Facility 1 5458
Protoss_Dragoon 2 7101
Protoss_Observatory 1 6758
Protoss_Shuttle 1 6771
Protoss_Forge 1 6892
Protoss_Observer 1 7673
Protoss_Robotics_Support_Bay 1 7723
Protoss_Reaver 1 8306
Protoss_Photon_Cannon 1 8740
8740
