Protoss_Nexus 2 9370
Protoss_Gateway 2 9913
Protoss_Assimilator 1 2486
Protoss_Cybernetics_Core 1 3017
Protoss_Zealot 1 3299
Protoss_Robotics_Facility 1 4376
Protoss_Dragoon 6 9895
Protoss_Shuttle 1 5667
Protoss_Robotics_Support_Bay 1 6022
Protoss_Reaver 1 6871
Protoss_Observatory 1 7574
Protoss_Observer 2 9199
Protoss_Scarab 10 9966
9966
