Protoss_Nexus 2 5751
Protoss_Gateway 5 9454
Protoss_Assimilator 2 8247
Protoss_Cybernetics_Core 1 2937
Protoss_Dragoon 7 8607
Protoss_Robotics_Facility 1 6049
Protoss_Observatory 1 7483
Protoss_Citadel_of_Adun 1 7827
Protoss_Observer 1 8155
Protoss_Templar_Archives 1 9249
Protoss_Zealot 3 9973
9973
