Protoss_Nexus 2 9358
Protoss_Gateway 2 5724
Protoss_Assimilator 1 2622
Protoss_Cybernetics_Core 1 3356
Protoss_Dragoon 9 9966
Protoss_Robotics_Facility 1 5264
Protoss_Observatory 1 6851
Protoss_Observer 2 8201
Protoss_Shuttle 1 8803
9966
