Protoss_Nexus 2 2619
Protoss_Gateway 2 4267
Protoss_Assimilator 2 7525
Protoss_Cybernetics_Core 1 4093
Protoss_Zealot 1 4523
Protoss_Dragoon 11 9247
Protoss_Robotics_Facility 1 7053
Protoss_Citadel_of_Adun 1 8357
Protoss_Shuttle 1 8409
Protoss_Robotics_Support_Bay 1 9113
Protoss_Templar_Archives 1 9395
Protoss_Stargate 1 9529
Protoss_Reaver 1 9649
9649
