Protoss_Nexus 3 7330
Protoss_Gateway 2 4815
Protoss_Zealot 1 3127
Protoss_Assimilator 2 7050
Protoss_Cybernetics_Core 1 4138
Protoss_Dragoon 7 8796
Protoss_Robotics_Facility 1 6825
Protoss_Observatory 1 8275
Protoss_Observer 2 9431
Protoss_Citadel_of_Adun 1 9029
Protoss_Forge 1 9096
Protoss_Stargate 1 9708
Protoss_Photon_Cannon 1 9996
9996
