Protoss_Nexus 2 8255
Protoss_Gateway 4 9427
Protoss_Assimilator 1 2433
Protoss_Cybernetics_Core 1 3226
Protoss_Robotics_Facility 1 4289
Protoss_Observatory 1 5616
Protoss_Dragoon 8 9527
Protoss_Observer 3 8525
Protoss_Shuttle 1 7021
9527
