Protoss_Nexus 2 9556
Protoss_Gateway 2 6192
Protoss_Assimilator 1 2588
Protoss_Cybernetics_Core 1 3074
Protoss_Dragoon 4 9011
Protoss_Citadel_of_Adun 1 5028
Protoss_Templar_Archives 1 6023
Protoss_Robotics_Facility 1 6565
Protoss_Dark_Templar 3 7763
Protoss_Shuttle 1 7946
Protoss_Observatory 1 8378
Protoss_Observer 1 8961
9556
