Protoss_Nexus 2 2713
Protoss_Gateway 4 9598
Protoss_Assimilator 2 6749
Protoss_Cybernetics_Core 1 4071
Protoss_Zealot 1 4759
Protoss_Dragoon 12 9767
Protoss_Robotics_Facility 1 7523
Protoss_Observatory 1 9039
Protoss_Citadel_of_Adun 1 9139
Protoss_Observer 1 9723
9767
