Protoss_Nexus 1 0
Protoss_Gateway 2 8555
Protoss_Assimilator 1 2517
Protoss_Cybernetics_Core 1 3232
Protoss_Dragoon 7 9846
Protoss_Robotics_Facility 1 4860
Protoss_Shuttle 2 9991
Protoss_Robotics_Support_Bay 1 6383
Protoss_Reaver 1 7053
Protoss_Observatory 1 7176
Protoss_Observer 1 8376
Protoss_Scarab 7 9615
9991
