Protoss_Nexus 2 4803
Protoss_Assimilator 3 7964
Protoss_Gateway 2 5613
Protoss_Zealot 3 4913
Protoss_Cybernetics_Core 1 5303
Protoss_Dragoon 8 8857
Protoss_Stargate 2 9909
Protoss_Fleet_Beacon 1 9587
9909
