Protoss_Nexus 2 6247
Protoss_Gateway 2 7438
Protoss_Assimilator 1 2433
Protoss_Cybernetics_Core 1 2899
Protoss_Zealot 2 9483
Protoss_Dragoon 9 9929
Protoss_Robotics_Facility 1 7099
Protoss_Shuttle 1 8403
Protoss_Robotics_Support_Bay 1 8778
Protoss_Reaver 1 9445
Protoss_Observatory 1 9833
9929
