Protoss_Nexus 2 9443
Protoss_Gateway 2 6805
Protoss_Assimilator 1 2362
Protoss_Cybernetics_Core 1 3084
Protoss_Dragoon 10 9876
Protoss_Robotics_Facility 1 5298
Protoss_Observatory 1 6621
Protoss_Observer 3 9598
Protoss_Shuttle 1 8696
9876
