Protoss_Nexus 3 8807
Protoss_Gateway 2 4139
Protoss_Assimilator 1 3365
Protoss_Cybernetics_Core 1 4050
Protoss_Zealot 2 8508
Protoss_Dragoon 10 9385
Protoss_Robotics_Facility 1 8310
Protoss_Shuttle 1 9615
9615
