Protoss_Nexus 1 0
Protoss_Gateway 2 4201
Protoss_Assimilator 1 2385
Protoss_Cybernetics_Core 1 3629
Protoss_Dragoon 6 9239
Protoss_Citadel_of_Adun 1 6649
Protoss_Robotics_Facility 1 6996
Protoss_Observatory 1 8322
Protoss_Zealot 2 8563
Protoss_Observer 2 9505
Protoss_Forge 1 9436
9505
