Protoss_Nexus 2 8942
Protoss_Gateway 4 9978
Protoss_Assimilator 1 2706
Protoss_Zealot 1 3081
Protoss_Cybernetics_Core 1 3403
Protoss_Dragoon 7 9691
Protoss_Robotics_Facility 1 6157
Protoss_Observatory 1 7488
Protoss_Observer 2 8736
Protoss_Shuttle 1 9436
9978
