Protoss_Nexus 2 2647
Protoss_Gateway 5 9179
Protoss_Assimilator 2 4737
Protoss_Cybernetics_Core 1 4211
Protoss_Dragoon 8 9493
Protoss_Robotics_Facility 1 6221
Protoss_Citadel_of_Adun 1 6829
Protoss_Observatory 1 7545
Protoss_Templar_Archives 1 7889
Protoss_Observer 4 9903
Protoss_Stargate 1 8102
Protoss_Dark_Templar 2 9247
9903
