Protoss_Nexus 3 9081
Protoss_Gateway 3 5441
Protoss_Assimilator 2 3950
Protoss_Cybernetics_Core 1 2884
Protoss_Dragoon 5 6451
Protoss_Robotics_Facility 1 7835
Protoss_Citadel_of_Adun 1 8510
Protoss_Shuttle 1 9117
Protoss_Robotics_Support_Bay 1 9484
Protoss_Templar_Archives 1 9738
9738
