Protoss_Nexus 2 8405
Protoss_Gateway 2 4859
Protoss_Assimilator 1 2375
Protoss_Cybernetics_Core 1 3015
Protoss_Dragoon 6 6959
Protoss_Citadel_of_Adun 1 5518
Protoss_Templar_Archives 1 6753
Protoss_Dark_Templar 3 8493
Protoss_Robotics_Facility 1 9503
9503
