Protoss_Nexus 2 9610
Protoss_Gateway 2 3584
Protoss_Assimilator 1 2269
Protoss_Cybernetics_Core 1 2939
Protoss_Dragoon 10 9085
Protoss_Robotics_Facility 1 6751
Protoss_Observatory 1 8172
Protoss_Zealot 2 8483
Protoss_Observer 1 8975
Protoss_Robotics_Support_Bay 1 9871
9871
