Protoss_Nexus 2 9436
Protoss_Gateway 2 6122
Protoss_Assimilator 1 2733
Protoss_Cybernetics_Core 1 3298
Protoss_Dragoon 8 9951
Protoss_Robotics_Facility 1 5758
Protoss_Shuttle 1 7046
Protoss_Observatory 1 7126
Protoss_Observer 2 8666
Protoss_Citadel_of_Adun 1 8093
9951
