Protoss_Nexus 1 0
Protoss_Gateway 3 6631
Protoss_Assimilator 1 2488
Protoss_Cybernetics_Core 1 3116
Protoss_Dragoon 9 9581
Protoss_Robotics_Facility 1 5549
Protoss_Observatory 1 6943
Protoss_Zealot 4 8031
Protoss_Observer 2 9586
Protoss_Shuttle 1 8381
9586
