Protoss_Nexus 3 9073
Protoss_Gateway 2 6741
Protoss_Assimilator 1 2473
Protoss_Cybernetics_Core 1 3023
Protoss_Dragoon 10 9731
Protoss_Robotics_Facility 1 6581
Protoss_Observatory 1 8071
Protoss_Observer 2 9947
Protoss_Citadel_of_Adun 1 9910
9947
