Protoss_Nexus 2 9177
Protoss_Gateway 1 2111
Protoss_Assimilator 1 2358
Protoss_Cybernetics_Core 1 3128
Protoss_Dragoon 6 9329
Protoss_Robotics_Facility 1 5375
Protoss_Zealot 2 7089
Protoss_Shuttle 1 6655
Protoss_Observatory 1 6741
Protoss_Robotics_Support_Bay 1 7430
Protoss_Observer 2 9497
Protoss_Reaver 1 8250
9497
