Protoss_Nexus 1 0
Protoss_Gateway 2 8951
Protoss_Assimilator 1 2300
Protoss_Cybernetics_Core 1 2853
Protoss_Dragoon 8 9937
Protoss_Robotics_Facility 1 4871
Protoss_Shuttle 1 6181
Protoss_Robotics_Support_Bay 1 6290
Protoss_Reaver 2 9363
Protoss_Scarab 10 9692
Protoss_Observatory 1 9474
9937
