Protoss_Nexus 2 7060
Protoss_Gateway 1 1819
Protoss_Assimilator 1 2197
Protoss_Cybernetics_Core 1 2845
Protoss_Dragoon 6 9423
Protoss_Robotics_Facility 1 5307
Protoss_Observatory 1 6642
Protoss_Observer 2 7777
Protoss_Robotics_Support_Bay 1 7797
Protoss_Zealot 2 8579
Protoss_Shuttle 1 8393
Protoss_Reaver 1 9295
9423
