Protoss_Nexus 2 8830
Protoss_Gateway 2 7320
Protoss_Assimilator 1 2468
Protoss_Cybernetics_Core 1 3168
Protoss_Dragoon 7 8361
Protoss_Robotics_Facility 1 4730
Protoss_Observatory 1 6148
Protoss_Observer 3 9051
Protoss_Zealot 2 9626
Protoss_Shuttle 1 9956
9956
