Protoss_Nexus 1 0
Protoss_Gateway 2 7052
Protoss_Assimilator 1 2548
Protoss_Zealot 1 3051
Protoss_Cybernetics_Core 1 3284
Protoss_Dragoon 6 9841
Protoss_Robotics_Facility 1 4738
Protoss_Shuttle 1 6051
Protoss_Robotics_Support_Bay 1 6113
Protoss_Reaver 2 8616
Protoss_Observatory 1 7533
Protoss_Scarab 1 9060
Protoss_Observer 1 9806
9841
