Protoss_Nexus 1 0
Protoss_Gateway 2 6146
Protoss_Assimilator 1 2660
Protoss_Cybernetics_Core 1 3098
Protoss_Dragoon 4 7246
Protoss_Robotics_Facility 1 5528
Protoss_Robotics_Support_Bay 1 6873
Protoss_Shuttle 1 6901
Protoss_Observatory 1 8527
8527
