Protoss_Nexus 3 6611
Protoss_Gateway 6 9885
Protoss_Assimilator 1 2253
Protoss_Cybernetics_Core 1 3035
Protoss_Dragoon 9 9929
Protoss_Robotics_Facility 1 7356
Protoss_Observatory 1 8786
Protoss_Observer 1 9355
Protoss_Citadel_of_Adun 1 9708
9929
