Protoss_Nexus 2 9092
Protoss_Gateway 2 6057
Protoss_Assimilator 1 2431
Protoss_Cybernetics_Core 1 3065
Protoss_Dragoon 12 9561
Protoss_Robotics_Facility 1 5377
Protoss_Observatory 1 6765
Protoss_Observer 1 7413
9561
