Protoss_Nexus 3 8488
Protoss_Gateway 4 9205
Protoss_Assimilator 1 3297
Protoss_Cybernetics_Core 1 4052
Protoss_Zealot 1 4343
Protoss_Dragoon 9 9613
Protoss_Robotics_Facility 1 6402
Protoss_Observatory 1 7775
Protoss_Observer 3 9685
9685
