Protoss_Nexus 2 8228
Protoss_Gateway 2 9499
Protoss_Assimilator 1 2474
Protoss_Cybernetics_Core 1 3130
Protoss_Dragoon 2 9321
Protoss_Robotics_Facility 1 4533
Protoss_Shuttle 1 6086
Protoss_Robotics_Support_Bay 1 6159
Protoss_Zealot 2 7436
Protoss_Reaver 2 8471
Protoss_Observatory 1 7640
Protoss_Scarab 6 9895
9895
