Protoss_Nexus 2 8829
Protoss_Gateway 3 9131
Protoss_Assimilator 1 2163
Protoss_Zealot 2 3780
Protoss_Cybernetics_Core 1 3803
Protoss_Dragoon 9 8567
Protoss_Robotics_Facility 1 6667
Protoss_Observatory 1 7968
Protoss_Observer 2 9335
9335
