Protoss_Nexus 1 0
Protoss_Gateway 2 8852
Protoss_Assimilator 1 2499
Protoss_Cybernetics_Core 1 3049
Protoss_Dragoon 3 9258
Protoss_Robotics_Facility 1 4648
Protoss_Shuttle 1 6046
Protoss_Robotics_Support_Bay 1 6238
Protoss_Reaver 2 8048
Protoss_Observatory 1 7950
Protoss_Observer 2 9988
Protoss_Scarab 1 9992
9992
