Protoss_Nexus 1 0
Protoss_Gateway 3 8672
Protoss_Assimilator 1 2430
Protoss_Cybernetics_Core 1 2996
Protoss_Dragoon 8 9256
Protoss_Robotics_Facility 1 6288
Protoss_Zealot 4 8592
Protoss_Shuttle 1 7666
Protoss_Observatory 1 7986
Protoss_Observer 3 9772
9772
