Protoss_Nexus 2 8465
Protoss_Assimilator 1 1913
Protoss_Gateway 3 9693
Protoss_Cybernetics_Core 1 3428
Protoss_Citadel_of_Adun 1 4448
Protoss_Robotics_Facility 1 4678
Protoss_Dragoon 3 9241
Protoss_Templar_Archives 1 5608
Protoss_Shuttle 1 6201
Protoss_Dark_Templar 3 7353
Protoss_Observatory 1 7191
Protoss_Observer 1 7966
9693
