Protoss_Nexus 2 9811
Protoss_Gateway 1 1988
Protoss_Assimilator 1 2331
Protoss_Cybernetics_Core 1 3014
Protoss_Dragoon 7 9013
Protoss_Robotics_Facility 2 5896
Protoss_Shuttle 1 7361
Protoss_Robotics_Support_Bay 1 7541
Protoss_Reaver 2 9315
9811
