Protoss_Nexus 2 5694
Protoss_Gateway 3 6543
Protoss_Assimilator 2 8202
Protoss_Cybernetics_Core 1 2963
Protoss_Dragoon 9 9439
Protoss_Robotics_Facility 1 5991
Protoss_Observatory 1 7522
Protoss_Observer 3 9863
Protoss_Citadel_of_Adun 1 8420
Protoss_Templar_Archives 1 9506
Protoss_Stargate 1 9631
9863
