Protoss_Nexus 2 8119
Protoss_Gateway 3 6053
Protoss_Assimilator 1 2500
Protoss_Cybernetics_Core 1 3087
Protoss_Dragoon 6 9385
Protoss_Citadel_of_Adun 1 5303
Protoss_Templar_Archives 1 6289
Protoss_Dark_Templar 5 8513
9385
