Protoss_Nexus 1 0
Protoss_Gateway 2 3469
Protoss_Assimilator 2 3006
Protoss_Zealot 10 6966
Protoss_Cybernetics_Core 1 7218
Protoss_Robotics_Facility 1 8342
Protoss_Dragoon 4 9406
Protoss_Shuttle 1 9641
9641
