Protoss_Nexus 2 6591
Protoss_Gateway 2 5653
Protoss_Assimilator 2 9427
Protoss_Cybernetics_Core 1 3033
Protoss_Dragoon 10 9507
Protoss_Robotics_Facility 1 7673
Protoss_Zealot 2 8809
Protoss_Observatory 1 9003
Protoss_Shuttle 1 9183
Protoss_Observer 1 9623
9623
