Protoss_Nexus 2 9519
Protoss_Gateway 2 5852
Protoss_Assimilator 1 2402
Protoss_Cybernetics_Core 1 3163
Protoss_Robotics_Facility 1 4201
Protoss_Zealot 3 8711
Protoss_Observatory 1 5498
Protoss_Dragoon 8 9641
Protoss_Observer 4 8161
Protoss_Shuttle 1 8763
9641
