Protoss_Nexus 3 9571
Protoss_Gateway 1 2258
Protoss_Assimilator 1 2535
Protoss_Cybernetics_Core 1 3345
Protoss_Dragoon 5 9951
Protoss_Robotics_Facility 1 5843
Protoss_Shuttle 1 7201
Protoss_Zealot 1 7395
Protoss_Robotics_Support_Bay 1 7408
Protoss_Reaver 1 8103
Protoss_Observatory 1 9769
9951
