Protoss_Nexus 1 0
Protoss_Gateway 3 8649
Protoss_Assimilator 1 2215
Protoss_Cybernetics_Core 1 2948
Protoss_Dragoon 8 9961
Protoss_Robotics_Facility 1 4484
Protoss_Zealot 2 6131
Protoss_Shuttle 1 5771
Protoss_Robotics_Support_Bay 1 5923
Protoss_Reaver 1 6706
Protoss_Observatory 1 7412
Protoss_Observer 1 8301
Protoss_Scarab 2 8947
Protoss_Citadel_of_Adun 1 9660
9961
