Protoss_Nexus 3 9456
Protoss_Gateway 3 9740
Protoss_Assimilator 1 2237
Protoss_Cybernetics_Core 1 3083
Protoss_Dragoon 10 9961
Protoss_Robotics_Facility 1 6485
Protoss_Observatory 1 7782
Protoss_Observer 2 9271
9961
