Protoss_Nexus 3 9058
Protoss_Gateway 3 7772
Protoss_Assimilator 1 2529
Protoss_Cybernetics_Core 1 3386
Protoss_Dragoon 7 9226
Protoss_Citadel_of_Adun 1 4560
Protoss_Robotics_Facility 1 5328
Protoss_Observatory 1 6660
Protoss_Observer 4 9488
9488
