Protoss_Nexus 2 9558
Protoss_Gateway 3 9958
Protoss_Assimilator 1 2427
Protoss_Zealot 2 8251
Protoss_Cybernetics_Core 1 4205
Protoss_Dragoon 4 7457
Protoss_Stargate 1 6050
Protoss_Citadel_of_Adun 1 6755
Protoss_Scout 1 7196
Protoss_Templar_Archives 1 7932
Protoss_Dark_Templar 3 9706
9958
