Protoss_Nexus 3 9763
Protoss_Gateway 2 6019
Protoss_Assimilator 1 2359
Protoss_Cybernetics_Core 1 2893
Protoss_Dragoon 8 8716
Protoss_Robotics_Facility 1 5728
Protoss_Observatory 1 7075
Protoss_Observer 3 9353
9763
