Protoss_Nexus 2 9064
Protoss_Gateway 2 6112
Protoss_Assimilator 1 2344
Protoss_Cybernetics_Core 1 3004
Protoss_Dragoon 11 9978
Protoss_Robotics_Facility 1 5463
Protoss_Observatory 1 6924
Protoss_Observer 2 8666
9978
