Protoss_Nexus 2 7648
Protoss_Gateway 3 8768
Protoss_Assimilator 1 2393
Protoss_Cybernetics_Core 1 3145
Protoss_Dragoon 11 9406
Protoss_Robotics_Facility 1 7898
Protoss_Observatory 1 9498
9498
