Protoss_Nexus 2 7618
Protoss_Gateway 3 8374
Protoss_Assimilator 2 9371
Protoss_Cybernetics_Core 1 3380
Protoss_Dragoon 8 9878
Protoss_Citadel_of_Adun 1 6253
Protoss_Templar_Archives 1 7248
Protoss_Dark_Templar 2 8251
Protoss_Stargate 1 9503
Protoss_Zealot 1 9868
9878
