Protoss_Nexus 1 0
Protoss_Gateway 2 5751
Protoss_Assimilator 1 2593
Protoss_Cybernetics_Core 1 2978
Protoss_Dragoon 7 9468
Protoss_Robotics_Facility 1 4788
Protoss_Shuttle 1 6296
Protoss_Robotics_Support_Bay 1 6793
Protoss_Zealot 2 7166
Protoss_Reaver 1 7401
Protoss_Observatory 1 8109
Protoss_Observer 1 8651
Protoss_Scarab 6 9859
9859
