Protoss_Nexus 1 0
Protoss_Gateway 2 3603
Protoss_Assimilator 1 2498
Protoss_Cybernetics_Core 1 3222
Protoss_Dragoon 10 8093
Protoss_Robotics_Facility 1 6773
Protoss_Observatory 1 8203
Protoss_Shuttle 1 8486
Protoss_Zealot 4 9913
Protoss_Robotics_Support_Bay 1 9269
Protoss_Observer 1 9388
9913
