Protoss_Nexus 1 0
Protoss_Gateway 2 2483
Protoss_Zealot 8 8601
Protoss_Forge 1 4798
Protoss_Photon_Cannon 4 9054
Protoss_Assimilator 1 7240
Protoss_Cybernetics_Core 1 9257
9257
