Protoss_Nexus 1 0
Protoss_Gateway 3 7480
Protoss_Assimilator 1 2319
Protoss_Cybernetics_Core 1 3008
Protoss_Dragoon 11 8783
Protoss_Robotics_Facility 1 5530
Protoss_Observatory 1 6878
Protoss_Observer 1 7471
Protoss_Shuttle 1 9416
Protoss_Zealot 3 9626
9626
