Protoss_Nexus 2 8208
Protoss_Gateway 2 5953
Protoss_Assimilator 1 2318
Protoss_Cybernetics_Core 1 3168
Protoss_Dragoon 7 8671
Protoss_Robotics_Facility 1 4753
Protoss_Observatory 1 6413
Protoss_Observer 2 9861
9861
