Protoss_Nexus 2 9200
Protoss_Gateway 2 5898
Protoss_Assimilator 1 2305
Protoss_Cybernetics_Core 1 3090
Protoss_Dragoon 9 8603
Protoss_Robotics_Facility 1 4507
Protoss_Observatory 1 6270
Protoss_Observer 1 6811
Protoss_Stargate 2 9423
9423
