Protoss_Nexus 2 6343
Protoss_Gateway 3 7769
Protoss_Assimilator 1 2683
Protoss_Cybernetics_Core 1 3299
Protoss_Dragoon 9 9636
Protoss_Robotics_Facility 1 8552
Protoss_Observatory 1 9940
9940
