Protoss_Nexus 2 8209
Protoss_Gateway 2 5592
Protoss_Assimilator 1 2438
Protoss_Cybernetics_Core 1 3158
Protoss_Dragoon 10 9488
Protoss_Robotics_Facility 1 4584
Protoss_Observatory 1 5983
Protoss_Observer 2 8266
Protoss_Shuttle 1 9711
9711
