Protoss_Nexus 2 8203
Protoss_Gateway 2 6553
Protoss_Assimilator 1 2458
Protoss_Cybernetics_Core 1 3083
Protoss_Dragoon 10 9536
Protoss_Robotics_Facility 1 5920
Protoss_Observatory 1 7296
Protoss_Observer 2 9793
9793
