Protoss_Nexus 1 0
Protoss_Gateway 2 6307
Protoss_Assimilator 1 2721
Protoss_Cybernetics_Core 1 3341
Protoss_Dragoon 7 9907
Protoss_Robotics_Facility 1 5685
Protoss_Observatory 1 7283
9907
