Protoss_Nexus 2 9668
Protoss_Gateway 1 1979
Protoss_Assimilator 1 2511
Protoss_Cybernetics_Core 1 3243
Protoss_Robotics_Facility 1 4400
Protoss_Zealot 1 4526
Protoss_Dragoon 6 9995
Protoss_Robotics_Support_Bay 1 5708
Protoss_Reaver 1 6366
Protoss_Shuttle 2 9986
Protoss_Observatory 1 8165
Protoss_Scarab 2 9368
9995
