Protoss_Nexus 2 9738
Protoss_Gateway 2 6037
Protoss_Assimilator 1 2649
Protoss_Cybernetics_Core 1 3255
Protoss_Robotics_Facility 1 4354
Protoss_Dragoon 6 9199
Protoss_Observatory 1 5645
Protoss_Observer 1 6323
Protoss_Shuttle 2 8037
9738
