Protoss_Nexus 1 0
Protoss_Gateway 2 5615
Protoss_Assimilator 1 2533
Protoss_Zealot 4 7407
Protoss_Cybernetics_Core 1 3232
Protoss_Dragoon 9 9983
Protoss_Robotics_Facility 1 4807
Protoss_Observatory 1 6097
Protoss_Observer 3 9099
Protoss_Shuttle 1 7481
Protoss_Forge 1 8797
Protoss_Citadel_of_Adun 1 9834
9983
