Protoss_Nexus 2 6205
Protoss_Gateway 2 5270
Protoss_Assimilator 1 2457
Protoss_Cybernetics_Core 1 2918
Protoss_Dragoon 8 8876
Protoss_Zealot 5 9628
Protoss_Robotics_Facility 1 7043
Protoss_Observatory 1 8569
9628
