Protoss_Nexus 2 8671
Protoss_Gateway 2 4498
Protoss_Assimilator 1 2523
Protoss_Cybernetics_Core 1 3086
Protoss_Dragoon 8 7911
Protoss_Citadel_of_Adun 2 6946
Protoss_Templar_Archives 1 7978
Protoss_Dark_Templar 2 9046
Protoss_Zealot 2 9896
9896
