Protoss_Nexus 2 4978
Protoss_Gateway 4 9833
Protoss_Assimilator 1 2600
Protoss_Cybernetics_Core 1 2981
Protoss_Dragoon 11 9170
Protoss_Robotics_Facility 1 8570
Protoss_Observatory 1 9947
Protoss_Zealot 1 9996
9996
