Protoss_Nexus 2 8253
Protoss_Gateway 4 9825
Protoss_Assimilator 1 2574
Protoss_Cybernetics_Core 1 3363
Protoss_Dragoon 8 8871
Protoss_Zealot 2 6856
Protoss_Citadel_of_Adun 1 8532
Protoss_Robotics_Facility 1 9263
9825
