Protoss_Nexus 2 9863
Protoss_Gateway 2 4461
Protoss_Assimilator 1 2458
Protoss_Zealot 2 4031
Protoss_Cybernetics_Core 1 3828
Protoss_Dragoon 11 9175
Protoss_Robotics_Facility 1 6990
Protoss_Observatory 1 8480
Protoss_Observer 2 9663
9863
