Protoss_Nexus 1 0
Protoss_Gateway 3 8433
Protoss_Assimilator 1 2529
Protoss_Cybernetics_Core 1 3233
Protoss_Dragoon 9 9837
Protoss_Robotics_Facility 1 4773
Protoss_Observatory 1 6125
Protoss_Observer 2 7339
Protoss_Shuttle 1 9105
9837
