Protoss_Nexus 1 0
Protoss_Gateway 2 6903
Protoss_Assimilator 1 2568
Protoss_Cybernetics_Core 1 3179
Protoss_Zealot 1 3496
Protoss_Dragoon 9 9191
Protoss_Robotics_Facility 1 6308
Protoss_Observatory 1 7608
Protoss_Observer 2 9636
9636
