Protoss_Nexus 2 7423
Protoss_Gateway 4 9513
Protoss_Assimilator 2 9315
Protoss_Cybernetics_Core 1 2983
Protoss_Dragoon 5 9763
Protoss_Zealot 1 4718
Protoss_Citadel_of_Adun 1 4915
Protoss_Templar_Archives 1 6168
Protoss_Dark_Templar 5 9011
9763
