Protoss_Nexus 2 8633
Protoss_Gateway 3 9522
Protoss_Assimilator 1 2478
Protoss_Cybernetics_Core 1 3121
Protoss_Dragoon 10 9611
Protoss_Robotics_Facility 1 7024
Protoss_Observatory 1 8515
Protoss_Observer 2 9716
9716
