Protoss_Nexus 1 0
Protoss_Gateway 2 5751
Protoss_Assimilator 1 2581
Protoss_Cybernetics_Core 1 3111
Protoss_Zealot 1 3446
Protoss_Dragoon 11 9226
Protoss_Robotics_Facility 1 7893
Protoss_Observatory 1 9193
Protoss_Observer 1 9731
9731
