Protoss_Nexus 2 6191
Protoss_Gateway 3 7889
Protoss_Assimilator 1 2634
Protoss_Cybernetics_Core 1 3457
Protoss_Dragoon 10 9576
Protoss_Robotics_Facility 1 6608
Protoss_Observatory 1 8024
Protoss_Observer 2 9261
Protoss_Citadel_of_Adun 1 9148
9576
