Protoss_Nexus 2 8727
Protoss_Gateway 2 5813
Protoss_Assimilator 1 2534
Protoss_Cybernetics_Core 1 3159
Protoss_Dragoon 6 9763
Protoss_Citadel_of_Adun 1 5555
Protoss_Templar_Archives 1 6608
Protoss_Zealot 1 7046
Protoss_Dark_Templar 4 9011
9763
