Protoss_Nexus 2 9538
Protoss_Gateway 2 3929
Protoss_Assimilator 1 2245
Protoss_Cybernetics_Core 1 2976
Protoss_Dragoon 7 7186
Protoss_Citadel_of_Adun 1 5565
Protoss_Templar_Archives 1 6768
Protoss_Dark_Templar 4 9370
Protoss_Zealot 1 8768
Protoss_Robotics_Facility 1 9918
9918
