Protoss_Nexus 2 9098
Protoss_Gateway 2 3479
Protoss_Assimilator 1 2447
Protoss_Cybernetics_Core 1 2948
Protoss_Dragoon 7 6866
Protoss_Zealot 3 7706
Protoss_Citadel_of_Adun 1 6253
Protoss_Templar_Archives 1 7323
Protoss_Dark_Templar 2 8401
9098
