Protoss_Nexus 2 6356
Protoss_Gateway 5 9483
Protoss_Assimilator 1 2519
Protoss_Cybernetics_Core 1 3064
Protoss_Dragoon 9 9786
Protoss_Zealot 2 9846
Protoss_Robotics_Facility 1 7513
Protoss_Observatory 1 8838
Protoss_Citadel_of_Adun 1 9337
Protoss_Observer 1 9741
9846
