Protoss_Nexus 2 9323
Protoss_Gateway 2 8290
Protoss_Assimilator 1 2475
Protoss_Cybernetics_Core 1 3068
Protoss_Dragoon 4 8086
Protoss_Robotics_Facility 1 4453
Protoss_Zealot 2 7481
Protoss_Shuttle 1 5816
Protoss_Observatory 1 5935
Protoss_Robotics_Support_Bay 1 6483
Protoss_Observer 2 8373
Protoss_Reaver 1 7321
Protoss_Scarab 7 9966
9966
