Protoss_Nexus 2 8231
Protoss_Gateway 2 4513
Protoss_Assimilator 1 2253
Protoss_Cybernetics_Core 1 2928
Protoss_Dragoon 11 9955
Protoss_Robotics_Facility 1 6488
Protoss_Shuttle 1 7961
Protoss_Robotics_Support_Bay 1 8359
Protoss_Reaver 1 8896
Protoss_Observatory 1 9501
9955
