Protoss_Nexus 2 8278
Protoss_Gateway 2 5727
Protoss_Assimilator 1 2318
Protoss_Cybernetics_Core 1 2978
Protoss_Dragoon 8 9448
Protoss_Citadel_of_Adun 1 5519
Protoss_Templar_Archives 1 6663
Protoss_Zealot 1 6811
Protoss_Dark_Templar 2 7751
Protoss_Stargate 1 9642
9642
