Protoss_Nexus 2 8358
Protoss_Assimilator 1 1391
Protoss_Gateway 2 6315
Protoss_Cybernetics_Core 1 3436
Protoss_Dragoon 6 9611
Protoss_Citadel_of_Adun 1 5884
Protoss_Templar_Archives 1 6908
Protoss_Dark_Templar 2 8068
Protoss_Robotics_Facility 1 8959
9611
