Protoss_Nexus 2 8433
Protoss_Gateway 3 9506
Protoss_Assimilator 1 2450
Protoss_Cybernetics_Core 1 3300
Protoss_Dragoon 12 9801
Protoss_Robotics_Facility 1 4953
Protoss_Observatory 1 6268
Protoss_Observer 2 7428
9801
