Protoss_Nexus 2 8158
Protoss_Gateway 3 9135
Protoss_Assimilator 1 2580
Protoss_Cybernetics_Core 1 3281
Protoss_Dragoon 11 9976
Protoss_Robotics_Facility 1 4884
Protoss_Observatory 1 6448
Protoss_Observer 2 8276
9976
