Protoss_Nexus 2 7300
Protoss_Gateway 4 9178
Protoss_Assimilator 1 2413
Protoss_Cybernetics_Core 1 3038
Protoss_Dragoon 10 8807
Protoss_Robotics_Facility 1 8081
Protoss_Observatory 1 9496
9496
