Protoss_Nexus 2 9816
Protoss_Gateway 3 7910
Protoss_Assimilator 1 2430
Protoss_Cybernetics_Core 1 3059
Protoss_Dragoon 9 9259
Protoss_Robotics_Facility 1 4585
Protoss_Shuttle 1 6141
Protoss_Observatory 1 6335
Protoss_Observer 3 9419
9816
