Protoss_Nexus 2 8973
Protoss_Gateway 2 9604
Protoss_Assimilator 1 2453
Protoss_Cybernetics_Core 1 3147
Protoss_Zealot 2 6691
Protoss_Dragoon 6 9408
Protoss_Robotics_Facility 1 4659
Protoss_Shuttle 1 6076
Protoss_Robotics_Support_Bay 1 6278
Protoss_Reaver 1 6978
Protoss_Observatory 1 7414
Protoss_Observer 2 9676
9676
