Protoss_Nexus 3 8621
Protoss_Gateway 4 9805
Protoss_Assimilator 1 2475
Protoss_Cybernetics_Core 1 3291
Protoss_Dragoon 8 9507
Protoss_Robotics_Facility 1 4619
Protoss_Observatory 1 6515
Protoss_Observer 2 7803
9805
