Protoss_Nexus 1 0
Protoss_Gateway 2 6123
Protoss_Assimilator 1 2619
Protoss_Zealot 3 4316
Protoss_Cybernetics_Core 1 4717
Protoss_Dragoon 8 9140
Protoss_Robotics_Facility 1 8625
Protoss_Observatory 1 9934
9934
