Protoss_Nexus 2 8757
Protoss_Gateway 2 5636
Protoss_Assimilator 1 2514
Protoss_Cybernetics_Core 1 3227
Protoss_Dragoon 8 9711
Protoss_Robotics_Facility 1 4988
Protoss_Observatory 1 6297
Protoss_Observer 2 7438
Protoss_Citadel_of_Adun 1 9836
9836
