Protoss_Nexus 2 8168
Protoss_Gateway 2 3403
Protoss_Assimilator 1 2364
Protoss_Cybernetics_Core 1 2923
Protoss_Dragoon 8 9366
Protoss_Zealot 2 9206
Protoss_Robotics_Facility 1 6248
Protoss_Shuttle 1 7546
Protoss_Robotics_Support_Bay 1 8386
Protoss_Reaver 1 8991
Protoss_Observatory 1 9293
9366
