Protoss_Nexus 2 8858
Protoss_Gateway 2 9586
Protoss_Assimilator 1 2563
Protoss_Cybernetics_Core 1 3202
Protoss_Dragoon 5 9391
Protoss_Robotics_Facility 1 5988
Protoss_Robotics_Support_Bay 1 7293
Protoss_Shuttle 1 7301
Protoss_Zealot 2 8286
Protoss_Reaver 1 8203
Protoss_Observatory 1 9108
Protoss_Observer 1 9656
9656
