Protoss_Nexus 2 7438
Protoss_Gateway 3 8617
Protoss_Assimilator 1 2618
Protoss_Cybernetics_Core 1 3162
Protoss_Dragoon 7 9826
Protoss_Citadel_of_Adun 1 5556
Protoss_Templar_Archives 1 6548
Protoss_Dark_Templar 2 8466
9826
