Protoss_Nexus 1 0
Protoss_Gateway 2 8038
Protoss_Assimilator 2 2832
Protoss_Cybernetics_Core 1 3423
Protoss_Zealot 4 7751
Protoss_Robotics_Facility 1 4773
Protoss_Robotics_Support_Bay 1 6112
Protoss_Shuttle 1 6191
Protoss_Observatory 1 6658
Protoss_Reaver 1 7331
Protoss_Observer 1 8391
Protoss_Dragoon 3 9558
Protoss_Scarab 6 9957
9957
