Protoss_Nexus 3 9805
Protoss_Gateway 3 9926
Protoss_Assimilator 1 2513
Protoss_Cybernetics_Core 1 3112
Protoss_Dragoon 6 7793
Protoss_Robotics_Facility 1 4683
Protoss_Observatory 1 6076
Protoss_Observer 4 9548
9926
