Protoss_Nexus 2 9744
Protoss_Gateway 2 5867
Protoss_Assimilator 1 2450
Protoss_Cybernetics_Core 1 3161
Protoss_Dragoon 8 10000
Protoss_Robotics_Facility 1 4803
Protoss_Observatory 1 6412
Protoss_Observer 1 7097
10000
