Protoss_Nexus 1 0
Protoss_Gateway 2 5285
Protoss_Assimilator 1 2589
Protoss_Zealot 6 9488
Protoss_Cybernetics_Core 1 4430
Protoss_Dragoon 5 8736
Protoss_Robotics_Facility 1 6828
Protoss_Shuttle 1 8316
Protoss_Robotics_Support_Bay 1 8571
Protoss_Reaver 1 9476
9488
