Protoss_Nexus 2 6333
Protoss_Gateway 4 9276
Protoss_Assimilator 1 2455
Protoss_Cybernetics_Core 1 3176
Protoss_Dragoon 13 9706
Protoss_Robotics_Facility 1 7101
Protoss_Observatory 1 8498
Protoss_Observer 2 9796
9796
