Protoss_Nexus 1 0
Protoss_Gateway 1 1953
Protoss_Assimilator 1 2468
Protoss_Cybernetics_Core 1 3059
Protoss_Zealot 1 3261
Protoss_Dragoon 6 8291
Protoss_Robotics_Facility 1 6148
Protoss_Shuttle 1 7701
Protoss_Robotics_Support_Bay 1 7704
Protoss_Reaver 2 9655
9655
