Protoss_Nexus 2 7969
Protoss_Gateway 4 9159
Protoss_Assimilator 1 2485
Protoss_Cybernetics_Core 1 3059
Protoss_Dragoon 8 8707
Protoss_Robotics_Facility 1 5667
Protoss_Observatory 1 7039
Protoss_Observer 3 8841
Protoss_Shuttle 1 9443
9443
