Protoss_Nexus 2 7199
Protoss_Gateway 3 8723
Protoss_Assimilator 1 2545
Protoss_Cybernetics_Core 1 3115
Protoss_Dragoon 12 9766
Protoss_Robotics_Facility 1 7476
Protoss_Observatory 1 8785
Protoss_Observer 1 9516
9766
