Protoss_Nexus 1 0
Protoss_Gateway 4 9309
Protoss_Assimilator 1 2576
Protoss_Cybernetics_Core 1 3285
Protoss_Dragoon 10 9651
Protoss_Robotics_Facility 1 5896
Protoss_Shuttle 1 7186
Protoss_Robotics_Support_Bay 1 7217
Protoss_Observatory 1 7278
Protoss_Reaver 1 8191
Protoss_Observer 2 9956
9956
