Protoss_Nexus 2 7903
Protoss_Gateway 3 8778
Protoss_Assimilator 1 2416
Protoss_Cybernetics_Core 1 3086
Protoss_Dragoon 13 9801
Protoss_Robotics_Facility 1 8184
Protoss_Observatory 1 9601
9801
