Protoss_Nexus 2 8853
Protoss_Gateway 2 6394
Protoss_Assimilator 1 2530
Protoss_Zealot 5 9808
Protoss_Cybernetics_Core 1 4073
Protoss_Dragoon 2 5951
Protoss_Citadel_of_Adun 1 5509
Protoss_Robotics_Facility 1 6082
Protoss_Templar_Archives 1 6621
Protoss_Shuttle 1 7376
Protoss_Dark_Templar 5 9801
9808
