Protoss_Nexus 2 7303
Protoss_Gateway 5 8388
Protoss_Assimilator 1 2488
Protoss_Cybernetics_Core 1 3025
Protoss_Dragoon 10 9661
Protoss_Robotics_Facility 1 7594
Protoss_Observatory 1 8911
Protoss_Observer 1 9541
Protoss_Citadel_of_Adun 1 9888
9888
