Protoss_Nexus 2 8928
Protoss_Gateway 1 1898
Protoss_Assimilator 1 2427
Protoss_Cybernetics_Core 1 3038
Protoss_Dragoon 6 9431
Protoss_Robotics_Facility 1 4303
Protoss_Shuttle 1 5601
Protoss_Robotics_Support_Bay 1 5855
Protoss_Reaver 2 7928
Protoss_Zealot 2 8416
Protoss_Observatory 1 8138
Protoss_Observer 2 9721
9721
