Protoss_Nexus 2 8983
Protoss_Gateway 3 6673
Protoss_Assimilator 1 2629
Protoss_Cybernetics_Core 1 3484
Protoss_Dragoon 11 9596
Protoss_Robotics_Facility 1 5778
Protoss_Observatory 1 7184
Protoss_Observer 3 9211
9596
