Protoss_Nexus 2 7294
Protoss_Gateway 2 2589
Protoss_Zealot 6 8586
Protoss_Assimilator 1 4624
Protoss_Cybernetics_Core 1 4828
Protoss_Dragoon 8 9940
Protoss_Robotics_Facility 1 8369
Protoss_Observatory 1 9871
9940
