Protoss_Nexus 3 7678
Protoss_Gateway 3 9223
Protoss_Assimilator 1 3348
Protoss_Cybernetics_Core 1 4052
Protoss_Zealot 1 4686
Protoss_Dragoon 7 9501
Protoss_Robotics_Facility 1 8533
Protoss_Observatory 1 9858
9858
