Protoss_Nexus 3 9784
Protoss_Gateway 3 8027
Protoss_Assimilator 1 2613
Protoss_Cybernetics_Core 1 3311
Protoss_Dragoon 9 9235
Protoss_Citadel_of_Adun 1 5510
Protoss_Robotics_Facility 1 6858
Protoss_Observatory 1 8380
Protoss_Observer 1 8956
9784
