Protoss_Nexus 2 7920
Protoss_Gateway 4 9779
Protoss_Assimilator 2 2702
Protoss_Zealot 2 4196
Protoss_Cybernetics_Core 1 3848
Protoss_Dragoon 9 9981
Protoss_Robotics_Facility 1 9090
9981
