Protoss_Nexus 1 0
Protoss_Gateway 2 6595
Protoss_Assimilator 1 2487
Protoss_Cybernetics_Core 1 3184
Protoss_Dragoon 9 9616
Protoss_Robotics_Facility 1 5198
Protoss_Observatory 1 6504
Protoss_Observer 5 9696
9696
