Protoss_Nexus 2 6722
Protoss_Gateway 3 9850
Protoss_Assimilator 1 2371
Protoss_Cybernetics_Core 1 2971
Protoss_Dragoon 8 9325
Protoss_Robotics_Facility 1 4409
Protoss_Observatory 1 5798
Protoss_Observer 3 8327
9850
