Protoss_Nexus 2 7090
Protoss_Gateway 3 8129
Protoss_Assimilator 1 2453
Protoss_Cybernetics_Core 1 3043
Protoss_Dragoon 13 9986
Protoss_Robotics_Facility 1 7733
Protoss_Observatory 1 9656
9986
