Protoss_Nexus 2 7418
Protoss_Gateway 3 9740
Protoss_Assimilator 1 2313
Protoss_Cybernetics_Core 1 2989
Protoss_Dragoon 4 9658
Protoss_Citadel_of_Adun 1 4763
Protoss_Templar_Archives 1 5864
Protoss_Dark_Templar 5 8894
Protoss_Robotics_Facility 1 9680
9740
