Protoss_Nexus 2 6301
Protoss_Gateway 2 5524
Protoss_Assimilator 1 2243
Protoss_Cybernetics_Core 1 2971
Protoss_Dragoon 8 8391
Protoss_Zealot 3 9551
Protoss_Robotics_Facility 1 7296
Protoss_Shuttle 1 8611
Protoss_Observatory 1 8699
Protoss_Robotics_Support_Bay 1 8983
Protoss_Reaver 1 9515
9551
