Protoss_Nexus 2 9118
Protoss_Gateway 3 7453
Protoss_Assimilator 1 2358
Protoss_Cybernetics_Core 1 3071
Protoss_Zealot 2 7046
Protoss_Dragoon 9 9616
Protoss_Robotics_Facility 1 5118
Protoss_Observatory 1 6447
Protoss_Observer 2 7923
9616
