Protoss_Nexus 2 8693
Protoss_Gateway 3 8499
Protoss_Assimilator 1 2339
Protoss_Cybernetics_Core 1 3003
Protoss_Dragoon 12 9978
Protoss_Robotics_Facility 1 5481
Protoss_Observatory 1 6779
Protoss_Observer 2 7923
Protoss_Zealot 1 9983
9983
