Protoss_Nexus 1 0
Protoss_Gateway 2 8569
Protoss_Assimilator 1 2586
Protoss_Cybernetics_Core 1 3150
Protoss_Dragoon 6 9707
Protoss_Robotics_Facility 1 4840
Protoss_Zealot 2 5915
Protoss_Shuttle 2 8277
Protoss_Robotics_Support_Bay 1 6695
Protoss_Reaver 1 7225
Protoss_Observatory 1 8899
Protoss_Observer 1 9485
9707
