Protoss_Nexus 2 8143
Protoss_Gateway 2 3449
Protoss_Assimilator 2 9513
Protoss_Cybernetics_Core 1 2939
Protoss_Dragoon 7 9049
Protoss_Citadel_of_Adun 1 5458
Protoss_Templar_Archives 1 6556
Protoss_Dark_Templar 1 8297
9513
