Protoss_Nexus 2 8996
Protoss_Gateway 2 5552
Protoss_Assimilator 1 2474
Protoss_Zealot 1 2941
Protoss_Cybernetics_Core 1 3237
Protoss_Dragoon 11 9559
Protoss_Robotics_Facility 1 7164
Protoss_Observatory 1 8617
Protoss_Observer 2 9773
9773
