Protoss_Nexus 1 0
Protoss_Assimilator 1 1622
Protoss_Gateway 3 6828
Protoss_Cybernetics_Core 1 3248
Protoss_Dragoon 6 9899
Protoss_Robotics_Facility 1 4445
Protoss_Observatory 1 5765
Protoss_Citadel_of_Adun 1 5802
Protoss_Observer 1 6415
Protoss_Shuttle 3 9109
Protoss_Zealot 6 8849
Protoss_Robotics_Support_Bay 1 8571
9899
