Protoss_Nexus 2 6192
Protoss_Gateway 4 9984
Protoss_Assimilator 1 2239
Protoss_Cybernetics_Core 1 3013
Protoss_Dragoon 10 9221
Protoss_Robotics_Facility 1 8588
Protoss_Observatory 1 9878
9984
