Protoss_Nexus 2 5269
Protoss_Gateway 2 5843
Protoss_Assimilator 1 2256
Protoss_Cybernetics_Core 1 2909
Protoss_Dragoon 9 9737
Protoss_Forge 1 6025
Protoss_Photon_Cannon 2 8208
Protoss_Zealot 2 9729
Protoss_Robotics_Facility 1 9297
9737
