Protoss_Nexus 2 7700
Protoss_Gateway 4 9117
Protoss_Assimilator 1 2514
Protoss_Cybernetics_Core 1 3151
Protoss_Dragoon 10 8648
Protoss_Zealot 2 9400
Protoss_Robotics_Facility 1 9613
9613
