Protoss_Nexus 1 0
Protoss_Gateway 2 6179
Protoss_Assimilator 1 2527
Protoss_Cybernetics_Core 1 3350
Protoss_Dragoon 8 8979
Protoss_Citadel_of_Adun 2 8810
Protoss_Robotics_Facility 1 6808
Protoss_Observatory 1 8239
Protoss_Shuttle 1 8261
8979
