Protoss_Nexus 2 8749
Protoss_Gateway 2 5109
Protoss_Assimilator 1 2587
Protoss_Cybernetics_Core 1 3220
Protoss_Robotics_Facility 1 4393
Protoss_Dragoon 11 9636
Protoss_Observatory 1 5823
Protoss_Observer 3 9116
9636
