Protoss_Nexus 1 0
Protoss_Gateway 2 8428
Protoss_Assimilator 1 2638
Protoss_Zealot 1 3111
Protoss_Cybernetics_Core 1 3490
Protoss_Dragoon 7 9565
Protoss_Robotics_Facility 1 5268
Protoss_Shuttle 1 7091
Protoss_Robotics_Support_Bay 1 7188
Protoss_Reaver 1 7993
Protoss_Observatory 1 9264
Protoss_Scarab 5 9970
9970
