Protoss_Nexus 2 8998
Protoss_Gateway 2 9839
Protoss_Assimilator 1 2590
Protoss_Cybernetics_Core 1 3323
Protoss_Dragoon 5 9851
Protoss_Robotics_Facility 1 4851
Protoss_Shuttle 1 6256
Protoss_Zealot 2 7256
Protoss_Robotics_Support_Bay 1 6798
Protoss_Reaver 1 7361
Protoss_Observatory 1 7746
Protoss_Observer 2 9015
9851
