Protoss_Nexus 2 9543
Protoss_Gateway 1 2037
Protoss_Assimilator 1 2448
Protoss_Cybernetics_Core 1 3084
Protoss_Zealot 2 7091
Protoss_Robotics_Facility 1 4548
Protoss_Dragoon 4 8716
Protoss_Robotics_Support_Bay 1 5843
Protoss_Shield_Battery 1 6004
Protoss_Shuttle 2 8195
Protoss_Reaver 2 9736
Protoss_Scarab 3 9389
9736
