Protoss_Nexus 1 0
Protoss_Gateway 3 9729
Protoss_Assimilator 1 2392
Protoss_Cybernetics_Core 1 3064
Protoss_Dragoon 7 9791
Protoss_Robotics_Facility 1 5383
Protoss_Shuttle 1 6676
Protoss_Robotics_Support_Bay 1 6888
Protoss_Zealot 2 7911
Protoss_Reaver 1 7632
Protoss_Observatory 1 8321
Protoss_Observer 1 9231
9791
