Protoss_Nexus 2 7477
Protoss_Gateway 3 9675
Protoss_Assimilator 1 2462
Protoss_Zealot 1 2913
Protoss_Cybernetics_Core 1 3861
Protoss_Dragoon 11 9879
Protoss_Robotics_Facility 2 8689
Protoss_Observatory 1 9523
9879
