Protoss_Nexus 2 9367
Protoss_Gateway 3 5983
Protoss_Assimilator 1 2487
Protoss_Cybernetics_Core 1 3077
Protoss_Dragoon 8 8439
Protoss_Zealot 4 8307
Protoss_Citadel_of_Adun 1 7989
Protoss_Templar_Archives 1 8992
Protoss_Dark_Templar 2 9977
9977
