Protoss_Nexus 2 6145
Protoss_Gateway 3 7576
Protoss_Assimilator 2 8811
Protoss_Cybernetics_Core 1 3083
Protoss_Dragoon 11 9895
Protoss_Robotics_Facility 1 7865
Protoss_Zealot 1 7959
Protoss_Stargate 1 9522
Protoss_Observatory 1 9689
9895
