Protoss_Nexus 2 8403
Protoss_Gateway 2 5713
Protoss_Assimilator 1 2218
Protoss_Cybernetics_Core 1 2881
Protoss_Dragoon 12 9931
Protoss_Robotics_Facility 1 4943
Protoss_Observatory 1 6309
Protoss_Observer 4 9421
9931
