Protoss_Nexus 1 0
Protoss_Gateway 2 2830
Protoss_Zealot 8 5761
Protoss_Assimilator 1 5298
Protoss_Cybernetics_Core 1 6480
Protoss_Dragoon 6 9206
Protoss_Robotics_Facility 1 8703
9206
