Protoss_Nexus 3 9701
Protoss_Gateway 2 4665
Protoss_Assimilator 1 2508
Protoss_Cybernetics_Core 1 3092
Protoss_Dragoon 10 9251
Protoss_Citadel_of_Adun 1 6056
Protoss_Robotics_Facility 1 8320
Protoss_Observatory 1 9760
9760
