Protoss_Nexus 2 9773
Protoss_Gateway 3 7803
Protoss_Assimilator 1 2488
Protoss_Cybernetics_Core 1 3249
Protoss_Dragoon 9 9006
Protoss_Robotics_Facility 1 7139
Protoss_Zealot 2 8356
Protoss_Observatory 1 8447
Protoss_Observer 1 9376
9773
