Protoss_Nexus 2 9442
Protoss_Gateway 2 7707
Protoss_Assimilator 1 2384
Protoss_Cybernetics_Core 1 2941
Protoss_Dragoon 8 9981
Protoss_Robotics_Facility 1 4373
Protoss_Shuttle 1 5659
Protoss_Robotics_Support_Bay 1 5753
Protoss_Reaver 1 6597
Protoss_Observatory 1 7481
Protoss_Observer 1 8085
Protoss_Scarab 8 9900
9981
