Protoss_Nexus 1 0
Protoss_Gateway 2 5997
Protoss_Assimilator 1 2433
Protoss_Cybernetics_Core 1 3048
Protoss_Dragoon 9 8862
Protoss_Robotics_Facility 1 5718
Protoss_Zealot 3 9696
Protoss_Observatory 1 7423
Protoss_Observer 1 8116
Protoss_Citadel_of_Adun 1 8124
Protoss_Shuttle 1 9141
Protoss_Templar_Archives 2 9443
9696
