Protoss_Nexus 2 9694
Protoss_Gateway 2 7338
Protoss_Assimilator 1 2550
Protoss_Cybernetics_Core 1 3083
Protoss_Dragoon 6 9866
Protoss_Robotics_Facility 1 4648
Protoss_Shuttle 1 5936
Protoss_Robotics_Support_Bay 1 6328
Protoss_Reaver 2 8126
Protoss_Scarab 8 9299
9866
