Protoss_Nexus 2 9143
Protoss_Gateway 2 7343
Protoss_Assimilator 1 2435
Protoss_Cybernetics_Core 1 3121
Protoss_Dragoon 10 9437
Protoss_Robotics_Facility 1 5940
Protoss_Observatory 1 7277
Protoss_Observer 3 9635
9635
