Protoss_Nexus 2 8303
Protoss_Gateway 2 3657
Protoss_Assimilator 1 2297
Protoss_Cybernetics_Core 1 3035
Protoss_Dragoon 5 6495
Protoss_Citadel_of_Adun 1 6007
Protoss_Templar_Archives 1 7299
Protoss_Robotics_Facility 1 7483
Protoss_Zealot 2 8199
Protoss_Shuttle 1 8773
Protoss_Dark_Templar 2 9057
Protoss_Observatory 1 9470
Protoss_Observer 1 9999
9999
