Protoss_Nexus 3 9765
Protoss_Gateway 3 9058
Protoss_Assimilator 1 2374
Protoss_Cybernetics_Core 1 3079
Protoss_Dragoon 9 9227
Protoss_Robotics_Facility 1 6620
Protoss_Observatory 1 7905
Protoss_Observer 2 9125
9765
