Protoss_Nexus 2 8923
Protoss_Gateway 2 6129
Protoss_Assimilator 1 2560
Protoss_Cybernetics_Core 1 3198
Protoss_Dragoon 10 9866
Protoss_Robotics_Facility 1 7189
Protoss_Observatory 1 8603
Protoss_Observer 1 9151
9866
