Protoss_Nexus 2 7473
Protoss_Gateway 2 8163
Protoss_Assimilator 1 2463
Protoss_Cybernetics_Core 1 3211
Protoss_Zealot 1 3631
Protoss_Dragoon 8 9661
Protoss_Robotics_Facility 1 6498
Protoss_Observatory 1 7923
Protoss_Observer 1 8511
9661
