Protoss_Nexus 3 7659
Protoss_Gateway 2 5888
Protoss_Assimilator 1 2259
Protoss_Cybernetics_Core 1 2949
Protoss_Dragoon 9 9316
Protoss_Robotics_Facility 1 5484
Protoss_Observatory 1 6833
Protoss_Observer 3 9501
9501
