Protoss_Nexus 2 6536
Protoss_Gateway 4 9948
Protoss_Assimilator 1 2548
Protoss_Cybernetics_Core 1 3012
Protoss_Dragoon 9 9453
Protoss_Robotics_Facility 1 7398
Protoss_Observatory 1 8843
Protoss_Observer 1 9576
9948
