Protoss_Nexus 2 2673
Protoss_Gateway 3 9423
Protoss_Assimilator 2 7981
Protoss_Cybernetics_Core 1 4175
Protoss_Zealot 4 9311
Protoss_Dragoon 10 9956
Protoss_Stargate 2 9337
Protoss_Fleet_Beacon 1 9168
9956
