Protoss_Nexus 1 0
Protoss_Gateway 2 4776
Protoss_Assimilator 1 2290
Protoss_Cybernetics_Core 1 3075
Protoss_Dragoon 8 7599
Protoss_Robotics_Facility 1 6317
Protoss_Observatory 1 7687
Protoss_Shuttle 1 7931
Protoss_Zealot 6 9579
Protoss_Observer 1 8833
9579
