Protoss_Nexus 3 8980
Protoss_Gateway 2 4771
Protoss_Assimilator 1 2424
Protoss_Cybernetics_Core 1 2985
Protoss_Dragoon 12 9499
Protoss_Robotics_Facility 1 7911
Protoss_Observatory 1 9388
Protoss_Observer 1 9925
9925
