Protoss_Nexus 1 0
Protoss_Gateway 2 8997
Protoss_Assimilator 1 2359
Protoss_Cybernetics_Core 1 3235
Protoss_Robotics_Facility 1 4624
Protoss_Dragoon 5 9238
Protoss_Robotics_Support_Bay 1 5990
Protoss_Reaver 3 9832
Protoss_Shuttle 1 7588
Protoss_Scarab 8 8744
9832
