Protoss_Nexus 1 0
Protoss_Gateway 2 3721
Protoss_Assimilator 1 2467
Protoss_Cybernetics_Core 1 3098
Protoss_Dragoon 11 9779
Protoss_Citadel_of_Adun 1 6199
Protoss_Zealot 1 6973
Protoss_Templar_Archives 1 7185
Protoss_Dark_Templar 2 8635
9779
