Protoss_Nexus 2 8288
Protoss_Gateway 3 7591
Protoss_Assimilator 1 2329
Protoss_Cybernetics_Core 1 2829
Protoss_Dragoon 8 9738
Protoss_Robotics_Facility 1 4378
Protoss_Shuttle 1 5751
Protoss_Observatory 1 6225
Protoss_Observer 2 9441
9738
