Protoss_Nexus 2 8636
Protoss_Gateway 2 5773
Protoss_Assimilator 1 2756
Protoss_Cybernetics_Core 1 3308
Protoss_Dragoon 2 5141
Protoss_Citadel_of_Adun 1 4743
Protoss_Templar_Archives 1 6113
Protoss_Dark_Templar 4 7868
Protoss_Robotics_Facility 1 9366
9366
