Protoss_Nexus 3 9257
Protoss_Gateway 2 6149
Protoss_Assimilator 1 2421
Protoss_Cybernetics_Core 1 3139
Protoss_Dragoon 8 8449
Protoss_Robotics_Facility 1 5731
Protoss_Observatory 1 7021
Protoss_Observer 2 8279
Protoss_Zealot 2 9561
Protoss_Shuttle 1 9949
9949
