Protoss_Nexus 3 9810
Protoss_Gateway 1 1906
Protoss_Assimilator 1 2723
Protoss_Zealot 2 6615
Protoss_Cybernetics_Core 1 3585
Protoss_Robotics_Facility 1 4579
Protoss_Dragoon 5 9961
Protoss_Shuttle 1 5887
Protoss_Robotics_Support_Bay 1 6445
Protoss_Reaver 1 6997
Protoss_Observatory 1 7370
Protoss_Observer 2 8651
9961
