Protoss_Nexus 1 0
Protoss_Gateway 1 1843
Protoss_Assimilator 1 2249
Protoss_Cybernetics_Core 1 2988
Protoss_Robotics_Facility 1 4058
Protoss_Dragoon 4 7591
Protoss_Shuttle 1 5416
Protoss_Observatory 1 6908
Protoss_Observer 1 7496
7591
