Protoss_Nexus 2 8318
Protoss_Gateway 3 9668
Protoss_Assimilator 1 2874
Protoss_Cybernetics_Core 1 3348
Protoss_Dragoon 9 9623
Protoss_Robotics_Facility 1 5704
Protoss_Observatory 1 7238
Protoss_Observer 4 9712
9712
