Protoss_Nexus 1 0
Protoss_Gateway 2 9912
Protoss_Assimilator 1 2429
Protoss_Cybernetics_Core 1 3163
Protoss_Dragoon 3 6253
Protoss_Robotics_Facility 1 5575
Protoss_Forge 1 6269
Protoss_Shuttle 1 6916
Protoss_Photon_Cannon 1 6983
Protoss_Robotics_Support_Bay 1 7245
Protoss_Reaver 2 8870
9912
