Protoss_Nexus 2 8243
Protoss_Gateway 2 5513
Protoss_Assimilator 2 2933
Protoss_Zealot 2 4271
Protoss_Cybernetics_Core 1 3891
Protoss_Dragoon 10 9761
Protoss_Robotics_Facility 1 8803
9761
