Protoss_Nexus 2 7542
Protoss_Gateway 2 2601
Protoss_Zealot 3 3671
Protoss_Assimilator 1 3823
Protoss_Cybernetics_Core 1 4408
Protoss_Dragoon 7 9996
Protoss_Robotics_Facility 1 7973
Protoss_Shuttle 1 9276
Protoss_Robotics_Support_Bay 1 9298
9996
