Protoss_Nexus 2 7831
Protoss_Gateway 2 4218
Protoss_Assimilator 1 2495
Protoss_Zealot 2 3846
Protoss_Cybernetics_Core 1 3623
Protoss_Dragoon 11 9116
Protoss_Robotics_Facility 1 8503
Protoss_Observatory 1 9972
9972
