Protoss_Nexus 2 8898
Protoss_Gateway 4 9635
Protoss_Assimilator 1 2493
Protoss_Cybernetics_Core 1 3148
Protoss_Dragoon 8 9801
Protoss_Robotics_Facility 1 4643
Protoss_Observatory 1 6118
Protoss_Observer 5 9648
9801
