Protoss_Nexus 2 7788
Protoss_Gateway 3 8987
Protoss_Assimilator 2 9202
Protoss_Cybernetics_Core 1 3008
Protoss_Dragoon 7 8631
Protoss_Robotics_Facility 1 6586
Protoss_Zealot 2 6911
Protoss_Observatory 1 7940
Protoss_Observer 2 9161
9202
