Protoss_Nexus 3 9731
Protoss_Gateway 2 6137
Protoss_Assimilator 1 2570
Protoss_Cybernetics_Core 1 3226
Protoss_Dragoon 6 7883
Protoss_Robotics_Facility 1 5503
Protoss_Observatory 1 6929
Protoss_Observer 3 9756
Protoss_Shuttle 1 8695
Protoss_Zealot 2 8971
9756
