Protoss_Nexus 2 7914
Protoss_Gateway 2 4663
Protoss_Assimilator 2 9590
Protoss_Cybernetics_Core 1 2997
Protoss_Dragoon 5 6766
Protoss_Citadel_of_Adun 1 6353
Protoss_Zealot 1 6581
Protoss_Robotics_Facility 2 9969
Protoss_Templar_Archives 1 7383
Protoss_Dark_Templar 1 8496
Protoss_Stargate 1 9008
9969
