Protoss_Nexus 2 3178
Protoss_Gateway 3 7528
Protoss_Assimilator 2 7777
Protoss_Zealot 9 9793
Protoss_Cybernetics_Core 1 4788
Protoss_Dragoon 4 7771
Protoss_Citadel_of_Adun 1 7038
Protoss_Templar_Archives 1 8078
Protoss_Dark_Templar 2 9955
9955
