Protoss_Nexus 2 9428
Protoss_Gateway 2 4728
Protoss_Assimilator 1 2420
Protoss_Cybernetics_Core 1 3015
Protoss_Dragoon 7 9091
Protoss_Robotics_Facility 1 6527
Protoss_Zealot 4 8056
Protoss_Shuttle 1 7946
Protoss_Observatory 1 8206
Protoss_Observer 1 8848
9428
