Protoss_Nexus 2 7948
Protoss_Gateway 4 8989
Protoss_Assimilator 1 2363
Protoss_Cybernetics_Core 1 2988
Protoss_Dragoon 11 8827
Protoss_Robotics_Facility 1 6810
Protoss_Observatory 1 8145
Protoss_Observer 1 8686
Protoss_Shuttle 1 9431
Protoss_Zealot 2 9746
9746
