Protoss_Nexus 2 8312
Protoss_Gateway 3 8883
Protoss_Assimilator 1 2554
Protoss_Cybernetics_Core 1 3248
Protoss_Dragoon 11 9926
Protoss_Robotics_Facility 1 5736
Protoss_Observatory 1 7053
Protoss_Observer 4 9893
9926
