Protoss_Nexus 1 0
Protoss_Gateway 3 7878
Protoss_Assimilator 1 2628
Protoss_Zealot 2 4331
Protoss_Cybernetics_Core 1 3878
Protoss_Dragoon 10 9733
Protoss_Robotics_Facility 1 5548
Protoss_Observatory 1 6888
Protoss_Observer 2 8193
9733
