Protoss_Nexus 2 8523
Protoss_Gateway 2 5518
Protoss_Assimilator 1 2553
Protoss_Cybernetics_Core 1 3368
Protoss_Dragoon 8 8111
Protoss_Robotics_Facility 1 6076
Protoss_Observatory 1 7569
Protoss_Observer 3 9566
9566
