Protoss_Nexus 1 0
Protoss_Gateway 2 8243
Protoss_Assimilator 1 2481
Protoss_Cybernetics_Core 1 3073
Protoss_Dragoon 4 9806
Protoss_Robotics_Facility 1 4630
Protoss_Shuttle 1 5931
Protoss_Observatory 1 6069
Protoss_Robotics_Support_Bay 1 6138
Protoss_Observer 2 9655
Protoss_Reaver 2 8603
Protoss_Scarab 3 9465
9806
