Protoss_Nexus 3 8542
Protoss_Gateway 5 9693
Protoss_Zealot 8 6793
Protoss_Assimilator 1 4889
Protoss_Cybernetics_Core 1 5677
Protoss_Dragoon 6 9048
Protoss_Robotics_Facility 1 9158
Protoss_Citadel_of_Adun 1 9363
9693
