Protoss_Nexus 3 8758
Protoss_Gateway 2 3688
Protoss_Assimilator 1 2488
Protoss_Cybernetics_Core 1 3168
Protoss_Dragoon 8 9626
Protoss_Zealot 1 6221
Protoss_Robotics_Facility 1 9143
9626
