Protoss_Nexus 2 7314
Protoss_Gateway 2 9375
Protoss_Assimilator 1 2448
Protoss_Cybernetics_Core 1 3038
Protoss_Dragoon 8 9698
Protoss_Robotics_Facility 1 5783
Protoss_Observatory 1 7120
Protoss_Observer 1 7831
Protoss_Robotics_Support_Bay 1 8193
Protoss_Shuttle 1 8433
Protoss_Reaver 1 9335
9698
