Protoss_Nexus 1 0
Protoss_Gateway 3 8802
Protoss_Assimilator 1 2383
Protoss_Cybernetics_Core 1 3577
Protoss_Zealot 2 5776
Protoss_Robotics_Facility 1 4663
Protoss_Dragoon 8 9801
Protoss_Robotics_Support_Bay 1 6018
Protoss_Shuttle 1 6141
Protoss_Reaver 1 7043
9801
