Protoss_Nexus 2 9716
Protoss_Gateway 2 6211
Protoss_Assimilator 1 2285
Protoss_Cybernetics_Core 1 2938
Protoss_Dragoon 12 9831
Protoss_Robotics_Facility 1 5273
Protoss_Observatory 1 6643
Protoss_Observer 2 8521
9831
