Protoss_Nexus 3 9901
Protoss_Gateway 3 6733
Protoss_Assimilator 1 2363
Protoss_Cybernetics_Core 1 3008
Protoss_Dragoon 11 9186
Protoss_Robotics_Facility 1 8056
Protoss_Observatory 1 9552
9901
