Protoss_Nexus 3 9179
Protoss_Gateway 3 9736
Protoss_Assimilator 2 5478
Protoss_Cybernetics_Core 1 4095
Protoss_Zealot 3 8763
Protoss_Citadel_of_Adun 1 5121
Protoss_Dragoon 5 9535
Protoss_Robotics_Facility 1 5720
Protoss_Shuttle 1 7135
Protoss_Robotics_Support_Bay 1 7525
Protoss_Reaver 1 8223
Protoss_Observatory 1 8285
9736
