Protoss_Nexus 2 7386
Protoss_Gateway 3 8654
Protoss_Assimilator 1 2545
Protoss_Cybernetics_Core 1 3183
Protoss_Dragoon 11 9811
Protoss_Robotics_Facility 1 5896
Protoss_Observatory 1 7569
Protoss_Observer 3 9435
9811
