Protoss_Nexus 2 6123
Protoss_Gateway 3 7023
Protoss_Assimilator 1 2478
Protoss_Zealot 3 8096
Protoss_Cybernetics_Core 1 3925
Protoss_Dragoon 10 9888
Protoss_Robotics_Facility 1 7668
Protoss_Observatory 1 8992
Protoss_Observer 1 9811
9888
