Protoss_Nexus 2 5977
Protoss_Assimilator 2 6589
Protoss_Gateway 2 8290
Protoss_Zealot 7 8605
Protoss_Forge 1 6516
Protoss_Photon_Cannon 5 9298
Protoss_Cybernetics_Core 1 7563
Protoss_Dragoon 3 9525
9525
