Protoss_Nexus 2 7958
Protoss_Gateway 2 3028
Protoss_Zealot 4 7026
Protoss_Assimilator 1 3617
Protoss_Cybernetics_Core 1 4889
Protoss_Dragoon 6 9281
Protoss_Robotics_Facility 1 7053
Protoss_Observatory 1 9207
Protoss_Shuttle 1 9371
9371
