Protoss_Nexus 1 0
Protoss_Gateway 3 8563
Protoss_Assimilator 1 2383
Protoss_Cybernetics_Core 1 2983
Protoss_Dragoon 14 9876
Protoss_Robotics_Facility 1 5942
Protoss_Observatory 1 7660
Protoss_Observer 2 8868
9876
