Protoss_Nexus 2 2741
Protoss_Gateway 4 8804
Protoss_Assimilator 1 3418
Protoss_Cybernetics_Core 1 4229
Protoss_Zealot 1 4785
Protoss_Dragoon 11 9783
Protoss_Robotics_Facility 1 7273
Protoss_Shuttle 1 8627
9783
