Protoss_Nexus 2 7860
Protoss_Gateway 3 8669
Protoss_Assimilator 1 2398
Protoss_Cybernetics_Core 1 3067
Protoss_Dragoon 8 8371
Protoss_Robotics_Facility 1 5422
Protoss_Observatory 1 6754
Protoss_Observer 2 8145
Protoss_Zealot 5 9725
9725
