Protoss_Nexus 2 5694
Protoss_Gateway 3 7858
Protoss_Assimilator 2 9845
Protoss_Cybernetics_Core 1 3073
Protoss_Dragoon 8 9266
Protoss_Robotics_Facility 1 6518
Protoss_Observatory 1 9635
9845
