Protoss_Nexus 3 7815
Protoss_Gateway 4 8783
Protoss_Assimilator 1 2213
Protoss_Cybernetics_Core 1 2883
Protoss_Dragoon 8 9931
Protoss_Robotics_Facility 1 6404
Protoss_Observatory 1 7698
Protoss_Observer 3 9951
Protoss_Citadel_of_Adun 1 8353
Protoss_Zealot 1 9101
9951
