Protoss_Nexus 3 9555
Protoss_Gateway 2 5198
Protoss_Assimilator 1 2250
Protoss_Cybernetics_Core 1 3057
Protoss_Dragoon 9 8841
Protoss_Robotics_Facility 1 8082
Protoss_Shuttle 1 9517
Protoss_Robotics_Support_Bay 1 9902
9902
