Protoss_Nexus 3 8407
Protoss_Gateway 2 4907
Protoss_Assimilator 1 2614
Protoss_Cybernetics_Core 1 3391
Protoss_Dragoon 8 9685
Protoss_Zealot 1 8905
Protoss_Robotics_Facility 1 9335
9685
