Protoss_Nexus 3 8150
Protoss_Gateway 4 9911
Protoss_Assimilator 1 2383
Protoss_Cybernetics_Core 1 2986
Protoss_Dragoon 8 9855
Protoss_Zealot 2 4855
Protoss_Robotics_Facility 1 9017
9911
