Protoss_Nexus 2 7425
Protoss_Gateway 2 3829
Protoss_Assimilator 1 2480
Protoss_Cybernetics_Core 1 3012
Protoss_Dragoon 7 7936
Protoss_Zealot 4 8776
Protoss_Citadel_of_Adun 1 8603
Protoss_Robotics_Facility 1 9297
Protoss_Templar_Archives 1 9810
9810
