Protoss_Nexus 1 0
Protoss_Gateway 3 8585
Protoss_Assimilator 1 2554
Protoss_Cybernetics_Core 1 3209
Protoss_Dragoon 7 8020
Protoss_Robotics_Facility 1 6398
Protoss_Observatory 1 7817
Protoss_Observer 1 8476
Protoss_Zealot 5 9966
Protoss_Shuttle 1 9078
Protoss_Shield_Battery 1 9305
Protoss_Citadel_of_Adun 1 9867
9966
