Protoss_Nexus 2 7181
Protoss_Gateway 3 9932
Protoss_Assimilator 1 2453
Protoss_Cybernetics_Core 1 2939
Protoss_Zealot 1 3119
Protoss_Dragoon 10 9753
Protoss_Robotics_Facility 1 8198
Protoss_Observatory 1 9708
9932
