Protoss_Nexus 2 5903
Protoss_Gateway 4 8825
Protoss_Assimilator 1 2468
Protoss_Cybernetics_Core 1 3026
Protoss_Dragoon 7 8631
Protoss_Zealot 7 9591
Protoss_Citadel_of_Adun 1 8237
9591
