Protoss_Nexus 2 6300
Protoss_Gateway 4 9335
Protoss_Assimilator 1 2468
Protoss_Cybernetics_Core 1 3128
Protoss_Dragoon 10 9796
Protoss_Robotics_Facility 1 6833
Protoss_Observatory 1 8413
Protoss_Zealot 1 8571
Protoss_Observer 2 9631
9796
