Protoss_Nexus 2 9303
Protoss_Gateway 2 5776
Protoss_Assimilator 1 2574
Protoss_Cybernetics_Core 1 3200
Protoss_Dragoon 6 9861
Protoss_Citadel_of_Adun 1 4848
Protoss_Templar_Archives 1 6058
Protoss_Dark_Templar 4 8056
Protoss_Robotics_Facility 1 7506
Protoss_Shuttle 1 8926
Protoss_Observatory 1 9660
9861
