Protoss_Nexus 2 9247
Protoss_Gateway 2 4683
Protoss_Assimilator 1 2378
Protoss_Cybernetics_Core 1 2959
Protoss_Dragoon 4 5856
Protoss_Citadel_of_Adun 1 5432
Protoss_Templar_Archives 1 6471
Protoss_Zealot 3 8253
Protoss_Dark_Templar 5 9146
Protoss_Robotics_Facility 1 9923
9923
