Protoss_Nexus 2 6988
Protoss_Gateway 4 8948
Protoss_Assimilator 2 8296
Protoss_Cybernetics_Core 1 2983
Protoss_Dragoon 8 8656
Protoss_Citadel_of_Adun 1 5539
Protoss_Stargate 1 6253
Protoss_Templar_Archives 1 6697
Protoss_Arbiter_Tribunal 1 7863
Protoss_Arbiter 1 9201
Protoss_Zealot 3 9731
9731
