Protoss_Nexus 1 0
Protoss_Gateway 2 5007
Protoss_Assimilator 1 2416
Protoss_Cybernetics_Core 1 2963
Protoss_Dragoon 14 9754
Protoss_Robotics_Facility 1 7695
Protoss_Observatory 1 8979
Protoss_Observer 1 9521
9754
