Protoss_Nexus 2 6013
Protoss_Gateway 3 8371
Protoss_Assimilator 1 2215
Protoss_Cybernetics_Core 1 2986
Protoss_Dragoon 11 8915
Protoss_Robotics_Facility 1 6903
Protoss_Observatory 1 9329
9329
