Protoss_Nexus 2 6053
Protoss_Gateway 3 9491
Protoss_Assimilator 1 2489
Protoss_Cybernetics_Core 1 3119
Protoss_Dragoon 6 7996
Protoss_Robotics_Facility 1 7295
Protoss_Shuttle 1 8746
Protoss_Robotics_Support_Bay 1 8936
Protoss_Reaver 1 9648
9648
