Protoss_Nexus 2 9460
Protoss_Gateway 1 2133
Protoss_Assimilator 1 2298
Protoss_Cybernetics_Core 1 3150
Protoss_Dragoon 5 9966
Protoss_Robotics_Facility 1 4446
Protoss_Zealot 2 5651
Protoss_Shuttle 1 5741
Protoss_Robotics_Support_Bay 1 5923
Protoss_Reaver 2 7695
Protoss_Scarab 17 9615
Protoss_Observatory 1 9029
Protoss_Observer 1 9956
9966
