Protoss_Nexus 3 9752
Protoss_Gateway 4 8283
Protoss_Assimilator 2 9564
Protoss_Cybernetics_Core 1 2956
Protoss_Dragoon 9 9947
Protoss_Robotics_Facility 1 5440
Protoss_Observatory 1 6937
Protoss_Observer 3 8707
Protoss_Zealot 1 9851
9947
