Protoss_Nexus 2 8440
Protoss_Assimilator 1 1823
Protoss_Gateway 5 9828
Protoss_Cybernetics_Core 1 3293
Protoss_Robotics_Facility 1 4288
Protoss_Dragoon 7 9318
Protoss_Shuttle 1 5736
Protoss_Observatory 1 5812
Protoss_Observer 3 7842
Protoss_Citadel_of_Adun 1 8899
9828
