Protoss_Nexus 1 0
Protoss_Gateway 2 3793
Protoss_Assimilator 1 2386
Protoss_Cybernetics_Core 1 3233
Protoss_Dragoon 5 6033
Protoss_Robotics_Facility 1 6973
Protoss_Zealot 4 7969
Protoss_Shuttle 1 8257
Protoss_Robotics_Support_Bay 1 8400
Protoss_Reaver 1 9159
9159
