Protoss_Nexus 2 6022
Protoss_Gateway 4 8896
Protoss_Assimilator 2 7451
Protoss_Cybernetics_Core 1 2880
Protoss_Dragoon 7 7851
Protoss_Robotics_Facility 1 6794
Protoss_Citadel_of_Adun 1 7178
Protoss_Templar_Archives 1 8443
Protoss_Shuttle 1 9121
Protoss_Dark_Templar 3 9721
Protoss_Stargate 1 9586
9721
