Protoss_Nexus 3 9111
Protoss_Gateway 5 9778
Protoss_Assimilator 1 2284
Protoss_Cybernetics_Core 1 2874
Protoss_Dragoon 11 9396
Protoss_Robotics_Facility 1 7738
Protoss_Observatory 1 9034
Protoss_Observer 1 9601
9778
