Protoss_Nexus 2 9597
Protoss_Gateway 3 9779
Protoss_Assimilator 1 2357
Protoss_Cybernetics_Core 1 2952
Protoss_Dragoon 6 9317
Protoss_Robotics_Facility 1 5548
Protoss_Zealot 2 8715
Protoss_Shuttle 1 7033
Protoss_Robotics_Support_Bay 1 7076
Protoss_Reaver 1 7935
Protoss_Observatory 1 8402
Protoss_Observer 2 9937
9937
