Protoss_Nexus 1 0
Protoss_Gateway 2 7737
Protoss_Assimilator 1 2548
Protoss_Cybernetics_Core 1 3353
Protoss_Dragoon 7 8836
Protoss_Robotics_Facility 1 5624
Protoss_Shuttle 1 6966
Protoss_Observatory 1 7078
Protoss_Observer 2 8636
Protoss_Robotics_Support_Bay 1 8188
Protoss_Reaver 1 9446
9446
