Protoss_Nexus 2 8917
Protoss_Gateway 3 9497
Protoss_Assimilator 1 2335
Protoss_Cybernetics_Core 1 2966
Protoss_Zealot 3 7197
Protoss_Dragoon 5 9151
Protoss_Citadel_of_Adun 2 5727
Protoss_Templar_Archives 1 6749
Protoss_Dark_Templar 2 7873
Protoss_Robotics_Facility 1 8295
Protoss_Observatory 1 9811
9811
