Protoss_Nexus 1 0
Protoss_Gateway 3 8101
Protoss_Assimilator 1 2399
Protoss_Cybernetics_Core 1 3071
Protoss_Zealot 5 8601
Protoss_Dragoon 7 9363
Protoss_Robotics_Facility 1 6028
Protoss_Observatory 1 7353
Protoss_Shuttle 1 7559
Protoss_Observer 2 9681
9681
