Protoss_Nexus 1 0
Protoss_Assimilator 1 1881
Protoss_Gateway 2 7310
Protoss_Cybernetics_Core 1 3665
Protoss_Dragoon 3 9095
Protoss_Robotics_Facility 1 5007
Protoss_Citadel_of_Adun 1 5903
Protoss_Shuttle 1 6345
Protoss_Templar_Archives 1 7066
Protoss_Dark_Templar 2 9625
9625
