Protoss_Nexus 2 9928
Protoss_Gateway 2 3512
Protoss_Assimilator 1 2435
Protoss_Cybernetics_Core 1 2963
Protoss_Dragoon 8 9526
Protoss_Robotics_Facility 1 5849
Protoss_Zealot 6 8924
Protoss_Shuttle 1 7256
9928
