Protoss_Nexus 2 9367
Protoss_Gateway 2 8545
Protoss_Assimilator 1 2442
Protoss_Cybernetics_Core 1 3065
Protoss_Zealot 2 7443
Protoss_Dragoon 6 9661
Protoss_Robotics_Facility 1 4631
Protoss_Observatory 1 5961
Protoss_Shuttle 1 6263
Protoss_Robotics_Support_Bay 1 6851
Protoss_Observer 2 9427
Protoss_Reaver 1 8227
9661
