Protoss_Nexus 3 9488
Protoss_Gateway 2 6072
Protoss_Assimilator 1 2219
Protoss_Cybernetics_Core 1 2873
Protoss_Dragoon 6 9861
Protoss_Citadel_of_Adun 1 5218
Protoss_Templar_Archives 1 6218
Protoss_Dark_Templar 6 9126
9861
