Protoss_Nexus 2 8291
Protoss_Gateway 2 8592
Protoss_Assimilator 1 2403
Protoss_Cybernetics_Core 1 3133
Protoss_Dragoon 6 9651
Protoss_Robotics_Facility 1 5394
Protoss_Observatory 1 6868
Protoss_Shuttle 1 7076
Protoss_Observer 3 9533
9651
