Protoss_Nexus 1 0
Protoss_Gateway 2 7137
Protoss_Assimilator 1 2604
Protoss_Cybernetics_Core 1 3357
Protoss_Dragoon 7 9675
Protoss_Robotics_Facility 1 4672
Protoss_Zealot 2 5705
Protoss_Shuttle 1 5961
Protoss_Robotics_Support_Bay 1 6083
Protoss_Reaver 1 6863
Protoss_Observatory 1 7333
Protoss_Observer 1 8036
Protoss_Scarab 3 9954
9954
