Protoss_Nexus 2 8487
Protoss_Gateway 3 9299
Protoss_Assimilator 1 2195
Protoss_Cybernetics_Core 1 2889
Protoss_Dragoon 10 9565
Protoss_Robotics_Facility 1 5501
Protoss_Observatory 1 6870
Protoss_Observer 4 9729
9729
