Protoss_Nexus 2 6905
Protoss_Gateway 3 8059
Protoss_Assimilator 1 2432
Protoss_Cybernetics_Core 1 2938
Protoss_Dragoon 13 9956
Protoss_Robotics_Facility 1 7561
Protoss_Observatory 1 9040
Protoss_Observer 1 9581
9956
