Protoss_Nexus 1 0
Protoss_Assimilator 1 1733
Protoss_Gateway 2 6382
Protoss_Cybernetics_Core 1 3109
Protoss_Dragoon 2 5501
Protoss_Robotics_Facility 1 4738
Protoss_Citadel_of_Adun 1 5178
Protoss_Templar_Archives 1 6335
Protoss_Observatory 1 6657
Protoss_Zealot 3 8936
Protoss_Observer 1 7196
Protoss_Dark_Templar 1 7436
Protoss_Shuttle 1 7798
Protoss_High_Templar 1 8161
8936
