Protoss_Nexus 1 0
Protoss_Gateway 2 3433
Protoss_Assimilator 1 2240
Protoss_Cybernetics_Core 1 2868
Protoss_Dragoon 7 8709
Protoss_Citadel_of_Adun 1 5119
Protoss_Zealot 1 5603
Protoss_Templar_Archives 1 6189
Protoss_Dark_Templar 5 9657
9657
