Protoss_Nexus 3 9217
Protoss_Gateway 3 9735
Protoss_Assimilator 1 2216
Protoss_Cybernetics_Core 1 2953
Protoss_Dragoon 10 9361
Protoss_Robotics_Facility 1 5536
Protoss_Observatory 1 6823
Protoss_Observer 3 8663
9735
