Protoss_Nexus 2 3483
Protoss_Gateway 2 5599
Protoss_Assimilator 1 3627
Protoss_Cybernetics_Core 1 4474
Protoss_Zealot 9 9721
Protoss_Dragoon 7 9981
Protoss_Shield_Battery 1 6353
9981
