Protoss_Nexus 1 0
Protoss_Gateway 2 5344
Protoss_Assimilator 2 2874
Protoss_Cybernetics_Core 1 3679
Protoss_Dragoon 6 7541
Protoss_Citadel_of_Adun 1 6699
Protoss_Templar_Archives 1 7783
Protoss_Dark_Templar 4 9546
9546
