Protoss_Nexus 2 7985
Protoss_Gateway 2 6034
Protoss_Assimilator 1 2233
Protoss_Cybernetics_Core 1 2891
Protoss_Dragoon 10 9159
Protoss_Robotics_Facility 1 5353
Protoss_Observatory 1 6667
Protoss_Observer 2 7801
9159
