Protoss_Nexus 2 9008
Protoss_Gateway 2 9448
Protoss_Assimilator 1 2573
Protoss_Cybernetics_Core 1 3256
Protoss_Dragoon 8 9530
Protoss_Robotics_Facility 1 5363
Protoss_Observatory 1 6678
Protoss_Observer 3 9881
9881
