Protoss_Nexus 2 6399
Protoss_Gateway 4 9377
Protoss_Assimilator 1 2375
Protoss_Cybernetics_Core 1 2953
Protoss_Dragoon 10 9171
Protoss_Robotics_Facility 1 7152
Protoss_Observatory 1 8615
Protoss_Observer 1 9519
Protoss_Citadel_of_Adun 1 9615
9615
