Protoss_Nexus 1 0
Protoss_Gateway 1 1887
Protoss_Assimilator 1 2271
Protoss_Cybernetics_Core 1 3007
Protoss_Dragoon 6 9655
Protoss_Robotics_Facility 1 4623
Protoss_Shuttle 1 5963
Protoss_Robotics_Support_Bay 1 6183
Protoss_Zealot 2 7263
Protoss_Reaver 2 8000
Protoss_Scarab 13 9887
9887
