Protoss_Nexus 2 9538
Protoss_Gateway 4 7818
Protoss_Assimilator 1 2198
Protoss_Cybernetics_Core 1 2883
Protoss_Robotics_Facility 1 3964
Protoss_Citadel_of_Adun 1 4453
Protoss_Shuttle 1 5256
Protoss_Templar_Archives 1 5503
Protoss_Dark_Templar 4 8966
Protoss_Dragoon 3 8691
Protoss_Observatory 1 9237
9538
