Protoss_Nexus 2 8407
Protoss_Gateway 2 4345
Protoss_Assimilator 1 2357
Protoss_Cybernetics_Core 1 2935
Protoss_Dragoon 4 8775
Protoss_Citadel_of_Adun 1 5783
Protoss_Robotics_Facility 1 6157
Protoss_Templar_Archives 1 6855
Protoss_Shuttle 1 7555
Protoss_Dark_Templar 3 8593
8775
