Protoss_Nexus 2 8345
Protoss_Gateway 2 3310
Protoss_Assimilator 1 2243
Protoss_Cybernetics_Core 1 2869
Protoss_Dragoon 5 6017
Protoss_Citadel_of_Adun 1 5591
Protoss_Zealot 1 5817
Protoss_Templar_Archives 1 6604
Protoss_Dark_Templar 4 9297
Protoss_Robotics_Facility 1 8713
Protoss_Shuttle 1 9993
9993
