Protoss_Nexus 3 8338
Protoss_Gateway 3 9222
Protoss_Assimilator 1 2357
Protoss_Cybernetics_Core 1 2853
Protoss_Dragoon 9 9433
Protoss_Robotics_Facility 1 8745
Protoss_Citadel_of_Adun 1 9177
9433
