Protoss_Nexus 1 0
Protoss_Gateway 3 7107
Protoss_Assimilator 1 2483
Protoss_Cybernetics_Core 1 3234
Protoss_Robotics_Facility 1 4328
Protoss_Dragoon 8 9431
Protoss_Observatory 1 5774
Protoss_Observer 3 7741
Protoss_Citadel_of_Adun 1 8530
Protoss_Templar_Archives 1 9763
Protoss_Shuttle 1 9976
9976
