Protoss_Nexus 3 8943
Protoss_Gateway 3 8404
Protoss_Assimilator 1 2243
Protoss_Cybernetics_Core 1 2913
Protoss_Zealot 1 3116
Protoss_Dragoon 8 9551
Protoss_Robotics_Facility 1 7093
Protoss_Observatory 1 8461
Protoss_Observer 1 9161
9551
