Protoss_Nexus 3 8918
Protoss_Gateway 4 9989
Protoss_Assimilator 1 2228
Protoss_Cybernetics_Core 1 2985
Protoss_Zealot 1 3106
Protoss_Dragoon 11 9913
Protoss_Robotics_Facility 1 6098
Protoss_Observatory 1 7413
Protoss_Observer 2 8553
9989
