Protoss_Nexus 2 8937
Protoss_Gateway 2 5387
Protoss_Assimilator 1 2565
Protoss_Cybernetics_Core 1 3246
Protoss_Dragoon 9 9987
Protoss_Robotics_Facility 1 5045
Protoss_Observatory 1 6386
Protoss_Observer 2 7755
Protoss_Citadel_of_Adun 1 9575
9987
