Protoss_Nexus 3 8582
Protoss_Gateway 4 9973
Protoss_Assimilator 2 9136
Protoss_Zealot 2 4881
Protoss_Cybernetics_Core 1 4706
Protoss_Dragoon 13 9696
Protoss_Citadel_of_Adun 1 8927
9973
