Protoss_Nexus 1 0
Protoss_Assimilator 1 1773
Protoss_Gateway 3 9412
Protoss_Cybernetics_Core 1 3345
Protoss_Stargate 1 4357
Protoss_Robotics_Facility 1 5133
Protoss_Corsair 3 6791
Protoss_Dragoon 2 7316
Protoss_Shuttle 1 6506
Protoss_Robotics_Support_Bay 1 7093
Protoss_Reaver 2 8683
Protoss_Citadel_of_Adun 1 8928
Protoss_Scarab 5 9972
9972
