Protoss_Nexus 1 0
Protoss_Gateway 1 1988
Protoss_Assimilator 1 2413
Protoss_Cybernetics_Core 1 3108
Protoss_Zealot 1 3341
Protoss_Dragoon 6 8258
Protoss_Robotics_Facility 1 5773
Protoss_Shuttle 1 7316
Protoss_Observatory 1 7721
Protoss_Robotics_Support_Bay 1 7843
Protoss_Reaver 1 8541
8541
