Protoss_Nexus 2 7791
Protoss_Gateway 4 9263
Protoss_Assimilator 1 2384
Protoss_Cybernetics_Core 1 3013
Protoss_Zealot 1 3353
Protoss_Dragoon 6 8469
Protoss_Robotics_Facility 1 4877
Protoss_Observatory 1 6237
Protoss_Observer 3 9501
9501
