Protoss_Nexus 2 6240
Protoss_Gateway 4 9816
Protoss_Assimilator 1 2434
Protoss_Cybernetics_Core 1 3073
Protoss_Dragoon 10 9246
Protoss_Robotics_Facility 1 7573
Protoss_Observatory 1 9046
Protoss_Observer 1 9661
9816
