Protoss_Nexus 2 9023
Protoss_Gateway 2 6038
Protoss_Assimilator 1 2603
Protoss_Cybernetics_Core 1 3407
Protoss_Citadel_of_Adun 1 4560
Protoss_Dragoon 5 9711
Protoss_Templar_Archives 1 5830
Protoss_Dark_Templar 4 7793
Protoss_Robotics_Facility 1 9363
9711
