Protoss_Nexus 2 8143
Protoss_Gateway 3 9973
Protoss_Assimilator 1 2418
Protoss_Cybernetics_Core 1 3105
Protoss_Dragoon 8 9451
Protoss_Robotics_Facility 1 7123
Protoss_Shuttle 1 8566
Protoss_Robotics_Support_Bay 1 8893
Protoss_Observatory 1 8938
Protoss_Zealot 2 9576
Protoss_Reaver 1 9681
9973
