Protoss_Nexus 2 7413
Protoss_Gateway 1 2022
Protoss_Assimilator 1 2498
Protoss_Cybernetics_Core 1 3173
Protoss_Dragoon 8 9615
Protoss_Robotics_Facility 1 6000
Protoss_Observatory 1 7501
9615
