Protoss_Nexus 2 8743
Protoss_Gateway 1 1945
Protoss_Assimilator 1 2348
Protoss_Cybernetics_Core 1 3063
Protoss_Dragoon 3 9711
Protoss_Robotics_Facility 1 4293
Protoss_Shuttle 1 5576
Protoss_Robotics_Support_Bay 1 5898
Protoss_Reaver 2 7668
Protoss_Zealot 1 6866
Protoss_Stargate 1 9591
9711
