Protoss_Nexus 2 9403
Protoss_Gateway 2 6843
Protoss_Assimilator 1 2273
Protoss_Cybernetics_Core 1 3121
Protoss_Dragoon 3 6011
Protoss_Robotics_Facility 1 4766
Protoss_Citadel_of_Adun 1 5962
Protoss_Templar_Archives 1 6993
Protoss_Dark_Templar 4 8753
Protoss_Shuttle 1 8081
Protoss_Observatory 1 9778
9778
