Protoss_Nexus 1 0
Protoss_Gateway 2 4530
Protoss_Assimilator 1 2228
Protoss_Cybernetics_Core 1 2883
Protoss_Dragoon 12 9098
Protoss_Robotics_Facility 1 7638
Protoss_Shuttle 1 9501
9501
