Protoss_Nexus 2 6093
Protoss_Gateway 4 9596
Protoss_Assimilator 1 2443
Protoss_Cybernetics_Core 1 3130
Protoss_Dragoon 7 9035
Protoss_Robotics_Facility 1 7113
Protoss_Zealot 5 9981
Protoss_Observatory 1 8576
Protoss_Citadel_of_Adun 1 8730
Protoss_Observer 2 9728
Protoss_Templar_Archives 1 9903
9981
