Protoss_Nexus 4 8278
Protoss_Gateway 3 9872
Protoss_Assimilator 1 2398
Protoss_Cybernetics_Core 1 3087
Protoss_Dragoon 7 9446
Protoss_Robotics_Facility 1 6293
Protoss_Observatory 1 8373
Protoss_Observer 2 9893
9893
