Protoss_Nexus 1 0
Protoss_Gateway 4 6578
Protoss_Assimilator 1 2506
Protoss_Cybernetics_Core 1 3169
Protoss_Dragoon 3 7566
Protoss_Citadel_of_Adun 1 4345
Protoss_Templar_Archives 1 5354
Protoss_Dark_Templar 4 8626
Protoss_Robotics_Facility 1 6993
Protoss_Shuttle 1 8511
8626
