Protoss_Nexus 2 8695
Protoss_Assimilator 1 1845
Protoss_Gateway 4 9580
Protoss_Cybernetics_Core 1 3308
Protoss_Dragoon 11 9961
Protoss_Robotics_Facility 1 4499
Protoss_Observatory 1 6116
Protoss_Observer 3 9641
9961
