Protoss_Nexus 3 7639
Protoss_Gateway 4 8822
Protoss_Zealot 2 4369
Protoss_Assimilator 2 8189
Protoss_Forge 1 5015
Protoss_Cybernetics_Core 1 5681
Protoss_Photon_Cannon 1 6025
Protoss_Dragoon 4 9821
Protoss_Citadel_of_Adun 1 6883
Protoss_Templar_Archives 1 8063
Protoss_Dark_Templar 2 9351
9821
