Protoss_Nexus 3 9771
Protoss_Gateway 3 8324
Protoss_Assimilator 1 2591
Protoss_Cybernetics_Core 1 3292
Protoss_Zealot 1 4195
Protoss_Dragoon 9 9435
Protoss_Robotics_Facility 1 6043
Protoss_Observatory 1 7419
Protoss_Observer 1 7971
9771
