Protoss_Nexus 2 7977
Protoss_Gateway 2 9510
Protoss_Assimilator 1 2313
Protoss_Cybernetics_Core 1 2982
Protoss_Dragoon 5 9301
Protoss_Robotics_Facility 1 4542
Protoss_Zealot 3 6557
Protoss_Shuttle 1 5825
Protoss_Robotics_Support_Bay 1 6050
Protoss_Reaver 1 6779
Protoss_Observatory 1 8759
Protoss_Scarab 2 9312
Protoss_Observer 1 9501
9510
