Protoss_Nexus 2 9168
Protoss_Gateway 2 6279
Protoss_Assimilator 1 2498
Protoss_Cybernetics_Core 1 3123
Protoss_Dragoon 11 9686
Protoss_Robotics_Facility 1 5609
Protoss_Observatory 1 7080
Protoss_Observer 3 9311
9686
