Protoss_Nexus 2 9668
Protoss_Gateway 4 8057
Protoss_Assimilator 1 2469
Protoss_Cybernetics_Core 1 3150
Protoss_Dragoon 7 8611
Protoss_Robotics_Facility 1 4523
Protoss_Observatory 1 5892
Protoss_Observer 2 9796
Protoss_Citadel_of_Adun 1 7665
Protoss_Zealot 2 9066
9796
