Protoss_Nexus 2 5170
Protoss_Gateway 1 1827
Protoss_Assimilator 3 7573
Protoss_Zealot 6 6191
Protoss_Forge 1 5669
Protoss_Photon_Cannon 1 6540
Protoss_Cybernetics_Core 1 7804
Protoss_Robotics_Facility 1 8954
Protoss_Dragoon 2 9897
9897
