Protoss_Nexus 2 8235
Protoss_Gateway 3 9694
Protoss_Assimilator 1 2243
Protoss_Cybernetics_Core 1 3178
Protoss_Dragoon 12 9877
Protoss_Robotics_Facility 1 5353
Protoss_Observatory 1 6677
Protoss_Observer 2 7831
Protoss_Shuttle 1 9611
9877
