Protoss_Nexus 2 3553
Protoss_Gateway 2 4803
Protoss_Zealot 3 8393
Protoss_Cybernetics_Core 1 4115
Protoss_Assimilator 2 6818
Protoss_Dragoon 8 9463
Protoss_Robotics_Facility 1 8247
9463
