Protoss_Nexus 2 7237
Protoss_Gateway 3 8253
Protoss_Assimilator 2 9217
Protoss_Cybernetics_Core 1 2854
Protoss_Dragoon 8 9851
Protoss_Robotics_Facility 1 5341
Protoss_Shuttle 1 6701
Protoss_Robotics_Support_Bay 1 6834
Protoss_Reaver 1 7603
Protoss_Observatory 1 8453
Protoss_Observer 1 9043
Protoss_Scarab 4 9999
9999
