Protoss_Nexus 2 5649
Protoss_Gateway 2 6187
Protoss_Assimilator 2 7638
Protoss_Cybernetics_Core 1 2869
Protoss_Dragoon 6 9859
Protoss_Robotics_Facility 1 6555
Protoss_Shuttle 1 7877
Protoss_Robotics_Support_Bay 1 8182
Protoss_Zealot 3 9317
Protoss_Reaver 1 8939
Protoss_Observatory 1 9632
9859
