Protoss_Nexus 3 9799
Protoss_Gateway 2 6253
Protoss_Assimilator 1 2389
Protoss_Cybernetics_Core 1 3023
Protoss_Dragoon 4 9975
Protoss_Robotics_Facility 1 5519
Protoss_Observatory 1 6931
Protoss_Shuttle 1 7593
Protoss_Robotics_Support_Bay 1 8004
Protoss_Reaver 1 8587
Protoss_Zealot 2 9069
Protoss_Observer 1 9639
9975
