Protoss_Nexus 3 9072
Protoss_Gateway 3 9013
Protoss_Assimilator 1 2392
Protoss_Cybernetics_Core 1 2977
Protoss_Dragoon 11 9321
Protoss_Citadel_of_Adun 1 5298
Protoss_Robotics_Facility 1 5663
Protoss_Observatory 1 7315
Protoss_Observer 3 9118
9321
