Protoss_Nexus 2 8196
Protoss_Gateway 2 8660
Protoss_Zealot 6 5562
Protoss_Assimilator 1 3819
Protoss_Cybernetics_Core 1 4938
Protoss_Citadel_of_Adun 1 6104
Protoss_Dragoon 3 7581
Protoss_Templar_Archives 1 7260
Protoss_Dark_Templar 2 9085
Protoss_Stargate 1 9302
9302
