Protoss_Nexus 2 8198
Protoss_Gateway 2 5733
Protoss_Assimilator 1 2451
Protoss_Cybernetics_Core 1 3004
Protoss_Dragoon 6 9601
Protoss_Citadel_of_Adun 1 4333
Protoss_Templar_Archives 1 5343
Protoss_Dark_Templar 3 7493
Protoss_Zealot 1 7093
Protoss_Forge 1 9982
9982
