Protoss_Nexus 2 7138
Protoss_Gateway 4 9054
Protoss_Assimilator 1 2503
Protoss_Cybernetics_Core 1 3199
Protoss_Dragoon 4 8076
Protoss_Robotics_Facility 1 4858
Protoss_Observatory 1 6298
Protoss_Observer 3 8786
Protoss_Zealot 3 9481
Protoss_Shuttle 1 9388
9481
