Protoss_Nexus 2 9338
Protoss_Gateway 2 8279
Protoss_Assimilator 1 2346
Protoss_Cybernetics_Core 1 2943
Protoss_Dragoon 8 9428
Protoss_Robotics_Facility 1 5873
Protoss_Citadel_of_Adun 1 7292
Protoss_Observatory 1 7457
Protoss_Shuttle 1 7921
Protoss_Observer 1 8823
9428
