Protoss_Nexus 1 0
Protoss_Gateway 2 8080
Protoss_Assimilator 1 2458
Protoss_Cybernetics_Core 1 3047
Protoss_Dragoon 7 9856
Protoss_Robotics_Facility 1 4883
Protoss_Shuttle 1 6181
Protoss_Robotics_Support_Bay 1 6252
Protoss_Observatory 1 6519
Protoss_Reaver 1 7083
Protoss_Citadel_of_Adun 1 7774
Protoss_Observer 3 9417
Protoss_Scarab 7 9912
9912
