Protoss_Nexus 2 3259
Protoss_Gateway 4 8560
Protoss_Assimilator 2 9797
Protoss_Cybernetics_Core 1 3967
Protoss_Zealot 1 4357
Protoss_Dragoon 9 9729
Protoss_Robotics_Facility 1 7284
Protoss_Observatory 1 8692
Protoss_Shuttle 1 8697
Protoss_Robotics_Support_Bay 1 9470
Protoss_Observer 1 9599
9797
