Protoss_Nexus 2 9245
Protoss_Gateway 3 6173
Protoss_Assimilator 1 2432
Protoss_Cybernetics_Core 1 3081
Protoss_Dragoon 13 9681
Protoss_Robotics_Facility 1 5539
Protoss_Observatory 1 6902
Protoss_Observer 1 8103
9681
