Protoss_Nexus 1 0
Protoss_Gateway 2 3621
Protoss_Assimilator 1 2475
Protoss_Cybernetics_Core 1 3077
Protoss_Dragoon 9 8661
Protoss_Zealot 2 6531
Protoss_Robotics_Facility 1 7733
Protoss_Shuttle 1 9083
Protoss_Robotics_Support_Bay 1 9193
9193
