Protoss_Nexus 2 2651
Protoss_Gateway 4 9400
Protoss_Assimilator 2 8176
Protoss_Cybernetics_Core 1 4101
Protoss_Zealot 5 9307
Protoss_Dragoon 10 8525
Protoss_Robotics_Facility 1 7130
Protoss_Observatory 1 8876
9400
