Protoss_Nexus 2 9340
Protoss_Gateway 2 3345
Protoss_Assimilator 1 2370
Protoss_Cybernetics_Core 1 2869
Protoss_Dragoon 5 8579
Protoss_Robotics_Facility 1 5843
Protoss_Zealot 5 7507
Protoss_Shuttle 1 7125
Protoss_Robotics_Support_Bay 1 7410
Protoss_Reaver 1 8099
Protoss_Scarab 3 9871
9871
