Protoss_Nexus 1 0
Protoss_Gateway 2 4333
Protoss_Assimilator 1 2375
Protoss_Cybernetics_Core 1 3209
Protoss_Dragoon 2 5541
Protoss_Citadel_of_Adun 1 5183
Protoss_Robotics_Facility 1 5878
Protoss_Templar_Archives 1 6213
Protoss_Shuttle 1 7166
Protoss_Dark_Templar 8 9991
9991
