Protoss_Nexus 2 8049
Protoss_Gateway 2 6046
Protoss_Assimilator 1 2410
Protoss_Cybernetics_Core 1 3043
Protoss_Dragoon 10 9449
Protoss_Robotics_Facility 1 5473
Protoss_Observatory 1 6821
Protoss_Observer 2 9341
9449
