Protoss_Nexus 2 7405
Protoss_Gateway 2 3445
Protoss_Assimilator 1 2250
Protoss_Cybernetics_Core 1 2947
Protoss_Dragoon 10 9309
Protoss_Zealot 2 7565
Protoss_Robotics_Facility 1 7947
Protoss_Shuttle 1 9459
Protoss_Robotics_Support_Bay 1 9682
9682
