Protoss_Nexus 3 9438
Protoss_Gateway 2 7913
Protoss_Assimilator 1 2385
Protoss_Cybernetics_Core 1 3166
Protoss_Dragoon 7 9161
Protoss_Robotics_Facility 1 4713
Protoss_Shuttle 1 6026
Protoss_Observatory 1 6533
Protoss_Observer 1 7986
9438
