Protoss_Nexus 1 0
Protoss_Gateway 2 7224
Protoss_Assimilator 1 2412
Protoss_Cybernetics_Core 1 2783
Protoss_Dragoon 6 9111
Protoss_Robotics_Facility 1 5906
Protoss_Zealot 6 9863
Protoss_Shuttle 1 7286
Protoss_Robotics_Support_Bay 1 7672
Protoss_Citadel_of_Adun 1 8559
Protoss_Reaver 1 8956
Protoss_Templar_Archives 1 9663
9863
