Protoss_Nexus 1 0
Protoss_Gateway 2 8256
Protoss_Assimilator 1 2342
Protoss_Cybernetics_Core 1 3125
Protoss_Dragoon 7 9566
Protoss_Robotics_Facility 1 4664
Protoss_Shuttle 1 5961
Protoss_Observatory 1 6468
Protoss_Robotics_Support_Bay 1 6932
Protoss_Observer 2 9817
Protoss_Reaver 2 8765
9817
