Protoss_Nexus 2 5913
Protoss_Gateway 4 9045
Protoss_Assimilator 1 2466
Protoss_Cybernetics_Core 1 3104
Protoss_Dragoon 8 8281
Protoss_Robotics_Facility 1 7431
Protoss_Shuttle 1 8759
Protoss_Robotics_Support_Bay 1 9083
Protoss_Reaver 1 9661
9661
