Protoss_Nexus 2 8699
Protoss_Assimilator 2 9909
Protoss_Gateway 2 6018
Protoss_Cybernetics_Core 1 3321
Protoss_Dragoon 5 9423
Protoss_Robotics_Facility 1 5401
Protoss_Citadel_of_Adun 1 5549
Protoss_Templar_Archives 1 6537
Protoss_Shuttle 1 6875
Protoss_Dark_Templar 3 8285
Protoss_Observatory 1 8133
Protoss_Observer 1 8773
9909
