Protoss_Nexus 3 8341
Protoss_Gateway 5 9538
Protoss_Assimilator 1 2313
Protoss_Cybernetics_Core 1 3068
Protoss_Dragoon 7 9876
Protoss_Zealot 1 6763
Protoss_Robotics_Facility 1 8633
9876
