Protoss_Nexus 2 8907
Protoss_Gateway 2 4117
Protoss_Assimilator 1 2813
Protoss_Zealot 5 9519
Protoss_Cybernetics_Core 1 3772
Protoss_Dragoon 10 8527
Protoss_Citadel_of_Adun 1 9452
9519
