Protoss_Nexus 3 9956
Protoss_Gateway 2 9330
Protoss_Assimilator 2 8449
Protoss_Cybernetics_Core 1 2935
Protoss_Dragoon 5 7869
Protoss_Robotics_Facility 1 6117
Protoss_Shuttle 1 7593
Protoss_Robotics_Support_Bay 1 7635
Protoss_Reaver 1 8733
Protoss_Observatory 1 8989
Protoss_Zealot 1 9375
Protoss_Observer 1 9785
9956
