Protoss_Nexus 3 9946
Protoss_Gateway 4 9538
Protoss_Assimilator 1 2207
Protoss_Cybernetics_Core 1 2919
Protoss_Zealot 1 3173
Protoss_Dragoon 9 9853
Protoss_Robotics_Facility 1 5765
Protoss_Observatory 1 7104
Protoss_Observer 2 8579
9946
