Protoss_Nexus 2 5877
Protoss_Gateway 4 9745
Protoss_Assimilator 2 9476
Protoss_Cybernetics_Core 1 2906
Protoss_Dragoon 10 8883
Protoss_Robotics_Facility 1 6584
Protoss_Observatory 1 7885
Protoss_Observer 1 8415
9745
