Protoss_Nexus 2 2643
Protoss_Gateway 5 8468
Protoss_Assimilator 1 3447
Protoss_Cybernetics_Core 1 4093
Protoss_Dragoon 16 9989
Protoss_Robotics_Facility 1 7129
Protoss_Zealot 2 9107
9989
