Protoss_Nexus 2 2637
Protoss_Gateway 4 8935
Protoss_Assimilator 2 7626
Protoss_Cybernetics_Core 1 4047
Protoss_Zealot 1 4517
Protoss_Dragoon 12 9313
Protoss_Robotics_Facility 1 8131
Protoss_Observatory 1 9488
9488
