Protoss_Nexus 2 7664
Protoss_Gateway 4 9136
Protoss_Assimilator 1 2233
Protoss_Cybernetics_Core 1 2855
Protoss_Zealot 2 5905
Protoss_Dragoon 6 9533
Protoss_Robotics_Facility 1 3994
Protoss_Shuttle 1 5319
Protoss_Robotics_Support_Bay 1 5556
Protoss_Reaver 1 6261
Protoss_Observatory 1 7797
Protoss_Scarab 10 9967
Protoss_Observer 1 9275
9967
