Protoss_Nexus 2 6499
Protoss_Gateway 2 6642
Protoss_Assimilator 1 2238
Protoss_Cybernetics_Core 1 3052
Protoss_Zealot 1 3231
Protoss_Dragoon 9 9417
Protoss_Robotics_Facility 1 7746
Protoss_Observatory 1 9237
Protoss_Shuttle 1 9521
Protoss_Robotics_Support_Bay 1 9891
9891
