Protoss_Nexus 2 6419
Protoss_Assimilator 5 7955
Protoss_Gateway 3 9861
Protoss_Cybernetics_Core 1 3531
Protoss_Dragoon 9 9447
Protoss_Robotics_Facility 1 7628
Protoss_Observatory 1 8991
Protoss_Citadel_of_Adun 1 9051
Protoss_Observer 1 9555
9861
