Protoss_Nexus 2 6863
Protoss_Gateway 4 9776
Protoss_Assimilator 1 2370
Protoss_Cybernetics_Core 1 3013
Protoss_Dragoon 9 9255
Protoss_Robotics_Facility 1 7420
Protoss_Observatory 1 8767
Protoss_Observer 2 9909
9909
