Protoss_Nexus 2 5647
Protoss_Gateway 3 6373
Protoss_Assimilator 1 2309
Protoss_Cybernetics_Core 1 2937
Protoss_Dragoon 9 8535
Protoss_Robotics_Facility 1 5876
Protoss_Observatory 1 7347
Protoss_Observer 2 8743
Protoss_Zealot 3 9287
Protoss_Shuttle 1 9453
9453
