Protoss_Nexus 2 7239
Protoss_Gateway 2 7790
Protoss_Assimilator 1 2487
Protoss_Cybernetics_Core 1 3076
Protoss_Zealot 1 3255
Protoss_Dragoon 9 9781
Protoss_Robotics_Facility 1 5515
Protoss_Observatory 1 6801
Protoss_Observer 2 8209
Protoss_Robotics_Support_Bay 1 8344
Protoss_Shuttle 1 9021
9781
