Protoss_Nexus 1 0
Protoss_Gateway 3 5597
Protoss_Assimilator 1 2396
Protoss_Cybernetics_Core 1 3176
Protoss_Dragoon 13 9267
Protoss_Zealot 3 9715
Protoss_Citadel_of_Adun 1 9031
9715
