Special_Protoss_Temple 14 0
Protoss_Nexus 1 0
Protoss_Gateway 2 2694
Protoss_Zealot 11 8493
Protoss_Forge 1 4845
Protoss_Assimilator 1 6158
Protoss_Photon_Cannon 4 8545
Protoss_Cybernetics_Core 1 8276
Protoss_Dragoon 2 9319
9319
