Protoss_Nexus 3 7744
Protoss_Gateway 1 1880
Protoss_Assimilator 1 2353
Protoss_Cybernetics_Core 1 2982
Protoss_Dragoon 6 8845
Protoss_Robotics_Facility 1 6799
Protoss_Shuttle 1 8423
Protoss_Robotics_Support_Bay 1 9072
Protoss_Zealot 1 9597
Protoss_Reaver 1 9625
Protoss_Observatory 1 9898
9898
