Protoss_Nexus 3 7930
Protoss_Gateway 4 9212
Protoss_Assimilator 1 2285
Protoss_Zealot 1 2931
Protoss_Cybernetics_Core 1 4247
Protoss_Dragoon 11 9999
Protoss_Robotics_Facility 1 8378
Protoss_Forge 1 9973
9999
