Protoss_Nexus 2 2677
Protoss_Gateway 4 8150
Protoss_Assimilator 2 6383
Protoss_Cybernetics_Core 1 4097
Protoss_Dragoon 12 9267
Protoss_Robotics_Facility 1 7331
Protoss_Observatory 1 8721
Protoss_Observer 2 9947
9947
