Protoss_Nexus 3 9858
Protoss_Gateway 5 8834
Protoss_Assimilator 2 6458
Protoss_Cybernetics_Core 1 4132
Protoss_Zealot 4 9075
Protoss_Dragoon 5 7540
Protoss_Robotics_Facility 1 6221
Protoss_Shuttle 1 7683
Protoss_Observatory 2 9446
Protoss_Observer 1 9989
9989
