Protoss_Nexus 2 7282
Protoss_Gateway 3 9687
Protoss_Assimilator 1 2272
Protoss_Zealot 2 3705
Protoss_Cybernetics_Core 1 3467
Protoss_Dragoon 8 9859
Protoss_Robotics_Facility 1 6178
Protoss_Observatory 1 7465
Protoss_Observer 2 8989
Protoss_Citadel_of_Adun 1 8067
Protoss_Templar_Archives 1 9633
9859
