Protoss_Nexus 3 7991
Protoss_Gateway 4 9256
Protoss_Assimilator 2 8029
Protoss_Cybernetics_Core 1 2821
Protoss_Dragoon 8 8783
Protoss_Robotics_Facility 1 8167
Protoss_Citadel_of_Adun 1 8611
Protoss_Observatory 1 9469
Protoss_Observer 1 9997
9997
