Protoss_Nexus 2 8899
Protoss_Gateway 3 9467
Protoss_Assimilator 1 2472
Protoss_Cybernetics_Core 1 3174
Protoss_Dragoon 4 9907
Protoss_Citadel_of_Adun 1 5434
Protoss_Templar_Archives 1 6445
Protoss_Zealot 1 6597
Protoss_Dark_Templar 7 9865
9907
