Special_Protoss_Temple 14 0
Protoss_Nexus 2 7111
Protoss_Gateway 2 5267
Protoss_Assimilator 1 2410
Protoss_Cybernetics_Core 1 3027
Protoss_Dragoon 11 9509
Protoss_Robotics_Facility 1 8236
Protoss_Citadel_of_Adun 1 8348
9509
