Protoss_Nexus 3 8342
Protoss_Gateway 5 9971
Protoss_Assimilator 2 5880
Protoss_Cybernetics_Core 1 4227
Protoss_Zealot 2 9385
Protoss_Dragoon 8 9951
Protoss_Robotics_Facility 1 6683
Protoss_Observatory 1 8009
Protoss_Observer 1 9097
Protoss_Citadel_of_Adun 1 9164
Protoss_Forge 1 9236
Protoss_Shuttle 1 9699
9971
