Protoss_Nexus 2 7616
Protoss_Gateway 2 8781
Protoss_Assimilator 2 9710
Protoss_Cybernetics_Core 1 2818
Protoss_Zealot 1 3167
Protoss_Dragoon 7 9109
Protoss_Robotics_Facility 1 5982
Protoss_Observatory 1 7577
Protoss_Observer 2 8709
Protoss_Citadel_of_Adun 1 8339
Protoss_Templar_Archives 1 9329
Protoss_Shuttle 1 9403
9710
