Special_Protoss_Temple 30 0
Protoss_Nexus 2 9630
Protoss_Gateway 1 1827
Protoss_Assimilator 1 2295
Protoss_Cybernetics_Core 1 2858
Protoss_Zealot 4 9303
Protoss_Dragoon 6 7949
Protoss_Robotics_Facility 1 5557
Protoss_Shuttle 1 6843
Protoss_Robotics_Support_Bay 1 6885
Protoss_Reaver 2 8797
Protoss_Observatory 1 9137
Protoss_Scarab 2 9840
Protoss_Observer 1 9849
9849
