Protoss_Nexus 2 9703
Protoss_Gateway 3 8881
Protoss_Assimilator 1 2433
Protoss_Cybernetics_Core 1 2975
Protoss_Dragoon 5 9925
Protoss_Robotics_Facility 1 4453
Protoss_Shuttle 1 5751
Protoss_Robotics_Support_Bay 1 5885
Protoss_Zealot 2 7099
Protoss_Reaver 2 7859
Protoss_Scarab 2 8660
Protoss_Observatory 1 9232
Protoss_Observer 1 9859
9925
