Protoss_Nexus 2 9999
Protoss_Gateway 2 3433
Protoss_Assimilator 1 2221
Protoss_Cybernetics_Core 1 2857
Protoss_Dragoon 9 8385
Protoss_Robotics_Facility 1 6823
Protoss_Shuttle 1 8105
Protoss_Robotics_Support_Bay 1 8127
Protoss_Zealot 3 9151
Protoss_Reaver 1 9009
Protoss_Observatory 1 9549
9999
