Protoss_Nexus 1 0
Protoss_Gateway 2 6756
Protoss_Assimilator 1 2406
Protoss_Zealot 1 2989
Protoss_Cybernetics_Core 1 3400
Protoss_Dragoon 6 9311
Protoss_Citadel_of_Adun 1 5605
Protoss_Robotics_Facility 1 6490
Protoss_Templar_Archives 1 6639
Protoss_Dark_Templar 3 8559
Protoss_Shuttle 1 7983
Protoss_Observatory 1 8140
Protoss_Observer 2 9721
9721
