Protoss_Nexus 3 5904
Protoss_Gateway 3 9642
Protoss_Assimilator 1 2421
Protoss_Cybernetics_Core 1 2962
Protoss_Dragoon 9 9257
Protoss_Robotics_Facility 1 8151
Protoss_Observatory 1 9551
9642
