Protoss_Nexus 2 6861
Protoss_Gateway 4 9863
Protoss_Assimilator 2 9130
Protoss_Cybernetics_Core 1 2877
Protoss_Dragoon 11 9553
Protoss_Robotics_Facility 1 7559
Protoss_Observatory 1 8981
Protoss_Citadel_of_Adun 1 9066
Protoss_Observer 1 9513
9863
