Protoss_Nexus 2 8117
Protoss_Gateway 1 2060
Protoss_Assimilator 1 2494
Protoss_Cybernetics_Core 1 3100
Protoss_Zealot 2 6293
Protoss_Robotics_Facility 1 4436
Protoss_Dragoon 5 9333
Protoss_Shuttle 1 5831
Protoss_Robotics_Support_Bay 1 6012
Protoss_Reaver 1 6733
Protoss_Scarab 13 9867
Protoss_Observatory 1 9823
9867
