Special_Protoss_Temple 30 0
Protoss_Nexus 1 0
Protoss_Gateway 2 6219
Protoss_Assimilator 1 2476
Protoss_Cybernetics_Core 1 3081
Protoss_Zealot 1 3249
Protoss_Dragoon 10 9515
Protoss_Robotics_Facility 1 6081
Protoss_Shuttle 1 7455
Protoss_Robotics_Support_Bay 1 8353
Protoss_Observatory 1 8671
Protoss_Reaver 1 8915
Protoss_Observer 1 9967
9967
