Protoss_Nexus 2 6637
Protoss_Gateway 3 8368
Protoss_Assimilator 1 2365
Protoss_Cybernetics_Core 1 3021
Protoss_Dragoon 11 9857
Protoss_Zealot 2 5949
Protoss_Robotics_Facility 1 7685
Protoss_Observatory 1 9483
9857
