Protoss_Nexus 2 6567
Protoss_Gateway 2 7632
Protoss_Assimilator 2 7722
Protoss_Cybernetics_Core 1 2833
Protoss_Dragoon 5 9147
Protoss_Citadel_of_Adun 1 5043
Protoss_Templar_Archives 1 6080
Protoss_Dark_Templar 1 7063
Protoss_Stargate 2 9107
Protoss_Fleet_Beacon 1 8557
Protoss_Carrier 1 9785
9785
