Protoss_Nexus 2 5062
Protoss_Gateway 3 8269
Protoss_Assimilator 2 7936
Protoss_Cybernetics_Core 1 2910
Protoss_Dragoon 9 9469
Protoss_Robotics_Facility 1 5765
Protoss_Observatory 1 7308
Protoss_Observer 3 9899
Protoss_Citadel_of_Adun 1 8884
Protoss_Zealot 1 9881
9899
