Protoss_Nexus 2 9247
Protoss_Gateway 3 4353
Protoss_Assimilator 2 3661
Protoss_Zealot 6 6183
Protoss_Cybernetics_Core 1 5650
Protoss_Citadel_of_Adun 1 6677
Protoss_Robotics_Facility 1 6833
Protoss_Dragoon 2 7147
Protoss_Templar_Archives 1 7783
Protoss_Shuttle 1 8233
Protoss_Dark_Templar 4 9595
9595
