Protoss_Nexus 2 9418
Protoss_Gateway 2 3545
Protoss_Assimilator 1 2265
Protoss_Cybernetics_Core 1 3023
Protoss_Dragoon 7 7175
Protoss_Citadel_of_Adun 1 6489
Protoss_Robotics_Facility 1 7889
Protoss_Templar_Archives 1 7984
Protoss_Dark_Templar 3 9991
Protoss_Shuttle 1 9675
9991
