Protoss_Nexus 2 4555
Protoss_Assimilator 3 7626
Protoss_Gateway 4 9254
Protoss_Zealot 3 5633
Protoss_Cybernetics_Core 1 5425
Protoss_Dragoon 9 9713
Protoss_Robotics_Facility 1 9037
Protoss_Citadel_of_Adun 1 9677
9713
