Protoss_Nexus 2 6246
Protoss_Gateway 2 8828
Protoss_Assimilator 2 8469
Protoss_Cybernetics_Core 1 3141
Protoss_Dragoon 4 7141
Protoss_Citadel_of_Adun 1 6778
Protoss_Robotics_Facility 1 7069
Protoss_Templar_Archives 1 7968
Protoss_Observatory 1 8414
Protoss_Shuttle 1 8666
Protoss_Dark_Templar 3 9826
Protoss_Observer 1 9568
9826
