Protoss_Nexus 2 5383
Protoss_Gateway 3 7209
Protoss_Assimilator 1 2335
Protoss_Cybernetics_Core 1 2838
Protoss_Dragoon 12 9397
Protoss_Robotics_Facility 1 6381
Protoss_Observatory 1 7721
Protoss_Observer 2 9691
9691
