Protoss_Nexus 3 9824
Protoss_Gateway 2 8735
Protoss_Assimilator 2 8579
Protoss_Cybernetics_Core 1 3027
Protoss_Zealot 1 3411
Protoss_Dragoon 5 8075
Protoss_Robotics_Facility 1 6462
Protoss_Citadel_of_Adun 1 7192
Protoss_Shuttle 1 7909
Protoss_Templar_Archives 1 8426
Protoss_Dark_Templar 1 9425
9824
