Protoss_Nexus 2 8058
Protoss_Gateway 2 4698
Protoss_Zealot 2 3371
Protoss_Assimilator 1 3119
Protoss_Cybernetics_Core 1 4173
Protoss_Dragoon 6 9046
Protoss_Citadel_of_Adun 1 8283
Protoss_Templar_Archives 1 9300
Protoss_Robotics_Facility 1 9932
9932
