Protoss_Nexus 2 6563
Protoss_Gateway 4 8801
Protoss_Assimilator 1 2200
Protoss_Cybernetics_Core 1 2849
Protoss_Zealot 1 3067
Protoss_Dragoon 12 9955
Protoss_Robotics_Facility 1 7277
Protoss_Observatory 1 8706
Protoss_Observer 2 9847
9955
