Protoss_Nexus 2 6498
Protoss_Gateway 1 1871
Protoss_Assimilator 1 2244
Protoss_Zealot 2 3537
Protoss_Cybernetics_Core 1 3134
Protoss_Dragoon 8 9878
Protoss_Robotics_Facility 1 8098
Protoss_Shuttle 1 9550
9878
