Protoss_Nexus 2 8181
Protoss_Gateway 1 1813
Protoss_Assimilator 1 2345
Protoss_Cybernetics_Core 1 2876
Protoss_Zealot 1 3175
Protoss_Dragoon 6 9493
Protoss_Robotics_Facility 1 5401
Protoss_Shuttle 1 6677
Protoss_Robotics_Support_Bay 1 7153
Protoss_Reaver 1 7683
Protoss_Observatory 1 8259
Protoss_Observer 2 9441
Protoss_Scarab 1 9971
9971
