Protoss_Nexus 1 0
Protoss_Gateway 2 6618
Protoss_Assimilator 1 2596
Protoss_Zealot 3 4115
Protoss_Cybernetics_Core 1 3945
Protoss_Dragoon 3 6451
Protoss_Citadel_of_Adun 1 6023
Protoss_Templar_Archives 1 7071
Protoss_Robotics_Facility 1 7120
Protoss_Dark_Templar 4 8864
Protoss_Shuttle 1 8405
Protoss_Observatory 1 9335
Protoss_Observer 1 9911
9911
