Protoss_Nexus 2 2596
Protoss_Gateway 2 4293
Protoss_Assimilator 2 9119
Protoss_Cybernetics_Core 1 4137
Protoss_Zealot 3 9755
Protoss_Dragoon 7 9003
Protoss_Robotics_Facility 1 7074
Protoss_Shuttle 1 8429
Protoss_Observatory 1 8607
Protoss_Robotics_Support_Bay 1 8665
Protoss_Observer 1 9465
9755
