Protoss_Nexus 2 6477
Protoss_Gateway 4 8588
Protoss_Assimilator 2 8757
Protoss_Cybernetics_Core 1 2987
Protoss_Dragoon 6 9153
Protoss_Citadel_of_Adun 1 5124
Protoss_Templar_Archives 1 6239
Protoss_Dark_Templar 2 9023
Protoss_Robotics_Facility 1 8033
Protoss_Observatory 1 9905
9905
