Protoss_Nexus 2 8029
Protoss_Gateway 2 8571
Protoss_Assimilator 1 2642
Protoss_Zealot 4 8127
Protoss_Cybernetics_Core 1 3666
Protoss_Dragoon 7 9863
Protoss_Robotics_Facility 1 5480
Protoss_Shuttle 1 6763
Protoss_Robotics_Support_Bay 1 7231
Protoss_Reaver 1 7769
Protoss_Scarab 4 9985
Protoss_Observatory 1 9506
9985
