Protoss_Nexus 1 0
Protoss_Gateway 2 5131
Protoss_Assimilator 1 2425
Protoss_Cybernetics_Core 1 2972
Protoss_Dragoon 11 9479
Protoss_Robotics_Facility 1 6479
Protoss_Robotics_Support_Bay 1 8063
Protoss_Zealot 2 8125
Protoss_Shuttle 1 8525
Protoss_Reaver 1 9427
9479
