Protoss_Nexus 2 7289
Protoss_Gateway 2 4582
Protoss_Assimilator 1 2183
Protoss_Cybernetics_Core 1 2805
Protoss_Zealot 3 9909
Protoss_Dragoon 10 9147
Protoss_Robotics_Facility 1 7963
Protoss_Shuttle 1 9339
Protoss_Robotics_Support_Bay 1 9471
9909
