Protoss_Nexus 2 7393
Protoss_Gateway 1 1820
Protoss_Assimilator 1 2159
Protoss_Cybernetics_Core 1 2805
Protoss_Zealot 2 8187
Protoss_Dragoon 6 9605
Protoss_Robotics_Facility 1 5398
Protoss_Shuttle 1 6677
Protoss_Robotics_Support_Bay 1 7018
Protoss_Reaver 1 7671
Protoss_Observatory 1 8528
Protoss_Observer 2 9737
Protoss_Scarab 2 9976
9976
