Special_Protoss_Temple 14 0
Protoss_Nexus 2 9013
Protoss_Gateway 2 5332
Protoss_Assimilator 1 2436
Protoss_Cybernetics_Core 1 2940
Protoss_Dragoon 10 8891
Protoss_Robotics_Facility 1 5929
Protoss_Observatory 1 7699
Protoss_Zealot 1 7999
Protoss_Observer 2 9193
9193
