Protoss_Nexus 3 8294
Protoss_Gateway 6 9431
Protoss_Assimilator 1 2255
Protoss_Cybernetics_Core 1 2957
Protoss_Dragoon 6 9555
Protoss_Robotics_Facility 1 6521
Protoss_Shuttle 1 7817
Protoss_Robotics_Support_Bay 1 8063
Protoss_Reaver 1 8719
Protoss_Observatory 1 9567
9567
