Protoss_Nexus 2 6197
Protoss_Gateway 3 9339
Protoss_Assimilator 2 8197
Protoss_Cybernetics_Core 1 2883
Protoss_Dragoon 11 9572
Protoss_Robotics_Facility 1 5296
Protoss_Observatory 1 6679
Protoss_Observer 2 7863
9572
