Protoss_Nexus 3 9651
Protoss_Gateway 2 5184
Protoss_Assimilator 2 3733
Protoss_Cybernetics_Core 1 2982
Protoss_Dragoon 11 9272
Protoss_Robotics_Facility 1 7905
Protoss_Observatory 1 9289
Protoss_Observer 1 9961
9961
