Protoss_Nexus 3 8266
Protoss_Gateway 4 9500
Protoss_Assimilator 1 2197
Protoss_Cybernetics_Core 1 2826
Protoss_Dragoon 7 9573
Protoss_Robotics_Facility 1 6897
Protoss_Observatory 1 8225
Protoss_Observer 2 9357
9573
