Protoss_Nexus 2 8961
Protoss_Gateway 2 5077
Protoss_Assimilator 2 9330
Protoss_Cybernetics_Core 1 2975
Protoss_Citadel_of_Adun 1 4065
Protoss_Dragoon 8 9939
Protoss_Templar_Archives 1 5451
Protoss_Dark_Templar 3 9063
Protoss_Stargate 1 9556
9939
