Protoss_Nexus 2 8719
Protoss_Gateway 9 6067
Protoss_Assimilator 1 4459
Protoss_Cybernetics_Core 1 5341
Protoss_Dragoon 2 7087
Protoss_Zealot 2 8121
Protoss_Citadel_of_Adun 1 7608
Protoss_Robotics_Facility 1 7928
Protoss_Templar_Archives 1 8843
Protoss_Shuttle 1 9309
Protoss_Dark_Templar 2 9839
9839
