Protoss_Nexus 2 6277
Special_Protoss_Temple 8 0
Protoss_Gateway 3 7784
Protoss_Assimilator 1 2425
Protoss_Cybernetics_Core 1 2969
Protoss_Zealot 1 3193
Protoss_Dragoon 10 8965
Protoss_Robotics_Facility 1 9378
9378
