Special_Protoss_Temple 30 0
Protoss_Nexus 3 9299
Protoss_Gateway 2 5903
Protoss_Assimilator 1 2373
Protoss_Cybernetics_Core 1 2987
Protoss_Dragoon 8 8325
Protoss_Robotics_Facility 1 5495
Protoss_Observatory 1 7240
Protoss_Observer 1 8235
Protoss_Shuttle 1 8837
Protoss_Robotics_Support_Bay 1 9659
Protoss_Zealot 2 9893
9893
