Protoss_Nexus 2 8610
Protoss_Gateway 2 5836
Protoss_Assimilator 1 2195
Protoss_Cybernetics_Core 1 2859
Protoss_Zealot 1 3037
Protoss_Dragoon 6 9963
Protoss_Citadel_of_Adun 1 4586
Protoss_Robotics_Facility 1 5488
Protoss_Templar_Archives 1 6079
Protoss_Shuttle 2 9511
Protoss_Dark_Templar 3 9211
Protoss_Observatory 1 7553
Protoss_Observer 1 8111
9963
