Protoss_Nexus 2 2677
Protoss_Gateway 4 7605
Protoss_Assimilator 2 6924
Protoss_Cybernetics_Core 1 4079
Protoss_Dragoon 11 8963
Protoss_Robotics_Facility 1 6794
Protoss_Zealot 1 7223
Protoss_Observatory 1 8133
Protoss_Observer 2 9291
Protoss_Robotics_Support_Bay 1 9353
9353
