Protoss_Nexus 3 8999
Protoss_Gateway 3 8184
Protoss_Assimilator 1 2257
Protoss_Cybernetics_Core 1 2901
Protoss_Dragoon 10 9953
Protoss_Robotics_Facility 1 4418
Protoss_Observatory 1 5904
Protoss_Observer 4 9221
9953
