Special_Protoss_Temple 14 0
Protoss_Nexus 2 2681
Protoss_Gateway 3 8895
Protoss_Assimilator 2 7801
Protoss_Cybernetics_Core 1 4134
Protoss_Zealot 1 4405
Protoss_Dragoon 10 9117
Protoss_Robotics_Facility 1 7172
Protoss_Observatory 1 8773
Protoss_Observer 2 9947
Protoss_Citadel_of_Adun 1 9632
9947
