Special_Protoss_Temple 14 0
Protoss_Nexus 2 6993
Protoss_Gateway 2 7679
Protoss_Assimilator 1 2319
Protoss_Cybernetics_Core 1 2963
Protoss_Dragoon 10 9561
Protoss_Robotics_Facility 1 5759
Protoss_Observatory 1 7123
Protoss_Observer 3 9057
9561
