Protoss_Nexus 2 8879
Protoss_Gateway 2 7524
Protoss_Assimilator 1 2814
Protoss_Cybernetics_Core 1 3167
Protoss_Zealot 5 9246
Protoss_Dragoon 5 7440
Protoss_Robotics_Facility 1 6542
Protoss_Observatory 1 7894
Protoss_Observer 1 8611
Protoss_Shuttle 1 9311
9311
