Protoss_Nexus 2 6629
Protoss_Gateway 3 8681
Protoss_Assimilator 2 8096
Protoss_Cybernetics_Core 1 3122
Protoss_Dragoon 6 9861
Protoss_Citadel_of_Adun 1 5562
Protoss_Templar_Archives 1 6879
Protoss_Robotics_Facility 1 7738
Protoss_Dark_Templar 3 9633
Protoss_Observatory 1 9163
Protoss_Stargate 1 9392
Protoss_Observer 1 9823
9861
