Protoss_Nexus 2 7013
Protoss_Gateway 2 7725
Protoss_Assimilator 1 2249
Protoss_Cybernetics_Core 1 2789
Protoss_Zealot 1 3051
Protoss_Dragoon 6 8049
Protoss_Robotics_Facility 1 5219
Protoss_Observatory 1 6507
Protoss_Observer 2 7643
Protoss_Shuttle 1 8383
Protoss_Robotics_Support_Bay 1 8738
Protoss_Reaver 1 9319
9319
