Protoss_Nexus 3 8749
Protoss_Gateway 4 9610
Protoss_Assimilator 1 3309
Protoss_Cybernetics_Core 1 3965
Protoss_Zealot 1 4499
Protoss_Dragoon 3 6223
Protoss_Citadel_of_Adun 1 6531
Protoss_Robotics_Facility 1 7516
Protoss_Templar_Archives 1 7532
Protoss_Dark_Templar 2 8651
Protoss_Shuttle 1 8809
Protoss_Observatory 1 9128
Protoss_Observer 1 9711
9711
