Special_Protoss_Temple 30 0
Protoss_Nexus 3 9765
Protoss_Gateway 2 7678
Protoss_Assimilator 1 2135
Protoss_Cybernetics_Core 1 2816
Protoss_Zealot 3 8327
Protoss_Dragoon 5 9807
Protoss_Robotics_Facility 1 5375
Protoss_Shuttle 1 6657
Protoss_Robotics_Support_Bay 1 7556
Protoss_Observatory 1 7608
Protoss_Reaver 1 8089
Protoss_Observer 1 9141
Protoss_Scarab 2 9975
9975
