Protoss_Nexus 2 6071
Protoss_Gateway 2 7393
Protoss_Assimilator 1 2412
Protoss_Cybernetics_Core 1 2947
Protoss_Dragoon 8 8739
Protoss_Robotics_Facility 1 6853
Protoss_Shuttle 1 8341
Protoss_Robotics_Support_Bay 1 8943
Protoss_Observatory 1 9452
Protoss_Zealot 2 9799
Protoss_Reaver 1 9807
9807
