Protoss_Nexus 2 9295
Protoss_Gateway 1 1933
Protoss_Zealot 3 4151
Protoss_Assimilator 1 3078
Protoss_Cybernetics_Core 1 3793
Protoss_Dragoon 6 9926
Protoss_Robotics_Facility 1 5153
Protoss_Shuttle 1 6516
Protoss_Robotics_Support_Bay 1 6718
Protoss_Reaver 3 9575
Protoss_Scarab 4 9188
Protoss_Observatory 1 9519
9926
