Protoss_Nexus 2 8940
Special_Protoss_Temple 30 0
Protoss_Gateway 2 3420
Protoss_Assimilator 1 2343
Protoss_Cybernetics_Core 1 2933
Protoss_Dragoon 15 9979
Protoss_Robotics_Facility 1 8175
Protoss_Observatory 1 9539
9979
