Protoss_Nexus 1 0
Protoss_Gateway 2 2990
Protoss_Zealot 11 9800
Protoss_Assimilator 1 4519
Protoss_Cybernetics_Core 1 5986
Protoss_Dragoon 6 9123
Protoss_Robotics_Facility 1 7792
Protoss_Shuttle 1 9271
9800
