Protoss_Nexus 3 9577
Protoss_Gateway 4 7393
Protoss_Assimilator 2 6750
Protoss_Zealot 2 5066
Protoss_Cybernetics_Core 1 4769
Protoss_Dragoon 9 9996
Protoss_Robotics_Facility 1 7943
Protoss_Observatory 1 9746
9996
