Protoss_Nexus 3 9105
Protoss_Gateway 3 9960
Protoss_Assimilator 1 2307
Protoss_Cybernetics_Core 1 3134
Protoss_Dragoon 6 7727
Protoss_Robotics_Facility 1 7218
Protoss_Shuttle 1 8523
Protoss_Observatory 1 8571
Protoss_Robotics_Support_Bay 1 8792
Protoss_Reaver 1 9425
Protoss_Zealot 2 9753
9960
