Protoss_Nexus 3 9084
Protoss_Gateway 3 9899
Protoss_Assimilator 1 2279
Protoss_Cybernetics_Core 1 3012
Protoss_Dragoon 9 9443
Protoss_Robotics_Facility 1 5586
Protoss_Observatory 1 6934
Protoss_Observer 3 9373
9899
