Protoss_Nexus 2 8723
Protoss_Gateway 2 4513
Protoss_Assimilator 1 2340
Protoss_Cybernetics_Core 1 3055
Protoss_Dragoon 6 6581
Protoss_Citadel_of_Adun 1 6065
Protoss_Templar_Archives 1 7093
Protoss_Zealot 2 7511
Protoss_Dark_Templar 4 9511
9511
