Protoss_Nexus 1 0
Protoss_Zealot 23 9891
Protoss_Gateway 2 7553
Protoss_Assimilator 1 2468
Protoss_Cybernetics_Core 1 3123
Protoss_Dragoon 6 8586
Protoss_Robotics_Facility 1 6003
Protoss_Observatory 1 7922
Protoss_Observer 1 8626
9891
