Protoss_Nexus 2 7585
Protoss_Gateway 3 8897
Protoss_Assimilator 2 9122
Protoss_Cybernetics_Core 1 3002
Protoss_Dragoon 7 9891
Protoss_Citadel_of_Adun 1 4278
Protoss_Templar_Archives 1 5303
Protoss_Dark_Templar 4 7298
9891
