Protoss_Nexus 2 7403
Protoss_Gateway 4 9733
Protoss_Assimilator 1 2460
Protoss_Cybernetics_Core 1 3057
Protoss_Dragoon 5 9278
Protoss_Citadel_of_Adun 2 5108
Protoss_Zealot 1 5836
Protoss_Templar_Archives 1 6098
Protoss_Dark_Templar 3 9283
Protoss_Robotics_Facility 1 8991
9733
