Protoss_Nexus 2 7513
Protoss_Gateway 3 9581
Protoss_Assimilator 2 2720
Protoss_Cybernetics_Core 1 3277
Protoss_Zealot 1 4187
Protoss_Dragoon 7 8739
Protoss_Robotics_Facility 1 8213
Protoss_Shuttle 1 9711
Protoss_Robotics_Support_Bay 1 9903
9903
