Protoss_Nexus 2 8508
Protoss_Gateway 3 9929
Protoss_Assimilator 1 2307
Protoss_Cybernetics_Core 1 2955
Protoss_Dragoon 6 9565
Protoss_Robotics_Facility 1 4359
Protoss_Shuttle 2 9861
Protoss_Zealot 2 6891
Protoss_Observatory 1 6226
Protoss_Observer 1 6761
Protoss_Robotics_Support_Bay 1 6861
Protoss_Reaver 1 7493
Protoss_Scarab 2 9496
9929
