Protoss_Nexus 2 9919
Protoss_Gateway 2 7695
Protoss_Assimilator 1 2327
Protoss_Cybernetics_Core 1 2973
Protoss_Dragoon 8 9985
Protoss_Robotics_Facility 1 4391
Protoss_Shuttle 1 5667
Protoss_Robotics_Support_Bay 1 5799
Protoss_Zealot 2 6957
Protoss_Reaver 1 6786
Protoss_Observatory 1 7220
Protoss_Observer 2 8440
Protoss_Scarab 4 8785
9985
