Protoss_Nexus 2 6969
Protoss_Gateway 2 7759
Protoss_Assimilator 3 8584
Protoss_Cybernetics_Core 1 3203
Protoss_Dragoon 5 7917
Protoss_Robotics_Facility 1 7495
Protoss_Citadel_of_Adun 1 8574
Protoss_Stargate 1 9191
Protoss_Observatory 1 9429
Protoss_Observer 1 9961
9961
