Protoss_Nexus 2 8360
Protoss_Gateway 2 5178
Protoss_Zealot 4 5051
Protoss_Assimilator 1 3364
Protoss_Cybernetics_Core 1 4473
Protoss_Dragoon 9 9383
Protoss_Robotics_Facility 1 9568
9568
