Special_Protoss_Temple 14 0
Protoss_Nexus 2 7941
Protoss_Gateway 2 5732
Protoss_Assimilator 4 9870
Protoss_Cybernetics_Core 1 3321
Protoss_Dragoon 8 9765
Protoss_Stargate 1 9339
9870
