Protoss_Nexus 2 3418
Protoss_Gateway 3 8094
Protoss_Assimilator 2 6760
Protoss_Cybernetics_Core 1 4251
Protoss_Forge 1 4854
Protoss_Dragoon 4 9896
Protoss_Photon_Cannon 1 5788
Protoss_Citadel_of_Adun 1 6411
Protoss_Templar_Archives 1 7436
Protoss_Dark_Templar 3 9501
Protoss_Robotics_Facility 1 8812
Protoss_Stargate 1 9130
9896
