Protoss_Nexus 2 6440
Protoss_Gateway 4 8555
Protoss_Assimilator 2 9865
Protoss_Cybernetics_Core 1 3196
Protoss_Dragoon 8 9296
Protoss_Robotics_Facility 1 7329
Protoss_Observatory 1 8766
Protoss_Shuttle 1 8921
Protoss_Robotics_Support_Bay 1 9694
Protoss_Zealot 1 9771
Protoss_Observer 1 9823
9865
