Protoss_Nexus 2 8649
Protoss_Gateway 2 5532
Protoss_Assimilator 1 2307
Protoss_Zealot 2 4047
Protoss_Cybernetics_Core 1 3889
Protoss_Dragoon 12 9929
Protoss_Robotics_Facility 1 8304
Protoss_Observatory 1 9945
9945
