Protoss_Nexus 3 9915
Protoss_Gateway 2 9135
Protoss_Assimilator 1 2465
Protoss_Cybernetics_Core 1 3709
Protoss_Zealot 2 8501
Protoss_Dragoon 4 9861
Protoss_Robotics_Facility 1 5703
Protoss_Shuttle 1 6993
Protoss_Robotics_Support_Bay 1 7347
Protoss_Reaver 1 7895
Protoss_Observatory 1 8808
Protoss_Observer 2 9939
9939
