Protoss_Nexus 2 8619
Protoss_Gateway 2 4922
Protoss_Assimilator 1 2361
Protoss_Cybernetics_Core 1 3001
Protoss_Dragoon 4 9397
Protoss_Citadel_of_Adun 1 4284
Protoss_Templar_Archives 1 5275
Protoss_Zealot 1 5601
Protoss_Dark_Templar 5 7933
Protoss_Robotics_Facility 1 9236
9397
