Protoss_Nexus 3 9984
Protoss_Gateway 4 9065
Protoss_Assimilator 1 2313
Protoss_Cybernetics_Core 1 2842
Protoss_Dragoon 10 9387
Protoss_Robotics_Facility 1 6902
Protoss_Observatory 1 8187
Protoss_Observer 2 9323
9984
