Protoss_Nexus 1 0
Protoss_Gateway 3 7465
Protoss_Assimilator 1 2214
Protoss_Cybernetics_Core 1 3075
Protoss_Zealot 4 9399
Protoss_Dragoon 9 8647
Protoss_Robotics_Facility 1 5890
Protoss_Observatory 1 7347
Protoss_Observer 2 9739
Protoss_Shuttle 1 8837
9739
