Protoss_Nexus 2 6239
Protoss_Gateway 4 8737
Protoss_Assimilator 1 2364
Protoss_Cybernetics_Core 1 2903
Protoss_Dragoon 12 9821
Protoss_Robotics_Facility 1 7528
Protoss_Observatory 1 8908
Protoss_Observer 1 9663
9821
