Protoss_Nexus 2 8122
Protoss_Gateway 2 4775
Protoss_Assimilator 1 2673
Protoss_Cybernetics_Core 1 3273
Protoss_Dragoon 12 9656
Protoss_Citadel_of_Adun 1 6002
Protoss_Templar_Archives 1 7027
Protoss_Robotics_Facility 1 9031
9656
