Protoss_Nexus 3 9727
Protoss_Gateway 2 4821
Protoss_Assimilator 1 2417
Protoss_Zealot 3 4727
Protoss_Cybernetics_Core 1 3841
Protoss_Dragoon 10 9929
Protoss_Robotics_Facility 1 7180
Protoss_Observatory 1 8590
Protoss_Observer 2 9981
9981
