Protoss_Nexus 2 6091
Protoss_Gateway 3 7660
Protoss_Assimilator 2 9112
Protoss_Cybernetics_Core 1 3069
Protoss_Dragoon 11 9773
Protoss_Robotics_Facility 1 7007
Protoss_Observatory 1 8413
Protoss_Observer 2 9721
Protoss_Citadel_of_Adun 1 9083
9773
