Protoss_Nexus 1 0
Protoss_Gateway 3 8750
Protoss_Zealot 15 7980
Protoss_Forge 1 4954
Protoss_Photon_Cannon 2 9314
Protoss_Assimilator 1 7978
Protoss_Cybernetics_Core 1 8209
Protoss_Citadel_of_Adun 1 9223
Protoss_Dragoon 1 9635
9635
