Protoss_Nexus 2 9193
Protoss_Gateway 3 9356
Protoss_Assimilator 1 2422
Protoss_Cybernetics_Core 1 3216
Protoss_Dragoon 10 9590
Protoss_Citadel_of_Adun 1 5794
Protoss_Templar_Archives 1 6836
Protoss_Dark_Templar 2 8086
9590
