Protoss_Nexus 1 0
Protoss_Gateway 2 7435
Protoss_Assimilator 1 2331
Protoss_Zealot 3 4180
Protoss_Cybernetics_Core 1 4663
Protoss_Dragoon 4 9701
Protoss_Robotics_Facility 1 6027
Protoss_Citadel_of_Adun 1 6328
Protoss_Templar_Archives 1 7338
Protoss_Shuttle 1 7446
Protoss_Observatory 1 8261
Protoss_Dark_Templar 3 9208
Protoss_Observer 1 8936
Protoss_Forge 1 9621
9701
