Protoss_Nexus 2 8203
Protoss_Gateway 4 9389
Protoss_Assimilator 1 2387
Protoss_Cybernetics_Core 1 3025
Protoss_Dragoon 6 9913
Protoss_Robotics_Facility 1 5548
Protoss_Shuttle 1 6919
Protoss_Robotics_Support_Bay 1 7071
Protoss_Zealot 1 7331
Protoss_Reaver 1 7821
Protoss_Observatory 1 8379
Protoss_Observer 2 9539
9913
