Protoss_Nexus 1 0
Protoss_Gateway 4 8611
Protoss_Assimilator 1 2581
Protoss_Cybernetics_Core 1 3323
Protoss_Robotics_Facility 1 4401
Protoss_Dragoon 9 8987
Protoss_Observatory 1 5722
Protoss_Observer 1 6321
Protoss_Shuttle 1 7031
8987
