Protoss_Nexus 2 6953
Protoss_Gateway 3 9597
Protoss_Assimilator 2 8997
Protoss_Cybernetics_Core 1 3141
Protoss_Dragoon 6 9817
Protoss_Citadel_of_Adun 1 5403
Protoss_Robotics_Facility 1 6095
Protoss_Templar_Archives 1 6403
Protoss_Dark_Templar 2 7391
Protoss_Shuttle 1 7527
Protoss_Observatory 1 8071
Protoss_Observer 1 9565
9817
