Protoss_Nexus 2 9328
Protoss_Assimilator 17 4732
Protoss_Gateway 2 2253
Protoss_Zealot 11 7949
Protoss_Forge 1 4780
Protoss_Cybernetics_Core 1 5872
Protoss_Photon_Cannon 4 7519
Protoss_Dragoon 4 9587
Protoss_Robotics_Facility 1 9035
9587
