Protoss_Nexus 2 2653
Protoss_Gateway 4 8041
Protoss_Assimilator 2 7186
Protoss_Cybernetics_Core 1 4090
Protoss_Zealot 2 8291
Protoss_Dragoon 9 9465
Protoss_Robotics_Facility 1 6908
Protoss_Observatory 1 8206
Protoss_Shuttle 1 8221
Protoss_Robotics_Support_Bay 1 9082
Protoss_Observer 1 9123
Protoss_Stargate 1 9454
Protoss_Reaver 1 9725
9725
