Protoss_Nexus 2 3360
Protoss_Assimilator 1 3664
Protoss_Gateway 6 9620
Protoss_Cybernetics_Core 2 9141
Protoss_Zealot 3 7351
Protoss_Dragoon 4 7953
Protoss_Citadel_of_Adun 1 6518
Protoss_Templar_Archives 1 7709
Protoss_Shield_Battery 1 8046
Protoss_Dark_Templar 4 9688
9688
