Protoss_Nexus 2 7547
Protoss_Gateway 2 3435
Protoss_Assimilator 2 9596
Protoss_Cybernetics_Core 1 4049
Protoss_Zealot 1 4191
Protoss_Dragoon 6 8191
Protoss_Citadel_of_Adun 1 7926
Protoss_Templar_Archives 1 9009
Protoss_Dark_Templar 2 9997
9997
