Protoss_Assimilator 17 2421
Protoss_Nexus 2 8013
Protoss_Gateway 3 9596
Protoss_Cybernetics_Core 1 2943
Protoss_Dragoon 7 9887
Protoss_Zealot 2 5995
Protoss_Citadel_of_Adun 1 5207
Protoss_Templar_Archives 1 6241
Protoss_Dark_Templar 4 8377
9887
