Protoss_Nexus 2 7092
Protoss_Assimilator 17 3704
Protoss_Gateway 2 2315
Protoss_Zealot 2 3373
Protoss_Cybernetics_Core 1 4181
Protoss_Dragoon 10 9609
Protoss_Robotics_Facility 1 8988
9609
