Protoss_Nexus 2 6635
Protoss_Gateway 3 9987
Protoss_Assimilator 1 2217
Protoss_Cybernetics_Core 1 2831
Protoss_Dragoon 6 8201
Protoss_Robotics_Facility 1 7011
Protoss_Shuttle 1 8611
Protoss_Robotics_Support_Bay 1 9024
Protoss_Zealot 2 9523
Protoss_Reaver 1 9583
9987
