Protoss_Nexus 2 8729
Protoss_Gateway 4 9977
Protoss_Assimilator 1 2219
Protoss_Cybernetics_Core 1 2933
Protoss_Dragoon 5 9931
Protoss_Robotics_Facility 1 5267
Protoss_Shuttle 1 6811
Protoss_Robotics_Support_Bay 1 6890
Protoss_Zealot 2 7713
Protoss_Reaver 1 7863
Protoss_Observatory 1 8939
Protoss_Scarab 4 9835
Protoss_Observer 1 9975
9977
