Protoss_Nexus 3 7659
Protoss_Gateway 3 9845
Protoss_Assimilator 1 2222
Protoss_Cybernetics_Core 1 2857
Protoss_Dragoon 9 9213
Protoss_Robotics_Facility 1 8073
Protoss_Observatory 1 9484
9845
