Protoss_Nexus 1 0
Protoss_Gateway 2 7051
Protoss_Assimilator 1 2445
Protoss_Cybernetics_Core 1 3025
Protoss_Dragoon 10 9767
Protoss_Robotics_Facility 1 5636
Protoss_Observatory 1 6927
Protoss_Observer 3 9379
Protoss_Shuttle 1 8477
Protoss_Robotics_Support_Bay 1 9484
9767
