Protoss_Nexus 2 5338
Protoss_Gateway 3 6273
Protoss_Zealot 4 3976
Protoss_Assimilator 2 8637
Protoss_Cybernetics_Core 1 4851
Protoss_Dragoon 12 9603
Protoss_Shield_Battery 1 8462
9603
