Protoss_Nexus 2 6248
Protoss_Gateway 2 3389
Protoss_Assimilator 2 9065
Protoss_Cybernetics_Core 1 2908
Protoss_Dragoon 6 7453
Protoss_Citadel_of_Adun 1 6529
Protoss_Robotics_Facility 1 7019
Protoss_Templar_Archives 1 7727
Protoss_Shuttle 1 8443
Protoss_Dark_Templar 4 9537
Protoss_Observatory 1 9894
9894
