Protoss_Nexus 2 2807
Protoss_Gateway 2 3852
Protoss_Assimilator 2 7998
Protoss_Cybernetics_Core 1 4389
Protoss_Zealot 1 4719
Protoss_Dragoon 10 9341
Protoss_Robotics_Facility 1 7327
Protoss_Observatory 1 8763
Protoss_Observer 1 9353
Protoss_Stargate 1 9677
9677
