Protoss_Nexus 2 4164
Protoss_Assimilator 2 4336
Protoss_Gateway 2 5946
Protoss_Zealot 2 4649
Protoss_Cybernetics_Core 1 5132
Protoss_Dragoon 6 8661
Protoss_Shield_Battery 1 7057
Protoss_Robotics_Facility 1 7844
Protoss_Shuttle 1 9155
Protoss_Robotics_Support_Bay 1 9468
9468
