Protoss_Nexus 3 7851
Protoss_Gateway 2 4357
Protoss_Assimilator 2 9322
Protoss_Cybernetics_Core 1 4145
Protoss_Zealot 1 4635
Protoss_Dragoon 10 9085
Protoss_Robotics_Facility 1 7993
Protoss_Shuttle 1 9283
Protoss_Robotics_Support_Bay 1 9507
Protoss_Observatory 1 9965
9965
