Protoss_Nexus 2 8677
Protoss_Gateway 2 6161
Protoss_Assimilator 1 2188
Protoss_Cybernetics_Core 1 2996
Protoss_Dragoon 8 9423
Protoss_Robotics_Facility 1 4908
Protoss_Shuttle 1 6417
Protoss_Observatory 1 6661
Protoss_Robotics_Support_Bay 1 7219
Protoss_Observer 1 7319
Protoss_Reaver 1 7921
9423
