Protoss_Nexus 3 9134
Protoss_Gateway 4 9875
Protoss_Assimilator 2 8804
Protoss_Cybernetics_Core 1 3057
Protoss_Dragoon 6 9705
Protoss_Citadel_of_Adun 1 6355
Protoss_Zealot 2 7477
Protoss_Templar_Archives 1 7601
Protoss_Dark_Templar 2 8953
9875
