Protoss_Nexus 3 8335
Protoss_Gateway 2 4678
Protoss_Assimilator 1 3592
Protoss_Cybernetics_Core 1 4207
Protoss_Dragoon 9 9431
Protoss_Zealot 2 8557
Protoss_Robotics_Facility 1 8923
9431
