Protoss_Nexus 3 9657
Protoss_Assimilator 3 6125
Protoss_Gateway 4 8613
Protoss_Zealot 6 9409
Protoss_Cybernetics_Core 1 5599
Protoss_Dragoon 4 9469
Protoss_Citadel_of_Adun 1 7380
Protoss_Templar_Archives 1 9078
9657
