Protoss_Nexus 2 5247
Protoss_Gateway 2 3295
Protoss_Assimilator 3 7788
Protoss_Zealot 7 6647
Protoss_Cybernetics_Core 1 6237
Protoss_Dragoon 6 9373
Protoss_Robotics_Facility 1 8989
9373
