Protoss_Nexus 2 6534
Protoss_Gateway 3 9516
Protoss_Assimilator 1 2158
Protoss_Cybernetics_Core 1 2814
Protoss_Dragoon 9 9917
Protoss_Robotics_Facility 1 6916
Protoss_Shuttle 1 8205
Protoss_Robotics_Support_Bay 1 8587
Protoss_Reaver 1 9243
Protoss_Observatory 1 9717
9917
