Protoss_Nexus 3 6570
Protoss_Gateway 4 9106
Protoss_Assimilator 1 2231
Protoss_Cybernetics_Core 1 2895
Protoss_Dragoon 8 9731
Protoss_Robotics_Facility 1 6927
Protoss_Observatory 1 8237
Protoss_Observer 1 9085
9731
