Protoss_Nexus 2 7892
Protoss_Gateway 2 6139
Protoss_Assimilator 1 2365
Protoss_Zealot 4 9769
Protoss_Cybernetics_Core 1 3870
Protoss_Dragoon 6 8769
Protoss_Robotics_Facility 1 5011
Protoss_Observatory 1 6364
Protoss_Observer 3 8115
Protoss_Shuttle 1 9137
Protoss_Robotics_Support_Bay 1 9245
9769
