Protoss_Nexus 2 9687
Protoss_Gateway 2 6491
Protoss_Assimilator 1 2388
Protoss_Cybernetics_Core 1 3015
Protoss_Dragoon 9 8939
Protoss_Robotics_Facility 1 5746
Protoss_Shuttle 1 7093
Protoss_Observatory 1 7453
Protoss_Observer 2 9817
Protoss_Robotics_Support_Bay 1 8099
Protoss_Reaver 1 8765
9817
