Protoss_Nexus 2 8575
Protoss_Gateway 4 9238
Protoss_Assimilator 1 2233
Protoss_Cybernetics_Core 1 2853
Protoss_Dragoon 8 7895
Protoss_Robotics_Facility 1 5360
Protoss_Observatory 1 6721
Protoss_Observer 1 7353
Protoss_Citadel_of_Adun 1 8150
Protoss_Templar_Archives 1 9172
Protoss_Shuttle 1 9487
9487
