Protoss_Nexus 2 8075
Protoss_Gateway 2 9130
Protoss_Assimilator 1 2406
Protoss_Cybernetics_Core 1 3058
Protoss_Dragoon 7 9735
Protoss_Robotics_Facility 1 5383
Protoss_Zealot 2 6809
Protoss_Shuttle 1 6665
Protoss_Robotics_Support_Bay 1 6701
Protoss_Reaver 1 7567
Protoss_Observatory 1 8406
Protoss_Observer 1 9673
9735
