Protoss_Nexus 3 8567
Protoss_Gateway 5 9229
Protoss_Assimilator 1 2320
Protoss_Cybernetics_Core 1 2845
Protoss_Dragoon 8 9537
Protoss_Robotics_Facility 1 7150
Protoss_Observatory 1 8470
Protoss_Zealot 3 9549
Protoss_Observer 2 9605
Protoss_Citadel_of_Adun 1 9781
9781
