Protoss_Nexus 3 9699
Protoss_Gateway 2 8013
Protoss_Assimilator 2 8554
Protoss_Cybernetics_Core 1 3303
Protoss_Dragoon 7 9747
Protoss_Citadel_of_Adun 1 6351
Protoss_Templar_Archives 1 7389
Protoss_Stargate 1 8352
Protoss_Dark_Templar 1 8375
9747
