Protoss_Nexus 2 6555
Protoss_Forge 1 2374
Protoss_Photon_Cannon 6 8008
Protoss_Gateway 2 9350
Protoss_Assimilator 2 9230
Protoss_Cybernetics_Core 1 5914
Protoss_Zealot 1 6641
Protoss_Citadel_of_Adun 1 7338
Protoss_Dragoon 2 8156
Protoss_Templar_Archives 1 8633
9350
