Special_Protoss_Temple 30 0
Protoss_Nexus 2 5953
Protoss_Gateway 2 7397
Protoss_Assimilator 1 2251
Protoss_Cybernetics_Core 1 2955
Protoss_Dragoon 5 6975
Protoss_Citadel_of_Adun 1 6541
Protoss_Robotics_Facility 1 7518
Protoss_Templar_Archives 1 7583
Protoss_Zealot 1 7981
Protoss_Dark_Templar 4 9425
Protoss_Shuttle 1 8821
Protoss_High_Templar 2 9555
Protoss_Forge 1 9681
9681
