Protoss_Nexus 2 9193
Protoss_Gateway 2 5520
Protoss_Assimilator 1 2544
Protoss_Cybernetics_Core 1 3163
Protoss_Dragoon 8 8020
Protoss_Robotics_Facility 1 6355
Protoss_Observatory 1 8460
Protoss_Zealot 4 9843
Protoss_Observer 1 9266
Protoss_Shuttle 1 9868
9868
