Protoss_Nexus 2 8608
Protoss_Gateway 2 4124
Protoss_Assimilator 1 2474
Protoss_Cybernetics_Core 1 3188
Protoss_Dragoon 7 7436
Protoss_Robotics_Facility 1 7074
Protoss_Observatory 1 8548
Protoss_Zealot 2 8986
Protoss_Observer 1 9101
Protoss_Shuttle 1 9796
9796
