Protoss_Nexus 1 0
Protoss_Gateway 2 6016
Protoss_Assimilator 1 2392
Protoss_Cybernetics_Core 1 3011
Protoss_Dragoon 11 9833
Protoss_Robotics_Facility 1 5720
Protoss_Shuttle 1 7001
Protoss_Robotics_Support_Bay 1 7593
Protoss_Reaver 2 9421
Protoss_Scarab 1 9473
9833
