Protoss_Assimilator 18 9946
Protoss_Nexus 2 7599
Protoss_Gateway 2 2595
Protoss_Zealot 5 4301
Protoss_Cybernetics_Core 1 4655
Protoss_Dragoon 8 9755
Protoss_Robotics_Facility 1 6781
Protoss_Observatory 1 8104
Protoss_Observer 2 9301
9946
