Protoss_Nexus 2 9976
Protoss_Gateway 2 6592
Protoss_Assimilator 1 2358
Protoss_Cybernetics_Core 1 3018
Protoss_Dragoon 9 8715
Protoss_Robotics_Facility 1 5815
Protoss_Shuttle 1 7099
Protoss_Observatory 1 7517
Protoss_Observer 1 8053
Protoss_Robotics_Support_Bay 1 8513
Protoss_Reaver 1 9045
Protoss_Zealot 1 9519
9976
