Protoss_Nexus 1 0
Protoss_Gateway 3 9455
Protoss_Zealot 4 5039
Protoss_Forge 1 3319
Protoss_Photon_Cannon 3 6486
Protoss_Assimilator 1 5233
Protoss_Cybernetics_Core 1 5769
Protoss_Dragoon 8 9945
Protoss_Citadel_of_Adun 1 9740
9945
