Protoss_Nexus 2 9158
Protoss_Gateway 2 5965
Protoss_Assimilator 1 2435
Protoss_Cybernetics_Core 1 3084
Protoss_Dragoon 12 9817
Protoss_Robotics_Facility 1 5468
Protoss_Shuttle 1 6811
Protoss_Observatory 1 6944
Protoss_Observer 2 9523
Protoss_Forge 1 9532
9817
