Protoss_Nexus 2 8534
Protoss_Gateway 3 9180
Protoss_Assimilator 1 2576
Protoss_Cybernetics_Core 1 3445
Protoss_Dragoon 9 9626
Protoss_Robotics_Facility 1 6641
Protoss_Observatory 1 8094
Protoss_Observer 2 9763
Protoss_Forge 1 9801
9801
