Protoss_Nexus 3 8601
Protoss_Gateway 4 9125
Protoss_Assimilator 2 9385
Protoss_Cybernetics_Core 1 3060
Protoss_Zealot 1 3567
Protoss_Dragoon 6 9729
Protoss_Citadel_of_Adun 2 9263
Protoss_Robotics_Facility 1 6901
Protoss_Observatory 1 8213
Protoss_Observer 2 9401
9729
