Protoss_Nexus 2 7172
Protoss_Gateway 4 9409
Protoss_Assimilator 1 2422
Protoss_Cybernetics_Core 1 3007
Protoss_Dragoon 9 8901
Protoss_Robotics_Facility 1 5612
Protoss_Observatory 1 6966
Protoss_Observer 3 9641
Protoss_Shuttle 1 9809
9809
