Protoss_Nexus 2 9219
Protoss_Gateway 2 9723
Protoss_Assimilator 1 2328
Protoss_Cybernetics_Core 1 3091
Protoss_Dragoon 8 9821
Protoss_Robotics_Facility 1 4514
Protoss_Shuttle 1 5803
Protoss_Robotics_Support_Bay 1 5943
Protoss_Reaver 1 6867
Protoss_Observatory 1 7327
Protoss_Observer 2 8521
9821
