Protoss_Nexus 2 6950
Protoss_Gateway 4 9684
Protoss_Assimilator 1 2324
Protoss_Cybernetics_Core 1 2928
Protoss_Dragoon 5 9515
Protoss_Robotics_Facility 1 5332
Protoss_Observatory 1 6619
Protoss_Observer 2 9709
Protoss_Robotics_Support_Bay 1 7271
Protoss_Shuttle 1 7753
Protoss_Zealot 2 8869
Protoss_Reaver 1 8655
9709
