Protoss_Nexus 2 9121
Protoss_Gateway 2 9635
Protoss_Assimilator 1 2611
Protoss_Zealot 2 7333
Protoss_Cybernetics_Core 1 4025
Protoss_Dragoon 6 9717
Protoss_Robotics_Facility 1 5494
Protoss_Shuttle 1 6805
Protoss_Robotics_Support_Bay 1 6907
Protoss_Reaver 2 9837
Protoss_Observatory 1 8632
Protoss_Observer 1 9167
Protoss_Scarab 1 9640
9837
