Protoss_Nexus 1 0
Protoss_Gateway 1 2056
Protoss_Assimilator 2 2843
Protoss_Cybernetics_Core 1 3553
Protoss_Robotics_Facility 1 4743
Protoss_Dragoon 1 5116
Protoss_Shuttle 1 6046
Protoss_Robotics_Support_Bay 1 6308
Protoss_Reaver 3 9181
Protoss_Zealot 1 7336
Protoss_Scarab 5 9547
Protoss_Citadel_of_Adun 1 9723
9723
