Protoss_Nexus 2 7647
Protoss_Gateway 3 8262
Protoss_Assimilator 1 2230
Protoss_Cybernetics_Core 1 2977
Protoss_Dragoon 8 9407
Protoss_Robotics_Facility 1 5272
Protoss_Observatory 1 6614
Protoss_Observer 3 9159
Protoss_Shuttle 1 8609
9407
