Protoss_Nexus 2 9121
Protoss_Gateway 2 4869
Protoss_Assimilator 1 2225
Protoss_Cybernetics_Core 1 2910
Protoss_Dragoon 8 9515
Protoss_Robotics_Facility 1 4348
Protoss_Observatory 1 6264
Protoss_Observer 2 9845
Protoss_Shuttle 1 7433
Protoss_Robotics_Support_Bay 1 8099
Protoss_Zealot 2 8469
Protoss_Reaver 1 8793
Protoss_Citadel_of_Adun 1 9746
9845
