Protoss_Nexus 3 9912
Protoss_Gateway 2 6900
Protoss_Assimilator 1 2334
Protoss_Zealot 2 4021
Protoss_Cybernetics_Core 1 3853
Protoss_Dragoon 5 8129
Protoss_Citadel_of_Adun 1 6229
Protoss_Robotics_Facility 1 7304
Protoss_Templar_Archives 1 7674
Protoss_Dark_Templar 2 8881
Protoss_Shuttle 1 8985
Protoss_Observatory 1 9052
Protoss_Observer 1 9887
9912
