Special_Protoss_Temple 30 0
Protoss_Nexus 2 6809
Protoss_Gateway 2 8066
Protoss_Assimilator 1 2340
Protoss_Cybernetics_Core 1 2993
Protoss_Dragoon 7 9619
Protoss_Robotics_Facility 1 5497
Protoss_Observatory 1 7028
Protoss_Observer 1 7579
Protoss_Robotics_Support_Bay 1 8197
Protoss_Shuttle 1 8649
Protoss_Reaver 1 9551
9619
