Protoss_Nexus 3 9529
Protoss_Gateway 3 8233
Protoss_Assimilator 2 7343
Protoss_Cybernetics_Core 1 3928
Protoss_Zealot 3 8283
Protoss_Dragoon 8 8885
Protoss_Robotics_Facility 2 7556
Protoss_Shuttle 1 8983
Protoss_Robotics_Support_Bay 1 9066
Protoss_Reaver 1 9885
9885
