Protoss_Nexus 2 7895
Protoss_Gateway 2 6010
Protoss_Assimilator 1 2465
Protoss_Cybernetics_Core 1 3141
Protoss_Dragoon 10 9611
Protoss_Robotics_Facility 1 5679
Protoss_Observatory 1 7010
Protoss_Observer 2 8281
Protoss_Shuttle 1 9007
Protoss_Robotics_Support_Bay 1 9095
Protoss_Reaver 1 9913
9913
