Protoss_Nexus 2 2802
Protoss_Gateway 2 4278
Protoss_Assimilator 1 3329
Protoss_Cybernetics_Core 1 4134
Protoss_Zealot 4 9843
Protoss_Dragoon 9 9651
Protoss_Robotics_Facility 1 6557
Protoss_Shuttle 1 7839
Protoss_Robotics_Support_Bay 1 8095
Protoss_Reaver 1 8791
Protoss_Observatory 1 9128
9843
