Protoss_Nexus 2 5689
Protoss_Gateway 3 9288
Protoss_Assimilator 2 8169
Protoss_Cybernetics_Core 1 3234
Protoss_Dragoon 6 9657
Protoss_Robotics_Facility 1 6385
Protoss_Shuttle 1 7749
Protoss_Observatory 1 7967
Protoss_Robotics_Support_Bay 1 8049
Protoss_Zealot 2 9009
Protoss_Reaver 1 8999
9657
