Protoss_Nexus 2 8116
Protoss_Gateway 2 6654
Protoss_Assimilator 1 2227
Protoss_Zealot 2 3995
Protoss_Cybernetics_Core 1 3683
Protoss_Dragoon 6 8589
Protoss_Robotics_Facility 1 5869
Protoss_Observatory 1 7181
Protoss_Observer 2 8313
Protoss_Shuttle 1 8915
Protoss_Robotics_Support_Bay 1 9239
Protoss_Reaver 1 9817
9817
