Protoss_Nexus 2 6649
Protoss_Gateway 2 3388
Protoss_Assimilator 1 2328
Protoss_Cybernetics_Core 1 2953
Protoss_Dragoon 8 9761
Protoss_Robotics_Facility 1 7023
Protoss_Shuttle 1 8681
Protoss_Observatory 1 9122
Protoss_Observer 1 9666
9761
