Special_Protoss_Temple 30 0
Protoss_Nexus 3 7819
Protoss_Gateway 4 9141
Protoss_Assimilator 1 2486
Protoss_Cybernetics_Core 1 3088
Protoss_Dragoon 10 9413
Protoss_Robotics_Facility 1 8202
Protoss_Observatory 1 9622
9622
