Protoss_Nexus 2 8755
Protoss_Gateway 3 7205
Protoss_Zealot 2 4597
Protoss_Assimilator 1 3587
Protoss_Cybernetics_Core 1 4546
Protoss_Dragoon 7 9159
Protoss_Robotics_Facility 1 6899
Protoss_Observatory 1 8187
Protoss_Observer 2 9369
Protoss_Shuttle 1 9541
Protoss_Robotics_Support_Bay 1 9765
9765
