Protoss_Nexus 2 8013
Protoss_Gateway 3 8995
Protoss_Assimilator 1 2250
Protoss_Cybernetics_Core 1 2947
Protoss_Dragoon 11 9609
Protoss_Robotics_Facility 1 5301
Protoss_Observatory 1 6737
Protoss_Observer 1 7741
9609
