Protoss_Nexus 1 0
Protoss_Gateway 2 5543
Protoss_Assimilator 1 2543
Protoss_Cybernetics_Core 1 3018
Protoss_Robotics_Facility 1 4352
Protoss_Dragoon 10 9946
Protoss_Observatory 1 5713
Protoss_Shuttle 1 5856
Protoss_Observer 2 7360
9946
