Protoss_Nexus 1 0
Protoss_Gateway 3 8516
Protoss_Assimilator 1 2367
Protoss_Cybernetics_Core 1 3078
Protoss_Dragoon 9 9526
Protoss_Robotics_Facility 1 5939
Protoss_Observatory 1 7280
Protoss_Observer 1 7846
Protoss_Shuttle 1 8536
Protoss_Zealot 2 8831
9526
