Protoss_Nexus 1 0
Protoss_Gateway 3 6333
Protoss_Assimilator 1 2569
Protoss_Zealot 10 8627
Protoss_Cybernetics_Core 1 4019
Protoss_Dragoon 2 8767
Protoss_Citadel_of_Adun 1 5276
Protoss_Templar_Archives 1 8362
Protoss_Dark_Templar 3 9519
9519
