Special_Protoss_Temple 30 0
Protoss_Nexus 3 9823
Protoss_Gateway 2 3385
Protoss_Assimilator 1 2296
Protoss_Cybernetics_Core 1 2830
Protoss_Dragoon 11 8993
Protoss_Robotics_Facility 1 7280
Protoss_Observatory 1 8593
Protoss_Observer 1 9719
9823
