Protoss_Nexus 3 7712
Protoss_Gateway 2 4125
Protoss_Assimilator 1 2779
Protoss_Cybernetics_Core 1 3289
Protoss_Dragoon 7 8843
Protoss_Forge 2 8264
Protoss_Robotics_Facility 1 9633
9633
