Special_Protoss_Temple 14 0
Protoss_Nexus 2 6823
Protoss_Gateway 2 4703
Protoss_Assimilator 1 2423
Protoss_Cybernetics_Core 1 2992
Protoss_Dragoon 12 9705
Protoss_Robotics_Facility 1 7032
Protoss_Shuttle 1 8445
Protoss_Robotics_Support_Bay 1 8620
Protoss_Reaver 1 9347
9705
