Protoss_Nexus 2 8538
Protoss_Gateway 2 5905
Protoss_Assimilator 1 2478
Protoss_Cybernetics_Core 1 3137
Protoss_Dragoon 10 9686
Protoss_Robotics_Facility 1 4643
Protoss_Observatory 1 6010
Protoss_Observer 2 7516
9686
