Protoss_Nexus 2 6732
Protoss_Gateway 2 9634
Protoss_Zealot 5 8017
Protoss_Assimilator 2 9292
Protoss_Forge 1 6782
Protoss_Cybernetics_Core 1 7381
Protoss_Photon_Cannon 2 8272
Protoss_Citadel_of_Adun 1 8644
Protoss_Robotics_Facility 1 9197
Protoss_Templar_Archives 1 9777
9777
