Protoss_Nexus 2 7930
Protoss_Gateway 2 6735
Protoss_Assimilator 1 2533
Protoss_Cybernetics_Core 1 3138
Protoss_Robotics_Facility 1 4358
Protoss_Dragoon 6 9661
Protoss_Observatory 1 5719
Protoss_Observer 2 7281
Protoss_Shuttle 1 8246
Protoss_Zealot 1 9981
9981
