Protoss_Nexus 3 8824
Protoss_Gateway 2 5844
Protoss_Assimilator 1 2265
Protoss_Cybernetics_Core 1 2952
Protoss_Dragoon 8 9497
Protoss_Robotics_Facility 1 5317
Protoss_Observatory 1 6709
Protoss_Observer 2 8113
Protoss_Shuttle 1 8715
Protoss_Robotics_Support_Bay 1 9041
Protoss_Reaver 1 9617
Protoss_Zealot 2 9873
9873
