Protoss_Nexus 2 7585
Protoss_Gateway 3 9427
Protoss_Assimilator 1 2213
Protoss_Cybernetics_Core 1 2926
Protoss_Dragoon 6 7865
Protoss_Robotics_Facility 1 5492
Protoss_Shuttle 1 6897
Protoss_Robotics_Support_Bay 1 7004
Protoss_Reaver 1 8571
Protoss_Zealot 2 9219
9427
