Protoss_Nexus 2 5605
Protoss_Gateway 2 4667
Protoss_Assimilator 2 7800
Protoss_Cybernetics_Core 1 3277
Protoss_Dragoon 5 9009
Protoss_Robotics_Facility 1 6118
Protoss_Stargate 2 9916
Protoss_Observatory 1 7634
Protoss_Fleet_Beacon 1 8053
Protoss_Zealot 4 9951
Protoss_Observer 1 9021
Protoss_Carrier 1 9415
9951
