Protoss_Nexus 2 7401
Protoss_Gateway 4 8951
Protoss_Zealot 1 2725
Protoss_Assimilator 1 3706
Protoss_Cybernetics_Core 1 4655
Protoss_Dragoon 10 9515
Protoss_Robotics_Facility 1 8706
9515
