Protoss_Nexus 2 9143
Protoss_Gateway 3 7253
Protoss_Assimilator 1 2173
Protoss_Cybernetics_Core 1 2895
Protoss_Robotics_Facility 1 3963
Protoss_Shuttle 1 5251
Protoss_Dragoon 10 9946
Protoss_Observatory 1 7515
Protoss_Observer 2 8658
9946
