Special_Protoss_Temple 30 0
Protoss_Nexus 3 7437
Protoss_Gateway 5 9635
Protoss_Assimilator 1 2316
Protoss_Cybernetics_Core 1 2802
Protoss_Dragoon 6 5881
Protoss_Citadel_of_Adun 1 7901
Protoss_Templar_Archives 1 8972
9635
