Protoss_Nexus 2 9596
Protoss_Gateway 2 5327
Protoss_Assimilator 1 2415
Protoss_Cybernetics_Core 1 3039
Protoss_Dragoon 11 8911
Protoss_Robotics_Facility 1 6768
Protoss_Observatory 1 8098
Protoss_Observer 2 9593
9596
