Protoss_Nexus 2 8899
Protoss_Gateway 2 6050
Protoss_Assimilator 1 2349
Protoss_Cybernetics_Core 1 2826
Protoss_Dragoon 3 5677
Protoss_Robotics_Facility 1 5445
Protoss_Citadel_of_Adun 1 5560
Protoss_Templar_Archives 1 6571
Protoss_Shuttle 1 6751
Protoss_Robotics_Support_Bay 1 6840
Protoss_Dark_Templar 4 9017
Protoss_Reaver 2 9075
9075
