Protoss_Nexus 2 5216
Protoss_Gateway 3 8393
Protoss_Assimilator 2 9009
Protoss_Cybernetics_Core 1 2888
Protoss_Dragoon 9 9717
Protoss_Robotics_Facility 1 6050
Protoss_Observatory 1 7551
Protoss_Shuttle 1 7805
Protoss_Observer 1 8707
Protoss_Robotics_Support_Bay 1 8866
Protoss_Reaver 1 9393
Protoss_Zealot 2 9967
9967
