Protoss_Nexus 3 9395
Protoss_Assimilator 3 4114
Protoss_Gateway 2 7868
Protoss_Cybernetics_Core 1 3367
Protoss_Dragoon 10 9923
Protoss_Robotics_Facility 1 7163
Protoss_Observatory 1 8482
Protoss_Observer 2 9671
9923
