Protoss_Nexus 2 2599
Protoss_Gateway 2 4143
Protoss_Assimilator 2 7899
Protoss_Cybernetics_Core 1 4023
Protoss_Zealot 2 8493
Protoss_Dragoon 9 9375
Protoss_Robotics_Facility 1 6649
Protoss_Shuttle 1 7945
Protoss_Robotics_Support_Bay 1 8170
Protoss_Reaver 1 8975
9375
