Protoss_Nexus 2 3237
Protoss_Gateway 4 9220
Protoss_Assimilator 2 6499
Protoss_Cybernetics_Core 1 4351
Protoss_Zealot 3 9393
Protoss_Dragoon 8 8639
Protoss_Robotics_Facility 1 7397
Protoss_Observatory 1 8743
Protoss_Stargate 2 9632
Protoss_Observer 1 9281
Protoss_Fleet_Beacon 1 9963
Protoss_Shuttle 1 9985
9985
