Protoss_Nexus 2 2677
Protoss_Gateway 2 4366
Protoss_Assimilator 2 6824
Protoss_Cybernetics_Core 1 4099
Protoss_Dragoon 11 9311
Protoss_Robotics_Facility 1 6851
Protoss_Shuttle 1 8171
Protoss_Observatory 2 9466
Protoss_Robotics_Support_Bay 1 8329
Protoss_Reaver 1 9073
9466
