Protoss_Nexus 2 6421
Protoss_Gateway 2 7163
Protoss_Assimilator 2 8831
Protoss_Zealot 2 3701
Protoss_Cybernetics_Core 1 3634
Protoss_Dragoon 8 9183
Protoss_Robotics_Facility 1 6787
Protoss_Shuttle 1 8097
Protoss_Observatory 1 8147
Protoss_Robotics_Support_Bay 1 8688
Protoss_Observer 1 8999
Protoss_Reaver 1 9967
9967
