Protoss_Nexus 2 8112
Protoss_Gateway 4 9679
Protoss_Assimilator 2 9438
Protoss_Cybernetics_Core 1 2984
Protoss_Dragoon 3 5489
Protoss_Citadel_of_Adun 1 5341
Protoss_Robotics_Facility 1 5407
Protoss_Templar_Archives 1 6394
Protoss_Shuttle 1 6705
Protoss_Dark_Templar 6 9305
9679
