Protoss_Nexus 1 0
Protoss_Gateway 3 5987
Protoss_Assimilator 1 2329
Protoss_Cybernetics_Core 1 2829
Protoss_Zealot 4 9949
Protoss_Dragoon 3 5291
Protoss_Citadel_of_Adun 1 4674
Protoss_Templar_Archives 1 5665
Protoss_Dark_Templar 10 9935
9949
