Protoss_Nexus 2 8578
Protoss_Gateway 3 9217
Protoss_Assimilator 1 2429
Protoss_Cybernetics_Core 1 3156
Protoss_Dragoon 8 9121
Protoss_Robotics_Facility 1 5976
Protoss_Observatory 1 7458
Protoss_Observer 1 9736
Protoss_Citadel_of_Adun 1 9771
9771
