Protoss_Nexus 2 9680
Protoss_Gateway 3 7038
Protoss_Assimilator 1 2373
Protoss_Cybernetics_Core 1 3148
Protoss_Dragoon 12 9577
Protoss_Robotics_Facility 1 4311
Protoss_Shuttle 1 5596
Protoss_Observatory 1 5773
Protoss_Observer 3 8466
9680
