Protoss_Nexus 2 6887
Protoss_Gateway 3 8243
Protoss_Assimilator 1 2287
Protoss_Zealot 2 8583
Protoss_Cybernetics_Core 1 3135
Protoss_Robotics_Facility 1 4183
Protoss_Dragoon 9 9937
Protoss_Observatory 1 5669
Protoss_Observer 2 7269
9937
