Protoss_Nexus 2 2577
Protoss_Gateway 4 9085
Protoss_Assimilator 2 6428
Protoss_Cybernetics_Core 1 4107
Protoss_Dragoon 13 9563
Protoss_Robotics_Facility 1 7087
Protoss_Observatory 1 8598
Protoss_Observer 2 9809
Protoss_Citadel_of_Adun 1 9990
9990
