Protoss_Nexus 3 7738
Protoss_Gateway 2 4585
Protoss_Assimilator 1 2362
Protoss_Cybernetics_Core 1 2989
Protoss_Dragoon 10 9365
Protoss_Robotics_Facility 1 8113
Protoss_Shuttle 1 9481
Protoss_Robotics_Support_Bay 1 9638
Protoss_Observatory 1 9682
9682
