Special_Protoss_Temple 14 0
Protoss_Nexus 2 6003
Protoss_Gateway 2 8787
Protoss_Assimilator 2 9087
Protoss_Cybernetics_Core 1 3165
Protoss_Dragoon 8 9435
Protoss_Robotics_Facility 1 7171
Protoss_Observatory 1 8471
Protoss_Robotics_Support_Bay 1 8865
Protoss_Citadel_of_Adun 1 8927
Protoss_Observer 1 9003
Protoss_Shuttle 1 9633
9633
