Protoss_Nexus 2 8181
Protoss_Gateway 2 5881
Protoss_Assimilator 1 2365
Protoss_Cybernetics_Core 1 3213
Protoss_Dragoon 12 9617
Protoss_Forge 1 7381
Protoss_Photon_Cannon 2 9506
9617
