Protoss_Nexus 3 9405
Protoss_Gateway 2 4917
Protoss_Assimilator 2 8171
Protoss_Cybernetics_Core 1 4091
Protoss_Zealot 2 6835
Protoss_Dragoon 8 8433
Protoss_Robotics_Facility 1 6477
Protoss_Observatory 1 7804
Protoss_Observer 2 9043
9405
