Protoss_Nexus 2 6768
Protoss_Gateway 5 9943
Protoss_Assimilator 1 2734
Protoss_Cybernetics_Core 1 3113
Protoss_Dragoon 8 9723
Protoss_Citadel_of_Adun 1 6101
Protoss_Robotics_Facility 1 7571
Protoss_Observatory 1 8941
Protoss_Observer 1 9491
9943
