Protoss_Nexus 2 6544
Protoss_Gateway 3 7918
Protoss_Assimilator 1 2518
Protoss_Cybernetics_Core 1 3398
Protoss_Dragoon 9 9886
Protoss_Robotics_Facility 1 5463
Protoss_Robotics_Support_Bay 1 6814
Protoss_Observatory 1 6998
Protoss_Observer 2 8348
Protoss_Shuttle 1 8950
Protoss_Citadel_of_Adun 1 9723
9886
