Protoss_Nexus 3 9815
Protoss_Gateway 2 6279
Protoss_Assimilator 1 2154
Protoss_Cybernetics_Core 1 2759
Protoss_Dragoon 7 9977
Protoss_Robotics_Facility 1 5514
Protoss_Shuttle 1 6823
Protoss_Robotics_Support_Bay 1 7318
Protoss_Reaver 1 7917
Protoss_Observatory 1 8186
Protoss_Zealot 2 8247
Protoss_Observer 2 9571
9977
