Protoss_Nexus 3 9657
Protoss_Gateway 3 7876
Protoss_Assimilator 1 2309
Protoss_Cybernetics_Core 1 2862
Protoss_Dragoon 11 9887
Protoss_Zealot 1 4595
Protoss_Robotics_Facility 1 5120
Protoss_Observatory 1 6507
Protoss_Observer 5 9861
9887
