Protoss_Nexus 2 8383
Protoss_Gateway 3 9992
Protoss_Assimilator 1 2481
Protoss_Cybernetics_Core 1 3263
Protoss_Zealot 1 3587
Protoss_Dragoon 9 9341
Protoss_Robotics_Facility 1 8481
Protoss_Citadel_of_Adun 1 8742
Protoss_Templar_Archives 1 9757
Protoss_Observatory 1 9819
9992
