Protoss_Nexus 2 8339
Special_Protoss_Temple 14 0
Protoss_Gateway 2 2551
Protoss_Zealot 2 3617
Protoss_Assimilator 1 3794
Protoss_Cybernetics_Core 1 4564
Protoss_Dragoon 8 9285
Protoss_Robotics_Facility 1 8215
Protoss_Robotics_Support_Bay 1 9616
Protoss_Shuttle 1 9871
9871
