Protoss_Nexus 2 9759
Protoss_Gateway 1 1867
Protoss_Assimilator 1 2355
Protoss_Zealot 1 2879
Protoss_Cybernetics_Core 1 3241
Protoss_Robotics_Facility 1 4287
Protoss_Dragoon 6 9241
Protoss_Shuttle 1 5571
Protoss_Robotics_Support_Bay 1 6037
Protoss_Reaver 2 9295
Protoss_Observatory 1 7244
Protoss_Observer 2 8655
Protoss_Scarab 3 9108
9759
