Protoss_Nexus 2 6952
Special_Protoss_Temple 14 0
Protoss_Assimilator 3 9365
Protoss_Gateway 3 9980
Protoss_Cybernetics_Core 1 3722
Protoss_Dragoon 6 8129
Protoss_Robotics_Facility 1 7567
Protoss_Citadel_of_Adun 1 8739
Protoss_Observatory 1 9111
Protoss_Stargate 1 9183
Protoss_Observer 1 9655
Protoss_Templar_Archives 1 9861
9980
