Protoss_Nexus 2 6069
Protoss_Gateway 2 7263
Protoss_Assimilator 2 9341
Protoss_Cybernetics_Core 1 3255
Protoss_Zealot 2 9443
Protoss_Dragoon 7 9429
Protoss_Robotics_Facility 1 6783
Protoss_Shuttle 1 8109
Protoss_Observatory 1 8190
Protoss_Robotics_Support_Bay 1 8939
Protoss_Observer 1 9011
Protoss_Reaver 1 9719
9719
