Protoss_Nexus 2 9605
Protoss_Gateway 2 4879
Protoss_Assimilator 1 2401
Protoss_Zealot 3 4259
Protoss_Cybernetics_Core 1 4025
Protoss_Dragoon 3 6369
Protoss_Robotics_Facility 1 5911
Protoss_Citadel_of_Adun 1 6659
Protoss_Templar_Archives 1 7669
Protoss_Shuttle 1 7689
Protoss_Dark_Templar 4 9411
9605
