Special_Protoss_Temple 14 0
Protoss_Nexus 3 9713
Protoss_Gateway 3 7865
Protoss_Assimilator 1 2383
Protoss_Cybernetics_Core 1 2967
Protoss_Zealot 1 3289
Protoss_Dragoon 7 9245
Protoss_Robotics_Facility 1 7048
Protoss_Observatory 1 8426
Protoss_Observer 2 9597
9713
