Protoss_Nexus 2 5477
Protoss_Gateway 3 9731
Protoss_Zealot 4 8517
Protoss_Assimilator 1 3122
Protoss_Cybernetics_Core 1 3577
Protoss_Dragoon 6 9365
Protoss_Robotics_Facility 1 6177
Protoss_Shuttle 1 7493
Protoss_Robotics_Support_Bay 1 7775
Protoss_Reaver 1 8395
Protoss_Observatory 1 8756
Protoss_Observer 1 9447
9731
