Protoss_Nexus 2 8979
Protoss_Gateway 2 7589
Protoss_Assimilator 1 2385
Protoss_Cybernetics_Core 1 3035
Protoss_Dragoon 8 9253
Protoss_Robotics_Facility 1 4450
Protoss_Observatory 1 5989
Protoss_Shuttle 1 6289
Protoss_Observer 3 8395
Protoss_Robotics_Support_Bay 1 8607
9253
