Special_Protoss_Temple 14 0
Protoss_Nexus 2 6192
Protoss_Gateway 2 7948
Protoss_Assimilator 1 2421
Protoss_Cybernetics_Core 1 3031
Protoss_Zealot 3 9079
Protoss_Dragoon 8 9941
Protoss_Robotics_Facility 1 7002
Protoss_Shuttle 1 8395
Protoss_Robotics_Support_Bay 1 8772
Protoss_Reaver 1 9421
9941
