Protoss_Nexus 2 8921
Protoss_Gateway 2 5369
Protoss_Assimilator 1 2371
Protoss_Cybernetics_Core 1 3025
Protoss_Zealot 4 9547
Protoss_Dragoon 8 9089
Protoss_Robotics_Facility 1 6225
Protoss_Observatory 1 7706
Protoss_Observer 1 8405
Protoss_Shuttle 1 9585
9585
