Protoss_Nexus 2 8162
Protoss_Gateway 2 6631
Protoss_Assimilator 1 2471
Protoss_Cybernetics_Core 1 3025
Protoss_Dragoon 10 9515
Protoss_Robotics_Facility 1 6039
Protoss_Observatory 1 7410
Protoss_Observer 2 9607
9607
