Protoss_Nexus 2 7513
Protoss_Gateway 4 9157
Protoss_Assimilator 1 2258
Protoss_Cybernetics_Core 1 2931
Protoss_Dragoon 12 9346
Protoss_Robotics_Facility 1 8353
Protoss_Observatory 1 9684
Protoss_Citadel_of_Adun 1 9976
9976
