Protoss_Nexus 3 9447
Protoss_Gateway 2 5278
Protoss_Assimilator 1 2491
Protoss_Cybernetics_Core 1 3128
Protoss_Dragoon 7 9953
Protoss_Robotics_Facility 1 5962
Protoss_Zealot 4 8141
Protoss_Shuttle 1 7379
Protoss_Observatory 1 7703
Protoss_Observer 2 9147
9953
