Special_Protoss_Temple 14 0
Protoss_Nexus 2 7405
Protoss_Gateway 2 7907
Protoss_Assimilator 1 2533
Protoss_Cybernetics_Core 1 3132
Protoss_Zealot 1 3301
Protoss_Dragoon 6 9511
Protoss_Robotics_Facility 1 5727
Protoss_Observatory 1 7114
Protoss_Observer 2 8591
Protoss_Shuttle 1 8821
Protoss_Robotics_Support_Bay 1 9468
9511
