Protoss_Nexus 2 8872
Protoss_Gateway 1 1882
Protoss_Assimilator 1 2188
Protoss_Cybernetics_Core 1 2871
Protoss_Zealot 2 7303
Protoss_Dragoon 6 9357
Protoss_Robotics_Facility 1 5265
Protoss_Shuttle 1 6565
Protoss_Robotics_Support_Bay 1 6881
Protoss_Reaver 1 7623
Protoss_Observatory 1 8429
Protoss_Scarab 5 9969
Protoss_Observer 1 9465
9969
