Protoss_Nexus 3 8995
Protoss_Gateway 5 9955
Protoss_Assimilator 1 2301
Protoss_Cybernetics_Core 1 3039
Protoss_Dragoon 8 9391
Protoss_Robotics_Facility 1 4413
Protoss_Observatory 1 5762
Protoss_Observer 2 7011
9955
