Protoss_Nexus 1 0
Protoss_Gateway 3 8224
Protoss_Assimilator 1 2436
Protoss_Cybernetics_Core 1 3338
Protoss_Dragoon 9 9587
Protoss_Robotics_Facility 1 4433
Protoss_Shuttle 1 5846
Protoss_Observatory 1 5970
Protoss_Observer 4 9913
9913
