Protoss_Nexus 2 9303
Protoss_Gateway 2 5208
Protoss_Assimilator 1 2448
Protoss_Cybernetics_Core 1 3023
Protoss_Dragoon 6 7626
Protoss_Citadel_of_Adun 1 6153
Protoss_Templar_Archives 1 7288
Protoss_Dark_Templar 2 8531
Protoss_Robotics_Facility 1 9977
9977
