Protoss_Nexus 3 7966
Protoss_Gateway 4 8652
Protoss_Assimilator 2 8685
Protoss_Cybernetics_Core 1 4175
Protoss_Zealot 1 4641
Protoss_Dragoon 8 8889
Protoss_Robotics_Facility 1 7077
Protoss_Observatory 1 8560
Protoss_Observer 2 9811
9811
