Protoss_Nexus 2 9907
Protoss_Gateway 2 8160
Protoss_Assimilator 1 2477
Protoss_Cybernetics_Core 1 3134
Protoss_Dragoon 6 9649
Protoss_Stargate 1 5499
Protoss_Fleet_Beacon 1 6795
Protoss_Carrier 1 7925
Protoss_Robotics_Facility 1 8647
9907
