Special_Protoss_Temple 14 0
Protoss_Nexus 2 6415
Protoss_Gateway 2 5171
Protoss_Assimilator 1 2559
Protoss_Cybernetics_Core 1 3267
Protoss_Zealot 1 3477
Protoss_Dragoon 11 9943
Protoss_Robotics_Facility 1 7663
Protoss_Shuttle 1 9729
Protoss_Robotics_Support_Bay 1 9831
9943
