Protoss_Nexus 2 7169
Protoss_Gateway 5 8490
Protoss_Assimilator 2 9171
Protoss_Cybernetics_Core 1 3123
Protoss_Dragoon 8 9675
Protoss_Robotics_Facility 1 5598
Protoss_Observatory 1 6933
Protoss_Observer 5 9999
9999
