Protoss_Nexus 2 6894
Protoss_Gateway 4 9741
Protoss_Assimilator 2 8582
Protoss_Cybernetics_Core 1 2976
Protoss_Dragoon 9 9123
Protoss_Robotics_Facility 1 5564
Protoss_Observatory 1 6960
Protoss_Observer 3 8907
Protoss_Citadel_of_Adun 1 8156
Protoss_Templar_Archives 1 9471
Protoss_Stargate 1 9576
9741
