Special_Protoss_Temple 14 0
Protoss_Nexus 2 9160
Protoss_Gateway 2 5524
Protoss_Assimilator 2 3917
Protoss_Zealot 4 5623
Protoss_Cybernetics_Core 1 4787
Protoss_Dragoon 10 9837
9837
