Protoss_Nexus 2 6235
Protoss_Gateway 3 9688
Protoss_Assimilator 1 2327
Protoss_Cybernetics_Core 1 2987
Protoss_Zealot 3 9355
Protoss_Dragoon 8 9957
Protoss_Robotics_Facility 1 6512
Protoss_Shuttle 1 7805
Protoss_Robotics_Support_Bay 1 8322
Protoss_Reaver 1 8921
Protoss_Observatory 1 9497
9957
