Protoss_Nexus 2 7587
Protoss_Gateway 4 9791
Protoss_Assimilator 1 2343
Protoss_Zealot 5 9451
Protoss_Cybernetics_Core 1 3078
Protoss_Citadel_of_Adun 1 4069
Protoss_Dragoon 1 4173
Protoss_Templar_Archives 1 5174
Protoss_Dark_Templar 7 8491
9791
