Protoss_Nexus 2 5659
Protoss_Gateway 2 6483
Protoss_Assimilator 2 9689
Protoss_Cybernetics_Core 1 2835
Protoss_Dragoon 9 9885
Protoss_Robotics_Facility 1 6089
Protoss_Shuttle 1 7547
Protoss_Robotics_Support_Bay 1 7825
Protoss_Observatory 1 8780
Protoss_Reaver 1 9229
9885
