Protoss_Nexus 2 5979
Protoss_Gateway 3 8425
Protoss_Assimilator 2 8599
Protoss_Cybernetics_Core 1 3004
Protoss_Dragoon 7 9575
Protoss_Robotics_Facility 1 6962
Protoss_Citadel_of_Adun 1 8057
Protoss_Observatory 1 8263
Protoss_Observer 1 8933
Protoss_Templar_Archives 1 9053
Protoss_Stargate 1 9259
Protoss_Zealot 2 9561
9575
