Special_Protoss_Temple 14 0
Protoss_Nexus 2 4281
Protoss_Assimilator 3 7983
Protoss_Gateway 3 9941
Protoss_Zealot 3 5595
Protoss_Cybernetics_Core 1 5357
Protoss_Dragoon 9 9587
Protoss_Robotics_Facility 1 8258
Protoss_Shuttle 1 9565
Protoss_Robotics_Support_Bay 1 9779
9941
