Protoss_Nexus 2 6175
Protoss_Gateway 2 7313
Protoss_Assimilator 1 2295
Protoss_Cybernetics_Core 1 2897
Protoss_Zealot 3 9337
Protoss_Dragoon 10 9989
Protoss_Robotics_Facility 1 6837
Protoss_Shuttle 1 8173
Protoss_Robotics_Support_Bay 1 8635
Protoss_Reaver 1 9389
Protoss_Observatory 1 9482
9989
