Protoss_Nexus 1 0
Protoss_Gateway 2 5375
Protoss_Assimilator 1 2550
Protoss_Cybernetics_Core 1 3154
Protoss_Dragoon 8 8060
Protoss_Robotics_Facility 1 6229
Protoss_Observatory 1 7644
Protoss_Observer 1 8191
Protoss_Zealot 3 9586
Protoss_Shuttle 1 9001
9586
