Protoss_Nexus 1 0
Protoss_Gateway 3 8379
Protoss_Assimilator 1 2382
Protoss_Cybernetics_Core 1 3176
Protoss_Dragoon 8 9651
Protoss_Robotics_Facility 1 6937
Protoss_Observatory 1 8251
Protoss_Zealot 4 9271
Protoss_Shuttle 1 9106
Protoss_Observer 1 9151
9651
