Protoss_Nexus 2 6330
Protoss_Gateway 3 7311
Protoss_Assimilator 1 2243
Protoss_Cybernetics_Core 1 3018
Protoss_Robotics_Facility 1 4027
Protoss_Dragoon 9 9161
Protoss_Observatory 1 5629
Protoss_Observer 3 8253
9161
