Protoss_Nexus 2 2627
Protoss_Gateway 4 8777
Protoss_Assimilator 2 7560
Protoss_Zealot 5 9331
Protoss_Cybernetics_Core 1 4307
Protoss_Dragoon 7 8579
Protoss_Robotics_Facility 1 6660
Protoss_Observatory 1 8127
Protoss_Observer 3 9859
9859
