Special_Protoss_Temple 14 0
Protoss_Nexus 2 6011
Protoss_Gateway 4 9193
Protoss_Assimilator 1 2233
Protoss_Cybernetics_Core 1 2863
Protoss_Dragoon 11 9333
Protoss_Zealot 1 7237
Protoss_Robotics_Facility 1 8670
9333
