Protoss_Nexus 2 7263
Protoss_Gateway 2 5614
Protoss_Assimilator 2 9222
Protoss_Zealot 3 4127
Protoss_Cybernetics_Core 1 3698
Protoss_Citadel_of_Adun 1 4911
Protoss_Dragoon 9 9767
Protoss_Robotics_Facility 1 7985
Protoss_Observatory 1 9301
9767
