Protoss_Nexus 2 7515
Protoss_Gateway 3 9941
Protoss_Assimilator 2 9570
Protoss_Cybernetics_Core 1 2871
Protoss_Dragoon 7 9419
Protoss_Citadel_of_Adun 1 4917
Protoss_Templar_Archives 1 5943
Protoss_Dark_Templar 4 7843
9941
