Protoss_Nexus 2 6914
Protoss_Gateway 6 9607
Protoss_Assimilator 1 2169
Protoss_Cybernetics_Core 1 2958
Protoss_Zealot 1 3127
Protoss_Dragoon 9 9939
Protoss_Robotics_Facility 1 7502
Protoss_Observatory 1 8944
Protoss_Observer 1 9609
9939
