Protoss_Nexus 1 0
Protoss_Gateway 4 9238
Protoss_Assimilator 1 2440
Protoss_Cybernetics_Core 1 3189
Protoss_Dragoon 12 10000
Protoss_Robotics_Facility 1 5501
Protoss_Observatory 1 6818
Protoss_Observer 2 9926
Protoss_Citadel_of_Adun 1 9273
10000
