Protoss_Nexus 2 8067
Protoss_Gateway 4 8941
Protoss_Assimilator 1 2355
Protoss_Cybernetics_Core 1 2963
Protoss_Dragoon 10 9277
Protoss_Robotics_Facility 1 5346
Protoss_Observatory 1 6631
Protoss_Observer 2 7765
Protoss_Citadel_of_Adun 1 8877
Protoss_Shuttle 1 9625
9625
