Protoss_Nexus 2 7349
Protoss_Gateway 2 4013
Protoss_Assimilator 1 2151
Protoss_Zealot 1 2829
Protoss_Cybernetics_Core 1 3650
Protoss_Dragoon 12 9575
Protoss_Robotics_Facility 1 8395
Protoss_Observatory 1 9789
9789
