Protoss_Nexus 2 2593
Protoss_Gateway 4 7113
Protoss_Assimilator 1 3285
Protoss_Cybernetics_Core 1 4019
Protoss_Zealot 1 4675
Protoss_Dragoon 16 9633
Protoss_Robotics_Facility 1 8885
9633
