Protoss_Nexus 2 8185
Protoss_Gateway 2 8927
Protoss_Assimilator 1 2279
Protoss_Cybernetics_Core 1 2833
Protoss_Zealot 1 3067
Protoss_Dragoon 8 9905
Protoss_Robotics_Facility 1 5473
Protoss_Shuttle 1 6755
Protoss_Robotics_Support_Bay 1 6806
Protoss_Reaver 2 9623
Protoss_Observatory 1 8221
Protoss_Observer 2 9525
Protoss_Scarab 2 9840
9905
