Protoss_Nexus 1 0
Protoss_Gateway 2 6457
Protoss_Assimilator 1 2534
Protoss_Cybernetics_Core 1 3262
Protoss_Dragoon 8 9406
Protoss_Robotics_Facility 2 9682
Protoss_Citadel_of_Adun 1 6338
Protoss_Templar_Archives 1 7366
Protoss_Dark_Templar 2 8411
9682
