Protoss_Nexus 3 9699
Protoss_Gateway 2 5550
Protoss_Assimilator 2 6411
Protoss_Cybernetics_Core 1 3760
Protoss_Zealot 1 3871
Protoss_Dragoon 10 9219
Protoss_Robotics_Facility 1 6939
Protoss_Citadel_of_Adun 1 7826
Protoss_Observatory 1 8311
Protoss_Observer 2 9455
Protoss_Stargate 1 8989
Protoss_Templar_Archives 1 9051
9699
