Protoss_Nexus 2 8559
Protoss_Gateway 3 9247
Protoss_Assimilator 1 2275
Protoss_Zealot 2 3891
Protoss_Cybernetics_Core 1 3395
Protoss_Dragoon 11 9797
Protoss_Robotics_Facility 1 5630
Protoss_Observatory 1 6913
Protoss_Observer 2 8643
9797
