Protoss_Nexus 3 9489
Protoss_Gateway 2 4247
Protoss_Assimilator 2 7081
Protoss_Cybernetics_Core 1 4086
Protoss_Zealot 3 9835
Protoss_Dragoon 8 8469
Protoss_Robotics_Facility 1 6695
Protoss_Shuttle 1 7977
Protoss_Robotics_Support_Bay 2 8377
Protoss_Reaver 1 8917
Protoss_Observatory 1 8998
Protoss_Observer 1 9969
9969
