Protoss_Nexus 3 9735
Protoss_Gateway 2 4595
Protoss_Assimilator 2 6997
Protoss_Cybernetics_Core 1 4230
Protoss_Dragoon 11 9429
Protoss_Robotics_Facility 1 6819
Protoss_Shuttle 1 8109
Protoss_Observatory 1 8235
Protoss_Robotics_Support_Bay 1 8979
Protoss_Observer 2 9893
Protoss_Reaver 1 9925
9925
