Special_Protoss_Temple 14 0
Protoss_Nexus 2 7298
Protoss_Gateway 2 4906
Protoss_Assimilator 2 9027
Protoss_Cybernetics_Core 1 3125
Protoss_Zealot 1 3439
Protoss_Dragoon 10 9545
Protoss_Citadel_of_Adun 1 8284
Protoss_Templar_Archives 1 9729
Protoss_Robotics_Facility 1 9949
9949
