Protoss_Nexus 2 6403
Protoss_Gateway 4 9058
Protoss_Assimilator 1 2217
Protoss_Zealot 1 2859
Protoss_Cybernetics_Core 1 3423
Protoss_Dragoon 11 9831
Protoss_Robotics_Facility 1 5095
Protoss_Observatory 1 6797
Protoss_Observer 3 8781
9831
