Protoss_Nexus 3 9999
Protoss_Gateway 2 5723
Protoss_Assimilator 1 2195
Protoss_Cybernetics_Core 1 2769
Protoss_Dragoon 8 9421
Protoss_Robotics_Facility 1 5105
Protoss_Observatory 1 6508
Protoss_Observer 2 9875
Protoss_Zealot 4 8655
Protoss_Shuttle 1 8423
9999
