Protoss_Nexus 2 2549
Protoss_Gateway 4 9109
Protoss_Assimilator 2 7087
Protoss_Cybernetics_Core 1 4017
Protoss_Zealot 1 4425
Protoss_Dragoon 6 7101
Protoss_Citadel_of_Adun 1 6589
Protoss_Robotics_Facility 1 7721
Protoss_Templar_Archives 1 8301
Protoss_Shuttle 1 9079
Protoss_Dark_Templar 2 9293
Protoss_Stargate 1 9335
Protoss_Observatory 1 9391
9391
