Protoss_Nexus 3 9136
Protoss_Gateway 4 9885
Protoss_Assimilator 1 2161
Protoss_Cybernetics_Core 1 2777
Protoss_Dragoon 12 9391
Protoss_Robotics_Facility 1 6771
Protoss_Observatory 1 8187
Protoss_Observer 3 9919
9919
