Protoss_Nexus 2 2549
Protoss_Gateway 2 4223
Protoss_Assimilator 2 8210
Protoss_Cybernetics_Core 1 4079
Protoss_Zealot 1 4451
Protoss_Dragoon 12 9777
Protoss_Robotics_Facility 1 7823
Protoss_Shuttle 1 9163
Protoss_Robotics_Support_Bay 1 9313
9777
