Protoss_Nexus 2 9758
Protoss_Gateway 2 6787
Protoss_Assimilator 1 2431
Protoss_Cybernetics_Core 1 3022
Protoss_Dragoon 9 9591
Protoss_Robotics_Facility 1 6098
Protoss_Observatory 1 7403
Protoss_Observer 2 9143
Protoss_Shuttle 1 8551
Protoss_Zealot 2 8837
9758
