Protoss_Nexus 2 7253
Protoss_Gateway 2 4657
Protoss_Assimilator 1 2340
Protoss_Cybernetics_Core 1 2923
Protoss_Zealot 1 3143
Protoss_Dragoon 10 9301
Protoss_Robotics_Facility 1 7775
Protoss_Observatory 1 9130
Protoss_Observer 1 9819
9819
