Protoss_Nexus 1 0
Protoss_Gateway 2 6981
Protoss_Assimilator 1 2489
Protoss_Cybernetics_Core 1 3208
Protoss_Dragoon 7 8086
Protoss_Robotics_Facility 1 6007
Protoss_Observatory 1 7324
Protoss_Observer 1 7911
Protoss_Citadel_of_Adun 1 8031
Protoss_Shuttle 1 8611
Protoss_Zealot 4 9468
9468
