Protoss_Nexus 2 5773
Protoss_Gateway 4 8260
Protoss_Assimilator 1 2473
Protoss_Cybernetics_Core 1 3253
Protoss_Dragoon 13 9906
Protoss_Robotics_Facility 1 6184
Protoss_Observatory 1 7640
Protoss_Observer 2 9976
9976
