Protoss_Nexus 1 0
Protoss_Gateway 3 9152
Protoss_Assimilator 1 2463
Protoss_Cybernetics_Core 1 3033
Protoss_Dragoon 6 9846
Protoss_Stargate 1 5881
Protoss_Fleet_Beacon 1 7146
Protoss_Carrier 1 8136
Protoss_Robotics_Facility 1 8793
9846
