Protoss_Nexus 2 9444
Protoss_Gateway 1 1998
Protoss_Assimilator 1 2562
Protoss_Cybernetics_Core 1 3198
Protoss_Robotics_Facility 1 4554
Protoss_Dragoon 7 9867
Protoss_Shuttle 2 9446
Protoss_Robotics_Support_Bay 1 6083
Protoss_Reaver 1 7151
Protoss_Observatory 1 8525
9867
