Protoss_Nexus 1 0
Protoss_Gateway 2 5848
Protoss_Assimilator 1 2409
Protoss_Cybernetics_Core 1 2951
Protoss_Dragoon 6 7593
Protoss_Robotics_Facility 1 4669
Protoss_Observatory 1 6074
Protoss_Observer 2 9018
Protoss_Shuttle 1 8116
Protoss_Zealot 4 9331
9331
