Protoss_Nexus 2 8988
Protoss_Gateway 4 9965
Protoss_Assimilator 1 2198
Protoss_Cybernetics_Core 1 2859
Protoss_Robotics_Facility 1 3993
Protoss_Dragoon 9 8538
Protoss_Shuttle 1 5331
Protoss_Observatory 1 5655
Protoss_Observer 3 9131
9965
