Protoss_Nexus 1 0
Protoss_Gateway 2 7735
Protoss_Assimilator 1 2393
Protoss_Cybernetics_Core 1 2998
Protoss_Dragoon 10 9876
Protoss_Robotics_Facility 1 5316
Protoss_Shuttle 1 6626
Protoss_Robotics_Support_Bay 1 6987
Protoss_Reaver 1 7531
Protoss_Observatory 1 7940
Protoss_Observer 1 8583
9876
