Protoss_Nexus 2 8508
Protoss_Gateway 4 9751
Protoss_Assimilator 1 2410
Protoss_Cybernetics_Core 1 2969
Protoss_Dragoon 9 8211
Protoss_Robotics_Facility 1 8253
Protoss_Citadel_of_Adun 1 8923
Protoss_Zealot 2 9586
Protoss_Observatory 1 9595
9751
