Protoss_Nexus 1 0
Protoss_Gateway 3 8901
Protoss_Assimilator 1 2473
Protoss_Cybernetics_Core 1 3053
Protoss_Dragoon 12 9517
Protoss_Robotics_Facility 1 6618
Protoss_Observatory 1 7988
Protoss_Observer 1 8576
9517
