Protoss_Nexus 1 0
Protoss_Gateway 2 2313
Protoss_Zealot 11 8361
Protoss_Forge 1 5323
Protoss_Photon_Cannon 6 9663
Protoss_Assimilator 1 8319
Protoss_Cybernetics_Core 1 9314
9663
