Protoss_Nexus 2 7808
Protoss_Gateway 3 8778
Protoss_Assimilator 1 2432
Protoss_Cybernetics_Core 1 2918
Protoss_Zealot 1 3271
Protoss_Dragoon 9 9976
Protoss_Robotics_Facility 1 6601
Protoss_Observatory 1 8003
Protoss_Observer 3 9820
9976
