Protoss_Nexus 2 7987
Protoss_Gateway 3 9083
Protoss_Assimilator 1 2478
Protoss_Cybernetics_Core 1 3028
Protoss_Dragoon 7 9478
Protoss_Robotics_Facility 1 6052
Protoss_Shuttle 1 7651
Protoss_Observatory 1 8294
Protoss_Observer 1 9101
9478
