Protoss_Nexus 1 0
Protoss_Gateway 2 8057
Protoss_Assimilator 1 2494
Protoss_Cybernetics_Core 1 3251
Protoss_Robotics_Facility 1 4504
Protoss_Zealot 3 9330
Protoss_Dragoon 5 9051
Protoss_Shuttle 1 5796
Protoss_Observatory 1 5952
Protoss_Robotics_Support_Bay 1 6381
Protoss_Observer 1 6698
Protoss_Reaver 1 7300
Protoss_Scarab 3 9848
9848
