Protoss_Nexus 2 9781
Protoss_Gateway 2 8157
Protoss_Assimilator 1 2403
Protoss_Cybernetics_Core 1 2958
Protoss_Dragoon 5 9286
Protoss_Robotics_Facility 1 4542
Protoss_Shuttle 1 5831
Protoss_Robotics_Support_Bay 1 6059
Protoss_Zealot 2 6996
Protoss_Reaver 1 6759
Protoss_Observatory 1 7127
Protoss_Observer 1 7904
Protoss_Scarab 2 9045
9781
