Protoss_Nexus 1 0
Protoss_Gateway 3 7471
Protoss_Assimilator 1 2325
Protoss_Cybernetics_Core 1 3029
Protoss_Dragoon 12 9486
Protoss_Robotics_Facility 1 5801
Protoss_Observatory 1 7164
Protoss_Observer 2 8308
9486
