Protoss_Nexus 1 0
Protoss_Gateway 3 7158
Protoss_Assimilator 1 2308
Protoss_Cybernetics_Core 1 2979
Protoss_Robotics_Facility 1 4093
Protoss_Dragoon 10 9931
Protoss_Shuttle 1 5381
Protoss_Observatory 1 5716
Protoss_Observer 1 6316
9931
