Protoss_Nexus 3 9241
Protoss_Gateway 3 7750
Protoss_Assimilator 1 2456
Protoss_Cybernetics_Core 1 3065
Protoss_Dragoon 7 8666
Protoss_Robotics_Facility 1 4579
Protoss_Shuttle 1 5866
Protoss_Observatory 1 6084
Protoss_Observer 5 9551
9551
