Protoss_Nexus 1 0
Protoss_Gateway 2 8938
Protoss_Assimilator 2 2976
Protoss_Cybernetics_Core 1 3503
Protoss_Dragoon 2 5253
Protoss_Robotics_Facility 1 5743
Protoss_Forge 1 6058
Protoss_Photon_Cannon 1 6870
Protoss_Shuttle 1 7036
Protoss_Zealot 2 8046
Protoss_Robotics_Support_Bay 1 7485
Protoss_Reaver 1 8026
Protoss_Citadel_of_Adun 1 8531
Protoss_Scarab 1 9977
9977
