Protoss_Nexus 2 6283
Protoss_Gateway 3 8299
Protoss_Assimilator 1 2443
Protoss_Cybernetics_Core 1 3007
Protoss_Dragoon 7 8481
Protoss_Robotics_Facility 1 4503
Protoss_Observatory 1 5851
Protoss_Observer 3 8631
Protoss_Zealot 3 9396
Protoss_Shuttle 1 9233
9396
