Protoss_Nexus 2 8208
Protoss_Gateway 2 3558
Protoss_Assimilator 1 2371
Protoss_Cybernetics_Core 1 3263
Protoss_Dragoon 7 6973
Protoss_Citadel_of_Adun 1 6198
Protoss_Templar_Archives 1 7513
Protoss_Dark_Templar 3 9896
Protoss_Robotics_Facility 1 9363
9896
