Protoss_Nexus 2 2861
Protoss_Gateway 3 5498
Protoss_Assimilator 2 7780
Protoss_Cybernetics_Core 1 4462
Protoss_Zealot 1 5011
Protoss_Dragoon 11 9946
Protoss_Robotics_Facility 1 7237
Protoss_Shuttle 1 8756
9946
