Protoss_Nexus 1 0
Protoss_Gateway 1 2072
Protoss_Assimilator 1 2468
Protoss_Cybernetics_Core 1 3346
Protoss_Robotics_Facility 1 4763
Protoss_Zealot 1 5131
Protoss_Robotics_Support_Bay 1 6786
Protoss_Dragoon 2 8348
Protoss_Shield_Battery 1 8117
8348
