Protoss_Nexus 1 0
Protoss_Assimilator 1 1739
Protoss_Gateway 3 8393
Protoss_Cybernetics_Core 1 3228
Protoss_Robotics_Facility 1 4258
Protoss_Dragoon 6 8920
Protoss_Shuttle 1 5546
Protoss_Observatory 1 7018
Protoss_Observer 3 8865
Protoss_Citadel_of_Adun 1 7961
Protoss_Templar_Archives 1 9198
Protoss_Zealot 1 9281
9281
