Protoss_Nexus 1 0
Protoss_Gateway 2 3513
Protoss_Assimilator 1 2223
Protoss_Cybernetics_Core 1 3004
Protoss_Dragoon 7 8623
Protoss_Robotics_Facility 1 6303
Protoss_Zealot 4 8021
Protoss_Observatory 1 7613
Protoss_Shuttle 1 7626
Protoss_Observer 1 8528
8623
