Protoss_Nexus 2 7383
Protoss_Gateway 2 4393
Protoss_Assimilator 1 2373
Protoss_Cybernetics_Core 1 3058
Protoss_Dragoon 11 9721
Protoss_Robotics_Facility 1 8398
Protoss_Citadel_of_Adun 1 9177
Protoss_Observatory 1 9806
9806
