Protoss_Nexus 1 0
Protoss_Gateway 3 8038
Protoss_Assimilator 1 2287
Protoss_Cybernetics_Core 1 2938
Protoss_Robotics_Facility 1 4103
Protoss_Dragoon 9 9706
Protoss_Observatory 1 5413
Protoss_Shuttle 1 5581
Protoss_Observer 3 8271
9706
