Protoss_Nexus 1 0
Protoss_Gateway 2 6386
Protoss_Assimilator 1 2461
Protoss_Zealot 1 3115
Protoss_Cybernetics_Core 1 4112
Protoss_Dragoon 7 8837
Protoss_Robotics_Facility 1 7067
Protoss_Observatory 1 8507
Protoss_Shuttle 1 9003
Protoss_Observer 1 9905
9905
