Protoss_Nexus 2 9612
Protoss_Gateway 2 3642
Protoss_Assimilator 1 2510
Protoss_Cybernetics_Core 1 3055
Protoss_Dragoon 10 9646
Protoss_Zealot 2 6403
Protoss_Robotics_Facility 1 7048
Protoss_Observatory 1 8393
Protoss_Observer 1 9306
9646
