Protoss_Nexus 1 0
Protoss_Gateway 1 2137
Protoss_Assimilator 1 2704
Protoss_Cybernetics_Core 1 3301
Protoss_Dragoon 6 9063
Protoss_Robotics_Facility 1 5796
Protoss_Shuttle 1 7261
Protoss_Zealot 2 9815
Protoss_Robotics_Support_Bay 1 7544
Protoss_Reaver 2 9776
9815
