Protoss_Nexus 3 9531
Protoss_Gateway 2 5888
Protoss_Assimilator 1 2552
Protoss_Cybernetics_Core 1 3255
Protoss_Dragoon 7 8104
Protoss_Robotics_Facility 1 4837
Protoss_Observatory 1 6317
Protoss_Observer 2 9211
9531
