Protoss_Nexus 2 9078
Protoss_Gateway 3 6924
Protoss_Assimilator 1 2561
Protoss_Cybernetics_Core 1 3173
Protoss_Dragoon 9 8596
Protoss_Robotics_Facility 1 5146
Protoss_Observatory 1 6636
Protoss_Observer 2 8631
9078
