Protoss_Nexus 2 8924
Protoss_Gateway 2 5323
Protoss_Assimilator 1 2398
Protoss_Cybernetics_Core 1 3248
Protoss_Dragoon 9 8392
Protoss_Robotics_Facility 1 8350
Protoss_Zealot 2 9291
Protoss_Observatory 1 9653
Protoss_Shuttle 1 9796
9796
