Protoss_Nexus 1 0
Protoss_Gateway 1 1905
Protoss_Assimilator 1 2215
Protoss_Cybernetics_Core 1 2908
Protoss_Dragoon 6 8015
Protoss_Robotics_Facility 1 4372
Protoss_Observatory 1 5783
8015
