Protoss_Nexus 2 9828
Protoss_Gateway 2 8761
Protoss_Assimilator 2 2714
Protoss_Zealot 2 4116
Protoss_Cybernetics_Core 1 4007
Protoss_Dragoon 5 8528
Protoss_Robotics_Facility 1 5155
Protoss_Shuttle 1 6446
Protoss_Robotics_Support_Bay 1 6878
Protoss_Reaver 2 8778
9828
