Protoss_Nexus 2 7863
Protoss_Gateway 2 5268
Protoss_Assimilator 2 2848
Protoss_Cybernetics_Core 1 3453
Protoss_Zealot 2 9541
Protoss_Dragoon 5 9511
Protoss_Robotics_Facility 1 9298
9541
