Protoss_Nexus 2 8757
Protoss_Gateway 4 8354
Protoss_Assimilator 1 2314
Protoss_Cybernetics_Core 1 2973
Protoss_Robotics_Facility 1 4143
Protoss_Dragoon 9 9631
Protoss_Shuttle 1 5441
Protoss_Observatory 1 5558
Protoss_Observer 2 7071
9631
