Protoss_Nexus 1 0
Protoss_Gateway 2 2868
Protoss_Zealot 3 7046
Protoss_Assimilator 1 3226
Protoss_Cybernetics_Core 1 3803
Protoss_Dragoon 4 8186
Protoss_Robotics_Facility 1 5880
Protoss_Citadel_of_Adun 1 6921
Protoss_Shuttle 1 7231
Protoss_Templar_Archives 1 7961
Protoss_Dark_Templar 4 9733
9733
