Protoss_Nexus 2 9758
Protoss_Gateway 3 8081
Protoss_Assimilator 1 2395
Protoss_Cybernetics_Core 1 3210
Protoss_Dragoon 12 9234
Protoss_Robotics_Facility 1 5293
Protoss_Observatory 1 6660
Protoss_Observer 2 7983
9758
