Protoss_Nexus 1 0
Protoss_Gateway 2 8113
Protoss_Assimilator 1 2568
Protoss_Cybernetics_Core 1 3183
Protoss_Dragoon 8 9978
Protoss_Robotics_Facility 1 4721
Protoss_Shuttle 1 6091
Protoss_Robotics_Support_Bay 1 6571
Protoss_Reaver 2 8206
Protoss_Observatory 1 7901
Protoss_Scarab 5 9850
Protoss_Observer 1 9258
9978
