Protoss_Nexus 2 9849
Protoss_Gateway 2 6170
Protoss_Assimilator 1 2608
Protoss_Cybernetics_Core 1 3197
Protoss_Dragoon 9 9243
Protoss_Robotics_Facility 1 4878
Protoss_Observatory 1 6275
Protoss_Observer 3 9371
9849
