Protoss_Nexus 2 7202
Protoss_Gateway 2 5560
Protoss_Assimilator 1 2501
Protoss_Cybernetics_Core 1 3119
Protoss_Dragoon 10 9541
Protoss_Citadel_of_Adun 1 4758
Protoss_Robotics_Facility 1 7633
Protoss_Observatory 1 9148
Protoss_Observer 1 9686
9686
