Protoss_Nexus 2 8683
Protoss_Gateway 4 9378
Protoss_Assimilator 1 2521
Protoss_Cybernetics_Core 1 3123
Protoss_Dragoon 9 9173
Protoss_Robotics_Facility 1 4700
Protoss_Observatory 1 6075
Protoss_Observer 4 9848
9848
