Protoss_Nexus 2 6344
Protoss_Gateway 1 1953
Protoss_Assimilator 1 2351
Protoss_Cybernetics_Core 1 3109
Protoss_Dragoon 8 9524
Protoss_Robotics_Facility 1 5525
Protoss_Observatory 1 6907
Protoss_Observer 3 9381
9524
