Protoss_Nexus 3 9429
Protoss_Gateway 2 5646
Protoss_Assimilator 1 2446
Protoss_Cybernetics_Core 1 3203
Protoss_Zealot 1 3401
Protoss_Dragoon 5 8496
Protoss_Robotics_Facility 1 4558
Protoss_Robotics_Support_Bay 1 6413
Protoss_Reaver 1 7031
Protoss_Observatory 1 7941
Protoss_Observer 1 9796
9796
