Protoss_Nexus 2 8465
Protoss_Gateway 2 6825
Protoss_Assimilator 1 2493
Protoss_Cybernetics_Core 1 3150
Protoss_Robotics_Facility 1 4333
Protoss_Dragoon 5 7821
Protoss_Observatory 1 5870
Protoss_Observer 1 6426
Protoss_Shuttle 1 7028
Protoss_Zealot 2 8731
8731
