Protoss_Nexus 2 8933
Protoss_Gateway 3 6249
Protoss_Assimilator 1 2517
Protoss_Zealot 6 9683
Protoss_Cybernetics_Core 1 3743
Protoss_Dragoon 6 8013
Protoss_Robotics_Facility 1 5040
Protoss_Observatory 1 6350
Protoss_Shuttle 1 6661
Protoss_Observer 2 8623
9683
