Protoss_Nexus 1 0
Protoss_Gateway 3 6264
Protoss_Assimilator 1 2436
Protoss_Cybernetics_Core 1 2988
Protoss_Dragoon 6 9108
Protoss_Citadel_of_Adun 1 4833
Protoss_Templar_Archives 1 5934
Protoss_Dark_Templar 3 7256
Protoss_Robotics_Facility 1 9153
Protoss_Zealot 2 9601
9601
