Protoss_Nexus 3 9369
Protoss_Gateway 2 5998
Protoss_Assimilator 1 2345
Protoss_Cybernetics_Core 1 3008
Protoss_Dragoon 7 7897
Protoss_Robotics_Facility 1 4779
Protoss_Observatory 1 6081
Protoss_Observer 2 7241
Protoss_Citadel_of_Adun 1 9713
9713
