Protoss_Nexus 2 8308
Protoss_Gateway 3 9750
Protoss_Assimilator 1 2575
Protoss_Cybernetics_Core 1 3308
Protoss_Dragoon 9 9428
Protoss_Robotics_Facility 1 5523
Protoss_Observatory 1 6868
Protoss_Observer 2 8121
9750
