Protoss_Nexus 3 9587
Protoss_Gateway 3 6248
Protoss_Assimilator 1 2517
Protoss_Cybernetics_Core 1 3110
Protoss_Dragoon 8 8505
Protoss_Robotics_Facility 1 4645
Protoss_Observatory 1 6083
Protoss_Observer 2 7945
9587
