Protoss_Nexus 2 7685
Protoss_Gateway 2 8393
Protoss_Assimilator 1 2522
Protoss_Cybernetics_Core 1 3053
Protoss_Dragoon 8 9836
Protoss_Robotics_Facility 1 4273
Protoss_Zealot 2 5955
Protoss_Shuttle 1 5621
Protoss_Observatory 1 7766
Protoss_Citadel_of_Adun 1 8284
Protoss_Observer 1 8446
Protoss_Templar_Archives 1 9595
9836
