Protoss_Nexus 1 0
Protoss_Gateway 3 9423
Protoss_Assimilator 1 2573
Protoss_Cybernetics_Core 1 3301
Protoss_Dragoon 10 9585
Protoss_Robotics_Facility 1 5393
Protoss_Observatory 1 6698
Protoss_Observer 2 8586
Protoss_Shuttle 1 9571
9585
