Protoss_Nexus 1 0
Protoss_Gateway 2 6721
Protoss_Assimilator 1 2478
Protoss_Cybernetics_Core 1 3048
Protoss_Dragoon 6 9321
Protoss_Stargate 1 5956
Protoss_Fleet_Beacon 1 7228
Protoss_Carrier 1 8341
Protoss_Robotics_Facility 1 8969
9321
