Protoss_Nexus 1 0
Protoss_Gateway 2 2578
Protoss_Zealot 13 7053
Protoss_Assimilator 1 6211
Protoss_Cybernetics_Core 1 6698
Protoss_Dragoon 5 9966
Protoss_Robotics_Facility 1 9678
9966
