Protoss_Nexus 2 8936
Protoss_Gateway 3 9979
Protoss_Assimilator 1 2478
Protoss_Cybernetics_Core 1 3039
Protoss_Zealot 3 9551
Protoss_Dragoon 6 7586
Protoss_Robotics_Facility 1 5774
Protoss_Observatory 1 7143
Protoss_Observer 2 8293
Protoss_Shuttle 1 9336
9979
