Protoss_Nexus 2 8659
Protoss_Gateway 2 6015
Protoss_Assimilator 1 2483
Protoss_Cybernetics_Core 1 3264
Protoss_Dragoon 11 9991
Protoss_Robotics_Facility 1 6248
Protoss_Observatory 1 7808
Protoss_Observer 2 9058
9991
