Protoss_Nexus 1 0
Protoss_Gateway 1 2146
Protoss_Assimilator 1 2505
Protoss_Cybernetics_Core 1 3148
Protoss_Dragoon 2 6880
Protoss_Robotics_Facility 1 4729
Protoss_Zealot 2 6278
Protoss_Robotics_Support_Bay 1 6104
Protoss_Shuttle 1 6111
Protoss_Reaver 1 7086
7086
