Protoss_Nexus 2 9382
Protoss_Gateway 2 6313
Protoss_Assimilator 1 2430
Protoss_Cybernetics_Core 1 3107
Protoss_Dragoon 11 9603
Protoss_Robotics_Facility 1 4500
Protoss_Observatory 1 5885
Protoss_Observer 2 7281
9603
