Protoss_Nexus 1 0
Protoss_Gateway 1 1918
Protoss_Assimilator 1 2308
Protoss_Cybernetics_Core 1 2932
Protoss_Zealot 1 3526
Protoss_Dragoon 6 8026
Protoss_Robotics_Facility 1 6593
Protoss_Citadel_of_Adun 1 7091
Protoss_Shuttle 1 7986
Protoss_Templar_Archives 1 8266
Protoss_Dark_Templar 1 9256
Protoss_Robotics_Support_Bay 1 9867
9867
