Protoss_Nexus 1 0
Protoss_Gateway 2 9094
Protoss_Assimilator 1 2463
Protoss_Cybernetics_Core 1 3077
Protoss_Robotics_Facility 1 4268
Protoss_Dragoon 5 9017
Protoss_Shuttle 1 5561
Protoss_Robotics_Support_Bay 1 5853
Protoss_Reaver 2 9686
Protoss_Zealot 1 6716
Protoss_Observatory 1 7738
Protoss_Scarab 8 9978
Protoss_Observer 1 8966
9978
