Protoss_Nexus 1 0
Protoss_Gateway 2 4758
Protoss_Assimilator 1 2714
Protoss_Cybernetics_Core 1 3258
Protoss_Zealot 1 3431
Protoss_Dragoon 5 9191
Protoss_Citadel_of_Adun 1 4495
Protoss_Templar_Archives 1 5683
Protoss_Dark_Templar 4 7843
Protoss_Robotics_Facility 1 8608
9191
