Protoss_Scout 1 0
Protoss_Nexus 3 9713
Protoss_Gateway 3 6213
Protoss_Assimilator 1 2407
Protoss_Cybernetics_Core 1 3143
Protoss_Robotics_Facility 1 4223
Protoss_Dragoon 6 7953
Protoss_Observatory 1 5578
Protoss_Observer 4 9416
9713
