Protoss_Nexus 1 0
Protoss_Gateway 2 8291
Protoss_Assimilator 1 2446
Protoss_Cybernetics_Core 1 3071
Protoss_Dragoon 3 7796
Protoss_Stargate 2 5392
Protoss_Scout 2 6671
Protoss_Zealot 1 7146
Protoss_Shield_Battery 1 7810
8291
