Protoss_Nexus 2 8464
Protoss_Gateway 4 9861
Protoss_Assimilator 1 2568
Protoss_Cybernetics_Core 1 3183
Protoss_Dragoon 6 8736
Protoss_Robotics_Facility 1 5843
Protoss_Citadel_of_Adun 1 7225
Protoss_Observatory 1 7248
Protoss_Observer 1 7846
Protoss_Templar_Archives 1 8704
Protoss_Shuttle 1 9556
9861
