Protoss_Nexus 3 9470
Protoss_Gateway 2 7526
Protoss_Assimilator 1 2331
Protoss_Cybernetics_Core 1 2964
Protoss_Dragoon 7 8531
Protoss_Robotics_Facility 1 5086
Protoss_Observatory 1 6383
Protoss_Observer 3 9476
Protoss_Citadel_of_Adun 1 8961
Protoss_Zealot 2 9836
9836
