Protoss_Nexus 1 0
Protoss_Gateway 2 8448
Protoss_Assimilator 1 2376
Protoss_Cybernetics_Core 1 3138
Protoss_Zealot 3 9771
Protoss_Dragoon 7 8970
Protoss_Robotics_Facility 1 5993
Protoss_Shuttle 2 9615
Protoss_Robotics_Support_Bay 1 7705
Protoss_Reaver 1 8563
Protoss_Citadel_of_Adun 1 9133
9771
