Protoss_Nexus 2 6698
Protoss_Gateway 3 7786
Protoss_Assimilator 1 2515
Protoss_Cybernetics_Core 1 3276
Protoss_Zealot 4 9921
Protoss_Dragoon 8 8951
Protoss_Robotics_Facility 1 7829
Protoss_Observatory 1 9508
Protoss_Shuttle 1 9546
9921
