Protoss_Nexus 2 8763
Protoss_Gateway 2 7617
Protoss_Assimilator 1 2343
Protoss_Cybernetics_Core 1 3049
Protoss_Robotics_Facility 1 4219
Protoss_Dragoon 3 6461
Protoss_Observatory 1 5611
Protoss_Shuttle 1 5826
Protoss_Observer 3 7932
Protoss_Zealot 4 9276
Protoss_Robotics_Support_Bay 1 8154
Protoss_Reaver 1 9246
9276
