Protoss_Nexus 1 0
Protoss_Gateway 3 5783
Protoss_Assimilator 1 2535
Protoss_Zealot 7 9901
Protoss_Cybernetics_Core 1 3885
Protoss_Dragoon 7 7772
Protoss_Citadel_of_Adun 1 7980
Protoss_Templar_Archives 1 9132
Protoss_Robotics_Facility 1 9563
9901
