Protoss_Nexus 2 8629
Protoss_Gateway 3 9483
Protoss_Assimilator 1 2443
Protoss_Cybernetics_Core 1 3255
Protoss_Dragoon 8 9236
Protoss_Robotics_Facility 1 6015
Protoss_Observatory 1 8047
Protoss_Observer 1 8711
Protoss_Shuttle 1 9313
9483
