Protoss_Nexus 1 0
Protoss_Gateway 1 1914
Protoss_Assimilator 1 2305
Protoss_Cybernetics_Core 1 2950
Protoss_Robotics_Facility 1 4069
Protoss_Dragoon 4 9069
Protoss_Zealot 2 5807
Protoss_Shuttle 1 5489
Protoss_Robotics_Support_Bay 1 5961
Protoss_Reaver 3 8605
Protoss_Scarab 14 9953
9953
