Protoss_Nexus 2 7211
Protoss_Gateway 2 7653
Protoss_Assimilator 1 2318
Protoss_Cybernetics_Core 1 3181
Protoss_Dragoon 9 9682
Protoss_Robotics_Facility 1 4783
Protoss_Observatory 1 6078
Protoss_Observer 4 9466
9682
