Protoss_Nexus 2 6623
Protoss_Assimilator 2 2983
Protoss_Gateway 3 9858
Protoss_Zealot 2 4466
Protoss_Cybernetics_Core 1 4128
Protoss_Dragoon 1 5126
Protoss_Citadel_of_Adun 1 6013
Protoss_Templar_Archives 1 7058
Protoss_Robotics_Facility 1 7504
Protoss_Dark_Templar 2 9116
Protoss_Shuttle 1 8991
Protoss_Observatory 1 9368
Protoss_Observer 1 9906
9906
