Protoss_Nexus 1 0
Protoss_Gateway 3 7983
Protoss_Assimilator 1 2623
Protoss_Cybernetics_Core 1 3093
Protoss_Dragoon 8 9679
Protoss_Robotics_Facility 1 6078
Protoss_Zealot 4 8791
Protoss_Shuttle 1 7669
Protoss_Observatory 1 7723
Protoss_Observer 1 8644
Protoss_Citadel_of_Adun 1 8905
9679
