Protoss_Nexus 1 0
Protoss_Gateway 2 5944
Protoss_Assimilator 1 2635
Protoss_Cybernetics_Core 1 3141
Protoss_Dragoon 4 8151
Protoss_Robotics_Facility 1 4893
Protoss_Observatory 1 6279
Protoss_Observer 1 6821
8151
