Protoss_Nexus 3 8843
Protoss_Gateway 2 6308
Protoss_Assimilator 1 2433
Protoss_Cybernetics_Core 1 3052
Protoss_Dragoon 8 9466
Protoss_Robotics_Facility 1 5513
Protoss_Observatory 1 6854
Protoss_Observer 3 9846
9846
