Protoss_Nexus 2 8171
Protoss_Gateway 2 5903
Protoss_Assimilator 1 2489
Protoss_Cybernetics_Core 1 3043
Protoss_Dragoon 3 5668
Protoss_Citadel_of_Adun 1 5256
Protoss_Templar_Archives 1 6300
Protoss_Zealot 1 6420
Protoss_Dark_Templar 6 9361
9361
