Protoss_Nexus 2 9133
Protoss_Gateway 2 4500
Protoss_Assimilator 1 2395
Protoss_Cybernetics_Core 1 3103
Protoss_Dragoon 12 9816
Protoss_Robotics_Facility 1 7553
Protoss_Observatory 1 8889
9816
