Protoss_Nexus 2 8068
Protoss_Gateway 2 8763
Protoss_Assimilator 1 2503
Protoss_Cybernetics_Core 1 3153
Protoss_Dragoon 5 9921
Protoss_Robotics_Facility 1 4628
Protoss_Shuttle 1 5916
Protoss_Robotics_Support_Bay 1 6208
Protoss_Reaver 1 6829
Protoss_Zealot 1 7001
Protoss_Observatory 1 7163
Protoss_Observer 3 9696
9921
