Protoss_Nexus 2 6468
Protoss_Gateway 3 9588
Protoss_Assimilator 1 2483
Protoss_Cybernetics_Core 1 3133
Protoss_Dragoon 12 9615
Protoss_Robotics_Facility 1 6784
Protoss_Observatory 1 8236
Protoss_Observer 1 9176
9615
