Protoss_Nexus 2 8807
Protoss_Gateway 1 1968
Protoss_Assimilator 1 2509
Protoss_Cybernetics_Core 1 3188
Protoss_Dragoon 4 9345
Protoss_Robotics_Facility 1 4658
Protoss_Zealot 2 6068
Protoss_Shuttle 2 9836
Protoss_Robotics_Support_Bay 1 6393
Protoss_Reaver 2 8288
Protoss_Scarab 2 9660
9836
