Protoss_Nexus 2 7558
Protoss_Gateway 2 6338
Protoss_Assimilator 1 2613
Protoss_Cybernetics_Core 1 3249
Protoss_Dragoon 8 9666
Protoss_Robotics_Facility 1 5624
Protoss_Observatory 1 7014
Protoss_Observer 2 8193
Protoss_Shuttle 1 8891
Protoss_Robotics_Support_Bay 1 9118
Protoss_Reaver 1 9793
9793
