Protoss_Nexus 1 0
Protoss_Assimilator 1 1786
Protoss_Gateway 1 2148
Protoss_Cybernetics_Core 1 3223
Protoss_Dragoon 5 8958
Protoss_Robotics_Facility 1 4492
Protoss_Shuttle 1 5801
Protoss_Robotics_Support_Bay 1 5998
Protoss_Reaver 3 9450
Protoss_Observatory 1 6914
Protoss_Scarab 7 8971
Protoss_Observer 1 8848
9450
