Protoss_Nexus 3 9938
Protoss_Gateway 3 8633
Protoss_Assimilator 1 2518
Protoss_Cybernetics_Core 1 3163
Protoss_Robotics_Facility 1 4333
Protoss_Shuttle 1 5621
Protoss_Observatory 1 5648
Protoss_Dragoon 8 9706
Protoss_Observer 4 9313
9938
