Protoss_Nexus 1 0
Protoss_Gateway 3 7036
Protoss_Assimilator 1 2646
Protoss_Zealot 2 3466
Protoss_Cybernetics_Core 1 3260
Protoss_Dragoon 12 9508
Protoss_Citadel_of_Adun 1 8601
Protoss_Templar_Archives 1 9623
9623
