Protoss_Nexus 2 8416
Protoss_Gateway 2 6338
Protoss_Assimilator 1 2402
Protoss_Cybernetics_Core 1 3038
Protoss_Dragoon 9 9221
Protoss_Citadel_of_Adun 2 9729
Protoss_Robotics_Facility 1 5159
Protoss_Observatory 1 6458
Protoss_Observer 2 8364
9729
