Protoss_Nexus 1 0
Protoss_Gateway 1 2110
Protoss_Assimilator 1 2557
Protoss_Cybernetics_Core 1 3313
Protoss_Dragoon 6 9306
Protoss_Robotics_Facility 1 6036
Protoss_Shuttle 1 7366
Protoss_Zealot 1 7571
Protoss_Robotics_Support_Bay 1 7828
Protoss_Reaver 1 8431
Protoss_Observatory 1 8707
Protoss_Observer 1 9895
9895
