Protoss_Nexus 1 0
Protoss_Gateway 2 6777
Protoss_Assimilator 1 2316
Protoss_Cybernetics_Core 1 3097
Protoss_Robotics_Facility 1 4227
Protoss_Dragoon 9 9285
Protoss_Observatory 1 5629
Protoss_Observer 2 8901
9285
