Protoss_Nexus 2 7491
Protoss_Gateway 2 3823
Protoss_Assimilator 1 2398
Protoss_Cybernetics_Core 1 3068
Protoss_Dragoon 10 8416
Protoss_Citadel_of_Adun 1 8372
Protoss_Templar_Archives 1 9885
9885
