Protoss_Nexus 2 7024
Protoss_Gateway 2 4567
Protoss_Assimilator 1 2276
Protoss_Cybernetics_Core 1 2873
Protoss_Dragoon 11 9619
Protoss_Robotics_Facility 1 8057
Protoss_Observatory 1 9442
9619
