Protoss_Nexus 3 9668
Protoss_Gateway 2 5517
Protoss_Assimilator 1 2283
Protoss_Cybernetics_Core 1 3210
Protoss_Dragoon 9 9423
Protoss_Robotics_Facility 1 4522
Protoss_Observatory 1 5999
Protoss_Observer 3 9783
9783
