Protoss_Nexus 1 0
Protoss_Gateway 1 1988
Protoss_Assimilator 1 2533
Protoss_Cybernetics_Core 1 3192
Protoss_Dragoon 7 8869
Protoss_Robotics_Facility 1 5643
Protoss_Shuttle 1 6936
Protoss_Observatory 1 7060
Protoss_Robotics_Support_Bay 1 7748
Protoss_Observer 1 7838
Protoss_Reaver 2 9573
9573
