Protoss_Nexus 2 6416
Protoss_Gateway 2 3475
Protoss_Assimilator 1 2359
Protoss_Cybernetics_Core 1 2984
Protoss_Dragoon 11 9257
Protoss_Robotics_Facility 1 7219
Protoss_Observatory 1 8548
Protoss_Observer 2 9789
9789
