Protoss_Nexus 2 9560
Protoss_Gateway 2 2553
Protoss_Zealot 7 5471
Protoss_Assimilator 1 3967
Protoss_Cybernetics_Core 1 5054
Protoss_Dragoon 6 8063
Protoss_Citadel_of_Adun 1 6826
Protoss_Templar_Archives 1 8188
Protoss_Dark_Templar 2 9261
9560
