Protoss_Nexus 2 8399
Protoss_Gateway 4 9319
Protoss_Assimilator 1 2349
Protoss_Cybernetics_Core 1 2898
Protoss_Dragoon 11 9681
Protoss_Robotics_Facility 1 5438
Protoss_Observatory 1 6733
Protoss_Observer 2 8966
9681
