Protoss_Nexus 1 0
Protoss_Gateway 2 4862
Protoss_Forge 1 3008
Protoss_Zealot 2 3631
Protoss_Assimilator 1 3661
Protoss_Photon_Cannon 1 3773
Protoss_Cybernetics_Core 1 4393
Protoss_Dragoon 11 9685
Protoss_Robotics_Facility 1 8079
Protoss_Shuttle 1 9729
9729
