Protoss_Nexus 2 8177
Protoss_Gateway 2 4873
Protoss_Assimilator 1 2520
Protoss_Cybernetics_Core 1 3276
Protoss_Dragoon 11 9837
Protoss_Robotics_Facility 1 5821
Protoss_Observatory 1 7291
Protoss_Observer 2 8725
9837
