Protoss_Nexus 1 0
Protoss_Gateway 2 7689
Protoss_Assimilator 1 2548
Protoss_Cybernetics_Core 1 3265
Protoss_Dragoon 6 8452
Protoss_Robotics_Facility 1 6042
Protoss_Observatory 1 7517
Protoss_Citadel_of_Adun 1 7545
Protoss_Observer 1 8516
8516
