Protoss_Nexus 2 7616
Protoss_Gateway 2 4413
Protoss_Assimilator 2 9808
Protoss_Cybernetics_Core 1 2959
Protoss_Dragoon 10 8961
Protoss_Zealot 1 7205
Protoss_Robotics_Facility 1 8345
Protoss_Shuttle 1 9956
9956
