Protoss_Nexus 2 6380
Protoss_Gateway 4 9011
Protoss_Assimilator 2 9404
Protoss_Cybernetics_Core 1 3125
Protoss_Dragoon 11 9785
Protoss_Robotics_Facility 1 7124
Protoss_Observatory 1 8529
Protoss_Observer 1 9277
9785
