Protoss_Nexus 2 9600
Protoss_Gateway 2 7716
Protoss_Assimilator 1 2618
Protoss_Cybernetics_Core 1 3213
Protoss_Dragoon 9 9981
Protoss_Robotics_Facility 1 4964
Protoss_Observatory 1 6399
Protoss_Observer 2 7558
Protoss_Shuttle 1 8386
9981
