Protoss_Nexus 3 9710
Protoss_Gateway 2 5887
Protoss_Assimilator 1 2425
Protoss_Cybernetics_Core 1 3047
Protoss_Dragoon 11 9887
Protoss_Robotics_Facility 1 4505
Protoss_Observatory 1 5894
Protoss_Observer 3 9489
9887
