Protoss_Nexus 2 7514
Protoss_Gateway 2 5004
Protoss_Assimilator 1 2478
Protoss_Cybernetics_Core 1 3115
Protoss_Dragoon 5 9288
Protoss_Citadel_of_Adun 1 5643
Protoss_Zealot 3 6703
Protoss_Templar_Archives 1 6749
Protoss_Dark_Templar 4 8598
Protoss_Robotics_Facility 1 9452
9452
