Protoss_Nexus 1 0
Protoss_Gateway 4 9963
Protoss_Zealot 3 6626
Protoss_Assimilator 1 3188
Protoss_Cybernetics_Core 1 4063
Protoss_Dragoon 3 6581
Protoss_Citadel_of_Adun 1 5228
Protoss_Templar_Archives 1 6223
Protoss_Dark_Templar 6 9793
Protoss_Robotics_Facility 1 7941
Protoss_Shuttle 1 9636
9963
