Protoss_Nexus 2 8815
Protoss_Gateway 2 4648
Protoss_Assimilator 1 2399
Protoss_Cybernetics_Core 1 3057
Protoss_Dragoon 4 5913
Protoss_Citadel_of_Adun 1 6285
Protoss_Zealot 2 6665
Protoss_Templar_Archives 1 7320
Protoss_Robotics_Facility 1 7524
Protoss_Dark_Templar 3 9337
Protoss_Shuttle 1 8925
Protoss_Observatory 1 9591
9591
