Protoss_Nexus 1 0
Protoss_Gateway 2 2612
Protoss_Zealot 9 9947
Protoss_Assimilator 1 3482
Protoss_Cybernetics_Core 1 4293
Protoss_Dragoon 4 6335
Protoss_Citadel_of_Adun 1 6823
Protoss_Templar_Archives 1 7861
Protoss_High_Templar 2 9811
Protoss_Forge 1 9159
9947
