Protoss_Nexus 1 0
Protoss_Gateway 1 1943
Protoss_Assimilator 1 2658
Protoss_Zealot 3 5076
Protoss_Cybernetics_Core 1 4607
Protoss_Robotics_Facility 1 5634
Protoss_Dragoon 2 6538
Protoss_Citadel_of_Adun 1 6308
Protoss_Robotics_Support_Bay 1 7098
Protoss_Shuttle 1 7101
Protoss_Templar_Archives 1 7503
Protoss_Reaver 2 9055
Protoss_Dark_Templar 2 9513
9513
