Protoss_Nexus 2 8203
Protoss_Gateway 2 5398
Protoss_Assimilator 1 2373
Protoss_Zealot 3 7443
Protoss_Cybernetics_Core 1 3338
Protoss_Dragoon 8 9671
Protoss_Robotics_Facility 1 8915
9671
