Protoss_Nexus 2 9689
Protoss_Gateway 3 7369
Protoss_Assimilator 1 2273
Protoss_Cybernetics_Core 1 2930
Protoss_Dragoon 11 8513
Protoss_Robotics_Facility 1 6715
Protoss_Zealot 5 9949
Protoss_Observatory 1 8062
Protoss_Observer 1 8603
Protoss_Shuttle 1 9369
9949
