Protoss_Nexus 3 9717
Protoss_Gateway 2 6118
Protoss_Assimilator 1 2528
Protoss_Cybernetics_Core 1 3263
Protoss_Dragoon 10 8846
Protoss_Robotics_Facility 1 5619
Protoss_Observatory 1 7196
Protoss_Observer 2 8343
9717
