Protoss_Nexus 2 7548
Protoss_Gateway 2 5808
Protoss_Assimilator 1 2480
Protoss_Cybernetics_Core 1 3088
Protoss_Dragoon 8 8693
Protoss_Robotics_Facility 1 5458
Protoss_Observatory 1 6754
Protoss_Observer 2 7928
Protoss_Shuttle 1 8081
Protoss_Robotics_Support_Bay 1 8325
Protoss_Reaver 1 9141
Protoss_Zealot 2 9445
9445
