Protoss_Nexus 1 0
Protoss_Gateway 2 5085
Protoss_Zealot 5 9401
Protoss_Assimilator 1 3789
Protoss_Cybernetics_Core 1 4281
Protoss_Dragoon 9 8649
Protoss_Robotics_Facility 1 8083
Protoss_Shuttle 1 9396
Protoss_Robotics_Support_Bay 1 9425
9425
