Protoss_Nexus 2 9255
Protoss_Gateway 2 8024
Protoss_Assimilator 1 2311
Protoss_Cybernetics_Core 1 3206
Protoss_Dragoon 5 9623
Protoss_Robotics_Facility 1 4693
Protoss_Shuttle 1 5977
Protoss_Robotics_Support_Bay 1 6043
Protoss_Zealot 2 7117
Protoss_Reaver 2 8289
Protoss_Scarab 4 9941
Protoss_Observatory 1 9503
9941
