Protoss_Nexus 2 6718
Protoss_Gateway 3 8163
Protoss_Assimilator 1 2625
Protoss_Cybernetics_Core 1 3343
Protoss_Dragoon 8 9301
Protoss_Robotics_Facility 1 7533
Protoss_Observatory 1 8834
Protoss_Observer 1 9451
9451
