Protoss_Nexus 3 8720
Protoss_Gateway 3 6950
Protoss_Assimilator 2 9979
Protoss_Cybernetics_Core 1 4109
Protoss_Zealot 1 4906
Protoss_Dragoon 8 8246
Protoss_Robotics_Facility 1 7293
Protoss_Shuttle 1 8621
Protoss_Robotics_Support_Bay 1 8818
Protoss_Observatory 1 9156
Protoss_Reaver 1 9523
9979
