Protoss_Nexus 2 8068
Protoss_Gateway 3 9992
Protoss_Assimilator 1 2623
Protoss_Cybernetics_Core 1 3318
Protoss_Dragoon 11 9471
Protoss_Robotics_Facility 1 6868
Protoss_Observatory 1 8248
Protoss_Observer 2 9428
9992
