Protoss_Nexus 1 0
Protoss_Gateway 2 3476
Protoss_Assimilator 1 2371
Protoss_Cybernetics_Core 1 2911
Protoss_Dragoon 9 7749
Protoss_Robotics_Facility 1 6573
Protoss_Shuttle 1 8025
Protoss_Robotics_Support_Bay 1 8207
Protoss_Reaver 1 8927
Protoss_Zealot 2 9289
9289
