Protoss_Nexus 2 7249
Protoss_Gateway 3 8381
Protoss_Assimilator 2 9487
Protoss_Cybernetics_Core 1 2893
Protoss_Dragoon 11 9865
Protoss_Robotics_Facility 1 5307
Protoss_Observatory 1 6644
Protoss_Observer 4 9701
Protoss_Citadel_of_Adun 1 8279
Protoss_Templar_Archives 1 9514
9865
