Protoss_Nexus 2 8203
Protoss_Gateway 2 5493
Protoss_Assimilator 2 9393
Protoss_Cybernetics_Core 1 2903
Protoss_Dragoon 7 9183
Protoss_Citadel_of_Adun 1 5049
Protoss_Robotics_Facility 1 5279
Protoss_Templar_Archives 1 6078
Protoss_Zealot 3 9481
Protoss_Shuttle 2 9331
Protoss_Dark_Templar 2 7211
Protoss_Observatory 1 8692
Protoss_Robotics_Support_Bay 1 9523
Protoss_Forge 1 9929
9929
