Protoss_Nexus 2 7080
Protoss_Gateway 5 8270
Protoss_Assimilator 2 9169
Protoss_Cybernetics_Core 1 3102
Protoss_Dragoon 8 8633
Protoss_Robotics_Facility 1 7829
Protoss_Observatory 1 9329
Protoss_Zealot 3 9603
Protoss_Shuttle 1 9899
9899
