Protoss_Nexus 3 9743
Protoss_Forge 1 2787
Protoss_Photon_Cannon 6 8899
Protoss_Assimilator 1 5786
Protoss_Gateway 1 6070
Protoss_Cybernetics_Core 1 7139
Protoss_Stargate 2 8215
Protoss_Scout 2 9356
9743
