Protoss_Nexus 2 7293
Protoss_Gateway 2 8632
Protoss_Assimilator 1 2475
Protoss_Zealot 3 9863
Protoss_Cybernetics_Core 1 3663
Protoss_Dragoon 6 9139
Protoss_Robotics_Facility 1 5635
Protoss_Observatory 1 6947
Protoss_Observer 2 8089
Protoss_Shuttle 1 8691
Protoss_Robotics_Support_Bay 1 8751
Protoss_Reaver 1 9653
9863
