Protoss_Nexus 2 7845
Protoss_Gateway 2 3473
Protoss_Assimilator 1 2408
Protoss_Cybernetics_Core 1 3047
Protoss_Dragoon 12 9266
Protoss_Zealot 2 8261
Protoss_Robotics_Facility 1 8844
9266
