Protoss_Nexus 2 9593
Protoss_Gateway 2 6858
Protoss_Assimilator 1 2603
Protoss_Cybernetics_Core 1 3273
Protoss_Dragoon 9 9923
Protoss_Robotics_Facility 1 6163
Protoss_Shuttle 1 7521
Protoss_Zealot 4 8448
Protoss_Observatory 1 8309
Protoss_Observer 1 9116
9923
