Protoss_Nexus 2 9771
Protoss_Gateway 1 1935
Protoss_Assimilator 1 2475
Protoss_Cybernetics_Core 1 3097
Protoss_Zealot 1 3211
Protoss_Dragoon 7 9332
Protoss_Robotics_Facility 1 5017
Protoss_Observatory 1 6499
Protoss_Observer 2 7673
Protoss_Shuttle 1 8531
Protoss_Citadel_of_Adun 1 9840
9840
