Protoss_Nexus 2 9895
Protoss_Gateway 2 6499
Protoss_Assimilator 1 2488
Protoss_Cybernetics_Core 1 3084
Protoss_Dragoon 3 9346
Protoss_Robotics_Facility 1 4984
Protoss_Citadel_of_Adun 1 5312
Protoss_Templar_Archives 1 6330
Protoss_Observatory 1 6759
Protoss_Observer 1 7301
Protoss_Dark_Templar 4 8571
Protoss_Shuttle 1 7903
9895
