Protoss_Gateway 2 7171
Protoss_Assimilator 1 3110
Protoss_Cybernetics_Core 1 3984
Protoss_Dragoon 10 10712
Protoss_Robotics_Facility 1 5920
Protoss_Observatory 1 6529
Protoss_Observer 2 8708
Protoss_Zealot 1 7468
Protoss_Shuttle 1 10237
10712
