Protoss_Assimilator 1 2395
Protoss_Gateway 3 8915
Protoss_Cybernetics_Core 1 4248
Protoss_Dragoon 12 10605
Protoss_Robotics_Facility 1 5974
Protoss_Observatory 1 6621
Protoss_Observer 3 9938
Protoss_Forge 1 9879
10605
