Protoss_Gateway 3 9444
Protoss_Assimilator 2 10276
Protoss_Cybernetics_Core 1 4077
Protoss_Dragoon 7 9548
Protoss_Robotics_Facility 1 5838
Protoss_Nexus 1 8025
Protoss_Observatory 1 6878
Protoss_Observer 3 10348
Protoss_Citadel_of_Adun 1 10609
10609
