Protoss_Assimilator 1 2215
Protoss_Gateway 3 7149
Protoss_Cybernetics_Core 1 4169
Protoss_Robotics_Facility 1 5502
Protoss_Dragoon 4 9913
Protoss_Observatory 1 6072
Protoss_Observer 2 7365
Protoss_Shuttle 2 9168
Protoss_Zealot 6 8968
Protoss_Robotics_Support_Bay 1 9421
Protoss_Reaver 1 10576
Protoss_Citadel_of_Adun 1 10729
10729
