Protoss_Gateway 2 7879
Protoss_Assimilator 1 3003
Protoss_Cybernetics_Core 1 3944
Protoss_Dragoon 11 10595
Protoss_Robotics_Facility 1 6217
Protoss_Observatory 1 6812
Protoss_Observer 2 8110
10595
