Protoss_Assimilator 2 5075
Protoss_Gateway 3 10519
Protoss_Cybernetics_Core 1 4178
Protoss_Robotics_Facility 1 5500
Protoss_Dragoon 9 10268
Protoss_Observatory 1 6198
Protoss_Observer 2 7525
Protoss_Shuttle 2 9452
Protoss_Zealot 2 9140
10519
