Protoss_Gateway 3 9841
Protoss_Zealot 5 5263
Protoss_Assimilator 1 5506
Protoss_Cybernetics_Core 1 6174
Protoss_Dragoon 6 10118
Protoss_Robotics_Facility 1 8437
Protoss_Observatory 1 9276
Protoss_Observer 1 10288
10288
