Protoss_Gateway 2 7732
Protoss_Assimilator 1 3165
Protoss_Cybernetics_Core 1 4087
Protoss_Dragoon 6 9888
Protoss_Robotics_Facility 1 6019
Protoss_Observatory 1 6701
Protoss_Observer 3 9845
9888
