Protoss_Gateway 4 10204
Protoss_Assimilator 1 3145
Protoss_Cybernetics_Core 1 4565
Protoss_Dragoon 10 10518
Protoss_Robotics_Facility 1 6977
Protoss_Observatory 1 7580
Protoss_Observer 2 8905
Protoss_Nexus 1 10593
10593
