Protoss_Gateway 3 6954
Protoss_Assimilator 1 3110
Protoss_Cybernetics_Core 1 4072
Protoss_Robotics_Facility 1 5545
Protoss_Dragoon 5 8398
Protoss_Observatory 1 6258
Protoss_Observer 2 8083
Protoss_Shuttle 1 8984
Protoss_Zealot 3 9008
Protoss_Nexus 2 11687
11687
