Protoss_Gateway 2 7318
Protoss_Assimilator 1 3050
Protoss_Cybernetics_Core 1 4004
Protoss_Zealot 1 4308
Protoss_Dragoon 7 9165
Protoss_Robotics_Facility 1 8029
Protoss_Forge 1 8514
Protoss_Observatory 1 8681
Protoss_Observer 1 9373
Protoss_Nexus 1 11765
11765
