Protoss_Gateway 2 6988
Protoss_Assimilator 1 3075
Protoss_Cybernetics_Core 1 3954
Protoss_Dragoon 8 9618
Protoss_Nexus 2 11195
Protoss_Stargate 1 9273
Protoss_Forge 1 9384
Protoss_Photon_Cannon 1 10550
Protoss_Scout 1 11115
11195
