Protoss_Gateway 3 9710
Protoss_Assimilator 1 2966
Protoss_Cybernetics_Core 1 3994
Protoss_Dragoon 9 10558
Protoss_Nexus 1 8376
Protoss_Robotics_Facility 1 8852
Protoss_Zealot 2 10013
Protoss_Shuttle 1 10052
Protoss_Observatory 1 10219
Protoss_Citadel_of_Adun 1 10853
10853
