Protoss_Nexus 2 5943
Protoss_Assimilator 2 5170
Protoss_Gateway 3 8612
Protoss_Cybernetics_Core 1 6706
Protoss_Robotics_Facility 2 8707
Protoss_Dragoon 8 10156
Protoss_Shuttle 1 9069
Protoss_Observatory 1 8676
Protoss_Robotics_Support_Bay 1 9549
10156
