Protoss_Gateway 2 8566
Protoss_Assimilator 1 3014
Protoss_Cybernetics_Core 1 4149
Protoss_Dragoon 5 10263
Protoss_Robotics_Facility 1 6257
Protoss_Robotics_Support_Bay 1 6821
Protoss_Shuttle 1 7407
Protoss_Reaver 1 8458
Protoss_Observatory 1 7977
Protoss_Observer 1 9062
10263
