Protoss_Assimilator 1 2360
Protoss_Gateway 2 10076
Protoss_Cybernetics_Core 1 4234
Protoss_Zealot 4 6708
Protoss_Robotics_Facility 1 5682
Protoss_Shuttle 1 6817
Protoss_Robotics_Support_Bay 1 6936
Protoss_Reaver 1 8151
Protoss_Observatory 1 7689
Protoss_Dragoon 3 10098
Protoss_Observer 3 10175
10175
