Protoss_Gateway 2 8028
Protoss_Assimilator 1 2926
Protoss_Cybernetics_Core 1 4037
Protoss_Dragoon 4 10023
Protoss_Stargate 1 6061
Protoss_Citadel_of_Adun 1 6733
Protoss_Scout 1 7505
Protoss_Templar_Archives 1 8193
Protoss_Dark_Templar 4 10063
10063
