Protoss_Gateway 3 8874
Protoss_Assimilator 1 3179
Protoss_Cybernetics_Core 1 4209
Protoss_Dragoon 10 10333
Protoss_Robotics_Facility 1 6905
Protoss_Observatory 1 7519
Protoss_Observer 1 8223
10333
