Protoss_Gateway 2 6482
Protoss_Assimilator 1 3040
Protoss_Cybernetics_Core 1 4115
Protoss_Dragoon 8 9348
Protoss_Robotics_Facility 1 6407
Protoss_Observatory 1 6987
Protoss_Observer 3 9142
Protoss_Nexus 1 11316
Protoss_Shuttle 1 10489
11316
