Protoss_Gateway 2 7520
Protoss_Assimilator 1 3003
Protoss_Cybernetics_Core 1 4013
Protoss_Robotics_Facility 1 5527
Protoss_Dragoon 5 10351
Protoss_Observatory 1 6466
Protoss_Observer 1 7378
10351
