Protoss_Gateway 1 2865
Protoss_Assimilator 1 2918
Protoss_Cybernetics_Core 1 4066
Protoss_Robotics_Facility 1 5402
Protoss_Dragoon 4 9378
Protoss_Zealot 4 7074
Protoss_Shuttle 1 7592
9378
