Protoss_Gateway 2 10896
Protoss_Assimilator 1 3155
Protoss_Cybernetics_Core 1 4199
Protoss_Robotics_Facility 1 5652
Protoss_Dragoon 4 10159
Protoss_Zealot 3 7903
Protoss_Shuttle 2 10802
Protoss_Robotics_Support_Bay 1 6666
Protoss_Reaver 1 7906
Protoss_Observatory 1 7971
Protoss_Observer 2 9285
10896
