Protoss_Gateway 4 10284
Protoss_Assimilator 1 2960
Protoss_Cybernetics_Core 1 4084
Protoss_Zealot 1 4258
Protoss_Dragoon 8 10463
Protoss_Robotics_Facility 1 7557
Protoss_Nexus 1 9990
Protoss_Observatory 1 8763
Protoss_Observer 2 10114
10463
