Protoss_Nexus 1 4787
Protoss_Gateway 3 8417
Protoss_Assimilator 2 8435
Protoss_Cybernetics_Core 1 5241
Protoss_Dragoon 9 10477
Protoss_Robotics_Facility 1 7121
Protoss_Forge 1 7469
Protoss_Observatory 1 7737
Protoss_Photon_Cannon 2 10203
Protoss_Observer 2 9098
10477
