Protoss_Gateway 3 6908
Protoss_Assimilator 1 2910
Protoss_Cybernetics_Core 1 3967
Protoss_Robotics_Facility 1 5303
Protoss_Dragoon 9 9620
Protoss_Observatory 1 5975
Protoss_Observer 3 7962
Protoss_Nexus 1 11391
11391
