Protoss_Gateway 3 7080
Protoss_Assimilator 1 3145
Protoss_Cybernetics_Core 1 4165
Protoss_Robotics_Facility 1 5612
Protoss_Dragoon 9 10283
Protoss_Observatory 1 6379
Protoss_Observer 4 10045
Protoss_Nexus 1 10480
10480
