Protoss_Gateway 2 8433
Protoss_Assimilator 1 2990
Protoss_Cybernetics_Core 1 4340
Protoss_Dragoon 6 9751
Protoss_Robotics_Facility 1 6980
Protoss_Observatory 1 7697
Protoss_Observer 3 10203
Protoss_Zealot 1 10028
10203
