Protoss_Gateway 2 5189
Protoss_Assimilator 2 3506
Protoss_Cybernetics_Core 1 4321
Protoss_Dragoon 13 10165
Protoss_Citadel_of_Adun 1 9515
Protoss_Nexus 1 11400
Protoss_Templar_Archives 1 10816
11400
