Protoss_Gateway 3 9434
Protoss_Assimilator 1 3010
Protoss_Cybernetics_Core 1 4153
Protoss_Dragoon 9 9748
Protoss_Robotics_Facility 1 6012
Protoss_Observatory 1 6629
Protoss_Observer 4 10388
Protoss_Nexus 1 9728
Protoss_Citadel_of_Adun 1 10415
10415
