Protoss_Gateway 2 6236
Protoss_Assimilator 1 2970
Protoss_Cybernetics_Core 1 3949
Protoss_Robotics_Facility 1 5499
Protoss_Dragoon 6 10386
Protoss_Observatory 1 6713
Protoss_Observer 4 9416
Protoss_Nexus 2 10575
10575
