Protoss_Gateway 3 8119
Protoss_Assimilator 1 2966
Protoss_Cybernetics_Core 1 3993
Protoss_Dragoon 6 9458
Protoss_Robotics_Facility 1 5807
Protoss_Observatory 1 6443
Protoss_Observer 1 7193
Protoss_Zealot 4 8533
Protoss_Shuttle 1 8477
Protoss_Nexus 1 11475
11475
