Protoss_Gateway 2 5560
Protoss_Assimilator 1 2929
Protoss_Cybernetics_Core 1 3865
Protoss_Zealot 1 4373
Protoss_Dragoon 6 7213
Protoss_Citadel_of_Adun 1 7744
Protoss_Robotics_Facility 1 8731
Protoss_Templar_Archives 1 9157
Protoss_Shuttle 1 10062
Protoss_Dark_Templar 2 10008
Protoss_Observatory 1 10134
10134
