Protoss_Gateway 2 7745
Protoss_Assimilator 1 3131
Protoss_Cybernetics_Core 1 4064
Protoss_Dragoon 10 10513
Protoss_Robotics_Facility 1 6886
Protoss_Observatory 1 7736
Protoss_Observer 2 9235
Protoss_Nexus 1 11156
11156
