Protoss_Gateway 2 9341
Protoss_Assimilator 1 2975
Protoss_Cybernetics_Core 1 4057
Protoss_Dragoon 7 9842
Protoss_Robotics_Facility 1 5892
Protoss_Shuttle 1 7072
Protoss_Observatory 1 6799
Protoss_Robotics_Support_Bay 1 7036
Protoss_Observer 2 10298
Protoss_Reaver 1 8923
Protoss_Nexus 1 11188
11188
