Protoss_Gateway 3 10732
Protoss_Assimilator 1 3151
Protoss_Cybernetics_Core 1 4074
Protoss_Dragoon 9 10188
Protoss_Robotics_Facility 1 5882
Protoss_Observatory 1 6616
Protoss_Observer 4 10030
Protoss_Nexus 2 11185
11185
