Protoss_Gateway 2 7124
Protoss_Assimilator 1 3059
Protoss_Cybernetics_Core 1 4079
Protoss_Dragoon 1 5043
Protoss_Robotics_Facility 1 5751
Protoss_Citadel_of_Adun 1 6436
Protoss_Shuttle 1 6757
Protoss_Templar_Archives 1 7429
Protoss_Dark_Templar 4 9040
Protoss_Nexus 2 11410
Protoss_Forge 1 10406
11410
