Protoss_Gateway 3 10879
Protoss_Assimilator 1 3212
Protoss_Cybernetics_Core 1 4181
Protoss_Dragoon 10 9628
Protoss_Robotics_Facility 1 7444
Protoss_Observatory 1 8150
Protoss_Observer 2 9728
Protoss_Nexus 1 11407
11407
