Protoss_Gateway 2 9089
Protoss_Assimilator 1 3150
Protoss_Cybernetics_Core 1 4114
Protoss_Robotics_Facility 1 5467
Protoss_Dragoon 6 10512
Protoss_Zealot 2 6497
Protoss_Shuttle 1 6462
Protoss_Robotics_Support_Bay 1 6682
Protoss_Reaver 2 10316
10512
