Protoss_Gateway 2 7034
Protoss_Assimilator 1 3065
Protoss_Cybernetics_Core 1 3899
Protoss_Dragoon 5 10073
Protoss_Robotics_Facility 1 6754
Protoss_Observatory 1 7313
Protoss_Shuttle 1 7982
Protoss_Zealot 2 9948
Protoss_Robotics_Support_Bay 1 8041
Protoss_Observer 1 8585
Protoss_Nexus 1 10200
Protoss_Reaver 1 9746
10200
