Protoss_Gateway 2 8364
Protoss_Assimilator 1 3011
Protoss_Cybernetics_Core 1 3994
Protoss_Dragoon 5 8742
Protoss_Robotics_Facility 1 5787
Protoss_Nexus 1 7785
Protoss_Observatory 1 6640
Protoss_Observer 3 10555
Protoss_Shuttle 1 9952
10555
