Protoss_Gateway 2 8781
Protoss_Assimilator 1 2895
Protoss_Cybernetics_Core 1 3904
Protoss_Robotics_Facility 1 5357
Protoss_Dragoon 9 10553
Protoss_Observatory 1 6034
Protoss_Observer 1 6808
Protoss_Nexus 1 8909
Protoss_Shuttle 1 8502
Protoss_Robotics_Support_Bay 1 9096
10553
