Protoss_Gateway 2 6091
Protoss_Assimilator 1 3264
Protoss_Cybernetics_Core 1 4162
Protoss_Dragoon 11 10464
Protoss_Robotics_Facility 1 7424
Protoss_Observatory 1 8241
Protoss_Observer 2 9574
Protoss_Nexus 1 11703
11703
