Protoss_Gateway 3 10777
Protoss_Assimilator 1 3218
Protoss_Cybernetics_Core 1 4111
Protoss_Dragoon 9 10420
Protoss_Robotics_Facility 1 7104
Protoss_Observatory 1 7656
Protoss_Nexus 1 9437
Protoss_Observer 3 10592
Protoss_Forge 1 9747
10777
