Protoss_Gateway 2 8070
Protoss_Assimilator 1 2955
Protoss_Cybernetics_Core 1 4093
Protoss_Dragoon 7 10433
Protoss_Robotics_Facility 1 6767
Protoss_Observatory 1 7437
Protoss_Nexus 1 9805
Protoss_Observer 1 9073
Protoss_Shuttle 1 9974
10433
