Protoss_Gateway 3 10044
Protoss_Zealot 1 3478
Protoss_Assimilator 2 9410
Protoss_Cybernetics_Core 1 5765
Protoss_Nexus 1 7452
Protoss_Citadel_of_Adun 1 6842
Protoss_Templar_Archives 1 7882
Protoss_Dark_Templar 3 10257
10257
