Protoss_Gateway 2 8104
Protoss_Assimilator 1 2955
Protoss_Cybernetics_Core 1 3902
Protoss_Dragoon 2 5943
Protoss_Robotics_Facility 1 5856
Protoss_Observatory 1 6493
Protoss_Citadel_of_Adun 1 7040
Protoss_Zealot 4 9153
Protoss_Observer 2 7858
Protoss_Shuttle 2 10272
10272
