Protoss_Gateway 3 10552
Protoss_Assimilator 2 3515
Protoss_Zealot 6 6668
Protoss_Cybernetics_Core 1 6537
Protoss_Dragoon 7 10212
Protoss_Robotics_Facility 1 8786
Protoss_Observatory 1 9457
Protoss_Observer 1 10143
10552
