Protoss_Gateway 2 5616
Protoss_Assimilator 1 3297
Protoss_Cybernetics_Core 1 4689
Protoss_Dragoon 11 10742
Protoss_Robotics_Facility 1 8950
Protoss_Nexus 1 10817
Protoss_Observatory 1 9558
10817
