Protoss_Gateway 2 7167
Protoss_Assimilator 1 3102
Protoss_Cybernetics_Core 1 4046
Protoss_Dragoon 7 9843
Protoss_Robotics_Facility 1 5872
Protoss_Observatory 1 6421
Protoss_Observer 3 9548
Protoss_Nexus 1 10509
10509
