Protoss_Gateway 2 6130
Protoss_Assimilator 1 2924
Protoss_Cybernetics_Core 1 3930
Protoss_Robotics_Facility 1 5309
Protoss_Dragoon 9 10723
Protoss_Observatory 1 5966
Protoss_Observer 2 10446
Protoss_Shuttle 1 8239
10723
