Protoss_Gateway 3 8844
Protoss_Assimilator 1 2961
Protoss_Cybernetics_Core 1 3828
Protoss_Dragoon 9 9213
Protoss_Robotics_Facility 1 7237
Protoss_Observatory 1 7859
Protoss_Observer 2 9180
Protoss_Shuttle 1 10081
Protoss_Nexus 1 11315
Protoss_Citadel_of_Adun 1 10891
11315
