Protoss_Gateway 2 10607
Protoss_Assimilator 1 3190
Protoss_Cybernetics_Core 1 4120
Protoss_Dragoon 4 9365
Protoss_Robotics_Facility 1 5852
Protoss_Shuttle 1 6847
Protoss_Robotics_Support_Bay 1 6631
Protoss_Zealot 3 10088
Protoss_Reaver 1 8031
Protoss_Observatory 1 8067
Protoss_Observer 2 10283
10607
