Protoss_Assimilator 2 3609
Protoss_Gateway 2 6123
Protoss_Cybernetics_Core 1 4480
Protoss_Dragoon 7 10693
Protoss_Citadel_of_Adun 1 6779
Protoss_Templar_Archives 1 7779
Protoss_Dark_Templar 2 8718
Protoss_Robotics_Facility 1 10652
10693
