Protoss_Gateway 2 6477
Protoss_Assimilator 1 3138
Protoss_Cybernetics_Core 1 4150
Protoss_Dragoon 11 10696
Protoss_Robotics_Facility 1 7439
Protoss_Observatory 1 7992
Protoss_Observer 2 9292
Protoss_Shuttle 1 10193
Protoss_Nexus 1 11429
11429
