Protoss_Gateway 2 7684
Protoss_Assimilator 1 2995
Protoss_Cybernetics_Core 1 3875
Protoss_Dragoon 8 10583
Protoss_Robotics_Facility 1 6822
Protoss_Observatory 1 7478
Protoss_Nexus 1 9679
Protoss_Observer 3 9727
Protoss_Shuttle 1 10642
10642
