Protoss_Gateway 2 10544
Protoss_Assimilator 1 3185
Protoss_Cybernetics_Core 1 4286
Protoss_Zealot 1 4258
Protoss_Dragoon 4 8797
Protoss_Nexus 1 10440
Protoss_Citadel_of_Adun 1 10645
10645
