Protoss_Gateway 4 10324
Protoss_Assimilator 1 3129
Protoss_Cybernetics_Core 1 4032
Protoss_Dragoon 4 7863
Protoss_Robotics_Facility 1 5829
Protoss_Observatory 1 6456
Protoss_Observer 2 8323
Protoss_Nexus 1 10056
Protoss_Citadel_of_Adun 1 9395
Protoss_Shuttle 1 10017
Protoss_Templar_Archives 1 10489
10489
