Protoss_Gateway 2 8179
Protoss_Assimilator 1 2989
Protoss_Cybernetics_Core 1 4013
Protoss_Robotics_Facility 1 5342
Protoss_Dragoon 9 10700
Protoss_Shuttle 1 6527
Protoss_Observatory 1 6446
Protoss_Observer 2 8200
Protoss_Nexus 1 10312
10700
