Protoss_Gateway 2 8617
Protoss_Assimilator 1 3084
Protoss_Cybernetics_Core 1 4109
Protoss_Dragoon 5 10737
Protoss_Robotics_Facility 1 6071
Protoss_Zealot 2 7803
Protoss_Shuttle 1 7097
Protoss_Robotics_Support_Bay 1 6685
Protoss_Reaver 1 8148
Protoss_Observatory 1 7744
Protoss_Observer 2 10365
10737
