Protoss_Gateway 3 7555
Protoss_Assimilator 1 3152
Protoss_Cybernetics_Core 1 4103
Protoss_Dragoon 7 8764
Protoss_Robotics_Facility 1 6175
Protoss_Observatory 1 6735
Protoss_Observer 4 10114
Protoss_Nexus 2 11557
11557
