Protoss_Gateway 3 10818
Protoss_Assimilator 1 3035
Protoss_Cybernetics_Core 1 4074
Protoss_Zealot 1 4033
Protoss_Robotics_Facility 1 5727
Protoss_Dragoon 7 10692
Protoss_Observatory 1 6424
Protoss_Observer 3 9198
Protoss_Nexus 1 10025
10818
