Protoss_Gateway 2 6488
Protoss_Assimilator 1 3049
Protoss_Cybernetics_Core 1 3869
Protoss_Dragoon 7 10728
Protoss_Robotics_Facility 1 5767
Protoss_Zealot 3 10138
Protoss_Shuttle 2 8257
Protoss_Observatory 1 7011
Protoss_Robotics_Support_Bay 1 7423
Protoss_Reaver 1 9556
Protoss_Observer 1 10548
10728
