Protoss_Gateway 2 7423
Protoss_Assimilator 1 3402
Protoss_Cybernetics_Core 1 4309
Protoss_Dragoon 9 10603
Protoss_Robotics_Facility 1 7047
Protoss_Observatory 1 7644
Protoss_Observer 1 8698
Protoss_Nexus 2 11220
11220
