Protoss_Assimilator 1 2324
Protoss_Gateway 4 9999
Protoss_Cybernetics_Core 1 4213
Protoss_Robotics_Facility 1 5513
Protoss_Dragoon 8 10520
Protoss_Shuttle 2 8311
Protoss_Observatory 1 8045
Protoss_Observer 2 9516
Protoss_Nexus 1 11384
11384
