Protoss_Gateway 1 2963
Protoss_Assimilator 1 3205
Protoss_Cybernetics_Core 1 4085
Protoss_Dragoon 6 10614
Protoss_Robotics_Facility 1 6082
Protoss_Zealot 2 7018
Protoss_Shuttle 1 7107
Protoss_Robotics_Support_Bay 1 6799
Protoss_Reaver 2 9606
Protoss_Observatory 1 10127
10614
