Protoss_Gateway 4 9962
Protoss_Assimilator 3 3550
Protoss_Cybernetics_Core 1 4221
Protoss_Dragoon 9 10383
Protoss_Nexus 1 8201
Protoss_Robotics_Facility 1 8532
Protoss_Observatory 1 9148
Protoss_Observer 2 10435
10435
