Protoss_Gateway 2 7515
Protoss_Assimilator 1 3247
Protoss_Cybernetics_Core 1 3930
Protoss_Dragoon 9 10468
Protoss_Robotics_Facility 1 7182
Protoss_Observatory 1 7731
Protoss_Zealot 1 8243
Protoss_Observer 2 9025
Protoss_Nexus 1 11776
11776
