Protoss_Gateway 2 6484
Protoss_Assimilator 1 3165
Protoss_Cybernetics_Core 1 4210
Protoss_Dragoon 8 9703
Protoss_Robotics_Facility 1 7515
Protoss_Observatory 1 8116
Protoss_Nexus 1 9947
Protoss_Observer 2 9425
Protoss_Robotics_Support_Bay 1 9806
Protoss_Zealot 2 10538
10538
