Protoss_Gateway 2 7432
Protoss_Assimilator 1 3125
Protoss_Zealot 1 3618
Protoss_Cybernetics_Core 1 4461
Protoss_Dragoon 10 10041
Protoss_Robotics_Facility 1 5923
Protoss_Observatory 1 6521
Protoss_Observer 2 7938
Protoss_Citadel_of_Adun 1 10134
Protoss_Nexus 1 11190
11190
