Protoss_Gateway 5 10834
Protoss_Assimilator 1 3075
Protoss_Cybernetics_Core 1 3969
Protoss_Dragoon 6 10378
Protoss_Nexus 2 11010
Protoss_Robotics_Facility 1 8432
Protoss_Observatory 1 9366
Protoss_Observer 1 10153
11010
