Protoss_Gateway 1 3101
Protoss_Assimilator 1 3115
Protoss_Cybernetics_Core 1 4109
Protoss_Dragoon 5 9968
Protoss_Robotics_Facility 1 6876
Protoss_Shuttle 1 7977
Protoss_Robotics_Support_Bay 1 7880
Protoss_Reaver 1 9101
Protoss_Zealot 1 8783
Protoss_Observatory 1 9246
Protoss_Observer 2 10550
10550
