Protoss_Gateway 2 6161
Protoss_Assimilator 1 3003
Protoss_Cybernetics_Core 1 4111
Protoss_Dragoon 9 9752
Protoss_Robotics_Facility 1 6002
Protoss_Observatory 1 6551
Protoss_Observer 2 7840
Protoss_Shuttle 1 10247
Protoss_Zealot 2 10354
10354
