Protoss_Gateway 3 7983
Protoss_Assimilator 1 3267
Protoss_Cybernetics_Core 1 4195
Protoss_Dragoon 8 10248
Protoss_Robotics_Facility 1 7036
Protoss_Observatory 1 7730
Protoss_Shuttle 1 8347
Protoss_Observer 1 8950
Protoss_Robotics_Support_Bay 1 8836
Protoss_Zealot 1 10402
10402
