Protoss_Gateway 3 10357
Protoss_Assimilator 1 3170
Protoss_Cybernetics_Core 1 4040
Protoss_Dragoon 10 10478
Protoss_Robotics_Facility 1 5986
Protoss_Observatory 1 6834
Protoss_Observer 3 8945
Protoss_Nexus 1 10415
10478
