Protoss_Gateway 2 7304
Protoss_Assimilator 1 3050
Protoss_Cybernetics_Core 1 4004
Protoss_Dragoon 7 10563
Protoss_Robotics_Facility 1 7412
Protoss_Observatory 1 8006
Protoss_Shuttle 1 8717
Protoss_Zealot 2 8813
10563
