Protoss_Gateway 2 7454
Protoss_Assimilator 1 3075
Protoss_Cybernetics_Core 1 3859
Protoss_Zealot 2 10148
Protoss_Dragoon 8 10223
Protoss_Robotics_Facility 1 7062
Protoss_Observatory 1 7736
Protoss_Observer 2 9108
Protoss_Nexus 1 11035
11035
