Protoss_Assimilator 2 3603
Protoss_Gateway 1 3291
Protoss_Zealot 3 5422
Protoss_Cybernetics_Core 1 4819
Protoss_Robotics_Facility 1 6453
Protoss_Dragoon 3 7430
Protoss_Shuttle 1 7439
Protoss_Robotics_Support_Bay 1 7195
Protoss_Reaver 2 10228
10228
