Protoss_Gateway 2 7482
Protoss_Assimilator 1 3269
Protoss_Cybernetics_Core 1 4160
Protoss_Dragoon 10 10393
Protoss_Robotics_Facility 1 7332
Protoss_Observatory 1 7979
Protoss_Observer 2 9988
Protoss_Nexus 1 10790
10790
