Protoss_Gateway 2 6530
Protoss_Assimilator 1 2782
Protoss_Zealot 3 5025
Protoss_Cybernetics_Core 1 4494
Protoss_Robotics_Facility 1 5983
Protoss_Dragoon 3 10573
Protoss_Shuttle 1 7992
Protoss_Robotics_Support_Bay 1 7907
Protoss_Observatory 1 8536
Protoss_Reaver 1 9401
Protoss_Nexus 1 10960
Protoss_Observer 1 10005
Protoss_Citadel_of_Adun 1 10614
10960
