Protoss_Assimilator 1 2511
Protoss_Gateway 1 3289
Protoss_Cybernetics_Core 1 4314
Protoss_Robotics_Facility 1 5656
Protoss_Dragoon 6 10305
Protoss_Robotics_Support_Bay 1 6237
Protoss_Observatory 1 6294
Protoss_Observer 1 7138
Protoss_Shuttle 2 10299
Protoss_Reaver 1 9396
10305
