Protoss_Gateway 3 10078
Protoss_Assimilator 1 3059
Protoss_Cybernetics_Core 1 3953
Protoss_Zealot 4 5997
Protoss_Dragoon 7 9848
Protoss_Robotics_Facility 1 8655
Protoss_Observatory 1 9828
Protoss_Observer 1 10588
Protoss_Nexus 1 11792
11792
