Protoss_Gateway 2 6979
Protoss_Assimilator 1 3121
Protoss_Cybernetics_Core 1 4089
Protoss_Robotics_Facility 1 5640
Protoss_Dragoon 7 10463
Protoss_Observatory 1 6396
Protoss_Observer 3 10365
Protoss_Nexus 2 10886
Protoss_Shuttle 1 9762
Protoss_Citadel_of_Adun 1 10250
10886
