Protoss_Gateway 3 9176
Protoss_Assimilator 1 3190
Protoss_Cybernetics_Core 1 4086
Protoss_Dragoon 9 10368
Protoss_Citadel_of_Adun 1 6483
Protoss_Templar_Archives 1 7543
Protoss_Dark_Templar 2 8563
Protoss_Nexus 1 9919
Protoss_Robotics_Facility 1 10137
10368
