Protoss_Gateway 4 10885
Protoss_Assimilator 1 3184
Protoss_Cybernetics_Core 1 4053
Protoss_Robotics_Facility 1 5585
Protoss_Dragoon 6 8961
Protoss_Observatory 1 6157
Protoss_Observer 4 9852
Protoss_Nexus 2 10867
10885
