Protoss_Gateway 2 5649
Protoss_Assimilator 2 4320
Protoss_Cybernetics_Core 1 3994
Protoss_Dragoon 8 9838
Protoss_Forge 1 5848
Protoss_Robotics_Facility 1 7917
Protoss_Photon_Cannon 1 8375
Protoss_Observatory 1 8659
Protoss_Robotics_Support_Bay 1 9106
Protoss_Shuttle 1 10262
10262
