Protoss_Gateway 3 9469
Protoss_Assimilator 1 2943
Protoss_Cybernetics_Core 1 3844
Protoss_Zealot 3 10333
Protoss_Dragoon 6 8793
Protoss_Nexus 1 9023
Protoss_Robotics_Facility 1 8834
Protoss_Shuttle 1 10042
Protoss_Observatory 1 9774
Protoss_Robotics_Support_Bay 1 9871
10333
