Protoss_Gateway 2 7734
Protoss_Assimilator 1 3080
Protoss_Cybernetics_Core 1 4062
Protoss_Dragoon 9 9414
Protoss_Robotics_Facility 1 6616
Protoss_Observatory 1 7176
Protoss_Observer 2 8530
Protoss_Shuttle 1 10207
Protoss_Nexus 1 11415
Protoss_Zealot 2 10543
11415
