Protoss_Gateway 2 10174
Protoss_Assimilator 1 3135
Protoss_Cybernetics_Core 1 3878
Protoss_Zealot 1 3848
Protoss_Dragoon 6 9923
Protoss_Robotics_Facility 1 5867
Protoss_Shuttle 1 6892
Protoss_Robotics_Support_Bay 1 6781
Protoss_Reaver 1 8221
Protoss_Observatory 1 8661
Protoss_Observer 1 9953
10174
