Protoss_Gateway 3 9090
Protoss_Assimilator 1 3051
Protoss_Cybernetics_Core 1 4029
Protoss_Dragoon 11 10700
Protoss_Nexus 1 8080
Protoss_Robotics_Facility 1 8207
Protoss_Observatory 1 8892
Protoss_Observer 2 10240
10700
