Protoss_Gateway 3 10066
Protoss_Assimilator 1 3179
Protoss_Cybernetics_Core 1 4279
Protoss_Robotics_Facility 1 5674
Protoss_Dragoon 6 9288
Protoss_Observatory 1 6329
Protoss_Observer 3 8788
Protoss_Nexus 1 10127
Protoss_Citadel_of_Adun 1 9661
10127
