Protoss_Gateway 3 8849
Protoss_Assimilator 1 3416
Protoss_Zealot 4 9603
Protoss_Cybernetics_Core 1 4877
Protoss_Dragoon 7 10693
Protoss_Robotics_Facility 1 7387
Protoss_Observatory 1 8038
Protoss_Shuttle 1 8722
10693
