Protoss_Gateway 3 10498
Protoss_Assimilator 1 3020
Protoss_Cybernetics_Core 1 4089
Protoss_Robotics_Facility 1 5457
Protoss_Dragoon 9 10013
Protoss_Observatory 1 6096
Protoss_Observer 3 9600
Protoss_Nexus 1 9807
Protoss_Shuttle 1 10807
10807
