Protoss_Gateway 4 10264
Protoss_Assimilator 1 3070
Protoss_Cybernetics_Core 1 3934
Protoss_Robotics_Facility 1 5501
Protoss_Dragoon 6 10718
Protoss_Observatory 1 6286
Protoss_Observer 2 8538
Protoss_Nexus 2 10522
10718
