Protoss_Gateway 2 6860
Protoss_Assimilator 1 3211
Protoss_Zealot 2 9230
Protoss_Cybernetics_Core 1 4457
Protoss_Dragoon 8 10128
Protoss_Robotics_Facility 1 7922
Protoss_Shuttle 1 9057
Protoss_Observatory 1 9010
Protoss_Observer 1 9993
10128
