Protoss_Gateway 2 9064
Protoss_Assimilator 1 3115
Protoss_Cybernetics_Core 1 4014
Protoss_Zealot 2 8538
Protoss_Dragoon 7 10713
Protoss_Robotics_Facility 1 7062
Protoss_Shuttle 1 8387
Protoss_Robotics_Support_Bay 1 8104
Protoss_Reaver 1 9501
Protoss_Observatory 1 9705
Protoss_Observer 1 10508
10713
