Protoss_Gateway 3 8074
Protoss_Assimilator 1 3075
Protoss_Cybernetics_Core 1 3951
Protoss_Dragoon 8 9378
Protoss_Robotics_Facility 1 6762
Protoss_Observatory 1 7311
Protoss_Observer 2 8668
Protoss_Shuttle 1 10142
Protoss_Zealot 2 10248
10248
