Protoss_Gateway 2 3068
Protoss_Zealot 3 4028
Protoss_Assimilator 1 4658
Protoss_Cybernetics_Core 1 5419
Protoss_Dragoon 8 10053
Protoss_Nexus 1 10061
Protoss_Robotics_Facility 1 10152
10152
