Protoss_Gateway 3 10322
Protoss_Assimilator 1 2965
Protoss_Cybernetics_Core 1 4145
Protoss_Dragoon 1 5018
Protoss_Citadel_of_Adun 1 5450
Protoss_Templar_Archives 1 6522
Protoss_Dark_Templar 9 10673
Protoss_Forge 1 7970
Protoss_Photon_Cannon 1 10040
10673
