Protoss_Gateway 2 8484
Protoss_Assimilator 1 3264
Protoss_Cybernetics_Core 1 4150
Protoss_Zealot 1 4043
Protoss_Dragoon 9 10486
Protoss_Robotics_Facility 1 6986
Protoss_Observatory 1 7571
Protoss_Observer 2 9278
Protoss_Nexus 1 10960
10960
