Protoss_Gateway 2 9209
Protoss_Assimilator 1 3026
Protoss_Cybernetics_Core 1 4124
Protoss_Zealot 1 4008
Protoss_Dragoon 6 10483
Protoss_Robotics_Facility 1 6882
Protoss_Observatory 1 7563
Protoss_Nexus 1 8951
Protoss_Observer 3 9550
Protoss_Shuttle 1 10451
10483
