Protoss_Gateway 5 9134
Protoss_Assimilator 1 3042
Protoss_Cybernetics_Core 1 4019
Protoss_Dragoon 6 9523
Protoss_Nexus 1 8005
Protoss_Robotics_Facility 1 8197
Protoss_Observatory 1 8838
Protoss_Shuttle 1 9492
Protoss_Zealot 6 10283
10283
