Protoss_Gateway 2 7426
Protoss_Assimilator 1 3056
Protoss_Cybernetics_Core 1 4031
Protoss_Dragoon 5 10728
Protoss_Robotics_Facility 1 5877
Protoss_Citadel_of_Adun 1 6314
Protoss_Observatory 1 6449
Protoss_Observer 1 7138
Protoss_Templar_Archives 1 8041
Protoss_Shuttle 1 8152
Protoss_Dark_Templar 2 8923
10728
