Protoss_Gateway 2 7313
Protoss_Assimilator 1 3029
Protoss_Cybernetics_Core 1 4143
Protoss_Dragoon 11 10565
Protoss_Robotics_Facility 1 6959
Protoss_Observatory 1 7604
Protoss_Observer 3 9592
Protoss_Nexus 1 10518
10565
