Protoss_Gateway 2 5812
Protoss_Assimilator 1 3046
Protoss_Cybernetics_Core 1 3919
Protoss_Zealot 1 3848
Protoss_Dragoon 4 10663
Protoss_Citadel_of_Adun 1 6737
Protoss_Robotics_Facility 1 7942
Protoss_Templar_Archives 1 7748
Protoss_Dark_Templar 4 9360
Protoss_Shuttle 1 8932
Protoss_Forge 2 9877
Protoss_Observatory 1 10044
10663
