Protoss_Gateway 3 10782
Protoss_Assimilator 1 3175
Protoss_Cybernetics_Core 1 4044
Protoss_Dragoon 7 9358
Protoss_Robotics_Facility 1 6969
Protoss_Observatory 1 7596
Protoss_Observer 2 8895
Protoss_Nexus 2 11581
11581
