Protoss_Gateway 2 7321
Protoss_Assimilator 1 3040
Protoss_Cybernetics_Core 1 3981
Protoss_Dragoon 10 9674
Protoss_Robotics_Facility 1 7104
Protoss_Observatory 1 7649
Protoss_Observer 2 8930
Protoss_Nexus 1 11174
Protoss_Shuttle 1 10359
Protoss_Zealot 2 10294
Protoss_Robotics_Support_Bay 1 10401
11174
