Protoss_Gateway 3 9980
Protoss_Assimilator 1 2953
Protoss_Cybernetics_Core 1 3784
Protoss_Dragoon 12 10437
Protoss_Robotics_Facility 1 5630
Protoss_Observatory 1 6494
Protoss_Observer 5 10333
Protoss_Nexus 1 9505
10437
