Protoss_Nexus 1 4857
Protoss_Gateway 2 7575
Protoss_Forge 1 4953
Protoss_Zealot 2 5780
Protoss_Photon_Cannon 4 9775
Protoss_Assimilator 1 6480
Protoss_Cybernetics_Core 1 7149
Protoss_Dragoon 7 10350
10350
