Protoss_Gateway 2 7386
Protoss_Assimilator 1 3118
Protoss_Cybernetics_Core 1 4079
Protoss_Dragoon 4 10018
Protoss_Robotics_Facility 1 6089
Protoss_Observatory 1 6775
Protoss_Robotics_Support_Bay 1 7327
Protoss_Observer 1 7513
Protoss_Shuttle 1 8427
Protoss_Reaver 1 9478
Protoss_Zealot 2 9043
10018
