Protoss_Gateway 3 8221
Protoss_Assimilator 1 2978
Protoss_Cybernetics_Core 1 3800
Protoss_Dragoon 9 10330
Protoss_Robotics_Facility 1 7607
Protoss_Zealot 4 9162
Protoss_Observatory 1 8296
Protoss_Shuttle 1 9079
Protoss_Observer 1 9682
10330
