Protoss_Gateway 2 6477
Protoss_Assimilator 1 3091
Protoss_Cybernetics_Core 1 4121
Protoss_Dragoon 5 7828
Protoss_Robotics_Facility 1 7782
Protoss_Citadel_of_Adun 1 8544
Protoss_Observatory 1 8384
Protoss_Zealot 7 10243
Protoss_Observer 2 9745
10243
