Protoss_Assimilator 2 9810
Protoss_Gateway 2 5646
Protoss_Cybernetics_Core 1 4221
Protoss_Robotics_Facility 1 5528
Protoss_Shuttle 1 6513
Protoss_Observatory 1 6417
Protoss_Dragoon 8 9634
Protoss_Observer 2 7860
Protoss_Nexus 1 10240
Protoss_Citadel_of_Adun 1 10181
Protoss_Zealot 2 10486
10486
