Protoss_Gateway 3 10619
Protoss_Assimilator 1 3128
Protoss_Cybernetics_Core 1 4129
Protoss_Dragoon 5 8418
Protoss_Robotics_Facility 1 7079
Protoss_Shuttle 1 8067
Protoss_Robotics_Support_Bay 1 8092
Protoss_Reaver 1 9236
Protoss_Observatory 1 8727
Protoss_Zealot 2 9545
Protoss_Nexus 1 10610
Protoss_Observer 1 9943
10619
