Protoss_Nexus 1 4405
Protoss_Gateway 3 8239
Protoss_Assimilator 1 4000
Protoss_Cybernetics_Core 1 5077
Protoss_Zealot 1 5046
Protoss_Dragoon 10 10474
Protoss_Robotics_Facility 1 9029
Protoss_Observatory 1 9622
Protoss_Observer 1 10366
10474
