Protoss_Gateway 3 7575
Protoss_Assimilator 1 3075
Protoss_Cybernetics_Core 1 4098
Protoss_Dragoon 8 10248
Protoss_Citadel_of_Adun 1 6349
Protoss_Templar_Archives 1 7395
Protoss_Dark_Templar 2 9703
Protoss_Robotics_Facility 1 11057
11057
