Protoss_Gateway 4 10109
Protoss_Assimilator 1 3198
Protoss_Cybernetics_Core 1 4089
Protoss_Dragoon 10 10387
Protoss_Nexus 1 8583
Protoss_Robotics_Facility 1 8848
Protoss_Observatory 1 9453
Protoss_Observer 1 10308
Protoss_Zealot 1 10353
10387
