Protoss_Gateway 1 2840
Protoss_Assimilator 1 3103
Protoss_Zealot 1 3708
Protoss_Cybernetics_Core 1 4811
Protoss_Dragoon 2 8383
Protoss_Citadel_of_Adun 1 5909
Protoss_Forge 1 10015
10015
