Protoss_Gateway 1 2947
Protoss_Assimilator 1 3213
Protoss_Cybernetics_Core 1 4217
Protoss_Dragoon 6 10359
Protoss_Citadel_of_Adun 1 5664
Protoss_Nexus 1 8595
Protoss_Robotics_Facility 1 10797
10797
