Protoss_Gateway 2 7983
Protoss_Assimilator 1 3302
Protoss_Cybernetics_Core 1 4219
Protoss_Dragoon 7 8828
Protoss_Robotics_Facility 1 5986
Protoss_Observatory 1 6572
Protoss_Observer 3 8700
Protoss_Nexus 2 11200
11200
