Protoss_Gateway 2 4385
Protoss_Assimilator 2 3200
Protoss_Zealot 5 6863
Protoss_Cybernetics_Core 1 6259
Protoss_Robotics_Facility 1 7892
Protoss_Dragoon 5 10713
Protoss_Robotics_Support_Bay 1 9351
Protoss_Citadel_of_Adun 1 10038
10713
