Protoss_Assimilator 1 2254
Protoss_Gateway 2 9522
Protoss_Cybernetics_Core 1 4226
Protoss_Zealot 4 6458
Protoss_Robotics_Facility 1 5548
Protoss_Shuttle 3 10508
Protoss_Robotics_Support_Bay 1 6791
Protoss_Observatory 1 6871
Protoss_Dragoon 5 10538
Protoss_Reaver 1 8101
Protoss_Observer 1 9607
10538
