Protoss_Gateway 2 7684
Protoss_Assimilator 1 2966
Protoss_Cybernetics_Core 1 4059
Protoss_Dragoon 7 9927
Protoss_Robotics_Facility 1 7008
Protoss_Shuttle 1 8002
Protoss_Zealot 4 9030
Protoss_Observatory 1 7799
Protoss_Observer 2 9613
Protoss_Robotics_Support_Bay 1 10215
10215
