Protoss_Assimilator 1 2390
Protoss_Gateway 2 6935
Protoss_Cybernetics_Core 1 4209
Protoss_Robotics_Facility 1 5612
Protoss_Dragoon 6 9788
Protoss_Observatory 1 6244
Protoss_Observer 3 9155
Protoss_Shuttle 1 8552
Protoss_Forge 1 8700
Protoss_Robotics_Support_Bay 1 8840
Protoss_Photon_Cannon 1 9677
Protoss_Reaver 1 10205
10205
