Protoss_Gateway 3 9724
Protoss_Assimilator 1 3136
Protoss_Cybernetics_Core 1 4084
Protoss_Robotics_Facility 1 5552
Protoss_Dragoon 8 10568
Protoss_Observatory 1 6294
Protoss_Nexus 1 8147
Protoss_Observer 3 8688
10568
