Protoss_Gateway 2 6620
Protoss_Assimilator 1 3219
Protoss_Cybernetics_Core 1 4252
Protoss_Dragoon 9 10713
Protoss_Robotics_Facility 1 6458
Protoss_Observatory 1 7299
Protoss_Observer 2 8798
Protoss_Shuttle 1 9699
Protoss_Nexus 1 11150
11150
