Protoss_Gateway 1 3074
Protoss_Assimilator 1 3205
Protoss_Cybernetics_Core 1 4195
Protoss_Dragoon 3 6895
Protoss_Robotics_Facility 1 6036
Protoss_Zealot 1 8328
Protoss_Shuttle 1 8687
8687
