Protoss_Gateway 2 6753
Protoss_Assimilator 1 3438
Protoss_Cybernetics_Core 1 4152
Protoss_Zealot 1 4183
Protoss_Dragoon 5 8353
Protoss_Citadel_of_Adun 1 7189
Protoss_Templar_Archives 1 8248
Protoss_Nexus 1 10313
Protoss_Dark_Templar 3 10488
Protoss_Robotics_Facility 1 10702
10702
