Protoss_Gateway 2 6754
Protoss_Assimilator 1 3149
Protoss_Cybernetics_Core 1 3944
Protoss_Dragoon 6 10113
Protoss_Robotics_Facility 1 6549
Protoss_Shuttle 1 7537
Protoss_Robotics_Support_Bay 1 7245
Protoss_Reaver 1 8671
Protoss_Observatory 1 8685
Protoss_Zealot 1 8973
Protoss_Observer 1 9393
10113
