Protoss_Gateway 3 10514
Protoss_Assimilator 2 10566
Protoss_Cybernetics_Core 1 4099
Protoss_Dragoon 5 9103
Protoss_Citadel_of_Adun 1 5515
Protoss_Templar_Archives 1 6576
Protoss_Dark_Templar 4 10073
Protoss_Robotics_Facility 1 8696
Protoss_Nexus 1 11434
11434
