Protoss_Gateway 2 7088
Protoss_Assimilator 1 3185
Protoss_Cybernetics_Core 1 3970
Protoss_Dragoon 4 9758
Protoss_Citadel_of_Adun 1 5924
Protoss_Templar_Archives 1 6919
Protoss_Robotics_Facility 1 7759
Protoss_Dark_Templar 3 8510
Protoss_Shuttle 1 8842
Protoss_Observatory 1 8826
Protoss_Observer 1 9558
Protoss_Nexus 1 11348
11348
