Protoss_Gateway 4 10323
Protoss_Assimilator 1 3030
Protoss_Cybernetics_Core 1 4122
Protoss_Robotics_Facility 1 5483
Protoss_Observatory 1 6064
Protoss_Dragoon 8 10274
Protoss_Observer 3 9122
Protoss_Shuttle 1 7917
Protoss_Nexus 1 10047
10323
