Protoss_Gateway 4 10874
Protoss_Assimilator 1 3303
Protoss_Zealot 1 3678
Protoss_Cybernetics_Core 1 4299
Protoss_Dragoon 7 10438
Protoss_Robotics_Facility 1 7351
Protoss_Observatory 1 7936
Protoss_Observer 2 9333
Protoss_Nexus 1 10734
Protoss_Shuttle 1 10332
10874
