Protoss_Gateway 2 5097
Protoss_Assimilator 1 2982
Protoss_Cybernetics_Core 1 4525
Protoss_Dragoon 6 9986
Protoss_Citadel_of_Adun 1 7545
Protoss_Robotics_Facility 1 8190
Protoss_Observatory 1 8770
Protoss_Zealot 2 9160
Protoss_Observer 2 10102
Protoss_Forge 1 10033
10102
