Protoss_Gateway 2 7018
Protoss_Assimilator 1 3330
Protoss_Cybernetics_Core 1 4194
Protoss_Dragoon 8 10698
Protoss_Robotics_Facility 1 6952
Protoss_Shuttle 1 7942
Protoss_Observatory 1 7574
Protoss_Observer 2 9263
Protoss_Citadel_of_Adun 1 8989
Protoss_Nexus 1 11228
11228
