Protoss_Gateway 3 7527
Protoss_Assimilator 1 3085
Protoss_Cybernetics_Core 1 4012
Protoss_Dragoon 9 10328
Protoss_Robotics_Facility 1 6743
Protoss_Observatory 1 7391
Protoss_Zealot 4 8628
Protoss_Observer 2 10183
Protoss_Shuttle 1 9277
10328
