Protoss_Gateway 2 8216
Protoss_Assimilator 1 3065
Protoss_Cybernetics_Core 1 4064
Protoss_Dragoon 7 9108
Protoss_Robotics_Facility 1 5924
Protoss_Observatory 1 6596
Protoss_Observer 3 9648
Protoss_Nexus 1 10622
Protoss_Zealot 2 10223
Protoss_Shuttle 1 10852
10852
