Protoss_Gateway 2 7042
Protoss_Assimilator 1 3257
Protoss_Cybernetics_Core 1 3994
Protoss_Dragoon 4 7993
Protoss_Robotics_Facility 1 6722
Protoss_Robotics_Support_Bay 1 7321
Protoss_Shuttle 1 7797
Protoss_Observatory 1 8975
8975
