Protoss_Gateway 2 5678
Protoss_Assimilator 1 2930
Protoss_Cybernetics_Core 1 3933
Protoss_Robotics_Facility 1 5224
Protoss_Dragoon 11 10092
Protoss_Observatory 1 5815
Protoss_Observer 3 9462
Protoss_Shuttle 1 7455
Protoss_Nexus 1 10571
10571
