Protoss_Gateway 2 9748
Protoss_Assimilator 1 3096
Protoss_Cybernetics_Core 1 3945
Protoss_Dragoon 3 10005
Protoss_Robotics_Facility 1 5842
Protoss_Shuttle 1 6942
Protoss_Robotics_Support_Bay 1 6686
Protoss_Reaver 2 9093
Protoss_Observatory 1 8398
Protoss_Observer 2 10585
10585
