Protoss_Gateway 2 7199
Protoss_Assimilator 1 3034
Protoss_Cybernetics_Core 1 3914
Protoss_Dragoon 8 9858
Protoss_Robotics_Facility 1 6936
Protoss_Observatory 1 7507
Protoss_Observer 2 8850
Protoss_Nexus 1 10495
10495
