Protoss_Gateway 2 7754
Protoss_Assimilator 1 3126
Protoss_Cybernetics_Core 1 4064
Protoss_Dragoon 6 10320
Protoss_Robotics_Facility 1 5946
Protoss_Observatory 1 6564
Protoss_Observer 3 8718
Protoss_Nexus 1 11052
11052
