Protoss_Assimilator 1 2510
Protoss_Gateway 3 10589
Protoss_Cybernetics_Core 1 4324
Protoss_Citadel_of_Adun 1 5344
Protoss_Robotics_Facility 1 5872
Protoss_Dragoon 3 9988
Protoss_Templar_Archives 1 6504
Protoss_Shuttle 1 7097
Protoss_Dark_Templar 3 8100
Protoss_Observatory 1 7639
Protoss_Observer 1 8563
Protoss_Nexus 1 10257
10589
