Protoss_Gateway 3 8668
Protoss_Assimilator 1 3126
Protoss_Cybernetics_Core 1 4282
Protoss_Dragoon 7 9973
Protoss_Citadel_of_Adun 1 5456
Protoss_Robotics_Facility 1 6522
Protoss_Nexus 2 10850
Protoss_Observatory 1 7108
Protoss_Observer 4 10085
10850
