Protoss_Gateway 2 6511
Protoss_Assimilator 1 3130
Protoss_Zealot 4 8004
Protoss_Cybernetics_Core 1 4128
Protoss_Dragoon 9 10730
Protoss_Robotics_Facility 1 6001
Protoss_Observatory 1 6545
Protoss_Observer 3 9696
Protoss_Shuttle 1 8377
Protoss_Forge 1 9394
Protoss_Citadel_of_Adun 1 10730
10730
