Protoss_Gateway 2 9300
Protoss_Assimilator 1 3178
Protoss_Cybernetics_Core 1 4297
Protoss_Dragoon 7 10728
Protoss_Robotics_Facility 1 5955
Protoss_Shuttle 1 6981
Protoss_Observatory 1 6737
Protoss_Observer 2 8186
Protoss_Robotics_Support_Bay 1 7569
Protoss_Reaver 2 10515
Protoss_Nexus 1 11275
11275
