Protoss_Gateway 1 3040
Protoss_Assimilator 1 3305
Protoss_Cybernetics_Core 1 4359
Protoss_Dragoon 5 10096
Protoss_Nexus 1 8955
Protoss_Citadel_of_Adun 1 9362
Protoss_Templar_Archives 1 10542
10542
