Protoss_Assimilator 1 2380
Protoss_Gateway 2 9336
Protoss_Cybernetics_Core 1 4167
Protoss_Robotics_Facility 1 5504
Protoss_Dragoon 8 10423
Protoss_Shuttle 1 6507
Protoss_Observatory 1 6376
Protoss_Observer 2 7712
Protoss_Nexus 1 9966
Protoss_Forge 1 9380
10423
