Protoss_Gateway 2 9452
Protoss_Assimilator 2 3226
Protoss_Cybernetics_Core 1 4205
Protoss_Dragoon 6 10076
Protoss_Robotics_Facility 1 6346
Protoss_Robotics_Support_Bay 1 6959
Protoss_Shuttle 1 7493
Protoss_Reaver 1 8660
Protoss_Observatory 1 9788
10076
