Protoss_Gateway 3 8806
Protoss_Assimilator 1 3027
Protoss_Cybernetics_Core 1 3955
Protoss_Dragoon 9 10006
Protoss_Robotics_Facility 1 5779
Protoss_Shuttle 1 7037
Protoss_Observatory 1 6783
Protoss_Observer 3 10016
Protoss_Nexus 1 11608
11608
