Protoss_Gateway 2 6139
Protoss_Assimilator 1 3023
Protoss_Cybernetics_Core 1 4204
Protoss_Dragoon 7 10358
Protoss_Robotics_Facility 1 6101
Protoss_Observatory 1 6718
Protoss_Observer 2 8020
Protoss_Zealot 4 9434
Protoss_Shuttle 1 8987
Protoss_Nexus 1 11253
11253
