Protoss_Gateway 3 10048
Protoss_Assimilator 1 3120
Protoss_Cybernetics_Core 1 3919
Protoss_Zealot 2 9585
Protoss_Dragoon 4 8713
Protoss_Citadel_of_Adun 1 7032
Protoss_Robotics_Facility 1 7992
Protoss_Templar_Archives 1 8128
Protoss_Observatory 1 8579
Protoss_Dark_Templar 3 10613
Protoss_Observer 2 9880
Protoss_Nexus 1 11126
Protoss_Shuttle 1 10482
11126
