Protoss_Gateway 2 7019
Protoss_Assimilator 1 3216
Protoss_Zealot 3 4913
Protoss_Cybernetics_Core 1 5613
Protoss_Dragoon 8 9887
Protoss_Robotics_Facility 1 9819
Protoss_Observatory 1 10382
10382
