Protoss_Gateway 2 6763
Protoss_Assimilator 1 3047
Protoss_Cybernetics_Core 1 4057
Protoss_Dragoon 8 10747
Protoss_Robotics_Facility 1 5997
Protoss_Observatory 1 6860
Protoss_Observer 1 7694
Protoss_Nexus 1 11536
11536
