Protoss_Gateway 2 8934
Protoss_Assimilator 2 3429
Protoss_Cybernetics_Core 1 4319
Protoss_Zealot 4 8348
Protoss_Robotics_Facility 1 5967
Protoss_Robotics_Support_Bay 1 6560
Protoss_Shuttle 1 7087
Protoss_Observatory 1 7106
Protoss_Reaver 1 8376
Protoss_Observer 1 8988
Protoss_Dragoon 3 10305
10305
