Protoss_Assimilator 1 2493
Protoss_Gateway 2 8901
Protoss_Cybernetics_Core 1 4334
Protoss_Zealot 4 6677
Protoss_Robotics_Facility 1 5667
Protoss_Shuttle 3 10492
Protoss_Citadel_of_Adun 1 7282
Protoss_Observatory 1 6906
Protoss_Observer 2 8335
Protoss_Dragoon 1 7958
Protoss_Templar_Archives 1 8362
Protoss_Forge 1 8089
Protoss_Dark_Templar 2 10023
Protoss_Photon_Cannon 1 10350
10492
