Protoss_Gateway 3 8469
Protoss_Assimilator 1 3102
Protoss_Cybernetics_Core 1 4049
Protoss_Dragoon 6 10123
Protoss_Robotics_Facility 1 6571
Protoss_Observatory 1 7219
Protoss_Observer 1 8493
Protoss_Zealot 4 10343
Protoss_Shuttle 1 9394
10343
