Protoss_Gateway 2 7491
Protoss_Assimilator 1 3084
Protoss_Cybernetics_Core 1 4080
Protoss_Dragoon 9 10363
Protoss_Robotics_Facility 1 6392
Protoss_Observatory 1 6952
Protoss_Observer 5 10293
10363
