Protoss_Gateway 2 7660
Protoss_Assimilator 3 4360
Protoss_Zealot 2 4703
Protoss_Cybernetics_Core 1 5849
Protoss_Citadel_of_Adun 1 6884
Protoss_Dragoon 2 10333
Protoss_Templar_Archives 1 8244
Protoss_Dark_Templar 2 9148
Protoss_Nexus 1 10925
10925
