Protoss_Gateway 2 6005
Protoss_Assimilator 1 3184
Protoss_Cybernetics_Core 1 4116
Protoss_Robotics_Facility 1 5587
Protoss_Dragoon 11 10383
Protoss_Observatory 1 6271
Protoss_Observer 3 9713
Protoss_Nexus 1 10541
10541
