Protoss_Gateway 2 10735
Protoss_Assimilator 1 3187
Protoss_Cybernetics_Core 1 4219
Protoss_Dragoon 5 10598
Protoss_Robotics_Facility 1 6045
Protoss_Shuttle 1 7152
Protoss_Zealot 2 7853
Protoss_Robotics_Support_Bay 1 7246
Protoss_Reaver 1 8406
Protoss_Observatory 1 8194
Protoss_Observer 2 9612
Protoss_Nexus 1 10790
10790
