Protoss_Gateway 2 7230
Protoss_Assimilator 2 3370
Protoss_Cybernetics_Core 1 4199
Protoss_Dragoon 4 9473
Protoss_Citadel_of_Adun 1 6053
Protoss_Templar_Archives 1 7044
Protoss_Dark_Templar 4 10333
Protoss_Nexus 1 9800
Protoss_Robotics_Facility 1 9508
10333
