Protoss_Gateway 3 9186
Protoss_Assimilator 1 2939
Protoss_Cybernetics_Core 1 3871
Protoss_Robotics_Facility 1 5413
Protoss_Dragoon 9 10722
Protoss_Shuttle 3 9767
Protoss_Observatory 1 6488
Protoss_Nexus 1 8813
Protoss_Observer 2 10446
10722
