Protoss_Gateway 3 9232
Protoss_Assimilator 1 3130
Protoss_Cybernetics_Core 1 3992
Protoss_Zealot 1 4453
Protoss_Dragoon 10 10318
Protoss_Robotics_Facility 1 6967
Protoss_Observatory 1 7617
Protoss_Observer 2 9298
Protoss_Shuttle 1 10199
10318
