Protoss_Gateway 1 2814
Protoss_Assimilator 1 3055
Protoss_Cybernetics_Core 1 3999
Protoss_Dragoon 2 7168
Protoss_Robotics_Facility 1 6233
Protoss_Citadel_of_Adun 1 6176
Protoss_Templar_Archives 1 7297
Protoss_Shuttle 1 7682
Protoss_Observatory 1 7945
Protoss_Dark_Templar 2 10128
Protoss_Observer 1 8883
10128
