Protoss_Gateway 2 7025
Protoss_Assimilator 1 3157
Protoss_Cybernetics_Core 1 4094
Protoss_Dragoon 10 10613
Protoss_Robotics_Facility 1 8383
Protoss_Observatory 1 9051
Protoss_Nexus 1 10715
Protoss_Observer 1 9748
10715
