Protoss_Gateway 2 7911
Protoss_Assimilator 1 3125
Protoss_Cybernetics_Core 1 4144
Protoss_Dragoon 7 9505
Protoss_Robotics_Facility 1 6192
Protoss_Zealot 1 6058
Protoss_Observatory 1 6792
Protoss_Observer 3 10513
Protoss_Shuttle 1 9672
Protoss_Nexus 2 11775
11775
