Protoss_Gateway 2 9893
Protoss_Assimilator 1 2956
Protoss_Cybernetics_Core 1 4131
Protoss_Robotics_Facility 1 5818
Protoss_Dragoon 5 9985
Protoss_Robotics_Support_Bay 1 6438
Protoss_Reaver 3 10877
Protoss_Shuttle 1 8484
10877
