Protoss_Gateway 2 9625
Protoss_Assimilator 1 3044
Protoss_Cybernetics_Core 1 3984
Protoss_Dragoon 6 9702
Protoss_Robotics_Facility 1 6162
Protoss_Shuttle 1 7177
Protoss_Robotics_Support_Bay 1 6831
Protoss_Observatory 1 6906
Protoss_Reaver 1 8228
Protoss_Observer 1 8832
9702
