Protoss_Gateway 3 10659
Protoss_Assimilator 1 2920
Protoss_Cybernetics_Core 1 3899
Protoss_Zealot 2 6218
Protoss_Robotics_Facility 1 5302
Protoss_Dragoon 5 10093
Protoss_Shuttle 1 6312
Protoss_Robotics_Support_Bay 1 7125
Protoss_Reaver 1 8526
Protoss_Observatory 1 8984
Protoss_Observer 1 10458
10659
