Protoss_Gateway 2 9569
Protoss_Assimilator 1 3089
Protoss_Zealot 4 5739
Protoss_Cybernetics_Core 1 5256
Protoss_Dragoon 5 10088
Protoss_Robotics_Facility 1 7073
Protoss_Shuttle 2 9327
Protoss_Robotics_Support_Bay 1 7955
Protoss_Reaver 2 10746
Protoss_Shield_Battery 1 9240
Protoss_Observatory 1 10391
10746
