Protoss_Gateway 3 8487
Protoss_Assimilator 1 2926
Protoss_Cybernetics_Core 1 3725
Protoss_Dragoon 8 10485
Protoss_Robotics_Facility 1 5572
Protoss_Shuttle 1 6647
Protoss_Observatory 1 6673
Protoss_Observer 2 10038
Protoss_Nexus 1 10080
10485
