Protoss_Gateway 1 2739
Protoss_Assimilator 1 2846
Protoss_Cybernetics_Core 1 3884
Protoss_Robotics_Facility 1 5252
Protoss_Dragoon 4 8338
Protoss_Shuttle 1 6312
Protoss_Observatory 1 7356
Protoss_Observer 1 8093
8338
