Protoss_Gateway 1 2842
Protoss_Assimilator 1 3067
Protoss_Cybernetics_Core 1 4049
Protoss_Dragoon 7 9963
Protoss_Robotics_Facility 1 5772
Protoss_Shuttle 1 6772
Protoss_Robotics_Support_Bay 1 6681
Protoss_Reaver 3 10196
Protoss_Observatory 1 8672
10196
