Protoss_Gateway 2 7033
Protoss_Assimilator 1 3167
Protoss_Cybernetics_Core 1 4122
Protoss_Dragoon 6 8630
Protoss_Robotics_Facility 1 6697
Protoss_Observatory 1 7377
Protoss_Observer 3 10353
Protoss_Nexus 2 11523
Protoss_Shuttle 1 9591
Protoss_Zealot 2 9568
11523
