Protoss_Gateway 2 10530
Protoss_Assimilator 1 3078
Protoss_Cybernetics_Core 1 3984
Protoss_Zealot 1 3838
Protoss_Dragoon 7 10123
Protoss_Robotics_Facility 1 7047
Protoss_Shuttle 1 8042
Protoss_Robotics_Support_Bay 1 7696
Protoss_Reaver 1 9093
Protoss_Observatory 1 9124
Protoss_Observer 2 10545
10545
