Protoss_Gateway 1 2972
Protoss_Assimilator 1 3187
Protoss_Cybernetics_Core 1 4468
Protoss_Dragoon 3 6857
Protoss_Robotics_Facility 1 6846
Protoss_Shuttle 1 7912
Protoss_Robotics_Support_Bay 2 7756
Protoss_Reaver 2 10458
Protoss_Nexus 1 11440
11440
