Protoss_Gateway 4 10821
Protoss_Assimilator 1 3048
Protoss_Cybernetics_Core 1 3997
Protoss_Dragoon 2 7606
Protoss_Robotics_Facility 1 6041
Protoss_Citadel_of_Adun 1 6601
Protoss_Observatory 1 6612
Protoss_Templar_Archives 1 7591
Protoss_Observer 2 9720
Protoss_Shuttle 1 8217
Protoss_Dark_Templar 4 9430
Protoss_Nexus 1 10853
10853
