Protoss_Gateway 2 3924
Protoss_Zealot 4 7623
Protoss_Assimilator 1 4214
Protoss_Cybernetics_Core 1 5785
Protoss_Dragoon 6 10028
Protoss_Robotics_Facility 1 8247
Protoss_Nexus 1 9750
Protoss_Observatory 1 9655
Protoss_Shuttle 1 10267
10267
