Protoss_Gateway 3 9481
Protoss_Assimilator 1 3151
Protoss_Cybernetics_Core 1 4105
Protoss_Dragoon 7 8767
Protoss_Robotics_Facility 1 7592
Protoss_Observatory 1 8265
Protoss_Observer 1 9073
Protoss_Zealot 5 10563
Protoss_Shuttle 1 9974
Protoss_Shield_Battery 1 9753
Protoss_Citadel_of_Adun 1 10763
10763
