Protoss_Gateway 2 6672
Protoss_Assimilator 1 3171
Protoss_Cybernetics_Core 1 4096
Protoss_Dragoon 6 10608
Protoss_Citadel_of_Adun 1 5744
Protoss_Templar_Archives 1 6954
Protoss_Dark_Templar 4 8803
Protoss_Robotics_Facility 1 8700
Protoss_Shuttle 1 9822
Protoss_Nexus 1 11095
Protoss_Observatory 1 10108
11095
