Protoss_Gateway 1 3029
Protoss_Assimilator 1 2895
Protoss_Cybernetics_Core 1 4046
Protoss_Dragoon 5 10713
Protoss_Robotics_Facility 1 5640
Protoss_Zealot 2 6248
Protoss_Shuttle 1 6637
Protoss_Robotics_Support_Bay 1 6371
Protoss_Reaver 2 8740
Protoss_Observatory 1 9477
Protoss_Nexus 1 11252
Protoss_Observer 1 10553
11252
