Protoss_Gateway 2 8563
Protoss_Assimilator 1 3111
Protoss_Cybernetics_Core 1 3829
Protoss_Robotics_Facility 1 5642
Protoss_Forge 1 5338
Protoss_Dragoon 8 10225
Protoss_Shuttle 2 10257
Protoss_Observatory 1 6298
Protoss_Observer 2 7933
Protoss_Photon_Cannon 5 10660
Protoss_Nexus 1 11312
11312
