Protoss_Assimilator 1 2478
Protoss_Gateway 2 8206
Protoss_Cybernetics_Core 1 4561
Protoss_Dragoon 3 9842
Protoss_Robotics_Facility 1 6201
Protoss_Citadel_of_Adun 1 6799
Protoss_Shuttle 1 7241
Protoss_Templar_Archives 1 7962
Protoss_Dark_Templar 2 10372
10372
