Protoss_Gateway 2 9488
Protoss_Assimilator 1 3000
Protoss_Cybernetics_Core 1 4029
Protoss_Dragoon 6 10398
Protoss_Robotics_Facility 1 6588
Protoss_Observatory 1 7316
Protoss_Shuttle 1 7972
Protoss_Observer 3 10130
Protoss_Nexus 1 10083
10398
