Protoss_Gateway 4 8714
Protoss_Assimilator 1 2795
Protoss_Cybernetics_Core 1 3779
Protoss_Robotics_Facility 1 5158
Protoss_Citadel_of_Adun 1 5349
Protoss_Shuttle 1 6152
Protoss_Templar_Archives 1 6399
Protoss_Dark_Templar 4 9713
Protoss_Dragoon 3 9438
Protoss_Observatory 1 9685
Protoss_Nexus 1 11330
11330
