Protoss_Gateway 2 10344
Protoss_Assimilator 1 3170
Protoss_Cybernetics_Core 1 4152
Protoss_Dragoon 8 10277
Protoss_Robotics_Facility 1 6557
Protoss_Observatory 1 7126
Protoss_Observer 3 10478
Protoss_Nexus 1 10800
10800
