Protoss_Gateway 4 10159
Protoss_Assimilator 1 2981
Protoss_Cybernetics_Core 1 3909
Protoss_Zealot 1 3950
Protoss_Dragoon 6 9216
Protoss_Robotics_Facility 1 6071
Protoss_Observatory 1 6685
Protoss_Observer 3 10098
Protoss_Nexus 1 9583
10159
