Protoss_Assimilator 1 2370
Protoss_Gateway 3 10308
Protoss_Cybernetics_Core 1 4241
Protoss_Stargate 1 5402
Protoss_Robotics_Facility 1 6327
Protoss_Corsair 3 7388
Protoss_Dragoon 2 8063
Protoss_Shuttle 1 7402
Protoss_Robotics_Support_Bay 1 7541
Protoss_Reaver 2 9728
Protoss_Citadel_of_Adun 1 9824
10308
