Protoss_Gateway 1 2884
Protoss_Assimilator 1 3010
Protoss_Cybernetics_Core 1 4004
Protoss_Zealot 1 3938
Protoss_Dragoon 6 9005
Protoss_Robotics_Facility 1 6967
Protoss_Shuttle 1 8212
Protoss_Observatory 1 8169
Protoss_Robotics_Support_Bay 1 8291
Protoss_Reaver 1 9586
9586
