Protoss_Gateway 2 6934
Protoss_Assimilator 1 3200
Protoss_Cybernetics_Core 1 4303
Protoss_Citadel_of_Adun 1 5456
Protoss_Dragoon 5 10458
Protoss_Templar_Archives 1 6726
Protoss_Dark_Templar 4 8540
Protoss_Nexus 1 10815
Protoss_Robotics_Facility 1 10557
10815
