Protoss_Gateway 3 9093
Protoss_Assimilator 1 3093
Protoss_Cybernetics_Core 1 3939
Protoss_Dragoon 9 10668
Protoss_Citadel_of_Adun 1 6849
Protoss_Templar_Archives 1 8059
Protoss_Dark_Templar 2 8953
Protoss_Nexus 1 11281
11281
