Protoss_Gateway 1 2918
Protoss_Assimilator 1 3095
Protoss_Cybernetics_Core 1 4069
Protoss_Dragoon 8 10362
Protoss_Robotics_Facility 1 7194
Protoss_Nexus 1 9205
Protoss_Observatory 1 7949
10362
