Protoss_Gateway 1 2841
Protoss_Assimilator 1 2945
Protoss_Cybernetics_Core 1 3959
Protoss_Dragoon 3 10458
Protoss_Robotics_Facility 1 5487
Protoss_Shuttle 1 6472
Protoss_Robotics_Support_Bay 1 6346
Protoss_Reaver 2 8713
Protoss_Zealot 1 7463
Protoss_Nexus 1 10535
Protoss_Stargate 1 10636
10636
