Protoss_Gateway 3 10584
Protoss_Assimilator 1 3155
Protoss_Cybernetics_Core 1 4129
Protoss_Dragoon 10 9865
Protoss_Robotics_Facility 1 7247
Protoss_Observatory 1 7857
Protoss_Observer 2 9145
Protoss_Nexus 1 11075
11075
