Protoss_Gateway 2 6044
Protoss_Assimilator 1 3125
Protoss_Cybernetics_Core 1 4214
Protoss_Dragoon 8 10490
Protoss_Robotics_Facility 1 5893
Protoss_Observatory 1 6489
Protoss_Observer 3 10345
Protoss_Nexus 1 10620
Protoss_Shuttle 1 9742
10620
