Protoss_Gateway 4 8953
Protoss_Assimilator 1 3066
Protoss_Cybernetics_Core 1 4046
Protoss_Dragoon 7 9358
Protoss_Robotics_Facility 1 5717
Protoss_Observatory 1 6340
Protoss_Observer 2 10393
Protoss_Citadel_of_Adun 1 8561
Protoss_Zealot 2 9663
Protoss_Nexus 1 11460
11460
