Protoss_Gateway 3 9241
Protoss_Assimilator 1 2858
Protoss_Cybernetics_Core 1 3894
Protoss_Dragoon 10 9834
Protoss_Robotics_Facility 1 6973
Protoss_Observatory 1 7580
Protoss_Observer 2 10398
Protoss_Nexus 1 11599
11599
