Protoss_Gateway 2 7175
Protoss_Assimilator 1 3095
Protoss_Cybernetics_Core 1 4019
Protoss_Dragoon 11 10433
Protoss_Robotics_Facility 1 6803
Protoss_Observatory 1 7528
Protoss_Observer 3 9908
Protoss_Nexus 1 10960
10960
