Protoss_Gateway 2 9175
Protoss_Assimilator 1 2943
Protoss_Cybernetics_Core 1 3839
Protoss_Dragoon 8 10175
Protoss_Robotics_Facility 1 7067
Protoss_Citadel_of_Adun 1 8188
Protoss_Observatory 1 7905
Protoss_Shuttle 1 8817
Protoss_Observer 1 9420
Protoss_Nexus 1 11130
11130
