Protoss_Gateway 2 7556
Protoss_Assimilator 1 3038
Protoss_Cybernetics_Core 1 3999
Protoss_Dragoon 9 9883
Protoss_Robotics_Facility 1 7262
Protoss_Observatory 1 8231
Protoss_Nexus 1 10510
Protoss_Observer 1 9363
Protoss_Shuttle 1 10472
Protoss_Zealot 2 10485
10510
