Protoss_Gateway 2 8976
Protoss_Assimilator 1 3055
Protoss_Cybernetics_Core 1 3943
Protoss_Dragoon 7 10603
Protoss_Robotics_Facility 1 6077
Protoss_Shuttle 1 7077
Protoss_Robotics_Support_Bay 1 6700
Protoss_Observatory 1 6967
Protoss_Reaver 1 8128
Protoss_Citadel_of_Adun 1 8670
Protoss_Observer 3 10014
10603
