Protoss_Gateway 3 9436
Protoss_Assimilator 1 3000
Protoss_Cybernetics_Core 1 3944
Protoss_Dragoon 9 10668
Protoss_Robotics_Facility 1 5815
Protoss_Observatory 1 6389
Protoss_Observer 2 8028
Protoss_Nexus 1 8967
Protoss_Shuttle 1 10022
10668
