Protoss_Gateway 3 10509
Protoss_Assimilator 2 4329
Protoss_Zealot 2 5090
Protoss_Cybernetics_Core 1 5190
Protoss_Dragoon 7 10178
Protoss_Robotics_Facility 1 6945
Protoss_Shuttle 1 8039
Protoss_Robotics_Support_Bay 1 7936
Protoss_Reaver 1 9132
Protoss_Observatory 1 9823
10509
