Protoss_Gateway 2 8809
Protoss_Assimilator 1 2982
Protoss_Cybernetics_Core 1 4062
Protoss_Dragoon 7 9908
Protoss_Robotics_Facility 1 5907
Protoss_Shuttle 1 6922
Protoss_Observatory 1 6981
Protoss_Nexus 2 11230
Protoss_Observer 1 8583
11230
