Protoss_Gateway 2 8120
Protoss_Assimilator 1 3009
Protoss_Cybernetics_Core 1 3679
Protoss_Dragoon 6 9858
Protoss_Robotics_Facility 1 7100
Protoss_Zealot 6 10460
Protoss_Shuttle 1 8182
Protoss_Robotics_Support_Bay 1 8120
Protoss_Citadel_of_Adun 1 9455
Protoss_Reaver 1 10001
Protoss_Templar_Archives 1 10559
10559
