Protoss_Gateway 3 9218
Protoss_Assimilator 1 3116
Protoss_Cybernetics_Core 1 4074
Protoss_Dragoon 7 10617
Protoss_Robotics_Facility 1 7162
Protoss_Shuttle 1 8427
Protoss_Observatory 1 8289
Protoss_Observer 2 9793
Protoss_Zealot 4 9962
10617
