Protoss_Gateway 2 8420
Protoss_Assimilator 1 3411
Protoss_Cybernetics_Core 1 4063
Protoss_Zealot 5 9843
Protoss_Dragoon 5 8187
Protoss_Robotics_Facility 1 7736
Protoss_Observatory 1 8342
Protoss_Observer 1 9208
Protoss_Nexus 1 10671
Protoss_Shuttle 1 10207
10671
