Protoss_Gateway 2 10496
Protoss_Assimilator 4 4258
Protoss_Cybernetics_Core 1 4241
Protoss_Dragoon 4 10150
Protoss_Robotics_Facility 1 6966
Protoss_Shuttle 1 8089
Protoss_Robotics_Support_Bay 1 8023
Protoss_Reaver 1 9192
Protoss_Zealot 2 9398
Protoss_Observatory 1 9210
Protoss_Observer 1 10344
10496
