Protoss_Gateway 3 10245
Protoss_Assimilator 1 2885
Protoss_Cybernetics_Core 1 3994
Protoss_Dragoon 4 8568
Protoss_Robotics_Facility 1 5805
Protoss_Observatory 1 6524
Protoss_Citadel_of_Adun 1 7003
Protoss_Observer 2 8243
Protoss_Nexus 1 9177
Protoss_Templar_Archives 1 8359
Protoss_Dark_Templar 3 10348
10348
