Protoss_Gateway 4 9507
Protoss_Assimilator 1 3178
Protoss_Cybernetics_Core 1 4219
Protoss_Robotics_Facility 1 5595
Protoss_Dragoon 9 9734
Protoss_Observatory 1 6170
Protoss_Observer 1 6918
Protoss_Shuttle 1 7927
9734
