Protoss_Gateway 2 7947
Protoss_Assimilator 1 3042
Protoss_Cybernetics_Core 1 3921
Protoss_Dragoon 10 10514
Protoss_Robotics_Facility 1 6830
Protoss_Observatory 1 7375
Protoss_Observer 3 9976
Protoss_Shuttle 1 9373
Protoss_Robotics_Support_Bay 1 9932
10514
