Protoss_Gateway 2 6416
Protoss_Assimilator 1 3141
Protoss_Cybernetics_Core 1 4059
Protoss_Dragoon 8 8767
Protoss_Robotics_Facility 1 7549
Protoss_Observatory 1 8908
Protoss_Nexus 1 10985
Protoss_Zealot 4 10440
Protoss_Observer 1 9863
Protoss_Shuttle 1 10764
10985
