Protoss_Gateway 1 2952
Protoss_Assimilator 2 3440
Protoss_Cybernetics_Core 1 4449
Protoss_Robotics_Facility 1 5937
Protoss_Dragoon 1 5863
Protoss_Shuttle 1 6942
Protoss_Robotics_Support_Bay 1 6756
Protoss_Reaver 3 10226
Protoss_Zealot 1 7933
Protoss_Citadel_of_Adun 1 10619
10619
