Protoss_Gateway 1 2901
Protoss_Assimilator 1 3092
Protoss_Cybernetics_Core 1 3984
Protoss_Dragoon 8 10620
Protoss_Robotics_Facility 1 7561
Protoss_Shuttle 1 8672
Protoss_Robotics_Support_Bay 1 8296
Protoss_Reaver 1 9761
Protoss_Observatory 1 10258
10620
