Protoss_Gateway 3 7251
Protoss_Assimilator 1 3062
Protoss_Cybernetics_Core 1 3979
Protoss_Dragoon 8 10363
Protoss_Robotics_Facility 1 6451
Protoss_Observatory 1 7248
Protoss_Observer 2 10008
Protoss_Zealot 4 9318
Protoss_Shuttle 1 8959
10363
