Protoss_Gateway 3 9412
Protoss_Assimilator 1 2964
Protoss_Cybernetics_Core 1 3974
Protoss_Dragoon 9 10273
Protoss_Robotics_Facility 1 7133
Protoss_Observatory 1 7728
Protoss_Observer 1 8443
Protoss_Shuttle 1 9432
Protoss_Zealot 2 9428
10273
