Protoss_Gateway 2 4284
Protoss_Assimilator 1 2925
Protoss_Cybernetics_Core 1 3849
Protoss_Dragoon 8 10508
Protoss_Nexus 1 8441
Protoss_Robotics_Facility 1 8217
Protoss_Shuttle 1 9577
Protoss_Observatory 1 9570
Protoss_Observer 1 10263
10508
