Protoss_Gateway 2 6439
Protoss_Assimilator 1 3140
Protoss_Cybernetics_Core 1 3914
Protoss_Robotics_Facility 1 5546
Protoss_Dragoon 10 10693
Protoss_Observatory 1 6161
Protoss_Shuttle 1 6752
Protoss_Observer 2 7957
10693
