Protoss_Gateway 2 6223
Protoss_Assimilator 1 3012
Protoss_Cybernetics_Core 1 3935
Protoss_Dragoon 11 9658
Protoss_Robotics_Facility 1 7962
Protoss_Observatory 1 8546
Protoss_Observer 2 10190
Protoss_Nexus 1 11388
11388
