Protoss_Gateway 2 7631
Protoss_Assimilator 1 3130
Protoss_Cybernetics_Core 1 4034
Protoss_Robotics_Facility 1 5552
Protoss_Dragoon 6 10408
Protoss_Observatory 1 6167
Protoss_Observer 2 7878
Protoss_Nexus 1 9722
Protoss_Shuttle 1 9142
Protoss_Zealot 1 10578
10578
