Protoss_Gateway 3 8814
Protoss_Assimilator 1 3115
Protoss_Cybernetics_Core 1 4294
Protoss_Dragoon 9 10633
Protoss_Robotics_Facility 1 6657
Protoss_Nexus 1 8336
Protoss_Robotics_Support_Bay 1 7262
Protoss_Observatory 1 7446
Protoss_Observer 2 8945
Protoss_Shuttle 1 9846
Protoss_Citadel_of_Adun 1 10619
10633
