Protoss_Gateway 2 7860
Protoss_Assimilator 1 3267
Protoss_Cybernetics_Core 1 4214
Protoss_Dragoon 6 9693
Protoss_Robotics_Facility 1 7867
Protoss_Nexus 2 11080
Protoss_Shuttle 1 8927
Protoss_Observatory 1 8579
Protoss_Observer 1 9988
11080
