Protoss_Gateway 5 10839
Protoss_Assimilator 1 3331
Protoss_Cybernetics_Core 1 4009
Protoss_Dragoon 8 10470
Protoss_Citadel_of_Adun 1 6997
Protoss_Nexus 1 8560
Protoss_Robotics_Facility 1 8765
Protoss_Observatory 1 9389
Protoss_Observer 1 10088
10839
