Protoss_Gateway 3 10113
Protoss_Assimilator 1 3026
Protoss_Cybernetics_Core 1 4052
Protoss_Dragoon 8 9868
Protoss_Robotics_Facility 1 7170
Protoss_Observatory 1 7906
Protoss_Nexus 1 10370
Protoss_Observer 1 10333
Protoss_Citadel_of_Adun 1 10667
10667
