Protoss_Gateway 3 7934
Protoss_Assimilator 1 2970
Protoss_Cybernetics_Core 1 4044
Protoss_Dragoon 12 10324
Protoss_Robotics_Facility 1 5505
Protoss_Shuttle 1 6492
Protoss_Observatory 1 6221
Protoss_Observer 3 9063
Protoss_Nexus 1 11472
11472
