Protoss_Gateway 2 7266
Protoss_Assimilator 1 3070
Protoss_Cybernetics_Core 1 4055
Protoss_Dragoon 3 10155
Protoss_Robotics_Facility 1 5958
Protoss_Citadel_of_Adun 1 6244
Protoss_Observatory 1 6562
Protoss_Templar_Archives 1 7370
Protoss_Observer 1 7418
Protoss_Shuttle 1 8319
Protoss_Dark_Templar 4 9403
Protoss_Nexus 1 10921
10921
