Protoss_Gateway 3 9007
Protoss_Assimilator 1 3020
Protoss_Cybernetics_Core 1 4036
Protoss_Dragoon 11 10373
Protoss_Nexus 1 8607
Protoss_Robotics_Facility 1 8862
Protoss_Observatory 1 9796
Protoss_Forge 1 10544
10544
