Protoss_Gateway 3 8644
Protoss_Assimilator 1 3010
Protoss_Cybernetics_Core 1 4074
Protoss_Dragoon 6 10378
Protoss_Robotics_Facility 1 6462
Protoss_Nexus 2 10530
Protoss_Observatory 1 7624
Protoss_Observer 4 10404
10530
