Protoss_Forge 2 10002
Protoss_Nexus 1 5689
Protoss_Photon_Cannon 4 8548
Protoss_Gateway 3 9324
Protoss_Zealot 7 10478
Protoss_Assimilator 1 8262
Protoss_Cybernetics_Core 1 9774
Protoss_Citadel_of_Adun 1 10847
10847
