Protoss_Gateway 2 6271
Protoss_Assimilator 1 3147
Protoss_Cybernetics_Core 1 4050
Protoss_Dragoon 8 8807
Protoss_Robotics_Facility 1 7423
Protoss_Observatory 1 8092
Protoss_Observer 1 8788
Protoss_Zealot 3 10183
Protoss_Shuttle 1 9897
10183
