Protoss_Gateway 3 9275
Protoss_Assimilator 1 2979
Protoss_Cybernetics_Core 1 4072
Protoss_Dragoon 8 10398
Protoss_Robotics_Facility 1 8131
Protoss_Observatory 1 8699
Protoss_Zealot 4 9868
Protoss_Shuttle 1 10002
Protoss_Observer 1 9748
10398
