Protoss_Gateway 3 10063
Protoss_Assimilator 1 3081
Protoss_Cybernetics_Core 1 4062
Protoss_Dragoon 6 8583
Protoss_Robotics_Facility 1 6283
Protoss_Observatory 1 7391
Protoss_Observer 3 9500
Protoss_Nexus 1 10230
Protoss_Zealot 2 9958
10230
