Protoss_Gateway 3 9838
Protoss_Assimilator 1 3247
Protoss_Cybernetics_Core 1 4323
Protoss_Robotics_Facility 1 5655
Protoss_Dragoon 2 7288
Protoss_Shuttle 1 6672
Protoss_Citadel_of_Adun 1 7020
Protoss_Templar_Archives 1 8033
Protoss_Dark_Templar 6 10725
Protoss_Nexus 1 10480
10725
