Protoss_Gateway 1 2871
Protoss_Assimilator 1 3080
Protoss_Cybernetics_Core 1 4072
Protoss_Dragoon 5 10673
Protoss_Stargate 1 6910
Protoss_Fleet_Beacon 1 7919
Protoss_Shield_Battery 1 7879
Protoss_Zealot 1 9513
10673
