Protoss_Gateway 2 9052
Protoss_Assimilator 1 2865
Protoss_Cybernetics_Core 1 4097
Protoss_Dragoon 6 10168
Protoss_Stargate 1 6657
Protoss_Fleet_Beacon 1 7715
Protoss_Carrier 1 9896
Protoss_Robotics_Facility 1 9762
Protoss_Forge 1 10337
Protoss_Observatory 1 10342
10342
