Protoss_Gateway 2 7159
Protoss_Assimilator 1 3075
Protoss_Cybernetics_Core 1 3983
Protoss_Dragoon 3 10083
Protoss_Robotics_Facility 1 5806
Protoss_Citadel_of_Adun 1 6207
Protoss_Templar_Archives 1 7215
Protoss_Observatory 1 7085
Protoss_Observer 1 7858
Protoss_Dark_Templar 4 9308
Protoss_Shuttle 1 8759
10083
