Protoss_Gateway 4 9156
Protoss_Assimilator 1 3070
Protoss_Cybernetics_Core 1 4149
Protoss_Dragoon 13 10653
Protoss_Nexus 1 7565
Protoss_Robotics_Facility 1 7378
Protoss_Observatory 1 8088
Protoss_Observer 2 10573
10653
