Protoss_Gateway 2 8035
Protoss_Assimilator 1 3115
Protoss_Cybernetics_Core 1 4036
Protoss_Dragoon 10 10527
Protoss_Robotics_Facility 1 6132
Protoss_Observatory 1 6779
Protoss_Observer 3 9623
Protoss_Shuttle 1 10047
10527
