Protoss_Gateway 3 10048
Protoss_Assimilator 1 3060
Protoss_Cybernetics_Core 1 3929
Protoss_Dragoon 6 10593
Protoss_Stargate 1 6926
Protoss_Fleet_Beacon 1 8042
Protoss_Carrier 1 10226
Protoss_Robotics_Facility 1 9987
10593
