Protoss_Gateway 3 10079
Protoss_Assimilator 1 3241
Protoss_Cybernetics_Core 1 4594
Protoss_Dragoon 3 7773
Protoss_Robotics_Facility 1 6539
Protoss_Citadel_of_Adun 1 6511
Protoss_Observatory 1 7125
Protoss_Templar_Archives 1 7724
Protoss_Observer 1 7878
Protoss_Zealot 1 8038
Protoss_Shuttle 1 8852
Protoss_Dark_Templar 4 9905
10079
