Protoss_Gateway 1 2894
Protoss_Assimilator 1 3159
Protoss_Cybernetics_Core 1 4094
Protoss_Robotics_Facility 1 5748
Protoss_Dragoon 7 10614
Protoss_Shuttle 2 10342
Protoss_Robotics_Support_Bay 1 6531
Protoss_Reaver 1 8196
Protoss_Observatory 1 8973
Protoss_Nexus 1 11236
11236
