Protoss_Gateway 2 6744
Protoss_Assimilator 1 3006
Protoss_Cybernetics_Core 1 3847
Protoss_Dragoon 6 8340
Protoss_Robotics_Facility 1 5863
Protoss_Observatory 1 6522
Protoss_Observer 2 9615
Protoss_Shuttle 1 9012
Protoss_Zealot 4 9928
9928
