Protoss_Gateway 3 9744
Protoss_Assimilator 1 2885
Protoss_Cybernetics_Core 1 3871
Protoss_Dragoon 6 10026
Protoss_Robotics_Facility 1 6857
Protoss_Observatory 1 7499
Protoss_Nexus 1 9200
Protoss_Observer 1 8203
10026
