Protoss_Gateway 2 8631
Protoss_Assimilator 1 2990
Protoss_Cybernetics_Core 1 3894
Protoss_Dragoon 10 10623
Protoss_Robotics_Facility 1 6510
Protoss_Shuttle 1 7522
Protoss_Robotics_Support_Bay 1 7435
Protoss_Reaver 1 8576
Protoss_Observatory 1 8388
Protoss_Observer 1 9180
10623
