Protoss_Gateway 4 10647
Protoss_Assimilator 1 3007
Protoss_Cybernetics_Core 1 3865
Protoss_Dragoon 9 8958
Protoss_Robotics_Facility 1 9447
Protoss_Nexus 1 10300
Protoss_Citadel_of_Adun 1 9819
Protoss_Zealot 2 10183
Protoss_Observatory 1 10043
10647
