Protoss_Gateway 1 2939
Protoss_Assimilator 1 3120
Protoss_Cybernetics_Core 1 3955
Protoss_Dragoon 4 7753
Protoss_Robotics_Facility 1 5801
Protoss_Observatory 1 6388
Protoss_Observer 2 8023
Protoss_Robotics_Support_Bay 1 8152
Protoss_Shuttle 1 8924
Protoss_Reaver 1 9975
Protoss_Zealot 1 9693
Protoss_Nexus 1 10903
10903
