Protoss_Gateway 4 10689
Protoss_Assimilator 1 3096
Protoss_Cybernetics_Core 1 4114
Protoss_Dragoon 7 9160
Protoss_Robotics_Facility 1 6810
Protoss_Observatory 1 7371
Protoss_Zealot 2 9783
10689
