Protoss_Gateway 2 7131
Protoss_Assimilator 1 3075
Protoss_Cybernetics_Core 1 4094
Protoss_Dragoon 3 10573
Protoss_Citadel_of_Adun 1 6347
Protoss_Robotics_Facility 1 7232
Protoss_Templar_Archives 1 7369
Protoss_Dark_Templar 1 8388
Protoss_Observatory 1 8197
10573
