Protoss_Gateway 3 8367
Protoss_Assimilator 1 2922
Protoss_Cybernetics_Core 1 3925
Protoss_Dragoon 12 10233
Protoss_Robotics_Facility 1 6995
Protoss_Observatory 1 7612
Protoss_Observer 2 8905
10233
