Protoss_Gateway 3 8646
Protoss_Assimilator 1 3053
Protoss_Cybernetics_Core 1 3961
Protoss_Dragoon 7 9413
Protoss_Robotics_Facility 1 5773
Protoss_Shuttle 1 6762
Protoss_Observatory 1 6532
Protoss_Observer 5 10148
Protoss_Nexus 2 11033
11033
