Protoss_Gateway 4 9372
Protoss_Assimilator 1 3265
Protoss_Cybernetics_Core 1 4355
Protoss_Dragoon 5 10315
Protoss_Robotics_Facility 1 6160
Protoss_Observatory 1 6834
Protoss_Observer 2 8218
10315
