Protoss_Gateway 3 9195
Protoss_Assimilator 1 3040
Protoss_Cybernetics_Core 1 3903
Protoss_Dragoon 7 9228
Protoss_Robotics_Facility 1 5697
Protoss_Observatory 1 6299
Protoss_Nexus 1 8075
Protoss_Observer 3 9228
Protoss_Zealot 3 9993
Protoss_Shuttle 1 10129
10129
