Protoss_Gateway 2 4454
Protoss_Assimilator 1 2968
Protoss_Cybernetics_Core 1 4159
Protoss_Dragoon 7 7720
Protoss_Citadel_of_Adun 1 7094
Protoss_Templar_Archives 1 8409
Protoss_Nexus 1 10000
Protoss_Dark_Templar 3 10643
Protoss_Robotics_Facility 1 10557
10643
