Protoss_Gateway 3 8171
Protoss_Assimilator 1 3073
Protoss_Cybernetics_Core 1 4065
Protoss_Dragoon 12 10618
Protoss_Robotics_Facility 1 7409
Protoss_Observatory 1 8115
Protoss_Observer 2 9921
Protoss_Citadel_of_Adun 1 10265
10618
