Protoss_Nexus 1 4653
Protoss_Gateway 3 6394
Protoss_Assimilator 2 8377
Protoss_Cybernetics_Core 1 5358
Protoss_Zealot 1 5608
Protoss_Dragoon 11 10693
Protoss_Robotics_Facility 1 8431
Protoss_Shuttle 1 9652
10693
