Protoss_Gateway 1 2968
Protoss_Assimilator 1 3065
Protoss_Cybernetics_Core 1 4242
Protoss_Robotics_Facility 1 5957
Protoss_Zealot 1 5728
Protoss_Robotics_Support_Bay 1 7234
Protoss_Dragoon 2 9095
Protoss_Shield_Battery 1 8565
9095
