Protoss_Assimilator 1 2336
Protoss_Gateway 3 9289
Protoss_Cybernetics_Core 1 4124
Protoss_Robotics_Facility 1 5452
Protoss_Dragoon 6 9667
Protoss_Shuttle 1 6442
Protoss_Observatory 1 7466
Protoss_Observer 3 9462
Protoss_Citadel_of_Adun 1 8857
Protoss_Templar_Archives 1 10094
Protoss_Zealot 1 9878
10094
