Protoss_Assimilator 1 2629
Protoss_Gateway 3 9554
Protoss_Cybernetics_Core 1 4034
Protoss_Robotics_Facility 1 5327
Protoss_Shuttle 1 6322
Protoss_Robotics_Support_Bay 1 5917
Protoss_Reaver 2 8425
Protoss_Forge 1 7265
Protoss_Shield_Battery 1 8081
Protoss_Dragoon 6 10689
Protoss_Observatory 1 9982
10689
