Protoss_Gateway 2 8765
Protoss_Assimilator 1 3004
Protoss_Cybernetics_Core 1 4059
Protoss_Dragoon 7 10189
Protoss_Robotics_Facility 1 5874
Protoss_Shuttle 1 6867
Protoss_Observatory 1 6971
Protoss_Observer 2 10473
Protoss_Nexus 1 9363
Protoss_Robotics_Support_Bay 1 9922
Protoss_Zealot 1 10340
10473
