Protoss_Gateway 3 9197
Protoss_Assimilator 1 2875
Protoss_Cybernetics_Core 1 3759
Protoss_Dragoon 5 9888
Protoss_Citadel_of_Adun 1 5388
Protoss_Templar_Archives 1 6463
Protoss_Dark_Templar 4 8065
Protoss_Robotics_Facility 1 9252
Protoss_Zealot 3 10588
Protoss_Shuttle 1 10382
Protoss_Observatory 1 10087
10588
