Protoss_Gateway 2 5068
Protoss_Assimilator 1 2865
Protoss_Cybernetics_Core 1 3804
Protoss_Dragoon 12 10183
Protoss_Robotics_Facility 1 8417
Protoss_Observatory 1 9112
Protoss_Nexus 1 11030
Protoss_Observer 1 9878
11030
