Protoss_Gateway 2 5289
Protoss_Assimilator 1 2970
Protoss_Cybernetics_Core 1 3954
Protoss_Dragoon 11 10468
Protoss_Nexus 1 9175
Protoss_Robotics_Facility 1 9592
Protoss_Citadel_of_Adun 1 10073
Protoss_Observatory 1 10254
10468
