Protoss_Gateway 2 7282
Protoss_Assimilator 1 3058
Protoss_Zealot 1 3712
Protoss_Cybernetics_Core 1 5008
Protoss_Dragoon 7 9584
Protoss_Robotics_Facility 1 8261
Protoss_Observatory 1 8955
Protoss_Shuttle 1 9899
Protoss_Observer 1 10502
10502
