Protoss_Gateway 2 5269
Protoss_Assimilator 2 3363
Protoss_Cybernetics_Core 1 4455
Protoss_Dragoon 7 9628
Protoss_Citadel_of_Adun 1 6855
Protoss_Templar_Archives 1 7895
Protoss_Dark_Templar 4 10578
10578
