Protoss_Gateway 2 4538
Protoss_Assimilator 1 3107
Protoss_Cybernetics_Core 1 3951
Protoss_Dragoon 10 10393
Protoss_Zealot 2 7000
Protoss_Robotics_Facility 1 8242
Protoss_Observatory 1 8841
Protoss_Observer 1 9903
Protoss_Nexus 1 11404
11404
