Protoss_Gateway 1 2969
Protoss_Assimilator 1 3002
Protoss_Cybernetics_Core 1 4100
Protoss_Dragoon 2 7058
Protoss_Robotics_Facility 1 5797
Protoss_Shuttle 1 6982
Protoss_Robotics_Support_Bay 1 7360
Protoss_Citadel_of_Adun 1 8154
Protoss_Reaver 1 8601
Protoss_Templar_Archives 1 9242
Protoss_Observatory 1 8851
Protoss_Observer 1 9583
Protoss_Dark_Templar 1 10353
10353
