Protoss_Gateway 2 6784
Protoss_Assimilator 1 3149
Protoss_Cybernetics_Core 1 4151
Protoss_Dragoon 7 8851
Protoss_Robotics_Facility 1 6031
Protoss_Observatory 1 6765
Protoss_Observer 2 9808
Protoss_Nexus 2 11323
11323
