Protoss_Gateway 1 3033
Protoss_Assimilator 1 3301
Protoss_Cybernetics_Core 1 4197
Protoss_Dragoon 6 9810
Protoss_Robotics_Facility 1 6990
Protoss_Shuttle 1 8157
Protoss_Zealot 2 10412
Protoss_Robotics_Support_Bay 1 7992
Protoss_Reaver 2 10821
10821
