Protoss_Gateway 2 6469
Protoss_Assimilator 1 3091
Protoss_Cybernetics_Core 1 4059
Protoss_Dragoon 9 9273
Protoss_Robotics_Facility 1 7450
Protoss_Observatory 1 8235
Protoss_Observer 1 9098
Protoss_Zealot 3 10550
Protoss_Shuttle 1 9999
10550
