Protoss_Gateway 3 7820
Protoss_Assimilator 1 3158
Protoss_Cybernetics_Core 1 4069
Protoss_Dragoon 9 9343
Protoss_Robotics_Facility 1 6340
Protoss_Observatory 1 7084
Protoss_Observer 2 9228
Protoss_Nexus 1 10870
10870
