Protoss_Gateway 2 9657
Protoss_Assimilator 2 3311
Protoss_Zealot 2 4713
Protoss_Cybernetics_Core 1 4903
Protoss_Dragoon 5 9275
Protoss_Robotics_Facility 1 6349
Protoss_Shuttle 1 7342
Protoss_Robotics_Support_Bay 1 7326
Protoss_Reaver 2 9823
Protoss_Nexus 1 11620
11620
