Protoss_Gateway 2 3764
Protoss_Zealot 3 7643
Protoss_Assimilator 1 3823
Protoss_Cybernetics_Core 1 4699
Protoss_Dragoon 4 8933
Protoss_Robotics_Facility 1 7074
Protoss_Citadel_of_Adun 1 7817
Protoss_Shuttle 1 8127
Protoss_Templar_Archives 1 8857
Protoss_Dark_Templar 4 10480
10480
