Protoss_Gateway 4 9250
Protoss_Assimilator 1 2911
Protoss_Cybernetics_Core 1 3869
Protoss_Robotics_Facility 1 5337
Protoss_Dragoon 9 10378
Protoss_Shuttle 1 6337
Protoss_Observatory 1 6006
Protoss_Observer 2 7668
Protoss_Nexus 1 10549
10549
