Protoss_Gateway 3 8977
Protoss_Assimilator 1 2992
Protoss_Cybernetics_Core 1 4106
Protoss_Dragoon 12 9981
Protoss_Robotics_Facility 1 6487
Protoss_Observatory 1 7108
Protoss_Observer 2 8580
Protoss_Nexus 1 11550
11550
