Protoss_Gateway 2 6683
Protoss_Assimilator 1 3075
Protoss_Cybernetics_Core 1 3994
Protoss_Dragoon 10 10498
Protoss_Robotics_Facility 1 5777
Protoss_Observatory 1 6591
Protoss_Observer 2 9108
Protoss_Shuttle 1 8767
Protoss_Nexus 1 10350
10498
