Protoss_Gateway 2 6705
Protoss_Assimilator 1 3000
Protoss_Cybernetics_Core 1 4082
Protoss_Dragoon 8 10218
Protoss_Robotics_Facility 1 6623
Protoss_Observatory 1 7262
Protoss_Observer 4 10423
Protoss_Nexus 2 10753
10753
