Protoss_Gateway 4 10274
Protoss_Assimilator 1 3118
Protoss_Cybernetics_Core 1 4019
Protoss_Dragoon 9 9920
Protoss_Robotics_Facility 1 5894
Protoss_Observatory 1 6523
Protoss_Observer 4 10445
Protoss_Nexus 1 10475
10475
