Protoss_Gateway 2 9009
Protoss_Assimilator 1 3165
Protoss_Cybernetics_Core 1 4079
Protoss_Dragoon 8 10725
Protoss_Robotics_Facility 1 5915
Protoss_Shuttle 1 6987
Protoss_Robotics_Support_Bay 1 7019
Protoss_Reaver 2 9251
Protoss_Observatory 1 8349
Protoss_Observer 1 9855
10725
