Protoss_Gateway 2 6456
Protoss_Assimilator 1 3098
Protoss_Cybernetics_Core 1 4015
Protoss_Dragoon 10 10288
Protoss_Citadel_of_Adun 1 5654
Protoss_Nexus 1 8994
Protoss_Robotics_Facility 1 8827
Protoss_Observatory 1 9596
Protoss_Observer 1 10283
10288
