Protoss_Gateway 2 7066
Protoss_Assimilator 1 3205
Protoss_Cybernetics_Core 1 4093
Protoss_Dragoon 9 9990
Protoss_Robotics_Facility 1 6072
Protoss_Observatory 1 6723
Protoss_Observer 3 9968
Protoss_Nexus 1 11641
11641
