Protoss_Gateway 3 7865
Protoss_Assimilator 1 3006
Protoss_Cybernetics_Core 1 3942
Protoss_Dragoon 9 9152
Protoss_Robotics_Facility 1 6959
Protoss_Observatory 1 7546
Protoss_Observer 3 9864
Protoss_Nexus 1 10969
Protoss_Citadel_of_Adun 1 10665
Protoss_Shuttle 1 10765
10969
