Protoss_Gateway 1 2849
Protoss_Assimilator 1 2948
Protoss_Cybernetics_Core 1 4005
Protoss_Dragoon 8 10271
Protoss_Robotics_Facility 1 6719
Protoss_Nexus 1 8136
Protoss_Observatory 1 7355
Protoss_Observer 3 9978
10271
