Protoss_Gateway 2 8333
Protoss_Assimilator 1 3061
Protoss_Cybernetics_Core 1 4020
Protoss_Zealot 1 3853
Protoss_Dragoon 9 10348
Protoss_Robotics_Facility 1 8077
Protoss_Shuttle 1 9097
Protoss_Observatory 1 8831
Protoss_Observer 2 10478
Protoss_Robotics_Support_Bay 1 9636
10478
