Protoss_Gateway 2 7721
Protoss_Assimilator 1 3090
Protoss_Cybernetics_Core 1 4046
Protoss_Robotics_Facility 1 5527
Protoss_Dragoon 5 8568
Protoss_Observatory 1 6318
Protoss_Observer 1 7023
Protoss_Shuttle 1 7924
Protoss_Nexus 1 10257
Protoss_Zealot 2 9328
10257
