Protoss_Gateway 3 7817
Protoss_Assimilator 1 3060
Protoss_Cybernetics_Core 1 4004
Protoss_Dragoon 11 10718
Protoss_Robotics_Facility 1 7707
Protoss_Observatory 1 8374
Protoss_Observer 2 9736
Protoss_Nexus 1 11037
11037
