Protoss_Gateway 2 7224
Protoss_Assimilator 1 2820
Protoss_Cybernetics_Core 1 3778
Protoss_Robotics_Facility 1 5167
Protoss_Zealot 5 10408
Protoss_Dragoon 7 9018
Protoss_Observatory 1 5724
Protoss_Observer 3 9448
Protoss_Shuttle 1 8095
Protoss_Nexus 1 11193
Protoss_Citadel_of_Adun 1 10829
11193
