Protoss_Gateway 3 7676
Protoss_Assimilator 1 2911
Protoss_Zealot 1 3553
Protoss_Cybernetics_Core 1 4311
Protoss_Robotics_Facility 1 5822
Protoss_Dragoon 8 10003
Protoss_Observatory 1 6495
Protoss_Observer 4 9875
Protoss_Nexus 1 9410
Protoss_Shuttle 1 10776
10776
