Protoss_Gateway 3 7160
Protoss_Assimilator 1 3033
Protoss_Cybernetics_Core 1 3884
Protoss_Dragoon 6 9855
Protoss_Citadel_of_Adun 1 5729
Protoss_Templar_Archives 1 6830
Protoss_Dark_Templar 3 8003
Protoss_Robotics_Facility 1 10347
Protoss_Zealot 2 10198
10347
