Protoss_Gateway 3 7145
Protoss_Assimilator 1 3114
Protoss_Zealot 6 10280
Protoss_Cybernetics_Core 1 4639
Protoss_Dragoon 6 8760
Protoss_Robotics_Facility 1 6234
Protoss_Observatory 1 6798
Protoss_Shuttle 1 7557
Protoss_Observer 2 9220
Protoss_Nexus 1 10725
10725
