Protoss_Assimilator 2 3580
Protoss_Gateway 3 10754
Protoss_Zealot 2 5063
Protoss_Cybernetics_Core 1 5024
Protoss_Dragoon 1 5873
Protoss_Citadel_of_Adun 1 6909
Protoss_Nexus 1 8415
Protoss_Templar_Archives 1 7954
Protoss_Robotics_Facility 1 8698
Protoss_Dark_Templar 2 9863
Protoss_Shuttle 1 9887
Protoss_Observatory 1 9816
Protoss_Observer 1 10503
10754
