Protoss_Assimilator 1 2342
Protoss_Gateway 2 7353
Protoss_Cybernetics_Core 1 4139
Protoss_Dragoon 4 7528
Protoss_Robotics_Facility 1 5823
Protoss_Observatory 1 6416
Protoss_Citadel_of_Adun 1 6940
Protoss_Observer 2 7715
Protoss_Templar_Archives 1 8043
Protoss_Zealot 1 8113
Protoss_Shuttle 1 8772
Protoss_Dark_Templar 4 9913
Protoss_Nexus 1 11215
11215
