Protoss_Gateway 2 8549
Protoss_Assimilator 1 2915
Protoss_Cybernetics_Core 1 4077
Protoss_Dragoon 9 10429
Protoss_Robotics_Facility 1 5977
Protoss_Observatory 1 6526
Protoss_Observer 4 10063
Protoss_Nexus 1 9003
10429
