Protoss_Gateway 2 6471
Protoss_Assimilator 1 3087
Protoss_Cybernetics_Core 1 3946
Protoss_Zealot 1 3798
Protoss_Dragoon 9 10633
Protoss_Robotics_Facility 1 7840
Protoss_Observatory 1 8533
10633
