Protoss_Gateway 2 6840
Protoss_Assimilator 1 3232
Protoss_Cybernetics_Core 1 4037
Protoss_Dragoon 4 8898
Protoss_Robotics_Facility 1 6087
Protoss_Observatory 1 6727
Protoss_Observer 1 7418
8898
