Protoss_Gateway 2 7705
Protoss_Assimilator 4 4191
Protoss_Cybernetics_Core 1 4344
Protoss_Dragoon 5 10328
Protoss_Citadel_of_Adun 1 6602
Protoss_Robotics_Facility 1 7744
Protoss_Zealot 1 7608
Protoss_Templar_Archives 1 8404
Protoss_Shuttle 1 9107
Protoss_Dark_Templar 2 9248
Protoss_Observatory 1 9564
Protoss_Nexus 1 11130
11130
