Protoss_Gateway 1 2862
Protoss_Assimilator 1 3133
Protoss_Zealot 2 4718
Protoss_Cybernetics_Core 1 4759
Protoss_Dragoon 6 10248
Protoss_Robotics_Facility 1 6678
Protoss_Shuttle 1 7917
Protoss_Robotics_Support_Bay 1 7670
Protoss_Reaver 2 10093
10248
