Protoss_Gateway 3 9529
Protoss_Assimilator 1 3115
Protoss_Cybernetics_Core 1 4059
Protoss_Robotics_Facility 1 5527
Protoss_Shuttle 1 6517
Protoss_Observatory 1 6096
Protoss_Dragoon 8 10453
Protoss_Observer 4 9910
Protoss_Nexus 2 11730
11730
