Protoss_Gateway 2 6863
Protoss_Assimilator 1 3084
Protoss_Cybernetics_Core 1 4053
Protoss_Dragoon 6 8084
Protoss_Robotics_Facility 1 6681
Protoss_Observatory 1 7291
Protoss_Observer 1 7974
Protoss_Shuttle 1 9025
Protoss_Zealot 2 8884
Protoss_Nexus 2 11791
11791
