Protoss_Gateway 1 2892
Protoss_Assimilator 1 3305
Protoss_Zealot 7 9210
Protoss_Cybernetics_Core 1 4985
Protoss_Dragoon 3 10198
Protoss_Robotics_Facility 1 6583
Protoss_Shuttle 1 7577
Protoss_Robotics_Support_Bay 1 7492
Protoss_Reaver 2 9778
Protoss_Observatory 1 9409
Protoss_Citadel_of_Adun 1 10064
Protoss_Observer 1 10382
10382
