Protoss_Gateway 2 8612
Protoss_Assimilator 1 3215
Protoss_Cybernetics_Core 1 4109
Protoss_Dragoon 9 10728
Protoss_Robotics_Facility 1 6158
Protoss_Observatory 1 6847
Protoss_Observer 2 8155
Protoss_Shuttle 1 9282
Protoss_Nexus 1 11392
11392
