Protoss_Gateway 2 10864
Protoss_Assimilator 1 3090
Protoss_Zealot 4 9043
Protoss_Cybernetics_Core 1 4710
Protoss_Dragoon 5 10568
Protoss_Robotics_Facility 1 6637
Protoss_Shuttle 2 10327
Protoss_Robotics_Support_Bay 1 7577
Protoss_Reaver 1 8898
10864
