Protoss_Gateway 3 9059
Protoss_Assimilator 1 3222
Protoss_Cybernetics_Core 1 4239
Protoss_Dragoon 8 10048
Protoss_Nexus 1 8510
Protoss_Robotics_Facility 1 8727
Protoss_Observatory 1 9282
Protoss_Observer 1 10048
10048
