Protoss_Gateway 1 2831
Protoss_Assimilator 1 3072
Protoss_Cybernetics_Core 1 3993
Protoss_Zealot 1 3808
Protoss_Dragoon 7 10079
Protoss_Robotics_Facility 1 6211
Protoss_Observatory 1 6947
Protoss_Observer 2 8270
Protoss_Shuttle 1 9427
Protoss_Nexus 1 11563
Protoss_Citadel_of_Adun 1 10736
11563
