Protoss_Gateway 2 7395
Protoss_Assimilator 1 3085
Protoss_Cybernetics_Core 1 3980
Protoss_Dragoon 3 10093
Protoss_Robotics_Facility 1 6178
Protoss_Citadel_of_Adun 1 6208
Protoss_Templar_Archives 1 7226
Protoss_Observatory 1 7207
Protoss_Observer 1 7898
Protoss_Dark_Templar 4 9318
Protoss_Shuttle 1 8799
Protoss_Nexus 1 11687
11687
