Protoss_Gateway 2 5223
Protoss_Assimilator 1 3135
Protoss_Zealot 1 3548
Protoss_Cybernetics_Core 1 4584
Protoss_Dragoon 9 10453
Protoss_Robotics_Facility 1 7177
Protoss_Robotics_Support_Bay 1 7822
Protoss_Shuttle 1 8447
Protoss_Reaver 1 9616
10453
