Protoss_Gateway 3 7865
Protoss_Assimilator 1 3523
Protoss_Zealot 2 4270
Protoss_Cybernetics_Core 1 4929
Protoss_Dragoon 12 10594
Protoss_Robotics_Facility 1 7229
Protoss_Observatory 1 7837
Protoss_Observer 3 10170
10594
