Protoss_Gateway 2 3378
Protoss_Zealot 5 5338
Protoss_Assimilator 1 3982
Protoss_Cybernetics_Core 1 6408
Protoss_Dragoon 10 10518
Protoss_Robotics_Facility 1 8293
Protoss_Shuttle 1 9359
Protoss_Observatory 1 9058
Protoss_Observer 1 10110
Protoss_Robotics_Support_Bay 1 10291
10518
