Protoss_Nexus 1 4703
Protoss_Assimilator 1 3850
Protoss_Gateway 4 9424
Protoss_Cybernetics_Core 1 5806
Protoss_Dragoon 9 10278
Protoss_Robotics_Facility 1 8347
Protoss_Observatory 1 9189
Protoss_Forge 1 9618
Protoss_Observer 1 10093
Protoss_Photon_Cannon 2 10595
10595
