Protoss_Gateway 3 9931
Protoss_Assimilator 1 3131
Protoss_Zealot 3 4970
Protoss_Cybernetics_Core 1 5798
Protoss_Dragoon 7 9515
Protoss_Robotics_Facility 1 7667
Protoss_Observatory 1 8313
Protoss_Observer 2 9900
9931
