Protoss_Nexus 1 4907
Protoss_Gateway 2 6229
Protoss_Zealot 4 7464
Protoss_Assimilator 2 7368
Protoss_Cybernetics_Core 1 7149
Protoss_Forge 1 7278
Protoss_Dragoon 6 10096
Protoss_Photon_Cannon 3 9434
Protoss_Citadel_of_Adun 1 9727
Protoss_Templar_Archives 1 10779
10779
