Protoss_Gateway 3 10728
Protoss_Zealot 7 6798
Protoss_Nexus 1 7240
Protoss_Assimilator 1 6156
Protoss_Cybernetics_Core 1 6769
Protoss_Forge 1 7816
Protoss_Citadel_of_Adun 1 8146
Protoss_Photon_Cannon 1 8880
Protoss_Dragoon 4 10703
10728
