Protoss_Gateway 4 10837
Protoss_Zealot 6 9602
Protoss_Assimilator 1 5082
Protoss_Cybernetics_Core 1 5771
Protoss_Dragoon 9 10518
Protoss_Nexus 1 10171
Protoss_Robotics_Facility 1 10113
10837
