Protoss_Gateway 4 10457
Protoss_Assimilator 2 5402
Protoss_Zealot 9 6834
Protoss_Cybernetics_Core 1 6572
Protoss_Dragoon 8 10516
Protoss_Robotics_Facility 1 9511
Protoss_Observatory 1 10230
10516
