Protoss_Gateway 2 6349
Protoss_Zealot 6 10356
Protoss_Assimilator 1 3665
Protoss_Cybernetics_Core 1 5475
Protoss_Citadel_of_Adun 1 6487
Protoss_Dragoon 1 6468
Protoss_Templar_Archives 1 7473
Protoss_Forge 1 7919
Protoss_Dark_Templar 2 8316
Protoss_High_Templar 2 9068
Protoss_Photon_Cannon 4 10315
Protoss_Nexus 1 10367
10367
