Protoss_Gateway 2 7307
Protoss_Zealot 3 4758
Protoss_Assimilator 1 3727
Protoss_Cybernetics_Core 1 4829
Protoss_Dragoon 8 10744
Protoss_Robotics_Facility 1 8191
Protoss_Observatory 1 8856
Protoss_Observer 2 10138
Protoss_Nexus 1 11022
Protoss_Robotics_Support_Bay 1 10237
11022
