Protoss_Gateway 3 10697
Protoss_Zealot 6 5930
Protoss_Assimilator 1 5447
Protoss_Shield_Battery 1 6128
Protoss_Cybernetics_Core 2 7128
Protoss_Nexus 1 8711
Protoss_Dragoon 5 9898
Protoss_Robotics_Facility 1 10159
10697
