Protoss_Nexus 2 10867
Protoss_Gateway 3 8197
Protoss_Assimilator 2 10094
Protoss_Cybernetics_Core 1 5374
Protoss_Zealot 1 5484
Protoss_Dragoon 10 10708
Protoss_Robotics_Facility 1 9480
Protoss_Observatory 1 10045
Protoss_Forge 1 10241
10867
