Protoss_Nexus 1 5226
Protoss_Gateway 6 10050
Protoss_Assimilator 1 4878
Protoss_Zealot 5 10038
Protoss_Cybernetics_Core 1 5725
Protoss_Dragoon 6 10158
Protoss_Robotics_Facility 1 7477
Protoss_Observatory 1 8154
Protoss_Observer 1 8923
Protoss_Citadel_of_Adun 1 9875
10158
