Protoss_Gateway 2 3427
Protoss_Zealot 7 7236
Protoss_Nexus 1 7155
Protoss_Assimilator 2 9180
Protoss_Cybernetics_Core 1 7376
Protoss_Citadel_of_Adun 1 8419
Protoss_Forge 1 8583
Protoss_Dragoon 2 8980
Protoss_Templar_Archives 1 9617
Protoss_Photon_Cannon 1 9615
Protoss_Dark_Templar 2 10452
10452
