Protoss_Gateway 2 5833
Protoss_Zealot 3 4656
Protoss_Assimilator 1 3641
Protoss_Cybernetics_Core 1 5394
Protoss_Dragoon 8 9334
Protoss_Robotics_Facility 1 7816
Protoss_Observatory 1 8363
Protoss_Observer 1 9088
Protoss_Citadel_of_Adun 1 9904
Protoss_Nexus 1 11392
11392
