Protoss_Nexus 1 4675
Protoss_Gateway 4 9783
Protoss_Assimilator 2 9242
Protoss_Cybernetics_Core 1 5433
Protoss_Dragoon 11 10622
Protoss_Robotics_Facility 1 8360
Protoss_Zealot 4 10536
Protoss_Observatory 1 8947
Protoss_Citadel_of_Adun 1 9863
Protoss_Observer 1 10372
10622
