Protoss_Nexus 1 5123
Protoss_Gateway 4 8232
Protoss_Assimilator 2 9459
Protoss_Cybernetics_Core 1 5724
Protoss_Zealot 3 10488
Protoss_Dragoon 11 9944
Protoss_Citadel_of_Adun 1 9210
Protoss_Forge 1 9365
Protoss_Photon_Cannon 1 10296
10488
