Protoss_Gateway 2 3463
Protoss_Zealot 5 5468
Protoss_Assimilator 1 5026
Protoss_Cybernetics_Core 1 5989
Protoss_Robotics_Facility 1 7382
Protoss_Dragoon 1 7278
Protoss_Shuttle 1 8377
Protoss_Robotics_Support_Bay 1 7961
Protoss_Nexus 1 9781
Protoss_Reaver 1 9428
Protoss_Observatory 1 9226
Protoss_Observer 1 10032
10032
