Protoss_Gateway 5 10565
Protoss_Assimilator 1 3130
Protoss_Cybernetics_Core 1 4140
Protoss_Dragoon 8 10160
Protoss_Robotics_Facility 1 6259
Protoss_Observatory 1 7006
Protoss_Nexus 1 8625
Protoss_Observer 2 8858
10565
