Protoss_Gateway 3 8140
Protoss_Assimilator 1 3003
Protoss_Zealot 3 5064
Protoss_Cybernetics_Core 1 4446
Protoss_Dragoon 12 10646
Protoss_Robotics_Facility 1 8477
Protoss_Observatory 1 9373
10646
