Protoss_Assimilator 1 2360
Protoss_Gateway 1 3208
Protoss_Cybernetics_Core 1 4204
Protoss_Robotics_Facility 1 5497
Protoss_Dragoon 4 10623
Protoss_Shuttle 1 6487
Protoss_Robotics_Support_Bay 1 6104
Protoss_Observatory 1 6260
Protoss_Observer 1 7090
Protoss_Reaver 3 10244
Protoss_Nexus 1 9615
Protoss_Shield_Battery 1 10153
10623
