Protoss_Gateway 3 10808
Protoss_Assimilator 1 2910
Protoss_Cybernetics_Core 1 3919
Protoss_Dragoon 6 10278
Protoss_Citadel_of_Adun 1 7127
Protoss_Nexus 1 8305
Protoss_Templar_Archives 1 8149
Protoss_Dark_Templar 3 10532
Protoss_Robotics_Facility 1 9987
10808
