Protoss_Nexus 2 9828
Protoss_Gateway 3 6234
Protoss_Assimilator 1 4644
Protoss_Cybernetics_Core 1 5247
Protoss_Dragoon 5 9313
Protoss_Zealot 3 9708
Protoss_Robotics_Facility 1 8712
Protoss_Citadel_of_Adun 1 9194
Protoss_Observatory 1 9281
Protoss_Shuttle 1 10002
Protoss_Forge 1 10518
10518
