Protoss_Gateway 2 10365
Protoss_Zealot 3 5108
Protoss_Assimilator 1 4055
Protoss_Cybernetics_Core 1 4943
Protoss_Dragoon 6 10678
Protoss_Robotics_Facility 1 7047
Protoss_Shuttle 1 8112
Protoss_Observatory 1 7781
Protoss_Observer 1 8715
Protoss_Robotics_Support_Bay 1 8885
Protoss_Reaver 1 10441
Protoss_Nexus 1 11522
11522
