Protoss_Assimilator 1 2293
Protoss_Gateway 2 6420
Protoss_Cybernetics_Core 1 4244
Protoss_Robotics_Facility 1 5542
Protoss_Dragoon 8 9663
Protoss_Observatory 1 6111
Protoss_Observer 2 7395
Protoss_Shuttle 1 8355
Protoss_Robotics_Support_Bay 1 8413
Protoss_Reaver 2 10768
10768
