Protoss_Gateway 2 8547
Protoss_Assimilator 1 3475
Protoss_Zealot 2 4683
Protoss_Cybernetics_Core 1 4582
Protoss_Dragoon 4 8233
Protoss_Robotics_Facility 2 11088
Protoss_Citadel_of_Adun 1 7216
Protoss_Templar_Archives 1 8300
Protoss_Dark_Templar 3 9935
Protoss_Forge 1 10405
11088
