Protoss_Gateway 2 5065
Protoss_Assimilator 1 3090
Protoss_Zealot 3 5053
Protoss_Cybernetics_Core 1 4709
Protoss_Dragoon 8 9563
Protoss_Citadel_of_Adun 1 8465
Protoss_Templar_Archives 1 9464
Protoss_Dark_Templar 2 10348
Protoss_Forge 1 10448
10448
