Protoss_Gateway 3 10688
Protoss_Zealot 4 6770
Protoss_Assimilator 1 3660
Protoss_Cybernetics_Core 1 4806
Protoss_Robotics_Facility 1 6243
Protoss_Dragoon 5 10062
Protoss_Shuttle 1 7333
Protoss_Robotics_Support_Bay 1 7195
Protoss_Reaver 2 10678
Protoss_Observatory 1 8094
Protoss_Observer 1 10078
10688
