Protoss_Gateway 2 8486
Protoss_Zealot 3 5113
Protoss_Assimilator 1 3869
Protoss_Cybernetics_Core 1 5028
Protoss_Dragoon 8 10410
Protoss_Robotics_Facility 1 7847
Protoss_Observatory 1 8518
Protoss_Observer 1 9613
Protoss_Robotics_Support_Bay 1 9803
10410
