Protoss_Gateway 4 8160
Protoss_Assimilator 1 3135
Protoss_Cybernetics_Core 1 3984
Protoss_Dragoon 12 10743
Protoss_Robotics_Facility 1 6367
Protoss_Observatory 1 6911
Protoss_Observer 1 7593
Protoss_Zealot 6 9823
10743
