Protoss_Gateway 2 6049
Protoss_Zealot 3 5058
Protoss_Assimilator 1 4080
Protoss_Cybernetics_Core 1 5164
Protoss_Dragoon 11 10617
Protoss_Robotics_Facility 1 9327
Protoss_Robotics_Support_Bay 1 9931
Protoss_Shuttle 1 10387
Protoss_Observatory 1 10036
10617
