Protoss_Gateway 2 6711
Protoss_Assimilator 1 3159
Protoss_Cybernetics_Core 1 3983
Protoss_Zealot 1 4436
Protoss_Dragoon 12 10586
Protoss_Robotics_Facility 1 8566
Protoss_Shuttle 1 10381
Protoss_Robotics_Support_Bay 1 10241
Protoss_Observatory 1 10447
10586
