Protoss_Gateway 2 5713
Protoss_Assimilator 1 3154
Protoss_Zealot 9 7640
Protoss_Cybernetics_Core 1 6844
Protoss_Dragoon 2 8368
Protoss_Robotics_Facility 1 9061
Protoss_Forge 1 9324
Protoss_Photon_Cannon 1 10412
10412
