Protoss_Gateway 2 3510
Protoss_Zealot 6 7025
Protoss_Assimilator 1 5358
Protoss_Cybernetics_Core 1 6055
Protoss_Robotics_Facility 1 8908
Protoss_Dragoon 5 10592
Protoss_Robotics_Support_Bay 1 9773
10592
