Protoss_Gateway 2 6716
Protoss_Assimilator 1 2856
Protoss_Cybernetics_Core 1 4458
Protoss_Zealot 1 4588
Protoss_Dragoon 11 10324
Protoss_Robotics_Facility 1 8644
Protoss_Robotics_Support_Bay 1 10059
Protoss_Nexus 1 11629
11629
