Protoss_Gateway 4 9748
Protoss_Zealot 5 6796
Protoss_Nexus 1 6588
Protoss_Assimilator 2 8340
Protoss_Cybernetics_Core 1 6694
Protoss_Dragoon 5 10140
Protoss_Forge 1 8016
Protoss_Robotics_Facility 1 9636
Protoss_Photon_Cannon 1 10252
Protoss_Shuttle 1 10629
10629
