Protoss_Gateway 4 10806
Protoss_Zealot 10 7703
Protoss_Nexus 1 7905
Protoss_Assimilator 2 9322
Protoss_Cybernetics_Core 1 7931
Protoss_Dragoon 6 10718
Protoss_Robotics_Facility 1 10818
10818
