Protoss_Gateway 3 10640
Protoss_Zealot 5 7126
Protoss_Nexus 1 6821
Protoss_Assimilator 2 6754
Protoss_Cybernetics_Core 1 6707
Protoss_Citadel_of_Adun 1 8111
Protoss_Robotics_Facility 1 9060
Protoss_Dragoon 4 10156
Protoss_Templar_Archives 1 9393
Protoss_Forge 1 9726
Protoss_Observatory 1 9701
Protoss_Photon_Cannon 1 10626
Protoss_Observer 1 10510
10640
