Protoss_Gateway 2 3378
Protoss_Zealot 11 8306
Protoss_Nexus 1 6893
Protoss_Assimilator 2 9796
Protoss_Cybernetics_Core 1 8051
Protoss_Shield_Battery 1 8469
Protoss_Dragoon 2 9366
Protoss_Citadel_of_Adun 1 9964
9964
