Protoss_Gateway 2 3427
Protoss_Zealot 11 9144
Protoss_Nexus 2 11057
Protoss_Assimilator 2 7832
Protoss_Cybernetics_Core 1 6656
Protoss_Dragoon 2 7510
Protoss_Citadel_of_Adun 1 8050
Protoss_Templar_Archives 1 9163
Protoss_Forge 1 8876
Protoss_Dark_Templar 2 10248
Protoss_Photon_Cannon 2 10634
11057
