Protoss_Gateway 4 10514
Protoss_Zealot 8 7278
Protoss_Nexus 1 7497
Protoss_Assimilator 2 9497
Protoss_Forge 1 7102
Protoss_Cybernetics_Core 1 8084
Protoss_Photon_Cannon 3 10730
Protoss_Dragoon 4 10583
10730
