Protoss_Gateway 4 9093
Protoss_Zealot 13 10100
Protoss_Nexus 1 5975
Protoss_Assimilator 2 7195
Protoss_Cybernetics_Core 1 6946
Protoss_Dragoon 2 7910
Protoss_Citadel_of_Adun 1 8445
Protoss_Robotics_Facility 1 10008
Protoss_Forge 1 10266
10266
