Protoss_Gateway 2 6624
Protoss_Zealot 3 4682
Protoss_Assimilator 1 4967
Protoss_Nexus 1 6267
Protoss_Cybernetics_Core 1 5992
Protoss_Forge 1 6002
Protoss_Dragoon 7 10626
Protoss_Photon_Cannon 3 10327
Protoss_Robotics_Facility 1 9609
Protoss_Observatory 1 10149
Protoss_Citadel_of_Adun 1 10872
10872
