Protoss_Gateway 3 6715
Protoss_Zealot 5 6676
Protoss_Assimilator 2 10550
Protoss_Cybernetics_Core 1 5143
Protoss_Dragoon 6 10242
Protoss_Forge 1 7676
Protoss_Photon_Cannon 2 9734
Protoss_Nexus 1 9827
Protoss_Citadel_of_Adun 1 9502
Protoss_Robotics_Facility 1 10466
Protoss_Templar_Archives 1 10611
10611
