Protoss_Gateway 3 8515
Protoss_Assimilator 1 3075
Protoss_Zealot 1 3498
Protoss_Cybernetics_Core 1 4717
Protoss_Dragoon 9 10340
Protoss_Nexus 1 7932
Protoss_Robotics_Facility 1 8205
Protoss_Observatory 1 8800
Protoss_Observer 2 10138
Protoss_Citadel_of_Adun 1 9967
10340
