Protoss_Gateway 2 3399
Protoss_Zealot 5 5163
Protoss_Assimilator 1 4415
Protoss_Cybernetics_Core 1 5099
Protoss_Dragoon 9 10665
Protoss_Forge 1 7489
Protoss_Nexus 1 10060
Protoss_Photon_Cannon 2 9570
10665
