Protoss_Assimilator 1 2255
Protoss_Gateway 1 3147
Protoss_Cybernetics_Core 1 4225
Protoss_Stargate 1 5386
Protoss_Robotics_Facility 1 5985
Protoss_Corsair 3 7277
Protoss_Shuttle 1 6992
Protoss_Forge 1 7534
Protoss_Dragoon 4 10398
Protoss_Photon_Cannon 2 10071
Protoss_Fleet_Beacon 1 10000
10398
