Protoss_Gateway 4 9333
Protoss_Zealot 5 7652
Protoss_Nexus 2 11443
Protoss_Assimilator 2 7490
Protoss_Cybernetics_Core 1 6660
Protoss_Citadel_of_Adun 1 7761
Protoss_Dragoon 1 7712
Protoss_Templar_Archives 1 8753
Protoss_Robotics_Facility 1 9352
Protoss_Forge 1 9336
Protoss_Dark_Templar 2 9640
Protoss_Observatory 1 9919
Protoss_Photon_Cannon 2 10711
Protoss_High_Templar 2 10496
11443
