Protoss_Gateway 2 5377
Protoss_Assimilator 1 3096
Protoss_Zealot 2 4553
Protoss_Cybernetics_Core 1 4711
Protoss_Dragoon 6 10563
Protoss_Citadel_of_Adun 1 5814
Protoss_Templar_Archives 1 6884
Protoss_Dark_Templar 3 8485
Protoss_Forge 1 7980
Protoss_Nexus 1 10500
Protoss_Photon_Cannon 2 10158
10563
