Protoss_Gateway 2 4611
Protoss_Assimilator 1 2976
Protoss_Cybernetics_Core 1 3766
Protoss_Zealot 4 6020
Protoss_Dragoon 3 7372
Protoss_Citadel_of_Adun 1 6985
Protoss_Templar_Archives 1 8013
Protoss_Forge 1 8060
Protoss_Dark_Templar 2 9100
Protoss_Photon_Cannon 2 9328
Protoss_Nexus 1 11584
11584
