Protoss_Gateway 2 3443
Protoss_Zealot 14 10028
Protoss_Nexus 1 6993
Protoss_Assimilator 1 6445
Protoss_Cybernetics_Core 1 7319
Protoss_Citadel_of_Adun 1 8507
Protoss_Templar_Archives 1 9711
Protoss_Forge 1 9476
Protoss_Shield_Battery 1 9803
10028
