Protoss_Assimilator 1 2493
Protoss_Gateway 1 3164
Protoss_Cybernetics_Core 1 4357
Protoss_Robotics_Facility 1 5647
Protoss_Dragoon 4 10150
Protoss_Robotics_Support_Bay 1 6211
Protoss_Shuttle 4 10727
Protoss_Reaver 1 7916
10727
