Protoss_Gateway 3 9368
Protoss_Assimilator 1 3184
Protoss_Zealot 2 4736
Protoss_Cybernetics_Core 1 4882
Protoss_Dragoon 10 10516
Protoss_Robotics_Facility 1 8538
Protoss_Shuttle 1 9539
Protoss_Robotics_Support_Bay 1 9517
Protoss_Observatory 1 9635
Protoss_Reaver 1 10654
10654
