Protoss_Gateway 2 6122
Protoss_Assimilator 1 2941
Protoss_Zealot 3 4738
Protoss_Cybernetics_Core 1 4697
Protoss_Dragoon 6 8018
Protoss_Citadel_of_Adun 1 8527
Protoss_Robotics_Facility 1 9594
Protoss_Templar_Archives 1 9511
Protoss_Shuttle 1 10575
Protoss_Dark_Templar 2 10528
Protoss_Observatory 1 10427
10575
