Protoss_Gateway 4 10641
Protoss_Zealot 5 6810
Protoss_Nexus 1 6662
Protoss_Assimilator 2 7262
Protoss_Cybernetics_Core 1 6427
Protoss_Dragoon 6 10262
Protoss_Citadel_of_Adun 1 8401
Protoss_Robotics_Facility 1 9196
Protoss_Forge 1 9367
Protoss_Templar_Archives 1 9881
Protoss_Observatory 1 9904
Protoss_Photon_Cannon 1 10588
10641
