Protoss_Gateway 3 9516
Protoss_Assimilator 1 2925
Protoss_Cybernetics_Core 1 3991
Protoss_Dragoon 12 10738
Protoss_Robotics_Facility 1 7172
Protoss_Nexus 1 9115
Protoss_Observatory 1 7908
Protoss_Observer 2 9350
10738
