Protoss_Gateway 3 9258
Protoss_Assimilator 1 2935
Protoss_Cybernetics_Core 1 3750
Protoss_Dragoon 8 9508
Protoss_Nexus 1 8470
Protoss_Robotics_Facility 1 8938
Protoss_Robotics_Support_Bay 1 9824
Protoss_Zealot 2 10158
10158
