Protoss_Gateway 2 7675
Protoss_Zealot 3 5338
Protoss_Assimilator 1 3618
Protoss_Cybernetics_Core 1 4931
Protoss_Dragoon 7 9688
Protoss_Citadel_of_Adun 1 7543
Protoss_Robotics_Facility 1 8601
Protoss_Observatory 1 9310
Protoss_Observer 1 10010
Protoss_Nexus 1 11457
11457
