Protoss_Gateway 2 4639
Protoss_Assimilator 1 3235
Protoss_Zealot 9 7318
Protoss_Cybernetics_Core 1 6715
Protoss_Dragoon 8 9973
Protoss_Robotics_Facility 1 9816
Protoss_Shuttle 1 10862
10862
