Protoss_Gateway 2 3555
Protoss_Zealot 10 9182
Protoss_Nexus 1 6996
Protoss_Assimilator 2 8294
Protoss_Cybernetics_Core 1 7479
Protoss_Citadel_of_Adun 1 8484
Protoss_Robotics_Facility 1 9727
Protoss_Templar_Archives 1 9958
Protoss_Forge 1 10353
Protoss_Dragoon 2 10606
Protoss_Observatory 1 10316
10606
