Protoss_Gateway 4 10114
Protoss_Zealot 5 9598
Protoss_Nexus 1 5969
Protoss_Assimilator 1 5080
Protoss_Cybernetics_Core 1 5817
Protoss_Dragoon 7 10370
Protoss_Robotics_Facility 1 9405
Protoss_Citadel_of_Adun 1 10513
Protoss_Shuttle 1 10819
10819
