Protoss_Gateway 3 9670
Protoss_Zealot 6 6936
Protoss_Nexus 1 6529
Protoss_Assimilator 2 7975
Protoss_Cybernetics_Core 1 6949
Protoss_Dragoon 2 7908
Protoss_Citadel_of_Adun 1 8454
Protoss_Forge 1 9159
Protoss_Templar_Archives 2 9702
Protoss_Robotics_Facility 1 10133
Protoss_Photon_Cannon 2 10277
10277
