Protoss_Gateway 3 8663
Protoss_Assimilator 1 3010
Protoss_Zealot 2 4552
Protoss_Cybernetics_Core 1 4557
Protoss_Dragoon 11 10358
Protoss_Robotics_Facility 1 6873
Protoss_Observatory 1 7499
Protoss_Observer 3 9460
Protoss_Nexus 1 11007
11007
