Protoss_Gateway 4 10390
Protoss_Zealot 2 4224
Protoss_Assimilator 1 3571
Protoss_Cybernetics_Core 1 4632
Protoss_Dragoon 11 10502
Protoss_Nexus 1 7969
Protoss_Robotics_Facility 1 8589
Protoss_Robotics_Support_Bay 1 9188
Protoss_Shuttle 1 10011
10502
