Protoss_Gateway 2 8067
Protoss_Zealot 2 4480
Protoss_Assimilator 1 3630
Protoss_Cybernetics_Core 1 4453
Protoss_Dragoon 10 10660
Protoss_Robotics_Facility 1 7337
Protoss_Shuttle 1 8317
Protoss_Robotics_Support_Bay 1 7955
Protoss_Reaver 2 10706
Protoss_Observatory 1 9825
10706
