Protoss_Gateway 2 7846
Protoss_Assimilator 1 2858
Protoss_Zealot 3 4684
Protoss_Cybernetics_Core 1 4643
Protoss_Dragoon 9 9736
Protoss_Robotics_Facility 1 8000
Protoss_Shuttle 1 9017
Protoss_Observatory 1 8636
Protoss_Robotics_Support_Bay 1 9227
Protoss_Observer 1 9620
Protoss_Reaver 1 10670
10670
