Protoss_Gateway 2 3295
Protoss_Zealot 9 8884
Protoss_Assimilator 1 4327
Protoss_Cybernetics_Core 1 5030
Protoss_Dragoon 4 6660
Protoss_Citadel_of_Adun 1 8215
Protoss_Templar_Archives 1 9325
Protoss_Forge 1 9314
Protoss_Robotics_Facility 1 10597
Protoss_Photon_Cannon 2 10288
Protoss_Dark_Templar 2 10706
10706
