Protoss_Gateway 2 7887
Protoss_Assimilator 1 3002
Protoss_Cybernetics_Core 1 3853
Protoss_Zealot 1 3808
Protoss_Dragoon 4 7236
Protoss_Citadel_of_Adun 1 6430
Protoss_Templar_Archives 1 7639
Protoss_Dark_Templar 4 9488
Protoss_Robotics_Facility 1 10542
10542
