Protoss_Gateway 2 3331
Protoss_Zealot 7 7070
Protoss_Nexus 1 6631
Protoss_Assimilator 2 8444
Protoss_Cybernetics_Core 1 7116
Protoss_Citadel_of_Adun 1 8230
Protoss_Dragoon 2 8284
Protoss_Templar_Archives 1 9231
Protoss_Forge 1 9377
Protoss_Dark_Templar 2 10068
Protoss_Photon_Cannon 2 10620
10620
