Protoss_Gateway 3 10274
Protoss_Assimilator 1 3019
Protoss_Zealot 2 4648
Protoss_Cybernetics_Core 1 4635
Protoss_Dragoon 8 10300
Protoss_Robotics_Facility 1 7141
Protoss_Robotics_Support_Bay 1 7693
Protoss_Observatory 1 7897
Protoss_Observer 1 8588
Protoss_Nexus 1 10265
Protoss_Reaver 1 9764
10300
