Protoss_Gateway 2 3357
Protoss_Zealot 9 7440
Protoss_Nexus 1 7462
Protoss_Assimilator 2 8762
Protoss_Cybernetics_Core 1 8094
Protoss_Dragoon 2 9166
Protoss_Citadel_of_Adun 1 9844
Protoss_Forge 1 9550
Protoss_Photon_Cannon 1 10587
Protoss_Templar_Archives 1 10829
10829
