Protoss_Gateway 1 2749
Protoss_Assimilator 1 2954
Protoss_Cybernetics_Core 1 3845
Protoss_Zealot 1 3742
Protoss_Dragoon 7 9704
Protoss_Robotics_Facility 1 6377
Protoss_Robotics_Support_Bay 1 6987
Protoss_Observatory 1 7004
Protoss_Reaver 3 10952
Protoss_Nexus 1 9678
Protoss_Observer 1 8722
10952
