Protoss_Gateway 3 10649
Protoss_Zealot 5 8232
Protoss_Nexus 1 5905
Protoss_Forge 1 5468
Protoss_Assimilator 2 7068
Protoss_Cybernetics_Core 1 6585
Protoss_Photon_Cannon 3 8963
Protoss_Dragoon 5 10446
Protoss_Robotics_Facility 1 8657
Protoss_Observatory 1 9197
Protoss_Observer 1 9886
10649
