Protoss_Gateway 3 10493
Protoss_Assimilator 1 2808
Protoss_Cybernetics_Core 1 3804
Protoss_Zealot 1 3750
Protoss_Dragoon 8 10616
Protoss_Citadel_of_Adun 1 5810
Protoss_Robotics_Facility 1 6250
Protoss_Templar_Archives 1 6895
Protoss_Shuttle 1 7335
Protoss_Dark_Templar 2 7750
Protoss_Nexus 1 10715
10715
