Protoss_Gateway 4 10867
Protoss_Assimilator 1 3048
Protoss_Cybernetics_Core 1 3937
Protoss_Dragoon 7 10182
Protoss_Zealot 2 10398
Protoss_Nexus 1 7771
Protoss_Robotics_Facility 1 7410
Protoss_Observatory 1 8057
Protoss_Robotics_Support_Bay 1 8104
Protoss_Observer 3 10128
10867
