Protoss_Gateway 3 7671
Protoss_Zealot 16 10576
Protoss_Nexus 1 7893
Protoss_Assimilator 2 9272
Protoss_Cybernetics_Core 1 8244
Protoss_Dragoon 2 9164
Protoss_Citadel_of_Adun 1 9805
Protoss_Forge 1 9971
Protoss_Robotics_Facility 1 10920
10920
