Protoss_Gateway 4 9997
Protoss_Zealot 11 9860
Protoss_Nexus 1 6659
Protoss_Assimilator 2 8591
Protoss_Cybernetics_Core 1 7136
Protoss_Citadel_of_Adun 1 8165
Protoss_Dragoon 2 8484
Protoss_Templar_Archives 1 9441
Protoss_Forge 1 9612
Protoss_Dark_Templar 2 10334
Protoss_Photon_Cannon 2 10621
10621
