Protoss_Gateway 2 8403
Protoss_Assimilator 1 2810
Protoss_Cybernetics_Core 1 3808
Protoss_Dragoon 8 9972
Protoss_Robotics_Facility 1 6409
Protoss_Observatory 1 7062
Protoss_Shuttle 1 7673
Protoss_Observer 2 8878
Protoss_Robotics_Support_Bay 1 8577
Protoss_Reaver 1 10048
10048
