Protoss_Gateway 4 10795
Protoss_Assimilator 2 9224
Protoss_Cybernetics_Core 1 3684
Protoss_Zealot 1 3686
Protoss_Dragoon 12 10406
Protoss_Nexus 1 7433
Protoss_Robotics_Facility 1 8907
Protoss_Observatory 1 9469
Protoss_Observer 1 10150
10795
