Protoss_Gateway 2 3455
Protoss_Zealot 12 8448
Protoss_Nexus 1 7333
Protoss_Assimilator 1 6413
Protoss_Cybernetics_Core 1 8079
Protoss_Forge 1 8077
Protoss_Photon_Cannon 5 10648
Protoss_Dragoon 4 10356
Protoss_Citadel_of_Adun 1 10191
10648
