Protoss_Gateway 4 9640
Protoss_Zealot 11 9310
Protoss_Nexus 1 6475
Protoss_Assimilator 2 8221
Protoss_Cybernetics_Core 1 8305
Protoss_Robotics_Facility 1 9885
Protoss_Citadel_of_Adun 1 9704
Protoss_Dragoon 3 10136
10136
