Protoss_Gateway 3 8795
Protoss_Assimilator 2 9670
Protoss_Cybernetics_Core 1 3830
Protoss_Zealot 4 10492
Protoss_Dragoon 8 9648
Protoss_Nexus 1 8162
Protoss_Robotics_Facility 1 8115
Protoss_Observatory 1 8726
Protoss_Observer 2 10058
Protoss_Citadel_of_Adun 1 10138
10492
