Protoss_Gateway 2 4421
Protoss_Assimilator 1 2840
Protoss_Cybernetics_Core 1 3807
Protoss_Dragoon 9 8194
Protoss_Robotics_Facility 1 7145
Protoss_Observatory 1 7745
Protoss_Observer 1 8438
Protoss_Zealot 4 9692
Protoss_Shuttle 1 9343
Protoss_Robotics_Support_Bay 1 9197
Protoss_Reaver 1 10444
10444
