Protoss_Gateway 4 10791
Protoss_Assimilator 1 2914
Protoss_Cybernetics_Core 1 3761
Protoss_Dragoon 14 10568
Protoss_Robotics_Facility 1 7361
Protoss_Observatory 1 7956
Protoss_Observer 2 9252
10791
