Protoss_Gateway 2 3283
Protoss_Zealot 5 5486
Protoss_Assimilator 1 4213
Protoss_Cybernetics_Core 1 5299
Protoss_Dragoon 9 10556
Protoss_Robotics_Facility 1 8875
Protoss_Nexus 1 10438
Protoss_Observatory 1 9427
Protoss_Shuttle 1 9969
Protoss_Robotics_Support_Bay 1 10029
10556
