Protoss_Gateway 2 8783
Protoss_Assimilator 2 10572
Protoss_Zealot 1 3372
Protoss_Cybernetics_Core 1 3969
Protoss_Dragoon 5 10492
Protoss_Citadel_of_Adun 1 5481
Protoss_Templar_Archives 1 6563
Protoss_Dark_Templar 2 8166
Protoss_Nexus 1 9009
Protoss_Robotics_Facility 1 9621
Protoss_Observatory 1 10225
10572
