Protoss_Gateway 3 10865
Protoss_Zealot 3 5360
Protoss_Assimilator 2 10135
Protoss_Cybernetics_Core 1 4462
Protoss_Citadel_of_Adun 1 5514
Protoss_Dragoon 1 6112
Protoss_Templar_Archives 1 6518
Protoss_Forge 1 6381
Protoss_Dark_Templar 2 8366
Protoss_Nexus 1 8659
Protoss_Photon_Cannon 6 10514
Protoss_High_Templar 2 10288
10865
