Protoss_Gateway 2 7511
Protoss_Assimilator 1 3058
Protoss_Zealot 2 4246
Protoss_Cybernetics_Core 1 4726
Protoss_Dragoon 10 10552
Protoss_Robotics_Facility 1 7083
Protoss_Observatory 1 7675
Protoss_Observer 2 8984
Protoss_Robotics_Support_Bay 1 8639
Protoss_Shuttle 1 9465
Protoss_Reaver 1 10560
10560
