Protoss_Gateway 2 3141
Protoss_Zealot 12 8938
Protoss_Shield_Battery 2 6033
Protoss_Forge 1 5820
Protoss_Photon_Cannon 4 8639
Protoss_Assimilator 1 8339
Protoss_Cybernetics_Core 1 9630
Protoss_Stargate 1 10918
10918
