Protoss_Gateway 2 3236
Protoss_Zealot 6 6142
Protoss_Assimilator 1 4625
Protoss_Cybernetics_Core 1 5619
Protoss_Dragoon 7 10628
Protoss_Nexus 2 10453
Protoss_Robotics_Facility 1 10141
10628
