Protoss_Gateway 3 10119
Protoss_Assimilator 1 3093
Protoss_Zealot 1 3488
Protoss_Cybernetics_Core 1 4065
Protoss_Dragoon 11 10576
Protoss_Nexus 1 9447
Protoss_Robotics_Facility 1 9791
Protoss_Observatory 1 10424
10576
