Protoss_Gateway 4 10527
Protoss_Zealot 6 7902
Protoss_Nexus 1 6748
Protoss_Assimilator 2 8238
Protoss_Cybernetics_Core 1 6490
Protoss_Dragoon 1 7540
Protoss_Citadel_of_Adun 1 7931
Protoss_Forge 1 8336
Protoss_Templar_Archives 1 9029
Protoss_Photon_Cannon 1 9748
Protoss_Dark_Templar 2 9866
Protoss_Robotics_Facility 1 10652
10652
