Protoss_Gateway 4 10787
Protoss_Assimilator 1 3523
Protoss_Cybernetics_Core 1 4616
Protoss_Zealot 2 4866
Protoss_Dragoon 9 9478
Protoss_Robotics_Facility 1 7610
Protoss_Observatory 1 8213
Protoss_Observer 2 9734
Protoss_Nexus 1 10675
10787
