Protoss_Gateway 2 3359
Protoss_Zealot 7 8366
Protoss_Assimilator 2 6985
Protoss_Nexus 1 6761
Protoss_Cybernetics_Core 1 6447
Protoss_Citadel_of_Adun 1 7525
Protoss_Dragoon 2 7542
Protoss_Templar_Archives 1 8563
Protoss_Robotics_Facility 1 9321
Protoss_High_Templar 4 10538
Protoss_Forge 1 9407
Protoss_Shuttle 1 10325
Protoss_Photon_Cannon 2 10483
10538
