Protoss_Gateway 2 5609
Protoss_Assimilator 1 2862
Protoss_Zealot 3 5062
Protoss_Cybernetics_Core 1 4941
Protoss_Dragoon 10 10640
Protoss_Robotics_Facility 1 8767
Protoss_Nexus 1 10905
Protoss_Observatory 1 9772
Protoss_Citadel_of_Adun 1 10829
Protoss_Observer 1 10536
10905
