Protoss_Gateway 3 9330
Protoss_Zealot 3 4964
Protoss_Assimilator 1 3698
Protoss_Cybernetics_Core 1 4471
Protoss_Dragoon 10 10682
Protoss_Nexus 1 8735
Protoss_Robotics_Facility 1 8501
Protoss_Observatory 1 9074
Protoss_Observer 2 10488
10682
