Protoss_Gateway 3 10850
Protoss_Assimilator 1 3404
Protoss_Zealot 3 4848
Protoss_Cybernetics_Core 1 4447
Protoss_Dragoon 10 10326
Protoss_Nexus 1 9485
Protoss_Robotics_Facility 1 9317
Protoss_Shuttle 1 10359
Protoss_Observatory 1 10072
10850
