Protoss_Gateway 4 6362
Protoss_Zealot 12 10358
Protoss_Shield_Battery 1 4382
Protoss_Forge 1 6989
Protoss_Assimilator 1 7526
Protoss_Photon_Cannon 4 10195
Protoss_Cybernetics_Core 1 8907
Protoss_Robotics_Facility 2 10909
10909
