Protoss_Gateway 2 3332
Protoss_Zealot 4 6380
Protoss_Nexus 1 5859
Protoss_Assimilator 2 7745
Protoss_Cybernetics_Core 1 6242
Protoss_Dragoon 2 7252
Protoss_Citadel_of_Adun 1 7820
Protoss_Forge 1 7874
Protoss_Templar_Archives 1 8919
Protoss_Robotics_Facility 1 9316
Protoss_Photon_Cannon 5 10345
Protoss_Observatory 1 10216
Protoss_Dark_Templar 2 10542
10542
