Protoss_Gateway 3 10185
Protoss_Zealot 11 10088
Protoss_Assimilator 2 7334
Protoss_Cybernetics_Core 1 6455
Protoss_Nexus 1 7649
Protoss_Citadel_of_Adun 1 7794
Protoss_Dragoon 2 8088
Protoss_Robotics_Facility 1 9478
Protoss_Templar_Archives 1 10769
10769
