Protoss_Gateway 2 3319
Protoss_Zealot 19 10198
Protoss_Nexus 1 7394
Protoss_Assimilator 2 9263
Protoss_Cybernetics_Core 1 7835
Protoss_Citadel_of_Adun 1 9377
Protoss_Templar_Archives 1 10440
10440
