Protoss_Gateway 2 7003
Protoss_Zealot 3 4762
Protoss_Assimilator 1 3957
Protoss_Cybernetics_Core 1 4721
Protoss_Dragoon 9 10630
Protoss_Robotics_Facility 1 8182
Protoss_Forge 1 8305
Protoss_Observatory 1 8772
Protoss_Photon_Cannon 5 9538
Protoss_Observer 2 10288
10630
