Protoss_Gateway 3 9391
Protoss_Assimilator 1 2910
Protoss_Cybernetics_Core 1 3835
Protoss_Zealot 1 3858
Protoss_Dragoon 9 10688
Protoss_Nexus 1 9044
Protoss_Robotics_Facility 1 9987
10688
