Protoss_Gateway 4 9814
Protoss_Assimilator 1 3295
Protoss_Zealot 5 10308
Protoss_Cybernetics_Core 1 4728
Protoss_Dragoon 12 10656
Protoss_Robotics_Facility 1 7969
Protoss_Observatory 1 8505
Protoss_Observer 2 10000
10656
