Protoss_Gateway 1 2711
Protoss_Assimilator 1 2812
Protoss_Cybernetics_Core 1 3812
Protoss_Dragoon 6 10688
Protoss_Robotics_Facility 1 6666
Protoss_Shuttle 1 7647
Protoss_Robotics_Support_Bay 1 7313
Protoss_Reaver 1 8734
Protoss_Observatory 1 9211
Protoss_Nexus 1 10851
Protoss_Observer 1 10152
10851
