Protoss_Gateway 3 10369
Protoss_Assimilator 1 2788
Protoss_Cybernetics_Core 1 3723
Protoss_Zealot 2 7534
Protoss_Dragoon 8 10102
Protoss_Citadel_of_Adun 1 6352
Protoss_Templar_Archives 1 7437
Protoss_Dark_Templar 2 8286
Protoss_Nexus 1 10002
Protoss_Robotics_Facility 1 10998
10998
