Protoss_Gateway 2 6111
Protoss_Zealot 2 4268
Protoss_Assimilator 2 10327
Protoss_Cybernetics_Core 1 5392
Protoss_Dragoon 7 9624
Protoss_Nexus 1 9169
Protoss_Robotics_Facility 1 8996
Protoss_Observatory 1 9632
Protoss_Observer 1 10390
Protoss_Citadel_of_Adun 1 10893
10893
