Protoss_Gateway 2 4877
Protoss_Zealot 1 3424
Protoss_Assimilator 1 3574
Protoss_Cybernetics_Core 1 4475
Protoss_Dragoon 12 10536
Protoss_Robotics_Facility 1 8489
Protoss_Shuttle 1 9753
Protoss_Observatory 1 9378
Protoss_Nexus 1 11228
Protoss_Observer 1 10110
Protoss_Robotics_Support_Bay 1 10105
11228
