Protoss_Gateway 2 5064
Protoss_Zealot 1 3430
Protoss_Assimilator 1 3580
Protoss_Cybernetics_Core 1 4463
Protoss_Dragoon 10 10026
Protoss_Robotics_Facility 1 8274
Protoss_Shuttle 1 9323
Protoss_Observatory 1 8942
Protoss_Robotics_Support_Bay 1 9684
Protoss_Observer 1 9926
10026
