Protoss_Gateway 2 3391
Protoss_Zealot 15 10316
Protoss_Nexus 1 6581
Protoss_Assimilator 2 10053
Protoss_Cybernetics_Core 1 7152
Protoss_Dragoon 2 8478
Protoss_Citadel_of_Adun 1 9592
Protoss_Forge 1 9644
Protoss_Templar_Archives 1 10706
10706
