Protoss_Gateway 2 3429
Protoss_Zealot 5 8546
Protoss_Assimilator 1 4174
Protoss_Cybernetics_Core 1 5295
Protoss_Dragoon 10 10588
Protoss_Robotics_Facility 1 7607
Protoss_Observatory 1 8481
Protoss_Nexus 1 10184
Protoss_Observer 2 10236
Protoss_Forge 1 9808
Protoss_Photon_Cannon 1 10671
10671
