Protoss_Gateway 2 3343
Protoss_Zealot 19 9852
Protoss_Nexus 1 7799
Protoss_Assimilator 2 9446
Protoss_Cybernetics_Core 1 8311
Protoss_Citadel_of_Adun 1 9606
Protoss_Robotics_Facility 1 10835
Protoss_Forge 1 10580
10835
