Protoss_Gateway 2 9464
Protoss_Assimilator 1 3472
Protoss_Zealot 2 4516
Protoss_Cybernetics_Core 1 4515
Protoss_Dragoon 8 10466
Protoss_Nexus 1 7493
Protoss_Robotics_Facility 1 7919
Protoss_Observatory 1 8556
Protoss_Observer 1 9266
Protoss_Robotics_Support_Bay 1 9177
Protoss_Reaver 1 10684
10684
