Protoss_Gateway 2 3427
Protoss_Zealot 7 8048
Protoss_Nexus 1 6635
Protoss_Assimilator 2 8993
Protoss_Forge 1 6458
Protoss_Photon_Cannon 5 9499
Protoss_Cybernetics_Core 1 8099
Protoss_Robotics_Facility 1 9413
Protoss_Dragoon 4 10570
Protoss_Observatory 1 10029
10570
