Protoss_Gateway 2 7234
Protoss_Zealot 3 4628
Protoss_Assimilator 2 10061
Protoss_Cybernetics_Core 1 4949
Protoss_Dragoon 8 9724
Protoss_Nexus 1 9038
Protoss_Robotics_Facility 1 9013
Protoss_Observatory 1 9692
Protoss_Citadel_of_Adun 1 10614
10614
