Protoss_Gateway 2 9708
Protoss_Assimilator 2 10015
Protoss_Zealot 2 4530
Protoss_Cybernetics_Core 1 4563
Protoss_Dragoon 6 10558
Protoss_Citadel_of_Adun 1 5993
Protoss_Templar_Archives 1 7013
Protoss_Nexus 1 8779
Protoss_Dark_Templar 2 8752
Protoss_Robotics_Facility 1 9744
10558
