Protoss_Gateway 2 5320
Protoss_Assimilator 1 2823
Protoss_Zealot 2 4036
Protoss_Cybernetics_Core 1 4901
Protoss_Dragoon 10 9622
Protoss_Robotics_Facility 1 7971
Protoss_Observatory 1 8520
Protoss_Observer 2 9844
Protoss_Robotics_Support_Bay 1 9664
Protoss_Nexus 1 11384
Protoss_Reaver 1 10894
11384
