Protoss_Gateway 3 9196
Protoss_Assimilator 2 9849
Protoss_Zealot 3 4830
Protoss_Cybernetics_Core 1 4761
Protoss_Dragoon 8 10362
Protoss_Nexus 1 8357
Protoss_Robotics_Facility 1 8333
Protoss_Observatory 1 9060
Protoss_Citadel_of_Adun 1 9922
Protoss_Observer 2 10340
10362
