Protoss_Gateway 6 10834
Protoss_Assimilator 1 2982
Protoss_Cybernetics_Core 1 3855
Protoss_Dragoon 7 10352
Protoss_Nexus 2 10894
Protoss_Robotics_Facility 1 7391
Protoss_Observatory 1 7948
Protoss_Observer 3 9878
Protoss_Citadel_of_Adun 1 10885
10894
