Protoss_Gateway 2 9592
Protoss_Assimilator 1 3065
Protoss_Cybernetics_Core 1 4015
Protoss_Zealot 3 10408
Protoss_Dragoon 2 6198
Protoss_Robotics_Facility 1 7093
Protoss_Citadel_of_Adun 1 7597
Protoss_Observatory 1 7680
Protoss_Forge 1 7854
Protoss_Templar_Archives 1 8595
Protoss_Observer 1 8543
Protoss_Photon_Cannon 1 9550
Protoss_High_Templar 2 10430
Protoss_Shuttle 1 10052
10430
