Protoss_Gateway 2 5504
Protoss_Assimilator 2 3294
Protoss_Cybernetics_Core 1 4239
Protoss_Zealot 1 4156
Protoss_Dragoon 9 9536
Protoss_Citadel_of_Adun 1 8299
Protoss_Templar_Archives 1 9890
Protoss_Forge 1 9594
Protoss_Nexus 1 11469
11469
