Protoss_Gateway 3 9154
Protoss_Assimilator 1 3171
Protoss_Cybernetics_Core 1 4299
Protoss_Dragoon 10 10298
Protoss_Robotics_Facility 1 6813
Protoss_Forge 1 7261
Protoss_Observatory 1 7521
Protoss_Observer 3 9740
10298
