Protoss_Gateway 2 4027
Protoss_Zealot 4 6006
Protoss_Cybernetics_Core 1 5089
Protoss_Assimilator 1 5101
Protoss_Dragoon 12 10628
Protoss_Nexus 1 11238
Protoss_Robotics_Facility 1 10680
11238
