Protoss_Gateway 2 7111
Protoss_Zealot 2 4058
Protoss_Assimilator 1 3619
Protoss_Cybernetics_Core 1 4871
Protoss_Citadel_of_Adun 1 5884
Protoss_Dragoon 5 10294
Protoss_Templar_Archives 1 6888
Protoss_Forge 1 7243
Protoss_Dark_Templar 4 8712
Protoss_Photon_Cannon 3 10108
Protoss_Nexus 1 11041
11041
