Protoss_Gateway 1 2789
Protoss_Assimilator 1 2868
Protoss_Cybernetics_Core 1 3853
Protoss_Robotics_Facility 2 10120
Protoss_Zealot 2 5470
Protoss_Shuttle 2 9823
Protoss_Dragoon 5 9932
Protoss_Robotics_Support_Bay 1 6310
Protoss_Reaver 2 8874
Protoss_Observatory 1 10048
10120
