Protoss_Gateway 3 9725
Protoss_Zealot 2 4778
Protoss_Assimilator 1 3890
Protoss_Cybernetics_Core 1 4991
Protoss_Dragoon 8 10653
Protoss_Robotics_Facility 1 6492
Protoss_Shuttle 1 7487
Protoss_Observatory 1 7209
Protoss_Robotics_Support_Bay 1 7778
Protoss_Observer 1 8098
Protoss_Reaver 2 10211
10653
