Protoss_Gateway 1 2905
Protoss_Assimilator 1 2961
Protoss_Cybernetics_Core 1 3935
Protoss_Robotics_Facility 1 5625
Protoss_Dragoon 5 9920
Protoss_Shuttle 1 6667
Protoss_Observatory 1 6293
Protoss_Observer 2 7872
Protoss_Nexus 1 9533
Protoss_Zealot 1 8640
9920
