Protoss_Gateway 1 2767
Protoss_Zealot 2 4524
Protoss_Assimilator 1 3889
Protoss_Cybernetics_Core 1 4505
Protoss_Dragoon 7 10476
Protoss_Robotics_Facility 1 6955
Protoss_Shuttle 1 7937
Protoss_Observatory 1 8100
Protoss_Observer 1 8782
Protoss_Robotics_Support_Bay 1 9001
Protoss_Nexus 2 11294
Protoss_Reaver 1 10948
11294
