Protoss_Gateway 3 9429
Protoss_Assimilator 1 3635
Protoss_Zealot 3 10138
Protoss_Cybernetics_Core 1 4663
Protoss_Dragoon 8 10683
Protoss_Robotics_Facility 1 7320
Protoss_Nexus 1 9260
Protoss_Observatory 1 8057
Protoss_Observer 1 8808
Protoss_Shuttle 1 10287
10683
