Protoss_Gateway 2 8525
Protoss_Zealot 3 4764
Protoss_Assimilator 2 9426
Protoss_Cybernetics_Core 1 4727
Protoss_Dragoon 8 9990
Protoss_Nexus 1 7978
Protoss_Robotics_Facility 1 7877
Protoss_Observatory 1 8469
Protoss_Observer 2 9750
Protoss_Citadel_of_Adun 1 9601
Protoss_Templar_Archives 1 10642
10642
