Protoss_Gateway 3 9873
Protoss_Assimilator 1 3157
Protoss_Zealot 2 4578
Protoss_Cybernetics_Core 1 4621
Protoss_Dragoon 10 10102
Protoss_Nexus 1 9107
Protoss_Robotics_Facility 1 8765
Protoss_Observatory 1 9331
Protoss_Observer 1 10028
10102
