Protoss_Gateway 2 3370
Protoss_Zealot 10 7203
Protoss_Shield_Battery 1 5514
Protoss_Nexus 1 10363
Protoss_Assimilator 1 9601
Protoss_Forge 1 9715
Protoss_Photon_Cannon 1 10740
10740
