Protoss_Gateway 2 5057
Protoss_Assimilator 1 2920
Protoss_Zealot 1 3500
Protoss_Cybernetics_Core 1 4643
Protoss_Dragoon 9 10576
Protoss_Citadel_of_Adun 1 6748
Protoss_Templar_Archives 1 7761
Protoss_Forge 1 7915
Protoss_Dark_Templar 3 9354
Protoss_Photon_Cannon 1 8969
Protoss_Nexus 1 11321
11321
