Protoss_Gateway 2 8467
Protoss_Assimilator 2 9535
Protoss_Zealot 2 4672
Protoss_Cybernetics_Core 1 4653
Protoss_Dragoon 8 10232
Protoss_Nexus 1 8178
Protoss_Robotics_Facility 1 8497
Protoss_Observatory 1 9053
Protoss_Citadel_of_Adun 1 9775
Protoss_Observer 2 10418
Protoss_Templar_Archives 1 10788
Protoss_Forge 1 10594
10788
