Protoss_Gateway 3 9090
Protoss_Zealot 1 3768
Protoss_Assimilator 1 3945
Protoss_Cybernetics_Core 1 4889
Protoss_Dragoon 11 10708
Protoss_Robotics_Facility 1 8294
Protoss_Observatory 1 9008
Protoss_Observer 2 10295
Protoss_Nexus 1 11148
11148
