Protoss_Gateway 2 5227
Protoss_Assimilator 1 3032
Protoss_Cybernetics_Core 1 3936
Protoss_Zealot 1 3858
Protoss_Dragoon 12 10574
Protoss_Nexus 1 9191
Protoss_Robotics_Facility 1 9952
Protoss_Citadel_of_Adun 1 9689
10574
