Protoss_Gateway 3 10404
Protoss_Assimilator 1 2948
Protoss_Cybernetics_Core 1 3774
Protoss_Dragoon 8 8326
Protoss_Citadel_of_Adun 1 8189
Protoss_Zealot 4 9044
Protoss_Templar_Archives 1 9315
Protoss_Dark_Templar 2 10152
10404
