Protoss_Gateway 4 9651
Protoss_Zealot 7 10454
Protoss_Nexus 1 6842
Protoss_Assimilator 2 8340
Protoss_Cybernetics_Core 1 7123
Protoss_Dragoon 1 8132
Protoss_Forge 1 8625
Protoss_Robotics_Facility 1 9517
Protoss_Citadel_of_Adun 1 9648
Protoss_Photon_Cannon 2 9982
Protoss_Observatory 1 10095
Protoss_Templar_Archives 1 10708
10708
