Protoss_Gateway 2 8759
Protoss_Assimilator 1 2960
Protoss_Cybernetics_Core 1 3833
Protoss_Zealot 1 3836
Protoss_Dragoon 10 10534
Protoss_Nexus 1 8849
Protoss_Robotics_Facility 1 8803
Protoss_Shuttle 1 9919
Protoss_Robotics_Support_Bay 1 9919
10534
