Protoss_Gateway 2 6808
Protoss_Zealot 7 9422
Protoss_Assimilator 1 4902
Protoss_Cybernetics_Core 1 6251
Protoss_Robotics_Facility 1 7577
Protoss_Dragoon 5 10368
Protoss_Shuttle 1 8567
Protoss_Robotics_Support_Bay 1 8175
Protoss_Reaver 1 9618
Protoss_Observatory 1 10016
10368
