Protoss_Gateway 2 7512
Protoss_Assimilator 1 3057
Protoss_Zealot 1 3596
Protoss_Cybernetics_Core 1 4063
Protoss_Dragoon 10 10580
Protoss_Nexus 1 7879
Protoss_Robotics_Facility 1 8517
Protoss_Citadel_of_Adun 1 9462
Protoss_Observatory 1 9980
10580
