Protoss_Gateway 2 8169
Protoss_Assimilator 1 3025
Protoss_Zealot 2 4268
Protoss_Cybernetics_Core 1 4887
Protoss_Dragoon 7 10478
Protoss_Robotics_Facility 1 7692
Protoss_Observatory 1 8285
Protoss_Observer 3 10178
Protoss_Nexus 1 10439
10478
