Protoss_Gateway 3 9914
Protoss_Zealot 8 9100
Protoss_Nexus 1 6590
Protoss_Assimilator 2 7752
Protoss_Cybernetics_Core 1 7164
Protoss_Dragoon 1 8016
Protoss_Citadel_of_Adun 1 8256
Protoss_Robotics_Facility 1 9175
Protoss_Templar_Archives 1 9417
Protoss_Forge 1 9331
Protoss_Shuttle 1 10157
Protoss_Observatory 1 9762
Protoss_Dark_Templar 2 10294
Protoss_Photon_Cannon 2 10540
10540
