Protoss_Gateway 3 8565
Protoss_Zealot 3 6336
Protoss_Assimilator 1 4752
Protoss_Cybernetics_Core 1 6478
Protoss_Dragoon 8 9866
Protoss_Robotics_Facility 1 9190
Protoss_Observatory 1 9835
Protoss_Observer 1 10520
10520
