Protoss_Gateway 3 10238
Protoss_Zealot 3 4726
Protoss_Assimilator 2 9405
Protoss_Cybernetics_Core 1 4716
Protoss_Dragoon 10 10506
Protoss_Nexus 1 8332
Protoss_Robotics_Facility 1 8639
Protoss_Observatory 1 9190
Protoss_Observer 2 10476
Protoss_Citadel_of_Adun 1 10437
10506
