Protoss_Gateway 2 8742
Protoss_Assimilator 1 3001
Protoss_Zealot 2 4590
Protoss_Cybernetics_Core 1 4612
Protoss_Dragoon 9 10474
Protoss_Nexus 1 8333
Protoss_Robotics_Facility 1 8667
Protoss_Observatory 1 10141
Protoss_Citadel_of_Adun 1 10686
10686
