Protoss_Gateway 2 6975
Protoss_Assimilator 1 2949
Protoss_Zealot 3 4584
Protoss_Cybernetics_Core 1 4734
Protoss_Dragoon 9 9766
Protoss_Robotics_Facility 1 6965
Protoss_Shuttle 1 7949
Protoss_Observatory 1 7780
Protoss_Robotics_Support_Bay 1 8011
Protoss_Observer 1 8588
Protoss_Reaver 2 11026
11026
