Protoss_Gateway 2 8553
Protoss_Assimilator 1 2949
Protoss_Zealot 1 3436
Protoss_Cybernetics_Core 1 4647
Protoss_Dragoon 7 9732
Protoss_Nexus 1 7870
Protoss_Robotics_Facility 1 8295
Protoss_Observatory 1 8841
Protoss_Observer 1 9544
9732
