Protoss_Gateway 2 5347
Protoss_Assimilator 1 3032
Protoss_Cybernetics_Core 1 3805
Protoss_Zealot 1 3698
Protoss_Dragoon 10 9486
Protoss_Robotics_Facility 1 7442
Protoss_Observatory 1 8016
Protoss_Robotics_Support_Bay 1 8509
Protoss_Observer 1 8760
Protoss_Reaver 1 10062
10062
