Protoss_Gateway 3 10417
Protoss_Assimilator 1 3022
Protoss_Zealot 3 4814
Protoss_Cybernetics_Core 1 4724
Protoss_Dragoon 8 10480
Protoss_Robotics_Facility 1 7204
Protoss_Shuttle 1 8243
Protoss_Observatory 1 7897
Protoss_Robotics_Support_Bay 1 8487
Protoss_Observer 1 8846
Protoss_Nexus 1 10215
Protoss_Reaver 2 10948
10948
