Protoss_Gateway 2 8921
Protoss_Assimilator 1 2944
Protoss_Cybernetics_Core 1 3795
Protoss_Zealot 1 4322
Protoss_Dragoon 8 10010
Protoss_Robotics_Facility 1 7183
Protoss_Observatory 1 7734
Protoss_Nexus 1 9466
Protoss_Observer 1 8494
Protoss_Shuttle 1 9955
Protoss_Robotics_Support_Bay 1 9969
10010
