Protoss_Gateway 4 9519
Protoss_Assimilator 2 10516
Protoss_Zealot 2 4486
Protoss_Cybernetics_Core 1 4435
Protoss_Dragoon 9 10404
Protoss_Robotics_Facility 1 7095
Protoss_Observatory 1 7637
Protoss_Nexus 1 9206
Protoss_Observer 2 9380
Protoss_Citadel_of_Adun 1 10893
10893
