Protoss_Gateway 3 6821
Protoss_Assimilator 1 3048
Protoss_Zealot 2 4732
Protoss_Cybernetics_Core 1 4753
Protoss_Dragoon 13 10742
Protoss_Nexus 1 11216
Protoss_Robotics_Facility 1 10690
11216
