Protoss_Gateway 4 10773
Protoss_Assimilator 2 10242
Protoss_Cybernetics_Core 1 3921
Protoss_Zealot 1 4006
Protoss_Dragoon 10 10312
Protoss_Nexus 1 8721
Protoss_Robotics_Facility 1 8562
Protoss_Observatory 1 9127
Protoss_Observer 2 10574
10773
