Protoss_Gateway 3 9413
Protoss_Assimilator 1 3033
Protoss_Zealot 6 9328
Protoss_Cybernetics_Core 1 4583
Protoss_Dragoon 6 10384
Protoss_Nexus 1 9069
Protoss_Robotics_Facility 1 8948
Protoss_Observatory 1 9583
Protoss_Observer 1 10278
10384
