Protoss_Gateway 3 10027
Protoss_Zealot 10 8502
Protoss_Nexus 1 6517
Protoss_Assimilator 2 7948
Protoss_Cybernetics_Core 1 6937
Protoss_Citadel_of_Adun 1 8007
Protoss_Dragoon 1 8460
Protoss_Templar_Archives 1 9138
Protoss_Forge 1 9216
Protoss_Dark_Templar 2 9976
Protoss_Photon_Cannon 3 10482
10482
