Protoss_Gateway 2 6421
Protoss_Assimilator 1 2808
Protoss_Cybernetics_Core 1 3947
Protoss_Dragoon 6 9684
Protoss_Citadel_of_Adun 1 5152
Protoss_Templar_Archives 1 6149
Protoss_Zealot 1 6206
Protoss_Dark_Templar 3 7816
Protoss_Nexus 1 10676
10676
