Protoss_Gateway 3 10583
Protoss_Assimilator 2 9841
Protoss_Zealot 5 7820
Protoss_Cybernetics_Core 1 4692
Protoss_Dragoon 2 10322
Protoss_Citadel_of_Adun 1 6611
Protoss_Robotics_Facility 1 6953
Protoss_Templar_Archives 1 7597
Protoss_Shuttle 1 7937
Protoss_Dark_Templar 2 9182
Protoss_Nexus 1 9941
Protoss_Observatory 1 9419
Protoss_Observer 1 10532
10583
