Protoss_Gateway 4 9758
Protoss_Zealot 13 10486
Protoss_Nexus 1 5837
Protoss_Assimilator 2 8858
Protoss_Cybernetics_Core 1 7409
Protoss_Citadel_of_Adun 1 8406
Protoss_Dragoon 4 9166
Protoss_Templar_Archives 1 9424
Protoss_Forge 1 9299
Protoss_Photon_Cannon 2 10350
Protoss_Dark_Templar 2 10480
10486
