Protoss_Gateway 2 7492
Protoss_Assimilator 1 3559
Protoss_Zealot 3 9220
Protoss_Cybernetics_Core 1 4565
Protoss_Dragoon 9 10336
Protoss_Robotics_Facility 1 7137
Protoss_Shuttle 1 8197
Protoss_Observatory 1 7808
Protoss_Observer 1 8800
Protoss_Robotics_Support_Bay 1 8816
Protoss_Reaver 1 10078
Protoss_Nexus 1 11041
11041
