Protoss_Gateway 2 7514
Protoss_Assimilator 1 2943
Protoss_Zealot 2 4450
Protoss_Cybernetics_Core 1 4441
Protoss_Dragoon 9 10006
Protoss_Robotics_Facility 1 7011
Protoss_Shuttle 1 7997
Protoss_Observatory 1 8045
Protoss_Robotics_Support_Bay 1 8402
Protoss_Observer 1 8772
Protoss_Reaver 1 9918
10006
