Protoss_Gateway 3 9328
Protoss_Zealot 2 4504
Protoss_Assimilator 2 10562
Protoss_Cybernetics_Core 1 4473
Protoss_Dragoon 9 10408
Protoss_Nexus 1 8305
Protoss_Robotics_Facility 1 8079
Protoss_Observatory 1 8717
Protoss_Observer 2 10408
Protoss_Citadel_of_Adun 1 10136
10562
