Protoss_Gateway 2 5445
Protoss_Assimilator 1 2808
Protoss_Cybernetics_Core 1 3987
Protoss_Zealot 1 4250
Protoss_Dragoon 12 10578
Protoss_Robotics_Facility 1 6888
Protoss_Shuttle 1 7915
Protoss_Robotics_Support_Bay 1 8084
Protoss_Reaver 2 10540
Protoss_Observatory 1 9053
10578
