Protoss_Gateway 2 7665
Protoss_Zealot 3 4740
Protoss_Assimilator 1 3552
Protoss_Cybernetics_Core 1 4788
Protoss_Dragoon 9 10522
Protoss_Citadel_of_Adun 1 6013
Protoss_Templar_Archives 1 7037
Protoss_Dark_Templar 1 7902
Protoss_Nexus 1 11438
11438
