Protoss_Gateway 4 10433
Protoss_Zealot 5 6038
Protoss_Assimilator 2 8222
Protoss_Nexus 1 6952
Protoss_Cybernetics_Core 1 6957
Protoss_Dragoon 8 10584
Protoss_Citadel_of_Adun 1 8737
Protoss_Robotics_Facility 1 10161
Protoss_Templar_Archives 1 10399
10584
