Protoss_Gateway 3 8855
Protoss_Assimilator 1 3042
Protoss_Cybernetics_Core 1 3889
Protoss_Zealot 1 4008
Protoss_Dragoon 13 10572
Protoss_Citadel_of_Adun 1 6667
Protoss_Templar_Archives 1 7657
Protoss_Dark_Templar 2 8976
10572
