Protoss_Gateway 3 9208
Protoss_Assimilator 1 2828
Protoss_Cybernetics_Core 1 3816
Protoss_Dragoon 14 10504
Protoss_Robotics_Facility 1 8172
Protoss_Observatory 1 8729
Protoss_Zealot 2 9638
Protoss_Observer 2 10291
10504
