Protoss_Gateway 5 10441
Protoss_Zealot 7 10546
Protoss_Nexus 1 6703
Protoss_Assimilator 2 9305
Protoss_Cybernetics_Core 1 6966
Protoss_Dragoon 7 9854
Protoss_Robotics_Facility 1 10958
10958
