Protoss_Gateway 2 3667
Protoss_Zealot 11 7813
Protoss_Assimilator 1 5570
Protoss_Cybernetics_Core 1 8329
Protoss_Citadel_of_Adun 1 9426
Protoss_Dragoon 4 10330
Protoss_Templar_Archives 1 10444
10444
