Protoss_Gateway 1 2712
Protoss_Assimilator 1 2947
Protoss_Cybernetics_Core 1 3827
Protoss_Zealot 1 3724
Protoss_Dragoon 7 10268
Protoss_Robotics_Facility 1 6927
Protoss_Robotics_Support_Bay 1 7529
Protoss_Observatory 1 7599
Protoss_Reaver 1 8716
Protoss_Observer 2 9922
Protoss_Nexus 1 11575
11575
