Protoss_Gateway 2 6484
Protoss_Assimilator 1 2868
Protoss_Zealot 2 4136
Protoss_Cybernetics_Core 1 4183
Protoss_Dragoon 11 10134
Protoss_Robotics_Facility 1 8302
Protoss_Nexus 1 9895
Protoss_Observatory 1 9048
Protoss_Observer 1 9750
10134
