Protoss_Gateway 2 3409
Protoss_Zealot 9 6398
Protoss_Assimilator 1 5045
Protoss_Cybernetics_Core 1 6187
Protoss_Dragoon 8 10088
Protoss_Nexus 1 9147
Protoss_Robotics_Facility 1 10055
10088
