Protoss_Gateway 3 9178
Protoss_Zealot 11 8046
Protoss_Nexus 1 6489
Protoss_Assimilator 2 10183
Protoss_Cybernetics_Core 1 8210
Protoss_Dragoon 4 10510
Protoss_Citadel_of_Adun 1 9786
Protoss_Robotics_Facility 1 10579
10579
