Protoss_Gateway 3 8912
Protoss_Zealot 19 10336
Protoss_Nexus 1 7520
Protoss_Assimilator 1 6713
Protoss_Cybernetics_Core 1 8166
Protoss_Citadel_of_Adun 1 9183
Protoss_Forge 1 9179
Protoss_Photon_Cannon 1 10666
10666
