Protoss_Gateway 2 6039
Protoss_Assimilator 1 2968
Protoss_Zealot 3 6972
Protoss_Cybernetics_Core 1 4501
Protoss_Dragoon 7 9362
Protoss_Robotics_Facility 1 7347
Protoss_Shuttle 1 8333
Protoss_Observatory 1 8235
Protoss_Robotics_Support_Bay 1 8371
Protoss_Observer 1 8956
Protoss_Reaver 1 10342
Protoss_Nexus 1 11370
11370
