Protoss_Gateway 3 10850
Protoss_Assimilator 2 10410
Protoss_Cybernetics_Core 1 3974
Protoss_Dragoon 5 7584
Protoss_Citadel_of_Adun 1 6551
Protoss_Templar_Archives 1 7565
Protoss_Forge 1 8058
Protoss_Dark_Templar 2 8408
Protoss_Photon_Cannon 2 8992
Protoss_Nexus 1 10643
Protoss_High_Templar 2 9712
10850
