Protoss_Gateway 2 5856
Protoss_Assimilator 1 3175
Protoss_Zealot 3 4963
Protoss_Cybernetics_Core 1 4888
Protoss_Dragoon 4 9188
Protoss_Citadel_of_Adun 1 6515
Protoss_Templar_Archives 1 7562
Protoss_Dark_Templar 2 8413
Protoss_Robotics_Facility 1 10028
Protoss_Forge 1 10009
10028
