Protoss_Gateway 2 3649
Protoss_Zealot 2 5403
Protoss_Assimilator 1 4085
Protoss_Cybernetics_Core 1 5206
Protoss_Citadel_of_Adun 1 6209
Protoss_Dragoon 3 9547
Protoss_Templar_Archives 1 7204
Protoss_Dark_Templar 4 8813
9547
