Protoss_Gateway 2 8991
Protoss_Assimilator 1 2858
Protoss_Zealot 2 4536
Protoss_Cybernetics_Core 1 4522
Protoss_Dragoon 10 10642
Protoss_Robotics_Facility 1 6925
Protoss_Observatory 1 7611
Protoss_Nexus 1 9171
Protoss_Observer 3 10518
10642
