Protoss_Gateway 2 4919
Protoss_Zealot 1 3448
Protoss_Assimilator 1 3630
Protoss_Cybernetics_Core 1 4639
Protoss_Dragoon 11 10408
Protoss_Nexus 1 9151
Protoss_Robotics_Facility 1 9367
Protoss_Citadel_of_Adun 1 10012
Protoss_Observatory 1 10147
10408
