Protoss_Gateway 3 10343
Protoss_Assimilator 1 2920
Protoss_Cybernetics_Core 1 3737
Protoss_Zealot 1 3990
Protoss_Dragoon 10 10382
Protoss_Nexus 1 8027
Protoss_Robotics_Facility 1 8898
Protoss_Observatory 1 9525
Protoss_Observer 1 10202
10382
