Protoss_Gateway 3 7343
Protoss_Assimilator 1 3008
Protoss_Cybernetics_Core 1 3821
Protoss_Zealot 1 4060
Protoss_Dragoon 16 10552
Protoss_Robotics_Facility 1 9120
Protoss_Shuttle 1 10537
Protoss_Robotics_Support_Bay 1 10101
10552
