Protoss_Gateway 2 4900
Protoss_Assimilator 1 2979
Protoss_Zealot 2 4870
Protoss_Cybernetics_Core 1 4745
Protoss_Robotics_Facility 1 6247
Protoss_Dragoon 10 10626
Protoss_Observatory 1 6803
Protoss_Observer 3 9126
Protoss_Nexus 1 9568
Protoss_Shuttle 1 10164
Protoss_Robotics_Support_Bay 1 10042
10626
