Protoss_Gateway 2 8135
Protoss_Assimilator 1 3076
Protoss_Zealot 2 4870
Protoss_Cybernetics_Core 1 4801
Protoss_Dragoon 10 10730
Protoss_Robotics_Facility 1 7565
Protoss_Observatory 1 8129
Protoss_Observer 2 9424
Protoss_Shuttle 1 10325
Protoss_Robotics_Support_Bay 1 9995
10730
