Protoss_Gateway 3 7737
Protoss_Assimilator 1 2846
Protoss_Cybernetics_Core 1 3790
Protoss_Zealot 5 8766
Protoss_Dragoon 7 9880
Protoss_Robotics_Facility 1 6930
Protoss_Shuttle 1 7909
Protoss_Observatory 1 7581
Protoss_Robotics_Support_Bay 1 8058
Protoss_Observer 1 8512
Protoss_Reaver 2 10690
10690
