Protoss_Gateway 2 9123
Protoss_Assimilator 2 9356
Protoss_Zealot 2 4470
Protoss_Cybernetics_Core 1 4566
Protoss_Dragoon 8 10062
Protoss_Nexus 1 8451
Protoss_Robotics_Facility 1 8800
Protoss_Citadel_of_Adun 1 8750
Protoss_Templar_Archives 1 9910
Protoss_Observatory 1 9521
Protoss_Observer 1 10252
10252
