Protoss_Gateway 2 7622
Protoss_Assimilator 1 2930
Protoss_Zealot 2 4530
Protoss_Cybernetics_Core 1 4529
Protoss_Dragoon 8 9616
Protoss_Robotics_Facility 1 7056
Protoss_Shuttle 1 8093
Protoss_Observatory 1 7816
Protoss_Observer 2 10350
Protoss_Robotics_Support_Bay 1 8553
Protoss_Reaver 1 9746
Protoss_Nexus 1 11513
11513
