Protoss_Gateway 2 7464
Protoss_Assimilator 1 2890
Protoss_Zealot 2 4532
Protoss_Cybernetics_Core 1 4520
Protoss_Dragoon 8 9468
Protoss_Robotics_Facility 1 7116
Protoss_Shuttle 1 8097
Protoss_Observatory 1 7758
Protoss_Robotics_Support_Bay 1 8257
Protoss_Observer 2 10354
Protoss_Reaver 2 10886
Protoss_Nexus 1 11374
11374
