Protoss_Gateway 4 10009
Protoss_Assimilator 1 2996
Protoss_Cybernetics_Core 1 3924
Protoss_Zealot 1 3924
Protoss_Dragoon 8 10034
Protoss_Nexus 1 6867
Protoss_Robotics_Facility 1 7238
Protoss_Observatory 1 7844
Protoss_Observer 1 8560
Protoss_Shuttle 1 9461
Protoss_Robotics_Support_Bay 1 9228
Protoss_Reaver 1 10578
10578
