Protoss_Gateway 1 2781
Protoss_Assimilator 1 2977
Protoss_Cybernetics_Core 1 4002
Protoss_Zealot 2 7842
Protoss_Dragoon 7 10417
Protoss_Robotics_Facility 1 6675
Protoss_Shuttle 1 7697
Protoss_Observatory 1 7254
Protoss_Robotics_Support_Bay 1 8034
Protoss_Observer 2 9954
Protoss_Reaver 2 11004
11004
