Protoss_Gateway 4 9847
Protoss_Assimilator 1 2915
Protoss_Cybernetics_Core 1 3749
Protoss_Zealot 2 7384
Protoss_Dragoon 9 10682
Protoss_Citadel_of_Adun 1 6171
Protoss_Templar_Archives 1 7224
Protoss_Dark_Templar 2 8206
Protoss_Nexus 1 9801
10682
