Protoss_Gateway 2 7593
Protoss_Assimilator 1 2975
Protoss_Zealot 2 4534
Protoss_Cybernetics_Core 1 4525
Protoss_Dragoon 9 9646
Protoss_Robotics_Facility 1 7033
Protoss_Shuttle 1 8117
Protoss_Observatory 1 7804
Protoss_Robotics_Support_Bay 1 8567
Protoss_Observer 2 10374
Protoss_Reaver 1 9770
10374
