Protoss_Gateway 2 8487
Protoss_Assimilator 2 9606
Protoss_Cybernetics_Core 1 4233
Protoss_Zealot 1 4294
Protoss_Dragoon 10 10612
Protoss_Nexus 1 8147
Protoss_Robotics_Facility 1 8662
Protoss_Citadel_of_Adun 1 9337
Protoss_Observatory 1 9205
Protoss_Observer 2 10490
Protoss_Templar_Archives 1 10557
10612
