Protoss_Gateway 2 7299
Protoss_Assimilator 1 2780
Protoss_Zealot 2 4474
Protoss_Cybernetics_Core 1 4472
Protoss_Dragoon 10 10476
Protoss_Robotics_Facility 1 6882
Protoss_Observatory 1 7624
Protoss_Observer 1 8310
Protoss_Robotics_Support_Bay 1 8228
Protoss_Reaver 1 9578
Protoss_Nexus 1 11197
11197
