Protoss_Gateway 4 9679
Protoss_Assimilator 1 2806
Protoss_Zealot 2 4324
Protoss_Cybernetics_Core 1 4576
Protoss_Dragoon 8 9902
Protoss_Citadel_of_Adun 1 7136
Protoss_Templar_Archives 1 8121
Protoss_Nexus 1 9703
Protoss_Dark_Templar 2 9104
9902
