Protoss_Gateway 2 9826
Protoss_Assimilator 1 2951
Protoss_Cybernetics_Core 1 3778
Protoss_Zealot 1 4052
Protoss_Dragoon 8 10594
Protoss_Robotics_Facility 1 7104
Protoss_Nexus 1 8795
Protoss_Shuttle 1 8457
Protoss_Robotics_Support_Bay 1 8297
Protoss_Reaver 2 10898
Protoss_Observatory 1 9881
10898
