Protoss_Gateway 4 9081
Protoss_Assimilator 1 2943
Protoss_Cybernetics_Core 1 3847
Protoss_Zealot 1 3756
Protoss_Dragoon 13 10662
Protoss_Nexus 1 7413
Protoss_Robotics_Facility 1 7743
Protoss_Observatory 1 8386
Protoss_Observer 2 9666
10662
