Protoss_Gateway 2 7127
Protoss_Assimilator 1 2875
Protoss_Zealot 2 4422
Protoss_Cybernetics_Core 1 4429
Protoss_Dragoon 9 10512
Protoss_Robotics_Facility 1 6765
Protoss_Observatory 1 7321
Protoss_Robotics_Support_Bay 1 7871
Protoss_Observer 2 9892
Protoss_Reaver 1 9236
Protoss_Nexus 1 10571
10571
