Protoss_Gateway 2 7707
Protoss_Assimilator 1 2931
Protoss_Zealot 2 4488
Protoss_Cybernetics_Core 1 4383
Protoss_Dragoon 11 10648
Protoss_Robotics_Facility 1 7118
Protoss_Shuttle 1 8119
Protoss_Observatory 1 7945
Protoss_Observer 2 10502
Protoss_Robotics_Support_Bay 1 8769
Protoss_Reaver 1 9898
Protoss_Nexus 1 11403
11403
