Protoss_Gateway 3 10720
Protoss_Assimilator 1 2907
Protoss_Zealot 2 4576
Protoss_Cybernetics_Core 1 4579
Protoss_Dragoon 9 10248
Protoss_Robotics_Facility 1 7489
Protoss_Observatory 1 8063
Protoss_Robotics_Support_Bay 1 8511
Protoss_Observer 1 8768
Protoss_Reaver 1 10028
Protoss_Nexus 1 10899
10899
