Protoss_Gateway 2 5931
Protoss_Assimilator 1 2994
Protoss_Zealot 4 9332
Protoss_Cybernetics_Core 1 4494
Protoss_Dragoon 10 10436
Protoss_Robotics_Facility 1 7605
Protoss_Shuttle 1 8637
Protoss_Observatory 1 8319
Protoss_Robotics_Support_Bay 1 9067
Protoss_Observer 1 9243
Protoss_Reaver 1 10516
10516
