Protoss_Gateway 4 9289
Protoss_Zealot 11 9374
Protoss_Nexus 1 6791
Protoss_Assimilator 2 8081
Protoss_Cybernetics_Core 1 7177
Protoss_Citadel_of_Adun 1 8310
Protoss_Templar_Archives 1 9345
Protoss_Dark_Templar 4 10380
Protoss_Forge 1 10468
10468
