Protoss_Gateway 2 7849
Protoss_Assimilator 1 3077
Protoss_Zealot 2 4692
Protoss_Cybernetics_Core 1 4693
Protoss_Dragoon 10 10532
Protoss_Robotics_Facility 1 7733
Protoss_Shuttle 1 8717
Protoss_Observatory 1 8348
Protoss_Robotics_Support_Bay 1 8994
Protoss_Observer 1 9320
Protoss_Reaver 1 10370
10532
