Protoss_Gateway 4 8913
Protoss_Assimilator 1 2812
Protoss_Cybernetics_Core 1 3771
Protoss_Zealot 1 3730
Protoss_Dragoon 13 10540
Protoss_Citadel_of_Adun 1 5650
Protoss_Nexus 1 8952
10540
