Protoss_Gateway 2 3287
Protoss_Zealot 11 8974
Protoss_Assimilator 2 9350
Protoss_Nexus 1 7572
Protoss_Cybernetics_Core 1 7106
Protoss_Dragoon 2 8372
Protoss_Citadel_of_Adun 1 9104
Protoss_Robotics_Facility 1 10242
Protoss_Templar_Archives 1 10244
Protoss_Forge 1 10221
10244
