Protoss_Gateway 2 7213
Protoss_Assimilator 1 2960
Protoss_Zealot 2 4536
Protoss_Cybernetics_Core 1 4557
Protoss_Dragoon 9 10502
Protoss_Robotics_Facility 1 7165
Protoss_Observatory 1 7823
Protoss_Shuttle 1 8501
Protoss_Robotics_Support_Bay 1 8761
Protoss_Observer 1 9104
Protoss_Reaver 1 10154
10502
