Protoss_Gateway 2 6745
Protoss_Assimilator 1 2891
Protoss_Zealot 3 5212
Protoss_Cybernetics_Core 1 5263
Protoss_Dragoon 10 10660
Protoss_Robotics_Facility 1 7823
Protoss_Shuttle 1 9089
Protoss_Robotics_Support_Bay 1 8911
Protoss_Reaver 1 10358
Protoss_Shield_Battery 1 10293
10660
