Protoss_Gateway 3 9496
Protoss_Assimilator 1 2979
Protoss_Zealot 4 9896
Protoss_Cybernetics_Core 1 5441
Protoss_Dragoon 6 10346
Protoss_Nexus 1 7911
Protoss_Robotics_Facility 1 8829
Protoss_Observatory 1 9487
Protoss_Robotics_Support_Bay 1 9850
10346
