Protoss_Gateway 2 7695
Protoss_Assimilator 1 3100
Protoss_Zealot 2 4964
Protoss_Cybernetics_Core 1 4847
Protoss_Dragoon 10 10636
Protoss_Robotics_Facility 1 7298
Protoss_Observatory 1 7880
Protoss_Shuttle 1 8339
Protoss_Robotics_Support_Bay 2 9938
Protoss_Observer 1 9130
Protoss_Reaver 1 10726
10726
