Protoss_Gateway 2 6989
Protoss_Assimilator 1 2870
Protoss_Cybernetics_Core 1 3932
Protoss_Zealot 1 3878
Protoss_Dragoon 10 10014
Protoss_Robotics_Facility 1 6666
Protoss_Observatory 1 7285
Protoss_Observer 2 9284
Protoss_Shuttle 1 8681
Protoss_Robotics_Support_Bay 1 8817
Protoss_Reaver 1 10348
10348
