Protoss_Gateway 3 10773
Protoss_Assimilator 2 9495
Protoss_Zealot 1 3576
Protoss_Cybernetics_Core 1 4808
Protoss_Dragoon 9 10186
Protoss_Nexus 1 8089
Protoss_Robotics_Facility 1 8007
Protoss_Observatory 1 8754
Protoss_Observer 2 10566
Protoss_Citadel_of_Adun 1 10396
10773
