Protoss_Gateway 2 3404
Protoss_Zealot 13 9608
Protoss_Forge 1 6132
Protoss_Photon_Cannon 4 9328
Protoss_Assimilator 1 8412
Protoss_Cybernetics_Core 1 9817
Protoss_Robotics_Facility 1 11164
11164
