Protoss_Gateway 3 10365
Protoss_Assimilator 1 2860
Protoss_Cybernetics_Core 1 3775
Protoss_Dragoon 14 10647
Protoss_Robotics_Facility 1 7372
Protoss_Observatory 1 7985
Protoss_Observer 2 9348
Protoss_Nexus 1 10517
10647
