Protoss_Gateway 4 10613
Protoss_Assimilator 1 3165
Protoss_Zealot 2 4598
Protoss_Cybernetics_Core 1 4598
Protoss_Dragoon 8 9898
Protoss_Robotics_Facility 1 7547
Protoss_Observatory 1 8161
Protoss_Nexus 1 9728
Protoss_Observer 2 9852
10613
