Protoss_Gateway 4 9841
Protoss_Zealot 6 6818
Protoss_Nexus 1 6737
Protoss_Assimilator 1 5633
Protoss_Cybernetics_Core 1 6402
Protoss_Dragoon 8 10730
Protoss_Robotics_Facility 1 9159
Protoss_Shuttle 1 10617
Protoss_Observatory 1 10253
10730
