Protoss_Gateway 2 3341
Protoss_Assimilator 1 3354
Protoss_Cybernetics_Core 1 4587
Protoss_Zealot 2 4896
Protoss_Dragoon 13 10416
Protoss_Robotics_Facility 1 8825
Protoss_Observatory 1 9472
Protoss_Robotics_Support_Bay 1 9514
10416
