Protoss_Gateway 3 9877
Protoss_Assimilator 1 2933
Protoss_Zealot 2 4544
Protoss_Cybernetics_Core 1 4527
Protoss_Dragoon 13 10373
Protoss_Shield_Battery 1 5468
Protoss_Robotics_Facility 1 8799
Protoss_Observatory 1 9508
10373
