Protoss_Gateway 2 4505
Protoss_Assimilator 1 2823
Protoss_Zealot 5 5650
Protoss_Cybernetics_Core 1 5865
Protoss_Dragoon 6 10066
Protoss_Robotics_Facility 1 7665
Protoss_Nexus 1 8992
Protoss_Observatory 1 8211
Protoss_Shuttle 1 8929
Protoss_Robotics_Support_Bay 1 9322
Protoss_Observer 1 9532
Protoss_Reaver 1 10612
10612
