Protoss_Gateway 3 10605
Protoss_Assimilator 1 2942
Protoss_Zealot 2 4654
Protoss_Cybernetics_Core 1 4619
Protoss_Dragoon 7 10110
Protoss_Citadel_of_Adun 1 6241
Protoss_Templar_Archives 1 7280
Protoss_Forge 1 7564
Protoss_Dark_Templar 2 8116
Protoss_Photon_Cannon 1 8556
Protoss_Nexus 1 10595
10605
