Protoss_Gateway 2 4999
Protoss_Assimilator 1 3298
Protoss_Zealot 1 3594
Protoss_Cybernetics_Core 1 4473
Protoss_Dragoon 6 9818
Protoss_Nexus 1 8296
Protoss_Robotics_Facility 1 8091
Protoss_Forge 1 8106
Protoss_Photon_Cannon 1 8988
Protoss_Observatory 1 8737
Protoss_Citadel_of_Adun 1 9748
Protoss_Observer 2 10104
10104
