Protoss_Gateway 2 6195
Protoss_Assimilator 1 2958
Protoss_Cybernetics_Core 1 3756
Protoss_Zealot 1 4012
Protoss_Dragoon 9 9202
Protoss_Robotics_Facility 1 8027
Protoss_Observatory 1 8669
Protoss_Robotics_Support_Bay 1 9074
Protoss_Observer 1 9376
Protoss_Reaver 1 10426
Protoss_Nexus 1 11531
11531
