Protoss_Gateway 2 10372
Protoss_Assimilator 1 2982
Protoss_Cybernetics_Core 1 3877
Protoss_Zealot 1 3850
Protoss_Dragoon 7 9950
Protoss_Robotics_Facility 1 6593
Protoss_Shuttle 1 7611
Protoss_Robotics_Support_Bay 1 7236
Protoss_Reaver 1 8662
Protoss_Observatory 1 8182
Protoss_Observer 2 9868
Protoss_Nexus 1 10795
10795
