Protoss_Gateway 1 2826
Protoss_Assimilator 1 2906
Protoss_Cybernetics_Core 1 3834
Protoss_Robotics_Facility 1 5305
Protoss_Dragoon 7 10022
Protoss_Observatory 1 6156
Protoss_Observer 2 7485
Protoss_Shuttle 1 8386
Protoss_Robotics_Support_Bay 1 8395
Protoss_Reaver 2 10793
10793
