Protoss_Gateway 2 6837
Protoss_Assimilator 1 2966
Protoss_Zealot 2 4488
Protoss_Cybernetics_Core 1 4507
Protoss_Dragoon 11 10542
Protoss_Robotics_Facility 1 6619
Protoss_Shuttle 1 7693
Protoss_Robotics_Support_Bay 1 7871
Protoss_Reaver 1 9028
Protoss_Observatory 1 8864
Protoss_Observer 1 10078
10542
