Protoss_Gateway 2 10578
Protoss_Assimilator 1 2817
Protoss_Cybernetics_Core 1 3785
Protoss_Dragoon 7 10338
Protoss_Robotics_Facility 1 5335
Protoss_Shuttle 1 6401
Protoss_Observatory 1 6442
Protoss_Observer 2 8692
Protoss_Nexus 1 9033
Protoss_Forge 1 9770
Protoss_Photon_Cannon 1 10713
10713
