Protoss_Gateway 2 7104
Protoss_Assimilator 1 2931
Protoss_Zealot 1 3380
Protoss_Cybernetics_Core 1 3995
Protoss_Dragoon 8 9924
Protoss_Robotics_Facility 1 6279
Protoss_Robotics_Support_Bay 1 6829
Protoss_Reaver 1 8120
Protoss_Observatory 1 8001
Protoss_Observer 2 10346
Protoss_Shuttle 1 9743
Protoss_Nexus 1 11645
11645
