Protoss_Gateway 2 10449
Protoss_Assimilator 1 2930
Protoss_Zealot 2 4572
Protoss_Cybernetics_Core 1 4703
Protoss_Dragoon 5 10598
Protoss_Robotics_Facility 1 6657
Protoss_Robotics_Support_Bay 1 7229
Protoss_Shuttle 1 7685
Protoss_Reaver 1 8736
Protoss_Observatory 1 8437
Protoss_Observer 1 9340
Protoss_Nexus 1 10853
10853
