Protoss_Gateway 2 10331
Protoss_Assimilator 2 8495
Protoss_Cybernetics_Core 1 3843
Protoss_Zealot 1 3698
Protoss_Dragoon 7 10302
Protoss_Nexus 1 7347
Protoss_Forge 2 8780
Protoss_Photon_Cannon 2 7879
Protoss_Citadel_of_Adun 1 10129
10331
