Protoss_Gateway 1 3022
Protoss_Assimilator 1 3077
Protoss_Cybernetics_Core 1 4043
Protoss_Robotics_Facility 1 5408
Protoss_Dragoon 4 10294
Protoss_Shuttle 1 6389
Protoss_Robotics_Support_Bay 1 6226
Protoss_Reaver 2 8492
Protoss_Observatory 1 8840
Protoss_Observer 1 9524
Protoss_Nexus 1 11533
11533
