Protoss_Gateway 4 10720
Protoss_Zealot 8 7126
Protoss_Nexus 1 6570
Protoss_Assimilator 2 7682
Protoss_Cybernetics_Core 1 7007
Protoss_Dragoon 9 10702
Protoss_Robotics_Facility 1 9337
Protoss_Shuttle 1 10323
Protoss_Observatory 1 9957
10720
