Protoss_Gateway 2 6043
Protoss_Assimilator 1 2973
Protoss_Cybernetics_Core 1 4169
Protoss_Zealot 5 10130
Protoss_Dragoon 9 10056
Protoss_Robotics_Facility 1 6905
Protoss_Observatory 1 7565
Protoss_Observer 2 9534
Protoss_Nexus 1 9973
Protoss_Citadel_of_Adun 1 9332
Protoss_Templar_Archives 1 10379
10379
