Protoss_Gateway 3 10045
Protoss_Assimilator 1 2841
Protoss_Cybernetics_Core 1 3660
Protoss_Zealot 2 6668
Protoss_Dragoon 9 10444
Protoss_Citadel_of_Adun 1 5891
Protoss_Templar_Archives 1 6939
Protoss_Dark_Templar 2 7774
Protoss_Nexus 1 9436
Protoss_Robotics_Facility 1 9650
Protoss_Observatory 1 10279
10444
