Protoss_Gateway 3 8265
Protoss_Assimilator 1 3030
Protoss_Zealot 2 4622
Protoss_Cybernetics_Core 1 4632
Protoss_Dragoon 9 10510
Protoss_Nexus 1 8447
Protoss_Citadel_of_Adun 1 8821
Protoss_Robotics_Facility 1 9224
Protoss_Observatory 1 9880
10510
