Protoss_Gateway 2 6959
Protoss_Assimilator 1 2969
Protoss_Cybernetics_Core 1 3827
Protoss_Zealot 1 3740
Protoss_Dragoon 5 10272
Protoss_Citadel_of_Adun 1 6096
Protoss_Templar_Archives 1 7283
Protoss_Dark_Templar 3 9105
Protoss_Nexus 1 11007
11007
