Protoss_Gateway 4 8003
Protoss_Assimilator 1 2961
Protoss_Cybernetics_Core 1 3763
Protoss_Zealot 3 10062
Protoss_Dragoon 12 10148
Protoss_Nexus 1 7855
Protoss_Robotics_Facility 1 10931
Protoss_Shield_Battery 1 10387
10931
