Protoss_Gateway 3 9749
Protoss_Assimilator 1 3065
Protoss_Cybernetics_Core 1 3870
Protoss_Dragoon 6 10388
Protoss_Robotics_Facility 1 5667
Protoss_Shuttle 1 6737
Protoss_Observatory 1 6496
Protoss_Observer 2 10152
Protoss_Robotics_Support_Bay 1 7265
Protoss_Reaver 2 9548
10388
