Protoss_Gateway 2 8748
Protoss_Assimilator 1 3028
Protoss_Cybernetics_Core 1 3964
Protoss_Zealot 3 8558
Protoss_Dragoon 4 9384
Protoss_Robotics_Facility 1 5662
Protoss_Observatory 1 6551
Protoss_Shuttle 1 7203
Protoss_Robotics_Support_Bay 1 7430
Protoss_Observer 1 7806
Protoss_Reaver 1 9012
Protoss_Nexus 1 10823
10823
