Protoss_Gateway 4 10254
Protoss_Assimilator 1 2978
Protoss_Zealot 4 10112
Protoss_Cybernetics_Core 1 4689
Protoss_Dragoon 9 8916
Protoss_Robotics_Facility 1 8077
Protoss_Observatory 1 8639
Protoss_Nexus 1 10572
Protoss_Observer 2 10060
10572
