Protoss_Gateway 3 7971
Protoss_Assimilator 1 3070
Protoss_Zealot 2 4720
Protoss_Cybernetics_Core 1 4746
Protoss_Dragoon 13 10456
Protoss_Robotics_Facility 1 7117
Protoss_Observatory 1 7689
Protoss_Observer 2 9122
10456
