Protoss_Gateway 2 7331
Protoss_Assimilator 1 2964
Protoss_Cybernetics_Core 1 3737
Protoss_Zealot 1 3880
Protoss_Dragoon 10 10300
Protoss_Robotics_Facility 1 7041
Protoss_Shuttle 1 8025
Protoss_Observatory 1 7672
Protoss_Robotics_Support_Bay 1 8457
Protoss_Observer 1 8628
Protoss_Reaver 1 9842
10300
