Protoss_Gateway 4 10634
Protoss_Zealot 7 8904
Protoss_Nexus 1 6750
Protoss_Assimilator 2 7500
Protoss_Cybernetics_Core 1 6557
Protoss_Dragoon 4 8248
Protoss_Citadel_of_Adun 1 7999
Protoss_Robotics_Facility 1 9275
Protoss_Templar_Archives 1 9381
Protoss_Dark_Templar 2 10262
Protoss_Shuttle 1 10445
Protoss_Observatory 1 10332
10634
