Protoss_Gateway 2 5859
Protoss_Assimilator 1 2941
Protoss_Zealot 2 4496
Protoss_Cybernetics_Core 1 4449
Protoss_Dragoon 11 10438
Protoss_Robotics_Facility 1 8013
Protoss_Observatory 1 8572
Protoss_Observer 2 9870
Protoss_Nexus 1 11363
11363
