Protoss_Gateway 5 10034
Protoss_Zealot 11 10426
Protoss_Nexus 1 5940
Protoss_Assimilator 2 8835
Protoss_Cybernetics_Core 1 7432
Protoss_Dragoon 3 9346
Protoss_Citadel_of_Adun 1 8802
Protoss_Templar_Archives 1 10110
Protoss_Forge 1 10291
10426
