Protoss_Nexus 1 4869
Protoss_Gateway 4 9473
Protoss_Forge 1 5321
Protoss_Zealot 14 10330
Protoss_Photon_Cannon 8 10712
Protoss_Assimilator 1 6779
Protoss_Cybernetics_Core 1 8694
Protoss_Citadel_of_Adun 1 10523
10712
