Protoss_Gateway 3 8351
Protoss_Assimilator 1 2890
Protoss_Zealot 2 8128
Protoss_Cybernetics_Core 1 4722
Protoss_Citadel_of_Adun 1 6041
Protoss_Dragoon 9 10294
Protoss_Templar_Archives 1 8283
Protoss_Dark_Templar 3 9266
Protoss_Robotics_Facility 1 11138
11138
