Protoss_Gateway 2 3393
Protoss_Zealot 13 9232
Protoss_Nexus 1 7007
Protoss_Assimilator 2 9745
Protoss_Cybernetics_Core 1 8577
Protoss_Citadel_of_Adun 1 9714
Protoss_Dragoon 2 10020
Protoss_Templar_Archives 1 10823
Protoss_Forge 1 10554
10823
