Protoss_Gateway 3 10879
Protoss_Assimilator 1 2768
Protoss_Zealot 1 3553
Protoss_Cybernetics_Core 1 4904
Protoss_Dragoon 3 8598
Protoss_Robotics_Facility 1 6339
Protoss_Shuttle 1 7332
Protoss_Robotics_Support_Bay 1 7256
Protoss_Reaver 2 10011
Protoss_Nexus 1 10270
10879
