Protoss_Gateway 2 6832
Protoss_Assimilator 1 2916
Protoss_Zealot 3 4526
Protoss_Cybernetics_Core 1 4604
Protoss_Dragoon 11 10346
Protoss_Robotics_Facility 1 8389
Protoss_Nexus 1 10889
Protoss_Shuttle 1 10429
10889
