Protoss_Gateway 2 7251
Protoss_Assimilator 1 2979
Protoss_Zealot 2 4542
Protoss_Cybernetics_Core 1 4565
Protoss_Dragoon 9 9398
Protoss_Robotics_Facility 1 6865
Protoss_Shuttle 1 7899
Protoss_Observatory 1 7739
Protoss_Observer 1 8502
Protoss_Robotics_Support_Bay 1 8733
Protoss_Reaver 1 9950
Protoss_Citadel_of_Adun 1 10316
10316
