Protoss_Gateway 3 8949
Protoss_Assimilator 1 2760
Protoss_Cybernetics_Core 1 3832
Protoss_Zealot 1 3674
Protoss_Dragoon 10 10602
Protoss_Robotics_Facility 1 6462
Protoss_Nexus 1 8289
Protoss_Observatory 1 7129
Protoss_Observer 3 9504
Protoss_Citadel_of_Adun 1 9551
10602
