Protoss_Nexus 1 4751
Protoss_Gateway 2 8497
Protoss_Assimilator 1 4270
Protoss_Zealot 2 5658
Protoss_Cybernetics_Core 1 6823
Protoss_Dragoon 6 10188
Protoss_Robotics_Facility 1 10032
10188
