Protoss_Gateway 3 8627
Protoss_Assimilator 2 8977
Protoss_Zealot 2 4454
Protoss_Cybernetics_Core 1 4454
Protoss_Dragoon 8 9850
Protoss_Nexus 1 8221
Protoss_Robotics_Facility 1 8002
Protoss_Observatory 1 8572
Protoss_Citadel_of_Adun 1 9430
Protoss_Observer 2 10148
Protoss_Templar_Archives 1 10493
Protoss_Forge 1 10398
10493
