Protoss_Gateway 1 3194
Protoss_Assimilator 1 3125
Protoss_Zealot 3 5203
Protoss_Cybernetics_Core 1 5304
Protoss_Dragoon 2 10283
Protoss_Robotics_Facility 2 7648
Protoss_Observatory 1 7877
Protoss_Shuttle 1 8337
Protoss_Robotics_Support_Bay 1 8231
Protoss_Observer 2 8940
Protoss_Reaver 2 10176
10283
