Protoss_Gateway 3 6715
Protoss_Assimilator 1 2806
Protoss_Cybernetics_Core 1 3844
Protoss_Dragoon 5 8238
Protoss_Robotics_Facility 1 7393
Protoss_Citadel_of_Adun 1 7159
Protoss_Forge 1 7626
Protoss_Templar_Archives 1 8258
Protoss_Photon_Cannon 3 10676
Protoss_Dark_Templar 2 9252
Protoss_High_Templar 2 10004
10676
