Protoss_Gateway 1 2814
Protoss_Assimilator 1 2996
Protoss_Zealot 2 4782
Protoss_Cybernetics_Core 1 4819
Protoss_Dragoon 7 10458
Protoss_Robotics_Facility 1 6703
Protoss_Robotics_Support_Bay 1 7243
Protoss_Nexus 1 9174
Protoss_Reaver 1 8504
Protoss_Observatory 1 8300
Protoss_Observer 1 9108
Protoss_Shuttle 1 10027
10458
