Protoss_Gateway 3 10863
Protoss_Zealot 2 4040
Protoss_Assimilator 1 3546
Protoss_Cybernetics_Core 1 4521
Protoss_Dragoon 11 10726
Protoss_Robotics_Facility 1 7256
Protoss_Nexus 1 8479
Protoss_Observatory 1 7819
Protoss_Observer 2 9100
10863
