Protoss_Gateway 3 10392
Protoss_Assimilator 1 3031
Protoss_Zealot 1 3628
Protoss_Cybernetics_Core 1 4769
Protoss_Dragoon 6 10268
Protoss_Robotics_Facility 1 6729
Protoss_Robotics_Support_Bay 1 7330
Protoss_Reaver 1 9041
Protoss_Nexus 1 10500
10500
