Protoss_Gateway 3 9653
Protoss_Assimilator 1 3543
Protoss_Cybernetics_Core 1 4227
Protoss_Zealot 3 8218
Protoss_Dragoon 12 10676
Protoss_Robotics_Facility 1 6807
Protoss_Observatory 1 7587
Protoss_Observer 2 8986
Protoss_Nexus 1 9855
10676
