Protoss_Gateway 3 9803
Protoss_Assimilator 1 3129
Protoss_Zealot 2 4644
Protoss_Cybernetics_Core 1 4656
Protoss_Dragoon 7 9836
Protoss_Robotics_Facility 1 7611
Protoss_Observatory 1 8217
Protoss_Observer 2 9800
Protoss_Nexus 1 10419
Protoss_Citadel_of_Adun 1 10691
10691
