Protoss_Gateway 2 6673
Protoss_Assimilator 2 10144
Protoss_Zealot 2 4718
Protoss_Cybernetics_Core 1 4739
Protoss_Dragoon 8 10564
Protoss_Nexus 1 8875
Protoss_Robotics_Facility 1 9282
Protoss_Citadel_of_Adun 1 10194
Protoss_Observatory 1 9859
Protoss_Observer 1 10584
10584
