Protoss_Gateway 2 7449
Protoss_Assimilator 1 3024
Protoss_Zealot 3 8184
Protoss_Cybernetics_Core 1 4877
Protoss_Dragoon 4 7972
Protoss_Citadel_of_Adun 1 7004
Protoss_Templar_Archives 1 8012
Protoss_Dark_Templar 4 10174
Protoss_Forge 1 8702
Protoss_Nexus 1 10397
Protoss_Photon_Cannon 2 9770
Protoss_High_Templar 1 10456
10456
