Protoss_Gateway 2 5239
Protoss_Assimilator 1 2989
Protoss_Zealot 3 10254
Protoss_Cybernetics_Core 1 4886
Protoss_Dragoon 10 9652
Protoss_Robotics_Facility 1 7857
Protoss_Robotics_Support_Bay 1 8451
Protoss_Shield_Battery 1 8673
Protoss_Reaver 1 9740
Protoss_Observatory 1 9499
Protoss_Observer 1 10386
10386
