Protoss_Gateway 2 8077
Protoss_Assimilator 2 9761
Protoss_Cybernetics_Core 1 3779
Protoss_Zealot 1 3730
Protoss_Dragoon 9 10214
Protoss_Nexus 1 8271
Protoss_Robotics_Facility 1 8721
Protoss_Observatory 1 9403
Protoss_Observer 1 10080
10214
