Protoss_Gateway 4 10423
Protoss_Assimilator 2 10509
Protoss_Zealot 2 4600
Protoss_Cybernetics_Core 1 4611
Protoss_Dragoon 11 10180
Protoss_Nexus 1 7961
Protoss_Robotics_Facility 1 8170
Protoss_Observatory 1 8775
Protoss_Observer 2 10062
10509
