Protoss_Gateway 2 6106
Protoss_Assimilator 1 2934
Protoss_Cybernetics_Core 1 3863
Protoss_Zealot 1 3802
Protoss_Dragoon 11 10504
Protoss_Robotics_Facility 1 7071
Protoss_Shuttle 1 8117
Protoss_Observatory 1 7745
Protoss_Robotics_Support_Bay 1 7997
Protoss_Observer 2 9718
10504
