Protoss_Gateway 2 7476
Protoss_Assimilator 1 2902
Protoss_Zealot 2 4468
Protoss_Cybernetics_Core 1 4448
Protoss_Dragoon 8 9574
Protoss_Robotics_Facility 1 6821
Protoss_Shuttle 1 7921
Protoss_Observatory 1 7509
Protoss_Observer 1 8524
Protoss_Robotics_Support_Bay 1 8430
Protoss_Reaver 2 10836
Protoss_Nexus 1 11161
11161
