Protoss_Gateway 2 9234
Protoss_Assimilator 2 9067
Protoss_Zealot 2 4842
Protoss_Cybernetics_Core 1 4897
Protoss_Dragoon 4 8224
Protoss_Nexus 1 8585
Protoss_Citadel_of_Adun 1 8011
Protoss_Robotics_Facility 1 9039
Protoss_Templar_Archives 1 9143
Protoss_Shuttle 1 10081
Protoss_Dark_Templar 2 10066
Protoss_Forge 1 10081
Protoss_Observatory 1 10436
10436
