Protoss_Gateway 3 10665
Protoss_Assimilator 1 2930
Protoss_Zealot 2 4572
Protoss_Cybernetics_Core 1 4547
Protoss_Dragoon 11 10356
Protoss_Robotics_Facility 1 6766
Protoss_Observatory 1 7611
Protoss_Nexus 1 9395
Protoss_Observer 2 8952
Protoss_Robotics_Support_Bay 1 8979
Protoss_Reaver 1 10106
10665
