Protoss_Gateway 4 10771
Protoss_Assimilator 2 9153
Protoss_Zealot 2 3506
Protoss_Cybernetics_Core 1 4665
Protoss_Dragoon 8 9718
Protoss_Nexus 1 8314
Protoss_Robotics_Facility 1 8058
Protoss_Observatory 1 8597
Protoss_Citadel_of_Adun 1 9340
Protoss_Observer 2 9920
Protoss_Templar_Archives 1 10377
10771
