Protoss_Gateway 3 10508
Protoss_Assimilator 2 9650
Protoss_Zealot 2 4796
Protoss_Cybernetics_Core 1 4697
Protoss_Dragoon 4 7804
Protoss_Citadel_of_Adun 1 6589
Protoss_Templar_Archives 1 7603
Protoss_Nexus 1 9197
Protoss_Forge 1 8347
Protoss_Dark_Templar 1 8556
Protoss_Photon_Cannon 2 9640
Protoss_High_Templar 2 10088
10508
