Protoss_Gateway 2 7483
Protoss_Assimilator 1 2867
Protoss_Zealot 2 4626
Protoss_Cybernetics_Core 1 4623
Protoss_Dragoon 7 9504
Protoss_Robotics_Facility 1 7005
Protoss_Shuttle 1 8083
Protoss_Observatory 1 7762
Protoss_Observer 1 8722
Protoss_Robotics_Support_Bay 1 8806
Protoss_Reaver 1 10032
Protoss_Nexus 1 11569
11569
