Protoss_Gateway 2 10289
Protoss_Assimilator 1 2828
Protoss_Zealot 2 4872
Protoss_Cybernetics_Core 1 4589
Protoss_Citadel_of_Adun 1 5629
Protoss_Dragoon 2 6712
Protoss_Templar_Archives 1 6619
Protoss_Forge 1 6900
Protoss_Dark_Templar 1 7464
Protoss_Photon_Cannon 3 9722
Protoss_High_Templar 3 9734
Protoss_Nexus 1 9693
10289
