Protoss_Gateway 2 6991
Protoss_Assimilator 1 2960
Protoss_Zealot 2 4324
Protoss_Cybernetics_Core 1 4512
Protoss_Dragoon 8 9466
Protoss_Robotics_Facility 1 6508
Protoss_Shuttle 1 7491
Protoss_Observatory 1 7240
Protoss_Observer 1 8094
Protoss_Robotics_Support_Bay 1 8137
Protoss_Reaver 1 9368
Protoss_Nexus 1 11506
11506
