Protoss_Gateway 2 7387
Protoss_Assimilator 1 2790
Protoss_Zealot 2 4460
Protoss_Cybernetics_Core 1 4554
Protoss_Dragoon 10 10714
Protoss_Robotics_Facility 1 7134
Protoss_Observatory 1 7704
Protoss_Observer 2 8994
Protoss_Nexus 1 10169
Protoss_Robotics_Support_Bay 1 9337
Protoss_Reaver 1 10700
10714
