Protoss_Gateway 2 8539
Protoss_Assimilator 2 9236
Protoss_Zealot 2 4612
Protoss_Cybernetics_Core 1 4617
Protoss_Dragoon 7 9734
Protoss_Nexus 1 8348
Protoss_Robotics_Facility 1 8135
Protoss_Observatory 1 8681
Protoss_Robotics_Support_Bay 1 8728
Protoss_Observer 1 9408
Protoss_Reaver 1 10458
10458
