Protoss_Gateway 2 6197
Protoss_Assimilator 1 2911
Protoss_Cybernetics_Core 1 3896
Protoss_Zealot 1 3742
Protoss_Dragoon 9 10702
Protoss_Robotics_Facility 1 7029
Protoss_Shuttle 1 8015
Protoss_Observatory 1 7927
Protoss_Observer 1 8618
Protoss_Robotics_Support_Bay 1 8717
Protoss_Reaver 1 10066
Protoss_Nexus 1 11319
11319
