Protoss_Gateway 2 7401
Protoss_Zealot 2 4516
Protoss_Assimilator 2 9707
Protoss_Cybernetics_Core 1 4569
Protoss_Dragoon 8 10228
Protoss_Robotics_Facility 1 7470
Protoss_Observatory 1 8068
Protoss_Observer 2 9356
Protoss_Nexus 1 10309
Protoss_Citadel_of_Adun 1 9790
10309
