Protoss_Gateway 4 10855
Protoss_Zealot 2 4054
Protoss_Assimilator 1 3661
Protoss_Cybernetics_Core 1 4744
Protoss_Dragoon 8 9418
Protoss_Nexus 1 8855
Protoss_Robotics_Facility 1 9341
Protoss_Citadel_of_Adun 1 10160
Protoss_Observatory 1 9976
10855
