Protoss_Gateway 2 7397
Protoss_Assimilator 1 2928
Protoss_Zealot 2 4624
Protoss_Cybernetics_Core 1 4848
Protoss_Dragoon 10 10650
Protoss_Robotics_Facility 1 7021
Protoss_Shuttle 1 8001
Protoss_Observatory 1 8143
Protoss_Observer 1 8888
Protoss_Robotics_Support_Bay 1 8818
Protoss_Reaver 1 9964
Protoss_Nexus 1 11462
11462
