Protoss_Gateway 1 2703
Protoss_Assimilator 1 2967
Protoss_Cybernetics_Core 1 3893
Protoss_Zealot 1 3814
Protoss_Dragoon 7 10378
Protoss_Robotics_Facility 1 6771
Protoss_Shuttle 1 7907
Protoss_Observatory 1 7584
Protoss_Robotics_Support_Bay 1 8167
Protoss_Observer 1 8582
Protoss_Nexus 1 10232
Protoss_Reaver 2 10718
10718
