Protoss_Gateway 2 6471
Protoss_Assimilator 1 3465
Protoss_Zealot 2 4960
Protoss_Cybernetics_Core 1 4723
Protoss_Dragoon 9 10564
Protoss_Robotics_Facility 1 7735
Protoss_Observatory 1 8352
Protoss_Observer 1 9244
Protoss_Shuttle 1 10355
Protoss_Robotics_Support_Bay 1 10261
10564
