Protoss_Gateway 4 10495
Protoss_Assimilator 1 2835
Protoss_Zealot 2 4432
Protoss_Cybernetics_Core 1 4446
Protoss_Dragoon 8 9748
Protoss_Robotics_Facility 1 7088
Protoss_Observatory 1 7695
Protoss_Nexus 1 9412
Protoss_Observer 1 8382
Protoss_Robotics_Support_Bay 1 8331
Protoss_Reaver 2 10826
10826
