Protoss_Gateway 2 10023
Protoss_Assimilator 1 2968
Protoss_Zealot 2 4504
Protoss_Cybernetics_Core 1 4464
Protoss_Dragoon 7 10402
Protoss_Robotics_Facility 1 6744
Protoss_Robotics_Support_Bay 1 7297
Protoss_Shuttle 1 8317
Protoss_Nexus 1 9991
Protoss_Reaver 2 10548
Protoss_Observatory 1 9065
10548
