Protoss_Gateway 2 7035
Protoss_Assimilator 1 2946
Protoss_Zealot 2 4562
Protoss_Cybernetics_Core 1 4659
Protoss_Dragoon 8 10722
Protoss_Robotics_Facility 1 6845
Protoss_Shuttle 1 7929
Protoss_Robotics_Support_Bay 1 8043
Protoss_Observatory 1 8127
Protoss_Reaver 1 9446
Protoss_Observer 1 10050
Protoss_Nexus 1 11447
11447
