Protoss_Gateway 5 10001
Protoss_Zealot 2 4428
Protoss_Assimilator 1 3660
Protoss_Cybernetics_Core 1 4497
Protoss_Dragoon 11 10644
Protoss_Nexus 1 7827
Protoss_Robotics_Facility 1 7565
Protoss_Observatory 1 8560
Protoss_Observer 2 10158
10644
