Protoss_Gateway 2 7927
Protoss_Zealot 2 4658
Protoss_Assimilator 2 9579
Protoss_Cybernetics_Core 1 4795
Protoss_Dragoon 10 10426
Protoss_Nexus 1 8010
Protoss_Robotics_Facility 1 9082
Protoss_Forge 1 9805
Protoss_Observatory 1 9732
Protoss_Observer 1 10418
10426
