Protoss_Gateway 4 10882
Protoss_Assimilator 1 2963
Protoss_Zealot 2 4642
Protoss_Cybernetics_Core 1 4633
Protoss_Dragoon 11 10258
Protoss_Nexus 1 8533
Protoss_Robotics_Facility 1 10312
10882
