Protoss_Gateway 3 8920
Protoss_Assimilator 1 3010
Protoss_Zealot 2 4674
Protoss_Cybernetics_Core 1 4638
Protoss_Dragoon 14 10538
Protoss_Robotics_Facility 1 8014
Protoss_Observatory 1 8601
Protoss_Observer 2 9884
10538
