Protoss_Gateway 2 7547
Protoss_Assimilator 1 3066
Protoss_Cybernetics_Core 1 3979
Protoss_Zealot 1 3884
Protoss_Dragoon 9 10204
Protoss_Robotics_Facility 1 7157
Protoss_Shuttle 1 8153
Protoss_Robotics_Support_Bay 1 8253
Protoss_Observatory 1 8353
Protoss_Observer 1 9032
Protoss_Reaver 1 10452
10452
