Protoss_Gateway 2 7684
Protoss_Assimilator 1 2807
Protoss_Zealot 2 4640
Protoss_Cybernetics_Core 1 4613
Protoss_Dragoon 10 10412
Protoss_Robotics_Facility 1 7366
Protoss_Shuttle 1 8371
Protoss_Observatory 1 8300
Protoss_Observer 1 9022
Protoss_Robotics_Support_Bay 1 8959
Protoss_Reaver 1 10260
10412
