Protoss_Gateway 2 7235
Protoss_Assimilator 1 3067
Protoss_Zealot 2 4948
Protoss_Cybernetics_Core 1 4935
Protoss_Dragoon 9 10100
Protoss_Robotics_Facility 1 7266
Protoss_Shuttle 1 8471
Protoss_Robotics_Support_Bay 1 8455
Protoss_Reaver 1 9596
Protoss_Observatory 1 9402
Protoss_Observer 1 10200
10200
