Protoss_Gateway 2 7565
Protoss_Assimilator 1 2886
Protoss_Zealot 2 4716
Protoss_Cybernetics_Core 1 4644
Protoss_Dragoon 10 10508
Protoss_Robotics_Facility 1 8651
Protoss_Shuttle 1 9729
Protoss_Observatory 1 9479
Protoss_Robotics_Support_Bay 1 10024
Protoss_Observer 1 10332
10508
