Protoss_Gateway 1 2802
Protoss_Assimilator 1 3018
Protoss_Zealot 2 4666
Protoss_Cybernetics_Core 1 4643
Protoss_Dragoon 4 8162
Protoss_Citadel_of_Adun 1 7188
Protoss_Nexus 1 8942
Protoss_Templar_Archives 1 8177
Protoss_Forge 1 8423
Protoss_Dark_Templar 3 10516
Protoss_Photon_Cannon 2 9316
10516
