Protoss_Gateway 3 6885
Protoss_Assimilator 1 2921
Protoss_Zealot 2 4590
Protoss_Cybernetics_Core 1 4629
Protoss_Dragoon 14 10400
Protoss_Forge 1 9836
Protoss_Robotics_Facility 1 10697
10697
