Protoss_Gateway 4 10339
Protoss_Assimilator 1 3010
Protoss_Zealot 2 4636
Protoss_Cybernetics_Core 1 4611
Protoss_Dragoon 11 10508
Protoss_Robotics_Facility 1 6850
Protoss_Observatory 1 7473
Protoss_Observer 2 8946
Protoss_Nexus 1 10045
10508
