Protoss_Gateway 2 9947
Protoss_Assimilator 2 10005
Protoss_Zealot 2 4606
Protoss_Cybernetics_Core 1 4613
Protoss_Dragoon 4 7716
Protoss_Citadel_of_Adun 1 6619
Protoss_Templar_Archives 1 7609
Protoss_Nexus 1 9061
Protoss_Forge 1 8212
Protoss_Dark_Templar 1 8528
Protoss_Photon_Cannon 4 10496
Protoss_High_Templar 2 10096
10496
