Protoss_Gateway 4 9349
Protoss_Assimilator 1 2803
Protoss_Cybernetics_Core 1 3738
Protoss_Zealot 1 3598
Protoss_Citadel_of_Adun 1 4729
Protoss_Dragoon 11 10550
Protoss_Templar_Archives 1 5748
Protoss_Dark_Templar 1 6674
Protoss_Nexus 1 8147
Protoss_Robotics_Facility 1 10622
10622
