Protoss_Gateway 2 7339
Protoss_Assimilator 1 2835
Protoss_Zealot 2 4500
Protoss_Cybernetics_Core 1 4530
Protoss_Dragoon 7 10028
Protoss_Robotics_Facility 1 7039
Protoss_Observatory 1 7599
Protoss_Observer 2 8958
Protoss_Nexus 1 9887
Protoss_Robotics_Support_Bay 1 8905
Protoss_Reaver 1 10138
Protoss_Citadel_of_Adun 1 10714
10714
