Protoss_Gateway 2 10315
Protoss_Assimilator 2 9790
Protoss_Zealot 2 4684
Protoss_Cybernetics_Core 1 4691
Protoss_Dragoon 4 7998
Protoss_Citadel_of_Adun 1 7033
Protoss_Templar_Archives 1 8083
Protoss_Nexus 1 9523
Protoss_Forge 1 8620
Protoss_Dark_Templar 1 8914
Protoss_Photon_Cannon 3 10737
Protoss_High_Templar 2 10466
10737
