Protoss_Gateway 3 10417
Protoss_Assimilator 2 9680
Protoss_Zealot 2 4634
Protoss_Cybernetics_Core 1 4662
Protoss_Dragoon 4 7748
Protoss_Citadel_of_Adun 1 6762
Protoss_Templar_Archives 1 7757
Protoss_Nexus 1 9113
Protoss_Forge 1 8164
Protoss_Dark_Templar 1 8588
Protoss_Photon_Cannon 2 9427
Protoss_High_Templar 2 10092
10417
