Protoss_Gateway 2 10059
Protoss_Assimilator 2 9380
Protoss_Zealot 2 4758
Protoss_Cybernetics_Core 1 4629
Protoss_Dragoon 4 7882
Protoss_Citadel_of_Adun 1 6347
Protoss_Templar_Archives 1 7587
Protoss_Nexus 1 9136
Protoss_Dark_Templar 1 8634
Protoss_Forge 1 8484
Protoss_Photon_Cannon 2 9690
Protoss_High_Templar 2 10138
10138
