Protoss_Gateway 2 9899
Protoss_Assimilator 2 9919
Protoss_Zealot 2 4626
Protoss_Cybernetics_Core 1 4716
Protoss_Dragoon 4 7816
Protoss_Citadel_of_Adun 1 6627
Protoss_Templar_Archives 1 7645
Protoss_Nexus 1 9071
Protoss_Forge 1 8116
Protoss_Dark_Templar 1 8568
Protoss_Photon_Cannon 5 10672
Protoss_High_Templar 2 10072
10672
