Protoss_Gateway 2 6906
Protoss_Assimilator 1 3018
Protoss_Zealot 2 4660
Protoss_Cybernetics_Core 1 4663
Protoss_Dragoon 11 10658
Protoss_Robotics_Facility 1 6945
Protoss_Shuttle 1 7953
Protoss_Robotics_Support_Bay 1 7913
Protoss_Observatory 1 8435
Protoss_Reaver 1 9314
Protoss_Observer 2 10520
Protoss_Forge 1 9975
10658
