Protoss_Gateway 2 6679
Protoss_Zealot 2 4506
Protoss_Assimilator 1 3819
Protoss_Cybernetics_Core 1 4650
Protoss_Dragoon 11 10120
Protoss_Robotics_Facility 1 7904
Protoss_Observatory 1 8536
Protoss_Observer 1 9620
Protoss_Nexus 1 11640
11640
