Protoss_Gateway 4 9229
Protoss_Assimilator 1 2962
Protoss_Cybernetics_Core 1 3773
Protoss_Zealot 1 3892
Protoss_Dragoon 15 10666
Protoss_Robotics_Facility 1 6493
Protoss_Observatory 1 7114
Protoss_Observer 2 8398
10666
