Protoss_Gateway 2 7553
Protoss_Assimilator 1 2989
Protoss_Zealot 2 4360
Protoss_Cybernetics_Core 1 4478
Protoss_Dragoon 10 10434
Protoss_Robotics_Facility 1 7051
Protoss_Shuttle 1 8117
Protoss_Robotics_Support_Bay 1 8046
Protoss_Reaver 1 9286
10434
