Protoss_Gateway 2 6991
Protoss_Assimilator 1 3067
Protoss_Zealot 2 4730
Protoss_Cybernetics_Core 1 4683
Protoss_Dragoon 11 10466
Protoss_Robotics_Facility 1 6967
Protoss_Shuttle 1 8015
Protoss_Robotics_Support_Bay 1 8205
Protoss_Reaver 1 9340
Protoss_Observatory 1 9146
Protoss_Observer 1 9944
10466
