Protoss_Gateway 3 10338
Protoss_Assimilator 1 2978
Protoss_Zealot 2 4250
Protoss_Cybernetics_Core 1 5175
Protoss_Dragoon 10 10536
Protoss_Robotics_Facility 1 7314
Protoss_Observatory 1 7925
Protoss_Observer 2 9420
Protoss_Nexus 1 10750
Protoss_Robotics_Support_Bay 1 9546
Protoss_Reaver 1 10894
10894
