Protoss_Gateway 2 7065
Protoss_Assimilator 1 3051
Protoss_Zealot 2 4770
Protoss_Cybernetics_Core 1 4715
Protoss_Dragoon 9 9932
Protoss_Robotics_Facility 1 7166
Protoss_Shuttle 1 8225
Protoss_Robotics_Support_Bay 1 8215
Protoss_Reaver 1 9512
Protoss_Observatory 1 9365
Protoss_Forge 1 10138
Protoss_Observer 1 10308
10308
