Protoss_Gateway 2 10335
Protoss_Forge 1 3725
Protoss_Photon_Cannon 7 7980
Protoss_Zealot 2 7156
Protoss_Nexus 1 8149
Protoss_Assimilator 1 7534
Protoss_Cybernetics_Core 1 8723
Protoss_Dragoon 2 10468
Protoss_Robotics_Facility 1 10198
Protoss_Citadel_of_Adun 1 10786
10786
