Protoss_Gateway 3 9444
Protoss_Zealot 6 10176
Protoss_Nexus 1 7198
Protoss_Forge 2 6782
Protoss_Assimilator 2 10036
Protoss_Photon_Cannon 3 8470
Protoss_Cybernetics_Core 1 8333
Protoss_Dragoon 2 9786
Protoss_Robotics_Facility 1 10788
10788
