Protoss_Gateway 3 9596
Protoss_Assimilator 1 3114
Protoss_Zealot 8 9970
Protoss_Cybernetics_Core 1 4755
Protoss_Shield_Battery 1 5661
Protoss_Dragoon 6 10640
Protoss_Robotics_Facility 1 9037
Protoss_Observatory 1 9609
Protoss_Observer 1 10286
10640
