Protoss_Gateway 2 5339
Protoss_Assimilator 1 3064
Protoss_Zealot 3 5216
Protoss_Cybernetics_Core 1 4567
Protoss_Dragoon 8 9524
Protoss_Robotics_Facility 1 7683
Protoss_Observatory 1 8398
Protoss_Observer 2 9678
Protoss_Robotics_Support_Bay 1 9403
Protoss_Nexus 1 11459
Protoss_Reaver 1 11030
11459
