Protoss_Gateway 2 3269
Protoss_Assimilator 1 3677
Protoss_Cybernetics_Core 1 4616
Protoss_Zealot 3 9656
Protoss_Citadel_of_Adun 1 6033
Protoss_Forge 1 6340
Protoss_Templar_Archives 1 7315
Protoss_High_Templar 2 8386
Protoss_Nexus 1 9947
Protoss_Photon_Cannon 3 10514
Protoss_Dark_Templar 1 9260
Protoss_Archon 1 8812
10514
