Protoss_Gateway 2 4899
Protoss_Assimilator 1 2884
Protoss_Zealot 1 3544
Protoss_Cybernetics_Core 1 4279
Protoss_Dragoon 9 8554
Protoss_Robotics_Facility 1 7863
Protoss_Observatory 1 8627
8627
