Protoss_Gateway 1 2888
Protoss_Assimilator 1 3057
Protoss_Zealot 2 4398
Protoss_Cybernetics_Core 1 4387
Protoss_Dragoon 5 8954
Protoss_Robotics_Facility 1 6941
Protoss_Observatory 1 7493
Protoss_Robotics_Support_Bay 1 7521
Protoss_Reaver 1 8842
8954
