Protoss_Gateway 2 3450
Protoss_Zealot 5 5638
Protoss_Assimilator 1 4123
Protoss_Cybernetics_Core 1 5717
Protoss_Dragoon 8 10524
Protoss_Robotics_Facility 1 8685
Protoss_Nexus 1 10428
Protoss_Observatory 1 9312
Protoss_Robotics_Support_Bay 1 9583
Protoss_Observer 1 10170
10524
