Protoss_Gateway 4 10835
Protoss_Assimilator 1 3425
Protoss_Cybernetics_Core 1 4602
Protoss_Zealot 2 5024
Protoss_Dragoon 9 9668
Protoss_Robotics_Facility 1 6735
Protoss_Observatory 1 7640
Protoss_Observer 2 9038
Protoss_Nexus 1 11364
11364
