Protoss_Gateway 3 8875
Protoss_Assimilator 2 4008
Protoss_Zealot 7 7702
Protoss_Cybernetics_Core 1 5649
Protoss_Dragoon 4 10178
Protoss_Citadel_of_Adun 1 7650
Protoss_Forge 1 8227
Protoss_Templar_Archives 1 8789
Protoss_Photon_Cannon 1 9510
Protoss_Dark_Templar 3 9802
Protoss_High_Templar 1 10002
Protoss_Nexus 1 11531
11531
