Protoss_Gateway 2 7703
Protoss_Assimilator 2 8862
Protoss_Cybernetics_Core 1 4187
Protoss_Zealot 2 9568
Protoss_Dragoon 8 10582
Protoss_Nexus 1 7822
Protoss_Citadel_of_Adun 1 8916
Protoss_Robotics_Facility 1 9861
Protoss_Templar_Archives 1 10348
Protoss_Observatory 1 10419
10582
