Protoss_Gateway 2 5009
Protoss_Assimilator 1 3072
Protoss_Zealot 2 10312
Protoss_Cybernetics_Core 1 4559
Protoss_Dragoon 12 10680
Protoss_Robotics_Facility 1 7225
Protoss_Shuttle 1 8243
Protoss_Robotics_Support_Bay 1 7871
Protoss_Reaver 2 10346
Protoss_Observatory 1 10032
10680
