Protoss_Gateway 3 9297
Protoss_Assimilator 1 2909
Protoss_Zealot 4 9928
Protoss_Cybernetics_Core 1 4335
Protoss_Dragoon 11 10148
Protoss_Robotics_Facility 1 7014
Protoss_Observatory 1 8011
Protoss_Observer 1 8792
Protoss_Robotics_Support_Bay 1 9433
Protoss_Shuttle 1 10747
10747
