Protoss_Gateway 3 7365
Protoss_Zealot 6 6012
Protoss_Assimilator 1 5415
Protoss_Cybernetics_Core 1 6719
Protoss_Dragoon 5 9066
Protoss_Citadel_of_Adun 1 7959
Protoss_Templar_Archives 1 8990
Protoss_Forge 1 9218
Protoss_Dark_Templar 2 9948
Protoss_Photon_Cannon 1 10228
10228
