Protoss_Gateway 3 9873
Protoss_Assimilator 1 2759
Protoss_Zealot 2 4314
Protoss_Cybernetics_Core 1 4328
Protoss_Dragoon 10 10712
Protoss_Robotics_Facility 1 6197
Protoss_Robotics_Support_Bay 1 6739
Protoss_Reaver 2 9330
Protoss_Observatory 1 7737
Protoss_Observer 1 8626
Protoss_Shuttle 1 10381
10712
