Protoss_Gateway 2 6727
Protoss_Assimilator 1 2984
Protoss_Zealot 2 4294
Protoss_Cybernetics_Core 1 4455
Protoss_Dragoon 9 10600
Protoss_Robotics_Facility 1 6849
Protoss_Observatory 1 7500
Protoss_Observer 2 9500
Protoss_Nexus 1 10286
Protoss_Robotics_Support_Bay 1 9278
Protoss_Reaver 1 10864
10864
