Protoss_Gateway 2 4999
Protoss_Assimilator 1 2937
Protoss_Zealot 3 9028
Protoss_Cybernetics_Core 1 4287
Protoss_Dragoon 11 10478
Protoss_Robotics_Facility 1 7727
Protoss_Observatory 1 8269
Protoss_Robotics_Support_Bay 1 8760
Protoss_Observer 1 9010
Protoss_Nexus 1 10573
Protoss_Reaver 1 10290
10573
