Protoss_Gateway 3 7921
Protoss_Assimilator 2 9761
Protoss_Zealot 2 4524
Protoss_Cybernetics_Core 1 4548
Protoss_Dragoon 10 10640
Protoss_Nexus 1 7845
Protoss_Robotics_Facility 1 7744
Protoss_Observatory 1 8345
Protoss_Observer 2 10394
Protoss_Citadel_of_Adun 1 9780
10640
