Protoss_Gateway 2 7609
Protoss_Assimilator 2 9248
Protoss_Zealot 2 4452
Protoss_Cybernetics_Core 1 4574
Protoss_Dragoon 3 7062
Protoss_Citadel_of_Adun 1 6498
Protoss_Nexus 1 7866
Protoss_Templar_Archives 1 7675
Protoss_Forge 1 8104
Protoss_Dark_Templar 2 8524
Protoss_Photon_Cannon 2 9190
Protoss_High_Templar 4 10600
10600
