Protoss_Gateway 2 7611
Protoss_Assimilator 1 2902
Protoss_Zealot 2 4536
Protoss_Cybernetics_Core 1 4471
Protoss_Dragoon 8 10566
Protoss_Robotics_Facility 1 7053
Protoss_Shuttle 1 8119
Protoss_Observatory 1 7964
Protoss_Observer 1 8722
Protoss_Robotics_Support_Bay 1 8933
Protoss_Nexus 1 10873
Protoss_Reaver 1 10510
10873
