Protoss_Gateway 2 7257
Protoss_Assimilator 1 2796
Protoss_Zealot 2 4540
Protoss_Cybernetics_Core 1 4566
Protoss_Dragoon 8 10632
Protoss_Robotics_Facility 1 6717
Protoss_Observatory 1 7394
Protoss_Robotics_Support_Bay 1 7592
Protoss_Observer 1 8306
Protoss_Shuttle 1 9360
Protoss_Reaver 1 10411
Protoss_Nexus 1 11513
11513
