Protoss_Gateway 3 9023
Protoss_Assimilator 2 10214
Protoss_Cybernetics_Core 1 3791
Protoss_Zealot 1 3670
Protoss_Dragoon 10 10662
Protoss_Robotics_Facility 1 7265
Protoss_Nexus 1 8950
Protoss_Observatory 1 8161
Protoss_Observer 2 9444
Protoss_Citadel_of_Adun 1 10670
10670
