Protoss_Gateway 2 6231
Protoss_Assimilator 2 10338
Protoss_Zealot 2 4522
Protoss_Cybernetics_Core 1 4493
Protoss_Dragoon 3 8416
Protoss_Citadel_of_Adun 1 5731
Protoss_Templar_Archives 1 6717
Protoss_Dark_Templar 4 8792
Protoss_Nexus 1 9299
Protoss_Forge 1 8401
Protoss_Photon_Cannon 4 9847
Protoss_High_Templar 2 10318
10338
