Protoss_Gateway 2 6127
Protoss_Assimilator 1 2824
Protoss_Cybernetics_Core 1 3812
Protoss_Dragoon 9 8736
Protoss_Robotics_Facility 1 8881
Protoss_Observatory 1 9466
Protoss_Zealot 1 9700
Protoss_Nexus 1 11113
Protoss_Observer 1 10146
Protoss_Robotics_Support_Bay 1 10162
11113
