Protoss_Gateway 2 10231
Protoss_Assimilator 1 2773
Protoss_Zealot 3 7022
Protoss_Cybernetics_Core 1 4702
Protoss_Dragoon 6 10520
Protoss_Nexus 3 11753
Protoss_Robotics_Facility 1 8864
Protoss_Observatory 1 9443
11753
