Protoss_Gateway 2 7271
Protoss_Assimilator 1 2967
Protoss_Zealot 2 4436
Protoss_Cybernetics_Core 1 4582
Protoss_Dragoon 8 9978
Protoss_Robotics_Facility 1 7106
Protoss_Observatory 1 7824
Protoss_Observer 1 8668
Protoss_Robotics_Support_Bay 1 8848
Protoss_Nexus 1 10505
10505
