Protoss_Gateway 2 3320
Protoss_Zealot 6 5392
Protoss_Assimilator 1 6286
Protoss_Cybernetics_Core 1 6823
Protoss_Nexus 1 8567
Protoss_Dragoon 6 10006
Protoss_Forge 1 8515
Protoss_Photon_Cannon 1 9596
Protoss_Robotics_Facility 1 10963
10963
