Protoss_Gateway 2 7100
Protoss_Assimilator 1 2876
Protoss_Cybernetics_Core 1 4544
Protoss_Zealot 1 4452
Protoss_Dragoon 9 10267
Protoss_Robotics_Facility 1 6983
Protoss_Observatory 1 7577
Protoss_Observer 2 9104
Protoss_Robotics_Support_Bay 1 9482
Protoss_Shuttle 1 10005
Protoss_Nexus 1 11576
11576
