Protoss_Gateway 4 10435
Protoss_Assimilator 1 2814
Protoss_Zealot 2 4590
Protoss_Cybernetics_Core 1 4597
Protoss_Dragoon 12 10414
Protoss_Robotics_Facility 1 6663
Protoss_Observatory 1 7747
Protoss_Observer 2 9064
10435
