Protoss_Gateway 3 8317
Protoss_Zealot 5 5668
Protoss_Assimilator 1 4350
Protoss_Cybernetics_Core 1 5333
Protoss_Dragoon 8 10650
Protoss_Robotics_Facility 1 9363
Protoss_Shuttle 1 10345
Protoss_Robotics_Support_Bay 1 10119
10650
