Protoss_Gateway 4 10421
Protoss_Forge 1 3214
Protoss_Zealot 9 8930
Protoss_Photon_Cannon 8 7614
Protoss_Assimilator 1 8559
Protoss_Cybernetics_Core 1 9672
Protoss_Dragoon 1 10566
10566
