Protoss_Gateway 3 7717
Protoss_Assimilator 1 3013
Protoss_Cybernetics_Core 1 3895
Protoss_Dragoon 14 10600
Protoss_Robotics_Facility 1 7256
Protoss_Observatory 1 8167
Protoss_Observer 1 9146
Protoss_Nexus 1 11131
11131
