Protoss_Gateway 3 8419
Protoss_Assimilator 1 3158
Protoss_Zealot 3 9396
Protoss_Cybernetics_Core 1 4330
Protoss_Dragoon 11 10400
Protoss_Nexus 1 8536
Protoss_Robotics_Facility 1 9399
Protoss_Observatory 1 10047
10400
