Protoss_Gateway 3 9409
Protoss_Assimilator 1 2960
Protoss_Zealot 4 9588
Protoss_Cybernetics_Core 1 4769
Protoss_Dragoon 8 10306
Protoss_Robotics_Facility 1 7251
Protoss_Shuttle 1 8295
Protoss_Observatory 1 8152
Protoss_Robotics_Support_Bay 1 8691
Protoss_Observer 1 8898
Protoss_Reaver 1 10262
10306
