Protoss_Gateway 3 8591
Protoss_Assimilator 1 3059
Protoss_Zealot 2 4364
Protoss_Cybernetics_Core 1 4571
Protoss_Dragoon 11 10346
Protoss_Robotics_Facility 1 7657
Protoss_Robotics_Support_Bay 1 8467
Protoss_Reaver 1 9596
Protoss_Observatory 1 9370
Protoss_Observer 1 10548
10548
