Protoss_Gateway 2 8270
Protoss_Assimilator 1 2935
Protoss_Zealot 2 4504
Protoss_Cybernetics_Core 1 4485
Protoss_Dragoon 8 9976
Protoss_Robotics_Facility 1 6653
Protoss_Shuttle 1 7637
Protoss_Observatory 1 7441
Protoss_Observer 1 8251
Protoss_Robotics_Support_Bay 1 8125
Protoss_Reaver 2 10852
Protoss_Nexus 1 11414
11414
