Protoss_Gateway 2 8989
Protoss_Assimilator 1 2937
Protoss_Zealot 2 4828
Protoss_Cybernetics_Core 1 4528
Protoss_Dragoon 8 10448
Protoss_Robotics_Facility 1 6257
Protoss_Shuttle 1 7245
Protoss_Robotics_Support_Bay 1 7005
Protoss_Reaver 1 8296
Protoss_Observatory 1 8630
Protoss_Observer 2 9958
Protoss_Nexus 1 11135
11135
