Protoss_Gateway 2 6839
Protoss_Assimilator 1 3004
Protoss_Zealot 2 4624
Protoss_Cybernetics_Core 1 4551
Protoss_Dragoon 10 10346
Protoss_Robotics_Facility 1 6844
Protoss_Shuttle 1 8251
Protoss_Observatory 1 8089
Protoss_Observer 1 8978
Protoss_Robotics_Support_Bay 1 8949
Protoss_Nexus 1 10359
Protoss_Reaver 1 10558
10558
