Protoss_Gateway 2 6911
Protoss_Assimilator 1 2852
Protoss_Zealot 2 4672
Protoss_Cybernetics_Core 1 4679
Protoss_Dragoon 9 10344
Protoss_Robotics_Facility 1 6915
Protoss_Observatory 1 7728
Protoss_Observer 1 8430
Protoss_Robotics_Support_Bay 1 8644
Protoss_Nexus 1 10409
Protoss_Reaver 1 10026
10409
