Protoss_Gateway 3 6703
Protoss_Assimilator 1 3071
Protoss_Zealot 2 4470
Protoss_Cybernetics_Core 1 4527
Protoss_Dragoon 15 10424
Protoss_Robotics_Facility 1 7869
Protoss_Observatory 1 8680
Protoss_Observer 1 9916
10424
