Protoss_Gateway 2 6816
Protoss_Assimilator 1 2797
Protoss_Zealot 2 4476
Protoss_Cybernetics_Core 1 4643
Protoss_Dragoon 11 10180
Protoss_Robotics_Facility 1 8369
Protoss_Robotics_Support_Bay 1 9810
Protoss_Shuttle 1 10347
Protoss_Observatory 1 10202
10347
