Protoss_Gateway 3 10577
Protoss_Assimilator 1 3032
Protoss_Zealot 1 3538
Protoss_Cybernetics_Core 1 4139
Protoss_Dragoon 10 10118
Protoss_Robotics_Facility 1 7865
Protoss_Observatory 1 8427
Protoss_Observer 2 9800
Protoss_Nexus 1 10611
10611
