Protoss_Gateway 2 5361
Protoss_Assimilator 1 2813
Protoss_Zealot 1 3434
Protoss_Cybernetics_Core 1 4675
Protoss_Dragoon 10 10118
Protoss_Robotics_Facility 1 7652
Protoss_Observatory 1 8305
Protoss_Observer 1 9028
Protoss_Shuttle 1 9929
Protoss_Nexus 1 10864
Protoss_Robotics_Support_Bay 1 9656
10864
