Protoss_Gateway 2 6740
Protoss_Assimilator 1 2897
Protoss_Zealot 2 4416
Protoss_Cybernetics_Core 1 4381
Protoss_Citadel_of_Adun 1 5789
Protoss_Dragoon 3 10511
Protoss_Templar_Archives 1 6819
Protoss_Dark_Templar 2 7824
Protoss_Forge 1 7610
Protoss_Nexus 1 9751
Protoss_Photon_Cannon 2 9588
Protoss_High_Templar 2 9736
10511
