Protoss_Gateway 4 8721
Protoss_Zealot 2 4818
Protoss_Nexus 1 5761
Protoss_Assimilator 1 4988
Protoss_Forge 1 5591
Protoss_Cybernetics_Core 1 6215
Protoss_Photon_Cannon 4 10532
Protoss_Dragoon 10 10434
10532
