Protoss_Gateway 2 4568
Protoss_Assimilator 2 8822
Protoss_Zealot 1 3412
Protoss_Cybernetics_Core 1 4154
Protoss_Dragoon 13 10482
Protoss_Nexus 1 8211
Protoss_Citadel_of_Adun 1 8511
Protoss_Templar_Archives 1 9943
Protoss_Robotics_Facility 1 11080
11080
