Protoss_Gateway 2 7596
Protoss_Assimilator 2 10356
Protoss_Zealot 2 5168
Protoss_Cybernetics_Core 1 5194
Protoss_Dragoon 6 10632
Protoss_Robotics_Facility 1 7423
Protoss_Observatory 1 7963
Protoss_Robotics_Support_Bay 1 8123
Protoss_Observer 1 8650
Protoss_Nexus 1 10183
Protoss_Reaver 1 10424
10632
