Protoss_Gateway 2 6991
Protoss_Assimilator 1 3040
Protoss_Zealot 2 4698
Protoss_Cybernetics_Core 1 4739
Protoss_Dragoon 7 10242
Protoss_Citadel_of_Adun 1 6654
Protoss_Templar_Archives 1 7671
Protoss_Dark_Templar 4 9490
Protoss_Forge 1 8572
Protoss_Nexus 1 11457
11457
