Protoss_Gateway 2 7206
Protoss_Assimilator 1 2945
Protoss_Zealot 2 4532
Protoss_Cybernetics_Core 1 4607
Protoss_Dragoon 6 8952
Protoss_Robotics_Facility 1 7123
Protoss_Shuttle 1 8181
Protoss_Robotics_Support_Bay 1 8276
Protoss_Reaver 1 9406
Protoss_Observatory 1 9841
9841
