Protoss_Gateway 2 6218
Protoss_Zealot 2 4586
Protoss_Assimilator 2 10572
Protoss_Cybernetics_Core 1 4890
Protoss_Dragoon 12 10584
Protoss_Robotics_Facility 1 7759
Protoss_Observatory 1 8406
Protoss_Observer 2 9640
Protoss_Nexus 1 10431
Protoss_Citadel_of_Adun 1 10318
10584
