Protoss_Gateway 3 10725
Protoss_Assimilator 1 3002
Protoss_Zealot 2 4598
Protoss_Cybernetics_Core 1 4643
Protoss_Dragoon 10 10656
Protoss_Robotics_Facility 1 7082
Protoss_Observatory 1 7691
Protoss_Observer 1 8528
Protoss_Robotics_Support_Bay 1 8458
Protoss_Reaver 1 9890
Protoss_Nexus 1 11135
11135
