Protoss_Gateway 3 9585
Protoss_Assimilator 1 3120
Protoss_Cybernetics_Core 1 4089
Protoss_Dragoon 13 10623
Protoss_Robotics_Facility 1 7427
Protoss_Observatory 1 7978
Protoss_Observer 1 8663
Protoss_Robotics_Support_Bay 1 10429
10623
