Protoss_Gateway 2 7083
Protoss_Assimilator 1 2980
Protoss_Zealot 2 4648
Protoss_Cybernetics_Core 1 4779
Protoss_Dragoon 7 9138
Protoss_Robotics_Facility 1 6799
Protoss_Shuttle 1 7811
Protoss_Observatory 1 7927
Protoss_Observer 1 8746
Protoss_Nexus 1 10387
Protoss_Robotics_Support_Bay 1 9279
Protoss_Reaver 1 10664
10664
