Protoss_Gateway 3 10654
Protoss_Assimilator 1 2972
Protoss_Cybernetics_Core 1 4004
Protoss_Robotics_Facility 1 5452
Protoss_Dragoon 5 10688
Protoss_Shuttle 1 6442
Protoss_Robotics_Support_Bay 1 6101
Protoss_Reaver 3 9711
Protoss_Observatory 1 9716
Protoss_Nexus 1 11395
11395
