Protoss_Gateway 2 10199
Protoss_Assimilator 1 3241
Protoss_Cybernetics_Core 1 4203
Protoss_Robotics_Facility 1 5602
Protoss_Dragoon 6 10453
Protoss_Shuttle 1 6587
Protoss_Observatory 1 6346
Protoss_Observer 1 7638
Protoss_Robotics_Support_Bay 1 7617
Protoss_Reaver 2 10276
10453
