Protoss_Gateway 2 5129
Protoss_Assimilator 1 3171
Protoss_Cybernetics_Core 1 4154
Protoss_Dragoon 10 10158
Protoss_Robotics_Facility 1 7396
Protoss_Observatory 1 8051
Protoss_Observer 1 8743
Protoss_Robotics_Support_Bay 1 8751
Protoss_Shuttle 1 9847
10158
