Protoss_Gateway 2 6343
Protoss_Assimilator 1 3211
Protoss_Zealot 1 3324
Protoss_Cybernetics_Core 1 4730
Protoss_Dragoon 7 10400
Protoss_Citadel_of_Adun 1 5647
Protoss_Templar_Archives 1 6566
Protoss_Forge 1 6575
Protoss_Dark_Templar 4 8602
Protoss_Photon_Cannon 5 8759
Protoss_Nexus 1 11325
11325
