Protoss_Gateway 2 7399
Protoss_Assimilator 1 3014
Protoss_Zealot 2 4626
Protoss_Cybernetics_Core 1 4676
Protoss_Dragoon 9 10348
Protoss_Robotics_Facility 1 6839
Protoss_Shuttle 1 7975
Protoss_Observatory 1 7680
Protoss_Robotics_Support_Bay 1 8401
Protoss_Observer 1 8578
Protoss_Reaver 1 9628
Protoss_Nexus 1 11181
11181
