Protoss_Gateway 2 3473
Protoss_Assimilator 2 4564
Protoss_Zealot 5 4818
Protoss_Cybernetics_Core 1 5673
Protoss_Dragoon 9 9886
Protoss_Forge 1 7663
Protoss_Nexus 1 10156
10156
