Protoss_Gateway 2 7940
Protoss_Assimilator 1 2941
Protoss_Zealot 2 4448
Protoss_Cybernetics_Core 1 4466
Protoss_Dragoon 9 10484
Protoss_Robotics_Facility 1 7077
Protoss_Shuttle 1 8135
Protoss_Observatory 1 7777
Protoss_Observer 1 8820
Protoss_Robotics_Support_Bay 1 8905
Protoss_Reaver 1 10090
10484
