Protoss_Gateway 2 5294
Protoss_Assimilator 1 3055
Protoss_Cybernetics_Core 1 3934
Protoss_Dragoon 14 10410
Protoss_Forge 1 8404
Protoss_Photon_Cannon 1 9453
Protoss_Robotics_Facility 1 10801
10801
