Protoss_Gateway 3 10804
Protoss_Zealot 6 6183
Protoss_Assimilator 1 5415
Protoss_Cybernetics_Core 1 7241
Protoss_Citadel_of_Adun 1 8312
Protoss_Dragoon 2 8258
Protoss_Templar_Archives 1 9362
Protoss_Forge 1 9939
Protoss_Dark_Templar 2 10323
10804
