Protoss_Gateway 3 9635
Protoss_Zealot 6 6103
Protoss_Assimilator 1 5084
Protoss_Cybernetics_Core 1 6254
Protoss_Dragoon 8 10718
Protoss_Robotics_Facility 1 8317
Protoss_Observatory 1 9071
Protoss_Observer 2 10423
10718
