Protoss_Gateway 4 9730
Protoss_Zealot 8 10503
Protoss_Assimilator 1 3580
Protoss_Cybernetics_Core 1 4806
Protoss_Robotics_Facility 1 6112
Protoss_Dragoon 4 8413
Protoss_Observatory 1 6670
Protoss_Observer 1 7363
Protoss_Nexus 1 9155
Protoss_Citadel_of_Adun 1 10379
10503
