Protoss_Gateway 3 10259
Protoss_Assimilator 1 3080
Protoss_Zealot 3 5073
Protoss_Cybernetics_Core 1 5054
Protoss_Dragoon 8 10643
Protoss_Nexus 2 8965
Protoss_Robotics_Facility 1 9477
Protoss_Shield_Battery 1 8901
Protoss_Observatory 1 10230
10643
