Protoss_Gateway 3 8985
Protoss_Assimilator 1 3112
Protoss_Cybernetics_Core 1 4079
Protoss_Dragoon 14 10620
Protoss_Robotics_Facility 1 8332
Protoss_Observatory 1 8920
Protoss_Observer 1 10043
Protoss_Robotics_Support_Bay 1 10446
10620
