Protoss_Nexus 1 4602
Protoss_Gateway 5 10486
Protoss_Assimilator 2 8130
Protoss_Zealot 8 7485
Protoss_Cybernetics_Core 1 6669
Protoss_Citadel_of_Adun 1 8004
Protoss_Dragoon 2 9298
Protoss_Forge 1 8210
Protoss_Templar_Archives 1 9032
Protoss_Photon_Cannon 4 9695
Protoss_Dark_Templar 2 9923
10486
