Protoss_Gateway 2 3479
Protoss_Zealot 7 6528
Protoss_Assimilator 1 4627
Protoss_Cybernetics_Core 1 6151
Protoss_Dragoon 8 10008
Protoss_Robotics_Facility 1 9142
Protoss_Observatory 1 10056
10056
