Protoss_Gateway 3 8396
Protoss_Assimilator 1 3146
Protoss_Cybernetics_Core 1 4077
Protoss_Dragoon 12 10268
Protoss_Robotics_Facility 1 5812
Protoss_Observatory 1 6426
Protoss_Observer 2 10218
10268
