Protoss_Nexus 1 4326
Protoss_Gateway 4 10656
Protoss_Assimilator 2 4253
Protoss_Cybernetics_Core 1 5237
Protoss_Dragoon 9 9295
Protoss_Robotics_Facility 1 8977
Protoss_Zealot 2 9415
Protoss_Observatory 1 9560
Protoss_Observer 1 10353
10656
