Protoss_Gateway 2 7144
Protoss_Assimilator 1 3200
Protoss_Zealot 3 6503
Protoss_Cybernetics_Core 1 5321
Protoss_Nexus 1 7516
Protoss_Dragoon 8 10357
Protoss_Shield_Battery 1 7614
Protoss_Citadel_of_Adun 1 9859
Protoss_Robotics_Facility 1 10456
Protoss_Templar_Archives 1 10867
10867
