Protoss_Gateway 2 8280
Protoss_Assimilator 1 3786
Protoss_Zealot 1 3868
Protoss_Cybernetics_Core 1 5203
Protoss_Dragoon 8 10266
Protoss_Robotics_Facility 1 6612
Protoss_Observatory 1 7235
Protoss_Observer 1 8016
Protoss_Shuttle 1 9139
Protoss_Robotics_Support_Bay 1 9495
Protoss_Reaver 1 10634
10634
