Protoss_Gateway 3 7262
Protoss_Zealot 17 9612
Protoss_Shield_Battery 1 6701
Protoss_Assimilator 1 8441
Protoss_Cybernetics_Core 1 9219
Protoss_Dragoon 2 10364
Protoss_Citadel_of_Adun 1 10838
10838
