Protoss_Gateway 1 2854
Protoss_Assimilator 1 3066
Protoss_Cybernetics_Core 1 4039
Protoss_Zealot 1 3948
Protoss_Dragoon 4 10354
Protoss_Robotics_Facility 1 5862
Protoss_Shuttle 1 6869
Protoss_Observatory 1 6494
Protoss_Robotics_Support_Bay 1 6820
Protoss_Observer 2 10584
Protoss_Reaver 2 9980
10584
