Protoss_Gateway 2 7423
Protoss_Assimilator 1 3120
Protoss_Zealot 2 4608
Protoss_Cybernetics_Core 1 4662
Protoss_Dragoon 7 9988
Protoss_Robotics_Facility 1 6599
Protoss_Shuttle 1 7692
Protoss_Robotics_Support_Bay 1 7491
Protoss_Reaver 1 8771
Protoss_Observatory 1 8236
Protoss_Observer 1 9375
Protoss_Nexus 1 11650
11650
