Protoss_Gateway 2 7114
Protoss_Assimilator 1 3486
Protoss_Zealot 3 9753
Protoss_Cybernetics_Core 1 4789
Protoss_Dragoon 8 9908
Protoss_Robotics_Facility 1 8802
Protoss_Observatory 1 9361
Protoss_Robotics_Support_Bay 1 9451
Protoss_Observer 1 10048
10048
