Protoss_Gateway 3 7864
Protoss_Zealot 5 5248
Protoss_Assimilator 1 4317
Protoss_Cybernetics_Core 1 5094
Protoss_Dragoon 9 9848
Protoss_Forge 1 7664
Protoss_Photon_Cannon 1 9440
Protoss_Robotics_Facility 1 10949
10949
