Protoss_Gateway 3 10298
Protoss_Zealot 5 10524
Protoss_Assimilator 1 4800
Protoss_Cybernetics_Core 1 5719
Protoss_Dragoon 10 9922
Protoss_Forge 1 8353
Protoss_Citadel_of_Adun 1 10474
Protoss_Photon_Cannon 1 10549
10549
