Protoss_Gateway 3 10829
Protoss_Assimilator 1 3635
Protoss_Zealot 3 5478
Protoss_Cybernetics_Core 1 6712
Protoss_Dragoon 5 10468
Protoss_Robotics_Facility 1 8792
Protoss_Nexus 1 10293
Protoss_Observatory 1 9373
Protoss_Observer 1 10068
10829
