Protoss_Gateway 2 3499
Protoss_Zealot 7 6693
Protoss_Assimilator 1 4596
Protoss_Cybernetics_Core 1 6293
Protoss_Citadel_of_Adun 1 7512
Protoss_Dragoon 3 10603
Protoss_Robotics_Facility 1 8360
Protoss_Templar_Archives 1 8629
Protoss_Shuttle 1 9352
Protoss_Forge 1 9205
Protoss_Dark_Templar 2 9488
Protoss_Photon_Cannon 2 10120
10603
