Protoss_Gateway 2 9137
Protoss_Assimilator 1 2946
Protoss_Zealot 2 4576
Protoss_Cybernetics_Core 1 4455
Protoss_Robotics_Facility 1 5739
Protoss_Dragoon 7 10702
Protoss_Shuttle 1 6723
Protoss_Observatory 1 6525
Protoss_Robotics_Support_Bay 1 7030
Protoss_Observer 2 10197
Protoss_Reaver 2 9562
10702
