Protoss_Gateway 3 8255
Protoss_Assimilator 1 3296
Protoss_Zealot 1 3582
Protoss_Cybernetics_Core 1 4519
Protoss_Robotics_Facility 1 5824
Protoss_Dragoon 10 10136
Protoss_Observatory 1 6757
Protoss_Observer 2 8162
Protoss_Nexus 1 10624
10624
