Protoss_Gateway 2 3371
Protoss_Zealot 6 7193
Protoss_Assimilator 1 4217
Protoss_Cybernetics_Core 1 5381
Protoss_Dragoon 3 8403
Protoss_Citadel_of_Adun 2 7439
Protoss_Templar_Archives 1 8434
Protoss_Dark_Templar 2 9278
Protoss_Forge 1 9203
Protoss_Nexus 1 10875
Protoss_High_Templar 1 10513
10875
