Protoss_Gateway 2 3455
Protoss_Zealot 8 6798
Protoss_Assimilator 1 5665
Protoss_Cybernetics_Core 1 6615
Protoss_Dragoon 6 10228
Protoss_Robotics_Facility 1 8832
Protoss_Shuttle 1 9957
Protoss_Robotics_Support_Bay 1 9715
Protoss_Forge 1 9958
10228
