Protoss_Gateway 3 9615
Protoss_Assimilator 1 2946
Protoss_Zealot 4 7593
Protoss_Cybernetics_Core 1 4974
Protoss_Dragoon 8 9633
Protoss_Robotics_Facility 1 8000
Protoss_Observatory 1 8606
Protoss_Observer 2 10278
Protoss_Nexus 1 11450
11450
