Protoss_Gateway 2 3393
Protoss_Zealot 7 9380
Protoss_Assimilator 1 4183
Protoss_Cybernetics_Core 1 5799
Protoss_Dragoon 8 10158
Protoss_Robotics_Facility 1 7709
Protoss_Observatory 1 8572
Protoss_Observer 1 9592
Protoss_Shuttle 1 10855
10855
