Protoss_Gateway 2 4640
Protoss_Assimilator 1 3089
Protoss_Zealot 4 5324
Protoss_Cybernetics_Core 1 5160
Protoss_Dragoon 11 10610
Protoss_Robotics_Facility 1 8905
Protoss_Observatory 1 9467
Protoss_Observer 1 10472
10610
