Protoss_Gateway 3 9862
Protoss_Zealot 5 5668
Protoss_Assimilator 1 5090
Protoss_Cybernetics_Core 1 6365
Protoss_Dragoon 8 9898
Protoss_Robotics_Facility 1 9142
Protoss_Observatory 1 9801
Protoss_Observer 1 10483
10483
