Protoss_Gateway 2 6463
Protoss_Assimilator 1 3105
Protoss_Zealot 3 4663
Protoss_Cybernetics_Core 1 4794
Protoss_Dragoon 12 10588
Protoss_Robotics_Facility 1 8902
Protoss_Observatory 1 9551
Protoss_Shuttle 1 10357
10588
