Protoss_Gateway 4 10522
Protoss_Zealot 6 5543
Protoss_Assimilator 1 3958
Protoss_Cybernetics_Core 1 5420
Protoss_Dragoon 13 10733
Protoss_Robotics_Facility 1 8987
Protoss_Observatory 1 9564
Protoss_Observer 1 10263
10733
