Protoss_Gateway 2 3517
Protoss_Zealot 7 5918
Protoss_Assimilator 1 4498
Protoss_Cybernetics_Core 1 5733
Protoss_Dragoon 10 10508
Protoss_Robotics_Facility 1 9317
Protoss_Observatory 1 10166
10508
