Protoss_Gateway 3 9042
Protoss_Zealot 3 4568
Protoss_Assimilator 1 3485
Protoss_Cybernetics_Core 1 4676
Protoss_Dragoon 9 10638
Protoss_Robotics_Facility 1 6347
Protoss_Shuttle 1 7487
Protoss_Observatory 1 7251
Protoss_Observer 1 8090
Protoss_Robotics_Support_Bay 1 8318
Protoss_Reaver 2 10516
10638
