Protoss_Gateway 2 9687
Protoss_Assimilator 1 3120
Protoss_Cybernetics_Core 1 4110
Protoss_Dragoon 7 10663
Protoss_Robotics_Facility 1 7696
Protoss_Nexus 1 8877
Protoss_Robotics_Support_Bay 1 8337
Protoss_Reaver 1 9676
Protoss_Observatory 1 9332
Protoss_Shield_Battery 1 9991
Protoss_Observer 1 10280
10663
