Protoss_Gateway 3 8939
Protoss_Assimilator 1 3175
Protoss_Zealot 1 3653
Protoss_Cybernetics_Core 1 4885
Protoss_Dragoon 9 10313
Protoss_Robotics_Facility 1 8007
Protoss_Observatory 1 8721
Protoss_Observer 2 10393
Protoss_Nexus 1 11175
11175
