Protoss_Gateway 2 6564
Protoss_Zealot 7 7336
Protoss_Assimilator 1 5533
Protoss_Cybernetics_Core 1 6600
Protoss_Citadel_of_Adun 1 8043
Protoss_Dragoon 4 9302
Protoss_Templar_Archives 1 9029
Protoss_Forge 1 9016
Protoss_Dark_Templar 2 10054
Protoss_Photon_Cannon 1 10058
Protoss_Nexus 1 11747
11747
