Protoss_Gateway 2 5857
Protoss_Zealot 9 9968
Protoss_Assimilator 1 5625
Protoss_Cybernetics_Core 1 6593
Protoss_Dragoon 5 10066
Protoss_Robotics_Facility 1 8922
Protoss_Shuttle 1 9905
Protoss_Observatory 1 9734
Protoss_Robotics_Support_Bay 1 10419
10419
