Protoss_Gateway 3 10529
Protoss_Zealot 4 6982
Protoss_Assimilator 1 4983
Protoss_Cybernetics_Core 1 6869
Protoss_Citadel_of_Adun 1 7969
Protoss_Dragoon 1 7938
Protoss_Templar_Archives 1 9061
Protoss_Forge 1 9581
Protoss_Dark_Templar 2 10116
Protoss_Photon_Cannon 1 10564
10564
