Protoss_Gateway 1 2859
Protoss_Assimilator 1 3081
Protoss_Zealot 4 6294
Protoss_Cybernetics_Core 1 6318
Protoss_Dragoon 3 9904
Protoss_Robotics_Facility 1 8150
Protoss_Shuttle 1 9177
Protoss_Observatory 1 8798
Protoss_Observer 1 9780
Protoss_Robotics_Support_Bay 1 9680
Protoss_Reaver 1 10832
10832
