Protoss_Gateway 2 7183
Protoss_Zealot 4 6138
Protoss_Nexus 1 7206
Protoss_Assimilator 2 10252
Protoss_Cybernetics_Core 1 6924
Protoss_Forge 1 7465
Protoss_Dragoon 5 10283
Protoss_Photon_Cannon 2 10580
Protoss_Robotics_Facility 1 9775
Protoss_Observatory 1 10367
10580
