Protoss_Gateway 2 8273
Protoss_Assimilator 1 2915
Protoss_Cybernetics_Core 1 3959
Protoss_Dragoon 9 10008
Protoss_Robotics_Facility 1 8081
Protoss_Observatory 1 8666
Protoss_Observer 1 9353
Protoss_Nexus 1 11637
11637
