Protoss_Gateway 4 9394
Protoss_Assimilator 2 4495
Protoss_Zealot 4 6203
Protoss_Cybernetics_Core 1 5885
Protoss_Citadel_of_Adun 1 7044
Protoss_Templar_Archives 1 8039
Protoss_Robotics_Facility 1 8924
Protoss_Dark_Templar 4 9668
Protoss_Shuttle 1 9947
Protoss_Observatory 1 9963
Protoss_Dragoon 1 10663
10663
