Protoss_Gateway 2 3921
Protoss_Zealot 6 6844
Protoss_Assimilator 1 4898
Protoss_Cybernetics_Core 1 6311
Protoss_Robotics_Facility 1 7736
Protoss_Shield_Battery 1 7225
Protoss_Dragoon 2 9060
Protoss_Shuttle 1 8717
Protoss_Robotics_Support_Bay 1 8569
Protoss_Reaver 1 10198
10198
