Protoss_Gateway 2 4659
Protoss_Zealot 8 7170
Protoss_Assimilator 1 6895
Protoss_Cybernetics_Core 1 8198
Protoss_Forge 1 8372
Protoss_Dragoon 4 10042
Protoss_Photon_Cannon 1 9384
10042
