Protoss_Gateway 2 5667
Protoss_Assimilator 1 3035
Protoss_Zealot 2 4121
Protoss_Cybernetics_Core 1 4873
Protoss_Dragoon 11 10180
Protoss_Robotics_Facility 1 8586
Protoss_Shuttle 1 9825
Protoss_Observatory 1 9438
Protoss_Robotics_Support_Bay 1 10203
Protoss_Observer 1 10428
10428
