Protoss_Gateway 2 5132
Protoss_Assimilator 1 2962
Protoss_Cybernetics_Core 1 3931
Protoss_Dragoon 12 10360
Protoss_Robotics_Facility 1 8870
Protoss_Observatory 1 9411
Protoss_Observer 1 10258
10360
