Protoss_Gateway 4 10531
Protoss_Zealot 10 10596
Protoss_Nexus 1 6654
Protoss_Assimilator 1 5962
Protoss_Cybernetics_Core 1 7107
Protoss_Citadel_of_Adun 1 8574
Protoss_Dragoon 1 8580
Protoss_Forge 1 8889
10596
