Protoss_Gateway 2 6131
Protoss_Assimilator 1 2845
Protoss_Zealot 5 10263
Protoss_Cybernetics_Core 1 4544
Protoss_Citadel_of_Adun 1 5584
Protoss_Dragoon 2 6488
Protoss_Templar_Archives 1 6611
Protoss_Forge 1 6799
Protoss_Dark_Templar 1 7638
Protoss_Nexus 1 9010
Protoss_Photon_Cannon 2 8789
Protoss_High_Templar 3 9658
10263
