Protoss_Gateway 2 7609
Protoss_Assimilator 1 2880
Protoss_Zealot 2 4508
Protoss_Cybernetics_Core 1 4485
Protoss_Dragoon 10 10568
Protoss_Robotics_Facility 1 6493
Protoss_Observatory 1 7289
Protoss_Observer 2 8575
Protoss_Shuttle 1 9476
Protoss_Robotics_Support_Bay 1 9371
Protoss_Reaver 1 10551
10568
