Protoss_Gateway 2 7063
Protoss_Zealot 10 9306
Protoss_Nexus 1 7122
Protoss_Assimilator 1 6200
Protoss_Cybernetics_Core 1 7421
Protoss_Citadel_of_Adun 1 8515
Protoss_Dragoon 2 8698
Protoss_Templar_Archives 1 9532
Protoss_Forge 1 9287
Protoss_Photon_Cannon 1 10206
Protoss_Dark_Templar 2 10380
10380
