Protoss_Gateway 2 7211
Protoss_Assimilator 1 3009
Protoss_Zealot 2 4390
Protoss_Cybernetics_Core 1 4898
Protoss_Dragoon 9 10593
Protoss_Robotics_Facility 1 6542
Protoss_Observatory 1 7116
Protoss_Observer 2 8474
Protoss_Robotics_Support_Bay 1 8452
Protoss_Reaver 2 10673
Protoss_Nexus 1 11290
11290
