Protoss_Gateway 2 6092
Protoss_Assimilator 1 3065
Protoss_Zealot 3 4883
Protoss_Cybernetics_Core 1 5574
Protoss_Robotics_Facility 1 6867
Protoss_Dragoon 11 10581
Protoss_Observatory 1 7440
Protoss_Observer 2 8730
Protoss_Shuttle 1 9692
Protoss_Robotics_Support_Bay 1 10167
10581
