Protoss_Gateway 2 8347
Protoss_Assimilator 1 3311
Protoss_Zealot 2 4813
Protoss_Cybernetics_Core 1 4678
Protoss_Dragoon 7 10264
Protoss_Robotics_Facility 1 6671
Protoss_Forge 1 6467
Protoss_Observatory 1 7233
Protoss_Observer 2 9498
Protoss_Shuttle 1 10399
Protoss_Robotics_Support_Bay 1 10223
10399
