Protoss_Gateway 3 6843
Protoss_Assimilator 1 2896
Protoss_Cybernetics_Core 1 3834
Protoss_Dragoon 9 10718
Protoss_Forge 1 7700
Protoss_Nexus 1 10614
Protoss_Photon_Cannon 2 10415
10718
