Protoss_Gateway 4 10130
Protoss_Zealot 8 8482
Protoss_Nexus 2 11444
Protoss_Assimilator 4 8714
Protoss_Cybernetics_Core 1 7149
Protoss_Citadel_of_Adun 1 8167
Protoss_Templar_Archives 1 9203
Protoss_Forge 1 10013
Protoss_Dark_Templar 3 10706
11444
