Protoss_Gateway 2 3718
Protoss_Zealot 8 7420
Protoss_Nexus 1 7055
Protoss_Assimilator 2 8853
Protoss_Cybernetics_Core 1 8021
Protoss_Citadel_of_Adun 1 9035
Protoss_Dragoon 2 9498
Protoss_Forge 1 9712
Protoss_Templar_Archives 1 10596
Protoss_Photon_Cannon 2 10608
10608
