Protoss_Gateway 3 9360
Protoss_Zealot 8 7242
Protoss_Nexus 1 7063
Protoss_Assimilator 2 9116
Protoss_Cybernetics_Core 1 7162
Protoss_Dragoon 8 10668
Protoss_Robotics_Facility 1 10731
10731
