Protoss_Gateway 1 2801
Protoss_Assimilator 1 2860
Protoss_Cybernetics_Core 1 3805
Protoss_Dragoon 4 9260
Protoss_Robotics_Facility 1 5599
Protoss_Shuttle 1 6587
Protoss_Robotics_Support_Bay 1 6266
Protoss_Citadel_of_Adun 1 7155
Protoss_Reaver 1 7638
Protoss_Stargate 2 9813
Protoss_Fleet_Beacon 1 9464
Protoss_Carrier 1 11646
11646
