Protoss_Gateway 3 7922
Protoss_Zealot 7 6568
Protoss_Nexus 1 7183
Protoss_Assimilator 2 9224
Protoss_Cybernetics_Core 1 7351
Protoss_Forge 1 7858
Protoss_Dragoon 2 8354
Protoss_Citadel_of_Adun 1 8780
Protoss_Templar_Archives 1 9773
Protoss_Photon_Cannon 2 10363
Protoss_Dark_Templar 2 10624
10624
