Protoss_Gateway 2 10701
Protoss_Assimilator 1 2881
Protoss_Zealot 2 4878
Protoss_Cybernetics_Core 1 4569
Protoss_Robotics_Facility 1 6176
Protoss_Dragoon 6 10288
Protoss_Robotics_Support_Bay 1 6766
Protoss_Reaver 1 8331
Protoss_Observatory 1 7902
Protoss_Nexus 1 11005
Protoss_Observer 1 10178
11005
