Protoss_Nexus 1 4571
Protoss_Gateway 3 10295
Protoss_Zealot 6 8503
Protoss_Assimilator 1 6547
Protoss_Cybernetics_Core 1 8742
Protoss_Forge 1 8582
Protoss_Photon_Cannon 2 10285
Protoss_Dragoon 4 10573
10573
