Protoss_Gateway 4 9622
Protoss_Zealot 14 10318
Protoss_Nexus 1 6060
Protoss_Assimilator 2 8163
Protoss_Cybernetics_Core 1 7009
Protoss_Citadel_of_Adun 1 9139
Protoss_Forge 1 9834
Protoss_Templar_Archives 1 10269
10318
