Protoss_Gateway 2 6671
Protoss_Assimilator 2 4484
Protoss_Cybernetics_Core 1 3958
Protoss_Zealot 1 4118
Protoss_Dragoon 10 10306
Protoss_Nexus 1 10285
Protoss_Robotics_Facility 1 11137
11137
