Protoss_Gateway 3 7833
Protoss_Zealot 11 9974
Protoss_Nexus 1 6906
Protoss_Forge 1 6167
Protoss_Photon_Cannon 7 10500
Protoss_Assimilator 2 9197
Protoss_Cybernetics_Core 1 10299
10500
