Protoss_Gateway 1 2661
Protoss_Zealot 3 4726
Protoss_Assimilator 1 3700
Protoss_Cybernetics_Core 1 4739
Protoss_Dragoon 7 10478
Protoss_Robotics_Facility 1 6693
Protoss_Shuttle 1 7723
Protoss_Robotics_Support_Bay 1 7555
Protoss_Reaver 1 8784
Protoss_Observatory 1 8875
Protoss_Observer 1 9666
10478
