Protoss_Gateway 2 7008
Protoss_Assimilator 1 3424
Protoss_Zealot 2 4222
Protoss_Cybernetics_Core 1 4747
Protoss_Dragoon 3 7084
Protoss_Citadel_of_Adun 1 6349
Protoss_Templar_Archives 1 7434
Protoss_Forge 1 8030
Protoss_Dark_Templar 5 10482
Protoss_Photon_Cannon 2 10460
10482
