Protoss_Gateway 2 5643
Protoss_Zealot 2 4356
Protoss_Assimilator 1 3723
Protoss_Cybernetics_Core 1 5137
Protoss_Dragoon 9 10514
Protoss_Robotics_Facility 1 8070
Protoss_Nexus 1 10157
Protoss_Observatory 1 8957
Protoss_Observer 2 10304
10514
