Protoss_Gateway 2 5390
Protoss_Assimilator 1 3565
Protoss_Zealot 1 4074
Protoss_Cybernetics_Core 1 4730
Protoss_Dragoon 13 10582
Protoss_Robotics_Facility 1 8987
Protoss_Shuttle 1 10007
Protoss_Robotics_Support_Bay 1 9844
10582
