Protoss_Gateway 4 10138
Protoss_Assimilator 1 3094
Protoss_Zealot 4 9408
Protoss_Cybernetics_Core 1 4714
Protoss_Dragoon 8 10320
Protoss_Nexus 1 9661
Protoss_Robotics_Facility 1 9795
10320
