Protoss_Gateway 2 6084
Protoss_Zealot 5 9500
Protoss_Assimilator 1 3852
Protoss_Cybernetics_Core 1 4746
Protoss_Dragoon 9 10738
Protoss_Robotics_Facility 1 8089
Protoss_Observatory 1 8706
Protoss_Observer 2 10010
Protoss_Nexus 1 11339
11339
