Protoss_Gateway 2 3399
Protoss_Zealot 10 8255
Protoss_Nexus 1 7010
Protoss_Assimilator 1 6560
Protoss_Cybernetics_Core 1 7762
Protoss_Citadel_of_Adun 1 9205
Protoss_Forge 1 9064
Protoss_Dragoon 4 10450
Protoss_Photon_Cannon 1 10400
Protoss_Templar_Archives 1 10864
10864
