Protoss_Gateway 3 8578
Protoss_Zealot 8 7963
Protoss_Nexus 1 7255
Protoss_Assimilator 1 6370
Protoss_Cybernetics_Core 1 7889
Protoss_Dragoon 6 10423
Protoss_Shield_Battery 1 9131
10423
