Protoss_Gateway 3 8288
Protoss_Zealot 13 10293
Protoss_Nexus 1 7485
Protoss_Assimilator 1 6835
Protoss_Cybernetics_Core 1 8157
Protoss_Forge 1 8810
Protoss_Citadel_of_Adun 1 9259
Protoss_Templar_Archives 1 10279
10293
