Protoss_Nexus 1 4659
Protoss_Gateway 3 5574
Protoss_Zealot 8 7148
Protoss_Assimilator 1 5872
Protoss_Cybernetics_Core 1 8261
Protoss_Forge 1 8484
Protoss_Shield_Battery 1 8465
Protoss_Dragoon 4 9966
9966
