Protoss_Gateway 3 10284
Protoss_Zealot 14 9338
Protoss_Nexus 1 7001
Protoss_Assimilator 1 7138
Protoss_Cybernetics_Core 1 8766
Protoss_Citadel_of_Adun 1 10187
Protoss_Dragoon 2 10090
Protoss_Shield_Battery 1 10317
10317
