Protoss_Gateway 2 4482
Protoss_Assimilator 1 2969
Protoss_Zealot 7 6408
Protoss_Cybernetics_Core 1 6071
Protoss_Dragoon 8 9943
Protoss_Nexus 1 9615
Protoss_Citadel_of_Adun 1 10062
Protoss_Robotics_Facility 1 10654
10654
