Protoss_Gateway 3 8604
Protoss_Zealot 11 7708
Protoss_Nexus 1 7795
Protoss_Assimilator 2 9805
Protoss_Forge 1 7799
Protoss_Cybernetics_Core 1 8224
Protoss_Photon_Cannon 4 10094
Protoss_Citadel_of_Adun 1 9363
Protoss_Dragoon 2 9838
Protoss_Templar_Archives 1 10384
10384
