Protoss_Gateway 4 10183
Protoss_Zealot 14 8855
Protoss_Nexus 1 7408
Protoss_Assimilator 2 9686
Protoss_Cybernetics_Core 1 8052
Protoss_Citadel_of_Adun 1 9177
Protoss_Robotics_Facility 1 10577
Protoss_Dragoon 1 10493
10577
