Protoss_Gateway 4 8177
Protoss_Zealot 1 3496
Protoss_Nexus 1 5626
Protoss_Assimilator 1 4561
Protoss_Cybernetics_Core 1 5209
Protoss_Dragoon 15 10726
Protoss_Forge 1 10460
10726
