Protoss_Gateway 2 8224
Protoss_Assimilator 1 3020
Protoss_Cybernetics_Core 1 3997
Protoss_Dragoon 10 10734
Protoss_Robotics_Facility 1 7571
Protoss_Observatory 1 8158
Protoss_Observer 1 9030
Protoss_Nexus 1 10582
Protoss_Robotics_Support_Bay 1 10063
10734
