Protoss_Gateway 3 9082
Protoss_Assimilator 1 3354
Protoss_Zealot 4 10284
Protoss_Cybernetics_Core 1 4521
Protoss_Dragoon 7 8376
Protoss_Citadel_of_Adun 1 7711
Protoss_Templar_Archives 1 8819
Protoss_Forge 1 9498
Protoss_Dark_Templar 2 9682
10284
