Protoss_Gateway 4 10376
Protoss_Zealot 14 9773
Protoss_Nexus 1 6745
Protoss_Assimilator 2 9001
Protoss_Shield_Battery 1 6792
Protoss_Cybernetics_Core 1 8074
Protoss_Dragoon 3 10108
Protoss_Robotics_Facility 1 10195
10376
