Protoss_Gateway 2 4675
Protoss_Assimilator 1 2840
Protoss_Cybernetics_Core 1 3759
Protoss_Dragoon 9 10388
Protoss_Robotics_Facility 1 6597
Protoss_Observatory 1 7203
Protoss_Robotics_Support_Bay 1 7258
Protoss_Reaver 1 8476
Protoss_Nexus 1 10075
Protoss_Observer 1 9080
Protoss_Shuttle 1 10052
10388
