Protoss_Gateway 3 10305
Protoss_Assimilator 1 3040
Protoss_Zealot 1 3514
Protoss_Cybernetics_Core 1 4743
Protoss_Dragoon 11 10506
Protoss_Nexus 1 9581
Protoss_Robotics_Facility 1 10409
10506
