Protoss_Gateway 2 7929
Protoss_Assimilator 1 3028
Protoss_Zealot 2 4703
Protoss_Cybernetics_Core 1 4785
Protoss_Dragoon 2 6713
Protoss_Citadel_of_Adun 1 6397
Protoss_Templar_Archives 1 7495
Protoss_Forge 1 7680
Protoss_Dark_Templar 4 9548
Protoss_High_Templar 2 10703
Protoss_Photon_Cannon 2 10177
Protoss_Nexus 1 11472
11472
