Protoss_Gateway 4 7977
Protoss_Assimilator 1 3055
Protoss_Zealot 2 4518
Protoss_Cybernetics_Core 1 4529
Protoss_Dragoon 11 9003
Protoss_Forge 1 9327
Protoss_Robotics_Facility 1 10541
Protoss_Photon_Cannon 2 10263
10541
