Protoss_Gateway 3 9209
Protoss_Zealot 9 6438
Protoss_Forge 1 5168
Protoss_Photon_Cannon 4 8740
Protoss_Nexus 1 8195
Protoss_Assimilator 1 7360
Protoss_Cybernetics_Core 1 8215
Protoss_Dragoon 3 10043
10043
