Protoss_Gateway 2 4317
Protoss_Assimilator 1 2963
Protoss_Cybernetics_Core 1 3859
Protoss_Dragoon 5 7113
Protoss_Robotics_Facility 1 8323
Protoss_Citadel_of_Adun 1 8513
Protoss_Shuttle 1 9317
Protoss_Zealot 1 9128
Protoss_Templar_Archives 1 10163
Protoss_Nexus 1 11640
11640
