Protoss_Gateway 3 7205
Protoss_Zealot 13 9276
Protoss_Assimilator 1 7265
Protoss_Cybernetics_Core 1 7974
Protoss_Citadel_of_Adun 1 9100
Protoss_Templar_Archives 1 10174
Protoss_Nexus 1 11331
11331
