Protoss_Gateway 2 3523
Protoss_Zealot 3 5013
Protoss_Assimilator 1 4096
Protoss_Cybernetics_Core 1 4889
Protoss_Dragoon 3 7323
Protoss_Citadel_of_Adun 1 6790
Protoss_Templar_Archives 1 7809
Protoss_Dark_Templar 5 10410
Protoss_Forge 1 8601
10410
