Protoss_Gateway 2 9137
Protoss_Zealot 3 4802
Protoss_Assimilator 1 3740
Protoss_Cybernetics_Core 1 4903
Protoss_Robotics_Facility 1 6424
Protoss_Dragoon 7 10660
Protoss_Shuttle 1 7491
Protoss_Robotics_Support_Bay 1 7545
Protoss_Reaver 2 9724
Protoss_Observatory 1 8644
10660
