Protoss_Gateway 3 6815
Protoss_Assimilator 2 10445
Protoss_Zealot 4 10142
Protoss_Nexus 1 6435
Protoss_Cybernetics_Core 1 5783
Protoss_Dragoon 9 10250
Protoss_Robotics_Facility 1 8231
Protoss_Observatory 1 8945
Protoss_Observer 2 10572
10572
