Protoss_Gateway 3 7250
Protoss_Assimilator 1 2952
Protoss_Zealot 3 4685
Protoss_Cybernetics_Core 1 4723
Protoss_Dragoon 13 10398
Protoss_Forge 1 9066
Protoss_Robotics_Facility 1 10070
Protoss_Photon_Cannon 3 10315
10398
