Protoss_Gateway 3 7768
Protoss_Assimilator 1 3024
Protoss_Zealot 9 9884
Protoss_Cybernetics_Core 1 4542
Protoss_Dragoon 2 6754
Protoss_Nexus 1 7560
Protoss_Citadel_of_Adun 1 8007
Protoss_Forge 1 9397
Protoss_Templar_Archives 1 10415
Protoss_Photon_Cannon 1 10412
10415
