Protoss_Gateway 3 10660
Protoss_Zealot 8 7578
Protoss_Assimilator 2 4872
Protoss_Cybernetics_Core 1 6855
Protoss_Dragoon 5 10145
Protoss_Citadel_of_Adun 1 8660
Protoss_Templar_Archives 1 9844
Protoss_Dark_Templar 2 10688
10688
