Protoss_Gateway 2 5496
Protoss_Zealot 5 7592
Protoss_Assimilator 1 7681
Protoss_Cybernetics_Core 1 8434
Protoss_Nexus 1 10395
Protoss_Dragoon 3 10268
Protoss_Forge 1 9652
Protoss_Shield_Battery 1 10235
Protoss_Photon_Cannon 1 10581
10581
