Protoss_Gateway 3 8277
Protoss_Assimilator 1 3572
Protoss_Zealot 3 5546
Protoss_Cybernetics_Core 1 5045
Protoss_Dragoon 11 10308
Protoss_Nexus 1 8495
Protoss_Shield_Battery 1 9694
10308
