Protoss_Gateway 2 3652
Protoss_Zealot 9 7688
Protoss_Assimilator 1 6806
Protoss_Cybernetics_Core 1 7333
Protoss_Dragoon 6 10172
Protoss_Forge 1 9296
Protoss_Photon_Cannon 1 10500
10500
