Protoss_Gateway 2 3480
Protoss_Zealot 9 7393
Protoss_Nexus 1 7195
Protoss_Assimilator 2 8682
Protoss_Cybernetics_Core 1 7826
Protoss_Dragoon 4 9943
Protoss_Forge 1 8565
Protoss_Photon_Cannon 1 9848
9943
