Protoss_Gateway 2 6109
Protoss_Zealot 11 10453
Protoss_Nexus 1 6775
Protoss_Assimilator 2 8761
Protoss_Cybernetics_Core 1 7961
Protoss_Forge 1 8572
Protoss_Citadel_of_Adun 1 8990
Protoss_Dragoon 2 9358
Protoss_Photon_Cannon 1 9674
Protoss_Templar_Archives 1 10615
10615
