Protoss_Gateway 2 7534
Protoss_Assimilator 1 2805
Protoss_Zealot 2 4993
Protoss_Cybernetics_Core 1 4746
Protoss_Dragoon 8 10688
Protoss_Robotics_Facility 1 6887
Protoss_Shuttle 1 8177
Protoss_Robotics_Support_Bay 1 7985
Protoss_Reaver 1 9561
Protoss_Observatory 1 9071
Protoss_Observer 1 10165
10688
