Protoss_Gateway 2 6521
Protoss_Assimilator 1 2975
Protoss_Zealot 2 4958
Protoss_Cybernetics_Core 1 4835
Protoss_Dragoon 2 6658
Protoss_Citadel_of_Adun 1 7175
Protoss_Nexus 1 9164
Protoss_Templar_Archives 1 8400
Protoss_Forge 1 8580
Protoss_Dark_Templar 5 10518
Protoss_Photon_Cannon 2 9730
Protoss_High_Templar 1 10528
10528
