Protoss_Gateway 3 10825
Protoss_Assimilator 1 3080
Protoss_Zealot 1 3542
Protoss_Cybernetics_Core 1 4837
Protoss_Dragoon 10 10396
Protoss_Robotics_Facility 1 8041
Protoss_Observatory 1 8753
Protoss_Observer 2 10032
Protoss_Nexus 1 11347
11347
