Protoss_Gateway 2 7098
Protoss_Assimilator 1 3090
Protoss_Zealot 2 4736
Protoss_Cybernetics_Core 1 4729
Protoss_Dragoon 9 10464
Protoss_Robotics_Facility 1 8229
Protoss_Observatory 1 9052
Protoss_Observer 2 10350
Protoss_Nexus 1 11107
11107
