Protoss_Gateway 3 9053
Protoss_Assimilator 1 3129
Protoss_Zealot 3 10494
Protoss_Cybernetics_Core 1 4641
Protoss_Dragoon 8 9968
Protoss_Robotics_Facility 1 7389
Protoss_Nexus 1 9244
Protoss_Observatory 1 8077
Protoss_Observer 2 9598
10494
