Protoss_Gateway 2 5153
Protoss_Assimilator 1 3015
Protoss_Zealot 7 6753
Protoss_Cybernetics_Core 1 4657
Protoss_Citadel_of_Adun 1 6235
Protoss_Dragoon 1 6845
Protoss_Templar_Archives 1 7379
Protoss_Dark_Templar 3 8975
Protoss_Forge 1 9233
Protoss_Nexus 1 10515
Protoss_High_Templar 2 9818
Protoss_Photon_Cannon 1 10692
10692
