Protoss_Gateway 3 10802
Protoss_Zealot 8 6638
Protoss_Assimilator 1 4575
Protoss_Cybernetics_Core 1 6139
Protoss_Dragoon 8 10280
Protoss_Forge 1 8055
Protoss_Photon_Cannon 1 9076
Protoss_Robotics_Facility 1 9817
Protoss_Citadel_of_Adun 1 10444
Protoss_Shuttle 1 10822
10822
