Protoss_Gateway 2 6507
Protoss_Zealot 2 4586
Protoss_Assimilator 1 3770
Protoss_Cybernetics_Core 1 4671
Protoss_Dragoon 10 10482
Protoss_Robotics_Facility 1 8408
Protoss_Observatory 1 8990
Protoss_Shuttle 1 9455
Protoss_Nexus 1 10796
Protoss_Robotics_Support_Bay 1 9793
Protoss_Observer 1 10058
10796
