Protoss_Gateway 3 8419
Protoss_Assimilator 1 2830
Protoss_Cybernetics_Core 1 3741
Protoss_Dragoon 13 10000
Protoss_Robotics_Facility 1 7043
Protoss_Observatory 1 7864
Protoss_Observer 1 8562
Protoss_Nexus 1 11560
11560
