Protoss_Gateway 4 10361
Protoss_Zealot 2 4286
Protoss_Assimilator 1 3522
Protoss_Cybernetics_Core 1 4341
Protoss_Dragoon 12 10548
Protoss_Robotics_Facility 1 9019
Protoss_Nexus 1 11033
11033
