Protoss_Gateway 3 10538
Protoss_Zealot 2 7768
Protoss_Assimilator 1 3664
Protoss_Cybernetics_Core 1 4654
Protoss_Dragoon 10 10078
Protoss_Robotics_Facility 1 8213
Protoss_Nexus 1 9922
Protoss_Observatory 1 8776
Protoss_Observer 1 9628
Protoss_Shuttle 1 10689
10689
