Protoss_Gateway 3 8754
Protoss_Assimilator 1 2997
Protoss_Zealot 1 3426
Protoss_Cybernetics_Core 1 4625
Protoss_Dragoon 12 10346
Protoss_Nexus 1 9243
Protoss_Robotics_Facility 1 9437
Protoss_Observatory 1 10215
10346
