Protoss_Gateway 2 6885
Protoss_Assimilator 1 3238
Protoss_Cybernetics_Core 1 4061
Protoss_Dragoon 7 10734
Protoss_Robotics_Facility 1 6895
Protoss_Shuttle 1 8109
Protoss_Robotics_Support_Bay 1 7725
Protoss_Observatory 1 8699
Protoss_Reaver 2 10440
10734
