Protoss_Nexus 1 4730
Protoss_Gateway 3 7213
Protoss_Zealot 4 9456
Protoss_Assimilator 2 7985
Protoss_Cybernetics_Core 1 6827
Protoss_Dragoon 6 8950
Protoss_Citadel_of_Adun 1 9527
Protoss_Forge 1 9809
Protoss_Shield_Battery 1 9879
Protoss_Templar_Archives 1 10742
Protoss_Photon_Cannon 1 10680
10742
