Protoss_Gateway 3 10668
Protoss_Assimilator 1 3025
Protoss_Cybernetics_Core 1 3979
Protoss_Dragoon 12 10168
Protoss_Robotics_Facility 1 7305
Protoss_Observatory 1 7895
Protoss_Observer 1 8928
Protoss_Nexus 1 10540
10668
