Protoss_Gateway 3 8633
Protoss_Assimilator 1 3100
Protoss_Cybernetics_Core 1 4154
Protoss_Dragoon 15 10583
Protoss_Robotics_Facility 1 7625
Protoss_Observatory 1 8211
Protoss_Observer 1 9073
Protoss_Zealot 1 9768
10583
