Protoss_Nexus 1 4517
Protoss_Gateway 2 5368
Protoss_Assimilator 3 10160
Protoss_Zealot 8 7872
Protoss_Cybernetics_Core 1 9097
Protoss_Forge 1 9134
Protoss_Citadel_of_Adun 1 10177
Protoss_Photon_Cannon 4 10632
10632
