Protoss_Gateway 6 8772
Protoss_Forge 1 5390
Protoss_Zealot 7 7840
Protoss_Assimilator 1 6552
Protoss_Cybernetics_Core 2 7683
Protoss_Citadel_of_Adun 1 8119
Protoss_Templar_Archives 1 9193
Protoss_Photon_Cannon 1 9176
Protoss_Nexus 1 11174
Protoss_Dark_Templar 1 10132
11174
