Protoss_Gateway 4 10798
Protoss_Zealot 13 8752
Protoss_Nexus 1 7614
Protoss_Assimilator 2 9302
Protoss_Cybernetics_Core 1 8484
Protoss_Citadel_of_Adun 1 9536
Protoss_Dragoon 1 9580
Protoss_Templar_Archives 1 10632
10798
