Protoss_Gateway 2 3403
Protoss_Zealot 11 9228
Protoss_Nexus 1 8157
Protoss_Assimilator 2 9371
Protoss_Cybernetics_Core 1 8345
Protoss_Dragoon 4 10076
Protoss_Robotics_Facility 1 9864
10076
