Protoss_Gateway 3 10268
Protoss_Zealot 11 10590
Protoss_Nexus 1 6731
Protoss_Assimilator 2 7863
Protoss_Cybernetics_Core 1 7517
Protoss_Dragoon 6 9988
Protoss_Robotics_Facility 1 9359
Protoss_Observatory 1 10059
Protoss_Shuttle 1 10755
10755
