Protoss_Gateway 2 6941
Protoss_Assimilator 1 2850
Protoss_Zealot 7 7125
Protoss_Cybernetics_Core 1 5641
Protoss_Dragoon 8 10334
Protoss_Robotics_Facility 1 8349
Protoss_Observatory 1 8926
Protoss_Observer 1 10118
10334
