Protoss_Gateway 1 2809
Protoss_Assimilator 1 3442
Protoss_Zealot 4 5993
Protoss_Cybernetics_Core 1 5642
Protoss_Robotics_Facility 1 7183
Protoss_Dragoon 4 9978
Protoss_Shuttle 1 8172
Protoss_Robotics_Support_Bay 1 8007
Protoss_Reaver 2 10341
10341
