Protoss_Assimilator 1 2245
Protoss_Gateway 2 6640
Protoss_Cybernetics_Core 1 4098
Protoss_Citadel_of_Adun 1 5181
Protoss_Robotics_Facility 1 5825
Protoss_Dragoon 6 9868
Protoss_Templar_Archives 1 6763
Protoss_Shuttle 1 7067
Protoss_Dark_Templar 3 9926
9926
