Protoss_Gateway 1 2762
Protoss_Assimilator 1 2964
Protoss_Cybernetics_Core 1 3779
Protoss_Robotics_Facility 2 10796
Protoss_Shuttle 1 6287
Protoss_Robotics_Support_Bay 1 5863
Protoss_Reaver 2 8390
Protoss_Zealot 1 7048
Protoss_Observatory 1 8049
Protoss_Dragoon 2 9340
Protoss_Observer 1 8994
10796
