Protoss_Nexus 1 4375
Protoss_Gateway 2 4208
Protoss_Zealot 5 7284
Protoss_Assimilator 2 9500
Protoss_Forge 1 6173
Protoss_Cybernetics_Core 1 6733
Protoss_Photon_Cannon 10 10512
Protoss_Citadel_of_Adun 1 7909
Protoss_Templar_Archives 1 9050
Protoss_Dark_Templar 2 9888
10512
