Protoss_Gateway 3 10814
Protoss_Assimilator 1 3011
Protoss_Zealot 7 9642
Protoss_Cybernetics_Core 1 5023
Protoss_Citadel_of_Adun 1 6031
Protoss_Dragoon 1 6168
Protoss_Templar_Archives 1 7025
Protoss_Dark_Templar 1 7854
Protoss_High_Templar 3 10394
Protoss_Forge 1 8710
Protoss_Nexus 1 11117
Protoss_Photon_Cannon 1 10441
11117
