Protoss_Gateway 2 6922
Protoss_Assimilator 1 2841
Protoss_Zealot 4 10424
Protoss_Cybernetics_Core 1 4737
Protoss_Dragoon 6 8620
Protoss_Robotics_Facility 1 6313
Protoss_Shuttle 1 7473
Protoss_Observatory 1 7153
Protoss_Observer 1 8076
Protoss_Robotics_Support_Bay 1 8087
Protoss_Nexus 1 10505
Protoss_Reaver 1 10074
Protoss_Citadel_of_Adun 1 10111
10505
