Protoss_Gateway 2 7753
Protoss_Assimilator 1 3048
Protoss_Zealot 2 4624
Protoss_Cybernetics_Core 1 4635
Protoss_Dragoon 8 10384
Protoss_Robotics_Facility 1 7177
Protoss_Observatory 1 7799
Protoss_Nexus 1 9649
Protoss_Observer 1 8522
Protoss_Robotics_Support_Bay 1 8652
Protoss_Reaver 2 10890
10890
