Protoss_Gateway 2 7606
Protoss_Assimilator 1 3578
Protoss_Zealot 2 4542
Protoss_Cybernetics_Core 1 4779
Protoss_Dragoon 8 9878
Protoss_Robotics_Facility 1 7117
Protoss_Shuttle 1 8147
Protoss_Observatory 1 7713
Protoss_Observer 1 8750
Protoss_Robotics_Support_Bay 1 8707
Protoss_Reaver 1 9836
9878
