Protoss_Gateway 2 8111
Protoss_Assimilator 1 3024
Protoss_Cybernetics_Core 1 3874
Protoss_Zealot 1 3892
Protoss_Dragoon 9 10186
Protoss_Shield_Battery 2 8619
Protoss_Nexus 1 8491
Protoss_Robotics_Facility 1 9206
Protoss_Observatory 1 9749
Protoss_Robotics_Support_Bay 1 10183
Protoss_Observer 1 10426
10426
