Protoss_Gateway 2 3319
Protoss_Zealot 5 10326
Protoss_Assimilator 1 3974
Protoss_Cybernetics_Core 1 4741
Protoss_Dragoon 11 10480
Protoss_Robotics_Facility 1 8164
Protoss_Shuttle 1 9255
Protoss_Robotics_Support_Bay 1 9397
Protoss_Reaver 1 10524
10524
