Protoss_Gateway 4 10510
Protoss_Assimilator 1 3006
Protoss_Zealot 2 5188
Protoss_Cybernetics_Core 1 4712
Protoss_Citadel_of_Adun 1 5699
Protoss_Dragoon 6 10320
Protoss_Templar_Archives 1 6686
Protoss_Dark_Templar 3 8430
Protoss_Nexus 1 10165
Protoss_Robotics_Facility 1 11122
11122
