Protoss_Gateway 2 7229
Protoss_Assimilator 1 2908
Protoss_Zealot 2 4510
Protoss_Cybernetics_Core 1 4515
Protoss_Dragoon 10 10670
Protoss_Robotics_Facility 1 6789
Protoss_Shuttle 1 7797
Protoss_Observatory 1 7720
Protoss_Observer 2 10072
Protoss_Robotics_Support_Bay 1 8295
Protoss_Reaver 1 9468
Protoss_Nexus 1 11365
11365
