Protoss_Gateway 3 10334
Protoss_Assimilator 1 2959
Protoss_Zealot 2 4648
Protoss_Cybernetics_Core 1 4539
Protoss_Dragoon 7 10692
Protoss_Robotics_Facility 1 6917
Protoss_Robotics_Support_Bay 1 7477
Protoss_Nexus 1 9409
Protoss_Reaver 2 10298
Protoss_Observatory 1 9228
Protoss_Shield_Battery 1 10135
10692
