Protoss_Gateway 3 6771
Protoss_Zealot 2 5264
Protoss_Assimilator 1 4899
Protoss_Cybernetics_Core 1 6315
Protoss_Dragoon 7 10480
Protoss_Robotics_Facility 1 8061
Protoss_Shuttle 1 9051
Protoss_Robotics_Support_Bay 1 9217
Protoss_Reaver 1 10344
10480
