Protoss_Gateway 2 5891
Protoss_Assimilator 1 2951
Protoss_Zealot 2 4282
Protoss_Cybernetics_Core 1 5279
Protoss_Dragoon 10 10708
Protoss_Robotics_Facility 1 7191
Protoss_Observatory 1 7731
Protoss_Observer 3 10038
Protoss_Nexus 1 11509
11509
