Protoss_Gateway 2 3321
Protoss_Zealot 10 9334
Protoss_Nexus 2 11659
Protoss_Assimilator 2 8487
Protoss_Cybernetics_Core 1 7866
Protoss_Dragoon 3 10272
Protoss_Citadel_of_Adun 1 9012
Protoss_Forge 1 8895
Protoss_Templar_Archives 1 10459
Protoss_Photon_Cannon 1 10721
11659
