Protoss_Gateway 2 3361
Protoss_Zealot 3 5708
Protoss_Nexus 1 5878
Protoss_Assimilator 2 9144
Protoss_Cybernetics_Core 1 5607
Protoss_Dragoon 8 10326
Protoss_Forge 1 7433
Protoss_Citadel_of_Adun 1 8475
Protoss_Photon_Cannon 3 9887
Protoss_Robotics_Facility 1 9265
Protoss_Observatory 1 9811
Protoss_Observer 1 10518
10518
