Protoss_Gateway 2 7543
Protoss_Assimilator 1 3048
Protoss_Cybernetics_Core 1 4046
Protoss_Dragoon 8 10324
Protoss_Robotics_Facility 1 7106
Protoss_Observatory 1 7793
Protoss_Shuttle 1 8405
Protoss_Robotics_Support_Bay 1 8745
Protoss_Observer 1 9008
Protoss_Nexus 1 10719
Protoss_Reaver 1 10244
10719
