Protoss_Gateway 2 3391
Protoss_Zealot 8 7682
Protoss_Nexus 1 6734
Protoss_Assimilator 2 9389
Protoss_Cybernetics_Core 1 6475
Protoss_Citadel_of_Adun 1 8294
Protoss_Forge 1 8950
Protoss_Templar_Archives 1 9422
Protoss_Photon_Cannon 4 10606
Protoss_Dark_Templar 2 10598
10606
