Protoss_Gateway 2 9592
Protoss_Assimilator 1 3059
Protoss_Zealot 2 4536
Protoss_Cybernetics_Core 1 4550
Protoss_Dragoon 3 6978
Protoss_Citadel_of_Adun 1 6793
Protoss_Nexus 1 8633
Protoss_Templar_Archives 1 7920
Protoss_Forge 1 7865
Protoss_Photon_Cannon 2 9299
Protoss_Dark_Templar 4 10516
10516
