Protoss_Gateway 3 10540
Protoss_Assimilator 1 2800
Protoss_Zealot 1 3494
Protoss_Cybernetics_Core 1 4606
Protoss_Dragoon 8 10510
Protoss_Robotics_Facility 1 7149
Protoss_Observatory 1 7819
Protoss_Robotics_Support_Bay 1 7853
Protoss_Observer 1 8540
Protoss_Reaver 1 9590
Protoss_Nexus 1 10817
Protoss_Shuttle 1 10493
10817
