Protoss_Gateway 4 10637
Protoss_Assimilator 1 3057
Protoss_Cybernetics_Core 1 3975
Protoss_Dragoon 9 10176
Protoss_Robotics_Facility 1 7867
Protoss_Observatory 1 8417
Protoss_Observer 2 9700
Protoss_Nexus 1 10608
Protoss_Robotics_Support_Bay 1 10364
10637
