Protoss_Gateway 4 10228
Protoss_Assimilator 1 2771
Protoss_Cybernetics_Core 1 3695
Protoss_Zealot 1 3676
Protoss_Dragoon 7 10410
Protoss_Citadel_of_Adun 1 6385
Protoss_Robotics_Facility 1 6706
Protoss_Templar_Archives 1 7379
Protoss_Shuttle 1 7733
Protoss_Dark_Templar 2 8216
Protoss_Nexus 1 10021
Protoss_Observatory 1 10315
10410
