Protoss_Gateway 1 2753
Protoss_Assimilator 1 3011
Protoss_Zealot 1 3446
Protoss_Cybernetics_Core 1 4750
Protoss_Dragoon 7 10114
Protoss_Robotics_Facility 1 6255
Protoss_Shuttle 1 7239
Protoss_Robotics_Support_Bay 1 7307
Protoss_Reaver 1 8432
Protoss_Observatory 1 8277
Protoss_Observer 2 9936
Protoss_Nexus 1 10933
10933
