Protoss_Gateway 3 6866
Protoss_Assimilator 1 3583
Protoss_Cybernetics_Core 1 4204
Protoss_Zealot 1 4046
Protoss_Dragoon 13 9952
Protoss_Forge 1 8767
Protoss_Photon_Cannon 3 10194
Protoss_Robotics_Facility 1 11079
11079
