Protoss_Gateway 2 7259
Protoss_Assimilator 1 3000
Protoss_Zealot 2 4602
Protoss_Cybernetics_Core 1 4654
Protoss_Dragoon 9 9592
Protoss_Robotics_Facility 1 6963
Protoss_Shuttle 1 7967
Protoss_Robotics_Support_Bay 1 7980
Protoss_Reaver 1 9128
Protoss_Observatory 1 8744
Protoss_Observer 2 10460
Protoss_Nexus 1 11489
11489
