Protoss_Gateway 2 3344
Protoss_Zealot 12 8793
Protoss_Assimilator 1 5829
Protoss_Cybernetics_Core 1 7299
Protoss_Citadel_of_Adun 1 9688
Protoss_Templar_Archives 1 10798
Protoss_Forge 1 10561
10798
