Protoss_Gateway 2 5070
Protoss_Assimilator 1 3120
Protoss_Zealot 3 10094
Protoss_Cybernetics_Core 1 4461
Protoss_Dragoon 5 7568
Protoss_Citadel_of_Adun 1 6374
Protoss_Forge 1 7016
Protoss_Templar_Archives 1 7365
Protoss_Dark_Templar 2 8320
Protoss_Photon_Cannon 3 10709
Protoss_Nexus 1 10251
Protoss_High_Templar 2 9298
Protoss_Archon 1 10207
10709
