Protoss_Gateway 3 4363
Protoss_Zealot 4 10006
Protoss_Assimilator 1 4668
Protoss_Cybernetics_Core 1 5669
Protoss_Dragoon 9 10308
Protoss_Robotics_Facility 1 9400
Protoss_Observatory 1 10163
10308
