Protoss_Gateway 2 6303
Protoss_Zealot 2 4450
Protoss_Assimilator 1 4268
Protoss_Cybernetics_Core 1 5647
Protoss_Dragoon 11 10626
Protoss_Robotics_Facility 1 9746
Protoss_Observatory 1 10375
10626
