Protoss_Gateway 2 3372
Protoss_Zealot 8 8786
Protoss_Nexus 2 10827
Protoss_Assimilator 2 8982
Protoss_Cybernetics_Core 1 6833
Protoss_Dragoon 1 7692
Protoss_Citadel_of_Adun 1 8094
Protoss_Templar_Archives 1 9119
Protoss_Forge 1 9312
Protoss_Dark_Templar 2 9996
Protoss_Photon_Cannon 2 10484
10827
