Protoss_Gateway 4 10736
Protoss_Zealot 9 8278
Protoss_Nexus 1 6777
Protoss_Assimilator 2 7484
Protoss_Cybernetics_Core 1 6728
Protoss_Dragoon 4 10098
Protoss_Forge 1 9775
10736
