Protoss_Gateway 2 8374
Protoss_Assimilator 3 5243
Protoss_Zealot 3 5420
Protoss_Cybernetics_Core 1 5189
Protoss_Dragoon 8 10526
Protoss_Robotics_Facility 1 7971
Protoss_Shuttle 1 9207
Protoss_Robotics_Support_Bay 1 9535
Protoss_Observatory 1 9595
Protoss_Observer 1 10406
10526
