Protoss_Gateway 2 5175
Protoss_Zealot 10 8118
Protoss_Assimilator 1 5120
Protoss_Cybernetics_Core 1 5924
Protoss_Citadel_of_Adun 1 7052
Protoss_Robotics_Facility 1 7987
Protoss_Forge 1 7666
Protoss_Photon_Cannon 1 8527
Protoss_Templar_Archives 1 8943
Protoss_Shuttle 1 9237
Protoss_Observatory 1 9420
Protoss_Dark_Templar 2 9788
Protoss_Observer 1 10163
Protoss_Nexus 1 11540
11540
