Protoss_Gateway 2 6382
Protoss_Zealot 5 9168
Protoss_Cybernetics_Core 1 4943
Protoss_Assimilator 1 5955
Protoss_Dragoon 7 10672
Protoss_Nexus 1 8862
Protoss_Robotics_Facility 1 9673
10672
