Protoss_Gateway 2 4339
Protoss_Assimilator 1 2840
Protoss_Cybernetics_Core 1 3792
Protoss_Dragoon 15 10678
Protoss_Robotics_Facility 1 8384
Protoss_Shuttle 1 9447
Protoss_Observatory 1 9407
Protoss_Observer 1 10098
10678
