Protoss_Gateway 4 9843
Protoss_Zealot 5 6122
Protoss_Nexus 1 6662
Protoss_Assimilator 2 8076
Protoss_Cybernetics_Core 1 6937
Protoss_Dragoon 8 10732
Protoss_Robotics_Facility 1 9237
Protoss_Forge 1 8667
Protoss_Photon_Cannon 2 10308
Protoss_Observatory 1 9817
10732
