Protoss_Gateway 3 9298
Protoss_Assimilator 1 2955
Protoss_Zealot 2 4796
Protoss_Cybernetics_Core 1 4778
Protoss_Dragoon 11 10316
Protoss_Nexus 1 9487
Protoss_Robotics_Facility 1 10383
10383
