Protoss_Gateway 3 10837
Protoss_Assimilator 3 9688
Protoss_Zealot 3 7112
Protoss_Cybernetics_Core 1 4729
Protoss_Citadel_of_Adun 1 5724
Protoss_Dragoon 2 6510
Protoss_Templar_Archives 1 6759
Protoss_Dark_Templar 2 8355
Protoss_Nexus 1 8810
Protoss_Forge 1 8275
Protoss_Photon_Cannon 3 9766
Protoss_High_Templar 2 10673
10837
