Protoss_Gateway 3 8305
Protoss_Zealot 4 9925
Protoss_Assimilator 1 3931
Protoss_Cybernetics_Core 1 4854
Protoss_Dragoon 11 10563
Protoss_Robotics_Facility 1 7777
Protoss_Observatory 1 8742
Protoss_Observer 2 10223
10563
