Protoss_Gateway 2 7127
Protoss_Assimilator 1 2839
Protoss_Zealot 3 4902
Protoss_Cybernetics_Core 1 4881
Protoss_Dragoon 4 10728
Protoss_Citadel_of_Adun 1 6495
Protoss_Templar_Archives 1 7644
Protoss_Forge 1 8200
Protoss_Dark_Templar 2 8510
Protoss_Photon_Cannon 3 10138
Protoss_Nexus 1 10655
Protoss_High_Templar 2 9922
10728
