Protoss_Gateway 4 10755
Protoss_Assimilator 1 2939
Protoss_Zealot 3 5192
Protoss_Cybernetics_Core 1 5007
Protoss_Dragoon 10 10402
Protoss_Robotics_Facility 1 7623
Protoss_Observatory 1 8211
Protoss_Observer 3 10508
Protoss_Nexus 1 10989
10989
