Protoss_Gateway 2 6432
Protoss_Assimilator 1 2860
Protoss_Zealot 2 4616
Protoss_Cybernetics_Core 1 4683
Protoss_Dragoon 9 10626
Protoss_Robotics_Facility 1 7111
Protoss_Observatory 1 7687
Protoss_Observer 2 8970
Protoss_Nexus 1 9877
Protoss_Shuttle 1 10253
Protoss_Robotics_Support_Bay 1 9873
10626
