Protoss_Gateway 2 3221
Protoss_Zealot 13 8298
Protoss_Nexus 1 8209
Protoss_Assimilator 2 9976
Protoss_Forge 1 7494
Protoss_Cybernetics_Core 1 8950
Protoss_Photon_Cannon 2 10427
Protoss_Citadel_of_Adun 1 10345
Protoss_Robotics_Facility 1 11098
11098
