Protoss_Gateway 2 3402
Protoss_Zealot 7 7284
Protoss_Nexus 1 6897
Protoss_Assimilator 2 7797
Protoss_Cybernetics_Core 1 7296
Protoss_Dragoon 2 8242
Protoss_Citadel_of_Adun 1 8495
Protoss_Templar_Archives 1 9527
Protoss_Forge 1 9327
Protoss_Photon_Cannon 2 10238
Protoss_Dark_Templar 2 10372
Protoss_Robotics_Facility 1 10952
10952
