Protoss_Gateway 3 9407
Protoss_Zealot 5 6362
Protoss_Nexus 2 11789
Protoss_Assimilator 2 7520
Protoss_Cybernetics_Core 1 6436
Protoss_Dragoon 9 10250
Protoss_Robotics_Facility 1 8565
Protoss_Shuttle 1 9547
Protoss_Observatory 1 9174
Protoss_Observer 1 10272
11789
