Protoss_Gateway 2 3338
Protoss_Zealot 7 7244
Protoss_Nexus 1 7041
Protoss_Assimilator 2 7773
Protoss_Cybernetics_Core 1 7270
Protoss_Citadel_of_Adun 1 8416
Protoss_Dragoon 4 9294
Protoss_Templar_Archives 1 9477
Protoss_Forge 1 9242
Protoss_Robotics_Facility 1 10288
Protoss_Photon_Cannon 1 10386
Protoss_Dark_Templar 2 10556
10556
