Protoss_Gateway 5 10491
Protoss_Zealot 6 9640
Protoss_Nexus 2 8626
Protoss_Assimilator 2 9113
Protoss_Cybernetics_Core 1 6284
Protoss_Dragoon 4 9810
Protoss_Robotics_Facility 1 9223
Protoss_Observatory 1 9844
Protoss_Observer 1 10538
10538
