Protoss_Gateway 2 3243
Protoss_Zealot 15 9192
Protoss_Nexus 1 7821
Protoss_Assimilator 2 9408
Protoss_Cybernetics_Core 1 7965
Protoss_Forge 1 8730
Protoss_Citadel_of_Adun 1 9267
Protoss_Photon_Cannon 2 9844
Protoss_Robotics_Facility 1 10525
10525
