Protoss_Gateway 1 2921
Protoss_Assimilator 1 2827
Protoss_Cybernetics_Core 1 3957
Protoss_Zealot 2 4878
Protoss_Robotics_Facility 1 5252
Protoss_Shuttle 1 6247
Protoss_Robotics_Support_Bay 1 6049
Protoss_Dragoon 1 6488
Protoss_Reaver 2 9836
Protoss_Shield_Battery 1 8988
9836
