Protoss_Gateway 1 2850
Protoss_Assimilator 1 2940
Protoss_Cybernetics_Core 1 3895
Protoss_Robotics_Facility 1 5325
Protoss_Zealot 2 5435
Protoss_Shuttle 1 6317
Protoss_Dragoon 2 8058
Protoss_Robotics_Support_Bay 1 6811
Protoss_Reaver 1 7946
8058
