Protoss_Gateway 4 8606
Protoss_Assimilator 1 3070
Protoss_Cybernetics_Core 1 4013
Protoss_Robotics_Facility 1 5554
Protoss_Dragoon 4 10098
Protoss_Citadel_of_Adun 1 6334
Protoss_Shuttle 1 6547
Protoss_Observatory 1 6274
Protoss_Observer 5 10517
Protoss_Zealot 10 10590
10590
