Protoss_Gateway 4 10703
Protoss_Assimilator 1 3462
Protoss_Cybernetics_Core 1 4068
Protoss_Zealot 1 4318
Protoss_Dragoon 7 9912
Protoss_Nexus 2 10327
Protoss_Robotics_Facility 1 7973
Protoss_Observatory 1 8648
Protoss_Observer 2 9948
Protoss_Robotics_Support_Bay 1 9899
10703
