Protoss_Gateway 4 9583
Protoss_Zealot 6 10376
Protoss_Assimilator 1 3585
Protoss_Cybernetics_Core 1 4612
Protoss_Dragoon 8 9730
Protoss_Nexus 1 7623
Protoss_Robotics_Facility 1 7839
Protoss_Observatory 1 8403
Protoss_Observer 2 9796
Protoss_Citadel_of_Adun 1 10527
10527
