Protoss_Assimilator 1 2646
Protoss_Gateway 1 3416
Protoss_Cybernetics_Core 1 4532
Protoss_Robotics_Facility 2 6551
Protoss_Shuttle 2 10622
Protoss_Observatory 1 6451
Protoss_Robotics_Support_Bay 1 6909
Protoss_Observer 2 8860
Protoss_Reaver 3 9542
Protoss_Dragoon 2 9703
Protoss_Nexus 1 9774
Protoss_Shield_Battery 2 9906
10622
