Protoss_Gateway 3 8739
Protoss_Assimilator 1 2795
Protoss_Cybernetics_Core 1 3907
Protoss_Citadel_of_Adun 1 4925
Protoss_Robotics_Facility 1 5863
Protoss_Templar_Archives 1 6282
Protoss_Shuttle 1 6852
Protoss_Dark_Templar 2 7403
Protoss_Observatory 1 7265
Protoss_Dragoon 6 9968
Protoss_Observer 1 7963
9968
