Protoss_Gateway 3 9117
Protoss_Assimilator 1 2865
Protoss_Cybernetics_Core 1 3814
Protoss_Robotics_Facility 1 5227
Protoss_Dragoon 9 10330
Protoss_Shuttle 1 6222
Protoss_Observatory 1 5934
Protoss_Observer 3 8029
Protoss_Nexus 1 8581
10330
