Protoss_Gateway 3 8552
Protoss_Zealot 7 8426
Protoss_Assimilator 1 4664
Protoss_Cybernetics_Core 1 6233
Protoss_Dragoon 10 10532
Protoss_Robotics_Facility 1 8747
Protoss_Observatory 1 9293
Protoss_Observer 1 9976
10532
