Protoss_Gateway 3 9965
Protoss_Assimilator 1 2981
Protoss_Cybernetics_Core 1 3849
Protoss_Zealot 1 3738
Protoss_Dragoon 10 10442
Protoss_Robotics_Facility 1 8775
Protoss_Observatory 1 9343
Protoss_Observer 1 10042
10442
