Protoss_Gateway 2 9809
Protoss_Assimilator 1 2845
Protoss_Cybernetics_Core 1 3935
Protoss_Stargate 1 5096
Protoss_Robotics_Facility 1 5600
Protoss_Dragoon 7 10048
Protoss_Observatory 1 6232
Protoss_Observer 3 9803
Protoss_Shuttle 1 8656
Protoss_Robotics_Support_Bay 1 9594
Protoss_Reaver 1 10853
10853
