Protoss_Assimilator 1 2486
Protoss_Gateway 4 9750
Protoss_Cybernetics_Core 1 4246
Protoss_Robotics_Facility 1 5569
Protoss_Dragoon 10 10513
Protoss_Observatory 1 6122
Protoss_Observer 2 8563
Protoss_Shuttle 1 7882
10513
