Protoss_Gateway 2 3321
Protoss_Zealot 9 7686
Protoss_Nexus 1 6922
Protoss_Assimilator 2 8830
Protoss_Cybernetics_Core 1 7559
Protoss_Dragoon 6 10510
Protoss_Robotics_Facility 1 9833
Protoss_Shuttle 1 10891
10891
