Protoss_Gateway 2 3327
Protoss_Zealot 11 8046
Protoss_Nexus 1 7593
Protoss_Assimilator 2 8846
Protoss_Cybernetics_Core 1 7305
Protoss_Citadel_of_Adun 1 8588
Protoss_Dragoon 2 9262
Protoss_Templar_Archives 1 9711
Protoss_Forge 1 9780
Protoss_Dark_Templar 2 10586
10586
