Protoss_Gateway 3 6608
Protoss_Assimilator 1 2983
Protoss_Zealot 1 3572
Protoss_Cybernetics_Core 1 5187
Protoss_Dragoon 11 10060
Protoss_Robotics_Facility 1 9619
Protoss_Observatory 1 10213
10213
