Protoss_Gateway 2 5209
Protoss_Assimilator 1 3047
Protoss_Cybernetics_Core 1 3965
Protoss_Zealot 2 10408
Protoss_Dragoon 9 10008
Protoss_Robotics_Facility 1 8347
Protoss_Shuttle 1 9371
Protoss_Observatory 1 9086
Protoss_Robotics_Support_Bay 1 9825
Protoss_Reaver 1 10960
10960
