Protoss_Gateway 2 6472
Protoss_Assimilator 1 3229
Protoss_Zealot 3 9598
Protoss_Cybernetics_Core 1 4476
Protoss_Dragoon 12 10570
Protoss_Robotics_Facility 1 8345
Protoss_Observatory 1 8895
Protoss_Observer 2 10176
10570
