Protoss_Gateway 1 2746
Protoss_Zealot 4 5246
Protoss_Assimilator 2 5591
Protoss_Cybernetics_Core 1 5370
Protoss_Dragoon 6 10030
Protoss_Robotics_Facility 1 7109
Protoss_Shuttle 1 8121
Protoss_Robotics_Support_Bay 1 7885
Protoss_Reaver 2 10696
10696
