Protoss_Gateway 2 6987
Protoss_Assimilator 1 3289
Protoss_Zealot 6 10060
Protoss_Cybernetics_Core 1 5168
Protoss_Dragoon 5 10228
Protoss_Robotics_Facility 1 7677
Protoss_Shuttle 1 8659
Protoss_Robotics_Support_Bay 1 8297
Protoss_Observatory 1 8325
Protoss_Observer 1 9262
Protoss_Reaver 1 10312
Protoss_Citadel_of_Adun 1 10879
10879
