Protoss_Gateway 2 4735
Protoss_Assimilator 1 2901
Protoss_Zealot 7 10030
Protoss_Cybernetics_Core 2 5701
Protoss_Dragoon 8 9428
Protoss_Robotics_Facility 1 8523
Protoss_Shuttle 1 9503
Protoss_Robotics_Support_Bay 1 9269
Protoss_Observatory 1 9659
Protoss_Reaver 1 10666
10666
