Protoss_Gateway 2 7741
Protoss_Assimilator 1 2999
Protoss_Zealot 2 4700
Protoss_Cybernetics_Core 1 4584
Protoss_Dragoon 9 10264
Protoss_Robotics_Facility 1 7209
Protoss_Shuttle 1 8321
Protoss_Robotics_Support_Bay 1 8359
Protoss_Reaver 1 9526
Protoss_Observatory 1 9489
10264
