Protoss_Gateway 2 3388
Protoss_Zealot 10 8364
Protoss_Assimilator 1 5140
Protoss_Cybernetics_Core 1 6089
Protoss_Dragoon 7 10598
Protoss_Robotics_Facility 1 8026
Protoss_Observatory 1 8575
Protoss_Observer 1 9308
Protoss_Shuttle 1 10209
Protoss_Robotics_Support_Bay 1 10115
10598
