Protoss_Gateway 2 3518
Protoss_Zealot 14 9043
Protoss_Assimilator 1 7340
Protoss_Cybernetics_Core 1 8498
Protoss_Dragoon 2 9988
Protoss_Robotics_Facility 1 10588
Protoss_Nexus 1 11561
11561
