Protoss_Gateway 2 9607
Protoss_Assimilator 1 2836
Protoss_Zealot 2 4624
Protoss_Cybernetics_Core 1 4677
Protoss_Dragoon 7 10466
Protoss_Nexus 1 9100
Protoss_Robotics_Facility 1 9117
Protoss_Observatory 1 9721
Protoss_Robotics_Support_Bay 1 10275
10466
