Protoss_Gateway 2 6538
Protoss_Assimilator 1 2817
Protoss_Zealot 3 4726
Protoss_Cybernetics_Core 1 4813
Protoss_Dragoon 7 8780
Protoss_Robotics_Facility 1 8247
Protoss_Nexus 1 9406
Protoss_Shuttle 1 9363
Protoss_Robotics_Support_Bay 1 9268
Protoss_Observatory 1 9675
Protoss_Reaver 1 10688
10688
