Protoss_Gateway 2 5108
Protoss_Assimilator 1 3157
Protoss_Zealot 7 8888
Protoss_Cybernetics_Core 2 8303
Protoss_Shield_Battery 1 5512
Protoss_Dragoon 1 9348
Protoss_Robotics_Facility 1 10515
10515
