Protoss_Gateway 2 7332
Protoss_Assimilator 2 9990
Protoss_Zealot 2 4498
Protoss_Cybernetics_Core 1 4578
Protoss_Dragoon 3 6914
Protoss_Citadel_of_Adun 1 6454
Protoss_Templar_Archives 1 7573
Protoss_Forge 1 7596
Protoss_Dark_Templar 2 8474
Protoss_Photon_Cannon 1 8567
Protoss_Nexus 1 10275
Protoss_High_Templar 2 10238
10275
