Protoss_Gateway 2 7373
Protoss_Assimilator 1 2802
Protoss_Zealot 2 4820
Protoss_Cybernetics_Core 1 4679
Protoss_Dragoon 10 10650
Protoss_Robotics_Facility 1 7165
Protoss_Shuttle 1 8333
Protoss_Robotics_Support_Bay 1 8374
Protoss_Observatory 1 8388
Protoss_Reaver 1 9510
Protoss_Observer 1 10114
10650
