Protoss_Gateway 4 10175
Protoss_Assimilator 2 10390
Protoss_Cybernetics_Core 1 3751
Protoss_Zealot 1 3780
Protoss_Dragoon 9 10074
Protoss_Nexus 1 8585
Protoss_Robotics_Facility 1 8577
Protoss_Observatory 1 9292
Protoss_Observer 1 10118
10390
