Protoss_Gateway 2 4531
Protoss_Assimilator 1 3271
Protoss_Zealot 9 6884
Protoss_Shield_Battery 1 4947
Protoss_Cybernetics_Core 1 6343
Protoss_Dragoon 8 9892
Protoss_Citadel_of_Adun 1 8372
Protoss_Templar_Archives 1 9615
Protoss_Forge 1 9866
Protoss_Dark_Templar 2 10466
Protoss_Photon_Cannon 2 10718
10718
