Protoss_Gateway 2 5007
Protoss_Assimilator 2 9005
Protoss_Zealot 3 9760
Protoss_Cybernetics_Core 1 4498
Protoss_Dragoon 7 8422
Protoss_Robotics_Facility 1 6998
Protoss_Nexus 1 8833
Protoss_Observatory 1 7603
Protoss_Observer 2 10306
Protoss_Robotics_Support_Bay 1 8559
Protoss_Reaver 1 9702
10306
