Protoss_Gateway 2 6777
Protoss_Assimilator 1 2939
Protoss_Zealot 2 4410
Protoss_Cybernetics_Core 1 4376
Protoss_Dragoon 9 9578
Protoss_Robotics_Facility 1 6829
Protoss_Observatory 1 7493
Protoss_Observer 1 8176
Protoss_Robotics_Support_Bay 1 8135
Protoss_Reaver 1 9710
Protoss_Nexus 1 11283
Protoss_Shuttle 1 10613
11283
