Protoss_Gateway 2 7456
Protoss_Assimilator 1 2910
Protoss_Zealot 3 4726
Protoss_Cybernetics_Core 1 4654
Protoss_Dragoon 9 9708
Protoss_Robotics_Facility 1 6309
Protoss_Shuttle 1 7391
Protoss_Observatory 2 7846
Protoss_Observer 2 10424
Protoss_Robotics_Support_Bay 1 8465
Protoss_Reaver 1 9820
10424
