Protoss_Gateway 2 7544
Protoss_Assimilator 1 2808
Protoss_Zealot 2 4566
Protoss_Cybernetics_Core 1 4576
Protoss_Dragoon 8 10646
Protoss_Robotics_Facility 1 7025
Protoss_Shuttle 1 8125
Protoss_Observatory 1 7825
Protoss_Observer 1 8728
Protoss_Robotics_Support_Bay 1 8677
Protoss_Reaver 1 9868
Protoss_Nexus 1 11549
11549
