Protoss_Gateway 2 7080
Protoss_Assimilator 1 2982
Protoss_Zealot 2 4360
Protoss_Cybernetics_Core 1 4435
Protoss_Dragoon 10 10326
Protoss_Robotics_Facility 1 6815
Protoss_Observatory 1 7370
Protoss_Observer 2 9418
Protoss_Nexus 1 10847
Protoss_Robotics_Support_Bay 1 9851
10847
