Protoss_Gateway 3 10665
Protoss_Zealot 8 9008
Protoss_Assimilator 1 5152
Protoss_Cybernetics_Core 1 6142
Protoss_Robotics_Facility 1 8032
Protoss_Dragoon 5 10213
Protoss_Observatory 1 9201
10665
