Protoss_Gateway 3 9941
Protoss_Assimilator 2 10493
Protoss_Zealot 2 4400
Protoss_Cybernetics_Core 1 4481
Protoss_Dragoon 12 10356
Protoss_Robotics_Facility 1 7676
Protoss_Observatory 1 8361
Protoss_Nexus 1 10215
Protoss_Observer 2 9686
Protoss_Citadel_of_Adun 1 10686
10686
