Protoss_Gateway 2 8162
Protoss_Zealot 11 9512
Protoss_Nexus 1 6867
Protoss_Forge 1 6464
Protoss_Photon_Cannon 11 10710
Protoss_Assimilator 1 8210
Protoss_Cybernetics_Core 1 9425
Protoss_Dragoon 2 10402
10710
