Protoss_Gateway 3 8893
Protoss_Assimilator 2 10157
Protoss_Zealot 2 4492
Protoss_Cybernetics_Core 1 4516
Protoss_Dragoon 11 10670
Protoss_Nexus 1 8277
Protoss_Robotics_Facility 1 8261
Protoss_Observatory 1 8834
Protoss_Observer 2 10130
Protoss_Citadel_of_Adun 1 10122
10670
