Protoss_Gateway 2 8643
Protoss_Assimilator 1 3074
Protoss_Cybernetics_Core 1 4153
Protoss_Zealot 1 4150
Protoss_Dragoon 9 10676
Protoss_Nexus 1 8304
Protoss_Forge 1 7810
Protoss_Photon_Cannon 2 9734
10676
