Protoss_Gateway 3 10711
Protoss_Assimilator 1 2982
Protoss_Zealot 1 3448
Protoss_Cybernetics_Core 1 4460
Protoss_Dragoon 10 10320
Protoss_Robotics_Facility 1 8525
Protoss_Observatory 1 9133
Protoss_Nexus 1 10945
Protoss_Observer 2 10464
10945
