Protoss_Gateway 3 5799
Protoss_Zealot 4 5650
Protoss_Assimilator 1 5115
Protoss_Cybernetics_Core 1 5493
Protoss_Dragoon 8 10044
Protoss_Nexus 1 10371
Protoss_Robotics_Facility 1 10043
10371
