Protoss_Gateway 2 7667
Protoss_Zealot 2 4098
Protoss_Assimilator 1 3666
Protoss_Cybernetics_Core 1 4865
Protoss_Dragoon 8 10038
Protoss_Robotics_Facility 1 8575
Protoss_Nexus 1 10020
Protoss_Shuttle 1 9565
Protoss_Robotics_Support_Bay 1 9185
Protoss_Reaver 1 10634
Protoss_Observatory 1 10349
10634
