Protoss_Gateway 2 8509
Protoss_Assimilator 2 9687
Protoss_Zealot 2 4722
Protoss_Cybernetics_Core 1 4704
Protoss_Citadel_of_Adun 1 5765
Protoss_Dragoon 2 6522
Protoss_Templar_Archives 1 6779
Protoss_Nexus 1 8315
Protoss_Dark_Templar 1 7626
Protoss_Forge 1 7870
Protoss_High_Templar 3 9444
Protoss_Photon_Cannon 3 10092
Protoss_Robotics_Facility 1 10766
10766
