Protoss_Gateway 4 10392
Protoss_Assimilator 1 3040
Protoss_Zealot 2 4474
Protoss_Cybernetics_Core 1 4364
Protoss_Dragoon 6 9202
Protoss_Citadel_of_Adun 1 6463
Protoss_Templar_Archives 1 7503
Protoss_Forge 1 7655
Protoss_Dark_Templar 1 8332
Protoss_Photon_Cannon 1 8828
Protoss_Nexus 1 10687
Protoss_High_Templar 2 9954
10687
