Protoss_Gateway 2 7903
Protoss_Zealot 4 5264
Protoss_Assimilator 1 3808
Protoss_Cybernetics_Core 1 5329
Protoss_Dragoon 6 10744
Protoss_Citadel_of_Adun 1 7789
Protoss_Templar_Archives 1 8778
Protoss_Dark_Templar 2 9762
10744
