Protoss_Gateway 2 8771
Protoss_Assimilator 2 9603
Protoss_Cybernetics_Core 1 3943
Protoss_Zealot 1 3822
Protoss_Dragoon 8 9958
Protoss_Nexus 1 8336
Protoss_Robotics_Facility 1 8315
Protoss_Observatory 1 8889
Protoss_Observer 2 10176
10176
