Protoss_Gateway 2 10447
Protoss_Assimilator 2 10131
Protoss_Zealot 2 4854
Protoss_Cybernetics_Core 1 4776
Protoss_Dragoon 4 8064
Protoss_Citadel_of_Adun 1 6805
Protoss_Templar_Archives 1 7821
Protoss_Forge 1 7542
Protoss_Photon_Cannon 2 9348
Protoss_Dark_Templar 1 8816
Protoss_Nexus 1 10101
Protoss_High_Templar 1 9868
10447
