Protoss_Gateway 2 9125
Protoss_Assimilator 2 10320
Protoss_Zealot 2 4524
Protoss_Cybernetics_Core 1 4529
Protoss_Dragoon 5 8642
Protoss_Nexus 1 8305
Protoss_Citadel_of_Adun 1 7911
Protoss_Forge 1 8122
Protoss_Templar_Archives 1 9127
Protoss_Photon_Cannon 2 9580
Protoss_Dark_Templar 2 9976
Protoss_High_Templar 2 10728
10728
