Protoss_Gateway 3 8974
Protoss_Assimilator 1 2954
Protoss_Zealot 2 4572
Protoss_Cybernetics_Core 1 4610
Protoss_Dragoon 11 10704
Protoss_Nexus 1 8422
Protoss_Robotics_Facility 1 8351
Protoss_Observatory 1 8997
Protoss_Observer 1 9676
Protoss_Robotics_Support_Bay 1 9544
Protoss_Reaver 1 10866
10866
