Protoss_Gateway 2 3495
Protoss_Zealot 8 8378
Protoss_Nexus 1 6525
Protoss_Assimilator 2 7979
Protoss_Cybernetics_Core 1 6531
Protoss_Dragoon 4 10686
Protoss_Citadel_of_Adun 1 7776
Protoss_Templar_Archives 1 8791
Protoss_Forge 1 8839
Protoss_Dark_Templar 2 9686
Protoss_Photon_Cannon 2 10444
Protoss_High_Templar 1 10548
10686
