Protoss_Gateway 2 7525
Protoss_Assimilator 1 2976
Protoss_Zealot 2 4598
Protoss_Cybernetics_Core 1 4583
Protoss_Dragoon 10 10706
Protoss_Robotics_Facility 1 6750
Protoss_Shuttle 1 7793
Protoss_Observatory 1 7767
Protoss_Observer 2 10180
Protoss_Robotics_Support_Bay 1 8449
Protoss_Reaver 1 9576
Protoss_Nexus 1 11579
11579
