Protoss_Gateway 2 3424
Protoss_Zealot 3 6652
Protoss_Assimilator 3 7091
Protoss_Nexus 1 6543
Protoss_Cybernetics_Core 1 6130
Protoss_Dragoon 9 10466
Protoss_Robotics_Facility 1 8823
Protoss_Shuttle 1 9871
Protoss_Observatory 1 9517
Protoss_Robotics_Support_Bay 1 9946
Protoss_Observer 1 10490
10490
