Protoss_Gateway 2 6223
Protoss_Assimilator 1 2799
Protoss_Zealot 2 4410
Protoss_Cybernetics_Core 1 4442
Protoss_Dragoon 1 5270
Protoss_Citadel_of_Adun 1 5869
Protoss_Templar_Archives 1 6857
Protoss_Dark_Templar 2 7726
Protoss_Nexus 1 9023
Protoss_Forge 1 7931
Protoss_Photon_Cannon 7 10539
Protoss_High_Templar 3 10084
10539
