Protoss_Gateway 3 6831
Protoss_Assimilator 1 2895
Protoss_Zealot 2 4250
Protoss_Cybernetics_Core 1 4322
Protoss_Dragoon 15 10348
Protoss_Robotics_Facility 1 6359
Protoss_Observatory 1 6909
Protoss_Observer 2 8220
Protoss_Shuttle 1 10871
10871
