Protoss_Gateway 2 3600
Protoss_Zealot 5 5774
Protoss_Assimilator 1 4018
Protoss_Cybernetics_Core 1 5470
Protoss_Dragoon 10 10546
Protoss_Robotics_Facility 1 9247
Protoss_Observatory 1 9815
10546
