Protoss_Gateway 1 3059
Protoss_Assimilator 1 3161
Protoss_Zealot 2 9475
Protoss_Cybernetics_Core 1 5015
Protoss_Robotics_Facility 1 6369
Protoss_Dragoon 2 6770
Protoss_Citadel_of_Adun 1 6989
Protoss_Shuttle 1 7432
Protoss_Robotics_Support_Bay 1 7221
Protoss_Templar_Archives 1 7989
Protoss_Reaver 3 10651
Protoss_Dark_Templar 1 8873
Protoss_Nexus 1 11705
11705
