Protoss_Gateway 4 9956
Protoss_Assimilator 2 10246
Protoss_Cybernetics_Core 1 3858
Protoss_Dragoon 14 10298
Protoss_Nexus 1 8369
Protoss_Robotics_Facility 1 8095
Protoss_Observatory 1 8646
Protoss_Observer 1 10168
10298
