Protoss_Gateway 3 7587
Protoss_Assimilator 1 2832
Protoss_Cybernetics_Core 1 3769
Protoss_Dragoon 12 10100
Protoss_Nexus 1 7382
Protoss_Robotics_Facility 2 10982
Protoss_Observatory 1 10328
10982
