Protoss_Gateway 1 2939
Protoss_Assimilator 1 3010
Protoss_Cybernetics_Core 1 4019
Protoss_Dragoon 6 9728
Protoss_Robotics_Facility 1 5674
Protoss_Robotics_Support_Bay 1 6242
Protoss_Shield_Battery 1 6450
Protoss_Reaver 2 10485
Protoss_Observatory 1 7915
Protoss_Shuttle 1 8832
Protoss_Observer 1 9435
Protoss_Nexus 1 11495
11495
