Protoss_Gateway 2 4044
Protoss_Assimilator 2 4193
Protoss_Zealot 11 7713
Protoss_Cybernetics_Core 1 7546
Protoss_Citadel_of_Adun 1 8544
Protoss_Templar_Archives 1 9541
Protoss_Forge 1 9735
Protoss_Dark_Templar 2 10393
10393
