Protoss_Gateway 4 9430
Protoss_Zealot 5 6183
Protoss_Assimilator 2 4838
Protoss_Cybernetics_Core 1 5827
Protoss_Dragoon 4 8078
Protoss_Citadel_of_Adun 1 7658
Protoss_Templar_Archives 1 8707
Protoss_Dark_Templar 2 9573
Protoss_Nexus 1 11369
Protoss_Forge 1 10347
11369
