Protoss_Gateway 3 10554
Protoss_Zealot 7 6833
Protoss_Assimilator 1 6110
Protoss_Cybernetics_Core 1 6662
Protoss_Dragoon 7 10103
Protoss_Robotics_Facility 1 10137
Protoss_Nexus 1 11285
11285
