Protoss_Gateway 3 8218
Protoss_Zealot 12 9055
Protoss_Forge 1 5850
Protoss_Assimilator 1 6785
Protoss_Cybernetics_Core 1 7590
Protoss_Nexus 1 8822
Protoss_Photon_Cannon 3 10713
Protoss_Dragoon 2 10723
10723
