Protoss_Gateway 1 2880
Protoss_Assimilator 1 3312
Protoss_Zealot 3 5333
Protoss_Shield_Battery 1 4461
Protoss_Cybernetics_Core 1 5319
Protoss_Dragoon 2 9378
Protoss_Robotics_Facility 2 7439
Protoss_Observatory 1 7747
Protoss_Shuttle 1 8202
Protoss_Robotics_Support_Bay 1 8031
Protoss_Observer 1 8483
Protoss_Reaver 2 9533
9533
