Protoss_Gateway 3 9107
Protoss_Zealot 8 8508
Protoss_Assimilator 1 5172
Protoss_Cybernetics_Core 1 5898
Protoss_Forge 1 6660
Protoss_Shield_Battery 1 6766
Protoss_Dragoon 6 10543
Protoss_Photon_Cannon 2 9551
Protoss_Robotics_Facility 1 10323
10543
