Protoss_Gateway 2 5724
Protoss_Assimilator 1 2960
Protoss_Zealot 3 4853
Protoss_Cybernetics_Core 1 4482
Protoss_Shield_Battery 1 4456
Protoss_Dragoon 7 10578
Protoss_Robotics_Facility 1 8308
Protoss_Shuttle 1 9447
Protoss_Robotics_Support_Bay 1 9268
Protoss_Reaver 1 10498
10578
