Protoss_Gateway 2 3599
Protoss_Zealot 9 6814
Protoss_Assimilator 1 5508
Protoss_Cybernetics_Core 1 6788
Protoss_Robotics_Facility 1 8313
Protoss_Shield_Battery 1 8109
Protoss_Dragoon 6 9976
Protoss_Shuttle 1 9591
Protoss_Robotics_Support_Bay 1 9341
Protoss_Reaver 1 10794
10794
