Protoss_Gateway 3 5325
Protoss_Zealot 9 7486
Protoss_Forge 2 5823
Protoss_Photon_Cannon 3 8605
Protoss_Assimilator 1 6788
Protoss_Cybernetics_Core 1 7478
Protoss_Dragoon 4 10380
Protoss_Citadel_of_Adun 1 9365
Protoss_Templar_Archives 1 10355
10380
