Protoss_Gateway 4 10848
Protoss_Zealot 7 7420
Protoss_Nexus 1 6661
Protoss_Shield_Battery 1 5786
Protoss_Assimilator 1 5994
Protoss_Forge 1 7724
Protoss_Cybernetics_Core 1 8189
Protoss_Photon_Cannon 2 8703
Protoss_Dragoon 7 10712
10848
