Protoss_Gateway 2 5791
Protoss_Assimilator 1 3095
Protoss_Zealot 2 4524
Protoss_Cybernetics_Core 1 4646
Protoss_Shield_Battery 1 4843
Protoss_Dragoon 4 10430
Protoss_Robotics_Facility 1 10507
10507
