Protoss_Gateway 3 9669
Protoss_Assimilator 1 3063
Protoss_Cybernetics_Core 1 4350
Protoss_Dragoon 3 10670
Protoss_Citadel_of_Adun 1 5506
Protoss_Templar_Archives 1 6899
Protoss_Zealot 4 10388
Protoss_Dark_Templar 2 9697
Protoss_High_Templar 2 8525
Protoss_Archon 1 9325
Protoss_Forge 1 9974
Psionic_Storm 1 9811
10670
