Protoss_Gateway 2 6648
Protoss_Zealot 4 6293
Protoss_Assimilator 1 4257
Protoss_Cybernetics_Core 1 5574
Protoss_Robotics_Facility 1 7655
Protoss_Dragoon 6 9845
Protoss_Robotics_Support_Bay 1 8216
Protoss_Reaver 1 9851
Protoss_Shuttle 1 10782
10782
