Protoss_Gateway 2 3674
Protoss_Zealot 7 6713
Protoss_Assimilator 1 4956
Protoss_Cybernetics_Core 1 6156
Protoss_Dragoon 1 7478
Protoss_Citadel_of_Adun 1 7944
Protoss_Templar_Archives 1 8969
Protoss_Dark_Templar 2 10098
Protoss_Forge 1 10312
10312
