Protoss_Nexus 2 11575
Protoss_Gateway 2 6270
Protoss_Assimilator 2 5734
Protoss_Cybernetics_Core 1 5604
Protoss_Robotics_Facility 1 7307
Protoss_Dragoon 6 9368
Protoss_Observatory 1 7871
Protoss_Shuttle 1 8717
Protoss_Robotics_Support_Bay 1 8436
Protoss_Observer 2 9922
Protoss_Forge 1 10379
11575
