Protoss_Gateway 2 5035
Protoss_Assimilator 1 3155
Protoss_Cybernetics_Core 1 4139
Protoss_Zealot 2 4928
Protoss_Dragoon 5 7285
Protoss_Citadel_of_Adun 1 7778
Protoss_Templar_Archives 1 9294
Protoss_Forge 1 9041
Protoss_Dark_Templar 2 10438
10438
