Protoss_Nexus 2 11151
Protoss_Assimilator 2 6112
Protoss_Gateway 3 8899
Protoss_Cybernetics_Core 1 5529
Protoss_Stargate 1 6753
Protoss_Citadel_of_Adun 1 6742
Protoss_Forge 1 6725
Protoss_Photon_Cannon 3 8220
Protoss_Corsair 2 8238
Protoss_Templar_Archives 1 8124
Protoss_Robotics_Facility 1 9598
Protoss_High_Templar 1 9308
Protoss_Shuttle 1 10622
Protoss_Robotics_Support_Bay 1 10280
11151
