Protoss_Gateway 3 9968
Protoss_Zealot 15 8653
Protoss_Assimilator 1 7065
Protoss_Cybernetics_Core 1 7654
Protoss_Citadel_of_Adun 1 9124
Protoss_Forge 1 9035
Protoss_Templar_Archives 1 10487
Protoss_Photon_Cannon 2 10709
10709
