Protoss_Gateway 2 9964
Protoss_Assimilator 1 3020
Protoss_Zealot 2 4338
Protoss_Cybernetics_Core 1 4989
Protoss_Dragoon 6 10663
Protoss_Robotics_Facility 1 6904
Protoss_Shuttle 1 7902
Protoss_Robotics_Support_Bay 1 7476
Protoss_Shield_Battery 1 8320
Protoss_Reaver 1 9016
10663
