Protoss_Gateway 2 4975
Protoss_Assimilator 1 3195
Protoss_Zealot 3 5913
Protoss_Cybernetics_Core 1 5254
Protoss_Dragoon 10 10317
Protoss_Robotics_Facility 1 8937
Protoss_Observatory 1 9517
Protoss_Shuttle 1 10057
10317
