Protoss_Assimilator 1 2220
Protoss_Gateway 3 10338
Protoss_Cybernetics_Core 1 4169
Protoss_Robotics_Facility 1 5562
Protoss_Dragoon 7 10293
Protoss_Shuttle 1 6687
Protoss_Observatory 1 6611
Protoss_Observer 1 7568
Protoss_Robotics_Support_Bay 1 7511
Protoss_Reaver 2 10041
10338
