Protoss_Assimilator 1 2393
Protoss_Gateway 3 8899
Protoss_Cybernetics_Core 1 4285
Protoss_Robotics_Facility 1 5635
Protoss_Dragoon 12 10683
Protoss_Shuttle 1 6662
Protoss_Observatory 1 6388
Protoss_Observer 2 8743
Protoss_Robotics_Support_Bay 1 9185
10683
