Protoss_Gateway 2 3584
Protoss_Zealot 11 8128
Protoss_Nexus 1 8885
Protoss_Assimilator 1 8085
Protoss_Forge 1 9050
Protoss_Cybernetics_Core 1 9403
Protoss_Photon_Cannon 2 10189
Protoss_Dragoon 2 10423
10423
