Protoss_Gateway 3 10749
Protoss_Zealot 5 5968
Protoss_Assimilator 1 4547
Protoss_Cybernetics_Core 1 5852
Protoss_Dragoon 6 8873
Protoss_Robotics_Facility 1 7872
Protoss_Observatory 1 9019
Protoss_Observer 1 9803
10749
