Protoss_Gateway 3 6882
Protoss_Zealot 9 9028
Protoss_Assimilator 1 5605
Protoss_Cybernetics_Core 1 6609
Protoss_Citadel_of_Adun 1 7845
Protoss_Templar_Archives 1 9058
Protoss_Dragoon 2 9498
Protoss_Dark_Templar 4 10698
10698
