Protoss_Gateway 3 8900
Protoss_Zealot 5 6128
Protoss_Assimilator 1 5111
Protoss_Cybernetics_Core 1 6005
Protoss_Dragoon 10 10580
Protoss_Robotics_Facility 1 9722
Protoss_Observatory 1 10380
10580
