Protoss_Gateway 2 3615
Protoss_Zealot 7 10288
Protoss_Assimilator 1 4603
Protoss_Cybernetics_Core 1 5859
Protoss_Dragoon 10 10514
Protoss_Robotics_Facility 1 8446
Protoss_Observatory 1 9113
Protoss_Observer 1 9838
10514
