Protoss_Gateway 3 9712
Protoss_Assimilator 1 2862
Protoss_Zealot 2 4558
Protoss_Cybernetics_Core 1 4499
Protoss_Dragoon 11 10598
Protoss_Robotics_Facility 1 7902
Protoss_Observatory 1 8501
Protoss_Observer 2 9795
10598
