Protoss_Gateway 3 8169
Protoss_Assimilator 1 2906
Protoss_Zealot 2 4613
Protoss_Cybernetics_Core 1 4625
Protoss_Dragoon 9 10533
Protoss_Robotics_Facility 1 6788
Protoss_Observatory 1 7380
Protoss_Observer 3 9297
Protoss_Nexus 1 11132
Protoss_Robotics_Support_Bay 1 10009
11132
