Protoss_Gateway 2 5554
Protoss_Assimilator 1 3059
Protoss_Zealot 3 4703
Protoss_Cybernetics_Core 1 4788
Protoss_Dragoon 11 10098
Protoss_Robotics_Facility 1 8382
Protoss_Observatory 1 8958
Protoss_Observer 1 9653
10098
