Protoss_Gateway 2 6190
Protoss_Zealot 9 10575
Protoss_Assimilator 1 3812
Protoss_Cybernetics_Core 1 4719
Protoss_Dragoon 2 6593
Protoss_Citadel_of_Adun 1 6344
Protoss_Templar_Archives 1 7334
Protoss_Forge 1 7414
Protoss_Dark_Templar 2 8183
Protoss_Photon_Cannon 2 8725
Protoss_High_Templar 2 9328
10575
