Protoss_Gateway 4 10557
Protoss_Assimilator 1 2950
Protoss_Zealot 2 4533
Protoss_Cybernetics_Core 1 4597
Protoss_Dragoon 10 10368
Protoss_Robotics_Facility 1 8279
Protoss_Nexus 1 10018
Protoss_Observatory 1 8997
10557
