Protoss_Gateway 1 2880
Protoss_Assimilator 1 3281
Protoss_Zealot 2 4813
Protoss_Cybernetics_Core 1 4697
Protoss_Dragoon 7 10237
Protoss_Robotics_Facility 1 6715
Protoss_Shuttle 1 7707
Protoss_Robotics_Support_Bay 1 7371
Protoss_Reaver 2 9926
Protoss_Observatory 1 10062
10237
