Protoss_Gateway 3 9224
Protoss_Assimilator 1 2840
Protoss_Cybernetics_Core 1 3909
Protoss_Robotics_Facility 1 5302
Protoss_Dragoon 7 10583
Protoss_Shuttle 1 6352
Protoss_Robotics_Support_Bay 1 6196
Protoss_Observatory 1 6664
Protoss_Reaver 2 9070
Protoss_Observer 2 10348
Protoss_Nexus 1 10935
10935
