Protoss_Assimilator 1 2407
Protoss_Gateway 1 3094
Protoss_Cybernetics_Core 1 4135
Protoss_Robotics_Facility 1 5427
Protoss_Zealot 2 5495
Protoss_Shuttle 1 6417
Protoss_Dragoon 6 10694
Protoss_Robotics_Support_Bay 1 6366
Protoss_Reaver 2 8743
Protoss_Forge 1 8784
Protoss_Observatory 1 9124
Protoss_Photon_Cannon 1 9785
Protoss_Observer 2 10410
10694
