Protoss_Gateway 2 5560
Protoss_Assimilator 1 2940
Protoss_Cybernetics_Core 1 3907
Protoss_Dragoon 11 10018
Protoss_Robotics_Facility 1 7593
Protoss_Zealot 1 7256
Protoss_Robotics_Support_Bay 1 8303
Protoss_Reaver 2 10608
Protoss_Nexus 1 10753
10753
