Protoss_Gateway 2 5272
Protoss_Assimilator 1 2950
Protoss_Cybernetics_Core 1 3901
Protoss_Dragoon 12 10486
Protoss_Robotics_Facility 1 7752
Protoss_Shuttle 1 8735
Protoss_Observatory 1 8327
Protoss_Robotics_Support_Bay 1 9165
Protoss_Observer 1 9402
Protoss_Reaver 1 10452
10486
