Protoss_Gateway 2 9331
Protoss_Zealot 6 8362
Protoss_Nexus 2 10489
Protoss_Assimilator 2 8156
Protoss_Cybernetics_Core 1 6844
Protoss_Dragoon 1 7760
Protoss_Citadel_of_Adun 1 8059
Protoss_Forge 1 8719
Protoss_Templar_Archives 1 9041
Protoss_Photon_Cannon 3 10020
Protoss_Dark_Templar 2 10172
Protoss_Robotics_Facility 1 10958
10958
