Protoss_Gateway 2 8921
Protoss_Zealot 5 6834
Protoss_Nexus 2 10473
Protoss_Assimilator 2 7986
Protoss_Cybernetics_Core 1 6484
Protoss_Citadel_of_Adun 1 7636
Protoss_Dragoon 1 7618
Protoss_Templar_Archives 1 8739
Protoss_Forge 1 9045
Protoss_Dark_Templar 2 9750
Protoss_Photon_Cannon 2 10048
Protoss_High_Templar 2 10502
Protoss_Robotics_Facility 1 11106
11106
