Protoss_Gateway 3 9759
Protoss_Zealot 2 5382
Protoss_Nexus 1 5299
Protoss_Assimilator 2 9421
Protoss_Cybernetics_Core 1 5391
Protoss_Dragoon 11 10424
Protoss_Shield_Battery 1 7876
Protoss_Robotics_Facility 1 9334
Protoss_Observatory 1 9997
Protoss_Forge 1 10367
10424
