Protoss_Gateway 2 6777
Protoss_Assimilator 1 2995
Protoss_Cybernetics_Core 1 3825
Protoss_Dragoon 7 10288
Protoss_Citadel_of_Adun 1 6237
Protoss_Templar_Archives 1 7479
Protoss_Forge 1 7760
Protoss_Dark_Templar 3 9302
Protoss_Nexus 1 10421
10421
