Protoss_Nexus 1 0
Protoss_Gateway 1 1679
Protoss_Zealot 3 4765
Protoss_Assimilator 1 3658
Protoss_Cybernetics_Core 1 4356
Protoss_Dragoon 1 5545
Protoss_Stargate 1 5625
Protoss_Robotics_Facility 1 6541
Protoss_Corsair 2 9403
Protoss_Shuttle 1 8245
9403
