Protoss_Nexus 2 3126
Protoss_Forge 1 3401
Protoss_Gateway 4 7269
Protoss_Assimilator 2 9366
Protoss_Photon_Cannon 2 9790
Protoss_Cybernetics_Core 1 5212
Protoss_Zealot 14 9695
Protoss_Citadel_of_Adun 1 6433
Protoss_Templar_Archives 1 9243
9790
