Protoss_Nexus 2 2697
Protoss_Forge 1 3778
Protoss_Gateway 4 9780
Protoss_Assimilator 2 6716
Protoss_Photon_Cannon 5 8841
Protoss_Cybernetics_Core 1 5697
Protoss_Zealot 3 8805
Protoss_Dragoon 2 7441
Protoss_Stargate 1 6927
Protoss_Citadel_of_Adun 1 7885
Protoss_Corsair 2 8657
Protoss_Templar_Archives 1 9449
9780
