Protoss_Nexus 1 0
Protoss_Gateway 2 2794
Protoss_Zealot 14 9211
Protoss_Assimilator 1 5647
Protoss_Cybernetics_Core 1 6545
Protoss_Dragoon 2 9581
Protoss_Robotics_Facility 1 8486
Protoss_Shuttle 1 9847
9847
