Protoss_Nexus 1 0
Protoss_Gateway 2 2245
Protoss_Zealot 17 8591
Protoss_Assimilator 1 5201
Protoss_Cybernetics_Core 1 7821
Protoss_Forge 1 8781
Protoss_Stargate 1 9212
Protoss_Photon_Cannon 1 9555
Protoss_Citadel_of_Adun 1 9997
9997
