Protoss_Nexus 3 6518
Protoss_Forge 1 2313
Protoss_Photon_Cannon 10 9467
Protoss_Gateway 1 4228
Protoss_Assimilator 2 7125
Protoss_Zealot 2 7216
Protoss_Cybernetics_Core 1 6587
Protoss_Stargate 2 8758
Protoss_Corsair 2 9631
Protoss_Robotics_Facility 1 9868
9868
