Protoss_Nexus 2 4463
Protoss_Forge 1 2158
Protoss_Photon_Cannon 2 3433
Protoss_Gateway 4 8168
Protoss_Assimilator 1 5008
Protoss_Zealot 7 9569
Protoss_Cybernetics_Core 1 5778
9569
