Protoss_Nexus 2 3374
Protoss_Forge 1 2236
Protoss_Photon_Cannon 2 4077
Protoss_Gateway 2 8420
Protoss_Assimilator 2 6671
Protoss_Cybernetics_Core 1 5558
Protoss_Zealot 3 8207
Protoss_Stargate 1 6771
Protoss_Citadel_of_Adun 1 7523
Protoss_Corsair 2 9115
Protoss_Templar_Archives 1 8615
9115
