Protoss_Nexus 2 3887
Protoss_Forge 1 2531
Protoss_Photon_Cannon 2 4107
Protoss_Gateway 3 9615
Protoss_Assimilator 3 9201
Protoss_Zealot 7 9803
Protoss_Cybernetics_Core 1 7777
Protoss_Dragoon 1 9051
Protoss_Citadel_of_Adun 1 9129
9803
