Protoss_Nexus 3 8797
Protoss_Forge 1 2585
Protoss_Photon_Cannon 7 9641
Protoss_Gateway 2 7683
Protoss_Zealot 3 7037
Protoss_Assimilator 2 8023
Protoss_Cybernetics_Core 1 6809
Protoss_Dragoon 1 7821
Protoss_Stargate 1 8221
Protoss_Corsair 1 9413
Protoss_Citadel_of_Adun 1 9919
9919
