Protoss_Nexus 1 0
Protoss_Gateway 2 2505
Protoss_Zealot 10 6057
Protoss_Assimilator 1 5095
Protoss_Cybernetics_Core 1 6645
Protoss_Dragoon 6 9907
Protoss_Robotics_Facility 1 7995
Protoss_Shuttle 1 9281
Protoss_Robotics_Support_Bay 1 9590
9907
