Protoss_Nexus 3 5833
Protoss_Forge 1 2679
Protoss_Photon_Cannon 3 8648
Protoss_Gateway 1 5238
Protoss_Assimilator 2 7114
Protoss_Cybernetics_Core 1 6825
Protoss_Zealot 4 9616
Protoss_Stargate 1 8041
Protoss_Robotics_Facility 1 8541
Protoss_Corsair 2 9901
Protoss_Robotics_Support_Bay 1 9868
9901
