Protoss_Nexus 2 5053
Protoss_Gateway 3 9945
Protoss_Zealot 10 9541
Protoss_Forge 1 3397
Protoss_Photon_Cannon 2 6083
Protoss_Assimilator 2 7374
Protoss_Cybernetics_Core 1 7070
Protoss_Stargate 1 8266
Protoss_Citadel_of_Adun 1 8864
Protoss_Corsair 1 9397
9945
