Protoss_Nexus 1 0
Protoss_Gateway 3 9851
Protoss_Assimilator 1 2324
Protoss_Cybernetics_Core 1 2931
Protoss_Zealot 5 9641
Protoss_Stargate 1 4204
Protoss_Dragoon 1 4493
Protoss_Corsair 2 6143
Protoss_Citadel_of_Adun 1 5802
Protoss_Templar_Archives 1 7127
Protoss_Forge 1 7602
Protoss_Dark_Templar 1 8107
Protoss_Photon_Cannon 1 8571
Protoss_High_Templar 1 8889
9851
