Protoss_Nexus 3 8837
Protoss_Forge 1 1847
Protoss_Photon_Cannon 7 9861
Protoss_Gateway 1 4866
Protoss_Assimilator 2 7197
Protoss_Cybernetics_Core 1 5872
Protoss_Dragoon 4 9535
Protoss_Stargate 1 7046
Protoss_Corsair 3 9717
9861
