Protoss_Nexus 2 3395
Protoss_Forge 1 2797
Protoss_Photon_Cannon 4 8586
Protoss_Gateway 3 9515
Protoss_Assimilator 2 7309
Protoss_Cybernetics_Core 1 6137
Protoss_Zealot 7 9911
Protoss_Stargate 1 7247
Protoss_Citadel_of_Adun 1 7679
Protoss_Corsair 2 9083
Protoss_Templar_Archives 1 8836
9911
