Protoss_Nexus 2 9381
Protoss_Gateway 1 1785
Protoss_Zealot 3 3991
Protoss_Assimilator 1 3212
Protoss_Cybernetics_Core 1 4362
Protoss_Stargate 1 5351
Protoss_Forge 1 5417
Protoss_Photon_Cannon 4 8706
Protoss_Corsair 3 8433
Protoss_Robotics_Facility 1 6700
Protoss_Citadel_of_Adun 1 8211
Protoss_Robotics_Support_Bay 1 9621
9621
