Protoss_Nexus 1 0
Protoss_Gateway 2 2605
Protoss_Zealot 9 7561
Protoss_Assimilator 1 3652
Protoss_Cybernetics_Core 1 4377
Protoss_Dragoon 1 5366
Protoss_Stargate 1 5786
Protoss_Corsair 1 7001
Protoss_Forge 1 7409
Protoss_Photon_Cannon 1 8514
Protoss_Citadel_of_Adun 1 8801
8801
