Protoss_Nexus 2 7747
Protoss_Gateway 3 9289
Protoss_Zealot 4 6017
Protoss_Assimilator 2 8750
Protoss_Cybernetics_Core 1 3909
Protoss_Stargate 1 4968
Protoss_Dragoon 1 5265
Protoss_Forge 1 6216
Protoss_Corsair 1 6313
Protoss_Photon_Cannon 1 7605
Protoss_Citadel_of_Adun 1 8007
Protoss_Templar_Archives 1 9090
9289
