Protoss_Nexus 2 2943
Protoss_Gateway 1 3328
Protoss_Forge 1 3708
Protoss_Photon_Cannon 1 4403
Protoss_Zealot 4 9746
Protoss_Assimilator 1 4868
Protoss_Cybernetics_Core 1 6227
Protoss_Robotics_Facility 1 9435
9746
