Protoss_Nexus 2 3576
Protoss_Forge 1 1990
Protoss_Photon_Cannon 5 9302
Protoss_Gateway 3 7983
Protoss_Assimilator 2 5860
Protoss_Cybernetics_Core 1 6194
Protoss_Robotics_Facility 1 7216
Protoss_Stargate 1 7328
Protoss_Citadel_of_Adun 1 7833
Protoss_Robotics_Support_Bay 1 8680
Protoss_Corsair 2 9551
Protoss_Reaver 1 9326
Protoss_Templar_Archives 1 9711
9711
