Protoss_Nexus 2 8548
Protoss_Gateway 2 7354
Protoss_Assimilator 1 2463
Protoss_Zealot 3 8116
Protoss_Cybernetics_Core 1 3919
Protoss_Dragoon 1 4911
Protoss_Stargate 1 5225
Protoss_Citadel_of_Adun 1 6059
Protoss_Corsair 1 6361
Protoss_Templar_Archives 1 7259
Protoss_Dark_Templar 1 9146
9146
