Protoss_Nexus 2 3432
Protoss_Forge 1 2076
Protoss_Gateway 4 9225
Protoss_Photon_Cannon 4 9950
Protoss_Assimilator 2 6616
Protoss_Zealot 3 7505
Protoss_Cybernetics_Core 1 5506
Protoss_Dragoon 1 6579
Protoss_Stargate 1 6652
Protoss_Citadel_of_Adun 1 7150
Protoss_Corsair 2 8669
Protoss_Templar_Archives 1 8333
Protoss_Robotics_Facility 1 9723
Protoss_Dark_Templar 1 9737
9950
