Protoss_Nexus 2 5084
Protoss_Gateway 4 9198
Protoss_Forge 1 2616
Protoss_Zealot 11 9806
Protoss_Photon_Cannon 3 7283
Protoss_Assimilator 2 8839
Protoss_Cybernetics_Core 1 6389
Protoss_Dragoon 1 7383
Protoss_Citadel_of_Adun 1 8336
9806
