Protoss_Nexus 1 0
Protoss_Gateway 2 2643
Protoss_Zealot 8 9231
Protoss_Assimilator 1 4740
Protoss_Forge 1 5895
Protoss_Cybernetics_Core 1 6547
Protoss_Photon_Cannon 1 7038
Protoss_Dragoon 1 7571
Protoss_Citadel_of_Adun 1 7592
9231
