Protoss_Nexus 2 3278
Protoss_Forge 1 2405
Protoss_Photon_Cannon 4 9678
Protoss_Gateway 3 8201
Protoss_Assimilator 2 6161
Protoss_Cybernetics_Core 1 5883
Protoss_Zealot 3 8029
Protoss_Stargate 1 6923
Protoss_Citadel_of_Adun 1 7323
Protoss_Corsair 3 9587
Protoss_Templar_Archives 1 8395
Protoss_Dark_Templar 2 9701
9701
