Protoss_Nexus 2 4101
Protoss_Forge 1 3077
Protoss_Photon_Cannon 4 9153
Protoss_Gateway 4 8409
Protoss_Assimilator 1 5122
Protoss_Zealot 10 9908
Protoss_Cybernetics_Core 1 5953
Protoss_Dragoon 1 7016
Protoss_Citadel_of_Adun 1 7462
9908
