Protoss_Nexus 1 0
Protoss_Gateway 3 6586
Protoss_Zealot 11 9898
Protoss_Assimilator 1 3968
Protoss_Cybernetics_Core 1 4873
Protoss_Citadel_of_Adun 1 5926
Protoss_Dragoon 1 5981
Protoss_Templar_Archives 1 7331
Protoss_Dark_Templar 2 9146
Protoss_High_Templar 2 9636
9898
