Protoss_Nexus 1 0
Protoss_Gateway 2 9219
Protoss_Assimilator 1 2543
Protoss_Zealot 3 7971
Protoss_Cybernetics_Core 1 3923
Protoss_Robotics_Facility 1 4934
Protoss_Dragoon 4 8911
Protoss_Shuttle 1 6291
Protoss_Robotics_Support_Bay 1 6653
Protoss_Reaver 2 8441
Protoss_Scarab 6 9975
9975
