Protoss_Nexus 2 4408
Protoss_Forge 1 2002
Protoss_Photon_Cannon 3 5368
Protoss_Gateway 2 7688
Protoss_Assimilator 2 7956
Protoss_Cybernetics_Core 1 5887
Protoss_Zealot 5 9645
Protoss_Dragoon 1 6886
Protoss_Citadel_of_Adun 1 7169
Protoss_Templar_Archives 1 8888
9645
