Protoss_Nexus 2 2723
Protoss_Forge 1 3285
Protoss_Gateway 1 4093
Protoss_Assimilator 2 5988
Protoss_Photon_Cannon 2 5128
Protoss_Cybernetics_Core 1 5587
Protoss_Zealot 5 9871
Protoss_Stargate 1 6736
Protoss_Robotics_Facility 1 7489
Protoss_Dragoon 1 7893
Protoss_Corsair 3 9110
Protoss_Shuttle 1 8791
Protoss_Robotics_Support_Bay 1 9101
Protoss_Reaver 1 9693
Protoss_Citadel_of_Adun 1 9782
9871
