Protoss_Nexus 2 3558
Protoss_Forge 1 2158
Protoss_Photon_Cannon 2 3873
Protoss_Gateway 5 9470
Protoss_Assimilator 1 5265
Protoss_Zealot 10 9771
Protoss_Cybernetics_Core 1 5963
Protoss_Citadel_of_Adun 1 7368
9771
