Protoss_Nexus 2 3568
Protoss_Forge 1 2030
Protoss_Photon_Cannon 6 9218
Protoss_Gateway 3 9638
Protoss_Assimilator 2 7684
Protoss_Zealot 4 8276
Protoss_Cybernetics_Core 1 7043
Protoss_Stargate 1 8121
Protoss_Citadel_of_Adun 1 8743
Protoss_Corsair 2 9858
Protoss_Templar_Archives 1 9913
9913
