Protoss_Nexus 2 3721
Protoss_Forge 2 9953
Protoss_Photon_Cannon 9 8499
Protoss_Gateway 1 4383
Protoss_Assimilator 2 6370
Protoss_Zealot 2 6619
Protoss_Cybernetics_Core 1 6095
Protoss_Stargate 1 7173
Protoss_Robotics_Facility 1 7817
Protoss_Corsair 1 8789
Protoss_Robotics_Support_Bay 1 9155
Protoss_Reaver 1 9699
9953
