Protoss_Nexus 1 0
Protoss_Gateway 2 2483
Protoss_Zealot 10 8201
Protoss_Assimilator 1 3654
Protoss_Cybernetics_Core 1 4893
Protoss_Dragoon 1 5881
Protoss_Stargate 1 6155
8201
