Protoss_Nexus 2 3731
Protoss_Forge 1 2037
Protoss_Photon_Cannon 8 9915
Protoss_Gateway 2 7811
Protoss_Assimilator 2 6812
Protoss_Zealot 2 7505
Protoss_Cybernetics_Core 1 5673
Protoss_Stargate 1 6747
Protoss_Citadel_of_Adun 1 7306
Protoss_Corsair 3 9973
Protoss_Templar_Archives 1 8403
Protoss_High_Templar 2 9551
9973
