Protoss_Nexus 1 0
Protoss_Gateway 1 2026
Protoss_Assimilator 1 2568
Protoss_Zealot 4 7571
Protoss_Cybernetics_Core 1 3948
Protoss_Dragoon 1 5043
Protoss_Robotics_Facility 1 6098
Protoss_Forge 1 6758
Protoss_Shuttle 1 7396
Protoss_Robotics_Support_Bay 1 7484
Protoss_Reaver 1 9242
9242
