Protoss_Nexus 2 4463
Protoss_Forge 1 2040
Protoss_Photon_Cannon 8 9850
Protoss_Gateway 4 9723
Protoss_Assimilator 2 8131
Protoss_Zealot 4 9273
Protoss_Cybernetics_Core 1 6995
Protoss_Stargate 1 7988
Protoss_Citadel_of_Adun 1 8234
Protoss_Corsair 1 9126
Protoss_Templar_Archives 1 9292
9850
