Protoss_Nexus 1 0
Protoss_Gateway 2 2213
Protoss_Zealot 11 8836
Protoss_Assimilator 1 4792
Protoss_Cybernetics_Core 1 6217
Protoss_Stargate 1 7310
Protoss_Dragoon 1 7641
Protoss_Citadel_of_Adun 1 8126
Protoss_Corsair 1 8451
8836
