Protoss_Nexus 1 0
Protoss_Gateway 1 1908
Protoss_Assimilator 1 2233
Protoss_Cybernetics_Core 1 2983
Protoss_Stargate 1 4026
Protoss_Dragoon 1 4341
Protoss_Corsair 4 8136
Protoss_Robotics_Facility 1 5608
Protoss_Forge 1 6317
Protoss_Shuttle 1 6911
Protoss_Photon_Cannon 3 9028
Protoss_Robotics_Support_Bay 1 7697
Protoss_Zealot 1 8911
Protoss_Reaver 1 8931
9028
