Protoss_Nexus 2 4124
Protoss_Forge 1 2303
Protoss_Photon_Cannon 3 9633
Protoss_Gateway 4 8101
Protoss_Assimilator 2 6359
Protoss_Zealot 2 6851
Protoss_Cybernetics_Core 1 5963
Protoss_Citadel_of_Adun 1 7001
Protoss_Dragoon 1 7476
Protoss_Templar_Archives 1 8213
Protoss_Dark_Templar 2 9251
Protoss_High_Templar 2 9241
Protoss_Robotics_Facility 1 9943
9943
