Protoss_Nexus 1 0
Protoss_Assimilator 1 1692
Protoss_Forge 1 2148
Protoss_Gateway 2 4073
Protoss_Photon_Cannon 3 8829
Protoss_Zealot 15 9089
Protoss_Cybernetics_Core 1 5735
Protoss_Citadel_of_Adun 1 6729
Protoss_Ground_Weapons_1 1 6941
Protoss_Templar_Archives 1 9321
9321
