Protoss_Nexus 2 3486
Protoss_Forge 1 2488
Protoss_Gateway 4 7577
Protoss_Assimilator 2 9488
Protoss_Photon_Cannon 1 4277
Protoss_Zealot 14 9911
Protoss_Cybernetics_Core 1 5663
Protoss_Citadel_of_Adun 1 6733
Protoss_Templar_Archives 1 9058
9911
