Protoss_Nexus 1 0
Protoss_Gateway 2 6444
Protoss_Assimilator 1 2522
Protoss_Cybernetics_Core 1 3188
Protoss_Zealot 10 8655
Protoss_Dragoon 1 4693
Protoss_Citadel_of_Adun 1 5609
Protoss_Templar_Archives 1 7958
Protoss_Forge 1 8845
Protoss_High_Templar 2 9257
Protoss_Photon_Cannon 1 9930
9930
