Protoss_Nexus 2 9327
Protoss_Gateway 3 9731
Protoss_Assimilator 1 2376
Protoss_Zealot 3 7626
Protoss_Cybernetics_Core 1 3387
Protoss_Stargate 1 4891
Protoss_Dragoon 2 7506
Protoss_Scout 1 6376
Protoss_Forge 1 6823
Protoss_Photon_Cannon 2 9179
Protoss_Citadel_of_Adun 1 9683
9731
