Protoss_Nexus 2 3155
Protoss_Forge 1 2349
Protoss_Photon_Cannon 6 9978
Protoss_Gateway 2 8159
Protoss_Assimilator 2 7976
Protoss_Cybernetics_Core 1 5296
Protoss_Zealot 3 8731
Protoss_Stargate 1 6444
Protoss_Citadel_of_Adun 1 6906
Protoss_Corsair 3 9227
Protoss_Templar_Archives 1 8061
Protoss_Dark_Templar 2 9507
9978
