Protoss_Nexus 2 4081
Protoss_Forge 1 1919
Protoss_Photon_Cannon 4 9619
Protoss_Gateway 1 4439
Protoss_Assimilator 2 6847
Protoss_Zealot 2 8705
Protoss_Cybernetics_Core 1 5707
Protoss_Stargate 1 6990
Protoss_Dragoon 1 7511
Protoss_Robotics_Facility 1 8052
Protoss_Corsair 1 8157
Protoss_Shuttle 1 9335
Protoss_Robotics_Support_Bay 1 9422
9619
