Protoss_Nexus 2 2753
Protoss_Forge 1 3101
Protoss_Photon_Cannon 2 3899
Protoss_Gateway 1 4387
Protoss_Zealot 3 7645
Protoss_Assimilator 2 6698
Protoss_Cybernetics_Core 1 6402
7645
