Protoss_Nexus 2 2763
Protoss_Gateway 4 7771
Protoss_Forge 1 3825
Protoss_Photon_Cannon 2 4577
Protoss_Zealot 14 9995
Protoss_Assimilator 2 5776
Protoss_Cybernetics_Core 1 6294
Protoss_Citadel_of_Adun 1 7513
Protoss_Templar_Archives 1 9379
9995
