Protoss_Nexus 1 0
Protoss_Gateway 3 9000
Protoss_Assimilator 1 2299
Protoss_Zealot 5 5731
Protoss_Cybernetics_Core 1 3889
Protoss_Stargate 1 5254
Protoss_Dragoon 7 9983
Protoss_Corsair 1 6579
9983
