Protoss_Nexus 2 3248
Protoss_Forge 1 2185
Protoss_Gateway 1 4213
Protoss_Photon_Cannon 2 4854
Protoss_Assimilator 1 5339
Protoss_Zealot 3 9261
Protoss_Cybernetics_Core 1 5776
9261
