Protoss_Nexus 2 7093
Protoss_Gateway 4 8312
Protoss_Zealot 15 9981
Protoss_Forge 1 4994
Protoss_Photon_Cannon 1 6221
Protoss_Assimilator 1 7608
Protoss_Cybernetics_Core 1 8678
Protoss_Citadel_of_Adun 1 9699
9981
