Protoss_Nexus 2 3699
Protoss_Forge 1 2390
Protoss_Photon_Cannon 4 8487
Protoss_Gateway 1 4645
Protoss_Assimilator 2 6382
Protoss_Cybernetics_Core 1 5722
Protoss_Zealot 4 9015
Protoss_Dragoon 1 6699
Protoss_Stargate 1 6920
Protoss_Robotics_Facility 1 7425
Protoss_Corsair 2 9279
Protoss_Citadel_of_Adun 1 8683
Protoss_Shuttle 1 8781
Protoss_Robotics_Support_Bay 1 9022
Protoss_Templar_Archives 1 9732
9732
