Protoss_Nexus 3 8253
Protoss_Assimilator 1 1731
Protoss_Forge 1 2227
Protoss_Photon_Cannon 3 8325
Protoss_Gateway 3 4454
Protoss_Zealot 13 8587
Protoss_Ground_Weapons_1 1 7021
8587
