Protoss_Nexus 2 3427
Protoss_Forge 1 2530
Protoss_Photon_Cannon 5 9960
Protoss_Gateway 1 4027
Protoss_Assimilator 2 5873
Protoss_Zealot 6 9475
Protoss_Cybernetics_Core 2 8881
Protoss_Stargate 1 6848
Protoss_Dragoon 1 7075
Protoss_Citadel_of_Adun 1 7440
9960
