Protoss_Nexus 2 4607
Protoss_Forge 1 2011
Protoss_Photon_Cannon 4 9461
Protoss_Gateway 4 9921
Protoss_Zealot 7 9793
Protoss_Assimilator 2 7718
Protoss_Cybernetics_Core 1 5861
Protoss_Citadel_of_Adun 1 6964
Protoss_Dragoon 1 7635
Protoss_Templar_Archives 1 8928
9921
