Protoss_Nexus 2 2779
Protoss_Gateway 3 9033
Protoss_Assimilator 2 7238
Protoss_Forge 1 4086
Protoss_Zealot 4 7549
Protoss_Photon_Cannon 2 6971
Protoss_Cybernetics_Core 1 5455
Protoss_Citadel_of_Adun 1 6702
Protoss_Templar_Archives 1 7775
Protoss_Dark_Templar 2 8823
Protoss_High_Templar 2 9575
9575
