Protoss_Nexus 2 7533
Protoss_Gateway 2 2275
Protoss_Zealot 13 6849
Protoss_Assimilator 1 8002
Protoss_Forge 1 8277
Protoss_Cybernetics_Core 1 8747
Protoss_Photon_Cannon 2 9562
Protoss_Stargate 1 9825
9825
