Protoss_Nexus 2 4078
Protoss_Forge 1 2034
Protoss_Photon_Cannon 3 4774
Protoss_Gateway 3 9335
Protoss_Assimilator 2 7148
Protoss_Zealot 5 9816
Protoss_Cybernetics_Core 1 6350
Protoss_Stargate 1 7440
Protoss_Citadel_of_Adun 1 8352
Protoss_Corsair 2 9616
Protoss_Templar_Archives 1 9475
9816
