Protoss_Nexus 2 3309
Protoss_Forge 1 1845
Protoss_Gateway 3 8650
Protoss_Zealot 11 9717
Protoss_Photon_Cannon 4 6999
Protoss_Assimilator 2 8266
Protoss_Cybernetics_Core 1 7112
Protoss_Citadel_of_Adun 1 8304
Protoss_Templar_Archives 1 9760
9760
