Protoss_Nexus 2 2838
Protoss_Gateway 4 9274
Protoss_Forge 1 3798
Protoss_Assimilator 2 5881
Protoss_Photon_Cannon 3 9588
Protoss_Zealot 8 9833
Protoss_Cybernetics_Core 1 5773
Protoss_Stargate 1 6775
Protoss_Citadel_of_Adun 1 6857
Protoss_Templar_Archives 1 7861
Protoss_Corsair 1 7985
Protoss_Robotics_Facility 1 8847
Protoss_Dark_Templar 2 9017
9833
