Protoss_Nexus 1 0
Protoss_Gateway 3 9289
Protoss_Assimilator 1 2183
Protoss_Zealot 9 9659
Protoss_Cybernetics_Core 1 3409
Protoss_Stargate 1 4723
Protoss_Corsair 2 6473
Protoss_Citadel_of_Adun 1 6925
Protoss_Templar_Archives 1 8073
Protoss_Forge 1 8733
9659
