Protoss_Nexus 2 2857
Protoss_Gateway 5 9959
Protoss_Forge 1 3961
Protoss_Assimilator 2 6562
Protoss_Zealot 6 9745
Protoss_Photon_Cannon 1 4731
Protoss_Cybernetics_Core 1 5811
Protoss_Stargate 1 6827
Protoss_Citadel_of_Adun 1 7182
Protoss_Corsair 3 9575
Protoss_Templar_Archives 1 8231
Protoss_Dark_Templar 1 9721
9959
