Protoss_Nexus 2 4001
Protoss_Forge 1 1939
Protoss_Photon_Cannon 4 9911
Protoss_Gateway 2 8337
Protoss_Assimilator 2 6494
Protoss_Zealot 5 8264
Protoss_Cybernetics_Core 1 5839
Protoss_Stargate 1 6892
Protoss_Citadel_of_Adun 1 7474
Protoss_Corsair 2 8685
Protoss_Templar_Archives 1 8524
Protoss_Robotics_Facility 1 9295
Protoss_Dark_Templar 2 9527
9911
