Protoss_Nexus 2 4589
Protoss_Forge 1 2017
Protoss_Photon_Cannon 3 5262
Protoss_Gateway 3 8080
Protoss_Zealot 11 9977
Protoss_Cybernetics_Core 1 5899
Protoss_Assimilator 2 8201
Protoss_Citadel_of_Adun 1 7304
Protoss_Templar_Archives 1 9763
9977
