Protoss_Nexus 2 3492
Protoss_Forge 1 2467
Protoss_Gateway 2 8785
Protoss_Photon_Cannon 4 9715
Protoss_Assimilator 2 7543
Protoss_Zealot 3 8079
Protoss_Cybernetics_Core 1 6351
Protoss_Stargate 1 7375
Protoss_Citadel_of_Adun 1 7823
Protoss_Corsair 2 9319
Protoss_Templar_Archives 1 8839
Protoss_Dark_Templar 2 9889
9889
