Protoss_Nexus 2 3244
Protoss_Forge 1 2137
Protoss_Photon_Cannon 2 3896
Protoss_Gateway 3 7944
Protoss_Assimilator 2 6352
Protoss_Zealot 6 8925
Protoss_Cybernetics_Core 1 5873
Protoss_Dragoon 1 6913
Protoss_Citadel_of_Adun 1 7093
Protoss_Templar_Archives 1 8715
Protoss_Robotics_Facility 1 9334
Protoss_Dark_Templar 2 9703
Protoss_High_Templar 2 9769
9769
