Protoss_Nexus 2 4035
Protoss_Forge 1 2062
Protoss_Photon_Cannon 2 3699
Protoss_Gateway 2 8025
Protoss_Assimilator 2 6939
Protoss_Cybernetics_Core 1 5417
Protoss_Zealot 3 7399
Protoss_Stargate 1 6492
Protoss_Citadel_of_Adun 1 7161
Protoss_Corsair 3 9811
Protoss_Templar_Archives 1 8183
Protoss_Robotics_Facility 1 8400
Protoss_Dark_Templar 2 9297
Protoss_Shuttle 1 9727
9811
