Protoss_Nexus 1 0
Protoss_Gateway 2 9655
Protoss_Zealot 9 9091
Protoss_Assimilator 1 3089
Protoss_Forge 1 4404
Protoss_Cybernetics_Core 1 6033
Protoss_Citadel_of_Adun 1 7294
Protoss_Photon_Cannon 5 9215
Protoss_Templar_Archives 1 8438
Protoss_Ground_Weapons_1 1 9083
Protoss_Robotics_Facility 1 9873
Protoss_Dark_Templar 1 9975
9975
