Protoss_Nexus 2 3914
Protoss_Forge 1 2293
Protoss_Photon_Cannon 6 9300
Protoss_Gateway 3 9863
Protoss_Assimilator 2 6894
Protoss_Cybernetics_Core 1 5751
Protoss_Zealot 6 9789
Protoss_Stargate 2 7381
Protoss_Citadel_of_Adun 1 7874
Protoss_Corsair 2 9477
Protoss_Templar_Archives 1 8962
9863
