Protoss_Nexus 2 3001
Protoss_Gateway 5 8892
Protoss_Forge 1 3463
Protoss_Photon_Cannon 2 9240
Protoss_Assimilator 1 5366
Protoss_Cybernetics_Core 1 5736
Protoss_Zealot 8 9151
Protoss_Stargate 1 6913
Protoss_Dragoon 1 7831
Protoss_Corsair 1 8176
Protoss_Citadel_of_Adun 1 8567
9240
