Protoss_Nexus 2 4481
Protoss_Forge 1 2297
Protoss_Photon_Cannon 5 9826
Protoss_Gateway 4 9853
Protoss_Assimilator 2 6313
Protoss_Cybernetics_Core 1 5946
Protoss_Zealot 3 8183
Protoss_Stargate 1 6954
Protoss_Dragoon 1 6957
Protoss_Citadel_of_Adun 1 7318
Protoss_Corsair 1 8093
Protoss_Templar_Archives 1 8365
Protoss_Dark_Templar 1 9343
Protoss_High_Templar 1 9983
9983
