Protoss_Nexus 2 4736
Protoss_Gateway 1 2007
Protoss_Zealot 11 9683
Protoss_Assimilator 2 9935
Protoss_Forge 1 5901
Protoss_Cybernetics_Core 1 6346
Protoss_Photon_Cannon 3 8694
Protoss_Stargate 1 7803
Protoss_Citadel_of_Adun 1 8844
Protoss_Corsair 1 8953
9935
