Protoss_Nexus 3 9889
Protoss_Forge 1 2213
Protoss_Photon_Cannon 2 4610
Protoss_Gateway 2 7398
Protoss_Assimilator 2 6087
Protoss_Zealot 2 6369
Protoss_Cybernetics_Core 1 5793
Protoss_Stargate 1 6791
Protoss_Citadel_of_Adun 1 7069
Protoss_Corsair 4 9834
Protoss_Templar_Archives 1 8065
Protoss_Dark_Templar 2 9247
9889
