Protoss_Nexus 2 3068
Protoss_Forge 1 3493
Protoss_Photon_Cannon 6 9846
Protoss_Gateway 1 4690
Protoss_Assimilator 2 6518
Protoss_Zealot 2 6288
Protoss_Cybernetics_Core 1 5943
Protoss_Stargate 1 7037
Protoss_Robotics_Facility 2 8753
Protoss_Corsair 1 8316
Protoss_Shuttle 1 9521
Protoss_Robotics_Support_Bay 1 9701
9846
