Protoss_Nexus 2 8153
Protoss_Gateway 2 2391
Protoss_Zealot 8 5201
Protoss_Assimilator 1 4831
Protoss_Cybernetics_Core 1 5617
Protoss_Stargate 1 6647
Protoss_Corsair 1 7777
Protoss_Forge 1 8493
Protoss_Citadel_of_Adun 1 9196
Protoss_Photon_Cannon 1 9935
9935
