Protoss_Nexus 2 3157
Protoss_Forge 1 3852
Protoss_Photon_Cannon 8 9704
Protoss_Gateway 1 5035
Protoss_Assimilator 2 7411
Protoss_Cybernetics_Core 1 6250
Protoss_Zealot 2 8505
Protoss_Stargate 1 7534
Protoss_Dragoon 2 8775
Protoss_Citadel_of_Adun 1 8128
Protoss_Corsair 2 9427
Protoss_Templar_Archives 1 9242
9704
