Protoss_Nexus 2 4668
Protoss_Forge 1 2181
Protoss_Gateway 2 9885
Protoss_Photon_Cannon 2 9620
Protoss_Zealot 6 9171
Protoss_Assimilator 2 5865
Protoss_Cybernetics_Core 1 5457
Protoss_Stargate 1 6765
Protoss_Citadel_of_Adun 1 7011
Protoss_Corsair 4 9795
Protoss_Templar_Archives 1 8909
Protoss_Dark_Templar 1 9909
9909
