Protoss_Nexus 2 3729
Protoss_Forge 1 2286
Protoss_Photon_Cannon 2 3983
Protoss_Gateway 6 8178
Protoss_Assimilator 2 9382
Protoss_Cybernetics_Core 1 5891
Protoss_Zealot 14 9841
Protoss_Dragoon 1 7199
Protoss_Citadel_of_Adun 1 7232
9841
