Protoss_Nexus 2 6461
Protoss_Gateway 2 2335
Protoss_Zealot 10 9395
Protoss_Shield_Battery 1 4448
Protoss_Forge 1 6949
Protoss_Assimilator 1 7257
Protoss_Photon_Cannon 2 8388
9395
