Protoss_Nexus 2 7961
Protoss_Gateway 3 9505
Protoss_Assimilator 1 2418
Protoss_Zealot 9 9831
Protoss_Cybernetics_Core 1 3738
Protoss_Stargate 1 5063
Protoss_Dragoon 1 5395
Protoss_Forge 1 6004
Protoss_Corsair 1 6521
Protoss_Photon_Cannon 2 9161
Protoss_Citadel_of_Adun 1 8530
9831
