Protoss_Nexus 2 3711
Protoss_Forge 1 2085
Protoss_Photon_Cannon 3 7805
Protoss_Gateway 3 9115
Protoss_Assimilator 2 6209
Protoss_Zealot 3 8651
Protoss_Cybernetics_Core 1 5835
Protoss_Stargate 1 7017
Protoss_Citadel_of_Adun 1 7473
Protoss_Corsair 1 8301
Protoss_Templar_Archives 1 8527
Protoss_Dark_Templar 1 9619
9619
