Protoss_Nexus 2 4414
Protoss_Forge 3 9554
Protoss_Photon_Cannon 4 5821
Protoss_Gateway 1 5009
Protoss_Assimilator 2 7517
Protoss_Cybernetics_Core 1 6565
Protoss_Zealot 4 9473
Protoss_Stargate 1 7939
Protoss_Citadel_of_Adun 2 9646
Protoss_Dragoon 1 8697
Protoss_Corsair 1 9501
9646
