Protoss_Nexus 2 3929
Protoss_Forge 1 2275
Protoss_Photon_Cannon 2 3163
Protoss_Gateway 6 8399
Protoss_Assimilator 2 6874
Protoss_Cybernetics_Core 1 5637
Protoss_Zealot 7 9409
Protoss_Dragoon 1 6725
Protoss_Citadel_of_Adun 1 7105
Protoss_Templar_Archives 1 9232
9409
