Protoss_Nexus 2 3398
Protoss_Forge 1 2214
Protoss_Photon_Cannon 2 4001
Protoss_Gateway 3 6368
Protoss_Zealot 11 9166
Protoss_Assimilator 2 8675
Protoss_Cybernetics_Core 1 8009
Protoss_Citadel_of_Adun 1 9048
Protoss_Robotics_Facility 1 9665
9665
