Protoss_Nexus 1 0
Protoss_Gateway 2 6242
Protoss_Assimilator 1 2433
Protoss_Zealot 8 7879
Protoss_Cybernetics_Core 1 3973
Protoss_Dragoon 1 5131
Protoss_Citadel_of_Adun 1 5574
Protoss_Templar_Archives 1 7173
Protoss_Forge 1 8312
Protoss_High_Templar 3 9395
Protoss_Photon_Cannon 1 9216
Protoss_Dark_Templar 1 9409
Protoss_Archon 1 9555
Protoss_Robotics_Facility 1 9857
9857
