Protoss_Nexus 2 3757
Protoss_Forge 1 2423
Protoss_Photon_Cannon 3 8023
Protoss_Gateway 1 4358
Protoss_Assimilator 2 5882
Protoss_Cybernetics_Core 1 5401
Protoss_Zealot 1 6053
Protoss_Stargate 1 6408
Protoss_Robotics_Facility 1 6971
Protoss_Corsair 4 9899
Protoss_Shuttle 1 8345
Protoss_Robotics_Support_Bay 1 8389
Protoss_Reaver 1 9395
9899
