Protoss_Nexus 2 4029
Protoss_Forge 1 2186
Protoss_Photon_Cannon 3 8942
Protoss_Gateway 4 9928
Protoss_Assimilator 2 6106
Protoss_Cybernetics_Core 1 5610
Protoss_Stargate 1 6747
Protoss_Zealot 2 7675
Protoss_Citadel_of_Adun 1 7270
Protoss_Corsair 3 9121
Protoss_Templar_Archives 1 8266
Protoss_Dark_Templar 2 9329
9928
