Protoss_Nexus 2 3215
Protoss_Forge 1 2785
Protoss_Photon_Cannon 4 8627
Protoss_Gateway 5 9504
Protoss_Assimilator 2 6366
Protoss_Cybernetics_Core 1 5632
Protoss_Zealot 3 7827
Protoss_Stargate 1 6631
Protoss_Citadel_of_Adun 1 7121
Protoss_Corsair 1 7787
Protoss_Templar_Archives 1 8175
Protoss_High_Templar 1 9181
Protoss_Dark_Templar 2 9213
9504
