Protoss_Nexus 2 4493
Protoss_Forge 1 2221
Protoss_Photon_Cannon 2 3111
Protoss_Gateway 2 8909
Protoss_Assimilator 2 7509
Protoss_Zealot 5 9163
Protoss_Cybernetics_Core 1 5977
Protoss_Stargate 1 7004
Protoss_Citadel_of_Adun 1 7679
9163
