Protoss_Nexus 2 4035
Protoss_Forge 1 2361
Protoss_Photon_Cannon 2 3719
Protoss_Gateway 1 4312
Protoss_Assimilator 2 6114
Protoss_Cybernetics_Core 1 5352
Protoss_Zealot 3 8887
Protoss_Stargate 1 6481
Protoss_Corsair 1 7615
Protoss_Citadel_of_Adun 1 7679
8887
