Protoss_Nexus 2 4014
Protoss_Forge 1 1893
Protoss_Photon_Cannon 4 9641
Protoss_Gateway 1 4540
Protoss_Assimilator 2 8334
Protoss_Zealot 4 8715
Protoss_Cybernetics_Core 1 7405
Protoss_Stargate 1 8571
Protoss_Citadel_of_Adun 1 9025
Protoss_Corsair 1 9747
9747
