Protoss_Nexus 2 3825
Protoss_Forge 1 2257
Protoss_Photon_Cannon 2 4225
Protoss_Gateway 1 4750
Protoss_Assimilator 2 6152
Protoss_Zealot 4 8025
Protoss_Cybernetics_Core 1 5829
Protoss_Stargate 1 6955
Protoss_Robotics_Facility 1 7289
Protoss_Corsair 3 9645
Protoss_Shuttle 1 8611
Protoss_Robotics_Support_Bay 1 8680
Protoss_Reaver 1 9513
9645
