Protoss_Nexus 2 3995
Protoss_Forge 1 2457
Protoss_Photon_Cannon 2 3407
Protoss_Gateway 6 8036
Protoss_Assimilator 2 6561
Protoss_Cybernetics_Core 1 5396
Protoss_Zealot 13 9905
Protoss_Dragoon 1 6431
Protoss_Citadel_of_Adun 1 7025
Protoss_Stargate 1 7524
Protoss_Templar_Archives 1 9258
9905
