Protoss_Nexus 3 9140
Protoss_Forge 1 2439
Protoss_Photon_Cannon 4 9713
Protoss_Gateway 1 5060
Protoss_Assimilator 2 7155
Protoss_Zealot 3 8637
Protoss_Cybernetics_Core 1 6503
Protoss_Stargate 1 7523
Protoss_Robotics_Facility 1 8289
Protoss_Corsair 3 9989
Protoss_Robotics_Support_Bay 1 9679
9989
