Protoss_Nexus 2 4053
Protoss_Forge 1 2007
Protoss_Photon_Cannon 4 9887
Protoss_Gateway 2 9142
Protoss_Assimilator 2 7425
Protoss_Zealot 3 7189
Protoss_Cybernetics_Core 1 6861
Protoss_Dragoon 1 8005
Protoss_Stargate 1 8078
Protoss_Citadel_of_Adun 1 8397
Protoss_Corsair 2 9813
Protoss_Templar_Archives 1 9511
9887
