Protoss_Nexus 2 4504
Protoss_Forge 1 2292
Protoss_Photon_Cannon 2 3583
Protoss_Gateway 1 4649
Protoss_Assimilator 2 7053
Protoss_Cybernetics_Core 1 5817
Protoss_Zealot 3 7586
Protoss_Stargate 1 6863
Protoss_Robotics_Facility 1 7752
Protoss_Corsair 4 9915
Protoss_Robotics_Support_Bay 1 9146
Protoss_Shuttle 1 9331
Protoss_Citadel_of_Adun 1 9838
9915
