Protoss_Nexus 2 3217
Protoss_Forge 1 2357
Protoss_Photon_Cannon 3 7024
Protoss_Gateway 3 9752
Protoss_Zealot 3 6559
Protoss_Assimilator 2 7856
Protoss_Cybernetics_Core 1 7294
Protoss_Citadel_of_Adun 1 8643
Protoss_Dragoon 2 9989
Protoss_Templar_Archives 1 9943
9989
