Protoss_Nexus 2 3239
Protoss_Forge 2 3659
Protoss_Gateway 3 7653
Protoss_Photon_Cannon 2 9153
Protoss_Assimilator 2 6215
Protoss_Zealot 3 7137
Protoss_Cybernetics_Core 1 6018
Protoss_Citadel_of_Adun 1 7198
9153
