Protoss_Nexus 2 3828
Protoss_Forge 1 2211
Protoss_Photon_Cannon 4 9998
Protoss_Gateway 3 9628
Protoss_Assimilator 2 7382
Protoss_Zealot 6 9377
Protoss_Cybernetics_Core 1 5714
Protoss_Stargate 1 7026
Protoss_Citadel_of_Adun 1 7840
Protoss_Dragoon 1 8023
Protoss_Corsair 1 8161
Protoss_Templar_Archives 1 9025
9998
