Protoss_Nexus 2 4415
Protoss_Forge 1 2265
Protoss_Photon_Cannon 2 3441
Protoss_Gateway 4 8645
Protoss_Zealot 15 9959
Protoss_Assimilator 2 8424
Protoss_Cybernetics_Core 1 6352
Protoss_Citadel_of_Adun 1 7433
Protoss_Templar_Archives 1 9565
9959
