Protoss_Nexus 2 2836
Protoss_Gateway 4 9269
Protoss_Forge 1 3908
Protoss_Assimilator 2 5215
Protoss_Photon_Cannon 3 8127
Protoss_Cybernetics_Core 1 4753
Protoss_Stargate 1 5924
Protoss_Zealot 2 7957
Protoss_Citadel_of_Adun 1 6337
Protoss_Corsair 2 7849
Protoss_Templar_Archives 1 7619
Protoss_Dark_Templar 2 8703
Protoss_High_Templar 2 9455
9455
