Protoss_Nexus 2 3485
Protoss_Forge 1 2170
Protoss_Photon_Cannon 2 9093
Protoss_Gateway 2 8054
Protoss_Assimilator 2 6155
Protoss_Zealot 6 8341
Protoss_Cybernetics_Core 1 5597
Protoss_Stargate 1 6705
Protoss_Citadel_of_Adun 1 7415
Protoss_Corsair 3 9245
Protoss_Templar_Archives 1 8611
9245
