Protoss_Nexus 3 9703
Protoss_Gateway 2 7109
Protoss_Forge 1 3760
Protoss_Assimilator 2 5702
Protoss_Photon_Cannon 5 9839
Protoss_Cybernetics_Core 1 4691
Protoss_Zealot 1 5225
Protoss_Stargate 1 5963
Protoss_Dragoon 1 6143
Protoss_Citadel_of_Adun 1 6648
Protoss_Corsair 3 8599
Protoss_Templar_Archives 1 7761
Protoss_Dark_Templar 2 8775
Protoss_High_Templar 2 9527
9839
