Protoss_Nexus 2 4417
Protoss_Forge 1 1914
Protoss_Photon_Cannon 5 9521
Protoss_Gateway 1 4795
Protoss_Assimilator 2 7260
Protoss_Zealot 6 9671
Protoss_Cybernetics_Core 1 6271
Protoss_Stargate 1 7353
Protoss_Citadel_of_Adun 1 7558
Protoss_Corsair 1 8485
Protoss_Templar_Archives 1 9043
9671
