Protoss_Nexus 1 0
Protoss_Gateway 2 8222
Protoss_Zealot 6 8601
Protoss_Assimilator 1 3442
Protoss_Cybernetics_Core 1 3981
Protoss_Stargate 1 5963
Protoss_Dragoon 1 6173
Protoss_Citadel_of_Adun 1 6836
Protoss_Corsair 1 7167
Protoss_Forge 1 7507
Protoss_Templar_Archives 1 7906
Protoss_Dark_Templar 2 9605
9605
