Protoss_Nexus 2 3351
Protoss_Forge 1 2096
Protoss_Gateway 3 7823
Protoss_Photon_Cannon 4 8641
Protoss_Assimilator 2 6347
Protoss_Cybernetics_Core 1 5570
Protoss_Zealot 1 5941
Protoss_Citadel_of_Adun 1 6939
Protoss_Stargate 1 7019
Protoss_Templar_Archives 1 7959
Protoss_Corsair 3 9839
Protoss_Dark_Templar 4 9763
9839
