Protoss_Nexus 2 2827
Protoss_Forge 1 3141
Protoss_Photon_Cannon 3 6429
Protoss_Gateway 1 4575
Protoss_Assimilator 2 6285
Protoss_Cybernetics_Core 1 5577
Protoss_Zealot 3 9241
Protoss_Stargate 1 6649
Protoss_Dragoon 1 6839
Protoss_Robotics_Facility 1 7568
Protoss_Corsair 4 9585
Protoss_Shuttle 1 8861
Protoss_Robotics_Support_Bay 1 9116
Protoss_Reaver 1 9763
9763
