Protoss_Nexus 2 3863
Protoss_Forge 1 2293
Protoss_Photon_Cannon 6 9837
Protoss_Gateway 3 9077
Protoss_Assimilator 2 7603
Protoss_Zealot 3 6495
Protoss_Cybernetics_Core 1 5559
Protoss_Dragoon 2 6885
Protoss_Stargate 1 6634
Protoss_Citadel_of_Adun 1 7231
Protoss_Corsair 1 7959
Protoss_Templar_Archives 1 8705
Protoss_Dark_Templar 2 9733
9837
