Protoss_Nexus 2 2909
Protoss_Gateway 6 9666
Protoss_Forge 1 3767
Protoss_Assimilator 2 6223
Protoss_Photon_Cannon 2 6768
Protoss_Zealot 6 8241
Protoss_Cybernetics_Core 1 6092
Protoss_Stargate 1 7176
Protoss_Citadel_of_Adun 1 7357
Protoss_Templar_Archives 1 8345
Protoss_Corsair 1 8833
Protoss_Dark_Templar 2 9333
Protoss_High_Templar 1 9803
Protoss_Ground_Weapons_1 1 9811
9811
