Protoss_Nexus 2 2736
Protoss_Gateway 1 3361
Protoss_Forge 1 3695
Protoss_Photon_Cannon 1 4383
Protoss_Assimilator 2 6043
Protoss_Zealot 5 8079
Protoss_Cybernetics_Core 1 5784
8079
