Protoss_Nexus 2 4467
Protoss_Gateway 4 9179
Protoss_Zealot 8 9897
Protoss_Assimilator 1 4771
Protoss_Cybernetics_Core 1 5093
Protoss_Stargate 1 6269
Protoss_Dragoon 1 7287
Protoss_Forge 1 7297
Protoss_Corsair 1 7423
Protoss_Citadel_of_Adun 1 8864
9897
