Protoss_Nexus 2 3702
Protoss_Forge 1 1921
Protoss_Photon_Cannon 1 3504
Protoss_Gateway 3 8947
Protoss_Assimilator 2 6776
Protoss_Zealot 6 9426
Protoss_Cybernetics_Core 1 5298
Protoss_Stargate 1 6351
Protoss_Citadel_of_Adun 1 8049
Protoss_Dragoon 1 8674
Protoss_Templar_Archives 1 9085
9426
