Protoss_Nexus 2 3603
Protoss_Forge 1 2197
Protoss_Photon_Cannon 3 4953
Protoss_Gateway 4 9424
Protoss_Assimilator 2 6605
Protoss_Cybernetics_Core 1 6013
Protoss_Zealot 2 8296
Protoss_Stargate 1 7014
Protoss_Dragoon 1 7101
Protoss_Citadel_of_Adun 1 7632
Protoss_Corsair 2 8780
Protoss_Templar_Archives 1 8632
Protoss_Dark_Templar 2 9626
9626
