Protoss_Nexus 2 3655
Protoss_Forge 1 2079
Protoss_Photon_Cannon 2 7735
Protoss_Gateway 3 9352
Protoss_Assimilator 2 5705
Protoss_Zealot 3 8877
Protoss_Cybernetics_Core 1 5108
Protoss_Stargate 1 6299
Protoss_Dragoon 1 7037
Protoss_Citadel_of_Adun 1 7450
Protoss_Corsair 3 9459
Protoss_Templar_Archives 1 8649
Protoss_Dark_Templar 1 9629
9629
