Protoss_Nexus 2 4522
Protoss_Forge 1 2540
Protoss_Photon_Cannon 2 3297
Protoss_Gateway 3 9387
Protoss_Assimilator 2 7375
Protoss_Zealot 7 9859
Protoss_Cybernetics_Core 1 5827
Protoss_Stargate 1 6837
Protoss_Robotics_Facility 1 7595
Protoss_Corsair 2 9835
Protoss_Shuttle 1 8969
9859
