Protoss_Nexus 2 8227
Protoss_Gateway 2 9602
Protoss_Zealot 10 9957
Protoss_Assimilator 1 2975
Protoss_Cybernetics_Core 1 3854
Protoss_Dragoon 1 4981
Protoss_Stargate 1 5181
Protoss_Forge 1 5391
Protoss_Citadel_of_Adun 1 5886
Protoss_Corsair 1 6311
Protoss_Photon_Cannon 1 7247
Protoss_Robotics_Facility 1 8775
Protoss_Templar_Archives 1 9971
9971
