Protoss_Nexus 2 8578
Protoss_Gateway 3 5306
Protoss_Assimilator 2 7216
Protoss_Zealot 11 7749
Protoss_Forge 1 3327
Protoss_Photon_Cannon 2 9548
Protoss_Ground_Weapons_1 1 8016
Protoss_Cybernetics_Core 1 9067
9548
