Protoss_Nexus 2 3223
Protoss_Forge 1 1980
Protoss_Photon_Cannon 2 4373
Protoss_Gateway 5 9862
Protoss_Assimilator 2 6296
Protoss_Cybernetics_Core 1 5765
Protoss_Zealot 3 8422
Protoss_Stargate 1 6772
Protoss_Citadel_of_Adun 1 7327
Protoss_Dragoon 1 7670
Protoss_Corsair 1 7899
Protoss_Templar_Archives 1 8439
Protoss_High_Templar 2 9571
9862
