Protoss_Nexus 2 4873
Protoss_Forge 1 2198
Protoss_Photon_Cannon 6 9551
Protoss_Gateway 3 9193
Protoss_Assimilator 2 7429
Protoss_Cybernetics_Core 1 6241
Protoss_Zealot 5 9637
Protoss_Stargate 1 7299
Protoss_Citadel_of_Adun 1 7872
Protoss_Corsair 2 9067
Protoss_Templar_Archives 1 8863
Protoss_Dark_Templar 1 9841
9841
