Protoss_Nexus 1 0
Protoss_Gateway 1 2463
Protoss_Assimilator 1 2702
Protoss_Zealot 10 9766
Protoss_Forge 1 3718
Protoss_Photon_Cannon 4 9708
Protoss_Ground_Weapons_1 1 9866
9866
