Protoss_Nexus 2 3658
Protoss_Forge 1 2053
Protoss_Photon_Cannon 6 9927
Protoss_Gateway 4 8959
Protoss_Assimilator 2 7519
Protoss_Zealot 8 9275
Protoss_Cybernetics_Core 1 6075
Protoss_Citadel_of_Adun 1 7128
Protoss_Templar_Archives 1 8702
Protoss_High_Templar 2 9855
Protoss_Dark_Templar 1 9877
9927
