Protoss_Nexus 2 3118
Protoss_Forge 1 2165
Protoss_Gateway 4 7405
Protoss_Photon_Cannon 1 4338
Protoss_Assimilator 2 8831
Protoss_Zealot 17 9977
Protoss_Cybernetics_Core 1 5253
Protoss_Stargate 1 6266
Protoss_Citadel_of_Adun 1 7016
Protoss_Corsair 1 7541
Protoss_Templar_Archives 1 9317
9977
