Protoss_Nexus 2 2898
Protoss_Forge 1 3433
Protoss_Photon_Cannon 2 5293
Protoss_Gateway 3 5692
Protoss_Assimilator 2 8732
Protoss_Zealot 9 8311
Protoss_Cybernetics_Core 1 7853
Protoss_Citadel_of_Adun 1 8972
8972
