Protoss_Nexus 3 8446
Protoss_Gateway 4 9099
Protoss_Forge 2 9968
Protoss_Assimilator 2 7919
Protoss_Photon_Cannon 1 4860
Protoss_Cybernetics_Core 1 5418
Protoss_Zealot 10 9455
Protoss_Dragoon 1 6521
Protoss_Citadel_of_Adun 1 6711
Protoss_Templar_Archives 1 8677
Protoss_Ground_Weapons_1 1 9751
9968
