Protoss_Nexus 2 4723
Protoss_Forge 1 2885
Protoss_Photon_Cannon 3 5605
Protoss_Gateway 4 9243
Protoss_Assimilator 2 9951
Protoss_Cybernetics_Core 1 6079
Protoss_Zealot 7 9577
Protoss_Stargate 1 7181
Protoss_Citadel_of_Adun 1 7512
Protoss_Corsair 1 8309
Protoss_Templar_Archives 1 9864
9951
