Protoss_Nexus 2 3235
Protoss_Forge 1 2239
Protoss_Photon_Cannon 6 9795
Protoss_Gateway 6 9307
Protoss_Zealot 4 8109
Protoss_Assimilator 2 6786
Protoss_Cybernetics_Core 1 6588
Protoss_Citadel_of_Adun 1 7728
Protoss_Templar_Archives 1 8718
Protoss_High_Templar 4 9869
9869
