Protoss_Nexus 2 3497
Protoss_Forge 1 2291
Protoss_Gateway 1 3993
Protoss_Assimilator 2 5823
Protoss_Photon_Cannon 4 9125
Protoss_Cybernetics_Core 1 5085
Protoss_Zealot 2 7769
Protoss_Stargate 1 6326
Protoss_Dragoon 1 6547
Protoss_Robotics_Facility 1 7074
Protoss_Corsair 4 9519
Protoss_Robotics_Support_Bay 1 8684
Protoss_Citadel_of_Adun 1 9359
9519
