Protoss_Nexus 2 3957
Protoss_Forge 1 2507
Protoss_Photon_Cannon 4 8115
Protoss_Gateway 3 9513
Protoss_Assimilator 2 6278
Protoss_Cybernetics_Core 1 5643
Protoss_Zealot 6 9687
Protoss_Citadel_of_Adun 1 7343
Protoss_Templar_Archives 1 8472
9687
