Protoss_Nexus 2 9981
Protoss_Gateway 2 5971
Protoss_Assimilator 1 2499
Protoss_Zealot 8 8607
Protoss_Cybernetics_Core 1 4247
Protoss_Dragoon 1 5465
Protoss_Citadel_of_Adun 1 5549
Protoss_Templar_Archives 1 6541
Protoss_Forge 1 7687
Protoss_High_Templar 4 9209
Protoss_Archon 1 8676
Protoss_Photon_Cannon 4 9426
9981
