Protoss_Nexus 2 3191
Protoss_Forge 1 2742
Protoss_Photon_Cannon 2 4484
Protoss_Gateway 4 9136
Protoss_Assimilator 2 6476
Protoss_Cybernetics_Core 1 5971
Protoss_Zealot 4 9999
Protoss_Stargate 1 6994
Protoss_Citadel_of_Adun 1 7157
Protoss_Dragoon 1 7943
Protoss_Corsair 2 9409
Protoss_Templar_Archives 1 8388
Protoss_High_Templar 2 9995
9999
