Protoss_Nexus 1 0
Protoss_Gateway 3 9970
Protoss_Assimilator 1 2218
Protoss_Cybernetics_Core 1 2875
Protoss_Zealot 7 7551
Protoss_Stargate 1 4015
Protoss_Corsair 1 5247
Protoss_Citadel_of_Adun 1 7112
Protoss_Forge 1 7891
Protoss_Templar_Archives 1 8118
Protoss_Photon_Cannon 1 8727
9970
