Protoss_Nexus 1 0
Protoss_Gateway 2 2496
Protoss_Zealot 11 8469
Protoss_Assimilator 1 4735
Protoss_Cybernetics_Core 1 5691
Protoss_Citadel_of_Adun 1 6909
Protoss_Dragoon 1 7017
Protoss_Templar_Archives 1 8157
Protoss_Forge 1 8760
Protoss_Dark_Templar 1 9187
Protoss_Photon_Cannon 1 9867
9867
