Protoss_Nexus 2 3131
Protoss_Forge 1 2168
Protoss_Photon_Cannon 2 4135
Protoss_Gateway 4 8823
Protoss_Assimilator 2 6093
Protoss_Zealot 5 9621
Protoss_Cybernetics_Core 1 5619
Protoss_Dragoon 1 6663
Protoss_Stargate 1 6739
Protoss_Citadel_of_Adun 1 7124
Protoss_Corsair 1 7965
Protoss_Templar_Archives 1 8434
Protoss_High_Templar 2 9917
9917
