Protoss_Nexus 1 0
Protoss_Gateway 3 8694
Protoss_Zealot 9 8857
Protoss_Assimilator 2 4139
Protoss_Cybernetics_Core 1 4949
Protoss_Stargate 1 6105
Protoss_Citadel_of_Adun 1 6672
Protoss_Corsair 1 7765
Protoss_Templar_Archives 1 8120
Protoss_Forge 1 8421
Protoss_Dark_Templar 2 9759
9759
