Protoss_Nexus 2 5599
Protoss_Gateway 2 6700
Protoss_Zealot 10 9391
Protoss_Forge 1 4412
Protoss_Photon_Cannon 2 8759
Protoss_Assimilator 1 6108
Protoss_Cybernetics_Core 1 7622
Protoss_Robotics_Facility 1 8917
Protoss_Citadel_of_Adun 1 9010
Protoss_Dragoon 1 9928
9928
