Protoss_Nexus 1 0
Protoss_Gateway 3 9838
Protoss_Assimilator 1 2685
Protoss_Zealot 11 9551
Protoss_Cybernetics_Core 1 5162
Protoss_Citadel_of_Adun 1 6362
Protoss_Dragoon 1 6530
Protoss_Templar_Archives 1 8753
Protoss_Forge 1 9961
9961
