Protoss_Nexus 1 0
Protoss_Gateway 1 2003
Protoss_Assimilator 1 2541
Protoss_Cybernetics_Core 1 3068
Protoss_Zealot 3 7681
Protoss_Stargate 1 4203
Protoss_Dragoon 1 4371
7681
