Protoss_Nexus 1 0
Protoss_Assimilator 1 1775
Protoss_Forge 1 2589
Protoss_Gateway 3 4803
Protoss_Photon_Cannon 2 8483
Protoss_Zealot 8 7181
Protoss_Cybernetics_Core 1 6892
Protoss_Ground_Weapons_1 1 7276
Protoss_Dragoon 6 9906
9906
