Protoss_Nexus 2 3231
Protoss_Forge 1 2516
Protoss_Photon_Cannon 5 9895
Protoss_Gateway 3 7166
Protoss_Assimilator 2 6385
Protoss_Zealot 11 9525
Protoss_Cybernetics_Core 1 5539
Protoss_Dragoon 2 8163
Protoss_Citadel_of_Adun 1 6735
Protoss_Templar_Archives 1 8808
9895
