Protoss_Nexus 2 3275
Protoss_Forge 1 2390
Protoss_Photon_Cannon 4 9733
Protoss_Gateway 3 9185
Protoss_Assimilator 2 7908
Protoss_Zealot 4 9345
Protoss_Cybernetics_Core 1 6364
Protoss_Stargate 1 7406
Protoss_Dragoon 1 7585
Protoss_Citadel_of_Adun 1 7848
Protoss_Corsair 1 8535
Protoss_Templar_Archives 1 8952
Protoss_Dark_Templar 1 9947
Protoss_High_Templar 1 9947
9947
