Protoss_Nexus 1 0
Protoss_Gateway 2 8190
Protoss_Zealot 12 9936
Protoss_Forge 1 2891
Protoss_Photon_Cannon 3 4107
Protoss_Assimilator 1 4357
Protoss_Cybernetics_Core 1 6710
Protoss_Dragoon 1 7701
Protoss_Citadel_of_Adun 1 7788
Protoss_Ground_Weapons_1 1 9896
9936
