Protoss_Nexus 1 0
Protoss_Gateway 1 2113
Protoss_Assimilator 1 2553
Protoss_Zealot 8 9591
Protoss_Cybernetics_Core 1 3783
Protoss_Robotics_Facility 1 5192
Protoss_Dragoon 1 5376
Protoss_Shuttle 2 9881
Protoss_Robotics_Support_Bay 1 6772
Protoss_Shield_Battery 1 7253
Protoss_Reaver 2 8600
Protoss_Citadel_of_Adun 1 8742
Protoss_Scarab 3 9890
9890
