Protoss_Nexus 1 0
Protoss_Gateway 2 7308
Protoss_Assimilator 1 2472
Protoss_Zealot 6 7696
Protoss_Cybernetics_Core 1 4323
Protoss_Dragoon 1 5376
Protoss_Citadel_of_Adun 1 5568
Protoss_Templar_Archives 1 6760
Protoss_Dark_Templar 1 7751
Protoss_Forge 1 8032
Protoss_Robotics_Facility 1 8582
Protoss_Photon_Cannon 2 9198
Protoss_High_Templar 2 9546
9546
