Special_Protoss_Temple 30 0
Protoss_Nexus 2 3383
Protoss_Forge 1 2656
Protoss_Photon_Cannon 6 9888
Protoss_Gateway 1 4259
Protoss_Zealot 4 8237
Protoss_Assimilator 2 9411
Protoss_Cybernetics_Core 1 6680
Protoss_Stargate 1 7759
Protoss_Dragoon 1 8839
Protoss_Corsair 2 9619
Protoss_Robotics_Facility 1 9374
9888
