Special_Protoss_Temple 30 0
Protoss_Nexus 2 4317
Protoss_Forge 1 1901
Protoss_Photon_Cannon 4 9757
Protoss_Gateway 2 8474
Protoss_Assimilator 2 7065
Protoss_Cybernetics_Core 1 5712
Protoss_Zealot 4 8721
Protoss_Dragoon 1 6765
Protoss_Stargate 1 6868
Protoss_Citadel_of_Adun 1 7606
Protoss_Corsair 2 9771
Protoss_Templar_Archives 1 8957
9771
