Special_Protoss_Temple 30 0
Protoss_Nexus 2 4135
Protoss_Forge 1 2326
Protoss_Photon_Cannon 4 8449
Protoss_Gateway 3 9994
Protoss_Assimilator 2 6612
Protoss_Zealot 5 9453
Protoss_Cybernetics_Core 1 6061
Protoss_Stargate 1 7074
Protoss_Dragoon 1 7295
Protoss_Corsair 2 9045
Protoss_Citadel_of_Adun 1 8554
Protoss_Templar_Archives 1 9632
9994
