Protoss_Nexus 2 8515
Protoss_Gateway 2 5539
Protoss_Assimilator 1 2503
Protoss_Zealot 10 9475
Protoss_Cybernetics_Core 1 3429
Protoss_Dragoon 1 4475
Protoss_Citadel_of_Adun 1 4831
Protoss_Templar_Archives 1 6645
Protoss_High_Templar 4 8723
Protoss_Forge 1 8653
Protoss_Archon 2 9534
Protoss_Photon_Cannon 2 9846
9846
