Protoss_Nexus 2 4007
Protoss_Forge 1 2222
Protoss_Photon_Cannon 4 9787
Protoss_Gateway 2 8775
Protoss_Assimilator 2 7237
Protoss_Zealot 6 9961
Protoss_Cybernetics_Core 1 5610
Protoss_Stargate 1 6898
Protoss_Citadel_of_Adun 1 7097
Protoss_Corsair 2 9015
Protoss_Templar_Archives 1 9577
9961
