Protoss_Nexus 2 9345
Protoss_Gateway 2 2610
Protoss_Zealot 10 7735
Protoss_Assimilator 1 4659
Protoss_Cybernetics_Core 1 5579
Protoss_Citadel_of_Adun 1 6868
Protoss_Stargate 1 7246
Protoss_Dragoon 1 7323
Protoss_Templar_Archives 1 8121
Protoss_Corsair 1 8385
Protoss_Forge 1 8642
Protoss_Dark_Templar 2 9863
9863
