Protoss_Nexus 2 4131
Protoss_Forge 1 2173
Protoss_Photon_Cannon 4 9728
Protoss_Gateway 3 9994
Protoss_Assimilator 2 7331
Protoss_Zealot 7 9669
Protoss_Cybernetics_Core 1 6542
Protoss_Stargate 1 7793
Protoss_Citadel_of_Adun 1 8309
Protoss_Corsair 2 9815
9994
