Protoss_Nexus 2 2825
Special_Protoss_Temple 30 0
Protoss_Forge 1 3249
Protoss_Gateway 2 9402
Protoss_Photon_Cannon 7 9213
Protoss_Assimilator 2 6587
Protoss_Zealot 4 8217
Protoss_Cybernetics_Core 1 5407
Protoss_Stargate 1 6570
Protoss_Citadel_of_Adun 1 7153
Protoss_Dragoon 1 7465
Protoss_Corsair 4 9659
Protoss_Templar_Archives 1 8573
Protoss_High_Templar 1 9825
Protoss_Dark_Templar 1 9953
9953
