Protoss_Nexus 2 9818
Protoss_Gateway 2 8498
Protoss_Assimilator 1 2350
Protoss_Zealot 7 9521
Protoss_Cybernetics_Core 1 3717
Protoss_Stargate 1 4739
Protoss_Dragoon 1 4977
Protoss_Citadel_of_Adun 1 5339
Protoss_Corsair 1 5895
Protoss_Templar_Archives 1 6487
Protoss_Forge 1 7131
Protoss_Dark_Templar 2 8239
Protoss_Photon_Cannon 3 9894
9894
