Special_Protoss_Temple 30 0
Protoss_Nexus 2 3767
Protoss_Forge 1 2165
Protoss_Photon_Cannon 6 9560
Protoss_Gateway 4 9910
Protoss_Assimilator 2 7305
Protoss_Cybernetics_Core 1 5818
Protoss_Zealot 4 9301
Protoss_Stargate 1 6813
Protoss_Citadel_of_Adun 1 7133
Protoss_Corsair 1 7965
Protoss_Templar_Archives 1 9314
9910
