Protoss_Nexus 2 3181
Protoss_Forge 1 2064
Protoss_Photon_Cannon 4 8786
Protoss_Gateway 2 9230
Protoss_Assimilator 2 8623
Protoss_Zealot 5 9867
Protoss_Cybernetics_Core 1 6290
Protoss_Stargate 1 7283
Protoss_Citadel_of_Adun 1 7483
Protoss_Dragoon 1 7933
Protoss_Corsair 1 8575
Protoss_Templar_Archives 1 9064
9867
