Special_Protoss_Temple 30 0
Protoss_Nexus 2 4277
Protoss_Forge 1 2473
Protoss_Photon_Cannon 4 9781
Protoss_Gateway 3 9467
Protoss_Assimilator 2 7605
Protoss_Zealot 1 6629
Protoss_Cybernetics_Core 1 7005
Protoss_Stargate 1 7993
Protoss_Citadel_of_Adun 1 8500
Protoss_Corsair 2 9853
Protoss_Templar_Archives 1 9669
9853
