Protoss_Nexus 2 7175
Protoss_Gateway 2 5416
Protoss_Zealot 5 6873
Protoss_Assimilator 1 3075
Protoss_Cybernetics_Core 1 3819
Protoss_Dragoon 1 4811
Protoss_Citadel_of_Adun 1 5089
Protoss_Templar_Archives 1 6275
Protoss_High_Templar 4 9077
Protoss_Forge 1 7737
Protoss_Archon 1 8277
Protoss_Photon_Cannon 6 9919
9919
