Protoss_Nexus 2 3219
Protoss_Forge 1 2375
Protoss_Photon_Cannon 2 3781
Protoss_Assimilator 2 6108
Protoss_Gateway 2 8767
Protoss_Zealot 5 8613
Protoss_Cybernetics_Core 1 5383
Protoss_Dragoon 1 6363
Protoss_Stargate 1 6559
Protoss_Citadel_of_Adun 1 7644
Protoss_Corsair 4 9663
Protoss_Templar_Archives 1 8754
Protoss_Dark_Templar 2 9779
9779
