Protoss_Nexus 2 4005
Protoss_Forge 2 9816
Protoss_Photon_Cannon 5 9701
Protoss_Gateway 2 7655
Protoss_Assimilator 2 6601
Protoss_Cybernetics_Core 1 5285
Protoss_Zealot 5 8731
Protoss_Stargate 1 6283
Protoss_Citadel_of_Adun 1 7165
Protoss_Corsair 3 9593
Protoss_Templar_Archives 1 9073
9816
