Protoss_Nexus 2 4091
Protoss_Forge 1 2170
Protoss_Photon_Cannon 4 9978
Protoss_Gateway 3 9695
Protoss_Assimilator 2 6986
Protoss_Zealot 3 9373
Protoss_Cybernetics_Core 1 5515
Protoss_Stargate 1 6616
Protoss_Citadel_of_Adun 1 7369
Protoss_Dragoon 1 7661
Protoss_Corsair 3 9239
Protoss_Templar_Archives 1 9137
9978
