Protoss_Nexus 2 3068
Protoss_Forge 3 4311
Protoss_Gateway 3 8864
Protoss_Assimilator 1 4929
Protoss_Zealot 12 9773
Protoss_Photon_Cannon 2 9129
Protoss_Cybernetics_Core 1 6989
Protoss_Stargate 1 8334
Protoss_Citadel_of_Adun 1 8457
Protoss_Corsair 1 9825
9825
