Protoss_Nexus 2 3246
Protoss_Forge 1 2470
Protoss_Photon_Cannon 4 9781
Protoss_Gateway 4 9452
Protoss_Assimilator 2 6768
Protoss_Cybernetics_Core 1 5621
Protoss_Zealot 3 8239
Protoss_Dragoon 1 6621
Protoss_Stargate 1 6642
Protoss_Citadel_of_Adun 1 6983
Protoss_Corsair 2 8529
Protoss_Templar_Archives 1 8014
Protoss_Dark_Templar 2 9325
9781
