Protoss_Nexus 2 8288
Protoss_Gateway 1 2161
Protoss_Assimilator 1 2866
Protoss_Zealot 3 4536
Protoss_Cybernetics_Core 1 4190
Protoss_Citadel_of_Adun 1 5516
Protoss_Dragoon 1 5696
Protoss_Forge 1 6153
Protoss_Templar_Archives 1 6646
Protoss_Photon_Cannon 3 9548
Protoss_High_Templar 2 9793
9793
