Protoss_Nexus 2 4068
Protoss_Forge 1 2178
Protoss_Photon_Cannon 3 9132
Protoss_Gateway 1 4367
Protoss_Assimilator 2 6540
Protoss_Cybernetics_Core 1 5363
Protoss_Zealot 1 5447
Protoss_Stargate 1 6353
Protoss_Dragoon 2 8541
Protoss_Robotics_Facility 1 7421
Protoss_Corsair 4 9877
Protoss_Shuttle 1 8771
Protoss_Robotics_Support_Bay 1 8974
Protoss_Reaver 1 9673
9877
