Protoss_Nexus 2 8269
Protoss_Gateway 1 1880
Protoss_Assimilator 2 9900
Protoss_Zealot 3 5649
Protoss_Cybernetics_Core 1 3850
Protoss_Stargate 1 4846
Protoss_Dragoon 1 4897
Protoss_Citadel_of_Adun 1 5361
Protoss_Corsair 1 6113
Protoss_Templar_Archives 1 6618
Protoss_Forge 1 7207
Protoss_Dark_Templar 1 7803
Protoss_High_Templar 2 9537
Protoss_Photon_Cannon 3 9711
9900
