Protoss_Nexus 1 0
Protoss_Gateway 2 9155
Protoss_Assimilator 1 2455
Protoss_Zealot 5 9477
Protoss_Cybernetics_Core 1 4031
Protoss_Dragoon 1 5023
Protoss_Robotics_Facility 1 5293
Protoss_Forge 1 6557
Protoss_Shuttle 1 6593
Protoss_Robotics_Support_Bay 1 7027
Protoss_Citadel_of_Adun 1 7123
Protoss_Reaver 1 7559
Protoss_Templar_Archives 1 8241
Protoss_Photon_Cannon 2 9613
Protoss_High_Templar 1 9515
9613
