Protoss_Nexus 2 4140
Protoss_Forge 1 2204
Protoss_Photon_Cannon 2 3173
Protoss_Gateway 1 4665
Protoss_Assimilator 2 7437
Protoss_Zealot 6 9757
Protoss_Cybernetics_Core 1 5827
Protoss_Stargate 1 6903
Protoss_Dragoon 1 6967
Protoss_Citadel_of_Adun 1 7245
Protoss_Corsair 1 8293
Protoss_Templar_Archives 1 9166
9757
