Protoss_Nexus 1 0
Protoss_Gateway 2 2465
Protoss_Zealot 15 9011
Protoss_Assimilator 1 5809
Protoss_Cybernetics_Core 1 7695
Protoss_Forge 1 7888
Protoss_Stargate 1 8736
Protoss_Dragoon 1 8893
Protoss_Citadel_of_Adun 1 9441
9441
