Protoss_Nexus 1 0
Protoss_Gateway 3 8695
Protoss_Zealot 11 8955
Protoss_Assimilator 1 5516
Protoss_Forge 1 6383
Protoss_Cybernetics_Core 1 7224
Protoss_Photon_Cannon 1 7771
Protoss_Citadel_of_Adun 1 8435
8955
