Protoss_Nexus 1 0
Protoss_Gateway 2 6085
Protoss_Zealot 8 8513
Protoss_Assimilator 1 3150
Protoss_Cybernetics_Core 1 3899
Protoss_Dragoon 1 4955
Protoss_Citadel_of_Adun 1 5291
Protoss_Templar_Archives 1 6332
Protoss_Forge 1 7521
Protoss_High_Templar 3 9853
Protoss_Archon 1 8599
Protoss_Photon_Cannon 3 8839
Protoss_Dark_Templar 2 9115
9853
