Special_Protoss_Temple 14 0
Protoss_Nexus 2 7005
Protoss_Gateway 2 2467
Protoss_Zealot 12 7737
Protoss_Assimilator 1 7548
Protoss_Cybernetics_Core 1 8333
Protoss_Stargate 1 9348
Protoss_Forge 1 9544
9544
