Protoss_Nexus 1 0
Protoss_Gateway 1 1923
Protoss_Assimilator 1 2433
Protoss_Zealot 4 7229
Protoss_Cybernetics_Core 1 3733
Protoss_Dragoon 1 4781
Protoss_Stargate 1 5146
Protoss_Citadel_of_Adun 1 5505
Protoss_Corsair 1 6425
Protoss_Templar_Archives 1 6655
Protoss_Forge 1 7541
Protoss_Dark_Templar 1 7941
Protoss_Photon_Cannon 4 9296
Protoss_High_Templar 2 9445
9445
