Protoss_Nexus 2 3781
Protoss_Forge 1 1905
Protoss_Photon_Cannon 6 9143
Protoss_Gateway 2 9937
Protoss_Zealot 4 6923
Protoss_Assimilator 2 7277
Protoss_Cybernetics_Core 1 6670
Protoss_Stargate 1 7717
Protoss_Citadel_of_Adun 1 8292
Protoss_Corsair 1 8889
Protoss_Templar_Archives 1 9325
9937
