Protoss_Nexus 2 9228
Protoss_Gateway 2 6110
Protoss_Assimilator 1 2383
Protoss_Zealot 7 7241
Protoss_Cybernetics_Core 1 3778
Protoss_Citadel_of_Adun 1 5320
Protoss_Templar_Archives 1 7017
Protoss_Forge 1 8061
Protoss_High_Templar 4 9831
Protoss_Archon 1 9109
Protoss_Dark_Templar 1 9281
Protoss_Photon_Cannon 2 9683
9831
