Protoss_Nexus 2 3754
Protoss_Forge 1 2119
Protoss_Photon_Cannon 2 4088
Protoss_Gateway 2 7727
Protoss_Assimilator 2 6898
Protoss_Cybernetics_Core 1 5625
Protoss_Zealot 9 9663
Protoss_Stargate 1 6637
Protoss_Citadel_of_Adun 1 7194
Protoss_Corsair 3 9831
Protoss_Templar_Archives 1 8978
9831
