Protoss_Nexus 2 8026
Protoss_Gateway 1 2093
Protoss_Assimilator 1 2618
Protoss_Cybernetics_Core 1 3316
Protoss_Zealot 3 5386
Protoss_Stargate 1 4422
Protoss_Corsair 1 5741
Protoss_Forge 1 6238
Protoss_Citadel_of_Adun 1 7030
Protoss_Photon_Cannon 4 9251
Protoss_Robotics_Facility 1 9731
9731
