Protoss_Nexus 3 9915
Protoss_Forge 1 2179
Protoss_Photon_Cannon 3 9511
Protoss_Gateway 3 7617
Protoss_Assimilator 2 6507
Protoss_Cybernetics_Core 1 5175
Protoss_Zealot 3 9361
Protoss_Stargate 1 6175
Protoss_Citadel_of_Adun 1 6336
Protoss_Corsair 2 8107
Protoss_Templar_Archives 1 7538
Protoss_Dark_Templar 2 8707
9915
