Protoss_Nexus 2 4117
Protoss_Forge 1 2397
Protoss_Photon_Cannon 4 5381
Protoss_Gateway 2 8614
Protoss_Assimilator 2 6903
Protoss_Zealot 6 9599
Protoss_Cybernetics_Core 1 6327
Protoss_Stargate 1 7335
Protoss_Dragoon 1 7553
Protoss_Citadel_of_Adun 1 7932
Protoss_Corsair 3 9959
9959
