Protoss_Nexus 2 4829
Protoss_Gateway 4 9777
Protoss_Zealot 10 9433
Protoss_Assimilator 1 5516
Protoss_Cybernetics_Core 1 6533
Protoss_Dragoon 2 7889
Protoss_Citadel_of_Adun 1 7763
Protoss_Templar_Archives 1 9114
Protoss_Forge 1 9528
9777
