Protoss_Nexus 2 3383
Protoss_Forge 1 3704
Protoss_Gateway 3 8433
Protoss_Photon_Cannon 6 9087
Protoss_Assimilator 2 7498
Protoss_Cybernetics_Core 1 5820
Protoss_Zealot 6 9601
Protoss_Stargate 1 7120
Protoss_Citadel_of_Adun 1 7382
Protoss_Corsair 2 9347
Protoss_Templar_Archives 1 9256
9601
