Special_Protoss_Temple 30 0
Protoss_Nexus 2 3239
Protoss_Forge 1 2269
Protoss_Photon_Cannon 6 9434
Protoss_Gateway 4 9891
Protoss_Assimilator 2 6415
Protoss_Cybernetics_Core 1 5118
Protoss_Zealot 4 9055
Protoss_Stargate 1 6213
Protoss_Dragoon 1 6305
Protoss_Citadel_of_Adun 1 6751
Protoss_Corsair 1 7759
Protoss_Templar_Archives 1 8259
Protoss_Dark_Templar 2 9367
9891
