Protoss_Nexus 1 0
Protoss_Gateway 2 2375
Protoss_Zealot 12 8269
Protoss_Assimilator 1 5046
Protoss_Cybernetics_Core 1 6187
Protoss_Citadel_of_Adun 1 7350
Protoss_Dragoon 2 7627
8269
