Protoss_Nexus 1 0
Protoss_Gateway 3 9109
Protoss_Assimilator 1 2486
Protoss_Cybernetics_Core 1 3282
Protoss_Stargate 1 4304
Protoss_Forge 1 4513
Protoss_Photon_Cannon 1 5252
Protoss_Corsair 1 5441
Protoss_Zealot 7 9726
Protoss_Citadel_of_Adun 1 6511
Protoss_Templar_Archives 1 9369
9726
