Protoss_Nexus 2 3313
Protoss_Forge 1 1955
Protoss_Gateway 3 8465
Protoss_Photon_Cannon 2 5059
Protoss_Assimilator 2 6477
Protoss_Cybernetics_Core 1 4845
Protoss_Zealot 2 8285
Protoss_Stargate 1 6209
Protoss_Citadel_of_Adun 1 6697
Protoss_Dragoon 1 6993
Protoss_Corsair 2 8569
Protoss_Templar_Archives 1 7898
Protoss_Dark_Templar 1 8887
Protoss_High_Templar 1 9453
9453
