Protoss_Nexus 2 3300
Protoss_Forge 1 2201
Protoss_Gateway 4 8075
Protoss_Photon_Cannon 2 4661
Protoss_Assimilator 2 6599
Protoss_Zealot 13 9945
Protoss_Cybernetics_Core 1 5879
Protoss_Stargate 1 6973
Protoss_Dragoon 1 7117
Protoss_Citadel_of_Adun 1 7275
Protoss_Templar_Archives 1 8585
9945
