Protoss_Nexus 2 2902
Protoss_Gateway 6 9901
Protoss_Forge 1 3713
Protoss_Assimilator 2 6684
Protoss_Photon_Cannon 2 7181
Protoss_Cybernetics_Core 1 4725
Protoss_Zealot 5 9361
Protoss_Stargate 1 6233
Protoss_Citadel_of_Adun 1 7292
Protoss_Corsair 2 8145
Protoss_Templar_Archives 1 8377
Protoss_Dark_Templar 1 9971
9971
