Special_Protoss_Temple 30 0
Protoss_Nexus 2 3350
Protoss_Forge 1 2539
Protoss_Photon_Cannon 4 9392
Protoss_Gateway 3 9551
Protoss_Assimilator 2 7059
Protoss_Zealot 3 7891
Protoss_Cybernetics_Core 1 5467
Protoss_Dragoon 1 7139
Protoss_Citadel_of_Adun 1 7617
Protoss_Templar_Archives 1 8870
Protoss_Dark_Templar 1 9975
Protoss_High_Templar 1 9985
9985
