Protoss_Nexus 2 3845
Protoss_Forge 1 2055
Protoss_Photon_Cannon 7 9565
Protoss_Gateway 1 4316
Protoss_Assimilator 2 7016
Protoss_Cybernetics_Core 1 6972
Protoss_Zealot 4 9589
Protoss_Stargate 2 8809
Protoss_Citadel_of_Adun 2 8987
Protoss_Corsair 1 9947
Protoss_Templar_Archives 1 9981
9981
