Special_Protoss_Temple 14 0
Protoss_Nexus 2 5367
Protoss_Forge 1 2603
Protoss_Photon_Cannon 6 8598
Protoss_Gateway 2 9727
Protoss_Assimilator 2 7518
Protoss_Cybernetics_Core 1 6547
Protoss_Zealot 3 8509
Protoss_Stargate 1 7721
Protoss_Robotics_Facility 1 8359
Protoss_Corsair 2 9519
Protoss_Robotics_Support_Bay 1 9823
9823
