Protoss_Nexus 2 3039
Protoss_Forge 2 4035
Protoss_Gateway 3 8995
Protoss_Assimilator 2 6750
Protoss_Photon_Cannon 3 9248
Protoss_Zealot 5 8951
Protoss_Cybernetics_Core 1 5601
Protoss_Stargate 1 6788
Protoss_Citadel_of_Adun 1 7798
Protoss_Corsair 3 9941
Protoss_Templar_Archives 1 8799
Protoss_High_Templar 1 9915
9941
