Protoss_Nexus 1 0
Protoss_Gateway 2 2488
Protoss_Zealot 12 7796
Protoss_Forge 1 4290
Protoss_Photon_Cannon 3 9346
Protoss_Assimilator 1 6438
Protoss_Cybernetics_Core 1 7163
Protoss_Citadel_of_Adun 1 8483
Protoss_Dragoon 2 8871
Protoss_Templar_Archives 1 9938
9938
