Protoss_Nexus 2 6188
Protoss_Gateway 2 2334
Protoss_Zealot 8 7401
Protoss_Forge 1 5091
Protoss_Photon_Cannon 7 9926
Protoss_Assimilator 2 9754
Protoss_Cybernetics_Core 1 8186
Protoss_Citadel_of_Adun 1 9909
Protoss_Dragoon 1 9986
9986
