Protoss_Nexus 2 2815
Protoss_Gateway 6 9899
Protoss_Forge 1 3848
Protoss_Photon_Cannon 4 8691
Protoss_Assimilator 2 6236
Protoss_Zealot 5 8637
Protoss_Cybernetics_Core 1 5042
Protoss_Stargate 1 6311
Protoss_Dragoon 1 6591
Protoss_Citadel_of_Adun 1 6991
Protoss_Corsair 1 7459
Protoss_Templar_Archives 1 8078
Protoss_Dark_Templar 1 9239
Protoss_High_Templar 2 9281
9899
