Protoss_Nexus 2 9709
Protoss_Gateway 2 2384
Protoss_Zealot 11 8741
Protoss_Assimilator 1 4613
Protoss_Cybernetics_Core 1 5466
Protoss_Stargate 1 6498
Protoss_Citadel_of_Adun 1 6969
Protoss_Forge 1 7358
Protoss_Corsair 1 7641
Protoss_Templar_Archives 1 9631
9709
