Protoss_Nexus 2 3458
Protoss_Forge 1 2893
Protoss_Photon_Cannon 5 8277
Protoss_Gateway 2 9108
Protoss_Assimilator 2 6598
Protoss_Cybernetics_Core 1 6023
Protoss_Zealot 2 7201
Protoss_Stargate 1 7103
Protoss_Corsair 3 9588
Protoss_Dragoon 1 9051
Protoss_Robotics_Facility 1 9257
9588
