Protoss_Nexus 2 3526
Protoss_Forge 1 2189
Protoss_Photon_Cannon 4 9889
Protoss_Gateway 2 8372
Protoss_Assimilator 2 6621
Protoss_Zealot 6 8507
Protoss_Cybernetics_Core 1 5375
Protoss_Stargate 1 6506
Protoss_Citadel_of_Adun 1 7082
Protoss_Corsair 1 7899
Protoss_Templar_Archives 1 8244
Protoss_Dark_Templar 2 9371
9889
