Protoss_Nexus 1 0
Protoss_Gateway 2 6153
Protoss_Assimilator 1 2498
Protoss_Zealot 10 9836
Protoss_Forge 2 8832
Protoss_Cybernetics_Core 1 4929
Protoss_Citadel_of_Adun 1 6061
Protoss_Templar_Archives 1 7955
Protoss_Ground_Weapons_1 1 8491
Protoss_High_Templar 2 8971
Protoss_Photon_Cannon 1 9690
Protoss_Archon 1 9805
9836
