Protoss_Nexus 2 3137
Protoss_Forge 1 2467
Protoss_Photon_Cannon 2 7075
Protoss_Gateway 3 8033
Protoss_Assimilator 2 7649
Protoss_Cybernetics_Core 1 5382
Protoss_Zealot 8 9427
Protoss_Dragoon 1 6493
Protoss_Stargate 1 6520
Protoss_Citadel_of_Adun 1 7484
Protoss_Corsair 1 8009
9427
