Protoss_Nexus 2 4033
Protoss_Gateway 2 8965
Protoss_Zealot 8 9315
Protoss_Forge 1 4553
Protoss_Cybernetics_Core 1 5369
Protoss_Assimilator 2 6611
Protoss_Photon_Cannon 2 7422
Protoss_Dragoon 1 6501
Protoss_Stargate 1 7166
Protoss_Citadel_of_Adun 1 8164
Protoss_Corsair 3 9939
Protoss_Templar_Archives 1 9384
9939
