Protoss_Nexus 2 6895
Protoss_Gateway 2 2611
Protoss_Zealot 13 9429
Protoss_Forge 1 5210
Protoss_Photon_Cannon 3 9815
Protoss_Assimilator 1 7441
Protoss_Cybernetics_Core 1 7739
Protoss_Citadel_of_Adun 1 8837
Protoss_Templar_Archives 1 9984
9984
