Protoss_Nexus 1 0
Protoss_Gateway 2 2225
Protoss_Zealot 14 7659
Protoss_Assimilator 1 5059
Protoss_Cybernetics_Core 1 6189
Protoss_Dragoon 2 7743
Protoss_Stargate 1 7874
Protoss_Citadel_of_Adun 1 8080
Protoss_Forge 1 8705
Protoss_Corsair 2 9707
Protoss_Templar_Archives 1 9119
Protoss_Photon_Cannon 1 9637
9707
