Protoss_Nexus 2 3083
Protoss_Forge 1 2764
Protoss_Photon_Cannon 3 8962
Protoss_Gateway 3 7523
Protoss_Assimilator 2 6076
Protoss_Zealot 7 9153
Protoss_Cybernetics_Core 1 5432
Protoss_Stargate 1 6621
Protoss_Citadel_of_Adun 1 7635
Protoss_Corsair 3 9479
Protoss_Templar_Archives 1 9315
9479
