Protoss_Nexus 1 0
Protoss_Gateway 2 2473
Protoss_Zealot 17 9476
Protoss_Assimilator 1 5978
Protoss_Cybernetics_Core 1 6628
Protoss_Citadel_of_Adun 1 7665
Protoss_Templar_Archives 1 9023
9476
