Protoss_Nexus 2 4077
Protoss_Forge 1 2305
Protoss_Photon_Cannon 2 3207
Protoss_Gateway 3 8893
Protoss_Assimilator 2 7554
Protoss_Cybernetics_Core 1 5360
Protoss_Zealot 9 9969
Protoss_Stargate 1 6477
Protoss_Corsair 3 8887
Protoss_Citadel_of_Adun 1 7750
Protoss_Templar_Archives 1 9119
Protoss_Ground_Weapons_1 1 9771
9969
