Protoss_Nexus 2 3179
Protoss_Forge 1 2660
Protoss_Photon_Cannon 4 9081
Protoss_Gateway 3 8911
Protoss_Assimilator 2 7097
Protoss_Cybernetics_Core 1 5539
Protoss_Zealot 4 9929
Protoss_Stargate 1 6525
Protoss_Dragoon 1 6841
Protoss_Citadel_of_Adun 1 7522
Protoss_Corsair 3 9403
Protoss_Templar_Archives 1 8637
Protoss_Dark_Templar 1 9643
9929
