Protoss_Nexus 2 4431
Protoss_Forge 1 2651
Protoss_Photon_Cannon 5 9885
Protoss_Gateway 2 7745
Protoss_Assimilator 2 6396
Protoss_Cybernetics_Core 1 5820
Protoss_Zealot 3 7605
Protoss_Dragoon 1 6803
Protoss_Stargate 1 6905
Protoss_Citadel_of_Adun 1 7195
Protoss_Corsair 3 9647
Protoss_Templar_Archives 1 8254
Protoss_Dark_Templar 2 9255
9885
