Protoss_Nexus 2 4173
Protoss_Forge 1 2266
Protoss_Photon_Cannon 5 9700
Protoss_Gateway 4 9260
Protoss_Assimilator 2 7083
Protoss_Cybernetics_Core 1 5492
Protoss_Zealot 3 9809
Protoss_Dragoon 1 6631
Protoss_Citadel_of_Adun 1 6913
Protoss_Templar_Archives 1 8057
Protoss_High_Templar 3 9791
9809
