Protoss_Nexus 2 4623
Protoss_Forge 1 2238
Protoss_Photon_Cannon 4 9180
Protoss_Gateway 1 4935
Protoss_Assimilator 2 6725
Protoss_Cybernetics_Core 1 6211
Protoss_Zealot 1 6259
Protoss_Stargate 1 7198
Protoss_Dragoon 1 7343
Protoss_Corsair 3 9593
Protoss_Robotics_Facility 1 8749
9593
