Special_Protoss_Temple 14 0
Protoss_Nexus 1 0
Protoss_Forge 2 7569
Protoss_Photon_Cannon 3 4853
Protoss_Gateway 4 9505
Protoss_Zealot 8 9899
Protoss_Assimilator 1 5221
Protoss_Cybernetics_Core 1 5996
Protoss_Stargate 1 7100
Protoss_Dragoon 1 7295
Protoss_Citadel_of_Adun 1 7869
Protoss_Corsair 1 8395
9899
