Protoss_Nexus 2 8041
Protoss_Gateway 3 9487
Protoss_Zealot 12 9829
Protoss_Assimilator 1 6729
Protoss_Cybernetics_Core 1 6999
Protoss_Citadel_of_Adun 1 8153
Protoss_Dragoon 2 8887
Protoss_Forge 1 9125
9829
