Special_Protoss_Temple 14 0
Protoss_Nexus 2 3283
Protoss_Forge 1 2568
Protoss_Photon_Cannon 3 8950
Protoss_Gateway 4 9775
Protoss_Assimilator 2 5663
Protoss_Cybernetics_Core 1 5293
Protoss_Zealot 7 8803
Protoss_Stargate 1 6281
Protoss_Citadel_of_Adun 1 6888
Protoss_Corsair 1 7411
Protoss_Templar_Archives 1 8013
Protoss_Dark_Templar 2 9405
9775
