Protoss_Nexus 2 6873
Protoss_Gateway 2 2289
Protoss_Zealot 17 9871
Protoss_Assimilator 2 9430
Protoss_Forge 1 8198
Protoss_Cybernetics_Core 1 8713
Protoss_Photon_Cannon 1 8893
Protoss_Stargate 1 9753
9871
