Special_Protoss_Temple 30 0
Protoss_Nexus 2 4373
Protoss_Forge 1 2252
Protoss_Photon_Cannon 4 6289
Protoss_Gateway 4 9467
Protoss_Assimilator 2 7479
Protoss_Zealot 3 7835
Protoss_Cybernetics_Core 1 6861
Protoss_Stargate 1 8389
Protoss_Citadel_of_Adun 1 8852
Protoss_Corsair 1 9593
9593
