Protoss_Nexus 2 8531
Protoss_Gateway 2 8859
Protoss_Zealot 6 7023
Protoss_Assimilator 2 9390
Protoss_Cybernetics_Core 1 3680
Protoss_Stargate 1 4679
Protoss_Dragoon 1 4839
Protoss_Corsair 3 7443
Protoss_Citadel_of_Adun 1 6233
Protoss_Templar_Archives 1 7285
Protoss_Dark_Templar 2 9175
Protoss_High_Templar 1 9927
9927
