Protoss_Nexus 1 0
Protoss_Gateway 2 7432
Protoss_Assimilator 1 2331
Protoss_Cybernetics_Core 1 2893
Protoss_Zealot 3 5385
Protoss_Stargate 1 3895
Protoss_Citadel_of_Adun 1 4753
Protoss_Corsair 2 6481
Protoss_Templar_Archives 1 5989
Protoss_Forge 1 6966
Protoss_Dark_Templar 1 7051
Protoss_Photon_Cannon 2 9890
Protoss_High_Templar 3 9763
9890
