Protoss_Nexus 2 3283
Protoss_Forge 1 2320
Protoss_Photon_Cannon 3 9080
Protoss_Gateway 4 9942
Protoss_Assimilator 2 6072
Protoss_Cybernetics_Core 1 5615
Protoss_Zealot 4 8953
Protoss_Dragoon 1 6737
Protoss_Stargate 1 6796
Protoss_Citadel_of_Adun 1 7691
Protoss_Corsair 1 7953
Protoss_Templar_Archives 1 8762
Protoss_Dark_Templar 2 9815
9942
