Protoss_Nexus 2 3382
Protoss_Forge 1 2117
Protoss_Gateway 4 9388
Protoss_Photon_Cannon 3 9316
Protoss_Assimilator 2 7195
Protoss_Cybernetics_Core 1 5665
Protoss_Zealot 9 9713
Protoss_Stargate 1 6967
Protoss_Citadel_of_Adun 1 7459
Protoss_Corsair 1 8097
Protoss_Templar_Archives 1 9415
9713
