Protoss_Nexus 2 4165
Protoss_Gateway 5 8842
Protoss_Zealot 6 8275
Protoss_Assimilator 1 4715
Protoss_Cybernetics_Core 1 6428
Protoss_Dragoon 3 9535
Protoss_Forge 1 8059
Protoss_Photon_Cannon 4 9957
9957
