Special_Protoss_Temple 14 0
Protoss_Nexus 2 3266
Protoss_Forge 1 2593
Protoss_Photon_Cannon 3 8919
Protoss_Gateway 4 9935
Protoss_Assimilator 2 5984
Protoss_Cybernetics_Core 1 5103
Protoss_Zealot 7 9659
Protoss_Stargate 1 6235
Protoss_Citadel_of_Adun 1 6789
Protoss_Corsair 4 9369
Protoss_Templar_Archives 1 9203
9935
