Protoss_Nexus 2 3279
Protoss_Forge 1 2423
Protoss_Photon_Cannon 4 8299
Protoss_Gateway 4 9971
Protoss_Assimilator 2 6443
Protoss_Cybernetics_Core 1 5836
Protoss_Zealot 1 6185
Protoss_Citadel_of_Adun 1 7125
Protoss_Stargate 1 7268
Protoss_Corsair 3 9609
Protoss_Templar_Archives 1 8676
Protoss_Dark_Templar 2 9707
9971
