Protoss_Nexus 2 3337
Protoss_Forge 1 2312
Protoss_Gateway 4 8661
Protoss_Photon_Cannon 1 4504
Protoss_Assimilator 2 6029
Protoss_Cybernetics_Core 1 5386
Protoss_Zealot 1 5623
Protoss_Stargate 1 6408
Protoss_Dragoon 8 9889
Protoss_Robotics_Facility 1 7281
Protoss_Corsair 1 7561
Protoss_Shuttle 1 8567
Protoss_Robotics_Support_Bay 1 8925
Protoss_Reaver 1 9487
9889
