Protoss_Nexus 2 3535
Protoss_Forge 1 2091
Protoss_Gateway 1 4033
Protoss_Photon_Cannon 4 8861
Protoss_Assimilator 2 7609
Protoss_Cybernetics_Core 1 5388
Protoss_Zealot 2 7265
Protoss_Stargate 1 6475
Protoss_Corsair 3 9701
Protoss_Robotics_Facility 1 8106
Protoss_Robotics_Support_Bay 1 9599
Protoss_Shuttle 1 9823
9823
