Special_Protoss_Temple 30 0
Protoss_Nexus 2 3289
Protoss_Forge 1 1952
Protoss_Photon_Cannon 7 9734
Protoss_Gateway 2 8463
Protoss_Assimilator 2 6201
Protoss_Cybernetics_Core 1 5413
Protoss_Zealot 3 7342
Protoss_Stargate 1 6416
Protoss_Citadel_of_Adun 1 7358
Protoss_Corsair 3 8783
Protoss_Templar_Archives 1 8513
9734
