Protoss_Nexus 2 4139
Protoss_Forge 1 2295
Protoss_Photon_Cannon 2 3235
Protoss_Gateway 3 7441
Protoss_Assimilator 2 7986
Protoss_Cybernetics_Core 1 5530
Protoss_Zealot 11 9837
Protoss_Citadel_of_Adun 1 6970
Protoss_Templar_Archives 1 8788
9837
