Protoss_Nexus 2 4594
Protoss_Forge 1 2055
Protoss_Photon_Cannon 4 4833
Protoss_Gateway 3 8963
Protoss_Assimilator 2 7499
Protoss_Cybernetics_Core 1 6412
Protoss_Zealot 5 9323
Protoss_Stargate 1 7876
Protoss_Citadel_of_Adun 1 8359
Protoss_Corsair 2 9693
Protoss_Templar_Archives 1 9433
9693
