Protoss_Nexus 2 4523
Protoss_Forge 1 1960
Protoss_Photon_Cannon 5 7613
Protoss_Gateway 1 4999
Protoss_Assimilator 1 5265
Protoss_Cybernetics_Core 1 6127
Protoss_Zealot 1 6581
Protoss_Citadel_of_Adun 1 7201
Protoss_Dragoon 1 7273
7613
