Protoss_Nexus 2 4193
Protoss_Forge 1 2486
Protoss_Photon_Cannon 5 8111
Protoss_Gateway 4 9293
Protoss_Assimilator 2 6329
Protoss_Zealot 5 8669
Protoss_Cybernetics_Core 1 5775
Protoss_Stargate 1 6761
Protoss_Citadel_of_Adun 1 7290
Protoss_Corsair 2 8559
Protoss_Templar_Archives 1 8509
Protoss_Dark_Templar 2 9545
9545
