Special_Protoss_Temple 14 0
Protoss_Nexus 2 3613
Protoss_Forge 1 2537
Protoss_Photon_Cannon 1 3243
Protoss_Gateway 2 8921
Protoss_Assimilator 2 6011
Protoss_Zealot 4 7857
Protoss_Cybernetics_Core 1 5705
Protoss_Stargate 1 6997
Protoss_Citadel_of_Adun 1 7291
Protoss_Corsair 2 9183
Protoss_Templar_Archives 1 8395
Protoss_Robotics_Facility 1 8743
Protoss_Dark_Templar 2 9977
9977
