Protoss_Nexus 2 9933
Protoss_Gateway 2 2299
Protoss_Zealot 8 6801
Protoss_Assimilator 1 4847
Protoss_Cybernetics_Core 1 5465
Protoss_Stargate 1 6520
Protoss_Forge 1 7234
Protoss_Corsair 1 7757
Protoss_Robotics_Facility 1 8017
Protoss_Photon_Cannon 2 9071
Protoss_Robotics_Support_Bay 1 9737
9933
