Protoss_Nexus 2 4111
Protoss_Gateway 1 1997
Protoss_Zealot 8 9145
Protoss_Forge 1 4452
Protoss_Photon_Cannon 3 6725
Protoss_Assimilator 2 8722
Protoss_Cybernetics_Core 1 8331
Protoss_Stargate 1 9586
Protoss_Robotics_Facility 1 9903
9903
