Protoss_Nexus 2 3926
Protoss_Forge 1 2649
Protoss_Photon_Cannon 2 3592
Protoss_Gateway 3 9489
Protoss_Assimilator 2 7365
Protoss_Cybernetics_Core 1 5308
Protoss_Zealot 6 9447
Protoss_Stargate 1 6416
Protoss_Citadel_of_Adun 1 7217
Protoss_Corsair 4 9539
Protoss_Templar_Archives 1 8694
Protoss_Dark_Templar 2 9841
9841
