Protoss_Nexus 2 3111
Protoss_Forge 1 3697
Protoss_Gateway 3 7491
Protoss_Photon_Cannon 6 9867
Protoss_Assimilator 2 5922
Protoss_Cybernetics_Core 1 5521
Protoss_Citadel_of_Adun 1 6544
Protoss_Templar_Archives 1 7616
Protoss_Zealot 3 9983
Protoss_High_Templar 4 9647
Protoss_Dark_Templar 1 9145
Protoss_Archon 1 9703
9983
