Protoss_Nexus 2 4317
Protoss_Forge 1 2365
Protoss_Photon_Cannon 7 9692
Protoss_Gateway 3 9564
Protoss_Assimilator 2 6549
Protoss_Zealot 3 7331
Protoss_Cybernetics_Core 1 5835
Protoss_Stargate 1 6949
Protoss_Citadel_of_Adun 1 7053
Protoss_Corsair 1 8087
Protoss_Templar_Archives 1 8243
Protoss_Dark_Templar 1 9303
9692
