Protoss_Nexus 1 0
Protoss_Gateway 4 8468
Protoss_Zealot 9 9161
Protoss_Assimilator 1 3589
Protoss_Cybernetics_Core 1 4401
Protoss_Forge 1 4942
Protoss_Stargate 1 5658
Protoss_Corsair 1 6956
Protoss_Photon_Cannon 3 9294
Protoss_Citadel_of_Adun 1 8659
Protoss_Ground_Weapons_1 1 9891
9891
