Protoss_Nexus 2 3239
Protoss_Forge 1 2181
Protoss_Photon_Cannon 3 6883
Protoss_Gateway 1 4791
Protoss_Assimilator 2 6251
Protoss_Cybernetics_Core 1 5933
Protoss_Zealot 2 7839
Protoss_Stargate 2 7649
Protoss_Corsair 5 9643
Protoss_Citadel_of_Adun 1 9337
9643
