Special_Protoss_Temple 14 0
Protoss_Nexus 2 3019
Protoss_Forge 1 3665
Protoss_Gateway 4 8517
Protoss_Photon_Cannon 2 9550
Protoss_Assimilator 2 6615
Protoss_Cybernetics_Core 1 5516
Protoss_Zealot 2 6255
Protoss_Dragoon 8 9935
Protoss_Stargate 1 7423
Protoss_Corsair 2 9457
9935
