Protoss_Nexus 2 4379
Protoss_Forge 1 2436
Protoss_Photon_Cannon 6 7168
Protoss_Gateway 3 9562
Protoss_Assimilator 2 8721
Protoss_Cybernetics_Core 1 5888
Protoss_Zealot 3 7331
Protoss_Stargate 1 7918
Protoss_Citadel_of_Adun 1 8405
Protoss_Corsair 1 9107
Protoss_Templar_Archives 1 9705
9705
