Protoss_Nexus 2 3187
Protoss_Forge 1 2034
Protoss_Gateway 3 8072
Protoss_Assimilator 2 6467
Protoss_Photon_Cannon 8 9791
Protoss_Zealot 2 5431
Protoss_Cybernetics_Core 1 5071
Protoss_Dragoon 1 6057
Protoss_Stargate 1 6163
Protoss_Citadel_of_Adun 1 6759
Protoss_Corsair 2 8267
Protoss_Templar_Archives 1 7808
Protoss_Dark_Templar 1 8803
Protoss_High_Templar 2 9531
9791
