Protoss_Nexus 2 4171
Protoss_Forge 1 2696
Protoss_Photon_Cannon 5 9269
Protoss_Gateway 1 4424
Protoss_Assimilator 2 7195
Protoss_Cybernetics_Core 1 5449
Protoss_Zealot 3 8839
Protoss_Stargate 2 8070
Protoss_Dragoon 1 6713
Protoss_Citadel_of_Adun 1 7649
Protoss_Corsair 4 9875
Protoss_Robotics_Facility 1 9707
9875
