Protoss_Nexus 2 4021
Protoss_Forge 1 2248
Protoss_Photon_Cannon 4 9773
Protoss_Gateway 3 9669
Protoss_Assimilator 2 8258
Protoss_Cybernetics_Core 1 5373
Protoss_Zealot 8 9249
Protoss_Stargate 1 6390
Protoss_Citadel_of_Adun 1 6855
Protoss_Corsair 5 9599
Protoss_Templar_Archives 1 9912
9912
