Protoss_Nexus 2 4743
Protoss_Gateway 5 9883
Protoss_Zealot 10 8889
Protoss_Assimilator 2 8410
Protoss_Cybernetics_Core 1 5746
Protoss_Forge 1 6230
Protoss_Stargate 1 6761
Protoss_Photon_Cannon 3 9009
Protoss_Citadel_of_Adun 1 7538
Protoss_Corsair 1 8131
Protoss_Templar_Archives 1 8671
9883
