Protoss_Nexus 2 6716
Protoss_Gateway 2 9847
Protoss_Assimilator 1 2240
Protoss_Zealot 9 9539
Protoss_Cybernetics_Core 1 3478
Protoss_Dragoon 1 4485
Protoss_Stargate 1 4819
Protoss_Corsair 5 9695
Protoss_Forge 1 7699
Protoss_Citadel_of_Adun 1 8924
9847
