Protoss_Nexus 1 0
Protoss_Gateway 2 2442
Protoss_Zealot 9 7576
Protoss_Assimilator 1 4496
Protoss_Cybernetics_Core 1 5562
Protoss_Dragoon 2 6561
Protoss_Citadel_of_Adun 1 6646
Protoss_Templar_Archives 1 8043
Protoss_High_Templar 2 9341
9341
