Special_Protoss_Temple 14 0
Protoss_Nexus 2 2925
Protoss_Gateway 4 8387
Protoss_Forge 1 3914
Protoss_Assimilator 2 9930
Protoss_Zealot 10 9255
Protoss_Photon_Cannon 5 9683
Protoss_Cybernetics_Core 1 5461
Protoss_Citadel_of_Adun 1 6764
Protoss_Dragoon 1 7077
Protoss_Templar_Archives 1 8733
9930
