Special_Protoss_Temple 14 0
Protoss_Nexus 2 3101
Protoss_Forge 1 2624
Protoss_Photon_Cannon 4 9989
Protoss_Gateway 4 9070
Protoss_Assimilator 2 5672
Protoss_Cybernetics_Core 1 5257
Protoss_Zealot 1 5869
Protoss_Stargate 1 6322
Protoss_Citadel_of_Adun 1 7189
Protoss_Corsair 3 8661
Protoss_Templar_Archives 1 8251
Protoss_Dark_Templar 2 9315
9989
