Protoss_Nexus 1 0
Protoss_Gateway 2 2205
Protoss_Zealot 9 8935
Protoss_Assimilator 1 4100
Protoss_Cybernetics_Core 1 5177
Protoss_Stargate 1 6627
Protoss_Dragoon 1 7011
Protoss_Citadel_of_Adun 1 7325
Protoss_Corsair 1 8177
Protoss_Forge 1 9167
9167
