Protoss_Nexus 2 8273
Special_Protoss_Temple 30 0
Protoss_Gateway 1 1956
Protoss_Forge 1 2655
Protoss_Assimilator 2 9992
Protoss_Photon_Cannon 2 4491
Protoss_Cybernetics_Core 1 3872
Protoss_Dragoon 1 4875
Protoss_Stargate 1 5255
Protoss_Corsair 1 6639
Protoss_Zealot 2 9505
Protoss_Citadel_of_Adun 1 9375
9992
