Special_Protoss_Temple 30 0
Protoss_Nexus 2 3556
Protoss_Forge 1 2238
Protoss_Gateway 1 3987
Protoss_Assimilator 2 6035
Protoss_Photon_Cannon 3 8910
Protoss_Cybernetics_Core 1 5181
Protoss_Zealot 5 9379
Protoss_Stargate 1 6272
Protoss_Dragoon 1 6573
Protoss_Robotics_Facility 1 7077
Protoss_Corsair 4 9383
Protoss_Robotics_Support_Bay 1 8439
Protoss_Reaver 1 9159
9383
