Protoss_Nexus 2 3648
Protoss_Forge 1 2108
Protoss_Photon_Cannon 10 9466
Protoss_Gateway 3 8200
Protoss_Assimilator 2 6755
Protoss_Cybernetics_Core 1 5993
Protoss_Zealot 2 7006
Protoss_Citadel_of_Adun 1 7331
Protoss_Templar_Archives 1 8402
Protoss_High_Templar 2 9406
9466
