Protoss_Nexus 1 0
Protoss_Gateway 2 2618
Protoss_Zealot 11 9436
Protoss_Assimilator 1 4996
Protoss_Cybernetics_Core 1 5623
Protoss_Forge 1 6717
Protoss_Photon_Cannon 2 9894
Protoss_Dragoon 1 8391
9894
