Special_Protoss_Temple 14 0
Protoss_Nexus 2 3959
Protoss_Forge 1 2286
Protoss_Photon_Cannon 2 3117
Protoss_Gateway 3 8344
Protoss_Assimilator 2 7633
Protoss_Zealot 10 9957
Protoss_Cybernetics_Core 1 5835
Protoss_Citadel_of_Adun 1 7069
Protoss_Dragoon 1 7211
Protoss_Stargate 2 9548
9957
