Special_Protoss_Temple 30 0
Protoss_Nexus 2 3816
Protoss_Forge 1 2131
Protoss_Photon_Cannon 5 9327
Protoss_Gateway 3 9406
Protoss_Assimilator 2 6811
Protoss_Cybernetics_Core 1 6175
Protoss_Zealot 3 9171
Protoss_Stargate 1 7266
Protoss_Dragoon 1 7341
Protoss_Citadel_of_Adun 1 8033
Protoss_Corsair 1 8395
Protoss_Templar_Archives 1 9738
9738
