Protoss_Nexus 2 3678
Protoss_Forge 1 2295
Protoss_Photon_Cannon 4 9693
Protoss_Gateway 1 4028
Protoss_Assimilator 2 5738
Protoss_Zealot 5 9151
Protoss_Cybernetics_Core 1 5248
Protoss_Stargate 2 7671
Protoss_Robotics_Facility 1 7098
Protoss_Corsair 4 9030
Protoss_Robotics_Support_Bay 1 8628
Protoss_Reaver 1 9286
9693
