Special_Protoss_Temple 14 0
Protoss_Nexus 2 3431
Protoss_Forge 1 2528
Protoss_Photon_Cannon 4 9447
Protoss_Gateway 3 8295
Protoss_Assimilator 2 6310
Protoss_Zealot 3 9949
Protoss_Cybernetics_Core 1 6176
Protoss_Stargate 2 7910
Protoss_Citadel_of_Adun 1 7630
Protoss_Corsair 4 9923
Protoss_Templar_Archives 1 9573
9949
