Protoss_Nexus 2 4110
Protoss_Forge 1 2469
Protoss_Photon_Cannon 3 9696
Protoss_Gateway 4 8905
Protoss_Assimilator 2 6709
Protoss_Zealot 3 7959
Protoss_Cybernetics_Core 1 5843
Protoss_Stargate 1 6929
Protoss_Dragoon 1 7061
Protoss_Citadel_of_Adun 1 7443
Protoss_Corsair 2 9523
Protoss_Templar_Archives 1 8461
Protoss_High_Templar 4 9887
9887
