Special_Protoss_Temple 14 0
Protoss_Nexus 2 2847
Protoss_Gateway 4 9647
Protoss_Forge 1 3476
Protoss_Photon_Cannon 1 4168
Protoss_Assimilator 2 6277
Protoss_Cybernetics_Core 1 4821
Protoss_Zealot 9 9429
Protoss_Dragoon 1 5827
Protoss_Stargate 1 6007
Protoss_Citadel_of_Adun 1 6979
Protoss_Corsair 2 7967
Protoss_Templar_Archives 1 8881
9647
