Protoss_Nexus 2 4365
Protoss_Forge 1 2325
Protoss_Photon_Cannon 3 9705
Protoss_Gateway 3 7595
Protoss_Assimilator 2 8735
Protoss_Zealot 9 9951
Protoss_Cybernetics_Core 1 5994
Protoss_Dragoon 1 6975
Protoss_Citadel_of_Adun 1 7161
Protoss_Stargate 2 9483
9951
