Protoss_Nexus 1 0
Protoss_Gateway 2 9697
Protoss_Assimilator 1 2434
Protoss_Zealot 4 7281
Protoss_Cybernetics_Core 1 3822
Protoss_Dragoon 1 4886
Protoss_Robotics_Facility 1 5579
Protoss_Shuttle 1 6891
Protoss_Robotics_Support_Bay 1 6996
Protoss_Reaver 2 8845
Protoss_Citadel_of_Adun 1 8413
Protoss_Scarab 6 9894
Protoss_Forge 1 9309
Protoss_Templar_Archives 1 9721
9894
