Special_Protoss_Temple 14 0
Protoss_Nexus 2 3258
Protoss_Forge 1 2606
Protoss_Photon_Cannon 3 9903
Protoss_Gateway 3 8201
Protoss_Assimilator 2 6875
Protoss_Cybernetics_Core 1 5311
Protoss_Zealot 7 9417
Protoss_Stargate 1 6297
Protoss_Corsair 4 9237
Protoss_Citadel_of_Adun 1 7634
Protoss_Templar_Archives 1 9595
9903
