Protoss_Nexus 2 3667
Protoss_Forge 1 2171
Protoss_Photon_Cannon 2 3991
Protoss_Gateway 4 8590
Protoss_Assimilator 2 6337
Protoss_Cybernetics_Core 1 5334
Protoss_Zealot 5 9637
Protoss_Stargate 1 6485
Protoss_Citadel_of_Adun 1 7007
Protoss_Corsair 2 8217
Protoss_Templar_Archives 1 9250
9637
