Protoss_Nexus 1 0
Protoss_Gateway 1 1931
Protoss_Assimilator 1 2410
Protoss_Zealot 3 4210
Protoss_Cybernetics_Core 1 3865
Protoss_Dragoon 6 9961
Protoss_Robotics_Facility 1 5566
Protoss_Shuttle 1 6851
Protoss_Robotics_Support_Bay 1 7297
Protoss_Reaver 2 9111
Protoss_Forge 1 7975
9961
