Protoss_Nexus 1 0
Protoss_Gateway 4 9485
Protoss_Zealot 9 9763
Protoss_Assimilator 1 4130
Protoss_Cybernetics_Core 1 4719
Protoss_Stargate 1 5739
Protoss_Forge 1 6149
Protoss_Citadel_of_Adun 1 6497
Protoss_Photon_Cannon 4 8334
Protoss_Corsair 2 7685
Protoss_Templar_Archives 1 8074
9763
