Protoss_Nexus 3 7682
Protoss_Gateway 2 2183
Protoss_Zealot 11 9255
Protoss_Assimilator 2 9338
Protoss_Forge 1 7047
Protoss_Photon_Cannon 2 9673
Protoss_Cybernetics_Core 1 7964
Protoss_Stargate 1 9034
Protoss_Robotics_Facility 1 9779
9779
