Special_Protoss_Temple 14 0
Protoss_Nexus 2 4313
Protoss_Forge 1 1970
Protoss_Photon_Cannon 3 6789
Protoss_Gateway 3 8687
Protoss_Assimilator 2 7679
Protoss_Zealot 7 9767
Protoss_Cybernetics_Core 1 5952
Protoss_Stargate 1 7107
Protoss_Dragoon 1 7319
Protoss_Corsair 2 8979
Protoss_Citadel_of_Adun 1 9229
9767
