Special_Protoss_Temple 14 0
Protoss_Nexus 2 4155
Protoss_Forge 1 2578
Protoss_Photon_Cannon 3 9209
Protoss_Gateway 3 8307
Protoss_Assimilator 2 7144
Protoss_Cybernetics_Core 1 5726
Protoss_Zealot 8 9719
Protoss_Stargate 1 6989
Protoss_Citadel_of_Adun 1 7411
Protoss_Corsair 2 8911
9719
