Protoss_Nexus 2 7681
Protoss_Gateway 1 1859
Protoss_Zealot 5 6977
Protoss_Assimilator 1 3086
Protoss_Cybernetics_Core 1 3513
Protoss_Stargate 1 4634
Protoss_Dragoon 1 4839
Protoss_Forge 1 5358
Protoss_Corsair 3 9517
Protoss_Photon_Cannon 5 9823
Protoss_Robotics_Facility 1 8311
9823
