Protoss_Nexus 2 3588
Protoss_Forge 1 2099
Protoss_Photon_Cannon 3 9995
Protoss_Gateway 3 7904
Protoss_Assimilator 2 8551
Protoss_Zealot 6 9991
Protoss_Cybernetics_Core 1 6470
Protoss_Stargate 1 7760
Protoss_Dragoon 1 7986
Protoss_Citadel_of_Adun 1 9101
9995
