Protoss_Nexus 1 0
Protoss_Gateway 3 7781
Protoss_Assimilator 1 2508
Protoss_Zealot 2 4051
Protoss_Cybernetics_Core 1 3833
Protoss_Dragoon 8 9876
Protoss_Robotics_Facility 1 5303
Protoss_Shuttle 1 6591
Protoss_Robotics_Support_Bay 1 6658
Protoss_Reaver 2 8545
9876
