Protoss_Nexus 2 8703
Protoss_Gateway 2 5632
Protoss_Assimilator 1 2400
Protoss_Zealot 7 8223
Protoss_Cybernetics_Core 1 4079
Protoss_Dragoon 1 5159
Protoss_Citadel_of_Adun 1 5374
Protoss_Templar_Archives 1 6367
Protoss_High_Templar 4 9023
Protoss_Archon 1 8359
Protoss_Forge 1 8646
Protoss_Photon_Cannon 3 9974
9974
