Protoss_Nexus 2 3424
Protoss_Forge 1 2652
Protoss_Gateway 4 8819
Protoss_Assimilator 2 7477
Protoss_Photon_Cannon 5 9964
Protoss_Cybernetics_Core 1 5256
Protoss_Zealot 9 9055
Protoss_Dragoon 1 6243
Protoss_Citadel_of_Adun 1 6424
Protoss_Templar_Archives 1 8384
Protoss_Ground_Weapons_1 1 9557
Protoss_Dark_Templar 2 9657
Protoss_High_Templar 2 9941
9964
