Protoss_Nexus 2 4071
Protoss_Forge 1 1941
Protoss_Photon_Cannon 4 8995
Protoss_Gateway 3 9675
Protoss_Assimilator 2 6713
Protoss_Cybernetics_Core 1 5713
Protoss_Zealot 4 9567
Protoss_Stargate 1 6931
Protoss_Dragoon 1 7141
Protoss_Citadel_of_Adun 1 7580
Protoss_Corsair 2 8831
Protoss_Templar_Archives 1 8646
Protoss_Dark_Templar 1 9797
9797
