Special_Protoss_Temple 14 0
Protoss_Nexus 2 3662
Protoss_Forge 1 2196
Protoss_Photon_Cannon 4 9569
Protoss_Gateway 2 8527
Protoss_Assimilator 2 7476
Protoss_Cybernetics_Core 1 5839
Protoss_Zealot 4 9387
Protoss_Stargate 1 6918
Protoss_Dragoon 1 7357
Protoss_Citadel_of_Adun 1 7747
Protoss_Corsair 3 9421
Protoss_Templar_Archives 1 9623
9623
