Protoss_Nexus 2 9773
Protoss_Gateway 2 5194
Protoss_Assimilator 1 2131
Protoss_Zealot 7 8621
Protoss_Cybernetics_Core 1 3774
Protoss_Dragoon 1 4789
Protoss_Citadel_of_Adun 1 4919
Protoss_Templar_Archives 1 5915
Protoss_High_Templar 2 6903
Protoss_Forge 1 7229
Protoss_Dark_Templar 2 7659
Protoss_Archon 1 7707
Protoss_Photon_Cannon 2 8193
9773
