Protoss_Nexus 2 2823
Protoss_Gateway 2 7098
Protoss_Assimilator 2 5583
Protoss_Zealot 10 8879
Protoss_Cybernetics_Core 1 4978
Protoss_Stargate 1 5969
Protoss_Citadel_of_Adun 1 6334
Protoss_Corsair 1 7161
Protoss_Templar_Archives 1 7874
Protoss_Forge 1 8465
Protoss_High_Templar 2 9481
Protoss_Photon_Cannon 3 9950
9950
