Protoss_Nexus 2 6599
Protoss_Gateway 4 8249
Protoss_Assimilator 1 2433
Protoss_Zealot 5 5835
Protoss_Cybernetics_Core 1 3457
Protoss_Stargate 1 4445
Protoss_Dragoon 11 9811
Protoss_Scout 1 5577
9811
