Protoss_Nexus 2 3284
Protoss_Forge 1 2632
Protoss_Photon_Cannon 4 9816
Protoss_Gateway 4 9484
Protoss_Assimilator 2 6102
Protoss_Cybernetics_Core 1 5423
Protoss_Stargate 1 6443
Protoss_Citadel_of_Adun 1 6737
Protoss_Dragoon 1 7133
Protoss_Corsair 2 8749
Protoss_Templar_Archives 1 8105
Protoss_Zealot 2 9645
Protoss_High_Templar 2 9577
9816
