Protoss_Nexus 2 5123
Protoss_Gateway 2 9606
Protoss_Zealot 10 9289
Protoss_Forge 1 4402
Protoss_Assimilator 2 7207
Protoss_Photon_Cannon 3 9378
Protoss_Cybernetics_Core 1 6119
Protoss_Stargate 1 7657
Protoss_Robotics_Facility 1 8414
Protoss_Corsair 2 9521
Protoss_Robotics_Support_Bay 1 9852
Protoss_Shuttle 1 9891
9891
