Protoss_Nexus 2 3191
Protoss_Forge 1 2361
Protoss_Photon_Cannon 2 8417
Protoss_Gateway 5 9375
Protoss_Assimilator 2 5765
Protoss_Cybernetics_Core 1 5045
Protoss_Zealot 3 8119
Protoss_Stargate 1 6105
Protoss_Dragoon 1 6345
Protoss_Citadel_of_Adun 1 6904
Protoss_Corsair 2 7937
Protoss_Templar_Archives 1 7919
Protoss_Dark_Templar 1 8929
9375
