Protoss_Nexus 2 5438
Protoss_Gateway 2 6008
Protoss_Forge 1 3087
Protoss_Zealot 11 9931
Protoss_Photon_Cannon 3 6873
Protoss_Assimilator 2 9982
Protoss_Cybernetics_Core 1 8563
9982
