Protoss_Nexus 1 0
Protoss_Gateway 2 2347
Protoss_Zealot 13 7696
Protoss_Assimilator 1 5201
Protoss_Cybernetics_Core 1 6834
Protoss_Citadel_of_Adun 1 7828
Protoss_Dragoon 1 7871
Protoss_Forge 1 8294
Protoss_Templar_Archives 1 8912
Protoss_Dark_Templar 1 9911
9911
