Protoss_Nexus 1 0
Protoss_Gateway 1 1971
Protoss_Assimilator 1 2394
Protoss_Zealot 5 7236
Protoss_Cybernetics_Core 1 3959
Protoss_Dragoon 1 5041
Protoss_Citadel_of_Adun 1 5159
Protoss_Robotics_Facility 1 5592
Protoss_Shuttle 1 6891
Protoss_Templar_Archives 1 6901
Protoss_Forge 1 7033
Protoss_Robotics_Support_Bay 1 7418
Protoss_Photon_Cannon 2 9854
Protoss_Reaver 2 9018
Protoss_High_Templar 2 9453
Protoss_Scarab 1 9717
9854
