Protoss_Nexus 2 3551
Protoss_Forge 2 9663
Protoss_Photon_Cannon 7 9466
Protoss_Gateway 2 8084
Protoss_Assimilator 2 5811
Protoss_Cybernetics_Core 1 4843
Protoss_Zealot 10 9755
Protoss_Stargate 1 6013
Protoss_Corsair 2 7841
Protoss_Citadel_of_Adun 1 7305
9755
