Special_Protoss_Temple 14 0
Protoss_Nexus 2 3679
Protoss_Forge 1 2191
Protoss_Photon_Cannon 3 8994
Protoss_Gateway 3 8675
Protoss_Assimilator 2 6650
Protoss_Cybernetics_Core 1 5451
Protoss_Zealot 7 9571
Protoss_Stargate 1 6468
Protoss_Citadel_of_Adun 1 7021
Protoss_Corsair 1 7605
Protoss_Templar_Archives 1 8183
Protoss_High_Templar 2 9703
9703
