Protoss_Nexus 3 9361
Protoss_Gateway 2 2430
Protoss_Zealot 12 9653
Protoss_Assimilator 1 5541
Protoss_Cybernetics_Core 1 5989
Protoss_Stargate 1 7096
Protoss_Dragoon 1 7255
Protoss_Forge 1 7831
Protoss_Corsair 2 8861
Protoss_Photon_Cannon 3 9927
9927
