Protoss_Nexus 1 0
Protoss_Gateway 2 2780
Protoss_Zealot 12 9796
Protoss_Forge 1 5973
Protoss_Photon_Cannon 2 9083
Protoss_Assimilator 1 8067
Protoss_Cybernetics_Core 1 9102
9796
