Special_Protoss_Temple 14 0
Protoss_Nexus 2 3775
Protoss_Forge 1 2097
Protoss_Photon_Cannon 2 9573
Protoss_Gateway 4 9112
Protoss_Assimilator 2 6974
Protoss_Cybernetics_Core 1 5220
Protoss_Zealot 8 9995
Protoss_Stargate 1 6231
Protoss_Citadel_of_Adun 1 6799
Protoss_Corsair 4 9599
9995
