Protoss_Nexus 2 3434
Protoss_Forge 1 2138
Protoss_Photon_Cannon 2 9436
Protoss_Gateway 4 7739
Protoss_Assimilator 2 8579
Protoss_Cybernetics_Core 1 5619
Protoss_Zealot 12 9651
Protoss_Citadel_of_Adun 1 6781
Protoss_Stargate 1 8337
Protoss_Templar_Archives 1 9283
Protoss_Corsair 1 9781
9781
