Special_Protoss_Temple 14 0
Protoss_Nexus 2 3149
Protoss_Forge 1 1887
Protoss_Photon_Cannon 3 9484
Protoss_Gateway 2 7788
Protoss_Assimilator 2 6128
Protoss_Zealot 2 6715
Protoss_Cybernetics_Core 1 5371
Protoss_Stargate 1 6472
Protoss_Citadel_of_Adun 1 7027
Protoss_Corsair 3 8959
Protoss_Templar_Archives 1 8113
Protoss_Dark_Templar 2 9101
Protoss_High_Templar 2 9929
9929
