Special_Protoss_Temple 14 0
Protoss_Nexus 2 3323
Protoss_Forge 1 2125
Protoss_Photon_Cannon 2 8132
Protoss_Gateway 2 8576
Protoss_Assimilator 2 7813
Protoss_Zealot 4 9795
Protoss_Cybernetics_Core 1 5879
Protoss_Stargate 1 6970
Protoss_Dragoon 2 8981
Protoss_Citadel_of_Adun 1 7410
Protoss_Corsair 3 9750
Protoss_Templar_Archives 1 8969
9795
