Protoss_Nexus 2 4201
Protoss_Forge 1 2292
Protoss_Photon_Cannon 3 8908
Protoss_Gateway 3 8575
Protoss_Assimilator 2 6264
Protoss_Cybernetics_Core 1 5589
Protoss_Zealot 4 9077
Protoss_Stargate 1 6611
Protoss_Citadel_of_Adun 1 7189
Protoss_Corsair 2 8789
Protoss_Templar_Archives 1 8183
Protoss_Dark_Templar 1 9203
9203
