Special_Protoss_Temple 14 0
Protoss_Nexus 2 3305
Protoss_Forge 2 7913
Protoss_Photon_Cannon 4 9758
Protoss_Gateway 3 9960
Protoss_Assimilator 2 8523
Protoss_Zealot 4 7919
Protoss_Cybernetics_Core 1 5585
Protoss_Stargate 1 6858
Protoss_Corsair 3 9629
Protoss_Citadel_of_Adun 1 8383
Protoss_Templar_Archives 1 9565
9960
