Protoss_Nexus 2 3371
Special_Protoss_Temple 14 0
Protoss_Forge 1 2009
Protoss_Photon_Cannon 3 9389
Protoss_Gateway 2 6861
Protoss_Assimilator 2 7301
Protoss_Zealot 11 9811
Protoss_Cybernetics_Core 1 5645
Protoss_Citadel_of_Adun 1 6633
Protoss_Stargate 2 8464
Protoss_Templar_Archives 1 8969
9811
