Protoss_Nexus 2 4105
Protoss_Forge 1 2841
Protoss_Photon_Cannon 4 9441
Protoss_Gateway 2 7533
Protoss_Assimilator 2 6642
Protoss_Cybernetics_Core 1 5707
Protoss_Zealot 8 9973
Protoss_Stargate 1 6836
Protoss_Citadel_of_Adun 1 7080
Protoss_Corsair 3 9925
Protoss_Templar_Archives 1 9578
9973
