Special_Protoss_Temple 30 0
Protoss_Nexus 1 0
Protoss_Gateway 3 4488
Protoss_Zealot 21 8567
Protoss_Forge 1 7953
Protoss_Photon_Cannon 3 9878
Protoss_Assimilator 1 9353
Protoss_Cybernetics_Core 1 9681
9878
