Protoss_Nexus 2 4007
Protoss_Forge 1 2261
Protoss_Photon_Cannon 5 9734
Protoss_Gateway 3 8790
Protoss_Assimilator 2 7124
Protoss_Cybernetics_Core 1 5839
Protoss_Zealot 7 9803
Protoss_Stargate 1 6983
Protoss_Citadel_of_Adun 1 7427
Protoss_Corsair 2 8831
Protoss_Templar_Archives 1 9284
9803
