Special_Protoss_Temple 14 0
Protoss_Nexus 2 3631
Protoss_Forge 1 2482
Protoss_Photon_Cannon 3 9884
Protoss_Gateway 2 9381
Protoss_Assimilator 2 8209
Protoss_Cybernetics_Core 1 6066
Protoss_Zealot 2 8135
Protoss_Stargate 1 7098
Protoss_Dragoon 1 7153
Protoss_Corsair 1 8239
Protoss_Citadel_of_Adun 1 8385
Protoss_Templar_Archives 1 9468
9884
