Special_Protoss_Temple 14 0
Protoss_Nexus 2 4074
Protoss_Forge 1 2647
Protoss_Photon_Cannon 4 9981
Protoss_Gateway 2 8143
Protoss_Assimilator 2 6953
Protoss_Cybernetics_Core 1 5438
Protoss_Zealot 6 9525
Protoss_Stargate 1 6746
Protoss_Citadel_of_Adun 1 7474
Protoss_Corsair 1 7893
Protoss_Templar_Archives 1 9116
9981
