Special_Protoss_Temple 14 0
Protoss_Nexus 1 0
Protoss_Gateway 3 9579
Protoss_Zealot 8 8520
Protoss_Forge 2 7539
Protoss_Photon_Cannon 4 8285
Protoss_Assimilator 1 7127
Protoss_Cybernetics_Core 1 8993
Protoss_Dragoon 1 9979
9979
