Protoss_Nexus 2 9557
Protoss_Gateway 2 2763
Protoss_Zealot 13 9787
Protoss_Assimilator 1 4397
Protoss_Cybernetics_Core 1 5609
Protoss_Citadel_of_Adun 1 6606
Protoss_Templar_Archives 1 8019
Protoss_High_Templar 2 9025
Protoss_Forge 1 9115
9787
