Protoss_Nexus 2 3119
Protoss_Forge 1 2488
Protoss_Photon_Cannon 4 9849
Protoss_Gateway 2 9235
Protoss_Assimilator 3 6957
Protoss_Cybernetics_Core 1 5376
Protoss_Stargate 1 6375
Protoss_Zealot 5 9763
Protoss_Corsair 5 9989
Protoss_Citadel_of_Adun 1 7945
9989
