Protoss_Nexus 2 3236
Protoss_Forge 1 2588
Protoss_Photon_Cannon 6 9975
Protoss_Gateway 2 8645
Protoss_Assimilator 2 6922
Protoss_Zealot 4 9091
Protoss_Cybernetics_Core 1 5974
Protoss_Stargate 1 6995
Protoss_Citadel_of_Adun 1 7629
Protoss_Corsair 3 9643
Protoss_Dragoon 2 9775
9975
