Protoss_Nexus 2 3449
Protoss_Forge 1 1919
Protoss_Photon_Cannon 3 8951
Protoss_Gateway 2 8286
Protoss_Assimilator 3 7803
Protoss_Cybernetics_Core 1 5225
Protoss_Zealot 6 9515
Protoss_Dragoon 1 6269
Protoss_Stargate 1 6277
Protoss_Citadel_of_Adun 1 6607
Protoss_Corsair 4 9295
Protoss_Templar_Archives 1 8174
Protoss_Dark_Templar 1 9437
9515
