Protoss_Nexus 2 4087
Protoss_Forge 1 2134
Protoss_Photon_Cannon 4 9732
Protoss_Gateway 2 7808
Protoss_Assimilator 2 6515
Protoss_Cybernetics_Core 1 5384
Protoss_Zealot 4 8445
Protoss_Stargate 1 6422
Protoss_Citadel_of_Adun 1 7093
Protoss_Corsair 2 8843
Protoss_Templar_Archives 1 8227
Protoss_High_Templar 2 9591
9732
