Special_Protoss_Temple 14 0
Protoss_Nexus 2 3446
Protoss_Forge 1 2019
Protoss_Gateway 3 8870
Protoss_Assimilator 2 7175
Protoss_Photon_Cannon 1 4515
Protoss_Cybernetics_Core 1 5247
Protoss_Zealot 6 9359
Protoss_Stargate 1 6245
Protoss_Corsair 4 9233
Protoss_Citadel_of_Adun 1 7549
Protoss_Templar_Archives 1 8610
9359
