Protoss_Nexus 1 0
Protoss_Gateway 2 2433
Protoss_Zealot 11 7436
Protoss_Assimilator 1 5133
Protoss_Cybernetics_Core 1 5587
Protoss_Stargate 1 7113
Protoss_Dragoon 1 7301
Protoss_Robotics_Facility 1 8092
Protoss_Corsair 1 8431
Protoss_Forge 1 9016
Protoss_Robotics_Support_Bay 1 9417
Protoss_Shuttle 1 9421
Protoss_Photon_Cannon 1 9823
9823
