Protoss_Nexus 2 7675
Protoss_Gateway 1 1849
Protoss_Zealot 4 6352
Protoss_Assimilator 2 9442
Protoss_Cybernetics_Core 1 3576
Protoss_Stargate 1 4587
Protoss_Dragoon 1 4753
Protoss_Forge 1 5363
Protoss_Corsair 4 9859
Protoss_Photon_Cannon 5 9944
Protoss_Robotics_Facility 1 8179
Protoss_Robotics_Support_Bay 1 9590
9944
