Protoss_Nexus 2 3579
Protoss_Forge 1 2101
Protoss_Gateway 4 7403
Protoss_Photon_Cannon 2 8618
Protoss_Assimilator 1 4658
Protoss_Zealot 5 8959
Protoss_Cybernetics_Core 1 5299
Protoss_Dragoon 8 9569
Protoss_Citadel_of_Adun 1 9281
Protoss_Ground_Weapons_1 1 9975
9975
