Protoss_Nexus 1 0
Protoss_Gateway 2 6607
Protoss_Assimilator 1 2608
Protoss_Zealot 3 4223
Protoss_Cybernetics_Core 1 3926
Protoss_Dragoon 9 9853
Protoss_Stargate 1 5295
Protoss_Corsair 4 9151
9853
