Special_Protoss_Temple 14 0
Protoss_Nexus 2 3303
Protoss_Forge 2 9332
Protoss_Photon_Cannon 2 3937
Protoss_Gateway 3 8061
Protoss_Assimilator 2 6599
Protoss_Cybernetics_Core 1 5400
Protoss_Zealot 10 9879
Protoss_Stargate 1 6431
Protoss_Citadel_of_Adun 1 7343
Protoss_Corsair 2 8675
Protoss_Templar_Archives 1 9404
9879
