Special_Protoss_Temple 30 0
Protoss_Nexus 2 3137
Protoss_Forge 2 8555
Protoss_Photon_Cannon 2 6860
Protoss_Gateway 2 8849
Protoss_Assimilator 2 6039
Protoss_Cybernetics_Core 1 4829
Protoss_Zealot 4 9603
Protoss_Stargate 1 5823
Protoss_Corsair 5 9641
Protoss_Citadel_of_Adun 1 7836
Protoss_Templar_Archives 1 9027
Protoss_Robotics_Facility 1 9924
9924
