Protoss_Nexus 2 3385
Protoss_Forge 1 2236
Protoss_Photon_Cannon 1 3469
Protoss_Gateway 6 9648
Protoss_Assimilator 2 5773
Protoss_Cybernetics_Core 1 5106
Protoss_Zealot 4 7709
Protoss_Citadel_of_Adun 1 6223
Protoss_Templar_Archives 1 7563
Protoss_Dark_Templar 4 9411
Protoss_High_Templar 1 9827
9827
