Protoss_Nexus 2 3817
Protoss_Forge 1 2467
Protoss_Photon_Cannon 2 9691
Protoss_Gateway 4 9574
Protoss_Assimilator 2 6602
Protoss_Zealot 4 8131
Protoss_Cybernetics_Core 1 6011
Protoss_Citadel_of_Adun 1 7202
Protoss_Templar_Archives 1 8247
Protoss_Dark_Templar 4 9989
9989
