Protoss_Nexus 2 3127
Protoss_Forge 1 2736
Protoss_Gateway 4 7154
Protoss_Assimilator 2 7297
Protoss_Photon_Cannon 4 9853
Protoss_Cybernetics_Core 1 4693
Protoss_Zealot 11 9766
Protoss_Citadel_of_Adun 1 6589
Protoss_Dragoon 1 8565
Protoss_Templar_Archives 1 8818
Protoss_Ground_Weapons_1 1 9429
9853
