Special_Protoss_Temple 14 0
Protoss_Nexus 2 3207
Protoss_Forge 1 2713
Protoss_Photon_Cannon 3 7725
Protoss_Gateway 6 9878
Protoss_Assimilator 2 6028
Protoss_Cybernetics_Core 1 5355
Protoss_Zealot 8 9973
Protoss_Stargate 1 6363
Protoss_Citadel_of_Adun 1 7186
Protoss_Corsair 2 8771
9973
