Protoss_Nexus 2 3161
Protoss_Forge 1 2527
Protoss_Photon_Cannon 2 9246
Protoss_Gateway 2 7947
Protoss_Assimilator 2 6052
Protoss_Cybernetics_Core 1 4845
Protoss_Zealot 4 7459
Protoss_Stargate 1 5849
Protoss_Citadel_of_Adun 1 6445
Protoss_Corsair 4 9891
Protoss_Templar_Archives 1 7528
Protoss_Dark_Templar 2 9097
Protoss_High_Templar 1 9849
9891
