Protoss_Nexus 2 3306
Protoss_Forge 1 2175
Protoss_Photon_Cannon 1 3585
Protoss_Gateway 4 9538
Protoss_Assimilator 2 7100
Protoss_Zealot 8 9583
Protoss_Cybernetics_Core 1 5712
Protoss_Dragoon 1 6691
Protoss_Stargate 1 6738
Protoss_Citadel_of_Adun 1 7600
Protoss_Corsair 1 7965
Protoss_Templar_Archives 1 8939
Protoss_Dark_Templar 1 9935
9935
