Special_Protoss_Temple 14 0
Protoss_Nexus 2 3989
Protoss_Forge 1 2243
Protoss_Photon_Cannon 2 3152
Protoss_Assimilator 3 6944
Protoss_Gateway 4 8089
Protoss_Cybernetics_Core 1 5616
Protoss_Zealot 8 9205
Protoss_Citadel_of_Adun 1 6673
Protoss_Templar_Archives 1 7730
Protoss_High_Templar 4 9884
9884
