Special_Protoss_Temple 14 0
Protoss_Nexus 2 3285
Protoss_Forge 1 2317
Protoss_Photon_Cannon 3 8245
Protoss_Assimilator 2 7025
Protoss_Gateway 3 9343
Protoss_Cybernetics_Core 1 5907
Protoss_Zealot 7 9847
Protoss_Stargate 1 6942
Protoss_Citadel_of_Adun 1 7686
Protoss_Corsair 3 9663
Protoss_Templar_Archives 1 9553
9847
