Special_Protoss_Temple 14 0
Protoss_Nexus 2 3359
Protoss_Forge 1 2441
Protoss_Photon_Cannon 2 9637
Protoss_Gateway 3 7997
Protoss_Assimilator 2 7194
Protoss_Cybernetics_Core 1 5019
Protoss_Zealot 11 9887
Protoss_Stargate 1 6083
Protoss_Dragoon 1 6377
Protoss_Citadel_of_Adun 1 6659
Protoss_Corsair 2 8145
9887
