Protoss_Nexus 2 3893
Protoss_Forge 1 1899
Protoss_Photon_Cannon 2 3070
Protoss_Gateway 4 7869
Protoss_Assimilator 2 9684
Protoss_Zealot 15 9959
Protoss_Cybernetics_Core 1 5387
Protoss_Stargate 1 6415
Protoss_Citadel_of_Adun 1 6811
Protoss_Corsair 1 7573
9959
