Protoss_Nexus 2 4265
Protoss_Forge 1 2073
Protoss_Photon_Cannon 6 9991
Protoss_Gateway 1 4585
Protoss_Assimilator 2 7180
Protoss_Zealot 3 9515
Protoss_Cybernetics_Core 1 5845
Protoss_Stargate 1 6908
Protoss_Corsair 2 9277
Protoss_Robotics_Facility 1 8558
Protoss_Robotics_Support_Bay 1 9859
9991
