Protoss_Nexus 3 9835
Protoss_Forge 1 2257
Protoss_Photon_Cannon 2 3501
Protoss_Gateway 3 9484
Protoss_Assimilator 2 6118
Protoss_Cybernetics_Core 1 5531
Protoss_Zealot 3 8701
Protoss_Stargate 1 6637
Protoss_Dragoon 1 6721
Protoss_Citadel_of_Adun 1 7333
Protoss_Corsair 3 9561
Protoss_Templar_Archives 1 8418
Protoss_Dark_Templar 2 9945
9945
