Protoss_Nexus 2 3285
Protoss_Forge 1 2838
Protoss_Photon_Cannon 2 4277
Protoss_Gateway 3 7755
Protoss_Assimilator 2 5430
Protoss_Zealot 10 9509
Protoss_Cybernetics_Core 1 6035
Protoss_Citadel_of_Adun 1 7027
Protoss_Templar_Archives 1 8682
Protoss_High_Templar 2 9691
9691
