Protoss_Nexus 2 4028
Protoss_Forge 1 2494
Protoss_Photon_Cannon 3 7635
Protoss_Gateway 3 9179
Protoss_Assimilator 2 8813
Protoss_Cybernetics_Core 1 5575
Protoss_Zealot 7 9667
Protoss_Stargate 1 6689
Protoss_Corsair 1 7915
Protoss_Citadel_of_Adun 1 8273
9667
