Protoss_Nexus 2 2825
Protoss_Forge 1 3420
Protoss_Gateway 1 4289
Protoss_Photon_Cannon 3 9374
Protoss_Assimilator 2 5642
Protoss_Zealot 5 9619
Protoss_Cybernetics_Core 1 5600
Protoss_Stargate 2 7678
Protoss_Robotics_Facility 1 7210
Protoss_Corsair 5 9949
Protoss_Citadel_of_Adun 1 8280
Protoss_Shuttle 1 8517
Protoss_Robotics_Support_Bay 1 8660
Protoss_Reaver 1 9543
9949
