Protoss_Nexus 2 3945
Protoss_Forge 1 2345
Protoss_Photon_Cannon 4 9545
Protoss_Gateway 2 7889
Protoss_Assimilator 2 6549
Protoss_Cybernetics_Core 1 5341
Protoss_Zealot 3 6855
Protoss_Stargate 1 6354
Protoss_Citadel_of_Adun 1 7157
Protoss_Corsair 3 9951
Protoss_Templar_Archives 1 8428
Protoss_Dragoon 2 9291
Protoss_High_Templar 1 9827
9951
