Protoss_Nexus 2 3609
Protoss_Forge 1 2088
Protoss_Photon_Cannon 1 2854
Protoss_Gateway 4 8513
Protoss_Assimilator 2 6948
Protoss_Zealot 7 9993
Protoss_Cybernetics_Core 1 5420
Protoss_Stargate 1 6435
Protoss_Citadel_of_Adun 1 6894
Protoss_Corsair 1 7663
Protoss_Templar_Archives 1 8077
Protoss_High_Templar 2 9345
9993
