Protoss_Nexus 1 0
Protoss_Gateway 2 2323
Protoss_Zealot 7 5281
Protoss_Assimilator 1 4791
Protoss_Cybernetics_Core 1 6127
Protoss_Forge 1 7204
Protoss_Citadel_of_Adun 1 8542
8542
