Protoss_Nexus 2 3383
Protoss_Forge 1 2265
Protoss_Gateway 3 7249
Protoss_Photon_Cannon 5 9350
Protoss_Assimilator 2 5153
Protoss_Cybernetics_Core 1 5460
Protoss_Stargate 1 6443
Protoss_Citadel_of_Adun 1 6833
Protoss_Corsair 3 9577
Protoss_Templar_Archives 1 7937
Protoss_High_Templar 2 8965
9577
