Protoss_Nexus 2 4035
Protoss_Forge 1 2681
Protoss_Photon_Cannon 3 9587
Protoss_Gateway 3 8315
Protoss_Assimilator 2 6231
Protoss_Cybernetics_Core 1 5924
Protoss_Zealot 10 9959
Protoss_Stargate 1 7028
Protoss_Citadel_of_Adun 1 7419
Protoss_Corsair 2 8779
9959
