Protoss_Nexus 2 3351
Protoss_Forge 1 2612
Protoss_Photon_Cannon 3 9632
Protoss_Gateway 3 9887
Protoss_Assimilator 2 7081
Protoss_Zealot 5 9617
Protoss_Cybernetics_Core 1 5657
Protoss_Stargate 1 7315
Protoss_Citadel_of_Adun 1 8093
Protoss_Dragoon 1 8263
Protoss_Corsair 3 9965
9965
