Protoss_Nexus 2 3577
Protoss_Forge 1 2255
Protoss_Photon_Cannon 2 7979
Protoss_Gateway 3 9913
Protoss_Assimilator 2 6281
Protoss_Zealot 11 9973
Protoss_Cybernetics_Core 1 5463
Protoss_Citadel_of_Adun 1 6635
Protoss_Stargate 1 8839
Protoss_Templar_Archives 1 8927
Protoss_Ground_Weapons_1 1 9973
9973
