Protoss_Nexus 2 4027
Protoss_Forge 1 2547
Protoss_Photon_Cannon 4 9382
Protoss_Gateway 2 7707
Protoss_Assimilator 2 6203
Protoss_Zealot 6 9045
Protoss_Cybernetics_Core 1 5427
Protoss_Stargate 1 6593
Protoss_Dragoon 1 6835
Protoss_Corsair 3 9611
Protoss_Citadel_of_Adun 1 7782
Protoss_Templar_Archives 1 9759
9759
