Protoss_Nexus 2 4060
Protoss_Forge 1 2245
Protoss_Photon_Cannon 3 9066
Protoss_Gateway 3 9317
Protoss_Assimilator 2 7529
Protoss_Cybernetics_Core 1 5493
Protoss_Zealot 5 9591
Protoss_Stargate 1 6641
Protoss_Citadel_of_Adun 1 7383
Protoss_Dragoon 1 7733
Protoss_Corsair 3 9457
Protoss_Templar_Archives 1 8989
9591
