Protoss_Nexus 2 4582
Protoss_Forge 1 2153
Protoss_Photon_Cannon 4 8368
Protoss_Gateway 1 4953
Protoss_Assimilator 2 7254
Protoss_Cybernetics_Core 1 6170
Protoss_Zealot 3 8141
Protoss_Stargate 2 8194
Protoss_Dragoon 1 7389
Protoss_Corsair 4 9713
Protoss_Citadel_of_Adun 1 8824
9713
