Protoss_Nexus 2 3253
Protoss_Forge 1 2350
Protoss_Photon_Cannon 1 3539
Protoss_Gateway 4 7603
Protoss_Assimilator 2 5601
Protoss_Cybernetics_Core 1 4975
Protoss_Zealot 15 9941
Protoss_Stargate 1 6112
Protoss_Citadel_of_Adun 1 6667
Protoss_Corsair 2 8107
Protoss_Templar_Archives 1 9679
9941
