Protoss_Nexus 2 3243
Protoss_Forge 1 2367
Protoss_Photon_Cannon 2 3825
Protoss_Gateway 3 9099
Protoss_Assimilator 2 6723
Protoss_Cybernetics_Core 1 5773
Protoss_Zealot 5 9483
Protoss_Dragoon 1 6923
Protoss_Stargate 1 6924
Protoss_Citadel_of_Adun 1 7511
Protoss_Corsair 3 9819
Protoss_Templar_Archives 1 9193
9819
