Protoss_Nexus 2 4280
Protoss_Forge 1 1942
Protoss_Photon_Cannon 5 9653
Protoss_Gateway 2 9906
Protoss_Assimilator 1 5074
Protoss_Zealot 3 8257
Protoss_Cybernetics_Core 1 7434
Protoss_Stargate 1 8581
Protoss_Citadel_of_Adun 2 9420
9906
