Special_Protoss_Temple 14 0
Protoss_Nexus 2 3223
Protoss_Forge 1 2597
Protoss_Photon_Cannon 3 9180
Protoss_Gateway 2 9693
Protoss_Assimilator 2 6653
Protoss_Cybernetics_Core 1 5366
Protoss_Zealot 7 9803
Protoss_Stargate 1 6471
Protoss_Corsair 4 9537
Protoss_Citadel_of_Adun 1 8411
9803
