Protoss_Nexus 2 4091
Protoss_Forge 1 2128
Protoss_Photon_Cannon 4 9659
Protoss_Gateway 1 4423
Protoss_Assimilator 2 7229
Protoss_Zealot 6 9823
Protoss_Cybernetics_Core 1 5722
Protoss_Stargate 1 6985
Protoss_Dragoon 1 7265
Protoss_Citadel_of_Adun 1 7716
Protoss_Corsair 2 8819
Protoss_Templar_Archives 1 9021
9823
