Protoss_Nexus 1 0
Protoss_Assimilator 1 1802
Protoss_Gateway 1 2387
Protoss_Cybernetics_Core 1 3378
Protoss_Stargate 1 4510
Protoss_Robotics_Facility 1 5472
Protoss_Robotics_Support_Bay 1 7324
Protoss_Shield_Battery 1 9919
9919
