Protoss_Nexus 2 3988
Protoss_Forge 1 2293
Protoss_Photon_Cannon 6 9755
Protoss_Gateway 3 8137
Protoss_Assimilator 2 7498
Protoss_Cybernetics_Core 1 5311
Protoss_Zealot 6 9143
Protoss_Stargate 1 6373
Protoss_Dragoon 1 6631
Protoss_Citadel_of_Adun 1 7101
Protoss_Corsair 1 7639
Protoss_Templar_Archives 1 8662
Protoss_Dark_Templar 1 9975
Protoss_High_Templar 1 9989
9989
