Special_Protoss_Temple 14 0
Protoss_Nexus 2 2860
Protoss_Gateway 6 9758
Protoss_Forge 1 3739
Protoss_Assimilator 2 6440
Protoss_Photon_Cannon 1 4499
Protoss_Cybernetics_Core 1 4937
Protoss_Zealot 4 9737
Protoss_Stargate 1 6163
Protoss_Dragoon 1 6179
Protoss_Citadel_of_Adun 1 6799
Protoss_Corsair 1 7295
Protoss_Templar_Archives 1 8014
Protoss_Dark_Templar 1 9003
Protoss_High_Templar 2 9413
9758
