Protoss_Nexus 2 3547
Protoss_Forge 1 1945
Protoss_Photon_Cannon 2 6709
Protoss_Gateway 3 8278
Protoss_Assimilator 2 5690
Protoss_Cybernetics_Core 1 4915
Protoss_Stargate 1 6069
Protoss_Zealot 7 9471
Protoss_Citadel_of_Adun 1 7057
Protoss_Corsair 2 7905
Protoss_Templar_Archives 1 9423
9471
