Protoss_Nexus 2 5692
Protoss_Gateway 2 2349
Protoss_Zealot 11 6367
Protoss_Assimilator 2 8272
Protoss_Forge 1 6722
Protoss_Cybernetics_Core 1 7549
Protoss_Photon_Cannon 3 9919
Protoss_Dragoon 1 8563
Protoss_Stargate 1 8967
Protoss_Citadel_of_Adun 1 9314
9919
