Protoss_Nexus 2 9449
Protoss_Gateway 1 1908
Protoss_Assimilator 1 2246
Protoss_Zealot 5 7211
Protoss_Cybernetics_Core 1 3823
Protoss_Dragoon 2 5657
Protoss_Stargate 1 5296
Protoss_Citadel_of_Adun 1 6336
Protoss_Corsair 3 7901
Protoss_Templar_Archives 1 7433
Protoss_Forge 1 7705
Protoss_Dark_Templar 1 8461
Protoss_Photon_Cannon 2 9752
Protoss_High_Templar 1 9279
9752
