Protoss_Nexus 2 3835
Protoss_Forge 1 2594
Protoss_Photon_Cannon 5 8882
Protoss_Gateway 2 9953
Protoss_Assimilator 2 6627
Protoss_Zealot 9 9685
Protoss_Cybernetics_Core 1 5037
Protoss_Stargate 1 6139
Protoss_Citadel_of_Adun 1 7065
Protoss_Corsair 4 9569
Protoss_Templar_Archives 1 9864
9953
