Protoss_Nexus 1 0
Protoss_Gateway 2 6068
Protoss_Assimilator 1 2534
Protoss_Zealot 12 9083
Protoss_Cybernetics_Core 1 3789
Protoss_Stargate 1 5023
Protoss_Corsair 1 6159
Protoss_Citadel_of_Adun 1 6610
Protoss_Forge 1 7557
Protoss_Templar_Archives 1 8449
Protoss_Photon_Cannon 2 9807
Protoss_Dark_Templar 1 9667
9807
