Protoss_Nexus 2 3803
Protoss_Forge 1 2514
Protoss_Photon_Cannon 4 9760
Protoss_Gateway 3 9455
Protoss_Assimilator 2 7763
Protoss_Cybernetics_Core 1 5508
Protoss_Dragoon 1 6485
Protoss_Stargate 1 6697
Protoss_Citadel_of_Adun 1 7003
Protoss_Zealot 2 7935
Protoss_Corsair 3 9651
Protoss_Templar_Archives 1 8163
Protoss_Dark_Templar 1 9415
9760
