Protoss_Nexus 2 6483
Protoss_Gateway 2 2451
Protoss_Zealot 18 9693
Protoss_Assimilator 1 7312
Protoss_Forge 1 8080
Protoss_Photon_Cannon 2 9929
Protoss_Cybernetics_Core 1 9271
9929
