Protoss_Nexus 2 3063
Protoss_Forge 1 3349
Protoss_Gateway 5 9637
Protoss_Photon_Cannon 5 9919
Protoss_Assimilator 2 7446
Protoss_Zealot 10 9821
Protoss_Cybernetics_Core 1 5880
Protoss_Citadel_of_Adun 1 6983
Protoss_Stargate 1 7076
Protoss_Corsair 1 8377
9919
