Special_Protoss_Temple 14 0
Protoss_Nexus 2 3918
Protoss_Forge 1 2366
Protoss_Photon_Cannon 3 9898
Protoss_Gateway 5 9233
Protoss_Assimilator 1 4739
Protoss_Cybernetics_Core 1 5227
Protoss_Zealot 11 9697
Protoss_Citadel_of_Adun 1 6495
Protoss_Templar_Archives 1 8560
9898
