Protoss_Nexus 2 3239
Protoss_Forge 1 2279
Protoss_Gateway 4 9971
Protoss_Photon_Cannon 8 9854
Protoss_Assimilator 2 9337
Protoss_Cybernetics_Core 1 4840
Protoss_Zealot 12 9551
Protoss_Citadel_of_Adun 1 6706
Protoss_Templar_Archives 1 8097
Protoss_Ground_Weapons_1 1 9875
9971
