Protoss_Nexus 2 3282
Protoss_Forge 1 2227
Protoss_Photon_Cannon 2 3937
Protoss_Gateway 2 6824
Protoss_Assimilator 2 6648
Protoss_Zealot 11 9859
Protoss_Cybernetics_Core 1 5699
Protoss_Stargate 1 7186
Protoss_Citadel_of_Adun 1 7496
Protoss_Corsair 1 8361
9859
