Protoss_Nexus 3 4020
Protoss_Forge 1 2341
Protoss_Photon_Cannon 3 9392
Protoss_Gateway 4 9825
Protoss_Assimilator 2 6057
Protoss_Cybernetics_Core 1 5501
Protoss_Zealot 7 9469
Protoss_Stargate 1 6550
Protoss_Citadel_of_Adun 1 7300
Protoss_Corsair 1 7709
Protoss_Templar_Archives 1 8942
9825
