Protoss_Nexus 2 4014
Protoss_Forge 1 2341
Protoss_Photon_Cannon 2 3699
Protoss_Gateway 4 9501
Protoss_Assimilator 2 5966
Protoss_Cybernetics_Core 1 5379
Protoss_Zealot 8 9645
Protoss_Stargate 1 6481
Protoss_Citadel_of_Adun 1 7197
Protoss_Corsair 2 8313
Protoss_Templar_Archives 1 9212
9645
