Protoss_Nexus 2 3822
Protoss_Forge 1 2289
Protoss_Photon_Cannon 1 2983
Protoss_Gateway 4 8616
Protoss_Assimilator 2 5186
Protoss_Zealot 2 6179
Protoss_Cybernetics_Core 1 5463
Protoss_Dragoon 11 9939
Protoss_Stargate 1 9119
9939
