Protoss_Nexus 2 8971
Protoss_Gateway 2 9369
Protoss_Assimilator 1 2456
Protoss_Zealot 3 6189
Protoss_Cybernetics_Core 1 3724
Protoss_Stargate 1 4922
Protoss_Citadel_of_Adun 1 5059
Protoss_Dragoon 1 5287
Protoss_Corsair 1 6053
Protoss_Templar_Archives 1 6168
Protoss_Forge 1 6519
Protoss_Dark_Templar 1 7505
Protoss_Photon_Cannon 4 9756
Protoss_High_Templar 2 9289
Psionic_Storm 1 9931
9931
