Protoss_Nexus 2 3889
Protoss_Forge 1 2169
Protoss_Photon_Cannon 3 9605
Protoss_Gateway 4 8349
Protoss_Assimilator 2 6619
Protoss_Zealot 10 9821
Protoss_Cybernetics_Core 1 5381
Protoss_Stargate 1 6451
Protoss_Citadel_of_Adun 1 6855
Protoss_Templar_Archives 1 9078
9821
