Protoss_Nexus 2 3645
Protoss_Forge 1 2103
Protoss_Gateway 2 9239
Protoss_Photon_Cannon 8 9981
Protoss_Assimilator 2 7077
Protoss_Cybernetics_Core 1 5359
Protoss_Zealot 3 7225
Protoss_Stargate 1 6409
Protoss_Citadel_of_Adun 1 6946
Protoss_Corsair 3 9283
Protoss_Templar_Archives 1 8171
Protoss_Dark_Templar 1 9199
9981
