Protoss_Nexus 2 4360
Protoss_Forge 1 1859
Protoss_Photon_Cannon 2 4535
Protoss_Gateway 2 8818
Protoss_Assimilator 2 7833
Protoss_Cybernetics_Core 1 5949
Protoss_Zealot 4 8589
Protoss_Stargate 1 6959
Protoss_Citadel_of_Adun 1 7108
Protoss_Corsair 1 8289
Protoss_Templar_Archives 1 8553
Protoss_Robotics_Facility 1 9218
Protoss_Dark_Templar 2 9857
9857
