Protoss_Nexus 2 3649
Protoss_Forge 1 2716
Protoss_Photon_Cannon 3 9785
Protoss_Assimilator 2 7467
Protoss_Gateway 3 9138
Protoss_Zealot 12 9793
Protoss_Cybernetics_Core 1 5639
Protoss_Stargate 1 6684
Protoss_Citadel_of_Adun 1 7387
Protoss_Corsair 3 9397
9793
