Protoss_Nexus 2 3220
Protoss_Forge 2 3663
Protoss_Gateway 3 8396
Protoss_Photon_Cannon 2 7181
Protoss_Assimilator 2 6418
Protoss_Zealot 9 9891
Protoss_Cybernetics_Core 1 5642
Protoss_Stargate 1 6663
Protoss_Corsair 2 8955
Protoss_Dragoon 1 7933
Protoss_Citadel_of_Adun 1 7967
Protoss_Templar_Archives 1 9427
9891
