Protoss_Nexus 2 3723
Protoss_Forge 1 2096
Protoss_Photon_Cannon 5 7809
Protoss_Gateway 5 9631
Protoss_Assimilator 2 9131
Protoss_Zealot 8 9921
Protoss_Cybernetics_Core 1 6667
Protoss_Dragoon 1 7647
Protoss_Citadel_of_Adun 1 8041
9921
