Protoss_Nexus 2 2969
Protoss_Forge 2 3259
Protoss_Gateway 2 7593
Protoss_Photon_Cannon 5 9527
Protoss_Assimilator 2 6221
Protoss_Cybernetics_Core 1 5461
Protoss_Zealot 3 8615
Protoss_Stargate 1 6655
Protoss_Citadel_of_Adun 1 7015
Protoss_Corsair 3 9227
Protoss_Templar_Archives 1 8207
Protoss_High_Templar 1 9247
Protoss_Dark_Templar 1 9651
9651
