Protoss_Nexus 3 6874
Protoss_Gateway 2 2515
Protoss_Zealot 12 9383
Protoss_Assimilator 1 6667
Protoss_Forge 1 7075
Protoss_Photon_Cannon 5 9749
Protoss_Cybernetics_Core 1 8663
9749
