Protoss_Nexus 2 3223
Protoss_Forge 1 2280
Protoss_Photon_Cannon 2 5736
Protoss_Gateway 3 8830
Protoss_Assimilator 1 4191
Protoss_Zealot 8 9955
Protoss_Cybernetics_Core 1 6985
Protoss_Stargate 1 8008
Protoss_Citadel_of_Adun 1 8185
Protoss_Corsair 1 9199
9955
