Protoss_Nexus 1 0
Protoss_Gateway 1 2043
Protoss_Assimilator 1 2323
Protoss_Cybernetics_Core 1 3134
Protoss_Forge 1 3851
Protoss_Stargate 1 4553
Protoss_Photon_Cannon 3 7201
Protoss_Corsair 2 7066
Protoss_Zealot 3 9566
9566
