Protoss_Nexus 2 3393
Protoss_Forge 1 2492
Protoss_Photon_Cannon 3 9499
Protoss_Gateway 3 9945
Protoss_Assimilator 2 7507
Protoss_Zealot 6 9535
Protoss_Cybernetics_Core 1 5599
Protoss_Stargate 1 6809
Protoss_Dragoon 1 7169
Protoss_Citadel_of_Adun 1 7538
Protoss_Corsair 1 8557
Protoss_Templar_Archives 1 8877
9945
