Protoss_Nexus 2 3462
Protoss_Forge 1 2819
Protoss_Photon_Cannon 6 9699
Protoss_Gateway 2 8595
Protoss_Assimilator 2 6933
Protoss_Zealot 7 9503
Protoss_Cybernetics_Core 1 5894
Protoss_Stargate 1 6983
Protoss_Citadel_of_Adun 1 7205
Protoss_Corsair 2 8933
Protoss_Templar_Archives 1 8554
Protoss_Dark_Templar 2 9895
9895
