Protoss_Nexus 2 8343
Protoss_Gateway 1 1932
Protoss_Assimilator 1 2443
Protoss_Zealot 5 8941
Protoss_Cybernetics_Core 1 4798
Protoss_Forge 1 5541
Protoss_Dragoon 1 5861
Protoss_Citadel_of_Adun 1 6078
Protoss_Photon_Cannon 2 8158
Protoss_Templar_Archives 1 7396
Protoss_High_Templar 2 9953
9953
