Protoss_Nexus 2 4461
Protoss_Gateway 1 1824
Protoss_Forge 1 2394
Protoss_Zealot 5 9761
Protoss_Photon_Cannon 8 9930
Protoss_Assimilator 2 7429
Protoss_Cybernetics_Core 1 5871
Protoss_Stargate 1 6958
Protoss_Corsair 3 9535
Protoss_Citadel_of_Adun 1 8803
Protoss_Shield_Battery 1 9539
9930
