Protoss_Nexus 2 4410
Protoss_Gateway 5 9784
Protoss_Forge 1 2420
Protoss_Zealot 4 7639
Protoss_Photon_Cannon 4 9699
Protoss_Assimilator 2 6158
Protoss_Cybernetics_Core 1 5517
Protoss_Citadel_of_Adun 1 6659
Protoss_Templar_Archives 1 7959
Protoss_High_Templar 4 9903
Protoss_Dark_Templar 1 9385
9903
