Protoss_Nexus 2 9318
Protoss_Gateway 2 6289
Protoss_Assimilator 1 2474
Protoss_Zealot 5 6246
Protoss_Cybernetics_Core 1 4393
Protoss_Citadel_of_Adun 1 5527
Protoss_Forge 1 7708
9318
