Protoss_Nexus 1 0
Protoss_Gateway 2 2615
Protoss_Zealot 11 8393
Protoss_Forge 1 4759
Protoss_Assimilator 1 5501
Protoss_Photon_Cannon 1 6465
Protoss_Cybernetics_Core 1 7499
Protoss_Dragoon 1 8489
Protoss_Citadel_of_Adun 1 9013
9013
