Protoss_Nexus 2 3883
Protoss_Forge 1 1917
Protoss_Photon_Cannon 5 8387
Protoss_Gateway 3 9748
Protoss_Assimilator 2 6380
Protoss_Zealot 3 8435
Protoss_Cybernetics_Core 1 5842
Protoss_Dragoon 2 9813
Protoss_Stargate 1 6963
Protoss_Citadel_of_Adun 1 7987
Protoss_Corsair 4 9955
Protoss_Templar_Archives 1 9081
9955
