Protoss_Nexus 1 0
Protoss_Gateway 1 1902
Protoss_Assimilator 1 2258
Protoss_Cybernetics_Core 1 3012
Protoss_Forge 1 3876
Protoss_Stargate 1 4303
Protoss_Photon_Cannon 3 7094
Protoss_Corsair 1 5441
Protoss_Robotics_Facility 1 8068
8068
