Protoss_Nexus 2 5861
Protoss_Gateway 2 7126
Protoss_Forge 1 2777
Protoss_Zealot 7 9445
Protoss_Photon_Cannon 2 6251
Protoss_Assimilator 2 9049
Protoss_Cybernetics_Core 1 7398
Protoss_Dragoon 1 8413
Protoss_Stargate 1 8503
Protoss_Citadel_of_Adun 1 8957
Protoss_Corsair 1 9741
9741
