Protoss_Nexus 2 3801
Protoss_Forge 1 2021
Protoss_Photon_Cannon 7 9702
Protoss_Gateway 1 4179
Protoss_Assimilator 1 4484
Protoss_Zealot 5 8611
Protoss_Cybernetics_Core 1 5291
Protoss_Stargate 1 6499
Protoss_Corsair 3 9517
Protoss_Citadel_of_Adun 1 7874
9702
