Protoss_Nexus 2 2911
Protoss_Forge 1 3245
Protoss_Photon_Cannon 3 9603
Protoss_Gateway 2 8182
Protoss_Assimilator 2 6021
Protoss_Cybernetics_Core 1 5487
Protoss_Zealot 4 8441
Protoss_Stargate 1 6546
Protoss_Dragoon 1 6813
Protoss_Citadel_of_Adun 1 7277
Protoss_Corsair 4 9767
Protoss_Templar_Archives 1 8284
Protoss_Dark_Templar 2 9299
9767
