Protoss_Nexus 2 8321
Protoss_Gateway 2 5388
Protoss_Assimilator 1 2664
Protoss_Zealot 5 9958
Protoss_Cybernetics_Core 1 4043
Protoss_Citadel_of_Adun 1 5323
Protoss_Templar_Archives 1 6328
Protoss_Forge 1 6628
Protoss_Dark_Templar 2 7346
Protoss_High_Templar 2 8396
Protoss_Photon_Cannon 2 9050
Protoss_Archon 1 9243
9958
