Protoss_Nexus 2 5970
Protoss_Gateway 4 7609
Protoss_Zealot 13 9881
Protoss_Forge 1 3848
Protoss_Photon_Cannon 3 9798
Protoss_Assimilator 2 9535
Protoss_Cybernetics_Core 1 6715
Protoss_Citadel_of_Adun 1 7750
9881
