Protoss_Nexus 1 0
Protoss_Gateway 2 2448
Protoss_Assimilator 1 3107
Protoss_Zealot 9 9266
Protoss_Cybernetics_Core 1 3924
Protoss_Stargate 1 5044
Protoss_Dragoon 1 5461
Protoss_Citadel_of_Adun 1 5693
Protoss_Corsair 1 6196
9266
