Protoss_Nexus 2 6237
Protoss_Gateway 3 6763
Protoss_Zealot 10 8006
Protoss_Assimilator 1 5193
Protoss_Cybernetics_Core 1 5568
Protoss_Forge 1 7618
Protoss_Photon_Cannon 1 8357
Protoss_Citadel_of_Adun 1 8643
Protoss_Templar_Archives 1 9673
Protoss_Robotics_Facility 1 9863
9863
