Protoss_Nexus 2 9908
Protoss_Gateway 2 5482
Protoss_Assimilator 1 2390
Protoss_Zealot 8 9216
Protoss_Cybernetics_Core 1 3778
Protoss_Dragoon 1 4766
Protoss_Citadel_of_Adun 1 5205
Protoss_Templar_Archives 1 6484
Protoss_High_Templar 4 8456
Protoss_Forge 1 8085
Protoss_Archon 2 9238
Protoss_Photon_Cannon 1 9294
9908
