Protoss_Nexus 2 4948
Protoss_Forge 1 2429
Protoss_Photon_Cannon 4 5204
Protoss_Gateway 1 5524
Protoss_Assimilator 2 8358
Protoss_Zealot 5 9351
Protoss_Cybernetics_Core 1 6975
Protoss_Citadel_of_Adun 1 8108
Protoss_Robotics_Facility 1 8927
Protoss_Templar_Archives 1 9667
9667
