Protoss_Nexus 2 8958
Protoss_Gateway 2 6488
Protoss_Assimilator 1 2583
Protoss_Zealot 6 7391
Protoss_Cybernetics_Core 1 4086
Protoss_Dragoon 1 5338
Protoss_Citadel_of_Adun 1 6062
Protoss_Templar_Archives 1 7123
Protoss_Forge 1 7863
Protoss_High_Templar 4 9326
Protoss_Archon 1 9035
Protoss_Photon_Cannon 3 9847
9847
