Protoss_Nexus 1 0
Protoss_Gateway 2 2568
Protoss_Zealot 10 6201
Protoss_Assimilator 1 5468
Protoss_Cybernetics_Core 1 6706
Protoss_Dragoon 1 7761
Protoss_Stargate 1 8076
8076
