Protoss_Nexus 2 6641
Protoss_Gateway 3 7589
Protoss_Zealot 13 9645
Protoss_Assimilator 1 4690
Protoss_Cybernetics_Core 1 5144
Protoss_Citadel_of_Adun 1 7136
Protoss_Forge 1 9531
9645
