Protoss_Nexus 2 3614
Protoss_Forge 1 2023
Protoss_Gateway 3 7698
Protoss_Photon_Cannon 2 9917
Protoss_Assimilator 2 7975
Protoss_Cybernetics_Core 1 5289
Protoss_Zealot 9 9427
Protoss_Citadel_of_Adun 1 6596
Protoss_Dragoon 1 6783
Protoss_Templar_Archives 1 9245
Protoss_Ground_Weapons_1 1 9995
9995
