Protoss_Nexus 2 3463
Protoss_Forge 1 2405
Protoss_Photon_Cannon 7 8528
Protoss_Gateway 1 4493
Protoss_Assimilator 2 8717
Protoss_Cybernetics_Core 1 5551
Protoss_Zealot 4 9696
Protoss_Stargate 1 6610
Protoss_Corsair 3 8950
Protoss_Citadel_of_Adun 1 8288
Protoss_Templar_Archives 1 9678
9696
