Protoss_Nexus 2 8193
Protoss_Gateway 2 2508
Protoss_Zealot 14 9441
Protoss_Assimilator 1 6000
Protoss_Forge 1 6848
Protoss_Cybernetics_Core 1 8738
Protoss_Photon_Cannon 1 9088
9441
