Protoss_Nexus 2 3308
Protoss_Forge 1 2119
Protoss_Gateway 5 8178
Protoss_Photon_Cannon 2 9583
Protoss_Assimilator 2 8738
Protoss_Zealot 13 9301
Protoss_Cybernetics_Core 1 5535
Protoss_Citadel_of_Adun 1 6550
Protoss_Dragoon 1 6676
Protoss_Templar_Archives 1 8799
Protoss_Ground_Weapons_1 1 9816
Protoss_High_Templar 1 9996
9996
