Protoss_Nexus 1 0
Protoss_Gateway 2 2430
Protoss_Zealot 9 6531
Protoss_Shield_Battery 1 3190
Protoss_Assimilator 1 7180
Protoss_Forge 1 7503
Protoss_Cybernetics_Core 1 8343
Protoss_Photon_Cannon 2 9981
Protoss_Citadel_of_Adun 1 9393
9981
