Protoss_Nexus 1 0
Protoss_Gateway 1 1914
Protoss_Assimilator 1 2475
Protoss_Forge 1 2977
Protoss_Photon_Cannon 2 7252
Protoss_Cybernetics_Core 1 4462
Protoss_Dragoon 1 5441
Protoss_Ground_Weapons_1 1 8689
Protoss_Zealot 1 9083
9083
