Protoss_Nexus 2 8668
Protoss_Gateway 1 1815
Protoss_Assimilator 1 2404
Protoss_Zealot 4 7436
Protoss_Cybernetics_Core 1 3832
Protoss_Dragoon 1 4826
Protoss_Stargate 1 5187
Protoss_Forge 1 5955
Protoss_Corsair 1 6381
Protoss_Photon_Cannon 3 9753
Protoss_Citadel_of_Adun 1 6958
Protoss_Robotics_Facility 1 7979
Protoss_Templar_Archives 1 8338
Protoss_Robotics_Support_Bay 1 9365
Protoss_Dark_Templar 1 9496
9753
