Protoss_Nexus 2 7791
Protoss_Gateway 1 2030
Protoss_Assimilator 1 2523
Protoss_Zealot 7 9381
Protoss_Cybernetics_Core 1 3978
Protoss_Stargate 1 5084
Protoss_Dragoon 1 5444
Protoss_Corsair 4 9111
Protoss_Forge 2 8603
Protoss_Citadel_of_Adun 1 8783
Protoss_Templar_Archives 1 9898
9898
