Protoss_Nexus 1 0
Protoss_Gateway 3 9917
Protoss_Assimilator 1 2420
Protoss_Zealot 4 6773
Protoss_Cybernetics_Core 1 3839
Protoss_Stargate 1 4977
Protoss_Citadel_of_Adun 1 5525
Protoss_Dragoon 1 5685
Protoss_Corsair 1 6167
Protoss_Templar_Archives 1 6599
Protoss_Forge 1 7075
Protoss_Photon_Cannon 3 9871
Protoss_Dark_Templar 1 8015
Protoss_High_Templar 2 9569
9917
