Protoss_Nexus 1 0
Protoss_Gateway 2 8201
Protoss_Assimilator 1 2476
Protoss_Zealot 3 5761
Protoss_Cybernetics_Core 1 3853
Protoss_Dragoon 1 4836
Protoss_Robotics_Facility 1 5635
Protoss_Citadel_of_Adun 1 6392
Protoss_Shuttle 1 6926
Protoss_Robotics_Support_Bay 1 6983
Protoss_Reaver 2 8889
Protoss_Templar_Archives 1 8323
Protoss_Forge 1 9148
Protoss_High_Templar 1 9321
Protoss_Photon_Cannon 2 9863
9863
