Protoss_Nexus 1 0
Protoss_Gateway 2 2343
Protoss_Zealot 11 6676
Protoss_Forge 1 6208
Protoss_Photon_Cannon 3 7983
Protoss_Assimilator 1 7595
Protoss_Cybernetics_Core 1 8372
Protoss_Stargate 1 9427
9427
