Protoss_Nexus 1 0
Protoss_Gateway 3 9559
Protoss_Zealot 14 9511
Protoss_Assimilator 1 3891
Protoss_Cybernetics_Core 1 5353
Protoss_Citadel_of_Adun 1 6440
Protoss_Templar_Archives 1 9945
9945
