Protoss_Nexus 2 9983
Protoss_Gateway 2 2707
Protoss_Zealot 9 8406
Protoss_Assimilator 1 4139
Protoss_Cybernetics_Core 1 4698
Protoss_Forge 1 5062
Protoss_Citadel_of_Adun 1 6378
Protoss_Templar_Archives 1 7818
Protoss_Photon_Cannon 2 9088
Protoss_High_Templar 2 9311
Protoss_Ground_Weapons_1 1 9756
9983
