Protoss_Nexus 2 9691
Protoss_Gateway 2 2792
Protoss_Zealot 10 8011
Protoss_Assimilator 1 3998
Protoss_Cybernetics_Core 1 4688
Protoss_Forge 1 5305
Protoss_Dragoon 1 5706
Protoss_Citadel_of_Adun 1 6285
Protoss_Templar_Archives 1 7471
Protoss_Photon_Cannon 2 9298
Protoss_Dark_Templar 1 9231
Protoss_High_Templar 2 9983
9983
