Protoss_Nexus 1 0
Protoss_Gateway 2 2423
Protoss_Zealot 12 8761
Protoss_Assimilator 1 5966
Protoss_Cybernetics_Core 1 6521
Protoss_Stargate 1 7559
Protoss_Dragoon 2 8726
Protoss_Corsair 1 8796
Protoss_Citadel_of_Adun 1 9315
Protoss_Forge 1 9665
9665
