Protoss_Nexus 2 3798
Protoss_Gateway 3 5353
Protoss_Zealot 17 9866
Protoss_Assimilator 1 6726
Protoss_Cybernetics_Core 1 7902
Protoss_Citadel_of_Adun 1 9120
Protoss_Forge 1 9198
Protoss_Photon_Cannon 1 9929
9929
