Protoss_Nexus 2 3154
Protoss_Forge 2 3526
Protoss_Photon_Cannon 4 9735
Protoss_Gateway 6 7393
Protoss_Assimilator 1 5037
Protoss_Cybernetics_Core 1 5763
Protoss_Zealot 16 9891
Protoss_Citadel_of_Adun 1 6929
Protoss_Dragoon 1 7811
9891
