Protoss_Nexus 1 0
Protoss_Gateway 2 6578
Protoss_Assimilator 1 2538
Protoss_Zealot 8 9026
Protoss_Cybernetics_Core 1 4737
Protoss_Stargate 1 5941
Protoss_Dragoon 1 6146
Protoss_Corsair 1 7076
Protoss_Citadel_of_Adun 1 7254
Protoss_Templar_Archives 1 8504
Protoss_Forge 1 8653
Protoss_Dark_Templar 2 9896
9896
