Protoss_Nexus 1 0
Protoss_Gateway 2 2393
Protoss_Zealot 14 9048
Protoss_Assimilator 1 4292
Protoss_Cybernetics_Core 1 5887
Protoss_Citadel_of_Adun 1 7171
Protoss_Dragoon 1 7816
9048
