Protoss_Nexus 1 0
Protoss_Gateway 2 5616
Protoss_Assimilator 1 2566
Protoss_Zealot 9 8741
Protoss_Cybernetics_Core 1 4031
Protoss_Dragoon 1 5021
Protoss_Forge 1 5245
Protoss_Citadel_of_Adun 1 6510
Protoss_Stargate 2 8383
Protoss_Photon_Cannon 1 9221
Protoss_Corsair 3 9991
9991
