Protoss_Nexus 2 4488
Protoss_Forge 1 2399
Protoss_Photon_Cannon 2 3163
Protoss_Gateway 1 5108
Protoss_Assimilator 2 6958
Protoss_Zealot 3 7410
Protoss_Cybernetics_Core 1 6559
Protoss_Robotics_Facility 1 7566
Protoss_Stargate 1 8027
Protoss_Dragoon 1 8721
Protoss_Shuttle 1 9196
Protoss_Robotics_Support_Bay 1 9218
9218
