Protoss_Nexus 2 8869
Protoss_Gateway 3 6703
Protoss_Assimilator 1 2422
Protoss_Zealot 11 9256
Protoss_Cybernetics_Core 1 3903
Protoss_Stargate 1 5493
Protoss_Citadel_of_Adun 1 5877
Protoss_Corsair 1 7316
Protoss_Templar_Archives 1 9038
9256
