Protoss_Nexus 2 3478
Protoss_Forge 1 2856
Protoss_Photon_Cannon 3 8973
Protoss_Gateway 1 4263
Protoss_Assimilator 2 7189
Protoss_Cybernetics_Core 1 5580
Protoss_Zealot 2 7391
Protoss_Dragoon 1 6576
Protoss_Stargate 1 6743
Protoss_Corsair 4 9776
Protoss_Robotics_Facility 1 8056
Protoss_Robotics_Support_Bay 3 9544
Protoss_Shuttle 1 9561
9776
