Protoss_Nexus 2 3103
Protoss_Forge 1 3947
Protoss_Photon_Cannon 8 9173
Protoss_Assimilator 2 6886
Protoss_Gateway 3 8733
Protoss_Cybernetics_Core 1 6846
Protoss_Stargate 2 8011
Protoss_Citadel_of_Adun 1 8179
Protoss_Corsair 3 9796
Protoss_Templar_Archives 1 9383
9796
