Protoss_Nexus 2 2961
Protoss_Forge 1 3277
Protoss_Photon_Cannon 5 9599
Protoss_Gateway 3 7133
Protoss_Assimilator 1 4709
Protoss_Zealot 12 9635
Protoss_Cybernetics_Core 1 6245
Protoss_Citadel_of_Adun 1 7351
Protoss_Stargate 2 8948
Protoss_Corsair 1 9737
Protoss_Robotics_Facility 1 9942
9942
