Protoss_Nexus 2 7643
Protoss_Assimilator 1 1833
Protoss_Gateway 1 2228
Protoss_Cybernetics_Core 1 3223
Protoss_Stargate 1 4270
Protoss_Robotics_Facility 1 4628
Protoss_Citadel_of_Adun 1 5161
Protoss_Corsair 1 5411
Protoss_Shuttle 1 5916
Protoss_Templar_Archives 1 6288
Protoss_Forge 1 6688
Protoss_High_Templar 2 8761
Protoss_Photon_Cannon 5 9799
Protoss_Dark_Templar 1 9513
Psionic_Storm 1 9911
9911
