Protoss_Nexus 2 3317
Protoss_Forge 1 2138
Protoss_Photon_Cannon 4 9976
Protoss_Gateway 5 8553
Protoss_Assimilator 2 9790
Protoss_Zealot 13 9875
Protoss_Cybernetics_Core 1 6801
Protoss_Citadel_of_Adun 1 7799
Protoss_Templar_Archives 1 9776
9976
