Protoss_Nexus 2 9034
Protoss_Gateway 1 1970
Protoss_Assimilator 1 2853
Protoss_Zealot 2 5906
Protoss_Cybernetics_Core 1 3773
Protoss_Dragoon 1 4761
Protoss_Stargate 1 4993
Protoss_Robotics_Facility 1 5802
Protoss_Corsair 2 8641
Protoss_Forge 1 6992
Protoss_Shuttle 1 7161
Protoss_Shield_Battery 1 7283
Protoss_Robotics_Support_Bay 1 7344
Protoss_Photon_Cannon 4 9918
Protoss_Reaver 1 8063
9918
