Protoss_Nexus 2 9568
Protoss_Gateway 1 2068
Protoss_Assimilator 1 2328
Protoss_Zealot 6 7807
Protoss_Cybernetics_Core 1 4827
Protoss_Dragoon 1 5851
Protoss_Citadel_of_Adun 1 6089
Protoss_Forge 1 6715
Protoss_Templar_Archives 1 7161
Protoss_Dark_Templar 1 8409
Protoss_Photon_Cannon 1 8883
Protoss_High_Templar 2 9913
9913
