Protoss_Nexus 2 9669
Protoss_Gateway 2 3095
Protoss_Zealot 15 8329
Protoss_Assimilator 1 6390
Protoss_Cybernetics_Core 1 7154
Protoss_Forge 1 7625
Protoss_Citadel_of_Adun 1 8186
Protoss_Templar_Archives 1 9269
Protoss_Photon_Cannon 2 9945
9945
