Protoss_Nexus 1 0
Protoss_Gateway 3 8501
Protoss_Assimilator 1 2428
Protoss_Zealot 4 5956
Protoss_Cybernetics_Core 1 4476
Protoss_Dragoon 10 9793
Protoss_Forge 1 6440
Protoss_Citadel_of_Adun 1 9326
9793
