Protoss_Nexus 2 9347
Protoss_Gateway 2 2487
Protoss_Zealot 7 8161
Protoss_Assimilator 1 3963
Protoss_Forge 1 4782
Protoss_Cybernetics_Core 1 5417
Protoss_Photon_Cannon 4 9946
Protoss_Citadel_of_Adun 1 6409
Protoss_Templar_Archives 1 7986
Protoss_High_Templar 2 8973
Protoss_Ground_Weapons_1 1 9459
9946
