Protoss_Nexus 2 4738
Protoss_Forge 1 2266
Protoss_Photon_Cannon 7 9305
Protoss_Gateway 1 5108
Protoss_Assimilator 2 7609
Protoss_Zealot 3 9441
Protoss_Cybernetics_Core 1 6228
Protoss_Dragoon 2 8351
Protoss_Citadel_of_Adun 1 7543
Protoss_Templar_Archives 1 9603
9603
