Special_Protoss_Temple 8 0
Protoss_Nexus 2 4599
Protoss_Forge 1 2233
Protoss_Photon_Cannon 5 9794
Protoss_Gateway 4 9620
Protoss_Assimilator 3 8682
Protoss_Cybernetics_Core 1 6009
Protoss_Citadel_of_Adun 1 7093
Protoss_Zealot 8 9297
Protoss_Robotics_Facility 1 9915
9915
