Protoss_Nexus 2 4280
Protoss_Forge 1 2428
Protoss_Photon_Cannon 2 3281
Protoss_Gateway 3 7704
Protoss_Assimilator 1 4984
Protoss_Cybernetics_Core 1 5568
Protoss_Zealot 1 8306
8306
