Protoss_Nexus 2 2564
Protoss_Forge 1 2897
Protoss_Photon_Cannon 4 8049
Protoss_Gateway 1 4073
Protoss_Assimilator 2 6660
Protoss_Zealot 5 8189
Protoss_Cybernetics_Core 1 5233
Protoss_Stargate 1 6341
Protoss_Robotics_Facility 2 8988
Protoss_Corsair 3 9889
Protoss_Robotics_Support_Bay 1 8496
Protoss_Reaver 1 9269
9889
