Protoss_Nexus 2 8721
Protoss_Gateway 2 2748
Protoss_Zealot 15 9316
Protoss_Assimilator 1 6237
Protoss_Cybernetics_Core 1 6973
Protoss_Citadel_of_Adun 1 8596
Protoss_Templar_Archives 1 9748
9748
