Protoss_Nexus 2 4391
Protoss_Forge 1 2652
Protoss_Photon_Cannon 7 9921
Protoss_Gateway 1 4807
Protoss_Assimilator 2 7634
Protoss_Cybernetics_Core 1 5825
Protoss_Zealot 6 9307
Protoss_Stargate 1 6995
Protoss_Citadel_of_Adun 1 7548
Protoss_Corsair 2 8887
Protoss_Templar_Archives 1 9775
9921
