Protoss_Nexus 1 0
Protoss_Gateway 2 2488
Protoss_Zealot 10 7381
Protoss_Assimilator 1 6122
Protoss_Cybernetics_Core 1 7056
Protoss_Forge 1 7650
Protoss_Citadel_of_Adun 1 8059
Protoss_Photon_Cannon 2 8915
Protoss_Templar_Archives 1 9279
9279
