Protoss_Nexus 1 0
Protoss_Gateway 1 1893
Protoss_Assimilator 2 3360
Protoss_Cybernetics_Core 1 3010
Protoss_Zealot 1 4599
Protoss_Dragoon 1 4955
Protoss_Robotics_Facility 1 5815
5815
