Protoss_Nexus 1 0
Protoss_Assimilator 1 1770
Protoss_Forge 1 2437
Protoss_Gateway 3 4739
Protoss_Photon_Cannon 4 9425
Protoss_Zealot 8 7225
Protoss_Ground_Weapons_1 1 7385
Protoss_Cybernetics_Core 1 7745
Protoss_Dragoon 3 8761
Protoss_Stargate 1 9103
9425
