Protoss_Nexus 2 3733
Protoss_Forge 1 2114
Protoss_Photon_Cannon 4 9288
Protoss_Gateway 3 7468
Protoss_Zealot 11 9436
Protoss_Assimilator 2 7788
Protoss_Cybernetics_Core 1 7065
Protoss_Citadel_of_Adun 1 8118
Protoss_Templar_Archives 1 9148
9436
