Protoss_Nexus 2 5188
Protoss_Forge 1 2247
Protoss_Photon_Cannon 7 9910
Protoss_Gateway 2 9169
Protoss_Zealot 6 9841
Protoss_Assimilator 2 8123
Protoss_Cybernetics_Core 1 6654
Protoss_Citadel_of_Adun 1 7709
Protoss_Templar_Archives 1 8887
Protoss_High_Templar 1 9971
9971
