Protoss_Nexus 1 0
Protoss_Gateway 2 2568
Protoss_Zealot 18 8707
Protoss_Assimilator 1 6133
Protoss_Cybernetics_Core 1 6993
Protoss_Citadel_of_Adun 1 8019
Protoss_Templar_Archives 1 9218
Protoss_Forge 1 9599
9599
