Protoss_Nexus 2 4515
Protoss_Gateway 2 9291
Protoss_Zealot 8 8814
Protoss_Forge 1 4776
Protoss_Photon_Cannon 4 6261
Protoss_Assimilator 2 9753
Protoss_Cybernetics_Core 1 8255
Protoss_Citadel_of_Adun 1 9353
9753
