Protoss_Nexus 2 3270
Protoss_Forge 1 2305
Protoss_Photon_Cannon 5 9957
Protoss_Gateway 3 8998
Protoss_Assimilator 2 7349
Protoss_Zealot 9 9443
Protoss_Cybernetics_Core 1 5435
Protoss_Citadel_of_Adun 1 6777
Protoss_Dragoon 1 7223
Protoss_Templar_Archives 1 8694
9957
