Protoss_Nexus 1 0
Protoss_Gateway 1 2043
Protoss_Assimilator 1 2573
Protoss_Zealot 3 4881
Protoss_Cybernetics_Core 1 4530
Protoss_Forge 1 6097
Protoss_Dragoon 2 7689
Protoss_Photon_Cannon 1 8358
8358
