Protoss_Nexus 2 5103
Protoss_Forge 1 2794
Protoss_Photon_Cannon 6 8754
Protoss_Gateway 1 5521
Protoss_Assimilator 2 7308
Protoss_Cybernetics_Core 1 6663
Protoss_Zealot 2 7568
Protoss_Stargate 1 7708
Protoss_Robotics_Facility 1 8418
Protoss_Corsair 2 9508
Protoss_Shuttle 1 9766
Protoss_Robotics_Support_Bay 1 9948
9948
