Protoss_Nexus 2 4128
Protoss_Forge 1 2173
Protoss_Photon_Cannon 3 4383
Protoss_Gateway 4 7553
Protoss_Assimilator 2 9982
Protoss_Zealot 13 9786
Protoss_Cybernetics_Core 1 6653
Protoss_Citadel_of_Adun 1 7848
Protoss_Templar_Archives 1 9403
9982
