Protoss_Nexus 2 5525
Protoss_Forge 1 2227
Protoss_Photon_Cannon 6 8863
Protoss_Gateway 2 9805
Protoss_Assimilator 2 7656
Protoss_Cybernetics_Core 1 6760
Protoss_Zealot 4 9585
Protoss_Citadel_of_Adun 1 8088
Protoss_Templar_Archives 1 9083
9805
