Protoss_Nexus 2 2898
Protoss_Forge 1 3203
Protoss_Photon_Cannon 5 10000
Protoss_Gateway 4 7938
Protoss_Assimilator 2 6556
Protoss_Cybernetics_Core 1 7535
Protoss_Zealot 7 8991
Protoss_Citadel_of_Adun 1 8651
Protoss_Templar_Archives 1 9664
10000
