Protoss_Nexus 1 0
Protoss_Gateway 2 2804
Protoss_Zealot 13 9568
Protoss_Assimilator 1 3956
Protoss_Forge 1 4259
Protoss_Photon_Cannon 1 6308
Protoss_Ground_Weapons_1 1 9329
9568
