Protoss_Nexus 3 9827
Protoss_Forge 1 2005
Protoss_Photon_Cannon 5 8415
Protoss_Gateway 1 4407
Protoss_Assimilator 2 6113
Protoss_Cybernetics_Core 1 5393
Protoss_Zealot 1 5625
Protoss_Stargate 1 6443
Protoss_Robotics_Facility 1 7306
Protoss_Corsair 2 9031
Protoss_Shuttle 1 8703
Protoss_Robotics_Support_Bay 1 9515
9827
