Protoss_Nexus 2 8903
Protoss_Gateway 1 1733
Protoss_Assimilator 2 9743
Protoss_Zealot 3 5428
Protoss_Cybernetics_Core 1 3683
Protoss_Dragoon 1 4676
Protoss_Stargate 1 5156
Protoss_Citadel_of_Adun 1 5921
Protoss_Forge 1 6023
Protoss_Corsair 1 6346
Protoss_Photon_Cannon 4 9574
Protoss_Templar_Archives 1 6935
Protoss_Dark_Templar 1 7991
Protoss_Robotics_Facility 1 8203
Protoss_Robotics_Support_Bay 1 9532
9743
