Protoss_Nexus 2 8468
Protoss_Gateway 2 9551
Protoss_Zealot 7 9141
Protoss_Assimilator 1 3156
Protoss_Cybernetics_Core 1 4003
Protoss_Stargate 1 5143
Protoss_Dragoon 1 5700
Protoss_Forge 1 5908
Protoss_Citadel_of_Adun 1 6103
Protoss_Corsair 2 7381
Protoss_Photon_Cannon 3 9271
Protoss_Templar_Archives 1 8659
Protoss_Dark_Templar 1 9776
9776
