Protoss_Nexus 2 5857
Protoss_Gateway 4 8403
Protoss_Zealot 9 6219
Protoss_Assimilator 3 9231
Protoss_Cybernetics_Core 1 6679
Protoss_Dragoon 6 9871
Protoss_Forge 1 9505
9871
