Protoss_Nexus 2 3028
Protoss_Forge 1 3539
Protoss_Photon_Cannon 2 9905
Protoss_Gateway 4 9597
Protoss_Assimilator 2 7825
Protoss_Zealot 11 9636
Protoss_Cybernetics_Core 1 5640
Protoss_Citadel_of_Adun 1 6673
Protoss_Dragoon 1 7513
Protoss_Templar_Archives 1 7978
Protoss_High_Templar 2 9753
9905
