Protoss_Nexus 2 3510
Protoss_Forge 1 2215
Protoss_Photon_Cannon 3 9420
Protoss_Gateway 3 8038
Protoss_Assimilator 2 8221
Protoss_Zealot 8 9716
Protoss_Cybernetics_Core 1 6374
Protoss_Dragoon 1 7533
Protoss_Citadel_of_Adun 1 7698
9716
