Protoss_Nexus 1 0
Protoss_Gateway 2 2653
Protoss_Zealot 12 8053
Protoss_Assimilator 1 4893
Protoss_Cybernetics_Core 1 6097
Protoss_Forge 1 6857
Protoss_Dragoon 1 7301
Protoss_Photon_Cannon 3 9393
Protoss_Robotics_Facility 1 8443
Protoss_Citadel_of_Adun 1 8779
Protoss_Templar_Archives 1 9783
Protoss_Observatory 1 9944
9944
