Protoss_Nexus 2 4088
Protoss_Forge 1 2019
Protoss_Photon_Cannon 4 9295
Protoss_Gateway 1 4728
Protoss_Assimilator 2 6633
Protoss_Zealot 4 7542
Protoss_Cybernetics_Core 1 6185
Protoss_Stargate 1 7258
Protoss_Citadel_of_Adun 1 7418
Protoss_Corsair 3 9651
Protoss_Robotics_Facility 1 8571
Protoss_Shuttle 1 9876
9876
