Protoss_Nexus 2 3263
Protoss_Forge 1 2021
Protoss_Photon_Cannon 2 4108
Protoss_Gateway 4 8435
Protoss_Assimilator 2 6529
Protoss_Zealot 7 9626
Protoss_Cybernetics_Core 1 6681
Protoss_Citadel_of_Adun 1 7822
Protoss_Templar_Archives 1 9062
Protoss_Dragoon 1 9726
Protoss_Robotics_Facility 1 9932
9932
