Protoss_Nexus 2 2581
Protoss_Forge 1 2951
Protoss_Photon_Cannon 5 9902
Protoss_Gateway 5 9625
Protoss_Assimilator 2 8442
Protoss_Zealot 13 9909
Protoss_Cybernetics_Core 1 6059
Protoss_Citadel_of_Adun 1 7122
Protoss_Dragoon 1 7731
Protoss_Templar_Archives 1 9157
9909
