Protoss_Nexus 2 2807
Protoss_Forge 1 3309
Protoss_Photon_Cannon 2 4400
Protoss_Gateway 3 7008
Protoss_Assimilator 2 6193
Protoss_Cybernetics_Core 1 6013
Protoss_Zealot 12 9736
Protoss_Citadel_of_Adun 1 7128
Protoss_Templar_Archives 1 8697
Protoss_Dark_Templar 2 9776
9776
