Protoss_Nexus 2 2853
Protoss_Forge 1 3188
Protoss_Photon_Cannon 1 3888
Protoss_Gateway 3 6918
Protoss_Assimilator 2 8798
Protoss_Zealot 11 9402
Protoss_Cybernetics_Core 1 6240
Protoss_Dragoon 1 7316
Protoss_Citadel_of_Adun 1 7419
Protoss_Templar_Archives 1 8418
Protoss_Ground_Weapons_1 1 9836
9836
