Protoss_Nexus 2 8787
Protoss_Gateway 1 2020
Protoss_Assimilator 1 2506
Protoss_Cybernetics_Core 1 3043
Protoss_Zealot 7 9415
Protoss_Stargate 1 4116
Protoss_Corsair 1 5247
Protoss_Scout 1 5389
Protoss_Dragoon 1 5705
Protoss_Citadel_of_Adun 1 9161
9415
