Protoss_Nexus 2 3617
Protoss_Forge 1 1971
Protoss_Photon_Cannon 5 9969
Protoss_Gateway 4 7302
Protoss_Assimilator 2 9480
Protoss_Zealot 16 9737
Protoss_Cybernetics_Core 1 5154
Protoss_Citadel_of_Adun 1 6407
Protoss_Templar_Archives 1 8191
Protoss_High_Templar 2 9371
Protoss_Ground_Weapons_1 1 9725
9969
