Protoss_Nexus 2 8763
Protoss_Gateway 1 1911
Protoss_Assimilator 1 2438
Protoss_Zealot 3 4576
Protoss_Cybernetics_Core 1 4073
Protoss_Dragoon 1 5178
Protoss_Stargate 1 5278
Protoss_Citadel_of_Adun 1 5778
Protoss_Corsair 1 6641
Protoss_Templar_Archives 1 6773
Protoss_Forge 1 7474
Protoss_Dark_Templar 1 7801
Protoss_Photon_Cannon 5 9993
Protoss_High_Templar 2 9353
Psionic_Storm 1 9671
9993
