Protoss_Nexus 2 3344
Protoss_Forge 1 2862
Protoss_Photon_Cannon 6 9888
Protoss_Gateway 1 4543
Protoss_Assimilator 1 5308
Protoss_Zealot 5 8956
Protoss_Cybernetics_Core 1 7990
Protoss_Robotics_Facility 1 9618
9888
