Protoss_Nexus 2 7935
Protoss_Gateway 1 2007
Protoss_Zealot 4 6953
Protoss_Assimilator 1 3267
Protoss_Cybernetics_Core 1 4035
Protoss_Stargate 1 5040
Protoss_Dragoon 1 5207
Protoss_Citadel_of_Adun 1 5693
Protoss_Corsair 1 6179
Protoss_Templar_Archives 1 7128
Protoss_Dark_Templar 1 8165
Protoss_Forge 1 8889
Protoss_High_Templar 1 9131
Protoss_Photon_Cannon 2 9871
9871
