Protoss_Nexus 2 4340
Protoss_Forge 1 2389
Protoss_Photon_Cannon 4 9395
Protoss_Gateway 2 8453
Protoss_Assimilator 2 7913
Protoss_Cybernetics_Core 1 6131
Protoss_Dragoon 1 7109
Protoss_Citadel_of_Adun 1 7241
Protoss_Zealot 3 9153
Protoss_Stargate 2 8952
Protoss_Templar_Archives 1 9403
9403
