Protoss_Nexus 2 3703
Protoss_Forge 1 2299
Protoss_Photon_Cannon 3 9854
Protoss_Gateway 4 7482
Protoss_Assimilator 2 8725
Protoss_Cybernetics_Core 1 5585
Protoss_Zealot 13 9685
Protoss_Citadel_of_Adun 1 6628
Protoss_Templar_Archives 1 9249
9854
