Protoss_Nexus 2 3741
Protoss_Forge 1 2092
Protoss_Photon_Cannon 4 9915
Protoss_Gateway 4 8380
Protoss_Assimilator 2 8659
Protoss_Cybernetics_Core 1 5405
Protoss_Zealot 8 9851
Protoss_Citadel_of_Adun 1 7404
9915
