Protoss_Nexus 2 3987
Protoss_Forge 1 2518
Protoss_Photon_Cannon 6 9347
Protoss_Gateway 2 9824
Protoss_Zealot 5 9501
Protoss_Assimilator 1 5733
Protoss_Cybernetics_Core 1 7407
Protoss_Citadel_of_Adun 1 8594
Protoss_Dragoon 1 8749
Protoss_Templar_Archives 1 9739
9824
