Protoss_Nexus 2 4004
Protoss_Forge 1 2362
Protoss_Photon_Cannon 5 9503
Protoss_Gateway 3 7430
Protoss_Assimilator 2 6928
Protoss_Cybernetics_Core 1 5984
Protoss_Zealot 6 9161
Protoss_Citadel_of_Adun 1 7229
Protoss_Dragoon 1 7596
Protoss_Templar_Archives 1 8302
Protoss_Robotics_Facility 1 9122
Protoss_High_Templar 2 9301
9503
