Protoss_Nexus 2 5692
Protoss_Gateway 5 9481
Protoss_Zealot 14 9556
Protoss_Forge 1 6745
Protoss_Assimilator 1 6820
Protoss_Photon_Cannon 2 7638
Protoss_Cybernetics_Core 1 8004
Protoss_Citadel_of_Adun 1 9024
Protoss_Stargate 1 9132
9556
