Protoss_Nexus 2 5327
Protoss_Gateway 4 9266
Protoss_Zealot 10 9927
Protoss_Assimilator 1 3463
Protoss_Forge 1 3751
Protoss_Photon_Cannon 2 6007
Protoss_Cybernetics_Core 1 6663
Protoss_Citadel_of_Adun 1 7785
Protoss_Dragoon 1 7893
9927
