Protoss_Nexus 1 0
Protoss_Assimilator 1 2125
Protoss_Gateway 2 8232
Protoss_Cybernetics_Core 1 3323
Protoss_Dragoon 9 9726
Protoss_Robotics_Facility 1 4479
Protoss_Observatory 1 5891
Protoss_Observer 1 6431
Protoss_Shuttle 1 7051
Protoss_Forge 1 8133
Protoss_Shield_Battery 1 8431
Protoss_Photon_Cannon 1 8833
Protoss_Citadel_of_Adun 1 9724
9726
