Protoss_Nexus 1 0
Protoss_Gateway 3 6679
Protoss_Assimilator 1 2543
Protoss_Zealot 3 4343
Protoss_Cybernetics_Core 1 4014
Protoss_Stargate 1 5101
Protoss_Dragoon 8 8611
Protoss_Corsair 1 6256
8611
