Protoss_Nexus 2 3503
Protoss_Forge 1 2193
Protoss_Photon_Cannon 3 9270
Protoss_Gateway 4 8930
Protoss_Assimilator 2 6324
Protoss_Cybernetics_Core 1 6071
Protoss_Citadel_of_Adun 1 7128
Protoss_Robotics_Facility 1 8089
Protoss_Templar_Archives 1 8514
Protoss_Zealot 1 9331
Protoss_Observatory 1 9518
Protoss_High_Templar 2 9856
9856
