Protoss_Nexus 2 2823
Protoss_Forge 2 7303
Protoss_Photon_Cannon 5 9725
Protoss_Assimilator 2 5745
Protoss_Gateway 3 6980
Protoss_Cybernetics_Core 1 7945
Protoss_Zealot 6 9053
Protoss_Citadel_of_Adun 1 9133
Protoss_Robotics_Facility 1 9420
9725
