Protoss_Nexus 1 0
Protoss_Gateway 2 2823
Protoss_Zealot 9 9293
Protoss_Assimilator 1 3736
Protoss_Cybernetics_Core 1 5086
Protoss_Forge 1 5585
Protoss_Stargate 1 6125
Protoss_Dragoon 1 6231
Protoss_Citadel_of_Adun 1 6675
Protoss_Scout 1 7471
Protoss_Templar_Archives 1 9129
Protoss_Photon_Cannon 1 9778
9778
