Protoss_Nexus 2 4026
Protoss_Forge 1 2200
Protoss_Photon_Cannon 2 3344
Protoss_Gateway 1 4391
Protoss_Assimilator 2 7253
Protoss_Zealot 1 5436
Protoss_Cybernetics_Core 1 5762
7253
