Protoss_Nexus 1 0
Protoss_Gateway 3 7402
Protoss_Assimilator 1 2410
Protoss_Zealot 9 8683
Protoss_Cybernetics_Core 1 3952
Protoss_Citadel_of_Adun 1 5043
Protoss_Dragoon 2 9859
Protoss_Templar_Archives 1 8315
Protoss_Forge 1 9052
Protoss_High_Templar 2 9343
Protoss_Photon_Cannon 2 9873
9873
