Protoss_Nexus 1 0
Protoss_Gateway 1 1899
Protoss_Assimilator 1 2417
Protoss_Zealot 3 4315
Protoss_Cybernetics_Core 1 4097
Protoss_Stargate 1 5102
Protoss_Citadel_of_Adun 1 5492
Protoss_Dragoon 1 5849
Protoss_Corsair 1 6293
Protoss_Forge 1 6637
Protoss_Templar_Archives 1 6765
Protoss_Dark_Templar 1 7785
7785
