Protoss_Nexus 2 5088
Protoss_Gateway 4 9020
Protoss_Zealot 5 7886
Protoss_Forge 1 3193
Protoss_Photon_Cannon 2 5171
Protoss_Assimilator 2 8476
Protoss_Cybernetics_Core 1 6502
Protoss_Citadel_of_Adun 1 7661
Protoss_Dragoon 1 8601
Protoss_Templar_Archives 1 9848
9848
