Protoss_Nexus 2 4566
Protoss_Forge 1 2187
Protoss_Photon_Cannon 3 9764
Protoss_Gateway 4 8636
Protoss_Assimilator 2 7512
Protoss_Zealot 8 9431
Protoss_Cybernetics_Core 1 6030
Protoss_Citadel_of_Adun 1 7223
Protoss_Templar_Archives 1 9120
9764
