Protoss_Nexus 2 7837
Protoss_Gateway 2 2533
Protoss_Zealot 9 8266
Protoss_Assimilator 2 9358
Protoss_Forge 1 5470
Protoss_Cybernetics_Core 1 5990
Protoss_Citadel_of_Adun 1 7044
Protoss_Photon_Cannon 3 9747
Protoss_Templar_Archives 1 8663
Protoss_High_Templar 2 9696
9747
