Protoss_Nexus 2 3093
Protoss_Forge 1 1936
Protoss_Photon_Cannon 1 3413
Protoss_Gateway 6 8500
Protoss_Assimilator 1 4701
Protoss_Zealot 10 9711
Protoss_Cybernetics_Core 1 4986
Protoss_Stargate 1 6248
Protoss_Dragoon 3 9523
Protoss_Corsair 2 7748
Protoss_Citadel_of_Adun 1 8740
9711
