Protoss_Nexus 2 4128
Protoss_Forge 1 2403
Protoss_Photon_Cannon 5 9743
Protoss_Gateway 4 8168
Protoss_Assimilator 2 7994
Protoss_Zealot 9 9856
Protoss_Cybernetics_Core 1 6730
Protoss_Citadel_of_Adun 1 8471
Protoss_Dragoon 1 9191
9856
