Protoss_Nexus 2 2880
Protoss_Forge 1 3283
Protoss_Gateway 3 9379
Protoss_Photon_Cannon 8 9289
Protoss_Assimilator 2 7041
Protoss_Zealot 4 7651
Protoss_Cybernetics_Core 1 6328
Protoss_Citadel_of_Adun 1 7368
Protoss_Templar_Archives 1 8838
Protoss_High_Templar 2 9836
Protoss_Ground_Weapons_1 1 9916
9916
