Protoss_Nexus 2 3053
Protoss_Gateway 3 8863
Protoss_Forge 1 3793
Protoss_Photon_Cannon 6 9283
Protoss_Zealot 7 8906
Protoss_Assimilator 2 8416
Protoss_Cybernetics_Core 1 6896
Protoss_Stargate 1 8250
Protoss_Corsair 1 9391
Protoss_Dragoon 2 9871
Protoss_Citadel_of_Adun 1 9816
9871
