Protoss_Nexus 1 0
Protoss_Gateway 3 6502
Protoss_Zealot 18 9511
Protoss_Assimilator 1 3543
Protoss_Cybernetics_Core 1 4063
Protoss_Citadel_of_Adun 1 5399
Protoss_Dragoon 1 5446
Protoss_Templar_Archives 1 8574
9511
