Protoss_Nexus 2 3036
Protoss_Forge 1 3556
Protoss_Photon_Cannon 5 5978
Protoss_Gateway 4 9393
Protoss_Assimilator 2 7972
Protoss_Zealot 8 9911
Protoss_Cybernetics_Core 1 7900
Protoss_Stargate 1 8898
Protoss_Citadel_of_Adun 1 9218
9911
