Protoss_Nexus 2 3840
Protoss_Forge 1 2036
Protoss_Photon_Cannon 2 4583
Protoss_Gateway 6 8941
Protoss_Assimilator 1 4760
Protoss_Cybernetics_Core 1 5486
Protoss_Zealot 12 9881
Protoss_Citadel_of_Adun 1 6685
Protoss_Dragoon 1 7556
Protoss_Templar_Archives 1 9438
9881
