Protoss_Nexus 1 0
Protoss_Gateway 1 2023
Protoss_Assimilator 2 3763
Protoss_Zealot 7 9433
Protoss_Cybernetics_Core 1 4558
Protoss_Stargate 1 5824
Protoss_Dragoon 1 5961
Protoss_Citadel_of_Adun 1 6161
Protoss_Forge 1 9073
9433
