Protoss_Nexus 2 3244
Protoss_Forge 1 2453
Protoss_Photon_Cannon 8 9594
Protoss_Gateway 3 9238
Protoss_Assimilator 2 7190
Protoss_Cybernetics_Core 1 5548
Protoss_Zealot 2 7611
Protoss_Dragoon 1 6701
Protoss_Citadel_of_Adun 1 6958
Protoss_Templar_Archives 1 8518
Protoss_High_Templar 2 9716
9716
