Protoss_Nexus 1 0
Protoss_Gateway 1 1814
Protoss_Assimilator 1 2621
Protoss_Zealot 3 4943
Protoss_Cybernetics_Core 1 3993
Protoss_Stargate 1 5298
Protoss_Dragoon 1 5591
Protoss_Corsair 2 7123
7123
