Protoss_Nexus 1 0
Protoss_Assimilator 2 4780
Protoss_Gateway 1 2324
Protoss_Cybernetics_Core 1 3351
Protoss_Stargate 3 9306
Protoss_Corsair 10 9710
Protoss_Dragoon 1 5526
Protoss_Forge 1 7394
Protoss_Shield_Battery 1 7475
Protoss_Photon_Cannon 1 8088
Protoss_Air_Weapons_1 1 8366
9710
