Protoss_Nexus 2 3338
Protoss_Forge 2 9083
Protoss_Photon_Cannon 1 3988
Protoss_Gateway 4 7468
Protoss_Assimilator 2 6113
Protoss_Zealot 13 9936
Protoss_Cybernetics_Core 1 5745
Protoss_Citadel_of_Adun 1 6764
9936
