Protoss_Nexus 2 3148
Protoss_Forge 2 3313
Protoss_Photon_Cannon 3 5278
Protoss_Gateway 4 9647
Protoss_Assimilator 1 6545
Protoss_Zealot 8 9588
Protoss_Cybernetics_Core 1 7350
Protoss_Citadel_of_Adun 1 8547
9647
