Protoss_Nexus 2 3500
Protoss_Forge 1 2891
Protoss_Photon_Cannon 4 8373
Protoss_Gateway 2 7793
Protoss_Assimilator 2 6200
Protoss_Cybernetics_Core 1 5570
Protoss_Zealot 1 5835
Protoss_Stargate 1 6588
Protoss_Citadel_of_Adun 1 6869
Protoss_Templar_Archives 1 7887
Protoss_Corsair 3 9477
Protoss_Dark_Templar 4 9851
Protoss_Robotics_Facility 1 9357
9851
