Protoss_Nexus 2 3251
Protoss_Forge 1 2089
Protoss_Photon_Cannon 3 8411
Protoss_Gateway 5 8911
Protoss_Assimilator 2 8215
Protoss_Zealot 7 9265
Protoss_Cybernetics_Core 1 6943
Protoss_Dragoon 1 8513
Protoss_Citadel_of_Adun 1 8694
9265
