Protoss_Nexus 2 4163
Protoss_Forge 1 2325
Protoss_Photon_Cannon 4 9128
Protoss_Gateway 2 8288
Protoss_Assimilator 2 5964
Protoss_Cybernetics_Core 1 5466
Protoss_Zealot 2 7641
Protoss_Dragoon 1 6561
Protoss_Stargate 1 6763
Protoss_Citadel_of_Adun 1 7398
Protoss_Corsair 2 8498
Protoss_Templar_Archives 1 8643
Protoss_Dark_Templar 2 9971
9971
