Protoss_Nexus 2 3523
Protoss_Forge 2 9934
Protoss_Photon_Cannon 3 9380
Protoss_Assimilator 1 4340
Protoss_Gateway 4 9259
Protoss_Zealot 7 8960
Protoss_Cybernetics_Core 1 5950
Protoss_Dragoon 1 6988
Protoss_Citadel_of_Adun 1 7053
Protoss_Ground_Weapons_1 1 9711
9934
