Protoss_Nexus 2 3302
Protoss_Forge 1 2115
Protoss_Gateway 4 8833
Protoss_Assimilator 2 9174
Protoss_Photon_Cannon 1 4971
Protoss_Zealot 9 9349
Protoss_Cybernetics_Core 1 5799
Protoss_Dragoon 1 6787
Protoss_Citadel_of_Adun 1 6841
Protoss_Templar_Archives 1 9112
9349
