Protoss_Nexus 2 3987
Protoss_Forge 1 2038
Protoss_Photon_Cannon 3 9303
Protoss_Gateway 3 8348
Protoss_Assimilator 2 7156
Protoss_Zealot 9 9596
Protoss_Cybernetics_Core 1 5948
Protoss_Citadel_of_Adun 1 7073
Protoss_Templar_Archives 1 8538
9596
