Protoss_Nexus 1 0
Protoss_Gateway 2 2473
Protoss_Zealot 12 8828
Protoss_Assimilator 1 5814
Protoss_Cybernetics_Core 1 8040
Protoss_Forge 1 8436
Protoss_Photon_Cannon 3 9906
9906
