Protoss_Nexus 2 4055
Protoss_Forge 1 1885
Protoss_Photon_Cannon 3 4681
Protoss_Assimilator 2 9193
Protoss_Gateway 3 7545
Protoss_Zealot 11 9983
Protoss_Cybernetics_Core 1 6943
Protoss_Citadel_of_Adun 1 7968
Protoss_Dragoon 1 8027
Protoss_Templar_Archives 1 9413
9983
