Protoss_Nexus 2 3899
Protoss_Forge 1 2328
Protoss_Photon_Cannon 2 8376
Protoss_Gateway 3 8633
Protoss_Assimilator 2 6099
Protoss_Cybernetics_Core 1 5447
Protoss_Zealot 1 5795
Protoss_Stargate 1 6464
Protoss_Citadel_of_Adun 1 7101
Protoss_Corsair 2 8201
Protoss_Templar_Archives 1 8196
Protoss_Dark_Templar 1 9307
Protoss_High_Templar 2 9731
Protoss_Robotics_Facility 1 9970
9970
