Protoss_Nexus 2 8912
Protoss_Gateway 2 3485
Protoss_Assimilator 1 2388
Protoss_Cybernetics_Core 1 3038
Protoss_Stargate 1 4350
Protoss_Zealot 10 9946
Protoss_Citadel_of_Adun 1 5374
Protoss_Corsair 1 5591
Protoss_Templar_Archives 1 6568
Protoss_Robotics_Facility 1 7209
Protoss_Dark_Templar 2 7591
Protoss_Forge 1 7698
Protoss_Photon_Cannon 1 9383
9946
