Protoss_Nexus 3 6087
Protoss_Gateway 2 2474
Protoss_Zealot 9 9749
Protoss_Forge 1 6507
Protoss_Photon_Cannon 2 7714
Protoss_Assimilator 2 8979
Protoss_Cybernetics_Core 1 8527
Protoss_Stargate 1 9641
9749
