Protoss_Nexus 2 3688
Protoss_Forge 1 2198
Protoss_Gateway 4 7523
Protoss_Photon_Cannon 1 4103
Protoss_Assimilator 2 7974
Protoss_Zealot 11 9286
Protoss_Cybernetics_Core 1 5505
Protoss_Citadel_of_Adun 1 6640
Protoss_Templar_Archives 1 8992
Protoss_Ground_Weapons_1 1 9981
9981
