Protoss_Nexus 2 9377
Protoss_Gateway 2 9222
Protoss_Assimilator 1 2551
Protoss_Zealot 2 4236
Protoss_Cybernetics_Core 1 3896
Protoss_Stargate 1 5045
Protoss_Dragoon 1 5456
Protoss_Corsair 1 6191
Protoss_Citadel_of_Adun 1 6368
Protoss_Forge 1 7056
Protoss_Templar_Archives 1 8018
Protoss_Photon_Cannon 1 8363
Protoss_Dark_Templar 1 9391
9391
