Protoss_Nexus 2 3498
Protoss_Forge 1 2250
Protoss_Photon_Cannon 2 8897
Protoss_Gateway 1 4400
Protoss_Assimilator 2 6992
Protoss_Cybernetics_Core 1 5734
Protoss_Zealot 3 8376
Protoss_Robotics_Facility 1 6923
Protoss_Stargate 1 7213
Protoss_Dragoon 1 7536
Protoss_Shuttle 1 8386
Protoss_Corsair 3 9721
Protoss_Robotics_Support_Bay 1 8968
Protoss_Reaver 1 9711
9721
