Protoss_Nexus 2 3353
Protoss_Forge 1 2336
Protoss_Gateway 3 8409
Protoss_Assimilator 2 5889
Protoss_Photon_Cannon 4 9726
Protoss_Cybernetics_Core 1 5119
Protoss_Zealot 1 5561
Protoss_Dragoon 1 6139
Protoss_Stargate 1 6250
Protoss_Citadel_of_Adun 1 6877
Protoss_Corsair 2 8027
9726
