Protoss_Nexus 2 4984
Protoss_Gateway 3 9774
Protoss_Forge 1 2896
Protoss_Zealot 9 9806
Protoss_Photon_Cannon 2 6937
Protoss_Assimilator 2 7064
Protoss_Cybernetics_Core 1 5963
Protoss_Stargate 1 7208
Protoss_Corsair 2 9196
Protoss_Citadel_of_Adun 1 8941
9806
