Protoss_Nexus 2 3113
Protoss_Forge 1 3403
Protoss_Gateway 6 9722
Protoss_Photon_Cannon 2 9762
Protoss_Assimilator 2 6754
Protoss_Zealot 10 9903
Protoss_Cybernetics_Core 1 5850
Protoss_Citadel_of_Adun 1 7129
Protoss_Templar_Archives 1 8695
Protoss_Dark_Templar 1 9891
9903
