Protoss_Nexus 3 9249
Protoss_Gateway 3 3879
Protoss_Zealot 9 8333
Protoss_Assimilator 2 7357
Protoss_Forge 1 5908
Protoss_Cybernetics_Core 1 6662
Protoss_Photon_Cannon 4 9828
Protoss_Citadel_of_Adun 1 8926
9828
