Protoss_Nexus 2 9355
Protoss_Gateway 1 2058
Protoss_Assimilator 1 2560
Protoss_Zealot 2 4416
Protoss_Cybernetics_Core 1 4060
Protoss_Citadel_of_Adun 1 5318
Protoss_Dragoon 1 5461
Protoss_Forge 1 6219
Protoss_Templar_Archives 1 6478
Protoss_Photon_Cannon 3 9873
Protoss_High_Templar 3 9599
9873
