Protoss_Nexus 2 3193
Protoss_Forge 1 3723
Protoss_Gateway 3 7603
Protoss_Photon_Cannon 4 8848
Protoss_Assimilator 2 6593
Protoss_Cybernetics_Core 1 5572
Protoss_Zealot 6 9196
Protoss_Stargate 1 6678
Protoss_Citadel_of_Adun 1 7129
Protoss_Corsair 3 9676
Protoss_Templar_Archives 1 9380
9676
