Protoss_Nexus 2 3718
Protoss_Forge 1 2260
Protoss_Photon_Cannon 2 4152
Protoss_Gateway 4 8346
Protoss_Assimilator 2 9388
Protoss_Zealot 9 9816
Protoss_Cybernetics_Core 1 5720
Protoss_Citadel_of_Adun 1 6822
Protoss_Dragoon 1 7788
Protoss_Templar_Archives 1 9371
9816
