Protoss_Nexus 2 3521
Protoss_Forge 1 2179
Protoss_Gateway 2 8821
Protoss_Assimilator 2 6250
Protoss_Photon_Cannon 3 9214
Protoss_Cybernetics_Core 1 5439
Protoss_Zealot 2 9749
Protoss_Stargate 1 6594
Protoss_Robotics_Facility 1 7688
Protoss_Corsair 2 8447
Protoss_Dragoon 1 8501
Protoss_Robotics_Support_Bay 1 9039
Protoss_Reaver 1 9633
9749
