Protoss_Nexus 2 3433
Protoss_Forge 1 2528
Protoss_Photon_Cannon 4 10000
Protoss_Gateway 3 8228
Protoss_Assimilator 2 8669
Protoss_Zealot 8 9263
Protoss_Cybernetics_Core 1 5981
Protoss_Citadel_of_Adun 1 7038
Protoss_Dragoon 1 7041
Protoss_Templar_Archives 1 8828
10000
