Protoss_Nexus 2 5383
Protoss_Forge 1 1895
Protoss_Photon_Cannon 6 6759
Protoss_Gateway 1 5828
Protoss_Assimilator 2 8575
Protoss_Zealot 4 8783
Protoss_Cybernetics_Core 1 7269
Protoss_Stargate 1 8396
Protoss_Citadel_of_Adun 1 9275
9275
