Protoss_Nexus 2 3587
Protoss_Forge 1 2405
Protoss_Photon_Cannon 5 9603
Protoss_Gateway 2 9218
Protoss_Assimilator 2 6775
Protoss_Zealot 2 9217
Protoss_Cybernetics_Core 1 5450
Protoss_Stargate 1 6591
Protoss_Robotics_Facility 1 7405
Protoss_Corsair 3 8997
Protoss_Citadel_of_Adun 1 8192
Protoss_Templar_Archives 1 9362
9603
