Protoss_Nexus 2 3088
Protoss_Forge 1 1871
Protoss_Photon_Cannon 9 9149
Protoss_Gateway 1 4628
Protoss_Assimilator 2 6961
Protoss_Zealot 4 8675
Protoss_Cybernetics_Core 1 6105
Protoss_Dragoon 1 9277
9277
