Protoss_Nexus 2 8727
Protoss_Gateway 1 2083
Protoss_Assimilator 1 2653
Protoss_Zealot 4 7216
Protoss_Cybernetics_Core 1 4033
Protoss_Stargate 1 5068
Protoss_Dragoon 1 5471
Protoss_Corsair 1 6206
Protoss_Citadel_of_Adun 1 6720
Protoss_Templar_Archives 1 7778
Protoss_Dark_Templar 2 9698
9698
