Protoss_Nexus 2 3077
Protoss_Forge 1 3408
Protoss_Photon_Cannon 3 4908
Protoss_Gateway 6 8635
Protoss_Assimilator 1 5370
Protoss_Cybernetics_Core 1 5991
Protoss_Zealot 9 9676
Protoss_Citadel_of_Adun 1 7099
Protoss_Stargate 1 8273
Protoss_Templar_Archives 1 9768
9768
