Protoss_Nexus 2 3799
Protoss_Forge 1 2373
Protoss_Photon_Cannon 3 9897
Protoss_Gateway 3 8039
Protoss_Assimilator 2 7036
Protoss_Zealot 9 9261
Protoss_Cybernetics_Core 1 5265
Protoss_Citadel_of_Adun 1 6492
Protoss_Templar_Archives 1 7755
Protoss_Dark_Templar 1 9855
Protoss_High_Templar 2 9863
Protoss_Ground_Weapons_1 1 9993
9993
