Protoss_Nexus 2 3249
Protoss_Forge 1 3545
Protoss_Gateway 3 7569
Protoss_Photon_Cannon 1 4247
Protoss_Assimilator 2 6261
Protoss_Cybernetics_Core 1 5145
Protoss_Zealot 2 6781
Protoss_Stargate 1 6145
Protoss_Citadel_of_Adun 1 6587
Protoss_Corsair 2 7913
Protoss_Templar_Archives 1 7722
Protoss_Dark_Templar 3 8723
Protoss_Robotics_Facility 1 9263
9263
