Protoss_Nexus 1 0
Protoss_Gateway 2 2094
Protoss_Zealot 5 8563
Protoss_Assimilator 1 3882
Protoss_Cybernetics_Core 1 4381
Protoss_Dragoon 1 5363
Protoss_Forge 1 5659
Protoss_Robotics_Facility 1 6113
Protoss_Photon_Cannon 3 9131
Protoss_Shuttle 1 7395
Protoss_Robotics_Support_Bay 1 7529
Protoss_Reaver 1 8297
Protoss_Stargate 1 8370
Protoss_Corsair 1 9499
Protoss_Scarab 1 9931
9931
