Protoss_Nexus 1 0
Protoss_Gateway 3 9926
Protoss_Assimilator 1 2542
Protoss_Cybernetics_Core 1 3155
Protoss_Zealot 7 9429
Protoss_Stargate 1 4392
Protoss_Corsair 2 6335
Protoss_Citadel_of_Adun 1 5949
9926
