Protoss_Nexus 2 3723
Protoss_Forge 1 2111
Protoss_Photon_Cannon 2 9458
Protoss_Gateway 5 9851
Protoss_Assimilator 2 5954
Protoss_Cybernetics_Core 1 5225
Protoss_Zealot 11 9779
Protoss_Stargate 1 6412
Protoss_Corsair 2 8199
Protoss_Citadel_of_Adun 1 7815
Protoss_Shield_Battery 1 9700
9851
