Protoss_Nexus 2 5611
Protoss_Gateway 2 2199
Protoss_Zealot 9 9023
Protoss_Assimilator 2 6258
Protoss_Forge 1 5998
Protoss_Cybernetics_Core 1 7067
Protoss_Photon_Cannon 2 7755
Protoss_Citadel_of_Adun 1 8641
Protoss_Templar_Archives 1 9673
9673
