Protoss_Nexus 2 3481
Protoss_Forge 1 2544
Protoss_Photon_Cannon 1 3322
Protoss_Gateway 5 7898
Protoss_Assimilator 2 8336
Protoss_Cybernetics_Core 1 5317
Protoss_Zealot 14 9943
Protoss_Citadel_of_Adun 1 6440
Protoss_Dragoon 1 6835
Protoss_Templar_Archives 1 9373
Protoss_Ground_Weapons_1 1 9811
9943
