Protoss_Nexus 2 3623
Protoss_Forge 1 3097
Protoss_Photon_Cannon 7 9833
Protoss_Gateway 1 5444
Protoss_Assimilator 2 6875
Protoss_Cybernetics_Core 1 6449
Protoss_Zealot 4 9643
Protoss_Stargate 1 7507
Protoss_Citadel_of_Adun 1 8762
Protoss_Corsair 2 9459
Protoss_Templar_Archives 1 9831
9833
