Protoss_Nexus 2 2818
Protoss_Forge 1 3083
Protoss_Photon_Cannon 4 9475
Protoss_Gateway 1 4424
Protoss_Assimilator 2 5983
Protoss_Cybernetics_Core 1 5468
Protoss_Zealot 1 5856
Protoss_Dragoon 1 6476
Protoss_Stargate 1 7803
Protoss_Robotics_Facility 2 9155
Protoss_Corsair 2 9598
Protoss_Shuttle 1 9901
9901
