Protoss_Nexus 2 3963
Protoss_Forge 1 2009
Protoss_Photon_Cannon 9 9708
Protoss_Gateway 3 8927
Protoss_Assimilator 2 8138
Protoss_Cybernetics_Core 1 5735
Protoss_Zealot 3 8101
Protoss_Citadel_of_Adun 1 6742
Protoss_Templar_Archives 1 8382
Protoss_High_Templar 2 9946
9946
