Protoss_Nexus 2 2999
Protoss_Forge 1 3321
Protoss_Photon_Cannon 2 5864
Protoss_Assimilator 2 4973
Protoss_Gateway 1 5569
Protoss_Zealot 4 9731
Protoss_Cybernetics_Core 1 6918
Protoss_Citadel_of_Adun 1 8033
9731
