Protoss_Nexus 2 3312
Protoss_Forge 1 2639
Protoss_Photon_Cannon 4 9098
Protoss_Gateway 2 7016
Protoss_Assimilator 2 6812
Protoss_Zealot 8 9821
Protoss_Cybernetics_Core 1 6103
Protoss_Citadel_of_Adun 1 7213
Protoss_Dragoon 1 7311
Protoss_Stargate 2 8699
Protoss_Corsair 2 9906
Protoss_Ground_Weapons_1 1 9896
9906
