Protoss_Nexus 3 8509
Protoss_Forge 1 2069
Protoss_Assimilator 2 5586
Protoss_Gateway 1 4431
Protoss_Photon_Cannon 7 9860
Protoss_Zealot 1 5597
Protoss_Cybernetics_Core 1 5729
Protoss_Stargate 1 6917
Protoss_Robotics_Facility 1 7396
Protoss_Corsair 1 8095
Protoss_Robotics_Support_Bay 1 8766
Protoss_Reaver 1 9645
9860
