Protoss_Nexus 2 2968
Protoss_Forge 1 3363
Protoss_Gateway 4 9285
Protoss_Photon_Cannon 4 7852
Protoss_Assimilator 2 6110
Protoss_Cybernetics_Core 1 5201
Protoss_Zealot 2 7111
Protoss_Stargate 1 6248
Protoss_Dragoon 1 6359
Protoss_Citadel_of_Adun 1 6953
Protoss_Corsair 4 9453
Protoss_Templar_Archives 1 8053
Protoss_Dark_Templar 2 9051
9453
