Protoss_Nexus 1 0
Protoss_Gateway 2 6299
Protoss_Assimilator 1 2564
Protoss_Zealot 6 7465
Protoss_Cybernetics_Core 1 4284
Protoss_Dragoon 1 5491
Protoss_Citadel_of_Adun 1 5892
Protoss_Templar_Archives 1 7367
Protoss_Forge 1 8253
Protoss_High_Templar 2 9278
9278
