Protoss_Nexus 2 4004
Protoss_Forge 1 2409
Protoss_Photon_Cannon 7 9829
Protoss_Assimilator 2 7095
Protoss_Gateway 3 9143
Protoss_Cybernetics_Core 1 5834
Protoss_Zealot 1 5987
Protoss_Stargate 1 6848
Protoss_Corsair 3 9411
Protoss_Citadel_of_Adun 1 8083
Protoss_Templar_Archives 1 9108
9829
