Protoss_Nexus 2 6678
Protoss_Gateway 3 9870
Protoss_Zealot 13 9461
Protoss_Forge 2 7672
Protoss_Photon_Cannon 1 5678
Protoss_Assimilator 2 9244
Protoss_Cybernetics_Core 1 8967
9870
