Protoss_Nexus 2 3728
Protoss_Forge 1 2140
Protoss_Photon_Cannon 1 4126
Protoss_Assimilator 1 4797
Protoss_Gateway 6 9440
Protoss_Zealot 10 9770
Protoss_Cybernetics_Core 1 6003
Protoss_Citadel_of_Adun 1 7153
9770
