Protoss_Nexus 2 8727
Protoss_Gateway 1 1851
Protoss_Assimilator 1 2189
Protoss_Zealot 3 5317
Protoss_Cybernetics_Core 1 3530
Protoss_Dragoon 1 4565
Protoss_Stargate 1 4816
Protoss_Citadel_of_Adun 1 5453
Protoss_Corsair 5 9501
Protoss_Templar_Archives 1 6445
Protoss_Forge 1 6918
Protoss_Dark_Templar 1 7991
Protoss_Photon_Cannon 2 9145
Protoss_High_Templar 2 9699
9699
