Protoss_Nexus 2 4342
Protoss_Forge 1 1948
Protoss_Photon_Cannon 3 4488
Protoss_Gateway 3 8073
Protoss_Assimilator 2 9505
Protoss_Zealot 9 9723
Protoss_Cybernetics_Core 1 5954
Protoss_Citadel_of_Adun 1 7170
Protoss_Dragoon 1 7311
Protoss_Templar_Archives 1 9427
9723
