Protoss_Nexus 1 0
Protoss_Gateway 3 7064
Protoss_Assimilator 1 2740
Protoss_Zealot 9 9581
Protoss_Cybernetics_Core 1 3884
Protoss_Dragoon 1 4916
Protoss_Stargate 1 5048
Protoss_Citadel_of_Adun 1 5640
Protoss_Corsair 1 6856
Protoss_Templar_Archives 1 8668
9581
