Protoss_Nexus 2 3298
Protoss_Forge 1 2243
Protoss_Photon_Cannon 8 9923
Protoss_Gateway 4 9253
Protoss_Assimilator 2 5646
Protoss_Cybernetics_Core 1 5250
Protoss_Zealot 5 8466
Protoss_Citadel_of_Adun 1 6365
Protoss_Templar_Archives 1 7743
Protoss_High_Templar 2 8916
Protoss_Archon 1 9872
Protoss_Ground_Weapons_1 1 9931
9931
