Protoss_Nexus 2 3586
Protoss_Forge 1 2470
Protoss_Photon_Cannon 2 9314
Protoss_Gateway 3 7888
Protoss_Assimilator 2 8559
Protoss_Cybernetics_Core 1 5674
Protoss_Zealot 11 9988
Protoss_Citadel_of_Adun 1 7269
Protoss_Templar_Archives 1 8713
Protoss_Robotics_Facility 1 9683
9988
