Protoss_Nexus 2 3703
Protoss_Forge 1 2512
Protoss_Photon_Cannon 5 9876
Protoss_Gateway 1 4448
Protoss_Assimilator 2 6233
Protoss_Cybernetics_Core 1 5463
Protoss_Zealot 3 9631
Protoss_Stargate 1 6641
Protoss_Corsair 4 9831
Protoss_Robotics_Facility 1 8864
9876
