Protoss_Nexus 3 7963
Protoss_Gateway 2 2203
Protoss_Zealot 9 5958
Protoss_Forge 1 4318
Protoss_Photon_Cannon 3 9568
Protoss_Assimilator 2 9449
Protoss_Cybernetics_Core 1 8782
9568
