Protoss_Nexus 1 0
Protoss_Gateway 2 2513
Protoss_Zealot 12 9786
Protoss_Assimilator 1 4889
Protoss_Cybernetics_Core 1 5416
Protoss_Forge 1 6318
Protoss_Photon_Cannon 5 9438
9786
