Protoss_Nexus 2 4763
Protoss_Forge 1 2248
Protoss_Photon_Cannon 5 9718
Protoss_Gateway 4 7768
Protoss_Assimilator 2 8523
Protoss_Cybernetics_Core 1 6373
Protoss_Zealot 10 9461
Protoss_Citadel_of_Adun 1 7459
Protoss_Dragoon 1 9061
Protoss_Templar_Archives 1 9202
9718
