Protoss_Nexus 2 5397
Protoss_Gateway 4 9815
Protoss_Zealot 14 9631
Protoss_Forge 1 5779
Protoss_Assimilator 1 6098
Protoss_Photon_Cannon 1 6473
Protoss_Cybernetics_Core 1 6913
Protoss_Citadel_of_Adun 1 8111
9815
