Protoss_Nexus 2 3318
Protoss_Forge 2 9598
Protoss_Photon_Cannon 2 8885
Protoss_Gateway 4 7733
Protoss_Assimilator 2 6148
Protoss_Zealot 13 9323
Protoss_Cybernetics_Core 1 5245
Protoss_Citadel_of_Adun 1 6433
Protoss_Templar_Archives 1 9473
Protoss_Ground_Weapons_1 1 9891
9891
