Protoss_Nexus 2 7993
Protoss_Gateway 2 2502
Protoss_Zealot 5 5506
Protoss_Assimilator 1 3605
Protoss_Cybernetics_Core 1 4640
Protoss_Forge 1 5306
Protoss_Photon_Cannon 3 9552
9552
