Protoss_Nexus 2 3104
Protoss_Forge 2 7791
Protoss_Photon_Cannon 2 5100
Protoss_Gateway 4 9689
Protoss_Assimilator 2 7676
Protoss_Zealot 5 9981
Protoss_Cybernetics_Core 1 6416
Protoss_Citadel_of_Adun 1 7587
Protoss_Dragoon 1 9071
9981
