Protoss_Nexus 3 9873
Protoss_Forge 1 3391
Protoss_Photon_Cannon 1 4208
Protoss_Gateway 4 7548
Protoss_Assimilator 2 7663
Protoss_Zealot 12 9473
Protoss_Cybernetics_Core 1 6332
Protoss_Citadel_of_Adun 1 7333
Protoss_Templar_Archives 1 9346
9873
