Protoss_Nexus 2 9223
Protoss_Gateway 2 8536
Protoss_Zealot 4 5017
Protoss_Assimilator 1 3181
Protoss_Cybernetics_Core 1 3920
Protoss_Stargate 1 5129
Protoss_Dragoon 1 5619
Protoss_Citadel_of_Adun 1 6069
Protoss_Forge 1 6255
Protoss_Corsair 1 6467
Protoss_Templar_Archives 1 7059
Protoss_Photon_Cannon 5 9819
Protoss_Dark_Templar 1 8231
9819
