Protoss_Nexus 1 0
Protoss_Gateway 2 2648
Protoss_Zealot 10 9801
Protoss_Assimilator 1 3685
Protoss_Cybernetics_Core 1 4418
Protoss_Dragoon 1 5561
Protoss_Citadel_of_Adun 1 6173
Protoss_Forge 1 7153
Protoss_Photon_Cannon 2 8893
Protoss_Templar_Archives 1 9458
9801
