Protoss_Nexus 2 3323
Protoss_Forge 1 2539
Protoss_Photon_Cannon 2 7814
Protoss_Gateway 4 9869
Protoss_Assimilator 2 6929
Protoss_Zealot 4 8113
Protoss_Cybernetics_Core 1 5762
Protoss_Dragoon 2 7488
Protoss_Stargate 1 7003
Protoss_Citadel_of_Adun 1 8139
9869
