Protoss_Nexus 2 3433
Protoss_Forge 1 2322
Protoss_Photon_Cannon 2 8932
Protoss_Gateway 4 8304
Protoss_Assimilator 2 7371
Protoss_Zealot 15 9968
Protoss_Cybernetics_Core 1 6384
Protoss_Citadel_of_Adun 1 7503
Protoss_Templar_Archives 1 9053
Protoss_Ground_Weapons_1 1 9996
9996
