Protoss_Nexus 2 4112
Protoss_Forge 1 2175
Protoss_Photon_Cannon 3 9445
Protoss_Gateway 4 8363
Protoss_Assimilator 1 4795
Protoss_Zealot 11 9497
Protoss_Cybernetics_Core 1 5547
Protoss_Citadel_of_Adun 1 6703
9497
