Protoss_Nexus 2 3429
Protoss_Forge 2 9867
Protoss_Photon_Cannon 2 3992
Protoss_Gateway 4 8077
Protoss_Assimilator 2 6539
Protoss_Zealot 11 9921
Protoss_Cybernetics_Core 1 6127
Protoss_Citadel_of_Adun 1 7265
Protoss_Templar_Archives 1 9823
9921
