Protoss_Nexus 2 3303
Protoss_Forge 2 9316
Protoss_Photon_Cannon 4 9204
Protoss_Gateway 3 9734
Protoss_Assimilator 2 6263
Protoss_Zealot 3 7803
Protoss_Cybernetics_Core 1 5856
Protoss_Stargate 1 6847
Protoss_Citadel_of_Adun 1 7369
Protoss_Corsair 3 9777
Protoss_Templar_Archives 1 8427
Protoss_Dark_Templar 2 9533
9777
