Protoss_Nexus 2 3359
Protoss_Forge 1 2091
Protoss_Gateway 3 9640
Protoss_Photon_Cannon 12 9883
Protoss_Assimilator 2 5872
Protoss_Zealot 1 5159
Protoss_Cybernetics_Core 1 5462
Protoss_Citadel_of_Adun 1 6478
Protoss_Templar_Archives 1 7543
Protoss_Dark_Templar 1 8543
Protoss_High_Templar 2 9305
9883
