Protoss_Nexus 2 3488
Protoss_Forge 1 2291
Protoss_Gateway 5 8918
Protoss_Photon_Cannon 3 9974
Protoss_Assimilator 2 6707
Protoss_Zealot 12 9782
Protoss_Cybernetics_Core 1 5967
Protoss_Citadel_of_Adun 1 7170
Protoss_Templar_Archives 1 9632
9974
