Protoss_Nexus 2 3331
Protoss_Forge 1 2320
Protoss_Gateway 4 8785
Protoss_Assimilator 2 6461
Protoss_Zealot 9 9959
Protoss_Cybernetics_Core 1 5087
Protoss_Photon_Cannon 1 5633
Protoss_Stargate 1 6269
Protoss_Citadel_of_Adun 1 6908
Protoss_Corsair 2 8097
Protoss_Robotics_Facility 1 9972
9972
