Protoss_Nexus 2 3007
Protoss_Forge 2 8769
Protoss_Photon_Cannon 4 9828
Protoss_Gateway 3 8218
Protoss_Assimilator 2 7469
Protoss_Zealot 5 8676
Protoss_Cybernetics_Core 1 7243
Protoss_Citadel_of_Adun 1 8327
Protoss_Dragoon 1 8578
9828
