Protoss_Nexus 2 3371
Protoss_Forge 1 2896
Protoss_Photon_Cannon 4 9473
Protoss_Gateway 4 7649
Protoss_Assimilator 2 6559
Protoss_Cybernetics_Core 1 5791
Protoss_Zealot 2 6651
Protoss_Citadel_of_Adun 1 6929
Protoss_Templar_Archives 1 7955
Protoss_Dragoon 1 8579
Protoss_High_Templar 5 9729
9729
