Protoss_Nexus 2 2907
Protoss_Forge 1 3491
Protoss_Gateway 4 9768
Protoss_Assimilator 2 5524
Protoss_Photon_Cannon 5 9643
Protoss_Cybernetics_Core 1 5395
Protoss_Zealot 3 8413
Protoss_Stargate 1 6733
Protoss_Citadel_of_Adun 1 6762
Protoss_Dragoon 1 7035
Protoss_Corsair 3 9651
Protoss_Templar_Archives 1 8148
Protoss_Dark_Templar 2 9165
Protoss_High_Templar 2 9917
9917
