Protoss_Nexus 2 4021
Protoss_Forge 1 2303
Protoss_Photon_Cannon 6 9368
Protoss_Gateway 2 8671
Protoss_Assimilator 2 7461
Protoss_Zealot 2 5903
Protoss_Cybernetics_Core 1 5761
Protoss_Stargate 1 6775
Protoss_Citadel_of_Adun 1 7244
Protoss_Corsair 1 7913
Protoss_Templar_Archives 1 8527
Protoss_Dark_Templar 1 9543
9543
