Protoss_Nexus 1 0
Protoss_Gateway 2 2436
Protoss_Zealot 9 9291
Protoss_Assimilator 1 4513
Protoss_Cybernetics_Core 2 6286
Protoss_Stargate 1 6505
Protoss_Dragoon 1 6563
Protoss_Citadel_of_Adun 1 6977
Protoss_Forge 1 7563
Protoss_Corsair 1 7855
Protoss_Templar_Archives 1 8225
Protoss_Photon_Cannon 2 9905
Protoss_Dark_Templar 1 9215
9905
