Protoss_Nexus 2 3449
Protoss_Forge 1 2361
Protoss_Photon_Cannon 7 9929
Protoss_Gateway 4 9571
Protoss_Assimilator 2 6693
Protoss_Cybernetics_Core 1 6065
Protoss_Zealot 7 9221
Protoss_Citadel_of_Adun 1 7295
Protoss_Templar_Archives 1 8875
9929
