Protoss_Nexus 2 3589
Protoss_Forge 1 2354
Protoss_Photon_Cannon 2 3875
Protoss_Gateway 1 4596
Protoss_Assimilator 2 6561
Protoss_Cybernetics_Core 1 5713
Protoss_Zealot 2 9929
9929
