Protoss_Nexus 2 3515
Protoss_Forge 2 8867
Protoss_Photon_Cannon 9 9994
Protoss_Gateway 4 9587
Protoss_Assimilator 2 7657
Protoss_Zealot 2 6875
Protoss_Cybernetics_Core 1 6351
Protoss_Citadel_of_Adun 1 7494
Protoss_Dragoon 1 7518
Protoss_Templar_Archives 1 8669
Protoss_High_Templar 1 9927
9994
