Protoss_Nexus 2 4169
Protoss_Forge 2 8734
Protoss_Photon_Cannon 5 5198
Protoss_Gateway 3 9419
Protoss_Assimilator 2 9707
Protoss_Zealot 4 9851
Protoss_Cybernetics_Core 1 8120
Protoss_Citadel_of_Adun 1 9128
9851
