Protoss_Nexus 2 9635
Protoss_Gateway 2 7898
Protoss_Assimilator 2 8828
Protoss_Zealot 6 8751
Protoss_Cybernetics_Core 1 3643
Protoss_Stargate 1 4627
Protoss_Dragoon 1 4651
Protoss_Citadel_of_Adun 1 5098
Protoss_Forge 1 5397
Protoss_Corsair 2 6849
Protoss_Templar_Archives 1 6181
Protoss_Photon_Cannon 3 8947
Protoss_Dark_Templar 1 7177
Protoss_High_Templar 1 9071
9635
