Special_Protoss_Temple 14 0
Protoss_Nexus 2 3847
Protoss_Forge 1 2295
Protoss_Photon_Cannon 4 8058
Protoss_Gateway 2 9570
Protoss_Assimilator 2 6379
Protoss_Cybernetics_Core 1 5099
Protoss_Zealot 2 6885
Protoss_Stargate 1 6111
Protoss_Corsair 4 9611
Protoss_Citadel_of_Adun 1 7471
Protoss_Templar_Archives 1 8506
Protoss_Dark_Templar 1 9879
9879
