Protoss_Nexus 2 3268
Protoss_Forge 2 8293
Protoss_Photon_Cannon 3 9474
Protoss_Gateway 4 9087
Protoss_Assimilator 2 6411
Protoss_Cybernetics_Core 1 5855
Protoss_Zealot 5 9139
Protoss_Stargate 1 6909
Protoss_Citadel_of_Adun 1 7219
Protoss_Dragoon 1 7587
Protoss_Corsair 1 8045
Protoss_Templar_Archives 1 8383
9474
