Protoss_Nexus 2 3779
Protoss_Forge 2 9304
Protoss_Photon_Cannon 2 9840
Protoss_Gateway 4 8732
Protoss_Assimilator 2 6768
Protoss_Cybernetics_Core 1 5203
Protoss_Zealot 3 8143
Protoss_Stargate 1 6353
Protoss_Citadel_of_Adun 1 7068
Protoss_Dragoon 1 7391
Protoss_Corsair 1 7549
Protoss_Templar_Archives 1 8077
Protoss_Dark_Templar 3 9875
Protoss_High_Templar 2 9817
9875
