Protoss_Nexus 2 3178
Protoss_Forge 2 8646
Protoss_Photon_Cannon 4 8343
Protoss_Gateway 4 9959
Protoss_Assimilator 2 6312
Protoss_Cybernetics_Core 1 5450
Protoss_Zealot 5 8349
Protoss_Stargate 1 6517
Protoss_Citadel_of_Adun 1 7179
Protoss_Corsair 1 7743
Protoss_Templar_Archives 1 8227
Protoss_Dark_Templar 1 9221
Protoss_High_Templar 1 9999
9999
