Protoss_Nexus 2 5045
Protoss_Forge 1 3009
Protoss_Photon_Cannon 5 9282
Protoss_Gateway 1 5167
Protoss_Assimilator 2 8561
Protoss_Zealot 5 9187
Protoss_Cybernetics_Core 1 6936
Protoss_Stargate 1 7942
Protoss_Corsair 2 9845
Protoss_Robotics_Facility 1 9427
9845
