Protoss_Nexus 2 9958
Protoss_Gateway 2 2148
Protoss_Zealot 15 8165
Protoss_Assimilator 1 5657
Protoss_Cybernetics_Core 1 6553
Protoss_Forge 1 7629
Protoss_Stargate 1 8067
Protoss_Photon_Cannon 1 8559
Protoss_Corsair 1 9207
9958
