Protoss_Nexus 2 2567
Protoss_Forge 1 2791
Protoss_Photon_Cannon 1 3492
Protoss_Gateway 4 9745
Protoss_Assimilator 2 5447
Protoss_Cybernetics_Core 1 4957
Protoss_Zealot 3 6357
Protoss_Stargate 2 6325
Protoss_Citadel_of_Adun 1 6794
Protoss_Corsair 7 9073
Protoss_Templar_Archives 1 7979
Protoss_Dark_Templar 1 9453
9745
