Protoss_Nexus 2 3513
Protoss_Forge 1 2428
Protoss_Photon_Cannon 1 3156
Protoss_Gateway 4 7666
Protoss_Assimilator 2 8108
Protoss_Cybernetics_Core 1 5203
Protoss_Zealot 13 9245
Protoss_Citadel_of_Adun 1 6373
Protoss_Stargate 2 9603
9603
