Protoss_Nexus 2 3302
Protoss_Forge 1 2276
Protoss_Gateway 2 7662
Protoss_Photon_Cannon 3 9347
Protoss_Assimilator 2 6922
Protoss_Zealot 9 9967
Protoss_Cybernetics_Core 1 5125
Protoss_Stargate 1 6629
Protoss_Citadel_of_Adun 1 7101
Protoss_Corsair 4 9819
Protoss_Templar_Archives 1 9486
9967
