Protoss_Nexus 2 6795
Protoss_Gateway 1 1816
Protoss_Forge 1 2638
Protoss_Zealot 12 9625
Protoss_Photon_Cannon 9 8791
Protoss_Assimilator 1 6951
Protoss_Cybernetics_Core 1 8077
Protoss_Citadel_of_Adun 1 9790
9790
