Protoss_Nexus 2 3203
Protoss_Forge 1 2536
Protoss_Photon_Cannon 2 9925
Protoss_Gateway 4 9359
Protoss_Assimilator 2 6152
Protoss_Cybernetics_Core 1 5037
Protoss_Zealot 3 8221
Protoss_Stargate 1 6034
Protoss_Dragoon 1 6381
Protoss_Citadel_of_Adun 1 6799
Protoss_Corsair 3 8589
Protoss_Templar_Archives 1 7967
Protoss_Dark_Templar 2 8999
Protoss_High_Templar 2 9751
9925
