Protoss_Nexus 2 3121
Protoss_Forge 1 2605
Protoss_Photon_Cannon 1 3413
Protoss_Gateway 2 9168
Protoss_Assimilator 2 5738
Protoss_Cybernetics_Core 1 4899
Protoss_Zealot 4 7423
Protoss_Stargate 2 7636
Protoss_Citadel_of_Adun 1 6591
Protoss_Corsair 7 9909
Protoss_Templar_Archives 1 7661
Protoss_Dark_Templar 2 9463
9909
