Protoss_Nexus 2 3711
Protoss_Forge 1 2510
Protoss_Photon_Cannon 1 3260
Protoss_Gateway 2 4253
Protoss_Assimilator 2 9561
Protoss_Zealot 15 9897
Protoss_Cybernetics_Core 1 6079
Protoss_Stargate 1 7117
Protoss_Corsair 3 9707
Protoss_Citadel_of_Adun 1 8898
9897
