Protoss_Nexus 2 2511
Protoss_Forge 1 2783
Protoss_Photon_Cannon 3 5833
Protoss_Gateway 2 9077
Protoss_Assimilator 2 6255
Protoss_Cybernetics_Core 1 4857
Protoss_Zealot 4 9675
Protoss_Stargate 2 6707
Protoss_Corsair 8 9827
Protoss_Citadel_of_Adun 1 8721
9827
