Protoss_Nexus 2 4113
Protoss_Forge 1 2316
Protoss_Photon_Cannon 3 9613
Protoss_Gateway 4 8712
Protoss_Assimilator 2 8897
Protoss_Cybernetics_Core 1 5465
Protoss_Zealot 9 9133
Protoss_Citadel_of_Adun 1 6516
Protoss_Dragoon 3 9937
9937
