Protoss_Nexus 2 2881
Protoss_Forge 1 3143
Protoss_Assimilator 1 3700
Protoss_Gateway 4 6797
Protoss_Photon_Cannon 1 4619
Protoss_Cybernetics_Core 1 4891
Protoss_Zealot 17 9661
Protoss_Citadel_of_Adun 1 6124
Protoss_Stargate 2 8820
Protoss_Ground_Weapons_1 1 9305
Protoss_Corsair 2 9949
9949
