Protoss_Nexus 2 4113
Protoss_Forge 1 2536
Protoss_Photon_Cannon 4 9736
Protoss_Gateway 1 4645
Protoss_Assimilator 2 6259
Protoss_Zealot 6 8842
Protoss_Cybernetics_Core 1 5641
Protoss_Stargate 2 7596
Protoss_Corsair 6 9893
Protoss_Citadel_of_Adun 1 9501
9893
