Protoss_Nexus 2 3024
Protoss_Forge 2 3733
Protoss_Gateway 2 6621
Protoss_Assimilator 2 6831
Protoss_Photon_Cannon 2 8855
Protoss_Cybernetics_Core 1 4811
Protoss_Zealot 8 9469
Protoss_Stargate 1 6023
Protoss_Corsair 3 9711
Protoss_Citadel_of_Adun 1 7267
9711
