Protoss_Nexus 1 0
Protoss_Gateway 2 2467
Protoss_Zealot 12 9257
Protoss_Assimilator 1 4683
Protoss_Cybernetics_Core 1 5610
Protoss_Forge 1 6523
Protoss_Stargate 1 7025
Protoss_Photon_Cannon 3 9740
Protoss_Citadel_of_Adun 1 7800
Protoss_Corsair 2 8787
9740
