Special_Protoss_Temple 14 0
Protoss_Nexus 2 4165
Protoss_Forge 1 2296
Protoss_Photon_Cannon 3 8949
Protoss_Gateway 4 9927
Protoss_Assimilator 2 6425
Protoss_Cybernetics_Core 1 5493
Protoss_Zealot 3 7615
Protoss_Stargate 1 6588
Protoss_Dragoon 1 6863
Protoss_Citadel_of_Adun 1 7328
Protoss_Corsair 3 9185
Protoss_Templar_Archives 1 8418
Protoss_Dark_Templar 2 9413
9927
