Special_Protoss_Temple 30 0
Protoss_Nexus 2 4163
Protoss_Forge 1 2427
Protoss_Photon_Cannon 4 8725
Protoss_Gateway 1 4562
Protoss_Assimilator 2 6070
Protoss_Zealot 3 8167
Protoss_Cybernetics_Core 1 5596
Protoss_Stargate 1 6681
Protoss_Dragoon 1 6953
Protoss_Robotics_Facility 1 7723
Protoss_Corsair 4 9965
Protoss_Robotics_Support_Bay 1 9087
9965
