Protoss_Nexus 2 6053
Protoss_Gateway 2 2515
Protoss_Zealot 10 9997
Protoss_Forge 1 4731
Protoss_Photon_Cannon 2 7986
Protoss_Assimilator 2 7219
Protoss_Cybernetics_Core 1 7015
Protoss_Stargate 1 8125
Protoss_Citadel_of_Adun 1 8655
Protoss_Corsair 1 9271
Protoss_Templar_Archives 1 9649
9997
