Protoss_Nexus 2 3828
Protoss_Forge 1 2117
Protoss_Photon_Cannon 5 7426
Protoss_Gateway 6 9903
Protoss_Assimilator 2 6699
Protoss_Cybernetics_Core 1 5383
Protoss_Zealot 4 9487
Protoss_Stargate 1 6533
Protoss_Citadel_of_Adun 1 7093
Protoss_Corsair 1 7723
Protoss_Templar_Archives 1 8365
Protoss_Robotics_Facility 1 9253
Protoss_High_Templar 2 9351
Protoss_Dark_Templar 1 9429
9903
