Protoss_Nexus 2 4376
Protoss_Forge 2 9042
Protoss_Photon_Cannon 4 8415
Protoss_Gateway 2 9314
Protoss_Assimilator 2 6736
Protoss_Zealot 4 8819
Protoss_Cybernetics_Core 1 6055
Protoss_Stargate 1 7111
Protoss_Citadel_of_Adun 1 8095
9314
