Protoss_Nexus 2 4491
Protoss_Forge 1 2065
Protoss_Photon_Cannon 3 6300
Protoss_Gateway 5 8500
Protoss_Assimilator 2 7035
Protoss_Cybernetics_Core 1 6223
Protoss_Zealot 12 9915
Protoss_Citadel_of_Adun 1 7217
Protoss_Templar_Archives 1 9002
9915
