Protoss_Nexus 2 3463
Protoss_Forge 1 2452
Protoss_Photon_Cannon 3 8837
Protoss_Gateway 4 9481
Protoss_Assimilator 2 7363
Protoss_Cybernetics_Core 1 4921
Protoss_Zealot 4 7823
Protoss_Stargate 1 5913
Protoss_Citadel_of_Adun 1 6585
Protoss_Corsair 3 9213
Protoss_Templar_Archives 1 7881
Protoss_High_Templar 2 9849
9849
