Protoss_Nexus 2 3185
Protoss_Forge 1 2530
Protoss_Photon_Cannon 4 8123
Protoss_Gateway 4 9633
Protoss_Assimilator 2 7527
Protoss_Cybernetics_Core 1 5359
Protoss_Zealot 6 9361
Protoss_Stargate 1 6595
Protoss_Dragoon 1 7103
Protoss_Citadel_of_Adun 1 7464
Protoss_Corsair 1 7801
Protoss_Templar_Archives 1 9085
9633
