Protoss_Nexus 2 4250
Protoss_Gateway 3 9972
Protoss_Zealot 11 9729
Protoss_Forge 1 4676
Protoss_Photon_Cannon 5 8103
Protoss_Assimilator 2 9450
Protoss_Cybernetics_Core 1 6625
Protoss_Dragoon 2 9589
Protoss_Robotics_Facility 1 8359
Protoss_Shield_Battery 1 8522
Protoss_Citadel_of_Adun 1 9276
Protoss_Stargate 1 9378
9972
