Special_Protoss_Temple 14 0
Protoss_Nexus 2 4637
Protoss_Forge 1 2464
Protoss_Photon_Cannon 5 9898
Protoss_Gateway 2 9390
Protoss_Assimilator 2 6779
Protoss_Zealot 4 9699
Protoss_Cybernetics_Core 1 7274
Protoss_Dragoon 1 8345
Protoss_Citadel_of_Adun 1 8484
Protoss_Templar_Archives 1 9657
9898
