Protoss_Nexus 2 4214
Protoss_Forge 1 1961
Protoss_Photon_Cannon 3 8884
Protoss_Gateway 5 8559
Protoss_Assimilator 3 9998
Protoss_Zealot 11 9829
Protoss_Cybernetics_Core 1 5833
Protoss_Stargate 1 7099
Protoss_Dragoon 1 7259
Protoss_Citadel_of_Adun 1 7766
9998
