Protoss_Nexus 2 3201
Protoss_Forge 1 2174
Protoss_Photon_Cannon 1 3565
Protoss_Gateway 5 9487
Protoss_Assimilator 2 5030
Protoss_Cybernetics_Core 1 4873
Protoss_Zealot 1 5471
Protoss_Stargate 1 6007
Protoss_Citadel_of_Adun 1 6592
Protoss_Corsair 2 7823
Protoss_Templar_Archives 1 7593
Protoss_Dark_Templar 2 9457
Protoss_High_Templar 2 9409
9487
