Special_Protoss_Temple 14 0
Protoss_Nexus 2 3265
Protoss_Forge 1 2595
Protoss_Photon_Cannon 3 9238
Protoss_Gateway 2 7082
Protoss_Assimilator 2 8741
Protoss_Cybernetics_Core 1 5877
Protoss_Zealot 9 9775
Protoss_Stargate 1 6901
Protoss_Citadel_of_Adun 1 7608
Protoss_Corsair 2 8939
Protoss_Templar_Archives 1 9849
9849
