Protoss_Nexus 2 3255
Protoss_Forge 1 2368
Protoss_Photon_Cannon 2 7613
Protoss_Gateway 4 8277
Protoss_Assimilator 2 6241
Protoss_Cybernetics_Core 1 5552
Protoss_Zealot 11 9947
Protoss_Stargate 1 6539
Protoss_Dragoon 1 6589
Protoss_Citadel_of_Adun 1 7103
Protoss_Corsair 1 7669
9947
