Protoss_Nexus 2 3238
Protoss_Forge 1 2318
Protoss_Photon_Cannon 2 9431
Protoss_Gateway 3 8368
Protoss_Assimilator 2 6841
Protoss_Zealot 8 9769
Protoss_Cybernetics_Core 1 5553
Protoss_Stargate 1 6648
Protoss_Citadel_of_Adun 1 7387
Protoss_Corsair 2 9021
Protoss_Templar_Archives 1 9103
9769
