Protoss_Nexus 2 3471
Protoss_Forge 1 2217
Protoss_Gateway 4 7803
Protoss_Assimilator 2 8014
Protoss_Zealot 10 9701
Protoss_Photon_Cannon 4 9451
Protoss_Cybernetics_Core 1 5332
Protoss_Dragoon 1 6431
Protoss_Citadel_of_Adun 1 6535
Protoss_Templar_Archives 1 8491
Protoss_High_Templar 2 9669
Protoss_Dark_Templar 1 9679
Protoss_Ground_Weapons_1 1 9783
9783
