Protoss_Nexus 2 3428
Protoss_Forge 1 2370
Protoss_Gateway 4 8731
Protoss_Assimilator 2 5769
Protoss_Photon_Cannon 3 9715
Protoss_Cybernetics_Core 1 4901
Protoss_Zealot 4 8197
Protoss_Stargate 1 5995
Protoss_Citadel_of_Adun 1 6630
Protoss_Dragoon 1 6695
Protoss_Corsair 4 9749
Protoss_Templar_Archives 1 7722
Protoss_Dark_Templar 1 8813
9749
