Protoss_Nexus 2 3431
Protoss_Forge 1 2197
Protoss_Photon_Cannon 7 9445
Protoss_Gateway 1 4385
Protoss_Assimilator 2 8503
Protoss_Cybernetics_Core 1 5411
Protoss_Stargate 1 6410
Protoss_Robotics_Facility 1 7370
Protoss_Corsair 3 9561
Protoss_Shuttle 1 8753
Protoss_Robotics_Support_Bay 1 9049
Protoss_Reaver 1 9885
9885
