Protoss_Nexus 2 9489
Protoss_Gateway 1 1846
Protoss_Assimilator 1 2318
Protoss_Zealot 4 6243
Protoss_Cybernetics_Core 1 3473
Protoss_Stargate 1 4545
Protoss_Dragoon 1 4871
Protoss_Corsair 1 5813
Protoss_Citadel_of_Adun 1 5993
Protoss_Forge 1 6757
Protoss_Templar_Archives 1 7032
Protoss_Photon_Cannon 3 8916
Protoss_Dark_Templar 2 8831
Protoss_High_Templar 1 9667
9667
