Protoss_Nexus 2 3267
Protoss_Forge 1 2743
Protoss_Photon_Cannon 2 9871
Protoss_Gateway 2 7221
Protoss_Assimilator 2 5825
Protoss_Cybernetics_Core 1 5015
Protoss_Zealot 10 9739
Protoss_Stargate 1 6113
Protoss_Citadel_of_Adun 1 6827
Protoss_Corsair 1 7455
Protoss_Templar_Archives 1 8747
9871
