Protoss_Nexus 2 3405
Protoss_Forge 1 2152
Protoss_Gateway 4 9399
Protoss_Assimilator 2 6353
Protoss_Photon_Cannon 3 8819
Protoss_Cybernetics_Core 1 4993
Protoss_Zealot 5 9703
Protoss_Stargate 1 6137
Protoss_Citadel_of_Adun 1 6932
Protoss_Corsair 2 8235
Protoss_Templar_Archives 1 7951
Protoss_High_Templar 2 9741
9741
