Protoss_Nexus 2 3015
Protoss_Forge 1 1843
Protoss_Photon_Cannon 2 3625
Protoss_Gateway 4 7872
Protoss_Assimilator 2 8308
Protoss_Zealot 13 9860
Protoss_Cybernetics_Core 1 5860
Protoss_Citadel_of_Adun 1 6959
Protoss_Templar_Archives 1 8730
9860
