Protoss_Nexus 2 4269
Protoss_Forge 1 2011
Protoss_Photon_Cannon 5 9988
Protoss_Gateway 3 7665
Protoss_Assimilator 2 7433
Protoss_Cybernetics_Core 1 5661
Protoss_Zealot 6 9003
Protoss_Citadel_of_Adun 1 6774
Protoss_Dragoon 1 6965
Protoss_Templar_Archives 1 8304
Protoss_High_Templar 2 9369
Protoss_Dark_Templar 1 9605
9988
