Protoss_Nexus 1 0
Protoss_Forge 2 5468
Protoss_Photon_Cannon 5 6294
Protoss_Gateway 2 7128
Protoss_Assimilator 1 5238
Protoss_Zealot 2 8305
Protoss_Cybernetics_Core 1 8182
Protoss_Robotics_Facility 1 9229
Protoss_Dragoon 1 9341
9341
