Protoss_Nexus 2 3509
Protoss_Forge 1 2234
Protoss_Photon_Cannon 5 9202
Protoss_Gateway 1 4313
Protoss_Assimilator 2 6929
Protoss_Zealot 4 9279
Protoss_Cybernetics_Core 1 5389
Protoss_Dragoon 1 6515
Protoss_Stargate 1 6577
Protoss_Corsair 4 9599
Protoss_Citadel_of_Adun 1 7921
Protoss_Templar_Archives 1 9353
9599
