Special_Protoss_Temple 14 0
Protoss_Nexus 2 3295
Protoss_Forge 1 2754
Protoss_Photon_Cannon 3 9596
Protoss_Gateway 4 9852
Protoss_Assimilator 2 7248
Protoss_Cybernetics_Core 1 5537
Protoss_Zealot 3 8339
Protoss_Stargate 1 6603
Protoss_Corsair 2 8701
Protoss_Citadel_of_Adun 1 8107
Protoss_Templar_Archives 1 9141
9852
