Protoss_Nexus 2 4185
Protoss_Forge 1 1883
Protoss_Photon_Cannon 3 9593
Protoss_Gateway 2 8950
Protoss_Assimilator 2 9074
Protoss_Cybernetics_Core 1 5469
Protoss_Zealot 5 8399
Protoss_Stargate 1 6781
Protoss_Citadel_of_Adun 1 6991
Protoss_Corsair 1 7981
Protoss_Templar_Archives 1 8507
Protoss_Robotics_Facility 1 9215
Protoss_Dark_Templar 1 9643
9643
