Protoss_Nexus 2 4017
Protoss_Forge 1 2233
Protoss_Photon_Cannon 4 8191
Protoss_Gateway 2 9305
Protoss_Assimilator 2 6843
Protoss_Cybernetics_Core 1 5303
Protoss_Zealot 3 8901
Protoss_Stargate 1 6439
Protoss_Corsair 3 9017
Protoss_Citadel_of_Adun 1 8661
Protoss_Templar_Archives 1 9755
9755
