Protoss_Nexus 2 2777
Protoss_Forge 1 3067
Protoss_Gateway 1 3857
Protoss_Photon_Cannon 3 9136
Protoss_Assimilator 2 6164
Protoss_Zealot 7 9847
Protoss_Cybernetics_Core 1 5355
Protoss_Stargate 2 7001
Protoss_Corsair 7 9679
Protoss_Citadel_of_Adun 1 7691
Protoss_Templar_Archives 1 9897
9897
