Protoss_Nexus 2 2671
Protoss_Forge 1 3130
Protoss_Gateway 1 3981
Protoss_Photon_Cannon 2 9163
Protoss_Assimilator 2 6262
Protoss_Zealot 8 9431
Protoss_Cybernetics_Core 1 5621
Protoss_Stargate 1 6884
Protoss_Robotics_Facility 1 7435
Protoss_Corsair 4 9879
Protoss_Shuttle 1 8731
Protoss_Robotics_Support_Bay 1 8879
Protoss_Reaver 1 9633
9879
