Protoss_Nexus 1 0
Protoss_Gateway 2 2523
Protoss_Zealot 10 8611
Protoss_Forge 1 5149
Protoss_Photon_Cannon 4 9733
Protoss_Assimilator 1 5954
Protoss_Cybernetics_Core 1 6328
Protoss_Citadel_of_Adun 1 7646
Protoss_Stargate 2 9229
Protoss_Corsair 1 9486
9733
