Special_Protoss_Temple 14 0
Protoss_Nexus 2 3217
Protoss_Forge 1 2086
Protoss_Photon_Cannon 3 9080
Protoss_Gateway 2 8365
Protoss_Assimilator 2 7357
Protoss_Cybernetics_Core 1 5429
Protoss_Zealot 9 9971
Protoss_Stargate 1 6521
Protoss_Citadel_of_Adun 1 6833
Protoss_Corsair 3 9633
9971
