Protoss_Nexus 1 0
Protoss_Gateway 3 8904
Protoss_Zealot 12 9750
Protoss_Assimilator 1 3537
Protoss_Cybernetics_Core 1 4307
Protoss_Dragoon 1 5461
Protoss_Stargate 1 5682
Protoss_Forge 1 5942
Protoss_Corsair 1 6936
Protoss_Citadel_of_Adun 1 7466
Protoss_Templar_Archives 1 9428
9750
