Special_Protoss_Temple 14 0
Protoss_Nexus 2 3280
Protoss_Forge 1 2635
Protoss_Photon_Cannon 2 9857
Protoss_Gateway 2 8231
Protoss_Assimilator 2 6341
Protoss_Cybernetics_Core 1 5151
Protoss_Zealot 10 9843
Protoss_Stargate 1 6295
Protoss_Citadel_of_Adun 1 7047
Protoss_Corsair 1 7425
Protoss_Templar_Archives 1 8617
Protoss_Robotics_Facility 1 8872
9857
