Special_Protoss_Temple 14 0
Protoss_Nexus 2 4263
Protoss_Forge 1 2420
Protoss_Photon_Cannon 3 5239
Protoss_Gateway 4 9539
Protoss_Assimilator 1 4831
Protoss_Cybernetics_Core 1 6503
Protoss_Citadel_of_Adun 1 7651
Protoss_Zealot 5 9877
Protoss_Dragoon 1 8439
9877
