Protoss_Nexus 2 4393
Protoss_Gateway 1 1895
Protoss_Zealot 11 9791
Protoss_Assimilator 2 8655
Protoss_Forge 2 5702
Protoss_Cybernetics_Core 1 7198
Protoss_Photon_Cannon 2 7840
Protoss_Stargate 1 8277
Protoss_Dragoon 1 8437
Protoss_Citadel_of_Adun 1 9215
Protoss_Corsair 1 9481
9791
