Protoss_Nexus 2 6282
Protoss_Forge 1 2059
Protoss_Photon_Cannon 2 4948
Protoss_Gateway 3 9619
Protoss_Assimilator 2 7981
Protoss_Zealot 3 9749
Protoss_Cybernetics_Core 1 7645
Protoss_Stargate 1 8704
Protoss_Citadel_of_Adun 1 8877
Protoss_Corsair 1 9897
9897
