Special_Protoss_Temple 14 0
Protoss_Nexus 2 3296
Protoss_Forge 1 2632
Protoss_Photon_Cannon 3 9521
Protoss_Gateway 2 8318
Protoss_Assimilator 2 6453
Protoss_Cybernetics_Core 1 5901
Protoss_Zealot 6 9831
Protoss_Stargate 1 6893
Protoss_Citadel_of_Adun 1 7337
Protoss_Corsair 2 8727
Protoss_Templar_Archives 1 8982
9831
