Protoss_Nexus 2 4109
Protoss_Forge 2 8019
Protoss_Photon_Cannon 6 9946
Protoss_Gateway 2 7910
Protoss_Assimilator 2 6899
Protoss_Cybernetics_Core 1 5353
Protoss_Zealot 4 8645
Protoss_Stargate 1 6404
Protoss_Citadel_of_Adun 1 7156
Protoss_Corsair 2 8162
Protoss_Templar_Archives 1 8281
Protoss_Dark_Templar 2 9295
9946
