Protoss_Nexus 2 3225
Protoss_Forge 1 2709
Protoss_Photon_Cannon 7 9988
Protoss_Gateway 2 8601
Protoss_Zealot 6 7871
Protoss_Assimilator 2 6952
Protoss_Cybernetics_Core 1 6161
Protoss_Stargate 1 7165
Protoss_Citadel_of_Adun 1 7727
Protoss_Corsair 3 9757
Protoss_Templar_Archives 1 9140
9988
