Protoss_Nexus 2 3200
Protoss_Forge 1 3558
Protoss_Gateway 4 9114
Protoss_Photon_Cannon 2 9923
Protoss_Assimilator 2 6038
Protoss_Zealot 7 9436
Protoss_Cybernetics_Core 1 5508
Protoss_Stargate 1 6533
Protoss_Citadel_of_Adun 1 6829
Protoss_Dragoon 1 7676
Protoss_Corsair 2 9091
Protoss_Templar_Archives 1 9463
Protoss_Robotics_Facility 1 9773
9923
