Protoss_Nexus 2 3178
Protoss_Forge 1 3633
Protoss_Photon_Cannon 2 4783
Protoss_Assimilator 2 8283
Protoss_Gateway 3 7785
Protoss_Cybernetics_Core 1 6504
Protoss_Zealot 11 10000
Protoss_Citadel_of_Adun 1 7679
Protoss_Templar_Archives 1 9739
Protoss_Robotics_Facility 1 9833
10000
