Protoss_Nexus 2 3331
Protoss_Forge 1 2155
Protoss_Gateway 3 8426
Protoss_Assimilator 2 7062
Protoss_Zealot 10 9471
Protoss_Cybernetics_Core 1 4807
Protoss_Photon_Cannon 1 5129
Protoss_Stargate 1 5940
Protoss_Corsair 2 7817
Protoss_Citadel_of_Adun 1 7483
Protoss_Robotics_Facility 1 9312
Protoss_Templar_Archives 1 9800
9800
