Protoss_Nexus 2 4232
Protoss_Forge 1 2139
Protoss_Photon_Cannon 3 9954
Protoss_Gateway 4 7914
Protoss_Assimilator 2 9148
Protoss_Cybernetics_Core 1 5548
Protoss_Zealot 10 9566
Protoss_Citadel_of_Adun 1 7149
Protoss_Templar_Archives 1 9488
9954
