Protoss_Nexus 1 0
Protoss_Gateway 3 6935
Protoss_Assimilator 1 2268
Protoss_Zealot 11 9329
Protoss_Cybernetics_Core 1 4885
Protoss_Dragoon 2 9307
Protoss_Stargate 1 5971
Protoss_Corsair 3 8705
Protoss_Citadel_of_Adun 1 8775
9329
