Protoss_Nexus 1 0
Protoss_Forge 1 2054
Protoss_Photon_Cannon 1 3419
Protoss_Gateway 1 3689
Protoss_Zealot 9 9625
Protoss_Assimilator 1 4969
Protoss_Cybernetics_Core 1 6871
Protoss_Stargate 1 8193
Protoss_Citadel_of_Adun 1 9055
Protoss_Corsair 1 9339
9625
