Protoss_Nexus 2 9575
Protoss_Gateway 2 6927
Protoss_Assimilator 1 2648
Protoss_Zealot 5 7836
Protoss_Cybernetics_Core 1 3956
Protoss_Stargate 1 4981
Protoss_Dragoon 1 5918
Protoss_Corsair 2 7301
Protoss_Citadel_of_Adun 1 6679
Protoss_Templar_Archives 1 7874
Protoss_Forge 1 8158
Protoss_Dark_Templar 2 8906
Protoss_Photon_Cannon 2 9893
Protoss_High_Templar 2 9691
9893
