Protoss_Nexus 2 3965
Protoss_Forge 1 2426
Protoss_Photon_Cannon 2 3304
Protoss_Gateway 3 8627
Protoss_Assimilator 2 7113
Protoss_Zealot 5 8827
Protoss_Cybernetics_Core 1 5927
Protoss_Stargate 1 6930
Protoss_Citadel_of_Adun 1 7490
Protoss_Corsair 2 9245
Protoss_Templar_Archives 1 8495
Protoss_Dark_Templar 3 9707
9707
