Protoss_Nexus 2 3259
Protoss_Forge 1 2533
Protoss_Photon_Cannon 4 9039
Protoss_Gateway 2 7897
Protoss_Assimilator 2 7135
Protoss_Cybernetics_Core 1 5331
Protoss_Zealot 6 9505
Protoss_Stargate 1 6521
Protoss_Dragoon 1 6757
Protoss_Citadel_of_Adun 1 7304
Protoss_Corsair 2 8681
Protoss_Templar_Archives 1 9432
9505
