Protoss_Nexus 2 3815
Protoss_Forge 1 2080
Protoss_Photon_Cannon 5 9718
Protoss_Gateway 3 7176
Protoss_Assimilator 2 8323
Protoss_Cybernetics_Core 1 5745
Protoss_Zealot 9 8836
Protoss_Citadel_of_Adun 1 6928
Protoss_Templar_Archives 1 8473
Protoss_High_Templar 2 9516
Protoss_Dark_Templar 1 9626
9718
