Protoss_Nexus 2 4081
Protoss_Forge 1 2229
Protoss_Photon_Cannon 3 9335
Protoss_Gateway 3 9113
Protoss_Assimilator 2 6359
Protoss_Cybernetics_Core 1 5519
Protoss_Zealot 5 8907
Protoss_Dragoon 1 6513
Protoss_Stargate 1 6721
Protoss_Citadel_of_Adun 1 7767
Protoss_Corsair 2 8493
Protoss_Templar_Archives 1 8815
9335
