Protoss_Nexus 2 3272
Protoss_Forge 1 2359
Protoss_Gateway 4 8185
Protoss_Assimilator 2 6575
Protoss_Photon_Cannon 2 9095
Protoss_Cybernetics_Core 1 4968
Protoss_Zealot 10 9881
Protoss_Dragoon 1 6067
Protoss_Citadel_of_Adun 1 6161
Protoss_Templar_Archives 1 8555
Protoss_Dark_Templar 2 9919
9919
