Protoss_Nexus 2 3849
Protoss_Forge 1 2504
Protoss_Assimilator 2 7009
Protoss_Gateway 2 4873
Protoss_Photon_Cannon 2 7725
Protoss_Cybernetics_Core 1 5963
Protoss_Zealot 5 8773
Protoss_Dragoon 2 7121
Protoss_Citadel_of_Adun 1 7403
Protoss_Robotics_Facility 1 8385
Protoss_Templar_Archives 1 8539
Protoss_Dark_Templar 2 9561
Protoss_Shuttle 1 9681
Protoss_Ground_Weapons_1 1 9826
9826
