Protoss_Nexus 2 3893
Protoss_Forge 2 5979
Protoss_Photon_Cannon 8 9955
Protoss_Assimilator 2 7489
Protoss_Gateway 2 7484
Protoss_Zealot 6 9756
Protoss_Cybernetics_Core 1 6605
Protoss_Citadel_of_Adun 1 7851
Protoss_Dragoon 1 7966
Protoss_Templar_Archives 1 9188
9955
