Protoss_Nexus 2 3851
Protoss_Forge 1 2319
Protoss_Photon_Cannon 4 9321
Protoss_Gateway 2 9881
Protoss_Assimilator 2 6533
Protoss_Cybernetics_Core 1 5639
Protoss_Stargate 2 7994
Protoss_Corsair 5 9609
Protoss_Citadel_of_Adun 1 8619
Protoss_Templar_Archives 1 9685
9881
