Protoss_Nexus 2 2753
Protoss_Gateway 2 3529
Protoss_Zealot 14 9981
Protoss_Forge 1 5183
Protoss_Assimilator 2 7856
Protoss_Photon_Cannon 3 8023
Protoss_Cybernetics_Core 1 6982
Protoss_Stargate 1 8368
Protoss_Citadel_of_Adun 1 9066
Protoss_Corsair 1 9545
9981
