Protoss_Nexus 2 3878
Protoss_Forge 1 2075
Protoss_Photon_Cannon 4 9578
Protoss_Gateway 4 8421
Protoss_Assimilator 2 7096
Protoss_Zealot 7 9796
Protoss_Cybernetics_Core 1 6145
Protoss_Stargate 1 7688
Protoss_Dragoon 1 7846
Protoss_Corsair 1 8826
Protoss_Citadel_of_Adun 1 9863
9863
