Protoss_Nexus 2 4639
Protoss_Forge 1 2441
Protoss_Photon_Cannon 4 9869
Protoss_Gateway 3 8178
Protoss_Assimilator 2 6977
Protoss_Cybernetics_Core 1 6153
Protoss_Zealot 3 9596
Protoss_Citadel_of_Adun 1 7178
Protoss_Stargate 1 7921
Protoss_Dragoon 1 8011
Protoss_Templar_Archives 1 8528
Protoss_Corsair 2 9698
Protoss_High_Templar 2 9816
9869
