Protoss_Nexus 2 3205
Protoss_Forge 1 2359
Protoss_Photon_Cannon 3 9957
Protoss_Gateway 4 9794
Protoss_Assimilator 2 6274
Protoss_Cybernetics_Core 1 5477
Protoss_Stargate 1 6557
Protoss_Citadel_of_Adun 1 7063
Protoss_Corsair 3 8912
Protoss_Zealot 1 7971
Protoss_Templar_Archives 1 8083
Protoss_Dark_Templar 2 9387
9957
