Protoss_Nexus 2 3201
Protoss_Forge 1 2757
Protoss_Photon_Cannon 2 3767
Protoss_Gateway 4 9122
Protoss_Zealot 5 9517
Protoss_Assimilator 2 7566
Protoss_Cybernetics_Core 1 6832
Protoss_Stargate 1 7833
Protoss_Dragoon 1 7851
Protoss_Citadel_of_Adun 1 8357
Protoss_Corsair 2 9589
Protoss_Templar_Archives 1 9369
9589
