Protoss_Nexus 2 3476
Protoss_Forge 1 2021
Protoss_Photon_Cannon 2 8247
Protoss_Gateway 3 9385
Protoss_Assimilator 2 6785
Protoss_Cybernetics_Core 1 4875
Protoss_Zealot 4 8873
Protoss_Dragoon 1 6073
Protoss_Stargate 2 9072
Protoss_Corsair 3 9693
Protoss_Robotics_Facility 1 8055
Protoss_Robotics_Support_Bay 1 9349
Protoss_Reaver 1 9941
9941
