Protoss_Nexus 2 4714
Protoss_Forge 1 2185
Protoss_Photon_Cannon 2 3594
Protoss_Gateway 4 9902
Protoss_Assimilator 2 9420
Protoss_Cybernetics_Core 1 5998
Protoss_Dragoon 1 6991
Protoss_Zealot 10 9870
Protoss_Citadel_of_Adun 1 7358
Protoss_Templar_Archives 1 9040
9902
