Protoss_Nexus 1 0
Protoss_Gateway 3 9635
Protoss_Assimilator 1 2450
Protoss_Cybernetics_Core 1 3003
Protoss_Zealot 3 5805
Protoss_Citadel_of_Adun 1 4438
Protoss_Templar_Archives 1 5467
Protoss_Stargate 1 5944
Protoss_Dark_Templar 4 9015
Protoss_Corsair 1 7215
9635
