Protoss_Nexus 1 0
Protoss_Gateway 2 9554
Protoss_Assimilator 1 2641
Protoss_Zealot 6 9001
Protoss_Cybernetics_Core 1 3436
Protoss_Dragoon 1 4531
Protoss_Robotics_Facility 1 4974
Protoss_Forge 1 6090
Protoss_Shuttle 1 6277
Protoss_Robotics_Support_Bay 1 6879
Protoss_Reaver 2 8479
Protoss_Photon_Cannon 3 9423
Protoss_Citadel_of_Adun 1 9627
Protoss_Scarab 3 9860
9860
