Protoss_Nexus 2 2881
Protoss_Gateway 3 7171
Protoss_Forge 1 3637
Protoss_Assimilator 2 8225
Protoss_Photon_Cannon 2 6638
Protoss_Cybernetics_Core 1 5088
Protoss_Zealot 12 9843
Protoss_Dragoon 1 6217
Protoss_Citadel_of_Adun 1 6366
Protoss_Templar_Archives 1 8884
9843
