Protoss_Nexus 2 4138
Protoss_Forge 1 1936
Protoss_Photon_Cannon 3 8624
Protoss_Gateway 2 7756
Protoss_Cybernetics_Core 1 5468
Protoss_Assimilator 2 7454
Protoss_Zealot 8 9435
Protoss_Stargate 1 7133
Protoss_Citadel_of_Adun 1 8097
Protoss_Corsair 1 8526
Protoss_Templar_Archives 1 9698
9698
