Protoss_Nexus 2 4611
Protoss_Forge 1 2771
Protoss_Photon_Cannon 8 8215
Protoss_Gateway 2 9890
Protoss_Assimilator 2 6738
Protoss_Cybernetics_Core 1 6218
Protoss_Zealot 2 7167
Protoss_Stargate 2 8509
Protoss_Corsair 4 9795
9890
