Protoss_Nexus 2 3540
Protoss_Forge 1 2361
Protoss_Gateway 3 8636
Protoss_Photon_Cannon 2 4703
Protoss_Assimilator 2 6089
Protoss_Cybernetics_Core 1 5605
Protoss_Zealot 3 8903
Protoss_Stargate 1 6671
Protoss_Citadel_of_Adun 1 7511
Protoss_Corsair 3 9353
Protoss_Dragoon 1 7981
Protoss_Templar_Archives 1 8513
Protoss_Dark_Templar 1 9573
Protoss_High_Templar 2 9679
9679
