Protoss_Nexus 2 9800
Protoss_Gateway 2 7122
Protoss_Zealot 5 8309
Protoss_Assimilator 1 3217
Protoss_Cybernetics_Core 1 4111
Protoss_Stargate 1 5272
Protoss_Dragoon 1 5787
Protoss_Citadel_of_Adun 1 5999
Protoss_Corsair 2 9689
Protoss_Templar_Archives 1 7404
Protoss_Forge 1 8102
Protoss_Dark_Templar 1 8409
Protoss_Photon_Cannon 1 8799
Protoss_High_Templar 1 9193
9800
