Protoss_Nexus 2 3776
Protoss_Forge 1 2255
Protoss_Photon_Cannon 2 4116
Protoss_Gateway 4 9919
Protoss_Assimilator 1 4914
Protoss_Cybernetics_Core 1 5814
Protoss_Zealot 14 9956
Protoss_Citadel_of_Adun 1 6888
Protoss_Templar_Archives 1 9000
9956
