Protoss_Nexus 1 0
Protoss_Gateway 2 7988
Protoss_Zealot 6 6507
Protoss_Assimilator 1 3445
Protoss_Cybernetics_Core 1 4231
Protoss_Stargate 1 5312
Protoss_Forge 1 5555
Protoss_Dragoon 1 5835
Protoss_Photon_Cannon 2 8789
Protoss_Citadel_of_Adun 1 7580
8789
