Protoss_Nexus 1 0
Protoss_Gateway 1 1881
Protoss_Assimilator 1 2293
Protoss_Zealot 8 8213
Protoss_Cybernetics_Core 1 3737
Protoss_Dragoon 1 4785
Protoss_Stargate 1 5060
Protoss_Citadel_of_Adun 1 5742
Protoss_Corsair 1 6379
Protoss_Templar_Archives 1 7231
Protoss_Forge 1 7639
Protoss_Dark_Templar 2 8997
Protoss_Photon_Cannon 3 9359
Protoss_High_Templar 1 9787
9787
