Protoss_Nexus 2 3379
Protoss_Forge 1 2372
Protoss_Photon_Cannon 3 7775
Protoss_Gateway 4 8898
Protoss_Assimilator 2 6420
Protoss_Cybernetics_Core 1 5583
Protoss_Zealot 1 5859
Protoss_Dragoon 1 6567
Protoss_Stargate 1 6815
Protoss_Citadel_of_Adun 1 7292
Protoss_Corsair 1 7949
Protoss_Templar_Archives 1 8381
Protoss_Dark_Templar 2 9441
Protoss_Robotics_Facility 1 9855
9855
