Protoss_Nexus 2 3219
Protoss_Forge 1 1849
Protoss_Gateway 3 6997
Protoss_Photon_Cannon 2 7395
Protoss_Assimilator 2 9677
Protoss_Zealot 13 9559
Protoss_Cybernetics_Core 1 5408
Protoss_Citadel_of_Adun 1 6477
Protoss_Templar_Archives 1 8435
9677
