Protoss_Nexus 2 2977
Protoss_Gateway 5 9658
Protoss_Forge 1 3943
Protoss_Photon_Cannon 4 7985
Protoss_Zealot 4 7653
Protoss_Assimilator 2 6663
Protoss_Cybernetics_Core 1 5821
Protoss_Dragoon 1 6837
Protoss_Stargate 1 7129
Protoss_Citadel_of_Adun 1 7474
Protoss_Corsair 1 8337
Protoss_Templar_Archives 1 8529
Protoss_Dark_Templar 1 9557
9658
