Protoss_Nexus 2 2999
Protoss_Forge 1 3404
Protoss_Gateway 2 4649
Protoss_Zealot 7 9697
Protoss_Assimilator 2 8318
Protoss_Cybernetics_Core 1 6497
Protoss_Stargate 2 8249
9697
