Protoss_Nexus 2 3158
Protoss_Forge 1 2161
Protoss_Photon_Cannon 4 8564
Protoss_Gateway 3 9660
Protoss_Assimilator 2 7027
Protoss_Zealot 6 9091
Protoss_Cybernetics_Core 1 6087
Protoss_Stargate 1 7090
Protoss_Citadel_of_Adun 1 7848
Protoss_Corsair 2 8875
Protoss_Templar_Archives 1 8991
9660
