Protoss_Nexus 2 5026
Protoss_Gateway 3 9821
Protoss_Forge 1 2621
Protoss_Photon_Cannon 3 9287
Protoss_Assimilator 2 6909
Protoss_Zealot 3 8403
Protoss_Cybernetics_Core 1 6047
Protoss_Stargate 1 7121
Protoss_Dragoon 1 7395
Protoss_Citadel_of_Adun 1 8084
Protoss_Corsair 3 9543
Protoss_Templar_Archives 1 9164
9821
