Protoss_Nexus 3 9827
Protoss_Forge 1 2006
Protoss_Photon_Cannon 5 9148
Protoss_Gateway 1 4739
Protoss_Assimilator 2 7191
Protoss_Cybernetics_Core 1 5821
Protoss_Zealot 2 6437
Protoss_Stargate 1 6920
Protoss_Corsair 3 9363
Protoss_Robotics_Facility 1 8572
9827
