Protoss_Nexus 2 4011
Protoss_Forge 1 1988
Protoss_Photon_Cannon 5 9929
Protoss_Gateway 3 9630
Protoss_Zealot 5 8589
Protoss_Assimilator 2 8158
Protoss_Cybernetics_Core 1 6777
Protoss_Citadel_of_Adun 1 7957
Protoss_Templar_Archives 1 8983
Protoss_High_Templar 1 9983
9983
