Protoss_Nexus 2 8051
Protoss_Gateway 2 6158
Protoss_Assimilator 1 2363
Protoss_Zealot 7 8567
Protoss_Cybernetics_Core 1 3635
Protoss_Dragoon 1 4635
Protoss_Citadel_of_Adun 1 5173
Protoss_Templar_Archives 1 6419
Protoss_High_Templar 4 9213
Protoss_Archon 1 8332
Protoss_Forge 1 8812
Protoss_Photon_Cannon 2 9685
9685
