Protoss_Nexus 2 3491
Protoss_Forge 1 1968
Protoss_Photon_Cannon 4 9627
Protoss_Gateway 4 8766
Protoss_Assimilator 2 5873
Protoss_Cybernetics_Core 1 5690
Protoss_Zealot 3 8305
Protoss_Stargate 1 6709
Protoss_Citadel_of_Adun 1 6981
Protoss_Corsair 1 7921
Protoss_Templar_Archives 1 8011
Protoss_Dark_Templar 1 8989
Protoss_High_Templar 3 9909
9909
