Protoss_Nexus 2 4379
Protoss_Forge 1 1943
Protoss_Photon_Cannon 3 5333
Protoss_Gateway 3 8846
Protoss_Assimilator 2 6744
Protoss_Cybernetics_Core 1 5891
Protoss_Zealot 5 8923
Protoss_Stargate 1 7053
Protoss_Citadel_of_Adun 1 7508
Protoss_Corsair 2 9111
Protoss_Templar_Archives 1 8536
Protoss_Dark_Templar 3 9843
9843
