Protoss_Nexus 2 3039
Protoss_Gateway 5 9137
Protoss_Forge 1 3723
Protoss_Assimilator 2 5887
Protoss_Photon_Cannon 1 4487
Protoss_Zealot 2 5541
Protoss_Cybernetics_Core 1 5383
Protoss_Stargate 1 6419
Protoss_Citadel_of_Adun 1 6591
Protoss_Dragoon 1 6615
Protoss_Templar_Archives 1 7587
Protoss_Corsair 1 7699
Protoss_Dark_Templar 2 9419
Protoss_High_Templar 4 9937
9937
