Protoss_Nexus 1 0
Protoss_Forge 1 2166
Protoss_Assimilator 1 2309
Protoss_Photon_Cannon 1 2977
Protoss_Gateway 2 4463
Protoss_Zealot 9 8119
Protoss_Cybernetics_Core 1 5103
Protoss_Citadel_of_Adun 1 6273
Protoss_Templar_Archives 1 7355
Protoss_Ground_Weapons_1 1 7737
Protoss_Dark_Templar 3 9561
9561
