Protoss_Nexus 2 3406
Protoss_Forge 1 2451
Protoss_Gateway 1 3993
Protoss_Assimilator 2 6409
Protoss_Photon_Cannon 3 8625
Protoss_Zealot 3 8859
Protoss_Cybernetics_Core 1 5924
Protoss_Dragoon 1 7129
Protoss_Stargate 1 7185
Protoss_Robotics_Facility 1 7717
Protoss_Corsair 3 9925
Protoss_Shuttle 1 9015
Protoss_Robotics_Support_Bay 1 9485
9925
