Protoss_Nexus 2 3233
Protoss_Forge 1 2358
Protoss_Photon_Cannon 4 8521
Protoss_Gateway 4 9851
Protoss_Assimilator 2 6721
Protoss_Cybernetics_Core 1 5523
Protoss_Zealot 3 6999
Protoss_Stargate 1 6589
Protoss_Citadel_of_Adun 1 7165
Protoss_Corsair 3 9337
Protoss_Templar_Archives 1 8167
Protoss_Dark_Templar 2 9273
9851
