Protoss_Nexus 2 4135
Protoss_Forge 1 2013
Protoss_Photon_Cannon 2 3077
Protoss_Gateway 1 4407
Protoss_Assimilator 2 8146
Protoss_Zealot 2 8063
Protoss_Cybernetics_Core 1 5737
Protoss_Dragoon 1 6745
Protoss_Stargate 1 6967
Protoss_Robotics_Facility 1 7867
Protoss_Corsair 1 8173
Protoss_Robotics_Support_Bay 1 9385
9385
