Protoss_Nexus 2 4247
Protoss_Forge 1 1947
Protoss_Photon_Cannon 2 3089
Protoss_Gateway 4 9691
Protoss_Assimilator 2 6784
Protoss_Cybernetics_Core 1 6151
Protoss_Zealot 5 9117
Protoss_Stargate 1 7357
Protoss_Citadel_of_Adun 1 7862
Protoss_Corsair 1 8579
Protoss_Templar_Archives 1 9000
9691
