Protoss_Nexus 2 3567
Protoss_Forge 1 2456
Protoss_Gateway 4 9432
Protoss_Photon_Cannon 1 4465
Protoss_Zealot 14 9791
Protoss_Assimilator 2 6799
Protoss_Cybernetics_Core 1 6237
Protoss_Citadel_of_Adun 1 7731
Protoss_Templar_Archives 1 9085
Protoss_Robotics_Facility 1 9690
9791
