Protoss_Nexus 2 3713
Protoss_Forge 1 2022
Protoss_Photon_Cannon 2 8892
Protoss_Gateway 4 8321
Protoss_Assimilator 2 8438
Protoss_Zealot 12 9927
Protoss_Cybernetics_Core 1 5534
Protoss_Citadel_of_Adun 1 7139
Protoss_Dragoon 1 8119
Protoss_Templar_Archives 1 9500
9927
