Protoss_Nexus 2 2866
Protoss_Forge 1 3319
Protoss_Photon_Cannon 2 7428
Protoss_Gateway 1 4301
Protoss_Assimilator 2 5695
Protoss_Cybernetics_Core 1 5305
Protoss_Zealot 3 9781
Protoss_Stargate 1 6291
Protoss_Dragoon 1 6661
Protoss_Robotics_Facility 1 7191
Protoss_Corsair 4 9449
Protoss_Shuttle 1 8495
Protoss_Robotics_Support_Bay 1 8619
Protoss_Reaver 1 9397
9781
