Protoss_Nexus 2 3103
Protoss_Forge 1 2114
Protoss_Photon_Cannon 3 6212
Protoss_Gateway 1 4271
Protoss_Assimilator 2 8033
Protoss_Zealot 4 9479
Protoss_Cybernetics_Core 1 5556
Protoss_Stargate 1 7232
Protoss_Dragoon 1 7359
Protoss_Corsair 3 9717
Protoss_Citadel_of_Adun 1 9282
9717
