Protoss_Nexus 2 3575
Protoss_Forge 1 2186
Protoss_Photon_Cannon 5 9715
Protoss_Gateway 1 4595
Protoss_Zealot 5 8707
Protoss_Assimilator 2 9624
Protoss_Cybernetics_Core 1 7871
Protoss_Stargate 1 8971
Protoss_Dragoon 1 9606
Protoss_Citadel_of_Adun 1 9993
9993
