Protoss_Nexus 2 9752
Protoss_Forge 2 7988
Protoss_Photon_Cannon 3 9022
Protoss_Gateway 2 5014
Protoss_Assimilator 1 4093
Protoss_Cybernetics_Core 1 6009
Protoss_Zealot 3 7315
Protoss_Stargate 1 7006
Protoss_Citadel_of_Adun 1 7245
Protoss_Dragoon 1 7917
Protoss_Corsair 2 8974
Protoss_Templar_Archives 1 8257
Protoss_Dark_Templar 1 9239
Protoss_High_Templar 1 9991
9991
