Protoss_Nexus 2 3589
Protoss_Forge 1 2231
Protoss_Gateway 4 8955
Protoss_Photon_Cannon 3 8058
Protoss_Assimilator 2 6529
Protoss_Cybernetics_Core 1 5891
Protoss_Zealot 8 9949
Protoss_Stargate 1 6973
Protoss_Citadel_of_Adun 1 7619
Protoss_Corsair 1 8117
Protoss_Templar_Archives 1 9879
9949
