Protoss_Nexus 2 9129
Protoss_Gateway 2 7101
Protoss_Assimilator 1 2457
Protoss_Zealot 2 4043
Protoss_Cybernetics_Core 1 3727
Protoss_Stargate 1 4783
Protoss_Dragoon 1 5083
Protoss_Citadel_of_Adun 1 5592
Protoss_Corsair 1 5943
Protoss_Forge 1 6533
Protoss_Templar_Archives 1 6631
Protoss_Dark_Templar 2 8099
Protoss_Photon_Cannon 3 9908
Protoss_High_Templar 2 9801
9908
