Protoss_Nexus 1 0
Protoss_Gateway 2 2553
Protoss_Zealot 11 9781
Protoss_Assimilator 1 4803
Protoss_Cybernetics_Core 1 6365
Protoss_Forge 1 7393
Protoss_Dragoon 4 8756
Protoss_Photon_Cannon 1 8599
9781
