Protoss_Nexus 2 4251
Protoss_Forge 1 2749
Protoss_Photon_Cannon 4 8997
Protoss_Gateway 1 4637
Protoss_Assimilator 2 6227
Protoss_Cybernetics_Core 1 5695
Protoss_Zealot 5 9801
Protoss_Dragoon 1 6963
Protoss_Stargate 1 7414
Protoss_Robotics_Facility 1 8221
Protoss_Corsair 3 9817
Protoss_Shuttle 1 9983
9983
