Protoss_Nexus 2 3763
Protoss_Forge 1 2133
Protoss_Photon_Cannon 5 9570
Protoss_Gateway 2 8560
Protoss_Assimilator 2 6753
Protoss_Zealot 3 7553
Protoss_Cybernetics_Core 1 6129
Protoss_Stargate 1 7308
Protoss_Citadel_of_Adun 1 7942
Protoss_Corsair 2 9801
Protoss_Templar_Archives 1 8970
9801
