Protoss_Nexus 2 3963
Protoss_Forge 1 2224
Protoss_Photon_Cannon 3 5939
Protoss_Gateway 1 4617
Protoss_Assimilator 2 7989
Protoss_Zealot 6 9123
Protoss_Cybernetics_Core 1 7250
Protoss_Stargate 1 8357
Protoss_Citadel_of_Adun 1 8589
Protoss_Corsair 1 9485
Protoss_Templar_Archives 1 9775
Protoss_Dragoon 1 9853
9853
