Protoss_Nexus 2 3565
Protoss_Forge 1 2293
Protoss_Photon_Cannon 3 6815
Protoss_Gateway 5 9845
Protoss_Assimilator 2 8329
Protoss_Cybernetics_Core 1 5279
Protoss_Zealot 4 8461
Protoss_Stargate 1 6361
Protoss_Corsair 3 9937
Protoss_Dragoon 1 7733
Protoss_Citadel_of_Adun 1 7954
Protoss_Templar_Archives 1 9054
9937
