Special_Protoss_Temple 30 0
Protoss_Nexus 2 2918
Protoss_Forge 1 3528
Protoss_Gateway 6 9888
Protoss_Assimilator 2 5677
Protoss_Photon_Cannon 2 9934
Protoss_Cybernetics_Core 1 4827
Protoss_Zealot 3 7533
Protoss_Stargate 1 5948
Protoss_Dragoon 1 6099
Protoss_Citadel_of_Adun 1 6810
Protoss_Corsair 3 8711
Protoss_Templar_Archives 1 7945
Protoss_High_Templar 3 9693
9934
