Protoss_Nexus 2 3905
Protoss_Forge 1 2128
Protoss_Photon_Cannon 4 9977
Protoss_Gateway 3 7696
Protoss_Assimilator 3 8405
Protoss_Cybernetics_Core 1 5237
Protoss_Zealot 8 9477
Protoss_Stargate 1 6308
Protoss_Citadel_of_Adun 1 6970
Protoss_Corsair 1 7561
Protoss_Templar_Archives 1 8213
Protoss_High_Templar 1 9669
9977
