Protoss_Nexus 2 2804
Protoss_Gateway 4 9143
Protoss_Forge 1 3591
Protoss_Assimilator 2 6808
Protoss_Photon_Cannon 4 8113
Protoss_Zealot 4 8687
Protoss_Cybernetics_Core 1 5061
Protoss_Stargate 1 6376
Protoss_Corsair 1 7519
Protoss_Citadel_of_Adun 1 7857
Protoss_Templar_Archives 1 8893
9143
