Protoss_Nexus 2 3521
Protoss_Forge 1 2122
Protoss_Gateway 4 8264
Protoss_Photon_Cannon 2 4703
Protoss_Assimilator 2 9791
Protoss_Zealot 12 9791
Protoss_Cybernetics_Core 1 6331
Protoss_Citadel_of_Adun 1 7365
Protoss_Templar_Archives 1 9796
9796
