Protoss_Nexus 2 3971
Protoss_Forge 1 2127
Protoss_Photon_Cannon 5 9633
Protoss_Gateway 1 4257
Protoss_Assimilator 2 8607
Protoss_Zealot 6 9573
Protoss_Cybernetics_Core 1 5673
Protoss_Dragoon 1 6855
Protoss_Stargate 1 6945
Protoss_Citadel_of_Adun 1 7955
Protoss_Corsair 3 9927
9927
