Special_Protoss_Temple 30 0
Protoss_Nexus 2 3963
Protoss_Forge 1 2337
Protoss_Photon_Cannon 5 8095
Protoss_Gateway 1 4341
Protoss_Assimilator 2 6286
Protoss_Zealot 3 9435
Protoss_Cybernetics_Core 1 5899
Protoss_Dragoon 2 7737
Protoss_Stargate 1 7000
Protoss_Robotics_Facility 1 7599
Protoss_Corsair 4 9979
Protoss_Shuttle 1 8879
Protoss_Robotics_Support_Bay 1 9970
9979
