Protoss_Nexus 2 3703
Protoss_Forge 1 2521
Protoss_Photon_Cannon 4 8495
Protoss_Gateway 2 8163
Protoss_Assimilator 3 7556
Protoss_Cybernetics_Core 1 5428
Protoss_Zealot 7 9973
Protoss_Stargate 1 6505
Protoss_Citadel_of_Adun 1 7020
Protoss_Corsair 2 9093
Protoss_Templar_Archives 1 8177
9973
