Protoss_Nexus 2 2865
Protoss_Forge 1 3110
Protoss_Photon_Cannon 3 9418
Protoss_Gateway 3 7317
Protoss_Assimilator 2 6828
Protoss_Cybernetics_Core 1 5511
Protoss_Zealot 11 9177
Protoss_Citadel_of_Adun 1 6499
Protoss_Templar_Archives 1 8657
Protoss_Robotics_Facility 1 9349
Protoss_High_Templar 2 9681
Protoss_Dark_Templar 1 9779
Protoss_Ground_Weapons_1 1 9869
9869
