Protoss_Nexus 2 4597
Special_Protoss_Temple 14 0
Protoss_Forge 1 2571
Protoss_Photon_Cannon 6 9524
Protoss_Gateway 3 9979
Protoss_Assimilator 2 7125
Protoss_Zealot 3 8579
Protoss_Cybernetics_Core 1 5801
Protoss_Stargate 1 6869
Protoss_Citadel_of_Adun 1 7585
Protoss_Corsair 2 8663
Protoss_Dragoon 1 8605
Protoss_Templar_Archives 1 9018
9979
