Protoss_Nexus 2 3000
Protoss_Forge 2 3392
Protoss_Gateway 3 9585
Protoss_Photon_Cannon 3 9142
Protoss_Zealot 10 9823
Protoss_Assimilator 3 9381
Protoss_Cybernetics_Core 1 5902
Protoss_Stargate 1 6986
Protoss_Citadel_of_Adun 1 7557
Protoss_Dragoon 1 7719
Protoss_Corsair 3 9763
9823
