Protoss_Nexus 2 3456
Protoss_Forge 1 2047
Protoss_Gateway 2 9387
Protoss_Assimilator 2 6433
Protoss_Photon_Cannon 4 9123
Protoss_Cybernetics_Core 1 5011
Protoss_Zealot 3 8631
Protoss_Dragoon 1 6193
Protoss_Stargate 1 6215
Protoss_Citadel_of_Adun 1 6898
Protoss_Corsair 2 8647
Protoss_Robotics_Facility 1 7927
Protoss_Templar_Archives 1 8163
Protoss_Shuttle 1 9617
Protoss_Robotics_Support_Bay 1 9703
9703
