Protoss_Nexus 2 3277
Protoss_Forge 1 2284
Protoss_Photon_Cannon 4 8448
Protoss_Gateway 3 8643
Protoss_Assimilator 3 9227
Protoss_Cybernetics_Core 1 6010
Protoss_Zealot 6 9767
Protoss_Stargate 1 7147
Protoss_Dragoon 1 7229
Protoss_Citadel_of_Adun 1 8038
Protoss_Corsair 2 9627
Protoss_Templar_Archives 1 9153
9767
