Special_Protoss_Temple 14 0
Protoss_Nexus 2 4525
Protoss_Forge 1 2566
Protoss_Photon_Cannon 3 9907
Protoss_Gateway 2 9283
Protoss_Assimilator 2 8112
Protoss_Zealot 4 8995
Protoss_Cybernetics_Core 1 6332
Protoss_Stargate 1 7336
Protoss_Citadel_of_Adun 1 7517
Protoss_Corsair 2 9693
Protoss_Templar_Archives 1 8864
9907
