Protoss_Nexus 1 0
Protoss_Gateway 2 5550
Protoss_Assimilator 1 2311
Protoss_Zealot 8 9055
Protoss_Cybernetics_Core 1 3945
Protoss_Citadel_of_Adun 1 5064
Protoss_Dragoon 1 5161
Protoss_Templar_Archives 1 6223
Protoss_High_Templar 4 9734
Protoss_Forge 1 7834
Protoss_Dark_Templar 2 8143
Protoss_Archon 1 8226
Protoss_Photon_Cannon 2 8796
9734
