Protoss_Nexus 2 2963
Protoss_Gateway 1 3263
Protoss_Forge 1 3949
Protoss_Assimilator 2 5756
Protoss_Photon_Cannon 2 9543
Protoss_Cybernetics_Core 1 4829
Protoss_Zealot 2 6753
Protoss_Dragoon 1 5817
Protoss_Stargate 1 6209
Protoss_Robotics_Facility 1 7050
Protoss_Corsair 5 9779
Protoss_Shuttle 1 8439
Protoss_Robotics_Support_Bay 1 8869
Protoss_Reaver 1 9409
9779
