Protoss_Nexus 1 0
Protoss_Gateway 3 9839
Protoss_Zealot 14 9403
Protoss_Assimilator 1 6128
Protoss_Cybernetics_Core 1 7360
Protoss_Dragoon 2 8489
Protoss_Citadel_of_Adun 1 8648
9839
