Protoss_Nexus 2 6383
Protoss_Gateway 2 2499
Protoss_Zealot 19 9893
Protoss_Forge 1 6643
Protoss_Assimilator 2 9773
Protoss_Photon_Cannon 1 8356
Protoss_Cybernetics_Core 1 8426
Protoss_Stargate 1 9485
Protoss_Citadel_of_Adun 1 9679
9893
