Protoss_Nexus 2 2918
Protoss_Gateway 3 9212
Protoss_Forge 1 3930
Protoss_Assimilator 2 6224
Protoss_Photon_Cannon 2 7969
Protoss_Cybernetics_Core 1 5374
Protoss_Zealot 3 9275
Protoss_Stargate 1 6409
Protoss_Dragoon 1 6573
Protoss_Citadel_of_Adun 1 7131
Protoss_Corsair 4 9559
Protoss_Templar_Archives 1 8383
Protoss_Dark_Templar 1 9521
9559
