Protoss_Nexus 2 3299
Protoss_Forge 1 2591
Protoss_Gateway 4 9925
Protoss_Photon_Cannon 2 9262
Protoss_Assimilator 2 9330
Protoss_Zealot 4 8625
Protoss_Cybernetics_Core 1 4953
Protoss_Dragoon 1 6177
Protoss_Stargate 1 6665
Protoss_Corsair 1 7829
Protoss_Citadel_of_Adun 1 7945
Protoss_Templar_Archives 1 9419
Protoss_Robotics_Facility 1 9750
9925
