Protoss_Nexus 2 4153
Protoss_Forge 1 2168
Protoss_Photon_Cannon 6 9609
Protoss_Gateway 3 7849
Protoss_Assimilator 2 6506
Protoss_Cybernetics_Core 1 5664
Protoss_Zealot 1 5769
Protoss_Dragoon 1 6651
Protoss_Stargate 1 7227
Protoss_Citadel_of_Adun 1 7633
Protoss_Corsair 2 9001
Protoss_Templar_Archives 1 8723
Protoss_High_Templar 2 9791
Protoss_Dark_Templar 1 9933
9933
