Protoss_Nexus 2 3359
Protoss_Forge 1 2499
Protoss_Photon_Cannon 1 3667
Protoss_Gateway 2 8096
Protoss_Assimilator 3 9020
Protoss_Cybernetics_Core 1 5453
Protoss_Stargate 1 6471
Protoss_Citadel_of_Adun 1 6529
Protoss_Dragoon 1 7029
Protoss_Corsair 4 9609
Protoss_Zealot 4 9129
Protoss_Templar_Archives 1 8689
Protoss_Dark_Templar 2 9899
9899
