Special_Protoss_Temple 30 0
Protoss_Nexus 2 4003
Protoss_Forge 1 2348
Protoss_Photon_Cannon 3 7145
Protoss_Gateway 5 9182
Protoss_Assimilator 2 6252
Protoss_Cybernetics_Core 1 5101
Protoss_Zealot 10 9859
Protoss_Stargate 1 6132
Protoss_Citadel_of_Adun 1 6661
Protoss_Corsair 1 7281
9859
