Special_Protoss_Temple 14 0
Protoss_Nexus 2 4171
Protoss_Forge 1 2588
Protoss_Photon_Cannon 2 3493
Protoss_Gateway 4 9836
Protoss_Assimilator 2 6598
Protoss_Cybernetics_Core 1 5847
Protoss_Zealot 2 7647
Protoss_Dragoon 1 6895
Protoss_Stargate 1 7038
Protoss_Citadel_of_Adun 1 7225
Protoss_Corsair 3 9823
Protoss_Templar_Archives 1 9091
9836
