Protoss_Nexus 2 3286
Protoss_Forge 1 2638
Protoss_Photon_Cannon 3 7029
Protoss_Gateway 6 9747
Protoss_Assimilator 2 7123
Protoss_Cybernetics_Core 1 5338
Protoss_Zealot 6 9331
Protoss_Stargate 1 6339
Protoss_Citadel_of_Adun 1 6736
Protoss_Corsair 2 9881
Protoss_Templar_Archives 1 8979
9881
