Protoss_Nexus 1 0
Protoss_Gateway 1 1891
Protoss_Assimilator 1 2367
Protoss_Zealot 6 6223
Protoss_Cybernetics_Core 1 3630
Protoss_Dragoon 1 4611
Protoss_Stargate 1 4883
Protoss_Citadel_of_Adun 1 5552
Protoss_Corsair 4 9359
Protoss_Templar_Archives 1 6851
Protoss_Forge 1 7846
Protoss_Dark_Templar 1 8047
Protoss_High_Templar 2 9615
Protoss_Photon_Cannon 1 9474
9615
