Protoss_Nexus 2 4543
Protoss_Gateway 2 2391
Protoss_Zealot 12 9441
Protoss_Assimilator 1 4901
Protoss_Cybernetics_Core 1 5646
Protoss_Stargate 1 6699
Protoss_Dragoon 1 6971
Protoss_Forge 1 7419
Protoss_Corsair 3 9255
Protoss_Photon_Cannon 5 9737
9737
