Special_Protoss_Temple 14 0
Protoss_Nexus 2 4112
Protoss_Forge 1 2453
Protoss_Photon_Cannon 3 9067
Protoss_Gateway 4 9862
Protoss_Assimilator 2 6933
Protoss_Cybernetics_Core 1 5411
Protoss_Zealot 4 8631
Protoss_Stargate 1 6468
Protoss_Dragoon 1 6749
Protoss_Citadel_of_Adun 1 7303
Protoss_Corsair 1 7609
Protoss_Templar_Archives 1 8437
Protoss_Dark_Templar 2 9527
9862
