Special_Protoss_Temple 14 0
Protoss_Nexus 2 3679
Protoss_Forge 1 2673
Protoss_Photon_Cannon 3 5396
Protoss_Gateway 4 9533
Protoss_Zealot 6 9985
Protoss_Assimilator 2 7250
Protoss_Cybernetics_Core 1 6551
Protoss_Dragoon 1 7557
Protoss_Stargate 1 7915
Protoss_Citadel_of_Adun 1 8590
Protoss_Corsair 2 9765
9985
