Protoss_Nexus 2 3117
Protoss_Forge 1 2199
Protoss_Gateway 3 9746
Protoss_Assimilator 2 5776
Protoss_Photon_Cannon 3 9510
Protoss_Cybernetics_Core 1 4951
Protoss_Zealot 5 8921
Protoss_Stargate 1 6045
Protoss_Citadel_of_Adun 1 6691
Protoss_Corsair 5 9839
Protoss_Templar_Archives 1 8119
Protoss_Dark_Templar 1 9523
9839
