Protoss_Nexus 2 4735
Protoss_Forge 1 2552
Protoss_Photon_Cannon 4 5669
Protoss_Gateway 2 9505
Protoss_Assimilator 2 9557
Protoss_Cybernetics_Core 1 7501
Protoss_Zealot 4 9793
Protoss_Stargate 1 8543
Protoss_Citadel_of_Adun 1 9014
Protoss_Corsair 1 9683
9793
