Protoss_Nexus 2 7943
Protoss_Gateway 2 2285
Protoss_Zealot 13 9814
Protoss_Assimilator 1 3270
Protoss_Cybernetics_Core 1 3725
Protoss_Stargate 1 4831
Protoss_Dragoon 1 5305
Protoss_Corsair 2 7165
Protoss_Forge 1 8619
Protoss_Citadel_of_Adun 1 9144
Protoss_Photon_Cannon 1 9875
9875
