Special_Protoss_Temple 14 0
Protoss_Nexus 2 3400
Protoss_Forge 1 2309
Protoss_Photon_Cannon 1 3607
Protoss_Gateway 5 9973
Protoss_Assimilator 2 9193
Protoss_Zealot 8 9517
Protoss_Cybernetics_Core 1 5559
Protoss_Stargate 1 6647
Protoss_Citadel_of_Adun 1 7617
Protoss_Corsair 1 8043
9973
