Protoss_Nexus 2 3811
Protoss_Forge 1 1835
Protoss_Photon_Cannon 2 2991
Protoss_Gateway 2 7689
Protoss_Assimilator 2 6877
Protoss_Cybernetics_Core 1 5205
Protoss_Zealot 10 9961
Protoss_Stargate 1 6231
Protoss_Corsair 3 8879
Protoss_Citadel_of_Adun 1 7569
Protoss_Templar_Archives 1 9860
9961
