Protoss_Nexus 2 8546
Protoss_Forge 1 2128
Protoss_Photon_Cannon 3 3326
Protoss_Gateway 2 4784
Protoss_Zealot 10 8183
Protoss_Assimilator 2 9546
Protoss_Cybernetics_Core 1 9370
9546
