Special_Protoss_Temple 14 0
Protoss_Nexus 2 4293
Protoss_Forge 1 2432
Protoss_Photon_Cannon 2 3301
Protoss_Gateway 4 9612
Protoss_Assimilator 2 7303
Protoss_Zealot 2 9875
Protoss_Cybernetics_Core 1 6770
Protoss_Stargate 1 7773
Protoss_Dragoon 1 7915
Protoss_Citadel_of_Adun 1 8856
Protoss_Corsair 1 8931
9875
