Protoss_Nexus 1 0
Protoss_Gateway 2 5353
Protoss_Assimilator 1 2352
Protoss_Cybernetics_Core 1 2873
Protoss_Zealot 15 9819
Protoss_Stargate 1 3969
Protoss_Dragoon 1 4185
Protoss_Corsair 1 5107
Protoss_Citadel_of_Adun 1 6876
Protoss_Forge 2 8131
Protoss_Templar_Archives 1 8889
Protoss_Dark_Templar 1 9907
9907
