Special_Protoss_Temple 14 0
Protoss_Nexus 2 3262
Protoss_Forge 1 2599
Protoss_Photon_Cannon 2 8359
Protoss_Gateway 2 8649
Protoss_Assimilator 2 6135
Protoss_Zealot 4 7593
Protoss_Cybernetics_Core 1 5529
Protoss_Stargate 1 6563
Protoss_Citadel_of_Adun 1 7334
Protoss_Dragoon 1 7673
Protoss_Corsair 4 9677
Protoss_Templar_Archives 1 8739
Protoss_Dark_Templar 2 9743
9743
