Protoss_Nexus 2 3209
Protoss_Forge 1 2687
Protoss_Photon_Cannon 3 8973
Protoss_Gateway 1 4592
Protoss_Assimilator 2 5973
Protoss_Cybernetics_Core 1 5577
Protoss_Zealot 3 7973
Protoss_Stargate 2 6985
Protoss_Corsair 7 9915
Protoss_Citadel_of_Adun 1 8507
Protoss_Templar_Archives 1 9569
9915
