Protoss_Nexus 2 4087
Protoss_Forge 1 2443
Protoss_Photon_Cannon 3 8949
Protoss_Gateway 4 8681
Protoss_Assimilator 2 6206
Protoss_Cybernetics_Core 1 5283
Protoss_Zealot 3 8001
Protoss_Stargate 1 6509
Protoss_Citadel_of_Adun 1 6892
Protoss_Corsair 1 7701
Protoss_Templar_Archives 1 7925
Protoss_High_Templar 4 9673
9673
