Protoss_Nexus 2 4028
Protoss_Forge 1 2161
Protoss_Photon_Cannon 3 8917
Protoss_Gateway 3 9817
Protoss_Assimilator 2 6514
Protoss_Cybernetics_Core 1 5337
Protoss_Zealot 7 9321
Protoss_Stargate 1 6393
Protoss_Citadel_of_Adun 1 7068
Protoss_Corsair 2 9595
Protoss_Templar_Archives 1 9043
9817
