Protoss_Nexus 3 6952
Protoss_Gateway 2 2445
Protoss_Zealot 10 7131
Protoss_Assimilator 2 8957
Protoss_Cybernetics_Core 1 7287
Protoss_Forge 1 7876
Protoss_Stargate 1 8281
Protoss_Photon_Cannon 1 8599
Protoss_Robotics_Facility 1 9273
Protoss_Corsair 1 9411
9411
