Protoss_Nexus 2 3942
Protoss_Forge 1 2317
Protoss_Photon_Cannon 2 3370
Protoss_Gateway 4 9463
Protoss_Assimilator 2 7048
Protoss_Cybernetics_Core 1 5351
Protoss_Zealot 8 9639
Protoss_Stargate 1 6390
Protoss_Dragoon 1 6761
Protoss_Corsair 3 9173
Protoss_Citadel_of_Adun 1 7791
Protoss_Templar_Archives 1 9891
9891
