Protoss_Nexus 2 3977
Protoss_Forge 1 2391
Protoss_Photon_Cannon 5 9218
Protoss_Gateway 1 4271
Protoss_Assimilator 2 5952
Protoss_Cybernetics_Core 1 5635
Protoss_Zealot 2 6975
Protoss_Stargate 1 6729
Protoss_Citadel_of_Adun 1 7401
Protoss_Corsair 4 9757
Protoss_Templar_Archives 1 8507
Protoss_Dark_Templar 1 9703
9757
