Protoss_Nexus 1 0
Protoss_Gateway 2 2468
Protoss_Zealot 4 7426
Protoss_Assimilator 1 3974
Protoss_Cybernetics_Core 1 4771
Protoss_Citadel_of_Adun 1 5984
Protoss_Dragoon 1 6041
Protoss_Templar_Archives 1 7199
Protoss_Forge 1 7345
Protoss_High_Templar 2 8211
Protoss_Photon_Cannon 6 9984
Protoss_Archon 1 9065
9984
