Protoss_Nexus 2 3192
Protoss_Forge 1 2101
Protoss_Gateway 5 9382
Protoss_Photon_Cannon 3 8202
Protoss_Assimilator 2 6561
Protoss_Cybernetics_Core 1 5307
Protoss_Zealot 3 8025
Protoss_Citadel_of_Adun 1 6345
Protoss_Templar_Archives 1 7363
Protoss_High_Templar 2 9105
Protoss_Dark_Templar 1 9099
9382
