Protoss_Nexus 2 2929
Protoss_Gateway 4 8968
Protoss_Forge 1 3827
Protoss_Assimilator 2 8772
Protoss_Photon_Cannon 2 5078
Protoss_Zealot 9 9587
Protoss_Cybernetics_Core 1 6027
Protoss_Citadel_of_Adun 1 7254
Protoss_Dragoon 1 7277
Protoss_Templar_Archives 1 8662
9587
