Protoss_Nexus 2 3257
Protoss_Forge 1 2062
Protoss_Gateway 2 9668
Protoss_Assimilator 3 6410
Protoss_Photon_Cannon 5 9711
Protoss_Zealot 6 8901
Protoss_Cybernetics_Core 1 5425
Protoss_Stargate 1 6549
Protoss_Dragoon 1 6793
Protoss_Citadel_of_Adun 1 7522
Protoss_Corsair 1 7973
Protoss_Templar_Archives 1 8578
Protoss_Dark_Templar 1 9589
9711
