Protoss_Nexus 2 4281
Protoss_Forge 1 2331
Protoss_Photon_Cannon 2 3428
Protoss_Gateway 1 4495
Protoss_Assimilator 2 5990
Protoss_Cybernetics_Core 1 5560
Protoss_Zealot 1 5607
Protoss_Stargate 1 6630
Protoss_Dragoon 1 6865
Protoss_Robotics_Facility 1 7453
Protoss_Corsair 4 9803
Protoss_Robotics_Support_Bay 1 8922
Protoss_Reaver 1 9451
9803
