Protoss_Nexus 3 9277
Protoss_Gateway 2 2483
Protoss_Zealot 14 8817
Protoss_Assimilator 1 4829
Protoss_Cybernetics_Core 1 5641
Protoss_Stargate 1 6667
Protoss_Dragoon 1 6739
Protoss_Forge 1 7151
Protoss_Corsair 3 9351
Protoss_Photon_Cannon 6 9923
9923
