Protoss_Nexus 2 3239
Protoss_Forge 1 2621
Protoss_Photon_Cannon 3 9036
Protoss_Gateway 3 9904
Protoss_Assimilator 2 6403
Protoss_Cybernetics_Core 1 5209
Protoss_Zealot 5 8821
Protoss_Stargate 1 6235
Protoss_Citadel_of_Adun 1 7348
Protoss_Corsair 5 9967
Protoss_Templar_Archives 1 8369
Protoss_Dark_Templar 2 9481
9967
