Protoss_Nexus 2 3220
Protoss_Forge 1 2492
Protoss_Photon_Cannon 3 8912
Protoss_Gateway 4 9631
Protoss_Assimilator 2 7034
Protoss_Cybernetics_Core 1 5181
Protoss_Zealot 8 9905
Protoss_Stargate 1 6347
Protoss_Corsair 2 8125
Protoss_Citadel_of_Adun 1 7589
9905
