Special_Protoss_Temple 14 0
Protoss_Nexus 2 3231
Protoss_Forge 1 2589
Protoss_Photon_Cannon 2 4075
Protoss_Gateway 2 9231
Protoss_Assimilator 2 6036
Protoss_Cybernetics_Core 1 5436
Protoss_Zealot 4 9399
Protoss_Stargate 1 6681
Protoss_Citadel_of_Adun 1 7277
Protoss_Corsair 3 9295
9399
