Protoss_Nexus 2 3961
Protoss_Forge 1 2213
Protoss_Photon_Cannon 3 9636
Protoss_Gateway 2 8420
Protoss_Assimilator 2 5948
Protoss_Cybernetics_Core 1 5242
Protoss_Zealot 8 9541
Protoss_Stargate 1 6273
Protoss_Citadel_of_Adun 1 7328
Protoss_Corsair 4 9437
Protoss_Templar_Archives 1 9785
9785
