Special_Protoss_Temple 14 0
Protoss_Nexus 2 3389
Protoss_Forge 1 2675
Protoss_Photon_Cannon 2 9537
Protoss_Gateway 2 8120
Protoss_Assimilator 2 7311
Protoss_Cybernetics_Core 1 5443
Protoss_Zealot 8 9817
Protoss_Stargate 1 6526
Protoss_Citadel_of_Adun 1 6878
Protoss_Dragoon 1 7103
Protoss_Corsair 1 7951
9817
