Protoss_Nexus 2 3627
Protoss_Forge 1 2411
Protoss_Gateway 1 4212
Protoss_Assimilator 2 6017
Protoss_Photon_Cannon 8 9637
Protoss_Cybernetics_Core 1 5298
Protoss_Zealot 4 9561
Protoss_Stargate 1 6351
Protoss_Citadel_of_Adun 1 7155
Protoss_Corsair 5 9981
Protoss_Robotics_Facility 1 9276
9981
