Protoss_Nexus 2 3837
Protoss_Forge 1 2312
Protoss_Photon_Cannon 4 9884
Protoss_Gateway 2 7656
Protoss_Zealot 8 9382
Protoss_Assimilator 2 6584
Protoss_Cybernetics_Core 1 5863
Protoss_Stargate 1 6956
Protoss_Citadel_of_Adun 1 7286
Protoss_Corsair 3 9705
Protoss_Templar_Archives 1 9068
9884
