Protoss_Nexus 2 4256
Protoss_Forge 1 2306
Protoss_Photon_Cannon 3 8780
Protoss_Assimilator 2 6323
Protoss_Gateway 2 7839
Protoss_Zealot 8 9711
Protoss_Cybernetics_Core 1 5886
Protoss_Stargate 1 6929
Protoss_Citadel_of_Adun 1 7171
Protoss_Corsair 1 8057
Protoss_Templar_Archives 1 9472
Protoss_Ground_Weapons_1 1 9953
9953
