Protoss_Nexus 2 2558
Protoss_Forge 1 2886
Protoss_Photon_Cannon 3 9902
Protoss_Gateway 4 9469
Protoss_Assimilator 2 5662
Protoss_Cybernetics_Core 1 4896
Protoss_Zealot 9 9739
Protoss_Stargate 1 5959
Protoss_Citadel_of_Adun 1 6901
Protoss_Corsair 3 9781
Protoss_Templar_Archives 1 9261
9902
