Protoss_Nexus 2 3747
Protoss_Forge 1 2661
Protoss_Photon_Cannon 2 9762
Protoss_Gateway 3 7211
Protoss_Assimilator 2 6225
Protoss_Cybernetics_Core 1 5325
Protoss_Zealot 12 9623
Protoss_Dragoon 1 6309
Protoss_Citadel_of_Adun 1 6690
Protoss_Stargate 2 9126
Protoss_Ground_Weapons_1 1 9997
9997
