Protoss_Nexus 2 8725
Protoss_Gateway 2 8026
Protoss_Assimilator 1 2292
Protoss_Cybernetics_Core 1 2913
Protoss_Zealot 4 7241
Protoss_Stargate 1 4064
Protoss_Dragoon 1 4401
Protoss_Corsair 1 5231
Protoss_Citadel_of_Adun 1 5688
Protoss_Templar_Archives 1 7203
Protoss_Dark_Templar 1 8241
Protoss_Forge 1 8333
Protoss_High_Templar 2 9281
Protoss_Photon_Cannon 3 9848
9848
