Protoss_Nexus 2 4019
Protoss_Forge 1 2417
Protoss_Photon_Cannon 3 4623
Protoss_Gateway 4 9509
Protoss_Assimilator 2 6593
Protoss_Zealot 5 8463
Protoss_Cybernetics_Core 1 5992
Protoss_Stargate 1 7051
Protoss_Citadel_of_Adun 1 7814
Protoss_Corsair 1 8185
Protoss_Templar_Archives 1 8807
Protoss_High_Templar 2 9901
9901
