Protoss_Nexus 2 8994
Protoss_Gateway 1 1903
Protoss_Assimilator 1 2416
Protoss_Zealot 7 9636
Protoss_Cybernetics_Core 1 3918
Protoss_Stargate 1 4967
Protoss_Corsair 2 7231
Protoss_Citadel_of_Adun 1 6343
Protoss_Forge 1 7864
Protoss_Templar_Archives 1 9673
9673
