Protoss_Nexus 2 3289
Protoss_Forge 1 2220
Protoss_Gateway 2 7811
Protoss_Assimilator 2 5653
Protoss_Photon_Cannon 2 8886
Protoss_Zealot 10 9985
Protoss_Cybernetics_Core 1 5235
Protoss_Stargate 1 6257
Protoss_Citadel_of_Adun 1 6919
Protoss_Corsair 4 9807
9985
