Protoss_Nexus 2 3719
Protoss_Forge 1 2341
Protoss_Photon_Cannon 1 3076
Protoss_Gateway 4 9773
Protoss_Assimilator 2 7456
Protoss_Zealot 8 9399
Protoss_Cybernetics_Core 1 5460
Protoss_Stargate 1 6524
Protoss_Citadel_of_Adun 1 7185
Protoss_Corsair 3 8711
Protoss_Ground_Weapons_1 1 9925
9925
