Protoss_Nexus 2 4249
Protoss_Forge 1 2664
Protoss_Photon_Cannon 3 9476
Protoss_Gateway 3 9746
Protoss_Assimilator 2 7063
Protoss_Cybernetics_Core 1 5468
Protoss_Zealot 8 9891
Protoss_Dragoon 1 6451
Protoss_Stargate 1 6689
Protoss_Citadel_of_Adun 1 7643
Protoss_Corsair 2 8543
Protoss_Templar_Archives 1 9681
9891
