Protoss_Nexus 1 0
Protoss_Gateway 2 2261
Protoss_Zealot 11 9403
Protoss_Shield_Battery 1 5851
Protoss_Forge 1 5924
Protoss_Photon_Cannon 4 8574
Protoss_Assimilator 1 7648
Protoss_Cybernetics_Core 1 8327
Protoss_Stargate 1 9566
9566
