Protoss_Nexus 2 3587
Protoss_Forge 1 2128
Protoss_Photon_Cannon 3 9505
Protoss_Gateway 2 8495
Protoss_Assimilator 2 6981
Protoss_Zealot 5 8697
Protoss_Cybernetics_Core 1 6162
Protoss_Stargate 1 7167
Protoss_Citadel_of_Adun 1 7748
Protoss_Corsair 2 9533
Protoss_Templar_Archives 1 8917
9533
