Protoss_Nexus 1 0
Protoss_Gateway 3 5088
Protoss_Zealot 14 9965
Protoss_Assimilator 1 3066
Protoss_Cybernetics_Core 1 4443
Protoss_Citadel_of_Adun 1 5463
Protoss_Forge 1 5943
Protoss_Photon_Cannon 3 8368
Protoss_Templar_Archives 1 9653
9965
