Protoss_Nexus 2 3305
Protoss_Forge 1 2532
Protoss_Photon_Cannon 3 9335
Protoss_Gateway 1 4483
Protoss_Assimilator 2 5969
Protoss_Cybernetics_Core 1 5665
Protoss_Zealot 4 8399
Protoss_Stargate 1 6733
Protoss_Robotics_Facility 1 7290
Protoss_Corsair 4 9789
Protoss_Robotics_Support_Bay 1 8848
Protoss_Reaver 1 9527
9789
