Protoss_Nexus 2 8744
Protoss_Gateway 2 2694
Protoss_Zealot 13 9076
Protoss_Assimilator 1 4183
Protoss_Cybernetics_Core 1 5544
Protoss_Forge 1 6820
Protoss_Photon_Cannon 2 8108
Protoss_Citadel_of_Adun 1 9448
9448
