Protoss_Nexus 1 0
Protoss_Gateway 1 1785
Protoss_Zealot 8 9565
Protoss_Forge 1 2951
Protoss_Photon_Cannon 5 7379
Protoss_Assimilator 1 5671
Protoss_Cybernetics_Core 1 8371
Protoss_Citadel_of_Adun 1 9511
Protoss_Stargate 1 9849
9849
