Protoss_Nexus 2 9100
Protoss_Gateway 1 1888
Protoss_Assimilator 1 2253
Protoss_Cybernetics_Core 1 2908
Protoss_Stargate 1 3913
Protoss_Corsair 2 5653
Protoss_Forge 1 5694
Protoss_Robotics_Facility 1 6098
Protoss_Photon_Cannon 2 9913
Protoss_Robotics_Support_Bay 1 7479
Protoss_Shuttle 1 7481
Protoss_Dragoon 2 8806
Protoss_Reaver 2 9435
9913
