Protoss_Nexus 2 3449
Protoss_Forge 1 2163
Protoss_Photon_Cannon 2 9286
Protoss_Assimilator 2 8139
Protoss_Gateway 3 5548
Protoss_Zealot 17 9558
Protoss_Cybernetics_Core 1 8300
9558
