Protoss_Nexus 1 0
Protoss_Assimilator 1 1673
Protoss_Gateway 1 2365
Protoss_Cybernetics_Core 1 3379
Protoss_Stargate 2 9200
Protoss_Robotics_Facility 1 4608
Protoss_Corsair 7 9935
Protoss_Shuttle 1 6011
Protoss_Fleet_Beacon 1 7328
Protoss_Forge 1 7572
Protoss_Photon_Cannon 1 8371
9935
