Protoss_Nexus 1 0
Protoss_Gateway 2 2608
Protoss_Zealot 13 6958
Protoss_Assimilator 1 6183
Protoss_Cybernetics_Core 1 7378
Protoss_Forge 1 7787
Protoss_Robotics_Facility 1 8399
Protoss_Dragoon 1 8601
Protoss_Citadel_of_Adun 1 9306
Protoss_Shuttle 1 9691
9691
