Protoss_Nexus 1 0
Protoss_Gateway 1 1937
Protoss_Assimilator 1 2442
Protoss_Zealot 8 8543
Protoss_Cybernetics_Core 1 4126
Protoss_Citadel_of_Adun 1 5242
Protoss_Forge 1 5635
Protoss_Templar_Archives 1 7910
Protoss_Photon_Cannon 3 8878
Protoss_High_Templar 2 9917
9917
