Protoss_Nexus 2 8096
Protoss_Gateway 2 2561
Protoss_Zealot 10 6566
Protoss_Assimilator 1 5265
Protoss_Cybernetics_Core 1 8450
Protoss_Dragoon 1 9446
Protoss_Robotics_Facility 1 9593
Protoss_Stargate 1 9773
9773
