Protoss_Nexus 2 3138
Protoss_Forge 1 3434
Protoss_Photon_Cannon 6 9903
Protoss_Assimilator 2 6396
Protoss_Gateway 1 5784
Protoss_Cybernetics_Core 1 6988
Protoss_Stargate 1 8252
Protoss_Robotics_Facility 1 8549
Protoss_Corsair 1 9416
Protoss_Shuttle 1 9971
9971
