Protoss_Nexus 2 9715
Protoss_Gateway 2 7608
Protoss_Assimilator 1 2402
Protoss_Cybernetics_Core 1 2996
Protoss_Robotics_Facility 1 4157
Protoss_Dragoon 3 7061
Protoss_Zealot 1 5228
Protoss_Shuttle 1 5451
Protoss_Observatory 1 5830
Protoss_Observer 2 7276
Protoss_Stargate 1 6665
Protoss_Corsair 4 9788
Protoss_Robotics_Support_Bay 1 8241
Protoss_Forge 1 8663
Protoss_Reaver 1 9866
9866
