Protoss_Nexus 2 9253
Protoss_Gateway 1 1843
Protoss_Assimilator 2 3628
Protoss_Zealot 5 6631
Protoss_Cybernetics_Core 1 4753
Protoss_Stargate 1 5874
Protoss_Forge 1 6104
Protoss_Corsair 4 9886
Protoss_Citadel_of_Adun 1 7288
Protoss_Templar_Archives 1 8374
Protoss_High_Templar 1 9361
Protoss_Photon_Cannon 1 9745
9886
