Protoss_Nexus 1 0
Protoss_Gateway 2 2721
Protoss_Zealot 17 9891
Protoss_Assimilator 1 6250
Protoss_Cybernetics_Core 1 7555
Protoss_Citadel_of_Adun 1 8607
Protoss_Dragoon 1 8658
Protoss_Templar_Archives 1 9748
9891
