Protoss_Nexus 1 0
Protoss_Gateway 1 1969
Protoss_Assimilator 1 2503
Protoss_Zealot 2 4271
Protoss_Cybernetics_Core 1 3694
Protoss_Stargate 1 4738
Protoss_Robotics_Facility 1 5156
Protoss_Dragoon 1 5351
Protoss_Corsair 2 9921
Protoss_Citadel_of_Adun 1 6352
Protoss_Robotics_Support_Bay 1 6663
Protoss_Forge 1 9438
9921
