Protoss_Nexus 2 9828
Protoss_Assimilator 1 1783
Protoss_Gateway 1 2301
Protoss_Cybernetics_Core 1 3475
Protoss_Stargate 1 4478
Protoss_Robotics_Facility 1 5004
Protoss_Corsair 5 9691
Protoss_Shuttle 1 6291
Protoss_Robotics_Support_Bay 1 6467
Protoss_Reaver 2 9996
Protoss_Air_Weapons_1 1 8511
Protoss_Forge 1 8730
Protoss_Shield_Battery 1 9133
Protoss_Photon_Cannon 2 9550
9996
