Protoss_Nexus 1 0
Protoss_Gateway 2 2708
Protoss_Zealot 13 8788
Protoss_Assimilator 1 4216
Protoss_Cybernetics_Core 1 5778
Protoss_Citadel_of_Adun 1 6979
Protoss_Forge 1 9082
9082
