Protoss_Nexus 2 0
Protoss_Gateway 2 2793
Protoss_Assimilator 1 3208
Protoss_Cybernetics_Core 1 3803
Protoss_Zealot 5 8053
Protoss_Stargate 1 5259
Protoss_Citadel_of_Adun 1 5933
Protoss_Dragoon 1 6236
8053
