Protoss_Nexus 1 0
Protoss_Gateway 3 8901
Protoss_Assimilator 1 2560
Protoss_Zealot 2 4236
Protoss_Forge 1 4186
Protoss_Photon_Cannon 1 4959
Protoss_Cybernetics_Core 1 5653
Protoss_Stargate 1 6772
Protoss_Citadel_of_Adun 1 6827
Protoss_Dragoon 1 6871
Protoss_Corsair 3 9720
Protoss_Ground_Weapons_1 1 9011
9720
