Protoss_Nexus 1 0
Protoss_Assimilator 1 1822
Protoss_Gateway 1 2260
Protoss_Cybernetics_Core 1 3258
Protoss_Dragoon 1 4246
Protoss_Stargate 1 4318
Protoss_Robotics_Facility 1 4906
Protoss_Corsair 3 7826
Protoss_Zealot 3 7705
Protoss_Robotics_Support_Bay 1 7107
Protoss_Reaver 1 8606
Protoss_Air_Weapons_1 1 9176
9176
