Protoss_Nexus 1 0
Protoss_Gateway 2 9151
Protoss_Assimilator 1 2348
Protoss_Zealot 4 6918
Protoss_Cybernetics_Core 1 3604
Protoss_Stargate 1 4608
Protoss_Dragoon 1 5053
Protoss_Robotics_Facility 1 5788
Protoss_Shuttle 1 7171
Protoss_Robotics_Support_Bay 1 7183
Protoss_Reaver 1 8241
Protoss_Forge 1 8489
9151
