Protoss_Nexus 2 7781
Protoss_Gateway 2 2425
Protoss_Zealot 7 4762
Protoss_Assimilator 1 5866
Protoss_Cybernetics_Core 1 6076
Protoss_Forge 1 7293
Protoss_Photon_Cannon 3 9305
Protoss_Citadel_of_Adun 1 8963
9305
