Protoss_Nexus 1 0
Protoss_Assimilator 1 1788
Protoss_Gateway 1 2288
Protoss_Cybernetics_Core 1 3288
Protoss_Stargate 1 4363
Protoss_Dragoon 1 4411
Protoss_Robotics_Facility 1 5165
Protoss_Corsair 5 9781
Protoss_Zealot 2 7041
Protoss_Shuttle 1 6641
Protoss_Forge 1 7401
Protoss_Robotics_Support_Bay 1 8316
Protoss_Photon_Cannon 2 8720
Protoss_Reaver 1 9126
Protoss_Air_Weapons_1 1 9686
9781
