Protoss_Nexus 2 7533
Protoss_Gateway 2 3998
Protoss_Assimilator 1 2774
Protoss_Zealot 14 9821
Protoss_Forge 1 7724
Protoss_Cybernetics_Core 1 8129
Protoss_Photon_Cannon 1 8437
9821
