Protoss_Nexus 1 0
Protoss_Gateway 1 1976
Protoss_Forge 1 2633
Protoss_Zealot 8 9604
Protoss_Photon_Cannon 5 4648
Protoss_Assimilator 1 4775
Protoss_Cybernetics_Core 1 5846
9604
