Protoss_Nexus 1 0
Protoss_Gateway 2 2615
Protoss_Zealot 4 6565
Protoss_Assimilator 1 3214
Protoss_Cybernetics_Core 1 4390
Protoss_Stargate 1 5375
Protoss_Citadel_of_Adun 1 6116
Protoss_Corsair 2 9649
Protoss_Forge 1 7827
Protoss_Photon_Cannon 1 9869
9869
