Protoss_Nexus 2 4358
Protoss_Forge 1 2049
Protoss_Photon_Cannon 2 3183
Protoss_Gateway 2 6488
Protoss_Assimilator 1 5906
Protoss_Zealot 3 7461
Protoss_Cybernetics_Core 1 6800
Protoss_Stargate 1 8005
8005
