Protoss_Nexus 2 8908
Protoss_Gateway 1 2121
Protoss_Assimilator 1 2523
Protoss_Zealot 6 9071
Protoss_Cybernetics_Core 1 4009
Protoss_Stargate 1 5317
Protoss_Corsair 1 6456
9071
