Protoss_Nexus 1 0
Protoss_Gateway 3 8247
Protoss_Assimilator 1 2599
Protoss_Cybernetics_Core 1 3256
Protoss_Zealot 11 9938
Protoss_Stargate 1 4387
Protoss_Forge 1 4649
Protoss_Corsair 2 6336
Protoss_Citadel_of_Adun 1 6908
Protoss_Ground_Weapons_1 1 9511
9938
