Protoss_Nexus 2 7963
Protoss_Gateway 2 8090
Protoss_Assimilator 2 9518
Protoss_Zealot 3 4566
Protoss_Cybernetics_Core 1 4228
Protoss_Citadel_of_Adun 1 5330
Protoss_Dragoon 1 5501
Protoss_Forge 1 6297
Protoss_Templar_Archives 1 6358
Protoss_Dark_Templar 1 7366
Protoss_High_Templar 3 9176
Protoss_Photon_Cannon 3 9258
9518
