Protoss_Nexus 2 8917
Protoss_Gateway 2 4503
Protoss_Assimilator 1 2946
Protoss_Zealot 3 5181
Protoss_Cybernetics_Core 1 4214
Protoss_Dragoon 1 5381
Protoss_Citadel_of_Adun 1 5705
Protoss_Stargate 1 6642
Protoss_Templar_Archives 1 6754
Protoss_Forge 1 7327
Protoss_Dark_Templar 1 7946
Protoss_Photon_Cannon 3 9873
Protoss_Corsair 1 8501
Protoss_High_Templar 2 8806
9873
