Protoss_Nexus 1 0
Protoss_Gateway 2 2578
Protoss_Zealot 12 9666
Protoss_Assimilator 1 4006
Protoss_Cybernetics_Core 1 4546
Protoss_Dragoon 1 5571
Protoss_Stargate 1 5803
Protoss_Citadel_of_Adun 1 6308
Protoss_Corsair 1 6981
Protoss_Templar_Archives 1 9253
9666
