Protoss_Nexus 1 0
Protoss_Gateway 2 2608
Protoss_Zealot 5 7521
Protoss_Assimilator 1 3316
Protoss_Cybernetics_Core 1 4688
Protoss_Robotics_Facility 1 6123
Protoss_Dragoon 4 8091
Protoss_Shuttle 1 8251
Protoss_Citadel_of_Adun 1 8609
Protoss_Robotics_Support_Bay 1 8878
Protoss_Reaver 1 9496
Protoss_Templar_Archives 1 9892
9892
