Protoss_Nexus 2 2934
Protoss_Gateway 3 8157
Protoss_Forge 1 3716
Protoss_Photon_Cannon 6 9998
Protoss_Assimilator 1 5683
Protoss_Zealot 7 9981
Protoss_Cybernetics_Core 1 6329
Protoss_Stargate 1 7398
Protoss_Corsair 2 9426
Protoss_Citadel_of_Adun 1 9188
Protoss_Robotics_Facility 1 9878
9998
