Protoss_Nexus 1 0
Protoss_Gateway 2 7433
Protoss_Zealot 8 9221
Protoss_Assimilator 1 3325
Protoss_Cybernetics_Core 1 4068
Protoss_Dragoon 1 5946
Protoss_Robotics_Facility 1 6163
Protoss_Citadel_of_Adun 1 6453
Protoss_Shuttle 1 7891
Protoss_Robotics_Support_Bay 1 8198
Protoss_Reaver 1 8793
9221
