Protoss_Nexus 2 3043
Protoss_Forge 1 3621
Protoss_Photon_Cannon 3 9543
Protoss_Gateway 4 8963
Protoss_Assimilator 2 6988
Protoss_Cybernetics_Core 1 6478
Protoss_Zealot 9 9806
Protoss_Dragoon 3 8580
Protoss_Citadel_of_Adun 1 8732
9806
