Protoss_Nexus 1 0
Protoss_Gateway 2 2602
Protoss_Zealot 9 8841
Protoss_Forge 1 4653
Protoss_Photon_Cannon 2 9503
Protoss_Assimilator 1 6840
Protoss_Cybernetics_Core 1 8081
9503
