Protoss_Nexus 2 3239
Protoss_Forge 1 3781
Protoss_Assimilator 3 9179
Protoss_Photon_Cannon 1 4643
Protoss_Gateway 4 9018
Protoss_Zealot 15 9576
Protoss_Cybernetics_Core 1 6441
Protoss_Citadel_of_Adun 1 7682
Protoss_Templar_Archives 1 9771
9771
