Protoss_Nexus 1 0
Protoss_Gateway 2 2439
Protoss_Zealot 17 9101
Protoss_Assimilator 1 5902
Protoss_Forge 1 7412
Protoss_Cybernetics_Core 1 8738
Protoss_Photon_Cannon 1 9403
Protoss_Citadel_of_Adun 1 9894
9894
