Protoss_Nexus 1 0
Protoss_Gateway 2 6378
Protoss_Assimilator 1 2693
Protoss_Zealot 7 9932
Protoss_Cybernetics_Core 1 3763
Protoss_Citadel_of_Adun 1 4763
Protoss_Templar_Archives 1 6833
Protoss_Forge 1 7351
Protoss_High_Templar 2 8578
Protoss_Photon_Cannon 2 9096
9932
