Protoss_Nexus 1 0
Protoss_Gateway 3 7158
Protoss_Assimilator 1 2386
Protoss_Zealot 12 9316
Protoss_Cybernetics_Core 1 3483
Protoss_Stargate 1 4599
Protoss_Citadel_of_Adun 1 5708
Protoss_Corsair 1 5916
Protoss_Templar_Archives 1 9582
9582
