Protoss_Nexus 2 5263
Protoss_Gateway 4 8133
Protoss_Zealot 15 9891
Protoss_Assimilator 1 5532
Protoss_Forge 1 5890
Protoss_Photon_Cannon 1 6714
Protoss_Cybernetics_Core 1 7100
Protoss_Citadel_of_Adun 1 8332
9891
