Protoss_Nexus 1 0
Protoss_Gateway 2 2672
Protoss_Zealot 8 7801
Protoss_Assimilator 1 3978
Protoss_Cybernetics_Core 1 4670
Protoss_Dragoon 1 5711
Protoss_Citadel_of_Adun 1 5836
Protoss_Templar_Archives 1 7608
Protoss_Dark_Templar 2 9106
Protoss_Forge 1 8882
Protoss_High_Templar 2 9353
9353
