Protoss_Nexus 2 4978
Protoss_Forge 1 2269
Protoss_Photon_Cannon 7 9461
Protoss_Gateway 2 5356
Protoss_Assimilator 1 5613
Protoss_Zealot 10 9651
Protoss_Cybernetics_Core 1 6909
Protoss_Stargate 1 7916
Protoss_Corsair 2 9766
9766
