Protoss_Nexus 1 0
Protoss_Gateway 2 2458
Protoss_Zealot 21 9816
Protoss_Assimilator 1 5153
Protoss_Cybernetics_Core 1 6150
Protoss_Stargate 1 7601
Protoss_Corsair 1 8751
9816
