Protoss_Nexus 1 0
Protoss_Gateway 1 1928
Protoss_Assimilator 1 2243
Protoss_Cybernetics_Core 1 2985
Protoss_Stargate 1 4029
Protoss_Robotics_Facility 1 4709
Protoss_Corsair 8 9925
Protoss_Forge 1 5982
Protoss_Shuttle 1 6209
Protoss_Robotics_Support_Bay 1 6745
Protoss_Photon_Cannon 2 9414
Protoss_Reaver 1 8955
9925
