Protoss_Nexus 1 0
Protoss_Gateway 2 7883
Protoss_Forge 1 2611
Protoss_Zealot 9 9496
Protoss_Photon_Cannon 3 8675
Protoss_Assimilator 1 5770
Protoss_Cybernetics_Core 1 6940
Protoss_Dragoon 1 8011
Protoss_Citadel_of_Adun 1 9282
9496
