Protoss_Nexus 1 0
Protoss_Gateway 2 2478
Protoss_Zealot 20 9733
Protoss_Assimilator 1 6407
Protoss_Forge 1 6667
Protoss_Cybernetics_Core 1 7722
Protoss_Citadel_of_Adun 1 8800
9733
