Protoss_Nexus 3 7792
Protoss_Forge 1 3479
Protoss_Assimilator 2 9789
Protoss_Gateway 1 4642
Protoss_Cybernetics_Core 1 5915
Protoss_Photon_Cannon 5 8608
Protoss_Stargate 1 7031
Protoss_Robotics_Facility 1 7386
Protoss_Corsair 2 9311
Protoss_Shuttle 2 9853
Protoss_Ground_Weapons_1 1 9311
9853
