Protoss_Nexus 1 0
Protoss_Gateway 2 6629
Protoss_Assimilator 1 2389
Protoss_Zealot 4 5483
Protoss_Cybernetics_Core 1 3711
Protoss_Stargate 1 5013
Protoss_Corsair 1 6151
Protoss_Dragoon 8 9826
Protoss_Robotics_Facility 1 7007
Protoss_Forge 1 7503
Protoss_Photon_Cannon 1 8458
Protoss_Shuttle 1 9091
Protoss_Robotics_Support_Bay 1 9478
9826
