Protoss_Nexus 2 9238
Protoss_Gateway 2 2583
Protoss_Zealot 12 8348
Protoss_Cybernetics_Core 1 4678
Protoss_Assimilator 1 5253
Protoss_Dragoon 1 6286
Protoss_Citadel_of_Adun 1 6821
Protoss_Templar_Archives 1 8653
Protoss_Forge 1 8821
9238
