Protoss_Nexus 1 0
Protoss_Gateway 2 6607
Protoss_Zealot 9 8781
Protoss_Assimilator 1 3109
Protoss_Cybernetics_Core 1 3680
Protoss_Stargate 1 4807
Protoss_Dragoon 1 4971
Protoss_Citadel_of_Adun 1 5513
Protoss_Corsair 1 6056
Protoss_Forge 1 7635
Protoss_Templar_Archives 1 8222
Protoss_High_Templar 2 9666
9666
