Protoss_Nexus 1 0
Protoss_Gateway 1 1958
Protoss_Assimilator 1 2483
Protoss_Zealot 4 8501
Protoss_Cybernetics_Core 1 4213
Protoss_Robotics_Facility 1 5218
Protoss_Stargate 1 5944
8501
