Protoss_Nexus 3 9775
Protoss_Forge 1 2892
Protoss_Photon_Cannon 3 9681
Protoss_Gateway 3 7081
Protoss_Assimilator 2 7314
Protoss_Cybernetics_Core 1 5063
Protoss_Zealot 2 7423
Protoss_Stargate 1 6193
Protoss_Citadel_of_Adun 1 6679
Protoss_Corsair 1 7561
Protoss_Templar_Archives 1 7969
Protoss_Dark_Templar 1 8995
Protoss_Robotics_Facility 1 9911
9911
