Protoss_Nexus 1 0
Protoss_Gateway 2 8447
Protoss_Zealot 3 4831
Protoss_Assimilator 1 3168
Protoss_Cybernetics_Core 1 5844
Protoss_Forge 1 6354
Protoss_Citadel_of_Adun 1 6956
Protoss_Photon_Cannon 2 9953
Protoss_Dragoon 1 7511
Protoss_Templar_Archives 1 8280
Protoss_Dark_Templar 2 9446
9953
