Protoss_Nexus 2 4450
Protoss_Forge 1 2013
Protoss_Photon_Cannon 4 9018
Protoss_Gateway 2 7288
Protoss_Zealot 8 9831
Protoss_Assimilator 2 9336
Protoss_Cybernetics_Core 1 7573
Protoss_Citadel_of_Adun 1 8608
Protoss_Templar_Archives 1 9651
9831
