Protoss_Nexus 2 9505
Protoss_Gateway 1 1907
Protoss_Assimilator 2 3326
Protoss_Zealot 4 5695
Protoss_Forge 1 3955
Protoss_Cybernetics_Core 1 5161
Protoss_Citadel_of_Adun 1 6246
Protoss_Dragoon 1 6297
Protoss_Photon_Cannon 3 8859
Protoss_Templar_Archives 1 7439
Protoss_High_Templar 3 9979
9979
