Protoss_Nexus 2 3794
Protoss_Forge 2 9423
Protoss_Photon_Cannon 2 4643
Protoss_Assimilator 2 7546
Protoss_Gateway 4 8596
Protoss_Zealot 8 8953
Protoss_Cybernetics_Core 1 6731
Protoss_Citadel_of_Adun 1 8103
Protoss_Robotics_Facility 1 9889
9889
