Protoss_Nexus 2 4517
Protoss_Forge 1 2183
Protoss_Photon_Cannon 6 9466
Protoss_Gateway 2 9754
Protoss_Assimilator 2 6697
Protoss_Zealot 4 8733
Protoss_Cybernetics_Core 1 6744
Protoss_Stargate 1 7874
Protoss_Citadel_of_Adun 1 8483
Protoss_Robotics_Facility 1 8662
Protoss_Corsair 1 9011
Protoss_Templar_Archives 1 9648
9754
