Protoss_Nexus 1 0
Protoss_Assimilator 1 1798
Protoss_Forge 1 2327
Protoss_Photon_Cannon 1 3334
Protoss_Gateway 3 4973
Protoss_Zealot 13 9512
Protoss_Ground_Weapons_1 1 7156
Protoss_Cybernetics_Core 1 7319
Protoss_Stargate 1 8927
9512
