Protoss_Nexus 1 0
Protoss_Gateway 2 6076
Protoss_Assimilator 1 2343
Protoss_Zealot 3 6431
Protoss_Cybernetics_Core 1 3761
Protoss_Citadel_of_Adun 1 4943
Protoss_Dragoon 1 5171
Protoss_Templar_Archives 1 5974
Protoss_Robotics_Facility 1 6948
Protoss_Dark_Templar 3 9031
Protoss_High_Templar 1 9046
9046
