Protoss_Nexus 2 8471
Protoss_Gateway 2 2638
Protoss_Zealot 5 4386
Protoss_Assimilator 1 4016
Protoss_Cybernetics_Core 1 5510
Protoss_Forge 1 6093
Protoss_Citadel_of_Adun 1 7015
Protoss_Photon_Cannon 1 8666
8666
