Protoss_Nexus 2 2986
Protoss_Forge 1 3281
Protoss_Gateway 3 6757
Protoss_Assimilator 2 6285
Protoss_Photon_Cannon 7 9815
Protoss_Zealot 10 8399
Protoss_Cybernetics_Core 1 5291
Protoss_Citadel_of_Adun 1 6476
Protoss_Templar_Archives 1 7463
Protoss_High_Templar 3 9423
Protoss_Ground_Weapons_1 1 9727
9815
