Protoss_Nexus 2 2979
Protoss_Forge 1 3563
Protoss_Photon_Cannon 2 4623
Protoss_Gateway 4 6630
Protoss_Assimilator 2 7829
Protoss_Cybernetics_Core 1 5997
Protoss_Citadel_of_Adun 1 7088
Protoss_Dragoon 1 7147
Protoss_Zealot 12 9387
Protoss_Templar_Archives 1 9465
9465
