Protoss_Nexus 3 8663
Protoss_Forge 1 2620
Protoss_Photon_Cannon 3 9131
Protoss_Gateway 1 4477
Protoss_Assimilator 2 6829
Protoss_Cybernetics_Core 1 5508
Protoss_Stargate 1 6493
Protoss_Corsair 4 9603
Protoss_Robotics_Facility 1 8199
Protoss_Robotics_Support_Bay 1 9543
9603
