Protoss_Nexus 3 6669
Protoss_Forge 1 2139
Protoss_Gateway 1 4224
Protoss_Photon_Cannon 3 9719
Protoss_Assimilator 2 6067
Protoss_Cybernetics_Core 1 5667
Protoss_Stargate 1 6857
Protoss_Robotics_Facility 2 8013
Protoss_Zealot 1 7946
Protoss_Corsair 4 9987
Protoss_Robotics_Support_Bay 1 9145
Protoss_Shuttle 1 9146
9987
