Protoss_Nexus 2 2847
Protoss_Forge 1 3313
Protoss_Photon_Cannon 2 7035
Protoss_Gateway 4 7589
Protoss_Assimilator 2 6698
Protoss_Cybernetics_Core 1 5677
Protoss_Zealot 7 9331
Protoss_Citadel_of_Adun 1 6877
Protoss_Robotics_Facility 1 9204
9331
