Protoss_Nexus 2 2885
Protoss_Forge 1 3298
Protoss_Gateway 2 5634
Protoss_Photon_Cannon 6 9982
Protoss_Assimilator 2 8480
Protoss_Zealot 10 9701
Protoss_Cybernetics_Core 1 6513
Protoss_Stargate 1 7646
Protoss_Citadel_of_Adun 1 7876
Protoss_Dragoon 1 8031
Protoss_Corsair 2 9496
9982
