Protoss_Nexus 2 4055
Protoss_Forge 1 2618
Protoss_Photon_Cannon 8 8909
Protoss_Gateway 1 4757
Protoss_Assimilator 2 7706
Protoss_Zealot 4 9459
Protoss_Cybernetics_Core 1 6447
Protoss_Stargate 1 7542
Protoss_Corsair 3 9993
Protoss_Citadel_of_Adun 1 9826
9993
