Protoss_Nexus 2 3429
Protoss_Forge 1 2297
Protoss_Photon_Cannon 4 9617
Protoss_Gateway 3 7998
Protoss_Assimilator 2 6409
Protoss_Zealot 1 5315
Protoss_Cybernetics_Core 1 6032
Protoss_Dragoon 1 7013
Protoss_Citadel_of_Adun 1 7057
Protoss_Templar_Archives 1 8047
Protoss_High_Templar 4 9785
Protoss_Dark_Templar 1 9059
Protoss_Robotics_Facility 1 9310
Protoss_Archon 1 9844
9844
