Protoss_Nexus 2 3805
Protoss_Forge 1 1917
Protoss_Photon_Cannon 4 9875
Protoss_Gateway 3 7471
Protoss_Assimilator 1 4626
Protoss_Zealot 12 9463
Protoss_Cybernetics_Core 1 5579
Protoss_Citadel_of_Adun 1 6856
Protoss_Templar_Archives 1 9228
9875
