Protoss_Nexus 2 4183
Protoss_Forge 1 2642
Protoss_Photon_Cannon 6 9933
Protoss_Gateway 5 9708
Protoss_Assimilator 2 6972
Protoss_Zealot 2 6183
Protoss_Cybernetics_Core 1 6399
Protoss_Stargate 1 7790
Protoss_Citadel_of_Adun 1 8212
Protoss_Corsair 2 9746
Protoss_Templar_Archives 1 9428
9933
