Protoss_Nexus 1 0
Protoss_Gateway 2 9583
Protoss_Assimilator 1 2327
Protoss_Zealot 5 8297
Protoss_Cybernetics_Core 1 4877
Protoss_Stargate 1 5902
Protoss_Dragoon 1 6007
Protoss_Citadel_of_Adun 1 6449
Protoss_Forge 1 7156
Protoss_Corsair 1 7239
Protoss_Templar_Archives 1 7818
Protoss_Photon_Cannon 2 9125
Protoss_Dark_Templar 2 9757
Protoss_Robotics_Facility 1 9036
9757
