Protoss_Nexus 2 3949
Protoss_Forge 1 2308
Protoss_Photon_Cannon 2 8473
Protoss_Gateway 2 8261
Protoss_Assimilator 2 6217
Protoss_Zealot 1 5227
Protoss_Cybernetics_Core 1 5466
Protoss_Stargate 1 6597
Protoss_Citadel_of_Adun 1 7001
Protoss_Corsair 3 9203
Protoss_Templar_Archives 1 8020
Protoss_Robotics_Facility 1 8093
Protoss_Dark_Templar 1 9135
Protoss_High_Templar 1 9355
Protoss_Shuttle 1 9395
9395
