Protoss_Nexus 2 3398
Protoss_Forge 1 2170
Protoss_Gateway 2 7636
Protoss_Photon_Cannon 7 9228
Protoss_Assimilator 2 6215
Protoss_Zealot 4 6971
Protoss_Cybernetics_Core 1 5502
Protoss_Citadel_of_Adun 1 6536
Protoss_Templar_Archives 1 7664
Protoss_High_Templar 3 9551
9551
