Protoss_Nexus 2 2801
Protoss_Gateway 3 9593
Protoss_Forge 1 3705
Protoss_Assimilator 2 6800
Protoss_Photon_Cannon 2 9535
Protoss_Zealot 8 9663
Protoss_Cybernetics_Core 1 5918
Protoss_Dragoon 1 6967
Protoss_Stargate 1 7347
Protoss_Citadel_of_Adun 1 7374
Protoss_Corsair 2 9781
Protoss_Templar_Archives 1 8675
Protoss_Ground_Weapons_1 1 9479
9781
