Protoss_Nexus 2 3352
Protoss_Forge 1 2702
Protoss_Photon_Cannon 3 8885
Protoss_Gateway 1 4119
Protoss_Assimilator 2 5927
Protoss_Cybernetics_Core 1 5381
Protoss_Stargate 1 6426
Protoss_Dragoon 1 6513
Protoss_Citadel_of_Adun 1 7002
Protoss_Zealot 1 7265
Protoss_Robotics_Facility 1 8037
8885
