Protoss_Nexus 1 0
Protoss_Forge 1 2178
Protoss_Photon_Cannon 4 6310
Protoss_Assimilator 2 6903
Protoss_Gateway 2 5717
Protoss_Zealot 6 9596
Protoss_Cybernetics_Core 1 7777
9596
