Protoss_Nexus 2 2983
Protoss_Forge 1 3228
Protoss_Photon_Cannon 11 9573
Protoss_Gateway 1 4890
Protoss_Assimilator 2 7004
Protoss_Zealot 1 6091
Protoss_Cybernetics_Core 1 6498
Protoss_Stargate 1 7528
Protoss_Robotics_Facility 1 7918
Protoss_Corsair 2 9381
Protoss_Robotics_Support_Bay 1 9263
Protoss_Reaver 1 9851
9851
