Protoss_Nexus 2 8000
Protoss_Gateway 1 2047
Protoss_Assimilator 2 9572
Protoss_Zealot 4 5511
Protoss_Cybernetics_Core 1 4631
Protoss_Citadel_of_Adun 1 5667
Protoss_Dragoon 1 6113
Protoss_Templar_Archives 1 6679
Protoss_Dark_Templar 1 7659
Protoss_Forge 1 7706
Protoss_High_Templar 2 9249
Protoss_Photon_Cannon 4 9951
9951
