Protoss_Nexus 2 4409
Protoss_Forge 1 2538
Protoss_Photon_Cannon 7 9891
Protoss_Gateway 3 7961
Protoss_Assimilator 2 6917
Protoss_Zealot 1 5757
Protoss_Cybernetics_Core 1 5839
Protoss_Dragoon 1 6819
Protoss_Citadel_of_Adun 1 6834
Protoss_Templar_Archives 1 8206
Protoss_Dark_Templar 1 9191
Protoss_High_Templar 3 9971
9971
