Protoss_Nexus 2 4313
Protoss_Forge 1 2331
Protoss_Photon_Cannon 3 9615
Protoss_Gateway 3 8898
Protoss_Assimilator 2 6732
Protoss_Cybernetics_Core 1 5940
Protoss_Zealot 2 6548
Protoss_Stargate 1 6939
Protoss_Dragoon 1 7156
Protoss_Citadel_of_Adun 1 7706
Protoss_Corsair 3 9826
Protoss_Templar_Archives 1 8716
Protoss_Dark_Templar 2 9736
9826
