Protoss_Nexus 2 2938
Protoss_Gateway 1 3447
Protoss_Assimilator 2 5848
Protoss_Cybernetics_Core 1 4552
Protoss_Stargate 1 5608
Protoss_Forge 1 6383
Protoss_Corsair 4 8886
Protoss_Robotics_Facility 2 9298
Protoss_Photon_Cannon 7 9859
Protoss_Robotics_Support_Bay 1 8278
Protoss_Reaver 1 9121
9859
