Protoss_Nexus 2 2908
Protoss_Forge 1 3482
Protoss_Gateway 4 9898
Protoss_Assimilator 2 5738
Protoss_Cybernetics_Core 1 5095
Protoss_Photon_Cannon 1 5304
Protoss_Zealot 4 9651
Protoss_Stargate 1 6483
Protoss_Dragoon 1 6716
Protoss_Citadel_of_Adun 1 6897
Protoss_Corsair 4 9479
Protoss_Templar_Archives 1 8033
Protoss_Dark_Templar 2 9606
9898
