Protoss_Nexus 2 3645
Protoss_Forge 1 2265
Protoss_Photon_Cannon 3 9150
Protoss_Gateway 3 8247
Protoss_Assimilator 2 5946
Protoss_Cybernetics_Core 1 5444
Protoss_Zealot 5 8575
Protoss_Dragoon 1 6449
Protoss_Stargate 1 6557
Protoss_Citadel_of_Adun 1 7019
Protoss_Corsair 2 8341
Protoss_Templar_Archives 1 8048
Protoss_Dark_Templar 2 9999
Protoss_High_Templar 2 9439
9999
