Protoss_Nexus 2 5628
Protoss_Forge 1 2207
Protoss_Photon_Cannon 6 9361
Protoss_Gateway 4 8382
Protoss_Zealot 8 9996
Protoss_Assimilator 1 7913
Protoss_Cybernetics_Core 1 9889
9996
