Protoss_Nexus 2 3796
Protoss_Forge 1 2163
Protoss_Photon_Cannon 5 9837
Protoss_Gateway 1 4925
Protoss_Assimilator 2 7904
Protoss_Zealot 4 9401
Protoss_Cybernetics_Core 1 7231
Protoss_Stargate 1 8264
Protoss_Citadel_of_Adun 2 9504
Protoss_Corsair 1 9446
9837
