Protoss_Gateway 2 3971
Protoss_Zealot 7 7599
Protoss_Nexus 1 8243
Protoss_Assimilator 2 9543
Protoss_Cybernetics_Core 1 7920
Protoss_Citadel_of_Adun 1 8963
Protoss_Forge 1 8946
Protoss_Dragoon 2 9433
Protoss_Templar_Archives 1 10161
Protoss_Photon_Cannon 1 10068
Protoss_Dark_Templar 2 10905
10905
