Protoss_Gateway 2 7851
Protoss_Zealot 3 5121
Protoss_Assimilator 1 4090
Protoss_Cybernetics_Core 1 5373
Protoss_Dragoon 8 11197
Protoss_Robotics_Facility 1 8917
Protoss_Observatory 1 9128
Protoss_Observer 2 10501
Protoss_Nexus 1 12110
Protoss_Robotics_Support_Bay 1 10509
12110
