Protoss_Gateway 4 11381
Protoss_Zealot 6 9965
Protoss_Assimilator 1 5445
Protoss_Cybernetics_Core 1 6315
Protoss_Dragoon 9 10971
Protoss_Nexus 1 11259
Protoss_Robotics_Facility 1 10839
11381
