Protoss_Gateway 2 5767
Protoss_Assimilator 1 3498
Protoss_Zealot 1 3911
Protoss_Cybernetics_Core 1 5128
Protoss_Dragoon 9 10906
Protoss_Robotics_Facility 1 7903
Protoss_Robotics_Support_Bay 1 8094
Protoss_Shuttle 1 8991
Protoss_Reaver 1 10251
10906
