Protoss_Gateway 3 11241
Protoss_Zealot 6 6293
Protoss_Assimilator 1 5810
Protoss_Shield_Battery 1 6400
Protoss_Cybernetics_Core 2 7672
Protoss_Nexus 1 9799
Protoss_Dragoon 5 10351
Protoss_Robotics_Facility 1 10885
11241
