Protoss_Nexus 1 5995
Protoss_Gateway 2 6773
Protoss_Zealot 4 7827
Protoss_Assimilator 2 7731
Protoss_Cybernetics_Core 1 7693
Protoss_Forge 1 7641
Protoss_Dragoon 6 10549
Protoss_Photon_Cannon 3 9887
Protoss_Citadel_of_Adun 1 10271
Protoss_Templar_Archives 1 11323
11323
