Protoss_Gateway 2 6893
Protoss_Zealot 6 10719
Protoss_Assimilator 1 4028
Protoss_Cybernetics_Core 1 6019
Protoss_Citadel_of_Adun 1 7031
Protoss_Dragoon 1 6921
Protoss_Templar_Archives 1 8017
Protoss_Forge 1 8282
Protoss_Dark_Templar 2 8769
Protoss_High_Templar 2 9521
Protoss_Photon_Cannon 4 10768
Protoss_Nexus 1 11455
11455
