Protoss_Gateway 2 4007
Protoss_Zealot 5 5831
Protoss_Assimilator 1 5389
Protoss_Cybernetics_Core 1 6533
Protoss_Robotics_Facility 1 8108
Protoss_Dragoon 1 7731
Protoss_Shuttle 1 8921
Protoss_Robotics_Support_Bay 1 8233
Protoss_Nexus 1 10869
Protoss_Reaver 1 10063
Protoss_Observatory 1 9498
Protoss_Observer 1 10395
10869
