Protoss_Nexus 2 11955
Protoss_Gateway 3 8741
Protoss_Assimilator 2 10457
Protoss_Cybernetics_Core 1 5918
Protoss_Zealot 1 5847
Protoss_Dragoon 10 11161
Protoss_Robotics_Facility 1 10206
Protoss_Observatory 1 10317
Protoss_Forge 1 10604
11955
