Protoss_Nexus 1 5791
Protoss_Assimilator 1 4213
Protoss_Gateway 4 9968
Protoss_Cybernetics_Core 1 6350
Protoss_Dragoon 9 10731
Protoss_Robotics_Facility 1 9073
Protoss_Observatory 1 9461
Protoss_Forge 1 9981
Protoss_Observer 1 10456
Protoss_Photon_Cannon 2 11048
11048
