Protoss_Nexus 1 5763
Protoss_Gateway 4 10327
Protoss_Assimilator 2 9605
Protoss_Cybernetics_Core 1 5977
Protoss_Dragoon 11 11075
Protoss_Robotics_Facility 1 9086
Protoss_Zealot 4 10899
Protoss_Observatory 1 9219
Protoss_Citadel_of_Adun 1 10407
Protoss_Observer 1 10735
11075
