Protoss_Gateway 4 11001
Protoss_Assimilator 2 5765
Protoss_Zealot 9 7197
Protoss_Cybernetics_Core 1 7116
Protoss_Dragoon 8 10969
Protoss_Robotics_Facility 1 10237
Protoss_Observatory 1 10502
11001
