Protoss_Gateway 2 3922
Protoss_Zealot 5 5701
Protoss_Assimilator 1 4345
Protoss_Cybernetics_Core 1 6952
Protoss_Dragoon 10 10971
Protoss_Robotics_Facility 1 9019
Protoss_Shuttle 1 9903
Protoss_Observatory 1 9330
Protoss_Observer 1 10473
Protoss_Robotics_Support_Bay 1 10563
10971
