Protoss_Gateway 3 11272
Protoss_Zealot 7 7161
Protoss_Nexus 1 8328
Protoss_Assimilator 1 6519
Protoss_Cybernetics_Core 1 7313
Protoss_Forge 1 8179
Protoss_Citadel_of_Adun 1 8690
Protoss_Photon_Cannon 1 9333
Protoss_Dragoon 4 11156
11272
