Protoss_Gateway 3 10475
Protoss_Assimilator 1 3494
Protoss_Zealot 3 5333
Protoss_Cybernetics_Core 1 6342
Protoss_Dragoon 7 9968
Protoss_Robotics_Facility 1 8393
Protoss_Observatory 1 8585
Protoss_Observer 2 10263
10475
