Protoss_Nexus 1 6314
Protoss_Gateway 6 10594
Protoss_Assimilator 1 5241
Protoss_Zealot 5 10401
Protoss_Cybernetics_Core 1 6269
Protoss_Dragoon 6 10611
Protoss_Robotics_Facility 1 8203
Protoss_Observatory 1 8426
Protoss_Observer 1 9286
Protoss_Citadel_of_Adun 1 10419
10611
