Protoss_Gateway 2 6377
Protoss_Zealot 3 5019
Protoss_Assimilator 1 4004
Protoss_Cybernetics_Core 1 5938
Protoss_Dragoon 8 9787
Protoss_Robotics_Facility 1 8542
Protoss_Observatory 1 8635
Protoss_Observer 1 9451
Protoss_Citadel_of_Adun 1 10448
Protoss_Nexus 1 12480
12480
