Protoss_Nexus 1 6211
Protoss_Gateway 4 8776
Protoss_Assimilator 2 9822
Protoss_Cybernetics_Core 1 6268
Protoss_Zealot 3 10851
Protoss_Dragoon 11 10397
Protoss_Citadel_of_Adun 1 9754
Protoss_Forge 1 9728
Protoss_Photon_Cannon 1 10749
10851
