Protoss_Gateway 3 8409
Protoss_Assimilator 1 3886
Protoss_Zealot 2 4633
Protoss_Cybernetics_Core 1 5473
Protoss_Dragoon 12 11047
Protoss_Robotics_Facility 1 7955
Protoss_Observatory 1 8109
Protoss_Observer 3 10533
11047
