Protoss_Gateway 4 8704
Protoss_Assimilator 1 3498
Protoss_Cybernetics_Core 1 4528
Protoss_Dragoon 12 11196
Protoss_Robotics_Facility 1 7093
Protoss_Observatory 1 7183
Protoss_Observer 1 7956
Protoss_Zealot 6 10186
11196
