Protoss_Assimilator 1 2656
Protoss_Gateway 2 6964
Protoss_Cybernetics_Core 1 4788
Protoss_Robotics_Facility 1 6268
Protoss_Dragoon 8 10116
Protoss_Observatory 1 6383
Protoss_Observer 2 7758
Protoss_Shuttle 1 8899
Protoss_Robotics_Support_Bay 1 8685
Protoss_Reaver 2 11403
11403
