Protoss_Gateway 2 6593
Protoss_Zealot 3 5421
Protoss_Assimilator 1 4443
Protoss_Cybernetics_Core 1 5708
Protoss_Dragoon 11 11070
Protoss_Robotics_Facility 1 10053
Protoss_Robotics_Support_Bay 1 10203
Protoss_Shuttle 1 10931
Protoss_Observatory 1 10308
11070
