Protoss_Gateway 2 5609
Protoss_Assimilator 1 3453
Protoss_Zealot 3 5416
Protoss_Cybernetics_Core 1 5253
Protoss_Dragoon 8 10016
Protoss_Citadel_of_Adun 1 9009
Protoss_Templar_Archives 1 10008
Protoss_Dark_Templar 2 10801
Protoss_Forge 1 10811
10811
