Protoss_Gateway 2 4054
Protoss_Zealot 6 7388
Protoss_Assimilator 1 5721
Protoss_Cybernetics_Core 1 6599
Protoss_Robotics_Facility 1 9634
Protoss_Dragoon 5 11045
Protoss_Robotics_Support_Bay 1 10045
11045
