Protoss_Gateway 2 7255
Protoss_Assimilator 1 3522
Protoss_Cybernetics_Core 1 4527
Protoss_Zealot 1 4799
Protoss_Dragoon 12 11039
Protoss_Robotics_Facility 1 9292
Protoss_Shuttle 1 10925
Protoss_Robotics_Support_Bay 1 10513
Protoss_Observatory 1 10719
11039
