Protoss_Gateway 2 9091
Protoss_Assimilator 1 3838
Protoss_Zealot 2 5046
Protoss_Cybernetics_Core 1 5126
Protoss_Dragoon 4 8686
Protoss_Robotics_Facility 2 11814
Protoss_Citadel_of_Adun 1 7760
Protoss_Templar_Archives 1 8844
Protoss_Dark_Templar 3 10388
Protoss_Forge 1 10768
11814
