Protoss_Gateway 3 11352
Protoss_Assimilator 1 3273
Protoss_Cybernetics_Core 1 4463
Protoss_Dragoon 6 10731
Protoss_Citadel_of_Adun 1 7671
Protoss_Nexus 1 9393
Protoss_Templar_Archives 1 8693
Protoss_Dark_Templar 3 10985
Protoss_Robotics_Facility 1 10713
11352
