Protoss_Nexus 2 10916
Protoss_Gateway 3 6778
Protoss_Assimilator 1 5007
Protoss_Cybernetics_Core 1 5791
Protoss_Dragoon 5 9766
Protoss_Zealot 3 10071
Protoss_Robotics_Facility 1 9438
Protoss_Citadel_of_Adun 1 9738
Protoss_Observatory 1 9553
Protoss_Shuttle 1 10546
Protoss_Forge 1 10881
10916
