Protoss_Gateway 2 6257
Protoss_Assimilator 1 3517
Protoss_Zealot 9 8003
Protoss_Cybernetics_Core 1 7388
Protoss_Dragoon 2 8821
Protoss_Robotics_Facility 1 9787
Protoss_Forge 1 9687
Protoss_Photon_Cannon 1 10865
10865
