Protoss_Gateway 2 9030
Protoss_Zealot 3 5476
Protoss_Assimilator 1 4232
Protoss_Cybernetics_Core 1 5572
Protoss_Dragoon 8 10863
Protoss_Robotics_Facility 1 8573
Protoss_Observatory 1 8790
Protoss_Observer 1 9976
Protoss_Robotics_Support_Bay 1 10075
10863
