Protoss_Gateway 3 8684
Protoss_Assimilator 1 3366
Protoss_Zealot 3 5427
Protoss_Cybernetics_Core 1 4990
Protoss_Dragoon 12 11099
Protoss_Robotics_Facility 1 9203
Protoss_Observatory 1 9645
11099
