Protoss_Gateway 3 9792
Protoss_Zealot 4 6173
Protoss_Assimilator 1 3063
Protoss_Cybernetics_Core 1 3910
Protoss_Robotics_Facility 1 5049
Protoss_Dragoon 5 9315
Protoss_Shuttle 1 6437
Protoss_Robotics_Support_Bay 1 6747
Protoss_Reaver 2 9633
Protoss_Observatory 1 7646
Protoss_Scarab 3 9265
Protoss_Observer 1 9481
9792
