Protoss_Assimilator 1 2723
Protoss_Gateway 1 3752
Protoss_Cybernetics_Core 1 4748
Protoss_Robotics_Facility 1 6223
Protoss_Dragoon 4 11076
Protoss_Shuttle 1 7031
Protoss_Robotics_Support_Bay 1 6376
Protoss_Observatory 1 6532
Protoss_Observer 1 7453
Protoss_Reaver 3 10879
Protoss_Nexus 1 10703
Protoss_Shield_Battery 1 10425
11076
