Protoss_Gateway 5 11109
Protoss_Assimilator 1 3493
Protoss_Cybernetics_Core 1 4684
Protoss_Dragoon 8 10613
Protoss_Robotics_Facility 1 6985
Protoss_Observatory 1 7278
Protoss_Nexus 1 9713
Protoss_Observer 2 9221
11109
