Protoss_Gateway 2 7260
Protoss_Assimilator 1 3219
Protoss_Cybernetics_Core 1 5002
Protoss_Zealot 1 4951
Protoss_Dragoon 11 10777
Protoss_Robotics_Facility 1 9370
Protoss_Robotics_Support_Bay 1 10331
Protoss_Nexus 1 12717
12717
