Protoss_Gateway 2 10909
Protoss_Zealot 3 5471
Protoss_Assimilator 1 4418
Protoss_Cybernetics_Core 1 5487
Protoss_Dragoon 6 11131
Protoss_Robotics_Facility 1 7773
Protoss_Shuttle 1 8656
Protoss_Observatory 1 8053
Protoss_Observer 1 9078
Protoss_Robotics_Support_Bay 1 9157
Protoss_Reaver 1 11076
Protoss_Nexus 1 12610
12610
