Protoss_Gateway 2 5155
Protoss_Assimilator 1 3339
Protoss_Cybernetics_Core 1 4310
Protoss_Zealot 4 6383
Protoss_Dragoon 3 7825
Protoss_Citadel_of_Adun 1 7529
Protoss_Templar_Archives 1 8557
Protoss_Forge 1 8423
Protoss_Dark_Templar 2 9553
Protoss_Photon_Cannon 2 9781
Protoss_Nexus 1 12672
12672
