Protoss_Gateway 2 8219
Protoss_Zealot 3 5701
Protoss_Assimilator 1 3981
Protoss_Cybernetics_Core 1 5475
Protoss_Dragoon 7 10141
Protoss_Citadel_of_Adun 1 8087
Protoss_Robotics_Facility 1 9327
Protoss_Observatory 1 9582
Protoss_Observer 1 10373
Protoss_Nexus 1 12545
12545
