Protoss_Assimilator 1 2856
Protoss_Gateway 1 3708
Protoss_Cybernetics_Core 1 4901
Protoss_Robotics_Facility 1 6373
Protoss_Dragoon 4 10603
Protoss_Robotics_Support_Bay 1 6483
Protoss_Shuttle 4 11271
Protoss_Reaver 1 8551
11271
