Protoss_Gateway 2 3922
Protoss_Zealot 11 8669
Protoss_Nexus 1 7981
Protoss_Assimilator 2 10159
Protoss_Cybernetics_Core 1 8595
Protoss_Shield_Battery 1 8741
Protoss_Dragoon 2 9819
Protoss_Citadel_of_Adun 1 10508
10508
