Protoss_Gateway 4 11350
Protoss_Zealot 10 8066
Protoss_Nexus 1 8993
Protoss_Assimilator 2 9685
Protoss_Cybernetics_Core 1 8475
Protoss_Dragoon 6 11171
Protoss_Robotics_Facility 1 11544
11544
