Protoss_Gateway 3 9059
Protoss_Assimilator 1 3438
Protoss_Zealot 1 3861
Protoss_Cybernetics_Core 1 5261
Protoss_Dragoon 9 10793
Protoss_Nexus 1 9020
Protoss_Robotics_Facility 1 8931
Protoss_Observatory 1 9072
Protoss_Observer 2 10501
Protoss_Citadel_of_Adun 1 10511
10793
