Protoss_Gateway 3 7259
Protoss_Zealot 5 7039
Protoss_Assimilator 2 10913
Protoss_Cybernetics_Core 1 5687
Protoss_Dragoon 6 10695
Protoss_Forge 1 8039
Protoss_Photon_Cannon 2 10187
Protoss_Nexus 1 10915
Protoss_Citadel_of_Adun 1 10046
Protoss_Robotics_Facility 1 11192
Protoss_Templar_Archives 1 11155
11192
