Protoss_Gateway 2 7168
Protoss_Zealot 3 5045
Protoss_Assimilator 1 5330
Protoss_Nexus 1 7355
Protoss_Cybernetics_Core 1 6536
Protoss_Forge 1 6365
Protoss_Dragoon 7 11079
Protoss_Photon_Cannon 3 10780
Protoss_Robotics_Facility 1 10335
Protoss_Observatory 1 10421
Protoss_Citadel_of_Adun 1 11416
11416
