Protoss_Gateway 3 9802
Protoss_Assimilator 1 3298
Protoss_Cybernetics_Core 1 4294
Protoss_Dragoon 8 9961
Protoss_Nexus 1 9558
Protoss_Robotics_Facility 1 9664
Protoss_Robotics_Support_Bay 1 10096
Protoss_Zealot 2 10521
10521
