Protoss_Gateway 4 10292
Protoss_Zealot 5 7159
Protoss_Nexus 1 7676
Protoss_Assimilator 2 8703
Protoss_Cybernetics_Core 1 7238
Protoss_Dragoon 5 10593
Protoss_Forge 1 8379
Protoss_Robotics_Facility 1 10362
Protoss_Photon_Cannon 1 10705
Protoss_Shuttle 1 11173
11173
