Protoss_Gateway 3 9912
Protoss_Assimilator 1 3547
Protoss_Zealot 2 5099
Protoss_Cybernetics_Core 1 5426
Protoss_Dragoon 10 10969
Protoss_Robotics_Facility 1 9264
Protoss_Shuttle 1 10083
Protoss_Robotics_Support_Bay 1 9789
Protoss_Observatory 1 9907
Protoss_Reaver 1 11289
11289
