Protoss_Gateway 2 3943
Protoss_Zealot 5 5526
Protoss_Assimilator 1 4778
Protoss_Cybernetics_Core 1 5643
Protoss_Dragoon 9 11118
Protoss_Forge 1 7852
Protoss_Nexus 1 11148
Protoss_Photon_Cannon 2 10023
11148
