Protoss_Gateway 3 10060
Protoss_Assimilator 1 3288
Protoss_Cybernetics_Core 1 4535
Protoss_Dragoon 12 11191
Protoss_Robotics_Facility 1 7898
Protoss_Nexus 1 10203
Protoss_Observatory 1 8180
Protoss_Observer 2 9713
11191
