Protoss_Gateway 4 9877
Protoss_Zealot 5 8015
Protoss_Nexus 2 12531
Protoss_Assimilator 2 7853
Protoss_Cybernetics_Core 1 7204
Protoss_Citadel_of_Adun 1 8305
Protoss_Dragoon 1 8165
Protoss_Templar_Archives 1 9297
Protoss_Robotics_Facility 1 10078
Protoss_Forge 1 9699
Protoss_Dark_Templar 2 10093
Protoss_Observatory 1 10191
Protoss_Photon_Cannon 2 11164
Protoss_High_Templar 2 10949
12531
