Protoss_Gateway 2 6666
Protoss_Assimilator 1 3304
Protoss_Zealot 3 5101
Protoss_Cybernetics_Core 1 5241
Protoss_Dragoon 6 8471
Protoss_Citadel_of_Adun 1 9071
Protoss_Robotics_Facility 1 10320
Protoss_Templar_Archives 1 10055
Protoss_Shuttle 1 11119
Protoss_Dark_Templar 2 10981
Protoss_Observatory 1 10699
11119
