Protoss_Gateway 4 11185
Protoss_Zealot 5 7173
Protoss_Nexus 1 7750
Protoss_Assimilator 2 7625
Protoss_Cybernetics_Core 1 6971
Protoss_Dragoon 6 10715
Protoss_Citadel_of_Adun 1 8945
Protoss_Robotics_Facility 1 9922
Protoss_Forge 1 9730
Protoss_Templar_Archives 1 10425
Protoss_Observatory 1 10176
Protoss_Photon_Cannon 1 11041
11185
