Protoss_Gateway 3 11184
Protoss_Zealot 5 7489
Protoss_Nexus 1 7909
Protoss_Assimilator 2 7117
Protoss_Cybernetics_Core 1 7251
Protoss_Citadel_of_Adun 1 8655
Protoss_Robotics_Facility 1 9786
Protoss_Dragoon 4 10609
Protoss_Templar_Archives 1 9937
Protoss_Forge 1 10089
Protoss_Observatory 1 9973
Protoss_Photon_Cannon 1 11079
Protoss_Observer 1 10873
11184
