Protoss_Gateway 2 7394
Protoss_Assimilator 1 3171
Protoss_Cybernetics_Core 1 4308
Protoss_Dragoon 9 10971
Protoss_Robotics_Facility 1 6978
Protoss_Shuttle 1 8531
Protoss_Robotics_Support_Bay 1 7839
Protoss_Reaver 2 10848
Protoss_Nexus 1 12203
12203
