Protoss_Gateway 4 11058
Protoss_Zealot 8 7641
Protoss_Nexus 1 8585
Protoss_Assimilator 2 9860
Protoss_Forge 1 7465
Protoss_Cybernetics_Core 1 8628
Protoss_Photon_Cannon 3 11183
Protoss_Dragoon 4 11036
11183
