Protoss_Gateway 2 3971
Protoss_Zealot 11 9507
Protoss_Nexus 2 12145
Protoss_Assimilator 2 8195
Protoss_Cybernetics_Core 1 7200
Protoss_Dragoon 2 7963
Protoss_Citadel_of_Adun 1 8594
Protoss_Templar_Archives 1 9707
Protoss_Forge 1 9239
Protoss_Dark_Templar 2 10701
Protoss_Photon_Cannon 2 11087
12145
