Protoss_Gateway 2 3987
Protoss_Zealot 14 10391
Protoss_Nexus 1 8081
Protoss_Assimilator 1 6808
Protoss_Cybernetics_Core 1 7863
Protoss_Citadel_of_Adun 1 9051
Protoss_Templar_Archives 1 10255
Protoss_Forge 1 9839
Protoss_Shield_Battery 1 10075
10391
