Protoss_Gateway 4 11186
Protoss_Zealot 10 8041
Protoss_Nexus 1 7677
Protoss_Assimilator 1 6260
Protoss_Forge 1 7049
Protoss_Cybernetics_Core 1 8254
Protoss_Photon_Cannon 4 11170
Protoss_Dragoon 6 11081
11186
