Protoss_Gateway 4 9637
Protoss_Zealot 13 10463
Protoss_Nexus 1 7063
Protoss_Assimilator 2 7558
Protoss_Cybernetics_Core 1 7490
Protoss_Dragoon 2 8363
Protoss_Citadel_of_Adun 1 8989
Protoss_Robotics_Facility 1 10734
Protoss_Forge 1 10629
10734
