Protoss_Assimilator 1 2618
Protoss_Gateway 1 3691
Protoss_Cybernetics_Core 1 4769
Protoss_Stargate 1 6021
Protoss_Robotics_Facility 1 6711
Protoss_Corsair 3 7640
Protoss_Shuttle 1 7536
Protoss_Forge 1 7897
Protoss_Dragoon 4 10851
Protoss_Photon_Cannon 2 10524
Protoss_Fleet_Beacon 1 10544
10851
