Protoss_Gateway 2 5921
Protoss_Assimilator 1 3459
Protoss_Zealot 2 4916
Protoss_Cybernetics_Core 1 5255
Protoss_Dragoon 6 11016
Protoss_Citadel_of_Adun 1 6358
Protoss_Templar_Archives 1 7428
Protoss_Dark_Templar 3 8938
Protoss_Forge 1 8343
Protoss_Nexus 1 11588
Protoss_Photon_Cannon 2 10611
11588
