Protoss_Gateway 2 8947
Protoss_Assimilator 1 3173
Protoss_Cybernetics_Core 1 4352
Protoss_Dragoon 8 10425
Protoss_Robotics_Facility 1 7135
Protoss_Observatory 1 7334
Protoss_Shuttle 1 8217
Protoss_Observer 2 9241
Protoss_Robotics_Support_Bay 1 8849
Protoss_Reaver 1 10683
10683
