Protoss_Gateway 3 8215
Protoss_Zealot 16 10939
Protoss_Nexus 1 8981
Protoss_Assimilator 2 9635
Protoss_Cybernetics_Core 1 8788
Protoss_Dragoon 2 9617
Protoss_Citadel_of_Adun 1 10349
Protoss_Forge 1 10334
Protoss_Robotics_Facility 1 11646
11646
