Protoss_Gateway 3 11193
Protoss_Zealot 5 8595
Protoss_Nexus 1 6993
Protoss_Forge 1 5831
Protoss_Assimilator 2 7431
Protoss_Cybernetics_Core 1 7129
Protoss_Photon_Cannon 3 9416
Protoss_Dragoon 5 10899
Protoss_Robotics_Facility 1 9383
Protoss_Observatory 1 9469
Protoss_Observer 1 10249
11193
