Protoss_Gateway 3 10214
Protoss_Zealot 6 7299
Protoss_Nexus 1 7617
Protoss_Assimilator 2 8338
Protoss_Cybernetics_Core 1 7493
Protoss_Dragoon 2 8361
Protoss_Citadel_of_Adun 1 8998
Protoss_Forge 1 9522
Protoss_Templar_Archives 2 10246
Protoss_Robotics_Facility 1 10859
Protoss_Photon_Cannon 2 10730
10859
