Protoss_Gateway 4 10934
Protoss_Zealot 2 4587
Protoss_Assimilator 1 3934
Protoss_Cybernetics_Core 1 5176
Protoss_Dragoon 11 10955
Protoss_Nexus 1 9057
Protoss_Robotics_Facility 1 9315
Protoss_Robotics_Support_Bay 1 9460
Protoss_Shuttle 1 10555
10955
