Protoss_Gateway 3 9207
Protoss_Assimilator 1 3373
Protoss_Zealot 2 4915
Protoss_Cybernetics_Core 1 5101
Protoss_Dragoon 11 10811
Protoss_Robotics_Facility 1 7599
Protoss_Observatory 1 7771
Protoss_Observer 3 9823
Protoss_Nexus 1 12095
12095
