Protoss_Gateway 2 5183
Protoss_Assimilator 1 3598
Protoss_Zealot 9 7681
Protoss_Cybernetics_Core 1 7259
Protoss_Dragoon 8 10426
Protoss_Robotics_Facility 1 10542
Protoss_Shuttle 1 11406
11406
