Protoss_Gateway 3 11037
Protoss_Assimilator 1 3171
Protoss_Cybernetics_Core 1 4348
Protoss_Zealot 1 4113
Protoss_Dragoon 8 11069
Protoss_Citadel_of_Adun 1 6354
Protoss_Robotics_Facility 1 6976
Protoss_Templar_Archives 1 7439
Protoss_Shuttle 1 7879
Protoss_Dark_Templar 2 8203
Protoss_Nexus 1 11803
11803
