Protoss_Gateway 3 10818
Protoss_Assimilator 1 3382
Protoss_Zealot 2 5011
Protoss_Cybernetics_Core 1 5179
Protoss_Dragoon 8 10753
Protoss_Robotics_Facility 1 7867
Protoss_Robotics_Support_Bay 1 7965
Protoss_Observatory 1 8169
Protoss_Observer 1 8951
Protoss_Nexus 1 11353
Protoss_Reaver 1 10399
11353
