Protoss_Gateway 2 8390
Protoss_Assimilator 1 3221
Protoss_Zealot 3 5047
Protoss_Cybernetics_Core 1 5187
Protoss_Dragoon 9 10189
Protoss_Robotics_Facility 1 8726
Protoss_Shuttle 1 9561
Protoss_Observatory 1 8908
Protoss_Robotics_Support_Bay 1 9499
Protoss_Observer 1 9983
Protoss_Reaver 1 11305
11305
