Protoss_Gateway 4 10541
Protoss_Zealot 11 10223
Protoss_Nexus 1 7747
Protoss_Assimilator 2 8954
Protoss_Cybernetics_Core 1 7680
Protoss_Citadel_of_Adun 1 8709
Protoss_Dragoon 2 8937
Protoss_Templar_Archives 1 9985
Protoss_Forge 1 9975
Protoss_Dark_Templar 2 10787
Protoss_Photon_Cannon 2 11074
11074
