Protoss_Gateway 2 8611
Protoss_Zealot 2 4843
Protoss_Assimilator 1 3993
Protoss_Cybernetics_Core 1 4997
Protoss_Dragoon 10 11113
Protoss_Robotics_Facility 1 8063
Protoss_Shuttle 1 8861
Protoss_Robotics_Support_Bay 1 8227
Protoss_Reaver 2 11341
Protoss_Observatory 1 10097
11341
