Protoss_Gateway 2 3839
Protoss_Zealot 9 9247
Protoss_Assimilator 1 4690
Protoss_Cybernetics_Core 1 5574
Protoss_Dragoon 4 7113
Protoss_Citadel_of_Adun 1 8759
Protoss_Templar_Archives 1 9869
Protoss_Forge 1 9677
Protoss_Robotics_Facility 1 11323
Protoss_Photon_Cannon 2 10741
Protoss_Dark_Templar 2 11159
11323
