Protoss_Gateway 4 11411
Protoss_Assimilator 1 3411
Protoss_Cybernetics_Core 1 4481
Protoss_Dragoon 7 10635
Protoss_Zealot 2 10761
Protoss_Nexus 1 8859
Protoss_Robotics_Facility 1 8136
Protoss_Observatory 1 8329
Protoss_Robotics_Support_Bay 1 8376
Protoss_Observer 3 10491
11411
