Protoss_Gateway 2 3875
Protoss_Zealot 7 7433
Protoss_Nexus 1 7719
Protoss_Assimilator 2 8807
Protoss_Cybernetics_Core 1 7660
Protoss_Citadel_of_Adun 1 8774
Protoss_Dragoon 2 8737
Protoss_Templar_Archives 1 9775
Protoss_Forge 1 9740
Protoss_Dark_Templar 2 10521
Protoss_Photon_Cannon 2 11073
11073
