Protoss_Gateway 2 3901
Protoss_Zealot 9 7803
Protoss_Nexus 1 8550
Protoss_Assimilator 2 9125
Protoss_Cybernetics_Core 1 8638
Protoss_Dragoon 2 9619
Protoss_Citadel_of_Adun 1 10388
Protoss_Forge 1 9913
Protoss_Photon_Cannon 1 11040
Protoss_Templar_Archives 1 11373
11373
