Protoss_Gateway 4 10658
Protoss_Zealot 5 9961
Protoss_Nexus 1 7057
Protoss_Assimilator 1 5443
Protoss_Cybernetics_Core 1 6361
Protoss_Dragoon 7 10823
Protoss_Robotics_Facility 1 10131
Protoss_Citadel_of_Adun 1 11057
Protoss_Shuttle 1 11363
11363
