Protoss_Gateway 2 8431
Protoss_Assimilator 1 3365
Protoss_Cybernetics_Core 1 4397
Protoss_Zealot 1 4171
Protoss_Dragoon 4 7689
Protoss_Citadel_of_Adun 1 6974
Protoss_Templar_Archives 1 8183
Protoss_Dark_Templar 4 9941
Protoss_Robotics_Facility 1 11268
11268
