Protoss_Gateway 2 4099
Protoss_Zealot 10 9545
Protoss_Nexus 1 8084
Protoss_Assimilator 2 8657
Protoss_Cybernetics_Core 1 8023
Protoss_Citadel_of_Adun 1 9028
Protoss_Robotics_Facility 1 10453
Protoss_Templar_Archives 1 10502
Protoss_Forge 1 10716
Protoss_Dragoon 2 11059
Protoss_Observatory 1 10588
11059
