Protoss_Gateway 4 11339
Protoss_Assimilator 2 9587
Protoss_Cybernetics_Core 1 4228
Protoss_Zealot 1 4049
Protoss_Dragoon 12 10859
Protoss_Nexus 1 8521
Protoss_Robotics_Facility 1 9633
Protoss_Observatory 1 9741
Protoss_Observer 1 10513
11339
