Protoss_Gateway 1 3293
Protoss_Assimilator 1 3317
Protoss_Cybernetics_Core 1 4389
Protoss_Zealot 1 4105
Protoss_Dragoon 7 10157
Protoss_Robotics_Facility 1 7103
Protoss_Robotics_Support_Bay 1 7259
Protoss_Observatory 1 7276
Protoss_Reaver 3 11587
Protoss_Nexus 1 10766
Protoss_Observer 1 9085
11587
