Protoss_Gateway 4 10184
Protoss_Zealot 11 9673
Protoss_Nexus 1 7563
Protoss_Assimilator 2 8584
Protoss_Cybernetics_Core 1 8849
Protoss_Robotics_Facility 1 10611
Protoss_Citadel_of_Adun 1 10248
Protoss_Dragoon 3 10589
10611
