Protoss_Gateway 2 7547
Protoss_Zealot 3 5125
Protoss_Assimilator 1 4320
Protoss_Cybernetics_Core 1 5265
Protoss_Dragoon 9 11083
Protoss_Robotics_Facility 1 8908
Protoss_Forge 1 8668
Protoss_Observatory 1 9044
Protoss_Photon_Cannon 5 9991
Protoss_Observer 2 10651
11083
