Protoss_Gateway 2 8055
Protoss_Assimilator 1 3421
Protoss_Zealot 2 4609
Protoss_Cybernetics_Core 1 5270
Protoss_Dragoon 10 11005
Protoss_Robotics_Facility 1 7809
Protoss_Observatory 1 7947
Protoss_Observer 2 9347
Protoss_Robotics_Support_Bay 1 8911
Protoss_Shuttle 1 10009
Protoss_Reaver 1 11195
11195
