Protoss_Gateway 2 3903
Protoss_Zealot 7 8729
Protoss_Assimilator 2 7348
Protoss_Nexus 1 7849
Protoss_Cybernetics_Core 1 6991
Protoss_Citadel_of_Adun 1 8069
Protoss_Dragoon 2 7995
Protoss_Templar_Archives 1 9107
Protoss_Robotics_Facility 1 10047
Protoss_High_Templar 4 10991
Protoss_Forge 1 9770
Protoss_Shuttle 1 10869
Protoss_Photon_Cannon 2 10936
10991
