Protoss_Gateway 4 11331
Protoss_Assimilator 1 3886
Protoss_Cybernetics_Core 1 5160
Protoss_Zealot 2 5229
Protoss_Dragoon 9 9931
Protoss_Robotics_Facility 1 8336
Protoss_Observatory 1 8485
Protoss_Observer 2 10097
Protoss_Nexus 1 11763
11763
