Protoss_Gateway 4 11335
Protoss_Assimilator 1 3277
Protoss_Cybernetics_Core 1 4305
Protoss_Dragoon 14 11021
Protoss_Robotics_Facility 1 8087
Protoss_Observatory 1 8228
Protoss_Observer 2 9615
11335
