Protoss_Gateway 3 9874
Protoss_Zealot 3 5327
Protoss_Assimilator 1 4061
Protoss_Cybernetics_Core 1 5015
Protoss_Dragoon 10 11135
Protoss_Nexus 1 9823
Protoss_Robotics_Facility 1 9227
Protoss_Observatory 1 9346
Protoss_Observer 2 10851
11135
