Protoss_Gateway 3 10663
Protoss_Assimilator 1 3456
Protoss_Zealot 1 3851
Protoss_Cybernetics_Core 1 4609
Protoss_Dragoon 11 11029
Protoss_Nexus 1 10535
Protoss_Robotics_Facility 1 10517
Protoss_Observatory 1 10696
11029
