Protoss_Gateway 3 9935
Protoss_Assimilator 1 3273
Protoss_Cybernetics_Core 1 4379
Protoss_Zealot 1 4221
Protoss_Dragoon 9 11141
Protoss_Nexus 1 10132
Protoss_Robotics_Facility 1 10713
11141
