Protoss_Gateway 3 9339
Protoss_Assimilator 2 10033
Protoss_Cybernetics_Core 1 4374
Protoss_Zealot 4 10855
Protoss_Dragoon 8 10101
Protoss_Nexus 1 9250
Protoss_Robotics_Facility 1 8841
Protoss_Observatory 1 8998
Protoss_Observer 2 10421
Protoss_Citadel_of_Adun 1 10682
10855
