Protoss_Gateway 2 3780
Protoss_Zealot 6 6505
Protoss_Assimilator 1 4988
Protoss_Cybernetics_Core 1 6163
Protoss_Dragoon 7 11081
Protoss_Nexus 2 11541
Protoss_Robotics_Facility 1 10867
11541
