Protoss_Gateway 2 3863
Protoss_Zealot 19 10561
Protoss_Nexus 1 8482
Protoss_Assimilator 2 9626
Protoss_Cybernetics_Core 1 8379
Protoss_Citadel_of_Adun 1 9921
Protoss_Templar_Archives 1 10984
10984
