Protoss_Gateway 2 3827
Protoss_Zealot 5 5849
Protoss_Assimilator 1 4576
Protoss_Cybernetics_Core 1 5843
Protoss_Dragoon 9 11009
Protoss_Robotics_Facility 1 9601
Protoss_Nexus 1 11526
Protoss_Observatory 1 9699
Protoss_Shuttle 1 10513
Protoss_Robotics_Support_Bay 1 10301
11526
