Protoss_Gateway 2 3685
Protoss_Zealot 12 9301
Protoss_Shield_Battery 2 6305
Protoss_Forge 1 6183
Protoss_Photon_Cannon 4 9092
Protoss_Assimilator 1 8702
Protoss_Cybernetics_Core 1 10174
Protoss_Stargate 1 11553
11553
