Protoss_Gateway 2 9327
Protoss_Assimilator 2 10935
Protoss_Zealot 1 3735
Protoss_Cybernetics_Core 1 4513
Protoss_Dragoon 5 10945
Protoss_Citadel_of_Adun 1 6025
Protoss_Templar_Archives 1 7107
Protoss_Dark_Templar 2 8619
Protoss_Nexus 1 10097
Protoss_Robotics_Facility 1 10347
Protoss_Observatory 1 10497
10945
