Protoss_Gateway 4 11071
Protoss_Zealot 6 8265
Protoss_Nexus 1 7836
Protoss_Assimilator 2 8601
Protoss_Cybernetics_Core 1 7034
Protoss_Dragoon 1 7993
Protoss_Citadel_of_Adun 1 8475
Protoss_Forge 1 8699
Protoss_Templar_Archives 1 9573
Protoss_Photon_Cannon 1 10201
Protoss_Dark_Templar 2 10319
Protoss_Robotics_Facility 1 11378
11378
