Protoss_Gateway 3 10729
Protoss_Zealot 11 10451
Protoss_Assimilator 2 7697
Protoss_Cybernetics_Core 1 6999
Protoss_Nexus 1 8737
Protoss_Citadel_of_Adun 1 8338
Protoss_Dragoon 2 8541
Protoss_Robotics_Facility 1 10204
Protoss_Templar_Archives 1 11313
11313
