Protoss_Gateway 2 4965
Protoss_Assimilator 1 3203
Protoss_Cybernetics_Core 1 4351
Protoss_Dragoon 9 8647
Protoss_Robotics_Facility 1 7871
Protoss_Observatory 1 8017
Protoss_Observer 1 8801
Protoss_Zealot 4 10055
Protoss_Shuttle 1 9887
Protoss_Robotics_Support_Bay 1 9469
Protoss_Reaver 1 11079
11079
