Protoss_Gateway 2 3876
Protoss_Zealot 4 6743
Protoss_Nexus 1 6947
Protoss_Assimilator 2 8108
Protoss_Cybernetics_Core 1 6786
Protoss_Dragoon 2 7705
Protoss_Citadel_of_Adun 1 8364
Protoss_Forge 1 8237
Protoss_Templar_Archives 1 9463
Protoss_Robotics_Facility 1 10042
Protoss_Photon_Cannon 5 10798
Protoss_Observatory 1 10488
Protoss_Dark_Templar 2 10995
10995
