Protoss_Gateway 3 11394
Protoss_Assimilator 1 3767
Protoss_Zealot 3 5211
Protoss_Cybernetics_Core 1 4991
Protoss_Dragoon 10 10779
Protoss_Nexus 1 10573
Protoss_Robotics_Facility 1 10043
Protoss_Shuttle 1 10903
Protoss_Observatory 1 10344
11394
