Protoss_Gateway 3 11409
Protoss_Zealot 3 5723
Protoss_Assimilator 2 10498
Protoss_Cybernetics_Core 1 5006
Protoss_Citadel_of_Adun 1 6058
Protoss_Dragoon 1 6565
Protoss_Templar_Archives 1 7062
Protoss_Forge 1 6744
Protoss_Dark_Templar 2 8819
Protoss_Nexus 1 9747
Protoss_Photon_Cannon 6 10967
Protoss_High_Templar 2 10741
11409
