Protoss_Gateway 4 6906
Protoss_Zealot 12 10721
Protoss_Shield_Battery 1 4654
Protoss_Forge 1 7352
Protoss_Assimilator 1 7889
Protoss_Photon_Cannon 4 10648
Protoss_Cybernetics_Core 1 9451
Protoss_Robotics_Facility 2 11635
11635
