Protoss_Gateway 2 3999
Protoss_Zealot 12 8811
Protoss_Nexus 1 8421
Protoss_Assimilator 1 6776
Protoss_Cybernetics_Core 1 8623
Protoss_Forge 1 8440
Protoss_Photon_Cannon 5 11101
Protoss_Dragoon 4 10809
Protoss_Citadel_of_Adun 1 10735
11101
