Protoss_Gateway 2 6153
Protoss_Assimilator 1 3225
Protoss_Zealot 3 5425
Protoss_Cybernetics_Core 1 5485
Protoss_Dragoon 10 11093
Protoss_Robotics_Facility 1 9493
Protoss_Nexus 1 11993
Protoss_Observatory 1 10044
Protoss_Citadel_of_Adun 1 11373
Protoss_Observer 1 10899
11993
