Protoss_Gateway 2 3971
Protoss_Zealot 7 8411
Protoss_Nexus 1 7723
Protoss_Assimilator 2 9356
Protoss_Forge 1 6821
Protoss_Photon_Cannon 5 9952
Protoss_Cybernetics_Core 1 8643
Protoss_Robotics_Facility 1 10139
Protoss_Dragoon 4 11023
Protoss_Observatory 1 10301
11023
