Protoss_Gateway 4 10358
Protoss_Assimilator 1 3658
Protoss_Zealot 5 10671
Protoss_Cybernetics_Core 1 5272
Protoss_Dragoon 12 11109
Protoss_Robotics_Facility 1 8695
Protoss_Observatory 1 8777
Protoss_Observer 2 10363
11109
