Protoss_Gateway 2 5421
Protoss_Zealot 1 3787
Protoss_Assimilator 1 3937
Protoss_Cybernetics_Core 1 5019
Protoss_Dragoon 12 10989
Protoss_Robotics_Facility 1 9215
Protoss_Shuttle 1 10297
Protoss_Observatory 1 9650
Protoss_Nexus 1 12316
Protoss_Observer 1 10473
Protoss_Robotics_Support_Bay 1 10377
12316
