Protoss_Gateway 2 3935
Protoss_Zealot 15 10679
Protoss_Nexus 1 7669
Protoss_Assimilator 2 10416
Protoss_Cybernetics_Core 1 7696
Protoss_Dragoon 2 8931
Protoss_Citadel_of_Adun 1 10136
Protoss_Forge 1 10007
Protoss_Templar_Archives 1 11250
11250
