Protoss_Gateway 2 3887
Protoss_Zealot 19 10215
Protoss_Nexus 1 8887
Protoss_Assimilator 2 9809
Protoss_Cybernetics_Core 1 8855
Protoss_Citadel_of_Adun 1 10150
Protoss_Robotics_Facility 1 11561
Protoss_Forge 1 10943
11561
