Protoss_Gateway 2 10008
Protoss_Assimilator 1 3835
Protoss_Zealot 2 4879
Protoss_Cybernetics_Core 1 5059
Protoss_Dragoon 8 10919
Protoss_Nexus 1 8581
Protoss_Robotics_Facility 1 8645
Protoss_Observatory 1 8828
Protoss_Observer 1 9629
Protoss_Robotics_Support_Bay 1 9449
Protoss_Reaver 1 11319
11319
