Protoss_Gateway 2 8878
Protoss_Assimilator 1 3243
Protoss_Cybernetics_Core 1 4378
Protoss_Dragoon 6 10921
Protoss_Citadel_of_Adun 1 6475
Protoss_Templar_Archives 1 7567
Protoss_Nexus 2 11831
Protoss_Dark_Templar 2 9091
Protoss_High_Templar 2 9843
Protoss_Forge 1 10466
11831
