Protoss_Gateway 3 9740
Protoss_Assimilator 2 10212
Protoss_Zealot 3 5193
Protoss_Cybernetics_Core 1 5305
Protoss_Dragoon 8 10815
Protoss_Nexus 1 9445
Protoss_Robotics_Facility 1 9059
Protoss_Observatory 1 9332
Protoss_Citadel_of_Adun 1 10466
Protoss_Observer 2 10703
10815
