Protoss_Gateway 3 11130
Protoss_Zealot 3 5577
Protoss_Assimilator 1 4104
Protoss_Cybernetics_Core 1 5511
Protoss_Dragoon 6 10963
Protoss_Nexus 1 9811
Protoss_Robotics_Facility 1 9088
Protoss_Observatory 1 9229
Protoss_Observer 1 10163
11130
