Protoss_Gateway 2 6655
Protoss_Zealot 2 4631
Protoss_Assimilator 2 10690
Protoss_Cybernetics_Core 1 5936
Protoss_Dragoon 7 10077
Protoss_Nexus 1 10257
Protoss_Robotics_Facility 1 9722
Protoss_Observatory 1 9904
Protoss_Observer 1 10753
Protoss_Citadel_of_Adun 1 11437
11437
