Protoss_Gateway 2 5864
Protoss_Assimilator 1 3186
Protoss_Zealot 2 4399
Protoss_Cybernetics_Core 1 5445
Protoss_Dragoon 10 10075
Protoss_Robotics_Facility 1 8697
Protoss_Observatory 1 8792
Protoss_Observer 2 10207
Protoss_Robotics_Support_Bay 1 9936
Protoss_Nexus 1 12472
Protoss_Reaver 1 11529
12472
