Protoss_Gateway 4 11306
Protoss_Zealot 3 5091
Protoss_Assimilator 1 4024
Protoss_Cybernetics_Core 1 5259
Protoss_Dragoon 8 10625
Protoss_Nexus 1 9189
Protoss_Robotics_Facility 1 8995
Protoss_Observatory 1 9102
Protoss_Observer 1 10199
Protoss_Shuttle 1 11389
11389
