Protoss_Gateway 1 3255
Protoss_Assimilator 1 3175
Protoss_Cybernetics_Core 1 4356
Protoss_Dragoon 6 11141
Protoss_Robotics_Facility 1 7392
Protoss_Shuttle 1 8191
Protoss_Robotics_Support_Bay 1 7585
Protoss_Reaver 1 9369
Protoss_Observatory 1 9483
Protoss_Nexus 1 11939
Protoss_Observer 1 10515
11939
