Protoss_Gateway 2 7778
Protoss_Zealot 3 4991
Protoss_Assimilator 2 10424
Protoss_Cybernetics_Core 1 5493
Protoss_Dragoon 8 10177
Protoss_Nexus 1 10126
Protoss_Robotics_Facility 1 9739
Protoss_Observatory 1 9964
Protoss_Citadel_of_Adun 1 11158
11158
