Protoss_Gateway 3 10913
Protoss_Assimilator 1 3151
Protoss_Cybernetics_Core 1 4267
Protoss_Zealot 2 7897
Protoss_Dragoon 8 10555
Protoss_Citadel_of_Adun 1 6896
Protoss_Templar_Archives 1 7981
Protoss_Dark_Templar 2 8739
Protoss_Nexus 1 11090
Protoss_Robotics_Facility 1 11724
11724
