Protoss_Gateway 6 11378
Protoss_Assimilator 1 3345
Protoss_Cybernetics_Core 1 4399
Protoss_Dragoon 7 10805
Protoss_Nexus 2 11982
Protoss_Robotics_Facility 1 8117
Protoss_Observatory 1 8220
Protoss_Observer 3 10241
Protoss_Citadel_of_Adun 1 11429
11982
