Protoss_Gateway 2 3973
Protoss_Zealot 5 8909
Protoss_Assimilator 1 4537
Protoss_Cybernetics_Core 1 5839
Protoss_Dragoon 10 11041
Protoss_Robotics_Facility 1 8333
Protoss_Observatory 1 8753
Protoss_Nexus 1 11272
Protoss_Observer 2 10599
Protoss_Forge 1 10171
Protoss_Photon_Cannon 1 11124
11272
