Protoss_Gateway 2 10252
Protoss_Assimilator 2 10378
Protoss_Zealot 2 4893
Protoss_Cybernetics_Core 1 5107
Protoss_Dragoon 6 11011
Protoss_Citadel_of_Adun 1 6537
Protoss_Templar_Archives 1 7557
Protoss_Nexus 1 9867
Protoss_Dark_Templar 2 9205
Protoss_Robotics_Facility 1 10470
11011
