Protoss_Gateway 2 8852
Protoss_Zealot 2 4589
Protoss_Assimilator 1 4049
Protoss_Cybernetics_Core 1 5385
Protoss_Dragoon 9 11123
Protoss_Nexus 2 12449
Protoss_Robotics_Facility 1 8619
Protoss_Observatory 1 8716
Protoss_Observer 1 9503
Protoss_Robotics_Support_Bay 1 9355
Protoss_Reaver 1 10991
12449
