Protoss_Gateway 2 5608
Protoss_Zealot 1 3793
Protoss_Assimilator 1 3943
Protoss_Cybernetics_Core 1 5007
Protoss_Dragoon 10 10479
Protoss_Robotics_Facility 1 9000
Protoss_Shuttle 1 9867
Protoss_Observatory 1 9214
Protoss_Robotics_Support_Bay 1 9956
Protoss_Observer 1 10289
10479
