Protoss_Gateway 2 6048
Protoss_Assimilator 2 3657
Protoss_Cybernetics_Core 1 4783
Protoss_Zealot 1 4519
Protoss_Dragoon 9 9989
Protoss_Citadel_of_Adun 1 8843
Protoss_Templar_Archives 1 10434
Protoss_Forge 1 9957
Protoss_Nexus 1 12557
12557
