Protoss_Gateway 2 7655
Protoss_Zealot 2 4421
Protoss_Assimilator 1 3982
Protoss_Cybernetics_Core 1 5415
Protoss_Citadel_of_Adun 1 6428
Protoss_Dragoon 5 10747
Protoss_Templar_Archives 1 7432
Protoss_Forge 1 7606
Protoss_Dark_Templar 4 9165
Protoss_Photon_Cannon 3 10561
Protoss_Nexus 1 12129
12129
