Protoss_Gateway 2 4571
Protoss_Zealot 4 6369
Protoss_Cybernetics_Core 1 5633
Protoss_Assimilator 1 5464
Protoss_Dragoon 12 11081
Protoss_Nexus 1 12326
Protoss_Robotics_Facility 1 11406
12326
