Protoss_Gateway 1 3333
Protoss_Assimilator 1 3231
Protoss_Cybernetics_Core 1 4397
Protoss_Robotics_Facility 2 10846
Protoss_Zealot 2 5833
Protoss_Shuttle 2 10367
Protoss_Dragoon 5 10385
Protoss_Robotics_Support_Bay 1 6582
Protoss_Reaver 2 9509
Protoss_Scarab 4 8734
Protoss_Observatory 1 10320
10846
