Protoss_Gateway 1 3449
Protoss_Assimilator 1 3324
Protoss_Cybernetics_Core 1 4479
Protoss_Robotics_Facility 1 6351
Protoss_Dragoon 5 10373
Protoss_Shuttle 1 7211
Protoss_Observatory 1 6565
Protoss_Observer 2 8235
Protoss_Nexus 1 10621
Protoss_Zealot 1 9003
10621
