Protoss_Gateway 1 3311
Protoss_Zealot 2 4887
Protoss_Assimilator 1 4252
Protoss_Cybernetics_Core 1 5049
Protoss_Dragoon 7 10929
Protoss_Robotics_Facility 1 7681
Protoss_Shuttle 1 8481
Protoss_Observatory 1 8372
Protoss_Observer 1 9145
Protoss_Robotics_Support_Bay 1 9273
Protoss_Nexus 2 12382
Protoss_Reaver 1 11583
12382
