Protoss_Gateway 3 10269
Protoss_Zealot 2 5141
Protoss_Assimilator 1 4253
Protoss_Cybernetics_Core 1 5535
Protoss_Dragoon 8 11106
Protoss_Robotics_Facility 1 7218
Protoss_Shuttle 1 8031
Protoss_Observatory 1 7481
Protoss_Robotics_Support_Bay 1 8050
Protoss_Observer 1 8461
Protoss_Reaver 2 10846
11106
