Protoss_Gateway 3 9698
Protoss_Assimilator 1 3534
Protoss_Cybernetics_Core 1 4843
Protoss_Dragoon 10 10751
Protoss_Robotics_Facility 1 7539
Protoss_Forge 1 7624
Protoss_Observatory 1 7793
Protoss_Observer 3 10103
10751
