Protoss_Gateway 2 10136
Protoss_Assimilator 1 3428
Protoss_Cybernetics_Core 1 4559
Protoss_Zealot 3 10771
Protoss_Dragoon 2 6651
Protoss_Robotics_Facility 1 7819
Protoss_Citadel_of_Adun 1 8141
Protoss_Observatory 1 7952
Protoss_Forge 1 8217
Protoss_Templar_Archives 1 9139
Protoss_Observer 1 8906
Protoss_Photon_Cannon 1 10003
Protoss_High_Templar 2 10883
Protoss_Shuttle 1 10596
10883
