Protoss_Gateway 2 5601
Protoss_Assimilator 1 3283
Protoss_Zealot 1 3863
Protoss_Cybernetics_Core 1 5187
Protoss_Dragoon 9 11029
Protoss_Citadel_of_Adun 1 7292
Protoss_Templar_Archives 1 8305
Protoss_Forge 1 8278
Protoss_Dark_Templar 3 9807
Protoss_Photon_Cannon 1 9422
Protoss_Nexus 1 12409
12409
