Protoss_Assimilator 1 2793
Protoss_Gateway 1 3768
Protoss_Cybernetics_Core 1 4778
Protoss_Robotics_Facility 1 6258
Protoss_Dragoon 4 10296
Protoss_Shuttle 1 7131
Protoss_Robotics_Support_Bay 1 6508
Protoss_Observatory 1 6653
Protoss_Observer 1 7553
Protoss_Reaver 2 10083
Protoss_Scarab 2 9014
Protoss_Nexus 1 12380
12380
