Protoss_Gateway 3 9634
Protoss_Zealot 1 4131
Protoss_Assimilator 1 4308
Protoss_Cybernetics_Core 1 5433
Protoss_Dragoon 11 11161
Protoss_Robotics_Facility 1 9020
Protoss_Observatory 1 9280
Protoss_Observer 2 10658
Protoss_Nexus 1 12236
12236
