Protoss_Gateway 2 3914
Protoss_Zealot 10 7566
Protoss_Shield_Battery 1 5786
Protoss_Nexus 1 11451
Protoss_Assimilator 1 9964
Protoss_Forge 1 10078
Protoss_Photon_Cannon 1 11193
11451
