Protoss_Gateway 3 10417
Protoss_Assimilator 1 3520
Protoss_Zealot 2 4941
Protoss_Cybernetics_Core 1 5165
Protoss_Dragoon 10 10555
Protoss_Nexus 1 10195
Protoss_Robotics_Facility 1 9491
Protoss_Observatory 1 9603
Protoss_Observer 1 10391
10555
