Protoss_Gateway 2 9069
Protoss_Zealot 3 5127
Protoss_Assimilator 2 9789
Protoss_Cybernetics_Core 1 5271
Protoss_Dragoon 8 10443
Protoss_Nexus 1 9066
Protoss_Robotics_Facility 1 8603
Protoss_Observatory 1 8741
Protoss_Observer 2 10113
Protoss_Citadel_of_Adun 1 10145
Protoss_Templar_Archives 1 11186
11186
