Protoss_Gateway 3 9643
Protoss_Assimilator 1 3228
Protoss_Cybernetics_Core 1 4300
Protoss_Zealot 4 6551
Protoss_Robotics_Facility 1 6018
Protoss_Shuttle 1 6826
Protoss_Observatory 1 6854
Protoss_Dragoon 7 10631
Protoss_Observer 3 9670
10631
