Protoss_Gateway 3 9973
Protoss_Assimilator 1 3998
Protoss_Zealot 3 10501
Protoss_Cybernetics_Core 1 5207
Protoss_Dragoon 8 11136
Protoss_Robotics_Facility 1 8046
Protoss_Nexus 1 10348
Protoss_Observatory 1 8329
Protoss_Observer 1 9171
Protoss_Shuttle 1 10831
11136
