Protoss_Gateway 2 9011
Protoss_Assimilator 2 9898
Protoss_Zealot 2 5035
Protoss_Cybernetics_Core 1 5197
Protoss_Dragoon 8 10685
Protoss_Nexus 1 9266
Protoss_Robotics_Facility 1 9223
Protoss_Observatory 1 9325
Protoss_Citadel_of_Adun 1 10319
Protoss_Observer 2 10781
Protoss_Templar_Archives 1 11332
Protoss_Forge 1 10957
11332
