Protoss_Gateway 2 7352
Protoss_Zealot 7 9785
Protoss_Assimilator 1 5265
Protoss_Cybernetics_Core 1 6795
Protoss_Robotics_Facility 1 8303
Protoss_Dragoon 5 10821
Protoss_Shuttle 1 9111
Protoss_Robotics_Support_Bay 1 8447
Protoss_Reaver 1 10253
Protoss_Observatory 1 10288
10821
