Protoss_Gateway 2 7519
Protoss_Assimilator 1 3312
Protoss_Zealot 3 4947
Protoss_Cybernetics_Core 1 5278
Protoss_Dragoon 9 10219
Protoss_Robotics_Facility 1 7691
Protoss_Shuttle 1 8493
Protoss_Observatory 1 8052
Protoss_Robotics_Support_Bay 1 8283
Protoss_Observer 1 8951
Protoss_Reaver 2 11661
Protoss_Scarab 1 9784
11661
