Protoss_Gateway 3 10458
Protoss_Zealot 8 9463
Protoss_Nexus 1 7678
Protoss_Assimilator 2 8115
Protoss_Cybernetics_Core 1 7708
Protoss_Dragoon 1 8469
Protoss_Citadel_of_Adun 1 8800
Protoss_Robotics_Facility 1 9901
Protoss_Templar_Archives 1 9961
Protoss_Forge 1 9694
Protoss_Shuttle 1 10701
Protoss_Observatory 1 10034
Protoss_Dark_Templar 2 10747
Protoss_Photon_Cannon 2 10993
10993
