Protoss_Gateway 3 10948
Protoss_Assimilator 1 3311
Protoss_Cybernetics_Core 1 4318
Protoss_Dragoon 8 8779
Protoss_Citadel_of_Adun 1 8733
Protoss_Zealot 4 9407
Protoss_Templar_Archives 1 9859
Protoss_Dark_Templar 2 10605
10948
