Protoss_Gateway 3 9109
Protoss_Zealot 3 6699
Protoss_Assimilator 1 5115
Protoss_Cybernetics_Core 1 7022
Protoss_Dragoon 8 10319
Protoss_Robotics_Facility 1 9916
Protoss_Observatory 1 10107
Protoss_Observer 1 10883
10883
