Protoss_Gateway 2 9303
Protoss_Assimilator 1 3323
Protoss_Cybernetics_Core 1 4377
Protoss_Zealot 1 4199
Protoss_Dragoon 10 10987
Protoss_Nexus 1 9937
Protoss_Robotics_Facility 1 9529
Protoss_Shuttle 1 10463
Protoss_Robotics_Support_Bay 1 10191
10987
