Protoss_Gateway 2 5771
Protoss_Assimilator 1 3395
Protoss_Cybernetics_Core 1 4480
Protoss_Zealot 1 4221
Protoss_Dragoon 12 11027
Protoss_Nexus 1 10279
Protoss_Robotics_Facility 1 10678
Protoss_Citadel_of_Adun 1 10233
11027
