Protoss_Gateway 2 9286
Protoss_Assimilator 1 3364
Protoss_Zealot 2 4953
Protoss_Cybernetics_Core 1 5156
Protoss_Dragoon 9 10927
Protoss_Nexus 1 9421
Protoss_Robotics_Facility 1 9393
Protoss_Observatory 1 10413
Protoss_Citadel_of_Adun 1 11230
11230
