Protoss_Gateway 2 8056
Protoss_Assimilator 1 3420
Protoss_Zealot 1 3959
Protoss_Cybernetics_Core 1 4607
Protoss_Dragoon 10 11033
Protoss_Nexus 1 8967
Protoss_Robotics_Facility 1 9243
Protoss_Citadel_of_Adun 1 10006
Protoss_Observatory 1 10252
11033
