Protoss_Gateway 4 10195
Protoss_Zealot 7 10817
Protoss_Nexus 1 7930
Protoss_Assimilator 2 8703
Protoss_Cybernetics_Core 1 7667
Protoss_Dragoon 1 8585
Protoss_Forge 1 8988
Protoss_Robotics_Facility 1 10243
Protoss_Citadel_of_Adun 1 10192
Protoss_Photon_Cannon 2 10435
Protoss_Observatory 1 10367
Protoss_Templar_Archives 1 11252
11252
