Protoss_Gateway 3 10782
Protoss_Zealot 3 5089
Protoss_Assimilator 2 9768
Protoss_Cybernetics_Core 1 5260
Protoss_Dragoon 10 10959
Protoss_Nexus 1 9420
Protoss_Robotics_Facility 1 9365
Protoss_Observatory 1 9462
Protoss_Observer 2 10839
Protoss_Citadel_of_Adun 1 10981
10981
