Protoss_Gateway 2 8713
Protoss_Assimilator 1 3388
Protoss_Zealot 2 4631
Protoss_Cybernetics_Core 1 5431
Protoss_Dragoon 7 10931
Protoss_Robotics_Facility 1 8418
Protoss_Observatory 1 8557
Protoss_Observer 3 10541
Protoss_Nexus 1 11527
11527
