Protoss_Gateway 3 10571
Protoss_Zealot 10 8865
Protoss_Nexus 1 7605
Protoss_Assimilator 2 8311
Protoss_Cybernetics_Core 1 7481
Protoss_Citadel_of_Adun 1 8551
Protoss_Dragoon 1 8913
Protoss_Templar_Archives 1 9682
Protoss_Forge 1 9579
Protoss_Dark_Templar 2 10429
Protoss_Photon_Cannon 3 10935
10935
