Protoss_Gateway 3 11127
Protoss_Assimilator 2 10204
Protoss_Zealot 5 8183
Protoss_Cybernetics_Core 1 5236
Protoss_Dragoon 2 10775
Protoss_Citadel_of_Adun 1 7155
Protoss_Robotics_Facility 1 7679
Protoss_Templar_Archives 1 8141
Protoss_Shuttle 1 8481
Protoss_Dark_Templar 2 9635
Protoss_Nexus 1 11029
Protoss_Observatory 1 9691
Protoss_Observer 1 10895
11127
