Protoss_Gateway 3 9957
Protoss_Assimilator 1 3396
Protoss_Zealot 6 9691
Protoss_Cybernetics_Core 1 5127
Protoss_Dragoon 6 10837
Protoss_Nexus 1 10157
Protoss_Robotics_Facility 1 9674
Protoss_Observatory 1 9855
Protoss_Observer 1 10641
10837
