Protoss_Gateway 2 9097
Protoss_Assimilator 1 3312
Protoss_Zealot 1 3799
Protoss_Cybernetics_Core 1 5191
Protoss_Dragoon 7 10185
Protoss_Nexus 1 8958
Protoss_Robotics_Facility 1 9021
Protoss_Observatory 1 9113
Protoss_Observer 1 9907
10185
