Protoss_Gateway 2 8058
Protoss_Assimilator 1 3306
Protoss_Zealot 2 4813
Protoss_Cybernetics_Core 1 4985
Protoss_Dragoon 9 10459
Protoss_Robotics_Facility 1 7737
Protoss_Shuttle 1 8541
Protoss_Observatory 1 8317
Protoss_Robotics_Support_Bay 1 8674
Protoss_Observer 1 9135
Protoss_Reaver 1 10553
10553
