Protoss_Gateway 3 10961
Protoss_Assimilator 1 3385
Protoss_Zealot 3 5177
Protoss_Cybernetics_Core 1 5268
Protoss_Dragoon 8 10933
Protoss_Robotics_Facility 1 7930
Protoss_Shuttle 1 8787
Protoss_Observatory 1 8169
Protoss_Robotics_Support_Bay 1 8759
Protoss_Observer 1 9209
Protoss_Nexus 1 11303
Protoss_Reaver 2 11583
11583
