Protoss_Gateway 2 6965
Protoss_Assimilator 1 3171
Protoss_Cybernetics_Core 1 4491
Protoss_Dragoon 6 10137
Protoss_Citadel_of_Adun 1 5696
Protoss_Templar_Archives 1 6693
Protoss_Zealot 1 6569
Protoss_Dark_Templar 3 8269
Protoss_Nexus 1 11764
11764
