Protoss_Gateway 2 5989
Protoss_Assimilator 1 3171
Protoss_Cybernetics_Core 1 4531
Protoss_Zealot 1 4613
Protoss_Dragoon 12 11031
Protoss_Robotics_Facility 1 7614
Protoss_Shuttle 1 8459
Protoss_Robotics_Support_Bay 1 8356
Protoss_Reaver 2 11175
Protoss_Observatory 1 9325
11175
