Protoss_Gateway 2 9465
Protoss_Assimilator 1 3307
Protoss_Cybernetics_Core 1 4339
Protoss_Zealot 1 4685
Protoss_Dragoon 8 10463
Protoss_Robotics_Facility 1 7909
Protoss_Observatory 1 8006
Protoss_Nexus 1 10554
Protoss_Observer 1 8857
Protoss_Shuttle 1 10499
Protoss_Robotics_Support_Bay 1 10241
10554
