Protoss_Gateway 4 10302
Protoss_Zealot 13 10849
Protoss_Nexus 1 6925
Protoss_Assimilator 2 9221
Protoss_Cybernetics_Core 1 7953
Protoss_Citadel_of_Adun 1 8950
Protoss_Dragoon 4 9619
Protoss_Templar_Archives 1 9968
Protoss_Forge 1 9662
Protoss_Photon_Cannon 2 10803
Protoss_Dark_Templar 2 10933
10933
