Protoss_Gateway 3 9872
Protoss_Zealot 2 4867
Protoss_Assimilator 2 10925
Protoss_Cybernetics_Core 1 5017
Protoss_Dragoon 9 10861
Protoss_Nexus 1 9393
Protoss_Robotics_Facility 1 8805
Protoss_Observatory 1 8989
Protoss_Observer 2 10771
Protoss_Citadel_of_Adun 1 10680
10925
