Protoss_Gateway 2 10232
Protoss_Assimilator 1 3195
Protoss_Cybernetics_Core 1 4323
Protoss_Robotics_Facility 1 6029
Protoss_Dragoon 3 10996
Protoss_Shuttle 1 6856
Protoss_Zealot 3 7953
Protoss_Robotics_Support_Bay 1 6718
Protoss_Reaver 2 9970
Protoss_Forge 1 9694
Protoss_Photon_Cannon 3 11165
11165
