Protoss_Gateway 4 10063
Protoss_Assimilator 2 10879
Protoss_Zealot 2 4849
Protoss_Cybernetics_Core 1 4979
Protoss_Dragoon 9 10857
Protoss_Robotics_Facility 1 7821
Protoss_Observatory 1 7909
Protoss_Nexus 1 10294
Protoss_Observer 2 9743
Protoss_Citadel_of_Adun 1 11437
11437
