Protoss_Assimilator 1 2638
Protoss_Gateway 2 9204
Protoss_Cybernetics_Core 1 4881
Protoss_Robotics_Facility 1 6389
Protoss_Dragoon 9 10715
Protoss_Shuttle 2 9796
Protoss_Nexus 1 10250
Protoss_Observatory 1 8306
Protoss_Robotics_Support_Bay 1 9364
Protoss_Observer 1 10551
10715
