Protoss_Gateway 2 8036
Protoss_Assimilator 1 3922
Protoss_Zealot 3 9583
Protoss_Cybernetics_Core 1 5109
Protoss_Dragoon 9 10789
Protoss_Robotics_Facility 1 7863
Protoss_Shuttle 1 8741
Protoss_Observatory 1 8080
Protoss_Observer 1 9163
Protoss_Robotics_Support_Bay 1 9088
Protoss_Reaver 1 10713
Protoss_Nexus 1 12129
12129
