Protoss_Gateway 3 7365
Protoss_Assimilator 1 3411
Protoss_Zealot 2 5095
Protoss_Cybernetics_Core 1 5297
Protoss_Dragoon 13 11195
Protoss_Nexus 1 12304
Protoss_Robotics_Facility 1 11416
12304
