Protoss_Gateway 4 11317
Protoss_Assimilator 2 10605
Protoss_Cybernetics_Core 1 4465
Protoss_Zealot 1 4369
Protoss_Dragoon 10 10765
Protoss_Nexus 1 9809
Protoss_Robotics_Facility 1 9288
Protoss_Observatory 1 9399
Protoss_Observer 2 10937
11317
