Protoss_Gateway 2 5891
Protoss_Assimilator 1 3395
Protoss_Cybernetics_Core 1 4349
Protoss_Zealot 1 4061
Protoss_Dragoon 10 9939
Protoss_Robotics_Facility 1 8168
Protoss_Observatory 1 8288
Protoss_Robotics_Support_Bay 1 8781
Protoss_Observer 1 9123
Protoss_Reaver 1 10697
10697
