Protoss_Gateway 3 9399
Protoss_Assimilator 1 3405
Protoss_Cybernetics_Core 1 4433
Protoss_Zealot 1 4371
Protoss_Dragoon 13 11025
Protoss_Citadel_of_Adun 1 7211
Protoss_Templar_Archives 1 8201
Protoss_Dark_Templar 2 9429
11025
