Protoss_Gateway 5 10985
Protoss_Zealot 7 10909
Protoss_Nexus 1 7791
Protoss_Assimilator 2 9668
Protoss_Cybernetics_Core 1 7510
Protoss_Dragoon 7 10307
Protoss_Robotics_Facility 1 11684
11684
