Protoss_Gateway 3 9752
Protoss_Assimilator 1 3191
Protoss_Cybernetics_Core 1 4360
Protoss_Dragoon 14 10957
Protoss_Robotics_Facility 1 8898
Protoss_Observatory 1 9001
Protoss_Zealot 2 10001
Protoss_Observer 2 10654
10957
