Protoss_Gateway 2 8209
Protoss_Zealot 3 5103
Protoss_Assimilator 1 3915
Protoss_Cybernetics_Core 1 5332
Protoss_Dragoon 9 10975
Protoss_Citadel_of_Adun 1 6557
Protoss_Templar_Archives 1 7581
Protoss_Dark_Templar 1 8355
Protoss_Nexus 1 12526
12526
