Protoss_Gateway 2 4211
Protoss_Zealot 11 8176
Protoss_Assimilator 1 5933
Protoss_Cybernetics_Core 1 8873
Protoss_Citadel_of_Adun 1 9970
Protoss_Dragoon 4 10783
Protoss_Templar_Archives 1 10988
10988
