Protoss_Gateway 1 1816
Protoss_Assimilator 1 2350
Protoss_Cybernetics_Core 1 2931
Protoss_Zealot 1 3127
Protoss_Dragoon 7 9521
Protoss_Robotics_Facility 1 5733
Protoss_Robotics_Support_Bay 1 7081
Protoss_Observatory 1 7151
Protoss_Reaver 1 7671
Protoss_Observer 2 9325
Protoss_Scarab 5 9384
Protoss_Nexus 1 9783
9783
