Protoss_Gateway 4 10977
Protoss_Zealot 5 6401
Protoss_Assimilator 2 8585
Protoss_Nexus 1 8040
Protoss_Cybernetics_Core 1 7501
Protoss_Dragoon 8 11037
Protoss_Citadel_of_Adun 1 9281
Protoss_Robotics_Facility 1 10887
Protoss_Templar_Archives 1 10943
11037
