Protoss_Gateway 2 7028
Protoss_Assimilator 1 3231
Protoss_Zealot 2 4499
Protoss_Cybernetics_Core 1 4727
Protoss_Dragoon 11 10587
Protoss_Robotics_Facility 1 9028
Protoss_Nexus 1 10983
Protoss_Observatory 1 9320
Protoss_Observer 1 10113
10983
