Protoss_Gateway 3 9722
Protoss_Zealot 11 8409
Protoss_Nexus 1 7577
Protoss_Assimilator 2 10546
Protoss_Cybernetics_Core 1 8754
Protoss_Dragoon 4 10963
Protoss_Citadel_of_Adun 1 10330
Protoss_Robotics_Facility 1 11305
11305
