Protoss_Gateway 3 9456
Protoss_Zealot 19 10699
Protoss_Nexus 1 8608
Protoss_Assimilator 1 7076
Protoss_Cybernetics_Core 1 8710
Protoss_Citadel_of_Adun 1 9727
Protoss_Forge 1 9542
Protoss_Photon_Cannon 1 11119
11119
