Protoss_Gateway 2 3953
Protoss_Zealot 9 6761
Protoss_Assimilator 1 5408
Protoss_Cybernetics_Core 1 6731
Protoss_Dragoon 8 10541
Protoss_Nexus 1 10235
Protoss_Robotics_Facility 1 10781
10781
