Protoss_Gateway 3 7887
Protoss_Assimilator 1 3371
Protoss_Cybernetics_Core 1 4365
Protoss_Zealot 1 4423
Protoss_Dragoon 16 11005
Protoss_Robotics_Facility 1 9846
Protoss_Shuttle 1 11081
Protoss_Robotics_Support_Bay 1 10373
11081
