Protoss_Gateway 3 10887
Protoss_Assimilator 1 3283
Protoss_Cybernetics_Core 1 4281
Protoss_Zealot 1 4353
Protoss_Dragoon 10 10835
Protoss_Nexus 1 9115
Protoss_Robotics_Facility 1 9624
Protoss_Observatory 1 9797
Protoss_Observer 1 10565
10887
