Protoss_Gateway 2 6400
Protoss_Assimilator 1 3538
Protoss_Zealot 3 5326
Protoss_Cybernetics_Core 1 5432
Protoss_Dragoon 4 9641
Protoss_Citadel_of_Adun 1 7059
Protoss_Templar_Archives 1 8106
Protoss_Dark_Templar 2 8866
Protoss_Robotics_Facility 1 10754
Protoss_Forge 1 10372
10754
