Protoss_Gateway 2 6583
Protoss_Assimilator 1 3331
Protoss_Zealot 3 7335
Protoss_Cybernetics_Core 1 5045
Protoss_Dragoon 7 9815
Protoss_Robotics_Facility 1 8073
Protoss_Shuttle 1 8877
Protoss_Observatory 1 8507
Protoss_Robotics_Support_Bay 1 8643
Protoss_Observer 1 9319
Protoss_Reaver 1 10977
Protoss_Nexus 1 12458
12458
