Protoss_Nexus 1 5883
Protoss_Gateway 3 10855
Protoss_Assimilator 1 4807
Protoss_Cybernetics_Core 1 6033
Protoss_Dragoon 8 10953
Protoss_Forge 1 8258
Protoss_Robotics_Facility 1 9852
Protoss_Photon_Cannon 4 9915
10953
