Protoss_Gateway 3 11394
Protoss_Assimilator 2 10773
Protoss_Cybernetics_Core 1 4518
Protoss_Dragoon 5 8037
Protoss_Citadel_of_Adun 1 7095
Protoss_Templar_Archives 1 8109
Protoss_Forge 1 8421
Protoss_Dark_Templar 2 8861
Protoss_Photon_Cannon 2 9445
Protoss_Nexus 1 11731
Protoss_High_Templar 2 10165
11731
