Protoss_Gateway 1 1978
Protoss_Assimilator 1 2373
Protoss_Cybernetics_Core 1 3180
Protoss_Zealot 3 7351
Protoss_Robotics_Facility 1 4486
Protoss_Dragoon 2 5641
Protoss_Shuttle 1 5901
Protoss_Robotics_Support_Bay 1 6229
Protoss_Reaver 2 9606
Protoss_Nexus 1 8420
Protoss_Scarab 7 9914
9914
