Protoss_Gateway 2 4193
Protoss_Zealot 2 5766
Protoss_Assimilator 1 4448
Protoss_Cybernetics_Core 1 5750
Protoss_Citadel_of_Adun 1 6753
Protoss_Dragoon 3 10000
Protoss_Templar_Archives 1 7748
Protoss_Dark_Templar 4 9266
10000
