Protoss_Gateway 2 5463
Protoss_Zealot 1 3811
Protoss_Assimilator 1 3993
Protoss_Cybernetics_Core 1 5183
Protoss_Dragoon 11 10861
Protoss_Nexus 1 10239
Protoss_Robotics_Facility 1 10093
Protoss_Citadel_of_Adun 1 10556
Protoss_Observatory 1 10419
10861
