Protoss_Gateway 2 9535
Protoss_Assimilator 1 3221
Protoss_Zealot 2 4899
Protoss_Cybernetics_Core 1 5066
Protoss_Dragoon 10 11095
Protoss_Robotics_Facility 1 7651
Protoss_Observatory 1 7883
Protoss_Nexus 1 10259
Protoss_Observer 3 10881
11095
