Protoss_Gateway 2 9667
Protoss_Assimilator 2 9719
Protoss_Zealot 2 4833
Protoss_Cybernetics_Core 1 5110
Protoss_Dragoon 8 10515
Protoss_Nexus 1 9539
Protoss_Robotics_Facility 1 9526
Protoss_Citadel_of_Adun 1 9294
Protoss_Templar_Archives 1 10454
Protoss_Observatory 1 9793
Protoss_Observer 1 10615
10615
