Protoss_Gateway 3 11264
Protoss_Assimilator 1 3270
Protoss_Zealot 2 4939
Protoss_Cybernetics_Core 1 5123
Protoss_Dragoon 9 10701
Protoss_Robotics_Facility 1 8215
Protoss_Observatory 1 8335
Protoss_Robotics_Support_Bay 1 8783
Protoss_Observer 1 9131
Protoss_Reaver 1 10663
Protoss_Nexus 1 11987
11987
