Protoss_Gateway 3 8281
Protoss_Assimilator 1 3209
Protoss_Cybernetics_Core 1 4334
Protoss_Zealot 5 9129
Protoss_Dragoon 7 10333
Protoss_Robotics_Facility 1 7656
Protoss_Shuttle 1 8453
Protoss_Observatory 1 7853
Protoss_Robotics_Support_Bay 1 8330
Protoss_Observer 1 8875
Protoss_Reaver 2 11325
11325
