Protoss_Gateway 2 8137
Protoss_Assimilator 1 3338
Protoss_Zealot 2 4897
Protoss_Cybernetics_Core 1 5069
Protoss_Dragoon 9 10099
Protoss_Robotics_Facility 1 7759
Protoss_Shuttle 1 8661
Protoss_Observatory 1 8076
Protoss_Robotics_Support_Bay 1 8839
Protoss_Observer 2 10737
Protoss_Reaver 1 10405
10737
