Protoss_Gateway 2 7671
Protoss_Assimilator 1 3238
Protoss_Zealot 2 4785
Protoss_Cybernetics_Core 1 4973
Protoss_Dragoon 9 10965
Protoss_Robotics_Facility 1 7491
Protoss_Observatory 1 7593
Protoss_Robotics_Support_Bay 1 8143
Protoss_Observer 2 10255
Protoss_Reaver 1 9871
Protoss_Nexus 1 11659
11659
