Protoss_Gateway 2 8251
Protoss_Assimilator 1 3294
Protoss_Zealot 2 4851
Protoss_Cybernetics_Core 1 4927
Protoss_Dragoon 11 11101
Protoss_Robotics_Facility 1 7844
Protoss_Shuttle 1 8663
Protoss_Observatory 1 8217
Protoss_Observer 2 10865
Protoss_Robotics_Support_Bay 1 9041
Protoss_Reaver 1 10533
Protoss_Nexus 1 12491
12491
