Protoss_Gateway 2 7843
Protoss_Assimilator 1 3143
Protoss_Zealot 2 4837
Protoss_Cybernetics_Core 1 5016
Protoss_Dragoon 10 10929
Protoss_Robotics_Facility 1 7608
Protoss_Observatory 1 7896
Protoss_Observer 1 8673
Protoss_Robotics_Support_Bay 1 8500
Protoss_Reaver 1 10213
Protoss_Nexus 1 12285
12285
