Protoss_Gateway 4 10837
Protoss_Assimilator 1 3438
Protoss_Zealot 1 3911
Protoss_Cybernetics_Core 1 5288
Protoss_Dragoon 10 10476
Protoss_Robotics_Facility 1 9598
Protoss_Observatory 1 9716
Protoss_Observer 1 10496
10837
