Protoss_Gateway 1 3325
Protoss_Assimilator 1 3340
Protoss_Cybernetics_Core 1 4546
Protoss_Zealot 2 8205
Protoss_Dragoon 7 10870
Protoss_Robotics_Facility 1 7401
Protoss_Shuttle 1 8241
Protoss_Observatory 1 7526
Protoss_Robotics_Support_Bay 1 8306
Protoss_Observer 2 10317
Protoss_Reaver 2 11639
11639
