Protoss_Gateway 4 10553
Protoss_Assimilator 1 3359
Protoss_Cybernetics_Core 1 4468
Protoss_Zealot 1 4287
Protoss_Dragoon 8 10487
Protoss_Nexus 1 7955
Protoss_Robotics_Facility 1 7964
Protoss_Observatory 1 8116
Protoss_Observer 1 8923
Protoss_Shuttle 1 10005
Protoss_Robotics_Support_Bay 1 9500
Protoss_Reaver 1 11213
11213
