Protoss_Gateway 2 8679
Protoss_Assimilator 1 3439
Protoss_Zealot 2 5233
Protoss_Cybernetics_Core 1 5345
Protoss_Dragoon 10 11183
Protoss_Robotics_Facility 1 8291
Protoss_Observatory 1 8401
Protoss_Observer 2 9787
Protoss_Shuttle 1 10869
Protoss_Robotics_Support_Bay 1 10267
11183
