Protoss_Gateway 2 8166
Protoss_Assimilator 1 3293
Protoss_Zealot 2 4893
Protoss_Cybernetics_Core 1 5073
Protoss_Dragoon 8 10069
Protoss_Robotics_Facility 1 7782
Protoss_Shuttle 1 8637
Protoss_Observatory 1 8088
Protoss_Observer 2 10713
Protoss_Robotics_Support_Bay 1 8825
Protoss_Reaver 1 10381
Protoss_Nexus 1 12601
12601
