Protoss_Gateway 2 6745
Protoss_Assimilator 1 3578
Protoss_Zealot 1 4091
Protoss_Cybernetics_Core 1 5431
Protoss_Dragoon 10 11021
Protoss_Robotics_Facility 1 8734
Protoss_Shuttle 1 9741
Protoss_Robotics_Support_Bay 1 9373
Protoss_Reaver 1 11056
11056
