Protoss_Gateway 2 9031
Protoss_Assimilator 2 9969
Protoss_Cybernetics_Core 1 4777
Protoss_Zealot 1 4657
Protoss_Dragoon 10 11065
Protoss_Nexus 1 9235
Protoss_Robotics_Facility 1 9388
Protoss_Citadel_of_Adun 1 9881
Protoss_Observatory 1 9477
Protoss_Observer 2 10853
Protoss_Templar_Archives 1 11101
11101
