Protoss_Gateway 2 8008
Protoss_Assimilator 1 3253
Protoss_Zealot 2 4895
Protoss_Cybernetics_Core 1 5064
Protoss_Dragoon 8 9921
Protoss_Robotics_Facility 1 7842
Protoss_Shuttle 1 8641
Protoss_Observatory 1 8030
Protoss_Robotics_Support_Bay 1 8529
Protoss_Observer 2 10717
Protoss_Reaver 2 11521
Protoss_Nexus 1 12462
12462
