Protoss_Gateway 4 10391
Protoss_Assimilator 1 3278
Protoss_Cybernetics_Core 1 4293
Protoss_Zealot 2 7747
Protoss_Dragoon 9 11135
Protoss_Citadel_of_Adun 1 6715
Protoss_Templar_Archives 1 7768
Protoss_Dark_Templar 2 8659
Protoss_Nexus 1 10889
11135
