Protoss_Gateway 2 8518
Protoss_Assimilator 1 3269
Protoss_Cybernetics_Core 1 4564
Protoss_Robotics_Facility 1 6109
Protoss_Dragoon 8 10018
Protoss_Observatory 1 6334
Protoss_Observer 2 9051
Protoss_Nexus 2 12588
Protoss_Forge 1 9227
Protoss_Photon_Cannon 1 10384
12588
