Protoss_Gateway 4 10223
Protoss_Assimilator 1 3169
Protoss_Zealot 2 4687
Protoss_Cybernetics_Core 1 5120
Protoss_Dragoon 8 10355
Protoss_Citadel_of_Adun 1 7680
Protoss_Templar_Archives 1 8665
Protoss_Nexus 1 10791
Protoss_Dark_Templar 2 9557
10791
