Protoss_Gateway 2 8088
Protoss_Assimilator 1 3448
Protoss_Zealot 5 10481
Protoss_Cybernetics_Core 1 5774
Protoss_Dragoon 2 7321
Protoss_Citadel_of_Adun 1 7400
Protoss_Robotics_Facility 1 8323
Protoss_Templar_Archives 1 8488
Protoss_Observatory 1 8533
Protoss_Shuttle 2 10778
Protoss_Dark_Templar 3 10018
Protoss_Observer 1 9696
Protoss_Forge 1 10142
10778
