Protoss_Gateway 2 5444
Protoss_Assimilator 1 3342
Protoss_Zealot 2 5233
Protoss_Cybernetics_Core 1 5289
Protoss_Robotics_Facility 1 6973
Protoss_Dragoon 10 11079
Protoss_Observatory 1 7075
Protoss_Observer 3 9489
Protoss_Nexus 1 10656
Protoss_Shuttle 1 10708
Protoss_Robotics_Support_Bay 1 10314
11079
