Protoss_Gateway 4 9625
Protoss_Assimilator 1 3306
Protoss_Cybernetics_Core 1 4391
Protoss_Zealot 1 4119
Protoss_Dragoon 13 11115
Protoss_Nexus 1 8501
Protoss_Robotics_Facility 1 8469
Protoss_Observatory 1 8658
Protoss_Observer 2 10029
11115
