Protoss_Gateway 2 10370
Protoss_Assimilator 1 3314
Protoss_Cybernetics_Core 1 4322
Protoss_Zealot 1 4415
Protoss_Dragoon 8 11047
Protoss_Robotics_Facility 1 7830
Protoss_Nexus 1 9883
Protoss_Shuttle 1 9001
Protoss_Robotics_Support_Bay 1 8569
Protoss_Reaver 2 11533
Protoss_Observatory 1 10153
11533
