Protoss_Gateway 2 7757
Protoss_Assimilator 1 3323
Protoss_Zealot 2 4899
Protoss_Cybernetics_Core 1 5101
Protoss_Dragoon 9 10955
Protoss_Robotics_Facility 1 7891
Protoss_Observatory 1 8095
Protoss_Shuttle 1 9045
Protoss_Robotics_Support_Bay 1 9033
Protoss_Observer 1 9467
Protoss_Reaver 1 10789
10955
