Protoss_Gateway 2 3831
Protoss_Zealot 11 9337
Protoss_Assimilator 2 9713
Protoss_Nexus 1 8660
Protoss_Cybernetics_Core 1 7650
Protoss_Dragoon 2 8825
Protoss_Citadel_of_Adun 1 9648
Protoss_Robotics_Facility 1 10968
Protoss_Templar_Archives 1 10788
Protoss_Forge 1 10584
10968
