Protoss_Gateway 2 8239
Protoss_Assimilator 1 3463
Protoss_Zealot 2 5327
Protoss_Cybernetics_Core 1 5391
Protoss_Dragoon 10 11089
Protoss_Robotics_Facility 1 8024
Protoss_Observatory 1 8152
Protoss_Shuttle 1 8883
Protoss_Robotics_Support_Bay 2 10210
Protoss_Observer 1 9493
Protoss_Reaver 1 11361
11361
