Protoss_Gateway 2 8393
Protoss_Assimilator 1 3440
Protoss_Zealot 2 5055
Protoss_Cybernetics_Core 1 5237
Protoss_Dragoon 10 10985
Protoss_Robotics_Facility 1 8459
Protoss_Shuttle 1 9261
Protoss_Observatory 1 8620
Protoss_Robotics_Support_Bay 1 9266
Protoss_Observer 1 9683
Protoss_Reaver 1 11005
11005
