Protoss_Gateway 2 7289
Protoss_Assimilator 1 3254
Protoss_Zealot 3 5575
Protoss_Cybernetics_Core 1 5807
Protoss_Dragoon 10 11113
Protoss_Robotics_Facility 1 8549
Protoss_Shuttle 1 9633
Protoss_Robotics_Support_Bay 1 9183
Protoss_Reaver 1 10993
Protoss_Shield_Battery 1 10565
11113
