Protoss_Gateway 2 7533
Protoss_Assimilator 1 3233
Protoss_Cybernetics_Core 1 4476
Protoss_Zealot 1 4241
Protoss_Dragoon 10 10467
Protoss_Robotics_Facility 1 7392
Protoss_Observatory 1 7557
Protoss_Observer 2 9647
Protoss_Shuttle 1 9225
Protoss_Robotics_Support_Bay 1 9089
Protoss_Reaver 1 10983
10983
