Protoss_Gateway 4 9833
Protoss_Zealot 11 9737
Protoss_Nexus 1 7879
Protoss_Assimilator 2 8444
Protoss_Cybernetics_Core 1 7721
Protoss_Citadel_of_Adun 1 8854
Protoss_Templar_Archives 1 9889
Protoss_Dark_Templar 4 10833
Protoss_Forge 1 10831
10833
