Protoss_Gateway 3 10040
Protoss_Assimilator 1 3342
Protoss_Zealot 4 10259
Protoss_Cybernetics_Core 1 5985
Protoss_Dragoon 6 10799
Protoss_Nexus 1 8999
Protoss_Robotics_Facility 1 9555
Protoss_Observatory 1 9759
Protoss_Robotics_Support_Bay 1 10122
10799
