Protoss_Gateway 2 6475
Protoss_Assimilator 1 3357
Protoss_Zealot 4 9695
Protoss_Cybernetics_Core 1 5038
Protoss_Dragoon 10 10889
Protoss_Robotics_Facility 1 8331
Protoss_Shuttle 1 9181
Protoss_Observatory 1 8591
Protoss_Robotics_Support_Bay 1 9339
Protoss_Observer 1 9606
Protoss_Reaver 1 11151
11151
