Protoss_Gateway 4 9457
Protoss_Assimilator 1 3175
Protoss_Cybernetics_Core 1 4315
Protoss_Zealot 1 4093
Protoss_Dragoon 13 10993
Protoss_Citadel_of_Adun 1 6194
Protoss_Nexus 1 10040
10993
