Protoss_Gateway 2 3885
Protoss_Assimilator 1 3717
Protoss_Cybernetics_Core 1 5131
Protoss_Zealot 2 5259
Protoss_Dragoon 13 10869
Protoss_Robotics_Facility 1 9551
Protoss_Observatory 1 9744
Protoss_Robotics_Support_Bay 1 9786
10869
