Protoss_Gateway 2 6739
Protoss_Assimilator 1 3321
Protoss_Cybernetics_Core 1 4300
Protoss_Zealot 1 4375
Protoss_Dragoon 9 9655
Protoss_Robotics_Facility 1 8753
Protoss_Observatory 1 8941
Protoss_Robotics_Support_Bay 1 9346
Protoss_Observer 1 9739
Protoss_Reaver 1 11061
Protoss_Nexus 1 12619
12619
