Protoss_Gateway 3 10437
Protoss_Assimilator 1 3564
Protoss_Zealot 2 4928
Protoss_Cybernetics_Core 1 5950
Protoss_Dragoon 8 10658
Protoss_Robotics_Facility 1 7743
Protoss_Observatory 1 7918
Protoss_Observer 3 10126
Protoss_Shuttle 1 11208
11208
