Protoss_Gateway 4 10385
Protoss_Zealot 6 7181
Protoss_Nexus 1 7825
Protoss_Assimilator 1 5996
Protoss_Cybernetics_Core 1 6946
Protoss_Dragoon 8 11183
Protoss_Robotics_Facility 1 9885
Protoss_Shuttle 1 11161
Protoss_Observatory 1 10525
11183
