Protoss_Gateway 2 11209
Protoss_Assimilator 1 3367
Protoss_Zealot 2 5211
Protoss_Cybernetics_Core 1 5348
Protoss_Dragoon 2 7301
Protoss_Citadel_of_Adun 1 6888
Protoss_Templar_Archives 1 8101
Protoss_Robotics_Facility 1 8923
Protoss_Dark_Templar 1 8866
Protoss_Forge 1 8748
Protoss_High_Templar 3 11193
Protoss_Shuttle 1 10251
Protoss_Photon_Cannon 1 10388
Psionic_Storm 1 9816
11209
