Protoss_Gateway 3 11149
Protoss_Assimilator 1 3305
Protoss_Zealot 2 5017
Protoss_Cybernetics_Core 1 5163
Protoss_Dragoon 7 10563
Protoss_Citadel_of_Adun 1 6785
Protoss_Templar_Archives 1 7824
Protoss_Forge 1 7927
Protoss_Dark_Templar 2 8569
Protoss_Photon_Cannon 1 9009
Protoss_Nexus 1 11683
11683
