Protoss_Gateway 4 11157
Protoss_Assimilator 1 3528
Protoss_Zealot 2 4961
Protoss_Cybernetics_Core 1 5142
Protoss_Dragoon 8 10351
Protoss_Robotics_Facility 1 8273
Protoss_Observatory 1 8433
Protoss_Nexus 1 10816
Protoss_Observer 2 10215
11157
