Protoss_Gateway 3 10421
Protoss_Assimilator 1 3296
Protoss_Zealot 2 4907
Protoss_Cybernetics_Core 1 5071
Protoss_Dragoon 13 10826
Protoss_Shield_Battery 1 5740
Protoss_Robotics_Facility 1 9525
Protoss_Observatory 1 9780
10826
