Protoss_Gateway 2 3948
Protoss_Zealot 13 9971
Protoss_Forge 1 6495
Protoss_Photon_Cannon 4 9781
Protoss_Assimilator 1 8775
Protoss_Cybernetics_Core 1 10361
Protoss_Robotics_Facility 1 11890
11890
