Protoss_Gateway 3 11317
Protoss_Assimilator 2 9858
Protoss_Zealot 1 3939
Protoss_Cybernetics_Core 1 5352
Protoss_Dragoon 9 10639
Protoss_Nexus 1 9177
Protoss_Robotics_Facility 1 8733
Protoss_Observatory 1 9026
Protoss_Observer 2 10929
Protoss_Citadel_of_Adun 1 10940
11317
