Protoss_Gateway 3 10909
Protoss_Assimilator 1 3223
Protoss_Cybernetics_Core 1 4319
Protoss_Dragoon 14 11100
Protoss_Robotics_Facility 1 8098
Protoss_Observatory 1 8257
Protoss_Observer 2 9711
Protoss_Nexus 1 11605
11605
