Protoss_Gateway 2 5543
Protoss_Assimilator 1 3661
Protoss_Zealot 1 3957
Protoss_Cybernetics_Core 1 5017
Protoss_Dragoon 6 10271
Protoss_Nexus 1 9384
Protoss_Robotics_Facility 1 8817
Protoss_Forge 1 8469
Protoss_Photon_Cannon 1 9441
Protoss_Observatory 1 9009
Protoss_Citadel_of_Adun 1 10292
Protoss_Observer 2 10467
10467
