Protoss_Gateway 2 5049
Protoss_Assimilator 1 3186
Protoss_Zealot 5 6013
Protoss_Cybernetics_Core 1 6409
Protoss_Dragoon 6 10519
Protoss_Robotics_Facility 1 8391
Protoss_Nexus 1 10080
Protoss_Observatory 1 8483
Protoss_Shuttle 1 9473
Protoss_Robotics_Support_Bay 1 9594
Protoss_Observer 1 9895
Protoss_Reaver 1 11247
11247
