Protoss_Gateway 3 10589
Protoss_Assimilator 1 3204
Protoss_Cybernetics_Core 1 4204
Protoss_Zealot 2 7031
Protoss_Dragoon 9 10897
Protoss_Citadel_of_Adun 1 6435
Protoss_Templar_Archives 1 7483
Protoss_Dark_Templar 2 8227
Protoss_Nexus 1 10524
Protoss_Robotics_Facility 1 10376
Protoss_Observatory 1 10551
10897
