Protoss_Gateway 2 10993
Protoss_Assimilator 1 3293
Protoss_Zealot 2 4935
Protoss_Cybernetics_Core 1 5247
Protoss_Dragoon 5 11051
Protoss_Robotics_Facility 1 7383
Protoss_Robotics_Support_Bay 1 7501
Protoss_Shuttle 1 8229
Protoss_Reaver 1 9371
Protoss_Observatory 1 8709
Protoss_Observer 1 9703
Protoss_Nexus 1 11941
11941
