Protoss_Gateway 2 6403
Protoss_Assimilator 1 3304
Protoss_Zealot 2 4859
Protoss_Cybernetics_Core 1 4993
Protoss_Dragoon 11 10891
Protoss_Robotics_Facility 1 8739
Protoss_Observatory 1 8844
Protoss_Observer 2 10233
Protoss_Nexus 1 12451
12451
