Protoss_Gateway 2 7381
Protoss_Assimilator 1 3329
Protoss_Zealot 2 4851
Protoss_Cybernetics_Core 1 5051
Protoss_Dragoon 11 10995
Protoss_Robotics_Facility 1 7345
Protoss_Shuttle 1 8237
Protoss_Robotics_Support_Bay 1 8143
Protoss_Reaver 1 9663
Protoss_Observatory 1 9136
Protoss_Observer 1 10441
10995
