Protoss_Gateway 3 10293
Protoss_Assimilator 1 3428
Protoss_Cybernetics_Core 1 4414
Protoss_Dragoon 6 10841
Protoss_Robotics_Facility 1 6393
Protoss_Shuttle 1 7281
Protoss_Observatory 1 6768
Protoss_Observer 2 10515
Protoss_Robotics_Support_Bay 1 7537
Protoss_Reaver 2 10183
10841
