Protoss_Gateway 2 7503
Protoss_Assimilator 1 3332
Protoss_Cybernetics_Core 1 4371
Protoss_Zealot 1 4103
Protoss_Dragoon 5 10725
Protoss_Citadel_of_Adun 1 6640
Protoss_Templar_Archives 1 7827
Protoss_Dark_Templar 3 9558
Protoss_Nexus 1 12095
12095
