Protoss_Gateway 2 7648
Protoss_Assimilator 1 3294
Protoss_Zealot 1 3743
Protoss_Cybernetics_Core 1 4539
Protoss_Dragoon 8 10377
Protoss_Robotics_Facility 1 7005
Protoss_Robotics_Support_Bay 1 7101
Protoss_Reaver 1 8755
Protoss_Observatory 1 8273
Protoss_Observer 2 10709
Protoss_Shuttle 1 10287
Protoss_Nexus 1 12733
12733
