Protoss_Gateway 2 7852
Protoss_Assimilator 1 2431
Protoss_Cybernetics_Core 1 3068
Protoss_Zealot 3 7961
Protoss_Dragoon 4 8637
Protoss_Robotics_Facility 1 4468
Protoss_Observatory 1 6103
Protoss_Shuttle 1 6307
Protoss_Robotics_Support_Bay 1 6982
Protoss_Observer 1 7209
Protoss_Reaver 1 7967
Protoss_Nexus 1 9031
Protoss_Scarab 2 9903
9903
