Protoss_Gateway 4 8547
Protoss_Assimilator 1 3324
Protoss_Cybernetics_Core 1 4307
Protoss_Zealot 3 10425
Protoss_Dragoon 12 10601
Protoss_Nexus 1 8943
Protoss_Robotics_Facility 1 11657
Protoss_Shield_Battery 1 10659
11657
