Protoss_Gateway 2 6587
Protoss_Assimilator 1 3336
Protoss_Cybernetics_Core 1 4713
Protoss_Zealot 5 10493
Protoss_Dragoon 9 10509
Protoss_Robotics_Facility 1 7631
Protoss_Observatory 1 7837
Protoss_Observer 2 9897
Protoss_Nexus 1 11061
Protoss_Citadel_of_Adun 1 9876
Protoss_Templar_Archives 1 10923
11061
