Protoss_Gateway 1 3370
Protoss_Assimilator 1 3269
Protoss_Cybernetics_Core 1 4378
Protoss_Robotics_Facility 1 6031
Protoss_Dragoon 7 10475
Protoss_Observatory 1 6428
Protoss_Observer 2 7848
Protoss_Shuttle 1 8930
Protoss_Robotics_Support_Bay 1 8667
Protoss_Reaver 2 11428
11428
