Protoss_Gateway 1 2126
Protoss_Assimilator 1 2480
Protoss_Cybernetics_Core 1 3147
Protoss_Robotics_Facility 1 4214
Protoss_Dragoon 4 9547
Protoss_Shuttle 1 5493
Protoss_Robotics_Support_Bay 1 5778
Protoss_Reaver 2 7447
Protoss_Observatory 1 8392
Protoss_Observer 1 8927
Protoss_Scarab 1 9072
Protoss_Nexus 1 9741
9741
