Protoss_Gateway 2 11122
Protoss_Assimilator 1 3180
Protoss_Cybernetics_Core 1 4329
Protoss_Dragoon 7 10791
Protoss_Robotics_Facility 1 6061
Protoss_Shuttle 1 6945
Protoss_Observatory 1 6714
Protoss_Observer 2 9055
Protoss_Nexus 1 10121
Protoss_Forge 1 10133
Protoss_Photon_Cannon 1 11166
11166
