Protoss_Gateway 2 7875
Protoss_Assimilator 1 3327
Protoss_Cybernetics_Core 1 4281
Protoss_Zealot 1 4243
Protoss_Dragoon 10 10753
Protoss_Robotics_Facility 1 7767
Protoss_Shuttle 1 8569
Protoss_Observatory 1 7944
Protoss_Robotics_Support_Bay 1 8729
Protoss_Observer 1 8991
Protoss_Reaver 1 10477
10753
