Protoss_Gateway 2 6256
Protoss_Assimilator 1 3393
Protoss_Cybernetics_Core 1 4389
Protoss_Zealot 1 4369
Protoss_Dragoon 9 10527
Protoss_Nexus 1 10289
Protoss_Robotics_Facility 1 9949
Protoss_Observatory 1 10150
Protoss_Observer 1 10943
10943
