Protoss_Gateway 4 11178
Protoss_Zealot 7 9267
Protoss_Nexus 1 7838
Protoss_Assimilator 2 7863
Protoss_Cybernetics_Core 1 7101
Protoss_Dragoon 4 8701
Protoss_Citadel_of_Adun 1 8543
Protoss_Robotics_Facility 1 10001
Protoss_Templar_Archives 1 9925
Protoss_Dark_Templar 2 10715
Protoss_Shuttle 1 10989
Protoss_Observatory 1 10604
11178
