Protoss_Gateway 2 10875
Protoss_Assimilator 2 8858
Protoss_Cybernetics_Core 1 4387
Protoss_Zealot 1 4061
Protoss_Dragoon 7 10755
Protoss_Nexus 1 8435
Protoss_Forge 2 9143
Protoss_Photon_Cannon 2 8332
Protoss_Citadel_of_Adun 1 10673
10875
