Protoss_Gateway 4 11264
Protoss_Zealot 8 7489
Protoss_Nexus 1 7658
Protoss_Assimilator 2 8045
Protoss_Cybernetics_Core 1 7551
Protoss_Dragoon 9 11155
Protoss_Robotics_Facility 1 10063
Protoss_Shuttle 1 10867
Protoss_Observatory 1 10229
11264
