Protoss_Gateway 4 10798
Protoss_Assimilator 1 3341
Protoss_Zealot 4 10475
Protoss_Cybernetics_Core 1 5233
Protoss_Dragoon 9 9369
Protoss_Robotics_Facility 1 8803
Protoss_Observatory 1 8911
Protoss_Nexus 1 11660
Protoss_Observer 2 10423
11660
