Protoss_Gateway 3 8515
Protoss_Assimilator 1 3433
Protoss_Zealot 2 5083
Protoss_Cybernetics_Core 1 5290
Protoss_Dragoon 13 10909
Protoss_Robotics_Facility 1 7843
Protoss_Observatory 1 7961
Protoss_Observer 2 9485
10909
