Protoss_Gateway 2 10916
Protoss_Assimilator 1 3345
Protoss_Cybernetics_Core 1 4421
Protoss_Zealot 1 4213
Protoss_Dragoon 7 10403
Protoss_Robotics_Facility 1 7319
Protoss_Shuttle 1 8155
Protoss_Robotics_Support_Bay 1 7508
Protoss_Reaver 1 9297
Protoss_Observatory 1 8454
Protoss_Observer 2 10231
Protoss_Nexus 1 11883
11883
