Protoss_Gateway 3 8809
Protoss_Assimilator 1 3393
Protoss_Zealot 2 4985
Protoss_Cybernetics_Core 1 5176
Protoss_Dragoon 9 10963
Protoss_Nexus 1 9535
Protoss_Citadel_of_Adun 1 9365
Protoss_Robotics_Facility 1 9950
Protoss_Observatory 1 10152
10963
