Protoss_Gateway 3 9983
Protoss_Assimilator 1 2171
Protoss_Zealot 1 2956
Protoss_Cybernetics_Core 1 4008
Protoss_Dragoon 3 7851
Protoss_Robotics_Facility 1 5145
Protoss_Shuttle 1 6436
Protoss_Robotics_Support_Bay 1 6808
Protoss_Reaver 2 8966
Protoss_Nexus 1 8478
Protoss_Scarab 2 9625
9983
