Protoss_Gateway 2 7376
Protoss_Assimilator 1 3279
Protoss_Zealot 3 4889
Protoss_Cybernetics_Core 1 5148
Protoss_Dragoon 11 10799
Protoss_Robotics_Facility 1 9115
Protoss_Nexus 1 11977
Protoss_Shuttle 1 10973
11977
