Protoss_Gateway 3 10936
Protoss_Assimilator 1 3394
Protoss_Zealot 1 3991
Protoss_Cybernetics_Core 1 5313
Protoss_Dragoon 6 10721
Protoss_Robotics_Facility 1 7455
Protoss_Robotics_Support_Bay 1 7602
Protoss_Reaver 1 9676
Protoss_Nexus 1 11588
11588
