Protoss_Gateway 3 9493
Protoss_Assimilator 1 3123
Protoss_Cybernetics_Core 1 4376
Protoss_Zealot 1 4037
Protoss_Dragoon 10 11055
Protoss_Robotics_Facility 1 7188
Protoss_Nexus 1 9377
Protoss_Observatory 1 7401
Protoss_Observer 3 9867
Protoss_Citadel_of_Adun 1 10095
11055
