Protoss_Gateway 3 8895
Protoss_Assimilator 1 3253
Protoss_Zealot 2 8491
Protoss_Cybernetics_Core 1 5266
Protoss_Citadel_of_Adun 1 6585
Protoss_Dragoon 9 10747
Protoss_Templar_Archives 1 8827
Protoss_Dark_Templar 3 9719
Protoss_Robotics_Facility 1 11864
11864
