Protoss_Gateway 3 9171
Protoss_Assimilator 2 9340
Protoss_Zealot 2 4817
Protoss_Cybernetics_Core 1 4998
Protoss_Dragoon 8 10303
Protoss_Nexus 1 9309
Protoss_Robotics_Facility 1 8728
Protoss_Observatory 1 8844
Protoss_Citadel_of_Adun 1 9974
Protoss_Observer 2 10511
Protoss_Templar_Archives 1 11037
Protoss_Forge 1 10761
11037
