Protoss_Gateway 3 7259
Protoss_Assimilator 1 3169
Protoss_Cybernetics_Core 1 4388
Protoss_Dragoon 5 8691
Protoss_Robotics_Facility 1 8119
Protoss_Citadel_of_Adun 1 7703
Protoss_Forge 1 7989
Protoss_Templar_Archives 1 8802
Protoss_Photon_Cannon 3 11129
Protoss_Dark_Templar 2 9705
Protoss_High_Templar 2 10457
11129
