Protoss_Gateway 1 3358
Protoss_Assimilator 1 3359
Protoss_Zealot 2 5145
Protoss_Cybernetics_Core 1 5363
Protoss_Dragoon 7 10911
Protoss_Robotics_Facility 1 7429
Protoss_Robotics_Support_Bay 1 7515
Protoss_Nexus 1 10262
Protoss_Reaver 1 9139
Protoss_Observatory 1 8572
Protoss_Observer 1 9471
Protoss_Shuttle 1 10571
10911
