Protoss_Gateway 2 3937
Protoss_Zealot 13 9595
Protoss_Nexus 1 8095
Protoss_Assimilator 2 10108
Protoss_Cybernetics_Core 1 9121
Protoss_Citadel_of_Adun 1 10258
Protoss_Dragoon 2 10473
Protoss_Templar_Archives 1 11367
Protoss_Forge 1 10917
11367
