Protoss_Nexus 1 5839
Protoss_Gateway 2 9041
Protoss_Assimilator 1 4633
Protoss_Zealot 2 6021
Protoss_Cybernetics_Core 1 7367
Protoss_Dragoon 6 10641
Protoss_Robotics_Facility 1 10758
10758
