Protoss_Gateway 3 11407
Protoss_Zealot 2 4403
Protoss_Assimilator 1 3909
Protoss_Cybernetics_Core 1 5065
Protoss_Dragoon 11 11179
Protoss_Robotics_Facility 1 7982
Protoss_Nexus 1 9567
Protoss_Observatory 1 8091
Protoss_Observer 2 9463
11407
