Protoss_Gateway 5 10578
Protoss_Zealot 11 10789
Protoss_Nexus 1 7028
Protoss_Assimilator 2 9198
Protoss_Cybernetics_Core 1 7976
Protoss_Dragoon 3 9799
Protoss_Citadel_of_Adun 1 9346
Protoss_Templar_Archives 1 10654
Protoss_Forge 1 10654
10789
