Protoss_Gateway 2 7795
Protoss_Assimilator 1 3342
Protoss_Zealot 2 4905
Protoss_Cybernetics_Core 1 5109
Protoss_Dragoon 9 9851
Protoss_Robotics_Facility 1 7591
Protoss_Shuttle 1 8443
Protoss_Observatory 1 8011
Protoss_Observer 1 8865
Protoss_Robotics_Support_Bay 1 9005
Protoss_Reaver 1 10585
Protoss_Citadel_of_Adun 1 10860
10860
