Protoss_Nexus 1 5957
Protoss_Gateway 4 10017
Protoss_Forge 1 5684
Protoss_Zealot 14 10693
Protoss_Photon_Cannon 8 11165
Protoss_Assimilator 1 7142
Protoss_Cybernetics_Core 1 9238
Protoss_Citadel_of_Adun 1 11067
11165
