Protoss_Gateway 1 3738
Protoss_Assimilator 1 3488
Protoss_Zealot 3 5566
Protoss_Cybernetics_Core 1 5848
Protoss_Dragoon 2 10736
Protoss_Robotics_Facility 2 8374
Protoss_Observatory 1 8149
Protoss_Shuttle 1 8881
Protoss_Robotics_Support_Bay 1 8503
Protoss_Observer 2 9303
Protoss_Reaver 2 10811
10811
