Protoss_Gateway 2 7217
Protoss_Assimilator 2 10507
Protoss_Zealot 2 5081
Protoss_Cybernetics_Core 1 5283
Protoss_Dragoon 8 11017
Protoss_Nexus 1 9963
Protoss_Robotics_Facility 1 10008
Protoss_Citadel_of_Adun 1 10738
Protoss_Observatory 1 10131
Protoss_Observer 1 10947
11017
