Protoss_Gateway 3 10197
Protoss_Assimilator 1 3906
Protoss_Cybernetics_Core 1 4771
Protoss_Zealot 3 8581
Protoss_Dragoon 12 11129
Protoss_Robotics_Facility 1 7533
Protoss_Observatory 1 7859
Protoss_Observer 2 9349
Protoss_Nexus 1 10943
11129
