Protoss_Gateway 4 10967
Protoss_Assimilator 2 10872
Protoss_Zealot 2 4963
Protoss_Cybernetics_Core 1 5155
Protoss_Dragoon 11 10633
Protoss_Nexus 1 9049
Protoss_Robotics_Facility 1 8896
Protoss_Observatory 1 9047
Protoss_Observer 2 10425
10967
