Protoss_Gateway 2 5783
Protoss_Assimilator 1 3352
Protoss_Zealot 3 10617
Protoss_Cybernetics_Core 1 5430
Protoss_Dragoon 10 10105
Protoss_Robotics_Facility 1 8583
Protoss_Robotics_Support_Bay 1 8723
Protoss_Shield_Battery 1 8945
Protoss_Reaver 1 10375
Protoss_Observatory 1 9771
Protoss_Observer 1 10749
10749
