Protoss_Gateway 2 8621
Protoss_Assimilator 2 10124
Protoss_Cybernetics_Core 1 4323
Protoss_Zealot 1 4093
Protoss_Dragoon 9 10667
Protoss_Nexus 1 9359
Protoss_Robotics_Facility 1 9447
Protoss_Observatory 1 9675
Protoss_Observer 1 10443
10667
