Protoss_Gateway 3 10347
Protoss_Assimilator 1 3492
Protoss_Zealot 2 5007
Protoss_Cybernetics_Core 1 5200
Protoss_Dragoon 7 10289
Protoss_Robotics_Facility 1 8337
Protoss_Observatory 1 8489
Protoss_Observer 2 10163
Protoss_Nexus 1 11507
Protoss_Citadel_of_Adun 1 11235
11507
