Protoss_Gateway 2 7993
Protoss_Assimilator 1 3387
Protoss_Zealot 3 8547
Protoss_Cybernetics_Core 1 5421
Protoss_Dragoon 4 8425
Protoss_Citadel_of_Adun 1 7548
Protoss_Templar_Archives 1 8556
Protoss_Dark_Templar 4 10627
Protoss_Forge 1 9065
Protoss_Nexus 1 11485
Protoss_Photon_Cannon 2 10223
Protoss_High_Templar 1 10909
11485
