Protoss_Gateway 2 9778
Protoss_Assimilator 2 9430
Protoss_Zealot 2 5205
Protoss_Cybernetics_Core 1 5441
Protoss_Dragoon 4 8677
Protoss_Nexus 1 9673
Protoss_Citadel_of_Adun 1 8555
Protoss_Robotics_Facility 1 9765
Protoss_Templar_Archives 1 9687
Protoss_Shuttle 1 10625
Protoss_Dark_Templar 2 10519
Protoss_Forge 1 10444
Protoss_Observatory 1 10708
10708
