Protoss_Gateway 2 8020
Protoss_Assimilator 1 3265
Protoss_Zealot 2 4831
Protoss_Cybernetics_Core 1 4992
Protoss_Dragoon 8 10027
Protoss_Robotics_Facility 1 7547
Protoss_Shuttle 1 8465
Protoss_Observatory 1 7781
Protoss_Observer 1 8887
Protoss_Robotics_Support_Bay 1 8702
Protoss_Reaver 2 11471
Protoss_Nexus 1 12249
12249
