Protoss_Gateway 2 10833
Protoss_Assimilator 1 3191
Protoss_Zealot 2 5235
Protoss_Cybernetics_Core 1 5133
Protoss_Citadel_of_Adun 1 6173
Protoss_Dragoon 2 7165
Protoss_Templar_Archives 1 7163
Protoss_Forge 1 7263
Protoss_Dark_Templar 1 7917
Protoss_Photon_Cannon 3 10175
Protoss_High_Templar 3 10187
Protoss_Nexus 1 10781
10833
