Protoss_Gateway 1 3323
Protoss_Assimilator 1 3464
Protoss_Cybernetics_Core 1 4578
Protoss_Dragoon 7 10102
Protoss_Robotics_Facility 1 7432
Protoss_Observatory 1 7687
Protoss_Observer 2 10418
Protoss_Shuttle 1 9996
10418
