Protoss_Gateway 3 11209
Protoss_Assimilator 1 3293
Protoss_Zealot 2 4935
Protoss_Cybernetics_Core 1 5091
Protoss_Dragoon 11 10809
Protoss_Robotics_Facility 1 7492
Protoss_Observatory 1 7883
Protoss_Nexus 1 10483
Protoss_Observer 2 9315
Protoss_Robotics_Support_Bay 1 9251
Protoss_Reaver 1 10741
11209
