Protoss_Gateway 4 11315
Protoss_Assimilator 2 9516
Protoss_Zealot 2 3869
Protoss_Cybernetics_Core 1 5209
Protoss_Dragoon 8 10171
Protoss_Nexus 1 9402
Protoss_Robotics_Facility 1 8784
Protoss_Observatory 1 8869
Protoss_Citadel_of_Adun 1 9884
Protoss_Observer 2 10283
Protoss_Templar_Archives 1 10921
11315
