Protoss_Gateway 3 11052
Protoss_Assimilator 2 10013
Protoss_Zealot 2 5159
Protoss_Cybernetics_Core 1 5241
Protoss_Dragoon 4 8257
Protoss_Citadel_of_Adun 1 7133
Protoss_Templar_Archives 1 8147
Protoss_Nexus 1 10285
Protoss_Forge 1 8710
Protoss_Dark_Templar 1 9009
Protoss_Photon_Cannon 2 10093
Protoss_High_Templar 2 10541
11052
