Protoss_Assimilator 1 2811
Protoss_Gateway 3 7840
Protoss_Cybernetics_Core 1 4859
Protoss_Dragoon 1 5651
Protoss_Citadel_of_Adun 1 6060
Protoss_Zealot 11 10471
Protoss_Templar_Archives 1 10773
10773
