Protoss_Gateway 2 8027
Protoss_Assimilator 1 3230
Protoss_Zealot 2 4989
Protoss_Cybernetics_Core 1 5167
Protoss_Dragoon 7 9957
Protoss_Robotics_Facility 1 7731
Protoss_Shuttle 1 8627
Protoss_Observatory 1 8034
Protoss_Observer 1 9085
Protoss_Robotics_Support_Bay 1 9078
Protoss_Reaver 1 10667
Protoss_Nexus 1 12657
12657
