Protoss_Gateway 2 6650
Protoss_Assimilator 1 3297
Protoss_Cybernetics_Core 1 4407
Protoss_Zealot 1 4165
Protoss_Dragoon 11 10957
Protoss_Robotics_Facility 1 7797
Protoss_Shuttle 1 8661
Protoss_Observatory 1 8017
Protoss_Robotics_Support_Bay 1 8269
Protoss_Observer 2 10081
10957
