Protoss_Gateway 1 3247
Protoss_Assimilator 1 3330
Protoss_Cybernetics_Core 1 4437
Protoss_Zealot 1 4177
Protoss_Dragoon 7 10831
Protoss_Robotics_Facility 1 7497
Protoss_Shuttle 1 8451
Protoss_Observatory 1 7856
Protoss_Robotics_Support_Bay 1 8439
Protoss_Observer 1 8945
Protoss_Nexus 1 11320
Protoss_Reaver 2 11353
11353
