Protoss_Gateway 2 7945
Protoss_Zealot 2 4879
Protoss_Assimilator 2 10070
Protoss_Cybernetics_Core 1 5113
Protoss_Dragoon 8 10681
Protoss_Robotics_Facility 1 8196
Protoss_Observatory 1 8340
Protoss_Observer 2 9719
Protoss_Nexus 1 11397
Protoss_Citadel_of_Adun 1 10334
11397
