Protoss_Gateway 2 7535
Protoss_Assimilator 1 3323
Protoss_Zealot 2 4687
Protoss_Cybernetics_Core 1 5056
Protoss_Dragoon 8 9919
Protoss_Robotics_Facility 1 7234
Protoss_Shuttle 1 8035
Protoss_Observatory 1 7512
Protoss_Observer 1 8457
Protoss_Robotics_Support_Bay 1 8409
Protoss_Reaver 1 10003
Protoss_Nexus 1 12594
12594
