Protoss_Gateway 4 11399
Protoss_Zealot 2 4417
Protoss_Assimilator 1 4024
Protoss_Cybernetics_Core 1 5288
Protoss_Dragoon 8 9871
Protoss_Nexus 1 9943
Protoss_Robotics_Facility 1 10067
Protoss_Citadel_of_Adun 1 10704
Protoss_Observatory 1 10248
11399
