Protoss_Gateway 2 6741
Protoss_Assimilator 1 3274
Protoss_Cybernetics_Core 1 4440
Protoss_Zealot 1 4105
Protoss_Dragoon 9 11155
Protoss_Robotics_Facility 1 7755
Protoss_Shuttle 1 8559
Protoss_Observatory 1 8199
Protoss_Observer 1 8981
Protoss_Robotics_Support_Bay 1 8989
Protoss_Reaver 1 10701
Protoss_Nexus 1 12407
12407
