Protoss_Gateway 2 7931
Protoss_Assimilator 1 3153
Protoss_Zealot 2 4823
Protoss_Cybernetics_Core 1 5098
Protoss_Dragoon 10 11167
Protoss_Robotics_Facility 1 7860
Protoss_Observatory 1 7976
Protoss_Observer 2 9357
Protoss_Nexus 1 11257
Protoss_Robotics_Support_Bay 1 9609
Protoss_Reaver 1 11335
11335
