Protoss_Gateway 2 7941
Protoss_Assimilator 1 3291
Protoss_Zealot 2 4987
Protoss_Cybernetics_Core 1 5392
Protoss_Dragoon 10 11103
Protoss_Robotics_Facility 1 7747
Protoss_Shuttle 1 8545
Protoss_Observatory 1 8415
Protoss_Observer 1 9251
Protoss_Robotics_Support_Bay 1 9090
Protoss_Reaver 1 10599
Protoss_Nexus 1 12550
12550
