Protoss_Gateway 2 9083
Protoss_Assimilator 2 9599
Protoss_Zealot 2 4975
Protoss_Cybernetics_Core 1 5161
Protoss_Dragoon 7 10187
Protoss_Nexus 1 9436
Protoss_Robotics_Facility 1 8861
Protoss_Observatory 1 8953
Protoss_Robotics_Support_Bay 1 9000
Protoss_Observer 1 9771
Protoss_Reaver 1 11093
11093
