Protoss_Gateway 2 10567
Protoss_Assimilator 1 3331
Protoss_Zealot 2 4867
Protoss_Cybernetics_Core 1 5008
Protoss_Dragoon 7 10855
Protoss_Robotics_Facility 1 7470
Protoss_Robotics_Support_Bay 1 7569
Protoss_Shuttle 1 8861
Protoss_Nexus 1 11079
Protoss_Reaver 2 11183
Protoss_Observatory 1 9337
11183
