Protoss_Gateway 4 11039
Protoss_Assimilator 1 3198
Protoss_Zealot 2 4795
Protoss_Cybernetics_Core 1 4990
Protoss_Dragoon 8 10201
Protoss_Robotics_Facility 1 7814
Protoss_Observatory 1 7967
Protoss_Nexus 1 10500
Protoss_Observer 1 8745
Protoss_Robotics_Support_Bay 1 8603
Protoss_Reaver 2 11461
11461
