Protoss_Gateway 2 7015
Protoss_Assimilator 1 3828
Protoss_Zealot 2 5323
Protoss_Cybernetics_Core 1 5267
Protoss_Dragoon 9 11017
Protoss_Robotics_Facility 1 8461
Protoss_Observatory 1 8624
Protoss_Observer 1 9607
Protoss_Shuttle 1 10899
Protoss_Robotics_Support_Bay 1 10533
11017
