Protoss_Gateway 2 7579
Protoss_Assimilator 1 3309
Protoss_Zealot 2 4925
Protoss_Cybernetics_Core 1 5203
Protoss_Dragoon 8 11175
Protoss_Robotics_Facility 1 7571
Protoss_Shuttle 1 8473
Protoss_Robotics_Support_Bay 1 8315
Protoss_Observatory 1 8399
Protoss_Reaver 1 10081
Protoss_Observer 1 10413
Protoss_Nexus 1 12535
12535
