Protoss_Gateway 5 10545
Protoss_Zealot 2 4791
Protoss_Assimilator 1 4023
Protoss_Cybernetics_Core 1 5041
Protoss_Dragoon 11 11097
Protoss_Nexus 1 8915
Protoss_Robotics_Facility 1 8291
Protoss_Observatory 1 8832
Protoss_Observer 2 10521
11097
