Protoss_Gateway 2 8091
Protoss_Assimilator 1 3429
Protoss_Cybernetics_Core 1 4523
Protoss_Zealot 1 4247
Protoss_Dragoon 9 10657
Protoss_Robotics_Facility 1 7883
Protoss_Shuttle 1 8697
Protoss_Robotics_Support_Bay 1 8525
Protoss_Observatory 1 8625
Protoss_Observer 1 9395
Protoss_Reaver 1 11087
11087
