Protoss_Gateway 3 9464
Protoss_Assimilator 1 3373
Protoss_Zealot 2 5037
Protoss_Cybernetics_Core 1 5182
Protoss_Dragoon 14 10991
Protoss_Robotics_Facility 1 8740
Protoss_Observatory 1 8873
Protoss_Observer 2 10247
10991
