Protoss_Gateway 4 11426
Protoss_Assimilator 1 3326
Protoss_Zealot 2 5005
Protoss_Cybernetics_Core 1 5177
Protoss_Dragoon 11 10711
Protoss_Nexus 1 9621
Protoss_Robotics_Facility 1 11038
11426
