Protoss_Gateway 2 8471
Protoss_Zealot 2 5021
Protoss_Assimilator 2 9942
Protoss_Cybernetics_Core 1 5339
Protoss_Dragoon 10 10879
Protoss_Nexus 1 9098
Protoss_Robotics_Facility 1 9808
Protoss_Forge 1 10168
Protoss_Observatory 1 10004
Protoss_Observer 1 10781
10879
