Protoss_Gateway 2 10859
Protoss_Assimilator 2 10153
Protoss_Zealot 2 5047
Protoss_Cybernetics_Core 1 5235
Protoss_Dragoon 4 8451
Protoss_Citadel_of_Adun 1 7577
Protoss_Templar_Archives 1 8627
Protoss_Nexus 1 10611
Protoss_Forge 1 8983
Protoss_Dark_Templar 1 9367
Protoss_Photon_Cannon 3 11190
Protoss_High_Templar 2 10919
11190
