Protoss_Gateway 2 8228
Protoss_Assimilator 1 3170
Protoss_Zealot 2 5003
Protoss_Cybernetics_Core 1 5157
Protoss_Dragoon 10 10865
Protoss_Robotics_Facility 1 8092
Protoss_Shuttle 1 8915
Protoss_Observatory 1 8572
Protoss_Observer 1 9385
Protoss_Robotics_Support_Bay 1 9231
Protoss_Reaver 1 10895
10895
