Protoss_Gateway 2 10491
Protoss_Assimilator 2 10368
Protoss_Zealot 2 4969
Protoss_Cybernetics_Core 1 5157
Protoss_Dragoon 4 8169
Protoss_Citadel_of_Adun 1 7163
Protoss_Templar_Archives 1 8153
Protoss_Nexus 1 10149
Protoss_Forge 1 8575
Protoss_Dark_Templar 1 8981
Protoss_Photon_Cannon 4 10949
Protoss_High_Templar 2 10549
10949
