Protoss_Gateway 2 7223
Protoss_Zealot 2 4869
Protoss_Assimilator 1 4182
Protoss_Cybernetics_Core 1 5194
Protoss_Dragoon 11 10573
Protoss_Robotics_Facility 1 8630
Protoss_Observatory 1 8808
Protoss_Observer 1 9983
Protoss_Nexus 1 12728
12728
