Protoss_Gateway 4 9893
Protoss_Assimilator 1 3166
Protoss_Cybernetics_Core 1 4282
Protoss_Zealot 1 3961
Protoss_Citadel_of_Adun 1 5273
Protoss_Dragoon 11 11003
Protoss_Templar_Archives 1 6292
Protoss_Dark_Templar 1 7127
Protoss_Nexus 1 9235
Protoss_Robotics_Facility 1 11348
11348
