Protoss_Gateway 2 8097
Protoss_Assimilator 1 3352
Protoss_Zealot 2 4723
Protoss_Cybernetics_Core 1 5022
Protoss_Dragoon 10 10887
Protoss_Robotics_Facility 1 7777
Protoss_Shuttle 1 8661
Protoss_Robotics_Support_Bay 1 8318
Protoss_Reaver 1 9921
10887
