Protoss_Gateway 3 10882
Protoss_Assimilator 1 3341
Protoss_Zealot 2 4613
Protoss_Cybernetics_Core 1 5719
Protoss_Dragoon 10 10989
Protoss_Robotics_Facility 1 8040
Protoss_Observatory 1 8197
Protoss_Observer 2 9783
Protoss_Nexus 1 11838
Protoss_Robotics_Support_Bay 1 9818
Protoss_Reaver 1 11529
11838
