Protoss_Gateway 3 10961
Protoss_Assimilator 2 10043
Protoss_Zealot 2 4997
Protoss_Cybernetics_Core 1 5206
Protoss_Dragoon 4 8201
Protoss_Citadel_of_Adun 1 7306
Protoss_Templar_Archives 1 8301
Protoss_Nexus 1 10201
Protoss_Forge 1 8527
Protoss_Dark_Templar 1 9041
Protoss_Photon_Cannon 2 9880
Protoss_High_Templar 2 10545
10961
