Protoss_Gateway 2 7450
Protoss_Assimilator 1 3381
Protoss_Zealot 2 5023
Protoss_Cybernetics_Core 1 5207
Protoss_Dragoon 11 11111
Protoss_Robotics_Facility 1 7671
Protoss_Shuttle 1 8497
Protoss_Robotics_Support_Bay 1 8185
Protoss_Observatory 1 8707
Protoss_Reaver 1 9949
Protoss_Observer 2 10883
Protoss_Forge 1 10338
11111
