Protoss_Gateway 1 3346
Protoss_Assimilator 1 3381
Protoss_Zealot 2 5029
Protoss_Cybernetics_Core 1 5187
Protoss_Dragoon 4 8615
Protoss_Citadel_of_Adun 1 7732
Protoss_Nexus 1 10030
Protoss_Templar_Archives 1 8721
Protoss_Forge 1 8786
Protoss_Dark_Templar 3 10969
Protoss_Photon_Cannon 2 9769
10969
