Protoss_Gateway 2 10443
Protoss_Assimilator 2 10282
Protoss_Zealot 2 4989
Protoss_Cybernetics_Core 1 5260
Protoss_Dragoon 4 8269
Protoss_Citadel_of_Adun 1 7171
Protoss_Templar_Archives 1 8189
Protoss_Nexus 1 10159
Protoss_Forge 1 8479
Protoss_Dark_Templar 1 9021
Protoss_Photon_Cannon 5 11125
Protoss_High_Templar 2 10525
11125
