Protoss_Gateway 2 7535
Protoss_Assimilator 1 3430
Protoss_Zealot 2 5093
Protoss_Cybernetics_Core 1 5227
Protoss_Dragoon 11 10919
Protoss_Robotics_Facility 1 7693
Protoss_Shuttle 1 8559
Protoss_Robotics_Support_Bay 1 8477
Protoss_Reaver 1 9975
Protoss_Observatory 1 9418
Protoss_Observer 1 10307
10919
