Protoss_Gateway 2 7883
Protoss_Assimilator 1 3198
Protoss_Zealot 2 4863
Protoss_Cybernetics_Core 1 5074
Protoss_Dragoon 7 10481
Protoss_Robotics_Facility 1 7765
Protoss_Observatory 1 7871
Protoss_Observer 2 9321
Protoss_Nexus 1 10975
Protoss_Robotics_Support_Bay 1 9177
Protoss_Reaver 1 10773
Protoss_Citadel_of_Adun 1 11258
11258
