Protoss_Gateway 3 7429
Protoss_Assimilator 1 3284
Protoss_Zealot 2 4953
Protoss_Cybernetics_Core 1 5173
Protoss_Dragoon 14 10853
Protoss_Forge 1 10199
Protoss_Robotics_Facility 1 11423
11423
