Protoss_Gateway 2 8109
Protoss_Assimilator 1 3249
Protoss_Zealot 2 5079
Protoss_Cybernetics_Core 1 5188
Protoss_Dragoon 10 10961
Protoss_Robotics_Facility 1 9377
Protoss_Shuttle 1 10273
Protoss_Observatory 1 9751
Protoss_Robotics_Support_Bay 1 10296
Protoss_Observer 1 10695
10961
