Protoss_Gateway 4 9773
Protoss_Assimilator 1 3325
Protoss_Cybernetics_Core 1 4317
Protoss_Zealot 1 4255
Protoss_Dragoon 15 11119
Protoss_Robotics_Facility 1 7219
Protoss_Observatory 1 7386
Protoss_Observer 2 8761
11119
