Protoss_Gateway 2 7779
Protoss_Assimilator 1 3430
Protoss_Zealot 2 5311
Protoss_Cybernetics_Core 1 5479
Protoss_Dragoon 9 10553
Protoss_Robotics_Facility 1 7992
Protoss_Shuttle 1 9015
Protoss_Robotics_Support_Bay 1 8727
Protoss_Reaver 1 10231
Protoss_Observatory 1 9674
Protoss_Observer 1 10563
10563
