Protoss_Gateway 4 10883
Protoss_Assimilator 1 3373
Protoss_Zealot 2 4999
Protoss_Cybernetics_Core 1 5155
Protoss_Dragoon 11 10961
Protoss_Robotics_Facility 1 7576
Protoss_Observatory 1 7745
Protoss_Observer 2 9309
Protoss_Nexus 1 11133
11133
