Protoss_Gateway 2 7609
Protoss_Assimilator 1 3414
Protoss_Zealot 2 5133
Protoss_Cybernetics_Core 1 5259
Protoss_Dragoon 9 10385
Protoss_Robotics_Facility 1 7892
Protoss_Shuttle 1 8769
Protoss_Robotics_Support_Bay 1 8487
Protoss_Reaver 1 10147
Protoss_Observatory 1 9637
Protoss_Forge 1 10501
Protoss_Observer 1 10671
10671
