Protoss_Gateway 2 10603
Protoss_Assimilator 2 9743
Protoss_Zealot 2 5121
Protoss_Cybernetics_Core 1 5173
Protoss_Dragoon 4 8335
Protoss_Citadel_of_Adun 1 6891
Protoss_Templar_Archives 1 8131
Protoss_Nexus 1 10224
Protoss_Dark_Templar 1 9087
Protoss_Forge 1 8847
Protoss_Photon_Cannon 2 10143
Protoss_High_Templar 2 10591
10603
