Protoss_Gateway 3 10140
Protoss_Assimilator 1 3477
Protoss_Zealot 8 10333
Protoss_Cybernetics_Core 1 5299
Protoss_Shield_Battery 1 5933
Protoss_Dragoon 6 11093
Protoss_Robotics_Facility 1 9763
Protoss_Observatory 1 9881
Protoss_Observer 1 10649
11093
