Protoss_Gateway 2 3994
Protoss_Zealot 5 6001
Protoss_Assimilator 1 4486
Protoss_Cybernetics_Core 1 6261
Protoss_Dragoon 8 10977
Protoss_Robotics_Facility 1 9411
Protoss_Nexus 1 11516
Protoss_Observatory 1 9584
Protoss_Robotics_Support_Bay 1 9855
Protoss_Observer 1 10533
11516
