Protoss_Gateway 2 10879
Protoss_Forge 1 4088
Protoss_Photon_Cannon 7 8433
Protoss_Zealot 2 7519
Protoss_Nexus 1 9237
Protoss_Assimilator 1 7897
Protoss_Cybernetics_Core 1 9267
Protoss_Dragoon 2 10921
Protoss_Robotics_Facility 1 10924
Protoss_Citadel_of_Adun 1 11330
11330
