Protoss_Gateway 4 11379
Protoss_Assimilator 1 3788
Protoss_Cybernetics_Core 1 5146
Protoss_Zealot 2 5387
Protoss_Dragoon 9 10121
Protoss_Robotics_Facility 1 7461
Protoss_Observatory 1 7912
Protoss_Observer 2 9401
Protoss_Nexus 1 12452
12452
