Protoss_Gateway 2 5883
Protoss_Assimilator 1 3427
Protoss_Zealot 3 5579
Protoss_Cybernetics_Core 1 5111
Protoss_Dragoon 8 9977
Protoss_Robotics_Facility 1 8409
Protoss_Observatory 1 8670
Protoss_Observer 2 10041
Protoss_Robotics_Support_Bay 1 9675
Protoss_Nexus 1 12547
Protoss_Reaver 1 11665
12547
