Protoss_Gateway 3 9988
Protoss_Zealot 6 10539
Protoss_Nexus 1 8286
Protoss_Forge 2 7145
Protoss_Assimilator 2 10399
Protoss_Photon_Cannon 3 8923
Protoss_Cybernetics_Core 1 8877
Protoss_Dragoon 2 10239
Protoss_Robotics_Facility 1 11514
11514
