Protoss_Gateway 2 3813
Protoss_Assimilator 1 4040
Protoss_Cybernetics_Core 1 5160
Protoss_Zealot 3 10019
Protoss_Citadel_of_Adun 1 6577
Protoss_Forge 1 6703
Protoss_Templar_Archives 1 7859
Protoss_High_Templar 2 8839
Protoss_Nexus 1 11035
Protoss_Photon_Cannon 3 10967
Protoss_Dark_Templar 1 9713
Protoss_Archon 1 8993
11035
