Protoss_Gateway 3 9419
Protoss_Assimilator 2 4371
Protoss_Zealot 7 8065
Protoss_Cybernetics_Core 1 6193
Protoss_Dragoon 4 10631
Protoss_Citadel_of_Adun 1 8194
Protoss_Forge 1 8590
Protoss_Templar_Archives 1 9333
Protoss_Photon_Cannon 1 9963
Protoss_Dark_Templar 3 10255
Protoss_High_Templar 1 10455
Protoss_Nexus 1 12619
12619
