Protoss_Gateway 1 3432
Protoss_Assimilator 1 3420
Protoss_Zealot 2 4761
Protoss_Cybernetics_Core 1 4931
Protoss_Dragoon 5 9407
Protoss_Robotics_Facility 1 7667
Protoss_Observatory 1 7765
Protoss_Robotics_Support_Bay 1 7793
Protoss_Reaver 1 9477
9477
