Protoss_Gateway 2 4003
Protoss_Assimilator 1 2287
Protoss_Zealot 1 2947
Protoss_Cybernetics_Core 1 3383
Protoss_Dragoon 9 7807
Protoss_Robotics_Facility 1 6669
Protoss_Observatory 1 8179
8179
