Protoss_Gateway 2 5553
Protoss_Assimilator 1 3435
Protoss_Zealot 2 10675
Protoss_Cybernetics_Core 1 5103
Protoss_Dragoon 12 11133
Protoss_Robotics_Facility 1 7951
Protoss_Shuttle 1 8787
Protoss_Robotics_Support_Bay 1 8143
Protoss_Reaver 2 10981
Protoss_Observatory 1 10304
11133
