Protoss_Gateway 2 8155
Protoss_Assimilator 1 3265
Protoss_Zealot 2 4899
Protoss_Cybernetics_Core 1 5015
Protoss_Dragoon 8 11019
Protoss_Robotics_Facility 1 7779
Protoss_Shuttle 1 8663
Protoss_Observatory 1 8236
Protoss_Observer 1 9085
Protoss_Robotics_Support_Bay 1 9205
Protoss_Nexus 1 11961
Protoss_Reaver 1 11145
11961
