Protoss_Gateway 3 9567
Protoss_Assimilator 2 10577
Protoss_Cybernetics_Core 1 4335
Protoss_Zealot 1 4033
Protoss_Dragoon 10 11115
Protoss_Robotics_Facility 1 7991
Protoss_Nexus 1 10038
Protoss_Observatory 1 8433
Protoss_Observer 2 9807
Protoss_Citadel_of_Adun 1 11214
11214
