Protoss_Gateway 2 7801
Protoss_Assimilator 1 3159
Protoss_Zealot 2 4903
Protoss_Cybernetics_Core 1 5110
Protoss_Dragoon 8 11085
Protoss_Robotics_Facility 1 7443
Protoss_Observatory 1 7666
Protoss_Robotics_Support_Bay 1 7864
Protoss_Observer 1 8669
Protoss_Shuttle 1 9904
Protoss_Reaver 1 11046
Protoss_Nexus 1 12601
12601
