Protoss_Gateway 3 8977
Protoss_Assimilator 1 2162
Protoss_Zealot 2 3717
Protoss_Cybernetics_Core 1 3432
Protoss_Dragoon 10 9965
Protoss_Robotics_Facility 1 5003
Protoss_Robotics_Support_Bay 1 6291
Protoss_Reaver 2 8285
Protoss_Observatory 1 7289
Protoss_Observer 1 8029
Protoss_Scarab 1 8542
Protoss_Shuttle 1 9485
9965
