Protoss_Gateway 2 8247
Protoss_Assimilator 2 9225
Protoss_Cybernetics_Core 1 4731
Protoss_Zealot 2 9931
Protoss_Dragoon 8 11035
Protoss_Nexus 1 8910
Protoss_Citadel_of_Adun 1 9460
Protoss_Robotics_Facility 1 10587
Protoss_Templar_Archives 1 10892
Protoss_Observatory 1 10691
11035
