Protoss_Gateway 2 8153
Protoss_Assimilator 2 9611
Protoss_Zealot 2 4815
Protoss_Cybernetics_Core 1 5118
Protoss_Dragoon 3 7515
Protoss_Citadel_of_Adun 1 7042
Protoss_Nexus 1 8954
Protoss_Templar_Archives 1 8219
Protoss_Forge 1 8467
Protoss_Dark_Templar 2 8977
Protoss_Photon_Cannon 2 9643
Protoss_High_Templar 4 11053
11053
