Protoss_Gateway 2 6671
Protoss_Assimilator 1 3187
Protoss_Cybernetics_Core 1 4356
Protoss_Dragoon 9 9189
Protoss_Robotics_Facility 1 9607
Protoss_Observatory 1 9738
Protoss_Zealot 1 10063
Protoss_Nexus 1 12201
Protoss_Observer 1 10509
Protoss_Robotics_Support_Bay 1 10434
12201
