Protoss_Gateway 4 10979
Protoss_Assimilator 1 3177
Protoss_Zealot 2 4953
Protoss_Cybernetics_Core 1 5141
Protoss_Dragoon 12 10867
Protoss_Robotics_Facility 1 7389
Protoss_Observatory 1 8019
Protoss_Observer 2 9427
10979
