Protoss_Gateway 2 6775
Protoss_Assimilator 2 10701
Protoss_Zealot 2 4885
Protoss_Cybernetics_Core 1 5037
Protoss_Dragoon 3 8869
Protoss_Citadel_of_Adun 1 6275
Protoss_Templar_Archives 1 7261
Protoss_Dark_Templar 4 9245
Protoss_Nexus 1 10387
Protoss_Forge 1 8764
Protoss_Photon_Cannon 4 10300
Protoss_High_Templar 2 10771
10771
