Protoss_Gateway 2 5543
Protoss_Assimilator 1 3300
Protoss_Zealot 3 9391
Protoss_Cybernetics_Core 1 4831
Protoss_Dragoon 11 10931
Protoss_Robotics_Facility 1 8453
Protoss_Observatory 1 8541
Protoss_Robotics_Support_Bay 1 9032
Protoss_Observer 1 9373
Protoss_Nexus 1 11661
Protoss_Reaver 1 10925
11661
