Protoss_Gateway 2 7271
Protoss_Assimilator 1 3347
Protoss_Zealot 2 4657
Protoss_Cybernetics_Core 1 4999
Protoss_Dragoon 9 11053
Protoss_Robotics_Facility 1 7575
Protoss_Observatory 1 7772
Protoss_Observer 2 9863
Protoss_Nexus 1 11374
Protoss_Robotics_Support_Bay 1 9550
Protoss_Reaver 1 11499
11499
