Protoss_Gateway 2 10775
Protoss_Assimilator 1 3136
Protoss_Zealot 3 7385
Protoss_Cybernetics_Core 1 5246
Protoss_Dragoon 6 10973
Protoss_Nexus 3 12841
Protoss_Robotics_Facility 1 9590
Protoss_Observatory 1 9715
12841
