Protoss_Gateway 2 7815
Protoss_Assimilator 1 3330
Protoss_Zealot 2 4799
Protoss_Cybernetics_Core 1 5126
Protoss_Dragoon 8 10431
Protoss_Robotics_Facility 1 7832
Protoss_Observatory 1 8096
Protoss_Observer 1 9031
Protoss_Robotics_Support_Bay 1 9120
Protoss_Nexus 1 11593
11593
