Protoss_Gateway 2 3864
Protoss_Zealot 6 5755
Protoss_Assimilator 1 6649
Protoss_Cybernetics_Core 1 7367
Protoss_Nexus 1 9655
Protoss_Dragoon 6 10459
Protoss_Forge 1 8878
Protoss_Photon_Cannon 1 10049
Protoss_Robotics_Facility 1 11689
11689
