Protoss_Gateway 3 7909
Protoss_Zealot 6 6375
Protoss_Assimilator 1 5778
Protoss_Cybernetics_Core 1 7263
Protoss_Dragoon 5 9519
Protoss_Citadel_of_Adun 1 8503
Protoss_Templar_Archives 1 9534
Protoss_Forge 1 9581
Protoss_Dark_Templar 2 10401
Protoss_Photon_Cannon 1 10681
10681
