Protoss_Gateway 2 7644
Protoss_Assimilator 1 3239
Protoss_Cybernetics_Core 1 5088
Protoss_Zealot 1 4815
Protoss_Dragoon 9 10720
Protoss_Robotics_Facility 1 7709
Protoss_Observatory 1 7849
Protoss_Observer 2 9467
Protoss_Robotics_Support_Bay 1 9754
Protoss_Shuttle 1 10549
Protoss_Nexus 1 12664
12664
