Protoss_Gateway 3 8465
Protoss_Assimilator 2 10124
Protoss_Zealot 2 4887
Protoss_Cybernetics_Core 1 5092
Protoss_Dragoon 10 11093
Protoss_Nexus 1 8933
Protoss_Robotics_Facility 1 8470
Protoss_Observatory 1 8617
Protoss_Observer 2 10757
Protoss_Citadel_of_Adun 1 10324
11093
