Protoss_Gateway 3 9841
Protoss_Assimilator 1 3272
Protoss_Zealot 4 10291
Protoss_Cybernetics_Core 1 4879
Protoss_Dragoon 11 10601
Protoss_Robotics_Facility 1 7740
Protoss_Observatory 1 8283
Protoss_Observer 1 9155
Protoss_Robotics_Support_Bay 1 9705
Protoss_Shuttle 1 11291
11291
