Protoss_Gateway 3 8861
Protoss_Zealot 5 6031
Protoss_Assimilator 1 4713
Protoss_Cybernetics_Core 1 5877
Protoss_Dragoon 8 11103
Protoss_Robotics_Facility 1 10089
Protoss_Shuttle 1 10889
Protoss_Robotics_Support_Bay 1 10391
11103
