Protoss_Gateway 4 10965
Protoss_Forge 1 3577
Protoss_Zealot 9 9293
Protoss_Photon_Cannon 8 8067
Protoss_Assimilator 1 8922
Protoss_Cybernetics_Core 1 10216
Protoss_Dragoon 1 11019
11019
