Protoss_Gateway 3 9953
Protoss_Assimilator 1 3323
Protoss_Zealot 4 9951
Protoss_Cybernetics_Core 1 5313
Protoss_Dragoon 8 10759
Protoss_Robotics_Facility 1 7977
Protoss_Shuttle 1 8839
Protoss_Observatory 1 8424
Protoss_Robotics_Support_Bay 1 8963
Protoss_Observer 1 9261
Protoss_Reaver 1 10897
10897
