Protoss_Gateway 3 9135
Protoss_Assimilator 1 3422
Protoss_Zealot 2 4727
Protoss_Cybernetics_Core 1 5115
Protoss_Dragoon 11 10799
Protoss_Robotics_Facility 1 8383
Protoss_Robotics_Support_Bay 1 8739
Protoss_Reaver 1 10231
Protoss_Observatory 1 9642
Protoss_Observer 1 10911
10911
