Protoss_Gateway 3 8963
Protoss_Assimilator 1 3521
Protoss_Zealot 3 9759
Protoss_Cybernetics_Core 1 4874
Protoss_Dragoon 11 10853
Protoss_Nexus 1 9624
Protoss_Robotics_Facility 1 10125
Protoss_Observatory 1 10319
10853
