Protoss_Gateway 3 8261
Protoss_Assimilator 1 3376
Protoss_Cybernetics_Core 1 4439
Protoss_Dragoon 14 11053
Protoss_Robotics_Facility 1 7982
Protoss_Observatory 1 8439
Protoss_Observer 1 9509
Protoss_Nexus 1 12219
12219
