Protoss_Gateway 2 8814
Protoss_Assimilator 1 3298
Protoss_Zealot 2 4867
Protoss_Cybernetics_Core 1 5029
Protoss_Dragoon 8 10429
Protoss_Robotics_Facility 1 7379
Protoss_Shuttle 1 8181
Protoss_Observatory 1 7713
Protoss_Observer 1 8614
Protoss_Robotics_Support_Bay 1 8397
Protoss_Reaver 2 11487
Protoss_Nexus 1 12502
12502
