Protoss_Gateway 2 9533
Protoss_Assimilator 1 3300
Protoss_Zealot 2 5191
Protoss_Cybernetics_Core 1 5072
Protoss_Dragoon 8 10901
Protoss_Robotics_Facility 1 6983
Protoss_Shuttle 1 7789
Protoss_Robotics_Support_Bay 1 7277
Protoss_Reaver 1 8931
Protoss_Observatory 1 8902
Protoss_Observer 2 10321
Protoss_Nexus 1 12223
12223
