Protoss_Gateway 2 7383
Protoss_Assimilator 1 3367
Protoss_Zealot 2 4987
Protoss_Cybernetics_Core 1 5095
Protoss_Dragoon 10 10799
Protoss_Robotics_Facility 1 7570
Protoss_Shuttle 1 8795
Protoss_Observatory 1 8361
Protoss_Observer 1 9341
Protoss_Robotics_Support_Bay 1 9221
Protoss_Nexus 1 11447
Protoss_Reaver 1 11193
11447
