Protoss_Gateway 2 7455
Protoss_Assimilator 1 3215
Protoss_Zealot 2 5035
Protoss_Cybernetics_Core 1 5223
Protoss_Dragoon 9 10797
Protoss_Robotics_Facility 1 7641
Protoss_Observatory 1 8000
Protoss_Observer 1 8793
Protoss_Robotics_Support_Bay 1 8916
Protoss_Nexus 1 11497
Protoss_Reaver 1 10661
11497
