Protoss_Gateway 2 7360
Protoss_Assimilator 1 3160
Protoss_Zealot 2 4839
Protoss_Cybernetics_Core 1 5187
Protoss_Dragoon 11 10633
Protoss_Robotics_Facility 1 9095
Protoss_Robotics_Support_Bay 1 10082
Protoss_Shuttle 1 10891
Protoss_Observatory 1 10474
10891
