Protoss_Gateway 3 7247
Protoss_Assimilator 1 3434
Protoss_Zealot 2 4833
Protoss_Cybernetics_Core 1 5071
Protoss_Dragoon 15 10877
Protoss_Robotics_Facility 1 8595
Protoss_Observatory 1 8952
Protoss_Observer 1 10279
10877
