Protoss_Gateway 3 11121
Protoss_Assimilator 1 3395
Protoss_Zealot 1 3901
Protoss_Cybernetics_Core 1 4683
Protoss_Dragoon 10 10571
Protoss_Robotics_Facility 1 8591
Protoss_Observatory 1 8699
Protoss_Observer 2 10163
Protoss_Nexus 1 11699
11699
