Protoss_Gateway 2 5905
Protoss_Assimilator 1 3176
Protoss_Zealot 1 3797
Protoss_Cybernetics_Core 1 5219
Protoss_Dragoon 10 10571
Protoss_Robotics_Facility 1 8378
Protoss_Observatory 1 8577
Protoss_Observer 1 9391
Protoss_Shuttle 1 10473
Protoss_Nexus 1 11952
Protoss_Robotics_Support_Bay 1 9928
11952
