Protoss_Gateway 2 11081
Protoss_Assimilator 1 3543
Protoss_Cybernetics_Core 1 5186
Protoss_Zealot 1 4996
Protoss_Dragoon 4 10323
Protoss_Robotics_Facility 1 7148
Protoss_Shuttle 1 8026
Protoss_Observatory 1 7468
Protoss_Robotics_Support_Bay 1 7833
Protoss_Observer 1 8448
Protoss_Reaver 2 11276
11276
