Protoss_Gateway 2 7441
Protoss_Assimilator 1 3564
Protoss_Zealot 1 4151
Protoss_Cybernetics_Core 1 5249
Protoss_Dragoon 7 10266
Protoss_Robotics_Facility 1 6768
Protoss_Shuttle 1 7606
Protoss_Observatory 1 6978
Protoss_Observer 1 8028
Protoss_Robotics_Support_Bay 1 8343
Protoss_Reaver 2 11231
11231
