Protoss_Gateway 2 5112
Protoss_Assimilator 2 9185
Protoss_Zealot 1 3775
Protoss_Cybernetics_Core 1 4698
Protoss_Dragoon 13 10935
Protoss_Nexus 1 9299
Protoss_Citadel_of_Adun 1 9055
Protoss_Templar_Archives 1 10487
Protoss_Robotics_Facility 1 11806
11806
