Protoss_Gateway 2 8140
Protoss_Assimilator 2 10719
Protoss_Zealot 2 5531
Protoss_Cybernetics_Core 1 5738
Protoss_Dragoon 6 11085
Protoss_Robotics_Facility 1 8149
Protoss_Observatory 1 8235
Protoss_Robotics_Support_Bay 1 8395
Protoss_Observer 1 9013
Protoss_Nexus 1 11271
Protoss_Reaver 1 11059
11271
