Protoss_Gateway 4 9265
Protoss_Zealot 2 5181
Protoss_Nexus 1 6849
Protoss_Assimilator 1 5351
Protoss_Forge 1 5954
Protoss_Cybernetics_Core 1 6759
Protoss_Photon_Cannon 4 10985
Protoss_Dragoon 10 10887
10985
