Protoss_Gateway 2 7284
Protoss_Assimilator 1 3260
Protoss_Zealot 2 4779
Protoss_Cybernetics_Core 1 4925
Protoss_Citadel_of_Adun 1 6333
Protoss_Dragoon 3 10964
Protoss_Templar_Archives 1 7363
Protoss_Dark_Templar 2 8277
Protoss_Forge 1 7973
Protoss_Nexus 1 10839
Protoss_Photon_Cannon 2 10041
Protoss_High_Templar 2 10189
10964
