Protoss_Gateway 2 7750
Protoss_Assimilator 1 3308
Protoss_Zealot 2 4895
Protoss_Cybernetics_Core 1 5151
Protoss_Dragoon 6 9405
Protoss_Robotics_Facility 1 7849
Protoss_Shuttle 1 8725
Protoss_Robotics_Support_Bay 1 8548
Protoss_Reaver 1 10041
Protoss_Observatory 1 10113
10113
