Protoss_Gateway 2 7535
Protoss_Assimilator 1 3403
Protoss_Zealot 2 5061
Protoss_Cybernetics_Core 1 5283
Protoss_Dragoon 7 10695
Protoss_Citadel_of_Adun 1 7198
Protoss_Templar_Archives 1 8215
Protoss_Dark_Templar 4 9943
Protoss_Forge 1 8935
Protoss_Nexus 1 12545
12545
