Protoss_Gateway 3 10129
Protoss_Assimilator 1 3483
Protoss_Cybernetics_Core 1 4633
Protoss_Dragoon 13 11076
Protoss_Robotics_Facility 1 8153
Protoss_Observatory 1 8250
Protoss_Observer 1 9026
Protoss_Robotics_Support_Bay 1 10701
11076
