Protoss_Gateway 2 7627
Protoss_Assimilator 1 3343
Protoss_Zealot 2 5011
Protoss_Cybernetics_Core 1 5323
Protoss_Dragoon 7 9591
Protoss_Robotics_Facility 1 7525
Protoss_Shuttle 1 8355
Protoss_Observatory 1 8199
Protoss_Observer 1 9109
Protoss_Nexus 1 11475
Protoss_Robotics_Support_Bay 1 9551
Protoss_Reaver 1 11299
11475
