Protoss_Gateway 3 11269
Protoss_Assimilator 1 3365
Protoss_Zealot 2 4961
Protoss_Cybernetics_Core 1 5187
Protoss_Dragoon 10 11109
Protoss_Robotics_Facility 1 7808
Protoss_Observatory 1 7963
Protoss_Observer 1 8891
Protoss_Robotics_Support_Bay 1 8730
Protoss_Reaver 1 10525
Protoss_Nexus 1 12223
12223
