Protoss_Gateway 3 9758
Protoss_Assimilator 1 2375
Protoss_Cybernetics_Core 1 3108
Protoss_Robotics_Facility 1 4258
Protoss_Dragoon 5 9941
Protoss_Shuttle 1 5546
Protoss_Robotics_Support_Bay 1 5653
Protoss_Reaver 3 8666
Protoss_Observatory 1 9268
Protoss_Scarab 7 9981
Protoss_Nexus 1 9603
9981
