Protoss_Gateway 2 6887
Protoss_Assimilator 1 3574
Protoss_Zealot 1 3687
Protoss_Cybernetics_Core 1 5274
Protoss_Dragoon 7 10853
Protoss_Citadel_of_Adun 1 6191
Protoss_Templar_Archives 1 7110
Protoss_Forge 1 6938
Protoss_Dark_Templar 4 9055
Protoss_Photon_Cannon 5 9212
Protoss_Nexus 1 12413
12413
