Protoss_Gateway 2 5673
Protoss_Assimilator 1 3534
Protoss_Cybernetics_Core 1 4698
Protoss_Dragoon 10 10611
Protoss_Robotics_Facility 1 8122
Protoss_Observatory 1 8323
Protoss_Observer 1 9106
Protoss_Robotics_Support_Bay 1 9023
Protoss_Shuttle 1 10391
10611
