Protoss_Gateway 2 6762
Protoss_Zealot 2 4949
Protoss_Assimilator 2 10935
Protoss_Cybernetics_Core 1 5434
Protoss_Dragoon 12 11037
Protoss_Robotics_Facility 1 8485
Protoss_Observatory 1 8678
Protoss_Observer 2 10003
Protoss_Nexus 1 11519
Protoss_Citadel_of_Adun 1 10862
11519
