Protoss_Gateway 2 10743
Protoss_Assimilator 1 3604
Protoss_Cybernetics_Core 1 4747
Protoss_Robotics_Facility 1 6328
Protoss_Dragoon 6 10906
Protoss_Shuttle 1 7131
Protoss_Observatory 1 6618
Protoss_Observer 1 8001
Protoss_Robotics_Support_Bay 1 7889
Protoss_Reaver 2 10911
10911
