Protoss_Gateway 2 5838
Protoss_Assimilator 1 3418
Protoss_Cybernetics_Core 1 4478
Protoss_Dragoon 14 10863
Protoss_Forge 1 8767
Protoss_Photon_Cannon 1 9906
Protoss_Robotics_Facility 1 11527
11527
