Protoss_Gateway 2 4017
Protoss_Assimilator 2 4927
Protoss_Zealot 5 5181
Protoss_Cybernetics_Core 1 6217
Protoss_Dragoon 9 10339
Protoss_Forge 1 8026
Protoss_Nexus 1 11244
11244
