Protoss_Gateway 2 8484
Protoss_Assimilator 1 3304
Protoss_Zealot 2 4811
Protoss_Cybernetics_Core 1 5010
Protoss_Dragoon 9 10937
Protoss_Robotics_Facility 1 7803
Protoss_Shuttle 1 8679
Protoss_Observatory 1 8049
Protoss_Observer 1 9183
Protoss_Robotics_Support_Bay 1 9177
Protoss_Reaver 1 10725
10937
