Protoss_Gateway 2 7943
Protoss_Assimilator 1 3377
Protoss_Zealot 2 4989
Protoss_Cybernetics_Core 1 5220
Protoss_Dragoon 9 10801
Protoss_Robotics_Facility 1 7565
Protoss_Shuttle 1 8519
Protoss_Observatory 1 7952
Protoss_Robotics_Support_Bay 1 8673
Protoss_Observer 1 8941
Protoss_Reaver 1 10263
Protoss_Nexus 1 12269
12269
