Protoss_Gateway 2 6751
Protoss_Assimilator 1 3173
Protoss_Cybernetics_Core 1 4333
Protoss_Dragoon 13 10887
Protoss_Robotics_Facility 1 8010
Protoss_Observatory 1 8099
Protoss_Observer 3 10663
Protoss_Nexus 1 12283
12283
