Protoss_Gateway 1 3381
Protoss_Assimilator 1 3334
Protoss_Zealot 2 4853
Protoss_Cybernetics_Core 1 5083
Protoss_Dragoon 2 7159
Protoss_Citadel_of_Adun 1 6235
Protoss_Templar_Archives 1 7225
Protoss_Forge 1 7525
Protoss_Dark_Templar 2 8765
Protoss_High_Templar 3 11171
Protoss_Nexus 1 11604
Protoss_Photon_Cannon 5 11031
Psionic_Storm 1 9595
11604
