Protoss_Gateway 3 9529
Protoss_Assimilator 1 3475
Protoss_Cybernetics_Core 1 4623
Protoss_Dragoon 14 11073
Protoss_Robotics_Facility 1 9058
Protoss_Observatory 1 9192
Protoss_Observer 1 10406
Protoss_Robotics_Support_Bay 1 10718
11073
