Protoss_Nexus 1 5690
Protoss_Gateway 5 11030
Protoss_Assimilator 2 8493
Protoss_Zealot 8 7848
Protoss_Cybernetics_Core 1 7213
Protoss_Citadel_of_Adun 1 8548
Protoss_Dragoon 2 9751
Protoss_Forge 1 8573
Protoss_Templar_Archives 1 9576
Protoss_Photon_Cannon 4 10148
Protoss_Dark_Templar 2 10376
11030
