Protoss_Gateway 4 10274
Protoss_Zealot 8 10866
Protoss_Assimilator 1 3943
Protoss_Cybernetics_Core 1 5350
Protoss_Robotics_Facility 1 6838
Protoss_Dragoon 4 8866
Protoss_Observatory 1 6942
Protoss_Observer 1 7726
Protoss_Nexus 1 10243
Protoss_Citadel_of_Adun 1 10923
10923
