Protoss_Nexus 1 5414
Protoss_Gateway 4 11200
Protoss_Assimilator 2 4616
Protoss_Cybernetics_Core 1 5781
Protoss_Dragoon 9 9748
Protoss_Robotics_Facility 1 9703
Protoss_Zealot 2 9778
Protoss_Observatory 1 9832
Protoss_Observer 1 10716
11200
