Protoss_Gateway 3 10803
Protoss_Assimilator 1 3443
Protoss_Zealot 3 5436
Protoss_Cybernetics_Core 1 5598
Protoss_Dragoon 8 11096
Protoss_Nexus 2 10053
Protoss_Robotics_Facility 1 10203
Protoss_Shield_Battery 1 9173
Protoss_Observatory 1 10502
11096
