Protoss_Gateway 3 10179
Protoss_Zealot 6 6466
Protoss_Assimilator 1 5447
Protoss_Cybernetics_Core 1 6798
Protoss_Dragoon 8 11171
Protoss_Robotics_Facility 1 9043
Protoss_Observatory 1 9343
Protoss_Observer 2 10786
11171
