Protoss_Gateway 3 8940
Protoss_Assimilator 1 3509
Protoss_Cybernetics_Core 1 4621
Protoss_Dragoon 12 10721
Protoss_Robotics_Facility 1 6538
Protoss_Observatory 1 6698
Protoss_Observer 2 10581
10721
