Protoss_Gateway 3 11348
Protoss_Zealot 6 6546
Protoss_Assimilator 1 5778
Protoss_Cybernetics_Core 1 7785
Protoss_Citadel_of_Adun 1 8856
Protoss_Dragoon 2 8711
Protoss_Templar_Archives 1 9906
Protoss_Forge 1 10302
Protoss_Dark_Templar 2 10776
11348
