Protoss_Gateway 2 7688
Protoss_Assimilator 1 3563
Protoss_Zealot 3 6866
Protoss_Cybernetics_Core 1 5865
Protoss_Nexus 1 8604
Protoss_Dragoon 8 10810
Protoss_Shield_Battery 1 7886
Protoss_Citadel_of_Adun 1 10403
Protoss_Robotics_Facility 1 11182
Protoss_Templar_Archives 1 11411
11411
