Protoss_Gateway 2 4023
Protoss_Zealot 7 6891
Protoss_Assimilator 1 4990
Protoss_Cybernetics_Core 1 6695
Protoss_Dragoon 8 10461
Protoss_Robotics_Facility 1 9868
Protoss_Observatory 1 10328
10461
