Protoss_Gateway 1 3398
Protoss_Assimilator 1 3429
Protoss_Cybernetics_Core 1 4583
Protoss_Zealot 1 4311
Protoss_Dragoon 4 10807
Protoss_Robotics_Facility 1 6588
Protoss_Shuttle 1 7413
Protoss_Observatory 1 6766
Protoss_Robotics_Support_Bay 1 7092
Protoss_Observer 2 10947
Protoss_Reaver 2 10615
10947
