Protoss_Gateway 2 8824
Protoss_Assimilator 1 4149
Protoss_Zealot 1 4231
Protoss_Cybernetics_Core 1 5747
Protoss_Dragoon 8 10719
Protoss_Robotics_Facility 1 7338
Protoss_Observatory 1 7507
Protoss_Observer 1 8379
Protoss_Shuttle 1 9683
Protoss_Robotics_Support_Bay 1 9767
Protoss_Reaver 1 11269
11269
