Protoss_Gateway 3 7806
Protoss_Zealot 17 9975
Protoss_Shield_Battery 1 6973
Protoss_Assimilator 1 8804
Protoss_Cybernetics_Core 1 9763
Protoss_Dragoon 2 10817
Protoss_Citadel_of_Adun 1 11382
11382
