Protoss_Gateway 2 7658
Protoss_Assimilator 1 3849
Protoss_Zealot 3 10116
Protoss_Cybernetics_Core 1 5333
Protoss_Dragoon 8 10361
Protoss_Robotics_Facility 1 9528
Protoss_Observatory 1 9633
Protoss_Robotics_Support_Bay 1 9723
Protoss_Observer 1 10411
10411
