Protoss_Gateway 2 7967
Protoss_Assimilator 1 3483
Protoss_Zealot 2 4971
Protoss_Cybernetics_Core 1 5206
Protoss_Dragoon 7 10441
Protoss_Robotics_Facility 1 7325
Protoss_Shuttle 1 8236
Protoss_Robotics_Support_Bay 1 7763
Protoss_Reaver 1 9406
Protoss_Observatory 1 8508
Protoss_Observer 1 9738
Protoss_Nexus 1 12738
12738
