Protoss_Gateway 3 8408
Protoss_Zealot 5 5611
Protoss_Assimilator 1 4680
Protoss_Cybernetics_Core 1 5638
Protoss_Dragoon 9 10301
Protoss_Forge 1 8027
Protoss_Photon_Cannon 1 9893
Protoss_Robotics_Facility 1 11675
11675
