Protoss_Gateway 3 11373
Protoss_Assimilator 1 3998
Protoss_Zealot 3 5841
Protoss_Cybernetics_Core 1 7256
Protoss_Dragoon 5 10921
Protoss_Robotics_Facility 1 9518
Protoss_Nexus 1 11381
Protoss_Observatory 1 9645
Protoss_Observer 1 10431
11381
