Protoss_Gateway 2 4043
Protoss_Zealot 7 7056
Protoss_Assimilator 1 4959
Protoss_Cybernetics_Core 1 6837
Protoss_Citadel_of_Adun 1 8056
Protoss_Dragoon 3 11056
Protoss_Robotics_Facility 1 9086
Protoss_Templar_Archives 1 9173
Protoss_Shuttle 1 9896
Protoss_Forge 1 9568
Protoss_Dark_Templar 2 9941
Protoss_Photon_Cannon 2 10573
11056
