Protoss_Gateway 3 10842
Protoss_Zealot 5 10887
Protoss_Assimilator 1 5163
Protoss_Cybernetics_Core 1 6263
Protoss_Dragoon 10 10375
Protoss_Forge 1 8716
Protoss_Citadel_of_Adun 1 11018
Protoss_Photon_Cannon 1 11002
11018
