Protoss_Gateway 2 9681
Protoss_Assimilator 1 3309
Protoss_Zealot 2 4939
Protoss_Cybernetics_Core 1 4999
Protoss_Robotics_Facility 1 6465
Protoss_Dragoon 7 11155
Protoss_Shuttle 1 7267
Protoss_Observatory 1 6797
Protoss_Robotics_Support_Bay 1 7302
Protoss_Observer 2 10560
Protoss_Reaver 2 10197
11155
