Protoss_Gateway 3 8799
Protoss_Assimilator 1 3659
Protoss_Zealot 1 3945
Protoss_Cybernetics_Core 1 5063
Protoss_Robotics_Facility 1 6550
Protoss_Dragoon 10 10589
Protoss_Observatory 1 7029
Protoss_Observer 2 8525
Protoss_Nexus 1 11712
11712
