Protoss_Gateway 2 3999
Protoss_Zealot 8 7161
Protoss_Assimilator 1 6028
Protoss_Cybernetics_Core 1 7159
Protoss_Dragoon 6 10681
Protoss_Robotics_Facility 1 9558
Protoss_Shuttle 1 10501
Protoss_Robotics_Support_Bay 1 9987
Protoss_Forge 1 10321
10681
