Protoss_Gateway 3 10159
Protoss_Assimilator 1 3309
Protoss_Zealot 4 7956
Protoss_Cybernetics_Core 1 5518
Protoss_Dragoon 8 10086
Protoss_Robotics_Facility 1 8726
Protoss_Observatory 1 8878
Protoss_Observer 2 10641
Protoss_Nexus 1 12538
12538
