Protoss_Gateway 2 3915
Protoss_Zealot 6 7556
Protoss_Assimilator 1 4580
Protoss_Cybernetics_Core 1 5925
Protoss_Dragoon 3 8856
Protoss_Citadel_of_Adun 2 7983
Protoss_Templar_Archives 1 8978
Protoss_Dark_Templar 2 9731
Protoss_Forge 1 9566
Protoss_Nexus 1 11963
Protoss_High_Templar 1 10966
11963
