Protoss_Gateway 2 3937
Protoss_Zealot 7 9743
Protoss_Assimilator 1 4546
Protoss_Cybernetics_Core 1 6343
Protoss_Dragoon 8 10611
Protoss_Robotics_Facility 1 8435
Protoss_Observatory 1 8844
Protoss_Observer 1 9955
Protoss_Shuttle 1 11399
11399
