Protoss_Gateway 2 5184
Protoss_Assimilator 1 3452
Protoss_Zealot 4 5687
Protoss_Cybernetics_Core 1 5704
Protoss_Dragoon 11 11063
Protoss_Robotics_Facility 1 9631
Protoss_Observatory 1 9739
Protoss_Observer 1 10835
11063
