Protoss_Gateway 3 10406
Protoss_Zealot 5 6031
Protoss_Assimilator 1 5453
Protoss_Cybernetics_Core 1 6909
Protoss_Dragoon 8 10351
Protoss_Robotics_Facility 1 9868
Protoss_Observatory 1 10073
Protoss_Observer 1 10846
10846
