Protoss_Gateway 2 7007
Protoss_Assimilator 1 3468
Protoss_Zealot 3 5026
Protoss_Cybernetics_Core 1 5338
Protoss_Dragoon 12 11041
Protoss_Robotics_Facility 1 9628
Protoss_Observatory 1 9823
Protoss_Shuttle 1 10901
11041
