Protoss_Gateway 2 4061
Protoss_Zealot 7 6281
Protoss_Assimilator 1 4861
Protoss_Cybernetics_Core 1 6277
Protoss_Dragoon 10 10961
Protoss_Robotics_Facility 1 10043
Protoss_Observatory 1 10438
10961
