Protoss_Gateway 4 11066
Protoss_Zealot 6 5906
Protoss_Assimilator 1 4321
Protoss_Cybernetics_Core 1 5964
Protoss_Dragoon 13 11186
Protoss_Robotics_Facility 1 9713
Protoss_Observatory 1 9836
Protoss_Observer 1 10626
11186
