Protoss_Gateway 2 10231
Protoss_Assimilator 1 3483
Protoss_Cybernetics_Core 1 4654
Protoss_Dragoon 7 11116
Protoss_Robotics_Facility 1 8422
Protoss_Nexus 1 9965
Protoss_Robotics_Support_Bay 1 8609
Protoss_Reaver 1 10311
Protoss_Observatory 1 9604
Protoss_Shield_Battery 1 10263
Protoss_Observer 1 10643
11116
