Protoss_Gateway 2 7108
Protoss_Zealot 7 7699
Protoss_Assimilator 1 5896
Protoss_Cybernetics_Core 1 7144
Protoss_Citadel_of_Adun 1 8587
Protoss_Dragoon 4 9755
Protoss_Templar_Archives 1 9573
Protoss_Forge 1 9379
Protoss_Dark_Templar 2 10507
Protoss_Photon_Cannon 1 10511
Protoss_Nexus 1 12835
12835
