Protoss_Gateway 3 9483
Protoss_Assimilator 1 3538
Protoss_Zealot 1 4016
Protoss_Cybernetics_Core 1 5429
Protoss_Dragoon 9 10766
Protoss_Robotics_Facility 1 8733
Protoss_Observatory 1 8993
Protoss_Observer 2 10756
Protoss_Nexus 1 12263
12263
