Protoss_Gateway 3 9586
Protoss_Zealot 3 4931
Protoss_Assimilator 1 3848
Protoss_Cybernetics_Core 1 5220
Protoss_Dragoon 9 11091
Protoss_Robotics_Facility 1 7073
Protoss_Shuttle 1 8031
Protoss_Observatory 1 7523
Protoss_Observer 1 8453
Protoss_Robotics_Support_Bay 1 8590
Protoss_Reaver 2 11151
11151
