Protoss_Gateway 2 6401
Protoss_Zealot 9 10331
Protoss_Assimilator 1 5988
Protoss_Cybernetics_Core 1 7137
Protoss_Dragoon 5 10519
Protoss_Robotics_Facility 1 9648
Protoss_Shuttle 1 10449
Protoss_Observatory 1 10006
Protoss_Robotics_Support_Bay 1 10691
10691
