Protoss_Gateway 1 3403
Protoss_Assimilator 1 3444
Protoss_Zealot 4 6657
Protoss_Cybernetics_Core 1 6862
Protoss_Dragoon 3 10357
Protoss_Robotics_Facility 1 8876
Protoss_Shuttle 1 9721
Protoss_Observatory 1 9070
Protoss_Observer 1 10143
Protoss_Robotics_Support_Bay 1 9952
Protoss_Reaver 1 11467
11467
