Protoss_Gateway 3 11073
Protoss_Zealot 4 7345
Protoss_Assimilator 1 5346
Protoss_Cybernetics_Core 1 7413
Protoss_Citadel_of_Adun 1 8513
Protoss_Dragoon 1 8391
Protoss_Templar_Archives 1 9605
Protoss_Forge 1 9944
Protoss_Dark_Templar 2 10569
Protoss_Photon_Cannon 1 11017
11073
