Protoss_Gateway 4 9938
Protoss_Assimilator 2 4858
Protoss_Zealot 4 6566
Protoss_Cybernetics_Core 1 6429
Protoss_Citadel_of_Adun 1 7588
Protoss_Templar_Archives 1 8583
Protoss_Robotics_Facility 1 9650
Protoss_Dark_Templar 4 10121
Protoss_Shuttle 1 10491
Protoss_Observatory 1 10235
Protoss_Dragoon 1 11116
11116
