Protoss_Gateway 2 7727
Protoss_Zealot 4 6501
Protoss_Nexus 1 8294
Protoss_Assimilator 2 10615
Protoss_Cybernetics_Core 1 7468
Protoss_Forge 1 7828
Protoss_Dragoon 5 10736
Protoss_Photon_Cannon 2 11033
Protoss_Robotics_Facility 1 10501
Protoss_Observatory 1 10639
11033
