Protoss_Gateway 2 8817
Protoss_Assimilator 1 3278
Protoss_Cybernetics_Core 1 4503
Protoss_Dragoon 9 10461
Protoss_Robotics_Facility 1 8807
Protoss_Observatory 1 8938
Protoss_Observer 1 9716
Protoss_Nexus 1 12725
12725
