Protoss_Gateway 2 5203
Protoss_Zealot 8 7533
Protoss_Assimilator 1 7258
Protoss_Cybernetics_Core 1 8742
Protoss_Forge 1 8735
Protoss_Dragoon 4 10495
Protoss_Photon_Cannon 1 9837
10495
