Protoss_Gateway 2 6211
Protoss_Assimilator 1 3398
Protoss_Zealot 2 4484
Protoss_Cybernetics_Core 1 5417
Protoss_Dragoon 11 10633
Protoss_Robotics_Facility 1 9312
Protoss_Shuttle 1 10369
Protoss_Observatory 1 9710
Protoss_Robotics_Support_Bay 1 10475
Protoss_Observer 1 10791
10791
