Protoss_Gateway 2 5676
Protoss_Assimilator 1 3325
Protoss_Cybernetics_Core 1 4475
Protoss_Dragoon 12 10813
Protoss_Robotics_Facility 1 9596
Protoss_Observatory 1 9683
Protoss_Observer 1 10621
10813
