Protoss_Gateway 2 4465
Protoss_Zealot 6 7207
Protoss_Assimilator 1 5261
Protoss_Cybernetics_Core 1 6855
Protoss_Robotics_Facility 1 8462
Protoss_Shield_Battery 1 7497
Protoss_Dragoon 2 9513
Protoss_Shuttle 1 9261
Protoss_Robotics_Support_Bay 1 8841
Protoss_Reaver 1 10833
10833
