Protoss_Gateway 2 6675
Protoss_Assimilator 1 3208
Protoss_Zealot 5 10626
Protoss_Cybernetics_Core 1 5088
Protoss_Citadel_of_Adun 1 6128
Protoss_Dragoon 2 6941
Protoss_Templar_Archives 1 7155
Protoss_Forge 1 7162
Protoss_Dark_Templar 1 8091
Protoss_Nexus 1 10098
Protoss_Photon_Cannon 2 9242
Protoss_High_Templar 3 10111
10626
