Protoss_Gateway 4 11075
Protoss_Zealot 10 10959
Protoss_Nexus 1 7742
Protoss_Assimilator 1 6325
Protoss_Cybernetics_Core 1 7651
Protoss_Citadel_of_Adun 1 9118
Protoss_Dragoon 1 9033
Protoss_Forge 1 9252
11075
