Protoss_Gateway 2 7607
Protoss_Zealot 10 9669
Protoss_Nexus 1 8210
Protoss_Assimilator 1 6563
Protoss_Cybernetics_Core 1 7965
Protoss_Citadel_of_Adun 1 9059
Protoss_Dragoon 2 9151
Protoss_Templar_Archives 1 10076
Protoss_Forge 1 9650
Protoss_Photon_Cannon 1 10659
Protoss_Dark_Templar 2 10833
10833
