Protoss_Gateway 2 8153
Protoss_Assimilator 1 3243
Protoss_Zealot 2 4871
Protoss_Cybernetics_Core 1 5029
Protoss_Dragoon 10 11021
Protoss_Robotics_Facility 1 7219
Protoss_Observatory 1 7561
Protoss_Observer 2 8938
Protoss_Shuttle 1 10020
Protoss_Robotics_Support_Bay 1 9643
Protoss_Reaver 1 11186
11186
