Protoss_Gateway 2 6636
Protoss_Assimilator 1 3428
Protoss_Zealot 3 5246
Protoss_Cybernetics_Core 1 6118
Protoss_Robotics_Facility 1 7593
Protoss_Dragoon 11 11034
Protoss_Observatory 1 7712
Protoss_Observer 2 9093
Protoss_Shuttle 1 10236
Protoss_Robotics_Support_Bay 1 10439
11034
