Protoss_Gateway 3 7387
Protoss_Assimilator 1 3259
Protoss_Cybernetics_Core 1 4378
Protoss_Dragoon 9 11171
Protoss_Forge 1 8063
Protoss_Nexus 1 11702
Protoss_Photon_Cannon 2 10868
11702
