Protoss_Gateway 2 7755
Protoss_Assimilator 1 3372
Protoss_Zealot 2 4753
Protoss_Cybernetics_Core 1 5442
Protoss_Dragoon 9 11046
Protoss_Robotics_Facility 1 7268
Protoss_Observatory 1 7388
Protoss_Observer 2 8837
Protoss_Robotics_Support_Bay 1 8724
Protoss_Reaver 2 11308
Protoss_Nexus 1 12378
12378
