Protoss_Gateway 2 8891
Protoss_Assimilator 1 3674
Protoss_Zealot 2 5176
Protoss_Cybernetics_Core 1 5222
Protoss_Dragoon 7 10717
Protoss_Robotics_Facility 1 7397
Protoss_Forge 1 6830
Protoss_Observatory 1 7505
Protoss_Observer 2 9861
Protoss_Shuttle 1 10943
Protoss_Robotics_Support_Bay 1 10495
10943
