Protoss_Gateway 4 10674
Protoss_Zealot 8 8845
Protoss_Nexus 2 12532
Protoss_Assimilator 4 9077
Protoss_Cybernetics_Core 1 7693
Protoss_Citadel_of_Adun 1 8711
Protoss_Templar_Archives 1 9747
Protoss_Forge 1 10376
Protoss_Dark_Templar 3 11159
12532
