Protoss_Gateway 2 4262
Protoss_Zealot 8 7783
Protoss_Nexus 1 8143
Protoss_Assimilator 2 9216
Protoss_Cybernetics_Core 1 8565
Protoss_Citadel_of_Adun 1 9579
Protoss_Dragoon 2 9951
Protoss_Forge 1 10075
Protoss_Templar_Archives 1 11140
Protoss_Photon_Cannon 2 11061
11140
