Protoss_Gateway 1 3345
Protoss_Assimilator 1 3223
Protoss_Cybernetics_Core 1 4349
Protoss_Dragoon 4 9713
Protoss_Robotics_Facility 1 6325
Protoss_Shuttle 1 7131
Protoss_Robotics_Support_Bay 1 6538
Protoss_Citadel_of_Adun 1 7699
Protoss_Reaver 1 8273
Protoss_Stargate 2 10448
Protoss_Fleet_Beacon 1 10008
Protoss_Carrier 1 12916
12916
