Protoss_Gateway 2 11245
Protoss_Assimilator 1 3244
Protoss_Zealot 2 5241
Protoss_Cybernetics_Core 1 5113
Protoss_Robotics_Facility 1 6902
Protoss_Dragoon 6 10741
Protoss_Robotics_Support_Bay 1 7038
Protoss_Reaver 1 8966
Protoss_Observatory 1 8174
Protoss_Nexus 1 12093
Protoss_Observer 1 10541
12093
