Protoss_Gateway 3 9904
Protoss_Zealot 8 7605
Protoss_Nexus 1 8151
Protoss_Assimilator 2 9479
Protoss_Cybernetics_Core 1 7706
Protoss_Dragoon 8 11121
Protoss_Robotics_Facility 1 11457
11457
