Protoss_Gateway 3 8466
Protoss_Zealot 7 6931
Protoss_Nexus 1 8271
Protoss_Assimilator 2 9587
Protoss_Cybernetics_Core 1 7895
Protoss_Forge 1 8221
Protoss_Dragoon 2 8807
Protoss_Citadel_of_Adun 1 9324
Protoss_Templar_Archives 1 10317
Protoss_Photon_Cannon 2 10816
Protoss_Dark_Templar 2 11077
11077
