Protoss_Gateway 3 9212
Protoss_Assimilator 1 3237
Protoss_Cybernetics_Core 1 4359
Protoss_Robotics_Facility 1 5979
Protoss_Dragoon 7 10649
Protoss_Shuttle 1 6781
Protoss_Observatory 1 6387
Protoss_Observer 3 8487
10649
