Protoss_Nexus 1 5659
Protoss_Gateway 3 10839
Protoss_Zealot 6 8866
Protoss_Assimilator 1 6910
Protoss_Cybernetics_Core 1 9286
Protoss_Forge 1 8945
Protoss_Photon_Cannon 2 10738
Protoss_Dragoon 4 11026
11026
