Protoss_Gateway 4 10166
Protoss_Zealot 14 10681
Protoss_Nexus 1 7148
Protoss_Assimilator 2 8526
Protoss_Cybernetics_Core 1 7553
Protoss_Citadel_of_Adun 1 9683
Protoss_Forge 1 10197
Protoss_Templar_Archives 1 10813
10813
