Protoss_Gateway 2 10490
Protoss_Assimilator 1 3367
Protoss_Cybernetics_Core 1 4381
Protoss_Robotics_Facility 1 6077
Protoss_Zealot 2 6469
Protoss_Shuttle 1 6881
Protoss_Observatory 1 6336
Protoss_Observer 3 10431
Protoss_Dragoon 5 11149
Protoss_Nexus 1 10391
11149
