Protoss_Gateway 3 8377
Protoss_Zealot 11 10337
Protoss_Nexus 1 7994
Protoss_Forge 1 6530
Protoss_Photon_Cannon 7 10953
Protoss_Assimilator 2 9560
Protoss_Cybernetics_Core 1 10843
10953
