Protoss_Gateway 2 7215
Protoss_Assimilator 2 4847
Protoss_Cybernetics_Core 1 4502
Protoss_Zealot 1 4481
Protoss_Dragoon 10 10759
Protoss_Nexus 1 11373
Protoss_Robotics_Facility 1 11863
11863
