Protoss_Gateway 1 1765
Protoss_Zealot 3 4129
Protoss_Assimilator 1 3103
Protoss_Cybernetics_Core 1 3843
Protoss_Dragoon 7 9731
Protoss_Robotics_Facility 1 5499
Protoss_Shuttle 1 6827
Protoss_Robotics_Support_Bay 1 7107
Protoss_Reaver 1 7739
Protoss_Observatory 1 8427
Protoss_Observer 1 9069
Protoss_Scarab 3 9652
9731
