Protoss_Gateway 2 6628
Protoss_Zealot 5 9863
Protoss_Assimilator 1 4215
Protoss_Cybernetics_Core 1 5290
Protoss_Dragoon 9 11191
Protoss_Robotics_Facility 1 8815
Protoss_Observatory 1 8978
Protoss_Observer 2 10373
Protoss_Nexus 1 12427
12427
