Protoss_Gateway 2 6187
Protoss_Zealot 2 4719
Protoss_Assimilator 1 4086
Protoss_Cybernetics_Core 1 5681
Protoss_Dragoon 9 10967
Protoss_Robotics_Facility 1 8796
Protoss_Nexus 1 11245
Protoss_Observatory 1 9229
Protoss_Observer 2 10667
11245
