Protoss_Gateway 4 10682
Protoss_Assimilator 1 3457
Protoss_Zealot 4 9771
Protoss_Cybernetics_Core 1 5258
Protoss_Dragoon 8 10773
Protoss_Nexus 1 10749
Protoss_Robotics_Facility 1 10521
10773
