Protoss_Gateway 2 5934
Protoss_Assimilator 1 3928
Protoss_Zealot 1 4437
Protoss_Cybernetics_Core 1 5274
Protoss_Dragoon 13 11035
Protoss_Robotics_Facility 1 9713
Protoss_Shuttle 1 10551
Protoss_Robotics_Support_Bay 1 10116
11035
