Protoss_Gateway 2 7552
Protoss_Assimilator 1 3787
Protoss_Zealot 2 4585
Protoss_Cybernetics_Core 1 5291
Protoss_Dragoon 3 7537
Protoss_Citadel_of_Adun 1 6893
Protoss_Templar_Archives 1 7978
Protoss_Forge 1 8393
Protoss_Dark_Templar 5 10935
Protoss_Photon_Cannon 2 10913
10935
