Protoss_Gateway 2 3943
Protoss_Zealot 10 8618
Protoss_Nexus 1 8098
Protoss_Assimilator 1 6923
Protoss_Cybernetics_Core 1 8306
Protoss_Citadel_of_Adun 1 9749
Protoss_Forge 1 9427
Protoss_Dragoon 4 10903
Protoss_Photon_Cannon 1 10853
Protoss_Templar_Archives 1 11408
11408
