Protoss_Gateway 3 9122
Protoss_Zealot 8 8326
Protoss_Nexus 1 8343
Protoss_Assimilator 1 6733
Protoss_Cybernetics_Core 1 8433
Protoss_Dragoon 6 10876
Protoss_Shield_Battery 1 9403
10876
