Protoss_Gateway 3 8832
Protoss_Zealot 13 10656
Protoss_Nexus 1 8573
Protoss_Assimilator 1 7198
Protoss_Cybernetics_Core 1 8701
Protoss_Forge 1 9173
Protoss_Citadel_of_Adun 1 9803
Protoss_Templar_Archives 1 10823
10823
