Protoss_Nexus 1 5747
Protoss_Gateway 3 6118
Protoss_Zealot 8 7511
Protoss_Assimilator 1 6235
Protoss_Cybernetics_Core 1 8805
Protoss_Forge 1 8847
Protoss_Shield_Battery 1 8737
Protoss_Dragoon 4 10419
10419
