Protoss_Gateway 3 10828
Protoss_Zealot 14 9701
Protoss_Nexus 1 8089
Protoss_Assimilator 1 7501
Protoss_Cybernetics_Core 1 9310
Protoss_Citadel_of_Adun 1 10731
Protoss_Dragoon 2 10543
Protoss_Shield_Battery 1 10589
10828
