Protoss_Gateway 3 11010
Protoss_Zealot 5 6366
Protoss_Assimilator 1 4481
Protoss_Cybernetics_Core 1 6288
Protoss_Dragoon 5 10636
Protoss_Robotics_Facility 1 8627
Protoss_Observatory 1 8826
Protoss_Robotics_Support_Bay 1 8929
Protoss_Shuttle 1 9771
Protoss_Observer 2 10795
11010
