Protoss_Gateway 2 5219
Protoss_Assimilator 1 3203
Protoss_Cybernetics_Core 1 4303
Protoss_Dragoon 9 10841
Protoss_Robotics_Facility 1 7323
Protoss_Observatory 1 7475
Protoss_Robotics_Support_Bay 1 7530
Protoss_Reaver 1 9111
Protoss_Nexus 1 11163
Protoss_Observer 1 9443
Protoss_Shuttle 1 10596
11163
