Protoss_Gateway 3 10849
Protoss_Assimilator 1 3403
Protoss_Zealot 1 3877
Protoss_Cybernetics_Core 1 5287
Protoss_Dragoon 11 10959
Protoss_Nexus 1 10669
Protoss_Robotics_Facility 1 11135
11135
