Protoss_Gateway 3 9626
Protoss_Assimilator 1 3717
Protoss_Zealot 4 10647
Protoss_Cybernetics_Core 1 5065
Protoss_Dragoon 7 8829
Protoss_Citadel_of_Adun 1 8255
Protoss_Templar_Archives 1 9363
Protoss_Forge 1 9861
Protoss_Dark_Templar 2 10135
10647
