Protoss_Gateway 2 5026
Protoss_Assimilator 1 3332
Protoss_Zealot 7 6771
Protoss_Cybernetics_Core 1 6615
Protoss_Dragoon 8 10396
Protoss_Nexus 1 10703
Protoss_Citadel_of_Adun 1 10606
Protoss_Robotics_Facility 1 11380
11380
