Protoss_Gateway 4 8721
Protoss_Zealot 1 3859
Protoss_Nexus 1 6714
Protoss_Assimilator 1 4924
Protoss_Cybernetics_Core 1 5753
Protoss_Dragoon 15 11179
Protoss_Forge 1 10823
11179
