Protoss_Gateway 3 9148
Protoss_Zealot 11 8071
Protoss_Nexus 1 8883
Protoss_Assimilator 2 10168
Protoss_Forge 1 8162
Protoss_Cybernetics_Core 1 8768
Protoss_Photon_Cannon 4 10547
Protoss_Citadel_of_Adun 1 9907
Protoss_Dragoon 2 10291
Protoss_Templar_Archives 1 10928
10928
