Protoss_Gateway 2 8768
Protoss_Assimilator 1 3383
Protoss_Cybernetics_Core 1 4541
Protoss_Dragoon 10 11187
Protoss_Robotics_Facility 1 8297
Protoss_Observatory 1 8430
Protoss_Observer 1 9393
Protoss_Nexus 1 11670
Protoss_Robotics_Support_Bay 1 10335
11670
