Protoss_Gateway 4 10920
Protoss_Zealot 14 10136
Protoss_Nexus 1 7833
Protoss_Assimilator 2 9364
Protoss_Shield_Battery 1 7064
Protoss_Cybernetics_Core 1 8618
Protoss_Dragoon 3 10561
Protoss_Robotics_Facility 1 10921
10921
