Protoss_Gateway 4 10727
Protoss_Zealot 14 9218
Protoss_Nexus 1 8496
Protoss_Assimilator 2 10049
Protoss_Cybernetics_Core 1 8596
Protoss_Citadel_of_Adun 1 9721
Protoss_Robotics_Facility 1 11303
Protoss_Dragoon 1 10946
11303
