Protoss_Gateway 2 8473
Protoss_Assimilator 1 3391
Protoss_Zealot 2 5066
Protoss_Cybernetics_Core 1 5329
Protoss_Dragoon 2 7166
Protoss_Citadel_of_Adun 1 6941
Protoss_Templar_Archives 1 8039
Protoss_Forge 1 8043
Protoss_Dark_Templar 4 10001
Protoss_High_Templar 2 11156
Protoss_Photon_Cannon 2 10630
Protoss_Nexus 1 12560
12560
