Protoss_Gateway 4 8521
Protoss_Assimilator 1 3418
Protoss_Zealot 2 4881
Protoss_Cybernetics_Core 1 5073
Protoss_Dragoon 11 9456
Protoss_Forge 1 9690
Protoss_Robotics_Facility 1 11267
Protoss_Photon_Cannon 2 10716
11267
