Protoss_Gateway 3 9753
Protoss_Zealot 9 6801
Protoss_Forge 1 5531
Protoss_Photon_Cannon 4 9193
Protoss_Nexus 1 9283
Protoss_Assimilator 1 7723
Protoss_Cybernetics_Core 1 8759
Protoss_Dragoon 3 10496
10496
