Protoss_Gateway 2 4861
Protoss_Assimilator 1 3326
Protoss_Cybernetics_Core 1 4403
Protoss_Dragoon 5 7566
Protoss_Robotics_Facility 1 9049
Protoss_Citadel_of_Adun 1 9057
Protoss_Shuttle 1 9861
Protoss_Zealot 1 9491
Protoss_Templar_Archives 1 10707
Protoss_Nexus 1 12728
12728
