Protoss_Gateway 3 8312
Protoss_Assimilator 1 3387
Protoss_Zealot 9 10247
Protoss_Cybernetics_Core 1 5086
Protoss_Dragoon 2 7207
Protoss_Nexus 1 8648
Protoss_Citadel_of_Adun 1 8551
Protoss_Forge 1 9760
Protoss_Templar_Archives 1 10959
Protoss_Photon_Cannon 1 10865
10959
