Protoss_Gateway 3 7359
Protoss_Assimilator 2 10808
Protoss_Zealot 4 10505
Protoss_Nexus 1 7523
Protoss_Cybernetics_Core 1 6327
Protoss_Dragoon 9 10703
Protoss_Robotics_Facility 1 8957
Protoss_Observatory 1 9217
Protoss_Observer 2 10935
10935
