Protoss_Gateway 2 4196
Protoss_Zealot 9 8051
Protoss_Assimilator 1 7169
Protoss_Cybernetics_Core 1 7877
Protoss_Dragoon 6 10625
Protoss_Forge 1 9659
Protoss_Photon_Cannon 1 10953
10953
