Protoss_Gateway 2 4067
Protoss_Zealot 3 5376
Protoss_Assimilator 1 4459
Protoss_Cybernetics_Core 1 5433
Protoss_Dragoon 3 7776
Protoss_Citadel_of_Adun 1 7334
Protoss_Templar_Archives 1 8353
Protoss_Dark_Templar 5 10863
Protoss_Forge 1 8964
10863
