Protoss_Gateway 2 6040
Protoss_Zealot 5 7955
Protoss_Assimilator 1 8044
Protoss_Cybernetics_Core 1 8978
Protoss_Nexus 1 11483
Protoss_Dragoon 3 10721
Protoss_Forge 1 10015
Protoss_Shield_Battery 1 10507
Protoss_Photon_Cannon 1 11034
11483
