Protoss_Gateway 3 11204
Protoss_Zealot 8 7941
Protoss_Assimilator 2 5235
Protoss_Cybernetics_Core 1 7399
Protoss_Dragoon 5 10598
Protoss_Citadel_of_Adun 1 9204
Protoss_Templar_Archives 1 10388
Protoss_Dark_Templar 2 11141
11204
