Protoss_Gateway 3 8821
Protoss_Assimilator 1 3935
Protoss_Zealot 3 5909
Protoss_Cybernetics_Core 1 5589
Protoss_Dragoon 11 10761
Protoss_Nexus 1 9583
Protoss_Shield_Battery 1 9966
10761
