Protoss_Gateway 3 7794
Protoss_Assimilator 1 3315
Protoss_Zealot 3 5048
Protoss_Cybernetics_Core 1 5267
Protoss_Dragoon 13 10851
Protoss_Forge 1 9429
Protoss_Robotics_Facility 1 10796
Protoss_Photon_Cannon 3 10768
10851
