Protoss_Gateway 3 7749
Protoss_Zealot 13 9639
Protoss_Assimilator 1 7628
Protoss_Cybernetics_Core 1 8518
Protoss_Citadel_of_Adun 1 9644
Protoss_Templar_Archives 1 10718
Protoss_Nexus 1 12419
12419
