Protoss_Gateway 2 9681
Protoss_Zealot 3 5165
Protoss_Assimilator 1 4103
Protoss_Cybernetics_Core 1 5447
Protoss_Robotics_Facility 1 7150
Protoss_Dragoon 7 11113
Protoss_Shuttle 1 8035
Protoss_Robotics_Support_Bay 1 7817
Protoss_Reaver 2 10359
Protoss_Observatory 1 8916
Protoss_Scarab 7 9969
11113
