Protoss_Gateway 2 6380
Protoss_Zealot 5 9071
Protoss_Assimilator 1 3863
Protoss_Cybernetics_Core 1 5231
Protoss_Dragoon 1 6469
Protoss_Citadel_of_Adun 1 8234
Protoss_Templar_Archives 1 9233
Protoss_Forge 1 8884
Protoss_High_Templar 2 10316
Protoss_Nexus 1 12363
Protoss_Photon_Cannon 1 11053
12363
