Protoss_Gateway 2 3878
Protoss_Zealot 9 7171
Protoss_Assimilator 1 5550
Protoss_Cybernetics_Core 1 7051
Protoss_Dragoon 8 10986
Protoss_Robotics_Facility 1 9981
Protoss_Forge 1 9737
Protoss_Observatory 1 10119
Protoss_Observer 1 10916
10986
