Protoss_Gateway 2 6653
Protoss_Zealot 11 10816
Protoss_Nexus 1 7863
Protoss_Assimilator 2 9124
Protoss_Cybernetics_Core 1 8505
Protoss_Forge 1 8935
Protoss_Citadel_of_Adun 1 9534
Protoss_Dragoon 2 9811
Protoss_Photon_Cannon 1 10127
Protoss_Templar_Archives 1 11159
11159
