Protoss_Gateway 2 8078
Protoss_Assimilator 1 3168
Protoss_Zealot 2 5356
Protoss_Cybernetics_Core 1 5290
Protoss_Dragoon 8 11141
Protoss_Robotics_Facility 1 7613
Protoss_Shuttle 1 8721
Protoss_Robotics_Support_Bay 1 8257
Protoss_Reaver 1 10196
Protoss_Observatory 1 9343
Protoss_Observer 1 10528
11141
