Protoss_Gateway 2 7065
Protoss_Assimilator 1 3338
Protoss_Zealot 2 5321
Protoss_Cybernetics_Core 1 5379
Protoss_Dragoon 2 7111
Protoss_Citadel_of_Adun 1 7719
Protoss_Nexus 1 10252
Protoss_Templar_Archives 1 8944
Protoss_Forge 1 8943
Protoss_Dark_Templar 5 10971
Protoss_Photon_Cannon 2 10183
Protoss_High_Templar 1 10981
10981
