Protoss_Gateway 2 4024
Protoss_Zealot 9 7756
Protoss_Nexus 1 8283
Protoss_Assimilator 2 9045
Protoss_Cybernetics_Core 1 8370
Protoss_Dragoon 4 10396
Protoss_Forge 1 8928
Protoss_Photon_Cannon 1 10301
10396
