Protoss_Gateway 2 5697
Protoss_Assimilator 1 3378
Protoss_Zealot 7 7116
Protoss_Cybernetics_Core 1 5201
Protoss_Citadel_of_Adun 1 6779
Protoss_Dragoon 1 7298
Protoss_Templar_Archives 1 7923
Protoss_Dark_Templar 3 9428
Protoss_Forge 1 9596
Protoss_Nexus 1 11603
Protoss_High_Templar 2 10271
Protoss_Photon_Cannon 1 11145
11603
