Protoss_Gateway 2 7642
Protoss_Assimilator 1 3453
Protoss_Zealot 2 5099
Protoss_Cybernetics_Core 1 5273
Protoss_Dragoon 9 10917
Protoss_Robotics_Facility 1 8955
Protoss_Observatory 1 9324
Protoss_Observer 2 10713
Protoss_Nexus 1 12195
12195
