Protoss_Gateway 3 9597
Protoss_Assimilator 1 3492
Protoss_Zealot 3 10857
Protoss_Cybernetics_Core 1 5185
Protoss_Dragoon 8 10421
Protoss_Robotics_Facility 1 8115
Protoss_Nexus 1 10332
Protoss_Observatory 1 8349
Protoss_Observer 2 9961
10857
