Protoss_Gateway 3 11346
Protoss_Zealot 8 7001
Protoss_Assimilator 1 4938
Protoss_Cybernetics_Core 1 6683
Protoss_Dragoon 8 10733
Protoss_Forge 1 8418
Protoss_Photon_Cannon 1 9529
Protoss_Robotics_Facility 1 10543
Protoss_Citadel_of_Adun 1 10988
Protoss_Shuttle 1 11366
11366
