Protoss_Gateway 3 11369
Protoss_Assimilator 1 3443
Protoss_Zealot 1 3905
Protoss_Cybernetics_Core 1 5381
Protoss_Dragoon 10 10849
Protoss_Robotics_Facility 1 8767
Protoss_Observatory 1 9025
Protoss_Observer 2 10395
Protoss_Nexus 1 12435
12435
