Protoss_Gateway 4 10905
Protoss_Zealot 2 4649
Protoss_Assimilator 1 3885
Protoss_Cybernetics_Core 1 4885
Protoss_Dragoon 12 11001
Protoss_Robotics_Facility 1 9745
Protoss_Nexus 1 12121
12121
