Protoss_Gateway 2 7051
Protoss_Zealot 2 4949
Protoss_Assimilator 1 4133
Protoss_Cybernetics_Core 1 5215
Protoss_Dragoon 10 10935
Protoss_Robotics_Facility 1 9134
Protoss_Observatory 1 9262
Protoss_Shuttle 1 9999
Protoss_Nexus 1 11884
Protoss_Robotics_Support_Bay 1 10065
Protoss_Observer 1 10421
11884
