Protoss_Gateway 3 8963
Protoss_Assimilator 1 3193
Protoss_Cybernetics_Core 1 4285
Protoss_Dragoon 13 10453
Protoss_Robotics_Facility 1 7769
Protoss_Observatory 1 8136
Protoss_Observer 1 8925
Protoss_Nexus 1 12648
12648
