Protoss_Gateway 3 9298
Protoss_Assimilator 1 3360
Protoss_Zealot 1 3789
Protoss_Cybernetics_Core 1 5169
Protoss_Dragoon 12 10799
Protoss_Nexus 1 10331
Protoss_Robotics_Facility 1 10163
Protoss_Observatory 1 10487
10799
