Protoss_Gateway 3 11082
Protoss_Zealot 2 8131
Protoss_Assimilator 1 4027
Protoss_Cybernetics_Core 1 5198
Protoss_Dragoon 10 10531
Protoss_Robotics_Facility 1 8939
Protoss_Nexus 1 11010
Protoss_Observatory 1 9048
Protoss_Observer 1 9991
Protoss_Shuttle 1 11233
11233
