Protoss_Nexus 1 5818
Protoss_Gateway 3 7757
Protoss_Zealot 4 9819
Protoss_Assimilator 2 8348
Protoss_Cybernetics_Core 1 7371
Protoss_Dragoon 6 9403
Protoss_Citadel_of_Adun 1 10071
Protoss_Forge 1 10172
Protoss_Shield_Battery 1 10151
Protoss_Templar_Archives 1 11286
Protoss_Photon_Cannon 1 11133
11286
