Protoss_Gateway 2 7429
Protoss_Assimilator 1 3601
Protoss_Cybernetics_Core 1 4605
Protoss_Dragoon 7 11187
Protoss_Robotics_Facility 1 7621
Protoss_Shuttle 1 8653
Protoss_Robotics_Support_Bay 1 7997
Protoss_Observatory 1 8971
Protoss_Reaver 2 11075
11187
