Protoss_Gateway 3 11212
Protoss_Assimilator 1 3388
Protoss_Cybernetics_Core 1 4523
Protoss_Dragoon 12 10621
Protoss_Robotics_Facility 1 8031
Protoss_Observatory 1 8167
Protoss_Observer 1 9291
Protoss_Nexus 1 11628
11628
