Protoss_Nexus 1 5605
Protoss_Gateway 2 5912
Protoss_Assimilator 3 10523
Protoss_Zealot 8 8235
Protoss_Cybernetics_Core 1 9641
Protoss_Forge 1 9497
Protoss_Citadel_of_Adun 1 10721
Protoss_Photon_Cannon 4 11085
11085
