Protoss_Gateway 6 9316
Protoss_Forge 1 5753
Protoss_Zealot 7 8203
Protoss_Assimilator 1 6915
Protoss_Cybernetics_Core 2 8227
Protoss_Citadel_of_Adun 1 8663
Protoss_Templar_Archives 1 9737
Protoss_Photon_Cannon 1 9629
Protoss_Nexus 1 12262
Protoss_Dark_Templar 1 10585
12262
