Protoss_Gateway 3 9177
Protoss_Assimilator 1 3463
Protoss_Cybernetics_Core 1 4698
Protoss_Dragoon 15 11036
Protoss_Robotics_Facility 1 8351
Protoss_Observatory 1 8483
Protoss_Observer 1 9436
Protoss_Zealot 1 10131
11036
