Protoss_Gateway 2 3947
Protoss_Zealot 11 9591
Protoss_Nexus 1 9245
Protoss_Assimilator 2 9734
Protoss_Cybernetics_Core 1 8889
Protoss_Dragoon 4 10529
Protoss_Robotics_Facility 1 10590
10590
