Protoss_Gateway 4 11342
Protoss_Zealot 13 9115
Protoss_Nexus 1 8702
Protoss_Assimilator 2 9665
Protoss_Cybernetics_Core 1 9028
Protoss_Citadel_of_Adun 1 10080
Protoss_Dragoon 1 10033
Protoss_Templar_Archives 1 11176
11342
