Protoss_Gateway 3 10812
Protoss_Zealot 11 10953
Protoss_Nexus 1 7819
Protoss_Assimilator 2 8226
Protoss_Cybernetics_Core 1 8061
Protoss_Dragoon 6 10441
Protoss_Robotics_Facility 1 10085
Protoss_Observatory 1 10331
Protoss_Shuttle 1 11299
11299
