Protoss_Assimilator 1 2608
Protoss_Gateway 2 7184
Protoss_Cybernetics_Core 1 4642
Protoss_Citadel_of_Adun 1 5725
Protoss_Robotics_Facility 1 6551
Protoss_Dragoon 6 10321
Protoss_Templar_Archives 1 7307
Protoss_Shuttle 1 7611
Protoss_Dark_Templar 3 10379
10379
