Protoss_Gateway 1 3306
Protoss_Assimilator 1 3327
Protoss_Cybernetics_Core 1 4323
Protoss_Robotics_Facility 2 11522
Protoss_Shuttle 1 6831
Protoss_Robotics_Support_Bay 1 6135
Protoss_Reaver 2 9025
Protoss_Zealot 1 7411
Protoss_Observatory 1 8321
Protoss_Scarab 12 9997
Protoss_Dragoon 2 9793
Protoss_Observer 1 9357
11522
