Protoss_Gateway 2 7485
Protoss_Assimilator 1 3213
Protoss_Zealot 7 7488
Protoss_Cybernetics_Core 1 6185
Protoss_Dragoon 8 10787
Protoss_Robotics_Facility 1 9075
Protoss_Observatory 1 9198
Protoss_Observer 1 10481
10787
