Protoss_Gateway 1 3353
Protoss_Assimilator 1 3805
Protoss_Zealot 4 6356
Protoss_Cybernetics_Core 1 6186
Protoss_Robotics_Facility 1 7909
Protoss_Dragoon 4 10431
Protoss_Shuttle 1 8716
Protoss_Robotics_Support_Bay 1 8279
Protoss_Reaver 2 10976
10976
