Protoss_Nexus 1 5463
Protoss_Gateway 2 4752
Protoss_Zealot 5 7647
Protoss_Assimilator 2 9863
Protoss_Forge 1 6536
Protoss_Cybernetics_Core 1 7277
Protoss_Photon_Cannon 10 10965
Protoss_Citadel_of_Adun 1 8453
Protoss_Templar_Archives 1 9594
Protoss_Dark_Templar 2 10341
10965
