Protoss_Gateway 3 11358
Protoss_Assimilator 1 3374
Protoss_Zealot 7 10005
Protoss_Cybernetics_Core 1 5567
Protoss_Citadel_of_Adun 1 6575
Protoss_Dragoon 1 6621
Protoss_Templar_Archives 1 7569
Protoss_Dark_Templar 1 8307
Protoss_High_Templar 3 10847
Protoss_Forge 1 9073
Protoss_Nexus 1 12205
Protoss_Photon_Cannon 1 10894
12205
