Protoss_Gateway 2 7466
Protoss_Assimilator 1 3204
Protoss_Zealot 4 10787
Protoss_Cybernetics_Core 1 5281
Protoss_Dragoon 6 9073
Protoss_Robotics_Facility 1 7039
Protoss_Shuttle 1 8017
Protoss_Observatory 1 7425
Protoss_Observer 1 8439
Protoss_Robotics_Support_Bay 1 8359
Protoss_Nexus 1 11593
Protoss_Reaver 1 10709
Protoss_Citadel_of_Adun 1 10655
11593
