Protoss_Gateway 2 8655
Protoss_Assimilator 1 3387
Protoss_Cybernetics_Core 1 4418
Protoss_Zealot 1 4255
Protoss_Dragoon 9 10639
Protoss_Shield_Battery 2 8891
Protoss_Nexus 1 9579
Protoss_Robotics_Facility 1 9932
Protoss_Observatory 1 10021
Protoss_Robotics_Support_Bay 1 10455
Protoss_Observer 1 10789
10789
