Protoss_Gateway 2 8150
Protoss_Assimilator 1 3941
Protoss_Zealot 2 4905
Protoss_Cybernetics_Core 1 5323
Protoss_Dragoon 8 10331
Protoss_Robotics_Facility 1 7843
Protoss_Shuttle 1 8691
Protoss_Observatory 1 7985
Protoss_Observer 1 9113
Protoss_Robotics_Support_Bay 1 8979
Protoss_Reaver 1 10471
10471
