Protoss_Gateway 2 3863
Protoss_Zealot 5 10689
Protoss_Assimilator 1 4337
Protoss_Cybernetics_Core 1 5285
Protoss_Dragoon 11 10933
Protoss_Robotics_Facility 1 8890
Protoss_Shuttle 1 9799
Protoss_Robotics_Support_Bay 1 9669
Protoss_Reaver 1 11159
11159
