Protoss_Gateway 2 8297
Protoss_Assimilator 1 3411
Protoss_Zealot 2 4987
Protoss_Cybernetics_Core 1 5179
Protoss_Dragoon 8 10837
Protoss_Robotics_Facility 1 7903
Protoss_Observatory 1 8071
Protoss_Nexus 1 10737
Protoss_Observer 1 8885
Protoss_Robotics_Support_Bay 1 8924
Protoss_Reaver 2 11525
11525
