Protoss_Gateway 3 7315
Protoss_Zealot 2 5627
Protoss_Assimilator 1 5262
Protoss_Cybernetics_Core 1 6859
Protoss_Dragoon 7 10933
Protoss_Robotics_Facility 1 8787
Protoss_Shuttle 1 9595
Protoss_Robotics_Support_Bay 1 9489
Protoss_Reaver 1 10979
10979
