Protoss_Gateway 3 10878
Protoss_Assimilator 1 3322
Protoss_Zealot 2 5011
Protoss_Cybernetics_Core 1 5083
Protoss_Dragoon 7 11145
Protoss_Robotics_Facility 1 7643
Protoss_Robotics_Support_Bay 1 7749
Protoss_Nexus 1 10497
Protoss_Reaver 2 10933
Protoss_Observatory 1 9500
Protoss_Shield_Battery 1 10407
11145
