Protoss_Gateway 1 3297
Protoss_Assimilator 1 3374
Protoss_Zealot 1 3809
Protoss_Cybernetics_Core 1 5294
Protoss_Dragoon 7 10567
Protoss_Robotics_Facility 1 6981
Protoss_Shuttle 1 7783
Protoss_Robotics_Support_Bay 1 7579
Protoss_Reaver 1 9067
Protoss_Observatory 1 8549
Protoss_Observer 2 10299
Protoss_Nexus 1 12021
12021
