Protoss_Gateway 2 6435
Protoss_Assimilator 1 3314
Protoss_Zealot 2 4645
Protoss_Cybernetics_Core 1 5823
Protoss_Dragoon 10 11161
Protoss_Robotics_Facility 1 7917
Protoss_Observatory 1 8003
Protoss_Observer 3 10401
Protoss_Nexus 1 12597
12597
