Protoss_Gateway 4 11054
Protoss_Assimilator 1 3369
Protoss_Zealot 2 5551
Protoss_Cybernetics_Core 1 5256
Protoss_Citadel_of_Adun 1 6243
Protoss_Dragoon 6 10773
Protoss_Templar_Archives 1 7230
Protoss_Dark_Templar 3 8883
Protoss_Nexus 1 11253
Protoss_Robotics_Facility 1 11848
11848
