Protoss_Gateway 2 3935
Protoss_Zealot 8 8045
Protoss_Nexus 1 7822
Protoss_Assimilator 2 9752
Protoss_Cybernetics_Core 1 7019
Protoss_Citadel_of_Adun 1 8838
Protoss_Forge 1 9313
Protoss_Templar_Archives 1 9966
Protoss_Photon_Cannon 4 11059
Protoss_Dark_Templar 2 11051
11059
