Protoss_Gateway 3 7410
Protoss_Assimilator 1 3946
Protoss_Cybernetics_Core 1 4748
Protoss_Zealot 1 4409
Protoss_Dragoon 13 10405
Protoss_Forge 1 9130
Protoss_Photon_Cannon 3 10647
Protoss_Robotics_Facility 1 11805
11805
