Protoss_Gateway 2 10136
Protoss_Assimilator 1 3422
Protoss_Zealot 2 4899
Protoss_Cybernetics_Core 1 5094
Protoss_Dragoon 3 7431
Protoss_Citadel_of_Adun 1 7337
Protoss_Nexus 1 9721
Protoss_Templar_Archives 1 8464
Protoss_Forge 1 8228
Protoss_Photon_Cannon 2 9752
Protoss_Dark_Templar 4 10969
10969
