Protoss_Gateway 3 11084
Protoss_Assimilator 1 3163
Protoss_Zealot 1 3857
Protoss_Cybernetics_Core 1 5150
Protoss_Dragoon 8 10963
Protoss_Robotics_Facility 1 7875
Protoss_Observatory 1 8091
Protoss_Robotics_Support_Bay 1 8125
Protoss_Observer 1 8903
Protoss_Reaver 1 10225
Protoss_Nexus 1 11905
Protoss_Shuttle 1 11037
11905
