Protoss_Gateway 2 3905
Protoss_Zealot 3 6071
Protoss_Nexus 1 6966
Protoss_Assimilator 2 9507
Protoss_Cybernetics_Core 1 6151
Protoss_Dragoon 8 10779
Protoss_Forge 1 7796
Protoss_Citadel_of_Adun 1 9019
Protoss_Photon_Cannon 3 10340
Protoss_Robotics_Facility 1 9991
Protoss_Observatory 1 10083
Protoss_Observer 1 10881
10881
