Protoss_Gateway 2 8087
Protoss_Assimilator 1 3411
Protoss_Cybernetics_Core 1 4590
Protoss_Dragoon 8 10777
Protoss_Robotics_Facility 1 7832
Protoss_Observatory 1 8065
Protoss_Shuttle 1 8949
Protoss_Robotics_Support_Bay 1 9017
Protoss_Observer 1 9371
Protoss_Nexus 1 11807
Protoss_Reaver 1 10879
11807
