Protoss_Gateway 2 3865
Protoss_Zealot 10 9697
Protoss_Nexus 2 12747
Protoss_Assimilator 2 8850
Protoss_Cybernetics_Core 1 8410
Protoss_Dragoon 3 10725
Protoss_Citadel_of_Adun 1 9556
Protoss_Forge 1 9258
Protoss_Templar_Archives 1 11003
Protoss_Photon_Cannon 1 11174
12747
