Protoss_Gateway 4 10772
Protoss_Assimilator 1 3134
Protoss_Cybernetics_Core 1 4239
Protoss_Zealot 1 4039
Protoss_Dragoon 7 10863
Protoss_Citadel_of_Adun 1 6929
Protoss_Robotics_Facility 1 7432
Protoss_Templar_Archives 1 7923
Protoss_Shuttle 1 8277
Protoss_Dark_Templar 2 8669
Protoss_Nexus 1 11109
Protoss_Observatory 1 10587
11109
