Protoss_Gateway 4 11181
Protoss_Assimilator 1 3420
Protoss_Cybernetics_Core 1 4519
Protoss_Dragoon 9 10629
Protoss_Robotics_Facility 1 8593
Protoss_Observatory 1 8689
Protoss_Observer 2 10063
Protoss_Nexus 1 11696
Protoss_Robotics_Support_Bay 1 10636
11696
