Protoss_Gateway 2 7773
Protoss_Assimilator 1 3271
Protoss_Zealot 2 4873
Protoss_Cybernetics_Core 1 5059
Protoss_Dragoon 10 11123
Protoss_Robotics_Facility 1 7515
Protoss_Shuttle 1 8341
Protoss_Observatory 1 7992
Protoss_Observer 2 10435
Protoss_Robotics_Support_Bay 1 8567
Protoss_Reaver 1 10103
Protoss_Nexus 1 12453
12453
