Protoss_Gateway 2 5614
Protoss_Assimilator 1 3483
Protoss_Zealot 3 10457
Protoss_Cybernetics_Core 1 5005
Protoss_Dragoon 5 8021
Protoss_Citadel_of_Adun 1 6918
Protoss_Forge 1 7379
Protoss_Templar_Archives 1 7909
Protoss_Dark_Templar 2 8773
Protoss_Photon_Cannon 3 11162
Protoss_Nexus 1 11339
Protoss_High_Templar 2 9751
Protoss_Archon 1 10388
11339
