Protoss_Gateway 3 4907
Protoss_Zealot 4 10369
Protoss_Assimilator 1 5031
Protoss_Cybernetics_Core 1 6213
Protoss_Dragoon 9 10761
Protoss_Robotics_Facility 1 10126
Protoss_Observatory 1 10435
10761
