Protoss_Gateway 2 3888
Protoss_Zealot 12 9156
Protoss_Assimilator 1 6192
Protoss_Cybernetics_Core 1 7843
Protoss_Citadel_of_Adun 1 10232
Protoss_Templar_Archives 1 11342
Protoss_Forge 1 10924
11342
