Protoss_Gateway 2 6847
Protoss_Zealot 2 4813
Protoss_Assimilator 1 4631
Protoss_Cybernetics_Core 1 6191
Protoss_Dragoon 11 11079
Protoss_Robotics_Facility 1 10472
Protoss_Observatory 1 10647
11079
