Protoss_Gateway 2 7803
Protoss_Assimilator 1 3363
Protoss_Zealot 2 4965
Protoss_Cybernetics_Core 1 5198
Protoss_Dragoon 9 10045
Protoss_Robotics_Facility 1 7689
Protoss_Shuttle 1 8511
Protoss_Robotics_Support_Bay 1 8252
Protoss_Reaver 1 9763
Protoss_Observatory 1 9016
Protoss_Observer 2 10823
Protoss_Nexus 1 12577
12577
