Protoss_Gateway 4 10387
Protoss_Zealot 5 6485
Protoss_Nexus 1 7750
Protoss_Assimilator 2 8439
Protoss_Cybernetics_Core 1 7481
Protoss_Dragoon 8 11185
Protoss_Robotics_Facility 1 9963
Protoss_Forge 1 9030
Protoss_Photon_Cannon 2 10761
Protoss_Observatory 1 10089
11185
