Protoss_Gateway 2 6926
Protoss_Zealot 5 9531
Protoss_Cybernetics_Core 1 5487
Protoss_Assimilator 1 6318
Protoss_Dragoon 7 11125
Protoss_Nexus 1 9950
Protoss_Robotics_Facility 1 10399
11125
