Protoss_Gateway 2 5719
Protoss_Zealot 10 8481
Protoss_Assimilator 1 5483
Protoss_Cybernetics_Core 1 6468
Protoss_Citadel_of_Adun 1 7596
Protoss_Robotics_Facility 1 8713
Protoss_Forge 1 8029
Protoss_Photon_Cannon 1 8980
Protoss_Templar_Archives 1 9487
Protoss_Shuttle 1 9781
Protoss_Observatory 1 9692
Protoss_Dark_Templar 2 10241
Protoss_Observer 1 10526
Protoss_Nexus 1 12628
12628
