Protoss_Gateway 4 11299
Protoss_Assimilator 1 3302
Protoss_Zealot 3 5555
Protoss_Cybernetics_Core 1 5551
Protoss_Dragoon 10 10855
Protoss_Robotics_Facility 1 8349
Protoss_Observatory 1 8483
Protoss_Observer 3 10871
Protoss_Nexus 1 12077
12077
