Protoss_Gateway 4 11280
Protoss_Zealot 9 8641
Protoss_Nexus 1 7865
Protoss_Assimilator 2 7847
Protoss_Cybernetics_Core 1 7272
Protoss_Dragoon 4 10551
Protoss_Forge 1 10138
11280
