Protoss_Gateway 3 8849
Protoss_Zealot 4 10288
Protoss_Assimilator 1 4294
Protoss_Cybernetics_Core 1 5398
Protoss_Dragoon 11 11016
Protoss_Robotics_Facility 1 8503
Protoss_Observatory 1 9014
Protoss_Observer 2 10586
11016
