Protoss_Gateway 2 6976
Protoss_Assimilator 1 3223
Protoss_Zealot 2 4979
Protoss_Cybernetics_Core 1 5227
Protoss_Dragoon 9 11079
Protoss_Robotics_Facility 1 7837
Protoss_Observatory 1 7959
Protoss_Observer 2 9333
Protoss_Nexus 1 10965
Protoss_Shuttle 1 10797
Protoss_Robotics_Support_Bay 1 10145
11079
