Protoss_Gateway 2 3916
Protoss_Zealot 8 9149
Protoss_Nexus 2 11915
Protoss_Assimilator 2 9345
Protoss_Cybernetics_Core 1 7377
Protoss_Dragoon 1 8145
Protoss_Citadel_of_Adun 1 8638
Protoss_Templar_Archives 1 9663
Protoss_Forge 1 9675
Protoss_Dark_Templar 2 10449
Protoss_Photon_Cannon 2 10937
11915
