Protoss_Gateway 3 9842
Protoss_Assimilator 1 3318
Protoss_Zealot 2 5159
Protoss_Cybernetics_Core 1 5322
Protoss_Dragoon 11 10769
Protoss_Nexus 1 10575
Protoss_Robotics_Facility 1 11109
11109
