Protoss_Gateway 2 4883
Protoss_Assimilator 1 3203
Protoss_Cybernetics_Core 1 4336
Protoss_Dragoon 15 11131
Protoss_Robotics_Facility 1 9110
Protoss_Shuttle 1 9991
Protoss_Observatory 1 9679
Protoss_Observer 1 10461
11131
