Protoss_Gateway 2 7671
Protoss_Assimilator 1 3202
Protoss_Zealot 3 5265
Protoss_Cybernetics_Core 1 5425
Protoss_Dragoon 4 11181
Protoss_Citadel_of_Adun 1 7039
Protoss_Templar_Archives 1 8188
Protoss_Forge 1 8563
Protoss_Dark_Templar 2 8963
Protoss_Photon_Cannon 3 10591
Protoss_Nexus 1 11743
Protoss_High_Templar 2 10375
11743
