Protoss_Gateway 2 8918
Protoss_Assimilator 3 5606
Protoss_Zealot 3 5783
Protoss_Cybernetics_Core 1 5733
Protoss_Dragoon 8 10979
Protoss_Robotics_Facility 1 8697
Protoss_Shuttle 1 9751
Protoss_Robotics_Support_Bay 1 9807
Protoss_Observatory 1 9867
Protoss_Observer 1 10769
10979
