Protoss_Gateway 3 11381
Protoss_Assimilator 3 10051
Protoss_Zealot 3 7475
Protoss_Cybernetics_Core 1 5273
Protoss_Citadel_of_Adun 1 6268
Protoss_Dragoon 2 6963
Protoss_Templar_Archives 1 7303
Protoss_Dark_Templar 2 8808
Protoss_Nexus 1 9898
Protoss_Forge 1 8638
Protoss_Photon_Cannon 3 10219
Protoss_High_Templar 2 11126
11381
