Protoss_Gateway 2 3765
Protoss_Zealot 13 8661
Protoss_Nexus 1 9297
Protoss_Assimilator 2 10339
Protoss_Forge 1 7857
Protoss_Cybernetics_Core 1 9494
Protoss_Photon_Cannon 2 10880
Protoss_Citadel_of_Adun 1 10889
Protoss_Robotics_Facility 1 11824
11824
