Protoss_Gateway 2 3946
Protoss_Zealot 7 7647
Protoss_Nexus 1 7985
Protoss_Assimilator 2 8160
Protoss_Cybernetics_Core 1 7840
Protoss_Dragoon 2 8695
Protoss_Citadel_of_Adun 1 9039
Protoss_Templar_Archives 1 10071
Protoss_Forge 1 9690
Protoss_Photon_Cannon 2 10691
Protoss_Dark_Templar 2 10825
Protoss_Robotics_Facility 1 11678
11678
