Protoss_Gateway 2 3882
Protoss_Zealot 7 7607
Protoss_Nexus 1 8129
Protoss_Assimilator 2 8136
Protoss_Cybernetics_Core 1 7814
Protoss_Citadel_of_Adun 1 8960
Protoss_Dragoon 4 9747
Protoss_Templar_Archives 1 10021
Protoss_Forge 1 9605
Protoss_Robotics_Facility 1 11014
Protoss_Photon_Cannon 1 10839
Protoss_Dark_Templar 2 11009
11014
