Protoss_Gateway 3 9951
Protoss_Zealot 5 6725
Protoss_Nexus 2 12877
Protoss_Assimilator 2 7883
Protoss_Cybernetics_Core 1 6980
Protoss_Dragoon 9 10703
Protoss_Robotics_Facility 1 9291
Protoss_Shuttle 1 10091
Protoss_Observatory 1 9446
Protoss_Observer 1 10635
12877
