Protoss_Gateway 5 11035
Protoss_Zealot 6 10003
Protoss_Nexus 2 9714
Protoss_Assimilator 2 9476
Protoss_Cybernetics_Core 1 6828
Protoss_Dragoon 4 10263
Protoss_Robotics_Facility 1 9949
Protoss_Observatory 1 10116
Protoss_Observer 1 10901
11035
