Protoss_Gateway 2 3787
Protoss_Zealot 15 9555
Protoss_Nexus 1 8909
Protoss_Assimilator 2 9771
Protoss_Cybernetics_Core 1 8509
Protoss_Forge 1 9093
Protoss_Citadel_of_Adun 1 9811
Protoss_Photon_Cannon 2 10297
Protoss_Robotics_Facility 1 11251
11251
