Protoss_Gateway 1 3465
Protoss_Assimilator 1 3190
Protoss_Cybernetics_Core 1 4501
Protoss_Zealot 2 5241
Protoss_Robotics_Facility 1 5978
Protoss_Shuttle 1 6791
Protoss_Robotics_Support_Bay 1 6321
Protoss_Dragoon 1 6941
Protoss_Reaver 2 10471
Protoss_Shield_Battery 1 9260
10471
