Protoss_Gateway 3 10509
Protoss_Assimilator 1 3344
Protoss_Cybernetics_Core 1 4393
Protoss_Zealot 1 4101
Protoss_Dragoon 10 10895
Protoss_Robotics_Facility 1 9501
Protoss_Observatory 1 9615
Protoss_Observer 1 10405
10895
