Protoss_Gateway 4 11247
Protoss_Assimilator 1 3825
Protoss_Cybernetics_Core 1 4612
Protoss_Zealot 1 4681
Protoss_Dragoon 7 10365
Protoss_Nexus 2 11415
Protoss_Robotics_Facility 1 8699
Protoss_Observatory 1 8920
Protoss_Observer 2 10311
Protoss_Robotics_Support_Bay 1 10171
11415
