Protoss_Gateway 3 9661
Protoss_Assimilator 1 3228
Protoss_Cybernetics_Core 1 4358
Protoss_Robotics_Facility 1 5953
Protoss_Dragoon 9 10783
Protoss_Shuttle 1 6766
Protoss_Observatory 1 6206
Protoss_Observer 3 8392
Protoss_Nexus 1 9669
10783
