Protoss_Gateway 3 9197
Protoss_Zealot 3 5071
Protoss_Assimilator 1 3990
Protoss_Cybernetics_Core 1 5356
Protoss_Dragoon 8 10901
Protoss_Nexus 1 9018
Protoss_Robotics_Facility 1 8898
Protoss_Observatory 1 9016
Protoss_Observer 2 10423
Protoss_Robotics_Support_Bay 1 9705
10901
