Protoss_Gateway 2 7922
Protoss_Assimilator 1 3323
Protoss_Cybernetics_Core 1 4447
Protoss_Zealot 1 4289
Protoss_Dragoon 2 6989
Protoss_Citadel_of_Adun 1 6857
Protoss_Templar_Archives 1 7987
Protoss_Forge 2 8087
Protoss_Dark_Templar 2 8823
Protoss_Photon_Cannon 3 11108
Protoss_Nexus 1 11889
11889
