Protoss_Gateway 3 9096
Protoss_Zealot 7 8789
Protoss_Assimilator 1 5027
Protoss_Cybernetics_Core 1 6777
Protoss_Dragoon 10 10985
Protoss_Robotics_Facility 1 9473
Protoss_Observatory 1 9565
Protoss_Observer 1 10339
10985
