Protoss_Gateway 4 9150
Protoss_Assimilator 1 3433
Protoss_Cybernetics_Core 1 4557
Protoss_Robotics_Facility 1 6280
Protoss_Dragoon 4 10551
Protoss_Citadel_of_Adun 1 6878
Protoss_Shuttle 1 7091
Protoss_Observatory 1 6546
Protoss_Observer 5 10880
Protoss_Zealot 10 10953
10953
