Protoss_Gateway 4 10127
Protoss_Zealot 6 10739
Protoss_Assimilator 1 3948
Protoss_Cybernetics_Core 1 5156
Protoss_Dragoon 8 10183
Protoss_Nexus 1 8711
Protoss_Robotics_Facility 1 8565
Protoss_Observatory 1 8675
Protoss_Observer 2 10159
Protoss_Citadel_of_Adun 1 11071
11071
