Protoss_Assimilator 1 3009
Protoss_Gateway 1 3960
Protoss_Cybernetics_Core 1 5076
Protoss_Robotics_Facility 2 7277
Protoss_Shuttle 2 11166
Protoss_Observatory 1 6723
Protoss_Robotics_Support_Bay 1 7181
Protoss_Observer 2 9223
Protoss_Reaver 3 10177
Protoss_Dragoon 2 10156
Protoss_Nexus 1 10862
Protoss_Shield_Battery 2 10178
Protoss_Scarab 11 9949
11166
