Protoss_Gateway 3 9283
Protoss_Assimilator 1 3158
Protoss_Cybernetics_Core 1 4451
Protoss_Citadel_of_Adun 1 5469
Protoss_Robotics_Facility 1 6589
Protoss_Templar_Archives 1 6826
Protoss_Shuttle 1 7396
Protoss_Dark_Templar 2 7856
Protoss_Observatory 1 7537
Protoss_Dragoon 6 10421
Protoss_Observer 1 8326
10421
