Protoss_Gateway 1 3394
Protoss_Assimilator 1 3303
Protoss_Cybernetics_Core 1 4439
Protoss_Robotics_Facility 1 6051
Protoss_Zealot 2 5798
Protoss_Shuttle 1 6861
Protoss_Dragoon 2 8511
Protoss_Robotics_Support_Bay 1 7083
Protoss_Reaver 1 8581
Protoss_Scarab 1 8165
8581
