Protoss_Gateway 2 3865
Protoss_Zealot 9 8049
Protoss_Nexus 1 8010
Protoss_Assimilator 2 9193
Protoss_Cybernetics_Core 1 8103
Protoss_Dragoon 6 10963
Protoss_Robotics_Facility 1 10559
Protoss_Shuttle 1 11435
11435
