Protoss_Gateway 2 7531
Protoss_Assimilator 1 3652
Protoss_Zealot 6 10423
Protoss_Cybernetics_Core 1 5712
Protoss_Dragoon 5 10681
Protoss_Robotics_Facility 1 8403
Protoss_Shuttle 1 9203
Protoss_Robotics_Support_Bay 1 8569
Protoss_Observatory 1 8597
Protoss_Observer 1 9625
Protoss_Reaver 1 10947
Protoss_Citadel_of_Adun 1 11423
11423
