Protoss_Gateway 3 7152
Protoss_Assimilator 1 3346
Protoss_Zealot 1 3935
Protoss_Cybernetics_Core 1 5731
Protoss_Dragoon 11 10513
Protoss_Robotics_Facility 1 10345
Protoss_Observatory 1 10485
10513
