Protoss_Gateway 2 3871
Protoss_Zealot 11 8409
Protoss_Nexus 1 8681
Protoss_Assimilator 2 9209
Protoss_Cybernetics_Core 1 7849
Protoss_Citadel_of_Adun 1 9132
Protoss_Dragoon 2 9715
Protoss_Templar_Archives 1 10255
Protoss_Forge 1 10143
Protoss_Dark_Templar 2 11039
11039
