Protoss_Gateway 1 3290
Protoss_Zealot 4 5609
Protoss_Assimilator 2 5954
Protoss_Cybernetics_Core 1 5914
Protoss_Dragoon 6 10483
Protoss_Robotics_Facility 1 7835
Protoss_Shuttle 1 8665
Protoss_Robotics_Support_Bay 1 8157
Protoss_Reaver 2 11331
11331
