Protoss_Assimilator 1 2849
Protoss_Gateway 4 10294
Protoss_Cybernetics_Core 1 4790
Protoss_Robotics_Facility 1 6295
Protoss_Dragoon 10 10966
Protoss_Observatory 1 6394
Protoss_Observer 2 8926
Protoss_Shuttle 1 8426
10966
