Protoss_Gateway 2 5753
Protoss_Assimilator 1 3410
Protoss_Cybernetics_Core 1 4509
Protoss_Zealot 2 10771
Protoss_Dragoon 9 10461
Protoss_Robotics_Facility 1 9073
Protoss_Shuttle 1 9915
Protoss_Observatory 1 9358
Protoss_Robotics_Support_Bay 1 10097
Protoss_Reaver 1 11595
11595
