Protoss_Gateway 2 10353
Protoss_Assimilator 1 3208
Protoss_Cybernetics_Core 1 4479
Protoss_Stargate 1 5731
Protoss_Robotics_Facility 1 6326
Protoss_Dragoon 7 10501
Protoss_Observatory 1 6504
Protoss_Observer 3 10166
Protoss_Shuttle 1 9200
Protoss_Robotics_Support_Bay 1 9866
Protoss_Reaver 1 11488
11488
