Protoss_Gateway 2 7016
Protoss_Assimilator 1 3592
Protoss_Zealot 3 9961
Protoss_Cybernetics_Core 1 5020
Protoss_Dragoon 12 11023
Protoss_Robotics_Facility 1 9071
Protoss_Observatory 1 9167
Protoss_Observer 2 10539
11023
