Protoss_Gateway 2 5279
Protoss_Assimilator 1 3264
Protoss_Zealot 7 10393
Protoss_Cybernetics_Core 2 6245
Protoss_Dragoon 8 9881
Protoss_Robotics_Facility 1 9249
Protoss_Shuttle 1 10047
Protoss_Robotics_Support_Bay 1 9541
Protoss_Observatory 1 9931
Protoss_Reaver 1 11301
11301
