Protoss_Gateway 2 3932
Protoss_Zealot 10 8727
Protoss_Assimilator 1 5503
Protoss_Cybernetics_Core 1 6633
Protoss_Dragoon 7 11051
Protoss_Robotics_Facility 1 8752
Protoss_Observatory 1 8847
Protoss_Observer 1 9671
Protoss_Shuttle 1 10753
Protoss_Robotics_Support_Bay 1 10387
11051
