Protoss_Gateway 2 8285
Protoss_Assimilator 1 3362
Protoss_Zealot 2 5063
Protoss_Cybernetics_Core 1 5128
Protoss_Dragoon 9 10717
Protoss_Robotics_Facility 1 7935
Protoss_Shuttle 1 8865
Protoss_Robotics_Support_Bay 1 8631
Protoss_Reaver 1 10161
Protoss_Observatory 1 9761
Protoss_Scarab 3 9984
10717
