Protoss_Gateway 2 10151
Protoss_Assimilator 1 3199
Protoss_Zealot 2 4987
Protoss_Cybernetics_Core 1 5221
Protoss_Dragoon 7 10919
Protoss_Nexus 1 10188
Protoss_Robotics_Facility 1 9843
Protoss_Observatory 1 9993
Protoss_Robotics_Support_Bay 1 10547
10919
