Protoss_Gateway 2 7082
Protoss_Assimilator 1 3180
Protoss_Zealot 3 5089
Protoss_Cybernetics_Core 1 5357
Protoss_Dragoon 7 9233
Protoss_Robotics_Facility 1 8973
Protoss_Nexus 1 10494
Protoss_Shuttle 1 9907
Protoss_Robotics_Support_Bay 1 9540
Protoss_Observatory 1 9947
Protoss_Reaver 1 11323
11323
