Protoss_Gateway 2 5652
Protoss_Assimilator 1 3520
Protoss_Zealot 7 9251
Protoss_Cybernetics_Core 2 8847
Protoss_Shield_Battery 1 5784
Protoss_Dragoon 1 9801
Protoss_Robotics_Facility 1 11241
11241
