Protoss_Gateway 2 4062
Protoss_Zealot 14 9406
Protoss_Assimilator 1 7703
Protoss_Cybernetics_Core 1 9042
Protoss_Dragoon 2 10441
Protoss_Robotics_Facility 1 11314
Protoss_Nexus 1 12649
12649
