Protoss_Gateway 2 5075
Protoss_Assimilator 1 3634
Protoss_Zealot 9 7247
Protoss_Shield_Battery 1 5219
Protoss_Cybernetics_Core 1 6887
Protoss_Dragoon 8 10345
Protoss_Citadel_of_Adun 1 8916
Protoss_Templar_Archives 1 10159
Protoss_Forge 1 10229
Protoss_Dark_Templar 2 10919
Protoss_Photon_Cannon 2 11171
11171
