Protoss_Gateway 2 5551
Protoss_Assimilator 2 9368
Protoss_Zealot 3 10123
Protoss_Cybernetics_Core 1 5042
Protoss_Dragoon 7 8875
Protoss_Robotics_Facility 1 7724
Protoss_Nexus 1 9921
Protoss_Observatory 1 7875
Protoss_Observer 2 10669
Protoss_Robotics_Support_Bay 1 8831
Protoss_Reaver 1 10337
10669
