Protoss_Gateway 2 7876
Protoss_Assimilator 2 10353
Protoss_Zealot 2 4861
Protoss_Cybernetics_Core 1 5122
Protoss_Dragoon 3 7367
Protoss_Citadel_of_Adun 1 6998
Protoss_Templar_Archives 1 8117
Protoss_Forge 1 7959
Protoss_Dark_Templar 2 8927
Protoss_Photon_Cannon 1 9020
Protoss_Nexus 1 11363
Protoss_High_Templar 2 10691
11363
