Protoss_Gateway 2 7917
Protoss_Assimilator 1 3165
Protoss_Zealot 2 5183
Protoss_Cybernetics_Core 1 5223
Protoss_Dragoon 10 11103
Protoss_Robotics_Facility 1 7891
Protoss_Shuttle 1 8877
Protoss_Robotics_Support_Bay 1 8646
Protoss_Observatory 1 8660
Protoss_Reaver 1 10145
Protoss_Observer 1 10477
11103
