Protoss_Gateway 4 10719
Protoss_Assimilator 2 10753
Protoss_Cybernetics_Core 1 4295
Protoss_Zealot 1 4143
Protoss_Dragoon 9 10527
Protoss_Nexus 1 9673
Protoss_Robotics_Facility 1 9303
Protoss_Observatory 1 9564
Protoss_Observer 1 10481
10753
