Protoss_Gateway 2 8000
Protoss_Assimilator 1 3273
Protoss_Zealot 3 5089
Protoss_Cybernetics_Core 1 5198
Protoss_Dragoon 9 10161
Protoss_Robotics_Facility 1 7035
Protoss_Shuttle 1 7935
Protoss_Observatory 2 8118
Protoss_Observer 2 10787
Protoss_Robotics_Support_Bay 1 8737
Protoss_Reaver 1 10455
10787
