Protoss_Gateway 3 11209
Protoss_Zealot 8 9371
Protoss_Assimilator 1 5515
Protoss_Cybernetics_Core 1 6686
Protoss_Robotics_Facility 1 8758
Protoss_Dragoon 5 10666
Protoss_Observatory 1 9473
11209
