Protoss_Gateway 2 7624
Protoss_Assimilator 1 3345
Protoss_Zealot 2 4723
Protoss_Cybernetics_Core 1 4979
Protoss_Dragoon 10 10779
Protoss_Robotics_Facility 1 7541
Protoss_Observatory 1 7642
Protoss_Observer 2 9781
Protoss_Nexus 1 11935
Protoss_Robotics_Support_Bay 1 10123
11935
