Protoss_Gateway 2 8088
Protoss_Assimilator 1 3171
Protoss_Zealot 2 4929
Protoss_Cybernetics_Core 1 5120
Protoss_Dragoon 8 11099
Protoss_Robotics_Facility 1 7751
Protoss_Shuttle 1 8669
Protoss_Observatory 1 8097
Protoss_Observer 1 9091
Protoss_Robotics_Support_Bay 1 8949
Protoss_Reaver 1 10503
Protoss_Nexus 1 12637
12637
