Protoss_Gateway 2 7321
Protoss_Assimilator 1 3302
Protoss_Zealot 2 4773
Protoss_Cybernetics_Core 1 4920
Protoss_Dragoon 9 10031
Protoss_Robotics_Facility 1 7555
Protoss_Observatory 1 7765
Protoss_Observer 1 8539
Protoss_Robotics_Support_Bay 1 8407
Protoss_Reaver 1 10345
Protoss_Nexus 1 12371
Protoss_Shuttle 1 11157
12371
