Protoss_Gateway 2 8706
Protoss_Zealot 11 9875
Protoss_Nexus 1 7955
Protoss_Forge 1 6827
Protoss_Photon_Cannon 11 11163
Protoss_Assimilator 1 8573
Protoss_Cybernetics_Core 1 9969
Protoss_Dragoon 2 10855
11163
