Protoss_Gateway 3 10485
Protoss_Assimilator 2 10856
Protoss_Zealot 2 4763
Protoss_Cybernetics_Core 1 5025
Protoss_Dragoon 12 10809
Protoss_Robotics_Facility 1 8402
Protoss_Observatory 1 8633
Protoss_Nexus 1 11303
Protoss_Observer 2 10049
Protoss_Citadel_of_Adun 1 11230
11303
