Protoss_Gateway 3 6343
Protoss_Zealot 4 6013
Protoss_Assimilator 1 5478
Protoss_Cybernetics_Core 1 6037
Protoss_Dragoon 8 10497
Protoss_Nexus 1 11459
Protoss_Robotics_Facility 1 10769
11459
