Protoss_Gateway 2 9053
Protoss_Assimilator 2 10050
Protoss_Zealot 2 5085
Protoss_Cybernetics_Core 1 5248
Protoss_Citadel_of_Adun 1 6309
Protoss_Dragoon 2 6975
Protoss_Templar_Archives 1 7323
Protoss_Nexus 1 9403
Protoss_Dark_Templar 1 8079
Protoss_Forge 1 8233
Protoss_High_Templar 3 9897
Protoss_Photon_Cannon 3 10545
Protoss_Robotics_Facility 1 11492
11492
