Protoss_Gateway 2 8447
Protoss_Zealot 4 5627
Protoss_Assimilator 1 4171
Protoss_Cybernetics_Core 1 5873
Protoss_Dragoon 6 11197
Protoss_Citadel_of_Adun 1 8333
Protoss_Templar_Archives 1 9322
Protoss_Dark_Templar 2 10215
11197
