Protoss_Gateway 2 9315
Protoss_Assimilator 2 9966
Protoss_Cybernetics_Core 1 4487
Protoss_Zealot 1 4185
Protoss_Dragoon 8 10411
Protoss_Nexus 1 9424
Protoss_Robotics_Facility 1 9041
Protoss_Observatory 1 9161
Protoss_Observer 2 10539
10539
