Protoss_Gateway 2 8211
Protoss_Zealot 2 4461
Protoss_Assimilator 1 4029
Protoss_Cybernetics_Core 1 5409
Protoss_Dragoon 8 10491
Protoss_Robotics_Facility 1 9301
Protoss_Nexus 1 11108
Protoss_Shuttle 1 10109
Protoss_Robotics_Support_Bay 1 9457
Protoss_Reaver 1 11269
Protoss_Observatory 1 10621
11269
