Protoss_Gateway 3 11255
Protoss_Assimilator 1 3345
Protoss_Zealot 1 3811
Protoss_Cybernetics_Core 1 5004
Protoss_Dragoon 10 10773
Protoss_Robotics_Facility 1 9251
Protoss_Observatory 1 9405
Protoss_Nexus 1 12033
Protoss_Observer 2 10827
12033
