Protoss_Gateway 4 10936
Protoss_Assimilator 1 3403
Protoss_Zealot 2 4837
Protoss_Cybernetics_Core 1 4908
Protoss_Dragoon 6 9655
Protoss_Citadel_of_Adun 1 7007
Protoss_Templar_Archives 1 8047
Protoss_Forge 1 8018
Protoss_Dark_Templar 1 8785
Protoss_Photon_Cannon 1 9281
Protoss_Nexus 1 11775
Protoss_High_Templar 2 10407
11775
