Protoss_Gateway 3 9437
Protoss_Assimilator 2 10520
Protoss_Zealot 2 4855
Protoss_Cybernetics_Core 1 5060
Protoss_Dragoon 11 11123
Protoss_Nexus 1 9365
Protoss_Robotics_Facility 1 8987
Protoss_Observatory 1 9106
Protoss_Observer 2 10493
Protoss_Citadel_of_Adun 1 10666
11123
