Protoss_Gateway 2 9187
Protoss_Assimilator 1 3437
Protoss_Cybernetics_Core 1 4697
Protoss_Zealot 1 4513
Protoss_Dragoon 9 11129
Protoss_Nexus 1 9392
Protoss_Forge 1 8173
Protoss_Photon_Cannon 2 10187
11129
