Protoss_Gateway 2 4039
Protoss_Zealot 8 8741
Protoss_Nexus 1 7613
Protoss_Assimilator 2 8342
Protoss_Cybernetics_Core 1 7075
Protoss_Dragoon 4 11139
Protoss_Citadel_of_Adun 1 8320
Protoss_Templar_Archives 1 9335
Protoss_Forge 1 9202
Protoss_Dark_Templar 2 10139
Protoss_Photon_Cannon 2 10897
Protoss_High_Templar 1 11001
11139
