Protoss_Gateway 3 9518
Protoss_Assimilator 1 3317
Protoss_Zealot 2 4935
Protoss_Cybernetics_Core 1 5154
Protoss_Dragoon 11 11157
Protoss_Nexus 1 9510
Protoss_Robotics_Facility 1 9077
Protoss_Observatory 1 9269
Protoss_Observer 1 10039
Protoss_Robotics_Support_Bay 1 9816
Protoss_Reaver 1 11501
11501
