Protoss_Gateway 2 9669
Protoss_Assimilator 2 10683
Protoss_Zealot 2 4887
Protoss_Cybernetics_Core 1 5073
Protoss_Dragoon 5 9095
Protoss_Nexus 1 9393
Protoss_Citadel_of_Adun 1 8455
Protoss_Forge 1 8485
Protoss_Templar_Archives 1 9671
Protoss_Photon_Cannon 2 10033
Protoss_Dark_Templar 2 10429
Protoss_High_Templar 2 11181
11181
