Protoss_Gateway 2 3968
Protoss_Zealot 3 7015
Protoss_Assimilator 3 7454
Protoss_Nexus 1 7631
Protoss_Cybernetics_Core 1 6674
Protoss_Dragoon 9 10919
Protoss_Robotics_Facility 1 9549
Protoss_Shuttle 1 10415
Protoss_Observatory 1 9789
Protoss_Robotics_Support_Bay 1 10218
Protoss_Observer 1 10853
10919
