Protoss_Gateway 2 10991
Protoss_Assimilator 2 10494
Protoss_Zealot 2 5217
Protoss_Cybernetics_Core 1 5320
Protoss_Dragoon 4 8517
Protoss_Citadel_of_Adun 1 7349
Protoss_Templar_Archives 1 8365
Protoss_Forge 1 7905
Protoss_Photon_Cannon 2 9801
Protoss_Dark_Templar 1 9269
Protoss_Nexus 1 11189
Protoss_High_Templar 1 10321
11189
