Protoss_Gateway 2 8069
Protoss_Assimilator 1 3339
Protoss_Zealot 2 4961
Protoss_Cybernetics_Core 1 5127
Protoss_Dragoon 10 11159
Protoss_Robotics_Facility 1 7476
Protoss_Shuttle 1 8337
Protoss_Observatory 1 8039
Protoss_Observer 2 10543
Protoss_Robotics_Support_Bay 1 8721
Protoss_Reaver 1 10211
Protoss_Nexus 1 12667
12667
