Protoss_Gateway 3 7375
Protoss_Assimilator 1 3258
Protoss_Zealot 2 4613
Protoss_Cybernetics_Core 1 4866
Protoss_Dragoon 15 10801
Protoss_Robotics_Facility 1 7085
Protoss_Observatory 1 7181
Protoss_Observer 2 8583
Protoss_Shuttle 1 11415
11415
