Protoss_Gateway 2 6767
Protoss_Assimilator 1 3162
Protoss_Zealot 2 4773
Protoss_Cybernetics_Core 1 4986
Protoss_Dragoon 1 5723
Protoss_Citadel_of_Adun 1 6413
Protoss_Templar_Archives 1 7401
Protoss_Dark_Templar 2 8179
Protoss_Nexus 1 10111
Protoss_Forge 1 8294
Protoss_Photon_Cannon 7 10992
Protoss_High_Templar 3 10537
10992
