Protoss_Gateway 4 11424
Protoss_Assimilator 2 10438
Protoss_Zealot 2 5001
Protoss_Cybernetics_Core 1 5203
Protoss_Citadel_of_Adun 1 6198
Protoss_Dragoon 3 9749
Protoss_Templar_Archives 1 7193
Protoss_Nexus 1 9558
Protoss_Dark_Templar 2 8901
Protoss_High_Templar 1 10076
Protoss_Robotics_Facility 1 11063
11424
