Protoss_Gateway 3 11383
Protoss_Assimilator 2 10659
Protoss_Cybernetics_Core 1 4502
Protoss_Dragoon 5 10611
Protoss_Nexus 2 11468
Protoss_Forge 1 8014
Protoss_Photon_Cannon 1 9042
Protoss_Robotics_Facility 1 10873
11468
