Protoss_Gateway 2 4144
Protoss_Zealot 5 6137
Protoss_Assimilator 1 4381
Protoss_Cybernetics_Core 1 6014
Protoss_Dragoon 10 10999
Protoss_Robotics_Facility 1 9973
Protoss_Observatory 1 10087
10999
