Protoss_Gateway 1 3388
Protoss_Assimilator 1 3443
Protoss_Zealot 2 4941
Protoss_Cybernetics_Core 1 5840
Protoss_Robotics_Facility 1 7361
Protoss_Dragoon 3 9353
Protoss_Shuttle 1 8341
Protoss_Robotics_Support_Bay 1 7679
Protoss_Citadel_of_Adun 1 9173
Protoss_Reaver 2 10546
Protoss_Forge 1 9258
Protoss_Templar_Archives 1 10169
Protoss_Dark_Templar 1 10951
10951
