Protoss_Gateway 1 3636
Protoss_Assimilator 1 3483
Protoss_Zealot 1 4471
Protoss_Cybernetics_Core 1 5403
Protoss_Robotics_Facility 2 11700
Protoss_Dragoon 5 10871
Protoss_Shuttle 1 8206
Protoss_Robotics_Support_Bay 1 7627
Protoss_Reaver 2 10400
11700
