Protoss_Assimilator 1 2762
Protoss_Gateway 2 8267
Protoss_Cybernetics_Core 1 4868
Protoss_Stargate 1 6108
Protoss_Citadel_of_Adun 1 6183
Protoss_Robotics_Facility 1 7158
Protoss_Corsair 2 7961
Protoss_Templar_Archives 1 7803
Protoss_Forge 1 7465
Protoss_Shuttle 1 7971
Protoss_Dark_Templar 3 9338
Protoss_Nexus 1 11623
Protoss_Dragoon 4 11138
11623
