Protoss_Gateway 1 3483
Protoss_Assimilator 1 3373
Protoss_Cybernetics_Core 1 4563
Protoss_Dragoon 6 10181
Protoss_Robotics_Facility 1 6400
Protoss_Robotics_Support_Bay 1 6514
Protoss_Shield_Battery 1 6722
Protoss_Reaver 2 11120
Protoss_Observatory 1 8187
Protoss_Shuttle 1 9376
Protoss_Observer 1 9798
Protoss_Nexus 1 12583
12583
