Protoss_Gateway 3 8131
Protoss_Assimilator 1 3195
Protoss_Cybernetics_Core 1 4313
Protoss_Dragoon 12 10553
Protoss_Nexus 1 8470
Protoss_Robotics_Facility 2 11708
Protoss_Observatory 1 10600
11708
