Protoss_Gateway 3 8537
Protoss_Assimilator 1 3193
Protoss_Cybernetics_Core 1 4321
Protoss_Robotics_Facility 1 5878
Protoss_Dragoon 12 11126
Protoss_Shuttle 1 6691
Protoss_Observatory 1 7023
Protoss_Observer 2 10246
Protoss_Nexus 1 11378
11378
