Protoss_Gateway 1 2163
Protoss_Assimilator 1 2564
Protoss_Zealot 2 8878
Protoss_Cybernetics_Core 1 4119
Protoss_Robotics_Facility 1 5175
Protoss_Dragoon 2 6023
Protoss_Citadel_of_Adun 1 6093
Protoss_Shuttle 1 6536
Protoss_Robotics_Support_Bay 1 6773
Protoss_Templar_Archives 1 7093
Protoss_Reaver 3 9606
Protoss_Dark_Templar 1 8126
Protoss_Scarab 5 9683
Protoss_Nexus 1 9913
9913
