Protoss_Assimilator 1 2768
Protoss_Gateway 1 3863
Protoss_Cybernetics_Core 1 4863
Protoss_Dragoon 5 8682
Protoss_Robotics_Facility 1 6813
Protoss_Shuttle 1 7656
Protoss_Observatory 1 7637
Protoss_Observer 2 9242
Protoss_Robotics_Support_Bay 1 8731
Protoss_Reaver 2 11616
Protoss_Nexus 1 12315
12315
