Protoss_Gateway 3 8553
Protoss_Assimilator 1 3298
Protoss_Cybernetics_Core 1 4298
Protoss_Robotics_Facility 1 5963
Protoss_Dragoon 12 10938
Protoss_Shuttle 2 10616
Protoss_Observatory 1 6349
Protoss_Observer 2 10798
Protoss_Shield_Battery 1 8189
10938
