Protoss_Gateway 4 10500
Protoss_Assimilator 2 10609
Protoss_Cybernetics_Core 1 4402
Protoss_Dragoon 14 10751
Protoss_Nexus 1 9457
Protoss_Robotics_Facility 1 8821
Protoss_Observatory 1 8918
Protoss_Observer 1 10531
10751
