Protoss_Assimilator 1 2809
Protoss_Gateway 1 3708
Protoss_Cybernetics_Core 1 4708
Protoss_Robotics_Facility 2 7413
Protoss_Zealot 4 7366
Protoss_Observatory 1 6843
Protoss_Robotics_Support_Bay 1 7494
Protoss_Forge 1 9670
Protoss_Photon_Cannon 1 10634
10634
