Protoss_Gateway 2 4588
Protoss_Assimilator 2 4556
Protoss_Zealot 11 8076
Protoss_Cybernetics_Core 1 8090
Protoss_Citadel_of_Adun 1 9088
Protoss_Templar_Archives 1 10085
Protoss_Forge 1 10098
Protoss_Dark_Templar 2 10846
10846
