Protoss_Gateway 4 9974
Protoss_Zealot 5 6546
Protoss_Assimilator 2 5201
Protoss_Cybernetics_Core 1 6371
Protoss_Dragoon 4 8531
Protoss_Citadel_of_Adun 1 8202
Protoss_Templar_Archives 1 9251
Protoss_Dark_Templar 2 10026
Protoss_Nexus 1 12457
Protoss_Forge 1 10710
12457
