Protoss_Gateway 1 1984
Protoss_Assimilator 1 2715
Protoss_Zealot 3 4736
Protoss_Shield_Battery 1 4013
Protoss_Cybernetics_Core 1 4423
Protoss_Dragoon 2 8631
Protoss_Robotics_Facility 2 6245
Protoss_Observatory 1 7299
Protoss_Shuttle 1 7306
Protoss_Robotics_Support_Bay 1 7583
Protoss_Observer 1 7886
Protoss_Reaver 2 8488
Protoss_Scarab 3 9946
9946
