Protoss_Gateway 3 11098
Protoss_Zealot 7 7196
Protoss_Assimilator 1 6473
Protoss_Cybernetics_Core 1 7206
Protoss_Dragoon 7 10556
Protoss_Robotics_Facility 1 10863
Protoss_Nexus 1 12373
12373
