Protoss_Gateway 3 8762
Protoss_Zealot 12 9418
Protoss_Forge 1 6213
Protoss_Assimilator 1 7148
Protoss_Cybernetics_Core 1 8134
Protoss_Nexus 1 9910
Protoss_Photon_Cannon 3 11166
Protoss_Dragoon 2 11176
11176
