Protoss_Gateway 2 6268
Protoss_Assimilator 1 3323
Protoss_Zealot 3 5216
Protoss_Cybernetics_Core 1 5026
Protoss_Shield_Battery 1 4728
Protoss_Dragoon 7 11031
Protoss_Robotics_Facility 1 9034
Protoss_Shuttle 1 9991
Protoss_Robotics_Support_Bay 1 9540
Protoss_Reaver 1 11133
11133
