Protoss_Assimilator 1 2788
Protoss_Gateway 3 10684
Protoss_Cybernetics_Core 1 4758
Protoss_Robotics_Facility 1 6238
Protoss_Shuttle 1 7046
Protoss_Observatory 1 6354
Protoss_Robotics_Support_Bay 1 6444
Protoss_Dragoon 3 10206
Protoss_Observer 1 7468
Protoss_Reaver 2 10666
Protoss_Zealot 1 8681
Protoss_Nexus 1 12503
12503
