Protoss_Gateway 1 3272
Protoss_Assimilator 1 3163
Protoss_Cybernetics_Core 1 4365
Protoss_Zealot 4 6565
Protoss_Robotics_Facility 2 10904
Protoss_Shuttle 2 10718
Protoss_Robotics_Support_Bay 1 6648
Protoss_Reaver 2 9906
Protoss_Dragoon 4 10856
10904
