Protoss_Gateway 3 9651
Protoss_Zealot 8 8871
Protoss_Assimilator 1 5535
Protoss_Cybernetics_Core 1 6442
Protoss_Forge 1 7023
Protoss_Shield_Battery 1 7038
Protoss_Dragoon 6 10996
Protoss_Photon_Cannon 2 10004
Protoss_Robotics_Facility 1 11049
11049
