Protoss_Gateway 2 6335
Protoss_Assimilator 1 3458
Protoss_Zealot 2 4887
Protoss_Cybernetics_Core 1 5190
Protoss_Shield_Battery 1 5115
Protoss_Dragoon 4 10883
Protoss_Robotics_Facility 1 11233
11233
