Protoss_Gateway 2 4143
Protoss_Zealot 9 7177
Protoss_Assimilator 1 5871
Protoss_Cybernetics_Core 1 7332
Protoss_Robotics_Facility 1 9039
Protoss_Shield_Battery 1 8381
Protoss_Dragoon 6 10429
Protoss_Shuttle 1 10135
Protoss_Robotics_Support_Bay 1 9613
Protoss_Reaver 1 11429
11429
