Protoss_Assimilator 1 2971
Protoss_Gateway 3 10531
Protoss_Cybernetics_Core 1 4944
Protoss_Robotics_Facility 1 6446
Protoss_Dragoon 6 10905
Protoss_Observatory 1 6566
Protoss_Robotics_Support_Bay 1 6639
Protoss_Observer 2 10499
Protoss_Shuttle 1 8421
Protoss_Reaver 1 9827
Protoss_Nexus 1 11161
11161
