Protoss_Gateway 3 5869
Protoss_Zealot 9 7849
Protoss_Forge 2 6186
Protoss_Photon_Cannon 3 9058
Protoss_Assimilator 1 7151
Protoss_Cybernetics_Core 1 8022
Protoss_Dragoon 4 10833
Protoss_Citadel_of_Adun 1 9909
Protoss_Templar_Archives 1 10899
10899
