Protoss_Assimilator 1 3474
Protoss_Gateway 1 4019
Protoss_Cybernetics_Core 1 5005
Protoss_Robotics_Facility 1 6479
Protoss_Dragoon 5 10665
Protoss_Shuttle 2 11287
Protoss_Observatory 1 6583
Protoss_Robotics_Support_Bay 1 7338
Protoss_Observer 1 7703
Protoss_Reaver 2 10113
11287
