Protoss_Gateway 4 11392
Protoss_Zealot 7 7783
Protoss_Nexus 1 7749
Protoss_Shield_Battery 1 6058
Protoss_Assimilator 1 6357
Protoss_Forge 1 8087
Protoss_Cybernetics_Core 1 8733
Protoss_Photon_Cannon 2 9156
Protoss_Dragoon 7 11165
11392
