Protoss_Gateway 3 10213
Protoss_Assimilator 1 3426
Protoss_Cybernetics_Core 1 4894
Protoss_Dragoon 3 11123
Protoss_Citadel_of_Adun 1 6050
Protoss_Templar_Archives 1 7443
Protoss_Zealot 4 10751
Protoss_Dark_Templar 2 10150
Protoss_High_Templar 2 8978
Protoss_Archon 1 9506
Protoss_Forge 1 10337
Psionic_Storm 1 9811
11123
