Protoss_Assimilator 1 2814
Protoss_Gateway 2 6893
Protoss_Cybernetics_Core 1 4810
Protoss_Citadel_of_Adun 1 5823
Protoss_Forge 1 6259
Protoss_Templar_Archives 1 7040
Protoss_Photon_Cannon 3 9065
Protoss_Dark_Templar 6 9325
Protoss_Dark_Archon 2 8693
Protoss_Robotics_Facility 1 10253
Protoss_Dragoon 2 10741
Protoss_Shuttle 1 11091
11091
