Protoss_Assimilator 1 2791
Protoss_Gateway 1 3826
Protoss_Cybernetics_Core 1 4897
Protoss_Dragoon 3 9491
Protoss_Robotics_Facility 1 6626
Protoss_Shuttle 1 7536
Protoss_Robotics_Support_Bay 1 6875
Protoss_Observatory 1 6950
Protoss_Observer 3 10310
Protoss_Forge 1 9223
Protoss_Reaver 1 9978
Protoss_Nexus 1 11708
Protoss_Photon_Cannon 3 11188
11708
