Protoss_Gateway 2 7192
Protoss_Zealot 4 6656
Protoss_Assimilator 1 4620
Protoss_Cybernetics_Core 1 6118
Protoss_Robotics_Facility 1 8381
Protoss_Dragoon 6 10298
Protoss_Robotics_Support_Bay 1 8488
Protoss_Reaver 1 10486
Protoss_Shuttle 1 11326
11326
