Protoss_Gateway 2 4218
Protoss_Zealot 7 7076
Protoss_Assimilator 1 5319
Protoss_Cybernetics_Core 1 6700
Protoss_Dragoon 1 7931
Protoss_Citadel_of_Adun 1 8488
Protoss_Templar_Archives 1 9513
Protoss_Dark_Templar 2 10551
Protoss_Forge 1 10675
10675
