Protoss_Nexus 2 12663
Protoss_Gateway 2 6814
Protoss_Assimilator 2 6097
Protoss_Cybernetics_Core 1 6148
Protoss_Robotics_Facility 1 8033
Protoss_Dragoon 6 9821
Protoss_Observatory 1 8143
Protoss_Shuttle 1 9261
Protoss_Robotics_Support_Bay 1 8708
Protoss_Observer 2 10285
Protoss_Forge 1 10742
12663
