Protoss_Nexus 2 12239
Protoss_Assimilator 2 6475
Protoss_Gateway 3 9443
Protoss_Cybernetics_Core 1 6073
Protoss_Stargate 1 7388
Protoss_Citadel_of_Adun 1 7286
Protoss_Forge 1 7088
Protoss_Photon_Cannon 3 8673
Protoss_Corsair 2 8601
Protoss_Templar_Archives 1 8668
Protoss_Robotics_Facility 1 10324
Protoss_High_Templar 1 9761
Protoss_Shuttle 1 11166
Protoss_Robotics_Support_Bay 1 10552
12239
