Protoss_Gateway 3 10512
Protoss_Zealot 15 9016
Protoss_Assimilator 1 7428
Protoss_Cybernetics_Core 1 8198
Protoss_Citadel_of_Adun 1 9668
Protoss_Forge 1 9398
Protoss_Templar_Archives 1 11031
Protoss_Photon_Cannon 2 11162
11162
