Protoss_Gateway 2 5579
Protoss_Assimilator 1 3518
Protoss_Cybernetics_Core 1 4683
Protoss_Zealot 2 5291
Protoss_Dragoon 5 7738
Protoss_Citadel_of_Adun 1 8322
Protoss_Templar_Archives 1 9838
Protoss_Forge 1 9404
Protoss_Dark_Templar 2 10891
10891
