Protoss_Gateway 2 10508
Protoss_Assimilator 1 3383
Protoss_Zealot 2 4701
Protoss_Cybernetics_Core 1 5533
Protoss_Dragoon 6 11116
Protoss_Robotics_Facility 1 7630
Protoss_Shuttle 1 8446
Protoss_Robotics_Support_Bay 1 7748
Protoss_Shield_Battery 1 8592
Protoss_Reaver 1 9651
Protoss_Scarab 4 9721
11116
