Protoss_Gateway 2 5519
Protoss_Assimilator 1 3558
Protoss_Zealot 3 6276
Protoss_Cybernetics_Core 1 5798
Protoss_Dragoon 10 10770
Protoss_Robotics_Facility 1 9663
Protoss_Observatory 1 9789
Protoss_Shuttle 1 10601
10770
