Protoss_Gateway 2 4128
Protoss_Zealot 11 8491
Protoss_Nexus 1 9973
Protoss_Assimilator 1 8448
Protoss_Forge 1 9413
Protoss_Cybernetics_Core 1 9947
Protoss_Photon_Cannon 2 10642
Protoss_Dragoon 2 10876
10876
