Protoss_Nexus 1 5917
Protoss_Gateway 5 11125
Protoss_Zealot 9 10756
Protoss_Assimilator 1 7193
Protoss_Forge 1 7567
Protoss_Cybernetics_Core 1 8480
Protoss_Photon_Cannon 1 9118
Protoss_Dragoon 4 10476
Protoss_Citadel_of_Adun 1 10069
11125
