Protoss_Assimilator 1 2756
Protoss_Gateway 3 9443
Protoss_Cybernetics_Core 1 4829
Protoss_Robotics_Facility 1 6361
Protoss_Dragoon 12 11136
Protoss_Shuttle 1 7206
Protoss_Observatory 1 6660
Protoss_Observer 2 9106
Protoss_Robotics_Support_Bay 1 9457
11136
