Protoss_Assimilator 1 2583
Protoss_Gateway 3 10882
Protoss_Cybernetics_Core 1 4713
Protoss_Robotics_Facility 1 6288
Protoss_Dragoon 7 10746
Protoss_Shuttle 1 7231
Protoss_Observatory 1 6883
Protoss_Observer 1 7931
Protoss_Robotics_Support_Bay 1 7783
Protoss_Reaver 2 10676
10882
