Protoss_Gateway 3 7426
Protoss_Zealot 9 9391
Protoss_Assimilator 1 5968
Protoss_Cybernetics_Core 1 7153
Protoss_Citadel_of_Adun 1 8389
Protoss_Templar_Archives 1 9602
Protoss_Dragoon 2 9951
Protoss_Dark_Templar 4 11151
11151
