Protoss_Gateway 3 11293
Protoss_Zealot 5 6331
Protoss_Assimilator 1 4910
Protoss_Cybernetics_Core 1 6396
Protoss_Dragoon 6 9326
Protoss_Robotics_Facility 1 8598
Protoss_Observatory 1 9291
Protoss_Observer 1 10166
11293
