Protoss_Gateway 2 4159
Protoss_Zealot 7 10651
Protoss_Assimilator 1 4966
Protoss_Cybernetics_Core 1 6403
Protoss_Dragoon 10 10967
Protoss_Robotics_Facility 1 9172
Protoss_Observatory 1 9385
Protoss_Observer 1 10201
10967
