Protoss_Gateway 3 9444
Protoss_Zealot 5 6491
Protoss_Assimilator 1 5474
Protoss_Cybernetics_Core 1 6549
Protoss_Dragoon 10 11033
Protoss_Robotics_Facility 1 10448
Protoss_Observatory 1 10652
11033
