Protoss_Gateway 2 6041
Protoss_Assimilator 1 3459
Protoss_Cybernetics_Core 1 4543
Protoss_Zealot 1 4276
Protoss_Dragoon 7 9526
Protoss_Robotics_Facility 1 9625
Protoss_Observatory 1 9793
Protoss_Robotics_Support_Bay 1 10065
Protoss_Observer 1 10596
Protoss_Nexus 1 12778
12778
