Protoss_Gateway 3 10924
Protoss_Zealot 15 9281
Protoss_Assimilator 1 5633
Protoss_Forge 1 7035
Protoss_Cybernetics_Core 1 7925
Protoss_Photon_Cannon 2 10379
Protoss_Citadel_of_Adun 1 9214
Protoss_Templar_Archives 1 10208
Protoss_Dark_Templar 2 10961
10961
