Protoss_Gateway 3 8713
Protoss_Assimilator 1 3269
Protoss_Zealot 2 4976
Protoss_Cybernetics_Core 1 5169
Protoss_Dragoon 9 10986
Protoss_Robotics_Facility 1 7514
Protoss_Observatory 1 7652
Protoss_Observer 3 9660
Protoss_Nexus 1 12220
Protoss_Robotics_Support_Bay 1 10281
12220
