Protoss_Gateway 3 10256
Protoss_Assimilator 1 3225
Protoss_Zealot 2 4921
Protoss_Cybernetics_Core 1 5043
Protoss_Dragoon 11 11051
Protoss_Robotics_Facility 1 8628
Protoss_Observatory 1 8773
Protoss_Observer 2 10158
11051
