Protoss_Assimilator 1 2783
Protoss_Gateway 3 9618
Protoss_Cybernetics_Core 1 4718
Protoss_Zealot 11 10871
Protoss_Dragoon 1 5666
Protoss_Citadel_of_Adun 1 6123
Protoss_Templar_Archives 1 7422
Protoss_Dark_Templar 1 8171
Protoss_High_Templar 3 9666
Psionic_Storm 1 9501
10871
