Protoss_Gateway 2 4844
Protoss_Assimilator 1 3419
Protoss_Cybernetics_Core 1 4476
Protoss_Dragoon 11 11021
Protoss_Robotics_Facility 1 7603
Protoss_Observatory 1 7715
Protoss_Observer 3 10401
Protoss_Forge 1 10473
Protoss_Robotics_Support_Bay 1 10689
11021
