Protoss_Gateway 2 6098
Protoss_Assimilator 1 3422
Protoss_Zealot 3 5066
Protoss_Cybernetics_Core 1 5332
Protoss_Dragoon 11 10551
Protoss_Robotics_Facility 1 9108
Protoss_Observatory 1 9230
Protoss_Observer 1 10016
10551
