Protoss_Gateway 2 6734
Protoss_Zealot 9 10938
Protoss_Assimilator 1 4175
Protoss_Cybernetics_Core 1 5263
Protoss_Dragoon 2 7046
Protoss_Citadel_of_Adun 1 6888
Protoss_Templar_Archives 1 7878
Protoss_Forge 1 7777
Protoss_Dark_Templar 2 8636
Protoss_Photon_Cannon 2 9178
Protoss_High_Templar 2 9781
10938
