Protoss_Gateway 1 3424
Protoss_Assimilator 1 3644
Protoss_Zealot 2 5176
Protoss_Cybernetics_Core 1 5241
Protoss_Dragoon 7 10690
Protoss_Robotics_Facility 1 7441
Protoss_Shuttle 1 8251
Protoss_Robotics_Support_Bay 1 7643
Protoss_Reaver 2 10561
Protoss_Observatory 1 10334
10690
