Protoss_Gateway 4 11101
Protoss_Assimilator 1 3313
Protoss_Zealot 2 4896
Protoss_Cybernetics_Core 1 5141
Protoss_Dragoon 10 10821
Protoss_Robotics_Facility 1 9005
Protoss_Nexus 1 11106
Protoss_Observatory 1 9269
11106
