Protoss_Gateway 3 10294
Protoss_Assimilator 1 3290
Protoss_Zealot 7 10115
Protoss_Cybernetics_Core 1 5101
Protoss_Citadel_of_Adun 1 6113
Protoss_Robotics_Facility 1 6943
Protoss_Templar_Archives 1 7201
Protoss_Shuttle 2 11007
Protoss_Dark_Templar 2 8027
Protoss_Forge 1 8027
Protoss_Photon_Cannon 1 9189
Protoss_High_Templar 1 10579
11007
