Protoss_Assimilator 1 2770
Protoss_Gateway 1 3638
Protoss_Cybernetics_Core 1 4679
Protoss_Robotics_Facility 1 6153
Protoss_Zealot 2 5858
Protoss_Shuttle 1 6961
Protoss_Dragoon 6 11147
Protoss_Robotics_Support_Bay 1 6638
Protoss_Reaver 2 9378
Protoss_Forge 1 9147
Protoss_Observatory 1 9396
Protoss_Photon_Cannon 1 10238
Protoss_Observer 2 10773
Protoss_Scarab 2 9981
11147
