Protoss_Gateway 3 9768
Protoss_Assimilator 1 3203
Protoss_Cybernetics_Core 1 4453
Protoss_Robotics_Facility 1 6028
Protoss_Dragoon 7 11036
Protoss_Shuttle 1 6896
Protoss_Robotics_Support_Bay 1 6468
Protoss_Observatory 1 6936
Protoss_Reaver 2 9705
Protoss_Observer 2 10711
Protoss_Scarab 1 7575
Protoss_Nexus 1 12023
12023
