Protoss_Gateway 2 10836
Protoss_Assimilator 1 3307
Protoss_Cybernetics_Core 1 4439
Protoss_Zealot 1 4517
Protoss_Dragoon 7 10703
Protoss_Robotics_Facility 1 6365
Protoss_Shuttle 1 7225
Protoss_Observatory 1 6643
Protoss_Observer 2 8249
Protoss_Nexus 1 12688
Protoss_Forge 1 10846
12688
