Protoss_Gateway 2 5816
Protoss_Assimilator 1 3313
Protoss_Cybernetics_Core 1 4445
Protoss_Dragoon 12 10939
Protoss_Robotics_Facility 1 8478
Protoss_Shuttle 1 9279
Protoss_Observatory 1 8599
Protoss_Robotics_Support_Bay 1 9437
Protoss_Observer 1 9765
Protoss_Reaver 1 11087
11087
