Protoss_Gateway 2 6104
Protoss_Assimilator 1 3303
Protoss_Cybernetics_Core 1 4451
Protoss_Dragoon 11 10471
Protoss_Robotics_Facility 1 8319
Protoss_Zealot 1 7619
Protoss_Robotics_Support_Bay 1 8575
Protoss_Reaver 2 11243
Protoss_Nexus 1 11841
11841
