Protoss_Gateway 3 11211
Protoss_Assimilator 1 3367
Protoss_Cybernetics_Core 1 4384
Protoss_Zealot 4 6878
Protoss_Dragoon 9 11161
Protoss_Robotics_Facility 1 8993
Protoss_Observatory 1 9363
Protoss_Observer 2 10831
11211
