Protoss_Gateway 1 3309
Protoss_Assimilator 2 8110
Protoss_Zealot 3 8603
Protoss_Cybernetics_Core 1 4917
Protoss_Robotics_Facility 1 6465
Protoss_Dragoon 2 8659
Protoss_Observatory 1 6640
Protoss_Shuttle 1 7481
Protoss_Observer 2 8011
Protoss_Stargate 2 10041
Protoss_Nexus 1 9624
Protoss_Robotics_Support_Bay 1 7991
Protoss_Fleet_Beacon 1 9418
Protoss_Carrier 2 13267
Protoss_Forge 1 10563
13267
