Protoss_Gateway 4 11083
Protoss_Assimilator 2 10188
Protoss_Zealot 2 4727
Protoss_Cybernetics_Core 1 4955
Protoss_Robotics_Facility 1 6531
Protoss_Dragoon 10 11049
Protoss_Observatory 1 6712
Protoss_Observer 4 9660
Protoss_Nexus 1 10597
11083
