Protoss_Gateway 2 9875
Protoss_Zealot 6 8725
Protoss_Nexus 2 11577
Protoss_Assimilator 2 8519
Protoss_Cybernetics_Core 1 7388
Protoss_Dragoon 1 8213
Protoss_Citadel_of_Adun 1 8603
Protoss_Forge 1 9082
Protoss_Templar_Archives 1 9585
Protoss_Photon_Cannon 3 10473
Protoss_Dark_Templar 2 10625
Protoss_Robotics_Facility 1 11684
11684
