Protoss_Gateway 2 9465
Protoss_Zealot 5 7197
Protoss_Nexus 2 11561
Protoss_Assimilator 2 8349
Protoss_Cybernetics_Core 1 7028
Protoss_Citadel_of_Adun 1 8180
Protoss_Dragoon 1 8071
Protoss_Templar_Archives 1 9283
Protoss_Forge 1 9408
Protoss_Dark_Templar 2 10203
Protoss_Photon_Cannon 2 10501
Protoss_High_Templar 2 10955
Protoss_Robotics_Facility 1 11832
11832
