Protoss_Gateway 3 10303
Protoss_Zealot 2 5745
Protoss_Nexus 1 6387
Protoss_Assimilator 2 9784
Protoss_Cybernetics_Core 1 5935
Protoss_Dragoon 11 10877
Protoss_Shield_Battery 1 8148
Protoss_Robotics_Facility 1 10060
Protoss_Observatory 1 10269
Protoss_Forge 1 10730
10877
