Protoss_Gateway 2 7321
Protoss_Assimilator 1 3358
Protoss_Cybernetics_Core 1 4369
Protoss_Dragoon 7 10741
Protoss_Citadel_of_Adun 1 6781
Protoss_Templar_Archives 1 8023
Protoss_Forge 1 8123
Protoss_Dark_Templar 3 9755
Protoss_Nexus 1 11509
11509
