Protoss_Gateway 2 6850
Protoss_Assimilator 1 2808
Protoss_Cybernetics_Core 1 3764
Protoss_Dragoon 9 10518
Protoss_Robotics_Facility 1 6252
Protoss_Shuttle 1 7987
Protoss_Robotics_Support_Bay 1 7567
Protoss_Reaver 2 10213
Protoss_Nexus 1 11115
11115
