Protoss_Gateway 4 10642
Protoss_Zealot 10 7678
Protoss_Nexus 1 6589
Protoss_Assimilator 1 5897
Protoss_Forge 1 6686
Protoss_Cybernetics_Core 1 7710
Protoss_Photon_Cannon 4 10717
Protoss_Dragoon 6 10628
10717
