Protoss_Gateway 2 8308
Protoss_Zealot 2 4226
Protoss_Assimilator 1 3686
Protoss_Cybernetics_Core 1 4841
Protoss_Dragoon 9 10670
Protoss_Nexus 2 11361
Protoss_Robotics_Facility 1 7893
Protoss_Observatory 1 8444
Protoss_Observer 1 9140
Protoss_Robotics_Support_Bay 1 9083
Protoss_Reaver 1 10356
11361
