Protoss_Gateway 3 10586
Protoss_Zealot 3 5214
Protoss_Assimilator 1 3741
Protoss_Cybernetics_Core 1 4967
Protoss_Dragoon 6 10510
Protoss_Nexus 1 8723
Protoss_Robotics_Facility 1 8362
Protoss_Observatory 1 8957
Protoss_Observer 1 9800
10586
