Protoss_Gateway 4 10762
Protoss_Zealot 3 4728
Protoss_Assimilator 1 3661
Protoss_Cybernetics_Core 1 4715
Protoss_Dragoon 8 10172
Protoss_Nexus 1 8101
Protoss_Robotics_Facility 1 8269
Protoss_Observatory 1 8830
Protoss_Observer 1 9836
Protoss_Shuttle 1 10845
10845
