Protoss_Gateway 2 8334
Protoss_Assimilator 1 2880
Protoss_Cybernetics_Core 1 3834
Protoss_Dragoon 6 10468
Protoss_Citadel_of_Adun 1 5931
Protoss_Templar_Archives 1 7023
Protoss_Nexus 2 10743
Protoss_Dark_Templar 2 8638
Protoss_High_Templar 2 9390
Protoss_Forge 1 10103
10743
