Protoss_Assimilator 1 2430
Protoss_Gateway 1 3224
Protoss_Cybernetics_Core 1 4234
Protoss_Robotics_Facility 1 5532
Protoss_Dragoon 4 9843
Protoss_Shuttle 1 6587
Protoss_Robotics_Support_Bay 1 6236
Protoss_Observatory 1 6381
Protoss_Observer 1 7190
Protoss_Reaver 2 9448
Protoss_Nexus 1 11292
11292
