Protoss_Gateway 3 9099
Protoss_Assimilator 1 2865
Protoss_Cybernetics_Core 1 3756
Protoss_Zealot 4 6188
Protoss_Robotics_Facility 1 5292
Protoss_Shuttle 1 6282
Protoss_Observatory 1 6582
Protoss_Dragoon 7 10178
Protoss_Observer 3 9307
10178
