Protoss_Assimilator 1 2275
Protoss_Gateway 2 8660
Protoss_Cybernetics_Core 1 4337
Protoss_Robotics_Facility 1 5663
Protoss_Dragoon 9 10262
Protoss_Shuttle 2 9252
Protoss_Nexus 1 9162
Protoss_Observatory 1 8034
Protoss_Robotics_Support_Bay 1 9092
Protoss_Observer 1 10188
10262
