Protoss_Gateway 2 9688
Protoss_Assimilator 1 2832
Protoss_Cybernetics_Core 1 3779
Protoss_Robotics_Facility 1 5303
Protoss_Dragoon 3 10543
Protoss_Shuttle 1 6312
Protoss_Zealot 3 7590
Protoss_Robotics_Support_Bay 1 6446
Protoss_Reaver 2 9335
Protoss_Forge 1 9331
Protoss_Photon_Cannon 3 10712
10712
