Protoss_Nexus 1 4795
Protoss_Gateway 3 10311
Protoss_Assimilator 1 4444
Protoss_Cybernetics_Core 1 5489
Protoss_Dragoon 8 10500
Protoss_Forge 1 7895
Protoss_Robotics_Facility 1 9126
Protoss_Photon_Cannon 4 9462
10500
