Protoss_Gateway 1 2874
Protoss_Assimilator 1 2970
Protoss_Cybernetics_Core 1 4076
Protoss_Zealot 3 7948
Protoss_Robotics_Facility 1 5680
Protoss_Dragoon 2 6388
Protoss_Shuttle 1 6797
Protoss_Robotics_Support_Bay 1 6677
Protoss_Reaver 2 10651
Protoss_Nexus 1 10212
10651
