Protoss_Gateway 2 7544
Protoss_Assimilator 1 3085
Protoss_Zealot 5 10118
Protoss_Cybernetics_Core 1 5230
Protoss_Dragoon 2 6868
Protoss_Citadel_of_Adun 1 6856
Protoss_Robotics_Facility 1 7597
Protoss_Templar_Archives 1 7944
Protoss_Observatory 1 8261
Protoss_Shuttle 2 10234
Protoss_Dark_Templar 3 9565
Protoss_Observer 1 9333
Protoss_Forge 1 9779
10234
