Protoss_Gateway 2 6201
Protoss_Assimilator 1 3215
Protoss_Zealot 1 3728
Protoss_Cybernetics_Core 1 4887
Protoss_Dragoon 10 10568
Protoss_Robotics_Facility 1 8008
Protoss_Shuttle 1 9197
Protoss_Robotics_Support_Bay 1 9101
Protoss_Reaver 1 10421
10568
