Protoss_Gateway 4 10293
Protoss_Assimilator 1 3075
Protoss_Zealot 1 3548
Protoss_Cybernetics_Core 1 4744
Protoss_Dragoon 10 10023
Protoss_Robotics_Facility 1 8872
Protoss_Observatory 1 9444
Protoss_Observer 1 10133
10293
