Protoss_Gateway 2 7974
Protoss_Assimilator 1 2906
Protoss_Cybernetics_Core 1 4020
Protoss_Robotics_Facility 1 5383
Protoss_Dragoon 8 9565
Protoss_Observatory 1 6062
Protoss_Observer 2 8688
Protoss_Nexus 2 11500
Protoss_Forge 1 8864
Protoss_Photon_Cannon 1 9931
11500
