Protoss_Gateway 3 9893
Protoss_Assimilator 1 3201
Protoss_Zealot 2 4565
Protoss_Cybernetics_Core 1 5406
Protoss_Dragoon 8 10205
Protoss_Robotics_Facility 1 7017
Protoss_Observatory 1 7646
Protoss_Observer 3 9763
Protoss_Shuttle 1 10664
10664
