Protoss_Gateway 2 10665
Protoss_Assimilator 1 3004
Protoss_Zealot 2 4848
Protoss_Cybernetics_Core 1 4804
Protoss_Dragoon 2 6848
Protoss_Citadel_of_Adun 1 6344
Protoss_Templar_Archives 1 7557
Protoss_Robotics_Facility 1 8197
Protoss_Dark_Templar 1 8413
Protoss_Forge 1 8385
Protoss_High_Templar 3 10740
Protoss_Shuttle 1 9707
Protoss_Photon_Cannon 1 9935
Psionic_Storm 1 9816
10740
