Protoss_Assimilator 1 2448
Protoss_Gateway 3 7296
Protoss_Cybernetics_Core 1 4315
Protoss_Dragoon 1 5198
Protoss_Citadel_of_Adun 1 5516
Protoss_Zealot 11 10108
Protoss_Templar_Archives 1 10229
10229
