Protoss_Gateway 1 2779
Protoss_Assimilator 1 3101
Protoss_Cybernetics_Core 1 4034
Protoss_Dragoon 7 9649
Protoss_Robotics_Facility 1 6706
Protoss_Observatory 1 7415
Protoss_Observer 2 10055
Protoss_Shuttle 1 9452
10055
