Protoss_Gateway 2 10537
Protoss_Assimilator 1 3180
Protoss_Cybernetics_Core 1 4642
Protoss_Zealot 1 4633
Protoss_Dragoon 4 9870
Protoss_Robotics_Facility 1 6422
Protoss_Shuttle 1 7482
Protoss_Observatory 1 7196
Protoss_Robotics_Support_Bay 1 7561
Protoss_Observer 1 8085
Protoss_Reaver 2 10641
10641
