Protoss_Gateway 2 6897
Protoss_Assimilator 1 3201
Protoss_Zealot 1 3788
Protoss_Cybernetics_Core 1 4705
Protoss_Dragoon 7 9813
Protoss_Robotics_Facility 1 6042
Protoss_Shuttle 1 7062
Protoss_Observatory 1 6706
Protoss_Observer 1 7665
Protoss_Robotics_Support_Bay 1 8071
Protoss_Reaver 2 10596
10596
