Protoss_Gateway 1 2837
Protoss_Assimilator 1 2971
Protoss_Zealot 2 4490
Protoss_Cybernetics_Core 1 4539
Protoss_Dragoon 2 6706
Protoss_Citadel_of_Adun 1 5691
Protoss_Templar_Archives 1 6681
Protoss_Forge 1 7162
Protoss_Dark_Templar 2 8312
Protoss_High_Templar 3 10718
Protoss_Nexus 1 10516
Protoss_Photon_Cannon 5 10578
Psionic_Storm 1 9595
10718
