Protoss_Gateway 2 6207
Protoss_Assimilator 1 2810
Protoss_Cybernetics_Core 1 3789
Protoss_Dragoon 13 10434
Protoss_Robotics_Facility 1 7284
Protoss_Observatory 1 7827
Protoss_Observer 3 10300
Protoss_Nexus 1 11195
11195
