Protoss_Gateway 3 8668
Protoss_Assimilator 1 2874
Protoss_Cybernetics_Core 1 3815
Protoss_Robotics_Facility 1 5253
Protoss_Dragoon 7 10196
Protoss_Shuttle 1 6237
Protoss_Observatory 1 6115
Protoss_Observer 3 8124
10196
