Protoss_Gateway 2 9946
Protoss_Assimilator 1 3004
Protoss_Cybernetics_Core 1 3837
Protoss_Robotics_Facility 1 5351
Protoss_Zealot 2 6106
Protoss_Shuttle 1 6337
Protoss_Observatory 1 6064
Protoss_Observer 3 10068
Protoss_Dragoon 5 10696
Protoss_Nexus 1 9303
10696
