Protoss_Gateway 3 10466
Protoss_Zealot 5 6003
Protoss_Assimilator 1 4118
Protoss_Cybernetics_Core 1 5744
Protoss_Dragoon 5 10183
Protoss_Robotics_Facility 1 7901
Protoss_Observatory 1 8554
Protoss_Robotics_Support_Bay 1 8657
Protoss_Shuttle 1 9227
Protoss_Observer 2 10432
10466
