Protoss_Gateway 2 3334
Protoss_Zealot 9 6808
Protoss_Assimilator 1 5187
Protoss_Cybernetics_Core 1 6507
Protoss_Dragoon 8 10533
Protoss_Robotics_Facility 1 9255
Protoss_Forge 1 9374
Protoss_Observatory 1 9847
Protoss_Observer 1 10553
10553
