Protoss_Gateway 2 5836
Protoss_Zealot 5 8708
Protoss_Assimilator 1 3500
Protoss_Cybernetics_Core 1 4687
Protoss_Dragoon 1 6016
Protoss_Citadel_of_Adun 1 7690
Protoss_Templar_Archives 1 8689
Protoss_Forge 1 8521
Protoss_High_Templar 2 9863
Protoss_Nexus 1 11275
Protoss_Photon_Cannon 1 10600
11275
