Protoss_Gateway 2 7378
Protoss_Assimilator 1 2960
Protoss_Cybernetics_Core 1 3903
Protoss_Zealot 1 3926
Protoss_Dragoon 2 6536
Protoss_Citadel_of_Adun 1 6313
Protoss_Templar_Archives 1 7443
Protoss_Forge 2 7724
Protoss_Dark_Templar 2 8370
Protoss_Photon_Cannon 3 10655
Protoss_Nexus 1 10801
10801
