Protoss_Gateway 3 8653
Protoss_Zealot 3 4708
Protoss_Assimilator 1 3627
Protoss_Cybernetics_Core 1 4812
Protoss_Dragoon 8 10448
Protoss_Nexus 1 7930
Protoss_Robotics_Facility 1 8172
Protoss_Observatory 1 8744
Protoss_Observer 2 10060
Protoss_Robotics_Support_Bay 1 9433
10448
