Protoss_Gateway 4 10880
Protoss_Assimilator 2 10075
Protoss_Zealot 2 4638
Protoss_Cybernetics_Core 1 4659
Protoss_Citadel_of_Adun 1 5654
Protoss_Dragoon 3 9296
Protoss_Templar_Archives 1 6649
Protoss_Nexus 1 8470
Protoss_Dark_Templar 2 8448
Protoss_High_Templar 1 9623
Protoss_Robotics_Facility 1 10337
10880
