Protoss_Gateway 3 10839
Protoss_Assimilator 2 10296
Protoss_Cybernetics_Core 1 3958
Protoss_Dragoon 5 10158
Protoss_Nexus 2 10380
Protoss_Forge 1 7651
Protoss_Photon_Cannon 1 8589
Protoss_Robotics_Facility 1 10147
10839
