Protoss_Gateway 1 3092
Protoss_Assimilator 1 3120
Protoss_Zealot 1 4108
Protoss_Cybernetics_Core 1 4859
Protoss_Robotics_Facility 2 10974
Protoss_Dragoon 5 10418
Protoss_Shuttle 1 7662
Protoss_Robotics_Support_Bay 1 7355
Protoss_Reaver 2 9765
10974
