Protoss_Gateway 1 2844
Protoss_Assimilator 1 3080
Protoss_Zealot 2 4578
Protoss_Cybernetics_Core 1 5296
Protoss_Robotics_Facility 1 6635
Protoss_Dragoon 3 8900
Protoss_Shuttle 1 7797
Protoss_Robotics_Support_Bay 1 7407
Protoss_Citadel_of_Adun 1 8629
Protoss_Reaver 2 9911
Protoss_Forge 1 8895
Protoss_Templar_Archives 1 9625
Protoss_Dark_Templar 1 10498
10498
