Protoss_Gateway 3 7993
Protoss_Assimilator 1 2830
Protoss_Cybernetics_Core 1 3777
Protoss_Robotics_Facility 1 5152
Protoss_Dragoon 12 10673
Protoss_Shuttle 1 6147
Protoss_Observatory 1 6751
Protoss_Observer 2 9883
Protoss_Nexus 1 10290
10673
