Protoss_Assimilator 1 2399
Protoss_Gateway 2 7723
Protoss_Cybernetics_Core 1 4324
Protoss_Stargate 1 5473
Protoss_Citadel_of_Adun 1 5639
Protoss_Robotics_Facility 1 6432
Protoss_Corsair 2 7598
Protoss_Templar_Archives 1 7259
Protoss_Forge 1 7102
Protoss_Shuttle 1 7427
Protoss_Dark_Templar 3 8885
Protoss_Nexus 1 10535
Protoss_Dragoon 4 10685
10685
