Protoss_Assimilator 1 2405
Protoss_Gateway 1 3319
Protoss_Cybernetics_Core 1 4319
Protoss_Dragoon 5 8229
Protoss_Robotics_Facility 1 6087
Protoss_Shuttle 1 7112
Protoss_Observatory 1 7365
Protoss_Observer 2 8879
Protoss_Robotics_Support_Bay 1 8459
Protoss_Reaver 2 10981
Protoss_Nexus 1 11227
11227
