Protoss_Gateway 3 8009
Protoss_Assimilator 1 2935
Protoss_Cybernetics_Core 1 3754
Protoss_Robotics_Facility 1 5237
Protoss_Dragoon 12 10485
Protoss_Shuttle 2 10072
Protoss_Observatory 1 6077
Protoss_Observer 2 10435
Protoss_Shield_Battery 1 7917
10485
