Protoss_Assimilator 1 2446
Protoss_Gateway 1 3164
Protoss_Cybernetics_Core 1 4164
Protoss_Robotics_Facility 2 6687
Protoss_Zealot 4 7003
Protoss_Observatory 1 6571
Protoss_Robotics_Support_Bay 1 7222
Protoss_Forge 1 9307
Protoss_Photon_Cannon 1 10181
10181
