Protoss_Gateway 1 2728
Protoss_Assimilator 1 2800
Protoss_Cybernetics_Core 1 3821
Protoss_Zealot 4 6202
Protoss_Robotics_Facility 2 10178
Protoss_Shuttle 2 10174
Protoss_Robotics_Support_Bay 1 6376
Protoss_Reaver 2 9271
Protoss_Dragoon 4 10403
10403
