Protoss_Assimilator 1 2425
Protoss_Gateway 3 10140
Protoss_Cybernetics_Core 1 4214
Protoss_Robotics_Facility 1 5512
Protoss_Shuttle 1 6502
Protoss_Observatory 1 6082
Protoss_Robotics_Support_Bay 1 6172
Protoss_Dragoon 3 9753
Protoss_Observer 1 7105
Protoss_Reaver 2 10031
Protoss_Zealot 1 8318
Protoss_Nexus 1 11415
11415
