Protoss_Assimilator 1 2608
Protoss_Gateway 3 9987
Protoss_Cybernetics_Core 1 4400
Protoss_Robotics_Facility 1 5720
Protoss_Dragoon 6 10452
Protoss_Observatory 1 6294
Protoss_Robotics_Support_Bay 1 6367
Protoss_Observer 2 10136
Protoss_Shuttle 1 7877
Protoss_Reaver 1 9192
Protoss_Nexus 1 10073
10452
