Protoss_Assimilator 1 3111
Protoss_Gateway 1 3475
Protoss_Cybernetics_Core 1 4461
Protoss_Robotics_Facility 1 5753
Protoss_Dragoon 5 10212
Protoss_Shuttle 2 10743
Protoss_Observatory 1 6311
Protoss_Robotics_Support_Bay 1 7066
Protoss_Observer 1 7340
Protoss_Reaver 2 9478
10743
