Protoss_Assimilator 1 2428
Protoss_Gateway 1 3282
Protoss_Cybernetics_Core 1 4353
Protoss_Dragoon 3 9038
Protoss_Robotics_Facility 1 5900
Protoss_Shuttle 1 6992
Protoss_Robotics_Support_Bay 1 6603
Protoss_Observatory 1 6678
Protoss_Observer 3 9947
Protoss_Forge 1 8860
Protoss_Reaver 1 9343
Protoss_Nexus 1 10620
Protoss_Photon_Cannon 3 10735
10735
