Protoss_Assimilator 1 2451
Protoss_Gateway 2 6349
Protoss_Cybernetics_Core 1 4266
Protoss_Citadel_of_Adun 1 5279
Protoss_Forge 1 5896
Protoss_Templar_Archives 1 6496
Protoss_Photon_Cannon 3 8612
Protoss_Dark_Templar 6 8872
Protoss_Dark_Archon 2 8512
Protoss_Robotics_Facility 1 9527
Protoss_Dragoon 2 10288
Protoss_Shuttle 1 10547
10547
