Protoss_Nexus 1 4829
Protoss_Gateway 5 10581
Protoss_Zealot 9 10393
Protoss_Assimilator 1 6830
Protoss_Forge 1 7204
Protoss_Cybernetics_Core 1 7936
Protoss_Photon_Cannon 1 8665
Protoss_Dragoon 4 10023
Protoss_Citadel_of_Adun 1 9525
10581
