Protoss_Gateway 3 10380
Protoss_Zealot 15 8918
Protoss_Assimilator 1 5270
Protoss_Forge 1 6672
Protoss_Cybernetics_Core 1 7381
Protoss_Photon_Cannon 2 9926
Protoss_Citadel_of_Adun 1 8670
Protoss_Templar_Archives 1 9664
Protoss_Dark_Templar 2 10508
10508
