Protoss_Gateway 2 5497
Protoss_Assimilator 1 3096
Protoss_Cybernetics_Core 1 3999
Protoss_Zealot 1 3913
Protoss_Dragoon 7 9073
Protoss_Robotics_Facility 1 8899
Protoss_Observatory 1 9521
Protoss_Robotics_Support_Bay 1 9793
Protoss_Observer 1 10233
Protoss_Nexus 1 11690
11690
