Protoss_Gateway 2 4300
Protoss_Assimilator 1 3056
Protoss_Cybernetics_Core 1 3932
Protoss_Dragoon 11 10568
Protoss_Robotics_Facility 1 6877
Protoss_Observatory 1 7443
Protoss_Observer 3 10038
Protoss_Forge 1 10110
Protoss_Robotics_Support_Bay 1 10417
10568
