Protoss_Assimilator 1 2420
Protoss_Gateway 3 9074
Protoss_Cybernetics_Core 1 4174
Protoss_Zealot 11 10508
Protoss_Dragoon 1 5213
Protoss_Citadel_of_Adun 1 5579
Protoss_Templar_Archives 1 6878
Protoss_Dark_Templar 1 7718
Protoss_High_Templar 3 9213
Psionic_Storm 1 9501
10508
