Protoss_Gateway 2 10292
Protoss_Assimilator 1 2944
Protoss_Cybernetics_Core 1 3895
Protoss_Zealot 1 4154
Protoss_Dragoon 7 10250
Protoss_Robotics_Facility 1 5639
Protoss_Shuttle 1 6681
Protoss_Observatory 1 6371
Protoss_Observer 2 7886
Protoss_Nexus 1 11600
Protoss_Forge 1 10483
11600
