Protoss_Gateway 3 9750
Protoss_Assimilator 1 2927
Protoss_Zealot 7 9752
Protoss_Cybernetics_Core 1 4557
Protoss_Citadel_of_Adun 1 5569
Protoss_Robotics_Facility 1 6217
Protoss_Templar_Archives 1 6657
Protoss_Shuttle 2 10463
Protoss_Dark_Templar 2 7574
Protoss_Forge 1 7664
Protoss_Photon_Cannon 1 8736
Protoss_High_Templar 1 10126
10463
