Protoss_Gateway 3 10667
Protoss_Assimilator 1 3004
Protoss_Cybernetics_Core 1 3840
Protoss_Zealot 4 6515
Protoss_Dragoon 9 10708
Protoss_Robotics_Facility 1 8267
Protoss_Observatory 1 9091
Protoss_Observer 2 10468
10708
