Protoss_Gateway 4 10539
Protoss_Assimilator 2 9825
Protoss_Zealot 2 4364
Protoss_Cybernetics_Core 1 4411
Protoss_Robotics_Facility 1 5805
Protoss_Dragoon 10 10596
Protoss_Observatory 1 6440
Protoss_Observer 4 9297
Protoss_Nexus 1 9509
10596
