Protoss_Gateway 1 2765
Protoss_Assimilator 2 7747
Protoss_Zealot 3 8240
Protoss_Cybernetics_Core 1 4373
Protoss_Robotics_Facility 1 5739
Protoss_Dragoon 2 8206
Protoss_Observatory 1 6368
Protoss_Shuttle 1 6937
Protoss_Observer 2 7648
Protoss_Stargate 2 9406
Protoss_Nexus 1 8536
Protoss_Robotics_Support_Bay 1 7719
Protoss_Fleet_Beacon 1 8874
Protoss_Carrier 2 11997
Protoss_Forge 1 10200
11997
