Protoss_Gateway 2 3690
Protoss_Zealot 14 9808
Protoss_Assimilator 1 6244
Protoss_Cybernetics_Core 1 7441
Protoss_Dragoon 2 10328
Protoss_Robotics_Facility 1 9680
Protoss_Shuttle 1 10743
10743
