Protoss_Forge 1 2781
Protoss_Nexus 1 5220
Protoss_Gateway 5 9810
Protoss_Photon_Cannon 2 5990
Protoss_Assimilator 2 8453
Protoss_Zealot 11 10575
Protoss_Cybernetics_Core 1 7217
Protoss_Citadel_of_Adun 1 8319
Protoss_Stargate 1 8810
Protoss_Corsair 1 9503
Protoss_Templar_Archives 1 10163
10575
