Protoss_Forge 1 2663
Protoss_Photon_Cannon 6 10155
Protoss_Nexus 1 5805
Protoss_Gateway 1 5374
Protoss_Assimilator 2 7384
Protoss_Cybernetics_Core 1 6850
Protoss_Zealot 2 7828
Protoss_Robotics_Facility 1 8270
Protoss_Stargate 1 8698
Protoss_Robotics_Support_Bay 1 8841
Protoss_Corsair 2 10208
Protoss_Reaver 2 11028
11028
