Protoss_Forge 1 3182
Protoss_Photon_Cannon 7 10388
Protoss_Nexus 2 10589
Protoss_Gateway 2 8579
Protoss_Zealot 3 7634
Protoss_Assimilator 2 8620
Protoss_Cybernetics_Core 1 7705
Protoss_Dragoon 1 8568
Protoss_Stargate 1 9266
Protoss_Corsair 1 10010
Protoss_Citadel_of_Adun 1 10815
10815
