Protoss_Forge 1 3276
Protoss_Photon_Cannon 3 9395
Protoss_Nexus 2 7625
Protoss_Gateway 1 6134
Protoss_Assimilator 2 7711
Protoss_Cybernetics_Core 1 7721
Protoss_Zealot 4 10213
Protoss_Stargate 1 9086
Protoss_Robotics_Facility 1 9735
Protoss_Corsair 2 10498
Protoss_Robotics_Support_Bay 1 10316
10498
