Protoss_Gateway 2 3537
Protoss_Zealot 9 6413
Protoss_Forge 1 6701
Protoss_Photon_Cannon 6 10420
Protoss_Nexus 1 9033
Protoss_Assimilator 2 10059
Protoss_Cybernetics_Core 1 8591
Protoss_Stargate 1 9994
10420
