Protoss_Nexus 1 4918
Protoss_Forge 1 3998
Protoss_Gateway 4 8165
Protoss_Assimilator 2 9963
Protoss_Photon_Cannon 2 10537
Protoss_Cybernetics_Core 1 6108
Protoss_Zealot 14 10292
Protoss_Citadel_of_Adun 1 7329
Protoss_Templar_Archives 1 10139
10537
