Protoss_Nexus 1 4489
Protoss_Forge 1 4375
Protoss_Gateway 4 10676
Protoss_Assimilator 2 7313
Protoss_Photon_Cannon 5 9588
Protoss_Cybernetics_Core 1 6593
Protoss_Zealot 3 9402
Protoss_Dragoon 2 8188
Protoss_Stargate 1 7972
Protoss_Citadel_of_Adun 1 8781
Protoss_Corsair 2 9254
Protoss_Templar_Archives 1 10345
10676
