Protoss_Gateway 3 7482
Protoss_Zealot 11 10495
Protoss_Assimilator 1 4565
Protoss_Cybernetics_Core 1 5769
Protoss_Citadel_of_Adun 1 6822
Protoss_Dragoon 1 6728
Protoss_Templar_Archives 1 8227
Protoss_Dark_Templar 2 9893
Protoss_High_Templar 2 10383
10495
