Protoss_Forge 1 2573
Protoss_Photon_Cannon 4 10155
Protoss_Nexus 1 6275
Protoss_Gateway 5 10866
Protoss_Assimilator 2 8700
Protoss_Cybernetics_Core 1 6877
Protoss_Zealot 8 10363
Protoss_Citadel_of_Adun 1 8126
Protoss_Dragoon 1 8125
Protoss_Templar_Archives 1 9832
Protoss_High_Templar 2 10678
10866
