Protoss_Gateway 1 2804
Protoss_Assimilator 1 2830
Protoss_Cybernetics_Core 1 3879
Protoss_Stargate 1 5071
Protoss_Dragoon 1 5088
Protoss_Corsair 4 8733
Protoss_Robotics_Facility 1 6802
Protoss_Forge 1 6914
Protoss_Shuttle 1 7807
Protoss_Photon_Cannon 3 9775
Protoss_Robotics_Support_Bay 1 8145
Protoss_Zealot 1 9508
Protoss_Reaver 1 9976
9976
