Protoss_Forge 1 3002
Protoss_Nexus 1 5070
Protoss_Photon_Cannon 4 10425
Protoss_Gateway 3 9097
Protoss_Assimilator 2 6758
Protoss_Cybernetics_Core 1 6779
Protoss_Zealot 3 8626
Protoss_Stargate 1 7968
Protoss_Citadel_of_Adun 1 8219
Protoss_Corsair 3 10184
Protoss_Templar_Archives 1 9291
Protoss_Dark_Templar 2 10448
10448
