Protoss_Forge 1 2755
Protoss_Photon_Cannon 2 4620
Protoss_Nexus 1 5350
Protoss_Gateway 5 10366
Protoss_Assimilator 1 5862
Protoss_Zealot 10 10368
Protoss_Cybernetics_Core 1 6859
Protoss_Citadel_of_Adun 1 8264
10368
