Protoss_Gateway 3 7201
Protoss_Assimilator 1 3020
Protoss_Zealot 11 9728
Protoss_Cybernetics_Core 1 4669
Protoss_Dragoon 1 5748
Protoss_Citadel_of_Adun 1 6597
Protoss_Templar_Archives 1 7898
Protoss_Forge 1 8914
Protoss_High_Templar 4 9974
Protoss_Archon 1 9607
Protoss_Photon_Cannon 1 10100
Protoss_Nexus 1 11564
11564
