Protoss_Forge 1 2627
Protoss_Nexus 1 5360
Protoss_Photon_Cannon 6 9965
Protoss_Gateway 3 10534
Protoss_Assimilator 2 8281
Protoss_Zealot 4 8873
Protoss_Cybernetics_Core 1 7939
Protoss_Stargate 1 9166
Protoss_Citadel_of_Adun 1 9639
Protoss_Corsair 2 10455
Protoss_Templar_Archives 1 10809
10809
