Protoss_Forge 1 2690
Protoss_Nexus 1 5173
Protoss_Gateway 5 10529
Protoss_Photon_Cannon 2 6021
Protoss_Assimilator 2 10428
Protoss_Zealot 10 10323
Protoss_Cybernetics_Core 1 6767
Protoss_Citadel_of_Adun 1 7931
Protoss_Templar_Archives 1 9927
10529
