Protoss_Forge 1 2744
Protoss_Photon_Cannon 3 10664
Protoss_Nexus 1 5389
Protoss_Gateway 3 9911
Protoss_Assimilator 2 6530
Protoss_Zealot 5 10150
Protoss_Cybernetics_Core 1 7703
Protoss_Citadel_of_Adun 1 8712
Protoss_Templar_Archives 1 10571
10664
