Protoss_Gateway 2 3171
Protoss_Zealot 13 7446
Protoss_Nexus 1 9325
Protoss_Assimilator 1 8599
Protoss_Forge 1 8874
Protoss_Cybernetics_Core 1 9643
Protoss_Photon_Cannon 2 10309
Protoss_Stargate 1 10870
10870
