Protoss_Nexus 1 4555
Protoss_Gateway 4 8667
Protoss_Forge 1 4422
Protoss_Photon_Cannon 2 5324
Protoss_Zealot 14 10592
Protoss_Assimilator 2 6373
Protoss_Cybernetics_Core 1 7190
Protoss_Citadel_of_Adun 1 8409
Protoss_Templar_Archives 1 10275
10592
