Protoss_Forge 1 2914
Protoss_Photon_Cannon 6 7081
Protoss_Nexus 1 6560
Protoss_Gateway 2 10164
Protoss_Assimilator 2 8523
Protoss_Zealot 2 9354
Protoss_Cybernetics_Core 1 7619
Protoss_Stargate 1 8773
Protoss_Citadel_of_Adun 1 9083
Protoss_Corsair 2 10056
Protoss_Templar_Archives 1 10120
10164
