Protoss_Forge 1 3110
Protoss_Nexus 1 4895
Protoss_Photon_Cannon 3 5574
Protoss_Gateway 3 10622
Protoss_Assimilator 3 9457
Protoss_Zealot 5 9922
Protoss_Cybernetics_Core 1 9114
Protoss_Citadel_of_Adun 1 10160
10622
