Protoss_Gateway 2 3319
Protoss_Zealot 14 9708
Protoss_Assimilator 1 5744
Protoss_Cybernetics_Core 1 6511
Protoss_Citadel_of_Adun 1 7509
Protoss_Dragoon 1 7513
Protoss_Nexus 1 10180
Protoss_Templar_Archives 1 9489
Protoss_Forge 1 10025
Protoss_High_Templar 2 10508
10508
