Protoss_Gateway 1 2839
Protoss_Assimilator 1 3196
Protoss_Zealot 3 5275
Protoss_Cybernetics_Core 1 4720
Protoss_Stargate 1 5903
Protoss_Robotics_Facility 1 7075
Protoss_Scout 1 7440
Protoss_Dragoon 3 10478
Protoss_Shuttle 1 8167
Protoss_Robotics_Support_Bay 1 8006
Protoss_Reaver 2 10681
10681
