Protoss_Gateway 3 9896
Protoss_Assimilator 1 2896
Protoss_Zealot 5 6328
Protoss_Cybernetics_Core 1 4785
Protoss_Stargate 1 6299
Protoss_Dragoon 7 10730
Protoss_Corsair 1 7176
10730
