Protoss_Forge 1 2589
Protoss_Photon_Cannon 3 10620
Protoss_Nexus 1 5988
Protoss_Gateway 3 9472
Protoss_Assimilator 2 7309
Protoss_Cybernetics_Core 1 6441
Protoss_Zealot 8 10202
Protoss_Stargate 1 8010
Protoss_Citadel_of_Adun 1 8698
Protoss_Corsair 1 8854
Protoss_Templar_Archives 1 10301
10620
