Protoss_Forge 1 2778
Protoss_Gateway 2 10781
Protoss_Photon_Cannon 2 10367
Protoss_Zealot 6 9768
Protoss_Nexus 1 6460
Protoss_Assimilator 2 6462
Protoss_Cybernetics_Core 1 6353
Protoss_Stargate 1 7810
Protoss_Citadel_of_Adun 1 7907
Protoss_Corsair 4 10392
Protoss_Templar_Archives 1 9805
Protoss_Dark_Templar 1 10656
10781
