Protoss_Forge 1 2614
Protoss_Photon_Cannon 3 6009
Protoss_Nexus 1 6381
Protoss_Gateway 3 8976
Protoss_Zealot 11 10574
Protoss_Cybernetics_Core 1 6795
Protoss_Assimilator 2 8798
Protoss_Citadel_of_Adun 1 8200
Protoss_Templar_Archives 1 10659
10659
