Protoss_Nexus 1 4708
Protoss_Gateway 1 4177
Protoss_Forge 1 4572
Protoss_Zealot 3 8462
Protoss_Photon_Cannon 6 10240
Protoss_Assimilator 2 7427
Protoss_Cybernetics_Core 1 6991
Protoss_Stargate 1 8158
Protoss_Citadel_of_Adun 1 8532
Protoss_Corsair 3 10224
Protoss_Templar_Archives 1 9599
Protoss_Dark_Templar 1 10500
10500
