Protoss_Nexus 1 4630
Protoss_Gateway 4 10170
Protoss_Forge 1 4395
Protoss_Assimilator 2 6478
Protoss_Photon_Cannon 3 10335
Protoss_Zealot 8 10430
Protoss_Cybernetics_Core 1 6669
Protoss_Stargate 1 7820
Protoss_Citadel_of_Adun 1 7753
Protoss_Templar_Archives 1 8757
Protoss_Corsair 1 8582
Protoss_Robotics_Facility 1 10041
Protoss_Dark_Templar 2 9764
10430
