Protoss_Forge 1 3112
Protoss_Photon_Cannon 6 8476
Protoss_Nexus 1 5555
Protoss_Gateway 1 5620
Protoss_Assimilator 1 5501
Protoss_Zealot 2 6920
Protoss_Cybernetics_Core 1 6854
Protoss_Dragoon 2 9483
Protoss_Stargate 1 10688
10688
