Protoss_Gateway 4 7450
Protoss_Assimilator 1 3136
Protoss_Zealot 3 5123
Protoss_Cybernetics_Core 1 5130
Protoss_Dragoon 9 9978
Protoss_Robotics_Facility 1 9876
Protoss_Forge 1 10212
10212
