Protoss_Forge 1 2604
Protoss_Photon_Cannon 4 10634
Protoss_Nexus 1 5845
Protoss_Gateway 2 10038
Protoss_Assimilator 2 8022
Protoss_Zealot 3 7786
Protoss_Cybernetics_Core 1 7757
Protoss_Dragoon 1 8752
Protoss_Stargate 1 9123
Protoss_Citadel_of_Adun 1 9293
Protoss_Corsair 2 10410
Protoss_Templar_Archives 1 10407
10634
