Protoss_Forge 1 3333
Protoss_Photon_Cannon 4 9337
Protoss_Nexus 1 5827
Protoss_Gateway 1 5213
Protoss_Assimilator 2 8003
Protoss_Cybernetics_Core 1 6409
Protoss_Zealot 3 8448
Protoss_Stargate 1 7579
Protoss_Robotics_Facility 1 8699
Protoss_Corsair 3 10043
Protoss_Robotics_Support_Bay 1 9688
Protoss_Reaver 1 10830
10830
