Protoss_Gateway 2 10525
Protoss_Zealot 12 10492
Protoss_Forge 1 3868
Protoss_Nexus 1 6965
Protoss_Photon_Cannon 2 10084
Protoss_Assimilator 2 7947
Protoss_Cybernetics_Core 1 7328
Protoss_Stargate 1 8900
Protoss_Citadel_of_Adun 1 9208
Protoss_Corsair 1 9614
10525
