Protoss_Forge 1 2646
Protoss_Nexus 1 5197
Protoss_Gateway 4 10533
Protoss_Photon_Cannon 4 10120
Protoss_Assimilator 2 7368
Protoss_Cybernetics_Core 1 6176
Protoss_Zealot 2 7820
Protoss_Stargate 1 7366
Protoss_Citadel_of_Adun 1 7916
Protoss_Corsair 4 10562
Protoss_Templar_Archives 1 9031
Protoss_High_Templar 1 10002
10562
