Protoss_Forge 1 2530
Protoss_Photon_Cannon 2 4033
Protoss_Nexus 1 6025
Protoss_Gateway 3 9819
Protoss_Assimilator 2 7250
Protoss_Cybernetics_Core 1 6820
Protoss_Zealot 4 9813
Protoss_Stargate 1 8564
Protoss_Citadel_of_Adun 1 9195
Protoss_Corsair 2 10483
Protoss_Templar_Archives 1 10259
10483
