Protoss_Nexus 1 4619
Protoss_Forge 1 3738
Protoss_Photon_Cannon 3 7176
Protoss_Gateway 1 5471
Protoss_Assimilator 2 6882
Protoss_Cybernetics_Core 1 6473
Protoss_Zealot 3 9838
Protoss_Stargate 1 7694
Protoss_Dragoon 1 7586
Protoss_Robotics_Facility 1 8762
Protoss_Corsair 4 10182
Protoss_Shuttle 1 9757
Protoss_Robotics_Support_Bay 1 9564
Protoss_Reaver 1 10808
10808
