Protoss_Forge 1 3186
Protoss_Nexus 1 4946
Protoss_Photon_Cannon 6 10338
Protoss_Gateway 5 9874
Protoss_Assimilator 2 7989
Protoss_Cybernetics_Core 1 6246
Protoss_Zealot 5 9792
Protoss_Stargate 1 7392
Protoss_Corsair 1 8080
Protoss_Robotics_Facility 1 8977
Protoss_Robotics_Support_Bay 1 9589
Protoss_Reaver 1 10770
Protoss_Dragoon 1 10642
10770
