Protoss_Forge 1 2511
Protoss_Photon_Cannon 5 10268
Protoss_Nexus 1 6209
Protoss_Gateway 1 5691
Protoss_Assimilator 2 7857
Protoss_Zealot 6 10268
Protoss_Cybernetics_Core 1 7167
Protoss_Stargate 1 8398
Protoss_Citadel_of_Adun 1 8454
Protoss_Corsair 1 9082
Protoss_Templar_Archives 1 9939
10268
