Protoss_Nexus 1 4655
Protoss_Gateway 1 4611
Protoss_Assimilator 1 4965
Protoss_Forge 1 5309
Protoss_Zealot 3 7565
Protoss_Photon_Cannon 4 7260
Protoss_Cybernetics_Core 1 8009
8009
