Protoss_Forge 1 3339
Protoss_Nexus 1 4983
Protoss_Photon_Cannon 2 5231
Protoss_Gateway 4 10032
Protoss_Assimilator 2 7073
Protoss_Cybernetics_Core 1 6867
Protoss_Zealot 4 10596
Protoss_Stargate 1 8039
Protoss_Citadel_of_Adun 1 8053
Protoss_Dragoon 1 8690
Protoss_Corsair 2 10006
Protoss_Templar_Archives 1 9284
Protoss_High_Templar 2 10742
10742
