Protoss_Forge 1 2836
Protoss_Nexus 1 5027
Protoss_Photon_Cannon 6 10542
Protoss_Gateway 6 10203
Protoss_Zealot 4 8706
Protoss_Assimilator 2 7383
Protoss_Cybernetics_Core 1 7484
Protoss_Citadel_of_Adun 1 8624
Protoss_Templar_Archives 1 9614
Protoss_High_Templar 4 10616
10616
