Protoss_Forge 1 3482
Protoss_Photon_Cannon 3 6352
Protoss_Nexus 1 6515
Protoss_Gateway 4 10139
Protoss_Assimilator 2 10548
Protoss_Cybernetics_Core 1 6975
Protoss_Zealot 7 10174
Protoss_Stargate 1 8226
Protoss_Citadel_of_Adun 1 8408
Protoss_Corsair 1 8906
Protoss_Templar_Archives 1 10760
10760
