Protoss_Forge 1 3083
Protoss_Photon_Cannon 4 10275
Protoss_Nexus 1 5461
Protoss_Gateway 4 10850
Protoss_Assimilator 2 7935
Protoss_Zealot 6 9396
Protoss_Cybernetics_Core 1 7654
Protoss_Stargate 1 8917
Protoss_Citadel_of_Adun 1 8999
Protoss_Corsair 2 10576
Protoss_Templar_Archives 1 10291
10850
