Protoss_Gateway 3 10866
Protoss_Assimilator 1 2815
Protoss_Cybernetics_Core 1 3771
Protoss_Zealot 7 8148
Protoss_Stargate 1 5060
Protoss_Corsair 1 5844
Protoss_Citadel_of_Adun 1 8008
Protoss_Forge 1 8488
Protoss_Templar_Archives 1 9014
Protoss_Photon_Cannon 1 9474
10866
