Protoss_Forge 1 3104
Protoss_Photon_Cannon 4 8862
Protoss_Nexus 1 5749
Protoss_Gateway 3 10409
Protoss_Assimilator 2 6875
Protoss_Cybernetics_Core 1 6539
Protoss_Zealot 6 10284
Protoss_Citadel_of_Adun 1 8239
Protoss_Templar_Archives 1 9368
10409
