Protoss_Forge 1 2845
Protoss_Photon_Cannon 5 10239
Protoss_Nexus 1 5753
Protoss_Gateway 3 10128
Protoss_Assimilator 2 8658
Protoss_Cybernetics_Core 1 6174
Protoss_Zealot 4 9456
Protoss_Stargate 1 7588
Protoss_Citadel_of_Adun 1 8147
Protoss_Corsair 3 9982
Protoss_Templar_Archives 1 9273
Protoss_High_Templar 2 10556
10556
