Protoss_Forge 1 2768
Protoss_Nexus 1 4953
Protoss_Photon_Cannon 2 4556
Protoss_Gateway 6 10893
Protoss_Assimilator 2 6983
Protoss_Cybernetics_Core 1 6385
Protoss_Zealot 3 9822
Protoss_Stargate 1 7640
Protoss_Citadel_of_Adun 1 7847
Protoss_Dragoon 1 7970
Protoss_Corsair 2 9024
Protoss_Templar_Archives 1 9115
Protoss_High_Templar 2 10038
10893
