Protoss_Forge 1 2894
Protoss_Photon_Cannon 6 7936
Protoss_Nexus 1 5657
Protoss_Gateway 2 8737
Protoss_Assimilator 2 8934
Protoss_Zealot 7 10550
Protoss_Cybernetics_Core 1 8662
Protoss_Stargate 1 9946
Protoss_Citadel_of_Adun 1 10721
10721
