Protoss_Forge 1 2632
Protoss_Photon_Cannon 3 9000
Protoss_Nexus 1 5965
Protoss_Gateway 4 9597
Protoss_Assimilator 2 6658
Protoss_Cybernetics_Core 1 6499
Protoss_Zealot 3 8624
Protoss_Dragoon 2 10624
Protoss_Citadel_of_Adun 1 7811
Protoss_Templar_Archives 1 8799
Protoss_Dark_Templar 2 10598
Protoss_High_Templar 2 10682
10682
