Protoss_Gateway 1 2788
Protoss_Zealot 7 9882
Protoss_Nexus 1 5933
Protoss_Assimilator 1 5195
Protoss_Cybernetics_Core 1 6121
Protoss_Forge 1 6038
Protoss_Stargate 1 7262
Protoss_Dragoon 1 7212
Protoss_Photon_Cannon 2 9988
Protoss_Corsair 2 10138
10138
