Protoss_Gateway 3 9590
Protoss_Zealot 9 9454
Protoss_Assimilator 2 4736
Protoss_Cybernetics_Core 1 5845
Protoss_Stargate 1 7150
Protoss_Citadel_of_Adun 1 7568
Protoss_Corsair 1 8362
Protoss_Templar_Archives 1 9016
Protoss_Forge 1 9018
Protoss_Dark_Templar 2 10506
10506
