Protoss_Forge 1 3253
Protoss_Nexus 1 5175
Protoss_Photon_Cannon 6 10635
Protoss_Gateway 1 5155
Protoss_Zealot 4 8834
Protoss_Assimilator 2 10008
Protoss_Cybernetics_Core 1 7576
Protoss_Stargate 1 8804
Protoss_Dragoon 1 9586
Protoss_Corsair 2 10216
Protoss_Robotics_Facility 1 10568
10635
