Protoss_Nexus 1 4617
Protoss_Forge 1 3846
Protoss_Gateway 2 10298
Protoss_Photon_Cannon 7 9960
Protoss_Assimilator 2 7184
Protoss_Zealot 4 8814
Protoss_Cybernetics_Core 1 6303
Protoss_Stargate 1 7615
Protoss_Citadel_of_Adun 1 8049
Protoss_Dragoon 1 8212
Protoss_Corsair 4 10256
Protoss_Templar_Archives 1 9469
Protoss_High_Templar 1 10572
Protoss_Dark_Templar 1 10700
10700
