Protoss_Forge 1 3062
Protoss_Photon_Cannon 4 10090
Protoss_Nexus 1 5841
Protoss_Gateway 3 9272
Protoss_Assimilator 2 7935
Protoss_Cybernetics_Core 1 6229
Protoss_Zealot 7 10552
Protoss_Citadel_of_Adun 1 7287
Protoss_Dragoon 1 7492
Protoss_Templar_Archives 1 8919
Protoss_High_Templar 2 9796
Protoss_Dark_Templar 1 10120
Protoss_Robotics_Facility 1 10917
10917
