Protoss_Forge 1 2726
Protoss_Photon_Cannon 4 10696
Protoss_Nexus 1 5695
Protoss_Gateway 4 9136
Protoss_Assimilator 2 7907
Protoss_Zealot 7 9606
Protoss_Cybernetics_Core 1 6526
Protoss_Dragoon 1 7542
Protoss_Citadel_of_Adun 1 8002
Protoss_Templar_Archives 1 9494
Protoss_High_Templar 1 10324
10696
