Protoss_Forge 1 2770
Protoss_Photon_Cannon 4 10475
Protoss_Nexus 1 5923
Protoss_Gateway 3 10890
Protoss_Assimilator 2 7928
Protoss_Zealot 7 10266
Protoss_Cybernetics_Core 1 7438
Protoss_Stargate 1 8838
Protoss_Citadel_of_Adun 1 9205
Protoss_Corsair 2 10412
10890
