Protoss_Forge 1 2498
Protoss_Photon_Cannon 4 10504
Protoss_Nexus 1 6109
Protoss_Gateway 2 9370
Protoss_Assimilator 2 7662
Protoss_Cybernetics_Core 1 6608
Protoss_Zealot 4 9318
Protoss_Dragoon 1 7512
Protoss_Stargate 1 7913
Protoss_Citadel_of_Adun 1 8502
Protoss_Corsair 2 10368
Protoss_Templar_Archives 1 9853
10504
