Protoss_Forge 1 2636
Protoss_Photon_Cannon 5 10458
Protoss_Nexus 1 5598
Protoss_Gateway 1 4911
Protoss_Zealot 3 7820
Protoss_Assimilator 2 7520
Protoss_Cybernetics_Core 1 7292
Protoss_Stargate 2 10266
Protoss_Robotics_Facility 1 9585
Protoss_Corsair 2 10072
10458
