Protoss_Forge 1 3096
Protoss_Photon_Cannon 6 10692
Protoss_Nexus 1 6107
Protoss_Gateway 4 10147
Protoss_Assimilator 2 7500
Protoss_Zealot 5 10246
Protoss_Cybernetics_Core 1 7491
Protoss_Citadel_of_Adun 1 8539
Protoss_Dragoon 1 8622
Protoss_Templar_Archives 1 9645
10692
