Protoss_Gateway 2 9086
Protoss_Zealot 12 10533
Protoss_Forge 1 3488
Protoss_Photon_Cannon 3 4854
Protoss_Assimilator 1 4954
Protoss_Cybernetics_Core 1 7606
Protoss_Dragoon 1 8448
Protoss_Citadel_of_Adun 1 8684
Protoss_Ground_Weapons_1 1 9896
10533
