Protoss_Forge 1 2987
Protoss_Nexus 1 5067
Protoss_Photon_Cannon 4 10480
Protoss_Gateway 3 10081
Protoss_Assimilator 2 8505
Protoss_Zealot 4 9942
Protoss_Cybernetics_Core 1 7260
Protoss_Stargate 1 8451
Protoss_Dragoon 1 8332
Protoss_Citadel_of_Adun 1 8744
Protoss_Corsair 1 9132
Protoss_Templar_Archives 1 9848
Protoss_Dark_Templar 1 10694
Protoss_High_Templar 1 10694
10694
