Protoss_Gateway 2 3506
Protoss_Zealot 10 8332
Protoss_Assimilator 1 5256
Protoss_Cybernetics_Core 1 6475
Protoss_Citadel_of_Adun 1 7764
Protoss_Stargate 1 8291
Protoss_Dragoon 1 8070
Protoss_Templar_Archives 1 9017
Protoss_Corsair 1 8982
Protoss_Forge 1 9239
Protoss_Nexus 1 11137
Protoss_Dark_Templar 2 10610
11137
