Protoss_Forge 1 2819
Protoss_Photon_Cannon 4 10534
Protoss_Nexus 1 5799
Protoss_Gateway 2 9671
Protoss_Assimilator 2 7834
Protoss_Zealot 6 10558
Protoss_Cybernetics_Core 1 6506
Protoss_Stargate 1 7943
Protoss_Citadel_of_Adun 1 7993
Protoss_Corsair 2 9612
Protoss_Templar_Archives 1 10473
10558
