Protoss_Gateway 2 6435
Protoss_Assimilator 1 3100
Protoss_Zealot 10 10072
Protoss_Cybernetics_Core 1 4325
Protoss_Dragoon 1 5222
Protoss_Citadel_of_Adun 1 5727
Protoss_Templar_Archives 1 7541
Protoss_High_Templar 4 9470
Protoss_Nexus 1 10307
Protoss_Forge 1 9250
Protoss_Archon 2 9833
Protoss_Photon_Cannon 2 10593
10593
