Protoss_Forge 1 2923
Protoss_Photon_Cannon 4 9196
Protoss_Nexus 1 5927
Protoss_Gateway 3 10890
Protoss_Assimilator 2 7209
Protoss_Zealot 5 10050
Protoss_Cybernetics_Core 1 6957
Protoss_Stargate 1 8119
Protoss_Dragoon 1 8042
Protoss_Corsair 2 9642
Protoss_Citadel_of_Adun 1 9450
Protoss_Templar_Archives 1 10528
10890
