Protoss_Forge 1 3113
Protoss_Nexus 1 5023
Protoss_Photon_Cannon 5 10642
Protoss_Gateway 3 8062
Protoss_Assimilator 2 6982
Protoss_Zealot 11 10122
Protoss_Cybernetics_Core 1 6435
Protoss_Dragoon 2 8910
Protoss_Citadel_of_Adun 1 7631
Protoss_Templar_Archives 1 9704
10642
