Protoss_Forge 1 2590
Protoss_Nexus 1 5317
Protoss_Gateway 5 9776
Protoss_Photon_Cannon 2 5156
Protoss_Assimilator 2 7581
Protoss_Cybernetics_Core 1 6307
Protoss_Zealot 9 10414
Protoss_Citadel_of_Adun 1 8252
Protoss_Stargate 1 8450
Protoss_Corsair 2 10448
Protoss_Templar_Archives 1 10039
10448
