Protoss_Gateway 2 7481
Protoss_Assimilator 1 2953
Protoss_Zealot 9 10564
Protoss_Cybernetics_Core 1 4506
Protoss_Dragoon 1 5352
Protoss_Stargate 1 5819
Protoss_Citadel_of_Adun 1 6131
Protoss_Corsair 3 8136
Protoss_Templar_Archives 1 7623
Protoss_Dark_Templar 1 8518
Protoss_Forge 1 9232
10564
