Protoss_Forge 1 2680
Protoss_Photon_Cannon 6 10713
Protoss_Nexus 1 6365
Protoss_Gateway 3 9404
Protoss_Assimilator 2 7194
Protoss_Cybernetics_Core 1 7614
Protoss_Zealot 3 9496
Protoss_Citadel_of_Adun 1 8672
Protoss_Dragoon 1 8836
Protoss_Templar_Archives 1 9713
Protoss_High_Templar 2 10620
Protoss_Dark_Templar 1 10630
10713
