Protoss_Forge 1 2494
Protoss_Photon_Cannon 6 9293
Protoss_Nexus 1 6212
Protoss_Gateway 1 5545
Protoss_Assimilator 2 7805
Protoss_Cybernetics_Core 1 6571
Protoss_Zealot 3 8412
Protoss_Stargate 1 7846
Protoss_Robotics_Facility 1 8925
Protoss_Corsair 3 9980
Protoss_Shuttle 1 9981
Protoss_Robotics_Support_Bay 1 9699
9981
