Protoss_Forge 1 3491
Protoss_Nexus 1 5310
Protoss_Photon_Cannon 8 10644
Protoss_Gateway 3 10309
Protoss_Assimilator 2 7600
Protoss_Cybernetics_Core 1 7047
Protoss_Zealot 5 9790
Protoss_Stargate 1 8246
Protoss_Citadel_of_Adun 1 9024
Protoss_Corsair 3 10284
Protoss_Templar_Archives 1 10022
10644
