Protoss_Gateway 2 6312
Protoss_Zealot 5 7470
Protoss_Assimilator 1 3672
Protoss_Cybernetics_Core 1 4715
Protoss_Dragoon 1 5558
Protoss_Citadel_of_Adun 1 5985
Protoss_Templar_Archives 1 7171
Protoss_Nexus 1 8967
Protoss_High_Templar 4 9824
Protoss_Forge 1 8334
Protoss_Archon 1 8576
Protoss_Photon_Cannon 6 10666
10666
