Protoss_Gateway 2 9394
Protoss_Assimilator 1 2947
Protoss_Zealot 7 10118
Protoss_Cybernetics_Core 1 4613
Protoss_Stargate 1 5784
Protoss_Dragoon 1 5724
Protoss_Citadel_of_Adun 1 6235
Protoss_Corsair 1 6492
Protoss_Templar_Archives 1 7383
Protoss_Forge 1 7728
Protoss_Dark_Templar 2 8986
Protoss_Photon_Cannon 3 10641
Protoss_Nexus 1 11610
11610
