Protoss_Forge 1 3641
Protoss_Nexus 1 5409
Protoss_Photon_Cannon 6 8488
Protoss_Gateway 4 10064
Protoss_Assimilator 2 7130
Protoss_Cybernetics_Core 1 7228
Protoss_Stargate 1 8948
Protoss_Corsair 2 10328
Protoss_Citadel_of_Adun 1 10028
Protoss_Dragoon 2 10278
10328
