Protoss_Forge 1 2762
Protoss_Photon_Cannon 6 10307
Protoss_Nexus 1 5559
Protoss_Gateway 4 10806
Protoss_Assimilator 2 7902
Protoss_Cybernetics_Core 1 6714
Protoss_Zealot 4 9898
Protoss_Stargate 1 7858
Protoss_Citadel_of_Adun 1 8029
Protoss_Corsair 1 8562
Protoss_Templar_Archives 1 10210
10806
