Protoss_Forge 1 2661
Protoss_Nexus 1 4973
Protoss_Photon_Cannon 4 9533
Protoss_Gateway 2 10126
Protoss_Assimilator 2 9220
Protoss_Zealot 5 10464
Protoss_Cybernetics_Core 1 7186
Protoss_Stargate 1 8328
Protoss_Citadel_of_Adun 1 8379
Protoss_Dragoon 1 8680
Protoss_Corsair 1 9172
Protoss_Templar_Archives 1 9960
10464
