Protoss_Forge 2 3811
Protoss_Nexus 1 4742
Protoss_Photon_Cannon 7 9878
Protoss_Gateway 2 9837
Protoss_Assimilator 2 7485
Protoss_Zealot 5 9968
Protoss_Cybernetics_Core 1 6941
Protoss_Stargate 1 8263
Protoss_Citadel_of_Adun 1 9085
Protoss_Corsair 1 8958
Protoss_Templar_Archives 1 10463
10463
