Protoss_Forge 1 2860
Protoss_Photon_Cannon 2 5812
Protoss_Nexus 1 5935
Protoss_Gateway 4 8181
Protoss_Assimilator 1 5573
Protoss_Zealot 13 10292
Protoss_Cybernetics_Core 1 7353
Protoss_Citadel_of_Adun 1 9452
10292
