Protoss_Forge 1 3163
Protoss_Nexus 1 5058
Protoss_Photon_Cannon 3 9440
Protoss_Gateway 4 10184
Protoss_Assimilator 2 6886
Protoss_Cybernetics_Core 1 6109
Protoss_Zealot 7 9662
Protoss_Stargate 1 7498
Protoss_Citadel_of_Adun 1 8096
Protoss_Corsair 2 9438
Protoss_Templar_Archives 1 9213
10184
