Protoss_Forge 1 2972
Protoss_Nexus 1 5011
Protoss_Photon_Cannon 2 4528
Protoss_Assimilator 2 6705
Protoss_Gateway 2 9663
Protoss_Zealot 5 9210
Protoss_Cybernetics_Core 1 6279
Protoss_Dragoon 1 7110
Protoss_Stargate 1 7604
Protoss_Citadel_of_Adun 1 8540
Protoss_Corsair 4 10260
Protoss_Templar_Archives 1 9650
Protoss_Dark_Templar 2 10526
10526
