Protoss_Forge 1 3070
Protoss_Photon_Cannon 4 10528
Protoss_Nexus 1 6069
Protoss_Gateway 3 10363
Protoss_Assimilator 2 8202
Protoss_Zealot 1 7226
Protoss_Cybernetics_Core 1 7901
Protoss_Stargate 1 9038
Protoss_Citadel_of_Adun 1 9396
Protoss_Corsair 2 10450
Protoss_Templar_Archives 1 10565
10565
