Protoss_Gateway 2 3363
Protoss_Zealot 12 8334
Protoss_Nexus 1 8797
Protoss_Assimilator 1 8145
Protoss_Cybernetics_Core 1 9229
Protoss_Stargate 1 10393
Protoss_Forge 1 10141
10393
