Protoss_Nexus 1 4903
Protoss_Forge 1 4125
Protoss_Gateway 3 10603
Protoss_Photon_Cannon 4 9834
Protoss_Assimilator 2 6588
Protoss_Cybernetics_Core 1 6534
Protoss_Zealot 5 9346
Protoss_Stargate 1 7733
Protoss_Citadel_of_Adun 1 7935
Protoss_Templar_Archives 1 9083
Protoss_Corsair 2 9482
10603
