Protoss_Forge 1 2775
Protoss_Photon_Cannon 3 9879
Protoss_Nexus 1 5860
Protoss_Gateway 1 5263
Protoss_Assimilator 2 7137
Protoss_Cybernetics_Core 1 6259
Protoss_Zealot 1 6044
Protoss_Stargate 1 7398
Protoss_Dragoon 2 9288
Protoss_Robotics_Facility 1 8615
Protoss_Corsair 4 10474
Protoss_Shuttle 1 9667
Protoss_Robotics_Support_Bay 1 9422
Protoss_Reaver 1 10718
10718
