Protoss_Forge 1 2502
Protoss_Photon_Cannon 6 9890
Protoss_Nexus 1 5573
Protoss_Gateway 2 10833
Protoss_Zealot 4 7520
Protoss_Assimilator 2 7874
Protoss_Cybernetics_Core 1 7566
Protoss_Stargate 1 8762
Protoss_Citadel_of_Adun 1 9188
Protoss_Corsair 1 9486
Protoss_Templar_Archives 1 10221
10833
