Protoss_Forge 1 2618
Protoss_Photon_Cannon 6 10468
Protoss_Nexus 1 6199
Protoss_Gateway 4 10037
Protoss_Assimilator 2 7483
Protoss_Zealot 3 9212
Protoss_Cybernetics_Core 1 6975
Protoss_Citadel_of_Adun 1 8145
Protoss_Dragoon 1 8576
Protoss_Templar_Archives 1 9375
Protoss_High_Templar 2 10562
10562
