Protoss_Gateway 3 9591
Protoss_Zealot 11 9552
Protoss_Assimilator 1 6113
Protoss_Forge 1 6980
Protoss_Cybernetics_Core 1 8120
Protoss_Photon_Cannon 1 8518
Protoss_Citadel_of_Adun 1 9331
9591
