Protoss_Forge 1 2836
Protoss_Photon_Cannon 3 10599
Protoss_Nexus 1 5765
Protoss_Gateway 1 5451
Protoss_Assimilator 2 6729
Protoss_Cybernetics_Core 1 6441
Protoss_Zealot 6 10228
Protoss_Dragoon 1 7296
Protoss_Stargate 1 7763
Protoss_Robotics_Facility 1 8440
Protoss_Corsair 3 9652
Protoss_Robotics_Support_Bay 1 9031
Protoss_Reaver 1 10352
10599
