Protoss_Forge 1 2921
Protoss_Photon_Cannon 4 9898
Protoss_Nexus 1 5551
Protoss_Gateway 1 4884
Protoss_Assimilator 2 7720
Protoss_Zealot 4 8186
Protoss_Cybernetics_Core 1 6439
Protoss_Stargate 1 7902
Protoss_Corsair 3 10218
Protoss_Robotics_Facility 1 9667
Protoss_Observatory 1 10239
Protoss_Robotics_Support_Bay 1 10398
10398
