Protoss_Gateway 1 2569
Protoss_Zealot 10 10007
Protoss_Assimilator 1 4104
Protoss_Forge 1 5495
Protoss_Cybernetics_Core 1 7129
Protoss_Citadel_of_Adun 1 8139
Protoss_Dragoon 1 9405
Protoss_Photon_Cannon 2 10185
Protoss_Templar_Archives 1 10539
Protoss_Ground_Weapons_1 1 9661
10539
