Protoss_Forge 1 2801
Protoss_Photon_Cannon 2 3920
Protoss_Nexus 1 5932
Protoss_Gateway 1 5561
Protoss_Assimilator 2 8034
Protoss_Zealot 6 10354
Protoss_Cybernetics_Core 1 6723
Protoss_Stargate 1 7948
Protoss_Dragoon 1 7714
Protoss_Citadel_of_Adun 1 8141
Protoss_Corsair 1 8890
Protoss_Templar_Archives 1 10062
10354
