Protoss_Forge 1 2765
Protoss_Nexus 1 5077
Protoss_Gateway 3 9327
Protoss_Photon_Cannon 1 5100
Protoss_Assimilator 2 6715
Protoss_Zealot 5 10424
Protoss_Cybernetics_Core 1 6085
Protoss_Stargate 1 7428
Protoss_Dragoon 1 7328
Protoss_Citadel_of_Adun 1 7926
Protoss_Corsair 2 9104
Protoss_Templar_Archives 1 8953
Protoss_High_Templar 2 9846
10424
