Protoss_Gateway 1 2791
Protoss_Assimilator 1 2990
Protoss_Zealot 5 7064
Protoss_Cybernetics_Core 1 4643
Protoss_Stargate 1 5871
Protoss_Dragoon 1 5860
Protoss_Corsair 3 8286
Protoss_Citadel_of_Adun 1 6898
Protoss_Templar_Archives 1 8010
Protoss_Forge 1 8115
Protoss_Dark_Templar 2 9953
Protoss_Photon_Cannon 2 10325
Protoss_Nexus 1 11118
Protoss_High_Templar 1 10724
11118
