Protoss_Forge 1 2972
Protoss_Photon_Cannon 6 9995
Protoss_Nexus 1 5989
Protoss_Gateway 3 10601
Protoss_Assimilator 2 7842
Protoss_Cybernetics_Core 1 6343
Protoss_Zealot 4 9996
Protoss_Stargate 1 7766
Protoss_Citadel_of_Adun 1 8499
Protoss_Corsair 3 10468
Protoss_Templar_Archives 1 9899
10601
