Protoss_Forge 2 10413
Protoss_Photon_Cannon 5 10448
Protoss_Nexus 1 5797
Protoss_Gateway 2 8551
Protoss_Assimilator 2 7198
Protoss_Cybernetics_Core 1 6181
Protoss_Zealot 5 9328
Protoss_Stargate 1 7328
Protoss_Citadel_of_Adun 1 8061
Protoss_Corsair 3 10190
Protoss_Templar_Archives 1 9969
10448
