Protoss_Forge 1 2815
Protoss_Photon_Cannon 5 9314
Protoss_Nexus 1 5345
Protoss_Gateway 4 8213
Protoss_Assimilator 1 5443
Protoss_Zealot 13 10198
Protoss_Cybernetics_Core 1 6596
Protoss_Dragoon 1 7536
Protoss_Citadel_of_Adun 1 7862
10198
