Protoss_Nexus 1 4672
Protoss_Gateway 3 8286
Protoss_Forge 1 4232
Protoss_Assimilator 2 9202
Protoss_Photon_Cannon 3 9458
Protoss_Cybernetics_Core 1 5493
Protoss_Zealot 10 10196
Protoss_Dragoon 1 6614
Protoss_Stargate 1 6950
Protoss_Citadel_of_Adun 1 7872
Protoss_Corsair 4 10272
Protoss_Templar_Archives 1 10384
10384
