Protoss_Forge 3 4908
Protoss_Nexus 1 4860
Protoss_Gateway 3 9760
Protoss_Assimilator 1 5526
Protoss_Zealot 12 10370
Protoss_Photon_Cannon 2 9876
Protoss_Cybernetics_Core 1 7885
Protoss_Stargate 1 9379
Protoss_Citadel_of_Adun 1 9353
Protoss_Corsair 1 10422
10422
