Protoss_Forge 2 4112
Protoss_Nexus 1 5005
Protoss_Gateway 2 10599
Protoss_Photon_Cannon 2 5278
Protoss_Zealot 5 10126
Protoss_Assimilator 2 8684
Protoss_Cybernetics_Core 1 7943
Protoss_Stargate 1 9332
Protoss_Citadel_of_Adun 1 9901
Protoss_Corsair 1 10022
10599
