Protoss_Gateway 2 10051
Protoss_Assimilator 1 3052
Protoss_Zealot 5 10074
Protoss_Cybernetics_Core 1 4927
Protoss_Dragoon 1 5770
Protoss_Robotics_Facility 1 6487
Protoss_Forge 1 7154
Protoss_Shuttle 1 7489
Protoss_Robotics_Support_Bay 1 7475
Protoss_Citadel_of_Adun 1 8019
Protoss_Reaver 1 8604
Protoss_Templar_Archives 1 9137
Protoss_Photon_Cannon 2 10360
Protoss_High_Templar 1 10262
10360
