Protoss_Gateway 1 2819
Protoss_Assimilator 1 3030
Protoss_Zealot 4 7826
Protoss_Cybernetics_Core 1 4629
Protoss_Dragoon 1 5528
Protoss_Stargate 1 6191
Protoss_Citadel_of_Adun 1 6401
Protoss_Corsair 1 7022
Protoss_Templar_Archives 1 7551
Protoss_Forge 1 8138
Protoss_Dark_Templar 1 8688
Protoss_Photon_Cannon 4 10043
Protoss_High_Templar 2 10192
10192
