Protoss_Forge 1 2716
Protoss_Photon_Cannon 2 4835
Protoss_Nexus 1 5546
Protoss_Gateway 2 8623
Protoss_Assimilator 2 7495
Protoss_Cybernetics_Core 1 6521
Protoss_Zealot 9 10260
Protoss_Stargate 1 7682
Protoss_Citadel_of_Adun 1 8090
Protoss_Corsair 3 10428
Protoss_Templar_Archives 1 9874
10428
