Protoss_Gateway 2 6981
Protoss_Zealot 8 9110
Protoss_Assimilator 1 3747
Protoss_Cybernetics_Core 1 4795
Protoss_Dragoon 1 5702
Protoss_Citadel_of_Adun 1 6187
Protoss_Templar_Archives 1 7228
Protoss_Forge 1 8118
Protoss_High_Templar 3 10600
Protoss_Archon 1 8898
Protoss_Photon_Cannon 3 9586
Protoss_Dark_Templar 2 9862
10600
