Protoss_Forge 1 3067
Protoss_Nexus 1 5038
Protoss_Photon_Cannon 4 10528
Protoss_Gateway 4 10348
Protoss_Assimilator 2 7365
Protoss_Cybernetics_Core 1 6517
Protoss_Zealot 3 8836
Protoss_Dragoon 1 7368
Protoss_Stargate 1 7687
Protoss_Citadel_of_Adun 1 7879
Protoss_Corsair 2 9126
Protoss_Templar_Archives 1 8910
Protoss_Dark_Templar 2 10072
10528
