Protoss_Forge 1 2767
Protoss_Photon_Cannon 4 10725
Protoss_Nexus 1 5883
Protoss_Gateway 3 10591
Protoss_Assimilator 2 7583
Protoss_Zealot 3 9970
Protoss_Cybernetics_Core 1 6411
Protoss_Stargate 1 7661
Protoss_Citadel_of_Adun 1 8265
Protoss_Dragoon 1 8408
Protoss_Corsair 3 9836
Protoss_Templar_Archives 1 10033
10725
