Protoss_Forge 2 4142
Protoss_Nexus 1 4813
Protoss_Gateway 5 10892
Protoss_Photon_Cannon 6 10592
Protoss_Assimilator 2 6654
Protoss_Zealot 8 10564
Protoss_Cybernetics_Core 1 6095
Protoss_Stargate 1 7301
Protoss_Citadel_of_Adun 1 7493
Protoss_Templar_Archives 1 8546
Protoss_Corsair 1 8294
Protoss_High_Templar 4 10656
10892
