Protoss_Forge 1 2552
Protoss_Nexus 1 5105
Protoss_Gateway 3 9361
Protoss_Photon_Cannon 2 5806
Protoss_Assimilator 2 7074
Protoss_Cybernetics_Core 1 5741
Protoss_Zealot 2 8882
Protoss_Stargate 1 7254
Protoss_Citadel_of_Adun 1 7593
Protoss_Dragoon 1 7740
Protoss_Corsair 2 9166
Protoss_Templar_Archives 1 8794
Protoss_Dark_Templar 1 9634
Protoss_High_Templar 1 10200
10200
