Protoss_Forge 1 2866
Protoss_Nexus 1 5031
Protoss_Photon_Cannon 6 10181
Protoss_Gateway 4 10787
Protoss_Assimilator 2 7012
Protoss_Cybernetics_Core 1 6014
Protoss_Zealot 4 9652
Protoss_Stargate 1 7258
Protoss_Dragoon 1 7052
Protoss_Citadel_of_Adun 1 7647
Protoss_Corsair 1 8356
Protoss_Templar_Archives 1 9155
Protoss_Dark_Templar 2 10114
10787
