Protoss_Forge 1 2798
Protoss_Nexus 1 5092
Protoss_Gateway 4 8971
Protoss_Photon_Cannon 2 5408
Protoss_Assimilator 2 7196
Protoss_Zealot 13 10542
Protoss_Cybernetics_Core 1 6775
Protoss_Stargate 1 8018
Protoss_Dragoon 1 7864
Protoss_Citadel_of_Adun 1 8171
Protoss_Templar_Archives 1 9481
10542
