Protoss_Gateway 1 2459
Protoss_Zealot 4 10078
Protoss_Assimilator 1 4421
Protoss_Forge 1 5271
Protoss_Photon_Cannon 3 9646
Protoss_Cybernetics_Core 1 6486
Protoss_Dragoon 2 10313
Protoss_Stargate 1 7876
Protoss_Robotics_Facility 1 8840
Protoss_Corsair 1 8613
Protoss_Shuttle 1 9892
Protoss_Robotics_Support_Bay 1 9781
Protoss_Ground_Weapons_1 1 9876
Protoss_Reaver 1 10943
10943
