Protoss_Forge 1 2776
Protoss_Nexus 2 11707
Protoss_Photon_Cannon 3 10258
Protoss_Gateway 3 8513
Protoss_Assimilator 2 7104
Protoss_Cybernetics_Core 1 6071
Protoss_Zealot 3 9958
Protoss_Stargate 1 7220
Protoss_Citadel_of_Adun 1 7232
Protoss_Corsair 2 8704
Protoss_Templar_Archives 1 8434
Protoss_Dark_Templar 2 9454
11707
