Protoss_Forge 1 2994
Protoss_Photon_Cannon 4 6128
Protoss_Nexus 1 5909
Protoss_Gateway 2 9510
Protoss_Assimilator 2 7500
Protoss_Zealot 6 10196
Protoss_Cybernetics_Core 1 7223
Protoss_Stargate 1 8380
Protoss_Dragoon 1 8300
Protoss_Citadel_of_Adun 1 8828
Protoss_Corsair 3 10556
10556
