Protoss_Gateway 2 3453
Protoss_Zealot 7 8128
Protoss_Assimilator 1 4723
Protoss_Cybernetics_Core 2 5611
Protoss_Forge 1 5922
Protoss_Photon_Cannon 3 8648
Protoss_Citadel_of_Adun 1 8025
Protoss_Templar_Archives 1 9067
Protoss_Dark_Templar 2 9910
Protoss_Robotics_Facility 1 10783
10783
