Protoss_Nexus 1 5175
Protoss_Forge 1 4301
Protoss_Gateway 3 9329
Protoss_Photon_Cannon 6 9834
Protoss_Assimilator 2 8095
Protoss_Cybernetics_Core 1 6716
Protoss_Zealot 6 10198
Protoss_Stargate 1 8165
Protoss_Citadel_of_Adun 1 8278
Protoss_Corsair 2 9944
Protoss_Templar_Archives 1 10152
10198
