Protoss_Forge 1 2786
Protoss_Nexus 1 5318
Protoss_Photon_Cannon 4 10636
Protoss_Gateway 2 9268
Protoss_Assimilator 2 7218
Protoss_Zealot 6 9104
Protoss_Cybernetics_Core 1 6271
Protoss_Stargate 1 7551
Protoss_Citadel_of_Adun 1 7978
Protoss_Corsair 1 8496
Protoss_Templar_Archives 1 9140
Protoss_Dark_Templar 2 10118
10636
