Protoss_Forge 2 4632
Protoss_Nexus 1 4831
Protoss_Gateway 3 9891
Protoss_Assimilator 2 7347
Protoss_Photon_Cannon 3 9995
Protoss_Zealot 5 9548
Protoss_Cybernetics_Core 1 6497
Protoss_Stargate 1 7833
Protoss_Citadel_of_Adun 1 8694
Protoss_Corsair 3 10538
Protoss_Templar_Archives 1 9695
Protoss_High_Templar 1 10662
10662
