Protoss_Forge 1 2488
Protoss_Nexus 1 4933
Protoss_Gateway 4 9063
Protoss_Assimilator 2 6234
Protoss_Photon_Cannon 5 10667
Protoss_Cybernetics_Core 1 5922
Protoss_Citadel_of_Adun 1 7025
Protoss_Dragoon 1 7168
Protoss_Templar_Archives 1 8016
Protoss_Zealot 3 10570
Protoss_Dark_Templar 2 8852
Protoss_High_Templar 6 10368
Protoss_Archon 1 10037
10667
