Protoss_Forge 1 3136
Protoss_Nexus 1 5142
Protoss_Photon_Cannon 4 10139
Protoss_Gateway 3 10447
Protoss_Assimilator 2 7656
Protoss_Zealot 3 8488
Protoss_Cybernetics_Core 1 6363
Protoss_Dragoon 1 7886
Protoss_Citadel_of_Adun 1 8513
Protoss_Templar_Archives 1 9766
Protoss_Dark_Templar 1 10722
Protoss_High_Templar 1 10732
10732
