Protoss_Forge 1 3298
Protoss_Nexus 1 5075
Protoss_Photon_Cannon 2 6444
Protoss_Gateway 2 9647
Protoss_Assimilator 2 6836
Protoss_Cybernetics_Core 1 6326
Protoss_Stargate 1 7581
Protoss_Zealot 2 9772
Protoss_Citadel_of_Adun 1 8517
Protoss_Corsair 3 9698
Protoss_Templar_Archives 1 9569
Protoss_Dark_Templar 1 10490
Protoss_High_Templar 1 10524
10524
