Protoss_Forge 1 3145
Protoss_Nexus 1 4972
Protoss_Photon_Cannon 6 10228
Protoss_Gateway 1 5369
Protoss_Assimilator 2 7396
Protoss_Cybernetics_Core 1 7178
Protoss_Zealot 2 8864
Protoss_Stargate 1 8332
Protoss_Dragoon 1 8148
Protoss_Robotics_Facility 1 9349
Protoss_Corsair 2 9670
Protoss_Robotics_Support_Bay 1 10305
10305
