Protoss_Gateway 2 3121
Protoss_Zealot 14 8256
Protoss_Assimilator 1 5656
Protoss_Cybernetics_Core 1 7085
Protoss_Dragoon 2 8490
Protoss_Stargate 1 8919
Protoss_Citadel_of_Adun 1 8976
Protoss_Forge 1 9302
Protoss_Corsair 2 10304
Protoss_Templar_Archives 1 10015
Protoss_Photon_Cannon 1 10384
10384
