Protoss_Forge 1 3086
Protoss_Photon_Cannon 6 9731
Protoss_Nexus 1 6086
Protoss_Gateway 3 10541
Protoss_Assimilator 2 7858
Protoss_Cybernetics_Core 1 6981
Protoss_Zealot 1 7086
Protoss_Stargate 1 8143
Protoss_Citadel_of_Adun 1 8924
Protoss_Corsair 3 10252
Protoss_Templar_Archives 1 10096
10541
