Protoss_Nexus 1 4694
Protoss_Gateway 6 10797
Protoss_Forge 1 4310
Protoss_Assimilator 2 7281
Protoss_Photon_Cannon 2 7928
Protoss_Cybernetics_Core 1 5621
Protoss_Zealot 5 9958
Protoss_Stargate 1 7278
Protoss_Citadel_of_Adun 1 8188
Protoss_Corsair 2 8742
Protoss_Templar_Archives 1 9273
Protoss_Dark_Templar 1 10718
10797
