Protoss_Forge 1 3182
Protoss_Nexus 1 5176
Protoss_Photon_Cannon 5 9706
Protoss_Gateway 1 5257
Protoss_Assimilator 3 9212
Protoss_Zealot 3 9072
Protoss_Cybernetics_Core 1 6765
Protoss_Stargate 1 8080
Protoss_Dragoon 1 8176
Protoss_Corsair 3 10034
Protoss_Citadel_of_Adun 1 9195
10034
