Protoss_Forge 1 3200
Protoss_Photon_Cannon 6 9345
Protoss_Nexus 1 7159
Protoss_Gateway 2 10623
Protoss_Assimilator 2 8115
Protoss_Cybernetics_Core 1 7443
Protoss_Zealot 3 9106
Protoss_Stargate 1 8766
Protoss_Robotics_Facility 1 9553
Protoss_Corsair 2 10116
Protoss_Robotics_Support_Bay 1 10271
10623
