Protoss_Forge 1 3388
Protoss_Nexus 1 4873
Protoss_Photon_Cannon 5 9724
Protoss_Gateway 1 5157
Protoss_Assimilator 3 8268
Protoss_Cybernetics_Core 1 6192
Protoss_Zealot 5 10122
Protoss_Stargate 1 7408
Protoss_Corsair 4 9998
Protoss_Robotics_Facility 1 9029
Protoss_Robotics_Support_Bay 1 9739
Protoss_Reaver 1 10948
10948
