Protoss_Forge 1 3215
Protoss_Photon_Cannon 5 7091
Protoss_Nexus 1 7280
Protoss_Gateway 4 10133
Protoss_Assimilator 2 8357
Protoss_Cybernetics_Core 1 7645
Protoss_Zealot 4 10290
Protoss_Citadel_of_Adun 1 8812
Protoss_Templar_Archives 1 9802
Protoss_Dark_Templar 2 10658
10658
