Protoss_Forge 1 2973
Protoss_Photon_Cannon 2 4103
Protoss_Nexus 1 5961
Protoss_Gateway 4 9439
Protoss_Assimilator 2 6695
Protoss_Cybernetics_Core 1 6345
Protoss_Stargate 1 7511
Protoss_Citadel_of_Adun 1 7822
Protoss_Corsair 1 8208
Protoss_Templar_Archives 1 8842
Protoss_Dark_Templar 2 9834
Protoss_High_Templar 4 10614
Protoss_Zealot 1 10584
10614
