Protoss_Forge 1 3361
Protoss_Nexus 1 4875
Protoss_Photon_Cannon 3 9709
Protoss_Gateway 3 8419
Protoss_Assimilator 2 6673
Protoss_Zealot 7 9750
Protoss_Cybernetics_Core 1 6328
Protoss_Stargate 1 7666
Protoss_Citadel_of_Adun 1 8531
Protoss_Corsair 3 10076
Protoss_Templar_Archives 1 10211
10211
