Protoss_Gateway 2 9861
Protoss_Zealot 8 9912
Protoss_Nexus 1 5825
Protoss_Forge 1 5150
Protoss_Cybernetics_Core 1 6265
Protoss_Assimilator 2 7208
Protoss_Photon_Cannon 2 8169
Protoss_Dragoon 1 7248
Protoss_Stargate 1 8211
Protoss_Citadel_of_Adun 1 9060
Protoss_Corsair 3 10536
Protoss_Templar_Archives 1 10280
10536
