Protoss_Forge 1 2964
Protoss_Photon_Cannon 3 10559
Protoss_Nexus 1 5771
Protoss_Gateway 1 5164
Protoss_Assimilator 2 7568
Protoss_Cybernetics_Core 1 6201
Protoss_Zealot 4 9510
Protoss_Stargate 1 7342
Protoss_Citadel_of_Adun 1 7707
Protoss_Corsair 3 9790
Protoss_Templar_Archives 1 9196
10559
