Protoss_Forge 1 2652
Protoss_Photon_Cannon 7 10312
Protoss_Nexus 1 5637
Protoss_Gateway 1 5212
Protoss_Assimilator 2 7613
Protoss_Cybernetics_Core 1 7868
Protoss_Zealot 4 10186
Protoss_Stargate 2 9854
Protoss_Citadel_of_Adun 2 9883
Protoss_Corsair 1 10544
Protoss_Templar_Archives 1 10877
10877
