Protoss_Forge 1 3064
Protoss_Nexus 1 4929
Protoss_Photon_Cannon 2 7822
Protoss_Gateway 3 8929
Protoss_Assimilator 2 8246
Protoss_Cybernetics_Core 1 6278
Protoss_Zealot 8 10024
Protoss_Dragoon 1 7240
Protoss_Stargate 1 7565
Protoss_Citadel_of_Adun 1 8380
Protoss_Corsair 1 8606
10024
