Protoss_Forge 1 2511
Protoss_Nexus 1 4855
Protoss_Photon_Cannon 4 10410
Protoss_Gateway 4 9520
Protoss_Assimilator 2 7608
Protoss_Zealot 5 9548
Protoss_Cybernetics_Core 1 6217
Protoss_Stargate 1 7418
Protoss_Citadel_of_Adun 1 7390
Protoss_Corsair 1 8098
Protoss_Templar_Archives 1 9259
Protoss_High_Templar 2 10206
Protoss_Dark_Templar 1 10300
10410
