Protoss_Forge 1 2837
Protoss_Photon_Cannon 6 10574
Protoss_Nexus 1 5189
Protoss_Gateway 3 10083
Protoss_Assimilator 2 6705
Protoss_Cybernetics_Core 1 6280
Protoss_Zealot 4 9366
Protoss_Stargate 1 7679
Protoss_Citadel_of_Adun 1 8004
Protoss_Corsair 1 8360
Protoss_Templar_Archives 1 9109
Protoss_High_Templar 1 10118
10574
