Protoss_Gateway 2 3280
Protoss_Zealot 11 9338
Protoss_Assimilator 1 5210
Protoss_Cybernetics_Core 1 6362
Protoss_Stargate 1 7543
Protoss_Citadel_of_Adun 1 7865
Protoss_Forge 1 7955
Protoss_Corsair 1 8238
Protoss_Templar_Archives 1 10527
Protoss_Nexus 1 11501
11501
