Protoss_Nexus 1 4607
Protoss_Gateway 6 10795
Protoss_Forge 1 4445
Protoss_Photon_Cannon 4 9438
Protoss_Assimilator 2 6833
Protoss_Zealot 5 9234
Protoss_Cybernetics_Core 1 5938
Protoss_Stargate 1 7356
Protoss_Dragoon 1 7338
Protoss_Citadel_of_Adun 1 7887
Protoss_Corsair 1 8056
Protoss_Templar_Archives 1 8974
Protoss_Dark_Templar 1 9986
Protoss_High_Templar 2 10028
10795
