Protoss_Nexus 1 4697
Protoss_Forge 1 4268
Protoss_Gateway 3 10426
Protoss_Photon_Cannon 3 6551
Protoss_Assimilator 2 7422
Protoss_Zealot 3 9004
Protoss_Cybernetics_Core 1 7159
Protoss_Stargate 1 8302
Protoss_Dragoon 1 8200
Protoss_Citadel_of_Adun 1 8803
Protoss_Corsair 3 10372
Protoss_Templar_Archives 1 9810
Protoss_Dark_Templar 1 10686
10686
