Protoss_Gateway 1 2848
Protoss_Zealot 8 10176
Protoss_Nexus 1 5850
Protoss_Assimilator 2 9903
Protoss_Cybernetics_Core 1 5791
Protoss_Forge 1 5888
Protoss_Photon_Cannon 2 7893
Protoss_Stargate 1 7278
Protoss_Corsair 2 8916
Protoss_Citadel_of_Adun 1 10624
10624
