Protoss_Gateway 2 3507
Protoss_Zealot 13 10026
Protoss_Forge 1 5807
Protoss_Photon_Cannon 3 10562
Protoss_Nexus 1 8687
Protoss_Assimilator 1 8038
Protoss_Cybernetics_Core 1 8635
Protoss_Citadel_of_Adun 1 9733
Protoss_Templar_Archives 1 10880
10880
