Protoss_Forge 1 3022
Protoss_Nexus 1 5139
Protoss_Assimilator 2 7128
Protoss_Gateway 1 5037
Protoss_Photon_Cannon 6 10640
Protoss_Cybernetics_Core 1 6501
Protoss_Zealot 5 9936
Protoss_Dragoon 1 7356
Protoss_Stargate 1 7750
Protoss_Robotics_Facility 1 8686
Protoss_Corsair 3 9828
Protoss_Robotics_Support_Bay 1 9567
Protoss_Reaver 1 10698
10698
