Protoss_Forge 1 2863
Protoss_Photon_Cannon 5 10447
Protoss_Nexus 1 5965
Protoss_Gateway 4 10156
Protoss_Assimilator 2 7680
Protoss_Cybernetics_Core 1 6388
Protoss_Zealot 3 10406
Protoss_Dragoon 1 7378
Protoss_Citadel_of_Adun 1 7809
Protoss_Templar_Archives 1 8953
Protoss_High_Templar 3 10538
10538
