Protoss_Forge 1 3526
Protoss_Nexus 1 4980
Protoss_Gateway 3 9250
Protoss_Photon_Cannon 2 9555
Protoss_Assimilator 2 7114
Protoss_Cybernetics_Core 1 5919
Protoss_Zealot 3 7316
Protoss_Stargate 1 7216
Protoss_Citadel_of_Adun 1 7781
Protoss_Corsair 3 9766
Protoss_Templar_Archives 1 8991
Protoss_Dark_Templar 3 10716
Protoss_High_Templar 1 10356
10716
