Protoss_Forge 1 2688
Protoss_Nexus 1 5327
Protoss_Gateway 1 4929
Protoss_Photon_Cannon 4 9608
Protoss_Assimilator 2 8206
Protoss_Cybernetics_Core 1 6284
Protoss_Zealot 2 7862
Protoss_Stargate 1 7520
Protoss_Corsair 3 10298
Protoss_Robotics_Facility 1 9300
Protoss_Robotics_Support_Bay 1 10047
Protoss_Shuttle 1 10719
10719
