Protoss_Forge 1 2826
Protoss_Nexus 1 5318
Protoss_Photon_Cannon 4 10627
Protoss_Gateway 3 10060
Protoss_Assimilator 2 6972
Protoss_Cybernetics_Core 1 6259
Protoss_Zealot 5 10276
Protoss_Stargate 1 7514
Protoss_Citadel_of_Adun 1 8331
Protoss_Dragoon 1 8358
Protoss_Corsair 1 8770
Protoss_Templar_Archives 1 10445
10627
