Protoss_Forge 1 3199
Protoss_Nexus 1 5037
Protoss_Photon_Cannon 3 8236
Protoss_Gateway 3 10422
Protoss_Assimilator 2 8774
Protoss_Zealot 4 10584
Protoss_Cybernetics_Core 1 6100
Protoss_Stargate 1 7594
Protoss_Dragoon 1 7870
Protoss_Citadel_of_Adun 1 8267
Protoss_Corsair 4 10470
Protoss_Templar_Archives 1 10503
10584
