Protoss_Forge 1 2835
Protoss_Photon_Cannon 4 9927
Protoss_Nexus 1 6415
Protoss_Gateway 1 5831
Protoss_Assimilator 2 7322
Protoss_Cybernetics_Core 1 7107
Protoss_Zealot 1 6856
Protoss_Stargate 1 8243
Protoss_Dragoon 1 8090
Protoss_Corsair 3 10190
Protoss_Robotics_Facility 1 9943
10190
