Protoss_Nexus 1 4563
Protoss_Forge 1 3902
Protoss_Gateway 3 10037
Protoss_Photon_Cannon 4 10058
Protoss_Assimilator 2 6728
Protoss_Zealot 8 10596
Protoss_Cybernetics_Core 1 6546
Protoss_Stargate 1 7846
Protoss_Citadel_of_Adun 1 8573
Protoss_Corsair 3 9936
Protoss_Templar_Archives 1 9681
10596
