Protoss_Gateway 2 3185
Protoss_Zealot 17 10468
Protoss_Nexus 1 8665
Protoss_Assimilator 2 10027
Protoss_Forge 1 8795
Protoss_Cybernetics_Core 1 9609
Protoss_Photon_Cannon 1 9640
Protoss_Stargate 1 10798
10798
