Protoss_Forge 1 2546
Protoss_Photon_Cannon 4 8729
Protoss_Nexus 1 6523
Protoss_Gateway 4 10782
Protoss_Assimilator 2 7206
Protoss_Zealot 2 7332
Protoss_Cybernetics_Core 1 6980
Protoss_Stargate 1 8154
Protoss_Citadel_of_Adun 1 8287
Protoss_Dragoon 1 8272
Protoss_Corsair 2 10111
Protoss_Templar_Archives 1 9327
Protoss_Dark_Templar 2 10286
10782
