Protoss_Gateway 3 10383
Protoss_Zealot 12 10426
Protoss_Assimilator 1 7326
Protoss_Cybernetics_Core 1 7895
Protoss_Nexus 1 9833
Protoss_Citadel_of_Adun 1 9049
Protoss_Dragoon 2 9634
Protoss_Forge 1 9722
10426
