Protoss_Forge 1 3272
Protoss_Nexus 1 5215
Protoss_Photon_Cannon 2 5308
Protoss_Gateway 6 10619
Protoss_Assimilator 2 6801
Protoss_Cybernetics_Core 1 6559
Protoss_Stargate 1 7721
Protoss_Citadel_of_Adun 1 7903
Protoss_Corsair 2 9014
Protoss_Templar_Archives 1 9011
Protoss_High_Templar 3 10622
Protoss_Dark_Templar 1 10626
10626
