Protoss_Forge 1 2902
Protoss_Photon_Cannon 2 3954
Protoss_Nexus 1 5869
Protoss_Gateway 3 9789
Protoss_Assimilator 2 8151
Protoss_Cybernetics_Core 1 6256
Protoss_Zealot 9 10566
Protoss_Stargate 1 7522
Protoss_Corsair 3 9484
Protoss_Citadel_of_Adun 1 8646
Protoss_Templar_Archives 1 10015
Protoss_Ground_Weapons_1 1 9771
10566
