Protoss_Forge 1 3248
Protoss_Nexus 1 4927
Protoss_Photon_Cannon 2 4474
Protoss_Gateway 3 9916
Protoss_Assimilator 2 7374
Protoss_Cybernetics_Core 1 6261
Protoss_Zealot 8 10338
Protoss_Stargate 1 7402
Protoss_Citadel_of_Adun 1 8162
Protoss_Corsair 2 8688
Protoss_Robotics_Facility 1 9988
Protoss_Templar_Archives 1 10719
10719
