Protoss_Forge 1 2917
Protoss_Nexus 1 5075
Protoss_Photon_Cannon 3 9827
Protoss_Gateway 4 10838
Protoss_Assimilator 2 6669
Protoss_Cybernetics_Core 1 6511
Protoss_Zealot 4 9550
Protoss_Dragoon 1 7484
Protoss_Stargate 1 7841
Protoss_Citadel_of_Adun 1 8587
Protoss_Corsair 1 8550
Protoss_Templar_Archives 1 9658
Protoss_Dark_Templar 2 10562
10838
