Protoss_Forge 1 3257
Protoss_Nexus 1 4971
Protoss_Photon_Cannon 4 9828
Protoss_Gateway 3 9807
Protoss_Assimilator 2 7694
Protoss_Cybernetics_Core 1 6435
Protoss_Zealot 4 10526
Protoss_Stargate 1 7570
Protoss_Dragoon 1 7588
Protoss_Citadel_of_Adun 1 8418
Protoss_Corsair 3 10000
Protoss_Templar_Archives 1 9533
Protoss_Dark_Templar 1 10390
10526
