Protoss_Forge 1 3165
Protoss_Nexus 1 5075
Protoss_Photon_Cannon 3 9697
Protoss_Gateway 4 10671
Protoss_Assimilator 2 6260
Protoss_Cybernetics_Core 1 6189
Protoss_Zealot 7 9400
Protoss_Stargate 1 7326
Protoss_Citadel_of_Adun 1 7784
Protoss_Corsair 1 8008
Protoss_Templar_Archives 1 8909
Protoss_Dark_Templar 2 10152
10671
