Protoss_Forge 1 2756
Protoss_Photon_Cannon 2 3954
Protoss_Nexus 1 5848
Protoss_Gateway 2 10231
Protoss_Assimilator 2 6978
Protoss_Zealot 2 7128
Protoss_Cybernetics_Core 1 6752
Protoss_Stargate 1 8319
Protoss_Dragoon 1 8324
Protoss_Citadel_of_Adun 1 8656
Protoss_Corsair 2 10218
Protoss_Robotics_Facility 1 9832
Protoss_Templar_Archives 1 10159
10231
