Protoss_Gateway 3 10288
Protoss_Zealot 10 8874
Protoss_Assimilator 1 4626
Protoss_Cybernetics_Core 1 5646
Protoss_Stargate 1 6868
Protoss_Dragoon 1 6868
Protoss_Citadel_of_Adun 1 7563
Protoss_Corsair 1 7610
Protoss_Templar_Archives 1 9008
Protoss_High_Templar 2 9934
Protoss_Nexus 1 11747
11747
