Protoss_Gateway 2 8328
Protoss_Assimilator 1 2928
Protoss_Cybernetics_Core 1 3789
Protoss_Zealot 3 5982
Protoss_Stargate 1 4940
Protoss_Citadel_of_Adun 1 5649
Protoss_Corsair 2 7078
Protoss_Templar_Archives 1 6885
Protoss_Forge 1 7563
Protoss_Dark_Templar 1 7798
Protoss_Photon_Cannon 2 10637
Protoss_High_Templar 3 10510
10637
