Protoss_Gateway 2 9755
Protoss_Zealot 6 7620
Protoss_Assimilator 2 9987
Protoss_Cybernetics_Core 1 4576
Protoss_Stargate 1 5724
Protoss_Dragoon 1 5586
Protoss_Corsair 3 8040
Protoss_Citadel_of_Adun 1 7129
Protoss_Templar_Archives 1 8181
Protoss_Dark_Templar 2 9922
Protoss_Nexus 1 10323
Protoss_High_Templar 1 10674
10674
