Protoss_Forge 1 3020
Protoss_Nexus 1 5071
Protoss_Photon_Cannon 4 9046
Protoss_Gateway 4 10867
Protoss_Assimilator 2 7040
Protoss_Cybernetics_Core 1 6732
Protoss_Zealot 1 6782
Protoss_Citadel_of_Adun 1 8021
Protoss_Stargate 1 8313
Protoss_Corsair 3 10206
Protoss_Templar_Archives 1 9572
Protoss_Dark_Templar 2 10454
10867
