Protoss_Nexus 1 4579
Protoss_Forge 1 3552
Protoss_Photon_Cannon 3 8388
Protoss_Gateway 1 5119
Protoss_Zealot 5 10568
Protoss_Cybernetics_Core 1 6591
Protoss_Assimilator 2 9155
Protoss_Stargate 1 10443
Protoss_Citadel_of_Adun 1 10678
10678
