Protoss_Forge 1 2909
Protoss_Nexus 1 5129
Protoss_Gateway 4 9557
Protoss_Photon_Cannon 1 5251
Protoss_Assimilator 2 6626
Protoss_Cybernetics_Core 1 6282
Protoss_Zealot 1 6220
Protoss_Stargate 1 7453
Protoss_Dragoon 8 10636
Protoss_Robotics_Facility 1 8475
Protoss_Corsair 1 8158
Protoss_Shuttle 1 9463
Protoss_Robotics_Support_Bay 1 9373
Protoss_Reaver 1 10532
10636
