Protoss_Forge 2 8166
Protoss_Photon_Cannon 3 5600
Protoss_Gateway 4 10401
Protoss_Zealot 8 10496
Protoss_Assimilator 1 5818
Protoss_Cybernetics_Core 1 6892
Protoss_Stargate 1 8145
Protoss_Dragoon 1 8042
Protoss_Citadel_of_Adun 1 8765
Protoss_Corsair 1 8992
10496
