Protoss_Forge 1 2648
Protoss_Photon_Cannon 3 5720
Protoss_Gateway 2 8807
Protoss_Zealot 7 10486
Protoss_Nexus 1 8291
Protoss_Assimilator 2 9583
Protoss_Cybernetics_Core 1 8412
Protoss_Stargate 1 9770
Protoss_Dragoon 2 9884
Protoss_Citadel_of_Adun 1 10569
10569
