Protoss_Nexus 1 4662
Protoss_Gateway 3 8427
Protoss_Forge 1 4499
Protoss_Photon_Cannon 7 10286
Protoss_Zealot 6 9720
Protoss_Assimilator 3 8631
Protoss_Cybernetics_Core 1 6481
Protoss_Stargate 1 8038
Protoss_Citadel_of_Adun 1 8684
Protoss_Corsair 3 10222
10286
