Protoss_Forge 1 3397
Protoss_Nexus 1 5073
Protoss_Photon_Cannon 2 4600
Protoss_Gateway 3 9201
Protoss_Assimilator 2 6743
Protoss_Cybernetics_Core 1 6201
Protoss_Zealot 10 10592
Protoss_Dragoon 1 7178
Protoss_Stargate 1 7608
Protoss_Citadel_of_Adun 1 7991
Protoss_Corsair 3 9496
Protoss_Templar_Archives 1 10033
10592
