Protoss_Forge 1 2582
Protoss_Photon_Cannon 5 9367
Protoss_Nexus 1 6689
Protoss_Gateway 1 6059
Protoss_Assimilator 3 8119
Protoss_Zealot 4 9166
Protoss_Cybernetics_Core 1 7556
Protoss_Stargate 1 9275
Protoss_Citadel_of_Adun 1 9660
9660
