Protoss_Gateway 1 2665
Protoss_Assimilator 1 2747
Protoss_Zealot 5 7212
Protoss_Cybernetics_Core 1 3858
Protoss_Stargate 1 5059
Protoss_Dragoon 1 4882
Protoss_Corsair 2 7360
Protoss_Citadel_of_Adun 1 6493
Protoss_Templar_Archives 1 7639
Protoss_Forge 1 7874
Protoss_Dark_Templar 2 9740
Protoss_Nexus 1 10555
10555
