Protoss_Forge 1 2549
Protoss_Photon_Cannon 7 10481
Protoss_Nexus 1 5081
Protoss_Gateway 2 9359
Protoss_Assimilator 2 6798
Protoss_Cybernetics_Core 1 6309
Protoss_Zealot 3 7939
Protoss_Stargate 1 7461
Protoss_Citadel_of_Adun 1 8254
Protoss_Corsair 3 9380
Protoss_Templar_Archives 1 9409
10481
