Protoss_Forge 1 2794
Protoss_Nexus 1 5043
Protoss_Gateway 3 9577
Protoss_Photon_Cannon 6 10608
Protoss_Assimilator 2 6152
Protoss_Cybernetics_Core 1 5992
Protoss_Zealot 3 9072
Protoss_Stargate 1 7276
Protoss_Dragoon 1 7004
Protoss_Citadel_of_Adun 1 7379
Protoss_Corsair 2 8560
Protoss_Templar_Archives 1 9079
Protoss_Dark_Templar 1 10182
Protoss_High_Templar 2 10644
10644
