Protoss_Gateway 5 9738
Protoss_Zealot 6 8872
Protoss_Nexus 1 5957
Protoss_Assimilator 1 5312
Protoss_Cybernetics_Core 1 7324
Protoss_Dragoon 3 10282
Protoss_Forge 1 8656
Protoss_Photon_Cannon 4 10704
10704
