Protoss_Forge 1 3122
Protoss_Photon_Cannon 7 10742
Protoss_Nexus 1 5775
Protoss_Gateway 3 8608
Protoss_Assimilator 2 8598
Protoss_Cybernetics_Core 1 6192
Protoss_Zealot 5 9634
Protoss_Citadel_of_Adun 1 7492
Protoss_Dragoon 1 7414
Protoss_Templar_Archives 1 9591
Protoss_Dark_Templar 1 10626
Protoss_High_Templar 2 10642
10742
