Protoss_Gateway 2 3558
Protoss_Zealot 9 8413
Protoss_Assimilator 1 5534
Protoss_Cybernetics_Core 1 6156
Protoss_Dragoon 5 10028
Protoss_Robotics_Facility 1 8508
Protoss_Shuttle 1 9502
Protoss_Robotics_Support_Bay 1 9396
Protoss_Reaver 1 10796
10796
