Protoss_Gateway 1 2835
Protoss_Assimilator 1 3097
Protoss_Zealot 5 10224
Protoss_Cybernetics_Core 1 4037
Protoss_Robotics_Facility 1 5497
Protoss_Shuttle 1 6487
Protoss_Robotics_Support_Bay 1 6076
Protoss_Dragoon 1 6692
Protoss_Reaver 2 10152
Protoss_Stargate 1 8446
Protoss_Nexus 1 9765
Protoss_Corsair 2 10516
Protoss_Forge 1 10060
10516
