Protoss_Forge 1 2849
Protoss_Photon_Cannon 4 7036
Protoss_Nexus 1 6165
Protoss_Gateway 4 10363
Protoss_Assimilator 2 8076
Protoss_Zealot 3 8432
Protoss_Cybernetics_Core 1 7757
Protoss_Stargate 1 9434
Protoss_Citadel_of_Adun 1 9748
Protoss_Corsair 1 10190
10363
