Protoss_Forge 1 2795
Protoss_Nexus 1 5075
Protoss_Photon_Cannon 5 10057
Protoss_Gateway 1 4862
Protoss_Assimilator 2 7520
Protoss_Cybernetics_Core 1 6070
Protoss_Zealot 6 9934
Protoss_Stargate 1 7546
Protoss_Citadel_of_Adun 1 8341
Protoss_Corsair 1 8888
10057
