Protoss_Gateway 2 3462
Protoss_Zealot 12 9672
Protoss_Assimilator 1 5374
Protoss_Cybernetics_Core 1 6829
Protoss_Stargate 1 8242
Protoss_Forge 1 8411
Protoss_Corsair 1 8974
Protoss_Photon_Cannon 3 10377
Protoss_Citadel_of_Adun 2 10890
Protoss_Dragoon 2 10498
10890
