Protoss_Nexus 1 4749
Protoss_Forge 1 4150
Protoss_Gateway 2 8622
Protoss_Photon_Cannon 7 10118
Protoss_Assimilator 2 6396
Protoss_Zealot 2 6788
Protoss_Cybernetics_Core 1 6925
Protoss_Stargate 1 8123
Protoss_Citadel_of_Adun 1 8042
Protoss_Corsair 3 10340
Protoss_Templar_Archives 1 9343
Protoss_Dark_Templar 2 10220
Protoss_High_Templar 1 10254
10340
