Protoss_Forge 1 2892
Protoss_Photon_Cannon 2 3982
Protoss_Nexus 1 5931
Protoss_Gateway 3 8337
Protoss_Assimilator 2 8583
Protoss_Cybernetics_Core 1 6426
Protoss_Zealot 11 10434
Protoss_Citadel_of_Adun 1 7866
Protoss_Templar_Archives 1 9684
10434
