Protoss_Forge 1 3190
Protoss_Nexus 1 5058
Protoss_Photon_Cannon 3 9666
Protoss_Gateway 4 10831
Protoss_Assimilator 2 6581
Protoss_Cybernetics_Core 1 5999
Protoss_Zealot 7 10256
Protoss_Stargate 1 7280
Protoss_Citadel_of_Adun 1 7685
Protoss_Corsair 4 9966
Protoss_Templar_Archives 1 10099
10831
