Protoss_Nexus 1 4821
Protoss_Gateway 4 7252
Protoss_Forge 1 4552
Protoss_Photon_Cannon 2 5604
Protoss_Zealot 15 9768
Protoss_Assimilator 2 9877
Protoss_Cybernetics_Core 1 9081
Protoss_Stargate 1 10364
10364
