Protoss_Forge 1 2674
Protoss_Nexus 1 5147
Protoss_Gateway 4 9721
Protoss_Photon_Cannon 3 10310
Protoss_Assimilator 2 6848
Protoss_Cybernetics_Core 1 5901
Protoss_Zealot 4 8752
Protoss_Stargate 1 7178
Protoss_Citadel_of_Adun 1 7793
Protoss_Corsair 2 9444
Protoss_Templar_Archives 1 8929
Protoss_Dark_Templar 1 9842
Protoss_High_Templar 1 10140
10310
