Protoss_Forge 1 2962
Protoss_Photon_Cannon 3 5440
Protoss_Nexus 1 6263
Protoss_Gateway 1 5919
Protoss_Zealot 2 7690
Protoss_Assimilator 2 10487
Protoss_Cybernetics_Core 1 10653
10653
