Protoss_Forge 1 2845
Protoss_Photon_Cannon 4 10520
Protoss_Nexus 1 5813
Protoss_Gateway 3 10565
Protoss_Assimilator 2 8855
Protoss_Cybernetics_Core 1 6269
Protoss_Zealot 8 9846
Protoss_Stargate 1 7435
Protoss_Citadel_of_Adun 1 7751
Protoss_Corsair 5 10196
Protoss_Templar_Archives 1 10808
10808
