Protoss_Forge 1 3181
Protoss_Photon_Cannon 5 9891
Protoss_Nexus 1 5577
Protoss_Gateway 3 10694
Protoss_Assimilator 2 7480
Protoss_Cybernetics_Core 1 6502
Protoss_Zealot 3 8050
Protoss_Stargate 1 7776
Protoss_Citadel_of_Adun 1 8157
Protoss_Corsair 1 8474
Protoss_Templar_Archives 1 9233
Protoss_High_Templar 2 10130
10694
