Protoss_Forge 1 3293
Protoss_Photon_Cannon 5 10016
Protoss_Nexus 1 5963
Protoss_Gateway 1 5320
Protoss_Assimilator 2 7792
Protoss_Cybernetics_Core 1 6345
Protoss_Zealot 3 9436
Protoss_Stargate 2 9115
Protoss_Dragoon 1 7460
Protoss_Citadel_of_Adun 1 8545
Protoss_Corsair 4 10472
Protoss_Robotics_Facility 1 10901
10901
