Protoss_Forge 1 3051
Protoss_Photon_Cannon 2 3924
Protoss_Nexus 1 5813
Protoss_Gateway 2 8081
Protoss_Assimilator 2 7217
Protoss_Cybernetics_Core 1 6176
Protoss_Zealot 8 10337
Protoss_Stargate 1 7316
Protoss_Corsair 4 9952
Protoss_Citadel_of_Adun 1 8628
Protoss_Templar_Archives 1 10822
10822
