Protoss_Forge 1 2518
Protoss_Photon_Cannon 12 10652
Protoss_Nexus 1 6175
Protoss_Gateway 1 5893
Protoss_Assimilator 1 5961
Protoss_Cybernetics_Core 1 8667
Protoss_Zealot 1 9050
Protoss_Stargate 1 9938
10652
