Protoss_Nexus 1 4811
Protoss_Forge 1 4262
Protoss_Gateway 4 9413
Protoss_Photon_Cannon 2 10297
Protoss_Assimilator 2 7212
Protoss_Cybernetics_Core 1 6412
Protoss_Zealot 2 6852
Protoss_Dragoon 8 10682
Protoss_Stargate 1 8468
Protoss_Corsair 2 10054
10682
