Protoss_Gateway 1 2725
Protoss_Assimilator 1 2827
Protoss_Zealot 3 5132
Protoss_Cybernetics_Core 1 4789
Protoss_Stargate 1 5951
Protoss_Dragoon 2 7144
Protoss_Citadel_of_Adun 1 6451
Protoss_Corsair 3 8160
Protoss_Templar_Archives 1 7517
Protoss_Forge 1 7888
Protoss_Dark_Templar 1 8584
Protoss_Nexus 1 10289
Protoss_High_Templar 1 9506
Protoss_Photon_Cannon 1 10716
10716
