Protoss_Gateway 2 9915
Protoss_Assimilator 1 3054
Protoss_Zealot 3 4860
Protoss_Cybernetics_Core 1 4837
Protoss_Dragoon 5 10320
Protoss_Robotics_Facility 1 6522
Protoss_Robotics_Support_Bay 1 7163
Protoss_Reaver 2 10396
Protoss_Nexus 1 9175
Protoss_Shuttle 1 9219
10396
