Protoss_Nexus 1 4903
Protoss_Forge 1 4294
Protoss_Gateway 3 8387
Protoss_Photon_Cannon 6 10614
Protoss_Assimilator 2 6519
Protoss_Cybernetics_Core 1 6417
Protoss_Citadel_of_Adun 1 7440
Protoss_Templar_Archives 1 8512
Protoss_Zealot 3 10580
Protoss_High_Templar 4 10394
Protoss_Dark_Templar 1 9892
Protoss_Archon 1 10002
10614
