Protoss_Forge 1 3033
Protoss_Photon_Cannon 6 7915
Protoss_Nexus 1 6171
Protoss_Gateway 3 10458
Protoss_Assimilator 2 9318
Protoss_Cybernetics_Core 1 6784
Protoss_Zealot 3 7928
Protoss_Stargate 1 8963
Protoss_Citadel_of_Adun 1 9301
Protoss_Corsair 1 9704
Protoss_Templar_Archives 1 10601
10601
