Protoss_Forge 1 3173
Protoss_Nexus 1 5201
Protoss_Photon_Cannon 4 10280
Protoss_Assimilator 3 7812
Protoss_Gateway 3 9746
Protoss_Cybernetics_Core 1 6413
Protoss_Zealot 6 9508
Protoss_Stargate 1 7573
Protoss_Citadel_of_Adun 1 8001
Protoss_Corsair 3 10541
10541
