Protoss_Gateway 1 2893
Protoss_Zealot 8 9742
Protoss_Nexus 1 5903
Protoss_Forge 1 5049
Protoss_Photon_Cannon 3 7472
Protoss_Assimilator 2 9319
Protoss_Cybernetics_Core 1 9227
Protoss_Stargate 1 10631
Protoss_Robotics_Facility 1 11097
11097
