Protoss_Forge 1 2843
Protoss_Nexus 1 5096
Protoss_Gateway 5 9737
Protoss_Assimilator 2 8492
Protoss_Photon_Cannon 3 7882
Protoss_Cybernetics_Core 1 5691
Protoss_Stargate 1 6884
Protoss_Zealot 6 10492
Protoss_Corsair 2 8686
Protoss_Citadel_of_Adun 1 8269
10492
