Protoss_Forge 1 2866
Protoss_Nexus 1 5171
Protoss_Photon_Cannon 4 10042
Protoss_Gateway 4 9645
Protoss_Assimilator 1 5210
Protoss_Cybernetics_Core 1 6216
Protoss_Zealot 11 10594
Protoss_Stargate 1 7432
Protoss_Citadel_of_Adun 1 7935
Protoss_Corsair 2 8930
10594
