Protoss_Forge 1 2652
Protoss_Photon_Cannon 4 5580
Protoss_Nexus 1 6386
Protoss_Gateway 3 9859
Protoss_Assimilator 2 8096
Protoss_Cybernetics_Core 1 7308
Protoss_Zealot 5 9920
Protoss_Stargate 1 8921
Protoss_Citadel_of_Adun 1 9255
Protoss_Corsair 2 10290
Protoss_Templar_Archives 1 10329
10329
