Protoss_Forge 1 2742
Protoss_Photon_Cannon 2 5737
Protoss_Nexus 1 5825
Protoss_Gateway 1 5561
Protoss_Assimilator 2 7034
Protoss_Cybernetics_Core 1 6668
Protoss_Zealot 2 8306
Protoss_Stargate 1 7865
Protoss_Robotics_Facility 1 8815
Protoss_Corsair 4 10520
Protoss_Dragoon 1 9208
Protoss_Shuttle 1 9961
Protoss_Robotics_Support_Bay 1 9671
10520
