Protoss_Forge 1 3190
Protoss_Nexus 1 5139
Protoss_Gateway 5 10121
Protoss_Assimilator 2 7779
Protoss_Photon_Cannon 2 10170
Protoss_Cybernetics_Core 1 5811
Protoss_Zealot 3 9446
Protoss_Dragoon 1 6712
Protoss_Stargate 1 7286
Protoss_Citadel_of_Adun 1 7419
Protoss_Corsair 2 8772
Protoss_Templar_Archives 1 8631
Protoss_High_Templar 1 10166
Protoss_Dark_Templar 1 10198
10198
