Protoss_Forge 1 3246
Protoss_Photon_Cannon 2 4339
Protoss_Nexus 1 5718
Protoss_Gateway 3 10385
Protoss_Assimilator 2 7962
Protoss_Cybernetics_Core 1 6204
Protoss_Zealot 6 10044
Protoss_Stargate 1 7461
Protoss_Citadel_of_Adun 1 8113
Protoss_Corsair 4 10136
Protoss_Templar_Archives 1 9590
Protoss_Dark_Templar 2 10588
10588
