Protoss_Gateway 2 3195
Protoss_Zealot 8 7398
Protoss_Assimilator 1 5444
Protoss_Cybernetics_Core 1 6361
Protoss_Stargate 1 7565
Protoss_Forge 1 7831
Protoss_Corsair 1 8354
Protoss_Robotics_Facility 1 9211
Protoss_Photon_Cannon 2 9818
Protoss_Robotics_Support_Bay 1 10185
Protoss_Nexus 1 11725
11725
