Protoss_Forge 1 2742
Protoss_Nexus 1 5170
Protoss_Photon_Cannon 2 4684
Protoss_Gateway 4 9653
Protoss_Assimilator 2 7343
Protoss_Cybernetics_Core 1 6821
Protoss_Zealot 6 10362
Protoss_Stargate 1 8176
Protoss_Dragoon 1 8026
Protoss_Citadel_of_Adun 1 8911
Protoss_Corsair 2 9716
10362
