Protoss_Forge 1 2973
Protoss_Photon_Cannon 4 9969
Protoss_Nexus 1 5895
Protoss_Gateway 2 8341
Protoss_Assimilator 2 8474
Protoss_Cybernetics_Core 1 6251
Protoss_Zealot 6 10056
Protoss_Stargate 1 7574
Protoss_Dragoon 1 7526
Protoss_Corsair 3 10002
Protoss_Citadel_of_Adun 1 9161
Protoss_Templar_Archives 1 10543
10543
