Protoss_Forge 1 2778
Protoss_Nexus 1 5031
Protoss_Photon_Cannon 3 7630
Protoss_Gateway 1 5687
Protoss_Assimilator 2 6848
Protoss_Cybernetics_Core 1 6829
Protoss_Zealot 2 8436
Protoss_Stargate 2 8694
Protoss_Corsair 5 10240
Protoss_Citadel_of_Adun 1 10233
10240
