Protoss_Forge 1 3273
Protoss_Nexus 1 5157
Protoss_Photon_Cannon 4 8854
Protoss_Gateway 4 10755
Protoss_Assimilator 1 4841
Protoss_Zealot 4 9948
Protoss_Cybernetics_Core 1 7791
Protoss_Stargate 1 9428
Protoss_Dragoon 1 9278
Protoss_Citadel_of_Adun 1 9890
Protoss_Corsair 1 10294
10755
