Protoss_Forge 1 3083
Protoss_Photon_Cannon 5 8858
Protoss_Nexus 1 5985
Protoss_Gateway 4 10189
Protoss_Assimilator 2 6926
Protoss_Zealot 5 9266
Protoss_Cybernetics_Core 1 6671
Protoss_Stargate 1 7806
Protoss_Citadel_of_Adun 1 8186
Protoss_Corsair 2 9156
Protoss_Templar_Archives 1 9405
Protoss_Dark_Templar 2 10292
10292
