Protoss_Forge 1 3007
Protoss_Photon_Cannon 6 10027
Protoss_Nexus 1 6182
Protoss_Gateway 2 8745
Protoss_Assimilator 2 10578
Protoss_Zealot 9 10462
Protoss_Cybernetics_Core 1 7159
Protoss_Stargate 1 8399
Protoss_Citadel_of_Adun 1 8358
Protoss_Corsair 1 9180
10578
