Protoss_Forge 1 2774
Protoss_Photon_Cannon 3 10249
Protoss_Nexus 1 5842
Protoss_Gateway 4 9915
Protoss_Assimilator 2 6722
Protoss_Cybernetics_Core 1 6273
Protoss_Zealot 2 8480
Protoss_Stargate 1 7518
Protoss_Dragoon 1 7518
Protoss_Citadel_of_Adun 1 8057
Protoss_Corsair 1 8370
Protoss_Templar_Archives 1 9083
Protoss_High_Templar 3 10614
10614
