Protoss_Forge 1 3134
Protoss_Photon_Cannon 1 3990
Protoss_Nexus 1 5405
Protoss_Gateway 2 9817
Protoss_Assimilator 2 6608
Protoss_Zealot 4 8454
Protoss_Cybernetics_Core 1 6601
Protoss_Stargate 1 8042
Protoss_Citadel_of_Adun 1 8187
Protoss_Corsair 2 9780
Protoss_Templar_Archives 1 9291
Protoss_Robotics_Facility 1 9937
Protoss_Dark_Templar 2 10724
10724
