Protoss_Nexus 1 4681
Protoss_Forge 1 3982
Protoss_Gateway 5 10650
Protoss_Photon_Cannon 4 10279
Protoss_Assimilator 2 6496
Protoss_Cybernetics_Core 1 6228
Protoss_Zealot 3 9598
Protoss_Dragoon 1 7088
Protoss_Stargate 1 7526
Protoss_Citadel_of_Adun 1 8156
Protoss_Corsair 1 8248
Protoss_Templar_Archives 1 9188
Protoss_High_Templar 2 10046
Protoss_Dark_Templar 1 10098
10650
