Protoss_Forge 1 2631
Protoss_Nexus 1 4979
Protoss_Gateway 3 8968
Protoss_Assimilator 2 7064
Protoss_Photon_Cannon 8 10538
Protoss_Zealot 2 6028
Protoss_Cybernetics_Core 1 5967
Protoss_Dragoon 1 6804
Protoss_Stargate 1 7208
Protoss_Citadel_of_Adun 1 7655
Protoss_Corsair 2 8864
Protoss_Templar_Archives 1 8704
Protoss_Dark_Templar 1 9550
Protoss_High_Templar 2 10278
10538
