Protoss_Forge 1 2728
Protoss_Photon_Cannon 5 10074
Protoss_Nexus 1 5608
Protoss_Gateway 3 10302
Protoss_Assimilator 2 7408
Protoss_Cybernetics_Core 1 7071
Protoss_Zealot 3 9768
Protoss_Stargate 1 8311
Protoss_Dragoon 1 8088
Protoss_Citadel_of_Adun 1 8929
Protoss_Corsair 1 8992
Protoss_Templar_Archives 1 10634
10634
