Protoss_Forge 1 2603
Protoss_Photon_Cannon 4 9993
Protoss_Nexus 2 9723
Protoss_Gateway 1 5764
Protoss_Assimilator 2 7790
Protoss_Cybernetics_Core 1 6804
Protoss_Zealot 5 9918
Protoss_Stargate 2 9295
Protoss_Corsair 4 10238
10238
