Protoss_Forge 1 2759
Protoss_Photon_Cannon 3 10456
Protoss_Nexus 1 5928
Protoss_Gateway 2 9318
Protoss_Assimilator 2 7370
Protoss_Cybernetics_Core 1 6544
Protoss_Zealot 7 10136
Protoss_Stargate 1 7887
Protoss_Corsair 3 10304
Protoss_Citadel_of_Adun 1 8975
10456
