Protoss_Gateway 1 2709
Protoss_Zealot 8 9538
Protoss_Assimilator 1 3550
Protoss_Cybernetics_Core 1 4359
Protoss_Stargate 1 5710
Protoss_Robotics_Facility 1 6677
Protoss_Corsair 1 6568
Protoss_Forge 1 7125
Protoss_Robotics_Support_Bay 1 7331
Protoss_Photon_Cannon 2 8945
Protoss_Reaver 1 8486
Protoss_Shield_Battery 1 9702
Protoss_Shuttle 1 10762
10762
