Protoss_Nexus 1 4639
Protoss_Gateway 4 10543
Protoss_Forge 1 4073
Protoss_Photon_Cannon 1 4915
Protoss_Assimilator 2 6874
Protoss_Cybernetics_Core 1 5717
Protoss_Zealot 9 10026
Protoss_Dragoon 1 6574
Protoss_Stargate 1 7052
Protoss_Citadel_of_Adun 1 7875
Protoss_Corsair 2 8564
Protoss_Templar_Archives 1 9777
10543
