Protoss_Forge 1 3203
Protoss_Nexus 1 5050
Protoss_Photon_Cannon 3 10650
Protoss_Gateway 3 9097
Protoss_Assimilator 2 7472
Protoss_Cybernetics_Core 1 6207
Protoss_Zealot 7 10014
Protoss_Stargate 1 7342
Protoss_Corsair 4 9834
Protoss_Citadel_of_Adun 1 8530
Protoss_Templar_Archives 1 10491
10650
