Protoss_Forge 1 3022
Protoss_Photon_Cannon 5 9900
Protoss_Nexus 1 6135
Protoss_Gateway 1 5587
Protoss_Assimilator 2 6436
Protoss_Cybernetics_Core 1 6607
Protoss_Zealot 4 9660
Protoss_Stargate 2 8788
Protoss_Dragoon 1 7464
Protoss_Robotics_Facility 1 8413
Protoss_Corsair 4 10252
Protoss_Robotics_Support_Bay 1 9472
Protoss_Reaver 1 10596
10596
