Protoss_Forge 1 2922
Protoss_Photon_Cannon 3 10452
Protoss_Nexus 1 6157
Protoss_Gateway 3 8491
Protoss_Assimilator 2 9332
Protoss_Zealot 9 10548
Protoss_Cybernetics_Core 1 6890
Protoss_Dragoon 1 7722
Protoss_Citadel_of_Adun 1 8057
Protoss_Stargate 2 10528
10548
