Protoss_Forge 1 2835
Protoss_Nexus 1 5348
Protoss_Gateway 1 4883
Protoss_Assimilator 2 6632
Protoss_Photon_Cannon 3 9657
Protoss_Cybernetics_Core 1 6077
Protoss_Zealot 5 9976
Protoss_Stargate 1 7317
Protoss_Dragoon 1 7320
Protoss_Robotics_Facility 1 8271
Protoss_Corsair 4 9980
Protoss_Robotics_Support_Bay 1 8887
Protoss_Reaver 1 10204
10204
