Protoss_Gateway 1 2707
Protoss_Zealot 5 8588
Protoss_Assimilator 1 3608
Protoss_Cybernetics_Core 1 4788
Protoss_Robotics_Facility 1 6147
Protoss_Dragoon 1 6002
Protoss_Stargate 1 6995
Protoss_Shuttle 1 7163
Protoss_Robotics_Support_Bay 1 7073
Protoss_Corsair 4 10416
Protoss_Reaver 1 8308
Protoss_Forge 1 8266
Protoss_Photon_Cannon 3 10372
10416
