Protoss_Forge 2 10578
Protoss_Nexus 1 5017
Protoss_Photon_Cannon 6 9563
Protoss_Gateway 2 8282
Protoss_Assimilator 2 7099
Protoss_Cybernetics_Core 1 6498
Protoss_Zealot 5 9852
Protoss_Stargate 1 7774
Protoss_Citadel_of_Adun 1 7995
Protoss_Corsair 2 9586
Protoss_Templar_Archives 1 9457
Protoss_Dark_Templar 2 10314
10578
