Protoss_Forge 1 3066
Protoss_Photon_Cannon 3 10443
Protoss_Nexus 1 5902
Protoss_Gateway 4 9801
Protoss_Assimilator 2 7306
Protoss_Zealot 3 8556
Protoss_Cybernetics_Core 1 6739
Protoss_Stargate 1 7974
Protoss_Dragoon 1 7808
Protoss_Citadel_of_Adun 1 8339
Protoss_Corsair 2 10120
Protoss_Templar_Archives 1 9357
Protoss_High_Templar 4 10634
10634
