Protoss_Gateway 2 10475
Protoss_Assimilator 1 3126
Protoss_Zealot 6 8878
Protoss_Forge 1 7318
Protoss_Photon_Cannon 1 8180
Protoss_Cybernetics_Core 1 8899
Protoss_Citadel_of_Adun 1 10074
Protoss_Dragoon 1 9933
10475
