Protoss_Gateway 6 10742
Protoss_Zealot 5 10386
Protoss_Nexus 1 5827
Protoss_Assimilator 2 6281
Protoss_Cybernetics_Core 1 5635
Protoss_Stargate 1 6826
Protoss_Citadel_of_Adun 1 7245
Protoss_Forge 1 7414
Protoss_Corsair 1 7522
Protoss_Templar_Archives 1 8255
Protoss_Photon_Cannon 1 8574
Protoss_Dark_Templar 2 9318
Protoss_High_Templar 2 10100
10742
