Protoss_Forge 1 2917
Protoss_Nexus 1 5053
Protoss_Photon_Cannon 3 9410
Protoss_Gateway 2 7810
Protoss_Assimilator 2 9748
Protoss_Cybernetics_Core 1 6480
Protoss_Zealot 9 10412
Protoss_Stargate 1 7688
Protoss_Citadel_of_Adun 1 7991
Protoss_Corsair 2 9952
10412
