Protoss_Gateway 2 3101
Protoss_Zealot 9 9532
Protoss_Assimilator 1 4697
Protoss_Cybernetics_Core 1 6073
Protoss_Stargate 1 7672
Protoss_Dragoon 1 7758
Protoss_Citadel_of_Adun 1 8221
Protoss_Corsair 1 8774
Protoss_Forge 1 9764
9764
