Protoss_Forge 1 3232
Protoss_Nexus 1 5087
Protoss_Photon_Cannon 2 8819
Protoss_Gateway 2 8483
Protoss_Assimilator 2 7032
Protoss_Cybernetics_Core 1 5902
Protoss_Zealot 4 8774
Protoss_Stargate 1 7038
Protoss_Dragoon 1 6804
Protoss_Citadel_of_Adun 1 7423
Protoss_Corsair 1 7950
Protoss_Templar_Archives 1 10320
10320
