Protoss_Forge 1 3125
Protoss_Nexus 1 5223
Protoss_Photon_Cannon 4 10194
Protoss_Gateway 3 9191
Protoss_Assimilator 2 6907
Protoss_Zealot 3 10546
Protoss_Cybernetics_Core 1 7072
Protoss_Stargate 2 8955
Protoss_Citadel_of_Adun 1 8526
Protoss_Corsair 4 10520
Protoss_Templar_Archives 1 10469
10546
