Protoss_Gateway 1 2852
Protoss_Forge 1 3252
Protoss_Assimilator 2 10589
Protoss_Photon_Cannon 2 5238
Protoss_Cybernetics_Core 1 4768
Protoss_Dragoon 1 5622
Protoss_Stargate 1 6300
Protoss_Corsair 1 7236
Protoss_Zealot 2 10102
Protoss_Nexus 1 10065
Protoss_Citadel_of_Adun 1 10271
10589
