Protoss_Gateway 2 10593
Protoss_Assimilator 1 3031
Protoss_Zealot 4 7878
Protoss_Cybernetics_Core 1 4718
Protoss_Dragoon 1 5633
Protoss_Robotics_Facility 1 6773
Protoss_Shuttle 1 7787
Protoss_Robotics_Support_Bay 1 7444
Protoss_Reaver 2 9890
Protoss_Citadel_of_Adun 1 9309
Protoss_Forge 1 9906
Protoss_Templar_Archives 1 10617
10617
