Protoss_Forge 1 2756
Protoss_Photon_Cannon 4 10521
Protoss_Nexus 1 5761
Protoss_Gateway 2 10833
Protoss_Assimilator 2 7554
Protoss_Zealot 4 9550
Protoss_Cybernetics_Core 1 7133
Protoss_Stargate 1 8484
Protoss_Citadel_of_Adun 1 8649
Protoss_Corsair 2 10430
Protoss_Templar_Archives 1 10262
10833
