Protoss_Forge 1 2902
Protoss_Photon_Cannon 5 10581
Protoss_Nexus 1 6096
Protoss_Gateway 2 8603
Protoss_Assimilator 2 8797
Protoss_Cybernetics_Core 1 6558
Protoss_Zealot 9 10136
Protoss_Stargate 1 7725
Protoss_Citadel_of_Adun 1 8233
Protoss_Corsair 4 10538
Protoss_Templar_Archives 1 9906
Protoss_Dragoon 2 10568
10581
