Protoss_Nexus 1 4717
Protoss_Gateway 4 9283
Protoss_Forge 1 4511
Protoss_Assimilator 2 10527
Protoss_Zealot 10 9852
Protoss_Photon_Cannon 5 10430
Protoss_Cybernetics_Core 1 6357
Protoss_Citadel_of_Adun 1 7660
Protoss_Dragoon 1 7824
Protoss_Templar_Archives 1 9629
10527
