Protoss_Forge 1 2573
Protoss_Photon_Cannon 3 4766
Protoss_Nexus 1 6653
Protoss_Gateway 1 6229
Protoss_Zealot 3 10246
Protoss_Assimilator 2 9778
Protoss_Cybernetics_Core 1 9663
Protoss_Stargate 1 10824
10824
