Protoss_Forge 1 2892
Protoss_Photon_Cannon 4 10440
Protoss_Nexus 1 5470
Protoss_Gateway 1 4924
Protoss_Assimilator 2 6335
Protoss_Zealot 5 9748
Protoss_Cybernetics_Core 1 6144
Protoss_Stargate 2 8716
Protoss_Robotics_Facility 1 8292
Protoss_Corsair 4 9627
Protoss_Robotics_Support_Bay 1 9076
Protoss_Reaver 1 10331
10440
