Protoss_Forge 1 2768
Protoss_Photon_Cannon 2 4738
Protoss_Nexus 1 5459
Protoss_Gateway 4 9486
Protoss_Assimilator 2 6934
Protoss_Cybernetics_Core 1 6230
Protoss_Zealot 5 10234
Protoss_Stargate 1 7530
Protoss_Citadel_of_Adun 1 7903
Protoss_Corsair 2 8814
Protoss_Templar_Archives 1 10146
10234
