Protoss_Forge 1 2883
Protoss_Photon_Cannon 2 3864
Protoss_Nexus 1 5751
Protoss_Gateway 3 9240
Protoss_Assimilator 2 8230
Protoss_Zealot 10 10554
Protoss_Cybernetics_Core 1 6731
Protoss_Citadel_of_Adun 1 7965
Protoss_Dragoon 1 7958
Protoss_Stargate 2 10593
10593
