Protoss_Gateway 2 10743
Protoss_Assimilator 1 2837
Protoss_Zealot 9 10136
Protoss_Cybernetics_Core 1 4374
Protoss_Dragoon 1 5232
Protoss_Stargate 1 5864
Protoss_Corsair 5 10292
Protoss_Nexus 1 8508
Protoss_Forge 1 8296
Protoss_Citadel_of_Adun 1 9820
10743
