Protoss_Forge 1 3221
Protoss_Nexus 1 4893
Protoss_Photon_Cannon 4 10736
Protoss_Gateway 4 9966
Protoss_Assimilator 2 6269
Protoss_Cybernetics_Core 1 6153
Protoss_Zealot 1 6466
Protoss_Stargate 1 7367
Protoss_Citadel_of_Adun 1 8085
Protoss_Corsair 3 9258
Protoss_Templar_Archives 1 9147
Protoss_Dark_Templar 2 10062
10736
