Protoss_Forge 1 3287
Protoss_Nexus 1 5199
Protoss_Gateway 2 8081
Protoss_Photon_Cannon 2 10739
Protoss_Assimilator 2 7965
Protoss_Zealot 7 9916
Protoss_Cybernetics_Core 1 6032
Protoss_Stargate 1 7353
Protoss_Citadel_of_Adun 1 7745
Protoss_Corsair 1 8082
Protoss_Templar_Archives 1 9617
Protoss_Dark_Templar 2 10668
10739
