Protoss_Forge 1 3180
Protoss_Photon_Cannon 3 9686
Protoss_Nexus 1 5801
Protoss_Gateway 2 8964
Protoss_Assimilator 2 8660
Protoss_Cybernetics_Core 1 6282
Protoss_Zealot 6 10228
Protoss_Dragoon 1 7256
Protoss_Stargate 1 7878
Protoss_Citadel_of_Adun 1 8463
Protoss_Corsair 4 10568
Protoss_Templar_Archives 1 10061
10568
