Protoss_Forge 1 3075
Protoss_Nexus 1 5229
Protoss_Gateway 4 10237
Protoss_Photon_Cannon 5 10516
Protoss_Assimilator 2 6690
Protoss_Cybernetics_Core 1 6249
Protoss_Zealot 2 8906
Protoss_Stargate 1 7756
Protoss_Citadel_of_Adun 1 8027
Protoss_Corsair 1 8464
Protoss_Templar_Archives 1 9321
10516
