Protoss_Gateway 5 10779
Protoss_Zealot 10 9486
Protoss_Nexus 1 6535
Protoss_Assimilator 2 9007
Protoss_Cybernetics_Core 1 6642
Protoss_Forge 1 6827
Protoss_Stargate 1 7806
Protoss_Photon_Cannon 3 9756
Protoss_Citadel_of_Adun 1 8434
Protoss_Corsair 1 8728
Protoss_Templar_Archives 1 9567
10779
