Protoss_Forge 1 2538
Protoss_Photon_Cannon 4 9742
Protoss_Nexus 1 5863
Protoss_Gateway 3 10571
Protoss_Assimilator 2 7310
Protoss_Cybernetics_Core 1 6609
Protoss_Zealot 4 10164
Protoss_Stargate 1 7976
Protoss_Dragoon 1 7888
Protoss_Citadel_of_Adun 1 8476
Protoss_Corsair 2 9428
Protoss_Templar_Archives 1 9542
Protoss_Dark_Templar 1 10544
10571
