Protoss_Forge 1 3175
Protoss_Photon_Cannon 3 9956
Protoss_Nexus 1 5947
Protoss_Gateway 3 9203
Protoss_Assimilator 2 7741
Protoss_Cybernetics_Core 1 6622
Protoss_Zealot 8 10316
Protoss_Stargate 1 8034
Protoss_Citadel_of_Adun 1 8307
Protoss_Corsair 2 9508
10316
