Protoss_Forge 1 2961
Protoss_Photon_Cannon 4 8968
Protoss_Nexus 1 5617
Protoss_Gateway 1 5701
Protoss_Assimilator 2 6518
Protoss_Cybernetics_Core 1 6687
Protoss_Stargate 1 7907
Protoss_Zealot 3 9308
Protoss_Robotics_Facility 1 8393
Protoss_Corsair 3 10234
Protoss_Robotics_Support_Bay 1 8962
Protoss_Reaver 1 10188
10234
