Protoss_Gateway 1 2922
Protoss_Zealot 10 10368
Protoss_Forge 1 5008
Protoss_Photon_Cannon 4 9605
Protoss_Nexus 1 8690
Protoss_Assimilator 1 9138
Protoss_Cybernetics_Core 1 10527
10527
