Protoss_Assimilator 1 2524
Protoss_Gateway 1 3214
Protoss_Cybernetics_Core 1 4214
Protoss_Robotics_Facility 1 5517
Protoss_Dragoon 1 5093
Protoss_Zealot 2 6368
Protoss_Shuttle 1 6502
Protoss_Robotics_Support_Bay 1 6406
Protoss_Citadel_of_Adun 1 7522
Protoss_Reaver 2 10211
Protoss_Forge 1 7715
Protoss_Photon_Cannon 3 10674
Protoss_Templar_Archives 1 9046
Protoss_High_Templar 1 9883
10674
