Protoss_Forge 1 2886
Protoss_Photon_Cannon 5 10150
Protoss_Nexus 1 5799
Protoss_Gateway 3 8286
Protoss_Assimilator 2 6725
Protoss_Zealot 7 10240
Protoss_Cybernetics_Core 1 6284
Protoss_Citadel_of_Adun 1 7385
Protoss_Dragoon 1 7322
Protoss_Templar_Archives 1 8731
Protoss_High_Templar 4 10616
Protoss_Dark_Templar 1 10416
Protoss_Archon 1 10161
10616
