Protoss_Nexus 1 4875
Protoss_Forge 1 4130
Protoss_Gateway 4 8446
Protoss_Photon_Cannon 7 10294
Protoss_Zealot 10 10006
Protoss_Cybernetics_Core 1 6863
Protoss_Assimilator 2 6930
Protoss_Citadel_of_Adun 1 8166
Protoss_Templar_Archives 1 9279
Protoss_High_Templar 3 10746
10746
