Protoss_Gateway 4 10381
Protoss_Zealot 9 10360
Protoss_Assimilator 1 4727
Protoss_Cybernetics_Core 1 5615
Protoss_Stargate 1 6784
Protoss_Forge 1 6746
Protoss_Citadel_of_Adun 1 7393
Protoss_Photon_Cannon 4 9081
Protoss_Corsair 2 8282
Protoss_Templar_Archives 1 8970
10381
