Protoss_Forge 1 3224
Protoss_Gateway 1 4200
Protoss_Photon_Cannon 2 4374
Protoss_Assimilator 2 9272
Protoss_Cybernetics_Core 1 5558
Protoss_Stargate 1 6740
Protoss_Dragoon 1 6642
Protoss_Nexus 1 8357
Protoss_Corsair 5 10294
Protoss_Citadel_of_Adun 1 8200
Protoss_Zealot 2 10044
Protoss_Templar_Archives 1 9312
Protoss_Dark_Templar 1 10280
10294
