Protoss_Forge 1 2975
Protoss_Photon_Cannon 4 10421
Protoss_Nexus 1 5672
Protoss_Gateway 1 5445
Protoss_Assimilator 2 7520
Protoss_Zealot 3 8706
Protoss_Cybernetics_Core 1 7230
Protoss_Dragoon 1 8104
Protoss_Stargate 2 9809
Protoss_Corsair 3 10516
Protoss_Robotics_Facility 1 10387
10516
