Protoss_Forge 1 3283
Protoss_Nexus 1 5007
Protoss_Gateway 4 10540
Protoss_Photon_Cannon 2 8888
Protoss_Assimilator 2 8475
Protoss_Cybernetics_Core 1 5639
Protoss_Zealot 7 8984
Protoss_Stargate 1 6788
Protoss_Citadel_of_Adun 1 7419
Protoss_Corsair 3 8646
Protoss_Templar_Archives 1 9679
10540
