Protoss_Forge 1 3098
Protoss_Nexus 1 5055
Protoss_Photon_Cannon 5 10280
Protoss_Gateway 1 4713
Protoss_Assimilator 2 8954
Protoss_Cybernetics_Core 1 5697
Protoss_Zealot 5 9468
Protoss_Stargate 1 6834
Protoss_Dragoon 1 7420
Protoss_Corsair 3 10588
Protoss_Robotics_Facility 1 10033
10588
