Protoss_Gateway 2 10502
Protoss_Zealot 10 9886
Protoss_Forge 1 4999
Protoss_Nexus 1 6915
Protoss_Assimilator 2 7804
Protoss_Photon_Cannon 3 10125
Protoss_Cybernetics_Core 1 7015
Protoss_Stargate 1 8702
Protoss_Robotics_Facility 1 9608
Protoss_Corsair 2 10118
Protoss_Robotics_Support_Bay 1 10300
Protoss_Shuttle 1 10787
10787
