Protoss_Nexus 1 4851
Protoss_Gateway 3 10444
Protoss_Assimilator 2 6193
Protoss_Cybernetics_Core 1 5324
Protoss_Stargate 1 6534
Protoss_Robotics_Facility 1 7852
Protoss_Corsair 2 7963
Protoss_Forge 1 7575
Protoss_Dragoon 3 10073
Protoss_Robotics_Support_Bay 1 8441
Protoss_Reaver 2 10633
10633
