Protoss_Forge 1 2788
Protoss_Photon_Cannon 3 9741
Protoss_Nexus 1 5471
Protoss_Gateway 3 9571
Protoss_Assimilator 2 7247
Protoss_Cybernetics_Core 1 6347
Protoss_Zealot 7 10168
Protoss_Stargate 1 7513
Protoss_Citadel_of_Adun 1 7917
Protoss_Corsair 1 8202
Protoss_Templar_Archives 1 9079
Protoss_High_Templar 2 10450
10450
