Protoss_Gateway 2 3326
Protoss_Zealot 12 10250
Protoss_Nexus 2 11153
Protoss_Assimilator 1 6138
Protoss_Cybernetics_Core 1 6885
Protoss_Stargate 1 8141
Protoss_Dragoon 1 8002
Protoss_Forge 1 8428
Protoss_Corsair 2 9458
Protoss_Photon_Cannon 3 10674
11153
