Protoss_Forge 1 3229
Protoss_Nexus 1 5076
Protoss_Photon_Cannon 4 10563
Protoss_Gateway 4 10380
Protoss_Assimilator 2 6699
Protoss_Cybernetics_Core 1 6319
Protoss_Stargate 1 7488
Protoss_Citadel_of_Adun 1 7633
Protoss_Dragoon 1 7880
Protoss_Corsair 2 9346
Protoss_Templar_Archives 1 9001
Protoss_Zealot 2 10242
Protoss_High_Templar 2 10324
10563
