Protoss_Gateway 2 3079
Protoss_Zealot 11 9852
Protoss_Nexus 2 9474
Protoss_Assimilator 2 9935
Protoss_Forge 1 7644
Protoss_Photon_Cannon 2 10420
Protoss_Cybernetics_Core 1 8860
Protoss_Stargate 1 10079
Protoss_Robotics_Facility 1 10973
10973
