Protoss_Forge 1 2880
Protoss_Photon_Cannon 2 4196
Protoss_Nexus 1 6693
Protoss_Gateway 3 7065
Protoss_Zealot 15 10220
Protoss_Assimilator 1 8794
Protoss_Cybernetics_Core 1 9492
10220
