Protoss_Gateway 1 2699
Protoss_Assimilator 2 10228
Protoss_Zealot 5 6760
Protoss_Cybernetics_Core 1 4469
Protoss_Stargate 1 5615
Protoss_Dragoon 1 5404
Protoss_Citadel_of_Adun 1 6187
Protoss_Corsair 3 10530
Protoss_Templar_Archives 1 7283
Protoss_Forge 1 7800
Protoss_Dark_Templar 1 8144
Protoss_Photon_Cannon 2 8711
Protoss_Nexus 1 10163
Protoss_High_Templar 1 10360
10530
