Protoss_Gateway 2 3391
Protoss_Zealot 15 9426
Protoss_Forge 1 6034
Protoss_Nexus 1 8516
Protoss_Photon_Cannon 1 7804
Protoss_Assimilator 2 10353
Protoss_Cybernetics_Core 1 8947
Protoss_Stargate 1 10397
10397
