Protoss_Forge 1 2694
Protoss_Photon_Cannon 2 10320
Protoss_Nexus 1 5567
Protoss_Gateway 4 10008
Protoss_Assimilator 2 7571
Protoss_Cybernetics_Core 1 6116
Protoss_Zealot 8 10592
Protoss_Stargate 1 7276
Protoss_Citadel_of_Adun 1 7695
Protoss_Corsair 4 10196
10592
