Protoss_Gateway 1 2768
Protoss_Zealot 4 6390
Protoss_Assimilator 1 3595
Protoss_Cybernetics_Core 1 4666
Protoss_Robotics_Facility 1 6008
Protoss_Dragoon 1 5788
Protoss_Stargate 1 6739
Protoss_Shuttle 1 7151
Protoss_Robotics_Support_Bay 1 7123
Protoss_Corsair 5 10596
Protoss_Reaver 1 8418
Protoss_Forge 1 8434
Protoss_Photon_Cannon 3 10489
10596
