Protoss_Gateway 4 9145
Protoss_Assimilator 1 3030
Protoss_Zealot 5 6432
Protoss_Cybernetics_Core 1 4353
Protoss_Stargate 1 5490
Protoss_Dragoon 11 10558
Protoss_Scout 1 6771
Protoss_Nexus 1 8391
10558
