Protoss_Gateway 2 6528
Protoss_Assimilator 1 2997
Protoss_Zealot 7 8820
Protoss_Cybernetics_Core 1 4975
Protoss_Dragoon 1 5906
Protoss_Citadel_of_Adun 1 6270
Protoss_Templar_Archives 1 7263
Protoss_High_Templar 4 9770
Protoss_Archon 1 8658
Protoss_Forge 1 9243
Protoss_Nexus 1 10495
Protoss_Photon_Cannon 3 10721
10721
