Protoss_Forge 1 3248
Protoss_Nexus 1 5112
Protoss_Photon_Cannon 3 10248
Protoss_Gateway 2 8789
Protoss_Assimilator 2 6246
Protoss_Cybernetics_Core 1 5877
Protoss_Zealot 6 9676
Protoss_Stargate 1 7140
Protoss_Citadel_of_Adun 1 7726
Protoss_Corsair 2 8596
Protoss_Templar_Archives 1 9607
Protoss_Dark_Templar 2 10558
10558
