Protoss_Gateway 2 9215
Protoss_Zealot 11 10020
Protoss_Nexus 1 5685
Protoss_Assimilator 2 7748
Protoss_Cybernetics_Core 1 6279
Protoss_Forge 1 6763
Protoss_Stargate 1 7538
Protoss_Citadel_of_Adun 1 8329
Protoss_Corsair 2 9074
Protoss_Photon_Cannon 2 10575
Protoss_Templar_Archives 1 10482
10575
