Protoss_Nexus 1 4693
Protoss_Gateway 4 9493
Protoss_Forge 1 4262
Protoss_Assimilator 2 6522
Protoss_Photon_Cannon 2 7754
Protoss_Cybernetics_Core 1 5929
Protoss_Zealot 6 10286
Protoss_Dragoon 1 6790
Protoss_Stargate 1 7262
Protoss_Citadel_of_Adun 1 7757
Protoss_Corsair 1 8070
Protoss_Templar_Archives 1 8847
Protoss_High_Templar 2 9684
Protoss_Archon 1 10213
10286
