Protoss_Forge 1 2735
Protoss_Nexus 1 5226
Protoss_Photon_Cannon 2 10183
Protoss_Gateway 4 8635
Protoss_Assimilator 2 9176
Protoss_Cybernetics_Core 1 6515
Protoss_Zealot 12 10248
Protoss_Citadel_of_Adun 1 7677
Protoss_Stargate 1 9382
Protoss_Templar_Archives 1 10179
Protoss_Corsair 1 10378
10378
