Protoss_Forge 1 3013
Protoss_Photon_Cannon 3 10529
Protoss_Nexus 1 6131
Protoss_Gateway 2 9162
Protoss_Assimilator 2 7167
Protoss_Cybernetics_Core 1 6586
Protoss_Zealot 2 7856
Protoss_Stargate 1 7744
Protoss_Citadel_of_Adun 1 7926
Protoss_Corsair 2 9274
Protoss_Robotics_Facility 1 9275
Protoss_Templar_Archives 1 9313
Protoss_Shuttle 1 10289
Protoss_Dark_Templar 2 10308
10529
