Protoss_Forge 1 2973
Protoss_Photon_Cannon 2 3962
Protoss_Nexus 1 5685
Protoss_Gateway 2 10018
Protoss_Assimilator 2 7108
Protoss_Cybernetics_Core 1 6139
Protoss_Zealot 5 9544
Protoss_Stargate 1 7372
Protoss_Corsair 4 10078
Protoss_Citadel_of_Adun 1 8556
Protoss_Templar_Archives 2 9797
10078
