Protoss_Forge 1 2970
Protoss_Photon_Cannon 6 10128
Protoss_Nexus 1 6079
Protoss_Gateway 3 10153
Protoss_Assimilator 2 7818
Protoss_Cybernetics_Core 1 6801
Protoss_Zealot 4 9278
Protoss_Stargate 1 8134
Protoss_Citadel_of_Adun 1 8718
Protoss_Corsair 3 10236
10236
