Protoss_Gateway 2 6090
Protoss_Assimilator 1 2728
Protoss_Zealot 7 9218
Protoss_Cybernetics_Core 1 4670
Protoss_Dragoon 1 5536
Protoss_Citadel_of_Adun 1 5815
Protoss_Templar_Archives 1 6811
Protoss_High_Templar 2 7650
Protoss_Forge 1 7826
Protoss_Dark_Templar 2 8406
Protoss_Archon 1 8006
Protoss_Photon_Cannon 2 8940
Protoss_Nexus 1 11565
11565
