Protoss_Forge 1 2958
Protoss_Nexus 1 4983
Protoss_Photon_Cannon 2 9164
Protoss_Gateway 5 10271
Protoss_Assimilator 2 6362
Protoss_Cybernetics_Core 1 5941
Protoss_Zealot 3 8716
Protoss_Stargate 1 7150
Protoss_Dragoon 1 7092
Protoss_Citadel_of_Adun 1 7800
Protoss_Corsair 2 8534
Protoss_Templar_Archives 1 8815
Protoss_Dark_Templar 1 9676
10271
