Protoss_Gateway 2 8844
Protoss_Assimilator 1 2812
Protoss_Cybernetics_Core 1 3869
Protoss_Zealot 11 9742
Protoss_Stargate 1 5432
Protoss_Corsair 3 7448
Protoss_Citadel_of_Adun 1 8481
Protoss_Robotics_Facility 1 9684
Protoss_Shuttle 1 10695
Protoss_Robotics_Support_Bay 1 10423
10695
