Protoss_Forge 1 2793
Protoss_Photon_Cannon 4 10316
Protoss_Nexus 1 5454
Protoss_Gateway 2 9423
Protoss_Assimilator 2 8073
Protoss_Cybernetics_Core 1 6735
Protoss_Zealot 4 9984
Protoss_Stargate 1 7963
Protoss_Dragoon 1 8104
Protoss_Citadel_of_Adun 1 8643
Protoss_Corsair 3 10018
Protoss_Templar_Archives 1 10519
10519
