Protoss_Gateway 2 3231
Protoss_Zealot 9 8436
Protoss_Assimilator 1 4784
Protoss_Cybernetics_Core 1 5605
Protoss_Stargate 1 6761
Protoss_Dragoon 1 6922
Protoss_Citadel_of_Adun 1 7350
Protoss_Corsair 1 7472
Protoss_Templar_Archives 1 9503
Protoss_Forge 1 9354
9503
