Protoss_Gateway 1 2827
Protoss_Assimilator 1 3007
Protoss_Zealot 3 4807
Protoss_Cybernetics_Core 1 4761
Protoss_Dragoon 6 10708
Protoss_Robotics_Facility 1 6760
Protoss_Shuttle 1 7747
Protoss_Robotics_Support_Bay 1 7745
Protoss_Reaver 2 10156
Protoss_Forge 1 8572
10708
