Protoss_Forge 1 3249
Protoss_Nexus 1 5216
Protoss_Gateway 4 9715
Protoss_Assimilator 2 8074
Protoss_Photon_Cannon 5 10711
Protoss_Cybernetics_Core 1 6152
Protoss_Zealot 9 9652
Protoss_Dragoon 1 6990
Protoss_Citadel_of_Adun 1 7320
Protoss_Templar_Archives 1 9280
Protoss_Ground_Weapons_1 1 9557
Protoss_Dark_Templar 2 10404
Protoss_High_Templar 2 10688
10711
