Protoss_Gateway 1 2755
Protoss_Zealot 5 7574
Protoss_Assimilator 1 3683
Protoss_Cybernetics_Core 1 4409
Protoss_Stargate 1 5679
Protoss_Dragoon 1 5586
Protoss_Forge 1 5955
Protoss_Corsair 3 10114
Protoss_Photon_Cannon 5 10570
Protoss_Nexus 1 9473
Protoss_Robotics_Facility 1 9505
10570
