Protoss_Forge 1 2567
Protoss_Photon_Cannon 3 7536
Protoss_Nexus 1 6105
Protoss_Gateway 3 9583
Protoss_Assimilator 2 8276
Protoss_Zealot 7 10364
Protoss_Cybernetics_Core 1 6848
Protoss_Stargate 1 8152
Protoss_Dragoon 1 8066
Protoss_Corsair 2 9576
Protoss_Citadel_of_Adun 1 10125
10364
