Protoss_Forge 2 3200
Protoss_Photon_Cannon 3 5590
Protoss_Gateway 2 9420
Protoss_Zealot 2 8440
Protoss_Nexus 1 8168
Protoss_Assimilator 2 8298
Protoss_Cybernetics_Core 1 7823
Protoss_Stargate 1 9344
Protoss_Citadel_of_Adun 1 9704
Protoss_Corsair 1 10030
Protoss_Templar_Archives 1 10811
10811
