Protoss_Forge 1 2820
Protoss_Photon_Cannon 4 9200
Protoss_Nexus 1 5903
Protoss_Gateway 3 10830
Protoss_Assimilator 2 8244
Protoss_Cybernetics_Core 1 6463
Protoss_Zealot 4 9600
Protoss_Stargate 1 7746
Protoss_Citadel_of_Adun 1 7723
Protoss_Corsair 3 10546
Protoss_Templar_Archives 1 9467
Protoss_Dark_Templar 1 10656
10830
