Protoss_Forge 2 10260
Protoss_Photon_Cannon 7 10213
Protoss_Nexus 1 5343
Protoss_Gateway 2 8980
Protoss_Assimilator 2 6408
Protoss_Cybernetics_Core 1 5739
Protoss_Zealot 10 10352
Protoss_Stargate 1 7058
Protoss_Corsair 2 8438
Protoss_Citadel_of_Adun 1 8201
10352
