Protoss_Gateway 2 6742
Protoss_Assimilator 1 2786
Protoss_Zealot 4 10016
Protoss_Cybernetics_Core 1 4079
Protoss_Stargate 1 5301
Protoss_Dragoon 7 9188
Protoss_Corsair 5 10088
Protoss_Citadel_of_Adun 1 9907
10088
