Protoss_Gateway 2 8740
Protoss_Assimilator 2 9218
Protoss_Cybernetics_Core 1 3981
Protoss_Zealot 2 4786
Protoss_Stargate 1 5183
Protoss_Citadel_of_Adun 1 5618
Protoss_Dragoon 2 6340
Protoss_Corsair 1 6008
Protoss_Templar_Archives 1 6967
Protoss_Nexus 1 8747
Protoss_Dark_Templar 2 8658
Protoss_Forge 1 8830
Protoss_High_Templar 2 9664
Protoss_Photon_Cannon 2 10241
Protoss_Archon 1 10122
10241
