Protoss_Gateway 2 10318
Protoss_Zealot 7 10068
Protoss_Nexus 1 5585
Protoss_Assimilator 2 6076
Protoss_Cybernetics_Core 1 5641
Protoss_Stargate 1 6848
Protoss_Dragoon 1 7016
Protoss_Forge 1 7214
Protoss_Corsair 4 10144
Protoss_Citadel_of_Adun 1 8193
Protoss_Photon_Cannon 3 10180
10318
