Protoss_Nexus 1 4615
Protoss_Gateway 2 7994
Protoss_Assimilator 2 6180
Protoss_Zealot 10 9476
Protoss_Cybernetics_Core 1 5874
Protoss_Stargate 1 7014
Protoss_Citadel_of_Adun 1 7230
Protoss_Corsair 1 7758
Protoss_Templar_Archives 1 8770
Protoss_Forge 1 9062
Protoss_High_Templar 2 10228
Protoss_Photon_Cannon 3 10697
10697
