Protoss_Forge 1 3244
Protoss_Photon_Cannon 4 10728
Protoss_Nexus 1 5866
Protoss_Gateway 2 9039
Protoss_Assimilator 2 7550
Protoss_Cybernetics_Core 1 6334
Protoss_Zealot 6 10122
Protoss_Stargate 1 7791
Protoss_Citadel_of_Adun 1 8370
Protoss_Corsair 1 8490
Protoss_Templar_Archives 1 10012
10728
