Protoss_Forge 1 3318
Protoss_Nexus 1 5041
Protoss_Photon_Cannon 2 10618
Protoss_Gateway 4 8920
Protoss_Zealot 5 10078
Protoss_Assimilator 2 7416
Protoss_Cybernetics_Core 2 7243
Protoss_Stargate 1 8030
Protoss_Citadel_of_Adun 1 8640
Protoss_Corsair 2 9496
Protoss_Templar_Archives 1 9923
10618
