Protoss_Forge 1 2616
Protoss_Nexus 1 5238
Protoss_Gateway 3 9766
Protoss_Assimilator 2 7772
Protoss_Photon_Cannon 1 5262
Protoss_Cybernetics_Core 1 6143
Protoss_Zealot 6 9956
Protoss_Stargate 1 7290
Protoss_Corsair 4 9830
Protoss_Citadel_of_Adun 1 8445
Protoss_Templar_Archives 1 9506
9956
