Protoss_Forge 1 2484
Protoss_Nexus 1 4941
Protoss_Photon_Cannon 3 10231
Protoss_Gateway 2 8684
Protoss_Assimilator 2 6725
Protoss_Zealot 2 7312
Protoss_Cybernetics_Core 1 6267
Protoss_Stargate 1 7517
Protoss_Citadel_of_Adun 1 7923
Protoss_Corsair 3 9556
Protoss_Templar_Archives 1 9009
Protoss_Dark_Templar 2 9848
Protoss_High_Templar 2 10676
10676
