Protoss_Forge 1 2701
Protoss_Nexus 1 4975
Protoss_Photon_Cannon 1 4238
Protoss_Gateway 4 10060
Protoss_Assimilator 2 7266
Protoss_Zealot 11 10579
Protoss_Cybernetics_Core 1 6706
Protoss_Stargate 1 7880
Protoss_Citadel_of_Adun 1 8153
Protoss_Corsair 1 8562
10579
