Protoss_Forge 1 2516
Protoss_Nexus 1 5241
Protoss_Photon_Cannon 3 9698
Protoss_Gateway 2 9182
Protoss_Assimilator 3 8400
Protoss_Cybernetics_Core 1 6121
Protoss_Zealot 6 10112
Protoss_Dragoon 1 7016
Protoss_Stargate 1 7322
Protoss_Citadel_of_Adun 1 7503
Protoss_Corsair 4 9892
Protoss_Templar_Archives 1 9070
Protoss_Dark_Templar 1 10184
10184
