Protoss_Gateway 2 2977
Protoss_Zealot 14 10418
Protoss_Assimilator 1 4310
Protoss_Cybernetics_Core 1 6496
Protoss_Stargate 1 7685
Protoss_Citadel_of_Adun 1 8433
Protoss_Corsair 2 8988
Protoss_Forge 1 8785
Protoss_Templar_Archives 1 9527
Protoss_Dark_Templar 1 10412
10418
