Protoss_Forge 1 2890
Protoss_Photon_Cannon 3 10331
Protoss_Nexus 1 5927
Protoss_Gateway 1 5288
Protoss_Assimilator 2 6512
Protoss_Cybernetics_Core 1 6329
Protoss_Zealot 4 9290
Protoss_Stargate 2 8488
Protoss_Citadel_of_Adun 1 7868
Protoss_Corsair 7 10552
Protoss_Templar_Archives 1 9923
10552
