Protoss_Gateway 2 3369
Protoss_Zealot 9 6523
Protoss_Nexus 1 8620
Protoss_Assimilator 1 7808
Protoss_Forge 1 8130
Protoss_Cybernetics_Core 1 9373
Protoss_Photon_Cannon 1 9260
9373
