Protoss_Forge 1 2858
Protoss_Photon_Cannon 5 10481
Protoss_Nexus 1 5799
Protoss_Gateway 3 9686
Protoss_Assimilator 2 7721
Protoss_Cybernetics_Core 1 6735
Protoss_Zealot 7 10400
Protoss_Stargate 1 8028
Protoss_Citadel_of_Adun 1 8323
Protoss_Corsair 2 9428
Protoss_Templar_Archives 1 10180
10481
