Protoss_Forge 1 2859
Protoss_Nexus 1 5151
Protoss_Photon_Cannon 3 10368
Protoss_Gateway 3 8489
Protoss_Assimilator 2 7380
Protoss_Cybernetics_Core 1 5987
Protoss_Stargate 1 7162
Protoss_Zealot 4 9166
Protoss_Citadel_of_Adun 1 7427
Protoss_Corsair 2 9086
Protoss_Templar_Archives 1 9080
Protoss_High_Templar 2 10024
Protoss_Dark_Templar 1 10598
10598
