Protoss_Gateway 1 2745
Protoss_Zealot 4 6949
Protoss_Assimilator 2 10039
Protoss_Cybernetics_Core 1 4472
Protoss_Stargate 1 5632
Protoss_Dragoon 1 5500
Protoss_Forge 1 5960
Protoss_Corsair 4 10456
Protoss_Photon_Cannon 5 10691
Protoss_Nexus 1 9467
Protoss_Robotics_Facility 1 9373
Protoss_Robotics_Support_Bay 1 10038
10691
