Protoss_Nexus 1 4829
Protoss_Forge 1 3860
Protoss_Photon_Cannon 2 4803
Protoss_Gateway 4 9723
Protoss_Assimilator 2 7191
Protoss_Cybernetics_Core 1 6811
Protoss_Stargate 1 7948
Protoss_Zealot 10 10572
Protoss_Citadel_of_Adun 1 8381
Protoss_Corsair 1 8686
Protoss_Templar_Archives 1 10405
10572
