Protoss_Forge 1 3079
Protoss_Photon_Cannon 3 10631
Protoss_Nexus 1 5423
Protoss_Gateway 2 10277
Protoss_Assimilator 2 8806
Protoss_Cybernetics_Core 1 6962
Protoss_Zealot 2 8732
Protoss_Stargate 1 8143
Protoss_Dragoon 1 7900
Protoss_Corsair 1 8836
Protoss_Citadel_of_Adun 1 9281
Protoss_Templar_Archives 1 10364
10631
