Protoss_Forge 2 8510
Protoss_Nexus 1 5097
Protoss_Photon_Cannon 4 10505
Protoss_Gateway 3 10856
Protoss_Assimilator 2 9120
Protoss_Zealot 4 8516
Protoss_Cybernetics_Core 1 6481
Protoss_Stargate 1 7903
Protoss_Corsair 3 10226
Protoss_Citadel_of_Adun 1 9279
Protoss_Templar_Archives 1 10461
10856
