Protoss_Forge 1 3221
Protoss_Photon_Cannon 3 10564
Protoss_Nexus 1 5871
Protoss_Gateway 3 9441
Protoss_Assimilator 2 9341
Protoss_Cybernetics_Core 1 6417
Protoss_Zealot 8 10450
Protoss_Stargate 1 7610
Protoss_Dragoon 1 7706
Protoss_Citadel_of_Adun 1 8322
Protoss_Corsair 2 9740
10564
