Protoss_Forge 1 2889
Protoss_Photon_Cannon 3 9655
Protoss_Nexus 1 5993
Protoss_Gateway 3 9471
Protoss_Assimilator 2 6861
Protoss_Cybernetics_Core 1 6485
Protoss_Zealot 4 9674
Protoss_Stargate 1 7656
Protoss_Citadel_of_Adun 1 8085
Protoss_Corsair 2 9386
Protoss_Templar_Archives 1 9079
Protoss_Dark_Templar 1 9950
9950
