Protoss_Forge 1 2846
Protoss_Nexus 2 10049
Protoss_Photon_Cannon 3 10483
Protoss_Gateway 1 4876
Protoss_Assimilator 2 7299
Protoss_Zealot 2 7660
Protoss_Cybernetics_Core 1 7040
Protoss_Robotics_Facility 1 8401
Protoss_Stargate 1 8359
Protoss_Corsair 2 9892
Protoss_Robotics_Support_Bay 1 9128
Protoss_Reaver 1 10392
10483
