Protoss_Forge 1 3120
Protoss_Photon_Cannon 3 9762
Protoss_Nexus 1 6025
Protoss_Gateway 3 8555
Protoss_Assimilator 2 7378
Protoss_Zealot 5 8824
Protoss_Cybernetics_Core 1 6585
Protoss_Citadel_of_Adun 1 7599
Protoss_Stargate 3 10596
Protoss_Dragoon 1 9628
Protoss_Corsair 2 10408
10596
