Protoss_Forge 1 3191
Protoss_Nexus 1 5075
Protoss_Photon_Cannon 3 10602
Protoss_Gateway 1 5247
Protoss_Assimilator 2 7072
Protoss_Cybernetics_Core 1 6305
Protoss_Zealot 6 9739
Protoss_Stargate 1 7487
Protoss_Robotics_Facility 1 8721
Protoss_Corsair 4 10283
Protoss_Robotics_Support_Bay 1 9267
Protoss_Shuttle 1 9909
10602
