Protoss_Forge 1 2936
Protoss_Nexus 1 4951
Protoss_Photon_Cannon 5 7502
Protoss_Gateway 1 5665
Protoss_Zealot 5 10141
Protoss_Cybernetics_Core 1 8592
Protoss_Assimilator 2 8564
Protoss_Stargate 2 10556
10556
