Protoss_Forge 1 3048
Protoss_Photon_Cannon 3 10482
Protoss_Nexus 1 5645
Protoss_Gateway 4 10324
Protoss_Assimilator 2 10416
Protoss_Cybernetics_Core 1 6319
Protoss_Zealot 9 10308
Protoss_Stargate 1 7555
Protoss_Citadel_of_Adun 1 8299
Protoss_Corsair 1 8320
Protoss_Templar_Archives 1 10277
10482
