Protoss_Forge 1 3185
Protoss_Nexus 1 5028
Protoss_Photon_Cannon 6 10722
Protoss_Gateway 2 9541
Protoss_Assimilator 2 7519
Protoss_Zealot 4 9688
Protoss_Cybernetics_Core 1 6870
Protoss_Stargate 1 8040
Protoss_Citadel_of_Adun 1 8525
Protoss_Corsair 3 10240
Protoss_Dragoon 2 10522
10722
