Protoss_Forge 1 3428
Protoss_Photon_Cannon 3 10048
Protoss_Nexus 1 5981
Protoss_Gateway 2 9581
Protoss_Assimilator 2 6889
Protoss_Cybernetics_Core 1 6508
Protoss_Zealot 7 10264
Protoss_Stargate 1 7720
Protoss_Citadel_of_Adun 1 8199
Protoss_Corsair 2 9690
Protoss_Templar_Archives 1 10841
10841
