Protoss_Forge 1 2880
Protoss_Photon_Cannon 4 9651
Protoss_Nexus 1 5382
Protoss_Gateway 2 9146
Protoss_Assimilator 2 7336
Protoss_Zealot 9 10592
Protoss_Cybernetics_Core 1 6380
Protoss_Stargate 1 7551
Protoss_Citadel_of_Adun 1 8105
Protoss_Corsair 3 10006
10592
