Protoss_Gateway 2 3148
Protoss_Zealot 9 7248
Protoss_Nexus 2 11046
Protoss_Assimilator 1 6078
Protoss_Cybernetics_Core 1 7045
Protoss_Stargate 1 8612
Protoss_Citadel_of_Adun 1 8584
Protoss_Forge 1 8772
Protoss_Corsair 2 10324
Protoss_Templar_Archives 1 9812
Protoss_Photon_Cannon 2 10272
Protoss_Dark_Templar 1 10740
11046
