Protoss_Forge 1 3085
Protoss_Nexus 1 4911
Protoss_Photon_Cannon 4 10596
Protoss_Gateway 2 10131
Protoss_Assimilator 3 7554
Protoss_Cybernetics_Core 1 6272
Protoss_Stargate 1 7420
Protoss_Zealot 5 10360
Protoss_Corsair 5 10586
Protoss_Citadel_of_Adun 1 8841
10596
