Protoss_Forge 1 2722
Protoss_Nexus 1 5115
Protoss_Photon_Cannon 2 8879
Protoss_Gateway 2 9472
Protoss_Assimilator 2 8410
Protoss_Zealot 4 10392
Protoss_Cybernetics_Core 1 6775
Protoss_Stargate 1 8015
Protoss_Dragoon 2 9728
Protoss_Citadel_of_Adun 1 8306
Protoss_Corsair 3 10347
Protoss_Templar_Archives 1 9865
10392
