Protoss_Gateway 3 10475
Protoss_Zealot 8 9117
Protoss_Forge 2 8136
Protoss_Photon_Cannon 4 9032
Protoss_Assimilator 1 7724
Protoss_Cybernetics_Core 1 9889
Protoss_Dragoon 1 10726
10726
