Protoss_Gateway 2 9201
Protoss_Assimilator 2 9354
Protoss_Zealot 4 6531
Protoss_Cybernetics_Core 1 4255
Protoss_Stargate 1 5446
Protoss_Dragoon 1 5244
Protoss_Citadel_of_Adun 1 6242
Protoss_Corsair 3 10464
Protoss_Templar_Archives 1 7481
Protoss_Forge 1 7324
Protoss_Nexus 1 9365
Protoss_Dark_Templar 1 8470
Protoss_Photon_Cannon 2 9236
Protoss_High_Templar 3 10388
10464
