Protoss_Forge 1 2731
Protoss_Photon_Cannon 4 10479
Protoss_Nexus 1 5879
Protoss_Gateway 2 8704
Protoss_Assimilator 2 7112
Protoss_Cybernetics_Core 1 6280
Protoss_Zealot 4 9042
Protoss_Stargate 1 7467
Protoss_Citadel_of_Adun 1 7989
Protoss_Corsair 2 9440
Protoss_Templar_Archives 1 9123
Protoss_High_Templar 2 10338
10479
