Protoss_Nexus 1 4771
Protoss_Forge 1 3878
Protoss_Gateway 4 10882
Protoss_Photon_Cannon 3 10030
Protoss_Assimilator 2 6922
Protoss_Zealot 10 10102
Protoss_Cybernetics_Core 1 6515
Protoss_Stargate 1 7725
Protoss_Citadel_of_Adun 1 7949
Protoss_Corsair 1 8528
Protoss_Templar_Archives 1 9745
Protoss_High_Templar 2 10726
10882
