Protoss_Gateway 2 10316
Protoss_Zealot 9 9494
Protoss_Nexus 1 5923
Protoss_Forge 1 5186
Protoss_Assimilator 2 9012
Protoss_Photon_Cannon 4 10468
Protoss_Cybernetics_Core 1 8427
Protoss_Stargate 1 9562
Protoss_Citadel_of_Adun 1 9719
Protoss_Corsair 1 10250
Protoss_Templar_Archives 1 10757
10757
