Protoss_Forge 1 3213
Protoss_Photon_Cannon 2 4101
Protoss_Nexus 1 6023
Protoss_Gateway 2 8553
Protoss_Assimilator 2 7261
Protoss_Zealot 8 10560
Protoss_Cybernetics_Core 1 6669
Protoss_Stargate 1 7837
Protoss_Dragoon 1 7636
Protoss_Citadel_of_Adun 1 8412
Protoss_Corsair 2 9332
Protoss_Templar_Archives 1 10009
10560
