Protoss_Forge 1 3438
Protoss_Photon_Cannon 4 10188
Protoss_Nexus 1 5897
Protoss_Gateway 2 8429
Protoss_Assimilator 2 7239
Protoss_Cybernetics_Core 1 6603
Protoss_Zealot 8 10570
Protoss_Stargate 1 7881
Protoss_Citadel_of_Adun 1 7976
Protoss_Corsair 3 10522
Protoss_Templar_Archives 1 10474
10570
