Protoss_Forge 1 2606
Protoss_Nexus 1 5163
Protoss_Photon_Cannon 3 10136
Protoss_Gateway 2 7757
Protoss_Assimilator 2 7898
Protoss_Zealot 11 10408
Protoss_Cybernetics_Core 1 6541
Protoss_Citadel_of_Adun 1 7529
Protoss_Stargate 2 9509
Protoss_Templar_Archives 1 9865
10408
