Protoss_Gateway 2 3349
Protoss_Zealot 12 7620
Protoss_Assimilator 1 5078
Protoss_Cybernetics_Core 1 7128
Protoss_Stargate 2 8822
Protoss_Dragoon 2 8372
Protoss_Forge 1 8557
Protoss_Corsair 4 10438
Protoss_Photon_Cannon 2 10396
10438
