Protoss_Forge 1 3333
Protoss_Nexus 1 4919
Protoss_Gateway 4 8050
Protoss_Assimilator 2 7894
Protoss_Photon_Cannon 4 10600
Protoss_Cybernetics_Core 1 5589
Protoss_Zealot 11 10363
Protoss_Citadel_of_Adun 1 7485
Protoss_Dragoon 1 9312
Protoss_Templar_Archives 1 9714
Protoss_Ground_Weapons_1 1 9429
10600
