Protoss_Forge 1 3310
Protoss_Nexus 1 4999
Protoss_Photon_Cannon 3 8472
Protoss_Gateway 6 10774
Protoss_Assimilator 2 6625
Protoss_Cybernetics_Core 1 6251
Protoss_Zealot 8 10570
Protoss_Stargate 1 7408
Protoss_Citadel_of_Adun 1 8082
Protoss_Corsair 2 9368
10774
