Protoss_Nexus 1 4817
Protoss_Forge 1 3934
Protoss_Photon_Cannon 4 10211
Protoss_Gateway 2 9381
Protoss_Assimilator 2 8081
Protoss_Cybernetics_Core 1 6642
Protoss_Zealot 6 10092
Protoss_Stargate 1 8062
Protoss_Citadel_of_Adun 1 8280
Protoss_Corsair 1 8760
Protoss_Templar_Archives 1 10751
10751
