Protoss_Forge 1 2833
Protoss_Nexus 1 5177
Protoss_Photon_Cannon 1 4216
Protoss_Gateway 6 10544
Protoss_Assimilator 2 6370
Protoss_Cybernetics_Core 1 6002
Protoss_Zealot 4 8306
Protoss_Citadel_of_Adun 1 7119
Protoss_Templar_Archives 1 8459
Protoss_Dark_Templar 4 10158
Protoss_High_Templar 1 10574
10574
