Protoss_Forge 1 3064
Protoss_Photon_Cannon 2 10438
Protoss_Nexus 1 5609
Protoss_Gateway 4 10470
Protoss_Assimilator 2 7199
Protoss_Zealot 4 8728
Protoss_Cybernetics_Core 1 6907
Protoss_Citadel_of_Adun 1 8098
Protoss_Templar_Archives 1 9143
Protoss_Dark_Templar 4 10736
10736
