Protoss_Forge 1 2710
Protoss_Nexus 1 4943
Protoss_Photon_Cannon 2 9143
Protoss_Gateway 5 10578
Protoss_Assimilator 2 8333
Protoss_Zealot 6 10480
Protoss_Cybernetics_Core 1 6419
Protoss_Stargate 1 7619
Protoss_Citadel_of_Adun 1 8101
Protoss_Corsair 1 8338
Protoss_Templar_Archives 1 9356
Protoss_Dark_Templar 1 10466
10578
