Protoss_Forge 2 9929
Protoss_Nexus 1 5095
Protoss_Photon_Cannon 2 4684
Protoss_Gateway 3 8957
Protoss_Assimilator 2 7196
Protoss_Cybernetics_Core 1 6296
Protoss_Zealot 10 10476
Protoss_Stargate 1 7476
Protoss_Citadel_of_Adun 1 8239
Protoss_Corsair 2 9272
Protoss_Templar_Archives 1 10300
10476
