Protoss_Gateway 2 3424
Protoss_Zealot 15 10502
Protoss_Assimilator 1 7068
Protoss_Nexus 1 8443
Protoss_Forge 1 7705
Protoss_Cybernetics_Core 1 8321
Protoss_Photon_Cannon 4 9949
Protoss_Stargate 1 10383
10502
