Protoss_Forge 2 9152
Protoss_Nexus 1 4929
Protoss_Photon_Cannon 2 7607
Protoss_Gateway 2 9745
Protoss_Assimilator 2 6636
Protoss_Cybernetics_Core 1 5725
Protoss_Zealot 4 10200
Protoss_Stargate 1 6868
Protoss_Corsair 5 10238
Protoss_Citadel_of_Adun 1 8732
Protoss_Templar_Archives 1 9923
Protoss_Robotics_Facility 1 11118
11118
