Protoss_Forge 1 3041
Protoss_Photon_Cannon 5 10026
Protoss_Nexus 1 6641
Protoss_Gateway 2 9120
Protoss_Assimilator 2 8082
Protoss_Cybernetics_Core 1 7102
Protoss_Zealot 7 10514
Protoss_Stargate 1 8268
Protoss_Citadel_of_Adun 1 8608
Protoss_Corsair 2 10344
Protoss_Templar_Archives 1 10482
10514
