Protoss_Gateway 2 7503
Protoss_Assimilator 1 3205
Protoss_Zealot 3 4820
Protoss_Cybernetics_Core 1 4822
Protoss_Dragoon 9 10600
Protoss_Stargate 1 6340
Protoss_Corsair 4 9748
10600
