Protoss_Forge 1 3124
Protoss_Nexus 1 4953
Protoss_Photon_Cannon 2 9993
Protoss_Gateway 2 8843
Protoss_Assimilator 2 6649
Protoss_Cybernetics_Core 1 5741
Protoss_Zealot 4 8056
Protoss_Stargate 1 6894
Protoss_Citadel_of_Adun 1 7341
Protoss_Corsair 4 10488
Protoss_Templar_Archives 1 8424
Protoss_Dark_Templar 2 9844
Protoss_High_Templar 1 10596
10596
