Protoss_Forge 1 2840
Protoss_Photon_Cannon 2 3899
Protoss_Nexus 1 5781
Protoss_Assimilator 3 7541
Protoss_Gateway 4 8985
Protoss_Cybernetics_Core 1 6512
Protoss_Zealot 8 9802
Protoss_Citadel_of_Adun 1 7569
Protoss_Templar_Archives 1 8626
Protoss_High_Templar 4 10631
10631
