Protoss_Forge 1 3294
Protoss_Nexus 1 5059
Protoss_Photon_Cannon 2 4630
Protoss_Gateway 4 8785
Protoss_Assimilator 2 9871
Protoss_Cybernetics_Core 1 6507
Protoss_Zealot 15 10486
Protoss_Stargate 1 7661
Protoss_Citadel_of_Adun 1 7953
Protoss_Corsair 1 8350
Protoss_Templar_Archives 1 10437
10486
