Protoss_Forge 1 2670
Protoss_Photon_Cannon 6 10738
Protoss_Nexus 1 6057
Protoss_Gateway 1 5481
Protoss_Assimilator 2 7777
Protoss_Zealot 3 10112
Protoss_Cybernetics_Core 1 6741
Protoss_Stargate 1 7953
Protoss_Corsair 2 9874
Protoss_Robotics_Facility 1 9752
Protoss_Robotics_Support_Bay 1 10307
10738
