Protoss_Forge 1 2877
Protoss_Photon_Cannon 2 4063
Protoss_Nexus 1 6019
Protoss_Gateway 3 10372
Protoss_Assimilator 2 7836
Protoss_Cybernetics_Core 1 6395
Protoss_Zealot 7 10186
Protoss_Stargate 1 7747
Protoss_Citadel_of_Adun 1 8491
Protoss_Corsair 3 10072
Protoss_Ground_Weapons_1 1 9955
10372
