Protoss_Forge 1 2914
Protoss_Nexus 1 5077
Protoss_Photon_Cannon 3 8992
Protoss_Assimilator 2 7622
Protoss_Gateway 3 10239
Protoss_Cybernetics_Core 1 6803
Protoss_Zealot 7 10444
Protoss_Stargate 1 7987
Protoss_Citadel_of_Adun 1 8582
Protoss_Corsair 3 10260
Protoss_Templar_Archives 1 10449
10449
