Protoss_Forge 1 2721
Protoss_Photon_Cannon 5 10618
Protoss_Nexus 1 5604
Protoss_Gateway 4 10894
Protoss_Assimilator 2 7340
Protoss_Cybernetics_Core 1 5968
Protoss_Zealot 8 10430
Protoss_Stargate 1 7230
Protoss_Citadel_of_Adun 1 7946
Protoss_Corsair 2 8698
Protoss_Templar_Archives 1 9718
10894
