Protoss_Gateway 3 9970
Protoss_Assimilator 1 2895
Protoss_Zealot 6 8440
Protoss_Cybernetics_Core 1 4453
Protoss_Stargate 1 5643
Protoss_Citadel_of_Adun 1 6159
Protoss_Corsair 1 6660
Protoss_Dragoon 1 6874
Protoss_Templar_Archives 1 8262
Protoss_Dark_Templar 2 9340
Protoss_Forge 1 9752
Protoss_High_Templar 1 10458
10458
