Protoss_Forge 1 2772
Protoss_Nexus 1 5098
Protoss_Photon_Cannon 1 4332
Protoss_Gateway 4 10434
Protoss_Assimilator 2 7697
Protoss_Zealot 8 10180
Protoss_Cybernetics_Core 1 6608
Protoss_Dragoon 1 7438
Protoss_Stargate 1 7783
Protoss_Citadel_of_Adun 1 8496
Protoss_Corsair 1 8562
Protoss_Templar_Archives 1 9835
Protoss_Dark_Templar 1 10682
10682
