Protoss_Forge 1 2736
Protoss_Photon_Cannon 5 10253
Protoss_Nexus 1 5719
Protoss_Gateway 1 5171
Protoss_Assimilator 2 7762
Protoss_Zealot 6 10314
Protoss_Cybernetics_Core 2 7541
Protoss_Dragoon 1 8428
Protoss_Stargate 1 8998
Protoss_Citadel_of_Adun 1 9711
Protoss_Corsair 2 10314
10314
