Protoss_Forge 1 3038
Protoss_Nexus 1 5151
Protoss_Photon_Cannon 2 10384
Protoss_Gateway 3 8893
Protoss_Assimilator 2 7791
Protoss_Cybernetics_Core 1 5915
Protoss_Zealot 11 10484
Protoss_Stargate 1 7128
Protoss_Dragoon 1 7124
Protoss_Citadel_of_Adun 1 7555
Protoss_Corsair 2 8742
10484
