Protoss_Gateway 2 3309
Protoss_Zealot 7 8662
Protoss_Nexus 2 11461
Protoss_Assimilator 1 5186
Protoss_Cybernetics_Core 1 6107
Protoss_Stargate 1 7450
Protoss_Dragoon 1 7388
Protoss_Corsair 2 8800
Protoss_Forge 1 8980
Protoss_Photon_Cannon 2 9932
Protoss_Citadel_of_Adun 1 10038
11461
