Protoss_Forge 1 3192
Protoss_Nexus 1 5075
Protoss_Photon_Cannon 5 10668
Protoss_Gateway 4 9651
Protoss_Assimilator 2 7870
Protoss_Zealot 6 10172
Protoss_Cybernetics_Core 1 6878
Protoss_Stargate 1 8021
Protoss_Citadel_of_Adun 1 8688
Protoss_Corsair 1 8710
10668
