Protoss_Forge 1 3372
Protoss_Nexus 1 5375
Protoss_Photon_Cannon 3 10503
Protoss_Gateway 2 8427
Protoss_Assimilator 2 6966
Protoss_Cybernetics_Core 1 6434
Protoss_Zealot 5 9586
Protoss_Stargate 1 7648
Protoss_Citadel_of_Adun 1 8132
Protoss_Corsair 1 8388
Protoss_Templar_Archives 1 9139
Protoss_High_Templar 2 10338
10503
