Protoss_Forge 1 2896
Protoss_Photon_Cannon 3 9627
Protoss_Nexus 1 5669
Protoss_Gateway 2 8958
Protoss_Assimilator 2 6943
Protoss_Cybernetics_Core 1 6311
Protoss_Zealot 3 8978
Protoss_Stargate 1 7530
Protoss_Citadel_of_Adun 1 8056
Protoss_Dragoon 1 8180
Protoss_Corsair 4 10374
Protoss_Templar_Archives 1 9115
Protoss_Dark_Templar 2 10092
10374
