Protoss_Forge 1 2496
Protoss_Photon_Cannon 2 3817
Protoss_Nexus 1 5685
Protoss_Gateway 4 8765
Protoss_Assimilator 2 10281
Protoss_Zealot 15 10556
Protoss_Cybernetics_Core 1 6283
Protoss_Stargate 1 7460
Protoss_Citadel_of_Adun 1 7707
Protoss_Corsair 1 8170
10556
