Protoss_Forge 1 3038
Protoss_Nexus 2 9151
Protoss_Photon_Cannon 2 4592
Protoss_Gateway 1 5163
Protoss_Assimilator 2 8382
Protoss_Cybernetics_Core 1 6296
Protoss_Zealot 6 10566
Protoss_Stargate 1 7443
Protoss_Corsair 4 10524
Protoss_Robotics_Facility 1 9643
Protoss_Shuttle 1 10659
Protoss_Robotics_Support_Bay 1 10360
10659
