Protoss_Forge 1 3638
Protoss_Photon_Cannon 5 10536
Protoss_Nexus 1 5803
Protoss_Gateway 2 6977
Protoss_Assimilator 2 8986
Protoss_Cybernetics_Core 1 6647
Protoss_Zealot 11 10376
Protoss_Citadel_of_Adun 1 7725
Protoss_Stargate 2 9967
10536
