Protoss_Nexus 1 4617
Protoss_Forge 1 4017
Protoss_Gateway 1 5185
Protoss_Photon_Cannon 3 10121
Protoss_Assimilator 2 6239
Protoss_Zealot 5 10216
Protoss_Cybernetics_Core 1 6496
Protoss_Stargate 2 8723
Protoss_Robotics_Facility 1 8404
Protoss_Corsair 5 10546
Protoss_Citadel_of_Adun 1 9176
Protoss_Shuttle 1 9413
Protoss_Robotics_Support_Bay 1 9108
Protoss_Reaver 1 10588
10588
