Protoss_Gateway 2 7590
Protoss_Assimilator 1 3084
Protoss_Zealot 11 10540
Protoss_Cybernetics_Core 1 4803
Protoss_Stargate 1 5973
Protoss_Dragoon 4 7836
Protoss_Corsair 6 9356
10540
