Protoss_Forge 1 3251
Protoss_Photon_Cannon 4 9410
Protoss_Nexus 1 6100
Protoss_Gateway 2 10168
Protoss_Assimilator 2 6989
Protoss_Zealot 2 9042
Protoss_Cybernetics_Core 1 6979
Protoss_Stargate 2 8707
Protoss_Citadel_of_Adun 1 8773
Protoss_Corsair 5 10570
Protoss_Templar_Archives 1 10334
10570
