Protoss_Nexus 1 4888
Protoss_Forge 1 3887
Protoss_Gateway 1 4852
Protoss_Photon_Cannon 2 5222
Protoss_Assimilator 2 6879
Protoss_Zealot 4 9748
Protoss_Cybernetics_Core 1 6717
Protoss_Dragoon 1 7854
Protoss_Stargate 2 8944
Protoss_Robotics_Facility 1 8731
Protoss_Corsair 4 10558
Protoss_Shuttle 1 10235
Protoss_Robotics_Support_Bay 1 9860
10558
