Protoss_Forge 1 3091
Protoss_Photon_Cannon 3 8382
Protoss_Nexus 1 5820
Protoss_Gateway 3 10075
Protoss_Assimilator 2 9410
Protoss_Cybernetics_Core 1 6471
Protoss_Zealot 7 10264
Protoss_Stargate 1 7734
Protoss_Corsair 1 8512
Protoss_Citadel_of_Adun 1 9169
10264
