Protoss_Forge 1 2854
Protoss_Photon_Cannon 2 4248
Protoss_Nexus 2 11627
Protoss_Gateway 3 10380
Protoss_Assimilator 2 6715
Protoss_Cybernetics_Core 1 6427
Protoss_Zealot 3 9298
Protoss_Stargate 1 7682
Protoss_Dragoon 1 7468
Protoss_Citadel_of_Adun 1 8229
Protoss_Corsair 3 10158
Protoss_Templar_Archives 1 9314
Protoss_Dark_Templar 2 10692
11627
