Protoss_Forge 1 3435
Protoss_Nexus 1 5077
Protoss_Photon_Cannon 2 5024
Protoss_Gateway 3 8651
Protoss_Assimilator 2 6027
Protoss_Zealot 10 10106
Protoss_Cybernetics_Core 1 6931
Protoss_Citadel_of_Adun 1 7923
Protoss_Templar_Archives 1 9578
Protoss_High_Templar 2 10438
10438
