Protoss_Forge 1 3046
Protoss_Nexus 1 5129
Protoss_Photon_Cannon 2 10275
Protoss_Gateway 3 10870
Protoss_Assimilator 2 8992
Protoss_Cybernetics_Core 1 6293
Protoss_Zealot 10 9994
Protoss_Stargate 1 7572
Protoss_Citadel_of_Adun 1 8226
Protoss_Corsair 1 8386
Protoss_Templar_Archives 1 10114
10870
