Protoss_Gateway 2 3387
Protoss_Zealot 15 8868
Protoss_Assimilator 1 5648
Protoss_Cybernetics_Core 1 6836
Protoss_Stargate 1 8265
Protoss_Forge 1 8475
Protoss_Corsair 2 9860
Protoss_Photon_Cannon 1 9434
Protoss_Robotics_Facility 1 10194
Protoss_Citadel_of_Adun 1 10771
10771
