Protoss_Gateway 1 2805
Protoss_Assimilator 1 2837
Protoss_Cybernetics_Core 1 3929
Protoss_Zealot 4 6878
Protoss_Dragoon 1 4762
Protoss_Stargate 1 5190
Protoss_Corsair 4 10208
Protoss_Robotics_Facility 1 7713
Protoss_Forge 2 8657
Protoss_Shuttle 1 8699
Protoss_Photon_Cannon 2 9800
Protoss_Robotics_Support_Bay 1 9179
Protoss_Reaver 1 10392
10392
