Protoss_Forge 1 2862
Protoss_Nexus 1 5175
Protoss_Gateway 3 8145
Protoss_Photon_Cannon 5 10097
Protoss_Assimilator 2 5750
Protoss_Cybernetics_Core 1 6356
Protoss_Stargate 1 7488
Protoss_Citadel_of_Adun 1 7729
Protoss_Corsair 3 10174
Protoss_Templar_Archives 1 8833
Protoss_High_Templar 2 9712
10174
