Protoss_Forge 1 3345
Protoss_Nexus 1 5201
Protoss_Photon_Cannon 7 8522
Protoss_Gateway 4 10159
Protoss_Assimilator 2 9061
Protoss_Cybernetics_Core 1 8125
Protoss_Zealot 3 10030
Protoss_Stargate 1 9291
Protoss_Citadel_of_Adun 1 9573
Protoss_Corsair 1 10108
10159
