Protoss_Forge 1 3278
Protoss_Photon_Cannon 3 10334
Protoss_Nexus 1 5827
Protoss_Gateway 3 9211
Protoss_Assimilator 2 6828
Protoss_Cybernetics_Core 1 6820
Protoss_Zealot 10 10556
Protoss_Stargate 1 8073
Protoss_Citadel_of_Adun 1 8315
Protoss_Corsair 2 9376
10556
