Protoss_Forge 1 2985
Protoss_Photon_Cannon 3 10532
Protoss_Nexus 1 5581
Protoss_Gateway 1 4976
Protoss_Assimilator 2 9154
Protoss_Zealot 4 10144
Protoss_Cybernetics_Core 1 7849
Protoss_Dragoon 1 8870
Protoss_Stargate 1 9200
Protoss_Citadel_of_Adun 1 10116
Protoss_Corsair 2 10544
10544
