Protoss_Forge 1 2685
Protoss_Photon_Cannon 1 3601
Protoss_Nexus 1 5401
Protoss_Gateway 4 9409
Protoss_Assimilator 2 7545
Protoss_Zealot 7 10590
Protoss_Cybernetics_Core 1 6316
Protoss_Stargate 1 7480
Protoss_Citadel_of_Adun 1 7790
Protoss_Corsair 1 8260
Protoss_Templar_Archives 1 8973
Protoss_High_Templar 2 10092
10590
