Protoss_Forge 1 2942
Protoss_Photon_Cannon 4 10292
Protoss_Nexus 1 5737
Protoss_Gateway 2 8785
Protoss_Assimilator 2 7146
Protoss_Cybernetics_Core 1 6237
Protoss_Zealot 3 7452
Protoss_Stargate 1 7399
Protoss_Citadel_of_Adun 1 8053
Protoss_Corsair 3 10548
Protoss_Templar_Archives 1 9324
Protoss_Dragoon 2 10038
Protoss_High_Templar 1 10574
10574
