Protoss_Gateway 2 3175
Protoss_Zealot 7 5352
Protoss_Nexus 1 7613
Protoss_Assimilator 1 6739
Protoss_Forge 1 7081
Protoss_Cybernetics_Core 1 8094
Protoss_Photon_Cannon 3 9883
Protoss_Dragoon 4 9708
Protoss_Stargate 1 9319
Protoss_Corsair 1 10006
10006
