Protoss_Forge 1 3209
Protoss_Nexus 1 5143
Protoss_Photon_Cannon 3 10379
Protoss_Gateway 3 10783
Protoss_Assimilator 2 7678
Protoss_Zealot 5 10214
Protoss_Cybernetics_Core 1 6553
Protoss_Stargate 1 8360
Protoss_Citadel_of_Adun 1 8989
Protoss_Dragoon 1 9010
Protoss_Corsair 3 10562
10783
