Protoss_Forge 1 2852
Protoss_Photon_Cannon 2 8726
Protoss_Nexus 1 5369
Protoss_Gateway 3 10809
Protoss_Assimilator 2 6878
Protoss_Zealot 11 10570
Protoss_Cybernetics_Core 1 6359
Protoss_Citadel_of_Adun 1 7531
Protoss_Stargate 1 9884
Protoss_Templar_Archives 1 9823
Protoss_Ground_Weapons_1 1 9973
10809
