Protoss_Forge 1 3144
Protoss_Photon_Cannon 4 10129
Protoss_Nexus 1 5819
Protoss_Gateway 2 8603
Protoss_Assimilator 2 6800
Protoss_Zealot 6 9642
Protoss_Cybernetics_Core 1 6323
Protoss_Stargate 1 7638
Protoss_Dragoon 1 7582
Protoss_Corsair 3 10208
Protoss_Citadel_of_Adun 1 8678
Protoss_Templar_Archives 1 10655
10655
