Protoss_Forge 1 2862
Protoss_Nexus 1 5009
Protoss_Photon_Cannon 3 10431
Protoss_Gateway 2 10051
Protoss_Assimilator 2 8198
Protoss_Zealot 4 9576
Protoss_Cybernetics_Core 1 6209
Protoss_Dragoon 1 7124
Protoss_Stargate 1 8062
Protoss_Citadel_of_Adun 1 8663
Protoss_Corsair 3 10054
10431
