Protoss_Forge 1 2869
Protoss_Photon_Cannon 3 10012
Protoss_Nexus 1 5879
Protoss_Gateway 3 9603
Protoss_Assimilator 2 7123
Protoss_Cybernetics_Core 1 6257
Protoss_Zealot 8 10318
Protoss_Stargate 1 7638
Protoss_Dragoon 1 7632
Protoss_Citadel_of_Adun 1 8500
Protoss_Corsair 4 10530
Protoss_Templar_Archives 1 9797
10530
