Protoss_Gateway 2 8305
Protoss_Assimilator 1 3006
Protoss_Zealot 13 10242
Protoss_Cybernetics_Core 1 4705
Protoss_Dragoon 1 5562
Protoss_Stargate 1 6137
Protoss_Citadel_of_Adun 1 6749
Protoss_Corsair 1 6872
Protoss_Forge 1 7765
Protoss_Templar_Archives 1 8847
Protoss_Photon_Cannon 1 10104
Protoss_Nexus 1 11421
Protoss_Dark_Templar 2 10668
11421
