Protoss_Forge 1 2964
Protoss_Nexus 1 5035
Protoss_Photon_Cannon 2 4572
Protoss_Gateway 3 9995
Protoss_Assimilator 2 7320
Protoss_Cybernetics_Core 1 6669
Protoss_Zealot 5 10080
Protoss_Dragoon 1 7670
Protoss_Stargate 1 7969
Protoss_Citadel_of_Adun 1 8407
Protoss_Corsair 3 10416
Protoss_Templar_Archives 1 10089
10416
