Protoss_Forge 1 3326
Protoss_Nexus 1 5103
Protoss_Photon_Cannon 4 10532
Protoss_Gateway 3 9109
Protoss_Assimilator 1 6112
Protoss_Cybernetics_Core 1 6949
Protoss_Zealot 9 10544
Protoss_Citadel_of_Adun 1 8342
10544
