Protoss_Gateway 2 3158
Protoss_Zealot 9 9682
Protoss_Forge 1 5493
Protoss_Nexus 1 7317
Protoss_Assimilator 2 8706
Protoss_Photon_Cannon 2 7533
Protoss_Cybernetics_Core 1 8038
Protoss_Stargate 1 9264
Protoss_Citadel_of_Adun 1 9858
Protoss_Corsair 1 10016
10016
