Protoss_Forge 2 10585
Protoss_Photon_Cannon 2 4151
Protoss_Nexus 1 5965
Protoss_Gateway 3 9387
Protoss_Assimilator 2 7428
Protoss_Cybernetics_Core 1 6375
Protoss_Zealot 8 10226
Protoss_Stargate 1 7560
Protoss_Corsair 2 9814
Protoss_Citadel_of_Adun 1 8863
10585
