Protoss_Forge 1 3111
Protoss_Photon_Cannon 1 3954
Protoss_Nexus 1 5531
Protoss_Gateway 2 8820
Protoss_Assimilator 2 7185
Protoss_Cybernetics_Core 1 6015
Protoss_Zealot 4 10076
Protoss_Stargate 1 7322
Protoss_Citadel_of_Adun 1 7887
Protoss_Dragoon 1 8270
Protoss_Corsair 3 10186
Protoss_Templar_Archives 1 9423
10186
