Protoss_Gateway 2 3271
Protoss_Zealot 9 9366
Protoss_Forge 1 4812
Protoss_Photon_Cannon 6 10160
Protoss_Nexus 1 7861
Protoss_Assimilator 2 10502
Protoss_Cybernetics_Core 1 9062
Protoss_Stargate 1 10570
Protoss_Citadel_of_Adun 1 10670
10670
