Protoss_Forge 1 2539
Protoss_Photon_Cannon 5 10400
Protoss_Nexus 1 6072
Protoss_Gateway 2 10802
Protoss_Assimilator 1 5671
Protoss_Zealot 3 8854
Protoss_Cybernetics_Core 1 8330
Protoss_Stargate 1 9626
Protoss_Citadel_of_Adun 2 10316
10802
