Protoss_Forge 1 2904
Protoss_Photon_Cannon 2 4142
Protoss_Nexus 1 5917
Protoss_Gateway 3 9099
Protoss_Assimilator 2 7230
Protoss_Cybernetics_Core 1 6357
Protoss_Zealot 6 9904
Protoss_Stargate 1 7610
Protoss_Citadel_of_Adun 1 7984
Protoss_Dragoon 1 8620
Protoss_Corsair 3 10132
Protoss_Templar_Archives 1 9320
Protoss_Dark_Templar 2 10656
10656
