Protoss_Forge 1 2842
Protoss_Photon_Cannon 3 9813
Protoss_Nexus 1 5852
Protoss_Gateway 3 10213
Protoss_Assimilator 2 8126
Protoss_Cybernetics_Core 1 6389
Protoss_Zealot 5 10188
Protoss_Stargate 1 7686
Protoss_Citadel_of_Adun 1 8279
Protoss_Dragoon 1 8480
Protoss_Corsair 3 10054
Protoss_Templar_Archives 1 9885
10213
