Protoss_Forge 1 2947
Protoss_Nexus 1 5045
Protoss_Photon_Cannon 1 4286
Protoss_Gateway 4 8499
Protoss_Assimilator 2 6198
Protoss_Cybernetics_Core 1 5871
Protoss_Zealot 15 10538
Protoss_Stargate 1 7157
Protoss_Citadel_of_Adun 1 7563
Protoss_Corsair 2 8704
Protoss_Templar_Archives 1 10575
10575
