Protoss_Forge 1 2883
Protoss_Nexus 1 5111
Protoss_Gateway 4 9696
Protoss_Photon_Cannon 2 10170
Protoss_Assimilator 2 6017
Protoss_Cybernetics_Core 1 6037
Protoss_Zealot 2 7913
Protoss_Stargate 1 7202
Protoss_Citadel_of_Adun 1 7365
Protoss_Dragoon 1 7290
Protoss_Corsair 4 10010
Protoss_Templar_Archives 1 8443
Protoss_Dark_Templar 2 9714
Protoss_High_Templar 2 10742
10742
