Protoss_Forge 1 2750
Protoss_Photon_Cannon 4 9115
Protoss_Nexus 1 6374
Protoss_Gateway 1 5849
Protoss_Assimilator 2 7851
Protoss_Cybernetics_Core 1 7066
Protoss_Zealot 3 8738
Protoss_Stargate 2 9239
Protoss_Dragoon 1 8136
Protoss_Corsair 4 10310
Protoss_Citadel_of_Adun 1 9720
10310
