Protoss_Forge 1 3194
Protoss_Nexus 1 5015
Protoss_Photon_Cannon 3 9927
Protoss_Gateway 2 10589
Protoss_Assimilator 2 7250
Protoss_Cybernetics_Core 1 6262
Protoss_Zealot 7 10400
Protoss_Stargate 1 7516
Protoss_Corsair 4 10134
Protoss_Citadel_of_Adun 1 9307
10589
