Protoss_Forge 1 2877
Protoss_Photon_Cannon 2 4164
Protoss_Nexus 1 6087
Protoss_Gateway 3 10307
Protoss_Assimilator 2 6962
Protoss_Cybernetics_Core 1 6453
Protoss_Zealot 6 10588
Protoss_Stargate 1 7590
Protoss_Corsair 4 10148
Protoss_Citadel_of_Adun 1 8701
Protoss_Templar_Archives 1 10163
10588
