Protoss_Nexus 1 4671
Protoss_Forge 1 3818
Protoss_Gateway 1 4421
Protoss_Photon_Cannon 4 9842
Protoss_Assimilator 1 5069
Protoss_Cybernetics_Core 1 5759
Protoss_Zealot 3 9312
Protoss_Stargate 1 7654
Protoss_Dragoon 1 8660
Protoss_Corsair 3 10024
Protoss_Citadel_of_Adun 1 10771
10771
