Protoss_Nexus 1 4652
Protoss_Gateway 6 10654
Protoss_Forge 1 4336
Protoss_Assimilator 2 7037
Protoss_Photon_Cannon 1 5246
Protoss_Cybernetics_Core 1 5833
Protoss_Zealot 4 10334
Protoss_Stargate 1 7208
Protoss_Dragoon 1 6926
Protoss_Citadel_of_Adun 1 7695
Protoss_Corsair 1 7892
Protoss_Templar_Archives 1 8910
Protoss_Dark_Templar 1 9750
Protoss_High_Templar 2 10160
10654
