Protoss_Forge 1 2725
Protoss_Photon_Cannon 4 10406
Protoss_Nexus 1 5883
Protoss_Gateway 1 5319
Protoss_Assimilator 2 7826
Protoss_Zealot 6 10420
Protoss_Cybernetics_Core 1 6618
Protoss_Stargate 1 8030
Protoss_Dragoon 1 8012
Protoss_Citadel_of_Adun 1 8612
Protoss_Corsair 2 9416
Protoss_Templar_Archives 1 9917
10420
