Protoss_Forge 1 3036
Protoss_Nexus 1 5367
Protoss_Photon_Cannon 4 10184
Protoss_Gateway 4 9810
Protoss_Assimilator 2 8011
Protoss_Cybernetics_Core 1 6758
Protoss_Zealot 4 10573
Protoss_Citadel_of_Adun 1 7970
Protoss_Dragoon 2 9416
Protoss_Templar_Archives 1 9141
Protoss_Dark_Templar 1 10168
Protoss_High_Templar 2 10546
10573
