Protoss_Forge 1 2663
Protoss_Nexus 1 5023
Protoss_Gateway 3 10297
Protoss_Photon_Cannon 4 9172
Protoss_Assimilator 2 7700
Protoss_Zealot 3 9184
Protoss_Cybernetics_Core 1 6103
Protoss_Stargate 1 7361
Protoss_Dragoon 1 7604
Protoss_Corsair 4 10462
Protoss_Robotics_Facility 1 9369
Protoss_Robotics_Support_Bay 1 10067
Protoss_Observatory 1 10198
10462
