Protoss_Gateway 2 8153
Protoss_Forge 1 3277
Protoss_Zealot 13 10248
Protoss_Photon_Cannon 2 10078
Protoss_Nexus 1 6302
Protoss_Assimilator 2 9356
Protoss_Cybernetics_Core 1 6562
Protoss_Citadel_of_Adun 1 8501
Protoss_Templar_Archives 1 9563
10248
