Protoss_Forge 1 2802
Protoss_Nexus 1 5268
Protoss_Photon_Cannon 3 9839
Protoss_Gateway 2 9105
Protoss_Assimilator 2 6998
Protoss_Cybernetics_Core 1 6469
Protoss_Zealot 3 9498
Protoss_Stargate 1 7726
Protoss_Dragoon 1 7652
Protoss_Citadel_of_Adun 1 8341
Protoss_Corsair 3 9768
Protoss_Templar_Archives 1 9327
Protoss_Dark_Templar 2 10304
10304
