Protoss_Forge 1 2890
Protoss_Photon_Cannon 6 10502
Protoss_Nexus 1 5780
Protoss_Gateway 3 9033
Protoss_Assimilator 2 8095
Protoss_Cybernetics_Core 1 6207
Protoss_Zealot 6 9740
Protoss_Stargate 1 7418
Protoss_Dragoon 1 7378
Protoss_Citadel_of_Adun 1 7997
Protoss_Corsair 1 8236
Protoss_Templar_Archives 1 9558
Protoss_Dark_Templar 1 10722
Protoss_High_Templar 1 10736
10736
