Protoss_Gateway 1 2722
Protoss_Assimilator 1 2767
Protoss_Cybernetics_Core 1 3707
Protoss_Zealot 6 10116
Protoss_Dragoon 2 5346
Protoss_Stargate 1 5034
Protoss_Corsair 4 9352
Protoss_Forge 1 6795
Protoss_Nexus 1 9532
Protoss_Photon_Cannon 4 10636
Protoss_Citadel_of_Adun 1 9415
10636
