Protoss_Forge 1 2922
Protoss_Nexus 1 5058
Protoss_Photon_Cannon 3 10496
Protoss_Gateway 3 8983
Protoss_Assimilator 2 6847
Protoss_Cybernetics_Core 1 6301
Protoss_Zealot 4 9465
Protoss_Stargate 1 7482
Protoss_Citadel_of_Adun 1 7751
Protoss_Corsair 3 10122
Protoss_Dragoon 1 8863
Protoss_Templar_Archives 1 9201
Protoss_Dark_Templar 3 10217
10496
