Protoss_Forge 1 2564
Protoss_Nexus 1 4889
Protoss_Photon_Cannon 7 10584
Protoss_Gateway 2 8189
Protoss_Assimilator 2 7417
Protoss_Cybernetics_Core 1 6254
Protoss_Zealot 5 9170
Protoss_Stargate 1 7618
Protoss_Citadel_of_Adun 1 8333
Protoss_Corsair 3 10060
Protoss_Templar_Archives 1 10044
10584
