Protoss_Forge 1 2900
Protoss_Nexus 1 4905
Protoss_Gateway 3 9551
Protoss_Photon_Cannon 4 10747
Protoss_Assimilator 2 6936
Protoss_Cybernetics_Core 1 5789
Protoss_Zealot 4 10308
Protoss_Stargate 1 6936
Protoss_Citadel_of_Adun 1 7581
Protoss_Corsair 4 10292
Protoss_Templar_Archives 1 8664
Protoss_Dark_Templar 1 9520
Protoss_High_Templar 1 9534
10747
