Protoss_Forge 1 3191
Protoss_Photon_Cannon 5 9629
Protoss_Nexus 1 5627
Protoss_Gateway 2 10849
Protoss_Assimilator 2 7224
Protoss_Zealot 9 10282
Protoss_Cybernetics_Core 1 5933
Protoss_Stargate 1 7184
Protoss_Citadel_of_Adun 1 7961
Protoss_Corsair 4 10166
Protoss_Templar_Archives 1 10760
10849
