Protoss_Forge 2 8672
Protoss_Nexus 1 4873
Protoss_Photon_Cannon 6 9595
Protoss_Gateway 4 10313
Protoss_Assimilator 2 6388
Protoss_Cybernetics_Core 1 6088
Protoss_Dragoon 1 7052
Protoss_Citadel_of_Adun 1 7712
Protoss_Zealot 5 9818
Protoss_Templar_Archives 1 9442
Protoss_High_Templar 2 10628
Protoss_Dark_Templar 1 10522
10628
