Protoss_Forge 1 2710
Protoss_Photon_Cannon 2 5352
Protoss_Nexus 1 5321
Protoss_Gateway 4 10535
Protoss_Assimilator 2 7391
Protoss_Zealot 8 10092
Protoss_Cybernetics_Core 1 6983
Protoss_Stargate 1 8161
Protoss_Citadel_of_Adun 1 8259
Protoss_Corsair 2 9500
Protoss_Templar_Archives 1 10001
10535
