Protoss_Gateway 2 6964
Protoss_Assimilator 1 3131
Protoss_Zealot 12 9680
Protoss_Cybernetics_Core 1 4685
Protoss_Stargate 1 6068
Protoss_Corsair 1 6756
Protoss_Citadel_of_Adun 1 7506
Protoss_Forge 1 8154
Protoss_Templar_Archives 1 9345
Protoss_Photon_Cannon 2 10554
Protoss_Dark_Templar 1 10414
10554
