Protoss_Gateway 4 9800
Protoss_Zealot 10 10088
Protoss_Forge 1 3684
Protoss_Nexus 1 6174
Protoss_Photon_Cannon 4 10681
Protoss_Assimilator 2 7526
Protoss_Cybernetics_Core 1 6632
Protoss_Stargate 1 7863
Protoss_Citadel_of_Adun 1 8593
Protoss_Corsair 1 8548
Protoss_Templar_Archives 1 10141
10681
