Protoss_Forge 1 3111
Protoss_Photon_Cannon 4 10507
Protoss_Nexus 1 5595
Protoss_Gateway 3 10351
Protoss_Assimilator 2 8360
Protoss_Cybernetics_Core 1 6404
Protoss_Dragoon 1 7232
Protoss_Stargate 1 7742
Protoss_Citadel_of_Adun 1 7899
Protoss_Zealot 2 8532
Protoss_Corsair 3 10248
Protoss_Templar_Archives 1 9059
Protoss_Dark_Templar 1 10162
10507
