Protoss_Gateway 2 3245
Protoss_Zealot 11 6964
Protoss_Nexus 1 7484
Protoss_Assimilator 2 8869
Protoss_Forge 1 7319
Protoss_Cybernetics_Core 1 8445
Protoss_Photon_Cannon 3 10666
Protoss_Dragoon 1 9310
Protoss_Stargate 1 10012
Protoss_Citadel_of_Adun 1 10210
10666
