Protoss_Gateway 2 3347
Protoss_Zealot 18 10290
Protoss_Nexus 1 8275
Protoss_Assimilator 1 7909
Protoss_Forge 1 8677
Protoss_Photon_Cannon 2 10676
Protoss_Cybernetics_Core 1 10167
10676
