Protoss_Gateway 1 2804
Protoss_Assimilator 1 2843
Protoss_Zealot 5 7808
Protoss_Cybernetics_Core 1 4719
Protoss_Dragoon 2 6404
Protoss_Stargate 1 6341
Protoss_Citadel_of_Adun 1 7232
Protoss_Corsair 3 8498
Protoss_Templar_Archives 1 8329
Protoss_Forge 1 8302
Protoss_Dark_Templar 1 9208
Protoss_Photon_Cannon 2 10499
Protoss_High_Templar 1 10026
Protoss_Nexus 1 11241
11241
