Protoss_Forge 1 2542
Protoss_Photon_Cannon 2 7456
Protoss_Nexus 1 5339
Protoss_Gateway 3 9174
Protoss_Assimilator 2 6287
Protoss_Cybernetics_Core 1 5811
Protoss_Stargate 1 7114
Protoss_Zealot 7 10068
Protoss_Citadel_of_Adun 1 7953
Protoss_Corsair 2 8502
Protoss_Templar_Archives 1 10319
10319
