Protoss_Forge 1 2865
Protoss_Nexus 1 4889
Protoss_Photon_Cannon 3 9139
Protoss_Gateway 4 10420
Protoss_Assimilator 2 6857
Protoss_Cybernetics_Core 1 6696
Protoss_Zealot 7 10404
Protoss_Stargate 1 7876
Protoss_Citadel_of_Adun 1 8005
Protoss_Corsair 2 9340
10420
