Protoss_Forge 1 2937
Protoss_Photon_Cannon 2 10436
Protoss_Nexus 1 5641
Protoss_Gateway 2 9654
Protoss_Assimilator 2 6780
Protoss_Cybernetics_Core 1 6083
Protoss_Zealot 2 7608
Protoss_Stargate 1 7500
Protoss_Citadel_of_Adun 1 7952
Protoss_Corsair 2 9286
Protoss_Templar_Archives 1 9190
Protoss_Robotics_Facility 1 9641
Protoss_Dark_Templar 2 10578
Protoss_Shuttle 1 10705
10705
