Protoss_Nexus 1 4855
Protoss_Forge 1 3946
Protoss_Gateway 5 10533
Protoss_Photon_Cannon 5 10666
Protoss_Assimilator 2 8043
Protoss_Zealot 10 10418
Protoss_Cybernetics_Core 1 6776
Protoss_Citadel_of_Adun 1 7879
Protoss_Stargate 1 8121
Protoss_Corsair 1 8974
10666
