Protoss_Forge 1 2977
Protoss_Nexus 1 5159
Protoss_Gateway 4 8637
Protoss_Photon_Cannon 1 4917
Protoss_Assimilator 2 6512
Protoss_Zealot 4 7678
Protoss_Cybernetics_Core 1 6193
Protoss_Stargate 1 7702
Protoss_Corsair 2 10352
Protoss_Dragoon 8 10378
10378
