Protoss_Forge 1 2963
Protoss_Photon_Cannon 3 10645
Protoss_Nexus 1 5710
Protoss_Gateway 5 10129
Protoss_Assimilator 1 5336
Protoss_Cybernetics_Core 1 6123
Protoss_Zealot 11 10294
Protoss_Citadel_of_Adun 1 7391
Protoss_Templar_Archives 1 9456
10645
