Protoss_Forge 1 2833
Protoss_Nexus 1 5069
Protoss_Photon_Cannon 2 4608
Protoss_Gateway 3 10330
Protoss_Assimilator 2 7548
Protoss_Zealot 6 10288
Protoss_Cybernetics_Core 1 7275
Protoss_Stargate 1 8422
Protoss_Citadel_of_Adun 1 8827
Protoss_Corsair 1 9156
Protoss_Templar_Archives 1 10081
10330
