Protoss_Forge 1 2846
Protoss_Photon_Cannon 6 10527
Protoss_Nexus 1 5737
Protoss_Gateway 4 10341
Protoss_Assimilator 2 7635
Protoss_Cybernetics_Core 1 6385
Protoss_Zealot 3 9194
Protoss_Stargate 1 7625
Protoss_Corsair 1 8342
Protoss_Citadel_of_Adun 1 8819
Protoss_Templar_Archives 1 9817
Protoss_High_Templar 2 10668
10668
