Protoss_Forge 1 2903
Protoss_Nexus 1 5205
Protoss_Photon_Cannon 5 10370
Protoss_Gateway 4 9301
Protoss_Assimilator 2 8055
Protoss_Cybernetics_Core 1 6602
Protoss_Zealot 7 10466
Protoss_Citadel_of_Adun 1 7743
Protoss_Dragoon 1 8378
Protoss_Templar_Archives 1 8899
Protoss_High_Templar 2 10072
Protoss_Dark_Templar 2 10594
10594
