Protoss_Gateway 2 6438
Protoss_Assimilator 1 2959
Protoss_Zealot 7 9586
Protoss_Cybernetics_Core 1 4514
Protoss_Dragoon 6 10374
Protoss_Robotics_Facility 1 6029
Protoss_Shuttle 1 7009
Protoss_Robotics_Support_Bay 1 6839
Protoss_Reaver 2 9676
10374
