Protoss_Forge 1 2876
Protoss_Nexus 1 5031
Protoss_Gateway 4 10867
Protoss_Photon_Cannon 8 10601
Protoss_Assimilator 2 9934
Protoss_Cybernetics_Core 1 5736
Protoss_Zealot 12 10148
Protoss_Citadel_of_Adun 1 7602
Protoss_Templar_Archives 1 8993
Protoss_Ground_Weapons_1 1 9875
10867
