Protoss_Forge 1 3150
Protoss_Photon_Cannon 8 10652
Protoss_Nexus 1 5933
Protoss_Gateway 1 5175
Protoss_Assimilator 2 9094
Protoss_Zealot 3 8800
Protoss_Cybernetics_Core 1 7861
Protoss_Stargate 1 9062
Protoss_Corsair 1 9804
Protoss_Citadel_of_Adun 1 10640
10652
