Protoss_Forge 1 2824
Protoss_Nexus 1 5074
Protoss_Photon_Cannon 2 4684
Protoss_Gateway 2 7720
Protoss_Assimilator 2 7245
Protoss_Zealot 11 10456
Protoss_Cybernetics_Core 1 6595
Protoss_Stargate 1 8231
Protoss_Citadel_of_Adun 1 8392
Protoss_Corsair 1 8958
10456
