Protoss_Forge 1 2886
Protoss_Photon_Cannon 1 3730
Protoss_Nexus 1 5614
Protoss_Gateway 4 9512
Protoss_Assimilator 2 5783
Protoss_Zealot 2 6776
Protoss_Cybernetics_Core 1 6359
Protoss_Dragoon 11 10686
Protoss_Stargate 1 10164
10686
