Protoss_Forge 1 2938
Protoss_Photon_Cannon 3 10139
Protoss_Nexus 1 5812
Protoss_Gateway 4 10721
Protoss_Assimilator 2 6654
Protoss_Cybernetics_Core 1 6397
Protoss_Zealot 7 10066
Protoss_Stargate 1 7595
Protoss_Citadel_of_Adun 1 8196
Protoss_Corsair 1 8306
Protoss_Templar_Archives 1 9838
10721
