Protoss_Forge 1 3174
Protoss_Photon_Cannon 3 10332
Protoss_Nexus 1 5883
Protoss_Gateway 2 10589
Protoss_Assimilator 2 7369
Protoss_Cybernetics_Core 1 6525
Protoss_Zealot 7 10586
Protoss_Stargate 1 7676
Protoss_Citadel_of_Adun 1 8759
Protoss_Corsair 4 10490
Protoss_Templar_Archives 1 9935
10589
