Protoss_Forge 1 2938
Protoss_Photon_Cannon 2 4446
Protoss_Nexus 1 5806
Protoss_Gateway 4 10397
Protoss_Assimilator 2 6563
Protoss_Cybernetics_Core 1 6275
Protoss_Zealot 8 10242
Protoss_Stargate 1 7526
Protoss_Citadel_of_Adun 1 8093
Protoss_Corsair 2 8910
Protoss_Templar_Archives 1 10108
10397
