Protoss_Forge 1 2700
Protoss_Nexus 1 5437
Protoss_Gateway 2 10135
Protoss_Photon_Cannon 8 10728
Protoss_Assimilator 2 7674
Protoss_Cybernetics_Core 1 6255
Protoss_Zealot 3 7822
Protoss_Stargate 1 7454
Protoss_Citadel_of_Adun 1 7842
Protoss_Corsair 3 9880
Protoss_Templar_Archives 1 9067
Protoss_Dark_Templar 1 9946
10728
