Protoss_Gateway 2 10265
Protoss_Assimilator 1 3053
Protoss_Zealot 3 6786
Protoss_Cybernetics_Core 1 4620
Protoss_Stargate 1 5967
Protoss_Citadel_of_Adun 1 5955
Protoss_Dragoon 1 6034
Protoss_Corsair 1 6650
Protoss_Templar_Archives 1 7064
Protoss_Forge 1 7116
Protoss_Dark_Templar 1 8252
Protoss_Photon_Cannon 4 10503
Protoss_High_Templar 2 10036
Protoss_Nexus 1 10763
Psionic_Storm 1 9931
10763
