Protoss_Forge 1 2766
Protoss_Photon_Cannon 3 10352
Protoss_Nexus 1 5681
Protoss_Gateway 4 9245
Protoss_Assimilator 2 7216
Protoss_Zealot 10 10418
Protoss_Cybernetics_Core 1 6277
Protoss_Stargate 1 7496
Protoss_Citadel_of_Adun 1 7751
Protoss_Templar_Archives 1 9974
10418
