Protoss_Forge 1 3137
Protoss_Nexus 1 4967
Protoss_Photon_Cannon 4 10422
Protoss_Gateway 1 5141
Protoss_Assimilator 2 7757
Protoss_Cybernetics_Core 1 6718
Protoss_Stargate 1 7894
Protoss_Zealot 3 10382
Protoss_Citadel_of_Adun 1 8849
Protoss_Corsair 4 10568
10568
