Protoss_Forge 1 3313
Protoss_Photon_Cannon 3 10532
Protoss_Nexus 1 5441
Protoss_Assimilator 2 8064
Protoss_Gateway 3 10034
Protoss_Zealot 12 10390
Protoss_Cybernetics_Core 1 6535
Protoss_Stargate 1 7729
Protoss_Citadel_of_Adun 1 8283
Protoss_Corsair 3 9994
10532
