Protoss_Forge 1 2746
Protoss_Photon_Cannon 2 9336
Protoss_Nexus 1 5577
Protoss_Gateway 4 10527
Protoss_Assimilator 2 6794
Protoss_Cybernetics_Core 1 5959
Protoss_Zealot 7 9912
Protoss_Stargate 1 7096
Protoss_Dragoon 1 7092
Protoss_Citadel_of_Adun 1 7962
Protoss_Corsair 2 8623
Protoss_Templar_Archives 1 9794
10527
