Protoss_Forge 1 2456
Protoss_Photon_Cannon 2 5282
Protoss_Nexus 1 6152
Protoss_Gateway 2 9714
Protoss_Assimilator 2 8430
Protoss_Cybernetics_Core 1 6845
Protoss_Zealot 4 9186
Protoss_Stargate 1 8004
Protoss_Citadel_of_Adun 1 8004
Protoss_Corsair 1 8886
Protoss_Templar_Archives 1 9449
Protoss_Robotics_Facility 1 10412
Protoss_Dark_Templar 2 10604
10604
