Protoss_Forge 1 2843
Protoss_Photon_Cannon 2 10607
Protoss_Nexus 1 5926
Protoss_Gateway 3 9695
Protoss_Assimilator 2 7674
Protoss_Cybernetics_Core 1 6259
Protoss_Zealot 8 10572
Protoss_Stargate 1 7484
Protoss_Citadel_of_Adun 1 8109
Protoss_Corsair 2 8878
Protoss_Templar_Archives 1 9323
Protoss_Dark_Templar 2 10710
10710
