Protoss_Forge 2 4260
Protoss_Nexus 1 5012
Protoss_Gateway 3 9292
Protoss_Photon_Cannon 2 7928
Protoss_Assimilator 2 7015
Protoss_Zealot 9 10488
Protoss_Cybernetics_Core 1 6538
Protoss_Stargate 1 7708
Protoss_Corsair 2 9552
Protoss_Dragoon 1 8680
Protoss_Citadel_of_Adun 1 8863
Protoss_Templar_Archives 1 10323
10488
