Protoss_Forge 1 2936
Protoss_Photon_Cannon 3 10338
Protoss_Nexus 1 6023
Protoss_Gateway 2 6381
Protoss_Assimilator 2 8470
Protoss_Zealot 9 9444
Protoss_Cybernetics_Core 1 7756
Protoss_Stargate 1 9025
Protoss_Citadel_of_Adun 1 9171
Protoss_Corsair 1 9908
Protoss_Templar_Archives 1 10292
Protoss_Dragoon 2 10214
10338
