Protoss_Forge 1 2539
Protoss_Photon_Cannon 3 4058
Protoss_Nexus 1 6445
Protoss_Gateway 2 10799
Protoss_Assimilator 1 7014
Protoss_Zealot 2 9434
Protoss_Cybernetics_Core 1 8691
Protoss_Stargate 1 9830
Protoss_Citadel_of_Adun 1 10386
Protoss_Dragoon 1 10292
Protoss_Corsair 1 10554
10799
