Protoss_Forge 1 2915
Protoss_Photon_Cannon 4 10553
Protoss_Nexus 1 5625
Protoss_Gateway 1 5132
Protoss_Assimilator 2 9115
Protoss_Cybernetics_Core 1 6261
Protoss_Zealot 2 8795
Protoss_Stargate 2 8973
Protoss_Scout 3 10475
10553
