Protoss_Gateway 2 3411
Protoss_Zealot 12 9980
Protoss_Nexus 2 8666
Protoss_Assimilator 1 7264
Protoss_Forge 1 7672
Protoss_Photon_Cannon 5 10496
Protoss_Cybernetics_Core 1 9559
10496
