Protoss_Forge 2 3856
Protoss_Nexus 1 4761
Protoss_Gateway 2 8489
Protoss_Photon_Cannon 5 10274
Protoss_Assimilator 2 6818
Protoss_Cybernetics_Core 1 6357
Protoss_Zealot 3 9212
Protoss_Stargate 1 7700
Protoss_Citadel_of_Adun 1 7911
Protoss_Corsair 3 9824
Protoss_Templar_Archives 1 9103
Protoss_High_Templar 1 9994
Protoss_Dark_Templar 1 10398
10398
