Protoss_Forge 1 2976
Protoss_Photon_Cannon 5 6756
Protoss_Nexus 1 7292
Protoss_Gateway 3 10712
Protoss_Assimilator 2 8484
Protoss_Zealot 4 10260
Protoss_Cybernetics_Core 1 7971
Protoss_Dragoon 1 9042
Protoss_Robotics_Facility 1 9652
Protoss_Citadel_of_Adun 1 10175
Protoss_Shuttle 1 10643
Protoss_Robotics_Support_Bay 1 10343
10712
