Protoss_Forge 1 2693
Protoss_Photon_Cannon 5 8556
Protoss_Nexus 1 5515
Protoss_Gateway 5 10527
Protoss_Assimilator 2 9728
Protoss_Zealot 8 10518
Protoss_Cybernetics_Core 1 7563
Protoss_Dragoon 1 8394
Protoss_Citadel_of_Adun 1 8937
10527
