Protoss_Gateway 1 2720
Protoss_Forge 1 2991
Protoss_Zealot 5 10358
Protoss_Photon_Cannon 8 10677
Protoss_Nexus 1 6253
Protoss_Assimilator 2 8026
Protoss_Cybernetics_Core 1 6767
Protoss_Stargate 1 8003
Protoss_Corsair 3 10132
Protoss_Citadel_of_Adun 1 9699
Protoss_Shield_Battery 1 9987
10677
