Protoss_Forge 1 2877
Protoss_Nexus 1 5015
Protoss_Photon_Cannon 2 6483
Protoss_Gateway 3 9726
Protoss_Assimilator 1 4788
Protoss_Zealot 8 10552
Protoss_Cybernetics_Core 1 7881
Protoss_Stargate 1 9053
Protoss_Citadel_of_Adun 1 9081
Protoss_Corsair 1 9796
10552
