Protoss_Gateway 5 10680
Protoss_Forge 1 3017
Protoss_Zealot 4 8236
Protoss_Photon_Cannon 4 10446
Protoss_Nexus 1 6202
Protoss_Assimilator 2 6755
Protoss_Cybernetics_Core 1 6413
Protoss_Citadel_of_Adun 1 7555
Protoss_Templar_Archives 1 8855
Protoss_High_Templar 4 10650
Protoss_Dark_Templar 1 10132
10680
