Protoss_Gateway 2 8409
Protoss_Forge 1 2970
Protoss_Zealot 5 9608
Protoss_Photon_Cannon 3 8930
Protoss_Nexus 1 6467
Protoss_Assimilator 2 7626
Protoss_Cybernetics_Core 1 7093
Protoss_Stargate 1 8231
Protoss_Citadel_of_Adun 1 8539
Protoss_Corsair 1 9260
9608
