Protoss_Forge 1 3089
Protoss_Photon_Cannon 3 10246
Protoss_Nexus 1 5185
Protoss_Gateway 3 10841
Protoss_Assimilator 2 8104
Protoss_Zealot 6 10132
Protoss_Cybernetics_Core 1 6495
Protoss_Stargate 1 7854
Protoss_Dragoon 1 7916
Protoss_Citadel_of_Adun 1 8434
Protoss_Corsair 1 9154
Protoss_Templar_Archives 1 9773
10841
