Protoss_Gateway 1 3132
Protoss_Nexus 1 5191
Protoss_Zealot 5 9056
Protoss_Assimilator 1 4781
Protoss_Cybernetics_Core 1 5673
Protoss_Forge 1 6443
Protoss_Dragoon 1 6976
Protoss_Stargate 1 7544
Protoss_Photon_Cannon 4 9449
Protoss_Corsair 3 10504
10504
