Protoss_Gateway 3 8781
Protoss_Forge 1 2990
Protoss_Zealot 6 9686
Protoss_Photon_Cannon 7 10118
Protoss_Nexus 1 6307
Protoss_Assimilator 2 6802
Protoss_Cybernetics_Core 1 6814
Protoss_Citadel_of_Adun 1 8064
Protoss_Templar_Archives 1 10731
10731
