Protoss_Forge 1 3416
Protoss_Nexus 1 5254
Protoss_Photon_Cannon 6 10446
Protoss_Gateway 2 9491
Protoss_Assimilator 2 7530
Protoss_Zealot 7 10100
Protoss_Cybernetics_Core 1 6790
Protoss_Stargate 1 8028
Protoss_Citadel_of_Adun 1 8101
Protoss_Corsair 2 9530
Protoss_Templar_Archives 1 9450
Protoss_Dark_Templar 2 10642
10642
