Protoss_Gateway 2 6870
Protoss_Assimilator 1 3135
Protoss_Zealot 8 9520
Protoss_Cybernetics_Core 1 4823
Protoss_Dragoon 1 5748
Protoss_Citadel_of_Adun 1 7443
Protoss_Nexus 1 9547
Protoss_Templar_Archives 1 8953
Protoss_High_Templar 2 10356
10356
