Protoss_Gateway 2 8022
Protoss_Forge 1 3374
Protoss_Zealot 7 10042
Protoss_Photon_Cannon 2 6998
Protoss_Nexus 1 7653
Protoss_Assimilator 2 9646
Protoss_Cybernetics_Core 1 8294
Protoss_Dragoon 1 9160
Protoss_Stargate 1 9548
Protoss_Citadel_of_Adun 1 9853
Protoss_Corsair 1 10338
10338
