Protoss_Gateway 2 3511
Protoss_Zealot 11 8990
Protoss_Forge 1 5356
Protoss_Assimilator 1 6098
Protoss_Photon_Cannon 1 7212
Protoss_Cybernetics_Core 1 8395
Protoss_Dragoon 1 9236
Protoss_Citadel_of_Adun 1 9909
9909
