Protoss_Forge 1 2514
Protoss_Photon_Cannon 5 9134
Protoss_Nexus 1 5675
Protoss_Gateway 3 10644
Protoss_Assimilator 2 6977
Protoss_Zealot 3 9032
Protoss_Cybernetics_Core 1 6738
Protoss_Dragoon 2 10560
Protoss_Stargate 1 8008
Protoss_Citadel_of_Adun 1 8883
Protoss_Corsair 4 10552
Protoss_Templar_Archives 1 9977
10644
