Protoss_Forge 1 2618
Protoss_Photon_Cannon 7 10449
Protoss_Nexus 1 5593
Protoss_Gateway 1 5075
Protoss_Assimilator 1 5081
Protoss_Zealot 5 9208
Protoss_Cybernetics_Core 1 6187
Protoss_Stargate 1 7544
Protoss_Corsair 3 10114
Protoss_Citadel_of_Adun 1 8770
10449
