Protoss_Nexus 1 4703
Protoss_Forge 1 3842
Protoss_Photon_Cannon 3 10350
Protoss_Gateway 2 9078
Protoss_Assimilator 2 6618
Protoss_Cybernetics_Core 1 6383
Protoss_Zealot 4 9038
Protoss_Stargate 1 7591
Protoss_Dragoon 1 7560
Protoss_Citadel_of_Adun 1 8173
Protoss_Corsair 4 10364
Protoss_Templar_Archives 1 9180
Protoss_Dark_Templar 2 10046
10364
