Protoss_Forge 1 2806
Protoss_Nexus 1 5080
Protoss_Gateway 3 8426
Protoss_Assimilator 2 9978
Protoss_Photon_Cannon 2 10010
Protoss_Zealot 14 10394
Protoss_Cybernetics_Core 1 6105
Protoss_Stargate 1 7579
Protoss_Citadel_of_Adun 1 7866
Protoss_Corsair 1 8280
Protoss_Ground_Weapons_1 1 9813
Protoss_Templar_Archives 1 10721
10721
