Protoss_Gateway 2 3267
Protoss_Zealot 13 8590
Protoss_Forge 1 6417
Protoss_Assimilator 1 7507
Protoss_Photon_Cannon 3 9837
Protoss_Cybernetics_Core 1 8474
Protoss_Stargate 1 9869
Protoss_Citadel_of_Adun 1 10470
Protoss_Corsair 1 10580
10580
