Protoss_Gateway 2 7487
Protoss_Assimilator 1 3046
Protoss_Zealot 7 9638
Protoss_Cybernetics_Core 1 4694
Protoss_Dragoon 1 5938
Protoss_Stargate 1 6458
Protoss_Corsair 1 7718
Protoss_Shield_Battery 1 8335
Protoss_Forge 1 9852
9852
