Protoss_Forge 1 2532
Protoss_Photon_Cannon 4 10492
Protoss_Nexus 1 6218
Protoss_Gateway 1 5629
Protoss_Assimilator 2 7271
Protoss_Zealot 2 6958
Protoss_Cybernetics_Core 1 6796
Protoss_Stargate 2 9968
Protoss_Robotics_Facility 1 9132
Protoss_Corsair 3 10533
Protoss_Robotics_Support_Bay 1 9746
Protoss_Shuttle 1 10277
10533
