Protoss_Gateway 1 2939
Protoss_Assimilator 1 3170
Protoss_Zealot 3 5478
Protoss_Cybernetics_Core 1 5426
Protoss_Forge 1 6694
Protoss_Dragoon 2 8436
Protoss_Photon_Cannon 1 9105
9105
