Protoss_Forge 1 2800
Protoss_Photon_Cannon 4 9153
Protoss_Nexus 1 6295
Protoss_Gateway 5 10879
Protoss_Assimilator 2 8224
Protoss_Zealot 7 10078
Protoss_Cybernetics_Core 1 7334
Protoss_Citadel_of_Adun 1 8419
Protoss_Templar_Archives 1 10093
10879
