Protoss_Forge 2 9515
Protoss_Photon_Cannon 5 10559
Protoss_Assimilator 2 7910
Protoss_Gateway 1 6604
Protoss_Zealot 1 7303
Protoss_Cybernetics_Core 1 8044
Protoss_Dragoon 1 8923
Protoss_Stargate 1 9243
Protoss_Citadel_of_Adun 1 9434
Protoss_Corsair 1 9963
Protoss_Templar_Archives 1 10764
10764
