Protoss_Forge 1 3459
Protoss_Nexus 1 5136
Protoss_Photon_Cannon 6 10635
Protoss_Gateway 1 5439
Protoss_Assimilator 1 5905
Protoss_Zealot 5 9553
Protoss_Cybernetics_Core 1 8886
Protoss_Robotics_Facility 1 10812
10812
