Protoss_Gateway 1 2903
Protoss_Zealot 4 7550
Protoss_Assimilator 1 3864
Protoss_Cybernetics_Core 1 4931
Protoss_Stargate 1 6085
Protoss_Dragoon 1 5954
Protoss_Citadel_of_Adun 1 6589
Protoss_Corsair 1 6776
Protoss_Templar_Archives 1 8024
Protoss_Nexus 1 9727
Protoss_Dark_Templar 1 8912
Protoss_Forge 1 9486
Protoss_High_Templar 1 9878
Protoss_Photon_Cannon 2 10618
10618
