Protoss_Forge 1 2737
Protoss_Photon_Cannon 5 10589
Protoss_Gateway 1 4202
Protoss_Nexus 1 6207
Protoss_Assimilator 2 6522
Protoss_Cybernetics_Core 1 6130
Protoss_Stargate 2 10248
Protoss_Corsair 4 10056
Protoss_Robotics_Facility 1 9648
Protoss_Shuttle 1 10735
10735
