Protoss_Gateway 3 8298
Protoss_Assimilator 1 3007
Protoss_Zealot 9 9280
Protoss_Cybernetics_Core 1 4848
Protoss_Citadel_of_Adun 1 5939
Protoss_Dragoon 2 10606
Protoss_Templar_Archives 1 9211
Protoss_Forge 1 9649
Protoss_High_Templar 2 10090
Protoss_Photon_Cannon 2 10620
10620
