Protoss_Nexus 1 4637
Protoss_Gateway 4 8238
Protoss_Assimilator 1 4114
Protoss_Forge 1 4425
Protoss_Cybernetics_Core 1 5334
Protoss_Photon_Cannon 1 5404
Protoss_Zealot 15 10452
Protoss_Citadel_of_Adun 1 6528
Protoss_Templar_Archives 1 9430
Protoss_Ground_Weapons_1 1 8913
Protoss_Robotics_Facility 1 10675
Protoss_High_Templar 2 10628
10675
