Protoss_Forge 1 3213
Protoss_Nexus 1 5057
Protoss_Photon_Cannon 3 9707
Protoss_Gateway 3 8542
Protoss_Assimilator 2 6975
Protoss_Cybernetics_Core 1 5997
Protoss_Zealot 5 10000
Protoss_Citadel_of_Adun 1 7063
Protoss_Dragoon 1 7270
Protoss_Templar_Archives 1 8335
Protoss_Dark_Templar 1 9332
Protoss_High_Templar 2 9398
Protoss_Archon 1 9847
Protoss_Robotics_Facility 1 10815
10815
