Protoss_Forge 2 3910
Protoss_Nexus 1 4940
Protoss_Photon_Cannon 3 6025
Protoss_Gateway 4 10543
Protoss_Assimilator 1 7142
Protoss_Zealot 8 10185
Protoss_Cybernetics_Core 1 8246
Protoss_Citadel_of_Adun 1 9443
10543
