Protoss_Nexus 2 11041
Protoss_Gateway 3 4775
Protoss_Zealot 9 8930
Protoss_Assimilator 2 7954
Protoss_Forge 1 6505
Protoss_Cybernetics_Core 1 7558
Protoss_Photon_Cannon 4 10575
Protoss_Citadel_of_Adun 1 9822
11041
