Protoss_Gateway 2 3029
Protoss_Zealot 11 6910
Protoss_Nexus 1 8731
Protoss_Assimilator 2 9419
Protoss_Cybernetics_Core 1 8567
Protoss_Forge 1 8902
Protoss_Stargate 1 9798
Protoss_Dragoon 1 9744
Protoss_Photon_Cannon 2 10246
Protoss_Corsair 1 10496
10496
