Protoss_Forge 1 2776
Protoss_Nexus 1 5313
Protoss_Gateway 2 9717
Protoss_Assimilator 2 6847
Protoss_Photon_Cannon 3 9961
Protoss_Cybernetics_Core 1 6335
Protoss_Zealot 2 10346
Protoss_Stargate 1 7639
Protoss_Robotics_Facility 1 8882
Protoss_Corsair 2 9044
Protoss_Dragoon 1 9248
Protoss_Robotics_Support_Bay 1 9487
Protoss_Reaver 1 10678
10678
