Protoss_Forge 1 2708
Protoss_Photon_Cannon 2 10205
Protoss_Nexus 1 5515
Protoss_Gateway 5 10747
Protoss_Assimilator 2 6551
Protoss_Cybernetics_Core 1 6121
Protoss_Zealot 11 10376
Protoss_Stargate 1 7457
Protoss_Corsair 2 8796
Protoss_Citadel_of_Adun 1 8711
Protoss_Shield_Battery 1 10148
10747
