Protoss_Forge 2 4205
Protoss_Nexus 1 4930
Protoss_Gateway 2 10446
Protoss_Photon_Cannon 6 10200
Protoss_Assimilator 2 6360
Protoss_Cybernetics_Core 1 6094
Protoss_Zealot 3 8705
Protoss_Stargate 1 7343
Protoss_Dragoon 1 7258
Protoss_Robotics_Facility 1 8297
Protoss_Corsair 2 10413
10446
