Protoss_Forge 1 3284
Protoss_Nexus 1 5105
Protoss_Photon_Cannon 1 4422
Protoss_Gateway 4 8812
Protoss_Assimilator 2 10474
Protoss_Zealot 14 10502
Protoss_Cybernetics_Core 1 6394
Protoss_Citadel_of_Adun 1 7463
Protoss_Dragoon 1 8988
Protoss_Templar_Archives 1 10431
10502
