Protoss_Gateway 2 3157
Protoss_Zealot 10 6433
Protoss_Nexus 1 8110
Protoss_Assimilator 2 9592
Protoss_Cybernetics_Core 1 7784
Protoss_Forge 1 7834
Protoss_Stargate 1 9043
Protoss_Photon_Cannon 3 10655
Protoss_Citadel_of_Adun 1 9833
Protoss_Corsair 1 9908
10655
