Protoss_Forge 1 2666
Protoss_Nexus 2 10301
Protoss_Assimilator 2 6183
Protoss_Gateway 1 5327
Protoss_Photon_Cannon 7 10607
Protoss_Zealot 1 6194
Protoss_Cybernetics_Core 1 6625
Protoss_Stargate 1 7962
Protoss_Robotics_Facility 1 8590
Protoss_Corsair 1 8692
Protoss_Robotics_Support_Bay 1 9214
Protoss_Reaver 1 10690
10690
