Protoss_Forge 1 2840
Protoss_Nexus 1 5090
Protoss_Photon_Cannon 8 10670
Protoss_Gateway 4 10149
Protoss_Assimilator 2 6243
Protoss_Cybernetics_Core 1 6146
Protoss_Zealot 5 9063
Protoss_Citadel_of_Adun 1 7261
Protoss_Templar_Archives 1 8639
Protoss_High_Templar 2 9663
Protoss_Archon 1 10171
Protoss_Ground_Weapons_1 1 9931
10670
