Protoss_Gateway 2 3526
Protoss_Zealot 15 10584
Protoss_Assimilator 1 4050
Protoss_Cybernetics_Core 1 5034
Protoss_Dragoon 1 5933
Protoss_Citadel_of_Adun 1 6223
Protoss_Forge 1 7790
Protoss_Templar_Archives 1 9888
10584
