Protoss_Gateway 1 2804
Protoss_Assimilator 1 3030
Protoss_Zealot 4 6903
Protoss_Cybernetics_Core 1 5144
Protoss_Dragoon 2 8533
Protoss_Stargate 1 6708
Protoss_Citadel_of_Adun 1 6919
Protoss_Corsair 5 10135
Protoss_Templar_Archives 1 8131
Protoss_Forge 1 7985
Protoss_Photon_Cannon 3 9944
Protoss_Dark_Templar 1 10338
10338
