Protoss_Gateway 2 3343
Protoss_Zealot 9 10394
Protoss_Assimilator 2 10550
Protoss_Nexus 1 8241
Protoss_Forge 2 7689
Protoss_Cybernetics_Core 1 8277
Protoss_Photon_Cannon 2 9854
Protoss_Citadel_of_Adun 1 9330
10550
