Protoss_Forge 1 2712
Protoss_Photon_Cannon 6 10732
Protoss_Gateway 4 10553
Protoss_Nexus 1 7100
Protoss_Zealot 3 7347
Protoss_Assimilator 2 9033
Protoss_Cybernetics_Core 1 8100
Protoss_Citadel_of_Adun 1 9094
Protoss_Templar_Archives 1 10108
10732
