Protoss_Forge 1 2811
Protoss_Photon_Cannon 5 9947
Protoss_Nexus 1 6515
Protoss_Gateway 2 9719
Protoss_Assimilator 2 8542
Protoss_Cybernetics_Core 1 7230
Protoss_Zealot 2 7688
Protoss_Stargate 1 8423
Protoss_Citadel_of_Adun 1 8599
Protoss_Corsair 3 10530
Protoss_Templar_Archives 1 9886
10530
