Protoss_Gateway 2 3099
Protoss_Zealot 9 6555
Protoss_Forge 1 4915
Protoss_Photon_Cannon 3 10315
Protoss_Nexus 2 9755
Protoss_Assimilator 2 10046
Protoss_Cybernetics_Core 1 9678
10315
