Protoss_Forge 1 2574
Protoss_Nexus 1 5089
Protoss_Photon_Cannon 5 10265
Protoss_Assimilator 2 8820
Protoss_Gateway 4 10559
Protoss_Cybernetics_Core 1 6954
Protoss_Zealot 9 9808
Protoss_Citadel_of_Adun 1 8033
Protoss_Templar_Archives 1 9797
Protoss_High_Templar 1 10678
10678
