Protoss_Gateway 4 10711
Protoss_Zealot 14 10228
Protoss_Nexus 1 7189
Protoss_Forge 1 6376
Protoss_Assimilator 1 6695
Protoss_Photon_Cannon 1 7220
Protoss_Cybernetics_Core 1 7809
Protoss_Citadel_of_Adun 1 9007
10711
