Protoss_Forge 1 3203
Protoss_Photon_Cannon 2 4872
Protoss_Nexus 1 5511
Protoss_Gateway 6 10001
Protoss_Assimilator 2 7239
Protoss_Cybernetics_Core 1 6588
Protoss_Zealot 6 10298
Protoss_Stargate 1 7885
Protoss_Dragoon 1 7864
Protoss_Citadel_of_Adun 1 8674
Protoss_Corsair 1 8750
Protoss_Robotics_Facility 1 11110
11110
