Protoss_Forge 1 2772
Protoss_Photon_Cannon 3 10192
Protoss_Nexus 1 5904
Protoss_Gateway 4 9259
Protoss_Assimilator 1 5392
Protoss_Zealot 11 10094
Protoss_Cybernetics_Core 1 6443
Protoss_Citadel_of_Adun 1 7599
10192
