Protoss_Forge 1 2888
Protoss_Nexus 1 5280
Protoss_Gateway 5 9814
Protoss_Photon_Cannon 3 10721
Protoss_Assimilator 2 7304
Protoss_Zealot 12 10379
Protoss_Cybernetics_Core 1 6863
Protoss_Citadel_of_Adun 1 8066
Protoss_Templar_Archives 1 10528
10721
