Protoss_Forge 2 8593
Protoss_Photon_Cannon 3 9542
Protoss_Gateway 2 10465
Protoss_Assimilator 1 6223
Protoss_Zealot 3 10508
Protoss_Cybernetics_Core 1 7073
Protoss_Stargate 1 8339
Protoss_Citadel_of_Adun 1 8686
Protoss_Corsair 2 9658
Protoss_Templar_Archives 1 10540
10540
