Protoss_Forge 1 3294
Protoss_Nexus 1 5325
Protoss_Photon_Cannon 2 4838
Protoss_Gateway 2 9528
Protoss_Assimilator 2 8290
Protoss_Zealot 5 10502
Protoss_Cybernetics_Core 1 7189
Protoss_Dragoon 1 8610
Protoss_Citadel_of_Adun 1 9039
Protoss_Stargate 2 10096
10502
