Protoss_Forge 1 2802
Protoss_Nexus 1 4897
Protoss_Photon_Cannon 3 10637
Protoss_Gateway 3 9071
Protoss_Assimilator 1 5269
Protoss_Cybernetics_Core 1 6239
Protoss_Zealot 8 10070
Protoss_Dragoon 1 7584
Protoss_Citadel_of_Adun 1 8709
Protoss_Templar_Archives 1 10422
10637
