Protoss_Forge 1 2958
Protoss_Nexus 1 5241
Protoss_Photon_Cannon 7 10676
Protoss_Gateway 4 10467
Protoss_Assimilator 2 7290
Protoss_Cybernetics_Core 1 6961
Protoss_Zealot 7 9818
Protoss_Citadel_of_Adun 1 8191
Protoss_Templar_Archives 1 9771
10676
