Protoss_Nexus 1 4699
Protoss_Forge 1 4088
Protoss_Gateway 4 10664
Protoss_Assimilator 2 6121
Protoss_Photon_Cannon 5 10390
Protoss_Cybernetics_Core 1 6291
Protoss_Zealot 3 9010
Protoss_Stargate 1 7778
Protoss_Citadel_of_Adun 1 7658
Protoss_Dragoon 1 7782
Protoss_Corsair 3 10248
Protoss_Templar_Archives 1 9044
Protoss_Dark_Templar 2 9912
Protoss_High_Templar 2 10664
10664
