Protoss_Forge 1 3097
Protoss_Photon_Cannon 3 4777
Protoss_Nexus 1 6305
Protoss_Gateway 3 9245
Protoss_Assimilator 3 10208
Protoss_Zealot 6 10086
Protoss_Cybernetics_Core 1 6816
Protoss_Stargate 1 7990
Protoss_Citadel_of_Adun 1 8332
Protoss_Dragoon 1 8438
Protoss_Corsair 2 9300
10208
