Protoss_Forge 1 2892
Protoss_Photon_Cannon 4 8805
Protoss_Nexus 1 5639
Protoss_Gateway 2 10466
Protoss_Assimilator 2 6976
Protoss_Cybernetics_Core 1 5995
Protoss_Zealot 2 7482
Protoss_Stargate 1 7156
Protoss_Corsair 4 10208
Protoss_Citadel_of_Adun 1 8367
Protoss_Templar_Archives 1 9402
Protoss_Dark_Templar 1 10626
10626
