Protoss_Forge 2 8890
Protoss_Nexus 1 5060
Protoss_Photon_Cannon 3 10221
Protoss_Gateway 4 9983
Protoss_Assimilator 2 7008
Protoss_Cybernetics_Core 1 6751
Protoss_Zealot 5 9736
Protoss_Stargate 1 7954
Protoss_Citadel_of_Adun 1 8115
Protoss_Dragoon 1 8334
Protoss_Corsair 1 8642
Protoss_Templar_Archives 1 9279
10221
