Protoss_Forge 2 9901
Protoss_Photon_Cannon 2 10587
Protoss_Nexus 1 5571
Protoss_Gateway 4 9628
Protoss_Assimilator 2 7365
Protoss_Cybernetics_Core 1 6099
Protoss_Zealot 3 8740
Protoss_Stargate 1 7398
Protoss_Citadel_of_Adun 1 7964
Protoss_Dragoon 1 8138
Protoss_Corsair 1 8146
Protoss_Templar_Archives 1 8973
Protoss_Dark_Templar 3 10622
Protoss_High_Templar 2 10564
10622
