Protoss_Forge 1 3300
Protoss_Nexus 1 5273
Protoss_Photon_Cannon 2 4738
Protoss_Gateway 4 9416
Protoss_Assimilator 2 7345
Protoss_Cybernetics_Core 1 6465
Protoss_Zealot 4 8736
Protoss_Stargate 1 7795
Protoss_Dragoon 8 10482
Protoss_Corsair 4 10532
10532
