Protoss_Forge 2 9243
Protoss_Nexus 1 4970
Protoss_Photon_Cannon 4 9090
Protoss_Gateway 4 10855
Protoss_Assimilator 2 6909
Protoss_Cybernetics_Core 1 6346
Protoss_Zealot 5 8946
Protoss_Stargate 1 7562
Protoss_Citadel_of_Adun 1 8075
Protoss_Corsair 1 8340
Protoss_Templar_Archives 1 9123
Protoss_Dark_Templar 1 9968
Protoss_High_Templar 1 10746
10855
