Protoss_Forge 1 2660
Protoss_Photon_Cannon 3 10284
Protoss_Nexus 1 5793
Protoss_Gateway 2 8923
Protoss_Assimilator 2 7936
Protoss_Zealot 7 10518
Protoss_Cybernetics_Core 1 6481
Protoss_Dragoon 1 7402
Protoss_Stargate 1 8094
Protoss_Citadel_of_Adun 1 8401
Protoss_Corsair 3 10310
Protoss_Templar_Archives 1 10099
10518
