Protoss_Nexus 1 4279
Protoss_Forge 1 3410
Protoss_Gateway 4 10729
Protoss_Photon_Cannon 3 9914
Protoss_Assimilator 2 7313
Protoss_Zealot 9 9850
Protoss_Cybernetics_Core 1 6027
Protoss_Stargate 1 7343
Protoss_Corsair 3 9964
Protoss_Citadel_of_Adun 1 8596
Protoss_Templar_Archives 1 10483
10729
