Protoss_Nexus 2 10273
Protoss_Forge 1 4344
Protoss_Photon_Cannon 5 10637
Protoss_Gateway 3 8294
Protoss_Assimilator 2 10231
Protoss_Cybernetics_Core 1 6495
Protoss_Zealot 12 10578
Protoss_Citadel_of_Adun 1 7621
Protoss_Templar_Archives 1 10620
10637
