Protoss_Forge 1 3606
Protoss_Photon_Cannon 5 10029
Protoss_Nexus 1 6837
Protoss_Gateway 1 6063
Protoss_Assimilator 2 9158
Protoss_Zealot 5 9784
Protoss_Cybernetics_Core 1 7832
Protoss_Stargate 1 8987
Protoss_Corsair 2 10442
Protoss_Robotics_Facility 1 10621
10621
