Protoss_Forge 1 2782
Protoss_Photon_Cannon 4 9852
Protoss_Nexus 1 5909
Protoss_Gateway 3 8984
Protoss_Assimilator 1 5252
Protoss_Zealot 7 10170
Protoss_Cybernetics_Core 1 6537
Protoss_Dragoon 1 7560
Protoss_Stargate 1 8136
Protoss_Citadel_of_Adun 1 8556
Protoss_Corsair 1 8826
10170
