Protoss_Forge 1 2617
Protoss_Nexus 1 5029
Protoss_Photon_Cannon 1 4692
Protoss_Gateway 4 9495
Protoss_Assimilator 2 7069
Protoss_Zealot 4 8974
Protoss_Cybernetics_Core 1 6514
Protoss_Stargate 1 8084
Protoss_Citadel_of_Adun 1 8043
Protoss_Corsair 2 9400
Protoss_Templar_Archives 1 9565
Protoss_Dragoon 3 10620
Protoss_Ground_Weapons_1 1 9919
10620
