Protoss_Forge 1 2733
Protoss_Photon_Cannon 9 10621
Protoss_Nexus 1 5912
Protoss_Gateway 4 10574
Protoss_Assimilator 1 6003
Protoss_Zealot 4 9538
Protoss_Cybernetics_Core 1 7413
Protoss_Stargate 1 9323
Protoss_Citadel_of_Adun 1 9789
Protoss_Corsair 1 10128
10621
