Protoss_Gateway 2 3044
Protoss_Zealot 15 8762
Protoss_Assimilator 1 6254
Protoss_Cybernetics_Core 1 7449
Protoss_Forge 1 8226
Protoss_Stargate 1 9112
Protoss_Photon_Cannon 1 9306
Protoss_Corsair 1 9804
Protoss_Nexus 1 11750
11750
