Protoss_Forge 1 2690
Protoss_Photon_Cannon 3 10661
Protoss_Nexus 1 5925
Protoss_Gateway 3 9271
Protoss_Assimilator 2 10222
Protoss_Zealot 10 10136
Protoss_Cybernetics_Core 1 6406
Protoss_Stargate 1 7870
Protoss_Citadel_of_Adun 1 8377
Protoss_Corsair 1 8926
10661
