Protoss_Forge 1 2873
Protoss_Nexus 1 5094
Protoss_Gateway 2 8558
Protoss_Photon_Cannon 3 10094
Protoss_Assimilator 2 7519
Protoss_Zealot 9 10564
Protoss_Cybernetics_Core 1 6021
Protoss_Stargate 1 7674
Protoss_Citadel_of_Adun 1 7997
Protoss_Corsair 4 10416
Protoss_Templar_Archives 1 10382
10564
