Protoss_Gateway 1 2712
Protoss_Forge 1 3235
Protoss_Zealot 12 10222
Protoss_Photon_Cannon 9 9538
Protoss_Nexus 1 8587
Protoss_Assimilator 1 7548
Protoss_Cybernetics_Core 1 8973
Protoss_Citadel_of_Adun 1 10686
10686
