Protoss_Forge 2 10504
Protoss_Photon_Cannon 5 10533
Protoss_Nexus 1 5447
Protoss_Gateway 3 9859
Protoss_Assimilator 2 6657
Protoss_Cybernetics_Core 1 6339
Protoss_Zealot 5 9890
Protoss_Stargate 1 7880
Protoss_Citadel_of_Adun 1 8350
Protoss_Corsair 2 9290
Protoss_Templar_Archives 1 9347
Protoss_Dark_Templar 1 10372
10533
