Protoss_Nexus 1 4359
Protoss_Forge 1 3388
Protoss_Photon_Cannon 1 4239
Protoss_Gateway 4 10641
Protoss_Assimilator 2 6044
Protoss_Cybernetics_Core 1 5853
Protoss_Zealot 3 6954
Protoss_Stargate 2 7370
Protoss_Citadel_of_Adun 1 7690
Protoss_Corsair 7 9670
Protoss_Templar_Archives 1 8875
Protoss_Dark_Templar 1 10200
10641
