Protoss_Forge 1 3025
Protoss_Photon_Cannon 1 3903
Protoss_Nexus 1 5305
Protoss_Gateway 4 8562
Protoss_Assimilator 2 8705
Protoss_Cybernetics_Core 1 6099
Protoss_Zealot 13 9842
Protoss_Citadel_of_Adun 1 7269
Protoss_Stargate 2 10648
10648
