Protoss_Forge 1 2837
Protoss_Photon_Cannon 3 9038
Protoss_Nexus 1 5736
Protoss_Gateway 4 9900
Protoss_Assimilator 2 7529
Protoss_Cybernetics_Core 1 6593
Protoss_Zealot 5 10144
Protoss_Stargate 1 7728
Protoss_Dragoon 1 8174
Protoss_Citadel_of_Adun 1 8713
Protoss_Corsair 2 10282
10282
