Protoss_Forge 1 3133
Protoss_Nexus 1 4995
Protoss_Photon_Cannon 2 10672
Protoss_Gateway 4 10255
Protoss_Assimilator 2 6749
Protoss_Cybernetics_Core 1 5933
Protoss_Zealot 3 8818
Protoss_Stargate 1 7079
Protoss_Dragoon 1 7128
Protoss_Citadel_of_Adun 1 7695
Protoss_Corsair 3 9186
Protoss_Templar_Archives 1 8863
Protoss_Dark_Templar 2 9746
Protoss_High_Templar 2 10498
10672
