Protoss_Forge 1 2994
Protoss_Photon_Cannon 7 10531
Protoss_Nexus 1 6961
Protoss_Gateway 2 9335
Protoss_Assimilator 2 8750
Protoss_Cybernetics_Core 1 7621
Protoss_Zealot 6 10568
Protoss_Stargate 1 8756
Protoss_Citadel_of_Adun 1 9673
Protoss_Corsair 1 9460
10568
