Protoss_Forge 1 2924
Protoss_Photon_Cannon 4 8841
Protoss_Nexus 1 5409
Protoss_Gateway 2 10051
Protoss_Assimilator 2 6437
Protoss_Cybernetics_Core 1 6355
Protoss_Zealot 5 9560
Protoss_Stargate 1 7562
Protoss_Corsair 3 10346
Protoss_Citadel_of_Adun 1 9153
Protoss_Templar_Archives 1 10313
10346
