Protoss_Forge 1 2891
Protoss_Nexus 1 5154
Protoss_Photon_Cannon 3 9953
Protoss_Gateway 2 8662
Protoss_Assimilator 2 6940
Protoss_Cybernetics_Core 1 6419
Protoss_Zealot 7 10176
Protoss_Stargate 1 7589
Protoss_Citadel_of_Adun 1 8059
Protoss_Corsair 4 10366
Protoss_Templar_Archives 1 10405
10405
