Protoss_Forge 1 2752
Protoss_Nexus 1 5058
Protoss_Gateway 4 9382
Protoss_Assimilator 1 4756
Protoss_Photon_Cannon 5 9638
Protoss_Cybernetics_Core 1 5908
Protoss_Zealot 14 10478
Protoss_Citadel_of_Adun 1 6922
10478
