Protoss_Forge 1 2913
Protoss_Photon_Cannon 3 10360
Protoss_Nexus 1 5905
Protoss_Gateway 4 9608
Protoss_Assimilator 2 9494
Protoss_Cybernetics_Core 1 6361
Protoss_Zealot 9 9730
Protoss_Citadel_of_Adun 1 7412
Protoss_Dragoon 3 10684
10684
