Protoss_Forge 2 4365
Protoss_Nexus 1 4724
Protoss_Gateway 4 8544
Protoss_Assimilator 2 8744
Protoss_Cybernetics_Core 1 5448
Protoss_Photon_Cannon 2 9662
Protoss_Zealot 15 10547
Protoss_Stargate 1 6860
Protoss_Corsair 2 10182
Protoss_Citadel_of_Adun 1 8174
10547
