Protoss_Nexus 1 4673
Protoss_Forge 1 3740
Protoss_Assimilator 1 4297
Protoss_Gateway 4 7693
Protoss_Photon_Cannon 1 5366
Protoss_Cybernetics_Core 1 5787
Protoss_Zealot 17 10258
Protoss_Citadel_of_Adun 1 7020
Protoss_Stargate 2 9865
Protoss_Ground_Weapons_1 1 9305
Protoss_Corsair 2 10546
10546
