Protoss_Forge 1 3202
Protoss_Nexus 1 4913
Protoss_Photon_Cannon 1 4160
Protoss_Gateway 2 10064
Protoss_Assimilator 2 6335
Protoss_Cybernetics_Core 1 5795
Protoss_Zealot 4 8020
Protoss_Stargate 2 8681
Protoss_Citadel_of_Adun 1 7487
Protoss_Corsair 7 10506
Protoss_Templar_Archives 1 8557
Protoss_Dark_Templar 2 10210
10506
