Protoss_Nexus 1 4647
Protoss_Gateway 4 8971
Protoss_Assimilator 1 4147
Protoss_Forge 1 4715
Protoss_Zealot 14 10168
Protoss_Photon_Cannon 3 10567
Protoss_Cybernetics_Core 1 5971
Protoss_Stargate 1 7118
Protoss_Corsair 2 10150
Protoss_Citadel_of_Adun 1 8292
10567
