Protoss_Nexus 1 4357
Protoss_Forge 1 3484
Protoss_Photon_Cannon 2 9518
Protoss_Gateway 3 10803
Protoss_Assimilator 2 9981
Protoss_Cybernetics_Core 1 5925
Protoss_Zealot 8 10466
Protoss_Stargate 1 7467
Protoss_Corsair 4 10228
Protoss_Citadel_of_Adun 1 8735
10803
