Protoss_Forge 1 2702
Protoss_Photon_Cannon 2 9300
Protoss_Nexus 1 5267
Protoss_Gateway 2 10823
Protoss_Assimilator 2 7196
Protoss_Cybernetics_Core 1 5881
Protoss_Zealot 4 8944
Protoss_Stargate 1 7140
Protoss_Citadel_of_Adun 1 7807
Protoss_Corsair 4 9970
Protoss_Templar_Archives 1 8899
Protoss_Dark_Templar 1 9834
Protoss_Arbiter_Tribunal 1 10129
10823
