Protoss_Forge 1 3107
Protoss_Photon_Cannon 1 4007
Protoss_Nexus 1 5503
Protoss_Gateway 2 5149
Protoss_Assimilator 2 10158
Protoss_Zealot 15 10494
Protoss_Cybernetics_Core 1 6975
Protoss_Stargate 1 8162
Protoss_Corsair 3 10304
Protoss_Citadel_of_Adun 1 9794
10494
