Protoss_Nexus 1 4303
Protoss_Forge 1 3380
Protoss_Photon_Cannon 3 6580
Protoss_Gateway 2 9973
Protoss_Assimilator 2 6852
Protoss_Cybernetics_Core 1 5753
Protoss_Zealot 4 10272
Protoss_Stargate 2 7752
Protoss_Corsair 8 10424
Protoss_Citadel_of_Adun 1 9617
10424
