Protoss_Nexus 1 4351
Protoss_Forge 1 3404
Protoss_Photon_Cannon 4 9874
Protoss_Gateway 1 4789
Protoss_Assimilator 2 6286
Protoss_Cybernetics_Core 1 5806
Protoss_Zealot 3 7140
Protoss_Stargate 1 6963
Protoss_Robotics_Facility 1 8065
Protoss_Corsair 5 10266
Protoss_Robotics_Support_Bay 1 8660
Protoss_Citadel_of_Adun 1 9390
Protoss_Shuttle 1 9715
Protoss_Templar_Archives 1 10401
Protoss_Reaver 1 10920
10920
