Protoss_Gateway 2 3491
Protoss_Zealot 10 7746
Protoss_Assimilator 1 5060
Protoss_Cybernetics_Core 1 6389
Protoss_Stargate 1 7540
Protoss_Citadel_of_Adun 1 7597
Protoss_Corsair 1 8224
Protoss_Templar_Archives 1 8853
Protoss_Nexus 1 10353
Protoss_Forge 1 9340
Protoss_Dark_Templar 1 9918
Protoss_Photon_Cannon 2 10444
Protoss_High_Templar 1 10650
10650
