Protoss_Forge 1 2680
Protoss_Photon_Cannon 9 10096
Protoss_Nexus 1 5647
Protoss_Gateway 3 8348
Protoss_Assimilator 2 8350
Protoss_Zealot 5 7946
Protoss_Cybernetics_Core 1 6307
Protoss_Citadel_of_Adun 1 7423
Protoss_Templar_Archives 1 8793
Protoss_High_Templar 3 10490
Protoss_Dark_Templar 1 9658
Protoss_Archon 1 10198
10490
