Protoss_Forge 1 3222
Protoss_Nexus 1 5069
Protoss_Photon_Cannon 3 10283
Protoss_Gateway 4 10736
Protoss_Assimilator 2 8264
Protoss_Zealot 8 10050
Protoss_Cybernetics_Core 1 6205
Protoss_Stargate 1 7567
Protoss_Citadel_of_Adun 1 8177
Protoss_Corsair 2 9236
Protoss_Templar_Archives 1 10808
10808
