Protoss_Forge 1 2887
Protoss_Photon_Cannon 9 7173
Protoss_Nexus 1 8455
Protoss_Gateway 1 8027
Protoss_Assimilator 2 10251
Protoss_Cybernetics_Core 1 9383
Protoss_Dragoon 1 10218
Protoss_Stargate 1 10530
10530
