Protoss_Gateway 2 3363
Protoss_Zealot 12 9854
Protoss_Assimilator 1 5280
Protoss_Cybernetics_Core 1 6506
Protoss_Forge 1 7120
Protoss_Stargate 1 8070
Protoss_Photon_Cannon 3 10487
Protoss_Citadel_of_Adun 1 8696
Protoss_Corsair 2 9384
10487
