Protoss_Forge 1 2579
Protoss_Photon_Cannon 3 9318
Protoss_Nexus 1 5245
Protoss_Gateway 4 10339
Protoss_Assimilator 2 6875
Protoss_Zealot 4 7730
Protoss_Cybernetics_Core 1 6419
Protoss_Stargate 1 7714
Protoss_Citadel_of_Adun 1 7907
Protoss_Corsair 1 8680
Protoss_Templar_Archives 1 9071
Protoss_Dark_Templar 1 9920
Protoss_High_Templar 1 10672
10672
