Protoss_Nexus 1 4481
Protoss_Forge 1 3594
Protoss_Photon_Cannon 2 9372
Protoss_Gateway 3 8004
Protoss_Assimilator 3 9082
Protoss_Cybernetics_Core 1 5891
Protoss_Zealot 12 10192
Protoss_Stargate 1 7310
Protoss_Citadel_of_Adun 1 7664
Protoss_Corsair 4 10322
Protoss_Ground_Weapons_1 1 9681
10322
