Protoss_Forge 1 2893
Protoss_Photon_Cannon 3 10364
Protoss_Nexus 1 8243
Protoss_Gateway 1 7809
Protoss_Assimilator 1 7921
Protoss_Zealot 2 9984
Protoss_Cybernetics_Core 1 9377
10364
