Protoss_Gateway 2 3411
Protoss_Zealot 10 10594
Protoss_Forge 1 5328
Protoss_Nexus 1 7845
Protoss_Photon_Cannon 2 8733
Protoss_Assimilator 2 7816
Protoss_Cybernetics_Core 1 7911
Protoss_Stargate 1 9170
Protoss_Citadel_of_Adun 1 9551
Protoss_Corsair 1 9868
Protoss_Templar_Archives 1 10545
10594
