Protoss_Forge 1 3167
Protoss_Photon_Cannon 2 4407
Protoss_Nexus 1 5887
Protoss_Gateway 4 10373
Protoss_Assimilator 2 7746
Protoss_Zealot 10 10568
Protoss_Cybernetics_Core 1 6541
Protoss_Stargate 1 7676
Protoss_Citadel_of_Adun 1 8287
Protoss_Corsair 2 9174
10568
