Protoss_Forge 1 3133
Protoss_Photon_Cannon 4 10483
Protoss_Nexus 1 5905
Protoss_Gateway 1 5541
Protoss_Assimilator 2 6856
Protoss_Zealot 6 9439
Protoss_Cybernetics_Core 1 6537
Protoss_Stargate 2 8641
Protoss_Corsair 6 10490
Protoss_Citadel_of_Adun 1 10397
10490
