Protoss_Forge 2 4330
Protoss_Nexus 1 4816
Protoss_Gateway 2 7517
Protoss_Assimilator 2 7428
Protoss_Photon_Cannon 2 9602
Protoss_Cybernetics_Core 1 5707
Protoss_Zealot 8 10066
Protoss_Stargate 1 7068
Protoss_Corsair 3 10308
Protoss_Citadel_of_Adun 1 8163
10308
