Protoss_Forge 1 3024
Protoss_Photon_Cannon 4 9472
Protoss_Nexus 1 5955
Protoss_Gateway 1 5458
Protoss_Assimilator 2 6667
Protoss_Zealot 3 8764
Protoss_Cybernetics_Core 1 6492
Protoss_Stargate 1 7726
Protoss_Dragoon 1 7700
Protoss_Robotics_Facility 1 8917
Protoss_Corsair 4 10562
Protoss_Robotics_Support_Bay 1 9535
10562
