Protoss_Forge 1 2893
Protoss_Photon_Cannon 3 9696
Protoss_Nexus 1 5957
Protoss_Gateway 4 10823
Protoss_Assimilator 2 7022
Protoss_Cybernetics_Core 1 6389
Protoss_Zealot 3 8212
Protoss_Stargate 1 7633
Protoss_Dragoon 1 7610
Protoss_Citadel_of_Adun 1 8224
Protoss_Corsair 3 9782
Protoss_Templar_Archives 1 9314
Protoss_Dark_Templar 2 10160
10823
