Protoss_Forge 1 3049
Protoss_Photon_Cannon 3 9584
Protoss_Nexus 1 5255
Protoss_Gateway 4 10377
Protoss_Assimilator 2 7960
Protoss_Cybernetics_Core 1 5817
Protoss_Zealot 4 8420
Protoss_Stargate 1 6958
Protoss_Citadel_of_Adun 1 7481
Protoss_Corsair 3 9810
Protoss_Templar_Archives 1 8777
Protoss_High_Templar 2 10596
10596
