Protoss_Forge 1 3192
Protoss_Nexus 1 5057
Protoss_Photon_Cannon 3 9985
Protoss_Gateway 2 7978
Protoss_Assimilator 2 9338
Protoss_Cybernetics_Core 1 6773
Protoss_Zealot 9 10372
Protoss_Stargate 1 7946
Protoss_Citadel_of_Adun 1 8504
Protoss_Corsair 2 9536
Protoss_Templar_Archives 1 10745
10745
