Protoss_Nexus 1 4649
Protoss_Forge 1 3763
Protoss_Photon_Cannon 5 10124
Protoss_Gateway 3 9703
Protoss_Assimilator 2 7383
Protoss_Cybernetics_Core 1 7326
Protoss_Zealot 4 10162
Protoss_Stargate 1 8832
Protoss_Citadel_of_Adun 1 9406
Protoss_Corsair 2 10432
Protoss_Templar_Archives 1 10403
10432
