Protoss_Forge 1 3127
Protoss_Nexus 1 4977
Protoss_Photon_Cannon 4 8870
Protoss_Gateway 4 10529
Protoss_Assimilator 2 8124
Protoss_Cybernetics_Core 1 6255
Protoss_Zealot 6 9958
Protoss_Stargate 1 7640
Protoss_Dragoon 1 7850
Protoss_Citadel_of_Adun 1 8360
Protoss_Corsair 1 8398
Protoss_Templar_Archives 1 9981
10529
