Protoss_Forge 1 2967
Protoss_Nexus 1 5220
Protoss_Gateway 4 9627
Protoss_Assimilator 2 6366
Protoss_Photon_Cannon 3 10462
Protoss_Cybernetics_Core 1 5797
Protoss_Zealot 4 8794
Protoss_Stargate 1 7040
Protoss_Citadel_of_Adun 1 7526
Protoss_Dragoon 1 7442
Protoss_Corsair 4 10346
Protoss_Templar_Archives 1 8618
Protoss_Dark_Templar 1 9560
10462
