Protoss_Forge 1 2771
Protoss_Nexus 1 4993
Protoss_Photon_Cannon 1 4312
Protoss_Gateway 5 10383
Protoss_Assimilator 2 5627
Protoss_Cybernetics_Core 1 5769
Protoss_Zealot 1 6068
Protoss_Stargate 1 7052
Protoss_Citadel_of_Adun 1 7488
Protoss_Corsair 2 8420
Protoss_Templar_Archives 1 8489
Protoss_Dark_Templar 2 10204
Protoss_High_Templar 2 10156
10383
