Protoss_Gateway 3 10868
Protoss_Zealot 11 10326
Protoss_Nexus 1 6042
Protoss_Forge 1 5273
Protoss_Photon_Cannon 5 8850
Protoss_Assimilator 2 10047
Protoss_Cybernetics_Core 1 7521
Protoss_Dragoon 2 10336
Protoss_Robotics_Facility 1 9553
Protoss_Shield_Battery 1 8970
Protoss_Citadel_of_Adun 1 10172
Protoss_Stargate 1 10423
10868
