Protoss_Forge 1 2662
Protoss_Photon_Cannon 3 7047
Protoss_Nexus 1 6283
Protoss_Gateway 5 9396
Protoss_Assimilator 2 7632
Protoss_Cybernetics_Core 1 7119
Protoss_Zealot 12 10512
Protoss_Citadel_of_Adun 1 8113
Protoss_Templar_Archives 1 9898
10512
