Protoss_Gateway 3 10301
Protoss_Zealot 9 10590
Protoss_Nexus 1 5643
Protoss_Forge 1 4820
Protoss_Photon_Cannon 2 7210
Protoss_Assimilator 2 7746
Protoss_Cybernetics_Core 1 8540
Protoss_Citadel_of_Adun 1 9558
Protoss_Templar_Archives 1 10621
10621
