Protoss_Forge 1 2558
Protoss_Photon_Cannon 3 9631
Protoss_Nexus 1 6006
Protoss_Gateway 5 9455
Protoss_Assimilator 3 10595
Protoss_Zealot 11 10426
Protoss_Cybernetics_Core 1 6729
Protoss_Stargate 1 8144
Protoss_Dragoon 1 8006
Protoss_Citadel_of_Adun 1 8662
10595
