Protoss_Forge 1 3061
Protoss_Photon_Cannon 5 10645
Protoss_Nexus 1 6429
Protoss_Gateway 2 10286
Protoss_Assimilator 2 7376
Protoss_Zealot 4 10296
Protoss_Cybernetics_Core 1 8170
Protoss_Dragoon 1 9092
Protoss_Citadel_of_Adun 1 9380
Protoss_Templar_Archives 1 10553
10645
