Protoss_Forge 1 2784
Protoss_Nexus 1 4949
Protoss_Photon_Cannon 3 10502
Protoss_Gateway 1 5012
Protoss_Assimilator 2 8803
Protoss_Zealot 4 9758
Protoss_Cybernetics_Core 1 6537
Protoss_Stargate 1 8273
Protoss_Corsair 2 9824
10502
