Protoss_Forge 1 2965
Protoss_Nexus 1 5047
Protoss_Photon_Cannon 2 8360
Protoss_Gateway 4 9173
Protoss_Assimilator 2 6838
Protoss_Cybernetics_Core 1 6448
Protoss_Zealot 11 10544
Protoss_Stargate 1 7584
Protoss_Dragoon 1 7336
Protoss_Citadel_of_Adun 1 7999
Protoss_Corsair 1 8266
10544
