Protoss_Forge 1 2567
Protoss_Photon_Cannon 3 4524
Protoss_Nexus 1 6081
Protoss_Gateway 3 9300
Protoss_Assimilator 2 6819
Protoss_Cybernetics_Core 1 6425
Protoss_Zealot 6 9470
Protoss_Citadel_of_Adun 1 7504
Protoss_Stargate 1 8080
Protoss_Corsair 3 10540
Protoss_Templar_Archives 1 10201
10540
