Protoss_Forge 2 4266
Protoss_Nexus 1 4693
Protoss_Gateway 3 10593
Protoss_Assimilator 2 6904
Protoss_Photon_Cannon 3 10158
Protoss_Cybernetics_Core 1 5922
Protoss_Zealot 8 10550
Protoss_Stargate 1 7154
Protoss_Dragoon 1 7214
Protoss_Citadel_of_Adun 1 8105
Protoss_Corsair 2 9014
Protoss_Templar_Archives 1 9715
10593
