Protoss_Forge 2 9639
Protoss_Photon_Cannon 4 9162
Protoss_Nexus 1 6168
Protoss_Gateway 2 10210
Protoss_Assimilator 2 7333
Protoss_Zealot 4 9416
Protoss_Cybernetics_Core 1 6951
Protoss_Stargate 1 8156
Protoss_Citadel_of_Adun 1 8991
10210
