Protoss_Forge 1 2870
Protoss_Photon_Cannon 7 10657
Protoss_Nexus 1 5949
Protoss_Gateway 1 5377
Protoss_Assimilator 2 7220
Protoss_Cybernetics_Core 1 6412
Protoss_Zealot 4 8958
Protoss_Stargate 1 7573
Protoss_Citadel_of_Adun 1 8043
Protoss_Dragoon 1 8350
Protoss_Corsair 2 9620
Protoss_Templar_Archives 1 9129
Protoss_High_Templar 1 10134
10657
