Protoss_Forge 1 2868
Protoss_Nexus 1 5105
Protoss_Gateway 5 9701
Protoss_Assimilator 2 10343
Protoss_Photon_Cannon 3 8438
Protoss_Zealot 4 10498
Protoss_Cybernetics_Core 1 6335
Protoss_Dragoon 10 10696
Protoss_Robotics_Facility 1 10744
10744
