Protoss_Forge 1 2714
Protoss_Photon_Cannon 5 8173
Protoss_Nexus 1 5620
Protoss_Gateway 6 10799
Protoss_Assimilator 2 7296
Protoss_Cybernetics_Core 1 6279
Protoss_Zealot 4 10084
Protoss_Stargate 1 7578
Protoss_Citadel_of_Adun 1 7989
Protoss_Corsair 1 8320
Protoss_Templar_Archives 1 9261
Protoss_Robotics_Facility 1 10447
Protoss_High_Templar 2 10098
Protoss_Dark_Templar 1 10176
10799
