Protoss_Forge 1 3282
Protoss_Photon_Cannon 4 9645
Protoss_Nexus 1 5889
Protoss_Gateway 3 10690
Protoss_Assimilator 2 7391
Protoss_Zealot 3 10172
Protoss_Cybernetics_Core 1 6560
Protoss_Stargate 1 7964
Protoss_Dragoon 2 8634
Protoss_Citadel_of_Adun 1 8605
Protoss_Corsair 3 10288
Protoss_Templar_Archives 1 9718
Protoss_Dark_Templar 1 10556
10690
