Protoss_Forge 1 2915
Protoss_Nexus 1 5030
Protoss_Photon_Cannon 2 10178
Protoss_Gateway 3 9264
Protoss_Assimilator 2 7438
Protoss_Zealot 8 10366
Protoss_Cybernetics_Core 1 6449
Protoss_Stargate 1 7693
Protoss_Citadel_of_Adun 1 8283
Protoss_Corsair 2 9618
Protoss_Templar_Archives 1 9999
10366
