Protoss_Forge 1 2814
Protoss_Nexus 1 5263
Protoss_Gateway 4 8699
Protoss_Assimilator 2 8611
Protoss_Zealot 10 10298
Protoss_Photon_Cannon 4 10198
Protoss_Cybernetics_Core 1 6228
Protoss_Dragoon 1 7178
Protoss_Citadel_of_Adun 1 7431
Protoss_Templar_Archives 1 9387
Protoss_High_Templar 2 10416
Protoss_Dark_Templar 1 10426
Protoss_Ground_Weapons_1 1 9783
10426
