Protoss_Forge 1 2590
Protoss_Nexus 1 5015
Protoss_Photon_Cannon 4 10139
Protoss_Gateway 3 9557
Protoss_Assimilator 2 6959
Protoss_Zealot 8 10282
Protoss_Cybernetics_Core 1 6582
Protoss_Stargate 1 7873
Protoss_Citadel_of_Adun 1 8589
Protoss_Corsair 3 10110
10282
