Protoss_Forge 1 2830
Protoss_Photon_Cannon 4 8938
Protoss_Nexus 1 5809
Protoss_Gateway 2 10201
Protoss_Assimilator 2 7440
Protoss_Cybernetics_Core 1 6199
Protoss_Zealot 3 9498
Protoss_Stargate 1 7484
Protoss_Corsair 3 9614
Protoss_Citadel_of_Adun 1 9557
Protoss_Templar_Archives 1 10651
10651
