Protoss_Forge 1 3012
Protoss_Photon_Cannon 2 7988
Protoss_Nexus 1 5339
Protoss_Gateway 2 7487
Protoss_Assimilator 2 7514
Protoss_Cybernetics_Core 1 5989
Protoss_Zealot 10 10466
Protoss_Stargate 1 7221
Protoss_Citadel_of_Adun 1 7307
Protoss_Corsair 3 10118
10466
