Protoss_Forge 1 2710
Protoss_Nexus 1 4945
Protoss_Photon_Cannon 2 4583
Protoss_Gateway 2 9450
Protoss_Assimilator 2 7033
Protoss_Cybernetics_Core 1 6239
Protoss_Zealot 7 10300
Protoss_Stargate 1 7394
Protoss_Dragoon 1 7420
Protoss_Corsair 4 9950
Protoss_Citadel_of_Adun 1 8742
Protoss_Templar_Archives 1 10047
10300
