Protoss_Forge 1 2831
Protoss_Photon_Cannon 5 9949
Protoss_Nexus 1 5301
Protoss_Gateway 1 5209
Protoss_Assimilator 2 7526
Protoss_Zealot 4 9876
Protoss_Cybernetics_Core 1 6285
Protoss_Dragoon 1 7262
Protoss_Stargate 1 7622
Protoss_Corsair 4 10196
Protoss_Citadel_of_Adun 1 8817
Protoss_Templar_Archives 1 10249
10249
