Protoss_Forge 2 6065
Protoss_Photon_Cannon 5 7041
Protoss_Gateway 2 8024
Protoss_Assimilator 1 5835
Protoss_Zealot 2 8902
Protoss_Cybernetics_Core 1 9078
Protoss_Robotics_Facility 1 10423
Protoss_Dragoon 1 10088
10423
