Protoss_Forge 1 2865
Protoss_Nexus 1 5049
Protoss_Photon_Cannon 1 4299
Protoss_Gateway 2 9626
Protoss_Assimilator 2 7434
Protoss_Cybernetics_Core 1 5991
Protoss_Zealot 8 10592
Protoss_Stargate 1 7471
Protoss_Corsair 3 10024
Protoss_Citadel_of_Adun 1 8985
Protoss_Templar_Archives 1 10157
10592
