Protoss_Forge 1 3211
Protoss_Photon_Cannon 3 10483
Protoss_Nexus 1 5832
Protoss_Gateway 4 9947
Protoss_Assimilator 2 6415
Protoss_Cybernetics_Core 1 6175
Protoss_Zealot 4 9270
Protoss_Stargate 1 7355
Protoss_Dragoon 1 7764
Protoss_Corsair 2 8715
Protoss_Citadel_of_Adun 1 8371
Protoss_Templar_Archives 1 9357
Protoss_High_Templar 2 10292
10483
