Protoss_Forge 1 3351
Protoss_Nexus 1 5087
Protoss_Photon_Cannon 3 10343
Protoss_Gateway 4 10748
Protoss_Assimilator 2 7845
Protoss_Cybernetics_Core 1 6433
Protoss_Zealot 3 8936
Protoss_Stargate 1 7648
Protoss_Corsair 2 9298
Protoss_Citadel_of_Adun 1 9003
Protoss_Templar_Archives 1 10037
10748
