Protoss_Gateway 1 2742
Protoss_Assimilator 1 2915
Protoss_Zealot 4 6840
Protoss_Cybernetics_Core 1 4369
Protoss_Stargate 1 5590
Protoss_Dragoon 1 5618
Protoss_Corsair 1 6410
Protoss_Citadel_of_Adun 1 6889
Protoss_Forge 1 7354
Protoss_Templar_Archives 1 7928
Protoss_Photon_Cannon 3 9663
Protoss_Dark_Templar 2 9578
Protoss_Nexus 1 11281
Protoss_High_Templar 1 10414
11281
