Protoss_Forge 1 2749
Protoss_Nexus 1 5197
Protoss_Gateway 4 10295
Protoss_Assimilator 2 6950
Protoss_Photon_Cannon 3 9566
Protoss_Cybernetics_Core 1 5889
Protoss_Zealot 5 10300
Protoss_Stargate 1 7182
Protoss_Citadel_of_Adun 1 7828
Protoss_Corsair 2 8832
Protoss_Templar_Archives 1 8847
Protoss_High_Templar 2 10488
10488
