Protoss_Forge 1 2480
Protoss_Photon_Cannon 3 10340
Protoss_Nexus 1 5977
Protoss_Gateway 2 9846
Protoss_Assimilator 2 9671
Protoss_Cybernetics_Core 1 6365
Protoss_Zealot 5 8996
Protoss_Stargate 1 7826
Protoss_Citadel_of_Adun 1 7887
Protoss_Corsair 1 8578
Protoss_Templar_Archives 1 9403
Protoss_Robotics_Facility 1 10409
Protoss_Dark_Templar 1 10390
10409
