Protoss_Forge 1 3340
Protoss_Nexus 1 5059
Protoss_Photon_Cannon 2 10618
Protoss_Gateway 2 8117
Protoss_Assimilator 2 6422
Protoss_Cybernetics_Core 1 5911
Protoss_Zealot 10 10336
Protoss_Stargate 1 7158
Protoss_Citadel_of_Adun 1 7723
Protoss_Corsair 1 8052
Protoss_Templar_Archives 1 9643
10618
