Protoss_Forge 1 2608
Protoss_Photon_Cannon 5 10735
Protoss_Nexus 1 6061
Protoss_Gateway 3 8561
Protoss_Assimilator 2 8030
Protoss_Cybernetics_Core 1 6557
Protoss_Zealot 6 9600
Protoss_Citadel_of_Adun 1 7670
Protoss_Dragoon 1 7712
Protoss_Templar_Archives 1 9200
Protoss_High_Templar 2 10116
Protoss_Dark_Templar 1 10352
10735
