Protoss_Gateway 3 9772
Protoss_Zealot 11 10456
Protoss_Nexus 1 5966
Protoss_Forge 1 5161
Protoss_Photon_Cannon 2 7282
Protoss_Assimilator 2 7727
Protoss_Cybernetics_Core 1 7952
Protoss_Stargate 1 9137
Protoss_Citadel_of_Adun 1 9169
Protoss_Dragoon 1 9034
Protoss_Corsair 1 9834
Protoss_Templar_Archives 1 10231
10456
