Protoss_Forge 1 2683
Protoss_Nexus 1 5009
Protoss_Photon_Cannon 3 9827
Protoss_Gateway 2 9261
Protoss_Assimilator 2 7954
Protoss_Cybernetics_Core 1 6325
Protoss_Zealot 9 10568
Protoss_Stargate 1 7566
Protoss_Citadel_of_Adun 1 7729
Protoss_Corsair 3 10230
10568
