Protoss_Forge 2 8638
Protoss_Photon_Cannon 3 9498
Protoss_Gateway 3 9213
Protoss_Assimilator 1 5022
Protoss_Cybernetics_Core 1 6211
Protoss_Zealot 7 10474
Protoss_Dragoon 1 7048
Protoss_Stargate 1 7446
Protoss_Citadel_of_Adun 1 7651
Protoss_Corsair 1 8132
Protoss_Templar_Archives 1 9847
10474
