Protoss_Forge 1 2656
Protoss_Photon_Cannon 2 5695
Protoss_Nexus 1 8074
Protoss_Gateway 3 10515
Protoss_Assimilator 2 8578
Protoss_Zealot 3 10346
Protoss_Cybernetics_Core 1 8541
Protoss_Stargate 1 9749
Protoss_Citadel_of_Adun 1 9773
Protoss_Corsair 1 10494
10515
