Protoss_Forge 1 2819
Protoss_Nexus 1 4971
Protoss_Gateway 2 7857
Protoss_Photon_Cannon 2 10467
Protoss_Assimilator 2 6932
Protoss_Cybernetics_Core 1 5531
Protoss_Stargate 1 6780
Protoss_Zealot 9 10002
Protoss_Citadel_of_Adun 2 8151
Protoss_Corsair 3 10240
Protoss_Templar_Archives 1 9135
Protoss_High_Templar 1 10712
10712
