Protoss_Forge 1 3229
Protoss_Nexus 1 5088
Protoss_Photon_Cannon 3 10268
Protoss_Gateway 2 9214
Protoss_Assimilator 2 7050
Protoss_Cybernetics_Core 1 6797
Protoss_Zealot 6 10428
Protoss_Stargate 1 7938
Protoss_Citadel_of_Adun 1 8233
Protoss_Corsair 2 9324
Protoss_Templar_Archives 1 9878
10428
