Protoss_Forge 1 2888
Protoss_Photon_Cannon 2 4106
Protoss_Nexus 1 6058
Protoss_Gateway 1 5571
Protoss_Assimilator 2 7282
Protoss_Cybernetics_Core 1 6619
Protoss_Zealot 7 10430
Protoss_Stargate 1 7772
Protoss_Robotics_Facility 1 9024
Protoss_Corsair 3 9860
Protoss_Robotics_Support_Bay 1 9748
10430
