Protoss_Forge 1 3232
Protoss_Nexus 1 5072
Protoss_Photon_Cannon 2 10604
Protoss_Gateway 2 9127
Protoss_Assimilator 2 6938
Protoss_Cybernetics_Core 1 6047
Protoss_Zealot 10 10440
Protoss_Stargate 1 7340
Protoss_Citadel_of_Adun 1 7943
Protoss_Corsair 1 8022
Protoss_Templar_Archives 1 9513
Protoss_Robotics_Facility 1 10066
10604
