Protoss_Nexus 1 4569
Protoss_Forge 1 3664
Protoss_Gateway 1 4753
Protoss_Photon_Cannon 3 9883
Protoss_Assimilator 2 6761
Protoss_Zealot 7 10444
Protoss_Cybernetics_Core 1 6251
Protoss_Stargate 2 8046
Protoss_Corsair 7 10276
Protoss_Citadel_of_Adun 1 8587
Protoss_Templar_Archives 1 10793
10793
