Protoss_Forge 1 3202
Protoss_Nexus 1 5169
Protoss_Photon_Cannon 5 10591
Protoss_Gateway 3 9487
Protoss_Assimilator 2 6617
Protoss_Cybernetics_Core 1 6340
Protoss_Stargate 1 7489
Protoss_Zealot 4 8912
Protoss_Citadel_of_Adun 1 7892
Protoss_Corsair 4 10138
Protoss_Templar_Archives 1 8901
Protoss_Dark_Templar 1 9752
Protoss_High_Templar 2 10388
10591
