Protoss_Forge 1 3017
Protoss_Photon_Cannon 3 5986
Protoss_Nexus 1 6055
Protoss_Gateway 4 10435
Protoss_Assimilator 1 5428
Protoss_Cybernetics_Core 1 7399
Protoss_Citadel_of_Adun 1 8547
Protoss_Zealot 5 10474
Protoss_Dragoon 1 9186
10474
