Protoss_Forge 1 2916
Protoss_Photon_Cannon 4 10068
Protoss_Nexus 1 5643
Protoss_Gateway 2 10777
Protoss_Assimilator 2 7130
Protoss_Cybernetics_Core 1 6535
Protoss_Stargate 2 9039
Protoss_Corsair 5 10206
Protoss_Citadel_of_Adun 1 9515
Protoss_Templar_Archives 1 10581
10777
