Protoss_Forge 1 2726
Protoss_Photon_Cannon 5 9991
Protoss_Nexus 1 5809
Protoss_Gateway 3 9585
Protoss_Assimilator 2 7237
Protoss_Cybernetics_Core 1 6225
Protoss_Zealot 9 10306
Protoss_Stargate 1 7377
Protoss_Corsair 1 8060
Protoss_Citadel_of_Adun 1 8511
Protoss_Templar_Archives 1 9966
10306
