Protoss_Forge 1 3318
Protoss_Photon_Cannon 6 9609
Protoss_Nexus 1 5922
Protoss_Gateway 4 10147
Protoss_Assimilator 2 6904
Protoss_Cybernetics_Core 1 6516
Protoss_Zealot 2 8066
Protoss_Dragoon 1 7354
Protoss_Stargate 1 7991
Protoss_Citadel_of_Adun 1 8311
Protoss_Corsair 2 9282
Protoss_Templar_Archives 1 9372
Protoss_High_Templar 2 10220
10220
