Protoss_Forge 1 3548
Protoss_Nexus 1 5138
Protoss_Photon_Cannon 4 9186
Protoss_Gateway 3 9972
Protoss_Assimilator 3 10206
Protoss_Cybernetics_Core 1 6438
Protoss_Zealot 3 8896
Protoss_Stargate 1 7678
Protoss_Citadel_of_Adun 1 7944
Protoss_Corsair 4 10392
Protoss_Templar_Archives 1 8981
Protoss_Dark_Templar 1 9974
10392
