Protoss_Forge 1 2826
Protoss_Photon_Cannon 3 10082
Protoss_Nexus 1 5873
Protoss_Gateway 3 10009
Protoss_Assimilator 2 6956
Protoss_Cybernetics_Core 1 6415
Protoss_Zealot 5 9504
Protoss_Dragoon 1 7260
Protoss_Stargate 1 7766
Protoss_Citadel_of_Adun 1 8663
Protoss_Corsair 2 9090
Protoss_Templar_Archives 1 9711
10082
