Protoss_Forge 2 8616
Protoss_Photon_Cannon 6 10693
Protoss_Nexus 1 5901
Protoss_Gateway 2 8806
Protoss_Assimilator 2 7496
Protoss_Cybernetics_Core 1 6249
Protoss_Zealot 4 9242
Protoss_Stargate 1 7449
Protoss_Citadel_of_Adun 1 8052
Protoss_Corsair 2 8759
Protoss_Templar_Archives 1 9177
Protoss_Dark_Templar 2 10042
10693
