Protoss_Forge 1 2956
Protoss_Nexus 1 5064
Protoss_Gateway 4 9081
Protoss_Assimilator 2 7172
Protoss_Photon_Cannon 2 9842
Protoss_Cybernetics_Core 1 5864
Protoss_Zealot 10 10478
Protoss_Dragoon 1 6814
Protoss_Citadel_of_Adun 1 7057
Protoss_Templar_Archives 1 9451
Protoss_Dark_Templar 2 10666
10666
