Protoss_Forge 1 3130
Protoss_Nexus 1 5051
Protoss_Photon_Cannon 4 9786
Protoss_Gateway 2 8793
Protoss_Assimilator 2 7732
Protoss_Cybernetics_Core 1 6227
Protoss_Zealot 6 10102
Protoss_Stargate 1 7566
Protoss_Dragoon 1 7504
Protoss_Citadel_of_Adun 1 8200
Protoss_Corsair 2 9278
Protoss_Templar_Archives 1 10328
10328
