Protoss_Gateway 3 7831
Protoss_Assimilator 1 2865
Protoss_Zealot 11 9926
Protoss_Cybernetics_Core 1 5781
Protoss_Dragoon 2 10054
Protoss_Stargate 1 7016
Protoss_Corsair 3 9302
Protoss_Citadel_of_Adun 1 9671
10054
