Protoss_Gateway 2 7823
Protoss_Assimilator 1 3245
Protoss_Zealot 5 8433
Protoss_Cybernetics_Core 1 4852
Protoss_Stargate 1 6026
Protoss_Dragoon 1 6665
Protoss_Corsair 2 7898
Protoss_Citadel_of_Adun 1 7575
Protoss_Templar_Archives 1 8770
Protoss_Forge 1 8755
Protoss_Dark_Templar 2 9653
Protoss_Photon_Cannon 2 10640
Protoss_Nexus 1 11367
Protoss_High_Templar 2 10438
11367
