Protoss_Gateway 2 10450
Protoss_Assimilator 1 3238
Protoss_Zealot 6 9598
Protoss_Cybernetics_Core 1 4332
Protoss_Dragoon 1 5278
Protoss_Robotics_Facility 1 6168
Protoss_Forge 1 6687
Protoss_Shuttle 1 7173
Protoss_Robotics_Support_Bay 1 7327
Protoss_Reaver 2 9524
Protoss_Photon_Cannon 3 10170
Protoss_Citadel_of_Adun 1 10523
10523
