Protoss_Forge 1 2618
Protoss_Photon_Cannon 2 8994
Protoss_Nexus 1 5268
Protoss_Gateway 3 10281
Protoss_Assimilator 2 7382
Protoss_Cybernetics_Core 1 5771
Protoss_Zealot 4 9470
Protoss_Dragoon 1 6820
Protoss_Stargate 2 10117
Protoss_Corsair 3 10290
Protoss_Robotics_Facility 1 9249
Protoss_Robotics_Support_Bay 1 9797
Protoss_Reaver 1 10986
10986
