Protoss_Forge 1 2832
Protoss_Nexus 1 5039
Protoss_Photon_Cannon 1 4278
Protoss_Gateway 4 8801
Protoss_Assimilator 2 7802
Protoss_Zealot 14 10594
Protoss_Cybernetics_Core 1 6467
Protoss_Citadel_of_Adun 1 8043
Protoss_Templar_Archives 1 10717
10717
