Protoss_Forge 1 3354
Protoss_Nexus 1 4993
Protoss_Photon_Cannon 2 4514
Protoss_Gateway 4 10018
Protoss_Zealot 5 10114
Protoss_Assimilator 2 8163
Protoss_Cybernetics_Core 1 7728
Protoss_Stargate 1 8878
Protoss_Dragoon 1 8598
Protoss_Citadel_of_Adun 1 9253
Protoss_Corsair 2 10186
Protoss_Templar_Archives 1 10265
10265
