Protoss_Forge 1 2734
Protoss_Photon_Cannon 3 10648
Protoss_Nexus 1 6163
Protoss_Gateway 4 8769
Protoss_Assimilator 2 8912
Protoss_Zealot 11 10076
Protoss_Cybernetics_Core 1 6721
Protoss_Citadel_of_Adun 1 7721
Protoss_Dragoon 1 7756
Protoss_Templar_Archives 1 10021
10648
