Protoss_Forge 1 2958
Protoss_Nexus 1 5332
Protoss_Gateway 3 9532
Protoss_Photon_Cannon 2 5450
Protoss_Assimilator 2 6686
Protoss_Cybernetics_Core 1 6501
Protoss_Zealot 3 9500
Protoss_Stargate 1 7716
Protoss_Citadel_of_Adun 1 8407
Protoss_Corsair 3 9950
Protoss_Dragoon 1 8728
Protoss_Templar_Archives 1 9409
Protoss_Dark_Templar 1 10320
Protoss_High_Templar 2 10426
10426
