Protoss_Forge 1 2956
Protoss_Nexus 1 4997
Protoss_Photon_Cannon 3 10704
Protoss_Gateway 4 10690
Protoss_Assimilator 2 6871
Protoss_Cybernetics_Core 1 6373
Protoss_Stargate 1 7602
Protoss_Citadel_of_Adun 1 7959
Protoss_Corsair 3 9509
Protoss_Zealot 1 8568
Protoss_Templar_Archives 1 8979
Protoss_Dark_Templar 2 10134
10704
