Protoss_Forge 1 2955
Protoss_Nexus 1 5025
Protoss_Photon_Cannon 4 9268
Protoss_Gateway 4 10747
Protoss_Assimilator 2 7318
Protoss_Cybernetics_Core 1 6419
Protoss_Zealot 3 7596
Protoss_Stargate 1 7634
Protoss_Citadel_of_Adun 1 8061
Protoss_Corsair 3 9934
Protoss_Templar_Archives 1 9063
Protoss_Dark_Templar 2 10020
10747
