Protoss_Forge 1 2992
Protoss_Nexus 1 5009
Protoss_Photon_Cannon 5 9876
Protoss_Gateway 2 10893
Protoss_Zealot 3 8648
Protoss_Assimilator 2 8506
Protoss_Cybernetics_Core 1 8035
Protoss_Stargate 1 9196
Protoss_Citadel_of_Adun 1 9465
Protoss_Corsair 1 9880
Protoss_Templar_Archives 1 10497
10893
