Protoss_Nexus 1 4621
Protoss_Forge 1 4009
Protoss_Gateway 4 9790
Protoss_Photon_Cannon 2 6624
Protoss_Assimilator 2 6948
Protoss_Cybernetics_Core 1 6253
Protoss_Stargate 1 7566
Protoss_Robotics_Facility 1 8435
Protoss_Zealot 1 8162
Protoss_Dragoon 6 10738
Protoss_Corsair 1 8258
Protoss_Shuttle 1 9455
Protoss_Robotics_Support_Bay 1 9436
Protoss_Reaver 1 10938
10938
