Protoss_Forge 1 3305
Protoss_Photon_Cannon 4 10087
Protoss_Nexus 1 5809
Protoss_Gateway 1 5275
Protoss_Assimilator 2 7649
Protoss_Zealot 3 8838
Protoss_Cybernetics_Core 1 6760
Protoss_Stargate 1 8007
Protoss_Dragoon 1 8172
Protoss_Corsair 3 10132
Protoss_Robotics_Facility 1 9595
10132
