Protoss_Gateway 2 8587
Protoss_Zealot 4 8934
Protoss_Assimilator 1 3687
Protoss_Cybernetics_Core 1 4878
Protoss_Stargate 1 6285
Protoss_Nexus 1 7620
Protoss_Citadel_of_Adun 1 6992
Protoss_Corsair 1 6992
Protoss_Forge 1 7466
Protoss_Templar_Archives 1 8174
Protoss_Photon_Cannon 3 10528
Protoss_Dark_Templar 2 9570
Protoss_High_Templar 2 10368
10528
