Protoss_Forge 1 2619
Protoss_Photon_Cannon 2 9639
Protoss_Nexus 1 5505
Protoss_Gateway 4 9217
Protoss_Assimilator 2 9035
Protoss_Zealot 12 10524
Protoss_Cybernetics_Core 1 6430
Protoss_Citadel_of_Adun 1 8035
Protoss_Dragoon 1 8866
Protoss_Templar_Archives 1 10396
10524
