Protoss_Forge 1 2736
Protoss_Photon_Cannon 6 10720
Protoss_Nexus 1 5875
Protoss_Gateway 1 5361
Protoss_Assimilator 2 7847
Protoss_Cybernetics_Core 1 6466
Protoss_Zealot 5 9962
Protoss_Stargate 1 7728
Protoss_Robotics_Facility 1 8773
Protoss_Corsair 4 10508
Protoss_Shuttle 1 9863
10720
