Protoss_Forge 1 2973
Protoss_Photon_Cannon 7 9930
Protoss_Nexus 1 5875
Protoss_Gateway 2 9424
Protoss_Assimilator 2 7666
Protoss_Zealot 2 6858
Protoss_Cybernetics_Core 1 6424
Protoss_Stargate 1 7658
Protoss_Citadel_of_Adun 1 8173
Protoss_Corsair 2 9220
Protoss_Templar_Archives 1 9181
Protoss_Dark_Templar 1 10162
10162
