Protoss_Forge 1 2606
Protoss_Photon_Cannon 2 3944
Protoss_Nexus 1 5907
Protoss_Gateway 3 9712
Protoss_Assimilator 2 7532
Protoss_Zealot 5 10278
Protoss_Cybernetics_Core 1 6918
Protoss_Stargate 1 8066
Protoss_Citadel_of_Adun 1 8784
Protoss_Corsair 1 8804
Protoss_Templar_Archives 1 9819
Protoss_Robotics_Facility 1 10775
Protoss_Dark_Templar 1 10648
10775
