Protoss_Forge 1 2719
Protoss_Nexus 1 5313
Protoss_Gateway 4 9160
Protoss_Photon_Cannon 2 5450
Protoss_Assimilator 2 10388
Protoss_Zealot 12 10388
Protoss_Cybernetics_Core 1 7227
Protoss_Citadel_of_Adun 1 8261
Protoss_Templar_Archives 1 10692
10692
