Protoss_Nexus 1 4596
Protoss_Gateway 4 10039
Protoss_Forge 1 4188
Protoss_Assimilator 2 7405
Protoss_Photon_Cannon 4 8860
Protoss_Zealot 4 9284
Protoss_Cybernetics_Core 1 5957
Protoss_Stargate 1 7421
Protoss_Corsair 1 8116
Protoss_Citadel_of_Adun 1 8753
Protoss_Templar_Archives 1 9789
10039
