Protoss_Forge 1 2724
Protoss_Photon_Cannon 5 10380
Protoss_Nexus 1 5763
Protoss_Gateway 1 5153
Protoss_Assimilator 2 9204
Protoss_Zealot 6 10170
Protoss_Cybernetics_Core 1 6569
Protoss_Dragoon 1 7602
Protoss_Stargate 1 7990
Protoss_Citadel_of_Adun 1 8851
Protoss_Corsair 3 10524
10524
