Protoss_Forge 1 3353
Protoss_Nexus 1 5297
Protoss_Gateway 1 5106
Protoss_Photon_Cannon 3 9668
Protoss_Assimilator 2 6601
Protoss_Cybernetics_Core 1 6323
Protoss_Zealot 4 9246
Protoss_Stargate 2 9423
Protoss_Corsair 5 10346
Protoss_Citadel_of_Adun 1 10286
10346
