Protoss_Forge 1 2725
Protoss_Photon_Cannon 4 10724
Protoss_Nexus 1 5697
Protoss_Gateway 3 8592
Protoss_Assimilator 3 9002
Protoss_Cybernetics_Core 1 6133
Protoss_Zealot 8 10074
Protoss_Stargate 1 7353
Protoss_Citadel_of_Adun 1 7866
Protoss_Corsair 1 8158
Protoss_Templar_Archives 1 9109
Protoss_High_Templar 1 10416
10724
