Protoss_Nexus 1 4710
Protoss_Forge 1 4125
Protoss_Gateway 6 10784
Protoss_Assimilator 2 6274
Protoss_Photon_Cannon 2 10681
Protoss_Cybernetics_Core 1 5723
Protoss_Zealot 3 8130
Protoss_Stargate 1 6993
Protoss_Dragoon 1 6846
Protoss_Citadel_of_Adun 1 7706
Protoss_Corsair 3 9308
Protoss_Templar_Archives 1 8841
Protoss_High_Templar 3 10440
10784
