Protoss_Forge 1 2890
Protoss_Photon_Cannon 3 7562
Protoss_Nexus 1 5357
Protoss_Gateway 5 10741
Protoss_Assimilator 2 8926
Protoss_Cybernetics_Core 1 6175
Protoss_Zealot 4 9058
Protoss_Stargate 1 7406
Protoss_Corsair 3 10534
Protoss_Dragoon 1 8480
Protoss_Citadel_of_Adun 1 8850
Protoss_Templar_Archives 1 9950
10741
