Protoss_Forge 1 2493
Protoss_Photon_Cannon 6 10494
Protoss_Nexus 1 5534
Protoss_Gateway 1 5177
Protoss_Assimilator 2 7110
Protoss_Cybernetics_Core 1 6495
Protoss_Zealot 3 8278
Protoss_Stargate 1 7818
Protoss_Robotics_Facility 1 8838
Protoss_Dragoon 1 8538
Protoss_Corsair 3 10155
Protoss_Shuttle 1 10153
10494
