Protoss_Forge 1 2690
Protoss_Photon_Cannon 2 3986
Protoss_Nexus 1 5807
Protoss_Gateway 5 10691
Protoss_Assimilator 2 7401
Protoss_Zealot 7 10546
Protoss_Cybernetics_Core 1 6664
Protoss_Stargate 1 7962
Protoss_Citadel_of_Adun 1 8467
Protoss_Corsair 2 9330
10691
