Protoss_Forge 1 3021
Protoss_Photon_Cannon 2 3935
Protoss_Nexus 1 6013
Protoss_Gateway 5 10429
Protoss_Assimilator 2 8866
Protoss_Zealot 11 9984
Protoss_Cybernetics_Core 1 6688
Protoss_Citadel_of_Adun 1 7717
Protoss_Templar_Archives 1 9731
Protoss_High_Templar 2 10592
Protoss_Dark_Templar 1 10736
10736
