Protoss_Forge 2 9268
Protoss_Nexus 1 5020
Protoss_Photon_Cannon 5 10706
Protoss_Gateway 2 8820
Protoss_Assimilator 2 6994
Protoss_Cybernetics_Core 1 6415
Protoss_Zealot 3 9022
Protoss_Stargate 1 7584
Protoss_Citadel_of_Adun 1 7881
Protoss_Corsair 3 9528
Protoss_Templar_Archives 1 8923
Protoss_Dark_Templar 2 9854
10706
