Protoss_Nexus 1 4670
Protoss_Gateway 4 10064
Protoss_Forge 1 4391
Protoss_Assimilator 2 7602
Protoss_Photon_Cannon 1 5278
Protoss_Zealot 9 10498
Protoss_Cybernetics_Core 1 6120
Protoss_Stargate 1 7358
Protoss_Citadel_of_Adun 1 7537
Protoss_Corsair 2 9022
Protoss_Templar_Archives 1 8811
Protoss_Dark_Templar 2 9650
Protoss_High_Templar 2 9878
10498
