Protoss_Forge 1 2680
Protoss_Photon_Cannon 7 10460
Protoss_Nexus 1 5705
Protoss_Assimilator 2 8897
Protoss_Gateway 3 8689
Protoss_Cybernetics_Core 1 6701
Protoss_Zealot 10 10482
Protoss_Dragoon 1 7544
Protoss_Citadel_of_Adun 1 8051
Protoss_Templar_Archives 1 9810
Protoss_High_Templar 1 10676
10676
