Protoss_Nexus 1 4571
Protoss_Gateway 5 10726
Protoss_Assimilator 2 7343
Protoss_Forge 1 4468
Protoss_Photon_Cannon 3 10586
Protoss_Cybernetics_Core 1 6322
Protoss_Zealot 3 7796
Protoss_Stargate 1 7547
Protoss_Citadel_of_Adun 1 7498
Protoss_Templar_Archives 1 8501
Protoss_Dragoon 1 8548
Protoss_Corsair 1 8540
Protoss_Dark_Templar 2 9550
Protoss_High_Templar 2 10302
10726
