Protoss_Forge 1 2766
Protoss_Photon_Cannon 3 10284
Protoss_Nexus 1 5791
Protoss_Gateway 4 8804
Protoss_Assimilator 2 9832
Protoss_Cybernetics_Core 1 6249
Protoss_Zealot 9 10028
Protoss_Citadel_of_Adun 1 7384
Protoss_Dragoon 1 7430
Protoss_Templar_Archives 1 9740
10284
