Protoss_Gateway 3 9180
Protoss_Forge 1 2885
Protoss_Photon_Cannon 6 10094
Protoss_Nexus 1 6521
Protoss_Assimilator 2 7434
Protoss_Cybernetics_Core 1 7043
Protoss_Zealot 3 10138
Protoss_Stargate 1 8230
Protoss_Citadel_of_Adun 1 8611
Protoss_Dragoon 1 8788
Protoss_Corsair 3 10262
Protoss_Templar_Archives 1 9610
Protoss_Dark_Templar 1 10454
10454
