Protoss_Gateway 1 2460
Protoss_Zealot 9 9394
Protoss_Forge 1 4237
Protoss_Photon_Cannon 3 10680
Protoss_Nexus 1 7717
Protoss_Assimilator 1 6611
Protoss_Cybernetics_Core 1 7783
Protoss_Stargate 1 9133
Protoss_Citadel_of_Adun 1 10075
Protoss_Corsair 2 10466
10680
