Protoss_Forge 1 2685
Protoss_Photon_Cannon 7 10038
Protoss_Nexus 1 7533
Protoss_Gateway 1 7219
Protoss_Assimilator 2 8961
Protoss_Cybernetics_Core 1 8299
Protoss_Stargate 1 9464
Protoss_Citadel_of_Adun 1 9387
Protoss_Corsair 1 10156
Protoss_Templar_Archives 1 10693
10693
