Protoss_Forge 2 8615
Protoss_Photon_Cannon 4 10155
Protoss_Nexus 1 6062
Protoss_Gateway 1 5487
Protoss_Assimilator 2 7483
Protoss_Zealot 4 9700
Protoss_Cybernetics_Core 1 7070
Protoss_Stargate 1 8521
Protoss_Citadel_of_Adun 1 8642
Protoss_Corsair 1 9212
Protoss_Templar_Archives 1 9833
Protoss_Dark_Templar 1 10688
10688
