Protoss_Forge 2 8803
Protoss_Photon_Cannon 3 6739
Protoss_Nexus 1 5945
Protoss_Gateway 5 10890
Protoss_Assimilator 2 8621
Protoss_Zealot 5 10158
Protoss_Cybernetics_Core 1 7753
Protoss_Stargate 1 8933
Protoss_Citadel_of_Adun 1 8854
Protoss_Corsair 1 9614
10890
