Protoss_Forge 1 2863
Protoss_Nexus 2 10580
Protoss_Photon_Cannon 3 5699
Protoss_Gateway 2 10325
Protoss_Assimilator 2 7604
Protoss_Zealot 2 7104
Protoss_Cybernetics_Core 1 7113
Protoss_Stargate 1 8361
Protoss_Citadel_of_Adun 1 8574
Protoss_Dragoon 1 8498
Protoss_Corsair 2 10216
Protoss_Templar_Archives 1 10176
10580
