Protoss_Forge 1 2688
Protoss_Photon_Cannon 5 9736
Protoss_Nexus 1 5691
Protoss_Gateway 1 5051
Protoss_Assimilator 2 7130
Protoss_Zealot 2 8830
Protoss_Cybernetics_Core 1 7627
Protoss_Stargate 1 8777
Protoss_Robotics_Facility 1 8994
Protoss_Corsair 2 10538
Protoss_Shuttle 1 10337
Protoss_Robotics_Support_Bay 1 10199
10538
