Protoss_Gateway 3 9131
Protoss_Assimilator 1 3127
Protoss_Zealot 12 10138
Protoss_Cybernetics_Core 1 4801
Protoss_Stargate 1 5956
Protoss_Forge 1 5972
Protoss_Citadel_of_Adun 1 6834
Protoss_Corsair 2 7416
Protoss_Templar_Archives 1 10506
10506
