Protoss_Forge 1 2906
Protoss_Nexus 1 4999
Protoss_Photon_Cannon 4 9249
Protoss_Gateway 4 10613
Protoss_Assimilator 2 6917
Protoss_Zealot 8 10200
Protoss_Cybernetics_Core 1 6469
Protoss_Stargate 1 7735
Protoss_Citadel_of_Adun 1 8353
Protoss_Corsair 4 10520
10613
