Protoss_Forge 1 2934
Protoss_Photon_Cannon 5 8842
Protoss_Nexus 1 5755
Protoss_Gateway 1 5237
Protoss_Assimilator 2 6883
Protoss_Zealot 3 10032
Protoss_Cybernetics_Core 1 6795
Protoss_Dragoon 2 8484
Protoss_Stargate 1 8045
Protoss_Robotics_Facility 1 8793
Protoss_Corsair 4 10576
Protoss_Shuttle 1 9775
Protoss_Robotics_Support_Bay 1 10418
10576
