Protoss_Forge 1 2751
Protoss_Nexus 1 5043
Protoss_Gateway 4 10219
Protoss_Assimilator 2 9165
Protoss_Photon_Cannon 1 5317
Protoss_Zealot 14 10380
Protoss_Cybernetics_Core 1 7774
Protoss_Citadel_of_Adun 1 8882
Protoss_Ground_Weapons_1 1 9499
Protoss_Templar_Archives 1 10426
10426
