Protoss_Gateway 2 9938
Protoss_Assimilator 1 2967
Protoss_Zealot 7 10584
Protoss_Cybernetics_Core 1 4389
Protoss_Stargate 1 5524
Protoss_Dragoon 1 5274
Protoss_Citadel_of_Adun 1 6021
Protoss_Corsair 1 6252
Protoss_Templar_Archives 1 7179
Protoss_Forge 1 7402
Protoss_Dark_Templar 2 9148
Protoss_Photon_Cannon 2 10282
Protoss_Nexus 1 10015
Protoss_High_Templar 1 9922
10584
