Protoss_Nexus 1 4589
Protoss_Gateway 3 8729
Protoss_Forge 2 10428
Protoss_Assimilator 2 6805
Protoss_Photon_Cannon 4 9557
Protoss_Zealot 4 9268
Protoss_Cybernetics_Core 1 6561
Protoss_Dragoon 1 7406
Protoss_Stargate 1 7802
Protoss_Citadel_of_Adun 1 7972
Protoss_Corsair 1 8666
Protoss_Templar_Archives 1 9127
Protoss_Dark_Templar 1 10066
Protoss_High_Templar 2 10112
10428
