Protoss_Nexus 1 4657
Protoss_Forge 1 3707
Protoss_Photon_Cannon 3 10165
Protoss_Gateway 3 8213
Protoss_Assimilator 2 7425
Protoss_Cybernetics_Core 1 6407
Protoss_Zealot 11 9774
Protoss_Citadel_of_Adun 1 7395
Protoss_Templar_Archives 1 9553
Protoss_Robotics_Facility 1 10543
Protoss_High_Templar 2 10428
Protoss_Dark_Templar 1 10526
Protoss_Ground_Weapons_1 1 9869
10543
