Protoss_Forge 1 2918
Protoss_Photon_Cannon 4 10536
Protoss_Nexus 1 5711
Protoss_Gateway 2 9087
Protoss_Assimilator 2 7927
Protoss_Zealot 6 9944
Protoss_Cybernetics_Core 1 6989
Protoss_Dragoon 1 7892
Protoss_Citadel_of_Adun 1 8462
Protoss_Stargate 1 9047
Protoss_Templar_Archives 1 9449
Protoss_Corsair 1 9810
Protoss_Dark_Templar 2 10696
10696
