Protoss_Gateway 2 8159
Protoss_Zealot 12 10369
Protoss_Nexus 1 6034
Protoss_Assimilator 2 9404
Protoss_Cybernetics_Core 1 5985
Protoss_Forge 1 6154
Protoss_Photon_Cannon 2 9387
Protoss_Stargate 1 7563
Protoss_Dragoon 1 7556
Protoss_Citadel_of_Adun 1 8029
Protoss_Corsair 1 8594
10369
