Protoss_Forge 1 3118
Protoss_Photon_Cannon 4 9242
Protoss_Nexus 1 5495
Protoss_Gateway 2 9059
Protoss_Assimilator 3 8153
Protoss_Cybernetics_Core 1 6324
Protoss_Zealot 7 10570
Protoss_Stargate 1 7550
Protoss_Citadel_of_Adun 1 7916
Protoss_Corsair 2 9690
Protoss_Templar_Archives 1 9073
10570
