Protoss_Forge 1 3125
Protoss_Nexus 1 5097
Protoss_Photon_Cannon 4 10481
Protoss_Gateway 2 10705
Protoss_Assimilator 2 7892
Protoss_Cybernetics_Core 1 6830
Protoss_Zealot 5 10106
Protoss_Stargate 1 8240
Protoss_Dragoon 1 8728
Protoss_Corsair 3 10304
Protoss_Citadel_of_Adun 1 9814
Protoss_Templar_Archives 1 10801
10801
