Protoss_Gateway 2 3396
Protoss_Zealot 15 10196
Protoss_Assimilator 1 6528
Protoss_Cybernetics_Core 1 7557
Protoss_Forge 1 7887
Protoss_Citadel_of_Adun 1 8839
Protoss_Photon_Cannon 2 9646
Protoss_Templar_Archives 1 10467
10467
