Protoss_Forge 1 3168
Protoss_Photon_Cannon 6 10271
Protoss_Gateway 3 10875
Protoss_Nexus 1 6389
Protoss_Assimilator 2 7722
Protoss_Zealot 3 9176
Protoss_Cybernetics_Core 1 6697
Protoss_Stargate 1 7914
Protoss_Citadel_of_Adun 1 8481
Protoss_Corsair 2 9260
Protoss_Dragoon 1 9352
Protoss_Templar_Archives 1 9914
10875
