Protoss_Forge 1 2608
Protoss_Photon_Cannon 3 10442
Protoss_Nexus 1 6245
Protoss_Gateway 6 10211
Protoss_Assimilator 2 8032
Protoss_Zealot 6 8240
Protoss_Cybernetics_Core 1 6973
Protoss_Stargate 1 8364
Protoss_Corsair 1 9200
Protoss_Dragoon 3 10730
10730
