Protoss_Nexus 1 4710
Protoss_Gateway 3 10108
Protoss_Forge 1 4527
Protoss_Assimilator 2 6821
Protoss_Photon_Cannon 2 8716
Protoss_Cybernetics_Core 1 6270
Protoss_Zealot 3 9872
Protoss_Stargate 1 7454
Protoss_Dragoon 1 7320
Protoss_Citadel_of_Adun 1 8027
Protoss_Corsair 4 10156
Protoss_Templar_Archives 1 9279
Protoss_Dark_Templar 1 10268
10268
