Protoss_Forge 1 3266
Protoss_Photon_Cannon 6 10120
Protoss_Nexus 1 6501
Protoss_Gateway 1 5977
Protoss_Assimilator 2 6305
Protoss_Zealot 3 8443
Protoss_Cybernetics_Core 1 7304
Protoss_Stargate 1 8739
Protoss_Citadel_of_Adun 1 8677
Protoss_Corsair 2 10048
Protoss_Templar_Archives 1 10043
10120
