Protoss_Forge 1 2947
Protoss_Photon_Cannon 4 9764
Protoss_Nexus 1 5919
Protoss_Gateway 4 10871
Protoss_Assimilator 2 8634
Protoss_Zealot 3 7996
Protoss_Cybernetics_Core 1 6910
Protoss_Stargate 1 8191
Protoss_Citadel_of_Adun 1 8423
Protoss_Corsair 1 8916
Protoss_Templar_Archives 1 9463
Protoss_Dark_Templar 1 10316
10871
