Protoss_Forge 1 2915
Protoss_Photon_Cannon 4 9790
Protoss_Nexus 1 5586
Protoss_Gateway 3 9163
Protoss_Assimilator 2 7038
Protoss_Cybernetics_Core 1 6258
Protoss_Zealot 3 7476
Protoss_Stargate 1 7491
Protoss_Citadel_of_Adun 1 7611
Protoss_Corsair 1 8292
Protoss_Templar_Archives 1 8762
Protoss_Robotics_Facility 1 9808
Protoss_High_Templar 2 10038
Protoss_Dark_Templar 1 10276
10276
