Protoss_Forge 1 3163
Protoss_Photon_Cannon 3 10654
Protoss_Nexus 1 6317
Protoss_Gateway 2 10179
Protoss_Assimilator 2 8709
Protoss_Zealot 4 9592
Protoss_Cybernetics_Core 1 7228
Protoss_Stargate 1 8381
Protoss_Citadel_of_Adun 1 8413
Protoss_Corsair 2 10290
Protoss_Templar_Archives 1 9760
10654
