Protoss_Forge 2 3989
Protoss_Nexus 1 4792
Protoss_Gateway 3 10481
Protoss_Photon_Cannon 3 9889
Protoss_Zealot 10 10420
Protoss_Assimilator 3 9978
Protoss_Cybernetics_Core 1 6798
Protoss_Stargate 1 8031
Protoss_Citadel_of_Adun 1 8453
Protoss_Dragoon 1 8466
Protoss_Corsair 3 10360
10481
