Protoss_Nexus 1 4743
Protoss_Gateway 4 9811
Protoss_Forge 1 4349
Protoss_Assimilator 3 9040
Protoss_Photon_Cannon 1 5218
Protoss_Cybernetics_Core 1 5637
Protoss_Zealot 5 10276
Protoss_Dragoon 1 6544
Protoss_Stargate 1 6900
Protoss_Citadel_of_Adun 1 7811
Protoss_Corsair 2 8276
Protoss_Templar_Archives 1 8946
Protoss_Dark_Templar 1 9814
10276
