Protoss_Forge 1 3096
Protoss_Nexus 1 5151
Protoss_Photon_Cannon 1 4414
Protoss_Gateway 2 8992
Protoss_Assimilator 3 9617
Protoss_Cybernetics_Core 1 6349
Protoss_Stargate 1 7516
Protoss_Citadel_of_Adun 1 7425
Protoss_Dragoon 1 7776
Protoss_Corsair 4 10206
Protoss_Zealot 4 9726
Protoss_Templar_Archives 1 9585
Protoss_Dark_Templar 2 10646
10646
