Protoss_Forge 1 3366
Protoss_Nexus 1 5061
Protoss_Photon_Cannon 2 4654
Protoss_Gateway 2 8171
Protoss_Assimilator 2 7188
Protoss_Cybernetics_Core 1 6273
Protoss_Zealot 9 10456
Protoss_Stargate 1 7444
Protoss_Dragoon 1 7442
Protoss_Citadel_of_Adun 1 8021
Protoss_Corsair 4 10202
Protoss_Templar_Archives 1 10612
10612
