Protoss_Forge 1 2765
Protoss_Photon_Cannon 6 10356
Protoss_Nexus 1 5945
Protoss_Gateway 3 8745
Protoss_Assimilator 2 7103
Protoss_Cybernetics_Core 1 6560
Protoss_Zealot 1 6366
Protoss_Dragoon 1 7398
Protoss_Stargate 1 8272
Protoss_Citadel_of_Adun 1 8529
Protoss_Corsair 2 9598
Protoss_Templar_Archives 1 9619
Protoss_High_Templar 2 10538
Protoss_Dark_Templar 1 10680
10680
