Protoss_Forge 1 2881
Protoss_Nexus 1 5069
Protoss_Photon_Cannon 4 9195
Protoss_Gateway 3 9539
Protoss_Assimilator 3 9824
Protoss_Cybernetics_Core 1 6906
Protoss_Zealot 6 10364
Protoss_Stargate 1 8192
Protoss_Dragoon 1 7976
Protoss_Citadel_of_Adun 1 8934
Protoss_Corsair 2 10224
Protoss_Templar_Archives 1 10049
10364
