Protoss_Forge 1 3188
Protoss_Nexus 1 5091
Protoss_Gateway 4 10821
Protoss_Photon_Cannon 2 10009
Protoss_Assimilator 2 9927
Protoss_Zealot 4 9222
Protoss_Cybernetics_Core 1 5849
Protoss_Dragoon 1 6924
Protoss_Stargate 1 7710
Protoss_Corsair 1 8426
Protoss_Citadel_of_Adun 1 8841
Protoss_Templar_Archives 1 10315
Protoss_Robotics_Facility 1 10944
10944
