Protoss_Gateway 2 3417
Protoss_Zealot 13 9964
Protoss_Assimilator 1 5796
Protoss_Cybernetics_Core 1 7539
Protoss_Citadel_of_Adun 1 8649
Protoss_Dragoon 1 8764
Protoss_Stargate 1 9143
Protoss_Corsair 1 9866
Protoss_Templar_Archives 1 10389
Protoss_Forge 1 10371
10389
