Protoss_Forge 1 2882
Protoss_Photon_Cannon 2 3964
Protoss_Nexus 1 5895
Protoss_Gateway 2 9365
Protoss_Assimilator 2 6962
Protoss_Cybernetics_Core 1 6601
Protoss_Zealot 3 7948
Protoss_Stargate 1 7778
Protoss_Citadel_of_Adun 1 7836
Protoss_Corsair 3 9808
Protoss_Templar_Archives 1 8989
Protoss_Dark_Templar 2 10346
10346
