Protoss_Forge 1 3185
Protoss_Photon_Cannon 2 4240
Protoss_Nexus 1 5963
Protoss_Gateway 4 10732
Protoss_Assimilator 2 7195
Protoss_Cybernetics_Core 1 6743
Protoss_Zealot 2 8244
Protoss_Dragoon 1 7642
Protoss_Stargate 1 8083
Protoss_Citadel_of_Adun 1 8121
Protoss_Corsair 3 10420
Protoss_Templar_Archives 1 9987
10732
