Protoss_Forge 1 2872
Protoss_Photon_Cannon 4 10620
Protoss_Nexus 1 5415
Protoss_Gateway 4 10223
Protoss_Assimilator 2 7594
Protoss_Cybernetics_Core 1 6293
Protoss_Zealot 7 9826
Protoss_Stargate 1 7475
Protoss_Citadel_of_Adun 1 7776
Protoss_Corsair 1 8180
Protoss_Templar_Archives 1 10073
10620
