Protoss_Gateway 3 9961
Protoss_Zealot 4 6390
Protoss_Nexus 1 5843
Protoss_Assimilator 2 6826
Protoss_Cybernetics_Core 1 5851
Protoss_Stargate 1 7033
Protoss_Citadel_of_Adun 1 7422
Protoss_Corsair 3 8992
Protoss_Forge 1 7952
Protoss_Templar_Archives 1 8596
Protoss_Photon_Cannon 4 10420
Protoss_Dark_Templar 1 10282
Protoss_High_Templar 1 10574
10574
