Protoss_Forge 1 2945
Protoss_Photon_Cannon 3 7892
Protoss_Nexus 1 5795
Protoss_Gateway 5 10078
Protoss_Assimilator 2 6849
Protoss_Cybernetics_Core 1 5997
Protoss_Zealot 10 10456
Protoss_Stargate 1 7177
Protoss_Citadel_of_Adun 1 7557
Protoss_Corsair 1 7878
10456
