Protoss_Gateway 2 7810
Protoss_Assimilator 1 2930
Protoss_Zealot 6 9514
Protoss_Cybernetics_Core 1 4722
Protoss_Dragoon 3 7850
Protoss_Stargate 1 6293
Protoss_Corsair 3 9202
Protoss_Citadel_of_Adun 1 8426
Protoss_Templar_Archives 1 9436
Protoss_Forge 1 9153
Protoss_Photon_Cannon 1 10145
Protoss_Dark_Templar 2 10516
10516
