Protoss_Forge 1 2741
Protoss_Photon_Cannon 3 6434
Protoss_Gateway 2 9003
Protoss_Nexus 2 9293
Protoss_Assimilator 2 10350
Protoss_Cybernetics_Core 1 6129
Protoss_Zealot 5 9998
Protoss_Stargate 1 7754
Protoss_Citadel_of_Adun 1 8027
Protoss_Corsair 1 8494
10350
