Protoss_Forge 1 2636
Protoss_Nexus 1 5207
Protoss_Photon_Cannon 6 10420
Protoss_Gateway 1 5186
Protoss_Zealot 6 10558
Protoss_Assimilator 2 9823
Protoss_Cybernetics_Core 1 9968
10558
