Protoss_Forge 1 2644
Protoss_Nexus 1 5248
Protoss_Gateway 2 10283
Protoss_Assimilator 2 7030
Protoss_Photon_Cannon 4 9870
Protoss_Cybernetics_Core 1 5907
Protoss_Zealot 3 9228
Protoss_Dragoon 1 6940
Protoss_Stargate 1 7260
Protoss_Citadel_of_Adun 1 7794
Protoss_Corsair 2 9244
Protoss_Robotics_Facility 1 9121
Protoss_Templar_Archives 1 9059
Protoss_Shuttle 1 10513
Protoss_Robotics_Support_Bay 1 10151
10513
