Protoss_Nexus 1 4755
Protoss_Gateway 1 4159
Protoss_Forge 1 4546
Protoss_Assimilator 2 6353
Protoss_Photon_Cannon 2 10290
Protoss_Cybernetics_Core 1 5725
Protoss_Zealot 2 7350
Protoss_Dragoon 1 6564
Protoss_Stargate 1 7254
Protoss_Robotics_Facility 1 8244
Protoss_Corsair 5 10376
Protoss_Shuttle 1 9335
Protoss_Robotics_Support_Bay 1 9317
Protoss_Reaver 1 10454
10454
