Protoss_Gateway 2 3203
Protoss_Zealot 15 10596
Protoss_Assimilator 1 5572
Protoss_Cybernetics_Core 1 6732
Protoss_Citadel_of_Adun 1 7767
Protoss_Templar_Archives 1 9019
Protoss_Forge 1 9888
10596
