Protoss_Gateway 2 3395
Protoss_Zealot 19 10490
Protoss_Nexus 1 8175
Protoss_Forge 1 7240
Protoss_Assimilator 2 10370
Protoss_Photon_Cannon 1 9103
Protoss_Cybernetics_Core 1 9322
Protoss_Stargate 1 10530
Protoss_Citadel_of_Adun 1 10575
10575
