Protoss_Gateway 2 6446
Protoss_Assimilator 1 2908
Protoss_Zealot 8 9652
Protoss_Cybernetics_Core 1 4841
Protoss_Citadel_of_Adun 1 5960
Protoss_Dragoon 1 5908
Protoss_Templar_Archives 1 7119
Protoss_High_Templar 4 10481
Protoss_Forge 1 8431
Protoss_Dark_Templar 2 8890
Protoss_Archon 1 8525
Protoss_Photon_Cannon 2 9543
10481
