Protoss_Gateway 3 8662
Protoss_Zealot 13 10028
Protoss_Nexus 1 5591
Protoss_Assimilator 2 7641
Protoss_Forge 1 5387
Protoss_Cybernetics_Core 1 6077
Protoss_Photon_Cannon 3 10630
Protoss_Stargate 1 7320
Protoss_Citadel_of_Adun 1 7710
Protoss_Corsair 2 9724
Protoss_Templar_Archives 1 9545
10630
