Protoss_Forge 1 2859
Protoss_Nexus 1 4989
Protoss_Photon_Cannon 2 8568
Protoss_Gateway 4 9641
Protoss_Assimilator 2 6992
Protoss_Zealot 5 8740
Protoss_Cybernetics_Core 1 6391
Protoss_Stargate 1 7765
Protoss_Citadel_of_Adun 1 7965
Protoss_Corsair 1 8694
Protoss_Templar_Archives 1 9165
Protoss_High_Templar 4 10478
10478
