Protoss_Forge 1 3149
Protoss_Photon_Cannon 4 6416
Protoss_Nexus 1 6527
Protoss_Gateway 2 10401
Protoss_Assimilator 2 10154
Protoss_Cybernetics_Core 1 8397
Protoss_Zealot 4 10390
Protoss_Stargate 1 9588
Protoss_Citadel_of_Adun 1 9910
Protoss_Corsair 1 10280
10401
