Protoss_Forge 1 3029
Protoss_Photon_Cannon 2 4048
Protoss_Nexus 1 6085
Protoss_Gateway 4 10508
Protoss_Assimilator 2 7900
Protoss_Zealot 2 10472
Protoss_Cybernetics_Core 1 7666
Protoss_Stargate 1 8818
Protoss_Dragoon 1 8662
Protoss_Citadel_of_Adun 1 9752
Protoss_Corsair 1 9528
10508
