Protoss_Gateway 1 2787
Protoss_Assimilator 1 2964
Protoss_Zealot 6 6820
Protoss_Cybernetics_Core 1 4526
Protoss_Dragoon 1 5358
Protoss_Stargate 1 5928
Protoss_Citadel_of_Adun 1 6448
Protoss_Corsair 4 9956
Protoss_Templar_Archives 1 7747
Protoss_Forge 1 8443
Protoss_Dark_Templar 1 8794
Protoss_High_Templar 2 10362
Protoss_Photon_Cannon 1 10221
10362
