Protoss_Forge 2 4387
Protoss_Gateway 2 5734
Protoss_Photon_Cannon 7 10522
Protoss_Nexus 1 6405
Protoss_Assimilator 2 6770
Protoss_Cybernetics_Core 1 6755
Protoss_Zealot 4 8678
Protoss_Stargate 1 7986
Protoss_Dragoon 1 7896
Protoss_Corsair 3 10234
Protoss_Robotics_Facility 1 10031
10522
