Protoss_Forge 1 2796
Protoss_Nexus 1 4909
Protoss_Gateway 3 10642
Protoss_Assimilator 2 6373
Protoss_Photon_Cannon 3 10257
Protoss_Cybernetics_Core 1 5847
Protoss_Zealot 5 9518
Protoss_Stargate 1 7090
Protoss_Citadel_of_Adun 1 7587
Protoss_Corsair 5 10436
Protoss_Templar_Archives 1 9015
Protoss_Dark_Templar 1 10270
10642
