Protoss_Forge 1 3270
Protoss_Photon_Cannon 3 6143
Protoss_Nexus 1 5471
Protoss_Gateway 4 10429
Protoss_Zealot 6 10582
Protoss_Assimilator 2 7847
Protoss_Cybernetics_Core 1 7447
Protoss_Dragoon 1 8304
Protoss_Stargate 1 8960
Protoss_Citadel_of_Adun 1 9486
Protoss_Corsair 2 10362
10582
