Protoss_Forge 2 7186
Protoss_Photon_Cannon 4 8808
Protoss_Gateway 2 5053
Protoss_Zealot 4 9530
Protoss_Nexus 1 8013
Protoss_Assimilator 2 10297
Protoss_Cybernetics_Core 1 8419
Protoss_Stargate 2 10365
Protoss_Dragoon 1 9498
Protoss_Corsair 1 10232
10365
