Protoss_Gateway 2 3181
Protoss_Zealot 13 10411
Protoss_Assimilator 1 3867
Protoss_Cybernetics_Core 1 4621
Protoss_Stargate 1 5876
Protoss_Dragoon 1 6052
Protoss_Corsair 2 7762
Protoss_Nexus 1 9735
Protoss_Forge 1 9216
Protoss_Citadel_of_Adun 1 10040
Protoss_Photon_Cannon 1 10622
10622
