Protoss_Gateway 2 3287
Protoss_Zealot 12 10038
Protoss_Nexus 1 6335
Protoss_Assimilator 1 5498
Protoss_Cybernetics_Core 1 6542
Protoss_Stargate 1 7744
Protoss_Dragoon 1 7718
Protoss_Forge 1 8016
Protoss_Corsair 3 9852
Protoss_Photon_Cannon 5 10484
10484
