Protoss_Forge 1 3298
Protoss_Nexus 1 4927
Protoss_Photon_Cannon 4 10128
Protoss_Gateway 4 10423
Protoss_Assimilator 2 6587
Protoss_Cybernetics_Core 1 6307
Protoss_Zealot 3 8427
Protoss_Stargate 1 7442
Protoss_Dragoon 1 7166
Protoss_Citadel_of_Adun 1 7835
Protoss_Corsair 3 9512
Protoss_Templar_Archives 1 8827
Protoss_Dark_Templar 2 9762
Protoss_High_Templar 2 10594
10594
