Protoss_Forge 1 2797
Protoss_Photon_Cannon 2 3744
Protoss_Nexus 1 5723
Protoss_Gateway 3 8751
Protoss_Assimilator 2 7414
Protoss_Cybernetics_Core 1 6444
Protoss_Zealot 10 10564
Protoss_Citadel_of_Adun 1 7472
Protoss_Stargate 2 10246
10564
