Protoss_Gateway 2 10007
Protoss_Zealot 10 10234
Protoss_Nexus 1 5656
Protoss_Assimilator 1 5918
Protoss_Cybernetics_Core 1 7956
Protoss_Stargate 1 9164
Protoss_Citadel_of_Adun 1 9795
Protoss_Corsair 1 10016
Protoss_Templar_Archives 1 10817
10817
