Protoss_Forge 1 3234
Protoss_Nexus 1 5103
Protoss_Photon_Cannon 2 4630
Protoss_Gateway 4 10829
Protoss_Assimilator 2 8130
Protoss_Zealot 3 9468
Protoss_Cybernetics_Core 1 6809
Protoss_Stargate 1 8064
Protoss_Citadel_of_Adun 1 8201
Protoss_Corsair 2 9614
Protoss_Templar_Archives 1 9284
Protoss_High_Templar 2 10306
10829
