Protoss_Gateway 2 6038
Protoss_Assimilator 1 2821
Protoss_Cybernetics_Core 1 3779
Protoss_Zealot 11 9324
Protoss_Stargate 1 4920
Protoss_Dragoon 1 5352
Protoss_Corsair 1 5600
Protoss_Citadel_of_Adun 1 7258
Protoss_Templar_Archives 1 9029
Protoss_Dark_Templar 2 10124
10124
