Protoss_Forge 1 2595
Protoss_Nexus 1 4937
Protoss_Photon_Cannon 2 5636
Protoss_Gateway 4 10763
Protoss_Assimilator 2 9649
Protoss_Zealot 5 9150
Protoss_Cybernetics_Core 1 7065
Protoss_Stargate 1 8220
Protoss_Citadel_of_Adun 1 9017
Protoss_Corsair 1 8954
10763
