Protoss_Gateway 2 3359
Protoss_Zealot 9 10488
Protoss_Nexus 2 10851
Protoss_Assimilator 1 5118
Protoss_Cybernetics_Core 1 6285
Protoss_Stargate 1 7507
Protoss_Dragoon 2 7668
Protoss_Citadel_of_Adun 1 8342
Protoss_Corsair 2 8864
Protoss_Forge 1 8567
Protoss_Photon_Cannon 1 10328
10851
