Protoss_Gateway 2 3319
Protoss_Zealot 10 9958
Protoss_Nexus 1 7633
Protoss_Assimilator 2 10386
Protoss_Cybernetics_Core 1 7303
Protoss_Stargate 1 8726
Protoss_Forge 1 8529
Protoss_Dragoon 2 10228
Protoss_Corsair 1 9634
Protoss_Photon_Cannon 2 10735
Protoss_Robotics_Facility 1 11065
11065
