Protoss_Forge 1 2977
Protoss_Photon_Cannon 2 4176
Protoss_Nexus 1 6281
Protoss_Gateway 4 9753
Protoss_Assimilator 2 7298
Protoss_Cybernetics_Core 1 6485
Protoss_Zealot 10 10544
Protoss_Stargate 1 7681
Protoss_Citadel_of_Adun 1 8141
Protoss_Corsair 1 8476
Protoss_Templar_Archives 1 10007
10544
