Protoss_Gateway 2 3131
Protoss_Zealot 12 10443
Protoss_Assimilator 1 4504
Protoss_Cybernetics_Core 1 5533
Protoss_Stargate 1 6701
Protoss_Corsair 2 8024
Protoss_Nexus 1 8868
Protoss_Dragoon 2 9239
Protoss_Forge 1 9325
Protoss_Photon_Cannon 1 10627
Protoss_Citadel_of_Adun 1 10869
10869
