Protoss_Forge 1 2893
Protoss_Photon_Cannon 8 10162
Protoss_Nexus 1 5880
Protoss_Gateway 2 9632
Protoss_Assimilator 2 9648
Protoss_Zealot 6 10314
Protoss_Cybernetics_Core 1 7691
Protoss_Citadel_of_Adun 1 8858
Protoss_Templar_Archives 1 10097
10314
