Protoss_Forge 1 3241
Protoss_Photon_Cannon 2 4202
Protoss_Nexus 1 5905
Protoss_Gateway 2 8935
Protoss_Assimilator 2 6619
Protoss_Cybernetics_Core 1 6361
Protoss_Zealot 3 8718
Protoss_Stargate 1 7590
Protoss_Citadel_of_Adun 1 7697
Protoss_Corsair 2 9456
Protoss_Templar_Archives 1 8719
Protoss_Dark_Templar 2 9774
Protoss_High_Templar 2 10526
10526
