Protoss_Forge 1 2562
Protoss_Nexus 1 5139
Protoss_Gateway 2 8997
Protoss_Assimilator 2 6840
Protoss_Photon_Cannon 2 9078
Protoss_Cybernetics_Core 1 5838
Protoss_Zealot 3 8746
Protoss_Stargate 1 7034
Protoss_Dragoon 1 7200
Protoss_Citadel_of_Adun 1 7455
Protoss_Corsair 4 9888
Protoss_Templar_Archives 1 8751
Protoss_Dark_Templar 2 10172
Protoss_Robotics_Facility 1 11007
11007
