Protoss_Forge 1 2432
Protoss_Photon_Cannon 2 3738
Protoss_Nexus 1 5603
Protoss_Gateway 2 8585
Protoss_Assimilator 2 7474
Protoss_Cybernetics_Core 1 6101
Protoss_Zealot 10 10558
Protoss_Stargate 1 7276
Protoss_Corsair 3 9476
Protoss_Citadel_of_Adun 1 8465
Protoss_Templar_Archives 1 10756
10756
