Protoss_Forge 1 3472
Protoss_Photon_Cannon 5 10326
Protoss_Nexus 1 5655
Protoss_Gateway 2 9716
Protoss_Assimilator 2 7896
Protoss_Cybernetics_Core 1 6428
Protoss_Zealot 3 8298
Protoss_Stargate 1 7678
Protoss_Dragoon 1 7696
Protoss_Citadel_of_Adun 1 8047
Protoss_Corsair 2 9094
Protoss_Templar_Archives 1 9632
Protoss_Dark_Templar 2 10696
10696
