Protoss_Forge 1 2519
Protoss_Photon_Cannon 5 10136
Protoss_Nexus 1 5889
Protoss_Gateway 4 10725
Protoss_Assimilator 2 7051
Protoss_Zealot 4 8021
Protoss_Cybernetics_Core 1 6376
Protoss_Citadel_of_Adun 1 7414
Protoss_Templar_Archives 1 8437
Protoss_High_Templar 4 10066
Protoss_Dark_Templar 1 10312
Protoss_Archon 1 9868
10725
