Protoss_Forge 1 3050
Protoss_Photon_Cannon 3 9814
Protoss_Nexus 1 5904
Protoss_Gateway 4 10758
Protoss_Assimilator 2 7530
Protoss_Cybernetics_Core 1 6307
Protoss_Zealot 4 9228
Protoss_Stargate 1 7513
Protoss_Dragoon 1 7496
Protoss_Citadel_of_Adun 1 8199
Protoss_Corsair 1 8206
Protoss_Templar_Archives 1 9333
Protoss_Dark_Templar 2 10274
10758
