Protoss_Forge 1 2906
Protoss_Nexus 1 5192
Protoss_Photon_Cannon 1 4354
Protoss_Gateway 5 10869
Protoss_Assimilator 2 9790
Protoss_Zealot 8 10114
Protoss_Cybernetics_Core 1 6455
Protoss_Stargate 1 7692
Protoss_Citadel_of_Adun 1 8513
Protoss_Corsair 1 8640
10869
