Protoss_Forge 1 3235
Protoss_Nexus 1 5078
Protoss_Photon_Cannon 3 7776
Protoss_Gateway 6 10643
Protoss_Assimilator 2 7720
Protoss_Cybernetics_Core 1 6234
Protoss_Zealot 6 9928
Protoss_Stargate 1 7384
Protoss_Citadel_of_Adun 1 7632
Protoss_Corsair 2 10478
Protoss_Templar_Archives 1 9875
10643
