Protoss_Gateway 2 5506
Protoss_Assimilator 1 2953
Protoss_Zealot 13 9090
Protoss_Cybernetics_Core 1 3953
Protoss_Stargate 1 5140
Protoss_Dragoon 1 5038
Protoss_Corsair 1 5940
Protoss_Forge 1 8499
Protoss_Photon_Cannon 4 10698
Protoss_Nexus 1 11066
11066
