Protoss_Forge 1 2725
Protoss_Photon_Cannon 3 4073
Protoss_Gateway 2 5680
Protoss_Zealot 10 8780
Protoss_Nexus 1 10338
Protoss_Assimilator 2 10143
Protoss_Cybernetics_Core 1 10266
10338
