Protoss_Gateway 2 9212
Protoss_Assimilator 1 2947
Protoss_Zealot 6 9122
Protoss_Cybernetics_Core 1 4876
Protoss_Stargate 1 6314
Protoss_Dragoon 1 6018
Protoss_Citadel_of_Adun 1 6414
Protoss_Corsair 2 7600
Protoss_Templar_Archives 1 7796
Protoss_Forge 1 8277
Protoss_Dark_Templar 2 10598
Protoss_Photon_Cannon 1 9703
Protoss_High_Templar 1 10596
10598
