Protoss_Forge 1 2854
Protoss_Nexus 1 5169
Protoss_Photon_Cannon 2 4734
Protoss_Gateway 4 10024
Protoss_Assimilator 2 7472
Protoss_Cybernetics_Core 1 6520
Protoss_Zealot 4 8476
Protoss_Stargate 1 7696
Protoss_Citadel_of_Adun 1 8243
Protoss_Corsair 2 9172
Protoss_Templar_Archives 1 9334
10024
