Protoss_Forge 1 3124
Protoss_Nexus 1 4941
Protoss_Photon_Cannon 3 9253
Protoss_Gateway 1 5045
Protoss_Assimilator 2 6746
Protoss_Zealot 6 10578
Protoss_Cybernetics_Core 1 6249
Protoss_Stargate 1 7410
Protoss_Robotics_Facility 1 8170
Protoss_Corsair 5 10556
Protoss_Shuttle 1 9353
Protoss_Robotics_Support_Bay 1 9359
Protoss_Reaver 1 10610
Protoss_Citadel_of_Adun 1 10778
10778
