Protoss_Forge 1 3196
Protoss_Nexus 1 5054
Protoss_Photon_Cannon 2 9106
Protoss_Gateway 2 9545
Protoss_Assimilator 2 6732
Protoss_Zealot 4 8190
Protoss_Cybernetics_Core 1 6425
Protoss_Stargate 1 7608
Protoss_Citadel_of_Adun 1 8230
Protoss_Dragoon 1 8420
Protoss_Corsair 4 10274
Protoss_Templar_Archives 1 9635
Protoss_Dark_Templar 2 10490
10490
