Protoss_Nexus 1 4721
Protoss_Gateway 4 9864
Protoss_Forge 1 4424
Protoss_Assimilator 2 9369
Protoss_Photon_Cannon 2 5825
Protoss_Zealot 9 10184
Protoss_Cybernetics_Core 1 6923
Protoss_Citadel_of_Adun 1 8150
Protoss_Dragoon 1 8024
Protoss_Templar_Archives 1 9558
10184
