Protoss_Forge 1 3274
Protoss_Nexus 1 4995
Protoss_Photon_Cannon 4 10257
Protoss_Gateway 3 10235
Protoss_Assimilator 2 6801
Protoss_Zealot 3 7308
Protoss_Cybernetics_Core 1 7023
Protoss_Stargate 1 8245
Protoss_Dragoon 5 10428
Protoss_Corsair 3 10434
10434
