Protoss_Forge 1 2914
Protoss_Photon_Cannon 2 4117
Protoss_Nexus 1 5734
Protoss_Gateway 4 10359
Protoss_Assimilator 2 7645
Protoss_Cybernetics_Core 1 6247
Protoss_Zealot 8 10236
Protoss_Stargate 1 7435
Protoss_Dragoon 1 7508
Protoss_Corsair 3 9770
Protoss_Citadel_of_Adun 1 8687
Protoss_Templar_Archives 1 10787
10787
