Protoss_Forge 1 3229
Protoss_Nexus 1 5086
Protoss_Photon_Cannon 2 9915
Protoss_Gateway 4 10613
Protoss_Assimilator 2 6539
Protoss_Cybernetics_Core 1 5997
Protoss_Zealot 8 10420
Protoss_Stargate 1 7286
Protoss_Citadel_of_Adun 1 8093
Protoss_Corsair 3 9278
Protoss_Templar_Archives 1 9902
10613
