Protoss_Forge 1 3014
Protoss_Photon_Cannon 4 10414
Protoss_Nexus 1 5871
Protoss_Gateway 4 10701
Protoss_Assimilator 2 8629
Protoss_Cybernetics_Core 1 6386
Protoss_Zealot 10 10520
Protoss_Dragoon 1 7248
Protoss_Citadel_of_Adun 2 8201
Protoss_Templar_Archives 1 10063
10701
