Protoss_Forge 1 2872
Protoss_Nexus 1 5072
Protoss_Photon_Cannon 3 10555
Protoss_Gateway 3 9983
Protoss_Assimilator 2 6896
Protoss_Cybernetics_Core 1 6164
Protoss_Zealot 3 8624
Protoss_Stargate 1 7298
Protoss_Citadel_of_Adun 1 7442
Protoss_Corsair 5 10594
Protoss_Templar_Archives 1 8533
Protoss_Dark_Templar 2 10422
10594
