Protoss_Forge 1 2829
Protoss_Photon_Cannon 3 10516
Protoss_Nexus 1 5341
Protoss_Gateway 1 4977
Protoss_Assimilator 2 7933
Protoss_Cybernetics_Core 1 6211
Protoss_Zealot 6 10546
Protoss_Stargate 1 7463
Protoss_Citadel_of_Adun 1 8352
Protoss_Corsair 3 9752
Protoss_Templar_Archives 1 9343
Protoss_Robotics_Facility 1 11085
11085
