Protoss_Forge 1 2659
Protoss_Nexus 1 5049
Protoss_Gateway 2 10564
Protoss_Assimilator 3 7007
Protoss_Photon_Cannon 5 10458
Protoss_Zealot 6 9498
Protoss_Cybernetics_Core 1 6321
Protoss_Stargate 1 7594
Protoss_Dragoon 1 7540
Protoss_Citadel_of_Adun 1 8418
Protoss_Corsair 1 8570
Protoss_Templar_Archives 1 9474
Protoss_Dark_Templar 1 10336
10564
