Protoss_Forge 1 3132
Protoss_Photon_Cannon 2 4052
Protoss_Nexus 1 6092
Protoss_Gateway 2 8746
Protoss_Assimilator 2 7666
Protoss_Cybernetics_Core 1 6458
Protoss_Zealot 8 10214
Protoss_Stargate 1 7751
Protoss_Citadel_of_Adun 1 8128
Protoss_Corsair 1 8462
Protoss_Templar_Archives 1 9357
Protoss_Robotics_Facility 1 10209
Protoss_Dark_Templar 1 10554
10554
