Protoss_Forge 1 3284
Protoss_Nexus 1 5001
Protoss_Photon_Cannon 3 9720
Protoss_Gateway 1 5488
Protoss_Assimilator 2 6570
Protoss_Cybernetics_Core 1 6473
Protoss_Zealot 3 8570
Protoss_Stargate 2 8030
Protoss_Corsair 7 10512
Protoss_Citadel_of_Adun 1 9403
Protoss_Templar_Archives 1 10465
10512
