Protoss_Forge 1 2873
Protoss_Photon_Cannon 5 10557
Protoss_Nexus 1 5341
Protoss_Gateway 2 8816
Protoss_Assimilator 2 8201
Protoss_Zealot 7 10032
Protoss_Cybernetics_Core 1 6831
Protoss_Stargate 1 8106
Protoss_Dragoon 1 8118
Protoss_Corsair 1 8794
Protoss_Citadel_of_Adun 1 9566
Protoss_Templar_Archives 1 10557
10557
