Protoss_Gateway 2 3379
Protoss_Zealot 14 9414
Protoss_Nexus 2 11069
Protoss_Assimilator 1 5426
Protoss_Cybernetics_Core 1 6537
Protoss_Stargate 1 7712
Protoss_Dragoon 1 7486
Protoss_Forge 1 7748
Protoss_Corsair 3 9948
Protoss_Photon_Cannon 6 10670
11069
