Protoss_Forge 1 3183
Protoss_Nexus 1 5094
Protoss_Photon_Cannon 3 10370
Protoss_Gateway 4 10177
Protoss_Assimilator 2 6812
Protoss_Cybernetics_Core 1 6279
Protoss_Zealot 4 8980
Protoss_Stargate 1 7566
Protoss_Dragoon 1 7444
Protoss_Citadel_of_Adun 1 8079
Protoss_Corsair 2 10128
Protoss_Templar_Archives 1 9196
Protoss_Dark_Templar 2 10078
10370
