Protoss_Gateway 2 6249
Protoss_Assimilator 1 2949
Protoss_Cybernetics_Core 1 3769
Protoss_Zealot 15 10416
Protoss_Stargate 1 5014
Protoss_Dragoon 1 4932
Protoss_Corsair 1 5704
Protoss_Citadel_of_Adun 1 7772
Protoss_Forge 2 8728
Protoss_Templar_Archives 1 9785
Protoss_Dark_Templar 1 10654
10654
