Protoss_Forge 1 2928
Protoss_Photon_Cannon 2 4175
Protoss_Nexus 1 6073
Protoss_Gateway 1 5391
Protoss_Assimilator 2 6587
Protoss_Cybernetics_Core 1 6456
Protoss_Zealot 1 6204
Protoss_Stargate 1 7675
Protoss_Dragoon 1 7612
Protoss_Robotics_Facility 1 8647
Protoss_Corsair 4 10400
Protoss_Robotics_Support_Bay 1 9370
Protoss_Reaver 1 10496
10496
