Protoss_Forge 1 3040
Protoss_Photon_Cannon 3 9696
Protoss_Nexus 1 5879
Protoss_Gateway 4 9577
Protoss_Assimilator 2 6803
Protoss_Cybernetics_Core 1 6179
Protoss_Zealot 3 8598
Protoss_Stargate 1 7554
Protoss_Citadel_of_Adun 1 7788
Protoss_Corsair 1 8298
Protoss_Templar_Archives 1 8821
Protoss_High_Templar 4 10420
10420
