Protoss_Forge 1 2698
Protoss_Nexus 1 4984
Protoss_Gateway 5 10278
Protoss_Photon_Cannon 3 8949
Protoss_Assimilator 2 7158
Protoss_Cybernetics_Core 1 6203
Protoss_Zealot 3 8622
Protoss_Citadel_of_Adun 1 7241
Protoss_Templar_Archives 1 8259
Protoss_High_Templar 2 9852
Protoss_Dark_Templar 1 9846
10278
