Protoss_Gateway 2 3179
Protoss_Zealot 9 10224
Protoss_Nexus 1 7397
Protoss_Assimilator 1 6444
Protoss_Cybernetics_Core 1 7305
Protoss_Forge 1 7468
Protoss_Stargate 1 8661
Protoss_Photon_Cannon 4 10598
Protoss_Corsair 1 9374
Protoss_Citadel_of_Adun 1 10361
10598
