Protoss_Forge 1 2714
Protoss_Photon_Cannon 1 3708
Protoss_Nexus 1 5545
Protoss_Gateway 1 4961
Protoss_Assimilator 2 7984
Protoss_Zealot 6 10472
Protoss_Cybernetics_Core 1 6652
Protoss_Dragoon 1 7633
Protoss_Stargate 2 10252
Protoss_Robotics_Facility 1 9057
Protoss_Corsair 3 10242
Protoss_Shuttle 1 10241
Protoss_Robotics_Support_Bay 1 10003
10472
