Protoss_Gateway 2 3341
Protoss_Zealot 10 7728
Protoss_Nexus 2 8744
Protoss_Assimilator 2 9554
Protoss_Cybernetics_Core 1 8183
Protoss_Forge 1 8473
Protoss_Stargate 1 9326
Protoss_Photon_Cannon 1 9346
Protoss_Robotics_Facility 1 10467
Protoss_Corsair 1 10008
10467
