Protoss_Forge 1 2758
Protoss_Photon_Cannon 3 9664
Protoss_Nexus 1 5820
Protoss_Gateway 3 10713
Protoss_Assimilator 2 7111
Protoss_Cybernetics_Core 1 6233
Protoss_Zealot 7 9918
Protoss_Stargate 1 7438
Protoss_Citadel_of_Adun 1 7964
Protoss_Corsair 2 10192
Protoss_Templar_Archives 1 9939
10713
