Protoss_Forge 1 3103
Protoss_Nexus 1 5103
Protoss_Photon_Cannon 4 10008
Protoss_Gateway 3 10865
Protoss_Assimilator 3 10054
Protoss_Cybernetics_Core 1 6349
Protoss_Zealot 4 9328
Protoss_Stargate 1 7590
Protoss_Citadel_of_Adun 1 8077
Protoss_Corsair 2 9364
Protoss_Templar_Archives 1 9259
Protoss_High_Templar 2 10218
10865
