Protoss_Forge 1 3218
Protoss_Nexus 1 5031
Protoss_Photon_Cannon 3 9783
Protoss_Gateway 3 10800
Protoss_Assimilator 2 7000
Protoss_Cybernetics_Core 1 6105
Protoss_Zealot 5 9418
Protoss_Stargate 1 7280
Protoss_Citadel_of_Adun 1 8244
Protoss_Corsair 5 10564
Protoss_Templar_Archives 1 9265
Protoss_Dark_Templar 2 10228
10800
