Protoss_Forge 1 2919
Protoss_Nexus 1 5045
Protoss_Photon_Cannon 3 9872
Protoss_Gateway 2 8440
Protoss_Assimilator 2 6258
Protoss_Cybernetics_Core 1 6359
Protoss_Zealot 7 10192
Protoss_Stargate 1 7517
Protoss_Dragoon 1 7306
Protoss_Citadel_of_Adun 1 7926
Protoss_Corsair 3 9960
Protoss_Templar_Archives 1 10308
10308
