Protoss_Forge 1 2988
Protoss_Photon_Cannon 5 9965
Protoss_Nexus 1 5769
Protoss_Gateway 1 5167
Protoss_Assimilator 2 6549
Protoss_Cybernetics_Core 1 6531
Protoss_Zealot 2 7572
Protoss_Stargate 1 7774
Protoss_Citadel_of_Adun 1 8297
Protoss_Corsair 4 10354
Protoss_Templar_Archives 1 9403
Protoss_Dark_Templar 1 10450
10450
