Protoss_Forge 1 2894
Protoss_Nexus 1 5235
Protoss_Gateway 2 8915
Protoss_Assimilator 2 7174
Protoss_Photon_Cannon 2 9868
Protoss_Cybernetics_Core 1 6018
Protoss_Zealot 4 8362
Protoss_Stargate 1 7193
Protoss_Citadel_of_Adun 1 7665
Protoss_Corsair 4 10344
Protoss_Templar_Archives 1 8794
Protoss_Robotics_Facility 1 9895
Protoss_Dark_Templar 2 9962
10344
