Protoss_Forge 1 2960
Protoss_Photon_Cannon 2 9951
Protoss_Nexus 1 5373
Protoss_Gateway 4 9844
Protoss_Assimilator 2 6436
Protoss_Cybernetics_Core 1 5872
Protoss_Zealot 4 8624
Protoss_Stargate 1 7187
Protoss_Citadel_of_Adun 1 7591
Protoss_Corsair 3 9110
Protoss_Templar_Archives 1 8639
Protoss_Dark_Templar 2 9478
9951
