Protoss_Nexus 1 4350
Protoss_Forge 1 3483
Protoss_Photon_Cannon 3 10649
Protoss_Gateway 4 10365
Protoss_Assimilator 2 6259
Protoss_Cybernetics_Core 1 5792
Protoss_Zealot 9 10336
Protoss_Stargate 1 7004
Protoss_Citadel_of_Adun 1 7797
Protoss_Corsair 3 10378
Protoss_Templar_Archives 1 10157
10649
