Protoss_Forge 1 3269
Protoss_Nexus 1 5110
Protoss_Photon_Cannon 3 10008
Protoss_Gateway 4 10878
Protoss_Assimilator 2 6980
Protoss_Cybernetics_Core 1 6159
Protoss_Zealot 8 10512
Protoss_Stargate 1 7332
Protoss_Corsair 2 8629
Protoss_Citadel_of_Adun 1 9121
Protoss_Templar_Archives 1 10709
10878
