Protoss_Forge 1 3186
Protoss_Nexus 1 5023
Protoss_Photon_Cannon 2 4822
Protoss_Gateway 2 10127
Protoss_Assimilator 2 6633
Protoss_Cybernetics_Core 1 6332
Protoss_Zealot 4 9996
Protoss_Stargate 1 7726
Protoss_Citadel_of_Adun 1 8173
Protoss_Corsair 3 9892
10127
