Protoss_Nexus 1 4769
Protoss_Gateway 6 10875
Protoss_Forge 1 4214
Protoss_Assimilator 2 6650
Protoss_Photon_Cannon 3 10195
Protoss_Cybernetics_Core 1 6047
Protoss_Zealot 7 9486
Protoss_Stargate 1 7287
Protoss_Citadel_of_Adun 1 7643
Protoss_Corsair 1 7968
Protoss_Templar_Archives 1 8694
Protoss_High_Templar 4 10632
Protoss_Archon 1 10279
10875
