Protoss_Forge 1 3008
Protoss_Nexus 1 5419
Protoss_Gateway 1 5108
Protoss_Assimilator 2 6614
Protoss_Photon_Cannon 8 10384
Protoss_Cybernetics_Core 1 6194
Protoss_Zealot 4 10158
Protoss_Stargate 1 7396
Protoss_Citadel_of_Adun 1 8051
Protoss_Corsair 5 10578
Protoss_Robotics_Facility 1 10470
10578
