Protoss_Forge 1 3272
Protoss_Nexus 1 5181
Protoss_Photon_Cannon 2 10284
Protoss_Gateway 2 9016
Protoss_Assimilator 2 7908
Protoss_Cybernetics_Core 1 6339
Protoss_Zealot 8 10414
Protoss_Stargate 1 7571
Protoss_Citadel_of_Adun 1 7774
Protoss_Dragoon 1 7850
Protoss_Corsair 1 8548
10414
