Protoss_Forge 1 3089
Protoss_Nexus 1 5012
Protoss_Photon_Cannon 3 9659
Protoss_Gateway 4 10527
Protoss_Assimilator 2 7631
Protoss_Cybernetics_Core 1 6077
Protoss_Zealot 8 10502
Protoss_Stargate 1 7392
Protoss_Corsair 2 8722
Protoss_Citadel_of_Adun 1 8485
10527
