Protoss_Forge 1 2909
Protoss_Photon_Cannon 4 10631
Protoss_Nexus 1 5629
Protoss_Gateway 2 8552
Protoss_Zealot 8 9979
Protoss_Assimilator 2 7181
Protoss_Cybernetics_Core 1 6759
Protoss_Stargate 1 8001
Protoss_Citadel_of_Adun 1 8182
Protoss_Corsair 3 10302
Protoss_Templar_Archives 1 9964
10631
