Protoss_Nexus 1 4743
Protoss_Forge 1 4346
Protoss_Gateway 4 10117
Protoss_Photon_Cannon 3 10451
Protoss_Assimilator 2 6541
Protoss_Cybernetics_Core 1 6298
Protoss_Zealot 9 10168
Protoss_Stargate 1 7525
Protoss_Citadel_of_Adun 1 8136
Protoss_Corsair 2 8806
Protoss_Templar_Archives 1 9659
Protoss_Dark_Templar 2 10498
10498
