Protoss_Nexus 1 4529
Protoss_Gateway 1 4071
Protoss_Forge 1 4176
Protoss_Assimilator 2 6996
Protoss_Photon_Cannon 5 9722
Protoss_Cybernetics_Core 1 6083
Protoss_Zealot 3 9030
Protoss_Stargate 1 7230
Protoss_Corsair 5 10408
Protoss_Robotics_Facility 1 9126
Protoss_Shuttle 1 10121
Protoss_Robotics_Support_Bay 1 9861
10408
