Protoss_Forge 1 3073
Protoss_Nexus 1 5041
Protoss_Photon_Cannon 2 4560
Protoss_Gateway 1 5236
Protoss_Assimilator 2 6761
Protoss_Cybernetics_Core 1 6379
Protoss_Zealot 4 9874
Protoss_Stargate 1 7684
Protoss_Dragoon 1 7624
Protoss_Robotics_Facility 1 8458
Protoss_Corsair 4 10468
Protoss_Shuttle 1 9671
Protoss_Robotics_Support_Bay 1 9379
10468
