Protoss_Forge 1 2933
Protoss_Nexus 1 5015
Protoss_Photon_Cannon 2 9760
Protoss_Gateway 4 10886
Protoss_Assimilator 2 6954
Protoss_Cybernetics_Core 1 5699
Protoss_Zealot 4 8160
Protoss_Stargate 1 7128
Protoss_Citadel_of_Adun 1 7554
Protoss_Corsair 5 10406
Protoss_Templar_Archives 1 8665
Protoss_Dark_Templar 2 9530
10886
