Protoss_Forge 1 3036
Protoss_Photon_Cannon 4 6946
Protoss_Nexus 1 5779
Protoss_Gateway 1 5371
Protoss_Assimilator 2 9714
Protoss_Cybernetics_Core 1 8628
Protoss_Zealot 3 9994
Protoss_Stargate 1 9991
Protoss_Citadel_of_Adun 1 10330
10330
