Protoss_Forge 1 2918
Protoss_Photon_Cannon 2 3916
Protoss_Nexus 1 5797
Protoss_Gateway 2 8799
Protoss_Assimilator 2 7618
Protoss_Cybernetics_Core 1 6167
Protoss_Zealot 9 10240
Protoss_Stargate 1 7338
Protoss_Corsair 2 8808
Protoss_Citadel_of_Adun 1 8609
Protoss_Templar_Archives 1 10051
10240
