Protoss_Forge 1 2593
Protoss_Nexus 1 5053
Protoss_Gateway 4 8162
Protoss_Assimilator 2 9717
Protoss_Photon_Cannon 2 9670
Protoss_Cybernetics_Core 1 5829
Protoss_Zealot 11 10102
Protoss_Stargate 1 7115
Protoss_Corsair 2 8600
Protoss_Citadel_of_Adun 1 9655
10102
