Protoss_Forge 1 2850
Protoss_Nexus 1 5213
Protoss_Gateway 4 9139
Protoss_Assimilator 2 7550
Protoss_Cybernetics_Core 1 5734
Protoss_Photon_Cannon 4 10642
Protoss_Zealot 10 10234
Protoss_Stargate 1 7091
Protoss_Citadel_of_Adun 1 7761
Protoss_Corsair 2 10376
10642
