Protoss_Forge 1 2845
Protoss_Photon_Cannon 2 9765
Protoss_Nexus 1 5512
Protoss_Gateway 2 9342
Protoss_Assimilator 2 6484
Protoss_Cybernetics_Core 1 5973
Protoss_Zealot 3 8576
Protoss_Stargate 1 7212
Protoss_Citadel_of_Adun 1 8160
Protoss_Corsair 4 10084
Protoss_Templar_Archives 1 9177
Protoss_Dark_Templar 2 10250
10250
