Protoss_Nexus 1 4577
Protoss_Forge 1 4031
Protoss_Gateway 2 9823
Protoss_Assimilator 2 7082
Protoss_Photon_Cannon 4 10565
Protoss_Cybernetics_Core 1 5783
Protoss_Zealot 7 9924
Protoss_Stargate 1 6930
Protoss_Citadel_of_Adun 1 7564
Protoss_Corsair 1 7682
Protoss_Templar_Archives 1 9673
Protoss_Dark_Templar 2 10722
10722
