Protoss_Forge 1 3338
Protoss_Nexus 1 5061
Protoss_Photon_Cannon 2 9834
Protoss_Gateway 2 9261
Protoss_Assimilator 2 6771
Protoss_Cybernetics_Core 1 6061
Protoss_Zealot 3 8200
Protoss_Stargate 1 7444
Protoss_Citadel_of_Adun 1 8259
Protoss_Corsair 4 10262
Protoss_Templar_Archives 1 9291
Protoss_Dark_Templar 2 10150
10262
