Protoss_Forge 1 2903
Protoss_Photon_Cannon 3 9527
Protoss_Nexus 1 6048
Protoss_Assimilator 2 6920
Protoss_Gateway 2 8735
Protoss_Zealot 8 10308
Protoss_Cybernetics_Core 1 6782
Protoss_Stargate 1 7974
Protoss_Citadel_of_Adun 1 8067
Protoss_Corsair 1 8654
Protoss_Templar_Archives 1 10368
Protoss_Ground_Weapons_1 1 9953
10368
