Protoss_Forge 1 2755
Protoss_Nexus 1 5095
Protoss_Gateway 3 9866
Protoss_Photon_Cannon 3 9696
Protoss_Assimilator 2 7281
Protoss_Cybernetics_Core 1 5963
Protoss_Zealot 7 10236
Protoss_Stargate 1 7484
Protoss_Citadel_of_Adun 1 7921
Protoss_Corsair 2 9896
Protoss_Templar_Archives 1 10032
10236
