Protoss_Forge 1 2810
Protoss_Photon_Cannon 3 10383
Protoss_Nexus 1 5753
Protoss_Gateway 2 9316
Protoss_Assimilator 2 6545
Protoss_Cybernetics_Core 1 6138
Protoss_Zealot 8 10138
Protoss_Stargate 1 7318
Protoss_Citadel_of_Adun 1 8224
Protoss_Corsair 4 10034
Protoss_Templar_Archives 1 10681
10681
