Protoss_Forge 1 3067
Protoss_Photon_Cannon 2 4234
Protoss_Nexus 1 5950
Protoss_Gateway 3 9881
Protoss_Assimilator 2 7239
Protoss_Zealot 5 10056
Protoss_Cybernetics_Core 1 6355
Protoss_Dragoon 1 7242
Protoss_Stargate 1 7720
Protoss_Citadel_of_Adun 1 8653
Protoss_Corsair 3 10402
10402
