Protoss_Forge 1 3261
Protoss_Photon_Cannon 3 10223
Protoss_Nexus 1 6041
Protoss_Gateway 3 10642
Protoss_Assimilator 2 7660
Protoss_Cybernetics_Core 1 6364
Protoss_Zealot 8 10488
Protoss_Dragoon 1 7198
Protoss_Stargate 1 7734
Protoss_Citadel_of_Adun 1 8539
Protoss_Corsair 2 9140
Protoss_Templar_Archives 1 10577
10642
