Protoss_Forge 1 2937
Protoss_Photon_Cannon 2 3796
Protoss_Nexus 1 5994
Protoss_Gateway 4 10727
Protoss_Assimilator 2 6735
Protoss_Cybernetics_Core 1 6197
Protoss_Zealot 8 10300
Protoss_Stargate 1 7396
Protoss_Citadel_of_Adun 1 7955
Protoss_Corsair 2 8726
Protoss_Templar_Archives 1 9841
10727
