Protoss_Forge 1 2817
Protoss_Nexus 1 5081
Protoss_Gateway 2 8707
Protoss_Assimilator 2 6250
Protoss_Photon_Cannon 2 9633
Protoss_Zealot 10 10582
Protoss_Cybernetics_Core 1 6131
Protoss_Stargate 1 7302
Protoss_Citadel_of_Adun 1 7815
Protoss_Corsair 4 10404
10582
