Protoss_Forge 1 3258
Protoss_Photon_Cannon 2 10509
Protoss_Nexus 1 5539
Protoss_Gateway 3 8107
Protoss_Assimilator 2 6822
Protoss_Cybernetics_Core 1 6221
Protoss_Zealot 12 10220
Protoss_Dragoon 1 7056
Protoss_Citadel_of_Adun 1 7586
Protoss_Stargate 2 10171
Protoss_Ground_Weapons_1 1 9997
10509
