Protoss_Nexus 1 4697
Protoss_Gateway 1 4383
Protoss_Forge 1 4482
Protoss_Assimilator 2 7577
Protoss_Photon_Cannon 4 8498
Protoss_Zealot 4 9606
Protoss_Cybernetics_Core 1 6781
Protoss_Stargate 1 7982
Protoss_Dragoon 1 7812
Protoss_Robotics_Facility 1 8668
Protoss_Corsair 4 10518
Protoss_Shuttle 1 9673
Protoss_Robotics_Support_Bay 1 10238
10518
