Protoss_Nexus 1 4659
Protoss_Forge 1 3877
Protoss_Gateway 1 4692
Protoss_Photon_Cannon 3 9977
Protoss_Assimilator 2 6375
Protoss_Cybernetics_Core 1 5979
Protoss_Zealot 7 10330
Protoss_Stargate 1 7306
Protoss_Citadel_of_Adun 1 7981
Protoss_Corsair 4 9960
Protoss_Robotics_Facility 1 9551
Protoss_Robotics_Support_Bay 1 10099
10330
