Protoss_Gateway 2 8922
Protoss_Assimilator 1 2889
Protoss_Cybernetics_Core 1 3809
Protoss_Zealot 4 7838
Protoss_Stargate 1 5109
Protoss_Dragoon 1 5148
Protoss_Corsair 1 5828
Protoss_Citadel_of_Adun 1 6584
Protoss_Templar_Archives 1 8099
Protoss_Dark_Templar 1 8988
Protoss_Forge 1 8930
Protoss_Nexus 1 10517
Protoss_High_Templar 2 10028
Protoss_Photon_Cannon 3 10595
10595
