Protoss_Forge 1 3014
Protoss_Photon_Cannon 3 5370
Protoss_Nexus 1 5811
Protoss_Gateway 4 10405
Protoss_Assimilator 2 7190
Protoss_Zealot 5 9060
Protoss_Cybernetics_Core 1 6888
Protoss_Stargate 1 8096
Protoss_Citadel_of_Adun 1 8710
Protoss_Corsair 1 8782
Protoss_Templar_Archives 1 9703
Protoss_High_Templar 2 10648
10648
