Protoss_Forge 1 3249
Protoss_Nexus 1 5205
Protoss_Photon_Cannon 3 9844
Protoss_Gateway 3 8105
Protoss_Assimilator 2 8655
Protoss_Cybernetics_Core 1 6195
Protoss_Zealot 12 10450
Protoss_Citadel_of_Adun 1 7505
Protoss_Stargate 2 9452
Protoss_Corsair 2 10466
Protoss_Ground_Weapons_1 1 9921
10466
