Protoss_Gateway 4 10821
Protoss_Zealot 7 8964
Protoss_Nexus 1 6278
Protoss_Assimilator 2 7982
Protoss_Cybernetics_Core 1 6831
Protoss_Forge 1 6976
Protoss_Stargate 1 8334
Protoss_Photon_Cannon 3 10301
Protoss_Dragoon 1 8362
Protoss_Citadel_of_Adun 1 9144
Protoss_Corsair 1 9112
Protoss_Templar_Archives 1 10161
10821
