Protoss_Gateway 2 3157
Protoss_Zealot 11 10000
Protoss_Shield_Battery 1 6299
Protoss_Forge 1 6521
Protoss_Photon_Cannon 4 9321
Protoss_Assimilator 1 8245
Protoss_Cybernetics_Core 1 9223
Protoss_Stargate 1 10611
10611
