Protoss_Forge 1 2870
Protoss_Photon_Cannon 3 9965
Protoss_Nexus 1 5846
Protoss_Gateway 3 9038
Protoss_Assimilator 2 7055
Protoss_Zealot 7 10044
Protoss_Cybernetics_Core 1 6354
Protoss_Stargate 1 7563
Protoss_Citadel_of_Adun 1 8059
Protoss_Corsair 3 10204
Protoss_Templar_Archives 1 9663
10204
