Protoss_Forge 1 2938
Protoss_Photon_Cannon 1 3823
Protoss_Nexus 1 5511
Protoss_Gateway 4 10669
Protoss_Assimilator 2 8053
Protoss_Zealot 8 9996
Protoss_Cybernetics_Core 1 6356
Protoss_Stargate 1 7569
Protoss_Citadel_of_Adun 1 8081
Protoss_Corsair 3 9308
Protoss_Ground_Weapons_1 1 9925
10669
