Protoss_Forge 1 2933
Protoss_Photon_Cannon 3 3952
Protoss_Nexus 1 5869
Protoss_Gateway 4 9687
Protoss_Assimilator 2 7304
Protoss_Cybernetics_Core 1 6277
Protoss_Zealot 5 10318
Protoss_Stargate 1 7418
Protoss_Citadel_of_Adun 1 8099
Protoss_Corsair 1 8156
Protoss_Dragoon 1 8486
Protoss_Templar_Archives 1 9093
Protoss_Dark_Templar 1 10014
Protoss_High_Templar 2 10548
10548
