Protoss_Forge 1 2878
Protoss_Photon_Cannon 3 10073
Protoss_Nexus 1 5575
Protoss_Gateway 1 5045
Protoss_Assimilator 2 6993
Protoss_Zealot 4 9228
Protoss_Cybernetics_Core 1 6504
Protoss_Stargate 1 7801
Protoss_Dragoon 1 7790
Protoss_Corsair 4 10494
Protoss_Robotics_Facility 1 9504
10494
