Protoss_Forge 1 2896
Protoss_Nexus 1 5207
Protoss_Gateway 5 10470
Protoss_Assimilator 2 6403
Protoss_Photon_Cannon 2 8721
Protoss_Cybernetics_Core 1 5937
Protoss_Zealot 4 8238
Protoss_Stargate 1 7156
Protoss_Citadel_of_Adun 1 7491
Protoss_Corsair 1 7886
Protoss_Templar_Archives 1 8937
Protoss_High_Templar 4 10246
10470
