Protoss_Nexus 1 4544
Protoss_Forge 1 3666
Protoss_Photon_Cannon 4 10359
Protoss_Gateway 5 9427
Protoss_Assimilator 2 6660
Protoss_Cybernetics_Core 1 6308
Protoss_Zealot 3 7738
Protoss_Stargate 1 7484
Protoss_Citadel_of_Adun 1 7744
Protoss_Corsair 2 10174
Protoss_Templar_Archives 1 8779
Protoss_High_Templar 4 9988
Protoss_Archon 1 10263
10359
