Protoss_Forge 1 3129
Protoss_Nexus 1 5097
Protoss_Photon_Cannon 3 10082
Protoss_Gateway 1 5379
Protoss_Assimilator 2 6566
Protoss_Cybernetics_Core 1 6561
Protoss_Zealot 4 8996
Protoss_Stargate 1 7778
Protoss_Robotics_Facility 1 8484
Protoss_Corsair 4 10386
Protoss_Robotics_Support_Bay 1 9296
Protoss_Reaver 1 10572
10572
