Protoss_Forge 1 2725
Protoss_Photon_Cannon 3 10252
Protoss_Nexus 1 5379
Protoss_Gateway 2 9391
Protoss_Assimilator 2 7578
Protoss_Zealot 5 9294
Protoss_Cybernetics_Core 1 7058
Protoss_Stargate 1 8212
Protoss_Citadel_of_Adun 1 8644
Protoss_Corsair 2 10130
Protoss_Templar_Archives 1 9813
10252
