Protoss_Gateway 2 8504
Protoss_Assimilator 1 2999
Protoss_Cybernetics_Core 1 3892
Protoss_Robotics_Facility 1 5351
Protoss_Dragoon 3 7808
Protoss_Zealot 1 5825
Protoss_Shuttle 1 6347
Protoss_Observatory 1 6278
Protoss_Observer 2 7873
Protoss_Stargate 1 7710
Protoss_Corsair 4 10385
Protoss_Robotics_Support_Bay 1 8689
Protoss_Forge 1 9260
Protoss_Nexus 1 11507
Protoss_Reaver 1 10911
11507
