Protoss_Gateway 2 3335
Protoss_Zealot 17 9698
Protoss_Assimilator 1 6499
Protoss_Forge 1 8009
Protoss_Cybernetics_Core 1 9634
Protoss_Photon_Cannon 1 10150
Protoss_Citadel_of_Adun 1 10790
10790
