Protoss_Nexus 1 4775
Protoss_Forge 1 3825
Protoss_Photon_Cannon 11 10320
Protoss_Gateway 1 5786
Protoss_Assimilator 2 7601
Protoss_Zealot 1 6688
Protoss_Cybernetics_Core 1 7394
Protoss_Stargate 1 8573
Protoss_Robotics_Facility 1 9112
Protoss_Corsair 2 9978
Protoss_Robotics_Support_Bay 1 9711
Protoss_Reaver 1 10896
10896
