Protoss_Forge 1 2804
Protoss_Photon_Cannon 6 10108
Protoss_Nexus 1 7420
Protoss_Gateway 4 9278
Protoss_Zealot 8 10593
Protoss_Assimilator 1 8510
Protoss_Cybernetics_Core 1 10785
10785
