Protoss_Gateway 2 6969
Protoss_Assimilator 1 3044
Protoss_Zealot 8 10008
Protoss_Cybernetics_Core 1 4599
Protoss_Stargate 1 5865
Protoss_Citadel_of_Adun 1 6117
Protoss_Corsair 1 6553
Protoss_Templar_Archives 1 7219
Protoss_Dark_Templar 2 8168
Protoss_High_Templar 1 8978
10008
