Protoss_Gateway 1 2919
Protoss_Assimilator 1 3215
Protoss_Cybernetics_Core 1 4105
Protoss_Zealot 2 5400
Protoss_Stargate 1 5425
Protoss_Citadel_of_Adun 1 6229
Protoss_Corsair 1 6338
Protoss_Dragoon 1 6903
Protoss_Templar_Archives 1 7415
Protoss_Dark_Templar 1 8318
Protoss_Forge 1 8264
Protoss_High_Templar 2 10213
Protoss_Photon_Cannon 2 10450
Protoss_Nexus 1 10920
10920
