Protoss_Forge 1 2910
Protoss_Photon_Cannon 10 10214
Protoss_Nexus 2 8310
Protoss_Gateway 1 5124
Protoss_Assimilator 2 7722
Protoss_Zealot 2 7813
Protoss_Cybernetics_Core 1 7483
Protoss_Stargate 2 9803
Protoss_Corsair 2 10228
Protoss_Robotics_Facility 1 11062
11062
