Protoss_Forge 1 2682
Protoss_Photon_Cannon 3 9458
Protoss_Nexus 1 5275
Protoss_Gateway 2 9411
Protoss_Assimilator 2 6939
Protoss_Zealot 3 7300
Protoss_Cybernetics_Core 1 6875
Protoss_Stargate 1 8113
Protoss_Dragoon 2 9185
Protoss_Citadel_of_Adun 1 8308
Protoss_Templar_Archives 1 9339
Protoss_Corsair 2 9763
Protoss_High_Templar 2 10423
10423
