Protoss_Nexus 1 4568
Protoss_Forge 1 3704
Protoss_Gateway 1 4749
Protoss_Assimilator 2 6916
Protoss_Photon_Cannon 6 10661
Protoss_Cybernetics_Core 1 5958
Protoss_Zealot 2 6732
Protoss_Stargate 1 7106
Protoss_Robotics_Facility 1 8156
Protoss_Dragoon 1 8268
Protoss_Corsair 4 10254
Protoss_Shuttle 1 9559
Protoss_Robotics_Support_Bay 1 9270
10661
