Protoss_Gateway 2 7949
Protoss_Assimilator 1 3234
Protoss_Cybernetics_Core 1 4101
Protoss_Stargate 1 5291
Protoss_Zealot 3 10484
Protoss_Scout 1 6729
Protoss_Citadel_of_Adun 1 7844
10484
