Protoss_Gateway 3 10747
Protoss_Assimilator 1 2921
Protoss_Cybernetics_Core 1 3827
Protoss_Zealot 5 10238
Protoss_Stargate 1 5249
Protoss_Dragoon 1 5240
Protoss_Corsair 2 6740
Protoss_Citadel_of_Adun 1 6698
Protoss_Templar_Archives 1 8023
Protoss_Forge 1 8199
Protoss_Dark_Templar 1 8854
Protoss_Photon_Cannon 1 9318
Protoss_High_Templar 1 9636
10747
