Protoss_Forge 1 3259
Protoss_Photon_Cannon 4 10178
Protoss_Nexus 1 5540
Protoss_Gateway 2 10844
Protoss_Assimilator 2 7886
Protoss_Zealot 6 9895
Protoss_Cybernetics_Core 1 6851
Protoss_Dragoon 1 7688
Protoss_Stargate 1 8275
Protoss_Corsair 2 10063
Protoss_Citadel_of_Adun 1 9819
Protoss_Templar_Archives 1 10836
10844
