Protoss_Gateway 2 3407
Protoss_Zealot 13 8164
Protoss_Assimilator 1 6334
Protoss_Cybernetics_Core 1 7905
Protoss_Stargate 1 9232
Protoss_Dragoon 1 9232
Protoss_Citadel_of_Adun 1 9713
Protoss_Forge 1 9732
Protoss_Corsair 1 9922
9922
