Protoss_Nexus 1 4459
Protoss_Forge 1 3996
Protoss_Photon_Cannon 4 9674
Protoss_Gateway 4 8269
Protoss_Assimilator 2 7093
Protoss_Cybernetics_Core 1 6430
Protoss_Zealot 10 10284
Protoss_Citadel_of_Adun 1 7605
Protoss_Dragoon 1 8262
Protoss_Templar_Archives 1 10187
10284
