Protoss_Forge 1 2833
Protoss_Nexus 1 5166
Protoss_Photon_Cannon 2 4824
Protoss_Gateway 2 9316
Protoss_Assimilator 2 7268
Protoss_Cybernetics_Core 1 6454
Protoss_Zealot 3 8804
Protoss_Stargate 1 7816
Protoss_Citadel_of_Adun 1 8419
Protoss_Corsair 2 9712
Protoss_Templar_Archives 1 9511
9712
