Protoss_Gateway 2 8422
Protoss_Assimilator 2 10589
Protoss_Zealot 4 7448
Protoss_Cybernetics_Core 1 4538
Protoss_Stargate 1 5698
Protoss_Dragoon 1 5702
Protoss_Citadel_of_Adun 1 6260
Protoss_Corsair 1 6378
Protoss_Forge 1 6650
Protoss_Templar_Archives 1 7415
Protoss_Dark_Templar 1 8258
Protoss_Photon_Cannon 2 9678
Protoss_Nexus 1 10282
Protoss_High_Templar 2 9952
10589
