Protoss_Gateway 1 2503
Protoss_Zealot 6 7734
Protoss_Assimilator 1 4215
Protoss_Cybernetics_Core 1 5599
Protoss_Dragoon 1 7132
Protoss_Stargate 1 7952
Protoss_Forge 1 9591
9591
