Protoss_Gateway 3 10841
Protoss_Zealot 10 10138
Protoss_Forge 1 3994
Protoss_Nexus 1 6845
Protoss_Photon_Cannon 2 6830
Protoss_Assimilator 2 7971
Protoss_Cybernetics_Core 1 7966
Protoss_Stargate 1 9311
Protoss_Citadel_of_Adun 1 9760
Protoss_Corsair 1 9994
10841
