Protoss_Forge 1 2675
Protoss_Photon_Cannon 8 10371
Protoss_Nexus 2 10795
Protoss_Assimilator 3 7795
Protoss_Gateway 1 6522
Protoss_Cybernetics_Core 1 7572
Protoss_Zealot 2 9155
Protoss_Citadel_of_Adun 1 9621
Protoss_Templar_Archives 1 10778
10795
