Protoss_Nexus 1 4533
Protoss_Forge 1 3680
Protoss_Photon_Cannon 2 9506
Protoss_Gateway 1 5159
Protoss_Assimilator 2 6518
Protoss_Zealot 4 8402
Protoss_Cybernetics_Core 1 6608
Protoss_Stargate 1 7760
Protoss_Dragoon 1 7800
Protoss_Robotics_Facility 1 8333
Protoss_Corsair 1 8840
Protoss_Shuttle 1 9359
Protoss_Robotics_Support_Bay 1 9109
9506
