Protoss_Gateway 1 2940
Protoss_Assimilator 1 2954
Protoss_Zealot 4 8178
Protoss_Cybernetics_Core 1 5026
Protoss_Stargate 1 6789
Protoss_Dragoon 1 6833
Protoss_Forge 1 6783
Protoss_Corsair 2 10023
Protoss_Nexus 2 10575
Protoss_Citadel_of_Adun 1 9116
Protoss_Photon_Cannon 2 9852
10575
