Protoss_Forge 1 2903
Protoss_Nexus 1 5235
Protoss_Gateway 1 4989
Protoss_Photon_Cannon 3 9372
Protoss_Assimilator 2 6681
Protoss_Zealot 2 6873
Protoss_Cybernetics_Core 1 6714
Protoss_Dragoon 1 7948
Protoss_Stargate 2 8525
Protoss_Robotics_Facility 1 9583
Protoss_Corsair 4 9938
9938
