Protoss_Forge 1 2917
Protoss_Photon_Cannon 3 7064
Protoss_Nexus 1 6250
Protoss_Gateway 3 9225
Protoss_Assimilator 2 7465
Protoss_Cybernetics_Core 1 6814
Protoss_Zealot 1 6753
Protoss_Stargate 1 8025
Protoss_Dragoon 1 7788
Protoss_Citadel_of_Adun 1 8609
Protoss_Corsair 3 10093
Protoss_Templar_Archives 1 9627
Protoss_Dark_Templar 3 10523
10523
