Protoss_Nexus 1 4740
Protoss_Forge 1 3854
Protoss_Photon_Cannon 4 9359
Protoss_Gateway 3 8289
Protoss_Assimilator 2 6823
Protoss_Zealot 5 10533
Protoss_Cybernetics_Core 1 6834
Protoss_Citadel_of_Adun 1 7905
Protoss_Dragoon 1 8114
Protoss_Templar_Archives 1 9021
Protoss_High_Templar 3 10218
10533
