Protoss_Gateway 2 3142
Protoss_Zealot 12 9942
Protoss_Assimilator 2 9152
Protoss_Nexus 1 7899
Protoss_Forge 1 6930
Protoss_Cybernetics_Core 1 7918
Protoss_Photon_Cannon 2 10637
Protoss_Citadel_of_Adun 1 8991
Protoss_Stargate 1 9467
Protoss_Corsair 1 10190
10637
