Protoss_Gateway 2 3271
Protoss_Zealot 19 10424
Protoss_Forge 1 7185
Protoss_Assimilator 1 7213
Protoss_Cybernetics_Core 1 8463
Protoss_Photon_Cannon 1 8359
Protoss_Citadel_of_Adun 1 9602
10424
