Protoss_Gateway 3 8113
Protoss_Assimilator 1 2814
Protoss_Cybernetics_Core 1 3807
Protoss_Stargate 1 5014
Protoss_Zealot 16 10474
Protoss_Dragoon 1 4952
Protoss_Corsair 2 6584
Protoss_Citadel_of_Adun 1 6402
10474
