Protoss_Forge 1 3128
Protoss_Photon_Cannon 2 4854
Protoss_Nexus 1 5679
Protoss_Gateway 3 10511
Protoss_Assimilator 3 9798
Protoss_Zealot 7 10400
Protoss_Cybernetics_Core 1 8673
Protoss_Dragoon 1 9798
Protoss_Citadel_of_Adun 1 10025
10511
