Protoss_Gateway 2 3501
Protoss_Zealot 9 8158
Protoss_Assimilator 1 4249
Protoss_Cybernetics_Core 1 5273
Protoss_Dragoon 1 6113
Protoss_Stargate 1 6831
Protoss_Corsair 1 7598
Protoss_Forge 1 8006
Protoss_Photon_Cannon 1 9261
Protoss_Citadel_of_Adun 1 9697
9697
