Protoss_Gateway 3 10185
Protoss_Zealot 4 6614
Protoss_Assimilator 2 9347
Protoss_Cybernetics_Core 1 4805
Protoss_Stargate 1 6013
Protoss_Dragoon 1 6012
Protoss_Forge 1 6813
Protoss_Corsair 1 6910
Protoss_Photon_Cannon 1 8352
Protoss_Nexus 1 9539
Protoss_Citadel_of_Adun 1 8903
Protoss_Templar_Archives 1 9986
10185
