Protoss_Gateway 2 3401
Protoss_Zealot 10 6654
Protoss_Assimilator 1 5692
Protoss_Cybernetics_Core 1 7541
Protoss_Dragoon 6 10654
Protoss_Robotics_Facility 1 9189
Protoss_Shuttle 1 10177
Protoss_Robotics_Support_Bay 1 10038
10654
