Protoss_Nexus 1 4735
Protoss_Gateway 1 4224
Protoss_Forge 1 4305
Protoss_Photon_Cannon 1 5150
Protoss_Zealot 4 10343
Protoss_Assimilator 1 5465
Protoss_Cybernetics_Core 1 7123
Protoss_Robotics_Facility 1 10629
10629
