Protoss_Forge 1 2444
Protoss_Photon_Cannon 7 10608
Protoss_Nexus 2 10629
Protoss_Gateway 1 5762
Protoss_Assimilator 2 7794
Protoss_Cybernetics_Core 1 6768
Protoss_Dragoon 4 10282
Protoss_Stargate 1 8091
Protoss_Corsair 3 10314
10629
