Protoss_Gateway 3 10287
Protoss_Assimilator 1 2806
Protoss_Cybernetics_Core 1 3737
Protoss_Dragoon 7 10456
Protoss_Robotics_Facility 1 5472
Protoss_Shuttle 1 6463
Protoss_Robotics_Support_Bay 1 6160
Protoss_Reaver 2 8738
10456
