Protoss_Forge 1 3044
Protoss_Photon_Cannon 2 10034
Protoss_Nexus 1 5828
Protoss_Gateway 2 10875
Protoss_Assimilator 2 5655
Protoss_Zealot 2 6698
Protoss_Cybernetics_Core 1 6581
Protoss_Stargate 1 7870
Protoss_Dragoon 2 9296
Protoss_Robotics_Facility 1 8808
Protoss_Corsair 4 10524
Protoss_Robotics_Support_Bay 1 9369
Protoss_Reaver 1 10560
10875
