Protoss_Forge 1 2952
Protoss_Nexus 1 5269
Protoss_Photon_Cannon 1 4310
Protoss_Gateway 4 9531
Protoss_Assimilator 2 7555
Protoss_Cybernetics_Core 1 6368
Protoss_Zealot 12 10470
Protoss_Citadel_of_Adun 1 7612
Protoss_Dragoon 1 8133
Protoss_Robotics_Facility 1 9979
Protoss_Templar_Archives 1 9837
Protoss_Ground_Weapons_1 1 9911
10470
