Protoss_Forge 1 3394
Protoss_Nexus 1 5187
Protoss_Photon_Cannon 4 9333
Protoss_Gateway 3 10411
Protoss_Assimilator 2 7906
Protoss_Cybernetics_Core 1 7033
Protoss_Zealot 7 10508
Protoss_Stargate 1 8292
Protoss_Citadel_of_Adun 1 8575
Protoss_Corsair 2 9680
Protoss_Templar_Archives 1 9732
10508
