Protoss_Gateway 1 2575
Protoss_Zealot 3 5362
Protoss_Assimilator 1 4255
Protoss_Cybernetics_Core 1 5252
Protoss_Dragoon 1 6292
Protoss_Stargate 1 6670
Protoss_Robotics_Facility 1 7735
Protoss_Corsair 2 10000
Protoss_Shuttle 1 9141
10000
