Protoss_Forge 1 2755
Protoss_Photon_Cannon 2 4180
Protoss_Nexus 1 6255
Protoss_Gateway 4 9064
Protoss_Assimilator 1 5605
Protoss_Zealot 7 10166
Protoss_Cybernetics_Core 1 6674
10166
