Protoss_Gateway 2 3141
Protoss_Zealot 17 9188
Protoss_Assimilator 1 5798
Protoss_Cybernetics_Core 1 8717
Protoss_Forge 1 9378
Protoss_Stargate 1 10257
Protoss_Photon_Cannon 1 10302
Protoss_Citadel_of_Adun 1 10893
10893
