Protoss_Forge 1 2998
Protoss_Photon_Cannon 8 10045
Protoss_Nexus 1 5990
Protoss_Gateway 3 10818
Protoss_Assimilator 2 10058
Protoss_Zealot 5 10333
Protoss_Cybernetics_Core 1 7470
Protoss_Citadel_of_Adun 1 8464
Protoss_Templar_Archives 1 9459
Protoss_Dark_Templar 1 10568
10818
