Protoss_Gateway 1 2681
Protoss_Zealot 3 4588
Protoss_Assimilator 1 3809
Protoss_Cybernetics_Core 1 5258
Protoss_Stargate 1 6396
Protoss_Forge 1 6014
Protoss_Photon_Cannon 4 9453
Protoss_Corsair 3 9030
Protoss_Robotics_Facility 1 7894
Protoss_Citadel_of_Adun 1 9107
Protoss_Nexus 1 11173
Protoss_Robotics_Support_Bay 1 10069
11173
