Protoss_Forge 1 2673
Protoss_Nexus 1 5224
Protoss_Gateway 4 10121
Protoss_Photon_Cannon 4 10697
Protoss_Assimilator 2 7213
Protoss_Zealot 3 8102
Protoss_Cybernetics_Core 1 6402
Protoss_Dragoon 1 7326
Protoss_Stargate 1 7697
Protoss_Citadel_of_Adun 1 8046
Protoss_Corsair 2 9266
Protoss_Templar_Archives 1 9229
Protoss_Robotics_Facility 1 10917
Protoss_Dark_Templar 1 10484
10917
