Protoss_Forge 1 2587
Protoss_Nexus 1 5368
Protoss_Photon_Cannon 5 10049
Protoss_Gateway 3 8879
Protoss_Assimilator 2 6457
Protoss_Cybernetics_Core 1 7090
Protoss_Robotics_Facility 1 8410
Protoss_Stargate 1 8373
Protoss_Citadel_of_Adun 1 8729
Protoss_Robotics_Support_Bay 1 9128
Protoss_Corsair 2 10148
Protoss_Reaver 1 10371
Protoss_Templar_Archives 1 10607
10607
