Protoss_Gateway 2 3539
Protoss_Zealot 8 9828
Protoss_Assimilator 1 5337
Protoss_Forge 1 6492
Protoss_Cybernetics_Core 1 7443
Protoss_Photon_Cannon 1 7785
Protoss_Dragoon 1 8318
Protoss_Citadel_of_Adun 1 8488
9828
