Protoss_Forge 1 3674
Protoss_Photon_Cannon 4 9900
Protoss_Nexus 1 5893
Protoss_Gateway 4 9305
Protoss_Assimilator 1 5719
Protoss_Zealot 10 10505
Protoss_Cybernetics_Core 1 6849
Protoss_Dragoon 1 7763
Protoss_Citadel_of_Adun 1 8358
10505
