Protoss_Gateway 2 7340
Protoss_Assimilator 1 3119
Protoss_Cybernetics_Core 1 4084
Protoss_Zealot 10 9252
Protoss_Dragoon 1 5440
Protoss_Citadel_of_Adun 1 6505
Protoss_Templar_Archives 1 8854
Protoss_Forge 1 9442
Protoss_High_Templar 2 10004
Protoss_Photon_Cannon 1 10677
10677
