Protoss_Gateway 2 3109
Protoss_Zealot 11 9433
Protoss_Assimilator 1 5389
Protoss_Cybernetics_Core 1 7113
Protoss_Stargate 1 8355
Protoss_Dragoon 1 8388
Protoss_Citadel_of_Adun 1 9022
Protoss_Corsair 1 9048
9433
