Protoss_Forge 1 2903
Protoss_Nexus 1 5135
Protoss_Gateway 3 8695
Protoss_Photon_Cannon 2 5625
Protoss_Assimilator 2 7365
Protoss_Zealot 9 10368
Protoss_Cybernetics_Core 1 6789
Protoss_Citadel_of_Adun 1 8076
Protoss_Stargate 2 10283
Protoss_Corsair 1 10478
10478
