Protoss_Forge 1 2634
Protoss_Photon_Cannon 8 10662
Protoss_Nexus 1 5523
Protoss_Gateway 2 8707
Protoss_Assimilator 2 7409
Protoss_Zealot 2 8102
Protoss_Cybernetics_Core 1 6569
Protoss_Stargate 1 7792
Protoss_Citadel_of_Adun 1 8202
Protoss_Corsair 3 10570
Protoss_Templar_Archives 1 9299
Protoss_High_Templar 2 10298
10662
