Protoss_Nexus 1 4515
Protoss_Forge 1 3882
Protoss_Gateway 1 4989
Protoss_Assimilator 2 6585
Protoss_Photon_Cannon 2 5875
Protoss_Cybernetics_Core 1 6483
Protoss_Zealot 5 10468
Protoss_Stargate 1 7781
Protoss_Robotics_Facility 1 8683
Protoss_Dragoon 1 8640
Protoss_Corsair 3 9707
Protoss_Shuttle 1 9687
Protoss_Robotics_Support_Bay 1 9549
Protoss_Reaver 1 10738
Protoss_Citadel_of_Adun 1 10678
10738
