Protoss_Forge 1 3512
Protoss_Nexus 1 5178
Protoss_Photon_Cannon 6 10264
Protoss_Gateway 1 5639
Protoss_Assimilator 2 7018
Protoss_Cybernetics_Core 1 6781
Protoss_Zealot 2 7258
Protoss_Stargate 2 10410
Protoss_Robotics_Facility 1 8759
Protoss_Corsair 3 10464
Protoss_Robotics_Support_Bay 1 9301
Protoss_Reaver 1 10746
10746
