Protoss_Forge 1 2637
Protoss_Photon_Cannon 8 10597
Protoss_Nexus 1 6255
Protoss_Gateway 4 10619
Protoss_Assimilator 2 8728
Protoss_Zealot 4 9870
Protoss_Cybernetics_Core 1 7891
Protoss_Stargate 1 9033
Protoss_Citadel_of_Adun 1 9130
Protoss_Corsair 1 9723
Protoss_Templar_Archives 1 10188
10619
