Protoss_Forge 2 4494
Protoss_Nexus 1 4793
Protoss_Gateway 3 9443
Protoss_Assimilator 2 7578
Protoss_Photon_Cannon 4 9815
Protoss_Zealot 4 8840
Protoss_Cybernetics_Core 1 6557
Protoss_Dragoon 1 7404
Protoss_Stargate 1 7776
Protoss_Citadel_of_Adun 1 7906
Protoss_Corsair 1 8552
Protoss_Templar_Archives 1 9074
Protoss_Dark_Templar 1 9980
Protoss_High_Templar 2 10412
10412
