Protoss_Forge 2 10550
Protoss_Photon_Cannon 9 9246
Protoss_Nexus 1 5513
Protoss_Gateway 1 5279
Protoss_Assimilator 2 6967
Protoss_Zealot 2 7216
Protoss_Cybernetics_Core 1 6991
Protoss_Stargate 1 8218
Protoss_Robotics_Facility 1 9011
Protoss_Corsair 1 9386
Protoss_Robotics_Support_Bay 1 9603
Protoss_Reaver 1 10744
10744
