Protoss_Gateway 2 8250
Protoss_Assimilator 1 3060
Protoss_Zealot 3 8713
Protoss_Cybernetics_Core 1 4815
Protoss_Dragoon 1 5658
Protoss_Stargate 1 6270
Protoss_Citadel_of_Adun 1 6955
Protoss_Corsair 1 6958
Protoss_Templar_Archives 1 8155
Protoss_Nexus 1 10340
Protoss_Dark_Templar 1 9893
10340
