Protoss_Gateway 2 9679
Protoss_Assimilator 1 3030
Protoss_Zealot 2 4658
Protoss_Cybernetics_Core 1 4754
Protoss_Dragoon 5 9907
Protoss_Stargate 1 6549
Protoss_Corsair 1 7253
Protoss_Robotics_Facility 1 8042
Protoss_Shuttle 1 9032
Protoss_Observatory 1 8663
Protoss_Observer 1 9635
9907
