Protoss_Forge 1 3085
Protoss_Nexus 1 5278
Protoss_Gateway 4 8473
Protoss_Assimilator 2 10085
Protoss_Photon_Cannon 1 5024
Protoss_Zealot 14 10508
Protoss_Cybernetics_Core 1 6559
Protoss_Citadel_of_Adun 1 7629
Protoss_Templar_Archives 1 9954
10508
