Protoss_Gateway 2 8885
Protoss_Assimilator 1 3020
Protoss_Zealot 3 6330
Protoss_Cybernetics_Core 1 4650
Protoss_Stargate 1 5984
Protoss_Dragoon 1 5728
Protoss_Citadel_of_Adun 1 6293
Protoss_Corsair 1 6758
Protoss_Templar_Archives 1 7334
Protoss_Forge 1 7543
Protoss_Dark_Templar 1 8368
Protoss_Photon_Cannon 3 10324
Protoss_Nexus 1 10433
Protoss_High_Templar 2 10088
10433
