Protoss_Forge 1 2900
Protoss_Photon_Cannon 3 10380
Protoss_Nexus 1 5916
Protoss_Gateway 4 8997
Protoss_Assimilator 2 6956
Protoss_Zealot 2 7448
Protoss_Cybernetics_Core 1 6859
Protoss_Citadel_of_Adun 1 7897
Protoss_Dragoon 1 8223
Protoss_Templar_Archives 1 9109
Protoss_Dark_Templar 2 9998
Protoss_High_Templar 2 9988
Protoss_Robotics_Facility 1 11137
11137
