Protoss_Gateway 2 10115
Protoss_Assimilator 1 3140
Protoss_Zealot 3 8568
Protoss_Cybernetics_Core 1 4819
Protoss_Robotics_Facility 1 6128
Protoss_Dragoon 4 9658
Protoss_Shuttle 1 7187
Protoss_Robotics_Support_Bay 1 7101
Protoss_Reaver 2 9486
10115
