Protoss_Forge 1 2599
Protoss_Photon_Cannon 3 6115
Protoss_Nexus 1 6200
Protoss_Gateway 2 8584
Protoss_Assimilator 2 8553
Protoss_Cybernetics_Core 1 6783
Protoss_Zealot 5 10242
Protoss_Dragoon 1 7633
Protoss_Citadel_of_Adun 1 8065
Protoss_Templar_Archives 1 9784
10242
