Protoss_Assimilator 1 2289
Protoss_Forge 1 2745
Protoss_Gateway 2 4969
Protoss_Photon_Cannon 3 9576
Protoss_Zealot 15 9686
Protoss_Cybernetics_Core 1 6631
Protoss_Citadel_of_Adun 1 7625
Protoss_Ground_Weapons_1 1 6941
Protoss_Templar_Archives 1 10217
10217
