Protoss_Forge 2 4090
Protoss_Nexus 1 4641
Protoss_Gateway 3 10500
Protoss_Photon_Cannon 3 10656
Protoss_Assimilator 2 7892
Protoss_Zealot 5 9643
Protoss_Cybernetics_Core 1 6383
Protoss_Stargate 1 7716
Protoss_Dragoon 1 7676
Protoss_Corsair 3 10233
Protoss_Citadel_of_Adun 1 9287
Protoss_Templar_Archives 1 10277
10656
