Protoss_Gateway 3 10627
Protoss_Assimilator 1 2973
Protoss_Zealot 3 8223
Protoss_Cybernetics_Core 1 4283
Protoss_Stargate 1 5936
Protoss_Dragoon 2 8253
Protoss_Scout 1 7570
Protoss_Forge 1 7420
Protoss_Photon_Cannon 2 9926
Protoss_Nexus 1 11119
Protoss_Citadel_of_Adun 1 10579
11119
