Protoss_Gateway 1 2922
Protoss_Assimilator 1 3165
Protoss_Zealot 4 8168
Protoss_Cybernetics_Core 1 4844
Protoss_Dragoon 1 5790
Protoss_Robotics_Facility 1 7292
Protoss_Forge 1 7355
Protoss_Shuttle 1 8292
Protoss_Robotics_Support_Bay 1 7932
Protoss_Reaver 1 10287
10287
