Protoss_Gateway 1 2587
Protoss_Assimilator 2 9857
Protoss_Zealot 3 4497
Protoss_Cybernetics_Core 1 5264
Protoss_Dragoon 1 6103
Protoss_Forge 1 6530
Protoss_Photon_Cannon 3 9336
Protoss_Nexus 1 9437
9857
