Protoss_Gateway 4 10094
Protoss_Forge 1 3213
Protoss_Zealot 11 10403
Protoss_Photon_Cannon 3 8030
Protoss_Nexus 1 6876
Protoss_Assimilator 2 9436
Protoss_Cybernetics_Core 1 7285
Protoss_Dragoon 1 8130
Protoss_Citadel_of_Adun 1 9232
10403
