Protoss_Forge 1 3127
Protoss_Nexus 1 5219
Protoss_Photon_Cannon 5 10707
Protoss_Gateway 1 4923
Protoss_Assimilator 2 6470
Protoss_Zealot 6 10072
Protoss_Cybernetics_Core 2 9777
Protoss_Stargate 1 7893
Protoss_Dragoon 1 7822
Protoss_Citadel_of_Adun 1 8336
10707
