Protoss_Gateway 4 9650
Protoss_Zealot 6 10283
Protoss_Assimilator 1 3845
Protoss_Cybernetics_Core 1 4944
Protoss_Stargate 1 6260
Protoss_Corsair 1 7028
Protoss_Dragoon 1 7253
Protoss_Robotics_Facility 1 7972
Protoss_Citadel_of_Adun 1 8465
Protoss_Observatory 1 8533
Protoss_Templar_Archives 1 9497
Protoss_Shuttle 1 10532
Protoss_Observer 1 10455
Protoss_Dark_Templar 1 10698
10698
