Protoss_Nexus 1 4540
Protoss_Forge 1 3668
Protoss_Photon_Cannon 8 10550
Protoss_Gateway 4 8826
Protoss_Assimilator 2 7160
Protoss_Cybernetics_Core 1 7230
Protoss_Citadel_of_Adun 1 8215
Protoss_Dragoon 1 8124
Protoss_Zealot 1 8834
Protoss_Templar_Archives 1 9318
Protoss_High_Templar 4 10202
10550
