Protoss_Nexus 1 4475
Protoss_Forge 1 3742
Protoss_Gateway 5 7909
Protoss_Photon_Cannon 1 4975
Protoss_Assimilator 2 8983
Protoss_Zealot 14 9920
Protoss_Cybernetics_Core 1 6217
Protoss_Citadel_of_Adun 1 7203
Protoss_Templar_Archives 1 10142
Protoss_Ground_Weapons_1 1 9697
10142
