Protoss_Forge 1 2608
Protoss_Photon_Cannon 4 10208
Protoss_Gateway 4 10817
Protoss_Nexus 1 6399
Protoss_Zealot 7 10390
Protoss_Assimilator 2 8315
Protoss_Cybernetics_Core 1 6757
Protoss_Citadel_of_Adun 1 7860
Protoss_Dragoon 1 8382
Protoss_Templar_Archives 1 9824
10817
