Protoss_Gateway 1 2507
Protoss_Zealot 11 9502
Protoss_Forge 1 4188
Protoss_Photon_Cannon 3 9806
Protoss_Nexus 1 8297
Protoss_Assimilator 2 9298
Protoss_Cybernetics_Core 1 8865
Protoss_Citadel_of_Adun 1 10537
Protoss_Dragoon 1 10442
10537
