Protoss_Forge 1 2589
Protoss_Nexus 1 5150
Protoss_Photon_Cannon 3 10540
Protoss_Gateway 4 9327
Protoss_Assimilator 2 8437
Protoss_Zealot 13 10274
Protoss_Cybernetics_Core 1 6742
Protoss_Citadel_of_Adun 1 7798
Protoss_Dragoon 1 7698
Protoss_Templar_Archives 1 9995
10540
