Protoss_Forge 1 2488
Protoss_Photon_Cannon 6 9614
Protoss_Nexus 1 5970
Protoss_Gateway 4 9302
Protoss_Assimilator 1 6088
Protoss_Cybernetics_Core 1 7174
Protoss_Zealot 13 10594
Protoss_Citadel_of_Adun 1 8308
Protoss_Dragoon 1 8552
Protoss_Templar_Archives 1 10646
10646
