Protoss_Gateway 2 7949
Protoss_Assimilator 1 3105
Protoss_Zealot 8 10283
Protoss_Cybernetics_Core 1 4709
Protoss_Stargate 1 6153
Protoss_Dragoon 1 6263
Protoss_Citadel_of_Adun 1 7127
Protoss_Corsair 1 6848
Protoss_Templar_Archives 1 8675
Protoss_Nexus 1 10502
Protoss_Dark_Templar 1 9823
Protoss_Forge 1 10220
10502
