Protoss_Forge 1 2631
Protoss_Photon_Cannon 3 5521
Protoss_Nexus 1 5870
Protoss_Gateway 3 10231
Protoss_Assimilator 2 7745
Protoss_Zealot 5 10413
Protoss_Cybernetics_Core 1 7246
Protoss_Stargate 1 8485
Protoss_Citadel_of_Adun 1 9248
Protoss_Corsair 2 10213
Protoss_Templar_Archives 1 10371
10413
