Protoss_Assimilator 1 2328
Protoss_Forge 1 2824
Protoss_Photon_Cannon 3 9072
Protoss_Gateway 3 5350
Protoss_Zealot 13 9184
Protoss_Ground_Weapons_1 1 7021
Protoss_Nexus 2 10045
10045
