Protoss_Forge 1 2987
Protoss_Photon_Cannon 4 9234
Protoss_Nexus 1 5491
Protoss_Gateway 1 5541
Protoss_Assimilator 2 6979
Protoss_Cybernetics_Core 1 6618
Protoss_Zealot 4 9612
Protoss_Dragoon 1 7446
Protoss_Stargate 1 7965
Protoss_Robotics_Facility 1 8619
Protoss_Corsair 2 9876
Protoss_Citadel_of_Adun 1 9579
Protoss_Shuttle 1 9677
Protoss_Robotics_Support_Bay 1 9470
Protoss_Templar_Archives 1 10628
10628
