Protoss_Forge 1 2870
Protoss_Nexus 1 5167
Protoss_Photon_Cannon 2 5071
Protoss_Gateway 5 10416
Protoss_Assimilator 1 5364
Protoss_Cybernetics_Core 1 6667
Protoss_Zealot 12 10590
Protoss_Citadel_of_Adun 1 7901
Protoss_Dragoon 1 7800
Protoss_Templar_Archives 1 10733
10733
