Protoss_Gateway 1 2673
Protoss_Zealot 5 8112
Protoss_Forge 1 3676
Protoss_Photon_Cannon 5 10731
Protoss_Nexus 1 7072
Protoss_Assimilator 2 7670
Protoss_Cybernetics_Core 1 7148
Protoss_Stargate 1 8818
Protoss_Robotics_Facility 1 9617
Protoss_Corsair 2 10342
Protoss_Dragoon 1 9732
Protoss_Robotics_Support_Bay 1 10303
10731
