Protoss_Forge 1 3282
Protoss_Nexus 1 5115
Protoss_Photon_Cannon 4 10695
Protoss_Gateway 3 10061
Protoss_Assimilator 2 7907
Protoss_Zealot 2 10044
Protoss_Cybernetics_Core 1 7257
Protoss_Dragoon 1 8120
Protoss_Stargate 1 8619
Protoss_Citadel_of_Adun 1 8746
Protoss_Corsair 1 9302
Protoss_Templar_Archives 1 9888
10695
