Protoss_Forge 1 2782
Protoss_Nexus 1 5040
Protoss_Gateway 1 5109
Protoss_Photon_Cannon 2 5601
Protoss_Assimilator 1 5936
Protoss_Zealot 3 9858
Protoss_Cybernetics_Core 1 6672
9858
