Protoss_Forge 1 2516
Protoss_Photon_Cannon 4 10366
Protoss_Nexus 1 5873
Protoss_Gateway 1 5335
Protoss_Assimilator 2 7444
Protoss_Zealot 2 9302
Protoss_Cybernetics_Core 1 6603
Protoss_Stargate 1 8035
Protoss_Dragoon 1 8258
Protoss_Robotics_Facility 1 9246
Protoss_Corsair 1 8754
Protoss_Shuttle 1 10231
Protoss_Robotics_Support_Bay 1 9870
10366
