Protoss_Nexus 1 4545
Protoss_Forge 1 3698
Protoss_Photon_Cannon 2 4646
Protoss_Gateway 1 5283
Protoss_Zealot 3 8242
Protoss_Assimilator 2 7295
Protoss_Cybernetics_Core 1 7298
8242
