Protoss_Gateway 2 3360
Protoss_Zealot 13 10238
Protoss_Assimilator 1 6160
Protoss_Cybernetics_Core 1 7327
Protoss_Forge 1 8054
Protoss_Stargate 1 8801
Protoss_Citadel_of_Adun 1 9101
Protoss_Corsair 2 10493
10493
