Protoss_Forge 1 2946
Protoss_Nexus 1 4947
Protoss_Photon_Cannon 6 10725
Protoss_Gateway 2 9055
Protoss_Assimilator 2 8573
Protoss_Cybernetics_Core 1 6192
Protoss_Zealot 3 9328
Protoss_Stargate 1 7489
Protoss_Citadel_of_Adun 1 7802
Protoss_Corsair 3 9824
Protoss_Templar_Archives 1 8957
Protoss_Dark_Templar 2 10254
10725
