Protoss_Forge 1 3064
Protoss_Nexus 1 5219
Protoss_Photon_Cannon 3 9261
Protoss_Gateway 1 4873
Protoss_Zealot 5 10158
Protoss_Assimilator 1 5966
Protoss_Cybernetics_Core 1 7299
Protoss_Stargate 1 9100
Protoss_Corsair 1 9788
Protoss_Citadel_of_Adun 1 10449
10449
