Protoss_Gateway 4 9208
Protoss_Zealot 15 10578
Protoss_Forge 1 5591
Protoss_Photon_Cannon 1 6968
Protoss_Nexus 1 8885
Protoss_Assimilator 1 8205
Protoss_Cybernetics_Core 1 9574
Protoss_Citadel_of_Adun 1 10595
10595
