Protoss_Gateway 2 3349
Protoss_Zealot 14 9823
Protoss_Assimilator 1 6441
Protoss_Forge 1 7057
Protoss_Photon_Cannon 1 9115
Protoss_Cybernetics_Core 1 9679
Protoss_Citadel_of_Adun 1 10752
10752
