Protoss_Nexus 1 4571
Protoss_Gateway 3 9929
Protoss_Assimilator 2 7835
Protoss_Forge 1 4683
Protoss_Zealot 4 8146
Protoss_Photon_Cannon 2 7718
Protoss_Cybernetics_Core 1 6351
Protoss_Citadel_of_Adun 1 7598
Protoss_Templar_Archives 1 8671
Protoss_Dark_Templar 2 9570
Protoss_High_Templar 2 10322
10322
