Protoss_Forge 1 3096
Protoss_Nexus 1 5356
Protoss_Photon_Cannon 4 10423
Protoss_Gateway 3 10039
Protoss_Zealot 5 8828
Protoss_Assimilator 2 8563
Protoss_Cybernetics_Core 1 7577
Protoss_Citadel_of_Adun 1 8727
Protoss_Templar_Archives 1 9789
Protoss_Dark_Templar 1 10686
10686
