Protoss_Forge 1 2883
Protoss_Photon_Cannon 2 4730
Protoss_Nexus 1 5521
Protoss_Gateway 6 9074
Protoss_Assimilator 2 9979
Protoss_Cybernetics_Core 1 6787
Protoss_Zealot 14 10438
Protoss_Dragoon 1 7946
Protoss_Citadel_of_Adun 1 8128
10438
