Protoss_Forge 1 2659
Protoss_Photon_Cannon 2 4446
Protoss_Nexus 1 5827
Protoss_Gateway 2 8921
Protoss_Assimilator 2 7536
Protoss_Cybernetics_Core 1 6313
Protoss_Zealot 3 7996
Protoss_Stargate 1 7537
Protoss_Citadel_of_Adun 1 8057
Protoss_Corsair 3 10408
Protoss_Templar_Archives 1 9079
Protoss_Robotics_Facility 1 9594
Protoss_Dark_Templar 2 10044
Protoss_Shuttle 1 10623
10623
