Protoss_Forge 1 3327
Protoss_Nexus 1 5023
Protoss_Photon_Cannon 2 9062
Protoss_Gateway 4 9565
Protoss_Assimilator 2 9954
Protoss_Zealot 16 10458
Protoss_Cybernetics_Core 1 7395
Protoss_Dragoon 1 8522
Protoss_Citadel_of_Adun 1 8731
Protoss_Templar_Archives 1 9916
10458
