Protoss_Gateway 3 10401
Protoss_Assimilator 1 3015
Protoss_Zealot 9 10428
Protoss_Cybernetics_Core 1 4634
Protoss_Stargate 1 6108
Protoss_Dragoon 1 6142
Protoss_Forge 1 6601
Protoss_Corsair 1 7118
Protoss_Photon_Cannon 2 9908
Protoss_Nexus 1 9753
Protoss_Citadel_of_Adun 1 9426
10428
