Protoss_Gateway 2 3231
Protoss_Zealot 10 9992
Protoss_Shield_Battery 1 4896
Protoss_Nexus 1 8253
Protoss_Forge 1 7546
Protoss_Assimilator 1 7854
Protoss_Photon_Cannon 2 9135
9992
