Protoss_Forge 1 2678
Protoss_Photon_Cannon 6 10451
Protoss_Nexus 1 5893
Protoss_Gateway 3 10071
Protoss_Assimilator 2 7776
Protoss_Zealot 3 7636
Protoss_Cybernetics_Core 1 6637
Protoss_Stargate 1 7881
Protoss_Citadel_of_Adun 1 8180
Protoss_Corsair 2 10112
Protoss_Templar_Archives 1 9555
Protoss_High_Templar 1 10570
Protoss_Dark_Templar 1 10614
10614
