Protoss_Forge 1 2536
Protoss_Photon_Cannon 4 10658
Protoss_Nexus 1 5793
Protoss_Gateway 2 9233
Protoss_Assimilator 2 7091
Protoss_Zealot 5 8861
Protoss_Cybernetics_Core 1 6735
Protoss_Stargate 1 7937
Protoss_Citadel_of_Adun 1 8370
Protoss_Corsair 2 9282
Protoss_Templar_Archives 1 9420
Protoss_Robotics_Facility 1 10489
Protoss_Dark_Templar 2 10274
10658
