Protoss_Nexus 1 4631
Protoss_Forge 1 3828
Protoss_Gateway 2 8639
Protoss_Assimilator 2 6701
Protoss_Photon_Cannon 2 10367
Protoss_Zealot 3 7155
Protoss_Cybernetics_Core 1 6639
Protoss_Stargate 1 7821
Protoss_Dragoon 1 7907
Protoss_Citadel_of_Adun 1 8089
Protoss_Corsair 3 9958
Protoss_Templar_Archives 1 9130
Protoss_Robotics_Facility 1 9515
Protoss_Dark_Templar 2 10214
10367
