Protoss_Forge 1 2793
Protoss_Photon_Cannon 12 10082
Protoss_Nexus 1 7137
Protoss_Gateway 1 6523
Protoss_Zealot 2 9586
Protoss_Assimilator 2 8759
Protoss_Cybernetics_Core 1 9239
Protoss_Stargate 1 11023
11023
