Protoss_Gateway 1 2903
Protoss_Zealot 11 10280
Protoss_Nexus 1 6528
Protoss_Assimilator 2 10532
Protoss_Forge 1 6498
Protoss_Cybernetics_Core 1 7242
Protoss_Photon_Cannon 3 9441
Protoss_Stargate 1 8848
Protoss_Citadel_of_Adun 1 9740
Protoss_Corsair 1 9550
10532
