Protoss_Nexus 1 4860
Protoss_Forge 1 4090
Protoss_Photon_Cannon 6 10593
Protoss_Gateway 1 5586
Protoss_Assimilator 2 7115
Protoss_Zealot 2 6885
Protoss_Cybernetics_Core 1 6839
Protoss_Stargate 1 8082
Protoss_Robotics_Facility 2 9947
Protoss_Corsair 1 8913
Protoss_Shuttle 1 10417
Protoss_Robotics_Support_Bay 1 10149
10593
