Protoss_Gateway 2 9296
Protoss_Zealot 8 9593
Protoss_Assimilator 1 5575
Protoss_Cybernetics_Core 1 6184
Protoss_Stargate 1 7673
Protoss_Citadel_of_Adun 1 8503
Protoss_Corsair 1 8363
Protoss_Forge 1 9217
Protoss_Templar_Archives 1 9691
Protoss_Photon_Cannon 1 10295
Protoss_Dark_Templar 2 10598
10598
