Protoss_Gateway 2 10551
Protoss_Zealot 9 9688
Protoss_Assimilator 1 3686
Protoss_Forge 1 5001
Protoss_Cybernetics_Core 1 6929
Protoss_Citadel_of_Adun 1 8190
Protoss_Photon_Cannon 5 9962
Protoss_Templar_Archives 1 9334
Protoss_Ground_Weapons_1 1 9083
Protoss_Robotics_Facility 1 11067
Protoss_Dark_Templar 1 10722
11067
