Protoss_Gateway 5 9788
Protoss_Nexus 1 4793
Protoss_Forge 1 4060
Protoss_Photon_Cannon 2 9987
Protoss_Assimilator 1 5963
Protoss_Cybernetics_Core 1 6632
Protoss_Zealot 8 9748
Protoss_Stargate 1 7958
Protoss_Dragoon 1 8578
Protoss_Corsair 1 8773
Protoss_Citadel_of_Adun 1 9463
9987
