Protoss_Nexus 1 4949
Protoss_Forge 1 4449
Protoss_Photon_Cannon 8 10451
Protoss_Gateway 1 5931
Protoss_Assimilator 2 8008
Protoss_Cybernetics_Core 1 7146
Protoss_Zealot 2 9102
Protoss_Stargate 1 8579
Protoss_Dragoon 2 9522
Protoss_Citadel_of_Adun 1 9024
Protoss_Corsair 2 10024
Protoss_Templar_Archives 1 10138
10451
