Protoss_Forge 1 2734
Protoss_Nexus 1 5036
Protoss_Photon_Cannon 2 4643
Protoss_Gateway 3 8840
Protoss_Assimilator 2 6949
Protoss_Zealot 6 9522
Protoss_Cybernetics_Core 1 6769
Protoss_Dragoon 1 7660
Protoss_Citadel_of_Adun 1 7989
Protoss_Templar_Archives 1 9611
Protoss_Robotics_Facility 1 10528
Protoss_Dark_Templar 2 10450
Protoss_High_Templar 2 10516
10528
