Protoss_Gateway 2 3287
Protoss_Zealot 8 5798
Protoss_Assimilator 1 5428
Protoss_Cybernetics_Core 1 6513
Protoss_Stargate 1 7692
Protoss_Corsair 1 8374
Protoss_Nexus 1 9945
Protoss_Forge 1 9090
Protoss_Citadel_of_Adun 1 10092
Protoss_Photon_Cannon 1 10682
10682
