Protoss_Forge 1 2693
Protoss_Nexus 1 5052
Protoss_Photon_Cannon 2 4627
Protoss_Gateway 1 5097
Protoss_Assimilator 2 8362
Protoss_Zealot 3 8802
Protoss_Cybernetics_Core 1 6806
Protoss_Stargate 1 8022
Protoss_Robotics_Facility 1 8599
Protoss_Corsair 1 8744
Protoss_Shuttle 1 9597
Protoss_Robotics_Support_Bay 1 9287
Protoss_Reaver 1 10662
Protoss_Citadel_of_Adun 1 10853
10853
