Protoss_Forge 3 4489
Protoss_Nexus 1 4931
Protoss_Gateway 3 9910
Protoss_Photon_Cannon 2 10744
Protoss_Assimilator 2 7439
Protoss_Zealot 6 10088
Protoss_Cybernetics_Core 1 7325
Protoss_Stargate 1 8506
Protoss_Dragoon 1 8306
Protoss_Citadel_of_Adun 1 8674
Protoss_Corsair 1 9186
Protoss_Templar_Archives 1 10039
10744
