Protoss_Nexus 1 4649
Protoss_Gateway 5 10855
Protoss_Forge 1 4558
Protoss_Assimilator 2 7159
Protoss_Zealot 6 10342
Protoss_Photon_Cannon 1 5478
Protoss_Cybernetics_Core 1 6707
Protoss_Stargate 1 7872
Protoss_Citadel_of_Adun 1 8078
Protoss_Corsair 3 10172
Protoss_Templar_Archives 1 9127
Protoss_Dark_Templar 1 10468
10855
