Protoss_Gateway 3 10185
Protoss_Assimilator 1 2780
Protoss_Zealot 9 10256
Protoss_Cybernetics_Core 1 4305
Protoss_Stargate 1 5768
Protoss_Corsair 2 7070
Protoss_Citadel_of_Adun 1 7821
Protoss_Templar_Archives 1 8969
Protoss_Forge 1 9330
10256
