Protoss_Forge 1 2810
Protoss_Photon_Cannon 2 5357
Protoss_Nexus 2 11681
Protoss_Gateway 2 8294
Protoss_Assimilator 2 6684
Protoss_Zealot 2 6966
Protoss_Cybernetics_Core 1 6689
Protoss_Stargate 1 7836
Protoss_Citadel_of_Adun 1 7965
Protoss_Corsair 4 10431
Protoss_Templar_Archives 1 8961
Protoss_Dark_Templar 2 9994
11681
