Protoss_Forge 1 2791
Protoss_Nexus 1 5015
Protoss_Photon_Cannon 6 9564
Protoss_Gateway 1 5291
Protoss_Assimilator 2 6912
Protoss_Cybernetics_Core 1 6754
Protoss_Zealot 4 9352
Protoss_Stargate 1 8056
Protoss_Robotics_Facility 1 8593
Protoss_Dragoon 1 8652
Protoss_Corsair 2 9636
Protoss_Shuttle 1 10389
Protoss_Robotics_Support_Bay 1 10005
10389
