Protoss_Forge 1 2822
Protoss_Photon_Cannon 3 9899
Protoss_Nexus 1 5545
Protoss_Gateway 5 10831
Protoss_Assimilator 2 6680
Protoss_Cybernetics_Core 1 6561
Protoss_Zealot 3 9996
Protoss_Stargate 1 7696
Protoss_Citadel_of_Adun 1 7717
Protoss_Dragoon 1 7758
Protoss_Corsair 1 8394
Protoss_Templar_Archives 1 9053
Protoss_Robotics_Facility 1 9960
Protoss_High_Templar 3 10734
10831
