Protoss_Forge 1 3064
Protoss_Nexus 1 5284
Protoss_Gateway 2 9681
Protoss_Photon_Cannon 4 10462
Protoss_Assimilator 2 8140
Protoss_Zealot 3 8676
Protoss_Cybernetics_Core 1 7247
Protoss_Stargate 1 8420
Protoss_Citadel_of_Adun 1 8719
Protoss_Corsair 2 9916
Protoss_Templar_Archives 1 9735
Protoss_Dark_Templar 2 10636
10636
