Protoss_Forge 1 2442
Protoss_Nexus 1 5101
Protoss_Gateway 3 9546
Protoss_Zealot 11 10314
Protoss_Photon_Cannon 4 7746
Protoss_Assimilator 2 8863
Protoss_Cybernetics_Core 1 8008
Protoss_Citadel_of_Adun 1 9200
Protoss_Templar_Archives 1 10656
10656
