Protoss_Forge 1 2809
Protoss_Nexus 1 5017
Protoss_Photon_Cannon 6 10634
Protoss_Gateway 1 5354
Protoss_Zealot 2 9074
Protoss_Assimilator 2 8592
Protoss_Cybernetics_Core 1 8227
Protoss_Stargate 1 9473
Protoss_Robotics_Facility 1 10245
Protoss_Corsair 1 10170
10634
