Protoss_Gateway 3 10642
Protoss_Zealot 10 6902
Protoss_Nexus 1 8717
Protoss_Forge 1 7771
Protoss_Photon_Cannon 3 10430
Protoss_Cybernetics_Core 1 9811
Protoss_Assimilator 1 9628
10642
