Protoss_Forge 1 2894
Protoss_Photon_Cannon 5 10573
Protoss_Nexus 1 6273
Protoss_Gateway 4 10749
Protoss_Assimilator 2 6910
Protoss_Cybernetics_Core 1 6842
Protoss_Zealot 3 8780
Protoss_Stargate 1 7999
Protoss_Dragoon 1 7704
Protoss_Citadel_of_Adun 1 8214
Protoss_Corsair 1 8690
Protoss_Templar_Archives 1 9261
Protoss_Dark_Templar 1 10090
Protoss_High_Templar 1 10730
10749
