Protoss_Forge 1 2790
Protoss_Nexus 1 5230
Protoss_Gateway 3 9687
Protoss_Photon_Cannon 2 5420
Protoss_Zealot 9 10428
Protoss_Assimilator 2 7465
Protoss_Cybernetics_Core 1 7489
Protoss_Stargate 1 8735
Protoss_Citadel_of_Adun 1 8695
Protoss_Corsair 1 9484
Protoss_Templar_Archives 1 10627
10627
