Protoss_Forge 1 2570
Protoss_Nexus 1 5304
Protoss_Gateway 1 4726
Protoss_Photon_Cannon 8 9361
Protoss_Assimilator 2 6791
Protoss_Zealot 3 8470
Protoss_Cybernetics_Core 1 6439
Protoss_Stargate 1 7603
Protoss_Robotics_Facility 1 8545
Protoss_Corsair 2 10208
Protoss_Robotics_Support_Bay 1 9192
Protoss_Shuttle 1 9741
Protoss_Reaver 1 10792
Protoss_Citadel_of_Adun 1 10669
10792
