Protoss_Forge 1 2890
Protoss_Photon_Cannon 6 10047
Protoss_Nexus 1 5706
Protoss_Gateway 3 10759
Protoss_Assimilator 2 7491
Protoss_Cybernetics_Core 1 6647
Protoss_Zealot 6 10386
Protoss_Stargate 2 8426
Protoss_Citadel_of_Adun 1 8770
Protoss_Corsair 2 10074
Protoss_Templar_Archives 1 9858
10759
