Protoss_Forge 1 2811
Protoss_Nexus 1 5190
Protoss_Photon_Cannon 2 4748
Protoss_Gateway 3 7264
Protoss_Zealot 11 9763
Protoss_Assimilator 2 9272
Protoss_Cybernetics_Core 1 8905
Protoss_Citadel_of_Adun 1 9944
Protoss_Robotics_Facility 1 10859
10859
