Protoss_Nexus 1 4665
Protoss_Forge 1 3874
Protoss_Photon_Cannon 7 10129
Protoss_Gateway 1 6369
Protoss_Assimilator 2 10476
Protoss_Cybernetics_Core 1 7883
Protoss_Zealot 4 9542
Protoss_Stargate 2 9171
Protoss_Corsair 4 10528
10528
