Protoss_Gateway 3 6329
Protoss_Assimilator 1 2962
Protoss_Zealot 19 10592
Protoss_Cybernetics_Core 1 4813
Protoss_Dragoon 1 5884
Protoss_Citadel_of_Adun 1 6628
Protoss_Templar_Archives 1 9887
Protoss_Forge 1 10374
10592
