Protoss_Gateway 3 9133
Protoss_Zealot 8 7620
Protoss_Assimilator 1 4209
Protoss_Cybernetics_Core 1 5701
Protoss_Stargate 1 7177
Protoss_Dragoon 9 10720
Protoss_Citadel_of_Adun 1 7793
Protoss_Corsair 1 7860
10720
