Protoss_Forge 1 2832
Protoss_Photon_Cannon 3 10457
Protoss_Nexus 1 5561
Protoss_Gateway 4 9811
Protoss_Assimilator 2 7157
Protoss_Cybernetics_Core 1 6604
Protoss_Zealot 2 7692
Protoss_Stargate 1 7842
Protoss_Citadel_of_Adun 1 8335
Protoss_Corsair 1 8534
Protoss_Templar_Archives 1 9345
Protoss_Dark_Templar 1 10196
Protoss_High_Templar 2 10360
10457
