Protoss_Forge 1 2682
Protoss_Photon_Cannon 3 8552
Protoss_Nexus 1 5503
Protoss_Gateway 3 10011
Protoss_Assimilator 2 6806
Protoss_Zealot 3 9248
Protoss_Cybernetics_Core 1 6731
Protoss_Stargate 1 8062
Protoss_Citadel_of_Adun 1 8369
Protoss_Corsair 1 8898
Protoss_Templar_Archives 1 9423
Protoss_Dark_Templar 1 10366
10366
