Protoss_Forge 1 2722
Protoss_Photon_Cannon 6 10687
Protoss_Nexus 1 6365
Protoss_Gateway 1 5819
Protoss_Zealot 5 9882
Protoss_Assimilator 2 7808
Protoss_Cybernetics_Core 1 8427
Protoss_Stargate 1 9603
Protoss_Robotics_Facility 1 10351
Protoss_Corsair 1 10364
10687
