Protoss_Forge 1 2982
Protoss_Nexus 1 5073
Protoss_Photon_Cannon 3 10636
Protoss_Gateway 5 10702
Protoss_Assimilator 2 8412
Protoss_Zealot 8 9544
Protoss_Cybernetics_Core 1 7187
Protoss_Citadel_of_Adun 1 8259
Protoss_Templar_Archives 1 10587
10702
