Protoss_Forge 1 3382
Protoss_Nexus 1 5007
Protoss_Photon_Cannon 4 9374
Protoss_Gateway 5 10400
Protoss_Assimilator 2 6963
Protoss_Cybernetics_Core 1 6528
Protoss_Zealot 3 8424
Protoss_Stargate 1 7676
Protoss_Citadel_of_Adun 1 8017
Protoss_Corsair 1 8384
Protoss_Templar_Archives 1 9071
Protoss_High_Templar 1 9928
Protoss_Dark_Templar 2 9960
10400
