Protoss_Nexus 2 11575
Protoss_Forge 1 3936
Protoss_Gateway 3 9296
Protoss_Assimilator 2 6482
Protoss_Photon_Cannon 2 8286
Protoss_Zealot 6 9662
Protoss_Cybernetics_Core 1 6299
Protoss_Stargate 1 7478
Protoss_Dragoon 1 7340
Protoss_Citadel_of_Adun 1 8085
Protoss_Corsair 1 8632
Protoss_Templar_Archives 1 9311
Protoss_Robotics_Facility 1 10547
Protoss_High_Templar 2 10308
Protoss_Dark_Templar 1 10414
11575
