Protoss_Forge 1 3363
Protoss_Photon_Cannon 2 9052
Protoss_Nexus 1 5769
Protoss_Gateway 4 10500
Protoss_Assimilator 2 8121
Protoss_Zealot 6 10408
Protoss_Cybernetics_Core 1 6867
Protoss_Stargate 1 8329
10500
