Protoss_Forge 2 4256
Protoss_Nexus 1 5031
Protoss_Gateway 3 8549
Protoss_Photon_Cannon 2 9900
Protoss_Assimilator 2 6812
Protoss_Zealot 3 7734
Protoss_Cybernetics_Core 1 6914
Protoss_Citadel_of_Adun 1 8094
9900
