Protoss_Forge 1 2818
Protoss_Photon_Cannon 2 3858
Protoss_Nexus 1 6285
Protoss_Gateway 2 9805
Protoss_Assimilator 2 8106
Protoss_Zealot 5 9760
Protoss_Cybernetics_Core 1 6873
Protoss_Stargate 1 8049
Protoss_Citadel_of_Adun 1 8575
9805
