Protoss_Forge 1 3054
Protoss_Photon_Cannon 2 4154
Protoss_Nexus 1 5787
Protoss_Gateway 6 8932
Protoss_Assimilator 2 7158
Protoss_Cybernetics_Core 1 6292
Protoss_Zealot 13 10502
Protoss_Dragoon 1 7178
Protoss_Citadel_of_Adun 1 7921
Protoss_Stargate 1 8569
Protoss_Templar_Archives 1 10154
10502
