Protoss_Nexus 1 4751
Protoss_Forge 1 4044
Protoss_Gateway 1 5315
Protoss_Photon_Cannon 2 9685
Protoss_Assimilator 2 6582
Protoss_Zealot 5 10052
Protoss_Cybernetics_Core 1 7131
Protoss_Stargate 1 8287
Protoss_Citadel_of_Adun 1 8596
Protoss_Dragoon 1 9084
Protoss_Corsair 1 8972
Protoss_Templar_Archives 1 9757
Protoss_Dark_Templar 1 10654
10654
