Protoss_Gateway 3 10573
Protoss_Assimilator 1 3182
Protoss_Cybernetics_Core 1 3851
Protoss_Zealot 5 9322
Protoss_Stargate 1 5175
Protoss_Dragoon 1 5192
Protoss_Corsair 2 7668
Protoss_Forge 1 6219
Protoss_Citadel_of_Adun 1 7797
Protoss_Robotics_Facility 1 9848
10573
