Protoss_Forge 1 2783
Protoss_Photon_Cannon 3 9689
Protoss_Nexus 1 5821
Protoss_Gateway 4 10824
Protoss_Assimilator 2 6703
Protoss_Cybernetics_Core 1 6506
Protoss_Stargate 1 7792
Protoss_Zealot 2 8272
Protoss_Citadel_of_Adun 1 8166
Protoss_Corsair 3 9718
Protoss_Templar_Archives 1 9162
Protoss_Dark_Templar 2 10076
10824
