Protoss_Forge 1 3036
Protoss_Photon_Cannon 4 10460
Protoss_Nexus 2 10932
Protoss_Gateway 1 5956
Protoss_Assimilator 2 7752
Protoss_Zealot 3 9234
Protoss_Cybernetics_Core 1 7399
Protoss_Stargate 1 8568
Protoss_Robotics_Facility 1 9483
Protoss_Corsair 3 10586
Protoss_Robotics_Support_Bay 1 10127
10932
