Protoss_Forge 1 2958
Protoss_Photon_Cannon 2 4466
Protoss_Nexus 1 5827
Protoss_Gateway 1 5208
Protoss_Assimilator 2 6711
Protoss_Cybernetics_Core 1 6248
Protoss_Zealot 3 9484
Protoss_Stargate 1 7526
Protoss_Corsair 1 8212
Protoss_Citadel_of_Adun 1 8575
9484
