Protoss_Gateway 3 10468
Protoss_Zealot 9 8258
Protoss_Assimilator 1 4202
Protoss_Forge 1 4685
Protoss_Photon_Cannon 1 6177
Protoss_Cybernetics_Core 1 7714
Protoss_Dragoon 5 10633
Protoss_Citadel_of_Adun 1 9489
Protoss_Ground_Weapons_1 1 9136
10633
