Protoss_Gateway 2 7138
Protoss_Assimilator 1 3030
Protoss_Zealot 8 8476
Protoss_Cybernetics_Core 1 4869
Protoss_Dragoon 1 5878
Protoss_Citadel_of_Adun 1 6470
Protoss_Templar_Archives 1 8069
Protoss_Forge 1 8909
Protoss_High_Templar 3 10142
Protoss_Photon_Cannon 1 9963
Protoss_Dark_Templar 1 10156
Protoss_Archon 1 9854
Protoss_Robotics_Facility 1 11051
11051
