Protoss_Nexus 1 4900
Protoss_Forge 1 4230
Protoss_Gateway 3 9618
Protoss_Photon_Cannon 3 8375
Protoss_Assimilator 2 6403
Protoss_Cybernetics_Core 1 7302
Protoss_Stargate 1 8471
Protoss_Citadel_of_Adun 1 8362
Protoss_Corsair 2 9756
Protoss_Templar_Archives 1 9533
Protoss_Dark_Templar 1 10510
Protoss_High_Templar 1 10528
Protoss_Dragoon 1 10542
10542
