Protoss_Forge 1 2768
Protoss_Photon_Cannon 2 3724
Protoss_Nexus 1 6118
Protoss_Gateway 4 9059
Protoss_Assimilator 2 9378
Protoss_Cybernetics_Core 1 6599
Protoss_Zealot 10 10180
Protoss_Citadel_of_Adun 1 7761
Protoss_Templar_Archives 1 10794
10794
