Protoss_Forge 1 2889
Protoss_Photon_Cannon 2 4330
Protoss_Nexus 1 6296
Protoss_Gateway 1 5545
Protoss_Assimilator 2 7650
Protoss_Cybernetics_Core 1 6713
Protoss_Zealot 3 8183
Protoss_Stargate 1 7908
Protoss_Robotics_Facility 1 8946
Protoss_Corsair 4 10512
Protoss_Robotics_Support_Bay 1 9594
Protoss_Shuttle 1 10227
Protoss_Citadel_of_Adun 1 10734
10734
