Protoss_Forge 1 2954
Protoss_Nexus 1 5009
Protoss_Photon_Cannon 3 7771
Protoss_Gateway 3 10648
Protoss_Zealot 3 7156
Protoss_Assimilator 2 8453
Protoss_Cybernetics_Core 1 8190
Protoss_Citadel_of_Adun 1 9539
Protoss_Dragoon 2 10736
Protoss_Templar_Archives 1 10839
10839
