Protoss_Forge 1 2490
Protoss_Photon_Cannon 4 10388
Protoss_Nexus 1 5806
Protoss_Gateway 1 5436
Protoss_Assimilator 2 8931
Protoss_Zealot 4 9312
Protoss_Cybernetics_Core 1 8301
Protoss_Stargate 1 9616
Protoss_Citadel_of_Adun 1 9921
Protoss_Corsair 1 10344
10388
