Protoss_Forge 1 3183
Protoss_Photon_Cannon 3 10229
Protoss_Nexus 1 5411
Protoss_Gateway 1 4809
Protoss_Assimilator 2 6617
Protoss_Cybernetics_Core 1 6212
Protoss_Zealot 4 9304
Protoss_Stargate 1 7682
Protoss_Dragoon 1 8100
Protoss_Corsair 3 9886
Protoss_Robotics_Facility 1 10011
10229
