Protoss_Forge 1 2790
Protoss_Photon_Cannon 3 6087
Protoss_Gateway 2 6357
Protoss_Nexus 1 6449
Protoss_Assimilator 3 7575
Protoss_Cybernetics_Core 1 7397
Protoss_Zealot 2 9326
Protoss_Stargate 1 8568
Protoss_Dragoon 1 8408
Protoss_Robotics_Facility 1 9699
Protoss_Corsair 3 10560
Protoss_Shuttle 1 10699
10699
