Protoss_Forge 1 2969
Protoss_Nexus 1 5067
Protoss_Photon_Cannon 2 4632
Protoss_Gateway 4 10069
Protoss_Assimilator 2 9877
Protoss_Zealot 9 10576
Protoss_Cybernetics_Core 1 7821
Protoss_Dragoon 1 8688
Protoss_Citadel_of_Adun 1 8938
Protoss_Templar_Archives 1 10419
10576
