Protoss_Forge 1 2840
Protoss_Photon_Cannon 2 6889
Protoss_Nexus 1 5685
Protoss_Gateway 2 9509
Protoss_Assimilator 2 7010
Protoss_Zealot 4 8926
Protoss_Cybernetics_Core 1 6609
Protoss_Stargate 1 7911
Protoss_Dragoon 1 7640
Protoss_Citadel_of_Adun 1 8371
Protoss_Corsair 3 9882
Protoss_Templar_Archives 1 9357
Protoss_Dark_Templar 2 10428
Protoss_Robotics_Facility 1 10764
10764
