Protoss_Forge 1 2872
Protoss_Photon_Cannon 2 3910
Protoss_Nexus 1 5721
Protoss_Gateway 6 9295
Protoss_Assimilator 2 7471
Protoss_Cybernetics_Core 1 6533
Protoss_Zealot 7 10006
Protoss_Dragoon 1 7472
Protoss_Citadel_of_Adun 1 8001
Protoss_Templar_Archives 1 10128
10128
