Protoss_Forge 3 10151
Protoss_Photon_Cannon 4 6568
Protoss_Nexus 1 6206
Protoss_Gateway 1 5905
Protoss_Assimilator 2 8114
Protoss_Cybernetics_Core 1 7461
Protoss_Zealot 4 10070
Protoss_Stargate 1 8984
Protoss_Citadel_of_Adun 2 10542
Protoss_Dragoon 1 9444
Protoss_Corsair 1 10098
10542
