Protoss_Forge 1 2854
Protoss_Photon_Cannon 2 4972
Protoss_Nexus 1 5617
Protoss_Gateway 1 5646
Protoss_Assimilator 2 6749
Protoss_Zealot 4 8622
Protoss_Cybernetics_Core 1 6725
Protoss_Stargate 1 8000
Protoss_Robotics_Facility 1 8483
Protoss_Corsair 3 10242
Protoss_Shuttle 1 9507
Protoss_Robotics_Support_Bay 1 9128
Protoss_Reaver 1 10558
10558
