Protoss_Forge 1 3020
Protoss_Photon_Cannon 3 8770
Protoss_Nexus 1 5549
Protoss_Gateway 1 5254
Protoss_Assimilator 2 6479
Protoss_Cybernetics_Core 1 6297
Protoss_Zealot 1 6650
Protoss_Stargate 1 7453
Protoss_Robotics_Facility 1 8165
Protoss_Corsair 4 10496
Protoss_Shuttle 1 9241
Protoss_Robotics_Support_Bay 1 8837
Protoss_Reaver 1 10440
10496
