Protoss_Nexus 2 11495
Protoss_Gateway 2 8005
Protoss_Forge 1 4357
Protoss_Assimilator 2 6299
Protoss_Photon_Cannon 5 10586
Protoss_Cybernetics_Core 1 5587
Protoss_Zealot 1 5822
Protoss_Stargate 1 7008
Protoss_Dragoon 1 6890
Protoss_Citadel_of_Adun 1 7544
Protoss_Corsair 3 9196
Protoss_Templar_Archives 1 8657
Protoss_Dark_Templar 2 9522
Protoss_High_Templar 2 10274
11495
