Protoss_Forge 1 2816
Protoss_Photon_Cannon 2 3845
Protoss_Nexus 1 5746
Protoss_Gateway 1 5329
Protoss_Assimilator 1 5306
Protoss_Cybernetics_Core 1 6369
Protoss_Zealot 3 7466
Protoss_Stargate 1 7903
7903
