Protoss_Gateway 2 9118
Protoss_Zealot 6 9198
Protoss_Assimilator 1 4039
Protoss_Cybernetics_Core 1 4877
Protoss_Stargate 1 7008
Protoss_Dragoon 1 6920
Protoss_Citadel_of_Adun 1 7732
Protoss_Corsair 1 7764
Protoss_Forge 1 8104
Protoss_Templar_Archives 1 8802
Protoss_Dark_Templar 2 10352
10352
