Protoss_Forge 1 3130
Protoss_Photon_Cannon 4 10642
Protoss_Nexus 1 5294
Protoss_Gateway 3 9977
Protoss_Assimilator 2 7301
Protoss_Zealot 5 10462
Protoss_Cybernetics_Core 1 6861
Protoss_Stargate 1 8094
Protoss_Citadel_of_Adun 1 8863
Protoss_Corsair 1 8846
Protoss_Templar_Archives 1 9901
10642
