Protoss_Forge 1 3349
Protoss_Nexus 1 4995
Protoss_Photon_Cannon 2 4650
Protoss_Gateway 4 10756
Protoss_Assimilator 2 7955
Protoss_Zealot 4 10216
Protoss_Cybernetics_Core 1 7097
Protoss_Stargate 1 8307
Protoss_Dragoon 1 8502
Protoss_Citadel_of_Adun 1 9175
Protoss_Corsair 2 9592
Protoss_Templar_Archives 1 10253
10756
