Protoss_Forge 1 2742
Protoss_Nexus 1 4859
Protoss_Photon_Cannon 4 9018
Protoss_Gateway 2 10729
Protoss_Assimilator 2 7488
Protoss_Cybernetics_Core 1 6659
Protoss_Zealot 3 10274
Protoss_Stargate 1 7842
Protoss_Robotics_Facility 1 8609
Protoss_Dragoon 2 9358
Protoss_Corsair 1 8558
Protoss_Citadel_of_Adun 1 9313
Protoss_Robotics_Support_Bay 1 9317
Protoss_Reaver 1 10456
Protoss_Templar_Archives 1 10446
10729
