Protoss_Forge 1 2767
Protoss_Photon_Cannon 2 9840
Protoss_Nexus 1 5277
Protoss_Gateway 2 8950
Protoss_Assimilator 2 6752
Protoss_Zealot 6 8938
Protoss_Cybernetics_Core 1 6493
Protoss_Stargate 1 7750
Protoss_Citadel_of_Adun 1 8311
Protoss_Corsair 3 9842
Protoss_Templar_Archives 1 9507
9842
