Protoss_Forge 1 2808
Protoss_Photon_Cannon 4 10745
Protoss_Nexus 1 5620
Protoss_Gateway 3 10524
Protoss_Assimilator 2 7979
Protoss_Zealot 6 9974
Protoss_Cybernetics_Core 1 6610
Protoss_Stargate 1 8071
Protoss_Citadel_of_Adun 1 8736
Protoss_Dragoon 1 8770
Protoss_Corsair 1 8758
Protoss_Templar_Archives 1 9921
10745
