Protoss_Forge 1 2782
Protoss_Nexus 1 5257
Protoss_Photon_Cannon 4 5738
Protoss_Gateway 3 10162
Protoss_Assimilator 2 7375
Protoss_Cybernetics_Core 1 7825
Protoss_Zealot 3 9502
Protoss_Stargate 1 8966
Protoss_Citadel_of_Adun 1 8842
Protoss_Dragoon 1 8900
Protoss_Templar_Archives 1 9920
Protoss_Corsair 2 10508
10508
