Protoss_Forge 1 2862
Protoss_Photon_Cannon 2 4188
Protoss_Nexus 1 6207
Protoss_Gateway 4 9541
Protoss_Zealot 15 10556
Protoss_Assimilator 2 9021
Protoss_Cybernetics_Core 1 7248
Protoss_Citadel_of_Adun 1 8329
Protoss_Templar_Archives 1 10461
10556
