Protoss_Forge 1 2716
Protoss_Nexus 1 5435
Protoss_Gateway 1 4641
Protoss_Assimilator 2 6492
Protoss_Photon_Cannon 1 5263
Protoss_Cybernetics_Core 1 5889
Protoss_Zealot 4 10394
Protoss_Stargate 1 7290
Protoss_Dragoon 1 7222
Protoss_Robotics_Facility 1 8130
Protoss_Corsair 5 10526
Protoss_Shuttle 1 9241
Protoss_Robotics_Support_Bay 1 8909
Protoss_Reaver 1 10560
Protoss_Observatory 1 10304
10560
