Protoss_Forge 1 3035
Protoss_Photon_Cannon 3 9645
Protoss_Nexus 1 6139
Protoss_Gateway 4 10126
Protoss_Assimilator 2 8058
Protoss_Cybernetics_Core 1 6697
Protoss_Zealot 2 7164
Protoss_Stargate 1 7878
Protoss_Dragoon 3 10274
Protoss_Robotics_Facility 1 8987
Protoss_Corsair 2 9644
Protoss_Shuttle 1 10781
Protoss_Robotics_Support_Bay 1 10379
10781
