Protoss_Forge 1 2810
Protoss_Nexus 1 4973
Protoss_Photon_Cannon 2 4631
Protoss_Gateway 5 10673
Protoss_Assimilator 2 10069
Protoss_Zealot 9 10516
Protoss_Cybernetics_Core 1 6787
Protoss_Stargate 1 7957
Protoss_Dragoon 1 8536
Protoss_Citadel_of_Adun 1 8689
Protoss_Corsair 3 10002
10673
