Protoss_Gateway 4 10075
Protoss_Zealot 8 10494
Protoss_Nexus 1 6259
Protoss_Assimilator 1 5368
Protoss_Cybernetics_Core 1 5989
Protoss_Stargate 1 7314
Protoss_Dragoon 1 8034
Protoss_Forge 1 7894
Protoss_Corsair 1 8020
Protoss_Citadel_of_Adun 1 9760
10494
