Protoss_Forge 1 2915
Protoss_Photon_Cannon 1 3815
Protoss_Nexus 1 5510
Protoss_Gateway 4 10462
Protoss_Assimilator 2 6720
Protoss_Cybernetics_Core 1 6295
Protoss_Zealot 4 10592
Protoss_Stargate 1 7621
Protoss_Citadel_of_Adun 1 8014
Protoss_Corsair 1 8354
Protoss_Templar_Archives 1 9001
Protoss_Dark_Templar 3 9912
10592
