Protoss_Forge 1 2518
Protoss_Photon_Cannon 1 4251
Protoss_Nexus 1 5494
Protoss_Gateway 3 9843
Protoss_Assimilator 2 7373
Protoss_Zealot 6 10023
Protoss_Cybernetics_Core 1 6194
Protoss_Stargate 1 7396
Protoss_Citadel_of_Adun 1 8945
Protoss_Dragoon 1 9421
Protoss_Templar_Archives 1 9981
10023
