Protoss_Nexus 1 4701
Protoss_Gateway 6 10562
Protoss_Forge 1 4364
Protoss_Assimilator 2 6820
Protoss_Photon_Cannon 2 7515
Protoss_Zealot 6 8838
Protoss_Cybernetics_Core 1 6988
Protoss_Stargate 1 8221
Protoss_Citadel_of_Adun 1 8253
Protoss_Templar_Archives 1 9241
Protoss_Corsair 1 9430
Protoss_Dark_Templar 2 10080
Protoss_High_Templar 1 10550
Protoss_Ground_Weapons_1 1 9811
10562
