Protoss_Forge 1 3005
Protoss_Nexus 1 5107
Protoss_Photon_Cannon 2 8511
Protoss_Gateway 4 10753
Protoss_Assimilator 2 9371
Protoss_Zealot 3 9892
Protoss_Cybernetics_Core 1 7327
Protoss_Citadel_of_Adun 1 8967
Protoss_Dragoon 1 9136
Protoss_Templar_Archives 1 9983
10753
