Protoss_Gateway 1 2805
Protoss_Assimilator 2 10587
Protoss_Zealot 2 4205
Protoss_Cybernetics_Core 1 4903
Protoss_Stargate 1 6042
Protoss_Dragoon 1 5840
Protoss_Citadel_of_Adun 1 6439
Protoss_Corsair 1 6764
Protoss_Templar_Archives 1 7427
Protoss_Forge 1 7412
Protoss_Dark_Templar 2 9014
Protoss_Photon_Cannon 3 10256
Protoss_Robotics_Facility 1 9089
Protoss_Nexus 1 10709
Protoss_High_Templar 1 9801
Protoss_Observatory 1 9642
Protoss_Observer 1 10370
10709
