Protoss_Forge 1 2794
Protoss_Photon_Cannon 3 5700
Protoss_Nexus 1 5395
Protoss_Gateway 4 10320
Protoss_Assimilator 2 7202
Protoss_Cybernetics_Core 1 6909
Protoss_Zealot 2 8893
Protoss_Stargate 1 8059
Protoss_Dragoon 1 7848
Protoss_Citadel_of_Adun 1 8528
Protoss_Corsair 2 9377
Protoss_Templar_Archives 1 9528
Protoss_Dark_Templar 2 10373
10373
