Protoss_Gateway 5 10087
Protoss_Zealot 12 10182
Protoss_Forge 1 4758
Protoss_Photon_Cannon 3 9062
Protoss_Nexus 1 7053
Protoss_Assimilator 2 8285
Protoss_Cybernetics_Core 1 7065
Protoss_Citadel_of_Adun 1 8701
Protoss_Dragoon 1 9162
Protoss_Templar_Archives 1 10687
10687
