Protoss_Forge 1 2890
Protoss_Photon_Cannon 6 10584
Protoss_Nexus 1 5655
Protoss_Gateway 3 9973
Protoss_Assimilator 2 8200
Protoss_Zealot 3 7092
Protoss_Cybernetics_Core 1 6455
Protoss_Dragoon 2 7632
Protoss_Stargate 1 7679
Protoss_Citadel_of_Adun 1 8127
Protoss_Corsair 1 8556
Protoss_Templar_Archives 1 9601
Protoss_Dark_Templar 2 10480
10584
