Protoss_Forge 1 2693
Protoss_Nexus 1 5143
Protoss_Gateway 3 8719
Protoss_Photon_Cannon 4 9388
Protoss_Assimilator 2 6944
Protoss_Cybernetics_Core 1 6466
Protoss_Zealot 1 6538
Protoss_Citadel_of_Adun 1 7835
Protoss_Stargate 1 8064
Protoss_Templar_Archives 1 8855
Protoss_Corsair 3 10436
Protoss_Dark_Templar 4 10510
10510
