Protoss_Gateway 2 10498
Protoss_Zealot 10 10554
Protoss_Assimilator 1 3572
Protoss_Cybernetics_Core 1 4750
Protoss_Dragoon 1 5728
Protoss_Stargate 1 6226
Protoss_Forge 1 5988
Protoss_Citadel_of_Adun 1 6782
Protoss_Corsair 1 6908
Protoss_Photon_Cannon 1 7994
Protoss_Nexus 1 10019
Protoss_Robotics_Facility 1 9969
Protoss_Templar_Archives 1 10867
10867
