Protoss_Forge 1 3137
Protoss_Photon_Cannon 2 4044
Protoss_Nexus 1 6314
Protoss_Gateway 3 10283
Protoss_Assimilator 2 7972
Protoss_Zealot 7 10456
Protoss_Cybernetics_Core 1 6723
Protoss_Stargate 1 7882
Protoss_Robotics_Facility 1 8789
Protoss_Corsair 2 10432
Protoss_Shuttle 1 9865
10456
