Protoss_Assimilator 1 2475
Protoss_Gateway 1 3087
Protoss_Cybernetics_Core 1 4190
Protoss_Stargate 1 5380
Protoss_Robotics_Facility 1 6228
Protoss_Corsair 4 9528
Protoss_Forge 1 7006
Protoss_Shuttle 2 8613
Protoss_Photon_Cannon 1 8049
Protoss_Dragoon 1 8160
Protoss_Robotics_Support_Bay 1 8501
Protoss_Air_Weapons_1 1 8399
Protoss_Reaver 1 9664
9664
