Protoss_Nexus 1 4649
Protoss_Gateway 3 10769
Protoss_Assimilator 2 7521
Protoss_Zealot 7 10032
Protoss_Forge 1 5198
Protoss_Cybernetics_Core 1 6289
Protoss_Photon_Cannon 1 7103
Protoss_Stargate 1 7734
Protoss_Robotics_Facility 1 8040
Protoss_Corsair 3 9670
Protoss_Dragoon 1 8622
Protoss_Shuttle 1 9317
Protoss_Citadel_of_Adun 1 9328
Protoss_Robotics_Support_Bay 1 9374
Protoss_Templar_Archives 1 10487
Protoss_Reaver 1 10716
10769
