Protoss_Forge 1 2885
Protoss_Nexus 1 5068
Protoss_Photon_Cannon 1 4270
Protoss_Gateway 4 9533
Protoss_Assimilator 2 6559
Protoss_Cybernetics_Core 1 5971
Protoss_Zealot 7 10204
Protoss_Stargate 1 7204
Protoss_Citadel_of_Adun 1 7803
Protoss_Corsair 1 7948
Protoss_Templar_Archives 1 9077
Protoss_Dark_Templar 1 10228
Protoss_High_Templar 1 10228
10228
