Protoss_Forge 2 9062
Protoss_Nexus 1 5305
Protoss_Gateway 3 9293
Protoss_Assimilator 2 7091
Protoss_Photon_Cannon 2 9813
Protoss_Cybernetics_Core 1 6020
Protoss_Zealot 1 6520
Protoss_Dragoon 1 6904
Protoss_Stargate 1 7280
Protoss_Citadel_of_Adun 1 7683
Protoss_Corsair 1 8028
Protoss_Templar_Archives 1 8813
Protoss_Dark_Templar 1 9822
Protoss_High_Templar 2 10168
Protoss_Robotics_Facility 1 10800
10800
