Protoss_Forge 1 2676
Protoss_Photon_Cannon 2 8482
Protoss_Nexus 1 5447
Protoss_Gateway 3 10248
Protoss_Assimilator 2 6302
Protoss_Zealot 3 9474
Protoss_Cybernetics_Core 1 6004
Protoss_Stargate 1 7344
Protoss_Dragoon 1 7784
Protoss_Citadel_of_Adun 1 8346
Protoss_Corsair 3 10056
Protoss_Templar_Archives 1 9545
Protoss_Dark_Templar 1 10376
10376
