Protoss_Nexus 1 4605
Protoss_Gateway 1 4019
Protoss_Forge 1 4324
Protoss_Zealot 7 10096
Protoss_Assimilator 2 9380
Protoss_Photon_Cannon 2 6574
Protoss_Cybernetics_Core 1 7239
Protoss_Stargate 1 8482
Protoss_Citadel_of_Adun 1 8869
Protoss_Corsair 1 9186
Protoss_Templar_Archives 1 10687
10687
