Protoss_Forge 1 2626
Protoss_Nexus 1 5165
Protoss_Gateway 1 4703
Protoss_Photon_Cannon 5 10514
Protoss_Zealot 3 7926
Protoss_Assimilator 2 7170
Protoss_Cybernetics_Core 1 6513
Protoss_Stargate 2 8808
Protoss_Citadel_of_Adun 1 8923
Protoss_Corsair 5 10562
Protoss_Templar_Archives 1 10197
10562
