Protoss_Gateway 2 9364
Protoss_Assimilator 1 3230
Protoss_Zealot 6 10063
Protoss_Cybernetics_Core 1 4929
Protoss_Dragoon 1 5768
Protoss_Stargate 1 6426
Protoss_Robotics_Facility 1 7502
Protoss_Corsair 2 7908
Protoss_Forge 1 7545
Protoss_Shuttle 1 8677
Protoss_Photon_Cannon 1 9004
10063
