Protoss_Nexus 1 4528
Protoss_Gateway 1 4257
Protoss_Forge 1 4292
Protoss_Photon_Cannon 1 5130
Protoss_Assimilator 2 6640
Protoss_Zealot 5 8676
Protoss_Cybernetics_Core 1 6680
8676
