Protoss_Nexus 1 4628
Protoss_Gateway 4 10165
Protoss_Forge 1 4505
Protoss_Assimilator 2 5812
Protoss_Photon_Cannon 3 8874
Protoss_Cybernetics_Core 1 5649
Protoss_Stargate 1 6969
Protoss_Zealot 2 8554
Protoss_Citadel_of_Adun 1 7233
Protoss_Corsair 2 8446
Protoss_Templar_Archives 1 8515
Protoss_Dark_Templar 2 9450
Protoss_High_Templar 2 10202
10202
