Protoss_Forge 2 4390
Protoss_Nexus 2 11031
Protoss_Gateway 4 10683
Protoss_Photon_Cannon 2 9444
Protoss_Assimilator 2 7618
Protoss_Zealot 3 8428
Protoss_Cybernetics_Core 1 6617
Protoss_Dragoon 1 7452
Protoss_Stargate 1 7953
Protoss_Citadel_of_Adun 1 7827
Protoss_Templar_Archives 1 8869
Protoss_Corsair 3 10138
Protoss_Dark_Templar 2 10060
11031
