Protoss_Forge 1 2793
Protoss_Photon_Cannon 7 9826
Protoss_Nexus 2 11717
Protoss_Gateway 1 6027
Protoss_Assimilator 2 10355
Protoss_Zealot 3 10138
Protoss_Cybernetics_Core 1 8915
Protoss_Stargate 1 10370
11717
