Protoss_Forge 1 2650
Protoss_Photon_Cannon 6 10674
Protoss_Nexus 1 5450
Protoss_Gateway 4 9855
Protoss_Assimilator 2 8116
Protoss_Zealot 8 9872
Protoss_Cybernetics_Core 1 6971
Protoss_Citadel_of_Adun 1 8024
Protoss_Templar_Archives 1 9598
Protoss_High_Templar 2 10602
Protoss_Dark_Templar 1 10624
10674
