Protoss_Nexus 1 4449
Protoss_Forge 1 3542
Protoss_Gateway 2 5094
Protoss_Assimilator 2 8162
Protoss_Zealot 11 9948
Protoss_Photon_Cannon 2 9593
Protoss_Cybernetics_Core 1 7584
Protoss_Stargate 2 9235
Protoss_Citadel_of_Adun 1 9098
Protoss_Corsair 2 10268
Protoss_Templar_Archives 1 10773
10773
