Protoss_Gateway 3 6202
Protoss_Assimilator 2 7813
Protoss_Zealot 11 8346
Protoss_Forge 1 3924
Protoss_Photon_Cannon 2 10295
Protoss_Ground_Weapons_1 1 8016
Protoss_Nexus 1 10370
Protoss_Cybernetics_Core 1 9963
10370
