Protoss_Forge 1 2762
Protoss_Photon_Cannon 5 9954
Protoss_Nexus 1 5519
Protoss_Gateway 3 10441
Protoss_Assimilator 2 7612
Protoss_Zealot 4 8680
Protoss_Cybernetics_Core 1 6570
Protoss_Stargate 1 7722
Protoss_Dragoon 1 7476
Protoss_Citadel_of_Adun 1 8576
Protoss_Corsair 3 9646
Protoss_Templar_Archives 1 9845
Protoss_Dark_Templar 2 10712
10712
