Protoss_Nexus 1 4690
Protoss_Forge 1 4030
Protoss_Photon_Cannon 2 6040
Protoss_Gateway 3 6588
Protoss_Assimilator 2 9329
Protoss_Zealot 9 8908
Protoss_Cybernetics_Core 1 8749
Protoss_Citadel_of_Adun 1 9868
9868
