Protoss_Gateway 2 7553
Protoss_Assimilator 1 3331
Protoss_Zealot 9 9999
Protoss_Forge 1 4645
Protoss_Photon_Cannon 1 5850
Protoss_Cybernetics_Core 1 6564
Protoss_Citadel_of_Adun 1 7927
Protoss_Ground_Weapons_1 1 8876
Protoss_Templar_Archives 1 10869
10869
