Protoss_Nexus 2 10238
Protoss_Gateway 4 9995
Protoss_Forge 2 10565
Protoss_Assimilator 2 8516
Protoss_Photon_Cannon 1 5607
Protoss_Cybernetics_Core 1 6314
Protoss_Zealot 10 10052
Protoss_Dragoon 1 7268
Protoss_Citadel_of_Adun 1 7607
Protoss_Templar_Archives 1 9573
Protoss_Ground_Weapons_1 1 9751
10565
