Protoss_Forge 1 3304
Protoss_Nexus 1 5194
Protoss_Gateway 1 5151
Protoss_Photon_Cannon 2 9995
Protoss_Assimilator 2 6484
Protoss_Cybernetics_Core 1 6216
Protoss_Zealot 1 6194
Protoss_Stargate 1 7438
9995
