Protoss_Forge 1 2434
Protoss_Nexus 1 5140
Protoss_Photon_Cannon 2 8194
Protoss_Gateway 3 6401
Protoss_Assimilator 1 5501
Protoss_Zealot 13 10156
Protoss_Cybernetics_Core 1 7693
Protoss_Stargate 1 9144
Protoss_Citadel_of_Adun 1 9460
Protoss_Corsair 2 10582
10582
