Protoss_Gateway 2 9773
Protoss_Assimilator 1 2930
Protoss_Zealot 6 9468
Protoss_Cybernetics_Core 1 5285
Protoss_Dragoon 1 6138
Protoss_Stargate 1 6604
Protoss_Citadel_of_Adun 1 7719
9773
