Protoss_Forge 1 2762
Protoss_Nexus 1 4910
Protoss_Gateway 4 8301
Protoss_Photon_Cannon 1 5085
Protoss_Assimilator 2 9428
Protoss_Zealot 17 10574
Protoss_Cybernetics_Core 1 6149
Protoss_Stargate 1 7311
Protoss_Citadel_of_Adun 1 7912
Protoss_Corsair 1 8138
Protoss_Templar_Archives 1 10213
10574
