Protoss_Forge 1 2888
Protoss_Nexus 1 5289
Protoss_Gateway 1 4889
Protoss_Assimilator 2 6420
Protoss_Photon_Cannon 4 9872
Protoss_Cybernetics_Core 1 5981
Protoss_Zealot 2 8366
Protoss_Stargate 1 7371
Protoss_Dragoon 1 7294
Protoss_Robotics_Facility 1 8268
Protoss_Corsair 4 10116
Protoss_Robotics_Support_Bay 1 9132
Protoss_Citadel_of_Adun 1 10255
10255
