Protoss_Forge 1 2795
Protoss_Photon_Cannon 6 10298
Protoss_Nexus 1 6665
Protoss_Gateway 3 10089
Protoss_Assimilator 2 8026
Protoss_Cybernetics_Core 1 7137
Protoss_Zealot 5 10234
Protoss_Stargate 1 8344
Protoss_Citadel_of_Adun 1 8768
Protoss_Corsair 2 9664
Protoss_Templar_Archives 1 9759
Protoss_Dark_Templar 1 10588
10588
