Protoss_Gateway 2 3284
Protoss_Zealot 13 10371
Protoss_Assimilator 1 5925
Protoss_Cybernetics_Core 1 7056
Protoss_Forge 1 7523
Protoss_Stargate 1 8208
Protoss_Dragoon 1 8008
Protoss_Photon_Cannon 2 8945
Protoss_Citadel_of_Adun 1 8741
10371
