Protoss_Forge 1 2577
Protoss_Nexus 1 5015
Protoss_Photon_Cannon 2 5120
Protoss_Gateway 5 10758
Protoss_Assimilator 2 6893
Protoss_Cybernetics_Core 1 6661
Protoss_Zealot 3 9019
Protoss_Stargate 1 7817
Protoss_Citadel_of_Adun 1 8223
Protoss_Dragoon 1 8417
Protoss_Corsair 1 8496
Protoss_Templar_Archives 1 9335
Protoss_High_Templar 2 10318
10758
