Protoss_Gateway 2 8630
Protoss_Zealot 8 9323
Protoss_Assimilator 1 4171
Protoss_Forge 1 4708
Protoss_Photon_Cannon 2 10584
Protoss_Cybernetics_Core 1 7092
Protoss_Dragoon 1 7953
Protoss_Citadel_of_Adun 1 8118
Protoss_Templar_Archives 1 9271
Protoss_Ground_Weapons_1 1 9246
Protoss_High_Templar 2 10128
10584
