Protoss_Forge 1 3206
Protoss_Nexus 1 5016
Protoss_Photon_Cannon 4 10293
Protoss_Gateway 1 5459
Protoss_Assimilator 2 8283
Protoss_Zealot 3 9048
Protoss_Cybernetics_Core 1 6933
Protoss_Stargate 1 9079
Protoss_Citadel_of_Adun 1 9475
Protoss_Corsair 1 9784
Protoss_Templar_Archives 1 10709
10709
