Protoss_Gateway 2 7596
Protoss_Zealot 10 9988
Protoss_Forge 1 5009
Protoss_Photon_Cannon 2 9506
Protoss_Nexus 1 7391
Protoss_Assimilator 1 6705
Protoss_Cybernetics_Core 1 8518
Protoss_Robotics_Facility 1 10111
Protoss_Citadel_of_Adun 1 9906
Protoss_Dragoon 1 10675
10675
