Protoss_Assimilator 1 2372
Protoss_Forge 1 3186
Protoss_Gateway 3 5699
Protoss_Photon_Cannon 2 9230
Protoss_Zealot 8 7778
Protoss_Cybernetics_Core 1 7788
Protoss_Ground_Weapons_1 1 7276
Protoss_Dragoon 6 10653
10653
