Protoss_Gateway 2 3392
Protoss_Zealot 11 9066
Protoss_Assimilator 1 5332
Protoss_Cybernetics_Core 1 6587
Protoss_Citadel_of_Adun 1 7805
Protoss_Dragoon 1 7764
Protoss_Templar_Archives 1 9053
Protoss_Forge 1 9357
Protoss_Dark_Templar 1 9934
Protoss_Photon_Cannon 1 10614
10614
