Protoss_Forge 1 2765
Protoss_Nexus 1 4923
Protoss_Photon_Cannon 2 4882
Protoss_Gateway 4 9719
Protoss_Assimilator 2 6690
Protoss_Zealot 5 10218
Protoss_Cybernetics_Core 1 6515
Protoss_Dragoon 1 7410
Protoss_Stargate 1 7784
Protoss_Citadel_of_Adun 1 8020
Protoss_Corsair 1 8562
Protoss_Templar_Archives 1 9330
Protoss_High_Templar 2 10664
10664
