Protoss_Gateway 3 10734
Protoss_Assimilator 1 3282
Protoss_Zealot 11 10148
Protoss_Cybernetics_Core 1 6058
Protoss_Citadel_of_Adun 1 7258
Protoss_Dragoon 1 7277
Protoss_Templar_Archives 1 9649
Protoss_Forge 1 10558
10734
