Protoss_Gateway 2 9395
Protoss_Zealot 3 4622
Protoss_Nexus 1 6451
Protoss_Forge 1 5988
Protoss_Assimilator 1 6067
Protoss_Cybernetics_Core 1 6994
Protoss_Photon_Cannon 7 10152
Protoss_Dragoon 4 10253
10253
