Protoss_Assimilator 1 2405
Protoss_Gateway 1 3214
Protoss_Cybernetics_Core 1 4222
Protoss_Stargate 1 5388
Protoss_Robotics_Facility 1 6077
Protoss_Corsair 6 10072
Protoss_Shuttle 1 7347
Protoss_Forge 1 7571
Protoss_Photon_Cannon 2 10374
Protoss_Nexus 1 10666
Protoss_Air_Weapons_1 1 9681
10666
