Protoss_Gateway 1 3009
Protoss_Assimilator 1 3150
Protoss_Zealot 8 10188
Protoss_Cybernetics_Core 1 4679
Protoss_Robotics_Facility 1 6386
Protoss_Dragoon 1 6123
Protoss_Shuttle 2 10777
Protoss_Robotics_Support_Bay 1 7220
Protoss_Shield_Battery 1 7701
Protoss_Reaver 2 9645
Protoss_Citadel_of_Adun 1 9638
10777
