Protoss_Forge 1 2713
Protoss_Photon_Cannon 3 10484
Protoss_Nexus 1 6951
Protoss_Gateway 2 6644
Protoss_Assimilator 1 6657
Protoss_Zealot 11 10273
Protoss_Cybernetics_Core 1 9874
Protoss_Citadel_of_Adun 1 10864
10864
