Protoss_Gateway 2 3626
Protoss_Zealot 7 10583
Protoss_Assimilator 1 4404
Protoss_Cybernetics_Core 1 5414
Protoss_Dragoon 1 6388
Protoss_Stargate 1 7026
Protoss_Citadel_of_Adun 1 7326
Protoss_Forge 1 8393
10583
