Protoss_Gateway 2 8204
Protoss_Assimilator 1 3069
Protoss_Zealot 6 8293
Protoss_Cybernetics_Core 1 5219
Protoss_Dragoon 1 6123
Protoss_Citadel_of_Adun 1 6464
Protoss_Templar_Archives 1 7656
Protoss_Dark_Templar 1 8498
Protoss_Forge 1 8629
Protoss_Robotics_Facility 1 9776
Protoss_Photon_Cannon 2 9945
Protoss_High_Templar 2 10293
10293
