Protoss_Gateway 2 3576
Protoss_Zealot 11 9738
Protoss_Assimilator 1 4922
Protoss_Forge 1 6886
Protoss_Cybernetics_Core 1 7495
Protoss_Citadel_of_Adun 1 8489
Protoss_Photon_Cannon 3 10725
Protoss_Templar_Archives 1 9538
Protoss_High_Templar 2 10490
10725
