Protoss_Gateway 2 3509
Protoss_Zealot 7 7923
Protoss_Assimilator 1 5393
Protoss_Cybernetics_Core 1 6233
Protoss_Dragoon 1 7078
Protoss_Stargate 1 7992
Protoss_Citadel_of_Adun 1 8588
Protoss_Corsair 1 8683
Protoss_Forge 1 9028
Protoss_Templar_Archives 1 9707
Protoss_Nexus 1 11535
Protoss_Photon_Cannon 1 10655
11535
