Protoss_Gateway 2 3254
Protoss_Zealot 11 8580
Protoss_Assimilator 1 5033
Protoss_Forge 1 5500
Protoss_Photon_Cannon 2 9756
Protoss_Cybernetics_Core 1 7734
Protoss_Stargate 1 9328
Protoss_Dragoon 2 10008
Protoss_Corsair 1 10018
Protoss_Citadel_of_Adun 1 10599
Protoss_Ground_Weapons_1 1 9811
10599
