Protoss_Gateway 1 2776
Protoss_Assimilator 2 10497
Protoss_Zealot 3 6246
Protoss_Cybernetics_Core 1 4746
Protoss_Stargate 1 5891
Protoss_Dragoon 1 5644
Protoss_Citadel_of_Adun 1 6257
Protoss_Corsair 1 6710
Protoss_Templar_Archives 1 7514
Protoss_Forge 1 7804
Protoss_Dark_Templar 1 8550
Protoss_Nexus 1 10061
Protoss_High_Templar 2 10284
Protoss_Photon_Cannon 3 10458
10497
