Protoss_Gateway 1 3057
Protoss_Assimilator 1 3463
Protoss_Zealot 3 5133
Protoss_Cybernetics_Core 1 5086
Protoss_Citadel_of_Adun 1 6412
Protoss_Dragoon 1 6443
Protoss_Forge 1 6750
Protoss_Templar_Archives 1 7542
Protoss_Photon_Cannon 3 10295
Protoss_Nexus 1 10080
Protoss_High_Templar 2 10540
10540
