Protoss_Gateway 2 3549
Protoss_Zealot 9 7373
Protoss_Assimilator 1 4765
Protoss_Cybernetics_Core 1 5594
Protoss_Stargate 1 7438
Protoss_Citadel_of_Adun 1 8039
Protoss_Corsair 2 8815
Protoss_Templar_Archives 1 9099
Protoss_Dark_Templar 2 9973
Protoss_Nexus 1 11729
11729
