Protoss_Gateway 2 3319
Protoss_Zealot 15 9003
Protoss_Assimilator 1 6284
Protoss_Cybernetics_Core 1 8789
Protoss_Forge 1 9373
Protoss_Dragoon 2 10008
Protoss_Photon_Cannon 1 10404
10404
