Protoss_Gateway 1 2989
Protoss_Assimilator 1 3215
Protoss_Cybernetics_Core 1 4212
Protoss_Zealot 3 5983
Protoss_Stargate 1 5467
Protoss_Corsair 1 6338
Protoss_Forge 1 6835
Protoss_Citadel_of_Adun 1 7926
Protoss_Photon_Cannon 4 9998
Protoss_Nexus 1 9818
Protoss_Robotics_Facility 1 10925
10925
