Protoss_Gateway 2 7006
Protoss_Assimilator 1 2980
Protoss_Zealot 7 7838
Protoss_Cybernetics_Core 1 4674
Protoss_Citadel_of_Adun 1 6216
Protoss_Templar_Archives 1 7913
Protoss_Forge 1 8658
Protoss_High_Templar 4 10578
Protoss_Archon 1 9408
Protoss_Nexus 1 11020
Protoss_Dark_Templar 1 10028
Protoss_Photon_Cannon 2 10430
11020
