Protoss_Gateway 2 7229
Protoss_Assimilator 1 3123
Protoss_Zealot 8 9053
Protoss_Cybernetics_Core 1 4854
Protoss_Dragoon 1 5703
Protoss_Citadel_of_Adun 1 6688
Protoss_Templar_Archives 1 8234
Protoss_Forge 1 8920
Protoss_Dark_Templar 1 9539
Protoss_High_Templar 2 10472
Protoss_Photon_Cannon 1 9953
10472
