Protoss_Gateway 2 3361
Protoss_Zealot 15 9608
Protoss_Assimilator 1 6406
Protoss_Cybernetics_Core 1 8591
Protoss_Forge 1 8485
Protoss_Stargate 1 9781
Protoss_Dragoon 1 9640
Protoss_Citadel_of_Adun 1 10337
10337
