Protoss_Gateway 3 10005
Protoss_Assimilator 1 3083
Protoss_Cybernetics_Core 1 4178
Protoss_Stargate 1 5349
Protoss_Forge 1 5110
Protoss_Photon_Cannon 1 5999
Protoss_Corsair 1 6038
Protoss_Zealot 7 10323
Protoss_Citadel_of_Adun 1 7407
Protoss_Templar_Archives 1 10265
10323
