Protoss_Assimilator 1 2387
Protoss_Gateway 1 3077
Protoss_Cybernetics_Core 1 4145
Protoss_Dragoon 3 10546
Protoss_Stargate 1 5405
Protoss_Corsair 6 10076
Protoss_Robotics_Facility 1 6990
Protoss_Forge 1 7014
Protoss_Shuttle 1 8441
Protoss_Photon_Cannon 1 8664
Protoss_Air_Weapons_1 1 8701
Protoss_Nexus 1 11142
11142
