Protoss_Gateway 1 2794
Protoss_Assimilator 1 3103
Protoss_Zealot 4 10073
Protoss_Cybernetics_Core 1 4781
Protoss_Dragoon 1 5698
Protoss_Robotics_Facility 1 6865
Protoss_Forge 1 7205
Protoss_Robotics_Support_Bay 1 7749
Protoss_Reaver 1 8906
10073
