Protoss_Assimilator 1 2396
Protoss_Gateway 1 3180
Protoss_Cybernetics_Core 1 4167
Protoss_Stargate 1 5312
Protoss_Dragoon 2 6820
Protoss_Robotics_Facility 1 6488
Protoss_Corsair 6 10238
Protoss_Shuttle 1 7469
Protoss_Forge 1 7833
Protoss_Photon_Cannon 2 9782
10238
