Protoss_Gateway 2 5819
Protoss_Assimilator 1 3497
Protoss_Forge 1 3662
Protoss_Photon_Cannon 3 10586
Protoss_Zealot 11 8728
Protoss_Cybernetics_Core 1 7484
Protoss_Citadel_of_Adun 1 8696
Protoss_Ground_Weapons_1 1 8336
Protoss_Templar_Archives 1 10158
10586
