Protoss_Gateway 4 10673
Protoss_Zealot 10 10030
Protoss_Nexus 1 6621
Protoss_Assimilator 1 6113
Protoss_Cybernetics_Core 1 7429
Protoss_Dragoon 2 8636
Protoss_Citadel_of_Adun 1 8659
Protoss_Templar_Archives 1 10010
Protoss_Forge 1 10125
10673
