Protoss_Gateway 2 3459
Protoss_Zealot 10 8498
Protoss_Assimilator 1 4650
Protoss_Cybernetics_Core 1 5590
Protoss_Stargate 1 6894
Protoss_Dragoon 1 6628
Protoss_Corsair 1 7583
Protoss_Citadel_of_Adun 1 8015
Protoss_Forge 1 8146
Protoss_Templar_Archives 1 9431
Protoss_Photon_Cannon 3 10100
Protoss_High_Templar 2 10708
10708
