Protoss_Forge 1 3490
Protoss_Nexus 1 5250
Protoss_Photon_Cannon 5 9024
Protoss_Gateway 2 10004
Protoss_Assimilator 2 7195
Protoss_Cybernetics_Core 1 6919
Protoss_Zealot 2 7798
Protoss_Stargate 1 8148
Protoss_Corsair 3 10185
Protoss_Dragoon 1 9798
Protoss_Robotics_Facility 1 10451
10451
