Protoss_Gateway 2 7049
Protoss_Assimilator 1 3095
Protoss_Zealot 10 10433
Protoss_Forge 2 9429
Protoss_Cybernetics_Core 1 5825
Protoss_Citadel_of_Adun 1 6957
Protoss_Templar_Archives 1 8851
Protoss_Ground_Weapons_1 1 8491
Protoss_High_Templar 2 9718
Protoss_Photon_Cannon 1 10437
Protoss_Archon 1 10104
10437
