Protoss_Gateway 2 3230
Protoss_Zealot 8 7998
Protoss_Forge 1 5688
Protoss_Photon_Cannon 7 10673
Protoss_Nexus 1 7980
Protoss_Assimilator 2 10351
Protoss_Cybernetics_Core 1 9082
Protoss_Citadel_of_Adun 1 10805
Protoss_Dragoon 1 10733
10805
