Protoss_Gateway 2 3384
Protoss_Zealot 12 8393
Protoss_Forge 1 4887
Protoss_Photon_Cannon 3 10093
Protoss_Assimilator 1 7035
Protoss_Cybernetics_Core 1 8059
Protoss_Citadel_of_Adun 1 9379
Protoss_Dragoon 2 9618
Protoss_Templar_Archives 1 10834
10834
