Protoss_Gateway 3 8130
Protoss_Assimilator 1 3080
Protoss_Cybernetics_Core 1 3959
Protoss_Zealot 7 9453
Protoss_Stargate 1 5275
Protoss_Citadel_of_Adun 1 5800
Protoss_Corsair 1 5963
Protoss_Templar_Archives 1 7264
Protoss_Dark_Templar 2 8728
9453
