Protoss_Forge 1 2901
Protoss_Photon_Cannon 7 10261
Protoss_Nexus 1 6260
Protoss_Gateway 3 6489
Protoss_Zealot 14 10568
Protoss_Assimilator 2 10015
Protoss_Cybernetics_Core 1 10714
10714
