Protoss_Gateway 2 9440
Protoss_Zealot 6 6705
Protoss_Forge 1 4935
Protoss_Photon_Cannon 4 7347
Protoss_Nexus 1 9735
Protoss_Assimilator 2 9865
Protoss_Cybernetics_Core 1 10701
10701
