Protoss_Nexus 1 4776
Protoss_Forge 1 4060
Protoss_Photon_Cannon 7 8125
Protoss_Assimilator 1 6641
Protoss_Gateway 4 10247
Protoss_Zealot 2 8238
Protoss_Cybernetics_Core 1 9084
Protoss_Dragoon 2 9938
10247
