Protoss_Forge 1 3248
Protoss_Photon_Cannon 5 10632
Protoss_Nexus 1 6223
Protoss_Gateway 2 8641
Protoss_Assimilator 2 6993
Protoss_Cybernetics_Core 1 6716
Protoss_Zealot 3 8202
Protoss_Dragoon 1 7550
Protoss_Stargate 1 7950
Protoss_Citadel_of_Adun 1 8091
Protoss_Corsair 3 10244
Protoss_Templar_Archives 1 9150
Protoss_Dark_Templar 2 10002
10632
