Protoss_Forge 1 2714
Protoss_Nexus 1 5174
Protoss_Gateway 4 10284
Protoss_Photon_Cannon 3 10063
Protoss_Assimilator 2 7792
Protoss_Cybernetics_Core 1 6561
Protoss_Zealot 9 10310
Protoss_Stargate 1 8012
Protoss_Citadel_of_Adun 1 8355
Protoss_Corsair 1 8694
Protoss_Templar_Archives 1 10311
10311
