Protoss_Gateway 2 9545
Protoss_Zealot 5 8533
Protoss_Nexus 1 5991
Protoss_Assimilator 1 5955
Protoss_Cybernetics_Core 1 6419
Protoss_Dragoon 2 9343
Protoss_Forge 1 7311
Protoss_Robotics_Facility 1 8887
Protoss_Photon_Cannon 2 9671
Protoss_Shuttle 1 9897
Protoss_Robotics_Support_Bay 1 9601
Protoss_Reaver 1 10948
10948
