Protoss_Gateway 2 3393
Protoss_Zealot 9 10498
Protoss_Assimilator 1 4578
Protoss_Cybernetics_Core 1 6024
Protoss_Citadel_of_Adun 1 7060
Protoss_Dragoon 1 7033
Protoss_Templar_Archives 1 8118
Protoss_Forge 1 8996
Protoss_High_Templar 2 10563
Protoss_Photon_Cannon 1 9845
10563
