Protoss_Gateway 2 3510
Protoss_Zealot 13 9607
Protoss_Assimilator 1 5180
Protoss_Cybernetics_Core 1 5729
Protoss_Citadel_of_Adun 1 6972
Protoss_Dragoon 2 7278
Protoss_Forge 1 9315
Protoss_Photon_Cannon 1 10245
Protoss_Templar_Archives 1 10530
10530
