Protoss_Gateway 4 9364
Protoss_Zealot 9 9758
Protoss_Assimilator 1 4186
Protoss_Cybernetics_Core 1 5297
Protoss_Forge 1 5539
Protoss_Stargate 1 6703
Protoss_Corsair 1 7553
Protoss_Photon_Cannon 3 10041
Protoss_Citadel_of_Adun 1 9555
Protoss_Ground_Weapons_1 1 9891
10041
