Protoss_Forge 1 2557
Protoss_Photon_Cannon 5 8360
Protoss_Nexus 1 6315
Protoss_Gateway 1 5895
Protoss_Assimilator 1 5862
Protoss_Cybernetics_Core 1 7023
Protoss_Zealot 1 7178
Protoss_Citadel_of_Adun 1 8097
Protoss_Dragoon 1 8020
8360
