Protoss_Gateway 2 3394
Protoss_Zealot 17 10145
Protoss_Assimilator 1 4897
Protoss_Cybernetics_Core 1 7222
Protoss_Stargate 1 8542
Protoss_Dragoon 1 8283
Protoss_Robotics_Facility 1 9268
Protoss_Corsair 1 9348
10145
