Protoss_Forge 1 2962
Protoss_Photon_Cannon 7 10439
Protoss_Nexus 1 6109
Protoss_Gateway 3 10460
Protoss_Assimilator 2 7146
Protoss_Zealot 3 7928
Protoss_Cybernetics_Core 1 6731
Protoss_Stargate 1 7994
Protoss_Citadel_of_Adun 1 7949
Protoss_Corsair 1 8684
Protoss_Templar_Archives 1 9139
Protoss_Dark_Templar 1 10050
10460
