Protoss_Gateway 2 3595
Protoss_Zealot 8 8902
Protoss_Assimilator 1 4624
Protoss_Cybernetics_Core 1 5481
Protoss_Stargate 1 6783
Protoss_Citadel_of_Adun 1 7251
Protoss_Corsair 1 7466
Protoss_Forge 1 7752
Protoss_Photon_Cannon 2 9218
Protoss_Templar_Archives 1 8959
Protoss_Nexus 1 11092
11092
