Protoss_Forge 1 2550
Protoss_Photon_Cannon 3 8501
Protoss_Nexus 1 5951
Protoss_Gateway 3 10533
Protoss_Assimilator 2 7536
Protoss_Cybernetics_Core 1 6350
Protoss_Zealot 8 10448
Protoss_Stargate 1 7870
Protoss_Citadel_of_Adun 1 8171
Protoss_Corsair 1 8580
Protoss_Templar_Archives 1 10064
10533
