Protoss_Gateway 1 2784
Protoss_Forge 1 3345
Protoss_Zealot 4 7823
Protoss_Photon_Cannon 4 10302
Protoss_Nexus 1 7921
Protoss_Assimilator 1 6848
Protoss_Cybernetics_Core 1 7844
Protoss_Dragoon 2 9758
Protoss_Stargate 1 9548
Protoss_Citadel_of_Adun 1 10358
Protoss_Corsair 1 10248
10358
