Protoss_Gateway 2 7653
Protoss_Assimilator 1 2960
Protoss_Zealot 5 7823
Protoss_Cybernetics_Core 1 4717
Protoss_Stargate 1 5946
Protoss_Dragoon 1 6083
Protoss_Citadel_of_Adun 1 6553
Protoss_Forge 1 8668
8668
