Protoss_Gateway 2 3514
Protoss_Zealot 11 10033
Protoss_Assimilator 1 5593
Protoss_Cybernetics_Core 1 6519
Protoss_Forge 1 7314
Protoss_Photon_Cannon 2 10641
Protoss_Dragoon 1 9138
10641
