Protoss_Forge 1 2705
Protoss_Nexus 1 5440
Protoss_Photon_Cannon 10 10213
Protoss_Gateway 3 9096
Protoss_Assimilator 2 7352
Protoss_Cybernetics_Core 1 6889
Protoss_Zealot 2 7603
Protoss_Citadel_of_Adun 1 8227
Protoss_Templar_Archives 1 9298
Protoss_High_Templar 2 10153
10213
