Protoss_Gateway 1 2619
Protoss_Zealot 9 8823
Protoss_Assimilator 1 4300
Protoss_Cybernetics_Core 1 5809
Protoss_Stargate 1 7183
Protoss_Citadel_of_Adun 1 7770
Protoss_Corsair 1 7873
Protoss_Templar_Archives 1 8919
Protoss_Dark_Templar 2 10520
Protoss_Nexus 1 11125
Protoss_Forge 1 10223
11125
