Protoss_Gateway 2 3338
Protoss_Zealot 9 8173
Protoss_Assimilator 1 5093
Protoss_Cybernetics_Core 1 6458
Protoss_Dragoon 2 7308
Protoss_Citadel_of_Adun 1 7542
Protoss_Templar_Archives 1 8939
Protoss_High_Templar 2 10088
10088
