Protoss_Gateway 2 3593
Protoss_Zealot 9 10208
Protoss_Assimilator 1 4235
Protoss_Cybernetics_Core 1 5674
Protoss_Stargate 1 7058
Protoss_Dragoon 1 7048
Protoss_Citadel_of_Adun 1 7734
Protoss_Corsair 1 7933
Protoss_Forge 1 8159
Protoss_Photon_Cannon 1 10375
10375
