Protoss_Forge 1 3076
Protoss_Nexus 1 5701
Protoss_Photon_Cannon 6 9858
Protoss_Gateway 4 10239
Protoss_Zealot 3 8458
Protoss_Assimilator 2 8742
Protoss_Cybernetics_Core 1 9493
Protoss_Dragoon 3 10418
10418
