Protoss_Gateway 3 8677
Protoss_Assimilator 1 3105
Protoss_Zealot 2 4648
Protoss_Cybernetics_Core 1 4729
Protoss_Dragoon 8 10623
Protoss_Robotics_Facility 1 6497
Protoss_Shuttle 1 7487
Protoss_Robotics_Support_Bay 1 7106
Protoss_Reaver 2 9590
10623
