Protoss_Gateway 2 6904
Protoss_Forge 1 3684
Protoss_Zealot 11 10528
Protoss_Photon_Cannon 3 7620
Protoss_Nexus 1 7230
Protoss_Assimilator 2 10579
Protoss_Cybernetics_Core 1 9459
10579
