Protoss_Gateway 2 3558
Protoss_Zealot 9 8973
Protoss_Assimilator 1 4235
Protoss_Cybernetics_Core 1 5585
Protoss_Stargate 1 6909
Protoss_Citadel_of_Adun 1 7510
Protoss_Dragoon 1 7828
Protoss_Forge 1 9266
Protoss_Nexus 1 11020
11020
