Protoss_Gateway 1 2867
Protoss_Assimilator 1 2991
Protoss_Zealot 5 7833
Protoss_Cybernetics_Core 1 4855
Protoss_Dragoon 1 5788
Protoss_Citadel_of_Adun 1 6055
Protoss_Robotics_Facility 1 6786
Protoss_Shuttle 1 7787
Protoss_Templar_Archives 1 7797
Protoss_Forge 1 7630
Protoss_Robotics_Support_Bay 1 7866
Protoss_Photon_Cannon 2 10601
Protoss_Reaver 2 10063
Protoss_High_Templar 2 10200
10601
