Protoss_Gateway 2 8219
Protoss_Zealot 9 10254
Protoss_Assimilator 1 4020
Protoss_Cybernetics_Core 1 4856
Protoss_Dragoon 1 5710
Protoss_Stargate 1 6353
Protoss_Forge 1 6244
Protoss_Corsair 1 7042
Protoss_Citadel_of_Adun 1 8087
Protoss_Photon_Cannon 1 9434
10254
