Protoss_Forge 1 2696
Protoss_Nexus 1 5380
Protoss_Photon_Cannon 3 10742
Protoss_Gateway 3 8800
Protoss_Assimilator 2 9148
Protoss_Zealot 6 10588
Protoss_Cybernetics_Core 1 7366
Protoss_Stargate 1 8805
Protoss_Dragoon 1 8733
Protoss_Citadel_of_Adun 1 9997
10742
