Protoss_Gateway 2 3243
Protoss_Zealot 13 8293
Protoss_Assimilator 1 5798
Protoss_Cybernetics_Core 1 7730
Protoss_Citadel_of_Adun 1 8724
Protoss_Dragoon 1 8618
Protoss_Forge 1 8891
Protoss_Templar_Archives 1 9808
Protoss_Dark_Templar 1 10658
10658
