Protoss_Gateway 2 3527
Protoss_Zealot 7 7653
Protoss_Assimilator 1 4207
Protoss_Cybernetics_Core 1 5258
Protoss_Dragoon 1 6153
Protoss_Citadel_of_Adun 1 6440
Protoss_Templar_Archives 1 8462
Protoss_Forge 1 8551
Protoss_High_Templar 3 10698
Protoss_Photon_Cannon 4 10701
10701
