Protoss_Gateway 2 3659
Protoss_Zealot 13 10384
Protoss_Assimilator 1 4994
Protoss_Cybernetics_Core 1 6505
Protoss_Citadel_of_Adun 1 7502
Protoss_Templar_Archives 1 8915
Protoss_High_Templar 2 9772
Protoss_Forge 1 9712
Protoss_Nexus 1 11349
11349
