Protoss_Gateway 2 3329
Protoss_Zealot 11 8033
Protoss_Assimilator 1 5730
Protoss_Cybernetics_Core 1 6483
Protoss_Stargate 1 8158
Protoss_Dragoon 1 8048
Protoss_Robotics_Facility 1 9286
Protoss_Corsair 1 9028
Protoss_Forge 1 9613
Protoss_Robotics_Support_Bay 1 9865
Protoss_Shuttle 1 10317
Protoss_Photon_Cannon 1 10570
10570
