Protoss_Gateway 3 8924
Protoss_Forge 1 3280
Protoss_Zealot 9 10293
Protoss_Photon_Cannon 6 8180
Protoss_Nexus 1 7795
Protoss_Assimilator 1 8221
Protoss_Cybernetics_Core 1 10242
10293
