Protoss_Forge 1 2698
Protoss_Nexus 1 5371
Protoss_Gateway 4 8299
Protoss_Photon_Cannon 2 9365
Protoss_Assimilator 1 5255
Protoss_Zealot 5 9556
Protoss_Cybernetics_Core 1 6195
Protoss_Dragoon 8 10316
Protoss_Citadel_of_Adun 1 10177
Protoss_Ground_Weapons_1 1 9975
10316
