Protoss_Assimilator 1 2399
Protoss_Gateway 1 3283
Protoss_Cybernetics_Core 1 4274
Protoss_Stargate 1 5555
Protoss_Robotics_Facility 1 6666
Protoss_Robotics_Support_Bay 1 7772
Protoss_Shield_Battery 1 10367
10367
