Protoss_Gateway 3 10337
Protoss_Assimilator 1 3288
Protoss_Zealot 6 10193
Protoss_Forge 1 4430
Protoss_Cybernetics_Core 1 5911
Protoss_Stargate 1 7139
Protoss_Citadel_of_Adun 1 7129
Protoss_Templar_Archives 1 8129
Protoss_Corsair 1 7863
Protoss_High_Templar 2 10480
Protoss_Dark_Templar 1 9068
Protoss_Ground_Weapons_1 1 8521
Protoss_Photon_Cannon 3 10670
10670
