Protoss_Gateway 2 9943
Protoss_Assimilator 1 3070
Protoss_Cybernetics_Core 1 4141
Protoss_Zealot 2 6488
Protoss_Stargate 1 5407
Protoss_Dragoon 3 8553
Protoss_Robotics_Facility 1 7007
Protoss_Corsair 1 7013
9943
