Protoss_Gateway 1 2789
Protoss_Assimilator 1 2975
Protoss_Forge 1 3464
Protoss_Cybernetics_Core 1 4719
Protoss_Photon_Cannon 1 5005
Protoss_Dragoon 1 5753
Protoss_Robotics_Facility 1 7211
Protoss_Observatory 1 8079
8079
