Protoss_Gateway 1 2939
Protoss_Assimilator 1 2920
Protoss_Cybernetics_Core 1 4030
Protoss_Forge 1 4448
Protoss_Stargate 1 5598
Protoss_Photon_Cannon 3 7948
Protoss_Corsair 2 7663
Protoss_Zealot 3 10163
10163
