Protoss_Gateway 1 2828
Protoss_Assimilator 1 3040
Protoss_Zealot 5 9538
Protoss_Cybernetics_Core 1 5694
Protoss_Forge 1 6138
Protoss_Dragoon 1 6608
Protoss_Citadel_of_Adun 1 6974
Protoss_Photon_Cannon 2 8905
Protoss_Templar_Archives 1 8292
Protoss_Nexus 1 10135
Protoss_High_Templar 2 10700
10700
