Protoss_Gateway 2 7185
Protoss_Assimilator 1 3071
Protoss_Zealot 5 6843
Protoss_Cybernetics_Core 1 5289
Protoss_Citadel_of_Adun 1 6423
Protoss_Forge 1 8305
Protoss_Nexus 1 11110
11110
