Protoss_Gateway 1 2798
Protoss_Assimilator 1 2855
Protoss_Cybernetics_Core 1 3908
Protoss_Forge 1 4473
Protoss_Stargate 1 5348
Protoss_Photon_Cannon 3 7841
Protoss_Corsair 1 6038
Protoss_Robotics_Facility 1 9262
9262
