Protoss_Forge 1 2776
Protoss_Photon_Cannon 4 10572
Protoss_Nexus 1 5894
Protoss_Gateway 3 10611
Protoss_Assimilator 2 7898
Protoss_Zealot 4 9914
Protoss_Cybernetics_Core 1 7291
Protoss_Stargate 1 8934
Protoss_Corsair 2 10486
Protoss_Citadel_of_Adun 1 10323
10611
