Protoss_Gateway 2 3235
Protoss_Zealot 9 9103
Protoss_Assimilator 1 5448
Protoss_Cybernetics_Core 1 6106
Protoss_Citadel_of_Adun 1 7321
Protoss_Dragoon 1 7333
Protoss_Forge 1 7492
Protoss_Photon_Cannon 2 10220
Protoss_Templar_Archives 1 9137
Protoss_Dark_Templar 1 10148
Protoss_High_Templar 1 10153
10220
