Protoss_Gateway 2 6284
Protoss_Assimilator 1 3261
Protoss_Zealot 5 10555
Protoss_Cybernetics_Core 1 4939
Protoss_Citadel_of_Adun 1 6219
Protoss_Templar_Archives 1 7224
Protoss_Forge 1 7225
Protoss_Dark_Templar 2 8093
Protoss_Nexus 1 10113
Protoss_High_Templar 2 9143
Protoss_Photon_Cannon 2 9797
Protoss_Archon 1 9542
10555
