Protoss_Gateway 4 8505
Protoss_Zealot 13 10478
Protoss_Forge 1 4445
Protoss_Photon_Cannon 3 10545
Protoss_Nexus 1 7762
Protoss_Assimilator 2 10132
Protoss_Cybernetics_Core 1 7611
Protoss_Citadel_of_Adun 1 8646
10545
