Protoss_Forge 1 2871
Protoss_Nexus 1 5205
Protoss_Photon_Cannon 10 10710
Protoss_Gateway 1 5365
Protoss_Assimilator 2 9810
Protoss_Zealot 4 8443
Protoss_Cybernetics_Core 1 6914
Protoss_Robotics_Facility 1 8849
Protoss_Citadel_of_Adun 1 9083
Protoss_Templar_Archives 1 10269
Protoss_Robotics_Support_Bay 1 10131
Protoss_Stargate 1 10914
10914
