Protoss_Gateway 2 6432
Protoss_Assimilator 1 3169
Protoss_Zealot 8 7868
Protoss_Cybernetics_Core 1 4784
Protoss_Citadel_of_Adun 1 5918
Protoss_Templar_Archives 1 7559
Protoss_Forge 1 7655
Protoss_Dark_Templar 1 8458
Protoss_Photon_Cannon 5 10689
Protoss_High_Templar 4 10323
Protoss_Archon 1 9655
10689
