Protoss_Gateway 2 10517
Protoss_Assimilator 1 3125
Protoss_Zealot 9 10325
Protoss_Cybernetics_Core 1 4614
Protoss_Dragoon 1 6118
Protoss_Robotics_Facility 1 6784
Protoss_Robotics_Support_Bay 1 7343
Protoss_Shuttle 1 7792
Protoss_Reaver 1 8886
Protoss_Forge 1 9160
Protoss_Citadel_of_Adun 1 10247
Protoss_Photon_Cannon 1 10703
10703
