Protoss_Gateway 2 3394
Protoss_Zealot 12 8993
Protoss_Assimilator 1 6665
Protoss_Cybernetics_Core 1 7749
Protoss_Stargate 1 8962
Protoss_Dragoon 1 8898
Protoss_Citadel_of_Adun 1 9705
Protoss_Corsair 2 10255
Protoss_Forge 1 10452
10452
