Protoss_Gateway 2 3344
Protoss_Assimilator 1 3704
Protoss_Zealot 9 9863
Protoss_Cybernetics_Core 1 4820
Protoss_Stargate 1 6089
Protoss_Dragoon 1 6208
Protoss_Citadel_of_Adun 1 6589
Protoss_Corsair 1 6793
9863
