Protoss_Gateway 2 6378
Protoss_Assimilator 1 2987
Protoss_Zealot 8 9813
Protoss_Cybernetics_Core 1 4674
Protoss_Dragoon 1 5513
Protoss_Citadel_of_Adun 1 6101
Protoss_Templar_Archives 1 7380
Protoss_High_Templar 4 9203
Protoss_Forge 1 8682
Protoss_Archon 2 9537
Protoss_Photon_Cannon 1 10041
Protoss_Nexus 1 11700
11700
