Protoss_Gateway 2 6193
Protoss_Assimilator 1 3215
Protoss_Cybernetics_Core 1 4124
Protoss_Zealot 11 9192
Protoss_Citadel_of_Adun 1 5289
Protoss_Templar_Archives 1 8553
Protoss_Dark_Templar 2 10023
Protoss_Nexus 1 11774
11774
