Protoss_Gateway 2 3439
Protoss_Zealot 10 10450
Protoss_Assimilator 1 4642
Protoss_Cybernetics_Core 1 6380
Protoss_Citadel_of_Adun 1 7427
Protoss_Dragoon 1 7328
Protoss_Templar_Archives 1 8914
Protoss_High_Templar 2 9848
Protoss_Forge 1 9803
Protoss_Archon 1 10205
Protoss_Photon_Cannon 1 10685
10685
