Protoss_Forge 1 2550
Protoss_Nexus 1 6001
Protoss_Photon_Cannon 3 5405
Protoss_Gateway 2 8017
Protoss_Assimilator 2 7011
Protoss_Cybernetics_Core 1 7185
Protoss_Zealot 10 10554
Protoss_Citadel_of_Adun 1 8174
Protoss_Templar_Archives 1 9246
10554
