Protoss_Gateway 1 2849
Protoss_Assimilator 1 3070
Protoss_Zealot 5 7963
Protoss_Cybernetics_Core 1 4689
Protoss_Dragoon 1 5593
Protoss_Citadel_of_Adun 1 6839
Protoss_Forge 1 6940
Protoss_Templar_Archives 1 8060
Protoss_Photon_Cannon 5 10650
Protoss_High_Templar 2 9665
Protoss_Nexus 1 10615
Protoss_Dark_Templar 1 10417
Psionic_Storm 1 9991
10650
