Protoss_Gateway 2 7864
Protoss_Assimilator 1 3272
Protoss_Cybernetics_Core 1 4068
Protoss_Zealot 8 10453
Protoss_Stargate 1 5393
Protoss_Forge 1 5295
Protoss_Dragoon 1 5803
Protoss_Photon_Cannon 1 6175
Protoss_Corsair 1 6313
Protoss_Citadel_of_Adun 1 7360
10453
