Protoss_Gateway 3 7659
Protoss_Zealot 10 8603
Protoss_Assimilator 1 5790
Protoss_Cybernetics_Core 1 6464
Protoss_Nexus 1 8029
Protoss_Forge 1 8215
Protoss_Photon_Cannon 1 9104
Protoss_Citadel_of_Adun 1 9539
Protoss_Templar_Archives 1 10569
Protoss_Robotics_Facility 1 11057
11057
