Protoss_Forge 1 3026
Protoss_Photon_Cannon 4 5951
Protoss_Nexus 1 6740
Protoss_Gateway 1 6420
Protoss_Assimilator 2 8955
Protoss_Zealot 5 9948
Protoss_Cybernetics_Core 1 7871
Protoss_Citadel_of_Adun 1 9004
Protoss_Robotics_Facility 1 10121
Protoss_Templar_Archives 1 10563
10563
