Protoss_Gateway 2 7384
Protoss_Assimilator 1 3180
Protoss_Zealot 6 7988
Protoss_Cybernetics_Core 1 4982
Protoss_Dragoon 1 6085
Protoss_Citadel_of_Adun 1 6958
Protoss_Templar_Archives 1 8019
Protoss_Forge 1 8460
Protoss_High_Templar 4 10073
Protoss_Nexus 1 10750
Protoss_Archon 1 9334
Protoss_Photon_Cannon 3 10594
10750
