Protoss_Forge 2 4108
Protoss_Photon_Cannon 4 5478
Protoss_Nexus 1 6105
Protoss_Assimilator 2 7894
Protoss_Gateway 1 6450
Protoss_Cybernetics_Core 1 8097
Protoss_Stargate 1 9741
9741
