Protoss_Forge 1 2913
Protoss_Nexus 1 5223
Protoss_Gateway 3 8259
Protoss_Photon_Cannon 6 10558
Protoss_Assimilator 2 9664
Protoss_Zealot 10 10106
Protoss_Cybernetics_Core 1 7351
Protoss_Citadel_of_Adun 1 8483
Protoss_Robotics_Facility 1 10148
10558
