Protoss_Gateway 2 6810
Protoss_Assimilator 1 2981
Protoss_Zealot 9 9246
Protoss_Cybernetics_Core 1 4680
Protoss_Dragoon 1 5613
Protoss_Citadel_of_Adun 1 6107
Protoss_Templar_Archives 1 7817
Protoss_High_Templar 3 10018
Protoss_Forge 1 9567
10018
