Protoss_Gateway 3 8485
Protoss_Zealot 13 10242
Protoss_Assimilator 1 5287
Protoss_Cybernetics_Core 1 6040
Protoss_Nexus 1 8433
Protoss_Citadel_of_Adun 1 8032
Protoss_Forge 1 10128
10242
