Protoss_Gateway 2 3675
Protoss_Zealot 8 6520
Protoss_Forge 1 4404
Protoss_Photon_Cannon 3 8880
Protoss_Assimilator 1 6103
Protoss_Cybernetics_Core 1 7263
Protoss_Stargate 2 9140
Protoss_Corsair 2 10174
10174
