Protoss_Gateway 2 10126
Protoss_Assimilator 2 10437
Protoss_Zealot 2 4678
Protoss_Cybernetics_Core 1 4576
Protoss_Stargate 1 5750
Protoss_Citadel_of_Adun 1 6032
Protoss_Corsair 1 6453
Protoss_Dragoon 1 6713
Protoss_Templar_Archives 1 7237
Protoss_Dark_Templar 2 9028
Protoss_Nexus 1 9334
Protoss_Forge 1 8425
Protoss_Photon_Cannon 1 9680
Protoss_High_Templar 1 10663
10663
