Protoss_Forge 1 2729
Protoss_Photon_Cannon 5 9752
Protoss_Gateway 1 4824
Protoss_Nexus 1 6778
Protoss_Assimilator 2 10418
Protoss_Zealot 4 10493
Protoss_Cybernetics_Core 1 7215
Protoss_Stargate 1 8547
Protoss_Dragoon 1 8843
Protoss_Corsair 1 9243
Protoss_Citadel_of_Adun 1 10726
10726
