Protoss_Gateway 2 3404
Protoss_Zealot 14 10038
Protoss_Assimilator 1 6597
Protoss_Forge 1 7445
Protoss_Nexus 1 9985
Protoss_Cybernetics_Core 1 9634
Protoss_Photon_Cannon 1 9835
10038
