Protoss_Forge 1 2620
Protoss_Nexus 1 5406
Protoss_Gateway 3 8594
Protoss_Photon_Cannon 2 10664
Protoss_Assimilator 2 8572
Protoss_Cybernetics_Core 1 6185
Protoss_Zealot 9 10024
Protoss_Citadel_of_Adun 1 7492
Protoss_Dragoon 1 7530
Protoss_Templar_Archives 1 10141
Protoss_Ground_Weapons_1 1 9995
10664
