Protoss_Forge 1 2636
Protoss_Nexus 1 5250
Protoss_Photon_Cannon 2 5350
Protoss_Gateway 5 9196
Protoss_Assimilator 2 10022
Protoss_Zealot 12 10593
Protoss_Cybernetics_Core 1 7114
Protoss_Dragoon 1 8193
Protoss_Citadel_of_Adun 1 8414
Protoss_Templar_Archives 1 10762
10762
