Protoss_Forge 1 3002
Protoss_Nexus 1 5255
Protoss_Photon_Cannon 7 9275
Protoss_Gateway 1 5389
Protoss_Assimilator 2 9314
Protoss_Cybernetics_Core 1 6447
Protoss_Zealot 4 10293
Protoss_Stargate 1 7655
Protoss_Corsair 3 9547
Protoss_Citadel_of_Adun 1 9184
Protoss_Templar_Archives 1 10574
10574
