Protoss_Gateway 1 2810
Protoss_Assimilator 1 3072
Protoss_Forge 1 3574
Protoss_Photon_Cannon 2 7999
Protoss_Cybernetics_Core 1 5358
Protoss_Dragoon 1 6188
Protoss_Ground_Weapons_1 1 8689
Protoss_Zealot 1 9680
9680
