Protoss_Forge 1 2716
Protoss_Nexus 1 5100
Protoss_Gateway 5 9074
Protoss_Photon_Cannon 2 10330
Protoss_Assimilator 2 9335
Protoss_Zealot 13 9898
Protoss_Cybernetics_Core 1 6431
Protoss_Citadel_of_Adun 1 7446
Protoss_Dragoon 1 7423
Protoss_Templar_Archives 1 9695
Protoss_Ground_Weapons_1 1 9816
Protoss_High_Templar 1 10743
10743
