Protoss_Gateway 3 10813
Protoss_Assimilator 1 3017
Protoss_Zealot 4 7370
Protoss_Cybernetics_Core 1 4735
Protoss_Stargate 1 6022
Protoss_Citadel_of_Adun 1 6421
Protoss_Dragoon 1 6432
Protoss_Corsair 1 6764
Protoss_Templar_Archives 1 7495
Protoss_Forge 1 7672
Protoss_Photon_Cannon 3 10618
Protoss_Dark_Templar 1 8762
Protoss_High_Templar 2 10316
10813
