Protoss_Gateway 1 2926
Protoss_Assimilator 1 3120
Protoss_Zealot 7 9978
Protoss_Cybernetics_Core 1 4874
Protoss_Stargate 1 6129
Protoss_Dragoon 1 6191
Protoss_Corsair 4 9708
Protoss_Nexus 1 9583
Protoss_Forge 2 9200
Protoss_Citadel_of_Adun 1 9679
Protoss_Templar_Archives 1 10794
10794
