Protoss_Gateway 2 3326
Protoss_Zealot 9 7128
Protoss_Shield_Battery 1 3638
Protoss_Assimilator 1 7777
Protoss_Forge 1 8100
Protoss_Cybernetics_Core 1 9239
Protoss_Photon_Cannon 2 10728
Protoss_Citadel_of_Adun 1 10289
10728
