Protoss_Gateway 1 2711
Protoss_Assimilator 1 3001
Protoss_Zealot 4 8033
Protoss_Cybernetics_Core 1 4728
Protoss_Dragoon 1 5573
Protoss_Stargate 1 6232
Protoss_Forge 1 6552
Protoss_Corsair 1 6978
Protoss_Photon_Cannon 3 10500
Protoss_Citadel_of_Adun 1 7854
Protoss_Robotics_Facility 1 9173
Protoss_Templar_Archives 1 9234
Protoss_Nexus 1 10460
Protoss_Robotics_Support_Bay 1 9813
Protoss_Dark_Templar 1 10243
10500
