Protoss_Gateway 2 3239
Protoss_Zealot 11 7273
Protoss_Forge 1 6805
Protoss_Photon_Cannon 3 8730
Protoss_Assimilator 1 8192
Protoss_Cybernetics_Core 1 9268
Protoss_Stargate 1 10472
10472
