Protoss_Gateway 2 9097
Protoss_Assimilator 1 3073
Protoss_Zealot 3 6358
Protoss_Cybernetics_Core 1 4749
Protoss_Dragoon 1 5583
Protoss_Robotics_Facility 1 6829
Protoss_Citadel_of_Adun 1 7288
Protoss_Shuttle 1 7822
Protoss_Robotics_Support_Bay 1 7431
Protoss_Reaver 2 9934
Protoss_Templar_Archives 1 9219
Protoss_Forge 1 9745
Protoss_High_Templar 1 10068
Protoss_Photon_Cannon 2 10610
10610
