Protoss_Gateway 2 3688
Protoss_Zealot 10 8608
Protoss_Assimilator 1 4595
Protoss_Cybernetics_Core 1 5584
Protoss_Forge 1 5902
Protoss_Dragoon 1 6453
Protoss_Citadel_of_Adun 1 7181
Protoss_Templar_Archives 1 8367
Protoss_Photon_Cannon 2 10045
Protoss_Dark_Templar 1 9978
Protoss_Nexus 1 11483
Protoss_High_Templar 2 10730
11483
