Protoss_Gateway 2 3447
Protoss_Zealot 8 9582
Protoss_Assimilator 1 4837
Protoss_Cybernetics_Core 1 5799
Protoss_Stargate 1 7130
Protoss_Corsair 1 7820
Protoss_Nexus 1 11594
11594
