Protoss_Gateway 2 3319
Protoss_Zealot 12 9358
Protoss_Assimilator 1 6563
Protoss_Cybernetics_Core 1 7417
Protoss_Stargate 1 8604
Protoss_Dragoon 2 9473
Protoss_Corsair 1 9393
Protoss_Citadel_of_Adun 1 10211
Protoss_Forge 1 10262
10262
