Protoss_Nexus 1 4580
Protoss_Forge 1 3801
Protoss_Photon_Cannon 6 10745
Protoss_Gateway 2 6604
Protoss_Assimilator 2 6921
Protoss_Zealot 9 10178
Protoss_Cybernetics_Core 1 7678
Protoss_Stargate 1 8896
Protoss_Citadel_of_Adun 1 8915
Protoss_Corsair 1 9583
Protoss_Templar_Archives 1 9909
10745
