Protoss_Gateway 3 6249
Protoss_Zealot 17 10463
Protoss_Nexus 1 5590
Protoss_Assimilator 1 7323
Protoss_Cybernetics_Core 1 8798
Protoss_Citadel_of_Adun 1 10016
Protoss_Forge 1 9795
Protoss_Photon_Cannon 1 10676
10676
