Protoss_Gateway 2 3603
Protoss_Zealot 9 9003
Protoss_Assimilator 1 4736
Protoss_Cybernetics_Core 1 5594
Protoss_Forge 1 5659
Protoss_Citadel_of_Adun 1 7274
Protoss_Templar_Archives 1 8714
Protoss_Photon_Cannon 2 9835
Protoss_High_Templar 2 10058
Protoss_Ground_Weapons_1 1 9756
Protoss_Nexus 1 11775
11775
