Protoss_Gateway 2 3456
Protoss_Zealot 13 10168
Protoss_Assimilator 1 4425
Protoss_Cybernetics_Core 1 6308
Protoss_Citadel_of_Adun 1 7376
Protoss_Dragoon 1 7998
Protoss_Templar_Archives 1 8419
Protoss_Forge 1 8323
Protoss_High_Templar 2 9540
Protoss_Photon_Cannon 1 10438
10438
