Protoss_Forge 1 2680
Protoss_Photon_Cannon 8 10719
Protoss_Nexus 1 7265
Protoss_Gateway 4 10499
Protoss_Assimilator 2 9763
Protoss_Zealot 5 10336
Protoss_Cybernetics_Core 1 9092
Protoss_Citadel_of_Adun 1 10089
10719
