Protoss_Forge 2 4123
Protoss_Nexus 1 4946
Protoss_Photon_Cannon 4 10482
Protoss_Gateway 6 8289
Protoss_Assimilator 1 5634
Protoss_Cybernetics_Core 1 6659
Protoss_Zealot 16 10488
Protoss_Citadel_of_Adun 1 7825
Protoss_Dragoon 1 8558
10488
