Protoss_Gateway 2 7474
Protoss_Assimilator 1 3135
Protoss_Zealot 8 9623
Protoss_Cybernetics_Core 1 5633
Protoss_Stargate 1 6986
Protoss_Dragoon 1 6893
Protoss_Corsair 1 7673
Protoss_Citadel_of_Adun 1 8150
Protoss_Templar_Archives 1 9400
Protoss_Forge 1 9250
Protoss_Dark_Templar 2 10643
10643
