Protoss_Forge 1 3186
Protoss_Photon_Cannon 10 10135
Protoss_Nexus 1 5891
Protoss_Gateway 3 9019
Protoss_Assimilator 2 7559
Protoss_Cybernetics_Core 1 6734
Protoss_Citadel_of_Adun 1 7734
Protoss_Dragoon 1 7918
Protoss_Templar_Archives 1 8744
Protoss_High_Templar 3 10713
Protoss_Dark_Templar 1 10318
10713
