Protoss_Gateway 2 6790
Protoss_Assimilator 1 3215
Protoss_Zealot 6 7768
Protoss_Cybernetics_Core 1 4744
Protoss_Dragoon 1 5703
Protoss_Citadel_of_Adun 1 6224
Protoss_Templar_Archives 1 8385
Protoss_Forge 1 8761
Protoss_High_Templar 3 10093
Protoss_Nexus 1 10715
Protoss_Archon 1 9774
Protoss_Dark_Templar 1 10253
10715
