Protoss_Forge 1 2996
Protoss_Photon_Cannon 2 3910
Protoss_Nexus 1 6280
Protoss_Gateway 1 6004
Protoss_Assimilator 2 7555
Protoss_Zealot 3 8007
Protoss_Cybernetics_Core 1 7455
Protoss_Robotics_Facility 1 8760
Protoss_Stargate 1 9072
Protoss_Dragoon 1 9468
Protoss_Shuttle 1 10092
Protoss_Robotics_Support_Bay 1 9666
10092
