Protoss_Gateway 3 7599
Protoss_Assimilator 1 3019
Protoss_Zealot 11 9853
Protoss_Cybernetics_Core 1 4799
Protoss_Stargate 1 6538
Protoss_Citadel_of_Adun 1 6773
Protoss_Corsair 1 7913
Protoss_Nexus 1 10661
Protoss_Templar_Archives 1 9934
10661
