Protoss_Gateway 2 6512
Protoss_Assimilator 1 3163
Protoss_Zealot 9 9338
Protoss_Cybernetics_Core 1 4927
Protoss_Dragoon 1 5768
Protoss_Forge 1 5842
Protoss_Citadel_of_Adun 1 7406
Protoss_Stargate 2 9428
Protoss_Photon_Cannon 1 9968
Protoss_Corsair 3 10588
10588
