Protoss_Nexus 1 4895
Protoss_Forge 1 4544
Protoss_Photon_Cannon 8 9920
Protoss_Assimilator 2 7483
Protoss_Gateway 3 9629
Protoss_Cybernetics_Core 1 7742
Protoss_Stargate 2 9056
Protoss_Citadel_of_Adun 1 9075
Protoss_Corsair 3 10393
Protoss_Templar_Archives 1 10279
10393
