Protoss_Nexus 1 4753
Protoss_Forge 1 3874
Protoss_Photon_Cannon 5 10346
Protoss_Gateway 3 8029
Protoss_Assimilator 1 5306
Protoss_Zealot 12 10232
Protoss_Cybernetics_Core 1 7141
Protoss_Citadel_of_Adun 1 8247
Protoss_Stargate 2 9993
Protoss_Corsair 1 10334
Protoss_Robotics_Facility 1 11136
11136
