Protoss_Assimilator 1 2430
Protoss_Gateway 1 3124
Protoss_Cybernetics_Core 1 4119
Protoss_Stargate 1 5315
Protoss_Robotics_Facility 1 5822
Protoss_Citadel_of_Adun 1 6057
Protoss_Corsair 1 6008
Protoss_Shuttle 1 6812
Protoss_Templar_Archives 1 7184
Protoss_Forge 1 7285
Protoss_High_Templar 2 9508
Protoss_Nexus 1 9435
Protoss_Photon_Cannon 5 10546
Protoss_Dark_Templar 1 10260
Psionic_Storm 1 9911
10546
