Protoss_Forge 1 3453
Protoss_Nexus 1 5270
Protoss_Photon_Cannon 3 9720
Protoss_Gateway 1 5159
Protoss_Assimilator 2 7786
Protoss_Cybernetics_Core 1 6476
Protoss_Zealot 2 7988
Protoss_Dragoon 1 7323
Protoss_Stargate 1 7788
Protoss_Corsair 4 10373
Protoss_Robotics_Facility 1 9250
Protoss_Robotics_Support_Bay 3 9992
Protoss_Shuttle 1 10457
10457
