Protoss_Gateway 2 8394
Protoss_Assimilator 1 3160
Protoss_Zealot 5 8743
Protoss_Cybernetics_Core 1 4955
Protoss_Citadel_of_Adun 1 6062
Protoss_Dragoon 1 6048
Protoss_Robotics_Facility 1 7201
Protoss_Shuttle 1 8572
Protoss_Robotics_Support_Bay 1 8414
Protoss_Reaver 1 9623
9623
