Protoss_Forge 1 3403
Protoss_Nexus 1 5198
Protoss_Photon_Cannon 7 10412
Protoss_Gateway 5 10839
Protoss_Assimilator 2 7246
Protoss_Zealot 2 6402
Protoss_Cybernetics_Core 1 6163
Protoss_Citadel_of_Adun 1 7327
Protoss_Templar_Archives 1 8408
Protoss_Dragoon 1 8884
Protoss_High_Templar 2 9256
Protoss_Dark_Templar 1 9636
Protoss_Robotics_Facility 1 10555
10839
