Protoss_Assimilator 1 2424
Protoss_Gateway 1 3326
Protoss_Cybernetics_Core 1 4313
Protoss_Stargate 1 5473
Protoss_Dragoon 1 5392
Protoss_Robotics_Facility 1 6667
Protoss_Corsair 2 6794
Protoss_Shuttle 1 7651
Protoss_Robotics_Support_Bay 1 7554
Protoss_Reaver 3 11012
Protoss_Nexus 1 10134
Protoss_Forge 1 10441
11012
