Protoss_Forge 1 2782
Protoss_Nexus 1 5259
Protoss_Photon_Cannon 2 4937
Protoss_Gateway 5 9519
Protoss_Assimilator 2 9938
Protoss_Cybernetics_Core 1 7037
Protoss_Zealot 11 10528
Protoss_Citadel_of_Adun 1 8216
Protoss_Templar_Archives 1 10407
10528
