Protoss_Nexus 1 4625
Protoss_Forge 1 4028
Protoss_Photon_Cannon 3 6252
Protoss_Gateway 5 9488
Protoss_Assimilator 2 8019
Protoss_Zealot 9 10324
Protoss_Cybernetics_Core 1 7064
Protoss_Citadel_of_Adun 1 8359
10324
