Protoss_Nexus 1 4625
Protoss_Gateway 4 9009
Protoss_Assimilator 2 9319
Protoss_Forge 1 4775
Protoss_Photon_Cannon 1 5685
Protoss_Zealot 10 9698
Protoss_Cybernetics_Core 1 7007
Protoss_Citadel_of_Adun 1 8080
Protoss_Dragoon 1 8083
Protoss_Templar_Archives 1 9837
Protoss_Ground_Weapons_1 1 9561
Protoss_High_Templar 2 10698
10698
