Protoss_Forge 1 2735
Protoss_Nexus 1 5109
Protoss_Photon_Cannon 4 10723
Protoss_Gateway 5 9449
Protoss_Assimilator 2 10387
Protoss_Zealot 13 10472
Protoss_Cybernetics_Core 1 7697
Protoss_Citadel_of_Adun 1 8695
Protoss_Templar_Archives 1 10672
10723
