Protoss_Gateway 1 2866
Protoss_Assimilator 1 3450
Protoss_Zealot 2 6503
Protoss_Cybernetics_Core 1 4669
Protoss_Dragoon 1 5508
Protoss_Stargate 1 6038
Protoss_Robotics_Facility 1 6996
Protoss_Corsair 2 9238
Protoss_Forge 1 7589
Protoss_Shuttle 1 8057
Protoss_Shield_Battery 1 7731
Protoss_Robotics_Support_Bay 1 7792
Protoss_Photon_Cannon 4 10665
Protoss_Reaver 1 9108
Protoss_Nexus 1 10826
10826
