Protoss_Forge 1 2827
Protoss_Photon_Cannon 7 10180
Protoss_Nexus 1 5960
Protoss_Gateway 2 9330
Protoss_Assimilator 1 5537
Protoss_Zealot 5 9158
Protoss_Cybernetics_Core 1 6794
Protoss_Citadel_of_Adun 1 7849
Protoss_Dragoon 1 7858
Protoss_Templar_Archives 1 8974
Protoss_Dark_Templar 2 10368
10368
