Protoss_Gateway 1 2779
Protoss_Assimilator 1 2991
Protoss_Zealot 3 6178
Protoss_Cybernetics_Core 1 4504
Protoss_Dragoon 1 5368
Protoss_Stargate 1 6186
Protoss_Citadel_of_Adun 1 6441
Protoss_Corsair 1 6898
Protoss_Templar_Archives 1 7605
Protoss_Forge 1 7475
Protoss_Photon_Cannon 3 10057
Protoss_Dark_Templar 1 8563
Protoss_Nexus 1 10430
Protoss_High_Templar 2 10353
Psionic_Storm 1 9721
10430
