Protoss_Gateway 2 3991
Protoss_Zealot 15 8926
Protoss_Assimilator 1 6987
Protoss_Cybernetics_Core 1 8050
Protoss_Forge 1 8222
Protoss_Citadel_of_Adun 1 9082
Protoss_Templar_Archives 1 10165
Protoss_Photon_Cannon 2 10692
Protoss_Nexus 1 11461
11461
