Protoss_Gateway 1 2964
Protoss_Assimilator 1 2925
Protoss_Zealot 6 8404
Protoss_Cybernetics_Core 1 5723
Protoss_Dragoon 1 6598
Protoss_Citadel_of_Adun 1 6985
Protoss_Forge 1 7312
Protoss_Templar_Archives 1 8057
Protoss_Dark_Templar 1 9156
Protoss_Photon_Cannon 1 9630
Protoss_High_Templar 2 10660
Protoss_Nexus 1 11360
11360
