Protoss_Forge 1 2509
Protoss_Nexus 1 5040
Protoss_Photon_Cannon 2 4955
Protoss_Gateway 1 5676
Protoss_Assimilator 1 5564
Protoss_Cybernetics_Core 1 6696
Protoss_Zealot 1 7163
7163
