Protoss_Gateway 3 9397
Protoss_Assimilator 1 3025
Protoss_Zealot 4 6553
Protoss_Cybernetics_Core 1 5372
Protoss_Dragoon 10 10540
Protoss_Forge 1 7037
Protoss_Citadel_of_Adun 1 10222
10540
