Protoss_Forge 2 6130
Protoss_Assimilator 2 5667
Protoss_Photon_Cannon 3 10170
Protoss_Gateway 2 8484
Protoss_Zealot 2 9268
Protoss_Cybernetics_Core 1 9434
Protoss_Citadel_of_Adun 1 10519
10519
