Protoss_Gateway 1 3004
Protoss_Assimilator 2 10354
Protoss_Cybernetics_Core 1 4169
Protoss_Robotics_Facility 1 5827
Protoss_Dragoon 1 5623
Protoss_Zealot 1 6678
Protoss_Robotics_Support_Bay 1 6540
Protoss_Reaver 2 10431
Protoss_Shuttle 1 8589
Protoss_Stargate 1 9818
Protoss_Nexus 1 10877
10877
