Protoss_Gateway 2 3383
Protoss_Zealot 7 8758
Protoss_Assimilator 1 4560
Protoss_Forge 1 5379
Protoss_Cybernetics_Core 1 6313
Protoss_Photon_Cannon 4 10693
Protoss_Citadel_of_Adun 1 7305
Protoss_Templar_Archives 1 8882
Protoss_High_Templar 2 9720
Protoss_Nexus 1 11139
Protoss_Ground_Weapons_1 1 9459
11139
