Protoss_Forge 1 2830
Protoss_Photon_Cannon 5 10541
Protoss_Nexus 1 6391
Protoss_Gateway 4 10516
Protoss_Assimilator 3 9279
Protoss_Cybernetics_Core 1 6905
Protoss_Citadel_of_Adun 1 7989
Protoss_Zealot 8 9894
Protoss_Robotics_Facility 1 11109
11109
