Protoss_Gateway 2 3451
Protoss_Zealot 17 9840
Protoss_Nexus 1 8007
Protoss_Forge 1 7736
Protoss_Assimilator 1 8083
Protoss_Photon_Cannon 2 10235
Protoss_Cybernetics_Core 1 9543
Protoss_Stargate 1 11018
11018
