Protoss_Forge 1 2863
Protoss_Photon_Cannon 7 10052
Protoss_Nexus 1 6530
Protoss_Gateway 1 6004
Protoss_Assimilator 2 8206
Protoss_Zealot 3 10038
Protoss_Cybernetics_Core 1 7124
Protoss_Dragoon 2 9098
Protoss_Citadel_of_Adun 1 8439
Protoss_Templar_Archives 1 10499
10499
