Protoss_Forge 2 8165
Protoss_Photon_Cannon 4 9251
Protoss_Nexus 1 5851
Protoss_Gateway 4 10044
Protoss_Assimilator 1 5711
Protoss_Cybernetics_Core 1 6653
Protoss_Zealot 10 10178
Protoss_Dragoon 1 7513
Protoss_Citadel_of_Adun 1 7764
Protoss_Templar_Archives 1 10629
10629
