Protoss_Forge 1 2985
Protoss_Photon_Cannon 8 10645
Protoss_Nexus 1 6221
Protoss_Gateway 1 6013
Protoss_Assimilator 2 8350
Protoss_Zealot 6 9916
Protoss_Cybernetics_Core 1 7020
Protoss_Citadel_of_Adun 1 8466
Protoss_Templar_Archives 1 9455
Protoss_High_Templar 1 10304
Protoss_Dark_Templar 1 10412
10645
