Protoss_Forge 1 3025
Protoss_Photon_Cannon 2 4028
Protoss_Nexus 1 6072
Protoss_Gateway 3 8600
Protoss_Assimilator 1 5581
Protoss_Cybernetics_Core 1 6464
Protoss_Zealot 1 8903
8903
