Protoss_Forge 1 2711
Protoss_Photon_Cannon 4 10035
Protoss_Nexus 1 5525
Protoss_Gateway 3 8364
Protoss_Zealot 11 10033
Protoss_Assimilator 2 8385
Protoss_Cybernetics_Core 1 7961
Protoss_Citadel_of_Adun 1 9014
Protoss_Templar_Archives 1 10044
10044
