Protoss_Gateway 1 2979
Protoss_Assimilator 1 3220
Protoss_Zealot 4 6963
Protoss_Cybernetics_Core 1 5315
Protoss_Stargate 1 6514
Protoss_Dragoon 1 6298
Protoss_Citadel_of_Adun 1 7115
Protoss_Corsair 1 7203
Protoss_Templar_Archives 1 8237
Protoss_Dark_Templar 1 9088
Protoss_Nexus 1 10330
Protoss_Forge 1 9865
Protoss_High_Templar 1 10063
Protoss_Photon_Cannon 1 10717
10717
