Protoss_Nexus 1 4356
Protoss_Forge 1 3494
Protoss_Photon_Cannon 4 8796
Protoss_Gateway 1 4969
Protoss_Assimilator 2 7257
Protoss_Zealot 5 8786
Protoss_Cybernetics_Core 1 6129
Protoss_Stargate 1 7386
Protoss_Robotics_Facility 2 10182
Protoss_Corsair 3 10486
Protoss_Robotics_Support_Bay 1 8944
Protoss_Reaver 1 10314
10486
