Protoss_Assimilator 1 2367
Protoss_Forge 1 3034
Protoss_Gateway 3 5635
Protoss_Photon_Cannon 4 10172
Protoss_Zealot 8 7822
Protoss_Ground_Weapons_1 1 7385
Protoss_Cybernetics_Core 1 8641
Protoss_Dragoon 3 9508
Protoss_Stargate 1 10148
10172
