Protoss_Gateway 2 3464
Protoss_Zealot 18 9304
Protoss_Assimilator 1 6730
Protoss_Cybernetics_Core 1 7889
Protoss_Citadel_of_Adun 1 8915
Protoss_Templar_Archives 1 10114
Protoss_Forge 1 10196
10196
