Protoss_Forge 1 3249
Protoss_Photon_Cannon 7 10668
Protoss_Nexus 1 6183
Protoss_Gateway 1 5703
Protoss_Assimilator 2 8231
Protoss_Cybernetics_Core 1 6721
Protoss_Zealot 6 9904
Protoss_Stargate 1 8040
Protoss_Citadel_of_Adun 1 8444
Protoss_Corsair 2 9484
Protoss_Templar_Archives 1 10671
10671
