Protoss_Gateway 1 2819
Protoss_Assimilator 1 3336
Protoss_Zealot 3 5303
Protoss_Cybernetics_Core 1 4824
Protoss_Citadel_of_Adun 1 5888
Protoss_Dragoon 1 6055
Protoss_Forge 1 6355
Protoss_Templar_Archives 1 7129
Protoss_Photon_Cannon 3 10182
Protoss_Dark_Templar 2 8788
Protoss_Nexus 1 10560
Protoss_High_Templar 1 10583
10583
