Protoss_Gateway 2 9267
Protoss_Assimilator 1 3090
Protoss_Cybernetics_Core 1 4027
Protoss_Zealot 4 7878
Protoss_Citadel_of_Adun 1 5666
Protoss_Forge 1 6143
Protoss_Dragoon 2 7118
Protoss_Templar_Archives 1 7839
Protoss_Photon_Cannon 2 9827
Protoss_Dark_Templar 1 8668
Protoss_High_Templar 2 10172
Protoss_Nexus 1 11633
11633
