Protoss_Gateway 2 3384
Protoss_Zealot 10 7978
Protoss_Assimilator 1 6719
Protoss_Cybernetics_Core 1 7952
Protoss_Forge 1 8247
Protoss_Citadel_of_Adun 1 8955
Protoss_Photon_Cannon 2 9662
Protoss_Templar_Archives 1 10175
10175
