Protoss_Gateway 2 3542
Protoss_Zealot 10 10298
Protoss_Assimilator 1 4874
Protoss_Cybernetics_Core 1 6192
Protoss_Citadel_of_Adun 1 7187
Protoss_Templar_Archives 1 8395
Protoss_Forge 1 8670
Protoss_High_Templar 3 10456
Protoss_Nexus 1 10739
Protoss_Photon_Cannon 2 10158
Protoss_Archon 1 9867
10739
