Protoss_Gateway 1 2814
Protoss_Assimilator 1 3109
Protoss_Cybernetics_Core 1 3984
Protoss_Zealot 3 7648
Protoss_Stargate 1 5278
Protoss_Corsair 4 9748
Protoss_Robotics_Facility 1 7049
Protoss_Forge 1 7461
Protoss_Shuttle 1 8107
Protoss_Photon_Cannon 2 9606
Protoss_Robotics_Support_Bay 1 8389
Protoss_Reaver 2 10651
Protoss_Nexus 1 11755
11755
