Protoss_Gateway 2 3644
Protoss_Zealot 15 9913
Protoss_Assimilator 1 6834
Protoss_Cybernetics_Core 1 7869
Protoss_Citadel_of_Adun 1 9492
Protoss_Nexus 1 10513
Protoss_Templar_Archives 1 10644
10644
