Protoss_Forge 1 2844
Protoss_Photon_Cannon 7 10657
Protoss_Gateway 2 10065
Protoss_Zealot 6 10438
Protoss_Nexus 1 6980
Protoss_Assimilator 2 8720
Protoss_Cybernetics_Core 1 7550
Protoss_Citadel_of_Adun 1 8605
Protoss_Templar_Archives 1 9783
Protoss_High_Templar 1 10718
10718
