Protoss_Forge 1 3391
Protoss_Photon_Cannon 6 9501
Protoss_Nexus 1 6895
Protoss_Gateway 1 6417
Protoss_Assimilator 2 7905
Protoss_Cybernetics_Core 1 7559
Protoss_Zealot 2 8165
Protoss_Stargate 1 8753
Protoss_Robotics_Facility 1 9612
Protoss_Corsair 2 10105
Protoss_Shuttle 1 10662
Protoss_Robotics_Support_Bay 1 10396
10662
