Protoss_Forge 1 2824
Protoss_Photon_Cannon 6 9610
Protoss_Nexus 1 7317
Protoss_Gateway 2 10701
Protoss_Assimilator 2 8253
Protoss_Cybernetics_Core 1 7656
Protoss_Zealot 4 10182
Protoss_Citadel_of_Adun 1 8984
Protoss_Templar_Archives 1 9979
10701
