Protoss_Forge 1 2770
Protoss_Photon_Cannon 3 5130
Protoss_Nexus 1 5920
Protoss_Gateway 4 8449
Protoss_Assimilator 2 10579
Protoss_Zealot 13 10383
Protoss_Cybernetics_Core 1 7549
Protoss_Citadel_of_Adun 1 8744
Protoss_Templar_Archives 1 10299
10579
