Protoss_Gateway 2 8138
Protoss_Zealot 7 7080
Protoss_Assimilator 1 4153
Protoss_Cybernetics_Core 1 6179
Protoss_Stargate 1 7467
Protoss_Dragoon 2 8740
Protoss_Citadel_of_Adun 1 8007
Protoss_Forge 1 8076
Protoss_Corsair 3 10046
Protoss_Templar_Archives 1 9127
Protoss_Photon_Cannon 4 10689
10689
