Protoss_Gateway 1 2812
Protoss_Assimilator 1 3020
Protoss_Zealot 7 8566
Protoss_Cybernetics_Core 1 5573
Protoss_Stargate 2 7176
Protoss_Dragoon 1 6668
Protoss_Citadel_of_Adun 1 7649
Protoss_Corsair 1 7858
Protoss_Forge 1 8254
Protoss_Templar_Archives 1 8791
Protoss_Nexus 1 10820
Protoss_Dark_Templar 1 9940
Protoss_Photon_Cannon 2 10497
Protoss_High_Templar 1 10698
10820
