Protoss_Gateway 2 10187
Protoss_Zealot 8 9411
Protoss_Nexus 1 6307
Protoss_Forge 1 5373
Protoss_Photon_Cannon 4 7008
Protoss_Assimilator 2 10350
Protoss_Cybernetics_Core 1 9151
Protoss_Citadel_of_Adun 1 10249
10350
