Protoss_Forge 1 2902
Protoss_Nexus 1 5062
Protoss_Photon_Cannon 5 10704
Protoss_Gateway 3 9894
Protoss_Assimilator 2 7946
Protoss_Zealot 9 10040
Protoss_Cybernetics_Core 1 6331
Protoss_Citadel_of_Adun 1 7673
Protoss_Dragoon 1 7970
Protoss_Templar_Archives 1 9590
10704
