Protoss_Nexus 1 4690
Protoss_Forge 1 3800
Protoss_Photon_Cannon 5 10747
Protoss_Gateway 4 8834
Protoss_Assimilator 2 7153
Protoss_Cybernetics_Core 1 8431
Protoss_Zealot 7 9588
Protoss_Citadel_of_Adun 1 9547
Protoss_Templar_Archives 1 10560
10747
