Protoss_Forge 1 3203
Protoss_Photon_Cannon 2 4113
Protoss_Nexus 1 6287
Protoss_Gateway 4 9623
Protoss_Assimilator 2 9596
Protoss_Zealot 9 10450
Protoss_Cybernetics_Core 1 6906
Protoss_Citadel_of_Adun 1 8046
Protoss_Dragoon 1 7953
Protoss_Templar_Archives 1 9856
10450
