Protoss_Forge 1 2615
Protoss_Photon_Cannon 9 10051
Protoss_Nexus 1 7922
Protoss_Assimilator 1 7350
Protoss_Gateway 2 10550
Protoss_Zealot 3 10133
Protoss_Cybernetics_Core 1 9104
Protoss_Citadel_of_Adun 1 10479
10550
