Protoss_Forge 1 2602
Protoss_Photon_Cannon 5 9162
Protoss_Nexus 2 11619
Protoss_Gateway 1 5303
Protoss_Assimilator 2 6710
Protoss_Cybernetics_Core 1 6289
Protoss_Zealot 1 6222
Protoss_Stargate 1 7488
Protoss_Robotics_Facility 1 8500
Protoss_Corsair 2 9628
Protoss_Shuttle 1 9599
Protoss_Robotics_Support_Bay 1 9963
11619
