Protoss_Forge 1 2963
Protoss_Photon_Cannon 4 10280
Protoss_Nexus 1 5971
Protoss_Gateway 2 8609
Protoss_Assimilator 1 5926
Protoss_Zealot 5 10152
Protoss_Cybernetics_Core 1 6885
Protoss_Dragoon 1 7872
10280
