Protoss_Gateway 2 3358
Protoss_Zealot 8 7400
Protoss_Assimilator 1 4430
Protoss_Forge 1 5110
Protoss_Cybernetics_Core 1 6176
Protoss_Citadel_of_Adun 1 7249
Protoss_Dragoon 1 7653
Protoss_Photon_Cannon 5 10490
Protoss_Templar_Archives 1 8721
Protoss_Nexus 1 11000
Protoss_High_Templar 2 10073
Protoss_Ground_Weapons_1 1 9306
11000
