Protoss_Assimilator 1 2369
Protoss_Gateway 1 3282
Protoss_Cybernetics_Core 1 4273
Protoss_Stargate 2 5902
Protoss_Corsair 9 10132
Protoss_Forge 1 7346
Protoss_Photon_Cannon 1 8188
Protoss_Air_Weapons_1 1 8355
Protoss_Robotics_Facility 1 9833
Protoss_Shuttle 1 10817
10817
