Protoss_Gateway 1 2629
Protoss_Assimilator 2 10340
Protoss_Zealot 3 6025
Protoss_Cybernetics_Core 1 4579
Protoss_Dragoon 1 5423
Protoss_Stargate 1 6201
Protoss_Citadel_of_Adun 1 6817
Protoss_Forge 1 6620
Protoss_Corsair 1 6943
Protoss_Photon_Cannon 4 10321
Protoss_Templar_Archives 1 7831
Protoss_Dark_Templar 1 8738
Protoss_Robotics_Facility 1 9397
Protoss_Nexus 1 10695
Protoss_Robotics_Support_Bay 1 9980
10695
