Protoss_Gateway 2 7816
Protoss_Assimilator 1 3113
Protoss_Zealot 9 10585
Protoss_Cybernetics_Core 1 5814
Protoss_Dragoon 1 6653
Protoss_Citadel_of_Adun 1 7093
Protoss_Robotics_Facility 1 8372
Protoss_Templar_Archives 1 8210
Protoss_Dark_Templar 2 9208
Protoss_Shuttle 1 9477
Protoss_High_Templar 2 9983
Protoss_Forge 1 10337
10585
