Protoss_Forge 1 2625
Protoss_Nexus 1 5414
Protoss_Photon_Cannon 2 4822
Protoss_Gateway 5 10092
Protoss_Assimilator 1 6091
Protoss_Zealot 11 10208
Protoss_Cybernetics_Core 1 7395
Protoss_Citadel_of_Adun 1 8461
Protoss_Dragoon 1 8342
10208
