Protoss_Forge 1 2776
Protoss_Nexus 1 5180
Protoss_Gateway 4 8104
Protoss_Photon_Cannon 5 10666
Protoss_Assimilator 2 8450
Protoss_Zealot 11 10073
Protoss_Cybernetics_Core 1 7216
Protoss_Citadel_of_Adun 1 8249
Protoss_Templar_Archives 1 9654
10666
