Protoss_Forge 1 2799
Protoss_Photon_Cannon 4 5691
Protoss_Nexus 1 7655
Protoss_Assimilator 1 6827
Protoss_Gateway 2 8291
Protoss_Cybernetics_Core 1 9012
Protoss_Zealot 6 10384
Protoss_Citadel_of_Adun 1 10247
10384
