Protoss_Forge 1 2742
Protoss_Nexus 1 5345
Protoss_Photon_Cannon 4 10686
Protoss_Gateway 3 8685
Protoss_Assimilator 2 9237
Protoss_Zealot 9 10158
Protoss_Cybernetics_Core 1 6855
Protoss_Citadel_of_Adun 1 7891
Protoss_Dragoon 1 8296
10686
