Protoss_Forge 1 2953
Protoss_Nexus 1 4974
Protoss_Photon_Cannon 8 10130
Protoss_Gateway 1 5362
Protoss_Assimilator 2 8319
Protoss_Zealot 5 9222
Protoss_Cybernetics_Core 1 7153
Protoss_Dragoon 1 8018
Protoss_Citadel_of_Adun 1 8508
Protoss_Templar_Archives 1 9606
Protoss_Dark_Templar 1 10648
10648
