Protoss_Forge 1 3164
Protoss_Photon_Cannon 5 9209
Protoss_Gateway 3 10342
Protoss_Nexus 1 6490
Protoss_Assimilator 2 10352
Protoss_Zealot 3 9728
Protoss_Cybernetics_Core 1 7914
Protoss_Stargate 1 9088
Protoss_Corsair 2 10473
Protoss_Citadel_of_Adun 1 10531
10531
