Protoss_Gateway 2 10447
Protoss_Zealot 7 9738
Protoss_Assimilator 1 3753
Protoss_Cybernetics_Core 1 4899
Protoss_Stargate 1 6188
Protoss_Dragoon 1 6447
Protoss_Forge 1 6505
Protoss_Citadel_of_Adun 1 6999
Protoss_Corsair 2 7978
Protoss_Photon_Cannon 3 10018
Protoss_Nexus 1 10260
Protoss_Templar_Archives 1 9555
Protoss_Dark_Templar 1 10523
10523
