Protoss_Gateway 2 10666
Protoss_Assimilator 1 3090
Protoss_Zealot 5 9988
Protoss_Cybernetics_Core 1 5274
Protoss_Dragoon 1 6118
Protoss_Robotics_Facility 1 6877
Protoss_Forge 1 7212
Protoss_Robotics_Support_Bay 1 7460
Protoss_Shuttle 1 7997
Protoss_Reaver 1 9048
Protoss_Photon_Cannon 3 10644
Protoss_Citadel_of_Adun 1 10098
10666
