Protoss_Gateway 2 6804
Protoss_Assimilator 1 3066
Protoss_Zealot 5 9210
Protoss_Cybernetics_Core 1 4749
Protoss_Stargate 1 5979
Protoss_Dragoon 1 6003
Protoss_Citadel_of_Adun 1 6354
Protoss_Robotics_Facility 1 7392
Protoss_Templar_Archives 1 7764
Protoss_Shuttle 1 8382
Protoss_Dark_Templar 2 8608
Protoss_Forge 1 8550
Protoss_Nexus 1 11150
Protoss_Photon_Cannon 2 10670
Protoss_High_Templar 1 10228
11150
