Protoss_Forge 1 3660
Protoss_Nexus 1 5472
Protoss_Photon_Cannon 5 10395
Protoss_Gateway 4 8534
Protoss_Assimilator 2 9579
Protoss_Cybernetics_Core 1 6439
Protoss_Zealot 8 10473
Protoss_Citadel_of_Adun 1 7802
Protoss_Dragoon 1 7818
Protoss_Templar_Archives 1 9696
Protoss_High_Templar 2 10583
10583
