Protoss_Gateway 2 3427
Protoss_Zealot 8 8376
Protoss_Assimilator 1 6390
Protoss_Forge 1 6690
Protoss_Photon_Cannon 2 10252
Protoss_Cybernetics_Core 1 8369
Protoss_Dragoon 1 9332
10252
