Protoss_Gateway 3 7777
Protoss_Zealot 12 10218
Protoss_Assimilator 1 4660
Protoss_Cybernetics_Core 1 5487
Protoss_Dragoon 1 6613
Protoss_Stargate 1 7616
Protoss_Corsair 1 9283
10218
