Protoss_Forge 1 2564
Protoss_Photon_Cannon 6 10567
Protoss_Nexus 1 6019
Protoss_Gateway 3 8245
Protoss_Assimilator 2 10190
Protoss_Zealot 9 9530
Protoss_Cybernetics_Core 1 6766
Protoss_Citadel_of_Adun 1 7905
Protoss_Templar_Archives 1 9933
10567
