Protoss_Forge 1 2677
Protoss_Nexus 1 5270
Protoss_Photon_Cannon 2 4790
Protoss_Gateway 4 8759
Protoss_Assimilator 2 9860
Protoss_Zealot 7 9553
Protoss_Cybernetics_Core 1 7379
Protoss_Citadel_of_Adun 1 8379
Protoss_Dragoon 1 8243
Protoss_Templar_Archives 1 10024
10024
