Protoss_Gateway 4 9299
Protoss_Zealot 9 6816
Protoss_Nexus 1 7649
Protoss_Assimilator 3 9828
Protoss_Cybernetics_Core 1 7575
Protoss_Dragoon 6 10618
Protoss_Forge 1 10102
10618
