Protoss_Gateway 2 3128
Protoss_Zealot 15 9120
Protoss_Nexus 1 9273
Protoss_Forge 1 8339
Protoss_Assimilator 1 8446
Protoss_Photon_Cannon 2 9586
Protoss_Cybernetics_Core 1 10450
10450
