Protoss_Forge 1 3075
Protoss_Photon_Cannon 2 3990
Protoss_Nexus 1 5855
Protoss_Gateway 1 5501
Protoss_Assimilator 1 5365
Protoss_Cybernetics_Core 1 6505
Protoss_Zealot 3 8048
Protoss_Stargate 1 7752
8048
