Protoss_Forge 1 2835
Protoss_Nexus 1 5396
Protoss_Photon_Cannon 3 6601
Protoss_Gateway 3 10735
Protoss_Assimilator 2 8826
Protoss_Zealot 9 10396
Protoss_Cybernetics_Core 1 7617
Protoss_Citadel_of_Adun 1 8628
Protoss_Dragoon 1 8590
Protoss_Templar_Archives 1 10059
10735
