Protoss_Forge 1 2812
Protoss_Nexus 1 5302
Protoss_Photon_Cannon 3 10167
Protoss_Gateway 3 8934
Protoss_Assimilator 2 8818
Protoss_Zealot 8 10313
Protoss_Cybernetics_Core 1 7270
Protoss_Dragoon 1 8280
Protoss_Citadel_of_Adun 1 8594
10313
