Protoss_Nexus 1 4820
Protoss_Forge 1 4136
Protoss_Photon_Cannon 2 10652
Protoss_Gateway 4 10493
Protoss_Assimilator 2 8422
Protoss_Zealot 11 10233
Protoss_Cybernetics_Core 1 6536
Protoss_Citadel_of_Adun 1 7569
Protoss_Dragoon 1 8260
Protoss_Templar_Archives 1 8874
Protoss_High_Templar 2 10500
10652
