Protoss_Gateway 2 3214
Protoss_Zealot 12 10393
Protoss_Nexus 1 7408
Protoss_Forge 1 6724
Protoss_Photon_Cannon 2 7975
Protoss_Assimilator 2 9470
Protoss_Cybernetics_Core 1 9229
Protoss_Citadel_of_Adun 1 10609
10609
