Protoss_Gateway 2 3144
Protoss_Zealot 14 10338
Protoss_Nexus 1 7560
Protoss_Forge 1 7010
Protoss_Photon_Cannon 1 7860
Protoss_Assimilator 2 9545
Protoss_Cybernetics_Core 1 8934
Protoss_Citadel_of_Adun 1 10414
10414
