Protoss_Nexus 1 5019
Protoss_Gateway 3 5424
Protoss_Zealot 16 9943
Protoss_Assimilator 2 9137
Protoss_Forge 1 7050
Protoss_Cybernetics_Core 1 8654
Protoss_Photon_Cannon 1 8830
Protoss_Stargate 1 10202
Protoss_Citadel_of_Adun 1 10124
10202
