Protoss_Gateway 2 8143
Protoss_Assimilator 1 3015
Protoss_Zealot 4 7208
Protoss_Cybernetics_Core 1 4065
Protoss_Stargate 1 5278
Protoss_Dragoon 1 5103
Protoss_Corsair 1 5978
Protoss_Citadel_of_Adun 1 6969
Protoss_Templar_Archives 1 8049
Protoss_Forge 1 8239
Protoss_Dark_Templar 2 8993
Protoss_High_Templar 2 10738
Protoss_Nexus 1 11495
Protoss_Photon_Cannon 1 10675
11495
