Protoss_Forge 1 2616
Protoss_Photon_Cannon 4 10042
Protoss_Nexus 1 5880
Protoss_Gateway 1 5624
Protoss_Assimilator 2 7230
Protoss_Zealot 4 8139
Protoss_Cybernetics_Core 1 7081
Protoss_Stargate 1 8303
Protoss_Citadel_of_Adun 1 8314
Protoss_Corsair 3 10248
Protoss_Robotics_Facility 1 9765
Protoss_Shuttle 1 10772
10772
