Protoss_Gateway 2 8273
Protoss_Assimilator 1 3075
Protoss_Zealot 3 4692
Protoss_Cybernetics_Core 1 5515
Protoss_Stargate 1 6668
Protoss_Citadel_of_Adun 1 6654
Protoss_Dragoon 1 6803
Protoss_Corsair 1 7358
Protoss_Templar_Archives 1 7949
Protoss_Forge 1 8290
Protoss_Dark_Templar 2 9118
Protoss_High_Templar 2 9870
Protoss_Nexus 1 11020
11020
