Protoss_Nexus 1 4373
Protoss_Forge 1 3548
Protoss_Photon_Cannon 5 10649
Protoss_Gateway 5 10521
Protoss_Assimilator 2 9039
Protoss_Zealot 13 10506
Protoss_Cybernetics_Core 1 6955
Protoss_Citadel_of_Adun 1 8018
Protoss_Dragoon 1 8478
Protoss_Templar_Archives 1 10053
10649
