Protoss_Gateway 2 3549
Protoss_Zealot 12 8650
Protoss_Assimilator 1 5490
Protoss_Cybernetics_Core 1 6993
Protoss_Forge 1 7454
Protoss_Dragoon 1 8048
Protoss_Photon_Cannon 3 10140
Protoss_Robotics_Facility 1 9637
Protoss_Citadel_of_Adun 1 9675
Protoss_Templar_Archives 1 10679
Protoss_Observatory 1 10392
10679
