Protoss_Forge 1 2618
Protoss_Nexus 1 5055
Protoss_Photon_Cannon 2 4855
Protoss_Gateway 4 9331
Protoss_Assimilator 2 7126
Protoss_Zealot 7 10223
Protoss_Cybernetics_Core 1 7577
Protoss_Citadel_of_Adun 1 8718
Protoss_Templar_Archives 1 9958
Protoss_Dragoon 1 10473
Protoss_Robotics_Facility 1 11126
11126
