Protoss_Nexus 1 4599
Protoss_Forge 1 3906
Protoss_Photon_Cannon 2 5147
Protoss_Gateway 3 7904
Protoss_Assimilator 2 6790
Protoss_Cybernetics_Core 1 6909
Protoss_Zealot 12 10333
Protoss_Citadel_of_Adun 1 8024
Protoss_Templar_Archives 1 9593
Protoss_Dark_Templar 2 10523
10523
