Protoss_Forge 1 2675
Protoss_Nexus 2 10645
Protoss_Photon_Cannon 3 10390
Protoss_Gateway 2 10012
Protoss_Assimilator 2 8005
Protoss_Zealot 3 9238
Protoss_Cybernetics_Core 1 6990
Protoss_Citadel_of_Adun 1 8059
Protoss_Dragoon 1 8000
Protoss_Templar_Archives 1 9188
Protoss_Dark_Templar 1 10028
10645
