Protoss_Nexus 1 4645
Protoss_Forge 1 3785
Protoss_Photon_Cannon 1 4635
Protoss_Gateway 3 7814
Protoss_Assimilator 2 9395
Protoss_Zealot 11 9999
Protoss_Cybernetics_Core 1 7136
Protoss_Dragoon 1 8063
Protoss_Citadel_of_Adun 1 8315
Protoss_Templar_Archives 1 9314
Protoss_Ground_Weapons_1 1 9836
9999
