Protoss_Forge 1 2986
Protoss_Photon_Cannon 4 10142
Protoss_Nexus 1 6132
Protoss_Gateway 2 9349
Protoss_Assimilator 2 8510
Protoss_Cybernetics_Core 1 7027
Protoss_Dragoon 1 7856
Protoss_Citadel_of_Adun 1 8137
Protoss_Zealot 3 9750
Protoss_Stargate 2 9997
Protoss_Templar_Archives 1 10299
10299
