Protoss_Gateway 1 2807
Protoss_Assimilator 1 3035
Protoss_Zealot 3 5173
Protoss_Cybernetics_Core 1 4969
Protoss_Dragoon 1 5925
Protoss_Stargate 1 6323
Protoss_Citadel_of_Adun 1 6674
Protoss_Corsair 1 7238
Protoss_Templar_Archives 1 7669
Protoss_Forge 1 8071
Protoss_Dark_Templar 1 8548
Protoss_Photon_Cannon 5 10740
Protoss_High_Templar 2 10100
Protoss_Nexus 1 10555
Psionic_Storm 1 9671
10740
