Protoss_Gateway 2 7428
Protoss_Assimilator 1 2991
Protoss_Zealot 7 9528
Protoss_Cybernetics_Core 1 5024
Protoss_Robotics_Facility 1 6552
Protoss_Dragoon 2 7083
Protoss_Robotics_Support_Bay 1 7511
Protoss_Shield_Battery 1 7627
9528
