Protoss_Nexus 2 8494
Protoss_Forge 2 8831
Protoss_Photon_Cannon 5 9962
Protoss_Gateway 3 5513
Protoss_Zealot 12 8971
Protoss_Assimilator 1 10183
Protoss_Cybernetics_Core 1 10857
10857
