Protoss_Forge 1 2715
Protoss_Nexus 1 5349
Protoss_Photon_Cannon 2 5295
Protoss_Gateway 2 6567
Protoss_Assimilator 1 7095
Protoss_Zealot 7 9633
Protoss_Cybernetics_Core 1 8595
9633
