Protoss_Gateway 1 2916
Protoss_Assimilator 1 3103
Protoss_Cybernetics_Core 1 3939
Protoss_Zealot 7 10012
Protoss_Stargate 1 5161
Protoss_Corsair 1 5844
Protoss_Scout 1 6583
Protoss_Dragoon 1 6452
Protoss_Nexus 1 10579
Protoss_Citadel_of_Adun 1 10057
10579
