Protoss_Gateway 4 10162
Protoss_Zealot 10 10524
Protoss_Assimilator 1 4060
Protoss_Forge 1 4348
Protoss_Nexus 1 7119
Protoss_Photon_Cannon 2 6754
Protoss_Cybernetics_Core 1 7559
Protoss_Citadel_of_Adun 1 8681
Protoss_Dragoon 1 8640
10524
