Protoss_Gateway 5 10377
Protoss_Zealot 14 10153
Protoss_Nexus 1 7484
Protoss_Forge 1 7342
Protoss_Assimilator 1 7417
Protoss_Photon_Cannon 2 8385
Protoss_Cybernetics_Core 1 8900
Protoss_Citadel_of_Adun 1 9920
Protoss_Stargate 1 10177
10377
