Protoss_Gateway 1 2875
Protoss_Assimilator 2 10450
Protoss_Zealot 3 5368
Protoss_Cybernetics_Core 1 4771
Protoss_Stargate 1 6297
Protoss_Dragoon 1 6213
Protoss_Citadel_of_Adun 1 6755
Protoss_Corsair 1 7013
Protoss_Forge 1 7361
Protoss_Templar_Archives 1 7754
Protoss_Photon_Cannon 4 10367
Protoss_Dark_Templar 1 8663
Protoss_Nexus 1 10170
Protoss_High_Templar 2 10580
10580
