Protoss_Forge 1 2689
Protoss_Photon_Cannon 4 10662
Protoss_Nexus 1 5533
Protoss_Gateway 4 9276
Protoss_Assimilator 2 9256
Protoss_Cybernetics_Core 1 6301
Protoss_Zealot 8 10448
Protoss_Citadel_of_Adun 1 8300
10662
