Protoss_Nexus 1 4776
Protoss_Gateway 4 8045
Protoss_Forge 1 4848
Protoss_Zealot 15 10144
Protoss_Assimilator 1 5306
Protoss_Photon_Cannon 1 5775
Protoss_Cybernetics_Core 1 6624
Protoss_Citadel_of_Adun 1 7857
10144
