Protoss_Forge 1 2867
Protoss_Photon_Cannon 2 9189
Protoss_Nexus 1 5705
Protoss_Gateway 1 5094
Protoss_Assimilator 1 5390
Protoss_Zealot 7 10125
Protoss_Cybernetics_Core 1 7599
Protoss_Stargate 1 8745
Protoss_Dragoon 1 8773
10125
