Protoss_Gateway 1 2747
Protoss_Assimilator 1 2812
Protoss_Cybernetics_Core 1 3948
Protoss_Zealot 5 8956
Protoss_Dragoon 1 4870
Protoss_Stargate 1 5708
Protoss_Corsair 1 6474
Protoss_Citadel_of_Adun 1 7708
Protoss_Templar_Archives 1 8811
Protoss_Forge 1 8883
Protoss_Dark_Templar 1 9708
Protoss_Photon_Cannon 1 9926
Protoss_High_Templar 1 10718
10718
