Protoss_Gateway 2 7627
Protoss_Assimilator 1 3098
Protoss_Zealot 11 9960
Protoss_Cybernetics_Core 1 5015
Protoss_Stargate 1 6331
Protoss_Dragoon 1 6564
Protoss_Citadel_of_Adun 1 7397
Protoss_Corsair 1 7424
Protoss_Templar_Archives 1 9329
Protoss_Forge 1 9588
Protoss_High_Templar 2 10182
Protoss_Photon_Cannon 3 10675
10675
