Protoss_Assimilator 1 2190
Protoss_Gateway 1 3289
Protoss_Cybernetics_Core 1 4307
Protoss_Stargate 1 5503
Protoss_Dragoon 2 6255
Protoss_Corsair 5 9515
Protoss_Forge 1 8296
9515
