Protoss_Nexus 1 4580
Protoss_Forge 1 3981
Protoss_Gateway 4 7549
Protoss_Assimilator 2 9101
Protoss_Photon_Cannon 2 10379
Protoss_Cybernetics_Core 1 6339
Protoss_Citadel_of_Adun 1 7359
Protoss_Zealot 11 9473
Protoss_Templar_Archives 1 9105
Protoss_High_Templar 2 10488
Protoss_Ground_Weapons_1 1 9971
10488
