Protoss_Forge 1 2959
Protoss_Photon_Cannon 5 10250
Protoss_Nexus 1 5796
Protoss_Gateway 3 8326
Protoss_Assimilator 2 7525
Protoss_Cybernetics_Core 1 6880
Protoss_Zealot 6 9758
Protoss_Citadel_of_Adun 1 8125
Protoss_Dragoon 1 8343
Protoss_Templar_Archives 1 9198
Protoss_Robotics_Facility 1 10316
Protoss_High_Templar 2 10048
10316
