Protoss_Forge 1 3115
Protoss_Photon_Cannon 6 10094
Protoss_Nexus 1 5779
Protoss_Gateway 2 10720
Protoss_Zealot 5 10098
Protoss_Assimilator 1 6330
Protoss_Cybernetics_Core 1 8303
Protoss_Citadel_of_Adun 1 9490
Protoss_Dragoon 1 9496
Protoss_Templar_Archives 1 10635
10720
