Protoss_Forge 1 2896
Protoss_Nexus 1 5495
Protoss_Photon_Cannon 3 10601
Protoss_Gateway 4 8378
Protoss_Assimilator 2 9322
Protoss_Cybernetics_Core 1 6481
Protoss_Zealot 13 10282
Protoss_Citadel_of_Adun 1 7524
Protoss_Templar_Archives 1 10145
10601
