Protoss_Forge 1 3453
Protoss_Photon_Cannon 6 10475
Protoss_Nexus 1 6635
Protoss_Assimilator 2 6724
Protoss_Gateway 3 10767
Protoss_Cybernetics_Core 1 7339
Protoss_Zealot 2 7645
Protoss_Citadel_of_Adun 1 8404
Protoss_Dragoon 1 8403
Protoss_Templar_Archives 1 9464
Protoss_High_Templar 2 10438
10767
