Protoss_Forge 1 2685
Protoss_Photon_Cannon 9 10280
Protoss_Nexus 1 5107
Protoss_Gateway 3 10798
Protoss_Assimilator 2 8193
Protoss_Zealot 3 7556
Protoss_Cybernetics_Core 1 7541
Protoss_Citadel_of_Adun 1 8678
Protoss_Templar_Archives 1 9886
10798
