Protoss_Forge 1 2750
Protoss_Nexus 1 5523
Protoss_Photon_Cannon 6 10605
Protoss_Assimilator 2 6645
Protoss_Gateway 3 9009
Protoss_Cybernetics_Core 1 7984
Protoss_Zealot 10 10317
Protoss_Citadel_of_Adun 1 9334
10605
