Protoss_Gateway 3 7575
Protoss_Assimilator 1 3140
Protoss_Zealot 3 4940
Protoss_Cybernetics_Core 1 4910
Protoss_Stargate 1 6146
Protoss_Dragoon 8 9358
Protoss_Corsair 1 6853
9358
