Protoss_Forge 1 2712
Protoss_Nexus 1 5195
Protoss_Photon_Cannon 4 9944
Protoss_Assimilator 2 6168
Protoss_Gateway 3 8841
Protoss_Zealot 7 9558
Protoss_Cybernetics_Core 1 7076
Protoss_Citadel_of_Adun 1 8204
Protoss_Templar_Archives 1 9566
Protoss_High_Templar 2 10628
10628
