Protoss_Forge 1 2990
Protoss_Photon_Cannon 6 5916
Protoss_Nexus 1 6896
Protoss_Gateway 4 10114
Protoss_Assimilator 1 6325
Protoss_Cybernetics_Core 1 7354
Protoss_Zealot 8 10300
Protoss_Dragoon 1 8476
Protoss_Citadel_of_Adun 1 9244
Protoss_Templar_Archives 1 10701
10701
