Protoss_Nexus 1 4615
Protoss_Forge 2 7900
Protoss_Photon_Cannon 5 10472
Protoss_Assimilator 2 6342
Protoss_Gateway 3 7876
Protoss_Cybernetics_Core 1 8841
Protoss_Zealot 6 9650
Protoss_Citadel_of_Adun 1 10029
Protoss_Robotics_Facility 1 10614
10614
