Protoss_Gateway 2 3567
Protoss_Zealot 11 9820
Protoss_Assimilator 1 4285
Protoss_Cybernetics_Core 1 5530
Protoss_Citadel_of_Adun 1 6703
Protoss_Templar_Archives 1 8036
Protoss_Forge 1 7985
Protoss_Photon_Cannon 2 9552
Protoss_High_Templar 4 10673
Protoss_Archon 1 9586
10673
