Protoss_Forge 1 3003
Protoss_Photon_Cannon 5 10745
Protoss_Nexus 1 5967
Protoss_Gateway 3 10085
Protoss_Zealot 4 10333
Protoss_Assimilator 2 8603
Protoss_Cybernetics_Core 1 9384
Protoss_Citadel_of_Adun 1 10515
10745
