Protoss_Forge 1 2790
Protoss_Nexus 1 5295
Protoss_Photon_Cannon 3 10017
Protoss_Gateway 4 9826
Protoss_Assimilator 2 6921
Protoss_Cybernetics_Core 1 6967
Protoss_Citadel_of_Adun 1 8024
Protoss_Robotics_Facility 1 9283
Protoss_Templar_Archives 1 9410
Protoss_Zealot 1 9928
Protoss_Observatory 1 9966
Protoss_High_Templar 2 10603
10603
