Protoss_Assimilator 1 2722
Protoss_Gateway 2 9128
Protoss_Cybernetics_Core 1 4219
Protoss_Dragoon 9 10473
Protoss_Robotics_Facility 1 5673
Protoss_Observatory 1 6339
Protoss_Observer 1 7028
Protoss_Shuttle 1 7947
Protoss_Forge 1 8730
Protoss_Shield_Battery 1 8879
Protoss_Photon_Cannon 1 9580
Protoss_Citadel_of_Adun 1 10620
10620
