Protoss_Gateway 4 9916
Protoss_Zealot 5 8483
Protoss_Forge 1 3790
Protoss_Photon_Cannon 2 5918
Protoss_Nexus 1 6880
Protoss_Assimilator 2 9073
Protoss_Cybernetics_Core 1 7398
Protoss_Citadel_of_Adun 1 8557
Protoss_Dragoon 1 9348
Protoss_Templar_Archives 1 10744
10744
