Protoss_Forge 1 2840
Protoss_Nexus 1 5145
Protoss_Gateway 4 9579
Protoss_Photon_Cannon 1 4896
Protoss_Assimilator 2 8057
Protoss_Zealot 10 10338
Protoss_Cybernetics_Core 1 6163
Protoss_Citadel_of_Adun 1 7283
Protoss_Dragoon 1 7653
Protoss_Templar_Archives 1 9297
Protoss_Robotics_Facility 1 10782
Protoss_High_Templar 2 10563
10782
