Protoss_Gateway 2 3719
Protoss_Zealot 9 9890
Protoss_Assimilator 1 4333
Protoss_Cybernetics_Core 1 5982
Protoss_Forge 1 6182
Protoss_Stargate 1 7170
Protoss_Dragoon 1 6978
Protoss_Citadel_of_Adun 1 7571
Protoss_Scout 1 8665
Protoss_Templar_Archives 1 10025
Protoss_Photon_Cannon 1 10525
10525
