Protoss_Forge 1 2797
Protoss_Photon_Cannon 2 4091
Protoss_Nexus 1 5818
Protoss_Gateway 1 5287
Protoss_Assimilator 2 7850
Protoss_Zealot 1 6033
Protoss_Cybernetics_Core 1 6658
7850
