Protoss_Gateway 1 2795
Protoss_Assimilator 1 3014
Protoss_Zealot 3 4912
Protoss_Cybernetics_Core 1 4993
Protoss_Stargate 1 6147
Protoss_Citadel_of_Adun 1 6388
Protoss_Dragoon 1 6596
Protoss_Corsair 1 6890
Protoss_Forge 1 7234
Protoss_Templar_Archives 1 7661
Protoss_Dark_Templar 1 8532
8532
