Protoss_Forge 1 2661
Protoss_Nexus 1 5145
Protoss_Photon_Cannon 7 10470
Protoss_Gateway 3 9919
Protoss_Zealot 6 9747
Protoss_Assimilator 2 10475
Protoss_Cybernetics_Core 1 7549
Protoss_Citadel_of_Adun 1 8764
Protoss_Templar_Archives 1 10465
10475
