Protoss_Forge 1 3384
Protoss_Nexus 1 5306
Protoss_Photon_Cannon 1 4392
Protoss_Gateway 3 8434
Protoss_Assimilator 2 9125
Protoss_Zealot 11 10293
Protoss_Cybernetics_Core 1 6916
Protoss_Citadel_of_Adun 1 7980
Protoss_Templar_Archives 1 9431
Protoss_Ground_Weapons_1 1 9606
Protoss_High_Templar 2 10502
10502
