Protoss_Forge 1 2784
Protoss_Photon_Cannon 3 10511
Protoss_Nexus 1 6358
Protoss_Gateway 4 9532
Protoss_Assimilator 2 8109
Protoss_Zealot 8 10028
Protoss_Cybernetics_Core 1 6926
Protoss_Citadel_of_Adun 1 8119
Protoss_Templar_Archives 1 10016
10511
