Protoss_Nexus 1 4706
Protoss_Gateway 2 9584
Protoss_Forge 1 4455
Protoss_Assimilator 2 6988
Protoss_Photon_Cannon 5 9691
Protoss_Zealot 5 10307
Protoss_Cybernetics_Core 1 6629
Protoss_Citadel_of_Adun 1 7722
Protoss_Stargate 1 8339
Protoss_Templar_Archives 1 9005
Protoss_Corsair 1 9163
Protoss_Ground_Weapons_1 1 9991
10307
