Protoss_Forge 1 2949
Protoss_Nexus 1 5309
Protoss_Gateway 4 9544
Protoss_Assimilator 2 7762
Protoss_Photon_Cannon 2 8765
Protoss_Zealot 7 10498
Protoss_Cybernetics_Core 1 6257
Protoss_Citadel_of_Adun 1 7329
Protoss_Templar_Archives 1 9174
Protoss_High_Templar 2 10320
Protoss_Dark_Templar 1 10283
10498
