Protoss_Forge 1 3123
Protoss_Photon_Cannon 2 9347
Protoss_Nexus 1 5540
Protoss_Assimilator 2 9796
Protoss_Gateway 4 8794
Protoss_Cybernetics_Core 1 6559
Protoss_Zealot 12 10188
Protoss_Citadel_of_Adun 1 7644
Protoss_Dragoon 1 7698
Protoss_Ground_Armor_1 1 9791
Protoss_Templar_Archives 1 10700
10700
