Protoss_Nexus 1 4672
Protoss_Gateway 1 4147
Protoss_Forge 1 4205
Protoss_Photon_Cannon 7 10653
Protoss_Assimilator 1 5071
Protoss_Zealot 7 10570
Protoss_Cybernetics_Core 1 6174
Protoss_Citadel_of_Adun 1 7247
Protoss_Templar_Archives 1 10164
10653
