Protoss_Forge 1 2533
Protoss_Nexus 1 4885
Protoss_Photon_Cannon 1 4160
Protoss_Gateway 6 9396
Protoss_Assimilator 1 5298
Protoss_Zealot 10 10308
Protoss_Cybernetics_Core 1 5882
Protoss_Stargate 1 7293
Protoss_Dragoon 3 10270
Protoss_Corsair 2 8345
Protoss_Citadel_of_Adun 1 9636
10308
