Protoss_Gateway 3 7398
Protoss_Zealot 18 10108
Protoss_Assimilator 1 4140
Protoss_Cybernetics_Core 1 4959
Protoss_Citadel_of_Adun 1 6295
Protoss_Dragoon 1 6193
Protoss_Templar_Archives 1 9470
10108
