Protoss_Nexus 1 4672
Protoss_Forge 1 3880
Protoss_Gateway 3 10275
Protoss_Photon_Cannon 8 10036
Protoss_Assimilator 2 7638
Protoss_Zealot 4 8248
Protoss_Cybernetics_Core 1 7224
Protoss_Citadel_of_Adun 1 8264
Protoss_Templar_Archives 1 9734
Protoss_High_Templar 2 10583
Protoss_Ground_Weapons_1 1 9916
10583
