Protoss_Nexus 1 4845
Protoss_Gateway 3 9759
Protoss_Forge 1 4390
Protoss_Photon_Cannon 6 10030
Protoss_Zealot 7 9503
Protoss_Assimilator 2 9013
Protoss_Cybernetics_Core 1 7792
Protoss_Stargate 1 9295
Protoss_Corsair 1 9988
Protoss_Dragoon 2 10618
Protoss_Citadel_of_Adun 1 10712
10712
