Protoss_Forge 2 10545
Protoss_Photon_Cannon 4 8678
Protoss_Nexus 1 5535
Protoss_Gateway 4 10423
Protoss_Assimilator 2 7490
Protoss_Zealot 1 6448
Protoss_Cybernetics_Core 1 7064
Protoss_Dragoon 2 9698
Protoss_Stargate 1 8363
Protoss_Robotics_Facility 2 10372
Protoss_Scout 1 9750
10545
