Protoss_Nexus 1 4727
Protoss_Forge 1 3795
Protoss_Photon_Cannon 4 10406
Protoss_Gateway 4 9254
Protoss_Assimilator 2 7500
Protoss_Zealot 8 10033
Protoss_Cybernetics_Core 1 6939
Protoss_Dragoon 1 7833
Protoss_Citadel_of_Adun 1 8636
Protoss_Templar_Archives 1 9699
Protoss_Dark_Templar 1 10683
10683
