Protoss_Gateway 2 3429
Protoss_Zealot 9 8863
Protoss_Assimilator 2 9955
Protoss_Forge 1 6067
Protoss_Cybernetics_Core 1 6886
Protoss_Citadel_of_Adun 1 7940
Protoss_Nexus 1 9629
Protoss_Photon_Cannon 3 10494
Protoss_Templar_Archives 1 9559
Protoss_High_Templar 2 10443
10494
