Protoss_Forge 1 3000
Protoss_Photon_Cannon 5 10490
Protoss_Nexus 1 5920
Protoss_Gateway 4 9064
Protoss_Assimilator 2 8591
Protoss_Zealot 9 10453
Protoss_Cybernetics_Core 1 7626
Protoss_Citadel_of_Adun 1 9367
Protoss_Dragoon 1 9938
10490
