Protoss_Forge 1 2670
Protoss_Nexus 1 5030
Protoss_Photon_Cannon 4 10355
Protoss_Gateway 3 8236
Protoss_Assimilator 2 8233
Protoss_Zealot 7 9850
Protoss_Cybernetics_Core 1 6774
Protoss_Citadel_of_Adun 1 7869
Protoss_Templar_Archives 1 9296
Protoss_High_Templar 3 10602
10602
