Protoss_Gateway 2 3553
Protoss_Zealot 12 9608
Protoss_Assimilator 1 4287
Protoss_Cybernetics_Core 1 5848
Protoss_Dragoon 1 6778
Protoss_Stargate 1 7228
Protoss_Citadel_of_Adun 1 7811
Protoss_Corsair 1 8033
Protoss_Forge 1 9255
Protoss_Templar_Archives 1 10155
10155
