Protoss_Nexus 1 4600
Protoss_Gateway 4 8277
Protoss_Forge 1 4285
Protoss_Assimilator 2 9212
Protoss_Photon_Cannon 1 5174
Protoss_Zealot 14 10354
Protoss_Cybernetics_Core 1 5858
Protoss_Citadel_of_Adun 1 6974
Protoss_Templar_Archives 1 8991
Protoss_High_Templar 2 10070
Protoss_Ground_Weapons_1 1 9557
Protoss_Robotics_Facility 1 11128
11128
