Protoss_Forge 1 3119
Protoss_Photon_Cannon 4 7226
Protoss_Nexus 1 5903
Protoss_Gateway 3 9504
Protoss_Zealot 7 10578
Protoss_Assimilator 2 9350
Protoss_Cybernetics_Core 1 9165
Protoss_Citadel_of_Adun 1 10330
Protoss_Dragoon 2 10643
10643
