Protoss_Nexus 1 4579
Protoss_Gateway 2 9344
Protoss_Forge 1 4320
Protoss_Photon_Cannon 5 10640
Protoss_Assimilator 2 6310
Protoss_Cybernetics_Core 1 6127
Protoss_Zealot 5 9600
Protoss_Stargate 2 8664
Protoss_Citadel_of_Adun 1 7571
Protoss_Corsair 6 10270
Protoss_Shield_Battery 1 10084
10640
