Protoss_Forge 1 2787
Protoss_Nexus 1 5192
Protoss_Gateway 4 9184
Protoss_Photon_Cannon 2 5278
Protoss_Assimilator 2 7710
Protoss_Cybernetics_Core 1 6207
Protoss_Zealot 7 10548
Protoss_Citadel_of_Adun 1 7801
Protoss_Templar_Archives 1 8866
Protoss_High_Templar 4 10378
Protoss_Archon 1 10164
10548
