Protoss_Gateway 1 2919
Protoss_Assimilator 2 4360
Protoss_Zealot 7 10030
Protoss_Cybernetics_Core 1 5454
Protoss_Stargate 1 6869
Protoss_Dragoon 1 6708
Protoss_Citadel_of_Adun 1 7057
Protoss_Forge 1 9670
10030
