Protoss_Forge 1 2633
Protoss_Photon_Cannon 2 5330
Protoss_Nexus 1 5632
Protoss_Gateway 6 9837
Protoss_Assimilator 1 5357
Protoss_Cybernetics_Core 1 6382
Protoss_Zealot 12 10478
Protoss_Citadel_of_Adun 1 7581
Protoss_Dragoon 1 8303
Protoss_Templar_Archives 1 10334
10478
