Protoss_Nexus 1 4828
Protoss_Forge 1 4153
Protoss_Photon_Cannon 5 6725
Protoss_Gateway 4 10289
Protoss_Assimilator 2 8569
Protoss_Zealot 8 10508
Protoss_Cybernetics_Core 1 8796
Protoss_Stargate 1 9943
Protoss_Citadel_of_Adun 1 10114
10508
