Protoss_Gateway 1 2710
Protoss_Assimilator 1 3218
Protoss_Zealot 3 5540
Protoss_Cybernetics_Core 1 4889
Protoss_Stargate 1 6343
Protoss_Dragoon 1 6338
Protoss_Corsair 2 7720
7720
