Protoss_Assimilator 2 5377
Protoss_Gateway 1 3220
Protoss_Cybernetics_Core 1 4247
Protoss_Stargate 3 10351
Protoss_Corsair 10 10307
Protoss_Dragoon 1 6273
Protoss_Forge 1 7991
Protoss_Shield_Battery 1 7923
Protoss_Photon_Cannon 1 8835
Protoss_Air_Weapons_1 1 8366
10351
