Protoss_Forge 2 9680
Protoss_Nexus 1 5130
Protoss_Photon_Cannon 1 4735
Protoss_Gateway 4 8364
Protoss_Assimilator 2 6710
Protoss_Zealot 13 10533
Protoss_Cybernetics_Core 1 6641
Protoss_Citadel_of_Adun 1 7660
10533
