Protoss_Nexus 1 4613
Protoss_Forge 1 3876
Protoss_Photon_Cannon 7 10410
Protoss_Gateway 2 10020
Protoss_Assimilator 2 8189
Protoss_Zealot 7 9912
Protoss_Cybernetics_Core 1 7236
Protoss_Stargate 1 8397
Protoss_Citadel_of_Adun 1 9155
Protoss_Corsair 2 10512
10512
