Protoss_Forge 2 10531
Protoss_Nexus 1 5315
Protoss_Photon_Cannon 3 10127
Protoss_Assimilator 1 4937
Protoss_Gateway 4 10155
Protoss_Zealot 7 9557
Protoss_Cybernetics_Core 1 6846
Protoss_Dragoon 1 7735
Protoss_Citadel_of_Adun 1 7949
Protoss_Ground_Weapons_1 1 9711
10531
