Protoss_Gateway 2 3285
Protoss_Zealot 7 8033
Protoss_Nexus 1 7080
Protoss_Assimilator 2 10085
Protoss_Forge 1 6450
Protoss_Cybernetics_Core 1 7064
Protoss_Stargate 1 8340
Protoss_Photon_Cannon 3 10275
Protoss_Corsair 2 10198
Protoss_Citadel_of_Adun 1 9504
10275
