Protoss_Forge 1 3488
Protoss_Nexus 1 5292
Protoss_Photon_Cannon 4 9120
Protoss_Gateway 2 8689
Protoss_Assimilator 2 6797
Protoss_Cybernetics_Core 1 6466
Protoss_Zealot 1 6432
Protoss_Stargate 1 7633
Protoss_Citadel_of_Adun 1 7765
Protoss_Templar_Archives 1 8783
Protoss_Corsair 3 10074
Protoss_Dark_Templar 4 10598
Protoss_Robotics_Facility 1 10551
10598
