Protoss_Forge 1 2965
Protoss_Photon_Cannon 5 10497
Protoss_Nexus 1 5695
Protoss_Gateway 2 8710
Protoss_Assimilator 2 8644
Protoss_Zealot 5 8948
Protoss_Cybernetics_Core 1 6544
Protoss_Citadel_of_Adun 1 7752
Protoss_Templar_Archives 1 9034
Protoss_Dark_Templar 2 9998
10497
