Protoss_Forge 1 2910
Protoss_Nexus 1 5025
Protoss_Photon_Cannon 6 10475
Protoss_Gateway 2 9306
Protoss_Assimilator 2 8328
Protoss_Zealot 3 8792
Protoss_Cybernetics_Core 1 7102
Protoss_Dragoon 1 8020
Protoss_Citadel_of_Adun 1 8225
Protoss_Templar_Archives 1 9232
Protoss_Dark_Templar 1 10062
Protoss_High_Templar 1 10136
10475
