Protoss_Nexus 1 4713
Protoss_Forge 2 9805
Protoss_Gateway 3 9050
Protoss_Photon_Cannon 8 10740
Protoss_Assimilator 2 6904
Protoss_Cybernetics_Core 1 6395
Protoss_Zealot 3 9038
Protoss_Stargate 1 7618
Protoss_Dragoon 1 7364
Protoss_Citadel_of_Adun 1 8191
Protoss_Corsair 2 9162
Protoss_Templar_Archives 1 9207
Protoss_Robotics_Facility 1 10474
Protoss_Dark_Templar 3 10364
10740
