Protoss_Nexus 1 4765
Protoss_Gateway 3 7664
Protoss_Assimilator 2 8430
Protoss_Cybernetics_Core 1 5564
Protoss_Forge 1 5500
Protoss_Photon_Cannon 1 6420
Protoss_Citadel_of_Adun 1 6959
Protoss_Zealot 13 10298
Protoss_Templar_Archives 1 9518
Protoss_Ground_Weapons_1 1 9586
10298
