Protoss_Forge 1 2922
Protoss_Photon_Cannon 4 9875
Protoss_Nexus 1 5955
Protoss_Gateway 2 9184
Protoss_Assimilator 2 6561
Protoss_Cybernetics_Core 1 6362
Protoss_Zealot 2 8238
Protoss_Dragoon 1 7308
Protoss_Stargate 1 7808
Protoss_Citadel_of_Adun 1 8294
Protoss_Corsair 2 9095
Protoss_Templar_Archives 1 9539
Protoss_Dark_Templar 2 10718
10718
