Protoss_Forge 1 2749
Protoss_Photon_Cannon 4 8816
Protoss_Nexus 1 6266
Protoss_Gateway 3 10276
Protoss_Assimilator 2 8900
Protoss_Cybernetics_Core 1 6755
Protoss_Zealot 7 9534
Protoss_Citadel_of_Adun 1 7791
Protoss_Templar_Archives 1 9669
Protoss_High_Templar 2 10530
10530
