Protoss_Forge 1 3549
Protoss_Nexus 1 5280
Protoss_Photon_Cannon 5 10255
Protoss_Gateway 3 10259
Protoss_Assimilator 2 7591
Protoss_Zealot 3 8720
Protoss_Cybernetics_Core 1 7068
Protoss_Dragoon 1 8118
Protoss_Citadel_of_Adun 1 8554
10259
