Protoss_Forge 1 3050
Protoss_Nexus 1 5036
Protoss_Photon_Cannon 8 10341
Protoss_Gateway 3 10134
Protoss_Assimilator 2 7787
Protoss_Cybernetics_Core 1 6444
Protoss_Zealot 2 8208
Protoss_Dragoon 1 7448
Protoss_Citadel_of_Adun 1 7854
Protoss_Templar_Archives 1 9414
Protoss_High_Templar 2 10463
10463
