Protoss_Forge 1 2789
Protoss_Nexus 1 5120
Protoss_Gateway 2 10136
Protoss_Assimilator 2 6865
Protoss_Photon_Cannon 4 8510
Protoss_Cybernetics_Core 1 6232
Protoss_Zealot 3 9918
Protoss_Dragoon 1 7398
Protoss_Citadel_of_Adun 1 7626
10136
