Protoss_Forge 1 2686
Protoss_Nexus 1 5043
Protoss_Photon_Cannon 3 9158
Protoss_Gateway 5 9807
Protoss_Assimilator 2 8812
Protoss_Zealot 7 9862
Protoss_Cybernetics_Core 1 7839
Protoss_Dragoon 1 9260
Protoss_Citadel_of_Adun 1 9590
9862
