Protoss_Forge 1 2635
Protoss_Photon_Cannon 3 10050
Protoss_Nexus 1 5779
Protoss_Gateway 3 9244
Protoss_Assimilator 2 7753
Protoss_Zealot 9 10193
Protoss_Cybernetics_Core 1 6844
Protoss_Citadel_of_Adun 1 7969
Protoss_Templar_Archives 1 9434
10193
