Protoss_Forge 1 2925
Protoss_Photon_Cannon 2 9123
Protoss_Nexus 1 5691
Protoss_Gateway 3 9529
Protoss_Assimilator 2 6696
Protoss_Cybernetics_Core 1 6343
Protoss_Zealot 1 6392
Protoss_Stargate 1 7509
Protoss_Citadel_of_Adun 1 7997
Protoss_Corsair 2 8798
Protoss_Templar_Archives 1 9092
Protoss_Dark_Templar 1 10054
Protoss_High_Templar 2 10478
Protoss_Robotics_Facility 1 11164
11164
