Protoss_Forge 1 2712
Protoss_Nexus 1 5094
Protoss_Gateway 4 9729
Protoss_Assimilator 2 9771
Protoss_Photon_Cannon 1 5718
Protoss_Zealot 9 9946
Protoss_Cybernetics_Core 1 6695
Protoss_Dragoon 1 7534
Protoss_Citadel_of_Adun 1 7737
Protoss_Templar_Archives 1 10008
10008
