Protoss_Forge 1 2482
Protoss_Photon_Cannon 3 5428
Protoss_Nexus 1 5847
Protoss_Assimilator 2 9790
Protoss_Gateway 3 8441
Protoss_Zealot 11 10580
Protoss_Cybernetics_Core 1 7839
Protoss_Citadel_of_Adun 1 8864
Protoss_Dragoon 1 8774
Protoss_Templar_Archives 1 10309
10580
