Protoss_Gateway 1 2836
Protoss_Assimilator 1 3384
Protoss_Zealot 5 7748
Protoss_Cybernetics_Core 1 4334
Protoss_Stargate 1 6068
Protoss_Citadel_of_Adun 1 6412
Protoss_Corsair 1 6858
7748
