Protoss_Forge 1 2873
Protoss_Nexus 1 5292
Protoss_Gateway 4 10380
Protoss_Photon_Cannon 2 10007
Protoss_Assimilator 2 8776
Protoss_Zealot 10 10363
Protoss_Cybernetics_Core 1 6094
Protoss_Citadel_of_Adun 1 7169
Protoss_Dragoon 1 9068
Protoss_Templar_Archives 1 10440
Protoss_Ground_Weapons_1 1 9726
10440
