Protoss_Forge 1 2847
Protoss_Nexus 1 5290
Protoss_Photon_Cannon 2 9644
Protoss_Gateway 1 5296
Protoss_Assimilator 2 7589
Protoss_Cybernetics_Core 1 6630
Protoss_Zealot 3 8973
Protoss_Robotics_Facility 1 8117
Protoss_Stargate 1 8258
Protoss_Dragoon 1 8283
Protoss_Shuttle 1 9282
Protoss_Corsair 3 10318
Protoss_Robotics_Support_Bay 1 9416
Protoss_Reaver 1 10756
10756
