Protoss_Forge 1 2742
Protoss_Photon_Cannon 2 8862
Protoss_Nexus 1 5524
Protoss_Gateway 3 10179
Protoss_Assimilator 2 9016
Protoss_Zealot 3 9663
Protoss_Cybernetics_Core 1 8204
Protoss_Stargate 1 9592
Protoss_Citadel_of_Adun 1 9758
Protoss_Templar_Archives 1 10839
10839
