Protoss_Forge 1 2611
Protoss_Photon_Cannon 2 4926
Protoss_Nexus 1 5588
Protoss_Gateway 3 9249
Protoss_Assimilator 2 7493
Protoss_Zealot 7 10508
Protoss_Cybernetics_Core 1 6887
Protoss_Stargate 1 8550
Protoss_Citadel_of_Adun 1 8933
Protoss_Corsair 2 9864
Protoss_Templar_Archives 1 9933
10508
