Protoss_Forge 1 2933
Protoss_Nexus 1 5145
Protoss_Gateway 3 9305
Protoss_Assimilator 2 6486
Protoss_Photon_Cannon 4 10473
Protoss_Cybernetics_Core 1 6015
Protoss_Zealot 1 6158
Protoss_Dragoon 1 6886
Protoss_Stargate 1 7295
Protoss_Citadel_of_Adun 1 7773
Protoss_Corsair 2 8624
10473
