Protoss_Gateway 2 4381
Protoss_Assimilator 1 2985
Protoss_Cybernetics_Core 1 3934
Protoss_Stargate 1 5395
Protoss_Zealot 10 10543
Protoss_Citadel_of_Adun 1 6270
Protoss_Corsair 1 6188
Protoss_Templar_Archives 1 7464
Protoss_Robotics_Facility 1 8403
Protoss_Dark_Templar 2 8338
Protoss_Forge 1 8295
Protoss_Nexus 1 10704
Protoss_Photon_Cannon 1 10130
10704
