Protoss_Gateway 2 3370
Protoss_Zealot 9 10346
Protoss_Nexus 2 7879
Protoss_Forge 1 7104
Protoss_Photon_Cannon 2 8461
Protoss_Assimilator 2 9576
Protoss_Cybernetics_Core 1 9423
Protoss_Stargate 1 10686
10686
