Protoss_Gateway 2 10118
Protoss_Assimilator 1 3148
Protoss_Zealot 2 4833
Protoss_Cybernetics_Core 1 4792
Protoss_Stargate 1 6090
Protoss_Dragoon 1 6203
Protoss_Corsair 1 6788
Protoss_Citadel_of_Adun 1 7264
Protoss_Forge 1 7653
Protoss_Templar_Archives 1 8914
Protoss_Photon_Cannon 1 9110
Protoss_Nexus 1 11169
Protoss_Dark_Templar 1 10138
11169
