Protoss_Forge 1 2781
Protoss_Photon_Cannon 4 10542
Protoss_Nexus 1 5700
Protoss_Gateway 4 9433
Protoss_Assimilator 2 8134
Protoss_Cybernetics_Core 1 6688
Protoss_Zealot 2 8750
Protoss_Citadel_of_Adun 1 8064
Protoss_Templar_Archives 1 9231
Protoss_High_Templar 4 10478
10542
