Protoss_Gateway 3 10670
Protoss_Forge 1 3493
Protoss_Zealot 9 10403
Protoss_Photon_Cannon 2 7684
Protoss_Nexus 1 6776
Protoss_Assimilator 2 7661
Protoss_Cybernetics_Core 1 6859
Protoss_Stargate 1 8253
Protoss_Corsair 2 9793
Protoss_Citadel_of_Adun 1 9837
10670
