Protoss_Forge 1 2795
Protoss_Nexus 1 5480
Protoss_Gateway 4 8419
Protoss_Photon_Cannon 1 4850
Protoss_Assimilator 2 8571
Protoss_Zealot 11 9883
Protoss_Cybernetics_Core 1 6401
Protoss_Citadel_of_Adun 1 7536
Protoss_Templar_Archives 1 9888
Protoss_Ground_Weapons_1 1 9981
9981
