Protoss_Forge 1 2652
Protoss_Photon_Cannon 5 10565
Protoss_Nexus 2 9985
Protoss_Gateway 1 5249
Protoss_Zealot 5 10005
Protoss_Cybernetics_Core 1 6516
Protoss_Assimilator 2 9000
Protoss_Citadel_of_Adun 1 9586
Protoss_Stargate 1 10817
10817
