Protoss_Gateway 3 9744
Protoss_Assimilator 1 3060
Protoss_Zealot 3 7617
Protoss_Cybernetics_Core 1 4622
Protoss_Dragoon 7 10583
Protoss_Citadel_of_Adun 1 6647
Protoss_Robotics_Facility 1 7203
Protoss_Shuttle 1 8192
Protoss_Robotics_Support_Bay 1 7767
Protoss_Reaver 1 9243
10583
