Protoss_Gateway 2 3493
Protoss_Zealot 16 10260
Protoss_Assimilator 1 3980
Protoss_Cybernetics_Core 1 5479
Protoss_Stargate 1 6623
Protoss_Dragoon 1 6373
Protoss_Corsair 1 7373
Protoss_Nexus 1 10800
Protoss_Forge 1 10281
10800
