Protoss_Nexus 1 4905
Protoss_Forge 1 4000
Protoss_Gateway 6 10618
Protoss_Photon_Cannon 2 10509
Protoss_Assimilator 2 7351
Protoss_Zealot 10 10500
Protoss_Cybernetics_Core 1 6746
Protoss_Citadel_of_Adun 1 8025
Protoss_Templar_Archives 1 9591
Protoss_Dark_Templar 1 10638
10638
