Protoss_Forge 1 3119
Protoss_Nexus 1 5187
Protoss_Gateway 4 8359
Protoss_Assimilator 2 9308
Protoss_Photon_Cannon 1 5281
Protoss_Zealot 16 10368
Protoss_Cybernetics_Core 1 6345
Protoss_Citadel_of_Adun 1 7396
Protoss_Ground_Weapons_1 1 9871
10368
