Protoss_Gateway 1 2954
Protoss_Assimilator 1 3157
Protoss_Zealot 2 5013
Protoss_Cybernetics_Core 1 4956
Protoss_Citadel_of_Adun 1 6214
Protoss_Dragoon 1 6208
Protoss_Forge 1 6816
Protoss_Templar_Archives 1 7374
Protoss_Photon_Cannon 3 10620
Protoss_High_Templar 3 10346
Protoss_Nexus 1 11147
11147
