Protoss_Forge 1 3102
Protoss_Photon_Cannon 2 4775
Protoss_Nexus 1 5337
Protoss_Gateway 1 5245
Protoss_Assimilator 2 7012
Protoss_Zealot 4 10414
Protoss_Cybernetics_Core 1 6523
Protoss_Dragoon 1 7450
Protoss_Stargate 1 7974
10414
