Protoss_Forge 1 3241
Protoss_Nexus 1 5187
Protoss_Photon_Cannon 2 9706
Protoss_Gateway 2 10189
Protoss_Assimilator 2 7798
Protoss_Zealot 4 9262
Protoss_Cybernetics_Core 1 7200
Protoss_Dragoon 1 8058
Protoss_Stargate 1 8461
Protoss_Citadel_of_Adun 1 8978
Protoss_Corsair 2 10022
Protoss_Templar_Archives 1 10112
10189
