Protoss_Forge 1 3125
Protoss_Nexus 1 5225
Protoss_Photon_Cannon 4 10747
Protoss_Gateway 3 9124
Protoss_Assimilator 2 9266
Protoss_Zealot 8 9860
Protoss_Cybernetics_Core 1 6877
Protoss_Citadel_of_Adun 1 7934
Protoss_Dragoon 1 7788
Protoss_Templar_Archives 1 9724
10747
