Protoss_Forge 1 2857
Protoss_Photon_Cannon 2 4899
Protoss_Nexus 1 5510
Protoss_Gateway 4 9242
Protoss_Assimilator 2 9985
Protoss_Zealot 9 10413
Protoss_Cybernetics_Core 1 6616
Protoss_Citadel_of_Adun 1 7718
Protoss_Dragoon 1 8535
Protoss_Templar_Archives 1 10267
10413
