Protoss_Forge 1 3002
Protoss_Nexus 1 5379
Protoss_Photon_Cannon 5 10350
Protoss_Gateway 2 10114
Protoss_Assimilator 2 7372
Protoss_Zealot 2 9814
Protoss_Cybernetics_Core 1 6346
Protoss_Stargate 1 7636
Protoss_Robotics_Facility 1 8599
Protoss_Corsair 3 9594
Protoss_Citadel_of_Adun 1 9088
Protoss_Templar_Archives 1 10258
10350
