Protoss_Forge 1 2492
Protoss_Photon_Cannon 6 7506
Protoss_Nexus 1 7175
Protoss_Gateway 1 6724
Protoss_Assimilator 2 9172
Protoss_Zealot 4 9380
Protoss_Cybernetics_Core 1 8165
Protoss_Stargate 1 9441
Protoss_Citadel_of_Adun 1 10171
10171
