Protoss_Gateway 2 6788
Protoss_Zealot 12 9329
Protoss_Assimilator 1 3680
Protoss_Cybernetics_Core 1 4851
Protoss_Dragoon 1 5968
Protoss_Citadel_of_Adun 1 6290
Protoss_Templar_Archives 1 9182
Protoss_Dark_Templar 2 10433
Protoss_Forge 1 10400
10433
