Protoss_Forge 1 2834
Protoss_Photon_Cannon 5 10103
Protoss_Nexus 1 5613
Protoss_Gateway 4 10667
Protoss_Assimilator 2 7483
Protoss_Zealot 5 9078
Protoss_Cybernetics_Core 1 6667
Protoss_Citadel_of_Adun 1 7682
Protoss_Templar_Archives 1 8752
Protoss_High_Templar 5 10654
10667
