Protoss_Nexus 1 4985
Protoss_Forge 1 4320
Protoss_Gateway 3 8499
Protoss_Photon_Cannon 4 9595
Protoss_Assimilator 2 7190
Protoss_Cybernetics_Core 1 6468
Protoss_Zealot 6 9793
Protoss_Stargate 1 7723
Protoss_Citadel_of_Adun 1 8025
Protoss_Corsair 3 10273
Protoss_Templar_Archives 1 10276
10276
