Protoss_Forge 1 2789
Protoss_Nexus 2 11616
Protoss_Gateway 4 8715
Protoss_Photon_Cannon 1 4930
Protoss_Assimilator 2 8610
Protoss_Cybernetics_Core 1 6157
Protoss_Zealot 8 9623
Protoss_Dragoon 1 7068
Protoss_Citadel_of_Adun 1 7644
Protoss_Templar_Archives 1 9470
Protoss_High_Templar 2 10683
Protoss_Ground_Weapons_1 1 9961
11616
