Protoss_Forge 1 2468
Protoss_Nexus 1 4880
Protoss_Photon_Cannon 9 9896
Protoss_Gateway 1 5524
Protoss_Assimilator 2 7558
Protoss_Zealot 4 9272
Protoss_Cybernetics_Core 1 7001
Protoss_Dragoon 1 10024
10024
