Protoss_Gateway 2 2990
Protoss_Zealot 5 9160
Protoss_Assimilator 1 4479
Protoss_Cybernetics_Core 1 5277
Protoss_Dragoon 1 6110
Protoss_Forge 1 6256
Protoss_Robotics_Facility 1 7307
Protoss_Photon_Cannon 3 9878
Protoss_Shuttle 1 8291
Protoss_Robotics_Support_Bay 1 7977
Protoss_Reaver 1 9342
Protoss_Stargate 1 9415
Protoss_Corsair 1 10096
10096
