Protoss_Forge 1 2970
Protoss_Photon_Cannon 3 10644
Protoss_Nexus 1 5591
Protoss_Gateway 3 8935
Protoss_Assimilator 2 7633
Protoss_Zealot 9 9858
Protoss_Cybernetics_Core 1 6161
Protoss_Citadel_of_Adun 1 7388
Protoss_Templar_Archives 1 8651
Protoss_Dark_Templar 1 10602
Protoss_High_Templar 2 10610
Protoss_Ground_Weapons_1 1 9993
10644
