Protoss_Forge 1 3694
Protoss_Nexus 1 5415
Protoss_Photon_Cannon 7 10580
Protoss_Gateway 1 6340
Protoss_Assimilator 2 7472
Protoss_Cybernetics_Core 1 7345
Protoss_Zealot 4 10240
Protoss_Stargate 1 8552
Protoss_Citadel_of_Adun 1 9658
Protoss_Corsair 2 10056
Protoss_Templar_Archives 1 10727
10727
