Protoss_Nexus 1 5041
Protoss_Forge 1 4142
Protoss_Gateway 3 8465
Protoss_Photon_Cannon 1 4994
Protoss_Assimilator 2 6858
Protoss_Cybernetics_Core 1 6041
Protoss_Zealot 2 7378
Protoss_Stargate 1 7190
Protoss_Citadel_of_Adun 1 7483
Protoss_Corsair 2 8510
Protoss_Templar_Archives 1 8618
Protoss_Dark_Templar 3 9470
Protoss_Robotics_Facility 1 10457
10457
