Protoss_Gateway 3 10822
Protoss_Assimilator 1 3139
Protoss_Cybernetics_Core 1 4051
Protoss_Zealot 7 10026
Protoss_Stargate 1 5437
Protoss_Corsair 2 6932
Protoss_Citadel_of_Adun 1 6845
10822
