Protoss_Forge 1 3075
Protoss_Nexus 1 5225
Protoss_Photon_Cannon 2 5980
Protoss_Gateway 4 9640
Protoss_Assimilator 2 8134
Protoss_Zealot 7 10273
Protoss_Cybernetics_Core 1 7302
Protoss_Stargate 1 8510
Protoss_Citadel_of_Adun 1 8935
Protoss_Corsair 3 10407
Protoss_Templar_Archives 1 10291
10407
