Protoss_Forge 1 2906
Protoss_Nexus 1 4975
Protoss_Photon_Cannon 3 10441
Protoss_Gateway 4 10710
Protoss_Assimilator 2 8787
Protoss_Zealot 12 10062
Protoss_Cybernetics_Core 1 7787
Protoss_Citadel_of_Adun 1 8851
Protoss_Templar_Archives 1 10505
Protoss_Robotics_Facility 1 10935
10935
