Protoss_Forge 1 2496
Protoss_Nexus 1 4931
Protoss_Photon_Cannon 4 10443
Protoss_Gateway 4 8322
Protoss_Assimilator 2 8522
Protoss_Cybernetics_Core 1 6592
Protoss_Zealot 11 9836
Protoss_Citadel_of_Adun 1 7631
Protoss_Dragoon 1 7532
Protoss_Templar_Archives 1 9348
Protoss_High_Templar 2 10250
10443
