Protoss_Forge 1 3086
Protoss_Photon_Cannon 4 8974
Protoss_Nexus 1 5513
Protoss_Gateway 3 10863
Protoss_Zealot 6 10444
Protoss_Assimilator 2 7384
Protoss_Cybernetics_Core 1 7753
Protoss_Stargate 1 8966
Protoss_Citadel_of_Adun 1 9404
Protoss_Corsair 1 9660
Protoss_Robotics_Facility 1 10794
10863
