Protoss_Nexus 1 4869
Protoss_Forge 1 4005
Protoss_Photon_Cannon 3 5655
Protoss_Gateway 6 9531
Protoss_Assimilator 1 5967
Protoss_Cybernetics_Core 1 6887
Protoss_Zealot 9 10273
Protoss_Citadel_of_Adun 1 7995
Protoss_Stargate 1 9318
Protoss_Templar_Archives 1 10664
10664
