Protoss_Gateway 2 3095
Protoss_Zealot 9 9620
Protoss_Assimilator 2 6855
Protoss_Nexus 1 7403
Protoss_Forge 1 6595
Protoss_Cybernetics_Core 1 7963
Protoss_Photon_Cannon 2 8502
Protoss_Citadel_of_Adun 1 9537
Protoss_Templar_Archives 1 10569
10569
