Protoss_Gateway 1 2979
Protoss_Assimilator 1 3250
Protoss_Zealot 4 7813
Protoss_Cybernetics_Core 1 4929
Protoss_Stargate 1 6113
Protoss_Dragoon 1 6218
Protoss_Corsair 1 6803
Protoss_Citadel_of_Adun 1 7616
Protoss_Templar_Archives 1 8674
Protoss_Nexus 1 10519
Protoss_Dark_Templar 2 10445
10519
