Protoss_Forge 1 3141
Protoss_Photon_Cannon 1 4069
Protoss_Nexus 1 5273
Protoss_Gateway 5 8794
Protoss_Assimilator 2 8933
Protoss_Cybernetics_Core 1 6213
Protoss_Zealot 14 10540
Protoss_Citadel_of_Adun 1 7336
Protoss_Dragoon 1 7582
Protoss_Templar_Archives 1 10269
Protoss_Ground_Weapons_1 1 9811
10540
