Protoss_Gateway 2 3219
Protoss_Zealot 12 10173
Protoss_Assimilator 1 5245
Protoss_Cybernetics_Core 1 6501
Protoss_Dragoon 2 8493
Protoss_Citadel_of_Adun 1 7990
Protoss_Forge 1 7873
10173
