Protoss_Forge 1 2606
Protoss_Photon_Cannon 9 10455
Protoss_Nexus 1 5755
Protoss_Gateway 3 9823
Protoss_Assimilator 2 8735
Protoss_Cybernetics_Core 1 6631
Protoss_Zealot 3 8698
Protoss_Citadel_of_Adun 1 7638
Protoss_Templar_Archives 1 9278
Protoss_High_Templar 2 10693
10693
