Protoss_Gateway 2 3389
Protoss_Zealot 9 7990
Protoss_Nexus 1 7550
Protoss_Assimilator 2 9854
Protoss_Cybernetics_Core 1 7149
Protoss_Forge 1 7726
Protoss_Photon_Cannon 1 8576
Protoss_Citadel_of_Adun 1 9455
Protoss_Dragoon 2 10088
10088
