Protoss_Nexus 2 11686
Protoss_Forge 1 3820
Protoss_Photon_Cannon 2 4995
Protoss_Gateway 1 5379
Protoss_Assimilator 2 6785
Protoss_Cybernetics_Core 1 6574
Protoss_Robotics_Facility 1 7957
Protoss_Stargate 1 8488
Protoss_Shuttle 1 8942
Protoss_Robotics_Support_Bay 1 8642
Protoss_Dragoon 1 9068
Protoss_Corsair 1 9183
Protoss_Reaver 2 11045
11686
