Protoss_Nexus 1 4610
Protoss_Forge 1 3680
Protoss_Photon_Cannon 4 10222
Protoss_Gateway 1 5320
Protoss_Assimilator 2 6580
Protoss_Cybernetics_Core 1 6364
Protoss_Zealot 1 6453
Protoss_Dragoon 1 7223
Protoss_Stargate 1 8848
Protoss_Robotics_Facility 2 10349
Protoss_Corsair 2 10195
Protoss_Shuttle 1 10797
10797
