Protoss_Forge 2 4271
Protoss_Nexus 1 4923
Protoss_Gateway 4 10846
Protoss_Photon_Cannon 5 10115
Protoss_Assimilator 2 7390
Protoss_Zealot 5 10458
Protoss_Cybernetics_Core 1 6432
Protoss_Citadel_of_Adun 1 7674
Protoss_Templar_Archives 1 8791
Protoss_High_Templar 3 10593
Protoss_Dark_Templar 1 9898
Protoss_Robotics_Facility 1 10745
Protoss_Ground_Weapons_1 1 9901
10846
