Protoss_Gateway 2 3433
Protoss_Zealot 8 7408
Protoss_Assimilator 1 5274
Protoss_Cybernetics_Core 1 6259
Protoss_Stargate 1 7473
Protoss_Dragoon 1 7283
Protoss_Citadel_of_Adun 1 8104
Protoss_Forge 1 8147
Protoss_Templar_Archives 1 9271
Protoss_Nexus 1 10470
Protoss_Photon_Cannon 2 10686
Protoss_Dark_Templar 1 10183
Protoss_High_Templar 1 10218
10686
