Protoss_Forge 1 2961
Protoss_Nexus 1 5255
Protoss_Photon_Cannon 4 9960
Protoss_Gateway 1 5434
Protoss_Assimilator 2 6981
Protoss_Zealot 5 9352
Protoss_Cybernetics_Core 1 6719
Protoss_Stargate 1 8051
Protoss_Citadel_of_Adun 1 8271
Protoss_Dragoon 1 8148
Protoss_Corsair 2 9583
Protoss_Templar_Archives 1 10549
10549
