Protoss_Forge 1 2805
Protoss_Photon_Cannon 4 8680
Protoss_Nexus 1 5880
Protoss_Gateway 4 10139
Protoss_Assimilator 2 8264
Protoss_Zealot 8 10570
Protoss_Cybernetics_Core 1 7449
Protoss_Citadel_of_Adun 1 8629
Protoss_Dragoon 1 8863
Protoss_Templar_Archives 1 10081
10570
