Protoss_Forge 1 2719
Protoss_Photon_Cannon 4 10594
Protoss_Gateway 2 10025
Protoss_Zealot 4 10048
Protoss_Assimilator 1 5636
Protoss_Cybernetics_Core 1 6467
Protoss_Stargate 1 7758
Protoss_Nexus 1 8755
Protoss_Dragoon 1 7872
Protoss_Corsair 1 8644
Protoss_Citadel_of_Adun 1 9076
Protoss_Templar_Archives 1 10123
10594
