Protoss_Nexus 1 4710
Protoss_Forge 1 4038
Protoss_Gateway 1 4647
Protoss_Assimilator 2 6141
Protoss_Photon_Cannon 1 4945
Protoss_Cybernetics_Core 1 5759
Protoss_Zealot 2 7783
Protoss_Stargate 1 6950
Protoss_Dragoon 1 6773
7783
