Protoss_Forge 1 3409
Protoss_Nexus 1 5201
Protoss_Photon_Cannon 3 6595
Protoss_Gateway 3 9971
Protoss_Zealot 5 9297
Protoss_Assimilator 2 7820
Protoss_Cybernetics_Core 1 7308
Protoss_Citadel_of_Adun 1 9143
9971
