Protoss_Nexus 1 4791
Protoss_Forge 1 3918
Protoss_Photon_Cannon 2 6611
Protoss_Assimilator 2 5570
Protoss_Gateway 1 6465
Protoss_Zealot 4 10328
Protoss_Cybernetics_Core 1 7814
Protoss_Citadel_of_Adun 1 8929
10328
