Protoss_Forge 1 2994
Protoss_Photon_Cannon 2 3992
Protoss_Nexus 1 6030
Protoss_Gateway 4 10836
Protoss_Assimilator 2 7326
Protoss_Cybernetics_Core 1 6734
Protoss_Zealot 4 9170
Protoss_Stargate 1 7995
Protoss_Dragoon 1 7887
Protoss_Citadel_of_Adun 1 8252
Protoss_Corsair 3 9887
Protoss_Templar_Archives 1 9293
Protoss_Dark_Templar 2 10203
10836
