Protoss_Forge 1 3236
Protoss_Nexus 1 5104
Protoss_Photon_Cannon 4 9845
Protoss_Gateway 2 7912
Protoss_Assimilator 2 7409
Protoss_Zealot 8 10418
Protoss_Cybernetics_Core 1 6999
Protoss_Citadel_of_Adun 1 8109
Protoss_Dragoon 1 8058
Protoss_Stargate 2 9744
Protoss_Corsair 2 10503
Protoss_Ground_Weapons_1 1 9896
10503
