Protoss_Forge 1 3006
Protoss_Photon_Cannon 7 10576
Protoss_Nexus 1 5796
Protoss_Assimilator 2 7692
Protoss_Gateway 3 10039
Protoss_Cybernetics_Core 1 6730
Protoss_Zealot 1 6584
Protoss_Stargate 1 7893
Protoss_Corsair 3 10008
Protoss_Citadel_of_Adun 1 8979
Protoss_Templar_Archives 1 10004
10576
