Protoss_Nexus 1 4760
Protoss_Forge 1 3960
Protoss_Gateway 4 10181
Protoss_Photon_Cannon 4 8599
Protoss_Assimilator 2 6707
Protoss_Cybernetics_Core 1 6097
Protoss_Zealot 2 7708
Protoss_Stargate 1 7293
Protoss_Dragoon 1 7106
Protoss_Citadel_of_Adun 1 7849
Protoss_Corsair 4 10050
Protoss_Templar_Archives 1 8949
Protoss_Dark_Templar 2 9798
10181
