Protoss_Gateway 4 9686
Protoss_Zealot 16 10528
Protoss_Assimilator 1 5221
Protoss_Cybernetics_Core 1 5904
Protoss_Citadel_of_Adun 1 6991
Protoss_Dragoon 1 7023
Protoss_Templar_Archives 1 8819
Protoss_High_Templar 2 10385
10528
