Protoss_Gateway 1 2747
Protoss_Assimilator 1 2786
Protoss_Zealot 3 5914
Protoss_Cybernetics_Core 1 4426
Protoss_Dragoon 1 5312
Protoss_Stargate 1 5861
Protoss_Citadel_of_Adun 1 6349
Protoss_Corsair 5 10098
Protoss_Templar_Archives 1 7341
Protoss_Forge 1 7515
Protoss_Dark_Templar 1 8738
Protoss_Photon_Cannon 2 9892
Protoss_Nexus 1 10519
Protoss_High_Templar 2 10446
10519
