Protoss_Forge 1 2783
Protoss_Nexus 1 5334
Protoss_Gateway 2 9271
Protoss_Photon_Cannon 3 8245
Protoss_Assimilator 2 7256
Protoss_Zealot 4 10123
Protoss_Cybernetics_Core 1 7029
Protoss_Dragoon 1 7893
Protoss_Stargate 2 8765
Protoss_Citadel_of_Adun 1 9161
Protoss_Corsair 5 10397
Protoss_Templar_Archives 1 10239
10397
