Protoss_Gateway 3 7960
Protoss_Assimilator 1 3337
Protoss_Zealot 9 10178
Protoss_Cybernetics_Core 1 4780
Protoss_Dragoon 1 5663
Protoss_Stargate 1 6093
Protoss_Citadel_of_Adun 1 6536
Protoss_Corsair 1 7453
Protoss_Templar_Archives 1 9564
10178
