Protoss_Nexus 1 4629
Protoss_Forge 1 3860
Protoss_Gateway 3 9964
Protoss_Assimilator 2 6324
Protoss_Photon_Cannon 8 10719
Protoss_Cybernetics_Core 1 5769
Protoss_Stargate 1 7001
Protoss_Dragoon 1 6754
Protoss_Citadel_of_Adun 1 7207
Protoss_Corsair 2 8580
Protoss_Templar_Archives 1 8408
Protoss_Robotics_Facility 1 9495
Protoss_Dark_Templar 1 9328
Protoss_High_Templar 1 10080
10719
