Protoss_Forge 1 2737
Protoss_Nexus 1 5520
Protoss_Photon_Cannon 1 4873
Protoss_Assimilator 1 5394
Protoss_Gateway 6 10336
Protoss_Zealot 10 10367
Protoss_Cybernetics_Core 1 6899
Protoss_Citadel_of_Adun 1 8049
10367
