Protoss_Forge 1 3115
Protoss_Photon_Cannon 8 10135
Protoss_Nexus 1 7847
Protoss_Gateway 2 10598
Protoss_Assimilator 2 9400
Protoss_Zealot 3 10288
Protoss_Cybernetics_Core 1 9002
Protoss_Citadel_of_Adun 1 10091
10598
