Protoss_Gateway 2 7195
Protoss_Assimilator 1 3161
Protoss_Zealot 6 8062
Protoss_Cybernetics_Core 1 5180
Protoss_Dragoon 1 6238
Protoss_Citadel_of_Adun 1 6788
Protoss_Templar_Archives 1 8263
Protoss_Forge 1 8850
Protoss_High_Templar 2 10025
10025
