Protoss_Forge 1 2545
Protoss_Photon_Cannon 3 5235
Protoss_Nexus 1 6134
Protoss_Gateway 3 8969
Protoss_Assimilator 2 10102
Protoss_Zealot 9 10320
Protoss_Cybernetics_Core 1 6850
Protoss_Citadel_of_Adun 1 8066
Protoss_Dragoon 1 8058
Protoss_Templar_Archives 1 10323
10323
