Protoss_Gateway 3 10766
Protoss_Zealot 13 10058
Protoss_Forge 2 8269
Protoss_Photon_Cannon 1 6425
Protoss_Nexus 1 8470
Protoss_Assimilator 2 9841
Protoss_Cybernetics_Core 1 9863
10766
