Protoss_Forge 1 2591
Protoss_Photon_Cannon 4 9222
Protoss_Nexus 1 6400
Protoss_Gateway 4 10341
Protoss_Assimilator 2 7598
Protoss_Zealot 2 7088
Protoss_Cybernetics_Core 1 7310
Protoss_Citadel_of_Adun 1 8380
Protoss_Templar_Archives 1 9567
Protoss_High_Templar 2 10443
Protoss_Robotics_Facility 1 10967
10967
