Protoss_Forge 1 2874
Protoss_Photon_Cannon 3 9773
Protoss_Nexus 1 5550
Protoss_Gateway 3 10437
Protoss_Assimilator 2 8703
Protoss_Zealot 6 9898
Protoss_Cybernetics_Core 1 6364
Protoss_Citadel_of_Adun 1 7712
Protoss_Templar_Archives 1 9656
Protoss_High_Templar 2 10650
10650
