Protoss_Forge 1 3109
Protoss_Photon_Cannon 5 10623
Protoss_Nexus 1 5495
Protoss_Gateway 1 5344
Protoss_Assimilator 2 6830
Protoss_Cybernetics_Core 1 6359
Protoss_Zealot 3 10228
Protoss_Stargate 1 7686
Protoss_Corsair 4 10428
Protoss_Robotics_Facility 1 10058
10623
