Protoss_Forge 1 2902
Protoss_Nexus 1 5275
Protoss_Photon_Cannon 5 10644
Protoss_Gateway 3 10672
Protoss_Assimilator 2 8285
Protoss_Zealot 4 10538
Protoss_Cybernetics_Core 1 7270
Protoss_Citadel_of_Adun 1 8447
Protoss_Templar_Archives 1 9874
10672
