Protoss_Forge 1 3067
Protoss_Nexus 1 5378
Protoss_Photon_Cannon 2 10061
Protoss_Gateway 3 8784
Protoss_Assimilator 2 9156
Protoss_Cybernetics_Core 1 6570
Protoss_Zealot 11 10585
Protoss_Citadel_of_Adun 1 8165
Protoss_Templar_Archives 1 9609
Protoss_Robotics_Facility 1 10877
10877
