Protoss_Forge 1 2955
Protoss_Photon_Cannon 5 10711
Protoss_Nexus 1 5656
Protoss_Gateway 2 9040
Protoss_Assimilator 2 7031
Protoss_Zealot 6 10213
Protoss_Cybernetics_Core 1 6298
Protoss_Dragoon 1 7543
Protoss_Citadel_of_Adun 2 8464
Protoss_Stargate 1 9571
Protoss_Templar_Archives 1 9541
Protoss_Corsair 1 10273
Protoss_High_Templar 2 10458
10711
