Protoss_Gateway 3 10413
Protoss_Zealot 11 8958
Protoss_Forge 1 6423
Protoss_Photon_Cannon 1 7302
Protoss_Nexus 2 10825
Protoss_Assimilator 2 10425
Protoss_Cybernetics_Core 1 9513
10825
