Protoss_Forge 1 2693
Protoss_Photon_Cannon 4 6699
Protoss_Gateway 1 5495
Protoss_Nexus 1 7095
Protoss_Assimilator 2 8071
Protoss_Zealot 6 10045
Protoss_Cybernetics_Core 1 7489
Protoss_Stargate 1 8855
Protoss_Citadel_of_Adun 2 10249
Protoss_Corsair 2 10150
Protoss_Templar_Archives 1 10714
10714
