Protoss_Gateway 2 3461
Protoss_Zealot 12 9010
Protoss_Assimilator 1 4616
Protoss_Cybernetics_Core 1 5917
Protoss_Citadel_of_Adun 1 7073
Protoss_Templar_Archives 1 8189
Protoss_High_Templar 2 9762
9762
