Protoss_Forge 2 10195
Protoss_Nexus 1 5110
Protoss_Photon_Cannon 2 9632
Protoss_Gateway 4 8629
Protoss_Assimilator 2 6745
Protoss_Zealot 13 9920
Protoss_Cybernetics_Core 1 6141
Protoss_Citadel_of_Adun 1 7329
Protoss_Templar_Archives 1 10369
Protoss_Ground_Weapons_1 1 9891
10369
