Protoss_Gateway 2 3455
Protoss_Zealot 4 6813
Protoss_Assimilator 1 4157
Protoss_Forge 1 4678
Protoss_Cybernetics_Core 1 6032
Protoss_Citadel_of_Adun 1 7091
Protoss_Ground_Weapons_1 1 8966
Protoss_Photon_Cannon 1 9930
9930
