Protoss_Gateway 2 3398
Protoss_Zealot 5 6103
Protoss_Assimilator 1 4202
Protoss_Cybernetics_Core 1 5536
Protoss_Forge 1 5903
Protoss_Nexus 1 9785
Protoss_Photon_Cannon 3 10299
10299
