Protoss_Forge 1 2993
Protoss_Photon_Cannon 4 10193
Protoss_Nexus 2 9990
Protoss_Gateway 1 5824
Protoss_Assimilator 2 7159
Protoss_Cybernetics_Core 1 6937
Protoss_Zealot 1 6848
Protoss_Stargate 1 8168
Protoss_Robotics_Facility 1 8857
Protoss_Corsair 1 9018
Protoss_Robotics_Support_Bay 1 9411
Protoss_Reaver 1 10576
10576
