Protoss_Forge 1 2845
Protoss_Photon_Cannon 5 10465
Protoss_Nexus 1 6555
Protoss_Gateway 4 8664
Protoss_Assimilator 2 9120
Protoss_Cybernetics_Core 1 7269
Protoss_Zealot 10 10058
Protoss_Citadel_of_Adun 1 8355
Protoss_Dragoon 1 9808
Protoss_Templar_Archives 1 10098
10465
