Protoss_Nexus 2 11665
Protoss_Forge 1 3988
Protoss_Photon_Cannon 1 4955
Protoss_Gateway 4 8444
Protoss_Assimilator 2 8260
Protoss_Zealot 12 10070
Protoss_Cybernetics_Core 1 7228
Protoss_Citadel_of_Adun 1 8229
Protoss_Templar_Archives 1 10242
11665
