Protoss_Forge 2 8388
Protoss_Nexus 1 4896
Protoss_Photon_Cannon 2 5847
Protoss_Gateway 4 10585
Protoss_Assimilator 2 8273
Protoss_Zealot 5 10578
Protoss_Cybernetics_Core 1 7312
Protoss_Citadel_of_Adun 1 8483
Protoss_Dragoon 1 9818
10585
