Protoss_Forge 2 4316
Protoss_Nexus 1 4845
Protoss_Gateway 4 9759
Protoss_Photon_Cannon 2 5456
Protoss_Zealot 3 6838
Protoss_Assimilator 2 7092
Protoss_Cybernetics_Core 1 7043
Protoss_Dragoon 8 10164
Protoss_Robotics_Facility 1 9937
Protoss_Citadel_of_Adun 1 9859
10164
