Protoss_Forge 1 3617
Protoss_Nexus 1 4979
Protoss_Photon_Cannon 2 5374
Protoss_Gateway 2 9442
Protoss_Assimilator 2 6389
Protoss_Zealot 4 10214
Protoss_Cybernetics_Core 1 7324
Protoss_Citadel_of_Adun 1 8573
Protoss_Templar_Archives 1 9937
10214
