Protoss_Forge 1 2828
Protoss_Photon_Cannon 6 10652
Protoss_Nexus 1 5821
Protoss_Gateway 1 5219
Protoss_Assimilator 2 7900
Protoss_Cybernetics_Core 1 6222
Protoss_Zealot 3 7526
Protoss_Stargate 2 9753
Protoss_Corsair 4 10438
Protoss_Robotics_Facility 1 9417
10652
