Protoss_Gateway 2 9432
Protoss_Zealot 4 5614
Protoss_Assimilator 1 3778
Protoss_Cybernetics_Core 1 4816
Protoss_Stargate 1 6174
Protoss_Dragoon 1 6366
Protoss_Citadel_of_Adun 1 6965
Protoss_Forge 1 6852
Protoss_Corsair 1 7064
Protoss_Templar_Archives 1 7955
Protoss_Photon_Cannon 5 10566
Protoss_Dark_Templar 1 8978
Protoss_Nexus 1 11015
11015
