Protoss_Gateway 2 3544
Protoss_Zealot 10 10398
Protoss_Assimilator 1 4282
Protoss_Cybernetics_Core 1 5314
Protoss_Dragoon 1 6308
Protoss_Citadel_of_Adun 1 7069
Protoss_Forge 1 7750
Protoss_Photon_Cannon 2 9640
Protoss_Templar_Archives 1 10354
10398
