Protoss_Gateway 2 3363
Protoss_Zealot 8 6066
Protoss_Assimilator 1 5634
Protoss_Cybernetics_Core 1 7518
Protoss_Dragoon 3 10356
Protoss_Stargate 1 9518
Protoss_Forge 1 9515
Protoss_Photon_Cannon 1 10408
10408
