Protoss_Gateway 2 10864
Protoss_Assimilator 1 3057
Protoss_Zealot 3 4912
Protoss_Cybernetics_Core 1 4835
Protoss_Dragoon 1 5988
Protoss_Stargate 1 6481
Protoss_Citadel_of_Adun 1 6859
Protoss_Scout 1 7915
Protoss_Templar_Archives 1 7977
Protoss_Forge 1 8273
Protoss_Dark_Templar 1 8818
Protoss_Photon_Cannon 1 9130
Protoss_Nexus 1 11425
Protoss_High_Templar 1 10513
11425
