Protoss_Nexus 1 4831
Protoss_Forge 1 3990
Protoss_Photon_Cannon 3 6650
Protoss_Gateway 4 8924
Protoss_Assimilator 2 8305
Protoss_Zealot 9 10318
Protoss_Cybernetics_Core 1 7182
Protoss_Citadel_of_Adun 1 8213
Protoss_Dragoon 1 8213
Protoss_Templar_Archives 1 10095
10318
