Protoss_Gateway 2 3312
Protoss_Zealot 9 7823
Protoss_Assimilator 1 5796
Protoss_Cybernetics_Core 1 6777
Protoss_Citadel_of_Adun 1 8262
Protoss_Forge 1 8733
Protoss_Templar_Archives 1 9304
9304
