Protoss_Forge 1 3136
Protoss_Nexus 1 5115
Protoss_Photon_Cannon 2 8561
Protoss_Gateway 4 10765
Protoss_Assimilator 2 7526
Protoss_Zealot 4 8710
Protoss_Cybernetics_Core 1 6658
Protoss_Dragoon 2 8235
Protoss_Stargate 1 8048
Protoss_Citadel_of_Adun 1 9035
10765
