Protoss_Forge 1 2919
Protoss_Nexus 1 5225
Protoss_Photon_Cannon 2 9679
Protoss_Gateway 4 9200
Protoss_Assimilator 2 7968
Protoss_Zealot 15 10565
Protoss_Cybernetics_Core 1 7280
Protoss_Citadel_of_Adun 1 8399
Protoss_Templar_Archives 1 9949
Protoss_Ground_Weapons_1 1 9996
10565
