Protoss_Gateway 2 3161
Protoss_Zealot 7 7678
Protoss_Nexus 1 8070
Protoss_Assimilator 2 9956
Protoss_Forge 1 8015
Protoss_Cybernetics_Core 1 8784
Protoss_Photon_Cannon 4 10643
Protoss_Stargate 1 9968
10643
