Protoss_Forge 1 2917
Protoss_Nexus 1 5123
Protoss_Gateway 4 9681
Protoss_Assimilator 2 7058
Protoss_Zealot 9 10556
Protoss_Cybernetics_Core 1 5983
Protoss_Photon_Cannon 1 6380
Protoss_Stargate 1 7314
Protoss_Citadel_of_Adun 1 7804
Protoss_Corsair 2 8694
Protoss_Robotics_Facility 1 11166
11166
