Protoss_Forge 1 2688
Protoss_Nexus 1 5151
Protoss_Gateway 3 10536
Protoss_Photon_Cannon 12 10630
Protoss_Assimilator 2 6469
Protoss_Zealot 1 5756
Protoss_Cybernetics_Core 1 6358
Protoss_Citadel_of_Adun 1 7374
Protoss_Templar_Archives 1 8439
Protoss_Dark_Templar 1 9290
Protoss_High_Templar 2 10052
10630
