Protoss_Forge 2 9913
Protoss_Nexus 1 5095
Protoss_Photon_Cannon 4 9951
Protoss_Gateway 3 10630
Protoss_Assimilator 2 6860
Protoss_Zealot 3 8400
Protoss_Cybernetics_Core 1 6752
Protoss_Stargate 1 7892
Protoss_Citadel_of_Adun 1 8265
Protoss_Corsair 3 10374
Protoss_Templar_Archives 1 9323
Protoss_Dark_Templar 2 10280
10630
