Protoss_Forge 2 10464
Protoss_Nexus 1 5221
Protoss_Photon_Cannon 2 4739
Protoss_Gateway 4 8973
Protoss_Assimilator 2 7136
Protoss_Zealot 11 10518
Protoss_Cybernetics_Core 1 7023
Protoss_Citadel_of_Adun 1 8161
Protoss_Templar_Archives 1 10719
10719
