Protoss_Forge 1 2576
Protoss_Photon_Cannon 3 9908
Protoss_Nexus 1 5885
Protoss_Gateway 1 5271
Protoss_Assimilator 2 8384
Protoss_Cybernetics_Core 1 6291
Protoss_Zealot 4 10112
Protoss_Stargate 1 7604
Protoss_Dragoon 1 7622
Protoss_Citadel_of_Adun 1 8559
Protoss_Corsair 4 10508
Protoss_Templar_Archives 1 9678
10508
