Protoss_Gateway 1 2833
Protoss_Assimilator 1 3187
Protoss_Zealot 5 10324
Protoss_Cybernetics_Core 1 4921
Protoss_Stargate 1 6095
Protoss_Dragoon 1 6034
Protoss_Citadel_of_Adun 1 6639
Protoss_Forge 1 6930
Protoss_Templar_Archives 1 7726
Protoss_Photon_Cannon 8 10356
Protoss_High_Templar 2 9708
10356
