Protoss_Nexus 1 4799
Protoss_Forge 2 9366
Protoss_Photon_Cannon 4 10575
Protoss_Gateway 3 9114
Protoss_Assimilator 2 8066
Protoss_Zealot 5 9273
Protoss_Cybernetics_Core 1 8139
Protoss_Citadel_of_Adun 1 9223
Protoss_Dragoon 1 9325
10575
