Protoss_Forge 1 2787
Protoss_Photon_Cannon 4 6801
Protoss_Nexus 1 6379
Protoss_Gateway 2 10785
Protoss_Zealot 6 10415
Protoss_Assimilator 2 8731
Protoss_Cybernetics_Core 1 8246
Protoss_Stargate 1 9558
Protoss_Citadel_of_Adun 1 9947
Protoss_Corsair 1 10258
10785
