Protoss_Forge 1 3493
Protoss_Nexus 1 5163
Protoss_Photon_Cannon 4 10220
Protoss_Gateway 4 8545
Protoss_Assimilator 2 7156
Protoss_Cybernetics_Core 1 6687
Protoss_Zealot 2 7248
Protoss_Citadel_of_Adun 1 7825
Protoss_Templar_Archives 1 8851
Protoss_Dragoon 1 9326
Protoss_High_Templar 5 10476
10476
