Protoss_Gateway 1 2649
Protoss_Zealot 6 7392
Protoss_Nexus 1 5930
Protoss_Assimilator 1 4944
Protoss_Cybernetics_Core 1 6315
Protoss_Stargate 1 7623
Protoss_Citadel_of_Adun 1 7819
Protoss_Forge 1 7864
Protoss_Corsair 4 10290
Protoss_Templar_Archives 1 8811
Protoss_Photon_Cannon 8 10565
10565
