Protoss_Forge 1 2765
Protoss_Photon_Cannon 3 7927
Protoss_Nexus 1 5339
Protoss_Gateway 2 8595
Protoss_Assimilator 2 6716
Protoss_Cybernetics_Core 1 6903
Protoss_Zealot 3 10095
10095
