Protoss_Gateway 2 3332
Protoss_Zealot 9 9888
Protoss_Assimilator 1 5110
Protoss_Cybernetics_Core 2 7182
Protoss_Stargate 1 7550
Protoss_Dragoon 1 7310
Protoss_Citadel_of_Adun 1 7873
Protoss_Forge 1 8160
Protoss_Corsair 1 8452
Protoss_Templar_Archives 1 9121
Protoss_Photon_Cannon 2 10652
Protoss_Dark_Templar 1 9962
10652
