Protoss_Forge 1 2951
Protoss_Photon_Cannon 2 4622
Protoss_Nexus 1 5381
Protoss_Gateway 1 5492
Protoss_Assimilator 2 7158
Protoss_Cybernetics_Core 1 6609
Protoss_Zealot 2 10526
10526
