Protoss_Forge 1 2900
Protoss_Photon_Cannon 6 10115
Protoss_Nexus 1 5813
Protoss_Gateway 2 9567
Protoss_Assimilator 2 8058
Protoss_Zealot 2 6500
Protoss_Cybernetics_Core 1 6657
Protoss_Stargate 1 7820
Protoss_Citadel_of_Adun 1 8140
Protoss_Corsair 1 8510
Protoss_Templar_Archives 1 9423
Protoss_Dark_Templar 1 10290
10290
