Protoss_Forge 1 2875
Protoss_Nexus 1 5115
Protoss_Photon_Cannon 4 9968
Protoss_Gateway 4 10729
Protoss_Assimilator 2 7403
Protoss_Cybernetics_Core 1 6402
Protoss_Zealot 4 9923
Protoss_Stargate 1 7690
Protoss_Citadel_of_Adun 1 7954
Protoss_Corsair 2 9178
Protoss_Templar_Archives 1 10301
10729
