Protoss_Assimilator 1 1784
Protoss_Gateway 1 2941
Protoss_Cybernetics_Core 1 4079
Protoss_Stargate 2 5578
Protoss_Corsair 9 10276
Protoss_Forge 1 7630
Protoss_Photon_Cannon 2 8977
Protoss_Air_Weapons_1 1 9081
10276
