Protoss_Gateway 3 8811
Protoss_Assimilator 2 4921
Protoss_Cybernetics_Core 1 4065
Protoss_Zealot 3 6898
Protoss_Stargate 1 5293
Protoss_Dragoon 6 10246
Protoss_Corsair 1 5984
10246
