Protoss_Gateway 2 8794
Protoss_Assimilator 2 9425
Protoss_Zealot 6 9348
Protoss_Cybernetics_Core 1 4539
Protoss_Stargate 1 5672
Protoss_Dragoon 1 5398
Protoss_Citadel_of_Adun 1 5994
Protoss_Forge 1 5994
Protoss_Corsair 2 7446
Protoss_Templar_Archives 1 7077
Protoss_Photon_Cannon 3 9694
Protoss_Dark_Templar 1 7924
Protoss_High_Templar 1 9818
Protoss_Nexus 1 11427
11427
