Protoss_Forge 2 9331
Protoss_Photon_Cannon 5 5945
Protoss_Nexus 1 5961
Protoss_Gateway 3 10315
Protoss_Assimilator 2 10304
Protoss_Zealot 4 10448
Protoss_Cybernetics_Core 1 9016
Protoss_Citadel_of_Adun 1 10024
10448
