Protoss_Forge 2 9464
Protoss_Nexus 1 5307
Protoss_Photon_Cannon 9 10741
Protoss_Gateway 4 10483
Protoss_Assimilator 2 8254
Protoss_Zealot 2 7472
Protoss_Cybernetics_Core 1 7247
Protoss_Citadel_of_Adun 1 8390
Protoss_Dragoon 1 8265
Protoss_Templar_Archives 1 9565
Protoss_High_Templar 1 10674
10741
