Protoss_Gateway 3 9194
Protoss_Zealot 12 9198
Protoss_Assimilator 1 4285
Protoss_Cybernetics_Core 1 5533
Protoss_Citadel_of_Adun 1 6567
Protoss_Dragoon 1 6583
Protoss_Templar_Archives 1 8835
Protoss_High_Templar 2 10228
Protoss_Dark_Templar 1 10523
10523
