Protoss_Forge 1 2710
Protoss_Nexus 1 5297
Protoss_Gateway 5 10258
Protoss_Photon_Cannon 1 5168
Protoss_Assimilator 2 7308
Protoss_Zealot 11 10582
Protoss_Cybernetics_Core 1 6231
Protoss_Dragoon 1 7064
Protoss_Stargate 1 7609
Protoss_Corsair 1 8294
Protoss_Citadel_of_Adun 1 9149
Protoss_Templar_Archives 1 10858
10858
