Protoss_Forge 1 2833
Protoss_Photon_Cannon 3 10745
Protoss_Nexus 1 8191
Protoss_Gateway 1 7983
Protoss_Assimilator 2 9554
Protoss_Cybernetics_Core 1 8969
Protoss_Zealot 2 9474
Protoss_Stargate 1 10239
Protoss_Dragoon 1 9956
10745
