Protoss_Forge 1 2980
Protoss_Photon_Cannon 2 3862
Protoss_Nexus 1 6053
Protoss_Gateway 1 5535
Protoss_Assimilator 1 5493
Protoss_Zealot 3 8146
Protoss_Cybernetics_Core 1 6774
8146
