Protoss_Forge 1 2794
Protoss_Nexus 1 5223
Protoss_Photon_Cannon 7 10192
Protoss_Gateway 1 5281
Protoss_Assimilator 2 9100
Protoss_Cybernetics_Core 1 6307
Protoss_Stargate 1 7455
Protoss_Robotics_Facility 1 8564
Protoss_Corsair 3 10158
Protoss_Shuttle 1 9649
Protoss_Robotics_Support_Bay 1 9497
Protoss_Reaver 1 10930
10930
