Protoss_Forge 1 2440
Protoss_Nexus 1 4807
Protoss_Photon_Cannon 2 4372
Protoss_Gateway 4 8768
Protoss_Assimilator 2 8905
Protoss_Zealot 13 10457
Protoss_Cybernetics_Core 1 6756
Protoss_Citadel_of_Adun 1 7855
Protoss_Templar_Archives 1 9626
10457
