Protoss_Forge 1 2920
Protoss_Photon_Cannon 2 4000
Protoss_Nexus 1 6390
Protoss_Gateway 3 9428
Protoss_Assimilator 2 7386
Protoss_Zealot 6 10208
Protoss_Cybernetics_Core 1 7239
Protoss_Stargate 1 8528
Protoss_Citadel_of_Adun 1 8568
Protoss_Corsair 3 10502
Protoss_Templar_Archives 1 9748
Protoss_Dark_Templar 2 10693
10693
