Protoss_Forge 1 3019
Protoss_Nexus 1 5088
Protoss_Gateway 1 4574
Protoss_Photon_Cannon 3 8762
Protoss_Assimilator 2 7123
Protoss_Cybernetics_Core 1 5947
Protoss_Zealot 1 5920
Protoss_Stargate 2 10395
Protoss_Robotics_Facility 1 8578
Protoss_Corsair 4 10242
Protoss_Shuttle 1 9621
Protoss_Robotics_Support_Bay 1 9662
Protoss_Reaver 1 11000
11000
