Protoss_Nexus 1 4463
Protoss_Forge 1 3727
Protoss_Gateway 1 4877
Protoss_Photon_Cannon 2 9910
Protoss_Assimilator 2 6859
Protoss_Zealot 8 10028
Protoss_Cybernetics_Core 1 6517
Protoss_Stargate 1 7929
Protoss_Robotics_Facility 1 8629
Protoss_Corsair 4 10476
Protoss_Shuttle 1 9627
Protoss_Robotics_Support_Bay 1 9327
Protoss_Reaver 1 10678
10678
