Protoss_Gateway 2 8876
Protoss_Assimilator 1 3008
Protoss_Zealot 7 9923
Protoss_Forge 1 4405
Protoss_Cybernetics_Core 1 6150
Protoss_Stargate 1 7308
Protoss_Dragoon 1 7108
Protoss_Citadel_of_Adun 1 7698
Protoss_Corsair 1 8003
Protoss_Templar_Archives 1 9347
Protoss_Photon_Cannon 2 9820
Protoss_Ground_Weapons_1 1 8826
Protoss_Robotics_Facility 1 10827
Protoss_High_Templar 1 10408
10827
