Protoss_Gateway 2 3419
Protoss_Zealot 10 9208
Protoss_Forge 1 5746
Protoss_Photon_Cannon 4 10480
Protoss_Assimilator 1 6551
Protoss_Cybernetics_Core 1 7224
Protoss_Citadel_of_Adun 1 8542
Protoss_Stargate 2 10274
Protoss_Corsair 1 10083
10480
