Protoss_Gateway 2 3583
Protoss_Zealot 11 10409
Protoss_Assimilator 1 4179
Protoss_Cybernetics_Core 1 5002
Protoss_Stargate 1 6416
Protoss_Dragoon 1 6688
Protoss_Corsair 1 7103
Protoss_Citadel_of_Adun 1 7701
Protoss_Templar_Archives 1 8694
10409
