Protoss_Gateway 1 2791
Protoss_Zealot 11 10388
Protoss_Nexus 1 6185
Protoss_Assimilator 2 9252
Protoss_Forge 2 6299
Protoss_Cybernetics_Core 1 8094
Protoss_Photon_Cannon 2 8587
Protoss_Stargate 1 9322
Protoss_Dragoon 1 9184
Protoss_Citadel_of_Adun 1 10111
Protoss_Corsair 1 10078
10388
