Protoss_Gateway 1 2405
Protoss_Zealot 5 6670
Protoss_Assimilator 1 3964
Protoss_Cybernetics_Core 1 5756
Protoss_Stargate 1 7021
Protoss_Dragoon 1 7742
Protoss_Corsair 4 10266
Protoss_Citadel_of_Adun 1 8891
Protoss_Templar_Archives 1 9916
Protoss_Forge 1 9634
Protoss_Photon_Cannon 1 10736
10736
