Protoss_Gateway 3 9800
Protoss_Zealot 12 10347
Protoss_Assimilator 1 4134
Protoss_Cybernetics_Core 1 5203
Protoss_Dragoon 1 6208
Protoss_Stargate 1 6727
Protoss_Forge 1 6539
Protoss_Corsair 1 7533
Protoss_Citadel_of_Adun 1 8362
Protoss_Templar_Archives 1 10324
10347
