Protoss_Forge 1 2940
Protoss_Photon_Cannon 2 3951
Protoss_Nexus 1 6137
Protoss_Gateway 6 10261
Protoss_Assimilator 2 6638
Protoss_Cybernetics_Core 1 6621
Protoss_Zealot 3 8744
Protoss_Citadel_of_Adun 1 7680
Protoss_Dragoon 1 7798
Protoss_Templar_Archives 1 8705
Protoss_Dark_Templar 2 9790
Protoss_High_Templar 2 10722
10722
