Protoss_Nexus 1 4713
Protoss_Forge 1 3892
Protoss_Photon_Cannon 3 5772
Protoss_Gateway 1 5865
Protoss_Assimilator 2 8952
Protoss_Zealot 5 10380
Protoss_Cybernetics_Core 1 8489
Protoss_Stargate 2 11003
Protoss_Citadel_of_Adun 1 10234
11003
