Protoss_Forge 1 3564
Protoss_Nexus 1 5221
Protoss_Photon_Cannon 4 10202
Protoss_Gateway 1 5134
Protoss_Assimilator 2 8266
Protoss_Zealot 7 9811
Protoss_Cybernetics_Core 1 6169
Protoss_Stargate 1 7710
Protoss_Citadel_of_Adun 1 8341
Protoss_Corsair 3 10548
Protoss_Templar_Archives 1 9704
10548
