Protoss_Nexus 1 4810
Protoss_Gateway 1 4369
Protoss_Assimilator 2 5868
Protoss_Cybernetics_Core 1 5409
Protoss_Stargate 2 7113
Protoss_Forge 1 7194
Protoss_Corsair 8 10123
Protoss_Photon_Cannon 3 9940
Protoss_Robotics_Facility 1 10156
10156
