Protoss_Forge 2 6576
Protoss_Photon_Cannon 8 10702
Protoss_Nexus 1 5685
Protoss_Assimilator 2 8086
Protoss_Gateway 2 8380
Protoss_Zealot 6 10353
Protoss_Cybernetics_Core 1 7501
Protoss_Citadel_of_Adun 1 8747
Protoss_Dragoon 1 8713
Protoss_Templar_Archives 1 10084
10702
