Protoss_Gateway 1 2734
Protoss_Assimilator 1 3182
Protoss_Zealot 3 4928
Protoss_Cybernetics_Core 1 4944
Protoss_Stargate 1 6141
Protoss_Dragoon 1 6143
Protoss_Citadel_of_Adun 1 6666
Protoss_Corsair 1 6843
Protoss_Templar_Archives 1 7664
Protoss_Forge 1 7520
Protoss_Dark_Templar 1 8508
Protoss_Photon_Cannon 3 10695
Protoss_Nexus 1 10606
Protoss_High_Templar 2 10463
10695
