Protoss_Forge 1 2651
Protoss_Photon_Cannon 1 4166
Protoss_Gateway 1 4585
Protoss_Zealot 9 10222
Protoss_Assimilator 1 5566
Protoss_Cybernetics_Core 1 7767
Protoss_Stargate 1 9238
Protoss_Citadel_of_Adun 1 9951
Protoss_Corsair 1 9936
10222
