Protoss_Gateway 3 9541
Protoss_Zealot 13 10553
Protoss_Nexus 1 6305
Protoss_Forge 1 5831
Protoss_Photon_Cannon 2 7133
Protoss_Assimilator 1 8860
Protoss_Cybernetics_Core 1 10075
10553
