Protoss_Forge 1 2736
Protoss_Photon_Cannon 3 10701
Protoss_Nexus 1 6024
Protoss_Gateway 4 8810
Protoss_Assimilator 2 9745
Protoss_Cybernetics_Core 1 6444
Protoss_Zealot 10 10163
Protoss_Citadel_of_Adun 1 8045
Protoss_Templar_Archives 1 10384
10701
