Protoss_Gateway 2 3428
Protoss_Zealot 10 8250
Protoss_Assimilator 1 5210
Protoss_Cybernetics_Core 1 6849
Protoss_Forge 1 7402
Protoss_Photon_Cannon 1 9021
Protoss_Citadel_of_Adun 1 9906
9906
