Protoss_Gateway 2 6749
Protoss_Assimilator 1 3165
Protoss_Zealot 7 10272
Protoss_Cybernetics_Core 1 4828
Protoss_Dragoon 1 5708
Protoss_Citadel_of_Adun 1 6074
Protoss_Templar_Archives 1 8060
Protoss_High_Templar 3 9670
Protoss_Forge 1 8856
Protoss_Archon 1 9273
Protoss_Nexus 1 11708
11708
