Protoss_Nexus 1 4633
Protoss_Forge 1 3725
Protoss_Gateway 3 8369
Protoss_Photon_Cannon 1 4895
Protoss_Assimilator 1 4964
Protoss_Zealot 6 9043
Protoss_Cybernetics_Core 1 6253
Protoss_Citadel_of_Adun 1 7249
Protoss_Ground_Weapons_1 1 9621
9621
