Protoss_Nexus 1 4663
Protoss_Forge 1 3966
Protoss_Photon_Cannon 4 10504
Protoss_Gateway 4 9683
Protoss_Assimilator 2 9152
Protoss_Zealot 9 10416
Protoss_Cybernetics_Core 1 6785
Protoss_Citadel_of_Adun 1 8000
Protoss_Templar_Archives 1 9176
10504
