Protoss_Forge 1 3023
Protoss_Photon_Cannon 2 4051
Protoss_Nexus 1 5757
Protoss_Gateway 3 9523
Protoss_Assimilator 2 7710
Protoss_Zealot 5 9424
Protoss_Cybernetics_Core 1 6823
Protoss_Stargate 1 7975
Protoss_Citadel_of_Adun 1 8386
Protoss_Corsair 2 9842
Protoss_Templar_Archives 1 9391
Protoss_Dark_Templar 3 10454
10454
