Protoss_Forge 1 2746
Protoss_Nexus 1 5300
Protoss_Gateway 4 8867
Protoss_Photon_Cannon 1 4895
Protoss_Assimilator 2 7639
Protoss_Zealot 8 10188
Protoss_Cybernetics_Core 1 6184
Protoss_Citadel_of_Adun 1 7540
Protoss_Dragoon 1 8205
Protoss_Templar_Archives 1 9219
Protoss_High_Templar 2 10268
10268
