Protoss_Gateway 2 5872
Protoss_Assimilator 1 3171
Protoss_Zealot 6 7798
Protoss_Cybernetics_Core 1 5169
Protoss_Citadel_of_Adun 1 6676
Protoss_Dragoon 1 6783
Protoss_Templar_Archives 1 8001
Protoss_Forge 1 8386
Protoss_Dark_Templar 1 8908
Protoss_High_Templar 3 10163
Protoss_Photon_Cannon 2 9690
10163
