Protoss_Gateway 1 2707
Protoss_Zealot 9 10018
Protoss_Forge 1 4348
Protoss_Photon_Cannon 3 9544
Protoss_Nexus 1 9147
Protoss_Assimilator 1 8226
Protoss_Cybernetics_Core 1 9451
Protoss_Dragoon 1 10380
10380
