Protoss_Forge 1 2881
Protoss_Nexus 1 5362
Protoss_Photon_Cannon 1 4793
Protoss_Gateway 1 5455
Protoss_Assimilator 2 6498
Protoss_Zealot 2 7043
Protoss_Cybernetics_Core 1 6535
Protoss_Robotics_Facility 1 8472
8472
