Protoss_Forge 1 2631
Protoss_Nexus 2 9910
Protoss_Photon_Cannon 3 9866
Protoss_Assimilator 2 6511
Protoss_Gateway 1 5604
Protoss_Cybernetics_Core 1 6678
Protoss_Zealot 1 6703
Protoss_Robotics_Facility 1 8094
Protoss_Stargate 1 8412
Protoss_Shuttle 1 9237
Protoss_Corsair 2 10093
Protoss_Robotics_Support_Bay 1 9131
10093
