Protoss_Nexus 1 4545
Protoss_Gateway 2 4425
Protoss_Zealot 14 10578
Protoss_Forge 1 5780
Protoss_Assimilator 2 8453
Protoss_Photon_Cannon 3 8770
Protoss_Cybernetics_Core 1 7878
Protoss_Stargate 1 9413
Protoss_Citadel_of_Adun 1 9962
Protoss_Corsair 1 10142
10578
