Protoss_Nexus 1 4970
Protoss_Forge 1 4230
Protoss_Photon_Cannon 2 5530
Protoss_Assimilator 2 8880
Protoss_Gateway 3 8681
Protoss_Cybernetics_Core 1 7400
Protoss_Zealot 11 10597
Protoss_Citadel_of_Adun 1 8575
Protoss_Templar_Archives 1 10635
Protoss_Robotics_Facility 1 11027
11027
