Protoss_Forge 1 2814
Protoss_Photon_Cannon 3 10245
Protoss_Nexus 1 5985
Protoss_Gateway 4 10619
Protoss_Assimilator 2 8995
Protoss_Cybernetics_Core 1 6364
Protoss_Zealot 10 9938
Protoss_Citadel_of_Adun 1 7475
Protoss_Templar_Archives 1 10010
10619
