Protoss_Nexus 1 4992
Protoss_Forge 1 4155
Protoss_Gateway 4 10010
Protoss_Photon_Cannon 2 10670
Protoss_Assimilator 2 6635
Protoss_Zealot 7 10033
Protoss_Cybernetics_Core 1 6404
Protoss_Stargate 1 7578
Protoss_Citadel_of_Adun 1 7725
Protoss_Dragoon 1 8423
Protoss_Corsair 2 9688
Protoss_Templar_Archives 1 10359
Protoss_Robotics_Facility 1 10967
10967
