Protoss_Forge 1 3306
Protoss_Nexus 1 5017
Protoss_Photon_Cannon 7 10735
Protoss_Gateway 2 9497
Protoss_Zealot 6 8468
Protoss_Assimilator 2 7549
Protoss_Cybernetics_Core 1 7057
Protoss_Stargate 1 8210
Protoss_Citadel_of_Adun 1 8623
Protoss_Corsair 3 10354
Protoss_Templar_Archives 1 10036
10735
