Protoss_Forge 1 2677
Protoss_Photon_Cannon 5 10465
Protoss_Nexus 1 5607
Protoss_Gateway 3 8072
Protoss_Assimilator 2 8920
Protoss_Cybernetics_Core 1 6641
Protoss_Zealot 9 9433
Protoss_Citadel_of_Adun 1 7824
Protoss_Templar_Archives 1 9369
Protoss_High_Templar 2 10263
Protoss_Dark_Templar 1 10373
10465
