Protoss_Nexus 1 4876
Protoss_Forge 1 4015
Protoss_Photon_Cannon 2 8400
Protoss_Gateway 5 10818
Protoss_Assimilator 1 5414
Protoss_Zealot 5 10343
Protoss_Cybernetics_Core 1 7561
Protoss_Citadel_of_Adun 1 8775
Protoss_Robotics_Facility 1 10327
10818
