Protoss_Forge 1 3101
Protoss_Nexus 1 5641
Protoss_Assimilator 2 7606
Protoss_Gateway 2 5769
Protoss_Photon_Cannon 2 8472
Protoss_Cybernetics_Core 1 6859
Protoss_Zealot 5 9370
Protoss_Dragoon 2 7868
Protoss_Citadel_of_Adun 1 8299
Protoss_Robotics_Facility 1 9579
Protoss_Templar_Archives 1 9435
Protoss_Dark_Templar 2 10308
Protoss_Shuttle 1 10577
Protoss_Ground_Weapons_1 1 9826
10577
