Protoss_Forge 1 3038
Protoss_Photon_Cannon 4 10616
Protoss_Nexus 1 6431
Protoss_Gateway 3 9074
Protoss_Assimilator 2 7574
Protoss_Cybernetics_Core 1 7049
Protoss_Zealot 3 10193
Protoss_Citadel_of_Adun 1 8074
Protoss_Stargate 1 8966
Protoss_Dragoon 1 8758
Protoss_Templar_Archives 1 9424
Protoss_Corsair 2 10295
Protoss_High_Templar 2 10563
10616
