Protoss_Forge 1 2882
Protoss_Photon_Cannon 5 10350
Protoss_Nexus 1 5853
Protoss_Gateway 5 10866
Protoss_Assimilator 2 7304
Protoss_Cybernetics_Core 1 6239
Protoss_Zealot 2 6676
Protoss_Citadel_of_Adun 1 7385
Protoss_Templar_Archives 1 8531
Protoss_Dark_Templar 2 9462
Protoss_High_Templar 2 10214
10866
