Protoss_Forge 1 2752
Protoss_Nexus 1 5123
Protoss_Gateway 3 9322
Protoss_Assimilator 2 7659
Protoss_Zealot 10 10068
Protoss_Cybernetics_Core 1 5703
Protoss_Photon_Cannon 1 5876
Protoss_Stargate 1 6985
Protoss_Corsair 2 8414
Protoss_Citadel_of_Adun 1 8379
Protoss_Robotics_Facility 1 10506
Protoss_Templar_Archives 1 10696
10696
