Protoss_Forge 1 2827
Protoss_Photon_Cannon 8 10577
Protoss_Nexus 1 5552
Protoss_Gateway 1 5727
Protoss_Assimilator 2 7874
Protoss_Zealot 5 8884
Protoss_Cybernetics_Core 1 6934
Protoss_Citadel_of_Adun 1 8311
Protoss_Templar_Archives 1 9384
Protoss_High_Templar 1 10226
10577
