Protoss_Forge 1 2672
Protoss_Photon_Cannon 4 10325
Protoss_Nexus 1 5670
Protoss_Gateway 4 9317
Protoss_Assimilator 2 7693
Protoss_Zealot 7 10393
Protoss_Cybernetics_Core 1 7041
Protoss_Stargate 1 8733
Protoss_Dragoon 1 8593
Protoss_Corsair 1 9423
Protoss_Citadel_of_Adun 1 10759
10759
