Protoss_Gateway 2 6355
Protoss_Assimilator 2 10576
Protoss_Zealot 7 7664
Protoss_Cybernetics_Core 1 4713
Protoss_Dragoon 1 5544
Protoss_Citadel_of_Adun 1 5976
Protoss_Templar_Archives 1 7688
Protoss_Forge 1 8284
Protoss_High_Templar 4 9456
Protoss_Archon 1 9060
Protoss_Nexus 1 10650
Protoss_Photon_Cannon 4 10183
10650
