Protoss_Forge 1 3368
Protoss_Photon_Cannon 8 8962
Protoss_Nexus 1 6403
Protoss_Gateway 2 10786
Protoss_Assimilator 2 7335
Protoss_Cybernetics_Core 1 7114
Protoss_Zealot 2 7764
Protoss_Stargate 2 9554
Protoss_Corsair 4 10392
10786
