Protoss_Nexus 1 4739
Protoss_Forge 1 3756
Protoss_Photon_Cannon 2 4868
Protoss_Gateway 6 10469
Protoss_Assimilator 2 8222
Protoss_Zealot 6 10568
Protoss_Cybernetics_Core 1 6729
Protoss_Dragoon 1 7970
Protoss_Stargate 1 8438
Protoss_Citadel_of_Adun 1 9001
Protoss_Corsair 1 9132
10568
