Protoss_Nexus 1 4690
Protoss_Forge 1 4087
Protoss_Gateway 3 10199
Protoss_Assimilator 2 6550
Protoss_Photon_Cannon 2 6315
Protoss_Cybernetics_Core 1 6084
Protoss_Zealot 1 6808
Protoss_Stargate 2 8731
Protoss_Robotics_Facility 1 8492
Protoss_Citadel_of_Adun 1 8643
Protoss_Corsair 4 9673
Protoss_Templar_Archives 1 9797
Protoss_Dark_Templar 2 10663
10663
