Protoss_Gateway 2 8884
Protoss_Zealot 6 7104
Protoss_Assimilator 1 4042
Protoss_Cybernetics_Core 1 5127
Protoss_Stargate 1 6357
Protoss_Forge 1 6152
Protoss_Dragoon 1 6582
Protoss_Photon_Cannon 2 9536
Protoss_Citadel_of_Adun 1 8476
9536
