Protoss_Gateway 1 2777
Protoss_Assimilator 1 2890
Protoss_Zealot 8 8810
Protoss_Cybernetics_Core 1 4633
Protoss_Dragoon 1 5532
Protoss_Stargate 1 6105
Protoss_Citadel_of_Adun 1 6638
Protoss_Corsair 1 6976
Protoss_Templar_Archives 1 8127
Protoss_Forge 1 8236
Protoss_Dark_Templar 2 9744
Protoss_Photon_Cannon 3 10106
Protoss_High_Templar 1 10534
10534
