Protoss_Gateway 2 8018
Protoss_Zealot 5 8906
Protoss_Assimilator 1 3814
Protoss_Cybernetics_Core 1 5007
Protoss_Stargate 1 6317
Protoss_Dragoon 1 6534
Protoss_Citadel_of_Adun 1 6895
Protoss_Corsair 2 10286
Protoss_Templar_Archives 1 8300
Protoss_Forge 1 8699
Protoss_Dark_Templar 1 9156
Protoss_Photon_Cannon 1 9546
Protoss_High_Templar 1 9940
Protoss_Nexus 1 11592
11592
