Protoss_Nexus 1 4769
Protoss_Gateway 5 10554
Protoss_Forge 1 4540
Protoss_Photon_Cannon 4 8732
Protoss_Zealot 4 8250
Protoss_Assimilator 2 7260
Protoss_Cybernetics_Core 1 6717
Protoss_Dragoon 1 7584
Protoss_Stargate 1 8174
Protoss_Citadel_of_Adun 1 8370
Protoss_Corsair 1 8934
Protoss_Templar_Archives 1 9425
Protoss_Dark_Templar 1 10304
10554
