Protoss_Forge 1 2852
Protoss_Photon_Cannon 2 4863
Protoss_Nexus 1 5568
Protoss_Gateway 4 10815
Protoss_Assimilator 1 5511
Protoss_Cybernetics_Core 1 6710
Protoss_Zealot 14 10553
Protoss_Citadel_of_Adun 1 7784
Protoss_Templar_Archives 1 9896
10815
