Protoss_Gateway 1 2862
Protoss_Zealot 3 7116
Protoss_Assimilator 1 3864
Protoss_Cybernetics_Core 1 4977
Protoss_Dragoon 1 5806
Protoss_Stargate 1 6232
Protoss_Forge 1 6592
Protoss_Corsair 1 6954
Protoss_Photon_Cannon 3 10466
Protoss_Nexus 1 10079
10466
