Protoss_Gateway 3 10531
Protoss_Assimilator 1 3047
Protoss_Cybernetics_Core 1 3899
Protoss_Zealot 3 6402
Protoss_Citadel_of_Adun 1 5334
Protoss_Templar_Archives 1 6363
Protoss_Stargate 1 6989
Protoss_Dark_Templar 4 9762
Protoss_Corsair 1 7812
10531
