Protoss_Forge 1 2782
Protoss_Photon_Cannon 2 4341
Protoss_Nexus 1 6506
Protoss_Gateway 4 10798
Protoss_Assimilator 2 10017
Protoss_Cybernetics_Core 1 6894
Protoss_Dragoon 1 7738
Protoss_Zealot 10 10467
Protoss_Citadel_of_Adun 1 8254
Protoss_Templar_Archives 1 9936
10798
