Protoss_Forge 1 2683
Protoss_Photon_Cannon 5 10637
Protoss_Nexus 1 5781
Protoss_Gateway 3 9211
Protoss_Assimilator 1 5012
Protoss_Zealot 7 9960
Protoss_Cybernetics_Core 1 7236
Protoss_Citadel_of_Adun 1 8572
Protoss_Dragoon 1 9348
Protoss_Templar_Archives 1 10653
10653
