Protoss_Nexus 1 4945
Protoss_Gateway 2 8872
Protoss_Assimilator 2 6346
Protoss_Cybernetics_Core 1 5925
Protoss_Zealot 2 9264
Protoss_Stargate 1 7079
Protoss_Dragoon 1 7376
Protoss_Citadel_of_Adun 1 7705
Protoss_Corsair 4 10050
Protoss_Templar_Archives 1 8698
Protoss_Forge 1 8987
Protoss_Dark_Templar 2 9800
Protoss_Photon_Cannon 2 10740
10740
