Protoss_Forge 1 2446
Protoss_Nexus 1 5011
Protoss_Gateway 3 7893
Protoss_Photon_Cannon 2 8142
Protoss_Assimilator 2 10274
Protoss_Zealot 13 10156
Protoss_Cybernetics_Core 1 6304
Protoss_Citadel_of_Adun 1 7373
Protoss_Templar_Archives 1 9331
10274
