Protoss_Forge 1 3107
Protoss_Nexus 1 5293
Protoss_Gateway 4 9822
Protoss_Assimilator 2 7322
Protoss_Photon_Cannon 2 5664
Protoss_Cybernetics_Core 1 6365
Protoss_Zealot 4 9750
Protoss_Stargate 1 7506
Protoss_Citadel_of_Adun 1 8163
Protoss_Dragoon 1 8342
Protoss_Corsair 1 8316
Protoss_Templar_Archives 1 9465
Protoss_Robotics_Facility 1 10591
Protoss_Dark_Templar 1 10502
Protoss_High_Templar 3 10710
10710
