Protoss_Forge 1 2868
Protoss_Photon_Cannon 2 4824
Protoss_Nexus 1 5553
Protoss_Gateway 1 5569
Protoss_Assimilator 1 5593
Protoss_Cybernetics_Core 1 6638
Protoss_Zealot 3 8272
8272
