Protoss_Forge 1 3012
Protoss_Nexus 1 5298
Protoss_Gateway 6 10413
Protoss_Assimilator 2 7514
Protoss_Photon_Cannon 2 6737
Protoss_Cybernetics_Core 1 6139
Protoss_Zealot 5 9402
Protoss_Citadel_of_Adun 1 7683
Protoss_Templar_Archives 1 8998
Protoss_Robotics_Facility 1 10891
10891
