Protoss_Forge 1 2909
Protoss_Nexus 1 5185
Protoss_Photon_Cannon 3 9684
Protoss_Gateway 1 5233
Protoss_Assimilator 2 6841
Protoss_Cybernetics_Core 1 6480
Protoss_Zealot 3 8218
9684
