Protoss_Forge 1 2969
Protoss_Nexus 1 5171
Protoss_Photon_Cannon 3 8522
Protoss_Gateway 4 9794
Protoss_Assimilator 2 7017
Protoss_Cybernetics_Core 1 6479
Protoss_Zealot 1 6456
Protoss_Dragoon 1 7314
Protoss_Stargate 1 7860
Protoss_Citadel_of_Adun 1 8188
Protoss_Corsair 1 8546
Protoss_Templar_Archives 1 9277
Protoss_Dark_Templar 2 10188
Protoss_Robotics_Facility 1 11049
11049
