Protoss_Forge 1 2568
Protoss_Photon_Cannon 6 10598
Protoss_Gateway 1 5391
Protoss_Nexus 1 6693
Protoss_Assimilator 2 7628
Protoss_Cybernetics_Core 1 7851
Protoss_Zealot 2 10014
Protoss_Stargate 1 9156
Protoss_Dragoon 1 9072
Protoss_Citadel_of_Adun 1 9559
Protoss_Corsair 1 9992
Protoss_Templar_Archives 1 10606
10606
