Protoss_Forge 1 2533
Protoss_Photon_Cannon 3 9371
Protoss_Nexus 1 5930
Protoss_Gateway 2 8652
Protoss_Cybernetics_Core 1 6364
Protoss_Assimilator 2 8051
Protoss_Zealot 8 10032
Protoss_Stargate 1 8178
Protoss_Citadel_of_Adun 1 8993
Protoss_Corsair 1 9123
Protoss_Templar_Archives 1 10594
10594
