Protoss_Nexus 1 4673
Protoss_Gateway 3 8067
Protoss_Forge 1 4234
Protoss_Assimilator 2 8822
Protoss_Photon_Cannon 2 7385
Protoss_Cybernetics_Core 1 5984
Protoss_Zealot 12 10440
Protoss_Dragoon 1 6964
Protoss_Citadel_of_Adun 1 7262
Protoss_Templar_Archives 1 9780
10440
