Protoss_Forge 1 2783
Protoss_Photon_Cannon 3 7787
Protoss_Gateway 2 10852
Protoss_Nexus 1 5863
Protoss_Assimilator 2 9446
Protoss_Zealot 5 10046
Protoss_Cybernetics_Core 1 6946
Protoss_Stargate 1 9080
Protoss_Dragoon 1 8962
Protoss_Citadel_of_Adun 1 9554
Protoss_Corsair 1 10058
Protoss_Templar_Archives 1 10650
10852
