Protoss_Gateway 1 2615
Protoss_Zealot 12 10468
Protoss_Nexus 1 6817
Protoss_Forge 1 6882
Protoss_Assimilator 2 8831
Protoss_Photon_Cannon 6 10581
Protoss_Cybernetics_Core 1 8813
Protoss_Stargate 1 10035
Protoss_Citadel_of_Adun 1 10296
10581
