Protoss_Forge 1 2909
Protoss_Nexus 1 5384
Protoss_Gateway 3 10745
Protoss_Photon_Cannon 3 9279
Protoss_Zealot 12 10234
Protoss_Assimilator 2 7463
Protoss_Cybernetics_Core 1 8124
Protoss_Citadel_of_Adun 1 9200
Protoss_Templar_Archives 1 10194
10745
