Protoss_Nexus 1 4831
Protoss_Gateway 5 10033
Protoss_Forge 1 4320
Protoss_Assimilator 2 6484
Protoss_Photon_Cannon 1 5234
Protoss_Zealot 2 6138
Protoss_Cybernetics_Core 1 6279
Protoss_Stargate 1 7464
Protoss_Citadel_of_Adun 1 7487
Protoss_Dragoon 1 7362
Protoss_Templar_Archives 1 8483
Protoss_Corsair 1 8296
Protoss_Dark_Templar 2 10166
Protoss_High_Templar 4 10684
10684
