Protoss_Forge 1 2603
Protoss_Photon_Cannon 5 9895
Protoss_Nexus 2 11619
Protoss_Gateway 1 5635
Protoss_Assimilator 2 7788
Protoss_Cybernetics_Core 1 6717
Protoss_Zealot 2 7034
Protoss_Stargate 1 7965
Protoss_Corsair 3 9960
Protoss_Robotics_Facility 1 9766
11619
