Protoss_Forge 1 2565
Protoss_Photon_Cannon 4 10374
Protoss_Nexus 1 5283
Protoss_Gateway 4 9662
Protoss_Assimilator 2 6470
Protoss_Cybernetics_Core 1 6586
Protoss_Zealot 3 8902
Protoss_Stargate 1 7754
Protoss_Citadel_of_Adun 1 7877
Protoss_Corsair 1 8518
Protoss_Templar_Archives 1 8907
Protoss_Dark_Templar 1 9736
Protoss_High_Templar 3 10656
10656
