Protoss_Gateway 1 2855
Protoss_Assimilator 2 9706
Protoss_Cybernetics_Core 1 3939
Protoss_Stargate 1 5103
Protoss_Corsair 7 9694
Protoss_Nexus 1 7992
Protoss_Robotics_Facility 1 8347
Protoss_Shield_Battery 1 9097
Protoss_Robotics_Support_Bay 1 9296
Protoss_Shuttle 1 10332
10332
