Protoss_Forge 1 2540
Protoss_Photon_Cannon 3 6080
Protoss_Nexus 1 6171
Protoss_Gateway 3 9742
Protoss_Assimilator 2 7341
Protoss_Cybernetics_Core 1 6787
Protoss_Zealot 5 9520
Protoss_Stargate 1 8098
Protoss_Citadel_of_Adun 1 8404
Protoss_Corsair 2 9708
Protoss_Templar_Archives 1 9432
Protoss_Dark_Templar 3 10590
10590
