Protoss_Forge 1 2585
Protoss_Photon_Cannon 5 10676
Protoss_Nexus 1 5803
Protoss_Gateway 3 10526
Protoss_Zealot 5 9186
Protoss_Assimilator 2 8755
Protoss_Cybernetics_Core 1 7673
Protoss_Citadel_of_Adun 1 8853
Protoss_Templar_Archives 1 9879
Protoss_High_Templar 1 10730
10730
