Protoss_Gateway 3 10717
Protoss_Forge 1 3218
Protoss_Photon_Cannon 3 10034
Protoss_Nexus 1 6818
Protoss_Assimilator 2 7506
Protoss_Zealot 3 9000
Protoss_Cybernetics_Core 1 6943
Protoss_Stargate 1 8166
Protoss_Dragoon 1 8142
Protoss_Citadel_of_Adun 1 8980
Protoss_Corsair 3 10140
Protoss_Templar_Archives 1 10060
10717
