Protoss_Forge 1 2758
Protoss_Nexus 1 4950
Protoss_Photon_Cannon 4 9311
Protoss_Gateway 3 10556
Protoss_Assimilator 2 7624
Protoss_Zealot 6 9688
Protoss_Cybernetics_Core 1 6983
Protoss_Stargate 1 8135
Protoss_Citadel_of_Adun 1 8744
Protoss_Corsair 2 9472
Protoss_Templar_Archives 1 9887
10556
