Protoss_Forge 2 9051
Protoss_Photon_Cannon 3 9976
Protoss_Nexus 1 5411
Protoss_Gateway 5 10631
Protoss_Assimilator 2 8284
Protoss_Zealot 5 9116
Protoss_Cybernetics_Core 1 6353
Protoss_Citadel_of_Adun 1 7539
Protoss_Templar_Archives 1 9291
Protoss_High_Templar 2 10132
10631
