Protoss_Forge 1 2504
Protoss_Photon_Cannon 2 4030
Protoss_Gateway 1 3833
Protoss_Zealot 3 6556
Protoss_Assimilator 1 4842
Protoss_Cybernetics_Core 1 6065
Protoss_Stargate 1 7208
Protoss_Corsair 4 10544
Protoss_Nexus 1 9467
Protoss_Citadel_of_Adun 1 8818
10544
