Protoss_Forge 1 3124
Protoss_Photon_Cannon 2 4810
Protoss_Nexus 1 5482
Protoss_Gateway 5 10414
Protoss_Assimilator 2 7451
Protoss_Zealot 5 10396
Protoss_Cybernetics_Core 1 7097
Protoss_Stargate 1 8306
Protoss_Dragoon 1 8180
Protoss_Citadel_of_Adun 1 8644
Protoss_Corsair 1 9086
10414
