Protoss_Gateway 2 7054
Protoss_Assimilator 1 2960
Protoss_Zealot 7 9164
Protoss_Cybernetics_Core 1 4531
Protoss_Dragoon 1 5382
Protoss_Citadel_of_Adun 1 6069
Protoss_Templar_Archives 1 7315
Protoss_High_Templar 4 9960
Protoss_Nexus 1 9843
Protoss_Archon 1 8631
Protoss_Forge 1 9409
Protoss_Photon_Cannon 2 10432
10432
