Protoss_Forge 1 2544
Protoss_Photon_Cannon 2 3836
Protoss_Nexus 1 6039
Protoss_Gateway 4 10587
Protoss_Assimilator 2 7381
Protoss_Cybernetics_Core 1 7047
Protoss_Zealot 5 9714
Protoss_Stargate 1 8402
Protoss_Citadel_of_Adun 1 8758
Protoss_Corsair 1 9176
Protoss_Templar_Archives 1 9896
10587
