Protoss_Forge 1 2763
Protoss_Assimilator 1 2906
Protoss_Photon_Cannon 1 3724
Protoss_Gateway 2 5359
Protoss_Zealot 9 8716
Protoss_Cybernetics_Core 1 5999
Protoss_Citadel_of_Adun 1 7169
Protoss_Templar_Archives 1 8251
Protoss_Ground_Weapons_1 1 7737
Protoss_Dark_Templar 3 10308
10308
