Protoss_Nexus 2 10946
Protoss_Gateway 2 7926
Protoss_Assimilator 2 6614
Protoss_Forge 1 5016
Protoss_Cybernetics_Core 1 5595
Protoss_Photon_Cannon 5 10568
Protoss_Zealot 2 7912
Protoss_Stargate 1 6775
Protoss_Dragoon 1 6978
Protoss_Citadel_of_Adun 1 7441
Protoss_Corsair 3 8800
Protoss_Templar_Archives 1 8431
Protoss_Dark_Templar 2 9450
Protoss_High_Templar 2 10202
10946
