Protoss_Forge 1 3048
Protoss_Nexus 1 5198
Protoss_Gateway 1 4889
Protoss_Assimilator 2 7006
Protoss_Photon_Cannon 3 9372
Protoss_Zealot 3 9456
Protoss_Cybernetics_Core 1 6820
Protoss_Dragoon 1 7876
Protoss_Stargate 1 8230
Protoss_Robotics_Facility 1 8911
Protoss_Corsair 3 10522
Protoss_Shuttle 1 9911
Protoss_Robotics_Support_Bay 1 9933
10522
