Protoss_Gateway 1 2819
Protoss_Assimilator 1 2810
Protoss_Zealot 8 8348
Protoss_Cybernetics_Core 1 5288
Protoss_Citadel_of_Adun 1 6429
Protoss_Templar_Archives 1 7828
Protoss_Forge 1 8202
Protoss_High_Templar 3 10268
Protoss_Photon_Cannon 4 10480
Psionic_Storm 1 9896
10480
