Protoss_Nexus 1 4791
Protoss_Forge 1 4001
Protoss_Gateway 2 5545
Protoss_Zealot 7 10294
Protoss_Assimilator 2 8915
Protoss_Cybernetics_Core 1 7393
Protoss_Stargate 2 9294
10294
