Protoss_Forge 1 2721
Protoss_Photon_Cannon 1 3734
Protoss_Nexus 1 5668
Protoss_Gateway 4 9979
Protoss_Assimilator 2 9053
Protoss_Zealot 10 10274
Protoss_Cybernetics_Core 1 6363
Protoss_Dragoon 1 7274
Protoss_Citadel_of_Adun 1 7537
Protoss_Templar_Archives 1 9524
10274
