Protoss_Forge 1 2610
Protoss_Photon_Cannon 2 3824
Protoss_Nexus 1 5927
Protoss_Gateway 1 5303
Protoss_Assimilator 2 8743
Protoss_Zealot 2 8660
Protoss_Cybernetics_Core 1 6633
Protoss_Dragoon 1 7492
Protoss_Stargate 1 8012
Protoss_Robotics_Facility 1 9061
Protoss_Corsair 1 8770
Protoss_Robotics_Support_Bay 1 9833
9833
