Protoss_Forge 1 2783
Protoss_Photon_Cannon 5 10462
Protoss_Nexus 1 5367
Protoss_Gateway 1 5491
Protoss_Zealot 5 9304
Protoss_Assimilator 2 10221
Protoss_Cybernetics_Core 1 8767
Protoss_Stargate 1 10016
Protoss_Dragoon 1 10353
Protoss_Citadel_of_Adun 1 10889
10889
