Protoss_Gateway 2 6867
Protoss_Assimilator 1 3096
Protoss_Zealot 8 9204
Protoss_Cybernetics_Core 1 5143
Protoss_Dragoon 1 6212
Protoss_Citadel_of_Adun 1 6445
Protoss_Templar_Archives 1 7437
Protoss_Forge 1 8284
Protoss_High_Templar 4 9956
Protoss_Archon 1 8975
Protoss_Photon_Cannon 4 10173
Protoss_Nexus 1 11773
11773
