Protoss_Forge 1 2790
Protoss_Photon_Cannon 4 9621
Protoss_Nexus 1 6093
Protoss_Gateway 3 10713
Protoss_Assimilator 2 7867
Protoss_Cybernetics_Core 1 6539
Protoss_Zealot 5 10237
Protoss_Stargate 1 7808
Protoss_Citadel_of_Adun 1 8025
Protoss_Corsair 1 9002
Protoss_Robotics_Facility 1 9831
Protoss_Templar_Archives 1 10071
10713
