Protoss_Forge 2 8585
Protoss_Photon_Cannon 3 9769
Protoss_Gateway 2 5910
Protoss_Assimilator 1 4690
Protoss_Cybernetics_Core 1 6905
Protoss_Zealot 3 7912
Protoss_Stargate 1 8051
Protoss_Citadel_of_Adun 1 8141
Protoss_Dragoon 1 8664
Protoss_Corsair 2 9571
Protoss_Templar_Archives 1 9153
Protoss_Dark_Templar 1 9986
Protoss_Nexus 1 11544
Protoss_High_Templar 1 10738
11544
