Protoss_Forge 1 2666
Protoss_Photon_Cannon 2 4767
Protoss_Nexus 1 5459
Protoss_Gateway 1 5401
Protoss_Assimilator 2 7974
Protoss_Zealot 6 10020
Protoss_Cybernetics_Core 1 6853
Protoss_Citadel_of_Adun 1 8711
Protoss_Dragoon 1 8728
10020
