Protoss_Forge 1 2821
Protoss_Photon_Cannon 3 6686
Protoss_Nexus 1 5755
Protoss_Gateway 1 5513
Protoss_Assimilator 2 8586
Protoss_Zealot 6 9720
Protoss_Cybernetics_Core 1 8146
Protoss_Stargate 1 9402
Protoss_Citadel_of_Adun 1 9485
Protoss_Corsair 1 10082
Protoss_Templar_Archives 1 10671
Protoss_Dragoon 1 10600
10671
