Protoss_Forge 2 9635
Protoss_Photon_Cannon 8 10470
Protoss_Gateway 2 10293
Protoss_Zealot 2 5730
Protoss_Nexus 1 6459
Protoss_Assimilator 1 5546
Protoss_Cybernetics_Core 1 7183
10470
