Protoss_Forge 1 2636
Protoss_Photon_Cannon 6 10366
Protoss_Nexus 2 8627
Protoss_Gateway 1 6119
Protoss_Assimilator 2 8284
Protoss_Cybernetics_Core 1 7185
Protoss_Zealot 4 9208
Protoss_Stargate 1 8380
Protoss_Dragoon 1 8194
Protoss_Citadel_of_Adun 1 8937
Protoss_Corsair 2 9828
Protoss_Templar_Archives 1 10029
10366
