Protoss_Forge 1 2828
Protoss_Nexus 1 5381
Protoss_Gateway 4 9851
Protoss_Photon_Cannon 3 8805
Protoss_Assimilator 2 7126
Protoss_Cybernetics_Core 1 6787
Protoss_Zealot 8 10546
Protoss_Stargate 1 8018
Protoss_Citadel_of_Adun 1 8515
Protoss_Corsair 1 8714
Protoss_Templar_Archives 1 10775
10775
