Protoss_Gateway 2 7997
Protoss_Assimilator 1 3054
Protoss_Zealot 2 4640
Protoss_Cybernetics_Core 1 4623
Protoss_Stargate 1 5828
Protoss_Dragoon 1 5830
Protoss_Citadel_of_Adun 1 6488
Protoss_Corsair 1 6540
Protoss_Forge 1 7130
Protoss_Templar_Archives 1 7527
Protoss_Dark_Templar 2 8846
Protoss_Photon_Cannon 3 10655
Protoss_Nexus 1 10921
Protoss_High_Templar 2 10548
10921
