Protoss_Gateway 2 3449
Protoss_Zealot 11 10378
Protoss_Assimilator 1 5400
Protoss_Cybernetics_Core 1 7261
Protoss_Forge 1 7990
Protoss_Dragoon 4 9503
Protoss_Photon_Cannon 1 9346
10378
