Protoss_Gateway 2 7842
Protoss_Assimilator 1 3052
Protoss_Zealot 10 8612
Protoss_Cybernetics_Core 1 5061
Protoss_Citadel_of_Adun 1 6573
Protoss_Templar_Archives 1 8595
Protoss_Forge 1 9170
Protoss_High_Templar 3 10356
Protoss_Dark_Templar 1 9604
Protoss_Photon_Cannon 1 10501
Protoss_Stargate 1 10928
10928
