Protoss_Forge 1 2762
Protoss_Photon_Cannon 3 9238
Protoss_Nexus 1 5590
Protoss_Gateway 4 10732
Protoss_Assimilator 2 7024
Protoss_Cybernetics_Core 1 6259
Protoss_Zealot 4 9706
Protoss_Stargate 1 7755
Protoss_Citadel_of_Adun 1 8389
Protoss_Corsair 1 8568
Protoss_Templar_Archives 1 9489
Protoss_Robotics_Facility 1 9948
Protoss_Dark_Templar 1 10458
10732
