Protoss_Gateway 3 10885
Protoss_Assimilator 1 2962
Protoss_Cybernetics_Core 1 3860
Protoss_Zealot 2 4640
Protoss_Dragoon 10 10456
Protoss_Stargate 1 6453
Protoss_Robotics_Facility 1 7067
Protoss_Shuttle 1 8207
Protoss_Robotics_Support_Bay 1 8286
Protoss_Reaver 1 9768
10885
