Protoss_Nexus 1 4658
Protoss_Forge 1 3916
Protoss_Photon_Cannon 2 8175
Protoss_Gateway 1 5197
Protoss_Assimilator 2 6292
Protoss_Cybernetics_Core 1 6201
Protoss_Zealot 3 10378
Protoss_Stargate 1 7336
Protoss_Dragoon 1 7408
Protoss_Robotics_Facility 1 8385
Protoss_Corsair 4 10046
Protoss_Shuttle 1 9391
Protoss_Robotics_Support_Bay 1 9067
Protoss_Reaver 1 10442
10442
