Protoss_Forge 1 3346
Protoss_Photon_Cannon 4 9744
Protoss_Nexus 1 6043
Protoss_Gateway 1 5533
Protoss_Assimilator 2 6824
Protoss_Cybernetics_Core 1 6591
Protoss_Zealot 5 10398
Protoss_Dragoon 1 7710
Protoss_Stargate 1 8459
Protoss_Robotics_Facility 1 9415
Protoss_Corsair 3 10414
Protoss_Shuttle 1 10879
10879
