Protoss_Forge 1 2730
Protoss_Photon_Cannon 5 10317
Protoss_Nexus 1 5555
Protoss_Gateway 2 9456
Protoss_Assimilator 2 7350
Protoss_Zealot 3 8150
Protoss_Cybernetics_Core 1 7025
Protoss_Stargate 1 8353
Protoss_Citadel_of_Adun 1 8838
Protoss_Corsair 2 10398
Protoss_Templar_Archives 1 9866
10398
