Protoss_Forge 1 2711
Protoss_Nexus 1 4895
Protoss_Photon_Cannon 3 6959
Protoss_Gateway 1 5167
Protoss_Assimilator 2 8630
Protoss_Zealot 4 10076
Protoss_Cybernetics_Core 1 6452
Protoss_Stargate 1 8277
Protoss_Dragoon 1 8106
Protoss_Corsair 3 10314
Protoss_Citadel_of_Adun 1 10178
10314
