Protoss_Forge 1 2842
Protoss_Nexus 1 4993
Protoss_Gateway 4 10729
Protoss_Photon_Cannon 6 10360
Protoss_Assimilator 2 6828
Protoss_Cybernetics_Core 1 5853
Protoss_Zealot 5 10140
Protoss_Stargate 1 7140
Protoss_Dragoon 1 7080
Protoss_Corsair 2 8858
Protoss_Citadel_of_Adun 1 8411
Protoss_Templar_Archives 1 9817
Protoss_High_Templar 2 10708
10729
