Protoss_Forge 1 2819
Protoss_Nexus 1 4978
Protoss_Gateway 1 4555
Protoss_Assimilator 2 6418
Protoss_Photon_Cannon 3 8747
Protoss_Cybernetics_Core 1 5765
Protoss_Zealot 3 10546
Protoss_Stargate 1 7026
Protoss_Dragoon 1 6838
Protoss_Robotics_Facility 1 7835
Protoss_Corsair 5 10408
Protoss_Shuttle 1 9045
Protoss_Robotics_Support_Bay 1 8884
Protoss_Reaver 1 10264
10546
