Protoss_Forge 1 3053
Protoss_Nexus 1 5359
Protoss_Gateway 4 10328
Protoss_Photon_Cannon 1 5212
Protoss_Zealot 14 10388
Protoss_Assimilator 2 7396
Protoss_Cybernetics_Core 1 7133
Protoss_Citadel_of_Adun 1 8627
Protoss_Templar_Archives 1 9981
Protoss_Robotics_Facility 1 10884
10884
