Protoss_Forge 1 2857
Protoss_Photon_Cannon 4 10315
Protoss_Nexus 1 7121
Protoss_Gateway 1 6573
Protoss_Assimilator 3 10400
Protoss_Cybernetics_Core 1 7647
Protoss_Zealot 3 8722
Protoss_Stargate 1 8944
Protoss_Citadel_of_Adun 1 9279
Protoss_Dragoon 1 9884
Protoss_Corsair 1 9828
Protoss_Templar_Archives 1 10570
10570
