Protoss_Forge 1 2754
Protoss_Nexus 1 4803
Protoss_Gateway 5 10827
Protoss_Assimilator 2 7020
Protoss_Cybernetics_Core 1 5474
Protoss_Photon_Cannon 3 9703
Protoss_Zealot 5 9632
Protoss_Stargate 1 6857
Protoss_Dragoon 1 7434
Protoss_Corsair 2 8299
Protoss_Citadel_of_Adun 1 8205
Protoss_Templar_Archives 1 9345
Protoss_Dark_Templar 2 10256
Protoss_Robotics_Facility 1 11151
11151
