Protoss_Gateway 2 3504
Protoss_Zealot 11 8328
Protoss_Assimilator 1 4587
Protoss_Cybernetics_Core 1 6914
Protoss_Citadel_of_Adun 1 7914
Protoss_Forge 1 7942
Protoss_Templar_Archives 1 9052
Protoss_Photon_Cannon 3 10146
Protoss_High_Templar 2 9993
Protoss_Nexus 1 11510
11510
