Protoss_Gateway 2 3746
Protoss_Zealot 6 8163
Protoss_Assimilator 1 4750
Protoss_Cybernetics_Core 1 6065
Protoss_Forge 1 6386
Protoss_Dragoon 1 6903
Protoss_Stargate 1 7436
Protoss_Citadel_of_Adun 1 8174
Protoss_Photon_Cannon 4 10720
Protoss_Nexus 1 10917
Protoss_Templar_Archives 1 10270
10917
