Protoss_Gateway 2 3364
Protoss_Zealot 4 8023
Protoss_Assimilator 1 4571
Protoss_Cybernetics_Core 1 5667
Protoss_Citadel_of_Adun 1 6880
Protoss_Dragoon 1 6788
Protoss_Templar_Archives 1 8095
Protoss_Forge 1 7942
Protoss_High_Templar 2 8958
Protoss_Photon_Cannon 6 10731
Protoss_Archon 1 9364
10731
