Protoss_Gateway 1 2799
Protoss_Assimilator 1 3013
Protoss_Zealot 7 10233
Protoss_Cybernetics_Core 1 4814
Protoss_Stargate 1 6012
Protoss_Corsair 2 7828
Protoss_Citadel_of_Adun 1 7239
Protoss_Forge 1 8461
Protoss_Nexus 1 10786
Protoss_Templar_Archives 1 10569
10786
