Protoss_Gateway 3 5984
Protoss_Zealot 14 10562
Protoss_Assimilator 1 3663
Protoss_Cybernetics_Core 1 5339
Protoss_Citadel_of_Adun 1 6359
Protoss_Forge 1 6540
Protoss_Photon_Cannon 3 9115
Protoss_Templar_Archives 1 10549
10562
