Protoss_Gateway 2 3590
Protoss_Zealot 13 9673
Protoss_Assimilator 1 4780
Protoss_Cybernetics_Core 1 6440
Protoss_Forge 1 7417
Protoss_Photon_Cannon 2 8855
Protoss_Nexus 1 10536
Protoss_Citadel_of_Adun 1 10344
10536
