Protoss_Gateway 1 2681
Protoss_Zealot 8 10162
Protoss_Forge 1 3548
Protoss_Photon_Cannon 5 8126
Protoss_Assimilator 1 6268
Protoss_Cybernetics_Core 1 9267
Protoss_Citadel_of_Adun 1 10407
Protoss_Stargate 1 10894
10894
