Protoss_Gateway 1 2784
Protoss_Assimilator 1 2850
Protoss_Cybernetics_Core 1 3804
Protoss_Stargate 1 4958
Protoss_Corsair 2 6250
Protoss_Forge 1 6291
Protoss_Robotics_Facility 1 7292
Protoss_Photon_Cannon 2 10660
Protoss_Robotics_Support_Bay 1 7927
Protoss_Shuttle 1 8377
Protoss_Dragoon 2 9553
Protoss_Reaver 2 10480
Protoss_Nexus 1 10892
10892
