Protoss_Forge 1 2760
Protoss_Nexus 1 5241
Protoss_Photon_Cannon 2 10033
Protoss_Assimilator 2 8736
Protoss_Gateway 3 6444
Protoss_Zealot 17 10155
Protoss_Cybernetics_Core 1 9196
10155
