Protoss_Gateway 2 3504
Protoss_Zealot 13 7555
Protoss_Assimilator 1 6780
Protoss_Cybernetics_Core 1 8274
Protoss_Forge 1 8384
Protoss_Robotics_Facility 1 9593
Protoss_Dragoon 1 9348
Protoss_Citadel_of_Adun 1 10202
Protoss_Shuttle 1 10587
10587
