Protoss_Assimilator 1 2270
Protoss_Gateway 1 3261
Protoss_Cybernetics_Core 1 4275
Protoss_Stargate 2 10245
Protoss_Robotics_Facility 1 5802
Protoss_Corsair 7 10532
Protoss_Shuttle 1 6907
Protoss_Fleet_Beacon 1 8224
Protoss_Forge 1 8169
Protoss_Photon_Cannon 1 9118
10532
