Protoss_Gateway 2 3457
Protoss_Zealot 10 7163
Protoss_Assimilator 1 5862
Protoss_Nexus 1 9888
Protoss_Cybernetics_Core 1 9346
Protoss_Dragoon 1 10193
Protoss_Robotics_Facility 1 10787
Protoss_Stargate 1 10818
10818
