Protoss_Gateway 1 2833
Protoss_Assimilator 1 3039
Protoss_Zealot 8 9140
Protoss_Cybernetics_Core 1 5022
Protoss_Citadel_of_Adun 1 6138
Protoss_Forge 1 6232
Protoss_Templar_Archives 1 8806
Protoss_Photon_Cannon 3 9625
Protoss_High_Templar 2 10664
10664
