Protoss_Gateway 1 2739
Protoss_Assimilator 2 4225
Protoss_Zealot 5 7228
Protoss_Cybernetics_Core 1 5649
Protoss_Stargate 1 6919
Protoss_Forge 1 6701
Protoss_Corsair 4 10483
Protoss_Citadel_of_Adun 1 8184
Protoss_Templar_Archives 1 9270
Protoss_Nexus 1 11045
Protoss_High_Templar 1 10108
Protoss_Photon_Cannon 1 10492
11045
