Protoss_Nexus 1 4930
Protoss_Forge 1 4031
Protoss_Photon_Cannon 6 10650
Protoss_Assimilator 2 6993
Protoss_Gateway 1 6680
Protoss_Cybernetics_Core 1 7884
Protoss_Stargate 1 9297
Protoss_Robotics_Facility 1 9743
Protoss_Corsair 1 10013
Protoss_Shuttle 1 10867
10867
