Protoss_Gateway 1 2750
Protoss_Forge 2 7439
Protoss_Zealot 6 9948
Protoss_Assimilator 1 4233
Protoss_Cybernetics_Core 1 5088
Protoss_Dragoon 1 5968
Protoss_Stargate 1 7216
Protoss_Corsair 2 8573
Protoss_Citadel_of_Adun 1 8312
Protoss_Photon_Cannon 2 10073
Protoss_Nexus 1 10395
Protoss_Templar_Archives 1 10537
Protoss_Shield_Battery 1 10201
10537
