Protoss_Gateway 1 2865
Protoss_Assimilator 1 3100
Protoss_Zealot 2 4868
Protoss_Cybernetics_Core 1 4590
Protoss_Stargate 1 5783
Protoss_Robotics_Facility 1 6350
Protoss_Dragoon 1 6098
Protoss_Corsair 2 10518
Protoss_Citadel_of_Adun 1 7248
Protoss_Robotics_Support_Bay 1 7111
Protoss_Forge 1 10035
10518
