Protoss_Gateway 2 3617
Protoss_Zealot 17 10488
Protoss_Assimilator 1 6847
Protoss_Cybernetics_Core 1 8451
Protoss_Citadel_of_Adun 1 9503
Protoss_Dragoon 1 9405
Protoss_Templar_Archives 1 10644
10644
