Protoss_Gateway 2 3384
Protoss_Zealot 5 7058
Protoss_Nexus 1 7374
Protoss_Assimilator 2 9025
Protoss_Cybernetics_Core 1 7003
Protoss_Stargate 1 8588
Protoss_Forge 1 8595
Protoss_Corsair 2 10053
Protoss_Photon_Cannon 3 10330
10330
