Protoss_Gateway 2 3334
Protoss_Zealot 15 9418
Protoss_Forge 1 5453
Protoss_Photon_Cannon 3 10220
Protoss_Assimilator 1 8388
Protoss_Cybernetics_Core 1 9451
Protoss_Robotics_Facility 1 11169
11169
