Protoss_Assimilator 1 2380
Protoss_Gateway 1 3197
Protoss_Cybernetics_Core 1 4371
Protoss_Stargate 1 5523
Protoss_Robotics_Facility 1 6198
Protoss_Corsair 5 10288
Protoss_Shuttle 1 7187
Protoss_Robotics_Support_Bay 1 6915
Protoss_Reaver 2 11041
Protoss_Air_Weapons_1 1 8511
Protoss_Forge 1 9327
Protoss_Shield_Battery 1 9581
Protoss_Photon_Cannon 2 10297
Protoss_Nexus 1 11620
11620
