Protoss_Nexus 1 4771
Protoss_Gateway 1 4254
Protoss_Forge 1 4250
Protoss_Zealot 2 5910
Protoss_Photon_Cannon 2 7312
Protoss_Assimilator 2 6816
Protoss_Cybernetics_Core 1 6758
Protoss_Stargate 1 8008
8008
