Protoss_Gateway 2 3689
Protoss_Assimilator 1 3805
Protoss_Cybernetics_Core 1 4699
Protoss_Zealot 5 8650
Protoss_Stargate 1 6304
Protoss_Citadel_of_Adun 1 6829
Protoss_Dragoon 1 6983
8650
