Protoss_Gateway 2 6915
Protoss_Assimilator 1 3287
Protoss_Zealot 8 9423
Protoss_Cybernetics_Core 1 5087
Protoss_Shield_Battery 1 5347
Protoss_Dragoon 1 6088
Protoss_Stargate 1 6438
Protoss_Citadel_of_Adun 1 7098
Protoss_Corsair 1 7123
Protoss_Templar_Archives 1 9461
Protoss_Forge 1 9242
9461
