Protoss_Gateway 3 9797
Protoss_Assimilator 1 3157
Protoss_Zealot 2 4833
Protoss_Forge 1 4783
Protoss_Photon_Cannon 1 5706
Protoss_Cybernetics_Core 1 6549
Protoss_Stargate 1 7817
Protoss_Citadel_of_Adun 1 7723
Protoss_Dragoon 1 7618
Protoss_Corsair 3 10317
Protoss_Ground_Weapons_1 1 9011
10317
