Protoss_Gateway 2 3321
Protoss_Zealot 7 5359
Protoss_Assimilator 1 6463
Protoss_Cybernetics_Core 1 6972
Protoss_Forge 1 7890
Protoss_Nexus 1 9573
Protoss_Photon_Cannon 3 10052
Protoss_Citadel_of_Adun 1 9859
10052
