Protoss_Assimilator 1 2419
Protoss_Gateway 1 3156
Protoss_Cybernetics_Core 1 4154
Protoss_Dragoon 1 4993
Protoss_Stargate 1 5363
Protoss_Robotics_Facility 1 6100
Protoss_Corsair 3 8423
Protoss_Zealot 3 8302
Protoss_Robotics_Support_Bay 1 7555
Protoss_Reaver 1 9651
Protoss_Air_Weapons_1 1 9176
9651
