Protoss_Forge 1 2729
Protoss_Photon_Cannon 5 9451
Protoss_Nexus 1 6245
Protoss_Gateway 3 9297
Protoss_Assimilator 1 6791
Protoss_Cybernetics_Core 1 8219
Protoss_Zealot 4 10088
Protoss_Citadel_of_Adun 1 9297
Protoss_Templar_Archives 1 10888
10888
