Protoss_Gateway 2 10047
Protoss_Assimilator 1 2945
Protoss_Zealot 4 7515
Protoss_Cybernetics_Core 1 4500
Protoss_Stargate 1 5653
Protoss_Dragoon 1 5800
Protoss_Robotics_Facility 1 6982
Protoss_Shuttle 1 8067
Protoss_Robotics_Support_Bay 1 7631
Protoss_Reaver 1 9286
Protoss_Forge 1 9086
10047
