Protoss_Assimilator 1 2339
Protoss_Gateway 1 3164
Protoss_Cybernetics_Core 1 4160
Protoss_Dragoon 1 5003
Protoss_Stargate 2 8767
Protoss_Robotics_Facility 1 6397
Protoss_Corsair 5 10390
Protoss_Shuttle 1 7392
Protoss_Forge 1 7640
Protoss_Robotics_Support_Bay 1 7980
Protoss_Photon_Cannon 3 10101
Protoss_Reaver 1 10601
Protoss_Air_Weapons_1 1 9621
10601
