Protoss_Assimilator 1 2394
Protoss_Gateway 1 3284
Protoss_Cybernetics_Core 1 4304
Protoss_Stargate 1 5483
Protoss_Robotics_Facility 1 6425
Protoss_Corsair 4 9478
Protoss_Forge 1 6957
Protoss_Shuttle 1 8252
Protoss_Robotics_Support_Bay 1 7916
Protoss_Air_Weapons_1 1 8421
Protoss_Reaver 1 10236
10236
