Protoss_Gateway 2 3520
Protoss_Zealot 12 10533
Protoss_Assimilator 1 5424
Protoss_Forge 1 5715
Protoss_Photon_Cannon 5 10160
Protoss_Cybernetics_Core 1 7639
Protoss_Citadel_of_Adun 1 8994
Protoss_Dragoon 1 9578
10533
