Protoss_Assimilator 1 2385
Protoss_Gateway 1 3184
Protoss_Cybernetics_Core 1 4184
Protoss_Stargate 1 5408
Protoss_Dragoon 1 5158
Protoss_Robotics_Facility 1 6359
Protoss_Corsair 5 10378
Protoss_Zealot 2 7638
Protoss_Shuttle 1 7537
Protoss_Forge 1 7998
Protoss_Robotics_Support_Bay 1 8764
Protoss_Photon_Cannon 2 9467
Protoss_Reaver 1 10171
Protoss_Air_Weapons_1 1 9686
10378
