Protoss_Gateway 2 4894
Protoss_Assimilator 1 3371
Protoss_Zealot 14 10418
Protoss_Nexus 1 9325
Protoss_Forge 1 8321
Protoss_Cybernetics_Core 1 9025
Protoss_Photon_Cannon 1 9184
10418
