Protoss_Gateway 2 3511
Protoss_Zealot 4 7162
Protoss_Assimilator 1 3811
Protoss_Cybernetics_Core 1 5286
Protoss_Stargate 1 6420
Protoss_Citadel_of_Adun 1 7012
Protoss_Corsair 2 10246
Protoss_Forge 1 8424
Protoss_Photon_Cannon 1 10616
10616
