Protoss_Forge 1 2646
Protoss_Photon_Cannon 2 3930
Protoss_Nexus 1 6150
Protoss_Gateway 2 7384
Protoss_Assimilator 1 6503
Protoss_Zealot 3 8058
Protoss_Cybernetics_Core 1 7696
Protoss_Stargate 1 9050
9050
