Protoss_Gateway 1 3017
Protoss_Assimilator 1 3120
Protoss_Zealot 6 9668
Protoss_Cybernetics_Core 1 4905
Protoss_Stargate 1 6362
Protoss_Corsair 1 7053
Protoss_Nexus 1 10700
10700
