Protoss_Gateway 2 10565
Protoss_Assimilator 1 3165
Protoss_Zealot 3 6638
Protoss_Cybernetics_Core 1 5107
Protoss_Dragoon 1 6008
Protoss_Stargate 1 6480
Protoss_Citadel_of_Adun 1 6472
Protoss_Corsair 1 7173
Protoss_Forge 1 7942
Protoss_Photon_Cannon 1 8874
Protoss_Nexus 1 10857
10857
