Protoss_Gateway 3 9143
Protoss_Assimilator 1 3196
Protoss_Cybernetics_Core 1 4152
Protoss_Zealot 11 10535
Protoss_Stargate 1 5432
Protoss_Forge 1 5246
Protoss_Corsair 2 6933
Protoss_Citadel_of_Adun 1 7804
Protoss_Ground_Weapons_1 1 9511
10535
