Protoss_Gateway 2 8986
Protoss_Assimilator 2 10115
Protoss_Zealot 3 5163
Protoss_Cybernetics_Core 1 5124
Protoss_Citadel_of_Adun 1 6226
Protoss_Dragoon 1 6248
Protoss_Forge 1 6894
Protoss_Templar_Archives 1 7254
Protoss_Dark_Templar 1 8113
Protoss_Nexus 1 9755
Protoss_High_Templar 3 9923
Protoss_Photon_Cannon 3 10005
10115
