Protoss_Gateway 2 5399
Protoss_Assimilator 1 3543
Protoss_Zealot 3 5778
Protoss_Cybernetics_Core 1 5110
Protoss_Dragoon 1 6128
Protoss_Citadel_of_Adun 1 6601
Protoss_Stargate 1 7687
Protoss_Templar_Archives 1 7650
Protoss_Forge 1 7924
Protoss_Dark_Templar 1 8693
Protoss_Photon_Cannon 3 10620
Protoss_Corsair 1 9098
Protoss_High_Templar 2 9553
Protoss_Nexus 1 10709
10709
