Protoss_Gateway 2 3474
Protoss_Zealot 12 10263
Protoss_Assimilator 1 4603
Protoss_Cybernetics_Core 1 5442
Protoss_Dragoon 1 6318
Protoss_Stargate 1 6848
Protoss_Citadel_of_Adun 1 7204
Protoss_Corsair 1 7578
Protoss_Templar_Archives 1 10149
10263
