Protoss_Gateway 2 3504
Protoss_Zealot 5 8118
Protoss_Assimilator 1 3913
Protoss_Cybernetics_Core 1 5584
Protoss_Robotics_Facility 1 7317
Protoss_Dragoon 4 8838
Protoss_Shuttle 1 9147
Protoss_Citadel_of_Adun 1 9505
Protoss_Robotics_Support_Bay 1 9326
Protoss_Reaver 1 10541
Protoss_Templar_Archives 1 10788
10788
