Protoss_Gateway 2 3459
Protoss_Assimilator 1 3547
Protoss_Zealot 5 5838
Protoss_Cybernetics_Core 1 7070
Protoss_Forge 1 7612
Protoss_Dragoon 4 10508
Protoss_Photon_Cannon 1 8832
10508
