Protoss_Gateway 2 3631
Protoss_Zealot 13 10208
Protoss_Assimilator 1 4722
Protoss_Cybernetics_Core 1 7024
Protoss_Dragoon 1 7998
Protoss_Citadel_of_Adun 1 8349
Protoss_Templar_Archives 1 9999
Protoss_Forge 1 10065
10208
