Protoss_Nexus 1 4726
Protoss_Gateway 3 9053
Protoss_Forge 1 4313
Protoss_Photon_Cannon 6 10745
Protoss_Assimilator 1 6280
Protoss_Zealot 7 10578
Protoss_Cybernetics_Core 1 7225
Protoss_Stargate 1 8443
Protoss_Corsair 2 10023
Protoss_Citadel_of_Adun 1 10084
Protoss_Robotics_Facility 1 11072
11072
