Protoss_Gateway 2 8329
Protoss_Zealot 8 9818
Protoss_Assimilator 1 3922
Protoss_Cybernetics_Core 1 4964
Protoss_Dragoon 1 6693
Protoss_Robotics_Facility 1 7357
Protoss_Citadel_of_Adun 1 7349
Protoss_Shuttle 1 8787
Protoss_Robotics_Support_Bay 1 8646
Protoss_Reaver 1 9838
9838
