Protoss_Forge 1 2804
Protoss_Photon_Cannon 5 10330
Protoss_Nexus 1 5940
Protoss_Gateway 1 6624
Protoss_Assimilator 2 8222
Protoss_Zealot 2 8348
Protoss_Cybernetics_Core 1 8084
Protoss_Dragoon 1 8990
Protoss_Robotics_Facility 1 9546
Protoss_Stargate 1 9713
Protoss_Robotics_Support_Bay 1 10165
Protoss_Corsair 1 10403
10403
