Protoss_Gateway 2 3349
Protoss_Zealot 12 8208
Protoss_Assimilator 1 5285
Protoss_Cybernetics_Core 1 7284
Protoss_Citadel_of_Adun 1 8284
Protoss_Nexus 1 10450
Protoss_Templar_Archives 1 9979
Protoss_Forge 1 10457
10457
