Protoss_Gateway 3 9705
Protoss_Zealot 11 10488
Protoss_Forge 1 4325
Protoss_Photon_Cannon 3 10000
Protoss_Nexus 1 7610
Protoss_Assimilator 2 10245
Protoss_Cybernetics_Core 1 8754
Protoss_Citadel_of_Adun 1 10005
Protoss_Dragoon 1 10213
10488
