Protoss_Nexus 1 5031
Protoss_Forge 1 4378
Protoss_Assimilator 3 9776
Protoss_Photon_Cannon 1 5390
Protoss_Gateway 4 9914
Protoss_Zealot 15 10173
Protoss_Cybernetics_Core 1 7337
Protoss_Citadel_of_Adun 1 8578
Protoss_Templar_Archives 1 10667
10667
