Protoss_Nexus 1 4835
Protoss_Forge 1 4218
Protoss_Photon_Cannon 3 10290
Protoss_Gateway 4 9859
Protoss_Assimilator 2 7585
Protoss_Cybernetics_Core 1 7374
Protoss_Zealot 9 10403
Protoss_Dragoon 3 9327
Protoss_Citadel_of_Adun 1 9628
10403
