Protoss_Gateway 2 7046
Protoss_Assimilator 1 3085
Protoss_Zealot 9 10188
Protoss_Cybernetics_Core 1 5002
Protoss_Stargate 1 6227
Protoss_Dragoon 1 6295
Protoss_Citadel_of_Adun 1 6788
Protoss_Templar_Archives 1 9124
Protoss_Forge 1 9470
10188
