Protoss_Gateway 2 3703
Protoss_Zealot 11 9263
Protoss_Assimilator 1 4760
Protoss_Cybernetics_Core 1 5807
Protoss_Dragoon 5 10643
Protoss_Stargate 1 7281
Protoss_Citadel_of_Adun 1 8095
Protoss_Corsair 3 9958
10643
