Protoss_Gateway 3 8054
Protoss_Assimilator 1 2983
Protoss_Zealot 12 9913
Protoss_Cybernetics_Core 1 4379
Protoss_Stargate 1 5644
Protoss_Citadel_of_Adun 1 6604
Protoss_Corsair 1 6513
Protoss_Templar_Archives 1 10478
10478
