Protoss_Gateway 2 7274
Protoss_Assimilator 1 3290
Protoss_Zealot 7 10529
Protoss_Cybernetics_Core 1 4659
Protoss_Citadel_of_Adun 1 5659
Protoss_Templar_Archives 1 7729
Protoss_Forge 1 7948
Protoss_High_Templar 2 9325
Protoss_Photon_Cannon 2 9843
10529
