Protoss_Gateway 3 8677
Protoss_Assimilator 1 3170
Protoss_Zealot 3 4888
Protoss_Cybernetics_Core 1 4872
Protoss_Robotics_Facility 1 6379
Protoss_Dragoon 12 10440
Protoss_Observatory 1 7080
Protoss_Observer 1 7948
10440
