Protoss_Gateway 1 2737
Protoss_Assimilator 1 3111
Protoss_Zealot 8 9999
Protoss_Forge 1 4684
Protoss_Cybernetics_Core 1 6114
Protoss_Citadel_of_Adun 1 7109
Protoss_Dragoon 1 7040
Protoss_Robotics_Facility 1 8277
Protoss_Robotics_Support_Bay 1 9316
Protoss_Ground_Weapons_1 1 9651
9999
