Protoss_Gateway 4 9029
Protoss_Zealot 15 10488
Protoss_Nexus 1 7055
Protoss_Assimilator 1 6129
Protoss_Forge 1 6487
Protoss_Photon_Cannon 1 7461
Protoss_Cybernetics_Core 1 7996
Protoss_Citadel_of_Adun 1 9228
10488
