Protoss_Gateway 2 3568
Protoss_Zealot 8 8398
Protoss_Assimilator 1 4575
Protoss_Cybernetics_Core 1 5566
Protoss_Dragoon 1 6458
Protoss_Citadel_of_Adun 1 6732
Protoss_Templar_Archives 1 8504
Protoss_Dark_Templar 2 9853
Protoss_Forge 1 9479
Protoss_High_Templar 2 10100
10100
