Protoss_Gateway 2 3439
Protoss_Zealot 12 9483
Protoss_Assimilator 1 5371
Protoss_Forge 1 6557
Protoss_Cybernetics_Core 1 7634
Protoss_Citadel_of_Adun 1 8721
Protoss_Dragoon 1 8928
9483
