Protoss_Forge 1 2866
Protoss_Photon_Cannon 7 10208
Protoss_Gateway 2 6252
Protoss_Nexus 1 6770
Protoss_Assimilator 1 6210
Protoss_Zealot 10 10248
Protoss_Cybernetics_Core 1 7805
Protoss_Stargate 1 8961
Protoss_Corsair 2 10363
10363
