Protoss_Gateway 1 2824
Protoss_Assimilator 1 2840
Protoss_Cybernetics_Core 1 3881
Protoss_Stargate 1 5074
Protoss_Robotics_Facility 1 5903
Protoss_Corsair 8 10522
Protoss_Forge 1 6579
Protoss_Shuttle 1 7105
Protoss_Robotics_Support_Bay 1 7193
Protoss_Photon_Cannon 2 10161
Protoss_Reaver 1 10000
10522
