Protoss_Gateway 2 8779
Protoss_Forge 1 3208
Protoss_Zealot 9 10093
Protoss_Photon_Cannon 3 9422
Protoss_Assimilator 1 6367
Protoss_Cybernetics_Core 1 7836
Protoss_Dragoon 1 8758
Protoss_Citadel_of_Adun 1 10178
10178
