Protoss_Gateway 3 9031
Protoss_Zealot 15 10193
Protoss_Assimilator 1 5880
Protoss_Cybernetics_Core 1 6938
Protoss_Citadel_of_Adun 1 8347
Protoss_Dragoon 1 8508
Protoss_Templar_Archives 1 9867
10193
