Protoss_Gateway 2 7525
Protoss_Assimilator 1 2986
Protoss_Zealot 4 6080
Protoss_Cybernetics_Core 1 4607
Protoss_Stargate 1 6058
Protoss_Corsair 1 6748
Protoss_Dragoon 8 10573
Protoss_Robotics_Facility 1 8201
Protoss_Forge 1 8100
Protoss_Photon_Cannon 1 9205
Protoss_Shuttle 1 9987
Protoss_Robotics_Support_Bay 1 9926
10573
