Protoss_Forge 1 3565
Protoss_Nexus 1 5415
Protoss_Photon_Cannon 5 10471
Protoss_Assimilator 1 8808
Protoss_Gateway 1 9152
Protoss_Cybernetics_Core 1 10159
Protoss_Zealot 1 10108
10471
