Protoss_Nexus 2 9584
Protoss_Forge 1 4076
Protoss_Assimilator 2 10386
Protoss_Gateway 1 5538
Protoss_Cybernetics_Core 1 6811
Protoss_Photon_Cannon 5 9355
Protoss_Stargate 1 8076
Protoss_Robotics_Facility 1 8580
Protoss_Corsair 2 9908
Protoss_Shuttle 2 10749
Protoss_Ground_Weapons_1 1 9311
10749
