Protoss_Gateway 2 3379
Protoss_Zealot 14 9768
Protoss_Assimilator 1 7235
Protoss_Forge 1 7273
Protoss_Photon_Cannon 2 8270
Protoss_Cybernetics_Core 1 8799
Protoss_Citadel_of_Adun 1 10042
10042
