Protoss_Gateway 1 2699
Protoss_Assimilator 1 3062
Protoss_Zealot 6 7308
Protoss_Cybernetics_Core 1 5008
Protoss_Stargate 1 6317
Protoss_Dragoon 1 6123
Protoss_Citadel_of_Adun 1 6912
Protoss_Scout 1 7645
Protoss_Forge 1 7545
Protoss_Templar_Archives 1 8054
Protoss_Photon_Cannon 4 10715
Protoss_Dark_Templar 1 8893
Protoss_High_Templar 1 10335
Protoss_Nexus 1 11615
11615
