Protoss_Gateway 2 3039
Protoss_Zealot 7 5582
Protoss_Assimilator 1 5216
Protoss_Cybernetics_Core 1 6633
Protoss_Forge 1 7120
Protoss_Stargate 1 8005
Protoss_Photon_Cannon 2 8622
Protoss_Corsair 3 10338
10338
