Protoss_Gateway 2 3584
Protoss_Zealot 6 8716
Protoss_Assimilator 1 4156
Protoss_Forge 1 4494
Protoss_Photon_Cannon 1 5344
Protoss_Cybernetics_Core 1 6021
Protoss_Dragoon 1 6894
Protoss_Citadel_of_Adun 1 7162
Protoss_Ground_Weapons_1 1 9245
Protoss_Nexus 1 11220
11220
