Protoss_Forge 1 2515
Protoss_Nexus 1 5350
Protoss_Photon_Cannon 7 8961
Protoss_Gateway 3 10068
Protoss_Assimilator 2 9849
Protoss_Zealot 5 10203
Protoss_Cybernetics_Core 1 7950
Protoss_Citadel_of_Adun 1 8973
Protoss_Templar_Archives 1 10517
10517
