Protoss_Gateway 2 3479
Protoss_Zealot 12 8945
Protoss_Cybernetics_Core 1 5574
Protoss_Assimilator 1 5850
Protoss_Dragoon 1 7033
Protoss_Citadel_of_Adun 1 7717
Protoss_Templar_Archives 1 9549
Protoss_Forge 1 9418
Protoss_Nexus 1 11030
11030
