Protoss_Gateway 2 3486
Protoss_Zealot 14 10418
Protoss_Assimilator 1 5454
Protoss_Cybernetics_Core 1 7002
Protoss_Stargate 1 8271
Protoss_Citadel_of_Adun 1 8521
Protoss_Corsair 1 8958
Protoss_Forge 1 10120
10418
