Protoss_Gateway 2 3545
Protoss_Zealot 11 10033
Protoss_Assimilator 1 4641
Protoss_Cybernetics_Core 1 5371
Protoss_Forge 1 5410
Protoss_Dragoon 1 6588
Protoss_Citadel_of_Adun 1 7579
Protoss_Templar_Archives 1 8909
Protoss_Photon_Cannon 1 9657
Protoss_Ground_Weapons_1 1 9501
Protoss_Nexus 1 11647
11647
