Protoss_Gateway 2 3344
Protoss_Zealot 10 8848
Protoss_Forge 1 6055
Protoss_Photon_Cannon 4 9608
Protoss_Nexus 1 9005
Protoss_Assimilator 1 8170
Protoss_Cybernetics_Core 1 10464
10464
