Protoss_Forge 1 2585
Protoss_Nexus 1 5285
Protoss_Photon_Cannon 7 10454
Protoss_Gateway 1 5262
Protoss_Assimilator 2 7388
Protoss_Cybernetics_Core 2 7409
Protoss_Stargate 2 9771
Protoss_Robotics_Facility 1 9079
Protoss_Corsair 3 10368
Protoss_Robotics_Support_Bay 1 9652
Protoss_Reaver 1 10941
10941
