Protoss_Gateway 2 7503
Protoss_Zealot 9 9378
Protoss_Assimilator 1 3706
Protoss_Cybernetics_Core 1 4576
Protoss_Stargate 1 5852
Protoss_Dragoon 1 5718
Protoss_Citadel_of_Adun 1 6409
Protoss_Corsair 1 6653
Protoss_Forge 1 8232
Protoss_Templar_Archives 1 9118
Protoss_High_Templar 2 10413
10413
