Protoss_Gateway 2 3110
Protoss_Zealot 14 10273
Protoss_Assimilator 1 4940
Protoss_Cybernetics_Core 1 6744
Protoss_Forge 1 7296
Protoss_Dragoon 1 7603
Protoss_Citadel_of_Adun 1 8338
Protoss_Photon_Cannon 1 9160
Protoss_Templar_Archives 1 10339
10339
