Protoss_Gateway 2 3375
Protoss_Zealot 8 9128
Protoss_Forge 1 4255
Protoss_Photon_Cannon 4 9936
Protoss_Nexus 1 7320
Protoss_Assimilator 1 6593
Protoss_Cybernetics_Core 1 7911
Protoss_Stargate 1 9247
Protoss_Corsair 1 10238
10238
