Protoss_Gateway 2 3144
Protoss_Zealot 13 10053
Protoss_Forge 1 4765
Protoss_Photon_Cannon 2 7145
Protoss_Nexus 1 8815
Protoss_Assimilator 1 8185
Protoss_Cybernetics_Core 1 9324
Protoss_Stargate 1 10936
10936
