Protoss_Forge 1 2654
Protoss_Nexus 1 5430
Protoss_Photon_Cannon 7 8345
Protoss_Gateway 3 8975
Protoss_Zealot 9 10500
Protoss_Assimilator 1 8183
Protoss_Cybernetics_Core 1 9969
10500
