Protoss_Forge 1 3489
Protoss_Nexus 2 11567
Protoss_Photon_Cannon 3 10428
Protoss_Gateway 3 7977
Protoss_Assimilator 2 7911
Protoss_Cybernetics_Core 1 5959
Protoss_Zealot 2 8020
Protoss_Stargate 1 7238
Protoss_Citadel_of_Adun 1 7575
Protoss_Corsair 1 8158
Protoss_Templar_Archives 1 8865
Protoss_Dark_Templar 1 9742
Protoss_Robotics_Facility 1 11105
11567
