Protoss_Gateway 1 2961
Protoss_Assimilator 1 3185
Protoss_Zealot 3 6703
Protoss_Cybernetics_Core 1 4847
Protoss_Robotics_Facility 1 6202
Protoss_Dragoon 1 5943
Protoss_Citadel_of_Adun 1 7144
Protoss_Robotics_Support_Bay 1 6788
Protoss_Reaver 1 7926
Protoss_Templar_Archives 1 8315
Protoss_Forge 1 8154
Protoss_Nexus 1 10193
Protoss_Shield_Battery 1 8936
Protoss_High_Templar 1 9663
Protoss_Photon_Cannon 3 10633
Protoss_Dark_Templar 1 10178
10633
