Protoss_Gateway 3 10211
Protoss_Assimilator 1 3030
Protoss_Zealot 10 10183
Protoss_Cybernetics_Core 1 4879
Protoss_Stargate 1 6418
Protoss_Dragoon 1 6288
Protoss_Forge 1 6608
Protoss_Corsair 1 7118
Protoss_Citadel_of_Adun 1 8049
Protoss_Photon_Cannon 1 9995
Protoss_Robotics_Facility 1 11100
11100
