Protoss_Gateway 2 7944
Protoss_Assimilator 1 3055
Protoss_Zealot 3 6285
Protoss_Cybernetics_Core 1 4599
Protoss_Stargate 1 5832
Protoss_Dragoon 1 5683
Protoss_Corsair 1 6533
Protoss_Citadel_of_Adun 1 6869
Protoss_Templar_Archives 1 7869
Protoss_Forge 1 8217
Protoss_Dark_Templar 2 8793
Protoss_Nexus 1 10445
Protoss_Photon_Cannon 3 10004
Protoss_High_Templar 2 10063
10445
