Protoss_Forge 1 2610
Protoss_Photon_Cannon 4 9765
Protoss_Nexus 1 6242
Protoss_Gateway 2 8184
Protoss_Zealot 8 10428
Protoss_Assimilator 2 9933
Protoss_Cybernetics_Core 1 8469
Protoss_Citadel_of_Adun 1 9504
Protoss_Templar_Archives 1 10547
10547
