Protoss_Gateway 2 9343
Protoss_Zealot 3 5428
Protoss_Assimilator 1 3765
Protoss_Cybernetics_Core 1 6740
Protoss_Forge 1 6951
Protoss_Citadel_of_Adun 1 7852
Protoss_Photon_Cannon 2 10700
Protoss_Dragoon 1 8258
Protoss_Templar_Archives 1 9176
Protoss_Dark_Templar 2 10193
10700
