Protoss_Gateway 2 9545
Protoss_Assimilator 1 3125
Protoss_Zealot 6 8218
Protoss_Cybernetics_Core 1 4982
Protoss_Stargate 1 6268
Protoss_Dragoon 1 6078
Protoss_Corsair 1 6998
Protoss_Citadel_of_Adun 1 7349
Protoss_Forge 1 7167
Protoss_Photon_Cannon 1 8309
Protoss_Templar_Archives 1 8973
Protoss_Dark_Templar 2 10383
Protoss_High_Templar 1 10703
10703
