Protoss_Gateway 1 2803
Protoss_Assimilator 2 3923
Protoss_Zealot 4 6292
Protoss_Forge 1 4552
Protoss_Cybernetics_Core 1 6057
Protoss_Citadel_of_Adun 1 7142
Protoss_Dragoon 1 7044
Protoss_Photon_Cannon 3 9606
Protoss_Templar_Archives 1 8335
Protoss_High_Templar 3 10726
Protoss_Nexus 1 11297
11297
