Protoss_Gateway 1 2729
Protoss_Assimilator 1 2921
Protoss_Zealot 6 7644
Protoss_Cybernetics_Core 1 4951
Protoss_Dragoon 1 5838
Protoss_Stargate 1 6176
Protoss_Citadel_of_Adun 1 6546
Protoss_Corsair 1 6878
Protoss_Templar_Archives 1 7934
Protoss_Forge 1 7919
Protoss_Dark_Templar 1 8828
Protoss_Photon_Cannon 1 9132
Protoss_High_Templar 1 9783
Protoss_Nexus 1 11151
11151
