Protoss_Assimilator 1 2395
Protoss_Forge 1 2924
Protoss_Photon_Cannon 1 4081
Protoss_Gateway 3 5869
Protoss_Zealot 13 10109
Protoss_Ground_Weapons_1 1 7156
Protoss_Cybernetics_Core 1 8215
Protoss_Stargate 1 9972
10109
