Protoss_Forge 2 10020
Protoss_Nexus 1 5586
Protoss_Photon_Cannon 2 5390
Protoss_Assimilator 2 8143
Protoss_Gateway 4 9492
Protoss_Zealot 8 9550
Protoss_Cybernetics_Core 1 7627
Protoss_Citadel_of_Adun 1 8999
Protoss_Robotics_Facility 1 11083
11083
