Protoss_Forge 1 2780
Protoss_Photon_Cannon 6 10213
Protoss_Nexus 1 6309
Protoss_Gateway 2 10650
Protoss_Assimilator 2 7294
Protoss_Zealot 4 9330
Protoss_Cybernetics_Core 1 7640
Protoss_Stargate 1 8919
Protoss_Citadel_of_Adun 1 9379
Protoss_Robotics_Facility 1 9856
Protoss_Corsair 1 9608
Protoss_Templar_Archives 1 10544
10650
