Protoss_Gateway 2 6972
Protoss_Assimilator 1 2940
Protoss_Zealot 3 7028
Protoss_Cybernetics_Core 1 4657
Protoss_Citadel_of_Adun 1 5839
Protoss_Dragoon 1 5918
Protoss_Templar_Archives 1 6870
Protoss_Robotics_Facility 1 8142
Protoss_Dark_Templar 3 9778
Protoss_High_Templar 1 9793
9793
