Protoss_Gateway 1 2794
Protoss_Assimilator 2 10497
Protoss_Zealot 2 4628
Protoss_Cybernetics_Core 1 4619
Protoss_Stargate 1 5768
Protoss_Citadel_of_Adun 1 5809
Protoss_Dragoon 1 6468
Protoss_Corsair 1 6488
Protoss_Templar_Archives 1 6934
Protoss_Dark_Templar 2 8765
Protoss_Forge 1 8004
Protoss_Nexus 1 9491
Protoss_Photon_Cannon 3 9670
Protoss_High_Templar 2 10269
10497
