Protoss_Forge 1 2980
Protoss_Nexus 1 5300
Protoss_Photon_Cannon 7 10335
Protoss_Gateway 1 5069
Protoss_Assimilator 2 7995
Protoss_Zealot 4 8853
Protoss_Cybernetics_Core 1 6929
Protoss_Citadel_of_Adun 1 8011
Protoss_Templar_Archives 1 9055
Protoss_High_Templar 1 10053
10335
