Protoss_Gateway 2 3534
Protoss_Zealot 5 4983
Protoss_Assimilator 1 4613
Protoss_Cybernetics_Core 1 6406
Protoss_Forge 1 6690
Protoss_Citadel_of_Adun 1 7911
Protoss_Nexus 1 10263
Protoss_Photon_Cannon 1 9413
10263
