Protoss_Gateway 2 3569
Protoss_Zealot 11 8488
Protoss_Assimilator 1 4661
Protoss_Cybernetics_Core 1 6113
Protoss_Citadel_of_Adun 1 7425
Protoss_Shield_Battery 1 7206
Protoss_Templar_Archives 1 8525
Protoss_Forge 1 8941
Protoss_Dark_Templar 1 9373
Protoss_High_Templar 2 10125
Protoss_Photon_Cannon 1 9790
10125
