Protoss_Gateway 2 9512
Protoss_Assimilator 1 2944
Protoss_Cybernetics_Core 1 3814
Protoss_Zealot 2 5475
Protoss_Dragoon 1 4873
Protoss_Robotics_Facility 1 5627
Protoss_Shuttle 1 6697
Protoss_Robotics_Support_Bay 1 6376
Protoss_Reaver 2 8868
Protoss_Citadel_of_Adun 1 8044
Protoss_Forge 1 7940
Protoss_Photon_Cannon 1 8827
Protoss_Templar_Archives 1 9334
9512
