Protoss_Forge 1 2743
Protoss_Nexus 1 5155
Protoss_Photon_Cannon 2 5286
Protoss_Gateway 5 8529
Protoss_Assimilator 2 6730
Protoss_Cybernetics_Core 1 6980
Protoss_Zealot 12 10193
Protoss_Citadel_of_Adun 1 8759
Protoss_Templar_Archives 1 10007
10193
