Protoss_Nexus 1 4778
Protoss_Forge 1 3878
Protoss_Gateway 3 7653
Protoss_Assimilator 2 6882
Protoss_Photon_Cannon 7 10562
Protoss_Zealot 10 8996
Protoss_Cybernetics_Core 1 6187
Protoss_Citadel_of_Adun 1 7372
Protoss_Templar_Archives 1 8359
Protoss_High_Templar 3 10170
Protoss_Ground_Weapons_1 1 9727
10562
