Protoss_Forge 1 3217
Protoss_Photon_Cannon 3 9878
Protoss_Nexus 2 10455
Protoss_Gateway 1 5373
Protoss_Assimilator 2 7426
Protoss_Cybernetics_Core 1 6404
Protoss_Stargate 1 7538
Protoss_Corsair 4 10200
Protoss_Robotics_Facility 1 9393
Protoss_Robotics_Support_Bay 1 9991
10455
