Protoss_Nexus 1 4771
Protoss_Forge 1 4160
Protoss_Photon_Cannon 2 5370
Protoss_Gateway 4 7526
Protoss_Assimilator 2 8426
Protoss_Cybernetics_Core 1 6893
Protoss_Citadel_of_Adun 1 7984
Protoss_Dragoon 1 7894
Protoss_Zealot 12 9984
Protoss_Templar_Archives 1 10361
10361
