Protoss_Gateway 1 2922
Protoss_Assimilator 1 3100
Protoss_Zealot 4 6888
Protoss_Cybernetics_Core 1 5129
Protoss_Stargate 1 6268
Protoss_Citadel_of_Adun 1 6594
Protoss_Corsair 1 6958
Protoss_Templar_Archives 1 7589
Protoss_Dark_Templar 3 10298
Protoss_Forge 1 9307
Protoss_Nexus 1 10756
Protoss_Photon_Cannon 1 10437
10756
