Protoss_Gateway 2 7523
Protoss_Assimilator 1 2895
Protoss_Zealot 3 7618
Protoss_Cybernetics_Core 1 4589
Protoss_Stargate 1 5825
Protoss_Dragoon 1 5813
Protoss_Citadel_of_Adun 1 6655
Protoss_Corsair 1 6648
Protoss_Templar_Archives 1 7739
Protoss_Forge 1 8408
Protoss_Dark_Templar 2 8588
Protoss_Nexus 1 10597
Protoss_High_Templar 2 9703
Protoss_Photon_Cannon 1 10421
10597
