Protoss_Forge 1 2864
Protoss_Photon_Cannon 5 10623
Protoss_Nexus 1 5695
Protoss_Gateway 3 8955
Protoss_Assimilator 2 7405
Protoss_Cybernetics_Core 1 6124
Protoss_Zealot 1 6154
Protoss_Citadel_of_Adun 1 7403
Protoss_Dragoon 1 8208
Protoss_Templar_Archives 1 8586
Protoss_Dark_Templar 1 9496
Protoss_High_Templar 2 9850
Protoss_Robotics_Facility 1 10717
Protoss_Archon 1 10210
10717
