Protoss_Forge 1 2647
Protoss_Photon_Cannon 5 10735
Protoss_Nexus 1 6243
Protoss_Gateway 4 10332
Protoss_Assimilator 2 8556
Protoss_Zealot 2 8938
Protoss_Cybernetics_Core 1 7101
Protoss_Citadel_of_Adun 1 8515
Protoss_Templar_Archives 1 9602
Protoss_High_Templar 1 10593
10735
