Protoss_Nexus 1 4639
Protoss_Forge 1 3910
Protoss_Photon_Cannon 2 7782
Protoss_Gateway 4 8485
Protoss_Assimilator 2 7295
Protoss_Cybernetics_Core 1 6573
Protoss_Zealot 7 9928
Protoss_Citadel_of_Adun 1 7773
Protoss_Robotics_Facility 1 10398
10398
