Protoss_Forge 1 2736
Protoss_Nexus 2 8461
Protoss_Gateway 1 5120
Protoss_Photon_Cannon 3 10466
Protoss_Assimilator 2 6664
Protoss_Cybernetics_Core 1 6563
Protoss_Stargate 1 7902
Protoss_Robotics_Facility 2 9207
Protoss_Zealot 1 8543
Protoss_Corsair 4 10584
Protoss_Robotics_Support_Bay 1 9593
Protoss_Shuttle 1 10042
10584
