Protoss_Forge 1 3071
Protoss_Photon_Cannon 2 10746
Protoss_Nexus 1 5507
Protoss_Gateway 4 8970
Protoss_Assimilator 2 10230
Protoss_Cybernetics_Core 1 6339
Protoss_Zealot 11 10430
Protoss_Citadel_of_Adun 1 7792
Protoss_Templar_Archives 1 9657
Protoss_Ground_Weapons_1 1 9763
10746
