Protoss_Nexus 1 4677
Protoss_Forge 1 3895
Protoss_Gateway 2 6530
Protoss_Photon_Cannon 6 10729
Protoss_Assimilator 2 9077
Protoss_Zealot 10 10298
Protoss_Cybernetics_Core 1 7409
Protoss_Stargate 1 8691
Protoss_Citadel_of_Adun 1 8772
Protoss_Dragoon 1 8778
Protoss_Corsair 2 10093
10729
