Protoss_Forge 1 3215
Protoss_Photon_Cannon 8 9656
Protoss_Nexus 1 5847
Protoss_Gateway 1 5653
Protoss_Assimilator 2 8303
Protoss_Zealot 4 10056
Protoss_Cybernetics_Core 1 7343
Protoss_Stargate 1 8587
Protoss_Corsair 3 10590
Protoss_Citadel_of_Adun 1 10722
10722
