Protoss_Forge 2 8591
Protoss_Nexus 1 5205
Protoss_Photon_Cannon 7 10736
Protoss_Gateway 4 10480
Protoss_Assimilator 2 9091
Protoss_Zealot 6 10306
Protoss_Cybernetics_Core 1 7013
Protoss_Citadel_of_Adun 1 8747
Protoss_Templar_Archives 1 9912
10736
