Protoss_Forge 1 2726
Protoss_Photon_Cannon 3 8353
Protoss_Nexus 1 5581
Protoss_Gateway 2 8914
Protoss_Assimilator 2 8578
Protoss_Zealot 5 10560
Protoss_Cybernetics_Core 1 7209
Protoss_Stargate 1 8432
Protoss_Dragoon 1 8264
Protoss_Citadel_of_Adun 1 9408
Protoss_Corsair 1 9124
10560
