Protoss_Forge 1 2894
Protoss_Nexus 1 5221
Protoss_Photon_Cannon 4 10364
Protoss_Gateway 3 8894
Protoss_Assimilator 2 7006
Protoss_Zealot 1 5912
Protoss_Cybernetics_Core 1 6928
Protoss_Dragoon 1 7760
Protoss_Citadel_of_Adun 1 7953
Protoss_Templar_Archives 1 8943
Protoss_High_Templar 4 10532
Protoss_Dark_Templar 1 9806
Protoss_Robotics_Facility 1 10504
Protoss_Archon 1 10143
10532
