Protoss_Forge 1 2940
Protoss_Nexus 1 5583
Protoss_Photon_Cannon 4 10469
Protoss_Gateway 4 10391
Protoss_Assimilator 2 7962
Protoss_Cybernetics_Core 1 6575
Protoss_Zealot 10 9912
Protoss_Citadel_of_Adun 1 7663
Protoss_Templar_Archives 1 9270
Protoss_High_Templar 2 10664
10664
