Protoss_Nexus 1 4543
Protoss_Forge 1 3618
Protoss_Photon_Cannon 9 10682
Protoss_Gateway 3 7251
Protoss_Assimilator 2 8981
Protoss_Cybernetics_Core 1 5979
Protoss_Zealot 12 9853
Protoss_Citadel_of_Adun 1 7017
Protoss_Templar_Archives 1 9246
Protoss_High_Templar 2 10312
Protoss_Ground_Weapons_1 1 9625
10682
