Protoss_Forge 1 2514
Protoss_Photon_Cannon 4 10622
Protoss_Nexus 1 5597
Protoss_Gateway 3 8367
Protoss_Assimilator 1 5223
Protoss_Zealot 12 10060
Protoss_Cybernetics_Core 1 6475
Protoss_Citadel_of_Adun 1 7752
Protoss_Templar_Archives 1 10124
10622
