Protoss_Forge 1 3083
Protoss_Photon_Cannon 3 8195
Protoss_Nexus 1 5531
Protoss_Gateway 2 9344
Protoss_Assimilator 2 6404
Protoss_Cybernetics_Core 1 6341
Protoss_Stargate 1 7522
Protoss_Citadel_of_Adun 1 7665
Protoss_Dragoon 1 7726
Protoss_Corsair 1 8206
Protoss_Templar_Archives 1 9090
Protoss_High_Templar 1 10348
10348
