Protoss_Gateway 1 2870
Protoss_Assimilator 1 3171
Protoss_Zealot 4 6913
Protoss_Cybernetics_Core 1 4584
Protoss_Dragoon 1 5633
Protoss_Stargate 1 6243
Protoss_Citadel_of_Adun 1 6828
Protoss_Corsair 1 7133
Protoss_Templar_Archives 1 7819
Protoss_Forge 1 7555
Protoss_High_Templar 1 10398
10398
