Protoss_Forge 1 3239
Protoss_Photon_Cannon 6 10680
Protoss_Gateway 5 10604
Protoss_Nexus 1 5975
Protoss_Assimilator 2 7569
Protoss_Zealot 2 6780
Protoss_Cybernetics_Core 1 7295
Protoss_Stargate 1 8835
Protoss_Citadel_of_Adun 1 9108
Protoss_Corsair 2 10343
Protoss_Templar_Archives 1 10324
10680
