Protoss_Forge 1 2905
Protoss_Photon_Cannon 2 9220
Protoss_Nexus 1 5741
Protoss_Gateway 2 9157
Protoss_Assimilator 2 6814
Protoss_Zealot 1 5824
Protoss_Cybernetics_Core 1 6362
Protoss_Stargate 1 7642
Protoss_Citadel_of_Adun 1 7897
Protoss_Corsair 3 9800
Protoss_Templar_Archives 1 8916
Protoss_Robotics_Facility 1 9287
Protoss_Dark_Templar 1 9882
Protoss_High_Templar 1 10102
Protoss_Shuttle 1 10291
10291
