Protoss_Gateway 2 10479
Protoss_Assimilator 1 2924
Protoss_Zealot 5 8894
Protoss_Cybernetics_Core 1 5773
Protoss_Stargate 1 6947
Protoss_Dragoon 1 6754
Protoss_Citadel_of_Adun 1 7345
Protoss_Forge 1 7753
Protoss_Corsair 1 7836
Protoss_Templar_Archives 1 8714
Protoss_Photon_Cannon 2 9872
Protoss_Dark_Templar 2 10504
Protoss_Robotics_Facility 1 10230
10504
