Protoss_Forge 1 2602
Protoss_Photon_Cannon 2 3853
Protoss_Nexus 1 6213
Protoss_Gateway 4 8821
Protoss_Assimilator 2 7718
Protoss_Zealot 10 10514
Protoss_Cybernetics_Core 1 7140
Protoss_Citadel_of_Adun 1 8265
Protoss_Templar_Archives 1 9931
Protoss_Robotics_Facility 1 10786
10786
