Protoss_Forge 1 2767
Protoss_Nexus 1 5190
Protoss_Gateway 2 8532
Protoss_Photon_Cannon 7 9975
Protoss_Assimilator 2 6812
Protoss_Zealot 4 7568
Protoss_Cybernetics_Core 1 6398
Protoss_Citadel_of_Adun 1 7432
Protoss_Templar_Archives 1 8560
Protoss_High_Templar 3 10298
10298
