Protoss_Nexus 1 4593
Protoss_Gateway 3 10489
Protoss_Forge 1 4302
Protoss_Assimilator 2 7397
Protoss_Photon_Cannon 2 10282
Protoss_Zealot 8 10260
Protoss_Cybernetics_Core 1 6814
Protoss_Dragoon 1 7714
Protoss_Stargate 1 8392
Protoss_Citadel_of_Adun 1 8270
Protoss_Corsair 2 10378
Protoss_Templar_Archives 1 9571
Protoss_Ground_Weapons_1 1 9479
10489
