Protoss_Forge 1 3066
Protoss_Nexus 1 5132
Protoss_Gateway 1 4899
Protoss_Assimilator 1 4878
Protoss_Photon_Cannon 1 5368
Protoss_Zealot 2 7554
Protoss_Cybernetics_Core 1 6685
Protoss_Stargate 2 8770
8770
