Protoss_Forge 1 3299
Protoss_Nexus 1 5144
Protoss_Photon_Cannon 3 9632
Protoss_Gateway 1 5015
Protoss_Assimilator 2 6524
Protoss_Cybernetics_Core 1 6277
Protoss_Stargate 1 7471
Protoss_Dragoon 1 7260
Protoss_Citadel_of_Adun 1 7898
Protoss_Zealot 1 7862
Protoss_Robotics_Facility 1 9231
9632
