Protoss_Forge 1 2865
Protoss_Photon_Cannon 5 10360
Protoss_Nexus 1 6091
Protoss_Gateway 2 9515
Protoss_Assimilator 2 7184
Protoss_Cybernetics_Core 1 6597
Protoss_Zealot 3 7896
Protoss_Citadel_of_Adun 1 7632
Protoss_Templar_Archives 1 8984
Protoss_High_Templar 2 10572
10572
