Protoss_Forge 1 2910
Protoss_Photon_Cannon 3 10735
Protoss_Nexus 1 6550
Protoss_Gateway 3 8872
Protoss_Assimilator 2 9547
Protoss_Cybernetics_Core 1 7019
Protoss_Zealot 11 10518
Protoss_Citadel_of_Adun 1 8139
Protoss_Templar_Archives 1 10544
10735
