Protoss_Forge 1 2928
Protoss_Photon_Cannon 3 10362
Protoss_Nexus 1 6105
Protoss_Gateway 3 9794
Protoss_Assimilator 2 7329
Protoss_Cybernetics_Core 1 6836
Protoss_Zealot 2 7145
Protoss_Stargate 1 7984
Protoss_Dragoon 1 7903
Protoss_Citadel_of_Adun 1 8602
Protoss_Corsair 3 10423
Protoss_Templar_Archives 1 9612
Protoss_Dark_Templar 2 10483
10483
