Protoss_Gateway 3 10483
Protoss_Assimilator 1 2949
Protoss_Cybernetics_Core 1 3835
Protoss_Stargate 1 5084
Protoss_Forge 1 4922
Protoss_Photon_Cannon 3 9627
Protoss_Corsair 2 6723
Protoss_Zealot 6 8948
Protoss_Citadel_of_Adun 1 7663
Protoss_Templar_Archives 1 8786
Protoss_Dark_Templar 2 9928
Protoss_Ground_Weapons_1 1 9086
10483
