Protoss_Forge 1 3135
Protoss_Photon_Cannon 7 10638
Protoss_Nexus 1 6201
Protoss_Gateway 3 8857
Protoss_Assimilator 2 7514
Protoss_Zealot 1 6354
Protoss_Cybernetics_Core 1 6735
Protoss_Dragoon 1 7566
Protoss_Citadel_of_Adun 1 7730
Protoss_Templar_Archives 1 9102
Protoss_Dark_Templar 1 9938
Protoss_High_Templar 3 10718
10718
