Protoss_Gateway 1 2943
Protoss_Assimilator 2 10169
Protoss_Zealot 4 6108
Protoss_Cybernetics_Core 1 5527
Protoss_Citadel_of_Adun 1 6563
Protoss_Dragoon 1 6860
Protoss_Templar_Archives 1 7575
Protoss_Dark_Templar 1 8406
Protoss_Forge 1 8303
Protoss_Nexus 1 9792
Protoss_High_Templar 2 9996
Protoss_Photon_Cannon 4 10698
10698
