Protoss_Gateway 1 2781
Protoss_Assimilator 1 3025
Protoss_Cybernetics_Core 1 3924
Protoss_Stargate 1 5168
Protoss_Dragoon 1 5120
Protoss_Corsair 5 10536
Protoss_Citadel_of_Adun 1 6399
Protoss_Forge 1 6542
Protoss_Nexus 1 8489
Protoss_Templar_Archives 1 7815
Protoss_Dark_Templar 1 8766
Protoss_Photon_Cannon 3 10449
10536
