Protoss_Nexus 1 4700
Protoss_Forge 1 4079
Protoss_Gateway 4 10794
Protoss_Assimilator 2 6335
Protoss_Cybernetics_Core 1 5991
Protoss_Photon_Cannon 1 6051
Protoss_Zealot 4 10248
Protoss_Stargate 1 7528
Protoss_Dragoon 1 7463
Protoss_Citadel_of_Adun 1 7793
Protoss_Corsair 4 10076
Protoss_Templar_Archives 1 8929
Protoss_Dark_Templar 2 10353
10794
