Protoss_Nexus 1 4730
Protoss_Gateway 1 4343
Protoss_Assimilator 2 6445
Protoss_Cybernetics_Core 1 5448
Protoss_Stargate 1 6653
Protoss_Forge 1 6980
Protoss_Corsair 4 9483
Protoss_Robotics_Facility 2 10492
Protoss_Photon_Cannon 7 10606
Protoss_Robotics_Support_Bay 1 8726
Protoss_Reaver 1 10166
10606
