Protoss_Forge 1 2862
Protoss_Photon_Cannon 3 9897
Protoss_Nexus 1 5437
Protoss_Gateway 3 9143
Protoss_Assimilator 2 6543
Protoss_Cybernetics_Core 1 6340
Protoss_Zealot 5 9172
Protoss_Dragoon 1 7196
Protoss_Stargate 1 7602
Protoss_Citadel_of_Adun 1 7915
Protoss_Corsair 2 8938
Protoss_Templar_Archives 1 8944
Protoss_Dark_Templar 2 10746
Protoss_High_Templar 2 10186
10746
