Protoss_Forge 1 2648
Protoss_Nexus 1 5175
Protoss_Gateway 4 9649
Protoss_Photon_Cannon 2 9227
Protoss_Assimilator 2 6750
Protoss_Zealot 7 10483
Protoss_Cybernetics_Core 1 6374
Protoss_Dragoon 1 7540
Protoss_Robotics_Facility 1 8452
Protoss_Citadel_of_Adun 1 8503
Protoss_Shuttle 1 9822
Protoss_Robotics_Support_Bay 1 9481
Protoss_Templar_Archives 1 10250
Protoss_Reaver 1 10873
10873
