Protoss_Nexus 1 4978
Protoss_Forge 1 4125
Protoss_Gateway 2 8164
Protoss_Photon_Cannon 1 5169
Protoss_Assimilator 2 7302
Protoss_Zealot 6 10073
Protoss_Cybernetics_Core 1 6889
Protoss_Citadel_of_Adun 1 8063
Protoss_Templar_Archives 1 10008
10073
