Protoss_Forge 1 2760
Protoss_Photon_Cannon 5 10584
Protoss_Nexus 1 5588
Protoss_Gateway 1 5821
Protoss_Assimilator 2 8501
Protoss_Zealot 4 9998
Protoss_Cybernetics_Core 1 8127
Protoss_Stargate 1 9309
Protoss_Citadel_of_Adun 2 10400
Protoss_Corsair 1 10043
10584
