Protoss_Nexus 1 4650
Protoss_Forge 1 3760
Protoss_Photon_Cannon 3 10211
Protoss_Gateway 3 10062
Protoss_Assimilator 2 7017
Protoss_Cybernetics_Core 1 6063
Protoss_Zealot 2 7548
Protoss_Stargate 1 7238
Protoss_Citadel_of_Adun 1 7618
Protoss_Corsair 2 8533
Protoss_Templar_Archives 1 9635
Protoss_Robotics_Facility 1 10031
Protoss_Dark_Templar 1 10558
Protoss_High_Templar 1 10588
10588
