Protoss_Assimilator 1 2450
Protoss_Gateway 1 3270
Protoss_Cybernetics_Core 1 4284
Protoss_Stargate 1 5440
Protoss_Dragoon 1 5193
Protoss_Robotics_Facility 1 6254
Protoss_Corsair 6 9467
Protoss_Forge 1 6303
Protoss_Shuttle 1 7807
Protoss_Photon_Cannon 3 9651
Protoss_Robotics_Support_Bay 1 9197
Protoss_Nexus 1 11080
Protoss_Reaver 1 10591
11080
