Protoss_Gateway 2 7147
Protoss_Assimilator 1 2834
Protoss_Zealot 6 9294
Protoss_Cybernetics_Core 1 4675
Protoss_Dragoon 6 10116
Protoss_Robotics_Facility 1 6904
Protoss_Observatory 1 7451
Protoss_Shuttle 1 8061
Protoss_Robotics_Support_Bay 1 8154
Protoss_Observer 2 10318
Protoss_Reaver 1 9714
Protoss_Nexus 1 10986
10986
