Protoss_Gateway 4 10163
Protoss_Assimilator 1 3058
Protoss_Cybernetics_Core 1 4183
Protoss_Dragoon 6 10528
Protoss_Robotics_Facility 1 6810
Protoss_Nexus 1 8468
Protoss_Citadel_of_Adun 1 8049
Protoss_Shuttle 1 8547
Protoss_Observatory 1 8504
Protoss_Observer 1 9954
10528
