Protoss_Gateway 4 10539
Protoss_Assimilator 1 2906
Protoss_Cybernetics_Core 1 3924
Protoss_Dragoon 9 9813
Protoss_Nexus 2 10450
Protoss_Robotics_Facility 1 8702
Protoss_Observatory 1 9260
Protoss_Observer 2 10560
10560
