Protoss_Gateway 2 5415
Protoss_Assimilator 2 9951
Protoss_Cybernetics_Core 1 4082
Protoss_Dragoon 14 10746
Protoss_Nexus 3 11620
Protoss_Robotics_Facility 1 9649
Protoss_Observatory 1 10201
11620
