Protoss_Gateway 2 5779
Protoss_Assimilator 1 2887
Protoss_Cybernetics_Core 1 3757
Protoss_Dragoon 10 10598
Protoss_Zealot 5 9683
Protoss_Robotics_Facility 1 9576
Protoss_Nexus 1 11235
11235
