Protoss_Nexus 2 10443
Protoss_Gateway 3 7352
Protoss_Assimilator 2 9735
Protoss_Cybernetics_Core 1 4974
Protoss_Dragoon 10 9718
Protoss_Robotics_Facility 1 9107
Protoss_Citadel_of_Adun 1 9645
Protoss_Observatory 1 9681
Protoss_Shuttle 1 10272
Protoss_Zealot 1 10453
10453
