Protoss_Gateway 2 8179
Protoss_Assimilator 1 2880
Protoss_Cybernetics_Core 1 3884
Protoss_Dragoon 5 9083
Protoss_Robotics_Facility 1 5756
Protoss_Shuttle 1 6792
Protoss_Robotics_Support_Bay 1 6576
Protoss_Citadel_of_Adun 1 7299
Protoss_Reaver 2 9821
Protoss_Templar_Archives 1 8539
Protoss_Dark_Templar 3 10408
10408
