Protoss_Nexus 1 4586
Protoss_Gateway 2 7251
Protoss_Assimilator 2 7257
Protoss_Cybernetics_Core 1 5211
Protoss_Forge 1 5222
Protoss_Photon_Cannon 2 8243
Protoss_Dragoon 2 6852
Protoss_Citadel_of_Adun 1 6423
Protoss_Templar_Archives 1 7450
Protoss_Zealot 1 7454
Protoss_Dark_Templar 3 9076
Protoss_Robotics_Facility 1 8928
Protoss_Shuttle 1 10017
Protoss_High_Templar 2 10182
10182
