Protoss_Gateway 2 6699
Protoss_Assimilator 1 2819
Protoss_Cybernetics_Core 1 3741
Protoss_Dragoon 12 10015
Protoss_Robotics_Facility 1 6522
Protoss_Observatory 1 7082
Protoss_Observer 3 10223
Protoss_Nexus 1 11310
11310
