Protoss_Gateway 4 10509
Protoss_Assimilator 1 3021
Protoss_Cybernetics_Core 1 3849
Protoss_Dragoon 11 10718
Protoss_Robotics_Facility 1 7998
Protoss_Nexus 1 9384
Protoss_Zealot 1 8508
Protoss_Observatory 1 8601
Protoss_Observer 2 10040
10718
