Protoss_Gateway 2 10656
Protoss_Assimilator 1 3106
Protoss_Cybernetics_Core 1 4099
Protoss_Dragoon 8 10630
Protoss_Robotics_Facility 1 6763
Protoss_Shuttle 1 7745
Protoss_Robotics_Support_Bay 1 7701
Protoss_Reaver 1 8832
Protoss_Nexus 1 10902
Protoss_Observatory 1 9707
Protoss_Observer 1 10384
10902
