Protoss_Gateway 3 7081
Protoss_Forge 1 3545
Protoss_Zealot 7 8933
Protoss_Photon_Cannon 4 7795
Protoss_Assimilator 1 7799
Protoss_Cybernetics_Core 1 8665
Protoss_Nexus 1 10819
Protoss_Dragoon 2 9933
Protoss_Citadel_of_Adun 1 10682
10819
