Protoss_Gateway 1 2873
Protoss_Assimilator 1 2895
Protoss_Cybernetics_Core 1 3993
Protoss_Zealot 4 6165
Protoss_Robotics_Facility 1 5398
Protoss_Shuttle 1 6387
Protoss_Robotics_Support_Bay 1 6446
Protoss_Reaver 2 9928
Protoss_Dragoon 3 10518
Protoss_Observatory 1 7733
Protoss_Observer 1 8878
Protoss_Shield_Battery 1 9696
10518
