Protoss_Gateway 2 6578
Protoss_Assimilator 1 3091
Protoss_Cybernetics_Core 1 4022
Protoss_Dragoon 7 8382
Protoss_Robotics_Facility 1 6678
Protoss_Observatory 1 7231
Protoss_Observer 3 9154
Protoss_Nexus 1 9969
Protoss_Robotics_Support_Bay 1 9551
Protoss_Shuttle 1 10055
Protoss_Zealot 2 10240
10240
