Protoss_Gateway 2 7124
Protoss_Assimilator 1 2999
Protoss_Cybernetics_Core 1 3916
Protoss_Dragoon 8 9848
Protoss_Robotics_Facility 1 6597
Protoss_Observatory 1 7425
Protoss_Observer 1 8216
Protoss_Nexus 1 9619
Protoss_Shuttle 1 9251
Protoss_Robotics_Support_Bay 1 9120
Protoss_Reaver 1 10378
Protoss_Zealot 2 10450
10450
