Protoss_Gateway 5 10454
Protoss_Assimilator 1 2858
Protoss_Zealot 1 3493
Protoss_Cybernetics_Core 1 4626
Protoss_Dragoon 11 10708
Protoss_Nexus 1 8581
Protoss_Robotics_Facility 1 9492
Protoss_Observatory 1 10077
10708
