Protoss_Nexus 1 4518
Protoss_Gateway 4 8834
Protoss_Assimilator 2 8232
Protoss_Cybernetics_Core 1 5005
Protoss_Dragoon 7 10696
Protoss_Robotics_Facility 1 8378
Protoss_Shuttle 1 9825
Protoss_Observatory 1 9496
Protoss_Zealot 4 10270
Protoss_Observer 1 10543
10696
