Protoss_Gateway 4 9965
Protoss_Assimilator 2 9108
Protoss_Cybernetics_Core 1 3979
Protoss_Dragoon 6 9140
Protoss_Citadel_of_Adun 1 6291
Protoss_Templar_Archives 1 7289
Protoss_Nexus 1 9288
Protoss_Robotics_Facility 1 9182
Protoss_Observatory 1 9781
Protoss_Observer 1 10462
10462
