Protoss_Gateway 2 5418
Protoss_Assimilator 1 2785
Protoss_Cybernetics_Core 1 3728
Protoss_Dragoon 10 10613
Protoss_Nexus 2 10190
Protoss_Robotics_Facility 1 8639
Protoss_Observatory 1 9201
Protoss_Observer 2 10575
10613
