Protoss_Nexus 1 4430
Protoss_Gateway 4 9444
Protoss_Assimilator 2 7221
Protoss_Cybernetics_Core 1 5126
Protoss_Zealot 3 9886
Protoss_Dragoon 14 10729
Protoss_Robotics_Facility 1 7717
Protoss_Shield_Battery 1 7481
Protoss_Observatory 1 9405
Protoss_Observer 1 10118
Protoss_Citadel_of_Adun 1 10521
10729
