Protoss_Nexus 1 4670
Protoss_Gateway 2 5974
Protoss_Assimilator 2 10130
Protoss_Cybernetics_Core 1 5234
Protoss_Zealot 3 10173
Protoss_Dragoon 8 9239
Protoss_Forge 1 7770
Protoss_Photon_Cannon 2 9882
Protoss_Robotics_Facility 1 11022
11022
