Protoss_Gateway 4 9795
Protoss_Assimilator 1 2946
Protoss_Cybernetics_Core 1 3842
Protoss_Dragoon 9 10152
Protoss_Robotics_Facility 1 6645
Protoss_Observatory 1 7289
Protoss_Nexus 2 10424
Protoss_Observer 3 9856
10424
