Protoss_Gateway 2 4330
Protoss_Assimilator 1 2814
Protoss_Cybernetics_Core 1 3745
Protoss_Dragoon 8 10226
Protoss_Citadel_of_Adun 1 6827
Protoss_Zealot 2 7136
Protoss_Templar_Archives 1 8183
Protoss_Dark_Templar 2 9076
Protoss_Nexus 1 11075
11075
