Protoss_Gateway 3 7014
Protoss_Assimilator 2 10583
Protoss_Cybernetics_Core 1 3743
Protoss_Dragoon 12 10532
Protoss_Nexus 1 7379
Protoss_Robotics_Facility 1 7995
Protoss_Zealot 1 8340
Protoss_Observatory 1 8694
Protoss_Shuttle 1 9441
Protoss_Observer 1 10044
10583
