Protoss_Gateway 4 9467
Protoss_Assimilator 1 2836
Protoss_Cybernetics_Core 1 3830
Protoss_Dragoon 6 7604
Protoss_Citadel_of_Adun 2 8978
Protoss_Nexus 1 9608
Protoss_Robotics_Facility 1 9213
Protoss_Templar_Archives 1 9987
Protoss_Shuttle 1 10219
Protoss_Observatory 1 9911
10219
