Protoss_Gateway 3 10809
Protoss_Assimilator 1 2880
Protoss_Cybernetics_Core 1 3805
Protoss_Dragoon 7 10183
Protoss_Robotics_Facility 1 6477
Protoss_Observatory 1 7104
Protoss_Observer 2 9843
Protoss_Nexus 1 9490
Protoss_Shuttle 1 8837
10809
