Protoss_Nexus 1 4556
Protoss_Gateway 4 9881
Protoss_Assimilator 1 4001
Protoss_Cybernetics_Core 1 5004
Protoss_Zealot 4 10553
Protoss_Dragoon 7 10728
Protoss_Robotics_Facility 1 7289
Protoss_Shuttle 1 8327
Protoss_Robotics_Support_Bay 1 8097
Protoss_Observatory 1 8191
Protoss_Observer 1 9778
10728
