Protoss_Gateway 2 6794
Protoss_Assimilator 1 2928
Protoss_Cybernetics_Core 1 3940
Protoss_Dragoon 9 10555
Protoss_Citadel_of_Adun 1 5924
Protoss_Templar_Archives 1 6919
Protoss_Dark_Templar 2 7844
Protoss_Nexus 1 9341
Protoss_Robotics_Facility 1 9714
10555
