Protoss_Gateway 2 4526
Protoss_Assimilator 2 8388
Protoss_Cybernetics_Core 1 3883
Protoss_Dragoon 6 10620
Protoss_Nexus 1 8091
Protoss_Citadel_of_Adun 1 7930
Protoss_Robotics_Facility 1 8697
Protoss_Templar_Archives 1 8920
Protoss_Shuttle 1 9719
Protoss_Dark_Templar 3 10532
Protoss_Stargate 1 10609
10620
