Protoss_Gateway 2 6638
Protoss_Assimilator 1 2831
Protoss_Cybernetics_Core 1 3745
Protoss_Dragoon 8 10486
Protoss_Robotics_Facility 1 6673
Protoss_Shuttle 1 7695
Protoss_Robotics_Support_Bay 1 7315
Protoss_Zealot 2 7898
Protoss_Reaver 1 8746
Protoss_Observatory 1 8458
Protoss_Nexus 1 10196
Protoss_Observer 1 9394
10486
