Protoss_Gateway 2 7997
Protoss_Assimilator 2 5001
Protoss_Zealot 5 6040
Protoss_Cybernetics_Core 1 6214
Protoss_Dragoon 5 10318
Protoss_Citadel_of_Adun 1 7443
Protoss_Templar_Archives 1 8507
Protoss_Dark_Templar 2 10052
10318
