Protoss_Gateway 2 6117
Protoss_Assimilator 1 3430
Protoss_Cybernetics_Core 1 4677
Protoss_Dragoon 8 9636
Protoss_Nexus 1 9154
Protoss_Robotics_Facility 1 9312
Protoss_Shuttle 1 10315
Protoss_Robotics_Support_Bay 1 10364
10364
