Protoss_Gateway 2 6596
Protoss_Assimilator 1 2908
Protoss_Cybernetics_Core 1 3821
Protoss_Dragoon 10 10000
Protoss_Robotics_Facility 1 6604
Protoss_Observatory 1 7156
Protoss_Observer 2 8910
Protoss_Nexus 1 9888
Protoss_Shuttle 1 10555
10555
