Protoss_Gateway 3 9029
Protoss_Assimilator 1 3642
Protoss_Zealot 2 4876
Protoss_Cybernetics_Core 1 4817
Protoss_Dragoon 8 9982
Protoss_Nexus 1 8463
Protoss_Robotics_Facility 1 8742
Protoss_Observatory 1 9342
Protoss_Observer 1 10058
10058
