Protoss_Gateway 4 10233
Protoss_Assimilator 1 2862
Protoss_Cybernetics_Core 1 3919
Protoss_Zealot 1 4418
Protoss_Dragoon 8 10352
Protoss_Nexus 1 7969
Protoss_Robotics_Facility 1 7787
Protoss_Shuttle 1 8849
Protoss_Robotics_Support_Bay 1 8632
Protoss_Reaver 1 9900
Protoss_Observatory 1 9426
Protoss_Observer 1 10504
10504
