Protoss_Gateway 2 6945
Protoss_Assimilator 1 2923
Protoss_Cybernetics_Core 1 3872
Protoss_Dragoon 6 10152
Protoss_Robotics_Facility 1 6879
Protoss_Observatory 1 7437
Protoss_Nexus 1 9257
Protoss_Shuttle 1 8549
Protoss_Robotics_Support_Bay 1 8273
Protoss_Reaver 1 9654
Protoss_Zealot 2 9300
Protoss_Observer 1 10258
10258
