Protoss_Gateway 2 6657
Protoss_Assimilator 1 2873
Protoss_Cybernetics_Core 1 3925
Protoss_Dragoon 9 9694
Protoss_Nexus 1 8693
Protoss_Robotics_Facility 1 9311
Protoss_Zealot 2 10594
Protoss_Shuttle 1 10397
10594
