Protoss_Gateway 3 9190
Protoss_Nexus 1 5008
Protoss_Assimilator 2 9970
Protoss_Cybernetics_Core 1 4829
Protoss_Dragoon 12 10342
Protoss_Robotics_Facility 1 8356
Protoss_Observatory 1 9045
Protoss_Observer 1 10088
10342
