Protoss_Gateway 3 10470
Protoss_Assimilator 1 3167
Protoss_Cybernetics_Core 1 4176
Protoss_Dragoon 6 7798
Protoss_Citadel_of_Adun 1 7250
Protoss_Templar_Archives 1 8244
Protoss_Dark_Templar 5 10693
Protoss_Nexus 1 11015
11015
