Protoss_Gateway 3 7357
Protoss_Zealot 7 10132
Protoss_Assimilator 1 4096
Protoss_Cybernetics_Core 1 4923
Protoss_Dragoon 8 9242
Protoss_Robotics_Facility 1 8678
Protoss_Shuttle 1 9659
Protoss_Robotics_Support_Bay 1 9685
Protoss_Reaver 1 10812
10812
