Protoss_Gateway 3 10490
Protoss_Assimilator 1 3125
Protoss_Cybernetics_Core 1 4134
Protoss_Dragoon 11 10422
Protoss_Robotics_Facility 1 6992
Protoss_Observatory 1 7584
Protoss_Observer 2 10133
Protoss_Nexus 1 10850
10850
