Protoss_Gateway 2 9817
Protoss_Assimilator 2 3221
Protoss_Cybernetics_Core 1 4450
Protoss_Forge 1 5160
Protoss_Robotics_Facility 1 6514
Protoss_Photon_Cannon 2 6975
Protoss_Robotics_Support_Bay 1 7142
Protoss_Shuttle 1 8062
Protoss_Reaver 1 9113
Protoss_Citadel_of_Adun 1 9721
9817
