Protoss_Gateway 2 7996
Protoss_Assimilator 1 3120
Protoss_Cybernetics_Core 1 3961
Protoss_Robotics_Facility 1 5502
Protoss_Dragoon 9 10482
Protoss_Observatory 1 6157
Protoss_Observer 3 9812
Protoss_Nexus 1 11409
11409
