Protoss_Gateway 3 9074
Protoss_Assimilator 1 2861
Protoss_Cybernetics_Core 1 3770
Protoss_Dragoon 11 10272
Protoss_Nexus 1 8359
Protoss_Robotics_Facility 1 8399
Protoss_Observatory 1 8986
Protoss_Observer 2 10295
10295
