Protoss_Gateway 2 6409
Protoss_Zealot 4 8422
Protoss_Assimilator 1 3682
Protoss_Cybernetics_Core 1 4746
Protoss_Dragoon 7 9732
Protoss_Robotics_Facility 1 7395
Protoss_Nexus 1 9265
Protoss_Observatory 1 8055
Protoss_Observer 1 8740
Protoss_Shuttle 1 9650
Protoss_Robotics_Support_Bay 1 9778
Protoss_Reaver 1 10906
10906
