Protoss_Gateway 2 5464
Protoss_Assimilator 1 2861
Protoss_Cybernetics_Core 1 3786
Protoss_Dragoon 10 9184
Protoss_Zealot 3 10278
Protoss_Robotics_Facility 1 8355
Protoss_Shuttle 1 9345
Protoss_Robotics_Support_Bay 1 9241
Protoss_Reaver 1 10602
10602
