Protoss_Gateway 2 7211
Protoss_Assimilator 1 3024
Protoss_Cybernetics_Core 1 3934
Protoss_Dragoon 10 10680
Protoss_Nexus 2 9890
Protoss_Robotics_Facility 1 9978
Protoss_Zealot 1 9928
10680
