Protoss_Gateway 2 5863
Protoss_Assimilator 2 3319
Protoss_Cybernetics_Core 1 4361
Protoss_Dragoon 8 10162
Protoss_Zealot 3 9188
Protoss_Robotics_Facility 1 8393
Protoss_Shuttle 1 9409
Protoss_Robotics_Support_Bay 1 9285
Protoss_Observatory 1 10140
Protoss_Reaver 1 10944
10944
