Protoss_Gateway 2 9467
Protoss_Assimilator 1 3128
Protoss_Cybernetics_Core 1 3795
Protoss_Dragoon 6 9238
Protoss_Robotics_Facility 1 6835
Protoss_Shuttle 1 7859
Protoss_Robotics_Support_Bay 1 7561
Protoss_Nexus 2 11041
Protoss_Reaver 1 9032
Protoss_Observatory 1 8903
Protoss_Observer 2 10590
11041
