Protoss_Gateway 1 2849
Protoss_Assimilator 1 3095
Protoss_Cybernetics_Core 1 3929
Protoss_Dragoon 7 10433
Protoss_Robotics_Facility 1 7060
Protoss_Shuttle 1 8047
Protoss_Robotics_Support_Bay 1 7729
Protoss_Reaver 1 9136
Protoss_Observatory 1 8589
Protoss_Observer 2 10342
Protoss_Zealot 1 10245
10433
