Protoss_Gateway 2 4855
Protoss_Assimilator 1 3360
Protoss_Zealot 6 9890
Protoss_Cybernetics_Core 1 4417
Protoss_Dragoon 11 10672
Protoss_Robotics_Facility 1 8367
Protoss_Shuttle 1 9459
Protoss_Robotics_Support_Bay 1 9418
Protoss_Reaver 1 10770
10770
