Protoss_Gateway 2 7419
Protoss_Assimilator 1 2882
Protoss_Zealot 1 3438
Protoss_Cybernetics_Core 1 4033
Protoss_Dragoon 10 10664
Protoss_Robotics_Facility 1 6823
Protoss_Observatory 1 7429
Protoss_Observer 2 8928
Protoss_Nexus 1 10184
Protoss_Citadel_of_Adun 1 9608
10664
