Protoss_Gateway 3 8221
Protoss_Assimilator 1 2866
Protoss_Cybernetics_Core 1 3880
Protoss_Dragoon 8 10694
Protoss_Citadel_of_Adun 1 7655
Protoss_Zealot 10 9596
Protoss_Robotics_Facility 1 10618
Protoss_Templar_Archives 1 10454
10694
