Protoss_Gateway 2 6711
Protoss_Assimilator 1 2953
Protoss_Cybernetics_Core 1 3920
Protoss_Dragoon 11 10162
Protoss_Robotics_Facility 1 6908
Protoss_Observatory 1 7513
Protoss_Observer 2 8856
Protoss_Nexus 1 10534
Protoss_Shuttle 1 9921
10534
