Protoss_Gateway 3 7834
Protoss_Assimilator 1 2800
Protoss_Cybernetics_Core 1 3784
Protoss_Dragoon 9 10480
Protoss_Nexus 1 7828
Protoss_Robotics_Facility 1 9028
Protoss_Zealot 3 8798
Protoss_Observatory 1 9576
10480
