Protoss_Gateway 3 10834
Protoss_Assimilator 1 2905
Protoss_Cybernetics_Core 1 4036
Protoss_Dragoon 9 9888
Protoss_Nexus 1 8723
Protoss_Robotics_Facility 1 9507
Protoss_Zealot 2 9423
Protoss_Observatory 1 10111
10834
