Protoss_Gateway 2 7197
Protoss_Assimilator 1 3001
Protoss_Zealot 2 4146
Protoss_Cybernetics_Core 1 4025
Protoss_Dragoon 4 7340
Protoss_Citadel_of_Adun 1 5664
Protoss_Templar_Archives 1 7021
Protoss_Dark_Templar 6 9860
Protoss_Nexus 1 10199
10199
