Protoss_Gateway 2 7032
Protoss_Assimilator 1 3130
Protoss_Cybernetics_Core 1 4033
Protoss_Dragoon 11 10523
Protoss_Robotics_Facility 1 5948
Protoss_Observatory 1 7147
Protoss_Observer 3 10008
Protoss_Nexus 1 11010
11010
