Protoss_Gateway 3 10701
Protoss_Assimilator 1 2883
Protoss_Cybernetics_Core 1 3833
Protoss_Dragoon 6 10478
Protoss_Robotics_Facility 1 5571
Protoss_Shuttle 1 6702
Protoss_Zealot 2 7472
Protoss_Observatory 2 8657
Protoss_Robotics_Support_Bay 1 7235
Protoss_Reaver 1 8376
Protoss_Nexus 1 10660
10701
