Protoss_Gateway 3 6604
Protoss_Assimilator 1 2872
Protoss_Cybernetics_Core 1 4013
Protoss_Dragoon 11 10072
Protoss_Zealot 2 8763
Protoss_Nexus 1 10563
Protoss_Citadel_of_Adun 1 10341
Protoss_Robotics_Facility 1 10929
10929
