Protoss_Gateway 3 9394
Protoss_Assimilator 2 10194
Protoss_Cybernetics_Core 1 3835
Protoss_Dragoon 10 10318
Protoss_Nexus 1 7816
Protoss_Robotics_Facility 1 8267
Protoss_Observatory 1 9078
Protoss_Robotics_Support_Bay 1 9698
Protoss_Observer 1 9893
10318
