Protoss_Gateway 2 9277
Protoss_Assimilator 1 2844
Protoss_Cybernetics_Core 1 3896
Protoss_Robotics_Facility 1 5465
Protoss_Dragoon 3 9263
Protoss_Shuttle 1 6457
Protoss_Robotics_Support_Bay 1 6291
Protoss_Observatory 1 6721
Protoss_Zealot 2 7633
Protoss_Reaver 2 11031
Protoss_Observer 2 9238
Protoss_Nexus 1 9810
11031
