Protoss_Gateway 2 7226
Protoss_Assimilator 1 2776
Protoss_Cybernetics_Core 1 3725
Protoss_Dragoon 5 10562
Protoss_Citadel_of_Adun 1 6346
Protoss_Robotics_Facility 1 7201
Protoss_Templar_Archives 1 7677
Protoss_Shuttle 2 10751
Protoss_Dark_Templar 3 9724
Protoss_Nexus 1 10676
10751
