Protoss_Assimilator 1 2388
Protoss_Gateway 4 10798
Protoss_Cybernetics_Core 1 4310
Protoss_Zealot 3 10135
Protoss_Robotics_Facility 1 5717
Protoss_Dragoon 7 9533
Protoss_Observatory 1 6406
Protoss_Observer 3 8528
Protoss_Citadel_of_Adun 1 9406
10798
