Protoss_Gateway 2 5463
Protoss_Assimilator 2 9555
Protoss_Cybernetics_Core 1 3864
Protoss_Dragoon 7 10138
Protoss_Robotics_Facility 1 7291
Protoss_Zealot 3 9813
Protoss_Shuttle 1 8522
Protoss_Observatory 1 8336
Protoss_Nexus 1 10035
Protoss_Citadel_of_Adun 1 9511
Protoss_Observer 2 9815
Protoss_Templar_Archives 1 10826
10826
