Protoss_Gateway 2 5438
Protoss_Assimilator 1 2955
Protoss_Cybernetics_Core 1 3964
Protoss_Dragoon 4 8203
Protoss_Zealot 3 6298
Protoss_Citadel_of_Adun 1 7298
Protoss_Templar_Archives 1 8470
Protoss_Dark_Templar 4 10133
Protoss_Nexus 1 10690
10690
