Protoss_Gateway 2 4638
Protoss_Assimilator 1 2843
Protoss_Cybernetics_Core 1 3811
Protoss_Dragoon 3 5766
Protoss_Citadel_of_Adun 1 6672
Protoss_Robotics_Facility 1 7326
Protoss_Zealot 2 7356
Protoss_Templar_Archives 1 7724
Protoss_Shuttle 1 8349
Protoss_Dark_Templar 6 10620
Protoss_Nexus 1 11051
11051
