Protoss_Assimilator 1 2215
Protoss_Gateway 3 10801
Protoss_Cybernetics_Core 1 4094
Protoss_Zealot 6 7038
Protoss_Citadel_of_Adun 1 6252
Protoss_Templar_Archives 1 7261
Protoss_Dark_Templar 4 9093
Protoss_Nexus 1 9710
Protoss_Dragoon 2 10498
10801
