Protoss_Gateway 3 10768
Protoss_Assimilator 1 3021
Protoss_Zealot 2 4478
Protoss_Cybernetics_Core 1 4554
Protoss_Citadel_of_Adun 1 5589
Protoss_Dragoon 5 10530
Protoss_Templar_Archives 1 7009
Protoss_Nexus 2 10955
Protoss_Dark_Templar 2 7882
Protoss_Stargate 1 10829
10955
