Protoss_Gateway 2 7512
Protoss_Assimilator 1 2997
Protoss_Cybernetics_Core 1 3869
Protoss_Dragoon 7 10073
Protoss_Citadel_of_Adun 1 6621
Protoss_Templar_Archives 1 7624
Protoss_Dark_Templar 3 9245
Protoss_Nexus 1 11059
Protoss_Robotics_Facility 1 11047
11059
