Protoss_Gateway 1 2923
Protoss_Assimilator 1 3460
Protoss_Cybernetics_Core 1 4169
Protoss_Zealot 2 9088
Protoss_Dragoon 3 7578
Protoss_Robotics_Facility 1 6974
Protoss_Robotics_Support_Bay 1 7674
Protoss_Shuttle 1 8142
Protoss_Reaver 2 10245
10245
