Protoss_Gateway 2 3542
Protoss_Zealot 5 5322
Protoss_Assimilator 1 4462
Protoss_Cybernetics_Core 1 6190
Protoss_Forge 1 6501
Protoss_Dragoon 1 7172
Protoss_Photon_Cannon 2 7893
7893
