Protoss_Gateway 3 9474
Protoss_Assimilator 1 3100
Protoss_Cybernetics_Core 1 4153
Protoss_Dragoon 9 9595
Protoss_Robotics_Facility 1 5867
Protoss_Observatory 1 6524
Protoss_Observer 2 8713
Protoss_Shuttle 2 10462
Protoss_Zealot 3 10197
10462
