Protoss_Gateway 3 9246
Protoss_Assimilator 1 2958
Protoss_Cybernetics_Core 1 3891
Protoss_Dragoon 9 10290
Protoss_Robotics_Facility 1 6517
Protoss_Observatory 1 7099
Protoss_Nexus 2 11161
Protoss_Observer 3 9246
Protoss_Shuttle 1 10859
11161
