Protoss_Nexus 2 11262
Protoss_Gateway 3 9275
Protoss_Assimilator 2 6200
Protoss_Cybernetics_Core 1 5036
Protoss_Zealot 3 9498
Protoss_Dragoon 10 10530
Protoss_Robotics_Facility 1 7955
Protoss_Shuttle 1 8963
Protoss_Robotics_Support_Bay 1 8561
Protoss_Observatory 1 8589
Protoss_Reaver 1 10014
Protoss_Citadel_of_Adun 1 10882
11262
