Protoss_Gateway 5 10353
Protoss_Assimilator 1 2847
Protoss_Cybernetics_Core 1 3970
Protoss_Dragoon 11 10700
Protoss_Nexus 1 7751
Protoss_Robotics_Facility 1 8090
Protoss_Observatory 1 8708
Protoss_Observer 2 9990
Protoss_Citadel_of_Adun 1 10057
10700
