Protoss_Gateway 1 2841
Protoss_Assimilator 1 3019
Protoss_Cybernetics_Core 1 3944
Protoss_Dragoon 6 10258
Protoss_Robotics_Facility 1 5762
Protoss_Shuttle 1 7007
Protoss_Observatory 1 7233
Protoss_Zealot 2 9295
Protoss_Observer 1 7968
Protoss_Robotics_Support_Bay 1 8037
Protoss_Reaver 1 9196
10258
