Protoss_Gateway 2 8545
Protoss_Assimilator 2 10075
Protoss_Cybernetics_Core 1 3880
Protoss_Dragoon 8 9968
Protoss_Robotics_Facility 1 6593
Protoss_Observatory 1 7251
Protoss_Nexus 1 8710
Protoss_Observer 2 8830
Protoss_Robotics_Support_Bay 1 8390
Protoss_Shuttle 1 9787
Protoss_Reaver 1 10878
10878
