Protoss_Gateway 3 9807
Protoss_Zealot 5 10498
Protoss_Assimilator 1 4759
Protoss_Cybernetics_Core 1 5564
Protoss_Dragoon 7 10455
Protoss_Nexus 1 9571
Protoss_Robotics_Facility 1 9480
10498
