Protoss_Gateway 3 7237
Protoss_Assimilator 1 2761
Protoss_Cybernetics_Core 1 3731
Protoss_Dragoon 11 10224
Protoss_Nexus 1 7381
Protoss_Robotics_Facility 1 8064
Protoss_Zealot 3 9358
Protoss_Observatory 1 8603
Protoss_Observer 2 10040
10224
