Protoss_Gateway 2 7414
Protoss_Zealot 3 4828
Protoss_Assimilator 1 3648
Protoss_Cybernetics_Core 1 4829
Protoss_Dragoon 7 9828
Protoss_Robotics_Facility 1 7997
Protoss_Nexus 1 10010
Protoss_Shuttle 1 9382
Protoss_Robotics_Support_Bay 1 9306
Protoss_Reaver 1 10451
10451
