Protoss_Gateway 2 6149
Protoss_Assimilator 1 3025
Protoss_Cybernetics_Core 1 3974
Protoss_Dragoon 6 7855
Protoss_Robotics_Facility 1 7222
Protoss_Shuttle 1 8227
Protoss_Observatory 1 7978
Protoss_Zealot 4 9067
Protoss_Observer 2 10198
Protoss_Nexus 2 11210
11210
