Protoss_Gateway 2 5359
Protoss_Assimilator 1 2894
Protoss_Cybernetics_Core 1 3813
Protoss_Dragoon 10 9195
Protoss_Citadel_of_Adun 1 6748
Protoss_Templar_Archives 1 7839
Protoss_Robotics_Facility 1 9912
Protoss_Nexus 1 10995
Protoss_Dark_Templar 2 10348
10995
