Protoss_Gateway 3 10686
Protoss_Assimilator 1 3046
Protoss_Cybernetics_Core 1 4050
Protoss_Robotics_Facility 1 5574
Protoss_Dragoon 4 10078
Protoss_Zealot 2 6670
Protoss_Shuttle 1 6562
Protoss_Robotics_Support_Bay 1 6371
Protoss_Reaver 2 8881
Protoss_Observatory 1 8234
Protoss_Observer 2 10398
Protoss_Nexus 1 11245
11245
