Protoss_Gateway 3 7485
Protoss_Assimilator 1 2887
Protoss_Zealot 5 9078
Protoss_Cybernetics_Core 1 4095
Protoss_Dragoon 7 10710
Protoss_Citadel_of_Adun 1 5925
Protoss_Templar_Archives 1 7093
Protoss_Dark_Templar 3 8400
10710
