Protoss_Gateway 3 8572
Protoss_Assimilator 1 2851
Protoss_Cybernetics_Core 1 3805
Protoss_Dragoon 11 10456
Protoss_Nexus 1 7765
Protoss_Robotics_Facility 1 7818
Protoss_Observatory 1 8397
Protoss_Observer 1 9390
10456
