Protoss_Gateway 5 10719
Protoss_Nexus 2 8549
Protoss_Assimilator 2 9739
Protoss_Zealot 2 4653
Protoss_Cybernetics_Core 1 4774
Protoss_Dragoon 9 9953
Protoss_Robotics_Facility 1 9133
Protoss_Observatory 1 9992
10719
