Protoss_Nexus 1 4820
Protoss_Gateway 4 9778
Protoss_Assimilator 1 4635
Protoss_Cybernetics_Core 1 5734
Protoss_Dragoon 9 10208
Protoss_Robotics_Facility 1 8422
Protoss_Zealot 3 10508
Protoss_Shuttle 1 9457
Protoss_Observatory 1 9430
Protoss_Observer 1 10228
Protoss_Citadel_of_Adun 1 10814
10814
