Protoss_Gateway 2 6792
Protoss_Assimilator 1 2955
Protoss_Cybernetics_Core 1 3846
Protoss_Dragoon 12 10080
Protoss_Robotics_Facility 1 6956
Protoss_Observatory 1 7547
Protoss_Observer 2 8835
Protoss_Nexus 1 10060
Protoss_Robotics_Support_Bay 1 10091
Protoss_Shuttle 1 10702
10702
