Protoss_Gateway 3 8967
Protoss_Assimilator 1 3130
Protoss_Cybernetics_Core 1 3984
Protoss_Dragoon 6 9883
Protoss_Citadel_of_Adun 1 6067
Protoss_Zealot 1 6177
Protoss_Templar_Archives 1 7619
Protoss_Dark_Templar 3 10353
Protoss_Nexus 1 10203
10353
