Protoss_Gateway 3 10699
Protoss_Assimilator 1 3054
Protoss_Cybernetics_Core 1 3879
Protoss_Dragoon 12 10042
Protoss_Robotics_Facility 1 8007
Protoss_Observatory 1 8571
Protoss_Nexus 1 10565
Protoss_Observer 1 9713
10699
