Protoss_Gateway 2 7957
Protoss_Assimilator 2 10305
Protoss_Cybernetics_Core 1 3793
Protoss_Dragoon 7 9444
Protoss_Nexus 1 7871
Protoss_Robotics_Facility 1 7934
Protoss_Shuttle 1 8957
Protoss_Robotics_Support_Bay 1 8920
Protoss_Stargate 1 9978
Protoss_Reaver 1 10108
Protoss_Zealot 2 10046
10305
