Protoss_Gateway 2 7156
Protoss_Assimilator 2 3500
Protoss_Cybernetics_Core 1 4422
Protoss_Dragoon 1 5278
Protoss_Citadel_of_Adun 1 5654
Protoss_Templar_Archives 1 6777
Protoss_Dark_Templar 7 10463
Protoss_Forge 1 8123
Protoss_Nexus 1 10798
10798
