Protoss_Gateway 3 10844
Protoss_Assimilator 1 3115
Protoss_Cybernetics_Core 1 4369
Protoss_Robotics_Facility 1 5904
Protoss_Dragoon 5 10413
Protoss_Robotics_Support_Bay 1 6466
Protoss_Shuttle 2 10754
Protoss_Zealot 3 7838
Protoss_Reaver 2 9851
Protoss_Observatory 1 10327
10844
