Protoss_Gateway 2 4445
Protoss_Assimilator 1 3206
Protoss_Cybernetics_Core 1 4032
Protoss_Dragoon 7 10073
Protoss_Citadel_of_Adun 1 6326
Protoss_Zealot 2 6895
Protoss_Templar_Archives 1 7469
Protoss_Dark_Templar 1 8353
Protoss_Nexus 2 10907
Protoss_Robotics_Facility 1 9739
10907
