Protoss_Gateway 3 7289
Protoss_Assimilator 1 2978
Protoss_Cybernetics_Core 1 3894
Protoss_Dragoon 11 10268
Protoss_Nexus 1 6905
Protoss_Robotics_Facility 1 9652
Protoss_Citadel_of_Adun 1 10201
Protoss_Observatory 1 10363
10363
