Protoss_Gateway 1 2951
Protoss_Assimilator 1 3332
Protoss_Cybernetics_Core 1 4207
Protoss_Dragoon 8 10632
Protoss_Robotics_Facility 1 7671
Protoss_Shuttle 1 8887
Protoss_Robotics_Support_Bay 1 8487
Protoss_Reaver 1 9938
Protoss_Observatory 1 9753
Protoss_Nexus 1 11449
11449
