Protoss_Gateway 2 7380
Protoss_Assimilator 1 3080
Protoss_Cybernetics_Core 1 3994
Protoss_Zealot 5 10517
Protoss_Dragoon 8 9160
Protoss_Robotics_Facility 1 7155
Protoss_Shuttle 1 8252
Protoss_Observatory 1 7875
Protoss_Observer 3 10233
10517
