Protoss_Gateway 3 10794
Protoss_Assimilator 1 2813
Protoss_Cybernetics_Core 1 3762
Protoss_Dragoon 10 10132
Protoss_Robotics_Facility 1 6712
Protoss_Observatory 1 7463
Protoss_Nexus 1 8977
Protoss_Observer 3 10388
10794
