Protoss_Gateway 2 6305
Protoss_Assimilator 1 3041
Protoss_Cybernetics_Core 1 3929
Protoss_Dragoon 5 10516
Protoss_Citadel_of_Adun 1 6493
Protoss_Robotics_Facility 1 7119
Protoss_Templar_Archives 1 7504
Protoss_Shuttle 1 8109
Protoss_Dark_Templar 4 9364
Protoss_Nexus 1 10298
10516
