Protoss_Gateway 2 6249
Protoss_Assimilator 2 10297
Protoss_Cybernetics_Core 1 3781
Protoss_Dragoon 9 10094
Protoss_Nexus 2 10193
Protoss_Robotics_Facility 1 8503
Protoss_Observatory 1 9131
Protoss_Observer 2 10436
Protoss_Citadel_of_Adun 1 10216
10436
