Protoss_Gateway 2 7774
Protoss_Zealot 3 4653
Protoss_Assimilator 1 3613
Protoss_Cybernetics_Core 1 4739
Protoss_Dragoon 7 9740
Protoss_Robotics_Facility 1 7099
Protoss_Shuttle 1 8097
Protoss_Robotics_Support_Bay 1 7806
Protoss_Reaver 2 10281
10281
