Protoss_Nexus 1 4451
Protoss_Gateway 3 7808
Protoss_Assimilator 1 4121
Protoss_Cybernetics_Core 1 5278
Protoss_Zealot 4 9198
Protoss_Dragoon 8 10702
Protoss_Robotics_Facility 1 7917
Protoss_Observatory 1 8645
Protoss_Observer 1 9378
Protoss_Shuttle 1 10279
Protoss_Robotics_Support_Bay 1 9930
10702
