Protoss_Gateway 3 10328
Protoss_Assimilator 1 2798
Protoss_Cybernetics_Core 1 3771
Protoss_Dragoon 10 10626
Protoss_Zealot 1 6181
Protoss_Nexus 2 10277
Protoss_Robotics_Facility 1 10051
10626
