Protoss_Gateway 4 10160
Protoss_Assimilator 1 2840
Protoss_Cybernetics_Core 1 3767
Protoss_Dragoon 12 10604
Protoss_Robotics_Facility 1 6447
Protoss_Observatory 1 7035
Protoss_Observer 1 7998
Protoss_Nexus 1 9507
Protoss_Citadel_of_Adun 1 10595
10604
