Protoss_Gateway 2 5824
Protoss_Zealot 1 3854
Protoss_Nexus 1 5512
Protoss_Assimilator 2 6724
Protoss_Cybernetics_Core 1 5637
Protoss_Dragoon 7 10602
Protoss_Citadel_of_Adun 1 7538
Protoss_Forge 1 7862
Protoss_Templar_Archives 1 8572
Protoss_Robotics_Facility 1 9033
Protoss_Photon_Cannon 2 9133
Protoss_Dark_Templar 2 9646
Protoss_Stargate 1 10111
Protoss_Shuttle 1 10089
Protoss_Observatory 1 9742
10602
