Protoss_Gateway 4 10819
Protoss_Assimilator 1 2849
Protoss_Cybernetics_Core 1 3885
Protoss_Dragoon 13 10410
Protoss_Nexus 1 8587
Protoss_Robotics_Facility 1 8769
Protoss_Observatory 1 9563
Protoss_Observer 1 10250
10819
