Protoss_Gateway 2 6950
Protoss_Assimilator 1 2973
Protoss_Cybernetics_Core 1 3878
Protoss_Dragoon 9 10643
Protoss_Robotics_Facility 1 6894
Protoss_Shuttle 1 7892
Protoss_Zealot 4 8637
Protoss_Observatory 1 7897
Protoss_Observer 2 9185
10643
