Protoss_Gateway 2 5849
Protoss_Zealot 2 4010
Protoss_Assimilator 1 3656
Protoss_Cybernetics_Core 1 4852
Protoss_Dragoon 10 10108
Protoss_Robotics_Facility 1 7781
Protoss_Robotics_Support_Bay 1 8885
Protoss_Shuttle 1 9482
Protoss_Observatory 1 9204
Protoss_Observer 1 10188
10188
