Protoss_Gateway 4 10885
Protoss_Assimilator 1 2855
Protoss_Cybernetics_Core 1 3971
Protoss_Dragoon 9 10096
Protoss_Robotics_Facility 1 7585
Protoss_Observatory 1 8148
Protoss_Nexus 2 10753
Protoss_Observer 2 10338
10885
