Protoss_Gateway 4 10514
Protoss_Assimilator 1 2800
Protoss_Cybernetics_Core 1 3784
Protoss_Dragoon 12 10688
Protoss_Nexus 1 8430
Protoss_Robotics_Facility 1 9022
Protoss_Observatory 1 9911
10688
