Protoss_Gateway 2 5473
Protoss_Assimilator 1 2793
Protoss_Cybernetics_Core 1 3743
Protoss_Zealot 1 3712
Protoss_Dragoon 10 10248
Protoss_Nexus 1 8477
Protoss_Robotics_Facility 1 8686
Protoss_Shuttle 1 9669
Protoss_Observatory 1 9479
Protoss_Robotics_Support_Bay 1 10091
Protoss_Observer 1 10272
10272
