Protoss_Gateway 1 2822
Protoss_Assimilator 1 2811
Protoss_Cybernetics_Core 1 3886
Protoss_Dragoon 8 10224
Protoss_Robotics_Facility 1 6356
Protoss_Shuttle 1 7335
Protoss_Robotics_Support_Bay 1 7448
Protoss_Zealot 1 7928
Protoss_Reaver 2 9628
Protoss_Observatory 1 8819
Protoss_Observer 1 10232
Protoss_Nexus 1 11748
11748
