Protoss_Gateway 2 6809
Protoss_Assimilator 1 2811
Protoss_Cybernetics_Core 1 3759
Protoss_Dragoon 5 10346
Protoss_Citadel_of_Adun 1 5694
Protoss_Templar_Archives 1 6683
Protoss_Robotics_Facility 1 7725
Protoss_Dark_Templar 5 9188
Protoss_Shuttle 1 8759
Protoss_Nexus 1 10687
10687
