Protoss_Gateway 2 8830
Protoss_Assimilator 1 2910
Protoss_Cybernetics_Core 1 3852
Protoss_Zealot 1 3768
Protoss_Dragoon 8 9723
Protoss_Nexus 1 8640
Protoss_Robotics_Facility 1 9567
Protoss_Shuttle 1 10637
10637
