Protoss_Gateway 3 10003
Protoss_Assimilator 1 2848
Protoss_Cybernetics_Core 1 3905
Protoss_Dragoon 10 10028
Protoss_Robotics_Facility 1 6682
Protoss_Observatory 1 7311
Protoss_Observer 3 9490
Protoss_Nexus 1 10078
10078
