Protoss_Assimilator 1 3117
Protoss_Gateway 2 8117
Protoss_Cybernetics_Core 1 4592
Protoss_Robotics_Facility 1 6006
Protoss_Dragoon 2 9216
Protoss_Robotics_Support_Bay 1 6568
Protoss_Shuttle 1 7335
Protoss_Citadel_of_Adun 1 7834
Protoss_Reaver 2 9908
Protoss_Templar_Archives 1 8823
Protoss_Dark_Templar 2 10466
10466
