Protoss_Gateway 2 4524
Protoss_Assimilator 1 2997
Protoss_Cybernetics_Core 1 3853
Protoss_Dragoon 7 7953
Protoss_Robotics_Facility 1 7567
Protoss_Observatory 1 8214
Protoss_Nexus 1 10039
Protoss_Observer 1 8938
Protoss_Robotics_Support_Bay 1 9128
Protoss_Shuttle 1 9957
Protoss_Reaver 1 11008
11008
