Protoss_Gateway 3 10711
Protoss_Assimilator 1 3088
Protoss_Cybernetics_Core 1 3994
Protoss_Dragoon 8 10384
Protoss_Nexus 1 8195
Protoss_Robotics_Facility 1 8237
Protoss_Observatory 1 9175
Protoss_Observer 1 10104
10711
