Protoss_Gateway 2 4456
Protoss_Assimilator 1 3065
Protoss_Cybernetics_Core 1 4045
Protoss_Dragoon 11 9825
Protoss_Nexus 1 9750
Protoss_Citadel_of_Adun 1 8924
Protoss_Zealot 2 9728
Protoss_Templar_Archives 1 10070
10070
