Protoss_Gateway 2 5846
Protoss_Assimilator 1 3015
Protoss_Cybernetics_Core 1 3959
Protoss_Zealot 3 10460
Protoss_Dragoon 8 9590
Protoss_Nexus 1 8457
Protoss_Robotics_Facility 1 8284
Protoss_Shuttle 1 9295
Protoss_Robotics_Support_Bay 1 8953
Protoss_Reaver 1 10454
10460
