Protoss_Gateway 2 5187
Protoss_Assimilator 1 3055
Protoss_Zealot 1 3593
Protoss_Cybernetics_Core 1 4359
Protoss_Dragoon 5 7458
Protoss_Citadel_of_Adun 1 7113
Protoss_Templar_Archives 1 8241
Protoss_Nexus 1 9956
Protoss_Dark_Templar 4 9898
9956
