Protoss_Gateway 1 2838
Protoss_Assimilator 1 2916
Protoss_Cybernetics_Core 1 3880
Protoss_Dragoon 3 6518
Protoss_Robotics_Facility 1 6647
Protoss_Citadel_of_Adun 1 7114
Protoss_Shuttle 1 7652
Protoss_Robotics_Support_Bay 1 7519
Protoss_Zealot 2 9058
Protoss_Reaver 2 10786
Protoss_Templar_Archives 1 8994
Protoss_Nexus 1 11005
Protoss_Dark_Templar 1 10088
11005
