Protoss_Gateway 5 8614
Protoss_Zealot 4 10310
Protoss_Assimilator 1 4300
Protoss_Cybernetics_Core 1 6350
Protoss_Dragoon 4 10736
Protoss_Robotics_Facility 1 7835
Protoss_Robotics_Support_Bay 1 8453
Protoss_Shuttle 1 8931
Protoss_Reaver 1 9982
Protoss_Nexus 1 11351
Protoss_Observatory 1 10340
11351
