Protoss_Assimilator 3 9632
Protoss_Gateway 4 10896
Protoss_Zealot 11 10464
Protoss_Nexus 1 6569
Protoss_Cybernetics_Core 1 6751
Protoss_Forge 1 6908
Protoss_Photon_Cannon 2 8515
Protoss_Citadel_of_Adun 1 9021
Protoss_Templar_Archives 1 10652
10896
