Protoss_Gateway 2 7505
Protoss_Assimilator 1 2925
Protoss_Cybernetics_Core 1 3786
Protoss_Zealot 1 3828
Protoss_Dragoon 9 10708
Protoss_Robotics_Facility 1 7162
Protoss_Shuttle 1 8162
Protoss_Robotics_Support_Bay 1 7949
Protoss_Reaver 1 9466
Protoss_Nexus 1 10740
Protoss_Observatory 1 10029
10740
