Protoss_Gateway 1 2753
Protoss_Assimilator 1 2935
Protoss_Cybernetics_Core 1 3827
Protoss_Dragoon 6 10290
Protoss_Robotics_Facility 1 5593
Protoss_Shuttle 1 6577
Protoss_Robotics_Support_Bay 1 6306
Protoss_Zealot 2 7632
Protoss_Reaver 1 7916
Protoss_Observatory 1 7600
Protoss_Nexus 1 9590
Protoss_Observer 2 9184
10290
