Protoss_Gateway 1 2853
Protoss_Assimilator 2 10421
Protoss_Cybernetics_Core 1 4141
Protoss_Dragoon 6 9830
Protoss_Robotics_Facility 1 6827
Protoss_Shuttle 1 7817
Protoss_Robotics_Support_Bay 1 7434
Protoss_Reaver 2 10228
Protoss_Observatory 1 10073
Protoss_Nexus 1 11532
11532
