Protoss_Gateway 2 9418
Protoss_Assimilator 2 9052
Protoss_Cybernetics_Core 1 3793
Protoss_Dragoon 4 7128
Protoss_Citadel_of_Adun 1 6048
Protoss_Templar_Archives 1 7097
Protoss_Nexus 1 8905
Protoss_Dark_Templar 4 10290
Protoss_Stargate 1 9285
Protoss_Arbiter_Tribunal 1 10893
10893
