Protoss_Gateway 3 6283
Protoss_Assimilator 1 3024
Protoss_Cybernetics_Core 1 3962
Protoss_Dragoon 9 10713
Protoss_Nexus 2 10649
Protoss_Robotics_Facility 1 9636
Protoss_Observatory 2 10276
10713
