Protoss_Gateway 2 3245
Protoss_Zealot 6 5458
Protoss_Assimilator 2 10377
Protoss_Cybernetics_Core 1 5979
Protoss_Dragoon 8 10540
Protoss_Nexus 1 9246
Protoss_Robotics_Facility 1 9703
Protoss_Forge 1 9797
10540
