Protoss_Gateway 3 9594
Protoss_Zealot 1 3500
Protoss_Nexus 1 5571
Protoss_Assimilator 2 8954
Protoss_Cybernetics_Core 1 5438
Protoss_Dragoon 11 10234
Protoss_Robotics_Facility 1 9614
Protoss_Shuttle 1 10713
Protoss_Observatory 1 10379
10713
