Protoss_Gateway 2 7726
Protoss_Assimilator 1 2815
Protoss_Cybernetics_Core 1 3787
Protoss_Dragoon 11 10520
Protoss_Nexus 2 10991
Protoss_Robotics_Facility 1 7197
Protoss_Shuttle 1 8967
Protoss_Robotics_Support_Bay 1 9482
Protoss_Reaver 1 10616
Protoss_Observatory 1 10411
10991
