Protoss_Gateway 2 4377
Protoss_Assimilator 1 2805
Protoss_Cybernetics_Core 1 3799
Protoss_Dragoon 8 9302
Protoss_Nexus 1 8572
Protoss_Robotics_Facility 1 8286
Protoss_Shuttle 1 9289
Protoss_Robotics_Support_Bay 1 9377
Protoss_Reaver 1 10510
Protoss_Observatory 1 10039
10510
