Protoss_Gateway 4 10403
Protoss_Assimilator 1 2926
Protoss_Cybernetics_Core 1 3958
Protoss_Dragoon 13 10692
Protoss_Nexus 1 8044
Protoss_Zealot 1 7926
Protoss_Robotics_Facility 1 9873
10692
