Protoss_Gateway 2 5676
Protoss_Assimilator 1 3015
Protoss_Cybernetics_Core 1 3975
Protoss_Dragoon 3 6506
Protoss_Citadel_of_Adun 1 6823
Protoss_Zealot 3 7966
Protoss_Robotics_Facility 1 7873
Protoss_Templar_Archives 1 8063
Protoss_Shuttle 1 8853
Protoss_Dark_Templar 5 10490
Protoss_Nexus 1 11587
11587
