Protoss_Gateway 2 6783
Protoss_Assimilator 1 2786
Protoss_Cybernetics_Core 1 3845
Protoss_Dragoon 9 10070
Protoss_Robotics_Facility 1 6477
Protoss_Observatory 1 7102
Protoss_Observer 2 8492
Protoss_Nexus 1 9497
Protoss_Shuttle 1 9393
Protoss_Robotics_Support_Bay 1 9309
Protoss_Reaver 1 10644
10644
