Protoss_Gateway 3 9642
Protoss_Assimilator 1 2873
Protoss_Cybernetics_Core 1 4118
Protoss_Dragoon 7 10496
Protoss_Robotics_Facility 1 6161
Protoss_Nexus 1 7796
Protoss_Observatory 1 6748
Protoss_Observer 2 8280
10496
