Protoss_Gateway 3 10869
Protoss_Assimilator 1 2971
Protoss_Cybernetics_Core 1 3903
Protoss_Dragoon 9 10548
Protoss_Nexus 2 11177
Protoss_Robotics_Facility 1 7329
Protoss_Observatory 1 8867
Protoss_Observer 2 10256
11177
