Protoss_Gateway 2 5478
Protoss_Assimilator 1 2915
Protoss_Cybernetics_Core 1 3834
Protoss_Dragoon 6 8328
Protoss_Nexus 1 8569
Protoss_Robotics_Facility 1 8329
Protoss_Shuttle 1 9323
Protoss_Robotics_Support_Bay 1 9408
Protoss_Zealot 2 9970
Protoss_Observatory 1 10003
Protoss_Reaver 1 10642
10642
