Protoss_Gateway 2 6825
Protoss_Assimilator 1 3002
Protoss_Cybernetics_Core 1 3913
Protoss_Dragoon 8 9362
Protoss_Robotics_Facility 1 6580
Protoss_Observatory 1 7227
Protoss_Shuttle 1 8025
Protoss_Robotics_Support_Bay 1 8196
Protoss_Zealot 3 10146
Protoss_Observer 1 8628
Protoss_Reaver 2 11038
11038
