Protoss_Gateway 2 5022
Protoss_Assimilator 1 2972
Protoss_Zealot 1 3458
Protoss_Cybernetics_Core 1 4519
Protoss_Dragoon 10 9638
Protoss_Nexus 1 8725
Protoss_Robotics_Facility 1 9532
Protoss_Observatory 1 10241
10241
