Protoss_Gateway 4 10796
Protoss_Assimilator 2 8753
Protoss_Cybernetics_Core 1 3775
Protoss_Dragoon 9 9412
Protoss_Nexus 2 11441
Protoss_Citadel_of_Adun 1 7798
Protoss_Robotics_Facility 1 8401
Protoss_Observatory 1 9008
Protoss_Observer 2 10316
11441
