Protoss_Gateway 2 8702
Protoss_Assimilator 1 2931
Protoss_Cybernetics_Core 1 3892
Protoss_Dragoon 5 7906
Protoss_Nexus 1 7823
Protoss_Robotics_Facility 2 8721
Protoss_Shuttle 1 9089
Protoss_Robotics_Support_Bay 1 8890
Protoss_Zealot 4 10208
Protoss_Reaver 2 10218
10218
