Protoss_Gateway 3 8741
Protoss_Assimilator 1 2837
Protoss_Cybernetics_Core 1 3835
Protoss_Dragoon 9 9792
Protoss_Nexus 1 7856
Protoss_Robotics_Facility 1 8115
Protoss_Observatory 1 8978
Protoss_Observer 1 9904
Protoss_Robotics_Support_Bay 1 10182
Protoss_Shuttle 1 10805
10805
