Protoss_Gateway 3 8172
Protoss_Zealot 3 6328
Protoss_Nexus 2 7261
Protoss_Assimilator 2 10546
Protoss_Cybernetics_Core 1 7240
Protoss_Dragoon 7 10333
Protoss_Robotics_Facility 1 10992
10992
