Protoss_Gateway 3 9307
Protoss_Assimilator 1 3447
Protoss_Zealot 4 10013
Protoss_Cybernetics_Core 1 4907
Protoss_Dragoon 10 10413
Protoss_Nexus 1 8513
Protoss_Robotics_Facility 1 8869
Protoss_Observatory 1 9481
Protoss_Observer 1 10168
10413
