Protoss_Gateway 4 10580
Protoss_Assimilator 1 3024
Protoss_Cybernetics_Core 1 3833
Protoss_Citadel_of_Adun 1 4866
Protoss_Dragoon 9 9940
Protoss_Nexus 1 8256
Protoss_Zealot 4 9794
Protoss_Robotics_Facility 1 8431
Protoss_Shuttle 1 9481
Protoss_Observatory 1 9913
10580
