Protoss_Gateway 2 8508
Protoss_Zealot 2 4383
Protoss_Assimilator 1 3886
Protoss_Cybernetics_Core 1 5094
Protoss_Dragoon 6 9433
Protoss_Nexus 1 7885
Protoss_Citadel_of_Adun 1 8954
Protoss_Robotics_Facility 1 9802
Protoss_Templar_Archives 1 10012
Protoss_Shuttle 1 10792
10792
