Protoss_Gateway 3 9638
Protoss_Assimilator 1 2912
Protoss_Zealot 2 4538
Protoss_Cybernetics_Core 1 4630
Protoss_Dragoon 11 10650
Protoss_Nexus 1 9298
Protoss_Robotics_Facility 1 9241
Protoss_Shuttle 1 10229
Protoss_Observatory 1 9900
10650
