Protoss_Gateway 2 8605
Protoss_Assimilator 1 2905
Protoss_Cybernetics_Core 1 3873
Protoss_Dragoon 8 10025
Protoss_Nexus 1 7635
Protoss_Robotics_Facility 1 7753
Protoss_Observatory 1 8445
Protoss_Shuttle 1 9039
Protoss_Robotics_Support_Bay 1 9101
Protoss_Observer 1 9642
Protoss_Reaver 1 10692
Protoss_Zealot 1 10462
10692
