Protoss_Gateway 2 6330
Protoss_Zealot 3 5764
Protoss_Nexus 1 5976
Protoss_Assimilator 2 7841
Protoss_Cybernetics_Core 1 5921
Protoss_Dragoon 9 10362
Protoss_Robotics_Facility 1 9367
Protoss_Shuttle 1 10409
Protoss_Robotics_Support_Bay 1 9991
10409
