Protoss_Gateway 1 2894
Protoss_Forge 1 3128
Protoss_Zealot 6 10383
Protoss_Photon_Cannon 10 9460
Protoss_Assimilator 1 7606
Protoss_Nexus 1 9024
Protoss_Cybernetics_Core 1 9040
10383
