Protoss_Nexus 1 4731
Protoss_Forge 1 3840
Protoss_Gateway 4 10689
Protoss_Photon_Cannon 1 4930
Protoss_Assimilator 2 6925
Protoss_Zealot 2 6412
Protoss_Cybernetics_Core 1 6429
Protoss_Dragoon 8 10330
Protoss_Robotics_Facility 1 8480
Protoss_Observatory 1 9079
Protoss_Observer 2 10442
10689
