Protoss_Gateway 2 5513
Protoss_Assimilator 1 3058
Protoss_Cybernetics_Core 1 3911
Protoss_Dragoon 7 8566
Protoss_Nexus 2 11780
Protoss_Robotics_Facility 1 8662
Protoss_Shuttle 1 9693
Protoss_Zealot 2 9536
Protoss_Observatory 1 9459
Protoss_Robotics_Support_Bay 1 9899
Protoss_Observer 1 10296
11780
