Protoss_Gateway 2 3272
Protoss_Zealot 13 10238
Protoss_Forge 1 4723
Protoss_Photon_Cannon 4 7330
Protoss_Assimilator 1 7395
Protoss_Cybernetics_Core 1 8528
Protoss_Citadel_of_Adun 1 9866
Protoss_Dragoon 2 10478
Protoss_Templar_Archives 1 10853
10853
