Protoss_Gateway 2 5855
Protoss_Assimilator 1 3075
Protoss_Cybernetics_Core 1 4109
Protoss_Dragoon 8 8827
Protoss_Robotics_Facility 1 7501
Protoss_Observatory 1 8726
Protoss_Nexus 1 10425
Protoss_Zealot 4 10348
Protoss_Observer 1 9428
Protoss_Shuttle 1 10392
10425
