Protoss_Gateway 2 8839
Protoss_Assimilator 2 9332
Protoss_Cybernetics_Core 1 3919
Protoss_Dragoon 7 10700
Protoss_Nexus 1 7859
Protoss_Citadel_of_Adun 1 7691
Protoss_Robotics_Facility 1 8531
Protoss_Templar_Archives 1 8965
Protoss_Shuttle 1 9725
Protoss_Dark_Templar 3 10582
Protoss_Observatory 1 9815
Protoss_Observer 1 10558
10700
