Protoss_Gateway 3 10500
Protoss_Assimilator 1 3038
Protoss_Cybernetics_Core 1 3904
Protoss_Dragoon 6 10362
Protoss_Citadel_of_Adun 1 5804
Protoss_Robotics_Facility 1 6447
Protoss_Zealot 1 6438
Protoss_Templar_Archives 1 7059
Protoss_Shuttle 1 7647
Protoss_Dark_Templar 2 7918
Protoss_Nexus 1 10304
Protoss_Observatory 1 10126
10500
