Protoss_Gateway 3 8248
Protoss_Assimilator 1 2966
Protoss_Cybernetics_Core 1 3909
Protoss_Dragoon 10 10214
Protoss_Zealot 1 6171
Protoss_Nexus 1 7703
Protoss_Robotics_Facility 1 7439
Protoss_Observatory 1 8002
Protoss_Observer 2 9328
Protoss_Shuttle 1 10711
10711
