Protoss_Assimilator 2 4454
Protoss_Nexus 1 4989
Protoss_Gateway 3 8071
Protoss_Cybernetics_Core 2 7707
Protoss_Zealot 3 6632
Protoss_Dragoon 5 10074
Protoss_Robotics_Facility 1 10612
10612
