Protoss_Gateway 1 2711
Protoss_Assimilator 1 2794
Protoss_Cybernetics_Core 1 3700
Protoss_Dragoon 7 10694
Protoss_Robotics_Facility 1 6883
Protoss_Shuttle 1 7865
Protoss_Zealot 2 8332
Protoss_Robotics_Support_Bay 1 7703
Protoss_Reaver 1 9010
Protoss_Observatory 1 8600
Protoss_Nexus 2 11263
Protoss_Observer 2 10216
11263
