Protoss_Nexus 2 10510
Protoss_Gateway 3 9568
Protoss_Assimilator 2 8384
Protoss_Cybernetics_Core 1 5204
Protoss_Zealot 1 5273
Protoss_Dragoon 3 7328
Protoss_Citadel_of_Adun 1 7669
Protoss_Robotics_Facility 1 8509
Protoss_Templar_Archives 1 9029
Protoss_Shuttle 1 9762
Protoss_Dark_Templar 3 10413
Protoss_Forge 1 9910
Protoss_Observatory 1 10099
10510
