Protoss_Gateway 3 8895
Protoss_Assimilator 1 2917
Protoss_Cybernetics_Core 1 3889
Protoss_Robotics_Facility 1 5362
Protoss_Dragoon 11 10593
Protoss_Observatory 1 5976
Protoss_Observer 2 8108
Protoss_Nexus 1 9195
10593
