Protoss_Gateway 2 5753
Protoss_Assimilator 1 3027
Protoss_Zealot 3 5020
Protoss_Cybernetics_Core 1 4597
Protoss_Dragoon 5 7958
Protoss_Citadel_of_Adun 1 6510
Protoss_Templar_Archives 1 7671
Protoss_Dark_Templar 2 8772
Protoss_Nexus 1 11233
11233
