Protoss_Gateway 3 8503
Protoss_Assimilator 2 4002
Protoss_Zealot 3 5012
Protoss_Cybernetics_Core 1 5097
Protoss_Dragoon 3 7568
Protoss_Citadel_of_Adun 1 6826
Protoss_Forge 1 7616
Protoss_Templar_Archives 1 7941
Protoss_Dark_Templar 4 10171
Protoss_Photon_Cannon 1 9136
10171
