Protoss_Gateway 2 7475
Protoss_Assimilator 1 3030
Protoss_Cybernetics_Core 1 3989
Protoss_Dragoon 11 10215
Protoss_Nexus 1 7951
Protoss_Robotics_Facility 1 8564
Protoss_Observatory 1 9499
Protoss_Shuttle 1 10203
Protoss_Robotics_Support_Bay 1 10385
10385
