Protoss_Gateway 3 7760
Protoss_Assimilator 1 3036
Protoss_Cybernetics_Core 1 3993
Protoss_Dragoon 4 9076
Protoss_Citadel_of_Adun 1 7075
Protoss_Templar_Archives 1 8065
Protoss_Dark_Templar 5 10416
Protoss_Nexus 1 10045
10416
