Protoss_Gateway 2 7041
Protoss_Assimilator 3 10080
Protoss_Zealot 3 6248
Protoss_Nexus 2 9665
Protoss_Cybernetics_Core 1 6281
Protoss_Dragoon 5 10004
Protoss_Robotics_Facility 1 8149
Protoss_Shuttle 1 9345
Protoss_Robotics_Support_Bay 1 9315
Protoss_Reaver 1 10546
10546
