Protoss_Gateway 3 8740
Protoss_Assimilator 1 3065
Protoss_Cybernetics_Core 1 3958
Protoss_Dragoon 7 8934
Protoss_Robotics_Facility 1 6792
Protoss_Observatory 1 7382
Protoss_Observer 2 8675
Protoss_Zealot 3 10218
Protoss_Citadel_of_Adun 1 9733
Protoss_Shuttle 1 9807
10218
