Protoss_Gateway 2 9173
Protoss_Assimilator 1 2969
Protoss_Cybernetics_Core 1 4031
Protoss_Dragoon 8 10700
Protoss_Robotics_Facility 1 6691
Protoss_Observatory 1 7233
Protoss_Nexus 1 8875
Protoss_Observer 2 9852
Protoss_Shuttle 1 8857
Protoss_Robotics_Support_Bay 2 9212
Protoss_Reaver 1 10902
10902
