Protoss_Gateway 2 6244
Protoss_Assimilator 2 3752
Protoss_Zealot 2 4724
Protoss_Cybernetics_Core 1 4804
Protoss_Dragoon 6 8726
Protoss_Robotics_Facility 1 8259
Protoss_Robotics_Support_Bay 1 8989
Protoss_Shuttle 1 9441
Protoss_Nexus 1 11136
Protoss_Reaver 1 10688
11136
