Protoss_Gateway 2 9502
Protoss_Assimilator 2 10385
Protoss_Cybernetics_Core 1 4105
Protoss_Dragoon 9 10664
Protoss_Nexus 2 9209
Protoss_Robotics_Facility 1 9075
Protoss_Citadel_of_Adun 1 9637
Protoss_Observatory 1 10149
Protoss_Templar_Archives 1 10689
10689
