Protoss_Gateway 6 10295
Protoss_Assimilator 1 2809
Protoss_Cybernetics_Core 1 3834
Protoss_Dragoon 8 10552
Protoss_Nexus 2 10320
Protoss_Robotics_Facility 1 8238
Protoss_Observatory 1 8873
Protoss_Observer 2 10282
10552
