Protoss_Gateway 2 6803
Protoss_Zealot 2 4082
Protoss_Assimilator 1 3752
Protoss_Cybernetics_Core 1 4832
Protoss_Dragoon 9 9834
Protoss_Robotics_Facility 1 7311
Protoss_Shuttle 1 8291
Protoss_Robotics_Support_Bay 1 8748
Protoss_Reaver 1 10026
Protoss_Observatory 1 9845
10026
