Protoss_Gateway 2 5818
Protoss_Assimilator 2 9242
Protoss_Cybernetics_Core 1 3773
Protoss_Dragoon 9 10040
Protoss_Nexus 1 7563
Protoss_Robotics_Facility 1 7408
Protoss_Observatory 1 8122
Protoss_Stargate 2 10991
Protoss_Observer 1 8802
Protoss_Fleet_Beacon 1 10207
10991
