Protoss_Gateway 2 6877
Protoss_Assimilator 1 2863
Protoss_Cybernetics_Core 1 3789
Protoss_Dragoon 8 10084
Protoss_Robotics_Facility 2 6843
Protoss_Observatory 1 7422
Protoss_Nexus 1 9009
Protoss_Observer 1 8104
Protoss_Shuttle 1 9287
Protoss_Robotics_Support_Bay 1 9160
Protoss_Reaver 1 10338
10338
