Protoss_Gateway 2 10053
Protoss_Assimilator 2 3924
Protoss_Zealot 3 5084
Protoss_Cybernetics_Core 1 5116
Protoss_Citadel_of_Adun 1 6262
Protoss_Dragoon 5 10742
Protoss_Templar_Archives 1 7286
Protoss_Nexus 1 8933
Protoss_Dark_Templar 2 8876
Protoss_Forge 1 8353
Protoss_Photon_Cannon 1 9253
Protoss_Robotics_Facility 1 10627
10742
