Protoss_Gateway 1 2846
Protoss_Assimilator 2 9475
Protoss_Cybernetics_Core 1 3901
Protoss_Dragoon 5 10288
Protoss_Robotics_Facility 1 6920
Protoss_Shuttle 1 7921
Protoss_Robotics_Support_Bay 1 7518
Protoss_Zealot 2 8556
Protoss_Reaver 1 8972
Protoss_Nexus 2 11625
Protoss_Observatory 1 9695
Protoss_Observer 1 10522
11625
