Protoss_Gateway 3 10345
Protoss_Assimilator 2 3183
Protoss_Cybernetics_Core 1 3892
Protoss_Dragoon 6 10458
Protoss_Robotics_Facility 1 6845
Protoss_Observatory 1 7604
Protoss_Nexus 1 8949
Protoss_Observer 2 10378
Protoss_Shuttle 1 8677
Protoss_Robotics_Support_Bay 1 8632
Protoss_Zealot 2 9566
Protoss_Reaver 1 9774
10458
