Protoss_Nexus 2 10813
Protoss_Gateway 3 10690
Protoss_Assimilator 1 4005
Protoss_Cybernetics_Core 1 5051
Protoss_Zealot 1 5208
Protoss_Dragoon 8 10142
Protoss_Robotics_Facility 1 10534
10813
