Protoss_Gateway 1 2892
Protoss_Assimilator 1 2954
Protoss_Zealot 2 4185
Protoss_Cybernetics_Core 1 4189
Protoss_Dragoon 8 10704
Protoss_Robotics_Facility 1 6985
Protoss_Robotics_Support_Bay 1 7575
Protoss_Shuttle 1 8342
Protoss_Reaver 1 9476
Protoss_Nexus 1 11297
11297
