Protoss_Gateway 2 5603
Protoss_Assimilator 1 2850
Protoss_Cybernetics_Core 1 3904
Protoss_Dragoon 9 10610
Protoss_Citadel_of_Adun 1 6673
Protoss_Templar_Archives 1 7672
Protoss_Zealot 1 7606
Protoss_Dark_Templar 2 8986
Protoss_Nexus 1 10099
Protoss_Robotics_Facility 1 10083
10610
