Protoss_Gateway 2 9680
Protoss_Assimilator 1 2789
Protoss_Cybernetics_Core 1 3750
Protoss_Dragoon 7 10518
Protoss_Robotics_Facility 1 6469
Protoss_Shuttle 1 7447
Protoss_Robotics_Support_Bay 1 7168
Protoss_Reaver 1 8576
Protoss_Zealot 2 8764
Protoss_Observatory 1 8333
Protoss_Nexus 1 9817
Protoss_Observer 2 9806
10518
