Protoss_Gateway 1 2731
Protoss_Assimilator 1 2950
Protoss_Cybernetics_Core 1 3790
Protoss_Dragoon 5 10232
Protoss_Robotics_Facility 1 5577
Protoss_Shuttle 1 6567
Protoss_Robotics_Support_Bay 1 6792
Protoss_Nexus 2 10959
Protoss_Zealot 2 8450
Protoss_Reaver 1 8502
Protoss_Observatory 1 8273
Protoss_Observer 2 9792
10959
