Protoss_Gateway 3 6280
Protoss_Zealot 5 9430
Protoss_Nexus 1 5775
Protoss_Assimilator 1 4769
Protoss_Cybernetics_Core 1 5705
Protoss_Dragoon 8 8828
Protoss_Robotics_Facility 1 10435
10435
