Protoss_Gateway 2 4514
Protoss_Assimilator 2 10568
Protoss_Cybernetics_Core 1 3911
Protoss_Dragoon 9 10256
Protoss_Nexus 1 8260
Protoss_Robotics_Facility 1 9070
Protoss_Shuttle 1 10093
Protoss_Robotics_Support_Bay 1 10088
10568
