Protoss_Gateway 4 10847
Protoss_Zealot 1 3518
Protoss_Assimilator 1 3960
Protoss_Cybernetics_Core 1 4610
Protoss_Nexus 2 10842
Protoss_Dragoon 9 10270
Protoss_Robotics_Facility 1 7478
Protoss_Observatory 1 8158
Protoss_Observer 2 9442
10847
