Protoss_Gateway 3 8856
Protoss_Assimilator 1 2848
Protoss_Cybernetics_Core 1 3781
Protoss_Dragoon 8 10148
Protoss_Robotics_Facility 1 6532
Protoss_Observatory 1 7092
Protoss_Nexus 1 9011
Protoss_Observer 2 8486
Protoss_Shuttle 1 9387
Protoss_Robotics_Support_Bay 1 9354
Protoss_Reaver 1 10624
10624
