Protoss_Gateway 3 9839
Protoss_Assimilator 1 2952
Protoss_Cybernetics_Core 1 3785
Protoss_Dragoon 8 10262
Protoss_Citadel_of_Adun 1 6913
Protoss_Templar_Archives 1 8070
Protoss_Nexus 1 9793
Protoss_Dark_Templar 2 9154
Protoss_Robotics_Facility 1 10401
10401
