Protoss_Gateway 4 10705
Protoss_Assimilator 1 3076
Protoss_Cybernetics_Core 1 4248
Protoss_Dragoon 7 9262
Protoss_Nexus 1 7969
Protoss_Robotics_Facility 1 8460
Protoss_Observatory 1 9123
Protoss_Observer 2 10494
Protoss_Zealot 2 9950
Protoss_Shuttle 1 10893
10893
