Protoss_Assimilator 1 2485
Protoss_Gateway 2 10241
Protoss_Cybernetics_Core 1 4279
Protoss_Dragoon 6 10015
Protoss_Robotics_Facility 1 5837
Protoss_Shuttle 2 10822
Protoss_Observatory 1 7551
Protoss_Nexus 1 9661
Protoss_Observer 2 9180
Protoss_Forge 1 8733
Protoss_Photon_Cannon 1 9989
10822
