Protoss_Gateway 2 9815
Protoss_Assimilator 1 2970
Protoss_Cybernetics_Core 1 3862
Protoss_Dragoon 7 9976
Protoss_Robotics_Facility 1 6605
Protoss_Shuttle 1 7695
Protoss_Robotics_Support_Bay 1 7331
Protoss_Reaver 1 8746
Protoss_Nexus 1 10053
Protoss_Observatory 1 9123
Protoss_Observer 1 9874
Protoss_Citadel_of_Adun 1 10739
10739
