Protoss_Gateway 2 8465
Protoss_Assimilator 1 3015
Protoss_Cybernetics_Core 1 3956
Protoss_Dragoon 8 9524
Protoss_Nexus 1 7945
Protoss_Robotics_Facility 1 8479
Protoss_Shuttle 1 9517
Protoss_Robotics_Support_Bay 1 9429
Protoss_Zealot 2 10126
Protoss_Reaver 1 10618
10618
