Protoss_Gateway 2 5702
Protoss_Zealot 4 8898
Protoss_Nexus 2 10611
Protoss_Assimilator 1 4781
Protoss_Cybernetics_Core 1 5593
Protoss_Dragoon 8 9804
Protoss_Robotics_Facility 1 9435
10611
