Protoss_Gateway 5 10716
Protoss_Assimilator 1 2914
Protoss_Cybernetics_Core 1 4064
Protoss_Dragoon 9 10162
Protoss_Nexus 2 10900
Protoss_Robotics_Facility 1 8087
Protoss_Observatory 1 8754
Protoss_Observer 1 10212
10900
