Protoss_Gateway 2 8274
Protoss_Assimilator 2 9300
Protoss_Cybernetics_Core 1 3939
Protoss_Dragoon 10 10266
Protoss_Nexus 1 7889
Protoss_Robotics_Facility 1 8181
Protoss_Observatory 1 8768
Protoss_Observer 1 9600
Protoss_Shuttle 1 10739
Protoss_Robotics_Support_Bay 1 10362
10739
