Protoss_Nexus 2 10610
Protoss_Gateway 3 10843
Protoss_Assimilator 2 8006
Protoss_Cybernetics_Core 1 5139
Protoss_Zealot 1 5012
Protoss_Dragoon 10 10637
Protoss_Robotics_Facility 1 8504
Protoss_Observatory 1 9402
Protoss_Observer 1 10102
Protoss_Citadel_of_Adun 1 10689
10843
