Protoss_Gateway 4 9857
Protoss_Assimilator 1 2895
Protoss_Cybernetics_Core 1 3836
Protoss_Dragoon 7 10153
Protoss_Nexus 1 7780
Protoss_Robotics_Facility 1 8063
Protoss_Observatory 1 8626
Protoss_Zealot 2 9998
Protoss_Observer 2 10068
10153
