Protoss_Gateway 3 10331
Protoss_Assimilator 1 2880
Protoss_Cybernetics_Core 1 3767
Protoss_Dragoon 5 8264
Protoss_Robotics_Facility 1 6597
Protoss_Observatory 1 7185
Protoss_Nexus 1 8740
Protoss_Shuttle 1 8095
Protoss_Robotics_Support_Bay 1 8417
Protoss_Observer 2 10406
Protoss_Zealot 2 9756
Protoss_Reaver 1 9802
10406
