Protoss_Gateway 2 5995
Protoss_Assimilator 1 3016
Protoss_Zealot 2 4078
Protoss_Cybernetics_Core 1 4035
Protoss_Dragoon 9 10112
Protoss_Citadel_of_Adun 1 5683
Protoss_Templar_Archives 1 6685
Protoss_Dark_Templar 2 7544
Protoss_Nexus 1 11363
11363
