Protoss_Gateway 2 6965
Protoss_Assimilator 1 2920
Protoss_Cybernetics_Core 1 4040
Protoss_Dragoon 7 9798
Protoss_Robotics_Facility 1 6988
Protoss_Shuttle 1 8287
Protoss_Observatory 1 7960
Protoss_Zealot 2 8989
Protoss_Nexus 2 11751
Protoss_Observer 1 9253
11751
