Protoss_Gateway 4 9702
Protoss_Assimilator 1 2955
Protoss_Cybernetics_Core 1 3911
Protoss_Dragoon 7 10070
Protoss_Zealot 4 8590
Protoss_Nexus 1 9491
Protoss_Robotics_Facility 1 9527
Protoss_Shuttle 1 10811
Protoss_Robotics_Support_Bay 1 10445
10811
