Protoss_Assimilator 2 3318
Protoss_Gateway 6 10755
Protoss_Cybernetics_Core 1 4309
Protoss_Dragoon 5 9124
Protoss_Nexus 2 8908
Protoss_Robotics_Facility 1 9069
Protoss_Shuttle 1 10119
Protoss_Robotics_Support_Bay 1 10109
10755
