Protoss_Gateway 3 10395
Protoss_Assimilator 1 3373
Protoss_Zealot 4 9328
Protoss_Cybernetics_Core 1 4306
Protoss_Dragoon 7 10356
Protoss_Nexus 1 8081
Protoss_Robotics_Facility 1 7682
Protoss_Shuttle 1 8663
Protoss_Robotics_Support_Bay 1 8555
Protoss_Observatory 1 8837
Protoss_Reaver 1 9860
Protoss_Observer 1 10464
10464
