Protoss_Gateway 4 9958
Protoss_Assimilator 1 3020
Protoss_Cybernetics_Core 1 3869
Protoss_Dragoon 6 10384
Protoss_Citadel_of_Adun 1 6558
Protoss_Templar_Archives 1 7545
Protoss_Zealot 1 7596
Protoss_Dark_Templar 4 9450
Protoss_Nexus 1 9787
10384
