Protoss_Gateway 2 7544
Protoss_Assimilator 1 3075
Protoss_Cybernetics_Core 1 4002
Protoss_Dragoon 7 9753
Protoss_Robotics_Facility 1 7232
Protoss_Observatory 1 7941
Protoss_Shuttle 1 8522
Protoss_Zealot 2 8825
Protoss_Observer 1 9236
9753
