Protoss_Nexus 2 9495
Protoss_Gateway 4 10544
Protoss_Assimilator 1 3965
Protoss_Zealot 3 8392
Protoss_Cybernetics_Core 1 5099
Protoss_Dragoon 12 10742
Protoss_Robotics_Facility 1 9649
10742
