Protoss_Gateway 2 7677
Protoss_Assimilator 1 2889
Protoss_Cybernetics_Core 1 3841
Protoss_Dragoon 4 10296
Protoss_Citadel_of_Adun 1 5148
Protoss_Templar_Archives 1 6353
Protoss_Nexus 1 8217
Protoss_Dark_Templar 4 9058
Protoss_Zealot 1 7794
Protoss_Robotics_Facility 1 10073
10296
