Protoss_Gateway 2 3596
Protoss_Zealot 6 6720
Protoss_Assimilator 1 4416
Protoss_Cybernetics_Core 1 5147
Protoss_Dragoon 11 10206
Protoss_Forge 1 6283
Protoss_Shield_Battery 1 7745
10206
