Protoss_Gateway 2 7149
Protoss_Assimilator 1 3141
Protoss_Cybernetics_Core 1 3937
Protoss_Dragoon 4 9128
Protoss_Citadel_of_Adun 1 6191
Protoss_Robotics_Facility 1 7201
Protoss_Templar_Archives 1 7319
Protoss_Dark_Templar 4 10088
Protoss_Shuttle 1 8411
Protoss_Zealot 1 8966
Protoss_Nexus 1 11748
11748
