Protoss_Gateway 4 10069
Protoss_Assimilator 1 2838
Protoss_Cybernetics_Core 1 3797
Protoss_Dragoon 10 9990
Protoss_Nexus 1 8289
Protoss_Robotics_Facility 1 8882
Protoss_Observatory 1 9439
Protoss_Observer 1 10456
10456
