Protoss_Gateway 2 9693
Protoss_Zealot 5 6358
Protoss_Forge 1 3862
Protoss_Photon_Cannon 2 5410
Protoss_Assimilator 1 5799
Protoss_Cybernetics_Core 1 6526
Protoss_Nexus 1 8304
Protoss_Robotics_Facility 1 8214
Protoss_Dragoon 5 10602
Protoss_Robotics_Support_Bay 1 9158
Protoss_Reaver 1 10404
10602
