Protoss_Gateway 2 7224
Protoss_Assimilator 1 2807
Protoss_Cybernetics_Core 1 3855
Protoss_Dragoon 7 9706
Protoss_Robotics_Facility 1 6648
Protoss_Observatory 1 7251
Protoss_Nexus 1 9670
Protoss_Observer 1 8500
Protoss_Robotics_Support_Bay 1 8554
Protoss_Shuttle 1 9401
Protoss_Reaver 1 10452
10452
