Protoss_Gateway 4 9852
Protoss_Assimilator 1 2766
Protoss_Cybernetics_Core 1 3823
Protoss_Zealot 5 10540
Protoss_Dragoon 10 9516
Protoss_Robotics_Facility 1 6841
Protoss_Observatory 1 7395
Protoss_Observer 3 10018
Protoss_Shuttle 1 10659
10659
