Protoss_Gateway 3 10611
Protoss_Assimilator 1 3096
Protoss_Cybernetics_Core 1 4103
Protoss_Dragoon 7 9642
Protoss_Nexus 2 11238
Protoss_Zealot 3 10342
Protoss_Robotics_Facility 1 8536
Protoss_Observatory 1 9593
Protoss_Observer 1 10324
11238
