Protoss_Gateway 2 6854
Protoss_Assimilator 1 2864
Protoss_Cybernetics_Core 1 3835
Protoss_Dragoon 10 10053
Protoss_Robotics_Facility 1 6595
Protoss_Observatory 1 7385
Protoss_Observer 3 9418
Protoss_Nexus 1 9805
10053
