Protoss_Gateway 2 8751
Protoss_Assimilator 1 3244
Protoss_Cybernetics_Core 1 3987
Protoss_Dragoon 8 9596
Protoss_Nexus 2 11431
Protoss_Robotics_Facility 1 8845
Protoss_Shuttle 1 9847
Protoss_Robotics_Support_Bay 1 9561
Protoss_Reaver 1 10997
11431
