Protoss_Nexus 2 10419
Protoss_Gateway 4 10862
Protoss_Assimilator 1 4014
Protoss_Cybernetics_Core 1 5005
Protoss_Zealot 1 5188
Protoss_Dragoon 12 10616
Protoss_Robotics_Facility 1 8647
Protoss_Observatory 1 9612
10862
