Protoss_Gateway 4 8347
Protoss_Zealot 8 9088
Protoss_Assimilator 4 9493
Protoss_Forge 1 5177
Protoss_Photon_Cannon 2 8420
Protoss_Nexus 1 8245
Protoss_Cybernetics_Core 1 8917
Protoss_Dragoon 2 9866
9866
