Protoss_Gateway 3 10230
Protoss_Assimilator 1 3050
Protoss_Cybernetics_Core 1 4026
Protoss_Dragoon 8 10506
Protoss_Robotics_Facility 1 7161
Protoss_Nexus 2 9302
Protoss_Observatory 1 7733
Protoss_Observer 2 9506
10506
