Protoss_Nexus 1 4783
Protoss_Gateway 4 10609
Protoss_Assimilator 2 9587
Protoss_Cybernetics_Core 1 5433
Protoss_Zealot 6 10010
Protoss_Dragoon 8 10205
Protoss_Robotics_Facility 1 9457
Protoss_Observatory 1 10281
Protoss_Shuttle 1 10807
10807
