Protoss_Gateway 1 2753
Protoss_Assimilator 1 2846
Protoss_Cybernetics_Core 1 3771
Protoss_Dragoon 7 10718
Protoss_Nexus 2 10641
Protoss_Robotics_Facility 1 7403
Protoss_Shuttle 1 8389
Protoss_Robotics_Support_Bay 1 7993
Protoss_Reaver 2 10668
Protoss_Observatory 1 9496
10718
