Protoss_Gateway 1 2775
Protoss_Assimilator 1 2962
Protoss_Zealot 9 8938
Protoss_Forge 1 4616
Protoss_Photon_Cannon 2 5892
Protoss_Cybernetics_Core 1 7565
Protoss_Nexus 2 10537
Protoss_Robotics_Facility 1 9061
Protoss_Shuttle 1 10165
Protoss_Robotics_Support_Bay 1 10097
10537
