Protoss_Gateway 3 10351
Protoss_Zealot 4 5636
Protoss_Forge 1 3916
Protoss_Photon_Cannon 3 7233
Protoss_Assimilator 1 5830
Protoss_Cybernetics_Core 1 6665
Protoss_Dragoon 8 10692
Protoss_Citadel_of_Adun 1 10636
10692
