Protoss_Gateway 2 10210
Protoss_Assimilator 2 10486
Protoss_Cybernetics_Core 1 4004
Protoss_Dragoon 7 10633
Protoss_Nexus 2 10230
Protoss_Robotics_Facility 1 8537
Protoss_Observatory 1 9393
Protoss_Citadel_of_Adun 1 10324
Protoss_Observer 1 10143
10633
