Protoss_Gateway 4 10569
Protoss_Assimilator 4 8515
Protoss_Zealot 3 4750
Protoss_Nexus 1 6765
Protoss_Cybernetics_Core 1 6739
Protoss_Dragoon 7 10040
Protoss_Robotics_Facility 1 10353
10569
