Protoss_Nexus 3 10109
Protoss_Gateway 4 10837
Protoss_Assimilator 2 9319
Protoss_Zealot 1 4652
Protoss_Cybernetics_Core 1 5234
Protoss_Citadel_of_Adun 1 6260
Protoss_Dragoon 3 10058
Protoss_Forge 1 6651
Protoss_Templar_Archives 1 7331
Protoss_Photon_Cannon 1 8066
Protoss_Dark_Templar 1 8202
Protoss_Robotics_Facility 1 9981
10837
