Protoss_Gateway 2 4409
Protoss_Assimilator 1 3126
Protoss_Cybernetics_Core 1 3938
Protoss_Dragoon 8 10532
Protoss_Citadel_of_Adun 1 6865
Protoss_Templar_Archives 1 7851
Protoss_Zealot 2 8038
Protoss_Dark_Templar 4 9648
Protoss_Nexus 1 10276
10532
