Protoss_Gateway 2 5545
Protoss_Assimilator 1 2816
Protoss_Cybernetics_Core 1 3816
Protoss_Dragoon 8 10416
Protoss_Citadel_of_Adun 1 6807
Protoss_Zealot 2 7398
Protoss_Templar_Archives 1 7791
Protoss_Dark_Templar 2 8796
Protoss_Nexus 1 10135
10416
