Protoss_Gateway 2 3293
Protoss_Zealot 8 8310
Protoss_Assimilator 1 4845
Protoss_Cybernetics_Core 1 6159
Protoss_Dragoon 6 9870
Protoss_Robotics_Facility 1 8739
Protoss_Observatory 1 9279
Protoss_Observer 1 10322
10322
