Protoss_Gateway 2 6359
Protoss_Assimilator 1 2802
Protoss_Cybernetics_Core 1 3957
Protoss_Dragoon 5 10280
Protoss_Citadel_of_Adun 1 5091
Protoss_Robotics_Facility 1 6112
Protoss_Templar_Archives 1 6720
Protoss_Shuttle 1 7097
Protoss_Dark_Templar 2 7568
Protoss_Nexus 1 9506
10280
