Protoss_Gateway 3 8267
Protoss_Assimilator 1 3018
Protoss_Cybernetics_Core 1 3941
Protoss_Dragoon 10 10526
Protoss_Robotics_Facility 1 5631
Protoss_Shuttle 1 6639
Protoss_Zealot 2 7522
Protoss_Robotics_Support_Bay 1 6663
Protoss_Reaver 1 7794
Protoss_Observatory 1 7691
Protoss_Observer 1 8444
10526
