Protoss_Assimilator 1 2231
Protoss_Gateway 2 6672
Protoss_Cybernetics_Core 1 4091
Protoss_Dragoon 4 10192
Protoss_Citadel_of_Adun 1 5849
Protoss_Robotics_Facility 1 6246
Protoss_Templar_Archives 1 6915
Protoss_Shuttle 1 7405
Protoss_Dark_Templar 2 7768
Protoss_Nexus 1 9873
Protoss_High_Templar 2 8912
Protoss_Zealot 2 9840
10192
