Protoss_Gateway 2 10413
Protoss_Assimilator 2 3328
Protoss_Zealot 2 4018
Protoss_Cybernetics_Core 1 3981
Protoss_Dragoon 7 10214
Protoss_Robotics_Facility 1 5965
Protoss_Shuttle 1 6989
Protoss_Robotics_Support_Bay 1 7100
Protoss_Reaver 1 8250
Protoss_Observatory 1 8145
Protoss_Observer 3 10414
Protoss_Nexus 1 11087
11087
