Protoss_Gateway 2 7819
Protoss_Zealot 3 5056
Protoss_Assimilator 2 8011
Protoss_Cybernetics_Core 1 5196
Protoss_Nexus 1 7313
Protoss_Dragoon 8 10302
Protoss_Robotics_Facility 1 9100
Protoss_Robotics_Support_Bay 1 9721
Protoss_Observatory 1 9905
10302
