Protoss_Gateway 2 9427
Protoss_Assimilator 1 2917
Protoss_Cybernetics_Core 1 3833
Protoss_Dragoon 7 10266
Protoss_Nexus 1 7759
Protoss_Robotics_Facility 1 8212
Protoss_Shuttle 1 9199
Protoss_Robotics_Support_Bay 1 8808
Protoss_Zealot 2 9946
Protoss_Observatory 1 9648
Protoss_Reaver 1 10250
10266
