Protoss_Gateway 2 6736
Protoss_Assimilator 1 2931
Protoss_Cybernetics_Core 1 3902
Protoss_Dragoon 8 9240
Protoss_Robotics_Facility 1 6477
Protoss_Observatory 1 7100
Protoss_Nexus 1 8728
Protoss_Observer 1 8086
Protoss_Shuttle 1 9145
Protoss_Robotics_Support_Bay 1 8792
Protoss_Reaver 1 10214
Protoss_Zealot 2 10410
10410
