Protoss_Gateway 3 9947
Protoss_Assimilator 1 2852
Protoss_Cybernetics_Core 1 3846
Protoss_Dragoon 9 10436
Protoss_Nexus 2 11457
Protoss_Robotics_Facility 1 7207
Protoss_Observatory 1 7808
Protoss_Observer 2 10266
Protoss_Shuttle 1 9473
11457
