Protoss_Gateway 4 10383
Protoss_Nexus 1 5123
Protoss_Zealot 2 5468
Protoss_Assimilator 1 4613
Protoss_Cybernetics_Core 1 5441
Protoss_Dragoon 8 10040
Protoss_Robotics_Facility 1 10926
10926
