Protoss_Gateway 4 10281
Protoss_Assimilator 2 8620
Protoss_Cybernetics_Core 1 3762
Protoss_Dragoon 5 9740
Protoss_Citadel_of_Adun 1 6161
Protoss_Templar_Archives 1 7150
Protoss_Nexus 1 8978
Protoss_Dark_Templar 1 7990
Protoss_Stargate 1 8571
Protoss_Arbiter_Tribunal 1 9655
Protoss_Arbiter 1 12130
12130
