Protoss_Gateway 3 10748
Protoss_Zealot 2 4584
Protoss_Assimilator 1 3879
Protoss_Cybernetics_Core 1 4640
Protoss_Dragoon 5 8580
Protoss_Nexus 2 10745
Protoss_Robotics_Facility 1 9161
Protoss_Observatory 1 9856
10748
