Protoss_Gateway 3 9209
Protoss_Assimilator 1 2916
Protoss_Cybernetics_Core 1 3781
Protoss_Zealot 1 3810
Protoss_Dragoon 11 10380
Protoss_Robotics_Facility 1 6811
Protoss_Observatory 1 7353
Protoss_Observer 2 9234
Protoss_Nexus 1 9489
10380
