Protoss_Gateway 2 10567
Protoss_Assimilator 1 2995
Protoss_Cybernetics_Core 1 3867
Protoss_Dragoon 7 9976
Protoss_Robotics_Facility 1 6600
Protoss_Observatory 1 7246
Protoss_Nexus 1 8667
Protoss_Observer 1 7942
Protoss_Shuttle 1 8843
Protoss_Robotics_Support_Bay 1 8542
Protoss_Reaver 1 10032
10567
