Protoss_Gateway 2 4984
Protoss_Zealot 3 10288
Protoss_Assimilator 2 9519
Protoss_Cybernetics_Core 1 4361
Protoss_Dragoon 7 8402
Protoss_Nexus 1 7915
Protoss_Robotics_Facility 1 8496
Protoss_Shuttle 1 9605
Protoss_Robotics_Support_Bay 1 9198
Protoss_Stargate 1 10210
Protoss_Observatory 1 9722
Protoss_Reaver 1 10656
10656
