Protoss_Gateway 4 10369
Protoss_Assimilator 2 9105
Protoss_Cybernetics_Core 1 3833
Protoss_Dragoon 5 7776
Protoss_Robotics_Facility 1 6804
Protoss_Observatory 1 7455
Protoss_Nexus 2 10889
Protoss_Observer 2 9478
Protoss_Zealot 1 8506
Protoss_Citadel_of_Adun 1 9355
Protoss_Templar_Archives 1 10720
10889
