Protoss_Gateway 1 2765
Protoss_Assimilator 1 2928
Protoss_Cybernetics_Core 1 3876
Protoss_Robotics_Facility 1 5405
Protoss_Dragoon 3 9904
Protoss_Shuttle 2 10701
Protoss_Robotics_Support_Bay 1 6187
Protoss_Zealot 2 7260
Protoss_Reaver 2 9798
Protoss_Nexus 2 11097
Protoss_Observatory 1 8247
11097
