Protoss_Gateway 4 10765
Protoss_Forge 1 3764
Protoss_Zealot 3 8654
Protoss_Photon_Cannon 2 5748
Protoss_Assimilator 1 5471
Protoss_Cybernetics_Core 1 6184
Protoss_Dragoon 8 10330
Protoss_Nexus 1 10563
10765
