Protoss_Gateway 2 6929
Protoss_Assimilator 1 2973
Protoss_Cybernetics_Core 1 3914
Protoss_Dragoon 11 10714
Protoss_Robotics_Facility 1 6873
Protoss_Shuttle 1 7915
Protoss_Observatory 1 7775
Protoss_Observer 2 10272
Protoss_Robotics_Support_Bay 1 8381
Protoss_Reaver 1 9668
Protoss_Zealot 2 9684
10714
