Protoss_Gateway 2 8586
Protoss_Assimilator 1 2931
Protoss_Cybernetics_Core 1 3791
Protoss_Dragoon 10 10202
Protoss_Robotics_Facility 1 6543
Protoss_Nexus 2 10855
Protoss_Observatory 1 7744
Protoss_Observer 3 9906
10855
