Protoss_Gateway 3 10725
Protoss_Assimilator 1 3022
Protoss_Cybernetics_Core 1 3955
Protoss_Dragoon 11 10468
Protoss_Robotics_Facility 1 7277
Protoss_Observatory 1 7940
Protoss_Nexus 1 9716
Protoss_Observer 2 9278
10725
