Protoss_Gateway 2 3167
Protoss_Zealot 6 5232
Protoss_Forge 1 5000
Protoss_Photon_Cannon 3 8024
Protoss_Assimilator 2 10286
Protoss_Cybernetics_Core 1 7006
Protoss_Citadel_of_Adun 1 8399
Protoss_Nexus 1 10185
Protoss_Templar_Archives 1 9577
Protoss_Robotics_Facility 1 10749
Protoss_Dark_Templar 1 10520
10749
