Protoss_Gateway 4 9235
Protoss_Assimilator 2 10438
Protoss_Cybernetics_Core 1 3927
Protoss_Nexus 1 5963
Protoss_Dragoon 8 8750
Protoss_Zealot 7 10064
Protoss_Citadel_of_Adun 1 8281
Protoss_Robotics_Facility 1 10866
10866
