Protoss_Gateway 2 5909
Protoss_Zealot 4 9634
Protoss_Nexus 1 5980
Protoss_Assimilator 2 8352
Protoss_Cybernetics_Core 1 5589
Protoss_Dragoon 6 10504
Protoss_Robotics_Facility 1 8499
Protoss_Shuttle 1 9491
Protoss_Robotics_Support_Bay 1 9063
Protoss_Stargate 1 10041
Protoss_Reaver 1 10542
Protoss_Observatory 1 10094
10542
