Protoss_Gateway 1 2801
Protoss_Assimilator 1 2981
Protoss_Cybernetics_Core 1 3879
Protoss_Robotics_Facility 1 5383
Protoss_Dragoon 6 10372
Protoss_Shuttle 1 6363
Protoss_Robotics_Support_Bay 1 6663
Protoss_Zealot 2 8784
Protoss_Reaver 2 10800
Protoss_Observatory 1 8081
Protoss_Nexus 2 11601
11601
