Protoss_Gateway 2 7058
Protoss_Assimilator 1 2967
Protoss_Cybernetics_Core 1 3883
Protoss_Dragoon 3 9322
Protoss_Citadel_of_Adun 1 6232
Protoss_Robotics_Facility 1 7264
Protoss_Templar_Archives 1 7346
Protoss_Shuttle 1 8251
Protoss_Dark_Templar 2 8186
Protoss_Nexus 1 9895
Protoss_Stargate 1 9387
9895
