Protoss_Gateway 4 10752
Protoss_Assimilator 1 2788
Protoss_Cybernetics_Core 1 3738
Protoss_Dragoon 11 10676
Protoss_Nexus 2 11068
Protoss_Robotics_Facility 1 7718
Protoss_Observatory 1 8393
Protoss_Observer 3 10530
11068
