Protoss_Gateway 2 9415
Protoss_Assimilator 1 2928
Protoss_Cybernetics_Core 1 4044
Protoss_Dragoon 8 10638
Protoss_Robotics_Facility 1 6571
Protoss_Shuttle 1 7619
Protoss_Robotics_Support_Bay 1 7307
Protoss_Reaver 2 10426
Protoss_Nexus 1 9789
Protoss_Observatory 1 9083
10638
