Protoss_Gateway 1 2801
Protoss_Zealot 3 4696
Protoss_Assimilator 1 3695
Protoss_Cybernetics_Core 1 4882
Protoss_Robotics_Facility 1 6224
Protoss_Dragoon 6 10162
Protoss_Shuttle 1 7241
Protoss_Robotics_Support_Bay 1 7021
Protoss_Reaver 1 8292
Protoss_Observatory 1 8223
Protoss_Observer 1 9220
Protoss_Nexus 1 11595
11595
