Protoss_Gateway 2 9470
Protoss_Assimilator 1 2998
Protoss_Cybernetics_Core 1 3853
Protoss_Dragoon 7 10350
Protoss_Nexus 2 11779
Protoss_Robotics_Facility 1 8121
Protoss_Shuttle 1 9107
Protoss_Robotics_Support_Bay 1 8803
Protoss_Zealot 2 10114
Protoss_Reaver 1 10158
11779
