Protoss_Gateway 3 10541
Protoss_Assimilator 1 2934
Protoss_Cybernetics_Core 1 3914
Protoss_Dragoon 8 10704
Protoss_Nexus 1 7671
Protoss_Robotics_Facility 1 8077
Protoss_Shuttle 1 9205
Protoss_Robotics_Support_Bay 1 8938
Protoss_Observatory 1 9290
Protoss_Reaver 1 10256
Protoss_Zealot 2 9952
10704
