Protoss_Gateway 7 10133
Protoss_Assimilator 2 4724
Protoss_Zealot 6 10548
Protoss_Cybernetics_Core 1 6662
Protoss_Dragoon 2 7550
Protoss_Citadel_of_Adun 1 7751
Protoss_Templar_Archives 1 8746
Protoss_Nexus 1 9879
Protoss_Dark_Templar 2 9580
10548
