Protoss_Gateway 2 5027
Protoss_Assimilator 1 2994
Protoss_Cybernetics_Core 1 3901
Protoss_Zealot 1 3914
Protoss_Dragoon 3 5942
Protoss_Stargate 2 7757
Protoss_Fleet_Beacon 1 7184
Protoss_Carrier 2 10885
Protoss_Forge 1 8611
Protoss_Photon_Cannon 2 9875
10885
