Protoss_Gateway 2 8130
Protoss_Assimilator 1 2842
Protoss_Cybernetics_Core 1 3783
Protoss_Dragoon 10 10290
Protoss_Nexus 1 8022
Protoss_Robotics_Facility 1 7891
Protoss_Shuttle 1 8983
Protoss_Observatory 1 8659
Protoss_Observer 1 9586
Protoss_Robotics_Support_Bay 1 9650
10290
