Protoss_Assimilator 1 2304
Protoss_Gateway 3 9505
Protoss_Cybernetics_Core 1 4077
Protoss_Dragoon 6 10738
Protoss_Citadel_of_Adun 1 6415
Protoss_Robotics_Facility 1 7411
Protoss_Templar_Archives 1 7401
Protoss_Dark_Templar 4 10568
Protoss_Shuttle 1 8459
Protoss_Observatory 1 8207
Protoss_Observer 1 9576
Protoss_Zealot 2 10366
10738
