Protoss_Gateway 2 10177
Protoss_Assimilator 1 2863
Protoss_Cybernetics_Core 1 3761
Protoss_Dragoon 6 10172
Protoss_Robotics_Facility 1 6419
Protoss_Shuttle 1 7407
Protoss_Robotics_Support_Bay 1 7041
Protoss_Zealot 2 8188
Protoss_Observatory 1 7836
Protoss_Reaver 1 8474
Protoss_Nexus 1 10073
Protoss_Observer 2 9972
10177
