Protoss_Gateway 2 3455
Protoss_Zealot 8 6336
Protoss_Assimilator 1 5203
Protoss_Cybernetics_Core 1 6494
Protoss_Dragoon 7 9912
Protoss_Nexus 2 11777
Protoss_Robotics_Facility 1 10143
11777
