Protoss_Gateway 2 5635
Protoss_Assimilator 2 9947
Protoss_Cybernetics_Core 1 3931
Protoss_Dragoon 6 9012
Protoss_Nexus 2 9730
Protoss_Citadel_of_Adun 1 8195
Protoss_Templar_Archives 1 9249
Protoss_Dark_Templar 2 10096
Protoss_Stargate 1 10985
10985
