Protoss_Gateway 2 10134
Protoss_Assimilator 1 2820
Protoss_Cybernetics_Core 1 3841
Protoss_Zealot 3 8536
Protoss_Dragoon 6 10040
Protoss_Robotics_Facility 1 6654
Protoss_Shuttle 1 7683
Protoss_Robotics_Support_Bay 1 7336
Protoss_Reaver 1 8806
Protoss_Observatory 1 8450
Protoss_Observer 2 10012
10134
