Protoss_Gateway 2 10273
Protoss_Assimilator 1 2801
Protoss_Cybernetics_Core 1 3880
Protoss_Dragoon 7 10690
Protoss_Robotics_Facility 1 5597
Protoss_Observatory 1 6161
Protoss_Observer 2 7458
Protoss_Nexus 1 9257
Protoss_Shuttle 1 8801
Protoss_Robotics_Support_Bay 1 8680
Protoss_Reaver 1 9896
10690
