Protoss_Gateway 4 10090
Protoss_Zealot 4 5448
Protoss_Assimilator 1 3532
Protoss_Cybernetics_Core 1 4891
Protoss_Dragoon 7 10522
Protoss_Robotics_Facility 1 7900
Protoss_Nexus 1 9571
Protoss_Observatory 1 8928
Protoss_Observer 2 10348
10522
