Protoss_Gateway 3 10072
Protoss_Assimilator 1 3038
Protoss_Cybernetics_Core 1 3985
Protoss_Zealot 3 9656
Protoss_Dragoon 8 10600
Protoss_Robotics_Facility 1 6732
Protoss_Nexus 1 8390
Protoss_Shuttle 1 7811
Protoss_Observatory 1 7514
Protoss_Robotics_Support_Bay 1 8357
Protoss_Observer 2 10232
Protoss_Reaver 1 9628
10600
