Protoss_Gateway 2 6307
Protoss_Assimilator 1 2950
Protoss_Cybernetics_Core 1 3847
Protoss_Dragoon 9 8790
Protoss_Robotics_Facility 1 7032
Protoss_Shuttle 1 8209
Protoss_Robotics_Support_Bay 1 7819
Protoss_Reaver 1 9426
Protoss_Nexus 1 11037
Protoss_Zealot 2 10008
Protoss_Observatory 1 10145
11037
