Protoss_Gateway 4 10487
Protoss_Assimilator 1 2908
Protoss_Zealot 2 4504
Protoss_Cybernetics_Core 1 4497
Protoss_Dragoon 8 9114
Protoss_Citadel_of_Adun 1 7966
Protoss_Templar_Archives 1 9074
Protoss_Nexus 1 10536
Protoss_Dark_Templar 4 10730
10730
