Protoss_Gateway 3 10537
Protoss_Assimilator 1 2993
Protoss_Cybernetics_Core 1 3762
Protoss_Dragoon 8 10181
Protoss_Robotics_Facility 1 6576
Protoss_Observatory 1 7146
Protoss_Nexus 2 10468
Protoss_Observer 3 9666
10537
