Protoss_Gateway 1 2901
Protoss_Assimilator 1 3251
Protoss_Cybernetics_Core 1 4022
Protoss_Dragoon 6 9956
Protoss_Robotics_Facility 1 6847
Protoss_Shuttle 1 7875
Protoss_Observatory 1 7475
Protoss_Robotics_Support_Bay 1 7674
Protoss_Zealot 1 8158
Protoss_Reaver 2 10017
Protoss_Nexus 1 11745
11745
