Protoss_Gateway 2 8621
Protoss_Assimilator 1 2974
Protoss_Zealot 2 4170
Protoss_Cybernetics_Core 1 5003
Protoss_Dragoon 8 10240
Protoss_Nexus 1 8223
Protoss_Robotics_Facility 1 8305
Protoss_Observatory 1 8962
Protoss_Observer 2 10316
10316
