Protoss_Gateway 2 8342
Protoss_Assimilator 1 2772
Protoss_Cybernetics_Core 1 3752
Protoss_Zealot 3 9980
Protoss_Dragoon 5 8440
Protoss_Robotics_Facility 1 6462
Protoss_Nexus 2 11727
Protoss_Observatory 1 7131
Protoss_Observer 1 7848
Protoss_Shuttle 1 8811
Protoss_Robotics_Support_Bay 1 9020
Protoss_Reaver 1 10194
11727
