Protoss_Gateway 2 8172
Protoss_Zealot 2 4704
Protoss_Assimilator 1 3756
Protoss_Cybernetics_Core 1 4551
Protoss_Dragoon 9 10182
Protoss_Robotics_Facility 1 7672
Protoss_Observatory 1 8277
Protoss_Observer 2 9558
Protoss_Nexus 1 11459
Protoss_Shuttle 1 10867
11459
