Protoss_Gateway 3 10012
Protoss_Assimilator 2 3328
Protoss_Cybernetics_Core 1 4296
Protoss_Zealot 1 4568
Protoss_Dragoon 5 10472
Protoss_Shield_Battery 1 6250
Protoss_Citadel_of_Adun 1 7496
Protoss_Nexus 1 9159
Protoss_Templar_Archives 1 8623
Protoss_Dark_Templar 2 9486
10472
