Protoss_Nexus 1 4549
Protoss_Gateway 2 5105
Protoss_Assimilator 2 7839
Protoss_Cybernetics_Core 1 4911
Protoss_Zealot 1 5260
Protoss_Dragoon 10 9866
Protoss_Robotics_Facility 1 8412
Protoss_Observatory 1 8961
Protoss_Citadel_of_Adun 1 9417
Protoss_Observer 2 10268
Protoss_Templar_Archives 1 10403
10403
