Protoss_Gateway 2 7398
Protoss_Assimilator 1 2802
Protoss_Cybernetics_Core 1 3764
Protoss_Zealot 1 3780
Protoss_Dragoon 9 10076
Protoss_Robotics_Facility 1 6505
Protoss_Shuttle 1 7629
Protoss_Robotics_Support_Bay 1 7299
Protoss_Reaver 1 9312
Protoss_Nexus 1 10723
Protoss_Observatory 1 9573
Protoss_Observer 1 10282
10723
