Protoss_Nexus 1 4792
Protoss_Gateway 2 5366
Protoss_Assimilator 1 4170
Protoss_Cybernetics_Core 1 5215
Protoss_Zealot 2 10412
Protoss_Dragoon 9 10610
Protoss_Robotics_Facility 1 10261
10610
