Protoss_Gateway 4 10203
Protoss_Assimilator 1 2953
Protoss_Cybernetics_Core 1 3824
Protoss_Dragoon 9 10478
Protoss_Nexus 2 10739
Protoss_Robotics_Facility 1 8091
Protoss_Observatory 1 8656
Protoss_Observer 2 9996
10739
