Protoss_Gateway 1 2749
Protoss_Assimilator 1 2803
Protoss_Cybernetics_Core 1 3739
Protoss_Zealot 1 3766
Protoss_Dragoon 8 10368
Protoss_Robotics_Facility 1 6601
Protoss_Shuttle 1 7617
Protoss_Robotics_Support_Bay 1 7465
Protoss_Reaver 2 10602
Protoss_Nexus 1 11441
11441
