Protoss_Gateway 2 5406
Protoss_Assimilator 1 2865
Protoss_Cybernetics_Core 1 4011
Protoss_Dragoon 10 10030
Protoss_Nexus 1 7519
Protoss_Zealot 2 7460
Protoss_Robotics_Facility 1 9539
Protoss_Shuttle 1 10635
Protoss_Robotics_Support_Bay 1 10284
10635
