Protoss_Gateway 2 6915
Protoss_Assimilator 1 2953
Protoss_Cybernetics_Core 1 3871
Protoss_Dragoon 9 10636
Protoss_Robotics_Facility 1 6577
Protoss_Observatory 1 7146
Protoss_Observer 1 7840
Protoss_Shuttle 1 8741
Protoss_Zealot 4 9114
Protoss_Nexus 1 11145
Protoss_Citadel_of_Adun 1 10680
11145
