Protoss_Nexus 2 10233
Protoss_Gateway 3 8165
Protoss_Assimilator 1 3993
Protoss_Cybernetics_Core 1 5166
Protoss_Zealot 1 5344
Protoss_Dragoon 10 10578
Protoss_Robotics_Facility 1 7789
Protoss_Observatory 1 8462
Protoss_Observer 2 10234
10578
