Protoss_Gateway 2 4230
Protoss_Zealot 2 4950
Protoss_Assimilator 1 3981
Protoss_Cybernetics_Core 1 5213
Protoss_Dragoon 6 10106
Protoss_Nexus 2 10783
Protoss_Robotics_Facility 1 9396
Protoss_Shuttle 1 10583
Protoss_Observatory 1 10288
10783
