Protoss_Gateway 2 5660
Protoss_Assimilator 1 3051
Protoss_Cybernetics_Core 1 4029
Protoss_Dragoon 10 10064
Protoss_Nexus 1 9131
Protoss_Citadel_of_Adun 1 8526
Protoss_Templar_Archives 1 10297
Protoss_Robotics_Facility 1 10660
10660
