Protoss_Gateway 1 2739
Protoss_Assimilator 2 8672
Protoss_Cybernetics_Core 1 3885
Protoss_Dragoon 8 10105
Protoss_Nexus 1 7954
Protoss_Robotics_Facility 1 8185
Protoss_Shuttle 1 9165
Protoss_Robotics_Support_Bay 1 9141
Protoss_Reaver 1 10266
Protoss_Stargate 2 10905
Protoss_Observatory 2 10437
10905
