Protoss_Gateway 2 9426
Protoss_Assimilator 1 3546
Protoss_Cybernetics_Core 1 3908
Protoss_Dragoon 6 10460
Protoss_Nexus 2 11295
Protoss_Robotics_Facility 1 7177
Protoss_Shuttle 1 8163
Protoss_Robotics_Support_Bay 1 7967
Protoss_Zealot 2 8866
Protoss_Reaver 1 9290
Protoss_Observatory 1 9087
Protoss_Observer 2 10496
11295
