Protoss_Gateway 3 10229
Protoss_Assimilator 2 9182
Protoss_Cybernetics_Core 1 3806
Protoss_Zealot 1 3818
Protoss_Dragoon 4 7248
Protoss_Nexus 2 9331
Protoss_Citadel_of_Adun 1 7797
Protoss_Templar_Archives 1 8783
Protoss_Dark_Templar 2 10074
10229
