Protoss_Gateway 2 8248
Protoss_Assimilator 1 2935
Protoss_Cybernetics_Core 1 3891
Protoss_Dragoon 9 9828
Protoss_Nexus 1 7779
Protoss_Robotics_Facility 1 7755
Protoss_Robotics_Support_Bay 1 8415
Protoss_Shuttle 1 8995
Protoss_Reaver 1 10522
10522
