Protoss_Gateway 4 10060
Protoss_Assimilator 2 3476
Protoss_Cybernetics_Core 1 4362
Protoss_Dragoon 4 10426
Protoss_Citadel_of_Adun 1 6142
Protoss_Templar_Archives 1 7357
Protoss_Zealot 1 7068
Protoss_Dark_Templar 4 9176
Protoss_Nexus 1 9904
Protoss_Robotics_Facility 1 10723
10723
