Protoss_Gateway 2 3363
Protoss_Zealot 7 9470
Protoss_Assimilator 1 5041
Protoss_Cybernetics_Core 1 5979
Protoss_Dragoon 8 10546
Protoss_Citadel_of_Adun 1 9291
Protoss_Forge 1 9932
Protoss_Templar_Archives 1 10564
10564
