Protoss_Gateway 1 2795
Protoss_Assimilator 2 9955
Protoss_Cybernetics_Core 1 3965
Protoss_Zealot 1 3856
Protoss_Dragoon 6 10304
Protoss_Nexus 1 8067
Protoss_Robotics_Facility 1 8219
Protoss_Shuttle 1 9203
Protoss_Robotics_Support_Bay 1 8970
Protoss_Reaver 1 10254
Protoss_Stargate 1 10337
Protoss_Observatory 1 10121
10337
