Protoss_Gateway 2 9504
Protoss_Assimilator 1 2845
Protoss_Cybernetics_Core 1 3777
Protoss_Robotics_Facility 1 5200
Protoss_Dragoon 8 10496
Protoss_Observatory 1 5898
Protoss_Observer 1 6818
Protoss_Nexus 1 8971
Protoss_Shuttle 1 9245
Protoss_Robotics_Support_Bay 1 9016
Protoss_Zealot 2 10300
Protoss_Reaver 1 10296
10496
