Protoss_Gateway 2 3199
Protoss_Zealot 8 7188
Protoss_Forge 1 4659
Protoss_Photon_Cannon 3 8561
Protoss_Assimilator 1 6615
Protoss_Cybernetics_Core 1 7934
Protoss_Dragoon 1 8883
8883
