Protoss_Gateway 4 10722
Protoss_Assimilator 1 2889
Protoss_Cybernetics_Core 1 3785
Protoss_Dragoon 10 10246
Protoss_Nexus 1 8597
Protoss_Robotics_Facility 1 8776
Protoss_Observatory 1 9328
Protoss_Observer 1 10006
10722
