Protoss_Gateway 3 8141
Protoss_Zealot 6 6463
Protoss_Shield_Battery 1 4196
Protoss_Assimilator 1 5473
Protoss_Cybernetics_Core 1 6679
Protoss_Dragoon 9 10013
Protoss_Robotics_Facility 1 10908
10908
