Protoss_Gateway 3 10446
Protoss_Assimilator 1 3031
Protoss_Cybernetics_Core 1 3880
Protoss_Dragoon 2 6394
Protoss_Citadel_of_Adun 1 5167
Protoss_Templar_Archives 1 6206
Protoss_Dark_Templar 4 7946
Protoss_Nexus 1 9299
Protoss_Robotics_Facility 1 9440
Protoss_Zealot 2 9406
Protoss_Shuttle 1 10431
Protoss_Observatory 1 10095
10446
