Protoss_Nexus 2 11195
Protoss_Gateway 2 5205
Protoss_Assimilator 2 8972
Protoss_Cybernetics_Core 1 4864
Protoss_Zealot 1 5368
Protoss_Dragoon 10 10236
Protoss_Robotics_Facility 1 7904
Protoss_Observatory 1 8751
Protoss_Shuttle 1 9351
Protoss_Robotics_Support_Bay 1 9280
Protoss_Observer 1 10028
11195
