Protoss_Gateway 3 10789
Protoss_Assimilator 1 2934
Protoss_Cybernetics_Core 1 3867
Protoss_Dragoon 10 10640
Protoss_Robotics_Facility 1 6617
Protoss_Observatory 1 7440
Protoss_Observer 2 8722
Protoss_Nexus 2 10953
10953
