Protoss_Gateway 4 10518
Protoss_Assimilator 1 2802
Protoss_Cybernetics_Core 1 3776
Protoss_Zealot 1 4118
Protoss_Dragoon 4 7136
Protoss_Citadel_of_Adun 1 6243
Protoss_Templar_Archives 1 7247
Protoss_Dark_Templar 4 10020
Protoss_Nexus 1 9205
10518
