Protoss_Gateway 2 6793
Protoss_Zealot 2 5780
Protoss_Nexus 1 5865
Protoss_Assimilator 2 7700
Protoss_Cybernetics_Core 1 5726
Protoss_Dragoon 6 10026
Protoss_Robotics_Facility 1 7693
Protoss_Shuttle 1 8689
Protoss_Robotics_Support_Bay 1 8388
Protoss_Reaver 1 10152
10152
