Protoss_Gateway 2 5720
Protoss_Assimilator 3 4856
Protoss_Cybernetics_Core 1 4258
Protoss_Dragoon 7 8060
Protoss_Robotics_Facility 1 8094
Protoss_Shuttle 1 9109
Protoss_Robotics_Support_Bay 1 9166
Protoss_Zealot 2 9596
Protoss_Reaver 1 10300
Protoss_Observatory 1 10132
Protoss_Nexus 1 11637
11637
