Protoss_Gateway 5 10399
Protoss_Assimilator 1 2812
Protoss_Cybernetics_Core 1 3820
Protoss_Zealot 1 3938
Protoss_Dragoon 7 10492
Protoss_Nexus 2 9944
Protoss_Robotics_Facility 1 7935
Protoss_Observatory 1 8677
Protoss_Observer 2 10034
Protoss_Citadel_of_Adun 1 10552
10552
