Protoss_Assimilator 3 8334
Protoss_Gateway 2 7647
Protoss_Zealot 3 5226
Protoss_Nexus 2 11577
Protoss_Forge 1 5702
Protoss_Photon_Cannon 1 6542
Protoss_Cybernetics_Core 1 7008
Protoss_Dragoon 5 9910
Protoss_Robotics_Facility 1 8681
Protoss_Shuttle 1 9673
Protoss_Robotics_Support_Bay 1 9345
Protoss_Reaver 1 10830
11577
