Protoss_Gateway 2 7749
Protoss_Assimilator 1 3050
Protoss_Cybernetics_Core 1 3934
Protoss_Dragoon 9 10508
Protoss_Robotics_Facility 1 6986
Protoss_Observatory 1 7652
Protoss_Nexus 1 9775
Protoss_Observer 3 10443
10508
