Protoss_Gateway 2 6359
Protoss_Assimilator 1 2919
Protoss_Zealot 2 4576
Protoss_Cybernetics_Core 1 4563
Protoss_Dragoon 8 10132
Protoss_Nexus 2 11573
Protoss_Robotics_Facility 1 9234
Protoss_Shuttle 1 10323
Protoss_Observatory 1 10086
11573
