Protoss_Gateway 2 7472
Protoss_Assimilator 1 2930
Protoss_Cybernetics_Core 1 3921
Protoss_Dragoon 9 10304
Protoss_Robotics_Facility 1 7660
Protoss_Observatory 1 8347
Protoss_Nexus 1 9846
Protoss_Observer 2 10272
Protoss_Zealot 2 9242
10304
