Protoss_Gateway 3 9030
Protoss_Assimilator 1 3030
Protoss_Cybernetics_Core 1 4076
Protoss_Dragoon 10 10168
Protoss_Nexus 1 9090
Protoss_Robotics_Facility 1 9434
Protoss_Zealot 1 10034
Protoss_Observatory 1 10160
10168
