Protoss_Nexus 1 4467
Protoss_Gateway 3 9623
Protoss_Assimilator 1 3888
Protoss_Cybernetics_Core 1 4901
Protoss_Zealot 2 10326
Protoss_Dragoon 10 10732
Protoss_Robotics_Facility 1 9465
Protoss_Shuttle 1 10455
Protoss_Observatory 1 10086
10732
