Protoss_Gateway 1 2848
Protoss_Assimilator 1 3033
Protoss_Cybernetics_Core 1 3980
Protoss_Zealot 1 3864
Protoss_Dragoon 6 9168
Protoss_Robotics_Facility 1 6753
Protoss_Observatory 1 7294
Protoss_Nexus 1 9057
Protoss_Observer 2 8660
Protoss_Shuttle 1 9561
Protoss_Robotics_Support_Bay 1 9629
Protoss_Reaver 1 10768
10768
