Protoss_Gateway 3 9198
Protoss_Assimilator 3 7860
Protoss_Zealot 7 8326
Protoss_Nexus 1 7136
Protoss_Cybernetics_Core 1 6726
Protoss_Citadel_of_Adun 1 8249
Protoss_Dragoon 4 9672
Protoss_Templar_Archives 1 9435
Protoss_Dark_Templar 3 10424
10424
