Protoss_Gateway 2 3147
Protoss_Zealot 6 5172
Protoss_Assimilator 1 4299
Protoss_Cybernetics_Core 1 5025
Protoss_Dragoon 8 10190
Protoss_Citadel_of_Adun 1 8794
Protoss_Templar_Archives 1 9991
10190
