Protoss_Gateway 2 8191
Protoss_Assimilator 1 3082
Protoss_Zealot 2 4488
Protoss_Cybernetics_Core 1 4627
Protoss_Dragoon 4 9998
Protoss_Nexus 2 11734
Protoss_Citadel_of_Adun 1 7322
Protoss_Robotics_Facility 1 8076
Protoss_Templar_Archives 1 8407
Protoss_Shuttle 1 9079
Protoss_Dark_Templar 3 9994
Protoss_Observatory 1 9364
Protoss_Observer 1 10058
11734
