Protoss_Gateway 2 10182
Protoss_Assimilator 1 2967
Protoss_Cybernetics_Core 1 3910
Protoss_Dragoon 7 10415
Protoss_Robotics_Facility 1 5657
Protoss_Shuttle 1 6682
Protoss_Robotics_Support_Bay 1 6381
Protoss_Reaver 2 8983
Protoss_Observatory 1 8535
Protoss_Observer 1 9587
10415
