Protoss_Gateway 2 3729
Protoss_Assimilator 3 8983
Protoss_Zealot 12 10102
Protoss_Nexus 1 7146
Protoss_Forge 1 6224
Protoss_Photon_Cannon 2 7228
Protoss_Cybernetics_Core 1 8323
Protoss_Citadel_of_Adun 1 9337
Protoss_Robotics_Facility 1 10207
Protoss_Templar_Archives 1 10631
10631
