Protoss_Gateway 1 2883
Protoss_Assimilator 2 8910
Protoss_Cybernetics_Core 1 3873
Protoss_Dragoon 8 10698
Protoss_Nexus 1 8437
Protoss_Stargate 2 10106
Protoss_Fleet_Beacon 1 8905
Protoss_Carrier 1 11109
11109
