Protoss_Assimilator 2 3374
Protoss_Gateway 4 10347
Protoss_Cybernetics_Core 1 4369
Protoss_Dragoon 9 10688
Protoss_Nexus 2 9410
Protoss_Robotics_Facility 1 9493
Protoss_Observatory 1 10213
10688
