Protoss_Nexus 2 11248
Protoss_Gateway 3 8153
Protoss_Assimilator 1 3890
Protoss_Cybernetics_Core 1 4957
Protoss_Zealot 6 10522
Protoss_Dragoon 11 10662
Protoss_Robotics_Facility 1 7681
Protoss_Observatory 1 8294
Protoss_Shuttle 1 9003
Protoss_Robotics_Support_Bay 1 8871
Protoss_Observer 1 9930
11248
