Protoss_Gateway 2 4663
Protoss_Assimilator 1 3120
Protoss_Cybernetics_Core 1 4275
Protoss_Dragoon 8 10168
Protoss_Robotics_Facility 1 7077
Protoss_Observatory 1 7702
Protoss_Nexus 2 11557
Protoss_Observer 3 9988
Protoss_Zealot 1 9918
11557
