Protoss_Gateway 1 2789
Protoss_Assimilator 1 2811
Protoss_Cybernetics_Core 1 3794
Protoss_Zealot 1 3748
Protoss_Robotics_Facility 1 5283
Protoss_Dragoon 5 10634
Protoss_Shuttle 1 6265
Protoss_Robotics_Support_Bay 1 6040
Protoss_Reaver 2 8902
Protoss_Observatory 1 7145
Protoss_Nexus 1 10181
Protoss_Observer 2 10382
10634
