Protoss_Gateway 3 8895
Protoss_Assimilator 2 9957
Protoss_Cybernetics_Core 1 3761
Protoss_Dragoon 7 9830
Protoss_Citadel_of_Adun 1 5929
Protoss_Templar_Archives 1 7022
Protoss_Nexus 2 11619
Protoss_Dark_Templar 1 7910
Protoss_Robotics_Facility 1 8819
Protoss_Observatory 1 9458
Protoss_Observer 1 10158
11619
