Protoss_Gateway 4 10671
Protoss_Assimilator 1 2772
Protoss_Cybernetics_Core 1 3780
Protoss_Dragoon 9 10004
Protoss_Nexus 2 9737
Protoss_Robotics_Facility 1 8551
Protoss_Observatory 1 9131
Protoss_Observer 1 9836
10671
