Protoss_Gateway 3 8928
Protoss_Assimilator 1 3050
Protoss_Cybernetics_Core 1 3892
Protoss_Dragoon 11 10708
Protoss_Robotics_Facility 1 6611
Protoss_Nexus 1 8370
Protoss_Observatory 1 7210
Protoss_Observer 3 9210
10708
