Protoss_Nexus 1 4491
Protoss_Gateway 4 9586
Protoss_Assimilator 2 7928
Protoss_Cybernetics_Core 1 5006
Protoss_Zealot 1 5378
Protoss_Dragoon 10 9986
Protoss_Robotics_Facility 1 8759
Protoss_Shuttle 1 9737
Protoss_Robotics_Support_Bay 1 9452
Protoss_Reaver 1 10928
10928
