Protoss_Gateway 2 6224
Protoss_Assimilator 1 2880
Protoss_Cybernetics_Core 1 3834
Protoss_Dragoon 6 8417
Protoss_Robotics_Facility 1 7263
Protoss_Zealot 4 10263
Protoss_Shuttle 1 9047
Protoss_Robotics_Support_Bay 1 8901
Protoss_Observatory 1 8966
Protoss_Citadel_of_Adun 1 9700
Protoss_Reaver 1 10098
10263
