Protoss_Gateway 2 6395
Protoss_Assimilator 1 3000
Protoss_Zealot 3 4942
Protoss_Cybernetics_Core 1 4790
Protoss_Dragoon 8 10402
Protoss_Nexus 2 11094
Protoss_Robotics_Facility 1 8849
Protoss_Observatory 1 9391
Protoss_Observer 1 10068
11094
