Protoss_Gateway 2 8091
Protoss_Assimilator 2 8624
Protoss_Cybernetics_Core 1 4130
Protoss_Dragoon 7 10214
Protoss_Nexus 1 7693
Protoss_Citadel_of_Adun 1 7344
Protoss_Templar_Archives 1 8449
Protoss_Dark_Templar 4 10380
Protoss_Robotics_Facility 1 10236
10380
