Protoss_Gateway 1 2783
Protoss_Assimilator 1 2797
Protoss_Cybernetics_Core 1 3848
Protoss_Zealot 2 6886
Protoss_Robotics_Facility 1 5184
Protoss_Dragoon 5 8430
Protoss_Shuttle 1 6175
Protoss_Robotics_Support_Bay 1 6141
Protoss_Reaver 1 7274
Protoss_Observatory 1 7104
Protoss_Observer 3 9246
Protoss_Nexus 2 11063
11063
