Protoss_Assimilator 2 3322
Protoss_Gateway 4 10417
Protoss_Cybernetics_Core 1 4287
Protoss_Zealot 1 4362
Protoss_Dragoon 6 9684
Protoss_Nexus 2 9523
Protoss_Citadel_of_Adun 1 9250
Protoss_Templar_Archives 1 10262
10417
