Protoss_Nexus 3 11729
Protoss_Gateway 2 5215
Protoss_Assimilator 1 3827
Protoss_Cybernetics_Core 1 4809
Protoss_Zealot 1 5182
Protoss_Dragoon 12 10544
Protoss_Robotics_Facility 1 7994
Protoss_Observatory 1 8698
Protoss_Observer 2 10566
11729
