Protoss_Gateway 2 6891
Protoss_Zealot 4 10212
Protoss_Assimilator 1 3786
Protoss_Cybernetics_Core 1 4567
Protoss_Dragoon 5 8696
Protoss_Nexus 1 9057
Protoss_Robotics_Facility 1 8854
Protoss_Shuttle 1 9857
Protoss_Robotics_Support_Bay 1 9845
Protoss_Observatory 1 9971
Protoss_Reaver 1 11010
11010
