Protoss_Gateway 3 10700
Protoss_Assimilator 1 3122
Protoss_Cybernetics_Core 1 3974
Protoss_Dragoon 9 10363
Protoss_Robotics_Facility 1 5907
Protoss_Observatory 1 6880
Protoss_Observer 2 8318
Protoss_Nexus 1 10767
10767
