Protoss_Gateway 2 6263
Protoss_Assimilator 1 2983
Protoss_Cybernetics_Core 1 3793
Protoss_Dragoon 9 9244
Protoss_Nexus 2 11774
Protoss_Robotics_Facility 1 8310
Protoss_Shuttle 1 9333
Protoss_Robotics_Support_Bay 1 9374
Protoss_Reaver 1 10532
Protoss_Observatory 1 10093
11774
