Protoss_Gateway 2 10085
Protoss_Zealot 3 4894
Protoss_Assimilator 1 4104
Protoss_Cybernetics_Core 1 5074
Protoss_Dragoon 6 10440
Protoss_Nexus 1 8061
Protoss_Robotics_Facility 1 8105
Protoss_Shuttle 1 9117
Protoss_Robotics_Support_Bay 1 9103
Protoss_Reaver 1 10256
10440
