Protoss_Gateway 3 10857
Protoss_Assimilator 1 3057
Protoss_Zealot 2 4104
Protoss_Cybernetics_Core 1 4151
Protoss_Dragoon 8 10600
Protoss_Nexus 1 8547
Protoss_Citadel_of_Adun 1 10210
10857
