Protoss_Gateway 2 5790
Protoss_Assimilator 1 3090
Protoss_Cybernetics_Core 1 4015
Protoss_Robotics_Facility 1 5489
Protoss_Shuttle 1 6592
Protoss_Dragoon 6 8820
Protoss_Observatory 1 6893
Protoss_Observer 2 8403
Protoss_Forge 1 7835
Protoss_Photon_Cannon 1 8990
Protoss_Nexus 1 11404
11404
