Protoss_Gateway 3 9350
Protoss_Assimilator 1 2965
Protoss_Zealot 1 3564
Protoss_Cybernetics_Core 1 4549
Protoss_Dragoon 9 10662
Protoss_Robotics_Facility 1 7148
Protoss_Nexus 1 8643
Protoss_Observatory 1 8452
Protoss_Observer 2 9796
10662
