Protoss_Gateway 1 2707
Protoss_Assimilator 1 2780
Protoss_Cybernetics_Core 1 3703
Protoss_Zealot 1 3676
Protoss_Dragoon 7 10492
Protoss_Forge 1 5210
Protoss_Photon_Cannon 2 6352
Protoss_Stargate 2 8092
Protoss_Scout 4 10745
10745
