Protoss_Gateway 2 6963
Protoss_Assimilator 1 3065
Protoss_Cybernetics_Core 1 4294
Protoss_Dragoon 8 9623
Protoss_Robotics_Facility 1 6880
Protoss_Observatory 1 7816
Protoss_Observer 2 9100
Protoss_Shuttle 1 10001
Protoss_Zealot 2 10233
10233
