Protoss_Gateway 2 8497
Protoss_Assimilator 1 2926
Protoss_Cybernetics_Core 1 3845
Protoss_Dragoon 9 10412
Protoss_Nexus 2 9017
Protoss_Robotics_Facility 1 9690
Protoss_Shuttle 1 10687
Protoss_Robotics_Support_Bay 1 10249
10687
