Protoss_Gateway 2 6840
Protoss_Assimilator 1 2963
Protoss_Cybernetics_Core 1 3890
Protoss_Dragoon 11 10290
Protoss_Robotics_Facility 1 6849
Protoss_Observatory 1 7435
Protoss_Observer 2 8972
Protoss_Nexus 1 9920
Protoss_Shuttle 1 9873
Protoss_Robotics_Support_Bay 1 10157
Protoss_Zealot 1 10470
10470
