Protoss_Gateway 4 10447
Protoss_Assimilator 1 2889
Protoss_Cybernetics_Core 1 3992
Protoss_Dragoon 11 10633
Protoss_Robotics_Facility 1 6273
Protoss_Observatory 1 6977
Protoss_Observer 3 9072
Protoss_Nexus 1 10480
10633
