Protoss_Gateway 3 8914
Protoss_Assimilator 1 2974
Protoss_Cybernetics_Core 1 3913
Protoss_Dragoon 8 9038
Protoss_Robotics_Facility 1 6559
Protoss_Observatory 1 7353
Protoss_Observer 1 8222
Protoss_Citadel_of_Adun 1 8735
Protoss_Zealot 4 9852
Protoss_Shuttle 1 10603
10603
