Protoss_Gateway 2 7471
Protoss_Assimilator 2 9255
Protoss_Cybernetics_Core 1 4601
Protoss_Dragoon 3 7496
Protoss_Citadel_of_Adun 1 6381
Protoss_Templar_Archives 1 7371
Protoss_Dark_Templar 4 10442
Protoss_Nexus 1 9886
Protoss_Stargate 1 10520
10520
