Protoss_Gateway 2 9093
Protoss_Assimilator 1 3019
Protoss_Cybernetics_Core 1 4009
Protoss_Zealot 1 3916
Protoss_Dragoon 9 10686
Protoss_Robotics_Facility 1 7436
Protoss_Observatory 1 8241
Protoss_Nexus 1 9669
Protoss_Observer 2 9546
10686
