Protoss_Gateway 2 7283
Protoss_Assimilator 1 2991
Protoss_Cybernetics_Core 1 4085
Protoss_Zealot 1 4130
Protoss_Dragoon 6 8140
Protoss_Citadel_of_Adun 1 6717
Protoss_Templar_Archives 1 7803
Protoss_Dark_Templar 4 10486
Protoss_Nexus 1 10764
Protoss_Robotics_Facility 1 10457
10764
