Protoss_Gateway 2 9169
Protoss_Assimilator 1 2884
Protoss_Cybernetics_Core 1 3910
Protoss_Dragoon 8 10144
Protoss_Robotics_Facility 1 6621
Protoss_Nexus 2 10239
Protoss_Observatory 1 7241
Protoss_Observer 2 8538
Protoss_Shuttle 1 9683
Protoss_Robotics_Support_Bay 1 9603
Protoss_Reaver 1 10746
Protoss_Zealot 1 10436
10746
