Protoss_Gateway 3 10629
Protoss_Assimilator 2 9956
Protoss_Cybernetics_Core 1 3789
Protoss_Dragoon 7 9056
Protoss_Nexus 2 11023
Protoss_Robotics_Facility 1 8034
Protoss_Observatory 1 9207
Protoss_Observer 1 10038
11023
