Protoss_Gateway 3 8695
Protoss_Assimilator 1 2838
Protoss_Cybernetics_Core 1 3849
Protoss_Dragoon 11 10728
Protoss_Nexus 2 11291
Protoss_Robotics_Facility 1 8025
Protoss_Observatory 1 8819
Protoss_Observer 2 10154
11291
