Protoss_Gateway 3 8726
Protoss_Assimilator 2 10016
Protoss_Cybernetics_Core 1 3822
Protoss_Dragoon 7 8828
Protoss_Nexus 1 8583
Protoss_Robotics_Facility 1 8564
Protoss_Shuttle 1 9637
Protoss_Robotics_Support_Bay 1 9650
Protoss_Observatory 1 9680
Protoss_Observer 1 10440
10440
