Protoss_Gateway 2 7002
Protoss_Assimilator 1 3124
Protoss_Cybernetics_Core 1 3989
Protoss_Dragoon 9 10648
Protoss_Citadel_of_Adun 1 6024
Protoss_Templar_Archives 1 7149
Protoss_Zealot 1 7378
Protoss_Dark_Templar 2 8130
Protoss_Nexus 1 10410
Protoss_Robotics_Facility 1 10642
10648
