Protoss_Gateway 3 8017
Protoss_Assimilator 1 2810
Protoss_Cybernetics_Core 1 3861
Protoss_Dragoon 9 10028
Protoss_Citadel_of_Adun 1 6617
Protoss_Robotics_Facility 1 7227
Protoss_Observatory 1 7783
Protoss_Observer 3 9776
Protoss_Nexus 1 11335
11335
