Protoss_Gateway 2 6267
Protoss_Assimilator 1 2988
Protoss_Cybernetics_Core 1 3907
Protoss_Zealot 3 8779
Protoss_Dragoon 9 10524
Protoss_Robotics_Facility 1 8041
Protoss_Observatory 1 8653
Protoss_Shuttle 1 9317
Protoss_Nexus 1 11151
Protoss_Observer 1 9988
11151
