Protoss_Gateway 5 10619
Protoss_Assimilator 1 2839
Protoss_Cybernetics_Core 1 3801
Protoss_Dragoon 6 10656
Protoss_Nexus 2 9286
Protoss_Robotics_Facility 1 7647
Protoss_Shuttle 1 8909
Protoss_Zealot 1 9008
Protoss_Robotics_Support_Bay 1 9009
Protoss_Reaver 1 10246
Protoss_Observatory 1 10313
10656
