Protoss_Gateway 3 10571
Protoss_Assimilator 1 3102
Protoss_Cybernetics_Core 1 3865
Protoss_Dragoon 6 10326
Protoss_Citadel_of_Adun 1 6081
Protoss_Templar_Archives 1 7101
Protoss_Nexus 2 10278
Protoss_Dark_Templar 3 9826
10571
