Protoss_Gateway 4 9209
Protoss_Assimilator 1 2912
Protoss_Cybernetics_Core 1 3793
Protoss_Dragoon 11 9976
Protoss_Nexus 2 11615
Protoss_Robotics_Facility 1 8538
Protoss_Zealot 1 9068
Protoss_Observatory 1 9132
Protoss_Observer 2 10528
11615
