Protoss_Gateway 4 10855
Protoss_Assimilator 1 2940
Protoss_Cybernetics_Core 1 3851
Protoss_Dragoon 8 10188
Protoss_Robotics_Facility 1 6484
Protoss_Observatory 1 7098
Protoss_Observer 2 8450
Protoss_Nexus 1 9579
Protoss_Shuttle 1 9105
Protoss_Robotics_Support_Bay 1 9015
Protoss_Reaver 1 10156
Protoss_Zealot 2 10482
10855
