Protoss_Gateway 2 3405
Protoss_Zealot 5 5108
Protoss_Assimilator 1 4425
Protoss_Cybernetics_Core 1 5089
Protoss_Dragoon 12 10688
Protoss_Nexus 1 10640
Protoss_Robotics_Facility 1 10883
10883
