Protoss_Gateway 2 10373
Protoss_Assimilator 2 3296
Protoss_Cybernetics_Core 1 4165
Protoss_Dragoon 7 10126
Protoss_Robotics_Facility 1 6622
Protoss_Shuttle 1 7669
Protoss_Robotics_Support_Bay 1 7512
Protoss_Reaver 1 8720
Protoss_Observatory 1 9005
Protoss_Nexus 1 10825
10825
