Protoss_Gateway 3 10377
Protoss_Assimilator 1 2992
Protoss_Cybernetics_Core 1 3820
Protoss_Dragoon 8 10225
Protoss_Nexus 2 9265
Protoss_Robotics_Facility 1 9512
Protoss_Shuttle 1 10587
10587
