Protoss_Gateway 4 10344
Protoss_Assimilator 1 2963
Protoss_Cybernetics_Core 1 3943
Protoss_Dragoon 10 10602
Protoss_Nexus 1 7036
Protoss_Robotics_Facility 1 7879
Protoss_Observatory 1 9154
Protoss_Observer 1 10006
10602
