Protoss_Gateway 2 8614
Protoss_Assimilator 1 3055
Protoss_Cybernetics_Core 1 4031
Protoss_Zealot 1 3994
Protoss_Robotics_Facility 1 5609
Protoss_Dragoon 9 10694
Protoss_Nexus 1 8558
Protoss_Observatory 1 7425
Protoss_Observer 2 8704
Protoss_Shuttle 1 9605
Protoss_Robotics_Support_Bay 1 9158
10694
