Protoss_Gateway 2 7482
Protoss_Assimilator 2 9824
Protoss_Zealot 2 7442
Protoss_Cybernetics_Core 1 4071
Protoss_Citadel_of_Adun 2 6286
Protoss_Dragoon 4 9718
Protoss_Robotics_Facility 1 6064
Protoss_Templar_Archives 1 7285
Protoss_Nexus 1 9067
Protoss_Shuttle 1 8449
Protoss_Dark_Templar 2 8674
Protoss_Observatory 1 8496
Protoss_Observer 1 10074
10074
