Protoss_Gateway 2 8167
Protoss_Assimilator 2 9867
Protoss_Cybernetics_Core 1 3977
Protoss_Dragoon 9 10520
Protoss_Nexus 2 10931
Protoss_Robotics_Facility 1 7635
Protoss_Observatory 1 8361
Protoss_Shuttle 1 9233
Protoss_Observer 3 10282
10931
