Protoss_Gateway 1 2679
Protoss_Assimilator 1 2746
Protoss_Cybernetics_Core 1 3697
Protoss_Zealot 1 3704
Protoss_Dragoon 7 9876
Protoss_Nexus 2 9781
Protoss_Robotics_Facility 1 8129
Protoss_Shuttle 1 9259
Protoss_Robotics_Support_Bay 1 9201
Protoss_Reaver 1 10432
Protoss_Observatory 1 9983
10432
