Protoss_Gateway 2 8083
Protoss_Assimilator 2 9839
Protoss_Cybernetics_Core 1 3884
Protoss_Dragoon 11 10492
Protoss_Nexus 1 7940
Protoss_Robotics_Facility 1 8093
Protoss_Observatory 1 8655
Protoss_Observer 3 10542
10542
