Protoss_Gateway 1 2726
Protoss_Assimilator 1 2910
Protoss_Cybernetics_Core 1 3725
Protoss_Dragoon 4 9122
Protoss_Robotics_Facility 2 8823
Protoss_Shuttle 2 9137
Protoss_Robotics_Support_Bay 1 6649
Protoss_Zealot 2 8256
Protoss_Reaver 3 10630
10630
