Protoss_Gateway 3 8529
Protoss_Assimilator 2 10576
Protoss_Cybernetics_Core 1 4005
Protoss_Dragoon 10 10366
Protoss_Nexus 1 7563
Protoss_Robotics_Facility 1 7861
Protoss_Observatory 1 8672
Protoss_Observer 3 10560
10576
