Protoss_Gateway 3 9586
Protoss_Forge 1 3164
Protoss_Assimilator 1 3346
Protoss_Cybernetics_Core 1 4054
Protoss_Dragoon 13 10693
Protoss_Zealot 1 5693
Protoss_Robotics_Facility 1 8297
Protoss_Observatory 1 9026
Protoss_Observer 1 9848
Protoss_Nexus 1 11229
11229
