Protoss_Gateway 5 10515
Protoss_Assimilator 3 9110
Protoss_Zealot 7 7242
Protoss_Nexus 1 7057
Protoss_Cybernetics_Core 1 7171
Protoss_Forge 1 7678
Protoss_Photon_Cannon 2 8784
Protoss_Citadel_of_Adun 1 8843
Protoss_Templar_Archives 1 9851
Protoss_Dark_Templar 1 10744
10744
