Protoss_Gateway 2 7350
Protoss_Assimilator 2 10261
Protoss_Cybernetics_Core 1 3913
Protoss_Dragoon 6 10274
Protoss_Robotics_Facility 1 7426
Protoss_Nexus 2 10063
Protoss_Observatory 1 8228
Protoss_Observer 3 10260
Protoss_Citadel_of_Adun 1 9697
Protoss_Templar_Archives 1 10871
10871
