Protoss_Gateway 4 10154
Protoss_Assimilator 1 3085
Protoss_Cybernetics_Core 1 3829
Protoss_Dragoon 11 10573
Protoss_Zealot 2 6903
Protoss_Nexus 1 8655
Protoss_Robotics_Facility 1 8812
Protoss_Observatory 1 9625
10573
