Protoss_Assimilator 3 10434
Protoss_Gateway 2 10208
Protoss_Cybernetics_Core 1 4318
Protoss_Dragoon 6 9828
Protoss_Nexus 1 8018
Protoss_Robotics_Facility 1 7995
Protoss_Shuttle 1 9141
Protoss_Robotics_Support_Bay 1 9411
Protoss_Reaver 1 10646
Protoss_Zealot 1 10430
10646
