Protoss_Gateway 2 6857
Protoss_Assimilator 2 9290
Protoss_Cybernetics_Core 1 4069
Protoss_Dragoon 9 10598
Protoss_Robotics_Facility 1 6495
Protoss_Nexus 2 9993
Protoss_Observatory 1 7123
Protoss_Observer 5 10530
Protoss_Citadel_of_Adun 1 10122
10598
