Protoss_Gateway 3 8409
Protoss_Assimilator 2 8902
Protoss_Cybernetics_Core 1 3851
Protoss_Dragoon 6 9482
Protoss_Robotics_Facility 1 5608
Protoss_Observatory 3 6897
Protoss_Nexus 1 8514
Protoss_Observer 3 9826
Protoss_Citadel_of_Adun 1 9341
Protoss_Zealot 2 9594
Protoss_Templar_Archives 1 10516
10516
