Protoss_Gateway 2 7840
Protoss_Assimilator 3 7642
Protoss_Zealot 4 6382
Protoss_Nexus 2 10950
Protoss_Forge 1 5485
Protoss_Photon_Cannon 1 6422
Protoss_Cybernetics_Core 1 7377
Protoss_Dragoon 5 10186
Protoss_Robotics_Facility 1 9698
Protoss_Observatory 1 10383
10950
