Protoss_Gateway 2 9867
Protoss_Assimilator 1 3010
Protoss_Cybernetics_Core 1 3981
Protoss_Dragoon 4 10410
Protoss_Robotics_Facility 1 5911
Protoss_Shuttle 1 6891
Protoss_Robotics_Support_Bay 1 6519
Protoss_Zealot 2 7616
Protoss_Reaver 1 7942
Protoss_Observatory 1 7694
Protoss_Observer 2 9148
Protoss_Nexus 1 10208
10410
