Protoss_Gateway 2 6394
Protoss_Assimilator 1 3120
Protoss_Cybernetics_Core 1 3967
Protoss_Dragoon 10 10386
Protoss_Robotics_Facility 1 7566
Protoss_Zealot 2 8072
Protoss_Observatory 1 8171
Protoss_Observer 2 10078
Protoss_Nexus 1 11638
11638
