Protoss_Gateway 3 7161
Protoss_Zealot 4 9950
Protoss_Nexus 1 6265
Protoss_Assimilator 1 5292
Protoss_Cybernetics_Core 1 5957
Protoss_Dragoon 7 9996
Protoss_Robotics_Facility 1 9833
Protoss_Observatory 1 10412
10412
