Protoss_Gateway 2 8235
Protoss_Assimilator 2 9460
Protoss_Cybernetics_Core 1 3964
Protoss_Dragoon 6 10314
Protoss_Citadel_of_Adun 1 6232
Protoss_Nexus 1 8143
Protoss_Templar_Archives 1 7461
Protoss_Dark_Templar 2 9170
Protoss_Robotics_Facility 1 9398
10314
