Protoss_Gateway 6 10847
Protoss_Assimilator 1 2837
Protoss_Cybernetics_Core 1 3747
Protoss_Dragoon 5 8910
Protoss_Robotics_Facility 1 6497
Protoss_Shuttle 1 7509
Protoss_Nexus 2 10671
Protoss_Robotics_Support_Bay 1 7721
Protoss_Reaver 1 8882
Protoss_Observatory 1 8601
Protoss_Observer 2 10088
10847
