Protoss_Gateway 4 10843
Protoss_Assimilator 3 9395
Protoss_Zealot 1 3674
Protoss_Cybernetics_Core 1 4190
Protoss_Dragoon 9 10412
Protoss_Nexus 1 8263
Protoss_Robotics_Facility 1 9069
Protoss_Observatory 1 9677
10843
