Protoss_Gateway 3 10558
Protoss_Assimilator 1 2941
Protoss_Cybernetics_Core 1 3822
Protoss_Dragoon 10 10636
Protoss_Nexus 2 10449
Protoss_Zealot 1 7644
Protoss_Robotics_Facility 1 9657
Protoss_Observatory 1 10209
10636
