Protoss_Assimilator 1 2628
Protoss_Gateway 1 3329
Protoss_Cybernetics_Core 1 4382
Protoss_Robotics_Facility 1 5764
Protoss_Dragoon 6 10203
Protoss_Shuttle 3 10562
Protoss_Observatory 1 6920
Protoss_Observer 2 8313
Protoss_Robotics_Support_Bay 1 7927
Protoss_Nexus 1 11663
11663
