Protoss_Gateway 1 2756
Protoss_Assimilator 1 3112
Protoss_Zealot 5 9690
Protoss_Cybernetics_Core 1 4705
Protoss_Dragoon 5 10442
Protoss_Robotics_Facility 1 6603
Protoss_Shuttle 1 7911
Protoss_Observatory 1 8012
Protoss_Observer 1 8730
Protoss_Robotics_Support_Bay 1 8788
Protoss_Reaver 1 9930
Protoss_Nexus 1 10891
10891
