Protoss_Gateway 2 10798
Protoss_Assimilator 1 2910
Protoss_Cybernetics_Core 1 3863
Protoss_Dragoon 5 10626
Protoss_Robotics_Facility 1 6334
Protoss_Nexus 2 10565
Protoss_Shuttle 1 7373
Protoss_Robotics_Support_Bay 1 7305
Protoss_Zealot 2 8192
Protoss_Reaver 1 8430
Protoss_Stargate 1 10490
Protoss_Observatory 1 10374
10798
