Protoss_Gateway 3 7460
Protoss_Assimilator 1 2983
Protoss_Cybernetics_Core 1 3832
Protoss_Dragoon 7 9970
Protoss_Robotics_Facility 1 6743
Protoss_Observatory 1 7430
Protoss_Zealot 6 10048
Protoss_Observer 2 8735
Protoss_Shuttle 1 9847
10048
