Protoss_Nexus 2 10649
Protoss_Gateway 3 8589
Protoss_Assimilator 2 8571
Protoss_Cybernetics_Core 1 5095
Protoss_Zealot 2 8866
Protoss_Dragoon 11 10460
Protoss_Robotics_Facility 1 7665
Protoss_Observatory 1 8261
Protoss_Observer 3 10376
Protoss_Citadel_of_Adun 1 10776
10776
