Protoss_Gateway 2 10380
Protoss_Assimilator 1 3120
Protoss_Cybernetics_Core 1 4035
Protoss_Dragoon 6 10588
Protoss_Robotics_Facility 1 5836
Protoss_Shuttle 1 6907
Protoss_Observatory 1 6998
Protoss_Robotics_Support_Bay 1 7256
Protoss_Observer 2 9783
Protoss_Reaver 1 8786
Protoss_Nexus 1 10220
10588
