Protoss_Gateway 2 6811
Protoss_Assimilator 1 2781
Protoss_Cybernetics_Core 1 3707
Protoss_Dragoon 10 9246
Protoss_Robotics_Facility 1 6739
Protoss_Observatory 1 7342
Protoss_Observer 2 10158
Protoss_Nexus 2 11511
11511
