Protoss_Gateway 2 6007
Protoss_Assimilator 1 2966
Protoss_Cybernetics_Core 1 3907
Protoss_Dragoon 12 9556
Protoss_Robotics_Facility 1 7453
Protoss_Observatory 1 8015
Protoss_Observer 2 9452
Protoss_Nexus 1 11477
11477
