Protoss_Gateway 2 6992
Protoss_Assimilator 1 3022
Protoss_Cybernetics_Core 1 3950
Protoss_Dragoon 7 8856
Protoss_Robotics_Facility 1 6742
Protoss_Observatory 1 7355
Protoss_Observer 3 9856
Protoss_Nexus 2 10918
Protoss_Citadel_of_Adun 1 10572
10918
