Protoss_Gateway 3 10649
Protoss_Assimilator 1 2678
Protoss_Cybernetics_Core 1 3915
Protoss_Dragoon 9 8882
Protoss_Robotics_Facility 1 5578
Protoss_Observatory 1 6135
Protoss_Observer 2 7624
Protoss_Shuttle 1 9477
Protoss_Nexus 1 10939
Protoss_Zealot 3 10480
10939
