Protoss_Gateway 3 9688
Protoss_Assimilator 1 3083
Protoss_Cybernetics_Core 1 3883
Protoss_Dragoon 8 10664
Protoss_Nexus 1 7464
Protoss_Robotics_Facility 1 7459
Protoss_Shuttle 1 8483
Protoss_Robotics_Support_Bay 1 8333
Protoss_Zealot 2 8834
Protoss_Reaver 1 9534
Protoss_Observatory 1 9088
10664
