Protoss_Gateway 3 10799
Protoss_Assimilator 1 2883
Protoss_Cybernetics_Core 2 3792
Protoss_Dragoon 7 10376
Protoss_Robotics_Facility 1 6779
Protoss_Shuttle 1 7767
Protoss_Robotics_Support_Bay 1 7831
Protoss_Zealot 2 8872
Protoss_Reaver 1 8974
Protoss_Observatory 1 8712
Protoss_Observer 2 10180
Protoss_Nexus 1 10973
10973
