Protoss_Gateway 3 8278
Protoss_Assimilator 2 9548
Protoss_Cybernetics_Core 1 3702
Protoss_Dragoon 9 9362
Protoss_Nexus 1 7405
Protoss_Robotics_Facility 1 7709
Protoss_Observatory 1 8408
Protoss_Observer 1 9732
9732
