Protoss_Gateway 2 6967
Protoss_Assimilator 1 3163
Protoss_Cybernetics_Core 1 4007
Protoss_Dragoon 10 10422
Protoss_Robotics_Facility 1 6946
Protoss_Observatory 1 7543
Protoss_Nexus 1 9399
Protoss_Observer 1 8308
Protoss_Shuttle 1 9624
Protoss_Robotics_Support_Bay 1 10009
10422
