Protoss_Nexus 2 9233
Protoss_Gateway 4 10433
Protoss_Assimilator 1 3902
Protoss_Cybernetics_Core 1 4929
Protoss_Dragoon 13 10688
Protoss_Robotics_Facility 1 9429
Protoss_Observatory 1 10062
10688
