Protoss_Gateway 3 10385
Protoss_Assimilator 2 8896
Protoss_Cybernetics_Core 1 3983
Protoss_Dragoon 7 9532
Protoss_Nexus 1 7461
Protoss_Robotics_Facility 1 7551
Protoss_Shuttle 1 8865
Protoss_Observatory 1 8465
Protoss_Observer 1 9468
Protoss_Robotics_Support_Bay 1 9369
Protoss_Citadel_of_Adun 1 10290
Protoss_Reaver 1 10692
10692
