Protoss_Gateway 3 10781
Protoss_Assimilator 1 2948
Protoss_Cybernetics_Core 1 3771
Protoss_Dragoon 8 9730
Protoss_Nexus 2 10459
Protoss_Robotics_Facility 1 7795
Protoss_Observatory 1 8386
Protoss_Observer 3 10278
10781
