Protoss_Gateway 2 10856
Protoss_Assimilator 1 2997
Protoss_Cybernetics_Core 1 3985
Protoss_Dragoon 5 10333
Protoss_Robotics_Facility 1 5733
Protoss_Shuttle 1 6789
Protoss_Robotics_Support_Bay 1 6717
Protoss_Zealot 2 7766
Protoss_Reaver 2 10220
Protoss_Observatory 1 8077
Protoss_Observer 1 8822
10856
