Protoss_Gateway 2 7469
Protoss_Assimilator 2 3496
Protoss_Zealot 2 4708
Protoss_Cybernetics_Core 1 4823
Protoss_Dragoon 5 10322
Protoss_Citadel_of_Adun 1 7271
Protoss_Robotics_Facility 1 8213
Protoss_Templar_Archives 1 8333
Protoss_Nexus 1 9805
Protoss_Shuttle 1 9195
Protoss_Dark_Templar 2 9336
Protoss_Observatory 1 9513
Protoss_Observer 1 10464
10464
