Protoss_Gateway 2 6423
Protoss_Assimilator 1 2808
Protoss_Zealot 1 3496
Protoss_Cybernetics_Core 1 4149
Protoss_Dragoon 8 9806
Protoss_Robotics_Facility 1 8378
Protoss_Observatory 1 9083
Protoss_Nexus 1 10547
Protoss_Observer 2 10422
Protoss_Robotics_Support_Bay 1 9913
Protoss_Shuttle 1 10847
10847
