Protoss_Gateway 4 10582
Protoss_Zealot 1 3268
Protoss_Assimilator 1 3491
Protoss_Cybernetics_Core 1 4351
Protoss_Dragoon 5 7012
Protoss_Nexus 2 9833
Protoss_Robotics_Facility 1 9737
Protoss_Observatory 1 10306
Protoss_Shuttle 1 10829
10829
