Protoss_Gateway 1 2890
Protoss_Assimilator 1 3071
Protoss_Cybernetics_Core 1 4167
Protoss_Zealot 1 3898
Protoss_Dragoon 7 10340
Protoss_Robotics_Facility 1 7089
Protoss_Shuttle 1 8335
Protoss_Robotics_Support_Bay 1 7918
Protoss_Reaver 1 9540
Protoss_Nexus 1 10871
Protoss_Observatory 1 9737
Protoss_Observer 1 10440
10871
