Protoss_Gateway 2 10618
Protoss_Assimilator 1 3036
Protoss_Cybernetics_Core 1 3945
Protoss_Dragoon 8 10598
Protoss_Robotics_Facility 1 6756
Protoss_Shuttle 1 7743
Protoss_Robotics_Support_Bay 1 7814
Protoss_Reaver 1 8942
Protoss_Observatory 1 8727
Protoss_Nexus 1 10670
Protoss_Observer 1 10136
10670
