Protoss_Gateway 2 4241
Protoss_Assimilator 1 2872
Protoss_Cybernetics_Core 1 3725
Protoss_Dragoon 6 10640
Protoss_Nexus 2 11617
Protoss_Robotics_Facility 1 8177
Protoss_Shuttle 1 9175
Protoss_Robotics_Support_Bay 1 8861
Protoss_Observatory 1 9582
Protoss_Reaver 1 10226
Protoss_Zealot 2 9864
11617
