Protoss_Gateway 3 10222
Protoss_Assimilator 2 8604
Protoss_Cybernetics_Core 1 3826
Protoss_Dragoon 9 10350
Protoss_Nexus 1 8013
Protoss_Robotics_Facility 1 8103
Protoss_Citadel_of_Adun 1 8844
Protoss_Observatory 1 8836
Protoss_Observer 1 9526
Protoss_Templar_Archives 1 10059
Protoss_Shuttle 1 10733
10733
