Protoss_Gateway 2 7510
Protoss_Assimilator 1 2851
Protoss_Cybernetics_Core 1 3859
Protoss_Dragoon 11 10002
Protoss_Robotics_Facility 1 6715
Protoss_Observatory 1 7331
Protoss_Observer 2 10440
Protoss_Nexus 2 11568
Protoss_Citadel_of_Adun 1 10752
11568
