Protoss_Gateway 3 8899
Protoss_Assimilator 1 3353
Protoss_Cybernetics_Core 1 4281
Protoss_Dragoon 13 10723
Protoss_Robotics_Facility 1 6741
Protoss_Observatory 1 7381
Protoss_Observer 2 10298
10723
