Protoss_Gateway 2 6164
Protoss_Assimilator 1 2804
Protoss_Cybernetics_Core 1 3867
Protoss_Dragoon 11 10664
Protoss_Nexus 1 8709
Protoss_Robotics_Facility 1 8625
Protoss_Observatory 1 9280
Protoss_Observer 2 10586
10664
