Protoss_Nexus 2 11380
Protoss_Gateway 2 4713
Protoss_Assimilator 2 9290
Protoss_Cybernetics_Core 1 5188
Protoss_Dragoon 7 10572
Protoss_Robotics_Facility 1 9761
Protoss_Observatory 1 10400
11380
