Protoss_Nexus 1 4471
Protoss_Gateway 2 6935
Protoss_Assimilator 1 3854
Protoss_Cybernetics_Core 1 5019
Protoss_Zealot 1 5050
Protoss_Dragoon 10 10262
Protoss_Forge 1 7546
Protoss_Photon_Cannon 2 8629
Protoss_Robotics_Facility 1 9527
Protoss_Observatory 1 10148
Protoss_Shuttle 1 10725
10725
