Protoss_Gateway 2 7471
Protoss_Assimilator 2 9113
Protoss_Zealot 1 3406
Protoss_Cybernetics_Core 1 4557
Protoss_Dragoon 8 9320
Protoss_Nexus 1 7731
Protoss_Citadel_of_Adun 1 7773
Protoss_Templar_Archives 1 8823
Protoss_Dark_Templar 2 10072
Protoss_Robotics_Facility 1 10701
10701
