Protoss_Gateway 2 8215
Protoss_Assimilator 1 3304
Protoss_Zealot 1 3782
Protoss_Cybernetics_Core 1 4653
Protoss_Dragoon 8 10388
Protoss_Nexus 2 10077
Protoss_Robotics_Facility 1 10463
10463
