Protoss_Gateway 2 7155
Protoss_Assimilator 1 2989
Protoss_Cybernetics_Core 1 3847
Protoss_Zealot 2 9128
Protoss_Dragoon 8 10130
Protoss_Robotics_Facility 1 6807
Protoss_Shuttle 1 7861
Protoss_Observatory 1 7808
Protoss_Robotics_Support_Bay 1 8341
Protoss_Reaver 1 9474
Protoss_Nexus 1 10737
Protoss_Observer 1 10204
10737
