Protoss_Gateway 4 10615
Protoss_Assimilator 2 10032
Protoss_Cybernetics_Core 1 3855
Protoss_Dragoon 5 10722
Protoss_Citadel_of_Adun 1 5099
Protoss_Templar_Archives 1 6189
Protoss_Nexus 2 9432
Protoss_Dark_Templar 3 8612
Protoss_Robotics_Facility 1 10070
10722
