Protoss_Gateway 2 8699
Protoss_Assimilator 1 2931
Protoss_Cybernetics_Core 1 3865
Protoss_Dragoon 7 10470
Protoss_Citadel_of_Adun 1 6103
Protoss_Templar_Archives 1 7108
Protoss_Dark_Templar 2 8692
Protoss_Nexus 1 9211
Protoss_Stargate 1 10404
10470
