Protoss_Gateway 4 9570
Protoss_Assimilator 2 3209
Protoss_Cybernetics_Core 1 4141
Protoss_Dragoon 9 10420
Protoss_Nexus 1 9025
Protoss_Robotics_Facility 1 8787
Protoss_Observatory 1 9444
Protoss_Observer 1 10144
10420
