Protoss_Gateway 2 5674
Protoss_Assimilator 2 3438
Protoss_Cybernetics_Core 1 4389
Protoss_Dragoon 11 10394
Protoss_Nexus 1 8831
Protoss_Robotics_Facility 1 8667
Protoss_Shuttle 1 9687
Protoss_Robotics_Support_Bay 1 10046
10394
