Protoss_Assimilator 3 4036
Protoss_Gateway 2 10493
Protoss_Zealot 2 4788
Protoss_Cybernetics_Core 1 5494
Protoss_Dragoon 6 10152
Protoss_Robotics_Facility 1 7175
Protoss_Shuttle 1 8167
Protoss_Robotics_Support_Bay 1 8032
Protoss_Reaver 1 9232
Protoss_Nexus 1 10170
10493
