Protoss_Gateway 2 8334
Protoss_Assimilator 1 3235
Protoss_Cybernetics_Core 1 4276
Protoss_Dragoon 8 10688
Protoss_Robotics_Facility 1 5810
Protoss_Observatory 1 6405
Protoss_Observer 3 10398
Protoss_Shuttle 1 9047
Protoss_Zealot 2 9788
10688
