Protoss_Gateway 3 10004
Protoss_Assimilator 1 2950
Protoss_Cybernetics_Core 1 3880
Protoss_Dragoon 4 10333
Protoss_Robotics_Facility 1 6607
Protoss_Zealot 3 8953
Protoss_Robotics_Support_Bay 1 7564
Protoss_Shuttle 1 8052
Protoss_Observatory 1 7763
Protoss_Reaver 1 9103
Protoss_Nexus 1 10290
Protoss_Observer 1 9707
10333
