Protoss_Gateway 2 8088
Protoss_Assimilator 1 2820
Protoss_Cybernetics_Core 1 3896
Protoss_Zealot 1 3860
Protoss_Dragoon 9 9952
Protoss_Nexus 1 8408
Protoss_Robotics_Facility 1 8112
Protoss_Observatory 1 8724
Protoss_Observer 1 9408
Protoss_Shuttle 1 10536
Protoss_Robotics_Support_Bay 1 10302
10536
