Protoss_Nexus 2 10868
Protoss_Gateway 3 10829
Protoss_Assimilator 2 7255
Protoss_Cybernetics_Core 1 4874
Protoss_Zealot 1 5094
Protoss_Dragoon 12 10428
Protoss_Robotics_Facility 1 8601
Protoss_Observatory 1 9147
Protoss_Observer 2 10452
Protoss_Citadel_of_Adun 1 10776
10868
