Protoss_Gateway 2 6885
Protoss_Assimilator 1 3098
Protoss_Cybernetics_Core 1 3978
Protoss_Zealot 1 4400
Protoss_Dragoon 11 9990
Protoss_Robotics_Facility 1 9253
Protoss_Observatory 1 9854
Protoss_Observer 1 10552
10552
