Protoss_Gateway 3 9039
Protoss_Assimilator 1 3255
Protoss_Cybernetics_Core 1 4129
Protoss_Dragoon 8 9255
Protoss_Robotics_Facility 1 6879
Protoss_Observatory 1 7472
Protoss_Observer 2 9060
Protoss_Shuttle 1 9802
Protoss_Robotics_Support_Bay 1 9506
Protoss_Reaver 1 10853
10853
