Protoss_Gateway 2 8382
Protoss_Assimilator 2 9749
Protoss_Cybernetics_Core 1 3948
Protoss_Zealot 1 3956
Protoss_Dragoon 7 9592
Protoss_Robotics_Facility 1 6837
Protoss_Nexus 1 8770
Protoss_Observatory 1 7577
Protoss_Observer 2 8934
Protoss_Citadel_of_Adun 1 9321
Protoss_Templar_Archives 1 10434
Protoss_Stargate 1 10990
10990
