Protoss_Gateway 2 9612
Protoss_Assimilator 2 9336
Protoss_Cybernetics_Core 1 3845
Protoss_Zealot 1 3732
Protoss_Dragoon 7 10344
Protoss_Robotics_Facility 1 5690
Protoss_Observatory 1 6504
Protoss_Observer 3 10048
Protoss_Nexus 1 9179
Protoss_Citadel_of_Adun 1 8903
Protoss_Templar_Archives 1 10055
10344
