Protoss_Gateway 2 6833
Protoss_Assimilator 1 2969
Protoss_Cybernetics_Core 1 3841
Protoss_Dragoon 10 9634
Protoss_Robotics_Facility 1 6679
Protoss_Observatory 1 7475
Protoss_Observer 2 9258
Protoss_Nexus 2 11163
11163
