Protoss_Gateway 3 9316
Protoss_Assimilator 2 8668
Protoss_Cybernetics_Core 1 3697
Protoss_Dragoon 10 10734
Protoss_Nexus 1 7727
Protoss_Stargate 1 8879
Protoss_Fleet_Beacon 1 10026
Protoss_Zealot 1 10596
10734
