Protoss_Gateway 3 8221
Protoss_Zealot 4 5432
Protoss_Forge 1 3440
Protoss_Assimilator 1 4208
Protoss_Cybernetics_Core 1 5009
Protoss_Dragoon 9 10266
Protoss_Robotics_Facility 1 8825
Protoss_Observatory 1 9715
Protoss_Observer 1 10442
10442
