Protoss_Gateway 3 10599
Protoss_Assimilator 1 3110
Protoss_Cybernetics_Core 1 4166
Protoss_Dragoon 10 10340
Protoss_Robotics_Facility 1 6809
Protoss_Observatory 1 7369
Protoss_Observer 2 8738
Protoss_Nexus 1 9912
Protoss_Shuttle 1 10059
Protoss_Zealot 1 10246
10599
