Protoss_Gateway 2 6319
Protoss_Assimilator 2 3691
Protoss_Zealot 4 5782
Protoss_Cybernetics_Core 1 5134
Protoss_Dragoon 9 10488
Protoss_Citadel_of_Adun 1 8449
Protoss_Templar_Archives 1 10389
10488
