Protoss_Gateway 2 6410
Protoss_Assimilator 1 2930
Protoss_Cybernetics_Core 1 3771
Protoss_Dragoon 4 10232
Protoss_Citadel_of_Adun 1 5307
Protoss_Templar_Archives 1 6293
Protoss_Dark_Templar 5 9150
Protoss_Nexus 1 9569
Protoss_Robotics_Facility 1 11187
11187
