Protoss_Gateway 2 6432
Protoss_Assimilator 1 2878
Protoss_Cybernetics_Core 1 3907
Protoss_Dragoon 5 9630
Protoss_Citadel_of_Adun 1 6126
Protoss_Templar_Archives 1 7179
Protoss_Nexus 1 8455
Protoss_Dark_Templar 4 8778
9630
