Protoss_Gateway 2 7403
Protoss_Assimilator 1 2995
Protoss_Cybernetics_Core 1 3869
Protoss_Dragoon 7 10308
Protoss_Robotics_Facility 1 6732
Protoss_Observatory 1 7326
Protoss_Observer 1 8088
Protoss_Nexus 1 9576
Protoss_Shuttle 1 9672
Protoss_Zealot 2 9513
10308
