Protoss_Gateway 2 5757
Protoss_Assimilator 1 3098
Protoss_Cybernetics_Core 1 4063
Protoss_Dragoon 11 9882
Protoss_Robotics_Facility 1 7395
Protoss_Shuttle 1 8487
Protoss_Observatory 1 8539
Protoss_Observer 1 9242
Protoss_Robotics_Support_Bay 1 9267
Protoss_Reaver 1 10488
10488
