Protoss_Gateway 2 10124
Protoss_Assimilator 1 2970
Protoss_Zealot 1 3466
Protoss_Cybernetics_Core 1 4543
Protoss_Dragoon 6 9906
Protoss_Robotics_Facility 2 7317
Protoss_Robotics_Support_Bay 1 7060
Protoss_Shuttle 1 7861
Protoss_Reaver 2 9164
10124
