Protoss_Gateway 2 5615
Protoss_Assimilator 1 3255
Protoss_Cybernetics_Core 1 4308
Protoss_Dragoon 11 10393
Protoss_Nexus 1 8615
Protoss_Robotics_Facility 1 8852
Protoss_Observatory 1 9571
Protoss_Observer 1 10493
10493
