Protoss_Gateway 3 7096
Protoss_Assimilator 1 2950
Protoss_Cybernetics_Core 1 3880
Protoss_Dragoon 5 9322
Protoss_Robotics_Facility 1 6623
Protoss_Citadel_of_Adun 1 7117
Protoss_Zealot 9 10043
Protoss_Nexus 1 11119
11119
