Protoss_Gateway 2 7005
Protoss_Assimilator 1 2966
Protoss_Cybernetics_Core 1 4002
Protoss_Dragoon 11 10640
Protoss_Robotics_Facility 1 6635
Protoss_Observatory 1 7203
Protoss_Observer 2 8692
Protoss_Nexus 1 10461
Protoss_Zealot 1 10580
10640
