Protoss_Gateway 2 7369
Protoss_Assimilator 1 3431
Protoss_Zealot 2 4338
Protoss_Cybernetics_Core 1 4429
Protoss_Dragoon 7 9838
Protoss_Nexus 1 10605
Protoss_Robotics_Facility 1 10818
10818
