Protoss_Gateway 2 6632
Protoss_Assimilator 2 10300
Protoss_Cybernetics_Core 1 3991
Protoss_Dragoon 4 9828
Protoss_Citadel_of_Adun 1 6330
Protoss_Templar_Archives 1 7369
Protoss_Robotics_Facility 1 8496
Protoss_Dark_Templar 2 8218
Protoss_Nexus 1 10005
Protoss_Observatory 1 9152
Protoss_Stargate 1 10133
Protoss_Observer 1 9848
10300
