Protoss_Gateway 2 8886
Protoss_Assimilator 1 2987
Protoss_Cybernetics_Core 1 3896
Protoss_Zealot 1 3924
Protoss_Dragoon 9 10468
Protoss_Robotics_Facility 1 7239
Protoss_Shuttle 1 8225
Protoss_Robotics_Support_Bay 1 7914
Protoss_Reaver 1 9276
Protoss_Observatory 1 8933
Protoss_Observer 2 10524
10524
