Protoss_Gateway 2 8153
Protoss_Assimilator 1 2868
Protoss_Cybernetics_Core 1 3931
Protoss_Dragoon 10 10586
Protoss_Robotics_Facility 1 5748
Protoss_Shuttle 1 6727
Protoss_Robotics_Support_Bay 1 6681
Protoss_Reaver 1 7810
Protoss_Observatory 1 8011
Protoss_Observer 1 8690
10586
