Protoss_Gateway 2 9769
Protoss_Zealot 3 5254
Protoss_Assimilator 1 4605
Protoss_Cybernetics_Core 1 5477
Protoss_Dragoon 7 10680
Protoss_Nexus 1 9584
Protoss_Robotics_Facility 1 9466
Protoss_Shuttle 1 10607
Protoss_Robotics_Support_Bay 1 10268
10680
