Protoss_Gateway 2 9381
Protoss_Assimilator 1 2822
Protoss_Cybernetics_Core 1 3927
Protoss_Zealot 2 8042
Protoss_Robotics_Facility 1 5407
Protoss_Dragoon 4 10226
Protoss_Shuttle 1 6517
Protoss_Robotics_Support_Bay 1 6110
Protoss_Reaver 1 7616
Protoss_Observatory 1 7643
Protoss_Observer 1 8960
Protoss_Nexus 1 11649
11649
