Protoss_Assimilator 1 2650
Protoss_Gateway 4 9590
Protoss_Cybernetics_Core 1 4344
Protoss_Dragoon 9 9862
Protoss_Robotics_Facility 1 7526
Protoss_Nexus 1 9008
Protoss_Observatory 1 8572
Protoss_Observer 2 9866
Protoss_Shuttle 1 10767
10767
