Protoss_Gateway 2 8293
Protoss_Assimilator 1 2848
Protoss_Cybernetics_Core 1 3851
Protoss_Dragoon 5 7722
Protoss_Nexus 1 7745
Protoss_Citadel_of_Adun 1 7437
Protoss_Robotics_Facility 1 8712
Protoss_Templar_Archives 1 8479
Protoss_Zealot 1 8578
Protoss_Dark_Templar 4 10172
Protoss_Shuttle 1 9717
Protoss_High_Templar 2 10302
Protoss_Forge 1 10278
10302
