Protoss_Gateway 4 10646
Protoss_Assimilator 4 4795
Protoss_Cybernetics_Core 1 4063
Protoss_Zealot 1 4348
Protoss_Dragoon 8 10330
Protoss_Nexus 1 10082
Protoss_Robotics_Facility 1 10297
10646
