Protoss_Gateway 2 6355
Protoss_Assimilator 1 2899
Protoss_Cybernetics_Core 1 3881
Protoss_Dragoon 10 10538
Protoss_Robotics_Facility 1 7777
Protoss_Observatory 1 8445
Protoss_Observer 3 10362
Protoss_Nexus 2 11279
11279
