Protoss_Gateway 2 8441
Protoss_Assimilator 2 8772
Protoss_Cybernetics_Core 1 3857
Protoss_Dragoon 9 10172
Protoss_Robotics_Facility 1 6841
Protoss_Nexus 1 8737
Protoss_Observatory 1 7555
Protoss_Observer 3 9802
Protoss_Citadel_of_Adun 1 8929
Protoss_Stargate 1 10600
Protoss_Templar_Archives 1 10873
10873
