Protoss_Gateway 3 7329
Protoss_Assimilator 2 3824
Protoss_Zealot 5 10263
Protoss_Cybernetics_Core 1 5774
Protoss_Dragoon 6 9020
Protoss_Citadel_of_Adun 1 8144
Protoss_Robotics_Facility 1 10067
Protoss_Templar_Archives 1 10664
10664
