Protoss_Gateway 2 7183
Protoss_Assimilator 1 2969
Protoss_Cybernetics_Core 1 3777
Protoss_Dragoon 10 10392
Protoss_Nexus 1 7874
Protoss_Robotics_Facility 1 8311
Protoss_Shuttle 1 9415
Protoss_Robotics_Support_Bay 1 9483
Protoss_Reaver 1 10686
10686
