Protoss_Gateway 4 9969
Protoss_Assimilator 1 2996
Protoss_Cybernetics_Core 1 3838
Protoss_Dragoon 11 10406
Protoss_Zealot 1 7200
Protoss_Nexus 1 9296
Protoss_Robotics_Facility 1 8800
Protoss_Observatory 1 9349
Protoss_Observer 1 10034
10406
