Protoss_Gateway 2 4737
Protoss_Assimilator 1 3095
Protoss_Cybernetics_Core 1 4043
Protoss_Dragoon 10 10538
Protoss_Nexus 2 11358
Protoss_Robotics_Facility 1 8917
Protoss_Observatory 1 9615
Protoss_Observer 1 10328
11358
