Protoss_Gateway 3 10484
Protoss_Assimilator 1 2856
Protoss_Cybernetics_Core 1 3795
Protoss_Dragoon 9 10074
Protoss_Robotics_Facility 1 6906
Protoss_Observatory 1 7523
Protoss_Nexus 1 9223
Protoss_Observer 3 9458
10484
