Protoss_Gateway 2 5437
Protoss_Assimilator 2 10053
Protoss_Cybernetics_Core 1 3850
Protoss_Dragoon 8 9944
Protoss_Nexus 2 9681
Protoss_Citadel_of_Adun 1 8213
Protoss_Templar_Archives 1 9661
Protoss_Dark_Templar 1 10690
10690
