Protoss_Gateway 1 2729
Protoss_Assimilator 2 10378
Protoss_Cybernetics_Core 1 3727
Protoss_Robotics_Facility 2 10303
Protoss_Dragoon 3 10564
Protoss_Shuttle 2 9507
Protoss_Robotics_Support_Bay 1 5860
Protoss_Reaver 3 10964
Protoss_Nexus 1 9605
Protoss_Observatory 1 10009
10964
