Protoss_Gateway 3 9599
Protoss_Assimilator 1 2939
Protoss_Cybernetics_Core 1 3815
Protoss_Dragoon 10 10454
Protoss_Robotics_Facility 1 6539
Protoss_Observatory 1 7095
Protoss_Observer 2 8952
Protoss_Nexus 1 9507
Protoss_Shuttle 1 9853
Protoss_Zealot 3 10428
10454
