Protoss_Gateway 4 10155
Protoss_Zealot 1 3436
Protoss_Nexus 1 5651
Protoss_Assimilator 2 7411
Protoss_Cybernetics_Core 1 5498
Protoss_Dragoon 9 9818
Protoss_Robotics_Facility 1 8893
Protoss_Observatory 1 9481
Protoss_Observer 1 10158
Protoss_Citadel_of_Adun 1 10787
10787
