Protoss_Gateway 4 10165
Protoss_Assimilator 1 2863
Protoss_Cybernetics_Core 1 3771
Protoss_Dragoon 10 10430
Protoss_Robotics_Facility 1 6527
Protoss_Observatory 1 7293
Protoss_Robotics_Support_Bay 1 7337
Protoss_Observer 3 10580
Protoss_Nexus 2 10671
10671
