Protoss_Gateway 2 8178
Protoss_Assimilator 1 3059
Protoss_Cybernetics_Core 1 4087
Protoss_Dragoon 11 10726
Protoss_Robotics_Facility 1 6738
Protoss_Nexus 1 8697
Protoss_Observatory 1 7449
Protoss_Observer 3 10272
10726
