Protoss_Gateway 4 8213
Protoss_Assimilator 3 5106
Protoss_Zealot 6 6574
Protoss_Cybernetics_Core 1 5962
Protoss_Dragoon 10 10670
Protoss_Robotics_Facility 1 9614
Protoss_Shuttle 1 10601
10670
