Protoss_Gateway 4 10468
Protoss_Assimilator 1 2992
Protoss_Cybernetics_Core 1 3968
Protoss_Dragoon 5 10668
Protoss_Citadel_of_Adun 1 5276
Protoss_Templar_Archives 1 6382
Protoss_Dark_Templar 5 9330
Protoss_Nexus 1 9277
Protoss_Robotics_Facility 1 10828
10828
