Protoss_Gateway 2 7353
Protoss_Assimilator 1 2836
Protoss_Cybernetics_Core 1 3787
Protoss_Dragoon 9 10184
Protoss_Robotics_Facility 1 6423
Protoss_Observatory 1 6997
Protoss_Observer 1 7860
Protoss_Shuttle 1 8789
Protoss_Nexus 1 10343
Protoss_Robotics_Support_Bay 1 9429
Protoss_Reaver 1 10774
10774
