Protoss_Assimilator 3 9038
Protoss_Gateway 2 6681
Protoss_Cybernetics_Core 1 4270
Protoss_Dragoon 7 10470
Protoss_Robotics_Facility 1 6229
Protoss_Zealot 2 7444
Protoss_Shuttle 1 7233
Protoss_Robotics_Support_Bay 1 6879
Protoss_Reaver 1 8284
Protoss_Nexus 1 9634
Protoss_Observatory 1 9021
Protoss_Citadel_of_Adun 1 9504
10470
