Protoss_Gateway 1 2781
Protoss_Assimilator 1 2922
Protoss_Cybernetics_Core 1 3769
Protoss_Zealot 2 5864
Protoss_Dragoon 4 9748
Protoss_Robotics_Facility 1 5543
Protoss_Shuttle 2 9993
Protoss_Robotics_Support_Bay 1 6589
Protoss_Reaver 3 11044
Protoss_Observatory 1 8576
Protoss_Nexus 1 10323
11044
