Protoss_Gateway 2 6385
Protoss_Assimilator 1 3020
Protoss_Cybernetics_Core 1 4047
Protoss_Dragoon 9 10448
Protoss_Citadel_of_Adun 1 6953
Protoss_Forge 1 7000
Protoss_Templar_Archives 1 8039
Protoss_Photon_Cannon 1 8921
Protoss_Dark_Templar 2 8933
Protoss_Nexus 1 11055
11055
