Protoss_Gateway 2 5865
Protoss_Assimilator 1 2876
Protoss_Cybernetics_Core 1 3768
Protoss_Dragoon 9 10440
Protoss_Robotics_Facility 1 6733
Protoss_Shuttle 1 7915
Protoss_Robotics_Support_Bay 1 7606
Protoss_Zealot 2 8240
Protoss_Reaver 2 10408
Protoss_Nexus 1 10373
10440
