Protoss_Gateway 2 8000
Protoss_Assimilator 2 9614
Protoss_Cybernetics_Core 1 3811
Protoss_Zealot 1 3756
Protoss_Dragoon 3 9194
Protoss_Citadel_of_Adun 1 5154
Protoss_Templar_Archives 1 6220
Protoss_Dark_Templar 2 7884
Protoss_Nexus 2 11766
Protoss_Stargate 1 7908
Protoss_Arbiter_Tribunal 1 9284
Protoss_Arbiter 1 12256
12256
