Protoss_Gateway 3 9281
Protoss_Assimilator 1 2812
Protoss_Cybernetics_Core 1 3786
Protoss_Dragoon 10 10620
Protoss_Robotics_Facility 1 7010
Protoss_Nexus 1 8803
Protoss_Observatory 1 7617
Protoss_Observer 4 10098
10620
