Protoss_Gateway 2 10711
Protoss_Assimilator 2 9379
Protoss_Cybernetics_Core 1 3857
Protoss_Dragoon 6 8968
Protoss_Nexus 1 7813
Protoss_Robotics_Facility 2 8391
Protoss_Observatory 1 8652
Protoss_Robotics_Support_Bay 1 8975
Protoss_Observer 1 9372
Protoss_Shuttle 1 9795
Protoss_Reaver 2 11034
11034
