Protoss_Gateway 3 9174
Protoss_Assimilator 1 3195
Protoss_Cybernetics_Core 1 4039
Protoss_Dragoon 11 10305
Protoss_Nexus 1 9840
Protoss_Robotics_Facility 1 10477
Protoss_Zealot 1 10483
10483
