Protoss_Gateway 2 8678
Protoss_Assimilator 1 2923
Protoss_Cybernetics_Core 1 3770
Protoss_Dragoon 9 10266
Protoss_Robotics_Facility 1 5581
Protoss_Shuttle 1 6569
Protoss_Robotics_Support_Bay 1 6561
Protoss_Reaver 1 7882
Protoss_Observatory 1 8337
Protoss_Zealot 1 8620
Protoss_Observer 1 9326
10266
