Protoss_Gateway 1 2832
Protoss_Assimilator 1 3003
Protoss_Cybernetics_Core 1 3927
Protoss_Dragoon 8 10290
Protoss_Robotics_Facility 1 6617
Protoss_Observatory 1 7186
Protoss_Nexus 1 8878
Protoss_Observer 1 8252
Protoss_Shuttle 1 9153
Protoss_Robotics_Support_Bay 1 9017
Protoss_Reaver 1 10204
Protoss_Citadel_of_Adun 1 10411
10411
