Protoss_Gateway 2 5331
Protoss_Assimilator 1 2978
Protoss_Cybernetics_Core 1 3911
Protoss_Dragoon 12 10164
Protoss_Nexus 1 8463
Protoss_Robotics_Facility 1 9081
Protoss_Observatory 1 9791
Protoss_Observer 1 10590
10590
