Protoss_Gateway 3 10318
Protoss_Assimilator 1 2786
Protoss_Cybernetics_Core 1 3729
Protoss_Dragoon 4 6212
Protoss_Citadel_of_Adun 1 6180
Protoss_Zealot 1 6832
Protoss_Templar_Archives 1 7251
Protoss_Dark_Templar 5 10293
Protoss_Nexus 1 9856
Protoss_Robotics_Facility 1 11071
11071
