Protoss_Gateway 2 6841
Protoss_Assimilator 1 2825
Protoss_Cybernetics_Core 1 3799
Protoss_Dragoon 10 9746
Protoss_Robotics_Facility 1 6606
Protoss_Observatory 1 7211
Protoss_Observer 1 7934
Protoss_Nexus 1 9477
Protoss_Shuttle 1 9833
Protoss_Robotics_Support_Bay 1 9724
Protoss_Reaver 1 10884
10884
