Protoss_Gateway 3 9980
Protoss_Assimilator 1 2951
Protoss_Cybernetics_Core 1 3879
Protoss_Dragoon 11 10428
Protoss_Robotics_Facility 1 5526
Protoss_Observatory 1 6163
Protoss_Observer 4 10404
Protoss_Nexus 1 8733
Protoss_Citadel_of_Adun 1 10335
10428
