Protoss_Gateway 3 9758
Protoss_Assimilator 1 2944
Protoss_Cybernetics_Core 1 3741
Protoss_Dragoon 10 10158
Protoss_Robotics_Facility 1 6419
Protoss_Observatory 1 7005
Protoss_Observer 3 9306
Protoss_Nexus 1 8975
10158
