Protoss_Gateway 2 6591
Protoss_Zealot 3 4810
Protoss_Assimilator 1 3638
Protoss_Cybernetics_Core 1 4856
Protoss_Dragoon 10 10464
Protoss_Robotics_Facility 1 8394
Protoss_Observatory 1 9053
Protoss_Nexus 1 10956
Protoss_Observer 2 10546
10956
