Protoss_Gateway 1 2782
Protoss_Assimilator 1 2937
Protoss_Cybernetics_Core 1 3874
Protoss_Robotics_Facility 2 10799
Protoss_Dragoon 3 10292
Protoss_Shuttle 1 6381
Protoss_Robotics_Support_Bay 1 6397
Protoss_Zealot 2 7420
Protoss_Reaver 3 10230
Protoss_Nexus 1 9633
Protoss_Observatory 1 8697
10799
