Protoss_Nexus 2 7717
Protoss_Gateway 5 10619
Protoss_Assimilator 2 7429
Protoss_Cybernetics_Core 1 5132
Protoss_Dragoon 7 10152
Protoss_Citadel_of_Adun 1 7557
Protoss_Templar_Archives 1 8549
Protoss_Stargate 1 9527
Protoss_Dark_Templar 2 9390
Protoss_Forge 1 9948
10619
