Protoss_Nexus 1 4409
Protoss_Gateway 2 5111
Protoss_Assimilator 2 6884
Protoss_Cybernetics_Core 1 4930
Protoss_Dragoon 10 9374
Protoss_Citadel_of_Adun 1 7730
Protoss_Templar_Archives 1 9330
Protoss_Stargate 1 10115
10115
