Protoss_Gateway 2 8273
Protoss_Assimilator 2 10450
Protoss_Cybernetics_Core 1 4035
Protoss_Zealot 1 3936
Protoss_Dragoon 8 10306
Protoss_Nexus 1 8112
Protoss_Robotics_Facility 1 8008
Protoss_Shuttle 1 9469
Protoss_Observatory 1 9167
Protoss_Robotics_Support_Bay 1 9705
Protoss_Observer 1 10072
10450
