Protoss_Gateway 3 8811
Protoss_Assimilator 2 5872
Protoss_Zealot 4 6684
Protoss_Nexus 1 6046
Protoss_Cybernetics_Core 1 6724
Protoss_Shield_Battery 1 7276
Protoss_Dragoon 6 10554
Protoss_Robotics_Facility 1 10057
10554
