Protoss_Gateway 2 10620
Protoss_Assimilator 1 3083
Protoss_Cybernetics_Core 1 4087
Protoss_Dragoon 7 10088
Protoss_Robotics_Facility 1 6856
Protoss_Shuttle 1 7992
Protoss_Robotics_Support_Bay 1 7612
Protoss_Observatory 2 8662
Protoss_Reaver 1 9061
Protoss_Nexus 1 11060
Protoss_Observer 2 10590
11060
