Protoss_Gateway 2 9644
Protoss_Assimilator 1 2788
Protoss_Cybernetics_Core 1 3713
Protoss_Robotics_Facility 1 5269
Protoss_Dragoon 8 10530
Protoss_Shuttle 1 6255
Protoss_Robotics_Support_Bay 1 6188
Protoss_Reaver 2 9918
Protoss_Observatory 1 9324
Protoss_Observer 1 10522
10530
