Protoss_Nexus 1 4561
Protoss_Gateway 3 8955
Protoss_Assimilator 2 6575
Protoss_Cybernetics_Core 1 5097
Protoss_Zealot 1 5238
Protoss_Dragoon 14 10684
Protoss_Robotics_Facility 1 8480
Protoss_Observatory 1 9036
Protoss_Observer 2 10436
10684
