Protoss_Gateway 2 5329
Protoss_Assimilator 1 2927
Protoss_Cybernetics_Core 1 3807
Protoss_Dragoon 12 10742
Protoss_Robotics_Facility 1 6546
Protoss_Observatory 1 7306
Protoss_Nexus 1 8921
Protoss_Observer 2 8670
10742
