Protoss_Gateway 2 6625
Protoss_Assimilator 1 2925
Protoss_Cybernetics_Core 1 3824
Protoss_Dragoon 10 10554
Protoss_Robotics_Facility 1 6681
Protoss_Observatory 1 7409
Protoss_Nexus 1 8861
Protoss_Observer 2 8906
Protoss_Robotics_Support_Bay 1 9148
Protoss_Shuttle 1 9933
10554
