Protoss_Gateway 4 10454
Protoss_Assimilator 1 2955
Protoss_Cybernetics_Core 1 3770
Protoss_Dragoon 6 9108
Protoss_Nexus 2 9861
Protoss_Robotics_Facility 1 8505
Protoss_Observatory 1 9229
Protoss_Observer 1 9936
10454
