Protoss_Gateway 3 10631
Protoss_Assimilator 2 3256
Protoss_Zealot 2 8366
Protoss_Cybernetics_Core 1 4472
Protoss_Dragoon 5 10268
Protoss_Robotics_Facility 1 7280
Protoss_Shuttle 1 8293
Protoss_Robotics_Support_Bay 1 8165
Protoss_Reaver 1 9354
Protoss_Nexus 1 10831
Protoss_Observatory 1 9795
Protoss_Observer 1 10502
10831
