Protoss_Gateway 2 9901
Protoss_Assimilator 1 2932
Protoss_Cybernetics_Core 1 3771
Protoss_Zealot 1 3802
Protoss_Dragoon 6 9992
Protoss_Robotics_Facility 1 6917
Protoss_Shuttle 1 7907
Protoss_Nexus 1 9175
Protoss_Robotics_Support_Bay 1 8096
Protoss_Reaver 1 9222
Protoss_Observatory 1 10103
10103
