Protoss_Gateway 2 6024
Protoss_Assimilator 2 10504
Protoss_Cybernetics_Core 1 3783
Protoss_Dragoon 8 9994
Protoss_Nexus 2 11314
Protoss_Robotics_Facility 1 8709
Protoss_Citadel_of_Adun 1 9037
Protoss_Templar_Archives 1 10086
11314
