Protoss_Gateway 3 10206
Protoss_Assimilator 1 2934
Protoss_Cybernetics_Core 1 3856
Protoss_Dragoon 6 9764
Protoss_Robotics_Facility 1 5521
Protoss_Shuttle 1 6771
Protoss_Zealot 2 8192
Protoss_Observatory 1 7117
Protoss_Observer 2 10066
Protoss_Robotics_Support_Bay 1 7770
Protoss_Reaver 1 9038
Protoss_Nexus 1 10381
10381
