Protoss_Gateway 2 10409
Protoss_Assimilator 2 3985
Protoss_Zealot 1 3560
Protoss_Cybernetics_Core 1 5000
Protoss_Dragoon 6 9966
Protoss_Robotics_Facility 1 7795
Protoss_Shuttle 1 8813
Protoss_Robotics_Support_Bay 1 8389
Protoss_Reaver 2 11024
11024
