Protoss_Gateway 2 6638
Protoss_Assimilator 2 10488
Protoss_Cybernetics_Core 1 3887
Protoss_Dragoon 8 8816
Protoss_Robotics_Facility 1 6677
Protoss_Observatory 1 7375
Protoss_Observer 2 8714
Protoss_Nexus 2 11195
Protoss_Citadel_of_Adun 1 9621
Protoss_Templar_Archives 1 10662
11195
