Protoss_Gateway 3 10181
Protoss_Assimilator 1 2823
Protoss_Cybernetics_Core 1 3840
Protoss_Dragoon 10 9962
Protoss_Nexus 1 9239
Protoss_Robotics_Facility 1 9582
Protoss_Observatory 1 10159
10181
