Protoss_Gateway 2 6491
Protoss_Assimilator 1 3043
Protoss_Cybernetics_Core 1 3987
Protoss_Dragoon 7 10678
Protoss_Citadel_of_Adun 1 6296
Protoss_Templar_Archives 1 7279
Protoss_Zealot 2 7240
Protoss_Dark_Templar 4 8934
Protoss_Nexus 1 10369
10678
