Protoss_Gateway 3 9825
Protoss_Assimilator 1 3043
Protoss_Zealot 1 3513
Protoss_Cybernetics_Core 1 3934
Protoss_Dragoon 11 10683
Protoss_Robotics_Facility 1 6848
Protoss_Observatory 1 7401
Protoss_Observer 4 9894
Protoss_Nexus 1 9815
Protoss_Shuttle 1 10602
10683
