Protoss_Gateway 2 6771
Protoss_Assimilator 1 2947
Protoss_Cybernetics_Core 1 3807
Protoss_Dragoon 12 10482
Protoss_Robotics_Facility 1 6479
Protoss_Shuttle 1 7481
Protoss_Robotics_Support_Bay 1 7323
Protoss_Reaver 1 8624
10482
