Protoss_Gateway 3 10568
Protoss_Assimilator 2 10291
Protoss_Cybernetics_Core 1 4001
Protoss_Dragoon 11 10698
Protoss_Nexus 2 10942
Protoss_Robotics_Facility 1 7477
Protoss_Observatory 1 8245
Protoss_Observer 3 10369
10942
