Protoss_Gateway 2 6879
Protoss_Assimilator 1 2989
Protoss_Cybernetics_Core 1 3873
Protoss_Dragoon 10 9546
Protoss_Robotics_Facility 1 6583
Protoss_Observatory 1 7410
Protoss_Observer 2 8978
Protoss_Nexus 2 11313
Protoss_Citadel_of_Adun 1 10877
11313
