Protoss_Gateway 4 9526
Protoss_Assimilator 1 2838
Protoss_Cybernetics_Core 1 3829
Protoss_Dragoon 12 10700
Protoss_Nexus 2 8861
Protoss_Robotics_Facility 1 9100
Protoss_Observatory 1 10048
10700
