Protoss_Gateway 3 10715
Protoss_Assimilator 1 3068
Protoss_Cybernetics_Core 1 3870
Protoss_Dragoon 8 10742
Protoss_Robotics_Facility 1 5736
Protoss_Zealot 1 6176
Protoss_Shuttle 1 6777
Protoss_Observatory 1 7259
Protoss_Robotics_Support_Bay 1 7683
Protoss_Observer 2 10362
Protoss_Reaver 1 9202
Protoss_Nexus 1 10889
10889
