Protoss_Gateway 2 5287
Protoss_Assimilator 1 2923
Protoss_Cybernetics_Core 1 3747
Protoss_Dragoon 12 10538
Protoss_Nexus 1 8517
Protoss_Robotics_Facility 1 8766
Protoss_Observatory 1 9366
Protoss_Observer 1 10044
10538
