Protoss_Gateway 3 8395
Protoss_Assimilator 2 9988
Protoss_Cybernetics_Core 1 3801
Protoss_Dragoon 9 9530
Protoss_Nexus 1 8188
Protoss_Robotics_Facility 1 7905
Protoss_Citadel_of_Adun 1 8678
Protoss_Observatory 1 8700
Protoss_Observer 1 9448
Protoss_Templar_Archives 1 10193
10193
