Protoss_Gateway 3 8484
Protoss_Assimilator 1 3004
Protoss_Cybernetics_Core 1 3841
Protoss_Dragoon 11 9742
Protoss_Robotics_Facility 1 6601
Protoss_Observatory 1 7233
Protoss_Observer 1 8088
Protoss_Robotics_Support_Bay 1 9846
Protoss_Zealot 1 10206
Protoss_Shuttle 1 10525
10525
