Protoss_Nexus 2 10399
Protoss_Gateway 2 5145
Protoss_Assimilator 1 3860
Protoss_Cybernetics_Core 1 4905
Protoss_Zealot 3 10342
Protoss_Dragoon 6 8246
Protoss_Robotics_Facility 1 7884
Protoss_Shuttle 1 8959
Protoss_Robotics_Support_Bay 1 9265
Protoss_Reaver 1 10390
10399
