Protoss_Gateway 4 10703
Protoss_Assimilator 1 2808
Protoss_Cybernetics_Core 1 3795
Protoss_Dragoon 11 9854
Protoss_Nexus 1 8799
Protoss_Robotics_Facility 1 9339
Protoss_Observatory 1 9925
10703
