Protoss_Nexus 1 4515
Protoss_Gateway 4 10777
Protoss_Assimilator 2 8802
Protoss_Cybernetics_Core 1 4979
Protoss_Zealot 1 5292
Protoss_Dragoon 12 10524
Protoss_Robotics_Facility 1 8475
Protoss_Observatory 1 9049
Protoss_Observer 1 9730
10777
