Protoss_Nexus 1 4633
Protoss_Gateway 3 7290
Protoss_Assimilator 2 9466
Protoss_Cybernetics_Core 1 4963
Protoss_Zealot 2 10062
Protoss_Dragoon 12 10530
Protoss_Robotics_Facility 1 9858
Protoss_Observatory 1 10443
10530
