Protoss_Gateway 3 8960
Protoss_Assimilator 1 2792
Protoss_Cybernetics_Core 1 3873
Protoss_Dragoon 10 10546
Protoss_Nexus 1 8207
Protoss_Robotics_Facility 1 9135
Protoss_Zealot 2 9638
Protoss_Observatory 1 10249
10546
