Protoss_Gateway 2 5159
Protoss_Zealot 2 3966
Protoss_Assimilator 2 9110
Protoss_Cybernetics_Core 1 4727
Protoss_Dragoon 5 7322
Protoss_Nexus 1 9099
Protoss_Citadel_of_Adun 1 8519
Protoss_Robotics_Facility 1 9221
Protoss_Templar_Archives 1 9581
Protoss_Shuttle 1 10431
Protoss_Dark_Templar 2 10448
Protoss_Observatory 1 10347
10448
