Protoss_Gateway 2 6445
Protoss_Assimilator 1 2792
Protoss_Cybernetics_Core 1 3861
Protoss_Dragoon 11 10664
Protoss_Robotics_Facility 1 7802
Protoss_Nexus 1 9231
Protoss_Observatory 1 8800
Protoss_Observer 1 9494
Protoss_Shuttle 1 10395
10664
