Protoss_Gateway 2 5624
Protoss_Assimilator 1 3180
Protoss_Zealot 1 3768
Protoss_Cybernetics_Core 1 4394
Protoss_Dragoon 9 10623
Protoss_Nexus 1 10847
Protoss_Stargate 1 10450
Protoss_Robotics_Facility 1 10918
10918
