Protoss_Gateway 2 6164
Protoss_Assimilator 1 2956
Protoss_Cybernetics_Core 1 3879
Protoss_Dragoon 9 9606
Protoss_Nexus 2 9157
Protoss_Robotics_Facility 1 9288
Protoss_Shuttle 1 10291
Protoss_Zealot 2 10234
Protoss_Observatory 1 10110
10291
