Protoss_Gateway 2 7765
Protoss_Assimilator 3 10102
Protoss_Cybernetics_Core 1 4330
Protoss_Dragoon 10 10598
Protoss_Nexus 2 11479
Protoss_Robotics_Facility 1 7797
Protoss_Observatory 1 8521
Protoss_Observer 3 10550
11479
