Protoss_Gateway 2 9751
Protoss_Assimilator 1 2910
Protoss_Zealot 2 7616
Protoss_Cybernetics_Core 1 4484
Protoss_Dragoon 7 10666
Protoss_Robotics_Facility 1 6852
Protoss_Shuttle 1 7851
Protoss_Robotics_Support_Bay 1 7559
Protoss_Reaver 1 8902
Protoss_Nexus 1 10159
Protoss_Observatory 1 9201
Protoss_Observer 1 10216
10666
