Protoss_Gateway 2 5155
Protoss_Assimilator 2 8579
Protoss_Zealot 13 10268
Protoss_Forge 1 7561
Protoss_Nexus 1 9294
Protoss_Photon_Cannon 2 10632
Protoss_Cybernetics_Core 1 9413
Protoss_Robotics_Facility 1 10959
10959
