Protoss_Gateway 3 9117
Protoss_Assimilator 1 2877
Protoss_Cybernetics_Core 1 3808
Protoss_Dragoon 9 10282
Protoss_Robotics_Facility 1 6473
Protoss_Observatory 1 7053
Protoss_Nexus 1 8791
Protoss_Observer 2 8342
Protoss_Shuttle 1 9465
Protoss_Robotics_Support_Bay 1 9738
Protoss_Reaver 1 11042
11042
