Protoss_Gateway 2 5925
Protoss_Assimilator 1 2836
Protoss_Cybernetics_Core 1 3902
Protoss_Dragoon 9 9796
Protoss_Robotics_Facility 1 6713
Protoss_Shuttle 1 7695
Protoss_Robotics_Support_Bay 1 7460
Protoss_Reaver 1 8746
Protoss_Observatory 1 8563
9796
