Protoss_Gateway 2 8585
Protoss_Assimilator 1 3351
Protoss_Cybernetics_Core 1 4544
Protoss_Zealot 1 4496
Protoss_Dragoon 9 10512
Protoss_Nexus 2 11749
Protoss_Robotics_Facility 1 8399
Protoss_Observatory 1 8935
Protoss_Observer 2 10456
11749
