Protoss_Assimilator 5 4592
Protoss_Gateway 2 6173
Protoss_Cybernetics_Core 1 4465
Protoss_Robotics_Facility 1 5907
Protoss_Dragoon 6 10054
Protoss_Zealot 2 7742
Protoss_Shuttle 1 6923
Protoss_Robotics_Support_Bay 1 6961
Protoss_Reaver 1 8122
Protoss_Citadel_of_Adun 1 8655
Protoss_Templar_Archives 1 10001
10054
