Protoss_Gateway 3 10632
Protoss_Zealot 4 7952
Protoss_Assimilator 1 3720
Protoss_Cybernetics_Core 1 5016
Protoss_Dragoon 10 10174
Protoss_Nexus 1 9875
Protoss_Robotics_Facility 1 9952
10632
