Protoss_Gateway 4 10771
Protoss_Assimilator 1 2828
Protoss_Cybernetics_Core 1 3773
Protoss_Zealot 2 8140
Protoss_Dragoon 3 9047
Protoss_Robotics_Facility 1 6529
Protoss_Nexus 2 11005
Protoss_Shuttle 1 7655
Protoss_Robotics_Support_Bay 1 7675
Protoss_Reaver 1 8832
Protoss_Observatory 1 8504
Protoss_Observer 2 10447
11005
