Protoss_Gateway 2 9109
Protoss_Assimilator 1 3019
Protoss_Cybernetics_Core 1 3846
Protoss_Dragoon 7 10742
Protoss_Robotics_Facility 1 6507
Protoss_Shuttle 1 7571
Protoss_Observatory 1 7308
Protoss_Robotics_Support_Bay 1 7407
Protoss_Zealot 2 8352
Protoss_Reaver 1 8791
Protoss_Observer 1 9537
Protoss_Nexus 1 11365
11365
