Protoss_Gateway 4 10715
Protoss_Assimilator 1 2964
Protoss_Cybernetics_Core 1 3902
Protoss_Dragoon 8 10074
Protoss_Robotics_Facility 1 6503
Protoss_Observatory 1 7307
Protoss_Observer 1 8024
Protoss_Zealot 4 9036
Protoss_Shuttle 1 8945
Protoss_Nexus 1 10343
Protoss_Robotics_Support_Bay 1 9935
10715
