Protoss_Gateway 1 2777
Protoss_Assimilator 1 2900
Protoss_Cybernetics_Core 1 3855
Protoss_Dragoon 7 10030
Protoss_Robotics_Facility 1 7225
Protoss_Shuttle 1 8277
Protoss_Robotics_Support_Bay 1 7843
Protoss_Reaver 2 10380
Protoss_Nexus 2 11785
11785
