Protoss_Gateway 2 9492
Protoss_Assimilator 1 2772
Protoss_Zealot 1 3432
Protoss_Cybernetics_Core 1 4013
Protoss_Dragoon 9 10350
Protoss_Nexus 2 9760
Protoss_Robotics_Facility 1 9277
Protoss_Shuttle 1 10275
Protoss_Robotics_Support_Bay 1 9895
10350
