Protoss_Gateway 3 10883
Protoss_Assimilator 2 4472
Protoss_Zealot 2 4870
Protoss_Cybernetics_Core 1 5671
Protoss_Dragoon 7 9966
Protoss_Nexus 1 9461
Protoss_Robotics_Facility 1 9689
Protoss_Observatory 1 10254
10883
