Protoss_Gateway 2 7393
Protoss_Assimilator 2 10243
Protoss_Cybernetics_Core 1 3753
Protoss_Dragoon 8 10058
Protoss_Citadel_of_Adun 1 6331
Protoss_Templar_Archives 1 7335
Protoss_Dark_Templar 2 8234
Protoss_Nexus 2 11737
Protoss_Stargate 1 10067
11737
