Protoss_Gateway 3 10402
Protoss_Assimilator 1 2845
Protoss_Cybernetics_Core 1 3917
Protoss_Dragoon 8 10074
Protoss_Robotics_Facility 1 7405
Protoss_Shuttle 1 8451
Protoss_Robotics_Support_Bay 1 8524
Protoss_Nexus 1 9985
Protoss_Reaver 2 10968
10968
