Protoss_Nexus 1 4550
Protoss_Gateway 4 9269
Protoss_Assimilator 2 8417
Protoss_Cybernetics_Core 1 5141
Protoss_Zealot 5 9962
Protoss_Dragoon 9 10698
Protoss_Robotics_Facility 1 8289
Protoss_Observatory 1 8955
Protoss_Shuttle 1 9565
Protoss_Observer 1 10168
10698
