Protoss_Assimilator 2 3381
Protoss_Gateway 2 4643
Protoss_Zealot 2 4924
Protoss_Cybernetics_Core 1 5098
Protoss_Dragoon 7 8350
Protoss_Citadel_of_Adun 1 8235
Protoss_Templar_Archives 1 9275
Protoss_Nexus 1 10507
Protoss_Dark_Templar 2 10148
Protoss_Robotics_Facility 1 11095
11095
