Protoss_Gateway 3 9341
Protoss_Assimilator 1 2968
Protoss_Cybernetics_Core 1 3829
Protoss_Zealot 3 7242
Protoss_Robotics_Facility 1 5321
Protoss_Dragoon 4 9930
Protoss_Shuttle 1 6301
Protoss_Robotics_Support_Bay 1 6026
Protoss_Reaver 2 10196
Protoss_Observatory 1 7639
Protoss_Nexus 1 9411
Protoss_Observer 2 9146
10196
