Protoss_Gateway 4 10054
Protoss_Assimilator 1 2957
Protoss_Cybernetics_Core 1 3887
Protoss_Dragoon 8 10622
Protoss_Nexus 2 9777
Protoss_Robotics_Facility 1 7919
Protoss_Observatory 1 8509
Protoss_Observer 3 10488
Protoss_Shuttle 1 10863
10863
