Protoss_Gateway 3 9559
Protoss_Assimilator 1 3038
Protoss_Cybernetics_Core 1 4039
Protoss_Dragoon 12 10276
Protoss_Nexus 1 8036
Protoss_Robotics_Facility 1 9046
Protoss_Shuttle 1 10391
Protoss_Observatory 1 10160
Protoss_Robotics_Support_Bay 1 10439
10439
