Protoss_Gateway 2 8689
Protoss_Forge 1 3267
Protoss_Zealot 3 5757
Protoss_Assimilator 1 5636
Protoss_Photon_Cannon 3 10475
Protoss_Cybernetics_Core 1 6472
Protoss_Dragoon 2 10153
Protoss_Citadel_of_Adun 1 8139
Protoss_Robotics_Facility 1 8802
Protoss_Templar_Archives 1 9488
Protoss_Shuttle 1 9807
10475
