Protoss_Gateway 2 6983
Protoss_Assimilator 2 10164
Protoss_Cybernetics_Core 1 3856
Protoss_Dragoon 10 10514
Protoss_Robotics_Facility 1 7025
Protoss_Observatory 1 7609
Protoss_Nexus 2 10379
Protoss_Observer 2 10294
10514
