Protoss_Gateway 2 5561
Protoss_Zealot 5 9252
Protoss_Assimilator 1 3789
Protoss_Cybernetics_Core 1 4799
Protoss_Dragoon 8 10170
Protoss_Robotics_Facility 1 8220
Protoss_Shuttle 1 9445
Protoss_Robotics_Support_Bay 1 9371
10170
