Protoss_Gateway 2 6562
Protoss_Assimilator 1 3110
Protoss_Cybernetics_Core 1 4021
Protoss_Dragoon 5 9930
Protoss_Citadel_of_Adun 1 6066
Protoss_Templar_Archives 1 7055
Protoss_Zealot 2 7368
Protoss_Dark_Templar 4 8894
Protoss_Nexus 1 11463
11463
