Protoss_Gateway 2 7227
Protoss_Assimilator 1 2772
Protoss_Cybernetics_Core 1 3711
Protoss_Dragoon 5 9932
Protoss_Citadel_of_Adun 2 5992
Protoss_Robotics_Facility 1 7197
Protoss_Templar_Archives 1 7151
Protoss_Zealot 1 7106
Protoss_Dark_Templar 3 8958
Protoss_Shuttle 1 8333
Protoss_Observatory 1 8222
Protoss_Nexus 1 10413
10413
