Protoss_Nexus 1 4631
Protoss_Gateway 3 9026
Protoss_Assimilator 2 8500
Protoss_Cybernetics_Core 1 5307
Protoss_Zealot 2 9710
Protoss_Dragoon 9 9424
Protoss_Robotics_Facility 1 8547
Protoss_Shuttle 1 9703
Protoss_Robotics_Support_Bay 1 9581
9710
