Protoss_Gateway 2 8059
Protoss_Assimilator 1 2849
Protoss_Cybernetics_Core 1 3895
Protoss_Dragoon 9 9986
Protoss_Nexus 1 7991
Protoss_Robotics_Facility 1 8610
Protoss_Observatory 1 9317
Protoss_Observer 1 9996
9996
