Protoss_Gateway 3 9836
Protoss_Zealot 1 3438
Protoss_Nexus 1 5056
Protoss_Assimilator 2 6220
Protoss_Cybernetics_Core 1 5207
Protoss_Dragoon 12 10670
Protoss_Robotics_Facility 1 7923
Protoss_Observatory 1 8595
Protoss_Observer 2 9876
10670
