Protoss_Gateway 1 2913
Protoss_Assimilator 1 3212
Protoss_Zealot 3 4952
Protoss_Cybernetics_Core 1 4413
Protoss_Dragoon 6 10540
Protoss_Robotics_Facility 1 6980
Protoss_Robotics_Support_Bay 1 7550
Protoss_Reaver 2 10020
10540
