Protoss_Gateway 2 5991
Protoss_Assimilator 1 2950
Protoss_Cybernetics_Core 1 3941
Protoss_Dragoon 5 9250
Protoss_Citadel_of_Adun 1 6242
Protoss_Templar_Archives 1 7356
Protoss_Dark_Templar 4 10406
Protoss_Nexus 1 9941
10406
