Protoss_Gateway 2 6089
Protoss_Zealot 1 3430
Protoss_Nexus 1 5624
Protoss_Assimilator 2 6554
Protoss_Cybernetics_Core 1 5847
Protoss_Dragoon 6 10582
Protoss_Citadel_of_Adun 1 7615
Protoss_Robotics_Facility 1 8889
Protoss_Templar_Archives 1 8693
Protoss_Dark_Templar 2 9526
Protoss_Stargate 1 9886
Protoss_Shuttle 1 9869
Protoss_Observatory 1 10257
10582
