Protoss_Gateway 2 8992
Protoss_Assimilator 2 8289
Protoss_Cybernetics_Core 1 3865
Protoss_Dragoon 9 10306
Protoss_Robotics_Facility 1 6955
Protoss_Nexus 1 8629
Protoss_Observatory 1 7620
Protoss_Citadel_of_Adun 1 9066
Protoss_Observer 3 10550
Protoss_Stargate 1 10230
Protoss_Templar_Archives 1 10255
10550
