Protoss_Gateway 2 6691
Protoss_Assimilator 1 2821
Protoss_Cybernetics_Core 1 3734
Protoss_Dragoon 6 8116
Protoss_Robotics_Facility 1 6822
Protoss_Observatory 1 7537
Protoss_Nexus 2 10459
Protoss_Observer 1 8226
Protoss_Shuttle 1 9215
Protoss_Robotics_Support_Bay 1 9347
Protoss_Reaver 1 10480
Protoss_Zealot 2 10258
10480
