Protoss_Gateway 2 9655
Protoss_Assimilator 1 2841
Protoss_Cybernetics_Core 1 3924
Protoss_Zealot 2 9050
Protoss_Dragoon 8 10565
Protoss_Robotics_Facility 1 6601
Protoss_Shuttle 1 7591
Protoss_Robotics_Support_Bay 1 7778
Protoss_Reaver 1 8904
Protoss_Nexus 1 10095
Protoss_Observatory 1 9293
Protoss_Observer 1 10050
10565
