Protoss_Gateway 4 10817
Protoss_Assimilator 1 2788
Protoss_Cybernetics_Core 1 3736
Protoss_Dragoon 8 10152
Protoss_Robotics_Facility 1 6800
Protoss_Observatory 1 7347
Protoss_Nexus 2 10057
Protoss_Observer 4 9992
10817
