Protoss_Gateway 3 10134
Protoss_Assimilator 1 2820
Protoss_Cybernetics_Core 1 3725
Protoss_Dragoon 6 10206
Protoss_Robotics_Facility 1 6455
Protoss_Shuttle 1 7447
Protoss_Robotics_Support_Bay 1 7500
Protoss_Reaver 1 8878
Protoss_Zealot 2 10014
Protoss_Nexus 1 9947
Protoss_Observatory 1 8983
Protoss_Observer 2 10286
10286
