Protoss_Gateway 3 6839
Protoss_Assimilator 1 3114
Protoss_Cybernetics_Core 1 4359
Protoss_Dragoon 4 10723
Protoss_Citadel_of_Adun 1 5654
Protoss_Templar_Archives 1 7044
Protoss_Dark_Templar 6 10118
Protoss_Nexus 1 10990
10990
