Protoss_Gateway 6 10379
Protoss_Assimilator 1 3075
Protoss_Cybernetics_Core 1 4059
Protoss_Dragoon 8 9308
Protoss_Robotics_Facility 1 5778
Protoss_Observatory 1 6491
Protoss_Observer 4 9998
Protoss_Nexus 1 10140
10379
