Protoss_Gateway 2 8547
Protoss_Assimilator 2 9314
Protoss_Cybernetics_Core 1 3811
Protoss_Zealot 1 3816
Protoss_Dragoon 8 9718
Protoss_Nexus 1 8335
Protoss_Citadel_of_Adun 1 8123
Protoss_Templar_Archives 1 9219
Protoss_Robotics_Facility 1 9616
Protoss_Dark_Templar 2 10486
Protoss_Shuttle 1 10603
Protoss_Observatory 1 10400
10603
