Protoss_Gateway 2 10586
Protoss_Assimilator 1 2878
Protoss_Cybernetics_Core 1 3827
Protoss_Dragoon 7 10080
Protoss_Robotics_Facility 1 5627
Protoss_Shuttle 1 6941
Protoss_Zealot 1 7062
Protoss_Observatory 1 6937
Protoss_Observer 2 9864
Protoss_Robotics_Support_Bay 1 7626
Protoss_Reaver 1 8812
Protoss_Nexus 1 10763
10763
