Protoss_Gateway 5 5316
Protoss_Assimilator 1 5262
Protoss_Cybernetics_Core 1 6308
Protoss_Zealot 2 6588
Protoss_Dragoon 8 10104
Protoss_Robotics_Facility 1 9788
Protoss_Shuttle 1 10865
10865
