Protoss_Assimilator 2 3388
Protoss_Gateway 2 5997
Protoss_Cybernetics_Core 1 4208
Protoss_Zealot 1 4230
Protoss_Dragoon 8 9284
Protoss_Nexus 1 8811
Protoss_Citadel_of_Adun 1 8833
Protoss_Templar_Archives 1 9891
Protoss_Stargate 1 10260
Protoss_Dark_Templar 2 10728
10728
