Protoss_Gateway 3 7906
Protoss_Zealot 1 3440
Protoss_Nexus 1 5555
Protoss_Assimilator 2 6465
Protoss_Cybernetics_Core 1 5415
Protoss_Dragoon 9 10192
Protoss_Robotics_Facility 1 8364
Protoss_Observatory 1 8975
Protoss_Shuttle 1 9525
Protoss_Observer 1 10128
10192
