Protoss_Nexus 1 4421
Protoss_Gateway 5 10400
Protoss_Assimilator 2 7787
Protoss_Cybernetics_Core 1 4846
Protoss_Zealot 3 10522
Protoss_Dragoon 12 10092
Protoss_Robotics_Facility 1 8968
Protoss_Citadel_of_Adun 1 10081
Protoss_Observatory 1 9731
Protoss_Observer 1 10480
10522
