Protoss_Gateway 4 10692
Protoss_Assimilator 1 3002
Protoss_Cybernetics_Core 1 3809
Protoss_Dragoon 11 10746
Protoss_Nexus 1 7868
Protoss_Robotics_Facility 1 8333
Protoss_Observatory 1 9337
Protoss_Observer 1 10382
10746
