Protoss_Gateway 4 10515
Protoss_Assimilator 1 3047
Protoss_Cybernetics_Core 1 4028
Protoss_Dragoon 8 9714
Protoss_Robotics_Facility 1 6681
Protoss_Observatory 1 7257
Protoss_Observer 4 9826
Protoss_Nexus 2 10289
10515
