Protoss_Nexus 1 4518
Protoss_Gateway 2 5346
Protoss_Assimilator 2 8588
Protoss_Zealot 3 9064
Protoss_Cybernetics_Core 1 5021
Protoss_Dragoon 7 9226
Protoss_Citadel_of_Adun 1 7551
Protoss_Templar_Archives 1 8842
Protoss_Forge 1 9158
Protoss_Dark_Templar 2 9980
Protoss_Photon_Cannon 1 10125
Protoss_Stargate 1 10574
10574
