Protoss_Gateway 4 9684
Protoss_Assimilator 1 3100
Protoss_Cybernetics_Core 1 3993
Protoss_Dragoon 11 10578
Protoss_Robotics_Facility 1 6787
Protoss_Observatory 1 7372
Protoss_Observer 2 8808
Protoss_Nexus 1 9690
10578
