Protoss_Gateway 4 9162
Protoss_Assimilator 1 2786
Protoss_Cybernetics_Core 1 3867
Protoss_Robotics_Facility 1 5172
Protoss_Dragoon 13 10588
Protoss_Observatory 1 5893
Protoss_Observer 4 10240
Protoss_Nexus 1 8921
10588
