Protoss_Gateway 3 10433
Protoss_Assimilator 1 3082
Protoss_Cybernetics_Core 1 4037
Protoss_Dragoon 8 9648
Protoss_Robotics_Facility 1 5802
Protoss_Observatory 1 6463
Protoss_Observer 1 7173
Protoss_Nexus 1 9283
Protoss_Shuttle 1 9067
Protoss_Citadel_of_Adun 1 9893
Protoss_Zealot 2 10250
10433
