Protoss_Gateway 4 10180
Protoss_Assimilator 2 3300
Protoss_Cybernetics_Core 1 4257
Protoss_Dragoon 9 10616
Protoss_Nexus 1 9231
Protoss_Robotics_Facility 1 9052
Protoss_Shuttle 1 10055
Protoss_Observatory 1 10064
10616
