Protoss_Gateway 2 7773
Protoss_Assimilator 2 9323
Protoss_Cybernetics_Core 1 3927
Protoss_Zealot 3 10154
Protoss_Dragoon 6 8646
Protoss_Nexus 1 8121
Protoss_Robotics_Facility 1 8355
Protoss_Citadel_of_Adun 1 8746
Protoss_Observatory 1 8979
Protoss_Templar_Archives 1 9758
Protoss_Observer 1 9674
Protoss_Stargate 1 10796
Protoss_Shuttle 1 10727
Protoss_Dark_Templar 2 10640
10796
