Protoss_Gateway 2 7031
Protoss_Assimilator 1 2932
Protoss_Cybernetics_Core 1 4085
Protoss_Dragoon 11 10274
Protoss_Robotics_Facility 1 7097
Protoss_Observatory 1 7706
Protoss_Observer 1 8382
Protoss_Citadel_of_Adun 1 10060
10274
