Protoss_Gateway 3 10068
Protoss_Nexus 1 5295
Protoss_Zealot 2 5224
Protoss_Assimilator 2 7309
Protoss_Cybernetics_Core 1 5272
Protoss_Dragoon 8 9944
Protoss_Stargate 2 10529
Protoss_Robotics_Facility 1 9032
Protoss_Citadel_of_Adun 1 8884
Protoss_Fleet_Beacon 1 9735
Protoss_Carrier 1 11937
11937
