Protoss_Nexus 1 4513
Protoss_Gateway 3 9937
Protoss_Assimilator 2 6805
Protoss_Cybernetics_Core 1 5019
Protoss_Zealot 1 5212
Protoss_Dragoon 10 10364
Protoss_Robotics_Facility 1 8619
Protoss_Citadel_of_Adun 1 9571
Protoss_Observatory 1 9276
Protoss_Observer 1 9968
Protoss_Templar_Archives 1 10848
10848
