Protoss_Gateway 3 9875
Protoss_Assimilator 2 8630
Protoss_Cybernetics_Core 1 3889
Protoss_Nexus 1 5949
Protoss_Dragoon 10 9368
Protoss_Robotics_Facility 1 8465
Protoss_Observatory 1 9023
Protoss_Shuttle 1 9713
Protoss_Zealot 2 9970
Protoss_Observer 1 10316
10316
