Protoss_Gateway 2 8021
Protoss_Assimilator 1 3226
Protoss_Cybernetics_Core 1 4124
Protoss_Zealot 2 8818
Protoss_Dragoon 4 8138
Protoss_Robotics_Facility 1 7209
Protoss_Citadel_of_Adun 1 8086
Protoss_Observatory 1 7761
Protoss_Observer 1 8448
Protoss_Templar_Archives 1 9329
Protoss_Shuttle 1 10022
Protoss_Nexus 1 11195
Protoss_Dark_Templar 2 10353
11195
