Protoss_Gateway 2 6337
Protoss_Zealot 2 4116
Protoss_Nexus 2 11435
Protoss_Assimilator 2 6382
Protoss_Cybernetics_Core 1 5777
Protoss_Dragoon 7 9728
Protoss_Robotics_Facility 1 7757
Protoss_Observatory 1 8337
Protoss_Shuttle 1 9307
Protoss_Observer 2 9638
Protoss_Robotics_Support_Bay 1 9042
Protoss_Reaver 1 10856
11435
