Protoss_Gateway 2 7063
Protoss_Assimilator 1 2816
Protoss_Cybernetics_Core 1 3985
Protoss_Dragoon 8 10680
Protoss_Robotics_Facility 1 6727
Protoss_Zealot 5 8246
Protoss_Shuttle 1 7717
Protoss_Observatory 1 7403
Protoss_Observer 2 9220
Protoss_Nexus 1 9951
10680
