Protoss_Gateway 4 10618
Protoss_Assimilator 1 2984
Protoss_Cybernetics_Core 1 3887
Protoss_Dragoon 8 10644
Protoss_Robotics_Facility 1 6652
Protoss_Observatory 1 7243
Protoss_Nexus 2 10353
Protoss_Observer 3 10036
10644
