Protoss_Nexus 1 4465
Protoss_Gateway 5 8899
Protoss_Assimilator 2 7452
Protoss_Cybernetics_Core 1 5068
Protoss_Dragoon 10 9828
Protoss_Robotics_Facility 1 8413
Protoss_Shuttle 1 9583
Protoss_Observatory 1 9183
Protoss_Observer 1 10186
Protoss_Zealot 4 10430
10430
