Protoss_Gateway 2 4578
Protoss_Assimilator 2 3089
Protoss_Cybernetics_Core 1 4096
Protoss_Dragoon 5 6938
Protoss_Citadel_of_Adun 1 6889
Protoss_Templar_Archives 1 8109
Protoss_Robotics_Facility 1 8851
Protoss_Dark_Templar 4 10286
Protoss_Shuttle 1 9869
Protoss_Nexus 1 11425
11425
