Protoss_Gateway 3 8968
Protoss_Assimilator 1 2763
Protoss_Cybernetics_Core 1 3824
Protoss_Zealot 1 3762
Protoss_Dragoon 11 10552
Protoss_Nexus 1 7869
Protoss_Robotics_Facility 1 8109
Protoss_Observatory 1 8815
Protoss_Observer 2 10164
10552
