Protoss_Gateway 4 10567
Protoss_Assimilator 1 3080
Protoss_Cybernetics_Core 1 3939
Protoss_Dragoon 9 10556
Protoss_Robotics_Facility 1 6705
Protoss_Nexus 2 10364
Protoss_Observatory 1 7608
Protoss_Observer 4 10542
10567
