Protoss_Nexus 3 11311
Protoss_Gateway 2 4768
Protoss_Assimilator 2 6187
Protoss_Cybernetics_Core 1 5097
Protoss_Dragoon 6 7492
Protoss_Citadel_of_Adun 1 7843
Protoss_Templar_Archives 1 9086
Protoss_Stargate 2 11038
Protoss_Dark_Templar 2 10066
Protoss_Arbiter_Tribunal 1 10812
11311
