Protoss_Gateway 2 5493
Protoss_Assimilator 1 3005
Protoss_Cybernetics_Core 1 3862
Protoss_Dragoon 11 10172
Protoss_Robotics_Facility 1 7477
Protoss_Nexus 2 11039
Protoss_Observatory 1 8048
Protoss_Observer 2 9338
11039
