Protoss_Gateway 2 5427
Protoss_Assimilator 1 2850
Protoss_Cybernetics_Core 1 3881
Protoss_Zealot 1 3792
Protoss_Citadel_of_Adun 1 5133
Protoss_Templar_Archives 1 6123
Protoss_Dark_Templar 4 7756
Protoss_Nexus 2 9821
Protoss_Stargate 1 9656
9821
