Protoss_Gateway 3 10734
Protoss_Assimilator 1 2853
Protoss_Cybernetics_Core 1 3821
Protoss_Dragoon 11 10180
Protoss_Robotics_Facility 1 7473
Protoss_Observatory 1 8059
Protoss_Observer 3 10334
Protoss_Nexus 1 10430
10734
