Protoss_Gateway 4 10436
Protoss_Assimilator 1 2878
Protoss_Cybernetics_Core 1 3795
Protoss_Zealot 1 3854
Protoss_Dragoon 7 10026
Protoss_Citadel_of_Adun 1 5717
Protoss_Templar_Archives 1 6725
Protoss_Dark_Templar 2 7770
Protoss_Nexus 1 9822
Protoss_Robotics_Facility 1 10253
10436
