Protoss_Gateway 2 7276
Protoss_Assimilator 1 2968
Protoss_Cybernetics_Core 1 3961
Protoss_Zealot 1 3926
Protoss_Dragoon 8 10522
Protoss_Citadel_of_Adun 1 6927
Protoss_Templar_Archives 1 8151
Protoss_Dark_Templar 4 10120
Protoss_Nexus 1 11337
Protoss_Robotics_Facility 1 11183
11337
