Protoss_Gateway 2 10252
Protoss_Assimilator 2 3217
Protoss_Cybernetics_Core 1 3959
Protoss_Zealot 3 8664
Protoss_Dragoon 6 9782
Protoss_Robotics_Facility 1 7249
Protoss_Shuttle 1 8545
Protoss_Robotics_Support_Bay 1 8140
Protoss_Reaver 1 9596
Protoss_Observatory 1 10396
10396
