Protoss_Gateway 3 8864
Protoss_Assimilator 1 3105
Protoss_Cybernetics_Core 1 3979
Protoss_Dragoon 9 10668
Protoss_Robotics_Facility 1 5851
Protoss_Observatory 1 6442
Protoss_Observer 2 7793
Protoss_Nexus 1 10980
10980
