Protoss_Assimilator 3 7374
Protoss_Gateway 2 7227
Protoss_Zealot 4 6354
Protoss_Nexus 2 11319
Protoss_Cybernetics_Core 1 6429
Protoss_Dragoon 7 10001
Protoss_Robotics_Facility 1 9208
Protoss_Observatory 1 9770
Protoss_Observer 1 10456
Protoss_Robotics_Support_Bay 1 10447
11319
