Protoss_Nexus 1 4533
Protoss_Gateway 3 9462
Protoss_Assimilator 2 7779
Protoss_Cybernetics_Core 1 5115
Protoss_Zealot 1 5064
Protoss_Dragoon 7 9380
Protoss_Citadel_of_Adun 1 7689
Protoss_Templar_Archives 1 8677
Protoss_Robotics_Facility 1 9615
Protoss_Dark_Templar 4 10268
Protoss_Forge 1 10051
Protoss_Observatory 1 10339
10339
