Protoss_Gateway 2 8221
Protoss_Assimilator 2 9393
Protoss_Cybernetics_Core 1 4121
Protoss_Zealot 1 4276
Protoss_Dragoon 6 9172
Protoss_Nexus 1 8231
Protoss_Robotics_Facility 1 8028
Protoss_Citadel_of_Adun 1 7911
Protoss_Templar_Archives 1 8921
Protoss_Observatory 1 8615
Protoss_Shuttle 1 9597
Protoss_Dark_Templar 2 9796
Protoss_Observer 1 10242
Protoss_Stargate 1 10943
10943
