Protoss_Gateway 3 8968
Protoss_Assimilator 2 10245
Protoss_Cybernetics_Core 1 3783
Protoss_Dragoon 10 9946
Protoss_Robotics_Facility 1 6871
Protoss_Nexus 1 8699
Protoss_Observatory 1 7513
Protoss_Observer 3 10416
Protoss_Citadel_of_Adun 1 10406
10416
