Protoss_Gateway 2 6797
Protoss_Assimilator 1 2999
Protoss_Cybernetics_Core 1 3886
Protoss_Dragoon 8 9196
Protoss_Robotics_Facility 1 6139
Protoss_Robotics_Support_Bay 1 6777
Protoss_Shuttle 1 7459
Protoss_Observatory 1 7596
Protoss_Reaver 2 10164
Protoss_Observer 1 9114
Protoss_Nexus 1 11704
11704
