Protoss_Gateway 2 7180
Protoss_Assimilator 1 3188
Protoss_Cybernetics_Core 1 3977
Protoss_Zealot 5 9498
Protoss_Dragoon 6 8288
Protoss_Robotics_Facility 1 6951
Protoss_Robotics_Support_Bay 1 8086
Protoss_Shuttle 1 8991
Protoss_Reaver 1 10466
Protoss_Nexus 1 11477
11477
