Protoss_Nexus 1 4595
Protoss_Gateway 5 10612
Protoss_Assimilator 2 6399
Protoss_Zealot 1 4992
Protoss_Cybernetics_Core 1 5353
Protoss_Dragoon 13 10696
Protoss_Robotics_Facility 1 8358
Protoss_Observatory 1 8997
Protoss_Citadel_of_Adun 1 9827
Protoss_Observer 2 10412
10696
