Protoss_Gateway 2 7375
Protoss_Assimilator 2 9359
Protoss_Cybernetics_Core 1 4015
Protoss_Dragoon 5 8272
Protoss_Nexus 1 7754
Protoss_Robotics_Facility 1 8047
Protoss_Shuttle 1 9031
Protoss_Robotics_Support_Bay 1 8664
Protoss_Observatory 1 9037
Protoss_Reaver 1 10082
Protoss_Zealot 4 10564
10564
