Protoss_Gateway 2 7027
Protoss_Assimilator 1 3024
Protoss_Cybernetics_Core 1 3798
Protoss_Dragoon 8 10384
Protoss_Robotics_Facility 1 6861
Protoss_Observatory 1 7409
Protoss_Observer 2 9720
Protoss_Nexus 1 9487
Protoss_Shuttle 1 9117
Protoss_Robotics_Support_Bay 1 9174
Protoss_Reaver 1 10408
10408
