Protoss_Assimilator 2 3392
Protoss_Gateway 3 7299
Protoss_Zealot 2 8818
Protoss_Cybernetics_Core 1 4968
Protoss_Dragoon 6 10302
Protoss_Robotics_Facility 1 6921
Protoss_Shuttle 1 7903
Protoss_Robotics_Support_Bay 1 7967
Protoss_Reaver 1 9154
Protoss_Nexus 1 10655
Protoss_Observatory 1 9565
Protoss_Observer 1 10274
10655
