Protoss_Gateway 3 8912
Protoss_Assimilator 1 2814
Protoss_Cybernetics_Core 1 3780
Protoss_Dragoon 10 10238
Protoss_Nexus 1 7908
Protoss_Robotics_Facility 1 8053
Protoss_Observatory 1 8701
Protoss_Observer 1 9500
Protoss_Zealot 2 10370
10370
