Protoss_Gateway 2 9270
Protoss_Assimilator 1 3003
Protoss_Cybernetics_Core 1 3852
Protoss_Zealot 2 9290
Protoss_Dragoon 6 10308
Protoss_Robotics_Facility 1 6843
Protoss_Shuttle 1 7831
Protoss_Nexus 1 9161
Protoss_Robotics_Support_Bay 1 8005
Protoss_Reaver 1 9260
Protoss_Observatory 1 9362
Protoss_Observer 1 10078
10308
