Protoss_Gateway 3 8322
Protoss_Assimilator 1 3142
Protoss_Cybernetics_Core 1 4383
Protoss_Zealot 1 4420
Protoss_Dragoon 8 10454
Protoss_Robotics_Facility 1 7085
Protoss_Nexus 1 8955
Protoss_Observatory 1 7744
Protoss_Observer 1 8430
Protoss_Robotics_Support_Bay 1 8630
Protoss_Shuttle 1 9781
Protoss_Reaver 1 10914
10914
