Protoss_Gateway 2 9671
Protoss_Assimilator 1 2978
Protoss_Cybernetics_Core 1 3787
Protoss_Dragoon 8 10678
Protoss_Robotics_Facility 1 6493
Protoss_Shuttle 2 10837
Protoss_Robotics_Support_Bay 1 7352
Protoss_Zealot 2 8276
Protoss_Reaver 1 8799
Protoss_Nexus 1 9943
Protoss_Observatory 1 8896
Protoss_Observer 1 9892
10837
