Protoss_Nexus 2 10519
Protoss_Gateway 2 5061
Protoss_Assimilator 2 7085
Protoss_Cybernetics_Core 1 5249
Protoss_Zealot 1 5370
Protoss_Dragoon 8 9940
Protoss_Robotics_Facility 1 8182
Protoss_Shuttle 1 9273
Protoss_Robotics_Support_Bay 1 9421
Protoss_Reaver 1 10606
10606
