Protoss_Gateway 2 6172
Protoss_Assimilator 1 3019
Protoss_Cybernetics_Core 1 3995
Protoss_Dragoon 5 7288
Protoss_Robotics_Facility 1 7054
Protoss_Shuttle 1 8137
Protoss_Zealot 4 8752
Protoss_Observatory 1 8123
Protoss_Observer 3 10083
Protoss_Nexus 2 11033
11033
