Protoss_Gateway 2 7254
Protoss_Assimilator 1 2941
Protoss_Cybernetics_Core 1 3883
Protoss_Dragoon 7 8938
Protoss_Robotics_Facility 1 6667
Protoss_Observatory 1 7329
Protoss_Observer 2 8644
Protoss_Nexus 1 9565
Protoss_Shuttle 1 9545
Protoss_Robotics_Support_Bay 1 9293
Protoss_Zealot 2 10084
Protoss_Reaver 1 10689
10689
