Protoss_Gateway 2 9147
Protoss_Assimilator 1 2997
Protoss_Cybernetics_Core 1 3764
Protoss_Zealot 2 9150
Protoss_Dragoon 8 10734
Protoss_Nexus 2 11557
Protoss_Robotics_Facility 1 7061
Protoss_Shuttle 1 8097
Protoss_Robotics_Support_Bay 1 8101
Protoss_Reaver 1 9226
Protoss_Observatory 1 9058
Protoss_Observer 2 10492
11557
