Protoss_Gateway 3 9221
Protoss_Assimilator 1 2894
Protoss_Cybernetics_Core 1 3791
Protoss_Dragoon 7 8716
Protoss_Nexus 1 8769
Protoss_Robotics_Facility 1 8745
Protoss_Shuttle 1 9761
Protoss_Robotics_Support_Bay 1 9642
Protoss_Reaver 1 10814
10814
