Protoss_Gateway 2 7519
Protoss_Assimilator 1 3050
Protoss_Zealot 6 8976
Protoss_Cybernetics_Core 1 4639
Protoss_Dragoon 7 10640
Protoss_Robotics_Facility 1 7301
Protoss_Observatory 1 7863
Protoss_Shuttle 1 8351
Protoss_Observer 2 9556
Protoss_Nexus 1 11373
11373
