Protoss_Gateway 3 9980
Protoss_Assimilator 1 2804
Protoss_Cybernetics_Core 1 3794
Protoss_Dragoon 12 10582
Protoss_Robotics_Facility 1 6608
Protoss_Nexus 1 7986
Protoss_Observatory 1 7155
Protoss_Robotics_Support_Bay 1 7835
Protoss_Reaver 1 9538
Protoss_Observer 1 10142
10582
