Protoss_Gateway 2 8061
Protoss_Assimilator 2 9358
Protoss_Cybernetics_Core 1 3811
Protoss_Zealot 1 3664
Protoss_Dragoon 7 9350
Protoss_Robotics_Facility 1 6523
Protoss_Observatory 1 7063
Protoss_Nexus 2 11721
Protoss_Observer 2 8504
Protoss_Citadel_of_Adun 1 9425
Protoss_Templar_Archives 1 10420
11721
