Protoss_Gateway 3 10682
Protoss_Assimilator 1 2782
Protoss_Cybernetics_Core 1 3823
Protoss_Zealot 3 9074
Protoss_Dragoon 7 10010
Protoss_Nexus 1 7405
Protoss_Robotics_Facility 1 7602
Protoss_Shuttle 1 8629
Protoss_Robotics_Support_Bay 1 8759
Protoss_Reaver 1 9902
Protoss_Observatory 1 9978
10682
