Protoss_Gateway 3 9658
Protoss_Assimilator 1 2920
Protoss_Cybernetics_Core 1 3828
Protoss_Dragoon 10 10578
Protoss_Robotics_Facility 1 5983
Protoss_Observatory 1 6532
Protoss_Observer 3 8530
Protoss_Nexus 1 9029
Protoss_Shuttle 1 10137
10578
