Protoss_Gateway 3 9422
Protoss_Assimilator 1 3190
Protoss_Cybernetics_Core 1 4044
Protoss_Dragoon 9 10473
Protoss_Zealot 5 10246
Protoss_Robotics_Facility 1 7462
Protoss_Observatory 1 8066
Protoss_Observer 1 9073
Protoss_Shuttle 1 10107
10473
