Protoss_Gateway 1 2864
Protoss_Assimilator 1 3060
Protoss_Cybernetics_Core 1 3918
Protoss_Stargate 1 5073
Protoss_Dragoon 6 10420
Protoss_Scout 1 6460
Protoss_Robotics_Facility 1 8287
Protoss_Observatory 1 9009
Protoss_Nexus 1 10566
Protoss_Observer 2 10460
10566
