Protoss_Gateway 2 3569
Protoss_Zealot 11 9653
Protoss_Assimilator 1 4579
Protoss_Forge 1 5069
Protoss_Photon_Cannon 2 6087
Protoss_Cybernetics_Core 1 7229
Protoss_Citadel_of_Adun 1 8478
Protoss_Dragoon 2 8633
Protoss_Templar_Archives 1 9572
Protoss_High_Templar 1 10433
10433
