Protoss_Gateway 3 10776
Protoss_Assimilator 2 8864
Protoss_Cybernetics_Core 1 3826
Protoss_Zealot 1 3752
Protoss_Dragoon 7 10440
Protoss_Citadel_of_Adun 1 6069
Protoss_Templar_Archives 1 7068
Protoss_Nexus 1 8857
Protoss_Dark_Templar 1 8034
Protoss_Robotics_Facility 1 8963
Protoss_Observatory 1 9910
Protoss_Stargate 1 10985
Protoss_Observer 1 10594
10985
