Protoss_Nexus 2 9806
Protoss_Gateway 2 5453
Protoss_Assimilator 2 9398
Protoss_Cybernetics_Core 1 5263
Protoss_Zealot 1 4986
Protoss_Dragoon 8 9982
Protoss_Citadel_of_Adun 1 9261
Protoss_Robotics_Facility 1 9902
Protoss_Templar_Archives 1 10495
10495
