Protoss_Gateway 2 8230
Protoss_Assimilator 2 9429
Protoss_Cybernetics_Core 1 4076
Protoss_Dragoon 9 9892
Protoss_Robotics_Facility 1 7025
Protoss_Nexus 1 8793
Protoss_Observatory 1 7680
Protoss_Observer 2 10240
Protoss_Citadel_of_Adun 1 10218
10240
