Protoss_Gateway 2 4405
Protoss_Assimilator 1 3040
Protoss_Cybernetics_Core 1 3845
Protoss_Dragoon 5 10368
Protoss_Citadel_of_Adun 1 6281
Protoss_Robotics_Facility 1 6979
Protoss_Templar_Archives 1 7269
Protoss_Shuttle 1 7967
Protoss_Dark_Templar 4 8986
Protoss_Nexus 1 10804
10804
