Protoss_Nexus 2 9851
Protoss_Gateway 2 6925
Protoss_Assimilator 1 4064
Protoss_Cybernetics_Core 1 5109
Protoss_Dragoon 9 10282
Protoss_Robotics_Facility 1 6755
Protoss_Observatory 1 7341
Protoss_Observer 1 8292
Protoss_Shuttle 1 8813
10282
