Protoss_Nexus 2 9595
Protoss_Gateway 8 10761
Protoss_Assimilator 2 9579
Protoss_Cybernetics_Core 1 5005
Protoss_Dragoon 10 9744
Protoss_Robotics_Facility 1 8537
Protoss_Observatory 1 9178
Protoss_Observer 1 9914
10761
