Protoss_Gateway 3 10092
Protoss_Zealot 13 9430
Protoss_Forge 1 4828
Protoss_Photon_Cannon 3 7313
Protoss_Assimilator 1 8563
Protoss_Cybernetics_Core 1 9275
Protoss_Dragoon 2 10182
10182
