Protoss_Nexus 1 4569
Protoss_Gateway 4 10623
Protoss_Assimilator 2 7097
Protoss_Cybernetics_Core 1 4989
Protoss_Zealot 1 5254
Protoss_Dragoon 10 9766
Protoss_Robotics_Facility 1 8085
Protoss_Shuttle 1 9257
Protoss_Robotics_Support_Bay 1 9010
Protoss_Reaver 1 10308
Protoss_Observatory 1 10201
10623
