Protoss_Gateway 3 9898
Protoss_Assimilator 2 10004
Protoss_Cybernetics_Core 1 4373
Protoss_Dragoon 10 10538
Protoss_Robotics_Facility 1 6936
Protoss_Observatory 1 7481
Protoss_Nexus 1 8946
Protoss_Observer 3 10404
10538
