Protoss_Nexus 1 4545
Protoss_Gateway 2 5315
Protoss_Assimilator 2 6973
Protoss_Cybernetics_Core 1 5067
Protoss_Dragoon 6 8906
Protoss_Citadel_of_Adun 1 7562
Protoss_Robotics_Facility 1 8495
Protoss_Templar_Archives 1 8702
Protoss_Shuttle 1 9539
Protoss_Dark_Templar 2 9658
Protoss_Stargate 1 10256
Protoss_Observatory 1 9725
Protoss_Observer 1 10412
10412
