Protoss_Gateway 2 3469
Protoss_Zealot 10 7368
Protoss_Forge 1 4415
Protoss_Photon_Cannon 3 10108
Protoss_Assimilator 1 5673
Protoss_Cybernetics_Core 1 8311
Protoss_Robotics_Facility 1 9602
Protoss_Shuttle 1 10592
Protoss_Robotics_Support_Bay 1 10256
10592
