Protoss_Gateway 2 4355
Protoss_Assimilator 2 9463
Protoss_Cybernetics_Core 1 3800
Protoss_Dragoon 9 10206
Protoss_Nexus 1 8031
Protoss_Robotics_Facility 1 8043
Protoss_Observatory 1 8891
Protoss_Citadel_of_Adun 1 9659
Protoss_Observer 1 9998
Protoss_Templar_Archives 1 10835
Protoss_Stargate 1 11040
11040
