Protoss_Nexus 2 9550
Protoss_Gateway 2 5213
Protoss_Assimilator 1 4062
Protoss_Cybernetics_Core 1 5061
Protoss_Zealot 3 10050
Protoss_Dragoon 6 9178
Protoss_Robotics_Facility 1 7491
Protoss_Robotics_Support_Bay 1 8060
Protoss_Shuttle 1 8813
Protoss_Observatory 1 8975
Protoss_Reaver 1 9864
Protoss_Air_Weapons_1 1 9825
Protoss_Observer 1 10468
10468
