Protoss_Gateway 2 7068
Protoss_Assimilator 1 2850
Protoss_Cybernetics_Core 1 3858
Protoss_Dragoon 9 10522
Protoss_Robotics_Facility 1 6799
Protoss_Observatory 1 7515
Protoss_Observer 2 8914
Protoss_Robotics_Support_Bay 1 8855
Protoss_Nexus 1 10567
Protoss_Zealot 2 9612
Protoss_Shuttle 1 10611
10611
