Protoss_Gateway 2 8283
Protoss_Assimilator 1 3100
Protoss_Cybernetics_Core 1 4177
Protoss_Zealot 1 4100
Protoss_Dragoon 9 10062
Protoss_Nexus 2 11537
Protoss_Robotics_Facility 1 8213
Protoss_Observatory 1 8828
Protoss_Observer 1 9608
11537
