Protoss_Gateway 2 7156
Protoss_Assimilator 3 10518
Protoss_Cybernetics_Core 1 4105
Protoss_Zealot 1 4260
Protoss_Dragoon 6 8912
Protoss_Robotics_Facility 1 6984
Protoss_Observatory 1 7641
Protoss_Nexus 1 9439
Protoss_Observer 1 8516
Protoss_Shuttle 1 9483
Protoss_Robotics_Support_Bay 1 9207
Protoss_Reaver 1 10534
10534
