Protoss_Gateway 3 9744
Protoss_Assimilator 1 3084
Protoss_Cybernetics_Core 1 3963
Protoss_Dragoon 10 10013
Protoss_Robotics_Facility 1 6691
Protoss_Observatory 1 7266
Protoss_Observer 2 8718
Protoss_Nexus 1 10260
10260
