Protoss_Gateway 3 9845
Protoss_Assimilator 1 3057
Protoss_Cybernetics_Core 1 3815
Protoss_Dragoon 9 10178
Protoss_Nexus 1 8133
Protoss_Robotics_Facility 1 8898
Protoss_Observatory 1 9681
Protoss_Observer 1 10412
10412
