Protoss_Gateway 3 10766
Protoss_Assimilator 1 3216
Protoss_Cybernetics_Core 1 4179
Protoss_Dragoon 7 9758
Protoss_Citadel_of_Adun 1 5800
Protoss_Templar_Archives 1 6853
Protoss_Dark_Templar 2 7738
Protoss_Nexus 1 10060
Protoss_Robotics_Facility 1 10075
10766
