Protoss_Gateway 3 9551
Protoss_Assimilator 2 10202
Protoss_Cybernetics_Core 1 3813
Protoss_Dragoon 8 10592
Protoss_Robotics_Facility 1 6571
Protoss_Shuttle 1 7593
Protoss_Nexus 1 9009
Protoss_Robotics_Support_Bay 1 7878
Protoss_Reaver 1 9014
Protoss_Observatory 1 8794
Protoss_Observer 2 10260
10592
