Protoss_Gateway 2 4336
Protoss_Assimilator 1 2795
Protoss_Cybernetics_Core 1 3717
Protoss_Dragoon 9 10448
Protoss_Citadel_of_Adun 1 6876
Protoss_Templar_Archives 1 8248
Protoss_Nexus 2 11002
Protoss_Dark_Templar 2 9180
11002
