Protoss_Gateway 4 10501
Protoss_Assimilator 1 3070
Protoss_Cybernetics_Core 1 4005
Protoss_Dragoon 7 9910
Protoss_Nexus 1 7854
Protoss_Robotics_Facility 1 8125
Protoss_Shuttle 1 9165
Protoss_Robotics_Support_Bay 1 8787
Protoss_Reaver 1 10311
10501
