Protoss_Gateway 2 6463
Protoss_Assimilator 1 3054
Protoss_Cybernetics_Core 1 4005
Protoss_Dragoon 8 10712
Protoss_Citadel_of_Adun 1 5997
Protoss_Templar_Archives 1 6991
Protoss_Nexus 1 8730
Protoss_Dark_Templar 3 8646
10712
