Protoss_Gateway 2 5485
Protoss_Assimilator 1 2914
Protoss_Cybernetics_Core 1 3741
Protoss_Zealot 1 3786
Protoss_Dragoon 10 10158
Protoss_Nexus 1 9083
Protoss_Robotics_Facility 1 9031
Protoss_Shuttle 1 10011
Protoss_Observatory 1 9635
Protoss_Robotics_Support_Bay 1 10267
10267
