Protoss_Gateway 4 10399
Protoss_Assimilator 1 2975
Protoss_Cybernetics_Core 1 4290
Protoss_Dragoon 7 10718
Protoss_Citadel_of_Adun 1 5713
Protoss_Templar_Archives 1 6913
Protoss_Dark_Templar 2 8400
Protoss_Nexus 1 9156
Protoss_Robotics_Facility 1 9717
10718
