Protoss_Gateway 2 10061
Protoss_Assimilator 1 2906
Protoss_Cybernetics_Core 1 3862
Protoss_Dragoon 6 10554
Protoss_Robotics_Facility 1 5560
Protoss_Shuttle 1 6845
Protoss_Observatory 1 6743
Protoss_Observer 1 7448
Protoss_Robotics_Support_Bay 1 7576
Protoss_Zealot 2 8714
Protoss_Reaver 1 8768
Protoss_Nexus 1 10425
10554
