Protoss_Gateway 2 9406
Protoss_Assimilator 1 2766
Protoss_Cybernetics_Core 1 3823
Protoss_Dragoon 8 10448
Protoss_Robotics_Facility 1 6301
Protoss_Shuttle 1 7283
Protoss_Robotics_Support_Bay 1 6923
Protoss_Zealot 1 7080
Protoss_Reaver 2 9400
Protoss_Observatory 1 8141
Protoss_Observer 1 10004
10448
