Protoss_Gateway 1 2803
Protoss_Assimilator 1 2868
Protoss_Cybernetics_Core 1 3833
Protoss_Zealot 2 7438
Protoss_Robotics_Facility 1 5366
Protoss_Dragoon 2 10448
Protoss_Shuttle 1 6381
Protoss_Robotics_Support_Bay 1 6201
Protoss_Reaver 1 7498
Protoss_Observatory 1 7082
Protoss_Observer 3 9371
Protoss_Nexus 1 9593
10448
