Protoss_Gateway 2 7217
Protoss_Assimilator 1 3106
Protoss_Cybernetics_Core 1 3937
Protoss_Dragoon 8 10530
Protoss_Citadel_of_Adun 2 6710
Protoss_Nexus 1 8375
Protoss_Templar_Archives 1 7774
Protoss_Dark_Templar 2 8773
Protoss_Robotics_Facility 1 9555
10530
