Protoss_Gateway 4 10247
Protoss_Assimilator 1 2845
Protoss_Cybernetics_Core 1 3835
Protoss_Dragoon 9 10682
Protoss_Citadel_of_Adun 1 6658
Protoss_Nexus 1 9264
Protoss_Templar_Archives 1 8468
Protoss_Dark_Templar 2 9470
Protoss_Robotics_Facility 1 10412
10682
