Protoss_Nexus 2 10793
Protoss_Gateway 3 10830
Protoss_Assimilator 1 4060
Protoss_Cybernetics_Core 1 5343
Protoss_Zealot 1 5428
Protoss_Dragoon 10 10058
Protoss_Robotics_Facility 1 8369
Protoss_Observatory 1 9845
Protoss_Observer 1 10530
10830
