Protoss_Gateway 2 6909
Protoss_Assimilator 2 10218
Protoss_Cybernetics_Core 1 3784
Protoss_Dragoon 6 10482
Protoss_Citadel_of_Adun 1 5964
Protoss_Robotics_Facility 1 6864
Protoss_Templar_Archives 1 7013
Protoss_Zealot 1 6844
Protoss_Shuttle 1 7881
Protoss_Dark_Templar 2 8038
Protoss_Observatory 1 8018
Protoss_Observer 3 10384
Protoss_Nexus 1 9955
10482
