Protoss_Gateway 3 9846
Protoss_Assimilator 1 2761
Protoss_Cybernetics_Core 1 3721
Protoss_Zealot 1 3696
Protoss_Dragoon 8 10692
Protoss_Robotics_Facility 1 5493
Protoss_Shuttle 1 6473
Protoss_Robotics_Support_Bay 1 6213
Protoss_Reaver 1 7524
Protoss_Nexus 1 9179
Protoss_Observatory 1 8165
Protoss_Observer 2 9720
10692
