Protoss_Gateway 5 10797
Protoss_Assimilator 2 3239
Protoss_Cybernetics_Core 1 4137
Protoss_Dragoon 7 10136
Protoss_Nexus 2 9548
Protoss_Robotics_Facility 1 9525
Protoss_Observatory 1 10091
10797
