Protoss_Gateway 2 6762
Protoss_Assimilator 1 3100
Protoss_Cybernetics_Core 1 4049
Protoss_Dragoon 9 9848
Protoss_Robotics_Facility 1 7221
Protoss_Observatory 1 7766
Protoss_Observer 3 9848
Protoss_Nexus 1 10010
10010
