Protoss_Gateway 5 10867
Protoss_Zealot 2 5448
Protoss_Nexus 1 5517
Protoss_Assimilator 2 6010
Protoss_Cybernetics_Core 1 5529
Protoss_Dragoon 7 10350
Protoss_Robotics_Facility 1 7337
Protoss_Shuttle 1 8325
Protoss_Robotics_Support_Bay 1 8348
Protoss_Reaver 1 9474
Protoss_Observatory 1 9218
Protoss_Observer 1 10078
10867
