Protoss_Gateway 2 7339
Protoss_Assimilator 1 2813
Protoss_Cybernetics_Core 1 3753
Protoss_Dragoon 10 10176
Protoss_Nexus 1 7866
Protoss_Robotics_Facility 1 8608
Protoss_Zealot 1 8497
Protoss_Shuttle 1 10051
Protoss_Robotics_Support_Bay 1 9734
10176
