Protoss_Gateway 2 9167
Protoss_Assimilator 2 9109
Protoss_Cybernetics_Core 1 3757
Protoss_Dragoon 9 10162
Protoss_Robotics_Facility 1 6680
Protoss_Observatory 1 7260
Protoss_Nexus 1 9191
Protoss_Observer 2 8896
Protoss_Citadel_of_Adun 1 8886
10162
