Protoss_Gateway 2 8090
Protoss_Assimilator 1 2954
Protoss_Cybernetics_Core 1 3866
Protoss_Dragoon 6 10384
Protoss_Robotics_Facility 1 7163
Protoss_Nexus 2 11603
Protoss_Shuttle 1 8759
Protoss_Observatory 1 8382
Protoss_Zealot 3 9504
Protoss_Observer 1 9362
11603
