Protoss_Gateway 3 10197
Protoss_Assimilator 1 3125
Protoss_Zealot 2 4216
Protoss_Cybernetics_Core 1 4921
Protoss_Dragoon 5 9456
Protoss_Robotics_Facility 1 7215
Protoss_Nexus 1 8313
Protoss_Shuttle 1 8203
Protoss_Robotics_Support_Bay 1 7881
Protoss_Reaver 1 9274
Protoss_Observatory 1 9933
10197
