Protoss_Gateway 2 8727
Protoss_Assimilator 1 2834
Protoss_Cybernetics_Core 1 3837
Protoss_Dragoon 8 10448
Protoss_Robotics_Facility 1 6527
Protoss_Shuttle 1 7539
Protoss_Robotics_Support_Bay 1 7219
Protoss_Observatory 1 7415
Protoss_Reaver 2 10344
Protoss_Nexus 1 10281
Protoss_Observer 1 9204
10448
