Protoss_Gateway 3 8106
Protoss_Assimilator 1 3165
Protoss_Cybernetics_Core 1 4089
Protoss_Dragoon 3 6833
Protoss_Robotics_Facility 1 6941
Protoss_Nexus 1 8444
Protoss_Observatory 1 7909
Protoss_Citadel_of_Adun 1 8684
Protoss_Observer 2 10073
Protoss_Zealot 7 10543
10543
