Protoss_Gateway 2 4730
Protoss_Assimilator 1 3048
Protoss_Cybernetics_Core 1 3965
Protoss_Dragoon 6 8126
Protoss_Citadel_of_Adun 1 6547
Protoss_Templar_Archives 1 7741
Protoss_Zealot 1 7964
Protoss_Dark_Templar 4 10112
Protoss_Nexus 2 11625
11625
