Protoss_Gateway 2 7317
Protoss_Assimilator 2 10058
Protoss_Cybernetics_Core 1 3751
Protoss_Dragoon 9 9282
Protoss_Nexus 2 7759
Protoss_Robotics_Facility 1 8151
Protoss_Observatory 1 8994
Protoss_Shuttle 1 9559
Protoss_Observer 1 10162
Protoss_Robotics_Support_Bay 1 10073
Protoss_Zealot 2 10424
Protoss_Citadel_of_Adun 1 10864
10864
