Protoss_Gateway 2 8988
Protoss_Assimilator 1 3005
Protoss_Cybernetics_Core 1 3839
Protoss_Dragoon 9 10276
Protoss_Robotics_Facility 1 7134
Protoss_Observatory 1 7832
Protoss_Observer 4 10534
Protoss_Nexus 1 11732
11732
