Protoss_Gateway 3 8323
Protoss_Zealot 4 5581
Protoss_Assimilator 1 4256
Protoss_Cybernetics_Core 1 5603
Protoss_Dragoon 10 10640
Protoss_Robotics_Facility 1 9128
Protoss_Observatory 1 9669
Protoss_Observer 1 10348
10640
