Protoss_Nexus 3 10243
Protoss_Gateway 2 5206
Protoss_Assimilator 1 3860
Protoss_Cybernetics_Core 1 4969
Protoss_Zealot 1 5082
Protoss_Dragoon 6 9680
Protoss_Robotics_Facility 1 8951
Protoss_Observatory 1 9673
Protoss_Citadel_of_Adun 1 10455
Protoss_Observer 1 10366
10455
