Protoss_Gateway 2 9702
Protoss_Assimilator 1 2962
Protoss_Cybernetics_Core 1 3826
Protoss_Dragoon 8 10604
Protoss_Nexus 2 11579
Protoss_Robotics_Facility 1 8053
Protoss_Shuttle 1 9103
Protoss_Robotics_Support_Bay 1 9138
Protoss_Reaver 1 10280
11579
