Protoss_Gateway 2 8531
Protoss_Assimilator 2 9227
Protoss_Cybernetics_Core 1 3823
Protoss_Zealot 1 3700
Protoss_Dragoon 10 10710
Protoss_Robotics_Facility 1 6654
Protoss_Observatory 1 7285
Protoss_Nexus 1 8839
Protoss_Observer 4 10520
Protoss_Citadel_of_Adun 1 9435
Protoss_Stargate 1 10712
10712
