Protoss_Nexus 1 4581
Protoss_Gateway 2 5265
Protoss_Assimilator 2 6528
Protoss_Cybernetics_Core 1 5018
Protoss_Zealot 1 5276
Protoss_Dragoon 6 10576
Protoss_Citadel_of_Adun 1 7299
Protoss_Robotics_Facility 1 8448
Protoss_Templar_Archives 1 8356
Protoss_Shuttle 1 9487
Protoss_Dark_Templar 2 9382
Protoss_Forge 1 9346
Protoss_Observatory 1 9648
Protoss_Stargate 1 10474
Protoss_Photon_Cannon 1 10423
Protoss_Observer 1 10334
10576
