Protoss_Gateway 4 10623
Protoss_Assimilator 1 2942
Protoss_Cybernetics_Core 1 3851
Protoss_Dragoon 6 10036
Protoss_Robotics_Facility 1 5550
Protoss_Shuttle 1 6791
Protoss_Zealot 2 7542
Protoss_Observatory 1 6815
Protoss_Robotics_Support_Bay 1 7273
Protoss_Observer 1 7550
Protoss_Nexus 1 9809
Protoss_Reaver 1 9290
10623
