Protoss_Gateway 2 4692
Protoss_Assimilator 1 3056
Protoss_Cybernetics_Core 1 3977
Protoss_Dragoon 10 9250
Protoss_Robotics_Facility 1 7504
Protoss_Shuttle 1 8711
Protoss_Robotics_Support_Bay 1 8527
Protoss_Reaver 1 9772
Protoss_Zealot 2 9852
9852
