Protoss_Gateway 1 2817
Protoss_Assimilator 1 2979
Protoss_Cybernetics_Core 1 3889
Protoss_Dragoon 5 9950
Protoss_Robotics_Facility 1 6830
Protoss_Zealot 2 8010
Protoss_Shuttle 1 7851
Protoss_Robotics_Support_Bay 1 7798
Protoss_Reaver 1 8942
Protoss_Nexus 1 10575
Protoss_Observatory 1 9289
10575
