Protoss_Gateway 2 4289
Protoss_Assimilator 1 2839
Protoss_Cybernetics_Core 1 3765
Protoss_Dragoon 6 7414
Protoss_Citadel_of_Adun 1 5960
Protoss_Zealot 1 6040
Protoss_Templar_Archives 1 7126
Protoss_Dark_Templar 2 8256
Protoss_Nexus 2 11263
Protoss_Robotics_Facility 1 11016
11263
