Protoss_Gateway 4 10477
Protoss_Assimilator 1 2977
Protoss_Cybernetics_Core 1 3798
Protoss_Dragoon 9 10408
Protoss_Robotics_Facility 1 6513
Protoss_Observatory 1 7070
Protoss_Observer 3 10286
Protoss_Nexus 2 10073
10477
