Protoss_Gateway 3 9872
Protoss_Assimilator 1 3105
Protoss_Cybernetics_Core 1 4064
Protoss_Dragoon 8 10308
Protoss_Robotics_Facility 1 6752
Protoss_Shuttle 1 7862
Protoss_Robotics_Support_Bay 1 7501
Protoss_Reaver 1 8986
10308
