Protoss_Gateway 1 3177
Protoss_Assimilator 1 3222
Protoss_Cybernetics_Core 1 4294
Protoss_Dragoon 5 8222
Protoss_Robotics_Facility 1 7547
Protoss_Shuttle 1 8712
Protoss_Robotics_Support_Bay 1 8501
Protoss_Zealot 2 10083
Protoss_Reaver 2 10818
10818
