Protoss_Gateway 2 8785
Protoss_Assimilator 1 2998
Protoss_Zealot 3 4801
Protoss_Cybernetics_Core 1 4749
Protoss_Dragoon 7 9980
Protoss_Nexus 1 8503
Protoss_Robotics_Facility 1 8407
Protoss_Shuttle 1 9401
Protoss_Robotics_Support_Bay 1 9486
Protoss_Reaver 1 10642
Protoss_Observatory 1 10059
10642
