Protoss_Gateway 3 8527
Protoss_Assimilator 2 8848
Protoss_Cybernetics_Core 1 3842
Protoss_Zealot 1 3746
Protoss_Dragoon 8 9734
Protoss_Nexus 1 7732
Protoss_Robotics_Facility 1 7973
Protoss_Observatory 1 8589
Protoss_Citadel_of_Adun 1 9535
Protoss_Observer 2 9872
Protoss_Templar_Archives 1 10633
Protoss_Stargate 1 10815
10815
