Protoss_Gateway 3 10884
Protoss_Assimilator 1 2970
Protoss_Cybernetics_Core 1 4004
Protoss_Dragoon 9 10365
Protoss_Robotics_Facility 1 5974
Protoss_Zealot 1 6655
Protoss_Shuttle 1 6967
Protoss_Robotics_Support_Bay 1 6721
Protoss_Reaver 1 8018
Protoss_Observatory 1 9089
Protoss_Observer 2 10385
10884
