Protoss_Gateway 2 6755
Protoss_Assimilator 1 2853
Protoss_Cybernetics_Core 1 3808
Protoss_Zealot 1 3752
Protoss_Dragoon 4 9992
Protoss_Citadel_of_Adun 1 5997
Protoss_Robotics_Facility 1 6872
Protoss_Templar_Archives 1 6981
Protoss_Shuttle 2 10795
Protoss_Dark_Templar 2 7938
Protoss_Observatory 1 8360
Protoss_Nexus 1 10105
Protoss_Observer 2 9658
Protoss_Robotics_Support_Bay 1 10389
10795
