Protoss_Gateway 2 9239
Protoss_Assimilator 1 2953
Protoss_Zealot 2 4136
Protoss_Cybernetics_Core 1 4691
Protoss_Dragoon 8 10444
Protoss_Robotics_Facility 1 6209
Protoss_Observatory 1 6766
Protoss_Observer 2 8048
Protoss_Nexus 2 11025
11025
