Protoss_Assimilator 2 3202
Protoss_Gateway 1 3109
Protoss_Cybernetics_Core 1 4178
Protoss_Zealot 3 10502
Protoss_Dragoon 5 8626
Protoss_Robotics_Facility 1 6907
Protoss_Observatory 1 7447
Protoss_Observer 1 8148
Protoss_Nexus 1 9499
Protoss_Shuttle 1 9155
Protoss_Robotics_Support_Bay 1 9018
Protoss_Reaver 1 10238
10502
