Protoss_Gateway 3 8379
Protoss_Assimilator 1 2930
Protoss_Cybernetics_Core 1 3749
Protoss_Zealot 1 3690
Protoss_Dragoon 12 10208
Protoss_Nexus 1 7949
Protoss_Robotics_Facility 1 7994
Protoss_Observatory 1 8667
Protoss_Observer 3 10591
10591
