Protoss_Gateway 2 6042
Protoss_Assimilator 1 2919
Protoss_Cybernetics_Core 1 3965
Protoss_Dragoon 10 10440
Protoss_Nexus 1 7720
Protoss_Robotics_Facility 1 7976
Protoss_Shuttle 1 8971
Protoss_Robotics_Support_Bay 1 8953
Protoss_Reaver 1 10158
Protoss_Observatory 1 9625
10440
