Protoss_Gateway 3 9200
Protoss_Assimilator 1 3169
Protoss_Cybernetics_Core 1 4198
Protoss_Robotics_Facility 1 5535
Protoss_Dragoon 9 10314
Protoss_Shuttle 2 7663
Protoss_Nexus 1 9105
Protoss_Observatory 1 8305
Protoss_Observer 1 10206
10314
