Protoss_Gateway 3 9071
Protoss_Assimilator 2 9317
Protoss_Cybernetics_Core 1 3689
Protoss_Dragoon 10 10068
Protoss_Nexus 1 7491
Protoss_Robotics_Facility 1 7237
Protoss_Observatory 1 7806
Protoss_Observer 2 9090
Protoss_Citadel_of_Adun 1 10527
10527
