Protoss_Gateway 2 4213
Protoss_Assimilator 2 8574
Protoss_Cybernetics_Core 1 3737
Protoss_Dragoon 4 6020
Protoss_Nexus 1 8467
Protoss_Citadel_of_Adun 1 7683
Protoss_Robotics_Facility 1 8625
Protoss_Templar_Archives 1 8691
Protoss_Shuttle 1 9735
Protoss_Dark_Templar 4 10438
Protoss_Stargate 1 10415
10438
