Protoss_Gateway 2 6680
Protoss_Assimilator 2 9749
Protoss_Cybernetics_Core 1 3851
Protoss_Dragoon 12 10214
Protoss_Nexus 1 8451
Protoss_Robotics_Facility 1 8758
Protoss_Observatory 1 9347
Protoss_Observer 1 10032
Protoss_Citadel_of_Adun 1 10829
10829
