Protoss_Gateway 2 4310
Protoss_Assimilator 1 2967
Protoss_Cybernetics_Core 1 3887
Protoss_Dragoon 6 8306
Protoss_Nexus 2 11767
Protoss_Robotics_Facility 1 7685
Protoss_Shuttle 1 8673
Protoss_Robotics_Support_Bay 1 8685
Protoss_Reaver 1 9904
Protoss_Observatory 1 9695
Protoss_Zealot 2 10010
Protoss_Observer 1 10508
11767
