Protoss_Nexus 1 4504
Protoss_Gateway 2 8948
Protoss_Assimilator 2 8820
Protoss_Cybernetics_Core 1 5118
Protoss_Zealot 1 4904
Protoss_Dragoon 8 10728
Protoss_Robotics_Facility 1 9625
Protoss_Observatory 1 10173
10728
