Protoss_Gateway 3 8377
Protoss_Assimilator 2 10480
Protoss_Cybernetics_Core 1 3905
Protoss_Dragoon 10 10484
Protoss_Nexus 2 10699
Protoss_Robotics_Facility 1 8087
Protoss_Observatory 1 8731
Protoss_Observer 2 10235
Protoss_Citadel_of_Adun 1 10378
10699
