Protoss_Nexus 1 4442
Protoss_Gateway 2 5149
Protoss_Assimilator 1 3960
Protoss_Cybernetics_Core 1 5101
Protoss_Zealot 1 5258
Protoss_Dragoon 8 9978
Protoss_Robotics_Facility 1 8585
Protoss_Shuttle 1 9597
Protoss_Robotics_Support_Bay 1 9209
Protoss_Reaver 1 10648
10648
