Protoss_Nexus 1 4430
Protoss_Gateway 2 5239
Protoss_Assimilator 1 3940
Protoss_Cybernetics_Core 1 4951
Protoss_Zealot 2 9888
Protoss_Dragoon 10 10044
Protoss_Robotics_Facility 1 8011
Protoss_Shuttle 1 9067
Protoss_Robotics_Support_Bay 1 8759
Protoss_Reaver 1 10118
Protoss_Observatory 1 9854
10118
