Protoss_Assimilator 1 2286
Protoss_Gateway 3 10617
Protoss_Cybernetics_Core 1 4019
Protoss_Dragoon 6 10692
Protoss_Citadel_of_Adun 1 5813
Protoss_Robotics_Facility 1 6797
Protoss_Templar_Archives 1 7171
Protoss_Shuttle 1 7955
Protoss_Dark_Templar 4 9188
Protoss_Nexus 1 9924
10692
