Protoss_Gateway 1 3044
Protoss_Assimilator 1 3230
Protoss_Cybernetics_Core 1 4296
Protoss_Dragoon 5 9248
Protoss_Robotics_Facility 1 7222
Protoss_Shuttle 1 8217
Protoss_Robotics_Support_Bay 1 7796
Protoss_Zealot 2 9850
Protoss_Reaver 1 9268
Protoss_Observatory 1 9654
9850
