Protoss_Gateway 3 10896
Protoss_Assimilator 1 3220
Protoss_Cybernetics_Core 1 3964
Protoss_Dragoon 3 6648
Protoss_Citadel_of_Adun 2 6454
Protoss_Templar_Archives 1 7522
Protoss_Dark_Templar 6 10238
Protoss_Nexus 1 10870
10896
