Protoss_Gateway 5 10405
Protoss_Assimilator 1 2766
Protoss_Cybernetics_Core 1 3709
Protoss_Zealot 1 3560
Protoss_Dragoon 10 10742
Protoss_Nexus 2 9542
Protoss_Robotics_Facility 1 10073
10742
