Protoss_Nexus 2 11221
Protoss_Gateway 3 8452
Protoss_Assimilator 2 7544
Protoss_Zealot 1 4608
Protoss_Cybernetics_Core 1 5059
Protoss_Dragoon 13 10366
Protoss_Robotics_Facility 1 9683
11221
