Protoss_Nexus 1 4405
Protoss_Gateway 2 5159
Protoss_Assimilator 2 7566
Protoss_Cybernetics_Core 1 4963
Protoss_Zealot 2 10486
Protoss_Dragoon 11 10648
Protoss_Stargate 2 9574
Protoss_Fleet_Beacon 1 9205
Protoss_Carrier 1 11607
11607
