Protoss_Gateway 3 8603
Protoss_Assimilator 2 9189
Protoss_Cybernetics_Core 1 3894
Protoss_Dragoon 4 8474
Protoss_Robotics_Facility 1 6469
Protoss_Nexus 2 10963
Protoss_Observatory 1 7007
Protoss_Observer 3 9160
Protoss_Citadel_of_Adun 1 9092
Protoss_Stargate 1 10667
Protoss_Templar_Archives 1 10542
10963
