Protoss_Gateway 2 8323
Protoss_Assimilator 2 8782
Protoss_Cybernetics_Core 1 4441
Protoss_Zealot 1 4240
Protoss_Dragoon 9 10200
Protoss_Nexus 1 7923
Protoss_Robotics_Facility 1 8395
Protoss_Observatory 1 9143
Protoss_Shuttle 1 9887
Protoss_Robotics_Support_Bay 1 9571
Protoss_Citadel_of_Adun 1 10595
Protoss_Observer 1 10490
10595
