Protoss_Gateway 3 10100
Protoss_Assimilator 1 2820
Protoss_Cybernetics_Core 1 3785
Protoss_Dragoon 10 10734
Protoss_Nexus 1 8515
Protoss_Robotics_Facility 1 9195
Protoss_Shuttle 1 10291
Protoss_Robotics_Support_Bay 1 10326
10734
