Protoss_Gateway 1 2719
Protoss_Assimilator 1 2932
Protoss_Cybernetics_Core 1 3736
Protoss_Dragoon 9 10684
Protoss_Robotics_Facility 1 6811
Protoss_Shuttle 1 7853
Protoss_Robotics_Support_Bay 1 7459
Protoss_Reaver 1 8928
Protoss_Observatory 1 8921
Protoss_Nexus 2 11689
Protoss_Observer 2 10582
11689
