Protoss_Gateway 2 6634
Protoss_Assimilator 1 2759
Protoss_Cybernetics_Core 1 3707
Protoss_Dragoon 7 10654
Protoss_Citadel_of_Adun 1 5881
Protoss_Robotics_Facility 1 6434
Protoss_Templar_Archives 1 6935
Protoss_Shuttle 1 7521
Protoss_Dark_Templar 3 8520
Protoss_Nexus 1 10003
Protoss_Observatory 1 9793
10654
