Protoss_Gateway 6 10292
Protoss_Assimilator 1 3244
Protoss_Cybernetics_Core 1 3873
Protoss_Dragoon 8 10718
Protoss_Nexus 2 8253
Protoss_Robotics_Facility 1 8695
Protoss_Observatory 1 9541
Protoss_Observer 1 10222
10718
