Protoss_Nexus 2 10795
Protoss_Gateway 4 10394
Protoss_Assimilator 1 3875
Protoss_Cybernetics_Core 1 4887
Protoss_Zealot 3 9822
Protoss_Dragoon 12 10706
Protoss_Robotics_Facility 1 8473
Protoss_Observatory 1 9099
Protoss_Observer 2 10566
10795
