Protoss_Gateway 2 4350
Protoss_Assimilator 2 10397
Protoss_Cybernetics_Core 1 3793
Protoss_Dragoon 10 9628
Protoss_Nexus 1 8783
Protoss_Robotics_Facility 1 9091
Protoss_Observatory 1 9671
Protoss_Shuttle 1 10163
Protoss_Robotics_Support_Bay 1 10433
10433
