Protoss_Gateway 2 8616
Protoss_Assimilator 2 9123
Protoss_Cybernetics_Core 1 3809
Protoss_Zealot 1 3850
Protoss_Dragoon 10 10520
Protoss_Nexus 1 8056
Protoss_Robotics_Facility 1 8639
Protoss_Citadel_of_Adun 1 8867
Protoss_Observatory 1 9199
Protoss_Observer 1 9898
Protoss_Templar_Archives 1 10323
10520
