Protoss_Gateway 1 2735
Protoss_Assimilator 1 2817
Protoss_Cybernetics_Core 1 3734
Protoss_Dragoon 5 10108
Protoss_Robotics_Facility 1 6468
Protoss_Shuttle 1 7455
Protoss_Observatory 1 7079
Protoss_Nexus 2 11395
Protoss_Robotics_Support_Bay 1 7853
Protoss_Observer 3 10410
Protoss_Zealot 2 9118
Protoss_Reaver 1 9204
11395
