Protoss_Gateway 2 8883
Protoss_Zealot 6 7117
Protoss_Nexus 2 11611
Protoss_Assimilator 2 8713
Protoss_Cybernetics_Core 1 6761
Protoss_Forge 1 7107
Protoss_Citadel_of_Adun 1 7892
Protoss_Dragoon 2 9058
Protoss_Templar_Archives 1 8987
Protoss_Photon_Cannon 1 9508
Protoss_Dark_Templar 3 10730
Protoss_Stargate 1 10395
11611
