Protoss_Nexus 2 8695
Protoss_Gateway 3 10726
Protoss_Assimilator 2 8720
Protoss_Cybernetics_Core 1 5021
Protoss_Dragoon 10 9968
Protoss_Robotics_Facility 1 8797
Protoss_Citadel_of_Adun 1 8860
Protoss_Shuttle 1 10003
Protoss_Observatory 1 10175
10726
