Protoss_Nexus 1 4593
Protoss_Gateway 2 5270
Protoss_Assimilator 1 4133
Protoss_Cybernetics_Core 1 5153
Protoss_Zealot 2 9434
Protoss_Dragoon 8 10246
Protoss_Robotics_Facility 1 7781
Protoss_Observatory 1 8549
Protoss_Observer 2 10076
10246
