Protoss_Nexus 2 9013
Protoss_Gateway 4 9365
Protoss_Assimilator 1 4009
Protoss_Cybernetics_Core 1 5046
Protoss_Zealot 1 5236
Protoss_Dragoon 10 10438
Protoss_Robotics_Facility 1 8729
Protoss_Observatory 1 9311
Protoss_Observer 1 10142
10438
