Protoss_Nexus 1 4511
Protoss_Gateway 3 8855
Protoss_Assimilator 2 6841
Protoss_Cybernetics_Core 1 5079
Protoss_Dragoon 5 10668
Protoss_Citadel_of_Adun 1 7231
Protoss_Forge 1 7461
Protoss_Templar_Archives 1 8300
Protoss_Robotics_Facility 1 8701
Protoss_Photon_Cannon 2 8777
Protoss_Shuttle 1 9689
Protoss_Stargate 1 9895
Protoss_Dark_Templar 3 9752
Protoss_Observatory 1 9979
10668
