Protoss_Gateway 4 10270
Protoss_Assimilator 1 2922
Protoss_Cybernetics_Core 1 3832
Protoss_Dragoon 6 10206
Protoss_Citadel_of_Adun 1 5948
Protoss_Templar_Archives 1 6977
Protoss_Nexus 1 8421
Protoss_Dark_Templar 1 7824
Protoss_Robotics_Facility 1 8418
Protoss_Observatory 1 9438
Protoss_Observer 1 10319
10319
