Protoss_Gateway 4 10647
Protoss_Assimilator 1 2965
Protoss_Cybernetics_Core 1 3862
Protoss_Zealot 1 3726
Protoss_Dragoon 5 7858
Protoss_Nexus 2 10465
Protoss_Citadel_of_Adun 1 8255
Protoss_Templar_Archives 1 9239
Protoss_Dark_Templar 2 10078
Protoss_Robotics_Facility 1 10609
10647
