Protoss_Gateway 2 5491
Protoss_Assimilator 1 3160
Protoss_Cybernetics_Core 1 4146
Protoss_Dragoon 9 10168
Protoss_Robotics_Facility 1 8165
Protoss_Observatory 1 8756
Protoss_Observer 1 9513
Protoss_Citadel_of_Adun 1 10479
Protoss_Shuttle 1 10632
Protoss_Zealot 2 10388
10632
