Protoss_Assimilator 2 3276
Protoss_Gateway 2 10177
Protoss_Cybernetics_Core 1 4473
Protoss_Zealot 1 4496
Protoss_Dragoon 4 9602
Protoss_Robotics_Facility 1 6287
Protoss_Shuttle 1 7285
Protoss_Robotics_Support_Bay 1 7453
Protoss_Reaver 1 8582
Protoss_Observatory 1 8387
Protoss_Observer 1 9186
Protoss_Nexus 1 10405
10405
