Protoss_Gateway 2 8070
Protoss_Assimilator 2 8964
Protoss_Cybernetics_Core 1 3843
Protoss_Zealot 1 4230
Protoss_Nexus 1 6528
Protoss_Dragoon 7 10378
Protoss_Citadel_of_Adun 1 7847
Protoss_Templar_Archives 1 8996
Protoss_Stargate 1 9346
Protoss_Arbiter_Tribunal 1 10335
Protoss_Dark_Templar 1 10368
10378
