Protoss_Gateway 1 2759
Protoss_Assimilator 1 3028
Protoss_Cybernetics_Core 1 3831
Protoss_Zealot 2 7430
Protoss_Dragoon 6 10268
Protoss_Robotics_Facility 1 5603
Protoss_Shuttle 2 10273
Protoss_Robotics_Support_Bay 1 6531
Protoss_Reaver 1 7836
Protoss_Observatory 1 7783
Protoss_Observer 2 9104
Protoss_Nexus 1 10171
10273
