Protoss_Gateway 2 9176
Protoss_Assimilator 1 2851
Protoss_Cybernetics_Core 1 3779
Protoss_Zealot 1 3806
Protoss_Dragoon 9 10652
Protoss_Robotics_Facility 2 10604
Protoss_Robotics_Support_Bay 1 6889
Protoss_Shuttle 1 7545
Protoss_Reaver 1 8956
Protoss_Nexus 1 10713
10713
