Protoss_Gateway 4 9630
Protoss_Assimilator 1 2812
Protoss_Cybernetics_Core 1 3817
Protoss_Dragoon 8 10546
Protoss_Robotics_Facility 1 7028
Protoss_Observatory 1 7596
Protoss_Nexus 1 9324
Protoss_Observer 2 9494
10546
