Protoss_Gateway 2 7319
Protoss_Assimilator 2 9898
Protoss_Cybernetics_Core 1 3949
Protoss_Dragoon 10 10606
Protoss_Nexus 1 7731
Protoss_Robotics_Facility 1 8441
Protoss_Shuttle 1 9429
Protoss_Observatory 1 9275
Protoss_Zealot 2 10344
Protoss_Robotics_Support_Bay 1 9732
Protoss_Observer 1 10164
10606
