Protoss_Nexus 1 4289
Protoss_Gateway 2 4565
Protoss_Assimilator 2 7806
Protoss_Zealot 3 5396
Protoss_Cybernetics_Core 1 5111
Protoss_Dragoon 10 10588
Protoss_Citadel_of_Adun 1 8120
Protoss_Templar_Archives 1 9121
Protoss_Stargate 1 9356
Protoss_Robotics_Facility 1 10449
Protoss_Arbiter_Tribunal 1 10379
10588
