Protoss_Gateway 3 6981
Protoss_Assimilator 1 2829
Protoss_Cybernetics_Core 1 3841
Protoss_Dragoon 11 10292
Protoss_Robotics_Facility 1 6495
Protoss_Observatory 1 7060
Protoss_Observer 1 7736
Protoss_Shuttle 1 8827
Protoss_Robotics_Support_Bay 1 8659
Protoss_Zealot 3 9540
Protoss_Reaver 1 9902
10292
