Protoss_Gateway 1 2823
Protoss_Assimilator 1 2916
Protoss_Cybernetics_Core 1 3873
Protoss_Dragoon 6 9198
Protoss_Robotics_Facility 1 6615
Protoss_Observatory 1 7353
Protoss_Nexus 2 9091
Protoss_Observer 3 10436
Protoss_Shuttle 1 9833
Protoss_Robotics_Support_Bay 1 9417
Protoss_Zealot 2 10542
10542
