Protoss_Gateway 3 8830
Protoss_Assimilator 1 3184
Protoss_Cybernetics_Core 1 3983
Protoss_Dragoon 13 10653
Protoss_Robotics_Facility 1 5823
Protoss_Observatory 1 6431
Protoss_Observer 2 7755
10653
