Protoss_Gateway 3 8781
Protoss_Assimilator 2 9459
Protoss_Cybernetics_Core 1 3809
Protoss_Zealot 3 10550
Protoss_Dragoon 7 10418
Protoss_Nexus 1 7817
Protoss_Robotics_Facility 1 8088
Protoss_Observatory 1 8677
Protoss_Citadel_of_Adun 1 9365
Protoss_Observer 2 9984
Protoss_Templar_Archives 1 10359
Protoss_Stargate 1 10590
10590
