Protoss_Assimilator 1 2426
Protoss_Gateway 4 10578
Protoss_Cybernetics_Core 1 4163
Protoss_Dragoon 7 9300
Protoss_Robotics_Facility 1 7102
Protoss_Zealot 1 6736
Protoss_Nexus 2 11024
Protoss_Observatory 1 7989
Protoss_Observer 3 10194
11024
