Protoss_Gateway 2 8107
Protoss_Assimilator 1 2950
Protoss_Cybernetics_Core 1 3816
Protoss_Dragoon 11 10508
Protoss_Nexus 1 8268
Protoss_Robotics_Facility 1 8132
Protoss_Observatory 1 8754
Protoss_Observer 2 10044
10508
