Protoss_Gateway 2 5529
Protoss_Assimilator 1 2920
Protoss_Cybernetics_Core 1 3924
Protoss_Dragoon 11 10320
Protoss_Robotics_Facility 1 7845
Protoss_Zealot 2 8466
Protoss_Shuttle 1 8841
Protoss_Robotics_Support_Bay 1 8548
Protoss_Reaver 1 9934
Protoss_Observatory 1 9855
10320
