Protoss_Gateway 2 6882
Protoss_Assimilator 1 2781
Protoss_Cybernetics_Core 1 3720
Protoss_Zealot 1 3772
Protoss_Dragoon 12 10156
Protoss_Robotics_Facility 1 6528
Protoss_Observatory 1 7067
Protoss_Observer 2 8386
Protoss_Nexus 1 9203
Protoss_Shuttle 1 9497
Protoss_Robotics_Support_Bay 1 9256
Protoss_Reaver 1 10756
10756
