Protoss_Gateway 2 9146
Protoss_Assimilator 2 9044
Protoss_Cybernetics_Core 1 3773
Protoss_Zealot 1 3696
Protoss_Dragoon 7 10384
Protoss_Citadel_of_Adun 1 5949
Protoss_Templar_Archives 1 7039
Protoss_Nexus 1 8984
Protoss_Dark_Templar 2 8710
Protoss_Stargate 1 8948
Protoss_Arbiter_Tribunal 1 10072
10384
