Protoss_Gateway 4 9855
Protoss_Assimilator 1 2907
Protoss_Cybernetics_Core 1 3722
Protoss_Dragoon 7 8352
Protoss_Nexus 1 8535
Protoss_Citadel_of_Adun 1 8959
Protoss_Robotics_Facility 1 9804
Protoss_Templar_Archives 1 10255
Protoss_Shuttle 1 10789
10789
