Protoss_Gateway 2 8146
Protoss_Assimilator 2 10276
Protoss_Cybernetics_Core 1 4049
Protoss_Dragoon 6 10170
Protoss_Nexus 1 7513
Protoss_Citadel_of_Adun 1 7344
Protoss_Robotics_Facility 1 8031
Protoss_Templar_Archives 1 8375
Protoss_Shuttle 1 9019
Protoss_Dark_Templar 2 9240
Protoss_Observatory 1 9207
Protoss_Observer 1 10048
10276
