Protoss_Gateway 2 9965
Protoss_Assimilator 1 2870
Protoss_Cybernetics_Core 1 3866
Protoss_Zealot 2 9306
Protoss_Dragoon 7 10058
Protoss_Robotics_Facility 1 6237
Protoss_Robotics_Support_Bay 1 6797
Protoss_Shuttle 1 7583
Protoss_Reaver 2 9743
10058
