Protoss_Gateway 2 9743
Protoss_Assimilator 2 9911
Protoss_Cybernetics_Core 1 3869
Protoss_Dragoon 9 10592
Protoss_Robotics_Facility 1 6539
Protoss_Nexus 1 8429
Protoss_Shuttle 1 8075
Protoss_Robotics_Support_Bay 1 8103
Protoss_Reaver 1 9342
Protoss_Observatory 1 9687
Protoss_Observer 1 10362
10592
