Protoss_Gateway 2 7183
Protoss_Assimilator 1 3198
Protoss_Cybernetics_Core 1 4181
Protoss_Dragoon 8 10328
Protoss_Robotics_Facility 1 6809
Protoss_Shuttle 1 7871
Protoss_Observatory 1 7565
Protoss_Robotics_Support_Bay 1 8176
Protoss_Observer 1 8516
Protoss_Zealot 2 8570
Protoss_Reaver 1 9566
Protoss_Nexus 2 11773
11773
