Protoss_Gateway 3 10713
Protoss_Assimilator 2 10557
Protoss_Cybernetics_Core 1 3794
Protoss_Zealot 1 3706
Protoss_Dragoon 7 9898
Protoss_Nexus 2 10583
Protoss_Robotics_Facility 1 8259
Protoss_Observatory 1 8804
Protoss_Observer 2 10152
10713
