Protoss_Gateway 4 10604
Protoss_Assimilator 1 3065
Protoss_Cybernetics_Core 1 4193
Protoss_Dragoon 4 8958
Protoss_Robotics_Facility 1 6375
Protoss_Robotics_Support_Bay 1 6937
Protoss_Shuttle 1 7392
Protoss_Zealot 2 7830
Protoss_Reaver 1 8443
Protoss_Observatory 1 8109
Protoss_Observer 2 9733
Protoss_Nexus 1 10741
10741
