Protoss_Gateway 2 7388
Protoss_Assimilator 2 9950
Protoss_Cybernetics_Core 1 3971
Protoss_Dragoon 11 10696
Protoss_Nexus 1 7867
Protoss_Robotics_Facility 1 8418
Protoss_Observatory 1 9044
Protoss_Observer 2 10436
Protoss_Citadel_of_Adun 1 10111
10696
