Protoss_Gateway 2 7114
Protoss_Assimilator 1 3050
Protoss_Cybernetics_Core 1 4140
Protoss_Dragoon 7 8573
Protoss_Robotics_Facility 1 6701
Protoss_Observatory 2 8897
Protoss_Robotics_Support_Bay 1 7546
Protoss_Reaver 1 8796
Protoss_Shuttle 1 9887
Protoss_Nexus 1 11425
Protoss_Observer 1 10490
11425
