Protoss_Assimilator 3 3849
Protoss_Gateway 4 9869
Protoss_Cybernetics_Core 1 4521
Protoss_Dragoon 10 10662
Protoss_Nexus 1 9533
Protoss_Robotics_Facility 1 9228
Protoss_Observatory 1 10313
10662
