Protoss_Nexus 2 11176
Protoss_Gateway 4 10563
Protoss_Assimilator 2 7058
Protoss_Cybernetics_Core 1 5055
Protoss_Dragoon 7 10458
Protoss_Robotics_Facility 1 6983
Protoss_Zealot 2 7756
Protoss_Observatory 1 7674
Protoss_Observer 3 10156
11176
