Protoss_Gateway 2 7111
Protoss_Assimilator 1 2952
Protoss_Cybernetics_Core 1 3952
Protoss_Dragoon 7 10260
Protoss_Robotics_Facility 1 6433
Protoss_Citadel_of_Adun 1 6283
Protoss_Templar_Archives 1 7340
Protoss_Shuttle 1 7475
Protoss_Dark_Templar 2 8184
Protoss_Observatory 1 9123
Protoss_Nexus 1 10849
10849
