Protoss_Gateway 2 10223
Protoss_Assimilator 2 9545
Protoss_Cybernetics_Core 1 3871
Protoss_Dragoon 7 9654
Protoss_Robotics_Facility 1 6553
Protoss_Observatory 1 7187
Protoss_Nexus 1 8827
Protoss_Observer 3 9578
Protoss_Citadel_of_Adun 1 9031
Protoss_Templar_Archives 1 10630
10630
