Protoss_Gateway 2 6478
Protoss_Assimilator 2 9770
Protoss_Cybernetics_Core 1 3931
Protoss_Dragoon 7 10386
Protoss_Robotics_Facility 1 6672
Protoss_Nexus 2 10153
Protoss_Observatory 1 7465
Protoss_Observer 2 8748
Protoss_Citadel_of_Adun 1 9967
10386
