Protoss_Gateway 2 9824
Protoss_Assimilator 2 9734
Protoss_Cybernetics_Core 1 3763
Protoss_Zealot 1 3752
Protoss_Dragoon 6 10214
Protoss_Citadel_of_Adun 1 6242
Protoss_Templar_Archives 1 7327
Protoss_Nexus 1 9225
Protoss_Dark_Templar 1 8208
Protoss_Robotics_Facility 1 9659
Protoss_Shuttle 1 10895
10895
