Protoss_Gateway 2 6828
Protoss_Assimilator 1 2824
Protoss_Cybernetics_Core 1 3892
Protoss_Dragoon 12 10242
Protoss_Robotics_Facility 1 6856
Protoss_Observatory 1 7750
Protoss_Observer 2 10436
Protoss_Nexus 1 10635
Protoss_Citadel_of_Adun 1 10074
10635
