Protoss_Gateway 2 5589
Protoss_Assimilator 1 2943
Protoss_Cybernetics_Core 1 3731
Protoss_Zealot 2 9876
Protoss_Citadel_of_Adun 1 4845
Protoss_Dragoon 8 9910
Protoss_Templar_Archives 1 5916
Protoss_Dark_Templar 2 6752
Protoss_Nexus 1 10671
Protoss_Robotics_Facility 1 10453
10671
