Protoss_Nexus 2 9411
Protoss_Gateway 6 10359
Protoss_Assimilator 2 9759
Protoss_Cybernetics_Core 1 5157
Protoss_Dragoon 6 9752
Protoss_Citadel_of_Adun 1 6771
Protoss_Templar_Archives 1 8158
Protoss_Dark_Templar 2 9000
10359
