Protoss_Gateway 2 6946
Protoss_Assimilator 1 2914
Protoss_Cybernetics_Core 1 3716
Protoss_Dragoon 7 10508
Protoss_Citadel_of_Adun 1 5824
Protoss_Templar_Archives 1 6855
Protoss_Zealot 1 6982
Protoss_Dark_Templar 3 9710
Protoss_Nexus 1 9477
10508
