Protoss_Gateway 4 10784
Protoss_Assimilator 1 2740
Protoss_Cybernetics_Core 1 3707
Protoss_Dragoon 10 9962
Protoss_Robotics_Facility 1 6259
Protoss_Observatory 1 6823
Protoss_Nexus 2 10372
Protoss_Observer 3 9958
10784
