Protoss_Gateway 2 4314
Protoss_Assimilator 1 2777
Protoss_Cybernetics_Core 1 3743
Protoss_Dragoon 9 9402
Protoss_Robotics_Facility 1 6811
Protoss_Shuttle 1 7807
Protoss_Robotics_Support_Bay 1 7739
Protoss_Zealot 2 8150
Protoss_Reaver 1 8880
Protoss_Nexus 1 11691
11691
