Protoss_Gateway 2 9909
Protoss_Assimilator 1 2955
Protoss_Cybernetics_Core 1 3879
Protoss_Zealot 1 3794
Protoss_Dragoon 7 10296
Protoss_Robotics_Facility 1 6756
Protoss_Shuttle 1 7757
Protoss_Robotics_Support_Bay 1 7507
Protoss_Reaver 1 8808
Protoss_Nexus 1 9923
Protoss_Observatory 1 8705
Protoss_Observer 2 10014
10296
