Protoss_Nexus 1 4717
Protoss_Gateway 2 5577
Protoss_Assimilator 1 4274
Protoss_Cybernetics_Core 1 5270
Protoss_Zealot 1 5420
Protoss_Dragoon 12 10650
Protoss_Robotics_Facility 1 10689
10689
