Protoss_Gateway 3 10634
Protoss_Assimilator 1 2803
Protoss_Cybernetics_Core 1 3799
Protoss_Dragoon 5 7924
Protoss_Robotics_Facility 1 6580
Protoss_Shuttle 1 7929
Protoss_Observatory 1 7811
Protoss_Robotics_Support_Bay 1 7958
Protoss_Observer 1 8638
Protoss_Nexus 1 10139
Protoss_Zealot 1 9110
Protoss_Reaver 1 9840
10634
