Protoss_Gateway 3 8515
Protoss_Assimilator 1 2937
Protoss_Cybernetics_Core 1 3757
Protoss_Zealot 1 3760
Protoss_Dragoon 9 9448
Protoss_Nexus 1 7787
Protoss_Robotics_Facility 1 8039
Protoss_Observatory 1 8629
Protoss_Observer 2 9918
Protoss_Shuttle 1 10819
Protoss_Robotics_Support_Bay 1 10430
10819
