Protoss_Gateway 2 8099
Protoss_Assimilator 1 2950
Protoss_Cybernetics_Core 1 4088
Protoss_Dragoon 8 10675
Protoss_Robotics_Facility 1 6876
Protoss_Robotics_Support_Bay 1 7452
Protoss_Shuttle 1 8357
Protoss_Observatory 1 8597
Protoss_Reaver 1 9481
Protoss_Observer 1 10085
10675
