Protoss_Nexus 1 4461
Protoss_Gateway 3 7722
Protoss_Assimilator 2 8631
Protoss_Cybernetics_Core 1 4949
Protoss_Zealot 3 9560
Protoss_Dragoon 12 10312
Protoss_Robotics_Facility 1 7949
Protoss_Shuttle 1 9355
Protoss_Robotics_Support_Bay 1 9667
Protoss_Reaver 1 10816
10816
