Protoss_Gateway 2 7157
Protoss_Assimilator 2 10105
Protoss_Cybernetics_Core 1 4023
Protoss_Dragoon 9 10438
Protoss_Nexus 1 7503
Protoss_Robotics_Facility 1 7845
Protoss_Shuttle 1 8841
Protoss_Robotics_Support_Bay 1 9092
Protoss_Zealot 2 9600
Protoss_Reaver 1 10312
Protoss_Observatory 1 10273
10438
