Protoss_Gateway 2 9656
Protoss_Assimilator 1 2880
Protoss_Cybernetics_Core 1 3889
Protoss_Dragoon 8 10034
Protoss_Robotics_Facility 1 6798
Protoss_Observatory 1 7356
Protoss_Observer 3 10288
Protoss_Nexus 1 9590
10288
