Protoss_Gateway 3 10891
Protoss_Zealot 2 4122
Protoss_Assimilator 2 9916
Protoss_Cybernetics_Core 1 4899
Protoss_Dragoon 8 10510
Protoss_Nexus 2 10899
Protoss_Robotics_Facility 1 8346
Protoss_Observatory 1 9008
Protoss_Observer 2 10550
Protoss_Citadel_of_Adun 1 10353
10899
