Protoss_Gateway 2 9240
Protoss_Assimilator 2 8848
Protoss_Zealot 1 3718
Protoss_Cybernetics_Core 1 4705
Protoss_Dragoon 6 10140
Protoss_Robotics_Facility 1 7001
Protoss_Nexus 1 8540
Protoss_Observatory 1 7832
Protoss_Observer 3 10502
Protoss_Citadel_of_Adun 1 9048
Protoss_Templar_Archives 1 10380
10502
