Protoss_Gateway 4 10662
Protoss_Assimilator 1 2934
Protoss_Cybernetics_Core 1 3741
Protoss_Dragoon 9 10124
Protoss_Nexus 2 10822
Protoss_Robotics_Facility 1 7733
Protoss_Observatory 1 8390
Protoss_Observer 3 10286
10822
