Protoss_Gateway 2 7149
Protoss_Assimilator 1 3065
Protoss_Cybernetics_Core 1 3937
Protoss_Dragoon 12 10482
Protoss_Robotics_Facility 1 7000
Protoss_Observatory 1 7757
Protoss_Observer 1 8468
Protoss_Shuttle 1 9629
Protoss_Robotics_Support_Bay 1 9265
Protoss_Nexus 1 11648
11648
