Protoss_Gateway 7 10693
Protoss_Zealot 4 8552
Protoss_Nexus 2 10159
Protoss_Assimilator 2 7620
Protoss_Cybernetics_Core 1 5697
Protoss_Dragoon 6 10384
Protoss_Robotics_Facility 1 8770
Protoss_Observatory 2 9357
Protoss_Observer 1 10046
10693
