Protoss_Gateway 2 8219
Protoss_Assimilator 2 9981
Protoss_Cybernetics_Core 1 3812
Protoss_Zealot 1 3878
Protoss_Dragoon 8 10583
Protoss_Nexus 2 10770
Protoss_Robotics_Facility 1 8200
Protoss_Observatory 1 8969
Protoss_Observer 2 10465
10770
