Protoss_Gateway 4 9712
Protoss_Assimilator 2 3192
Protoss_Cybernetics_Core 1 4367
Protoss_Nexus 1 6665
Protoss_Dragoon 11 10726
Protoss_Robotics_Facility 1 8802
Protoss_Observatory 1 9347
Protoss_Observer 1 10028
10726
