Protoss_Gateway 3 9405
Protoss_Assimilator 1 2995
Protoss_Cybernetics_Core 1 4033
Protoss_Zealot 1 3908
Protoss_Dragoon 10 10588
Protoss_Nexus 1 9086
Protoss_Robotics_Facility 1 8702
Protoss_Observatory 1 9321
Protoss_Observer 1 10008
10588
