Protoss_Gateway 4 10013
Protoss_Assimilator 2 9177
Protoss_Cybernetics_Core 1 4141
Protoss_Nexus 2 10207
Protoss_Dragoon 9 10270
Protoss_Robotics_Facility 1 8582
Protoss_Observatory 1 9181
Protoss_Observer 1 9944
10270
