Protoss_Nexus 1 4375
Protoss_Gateway 3 10832
Protoss_Assimilator 1 4002
Protoss_Cybernetics_Core 1 4881
Protoss_Zealot 3 9594
Protoss_Dragoon 8 8992
Protoss_Robotics_Facility 1 10010
10832
