Protoss_Gateway 2 7303
Protoss_Assimilator 1 2964
Protoss_Cybernetics_Core 1 3915
Protoss_Dragoon 10 10366
Protoss_Robotics_Facility 1 6775
Protoss_Observatory 1 7348
Protoss_Nexus 2 10312
Protoss_Observer 3 9690
10366
