Protoss_Nexus 2 10077
Protoss_Gateway 4 10511
Protoss_Assimilator 2 8176
Protoss_Cybernetics_Core 1 5047
Protoss_Zealot 1 5236
Protoss_Dragoon 8 9744
Protoss_Robotics_Facility 1 8480
Protoss_Observatory 1 9238
Protoss_Observer 2 10520
10520
