Protoss_Gateway 2 8376
Protoss_Assimilator 1 2824
Protoss_Cybernetics_Core 1 3755
Protoss_Dragoon 8 10216
Protoss_Robotics_Facility 1 6791
Protoss_Nexus 1 8669
Protoss_Observatory 1 7524
Protoss_Observer 1 8614
Protoss_Robotics_Support_Bay 1 8815
Protoss_Shuttle 1 9644
Protoss_Zealot 2 9384
Protoss_Reaver 1 10710
10710
