Protoss_Gateway 2 10626
Protoss_Assimilator 1 2938
Protoss_Cybernetics_Core 1 3867
Protoss_Dragoon 3 7114
Protoss_Robotics_Facility 1 5545
Protoss_Zealot 4 10114
Protoss_Shuttle 1 6527
Protoss_Robotics_Support_Bay 1 6351
Protoss_Reaver 1 7962
Protoss_Nexus 1 10085
10626
