Protoss_Nexus 1 4377
Protoss_Gateway 2 4974
Protoss_Assimilator 1 4025
Protoss_Cybernetics_Core 1 4903
Protoss_Zealot 1 4914
Protoss_Dragoon 8 9532
Protoss_Robotics_Facility 1 9552
Protoss_Shuttle 1 10533
10533
