Protoss_Gateway 2 8094
Protoss_Assimilator 2 9455
Protoss_Cybernetics_Core 1 3888
Protoss_Dragoon 11 10556
Protoss_Robotics_Facility 1 6676
Protoss_Observatory 1 7222
Protoss_Nexus 1 8656
Protoss_Observer 2 8512
Protoss_Citadel_of_Adun 1 9662
10556
