Protoss_Gateway 3 8949
Protoss_Assimilator 1 3170
Protoss_Cybernetics_Core 1 4352
Protoss_Dragoon 12 10080
Protoss_Nexus 1 9023
Protoss_Shield_Battery 1 9063
Protoss_Robotics_Facility 1 10839
Protoss_Zealot 1 10420
10839
