Protoss_Gateway 2 6882
Protoss_Assimilator 1 2828
Protoss_Cybernetics_Core 1 3908
Protoss_Dragoon 10 10174
Protoss_Robotics_Facility 1 6455
Protoss_Observatory 1 7144
Protoss_Nexus 2 10603
Protoss_Observer 3 9108
10603
