Protoss_Gateway 4 10226
Protoss_Assimilator 2 8141
Protoss_Nexus 1 5555
Protoss_Cybernetics_Core 1 5089
Protoss_Zealot 1 5080
Protoss_Dragoon 10 10298
Protoss_Robotics_Facility 1 7871
Protoss_Observatory 1 8579
Protoss_Observer 3 10510
10510
