Protoss_Gateway 2 4266
Protoss_Assimilator 1 2796
Protoss_Cybernetics_Core 1 3761
Protoss_Dragoon 7 10232
Protoss_Nexus 2 9961
Protoss_Robotics_Facility 1 8657
Protoss_Shuttle 1 9643
Protoss_Robotics_Support_Bay 1 9475
Protoss_Reaver 1 10734
10734
