Protoss_Gateway 3 8394
Protoss_Assimilator 1 2951
Protoss_Cybernetics_Core 1 3871
Protoss_Dragoon 13 10676
Protoss_Nexus 1 7421
Protoss_Robotics_Facility 1 7769
Protoss_Observatory 1 8401
Protoss_Observer 1 9090
10676
