Protoss_Nexus 2 11603
Protoss_Gateway 2 5431
Protoss_Assimilator 2 8177
Protoss_Cybernetics_Core 1 5146
Protoss_Dragoon 10 10114
Protoss_Robotics_Facility 1 8969
Protoss_Zealot 2 8520
Protoss_Citadel_of_Adun 1 9735
Protoss_Observatory 1 9690
11603
