Protoss_Gateway 2 6315
Protoss_Assimilator 3 4762
Protoss_Zealot 5 8900
Protoss_Cybernetics_Core 1 5558
Protoss_Dragoon 5 8326
Protoss_Citadel_of_Adun 1 7298
Protoss_Templar_Archives 1 8965
Protoss_Dark_Templar 4 10714
10714
