Protoss_Gateway 2 8159
Protoss_Assimilator 2 8894
Protoss_Cybernetics_Core 1 3825
Protoss_Dragoon 11 10664
Protoss_Robotics_Facility 1 5471
Protoss_Zealot 1 6022
Protoss_Observatory 1 6143
Protoss_Observer 3 9036
Protoss_Nexus 1 8702
Protoss_Citadel_of_Adun 1 8803
Protoss_Templar_Archives 1 10394
10664
