Protoss_Gateway 1 2895
Protoss_Assimilator 1 3070
Protoss_Cybernetics_Core 1 4047
Protoss_Dragoon 4 10173
Protoss_Robotics_Facility 1 5805
Protoss_Zealot 2 6653
Protoss_Shuttle 1 6812
Protoss_Robotics_Support_Bay 1 6423
Protoss_Reaver 3 10801
Protoss_Shield_Battery 1 8866
10801
