Protoss_Nexus 1 4435
Protoss_Gateway 3 9626
Protoss_Assimilator 2 8884
Protoss_Cybernetics_Core 1 4947
Protoss_Zealot 1 4836
Protoss_Dragoon 13 10530
Protoss_Robotics_Facility 1 8765
Protoss_Observatory 1 9632
Protoss_Observer 1 10392
Protoss_Citadel_of_Adun 1 10775
10775
