Protoss_Nexus 2 9161
Protoss_Gateway 3 10663
Protoss_Assimilator 2 9340
Protoss_Cybernetics_Core 1 4783
Protoss_Zealot 1 4594
Protoss_Dragoon 12 10529
Protoss_Robotics_Facility 1 9225
Protoss_Citadel_of_Adun 1 9568
Protoss_Observatory 1 10161
Protoss_Forge 1 10546
10663
