Protoss_Gateway 1 2751
Protoss_Assimilator 1 2952
Protoss_Cybernetics_Core 1 3869
Protoss_Dragoon 7 10418
Protoss_Robotics_Facility 1 5723
Protoss_Shuttle 1 6703
Protoss_Zealot 1 6860
Protoss_Robotics_Support_Bay 1 6828
Protoss_Reaver 2 10710
Protoss_Observatory 1 7792
Protoss_Observer 2 9200
Protoss_Nexus 1 10285
10710
