Protoss_Gateway 2 8366
Protoss_Assimilator 1 2810
Protoss_Cybernetics_Core 1 3803
Protoss_Zealot 1 3764
Protoss_Dragoon 10 10244
Protoss_Nexus 2 11504
Protoss_Robotics_Facility 1 8213
Protoss_Observatory 1 9869
Protoss_Observer 1 10548
11504
