Protoss_Gateway 2 4996
Protoss_Assimilator 1 2944
Protoss_Zealot 1 3408
Protoss_Cybernetics_Core 1 4513
Protoss_Dragoon 10 9598
Protoss_Nexus 1 7936
Protoss_Robotics_Facility 1 8109
Protoss_Observatory 1 8713
Protoss_Observer 1 9462
Protoss_Robotics_Support_Bay 1 9901
Protoss_Shuttle 1 10363
10363
