Protoss_Gateway 2 6750
Protoss_Assimilator 2 9354
Protoss_Cybernetics_Core 1 3841
Protoss_Dragoon 9 10224
Protoss_Robotics_Facility 1 5607
Protoss_Zealot 1 6046
Protoss_Observatory 1 6173
Protoss_Observer 2 7664
Protoss_Nexus 1 8607
Protoss_Citadel_of_Adun 1 8923
Protoss_Templar_Archives 1 9967
10224
