Protoss_Nexus 2 10667
Protoss_Gateway 4 10121
Protoss_Assimilator 2 8915
Protoss_Cybernetics_Core 1 4962
Protoss_Zealot 3 9554
Protoss_Dragoon 10 10556
Protoss_Robotics_Facility 1 7983
Protoss_Observatory 1 8687
Protoss_Observer 2 9966
10667
