Protoss_Gateway 4 8733
Protoss_Zealot 4 10212
Protoss_Nexus 2 6249
Protoss_Assimilator 2 8805
Protoss_Cybernetics_Core 1 5964
Protoss_Dragoon 8 10356
Protoss_Robotics_Facility 1 8850
Protoss_Observatory 1 10179
10356
