Protoss_Gateway 3 9286
Protoss_Assimilator 2 10218
Protoss_Cybernetics_Core 1 3883
Protoss_Dragoon 12 10622
Protoss_Nexus 1 8201
Protoss_Robotics_Facility 1 8058
Protoss_Observatory 1 8689
Protoss_Observer 2 10016
Protoss_Zealot 1 10040
Protoss_Citadel_of_Adun 1 10605
10622
