Protoss_Gateway 3 7061
Protoss_Zealot 4 5172
Protoss_Assimilator 1 4108
Protoss_Cybernetics_Core 1 5464
Protoss_Dragoon 9 10232
Protoss_Robotics_Facility 1 8677
Protoss_Observatory 1 9217
Protoss_Observer 2 10508
10508
