Protoss_Gateway 3 10594
Protoss_Assimilator 1 2914
Protoss_Cybernetics_Core 1 3915
Protoss_Dragoon 7 10634
Protoss_Robotics_Facility 1 5693
Protoss_Zealot 2 6754
Protoss_Shuttle 1 6715
Protoss_Observatory 1 6706
Protoss_Observer 2 9914
Protoss_Robotics_Support_Bay 1 7575
Protoss_Reaver 1 8724
Protoss_Nexus 1 10661
10661
