Protoss_Gateway 4 10597
Protoss_Assimilator 2 9501
Protoss_Cybernetics_Core 1 3771
Protoss_Zealot 1 3660
Protoss_Citadel_of_Adun 1 4793
Protoss_Dragoon 7 10366
Protoss_Templar_Archives 1 5777
Protoss_Dark_Templar 7 8782
Protoss_Nexus 1 7912
Protoss_Robotics_Facility 1 10164
10597
