Protoss_Gateway 4 10856
Protoss_Assimilator 1 2903
Protoss_Cybernetics_Core 1 3843
Protoss_Dragoon 6 10386
Protoss_Robotics_Facility 1 5538
Protoss_Zealot 4 9369
Protoss_Shuttle 1 6533
Protoss_Robotics_Support_Bay 1 6477
Protoss_Reaver 1 7782
Protoss_Nexus 1 10113
10856
