Protoss_Gateway 3 10415
Protoss_Assimilator 1 2910
Protoss_Cybernetics_Core 1 3786
Protoss_Dragoon 9 10578
Protoss_Robotics_Facility 1 7198
Protoss_Nexus 2 10116
Protoss_Observatory 1 7905
Protoss_Observer 3 9884
Protoss_Shuttle 1 10785
10785
