Protoss_Gateway 2 10578
Protoss_Assimilator 1 3027
Protoss_Cybernetics_Core 1 3945
Protoss_Zealot 1 3778
Protoss_Dragoon 7 10261
Protoss_Robotics_Facility 1 6677
Protoss_Shuttle 1 7685
Protoss_Robotics_Support_Bay 1 7315
Protoss_Reaver 1 8736
Protoss_Observatory 1 8334
Protoss_Observer 2 10111
Protoss_Nexus 1 11544
11544
