Protoss_Gateway 3 9546
Protoss_Assimilator 1 2955
Protoss_Cybernetics_Core 1 3849
Protoss_Dragoon 8 10460
Protoss_Robotics_Facility 1 5779
Protoss_Observatory 1 6472
Protoss_Observer 1 7490
Protoss_Nexus 1 8952
Protoss_Shuttle 1 10489
Protoss_Citadel_of_Adun 1 10518
10518
