Protoss_Gateway 2 6735
Protoss_Assimilator 1 2928
Protoss_Cybernetics_Core 1 3835
Protoss_Dragoon 9 10412
Protoss_Robotics_Facility 1 6522
Protoss_Observatory 1 7077
Protoss_Observer 1 7758
Protoss_Nexus 1 9305
Protoss_Shuttle 1 9241
Protoss_Robotics_Support_Bay 1 9525
Protoss_Reaver 1 10924
10924
