Protoss_Nexus 2 9434
Protoss_Gateway 4 9953
Protoss_Assimilator 2 9055
Protoss_Cybernetics_Core 1 5073
Protoss_Zealot 1 5218
Protoss_Dragoon 10 10730
Protoss_Citadel_of_Adun 1 9239
Protoss_Templar_Archives 1 10323
Protoss_Stargate 1 10521
10730
