Protoss_Nexus 1 4421
Protoss_Gateway 4 9489
Protoss_Assimilator 2 9745
Protoss_Zealot 3 9954
Protoss_Cybernetics_Core 1 5342
Protoss_Dragoon 12 10738
Protoss_Robotics_Facility 1 8957
Protoss_Observatory 1 9717
10738
