Protoss_Gateway 4 10849
Protoss_Assimilator 1 2854
Protoss_Cybernetics_Core 1 3742
Protoss_Dragoon 9 10470
Protoss_Nexus 2 10868
Protoss_Robotics_Facility 1 7482
Protoss_Observatory 1 8095
Protoss_Observer 3 10020
10868
