Protoss_Gateway 2 7083
Protoss_Assimilator 1 2868
Protoss_Cybernetics_Core 1 3978
Protoss_Dragoon 8 9960
Protoss_Citadel_of_Adun 1 5958
Protoss_Templar_Archives 1 6955
Protoss_Zealot 1 7246
Protoss_Dark_Templar 2 8194
Protoss_Nexus 1 9763
Protoss_Robotics_Facility 1 9233
Protoss_Shuttle 1 10239
Protoss_Robotics_Support_Bay 1 9927
Protoss_Observatory 1 10288
10288
