Protoss_Gateway 5 9782
Protoss_Assimilator 1 2938
Protoss_Cybernetics_Core 1 3819
Protoss_Dragoon 10 10590
Protoss_Nexus 1 7401
Protoss_Robotics_Facility 1 7296
Protoss_Shuttle 1 8431
Protoss_Observatory 1 8347
Protoss_Observer 1 9296
Protoss_Robotics_Support_Bay 1 9577
Protoss_Zealot 3 10150
10590
