Protoss_Gateway 1 2777
Protoss_Assimilator 1 2965
Protoss_Cybernetics_Core 1 3845
Protoss_Dragoon 6 9334
Protoss_Robotics_Facility 1 5544
Protoss_Zealot 1 6072
Protoss_Shuttle 1 6623
Protoss_Robotics_Support_Bay 1 6569
Protoss_Reaver 1 7696
Protoss_Observatory 1 7960
Protoss_Observer 1 8696
Protoss_Nexus 1 11116
11116
