Protoss_Gateway 2 8348
Protoss_Assimilator 1 2858
Protoss_Cybernetics_Core 1 3756
Protoss_Zealot 3 9954
Protoss_Dragoon 9 10728
Protoss_Nexus 1 7892
Protoss_Robotics_Facility 1 8153
Protoss_Shuttle 1 9135
Protoss_Robotics_Support_Bay 1 8797
Protoss_Reaver 1 10186
Protoss_Observatory 1 9770
10728
