Protoss_Gateway 5 10866
Protoss_Assimilator 1 2945
Protoss_Cybernetics_Core 1 3747
Protoss_Dragoon 9 10528
Protoss_Robotics_Facility 1 5511
Protoss_Zealot 1 5963
Protoss_Nexus 2 10529
Protoss_Observatory 1 7145
Protoss_Observer 4 9652
Protoss_Citadel_of_Adun 1 10134
10866
