Protoss_Gateway 2 10315
Protoss_Assimilator 1 2907
Protoss_Cybernetics_Core 1 3825
Protoss_Dragoon 6 10040
Protoss_Robotics_Facility 1 5475
Protoss_Zealot 2 6730
Protoss_Shuttle 1 6463
Protoss_Robotics_Support_Bay 1 6407
Protoss_Reaver 1 7702
Protoss_Nexus 1 9902
10315
