Protoss_Gateway 1 2816
Protoss_Assimilator 1 2824
Protoss_Cybernetics_Core 1 3826
Protoss_Dragoon 7 10076
Protoss_Robotics_Facility 1 5555
Protoss_Shuttle 1 6537
Protoss_Robotics_Support_Bay 1 6722
Protoss_Reaver 1 7910
Protoss_Observatory 1 8507
Protoss_Nexus 1 10949
Protoss_Observer 1 9862
10949
