Protoss_Gateway 3 8467
Protoss_Assimilator 1 2795
Protoss_Cybernetics_Core 1 3787
Protoss_Zealot 1 3756
Protoss_Dragoon 8 10502
Protoss_Robotics_Facility 1 6865
Protoss_Nexus 2 11043
Protoss_Observatory 1 7447
Protoss_Observer 3 9440
11043
