Protoss_Gateway 1 2757
Protoss_Assimilator 2 8146
Protoss_Cybernetics_Core 1 3843
Protoss_Zealot 1 3856
Protoss_Dragoon 4 9660
Protoss_Citadel_of_Adun 1 5125
Protoss_Templar_Archives 1 6115
Protoss_Dark_Templar 3 10598
Protoss_Nexus 1 8460
Protoss_Stargate 1 8432
Protoss_Arbiter_Tribunal 1 9823
10598
