Protoss_Gateway 2 4423
Protoss_Assimilator 2 9333
Protoss_Cybernetics_Core 1 3971
Protoss_Dragoon 10 10026
Protoss_Nexus 1 8981
Protoss_Robotics_Facility 1 9679
Protoss_Observatory 1 10287
10287
