Protoss_Gateway 2 9003
Protoss_Assimilator 2 9344
Protoss_Cybernetics_Core 1 3721
Protoss_Zealot 1 3692
Protoss_Dragoon 9 10672
Protoss_Citadel_of_Adun 1 6149
Protoss_Templar_Archives 1 7166
Protoss_Dark_Templar 1 8040
Protoss_Nexus 1 9721
Protoss_Robotics_Facility 1 9132
Protoss_Observatory 1 9818
Protoss_Observer 1 10528
10672
