Protoss_Gateway 3 8504
Protoss_Assimilator 2 10005
Protoss_Cybernetics_Core 1 3736
Protoss_Zealot 1 3692
Protoss_Dragoon 10 10666
Protoss_Robotics_Facility 1 6560
Protoss_Observatory 1 7114
Protoss_Nexus 1 8472
Protoss_Observer 4 10135
Protoss_Citadel_of_Adun 1 10214
10666
