Protoss_Gateway 2 4594
Protoss_Assimilator 2 9636
Protoss_Cybernetics_Core 1 4065
Protoss_Dragoon 8 10136
Protoss_Nexus 1 9125
Protoss_Robotics_Facility 1 8985
Protoss_Observatory 1 9793
Protoss_Citadel_of_Adun 1 10581
Protoss_Observer 1 10510
10581
