Protoss_Assimilator 3 7996
Protoss_Gateway 3 10050
Protoss_Nexus 1 5623
Protoss_Zealot 7 8596
Protoss_Cybernetics_Core 1 5986
Protoss_Dragoon 3 10528
Protoss_Robotics_Facility 2 9617
Protoss_Shuttle 1 10111
Protoss_Robotics_Support_Bay 1 9768
Protoss_Reaver 1 10992
10992
