Protoss_Gateway 2 8250
Protoss_Assimilator 1 2873
Protoss_Cybernetics_Core 1 3901
Protoss_Zealot 1 4080
Protoss_Dragoon 9 10622
Protoss_Nexus 1 8001
Protoss_Robotics_Facility 1 8117
Protoss_Observatory 1 8756
Protoss_Shuttle 1 9551
Protoss_Robotics_Support_Bay 1 9982
Protoss_Observer 1 10154
10622
