Protoss_Gateway 3 9901
Protoss_Assimilator 2 9885
Protoss_Cybernetics_Core 1 3784
Protoss_Dragoon 11 10046
Protoss_Robotics_Facility 1 6733
Protoss_Observatory 1 7343
Protoss_Observer 2 10200
Protoss_Nexus 1 9597
Protoss_Citadel_of_Adun 1 10281
10281
