Protoss_Assimilator 3 3979
Protoss_Gateway 2 5265
Protoss_Zealot 2 5140
Protoss_Cybernetics_Core 1 4835
Protoss_Dragoon 8 10482
Protoss_Nexus 1 8793
Protoss_Robotics_Facility 1 10652
10652
