Protoss_Gateway 3 10409
Protoss_Assimilator 1 3145
Protoss_Cybernetics_Core 1 4174
Protoss_Dragoon 8 9628
Protoss_Nexus 1 9720
Protoss_Robotics_Facility 1 9825
Protoss_Zealot 2 10323
10409
