Protoss_Gateway 2 8542
Protoss_Assimilator 1 3176
Protoss_Zealot 1 3594
Protoss_Cybernetics_Core 1 4485
Protoss_Dragoon 7 9686
Protoss_Nexus 1 7839
Protoss_Robotics_Facility 1 8364
Protoss_Forge 1 8948
Protoss_Observatory 1 9283
Protoss_Citadel_of_Adun 1 10779
10779
