Protoss_Gateway 2 6984
Protoss_Assimilator 1 2986
Protoss_Cybernetics_Core 1 3933
Protoss_Dragoon 9 10322
Protoss_Robotics_Facility 1 5688
Protoss_Zealot 1 6264
Protoss_Observatory 1 6303
Protoss_Observer 3 9960
Protoss_Nexus 1 10448
Protoss_Citadel_of_Adun 1 10161
10448
