Protoss_Gateway 3 10754
Protoss_Zealot 1 3406
Protoss_Assimilator 1 3730
Protoss_Cybernetics_Core 1 4887
Protoss_Dragoon 7 9978
Protoss_Nexus 2 10277
Protoss_Robotics_Facility 1 9161
Protoss_Observatory 1 9926
10754
