Protoss_Gateway 1 2742
Protoss_Assimilator 1 2843
Protoss_Cybernetics_Core 1 3807
Protoss_Zealot 1 3794
Protoss_Dragoon 8 10516
Protoss_Robotics_Facility 1 6914
Protoss_Shuttle 1 8195
Protoss_Robotics_Support_Bay 1 8364
Protoss_Nexus 1 10302
Protoss_Reaver 1 9580
Protoss_Observatory 1 9097
Protoss_Observer 1 10184
10516
