Protoss_Gateway 2 6883
Protoss_Assimilator 1 2974
Protoss_Cybernetics_Core 1 3829
Protoss_Dragoon 12 10468
Protoss_Robotics_Facility 1 6777
Protoss_Observatory 1 7430
Protoss_Nexus 1 9574
Protoss_Observer 3 10120
10468
