Protoss_Gateway 4 10347
Protoss_Assimilator 1 2724
Protoss_Zealot 2 4444
Protoss_Cybernetics_Core 1 4533
Protoss_Dragoon 10 9980
Protoss_Nexus 2 11369
Protoss_Robotics_Facility 1 7535
Protoss_Observatory 1 8317
Protoss_Observer 3 10450
Protoss_Citadel_of_Adun 1 10223
11369
