Protoss_Gateway 4 10075
Protoss_Assimilator 1 2916
Protoss_Cybernetics_Core 1 3788
Protoss_Dragoon 8 10336
Protoss_Nexus 2 8905
Protoss_Robotics_Facility 1 8601
Protoss_Citadel_of_Adun 1 9287
Protoss_Observatory 1 9340
Protoss_Observer 1 10222
Protoss_Templar_Archives 1 10552
Protoss_Stargate 1 10971
10971
