Protoss_Gateway 2 6881
Protoss_Assimilator 1 2871
Protoss_Zealot 3 4734
Protoss_Cybernetics_Core 1 4685
Protoss_Dragoon 10 10370
Protoss_Robotics_Facility 1 7049
Protoss_Observatory 1 7750
Protoss_Observer 1 8840
Protoss_Nexus 1 10098
Protoss_Citadel_of_Adun 1 9729
10370
