Protoss_Gateway 4 9990
Protoss_Assimilator 1 2889
Protoss_Cybernetics_Core 1 4018
Protoss_Dragoon 7 10534
Protoss_Nexus 2 8703
Protoss_Robotics_Facility 1 9169
Protoss_Observatory 1 9715
10534
