Protoss_Gateway 3 9266
Protoss_Assimilator 1 2783
Protoss_Cybernetics_Core 1 3709
Protoss_Dragoon 11 10546
Protoss_Robotics_Facility 1 6377
Protoss_Observatory 1 7181
Protoss_Nexus 1 9135
Protoss_Observer 3 9156
Protoss_Citadel_of_Adun 1 9399
10546
