Protoss_Gateway 2 6123
Protoss_Assimilator 1 3076
Protoss_Cybernetics_Core 1 3961
Protoss_Dragoon 13 10200
Protoss_Robotics_Facility 1 8021
Protoss_Shuttle 1 9003
Protoss_Robotics_Support_Bay 1 9191
10200
