Protoss_Nexus 1 4419
Protoss_Gateway 2 5053
Protoss_Assimilator 2 9300
Protoss_Cybernetics_Core 1 4865
Protoss_Zealot 2 6633
Protoss_Dragoon 10 10298
Protoss_Robotics_Facility 1 9194
Protoss_Observatory 1 9814
Protoss_Citadel_of_Adun 1 10317
Protoss_Observer 1 10546
10546
