Protoss_Gateway 2 8133
Protoss_Assimilator 2 9082
Protoss_Cybernetics_Core 1 3802
Protoss_Dragoon 9 10250
Protoss_Robotics_Facility 1 5479
Protoss_Zealot 1 5988
Protoss_Observatory 1 6128
Protoss_Observer 2 7582
Protoss_Nexus 1 8492
Protoss_Citadel_of_Adun 1 8617
Protoss_Templar_Archives 1 9921
Protoss_Shuttle 1 10653
10653
