Protoss_Gateway 3 8676
Protoss_Assimilator 2 9681
Protoss_Cybernetics_Core 1 3915
Protoss_Dragoon 11 10668
Protoss_Nexus 1 7705
Protoss_Robotics_Facility 1 8389
Protoss_Observatory 1 8965
Protoss_Citadel_of_Adun 1 9705
Protoss_Observer 1 10220
Protoss_Templar_Archives 1 10739
10739
