Protoss_Gateway 2 8659
Protoss_Assimilator 2 10443
Protoss_Cybernetics_Core 1 3851
Protoss_Dragoon 9 10692
Protoss_Robotics_Facility 1 5610
Protoss_Zealot 1 6068
Protoss_Observatory 1 6309
Protoss_Observer 3 9152
Protoss_Nexus 2 10510
Protoss_Citadel_of_Adun 1 10309
10692
