Protoss_Gateway 3 6884
Protoss_Assimilator 1 2956
Protoss_Cybernetics_Core 1 3776
Protoss_Dragoon 8 8896
Protoss_Zealot 2 7768
Protoss_Robotics_Facility 1 5970
Protoss_Observatory 1 6643
Protoss_Observer 1 7648
Protoss_Nexus 2 11233
11233
