Protoss_Gateway 2 6546
Protoss_Assimilator 1 3116
Protoss_Cybernetics_Core 1 4147
Protoss_Zealot 1 3998
Protoss_Dragoon 12 10524
Protoss_Robotics_Facility 1 8086
Protoss_Shuttle 1 9077
Protoss_Robotics_Support_Bay 1 8839
Protoss_Reaver 1 10230
10524
