Protoss_Gateway 5 10679
Protoss_Assimilator 1 2912
Protoss_Cybernetics_Core 1 3908
Protoss_Dragoon 7 10652
Protoss_Robotics_Facility 1 5668
Protoss_Zealot 4 9540
Protoss_Observatory 1 6333
Protoss_Observer 2 7628
Protoss_Nexus 1 9160
Protoss_Shuttle 1 9769
Protoss_Citadel_of_Adun 1 10058
10679
