Protoss_Gateway 1 2733
Protoss_Assimilator 1 2828
Protoss_Cybernetics_Core 1 3798
Protoss_Zealot 1 3658
Protoss_Dragoon 8 10008
Protoss_Robotics_Facility 1 7107
Protoss_Shuttle 1 8203
Protoss_Robotics_Support_Bay 1 7810
Protoss_Reaver 1 9254
Protoss_Nexus 1 11404
Protoss_Observatory 1 10224
11404
