Protoss_Gateway 3 9009
Protoss_Assimilator 2 9668
Protoss_Cybernetics_Core 1 3808
Protoss_Dragoon 10 10394
Protoss_Nexus 1 7591
Protoss_Robotics_Facility 1 8316
Protoss_Zealot 1 8980
Protoss_Citadel_of_Adun 1 9694
Protoss_Observatory 1 9301
Protoss_Observer 1 9982
Protoss_Templar_Archives 1 10867
10867
