Protoss_Gateway 2 7484
Protoss_Assimilator 2 10136
Protoss_Cybernetics_Core 1 3873
Protoss_Dragoon 9 10556
Protoss_Robotics_Facility 1 5611
Protoss_Observatory 1 6417
Protoss_Zealot 1 6890
Protoss_Observer 2 7700
Protoss_Nexus 2 10828
Protoss_Citadel_of_Adun 1 8874
Protoss_Templar_Archives 1 10129
10828
