Protoss_Gateway 4 10096
Protoss_Assimilator 2 10211
Protoss_Cybernetics_Core 1 4165
Protoss_Zealot 1 4218
Protoss_Dragoon 7 10598
Protoss_Citadel_of_Adun 1 5961
Protoss_Templar_Archives 1 6973
Protoss_Nexus 2 8649
Protoss_Dark_Templar 2 8706
Protoss_Robotics_Facility 1 9039
Protoss_Observatory 1 9825
Protoss_Observer 1 10506
10598
