Protoss_Gateway 3 9034
Protoss_Assimilator 1 3057
Protoss_Cybernetics_Core 1 3833
Protoss_Zealot 1 3988
Protoss_Dragoon 11 10726
Protoss_Robotics_Facility 1 5882
Protoss_Observatory 1 6643
Protoss_Observer 1 7394
Protoss_Nexus 2 10449
10726
