Protoss_Nexus 1 4473
Protoss_Gateway 2 4958
Protoss_Assimilator 2 10502
Protoss_Cybernetics_Core 1 5035
Protoss_Zealot 4 8330
Protoss_Dragoon 9 10692
Protoss_Robotics_Facility 1 10669
10692
