Protoss_Gateway 3 7544
Protoss_Assimilator 1 2778
Protoss_Cybernetics_Core 1 3741
Protoss_Dragoon 13 10406
Protoss_Robotics_Facility 1 6909
Protoss_Zealot 3 9642
Protoss_Observatory 1 7541
Protoss_Shuttle 1 8421
Protoss_Observer 1 9024
10406
