Protoss_Nexus 1 4376
Protoss_Gateway 2 5038
Protoss_Assimilator 2 9326
Protoss_Cybernetics_Core 1 4783
Protoss_Zealot 1 5066
Protoss_Dragoon 12 10300
Protoss_Robotics_Facility 1 8118
Protoss_Observatory 1 8776
Protoss_Observer 2 10282
10300
