Protoss_Gateway 2 7161
Protoss_Assimilator 2 9585
Protoss_Cybernetics_Core 1 3849
Protoss_Dragoon 7 10538
Protoss_Robotics_Facility 1 5511
Protoss_Zealot 2 10432
Protoss_Observatory 1 6169
Protoss_Observer 2 7512
Protoss_Nexus 1 9292
Protoss_Citadel_of_Adun 1 8817
Protoss_Templar_Archives 1 9905
Protoss_Shuttle 1 10417
Protoss_Stargate 1 10576
10576
