Protoss_Nexus 2 8286
Protoss_Gateway 2 8621
Protoss_Assimilator 2 9420
Protoss_Zealot 2 5518
Protoss_Cybernetics_Core 1 5144
Protoss_Dragoon 7 10488
Protoss_Robotics_Facility 1 9137
Protoss_Citadel_of_Adun 1 9299
Protoss_Observatory 1 9757
Protoss_Templar_Archives 1 10338
Protoss_Shuttle 1 10441
10488
