Protoss_Nexus 1 4533
Protoss_Gateway 3 10478
Protoss_Assimilator 1 4156
Protoss_Cybernetics_Core 1 5089
Protoss_Zealot 1 4994
Protoss_Dragoon 7 9470
Protoss_Robotics_Facility 1 8714
Protoss_Shuttle 1 9733
Protoss_Robotics_Support_Bay 1 9692
Protoss_Reaver 1 10916
10916
