Protoss_Gateway 3 10573
Protoss_Assimilator 1 2961
Protoss_Cybernetics_Core 1 3881
Protoss_Dragoon 7 10680
Protoss_Robotics_Facility 1 5521
Protoss_Shuttle 1 6675
Protoss_Zealot 2 7450
Protoss_Robotics_Support_Bay 1 6927
Protoss_Reaver 1 8134
Protoss_Nexus 1 9802
Protoss_Observatory 1 9066
Protoss_Observer 1 9774
Protoss_Citadel_of_Adun 1 10880
10880
