Protoss_Gateway 4 9320
Protoss_Assimilator 1 2890
Protoss_Cybernetics_Core 1 3862
Protoss_Dragoon 10 10114
Protoss_Robotics_Facility 1 5604
Protoss_Zealot 1 6050
Protoss_Observatory 1 6272
Protoss_Observer 2 7568
Protoss_Nexus 1 8871
Protoss_Shuttle 1 10743
10743
