Protoss_Gateway 2 6777
Protoss_Assimilator 3 10556
Protoss_Zealot 2 6612
Protoss_Nexus 1 6743
Protoss_Cybernetics_Core 1 6219
Protoss_Dragoon 9 10476
Protoss_Robotics_Facility 1 10860
10860
