Protoss_Gateway 2 10215
Protoss_Assimilator 1 2891
Protoss_Cybernetics_Core 1 3804
Protoss_Dragoon 6 9992
Protoss_Robotics_Facility 1 5519
Protoss_Zealot 1 6034
Protoss_Shuttle 1 6625
Protoss_Robotics_Support_Bay 1 6839
Protoss_Reaver 1 7966
Protoss_Observatory 1 7936
Protoss_Observer 2 9978
Protoss_Nexus 1 10294
Protoss_Citadel_of_Adun 1 10587
10587
