Protoss_Gateway 2 6071
Protoss_Assimilator 1 3128
Protoss_Zealot 2 4292
Protoss_Cybernetics_Core 1 4421
Protoss_Dragoon 10 9936
Protoss_Nexus 2 11546
Protoss_Robotics_Facility 1 9821
11546
