Protoss_Gateway 2 8014
Protoss_Assimilator 1 2942
Protoss_Cybernetics_Core 1 3884
Protoss_Zealot 1 3738
Protoss_Dragoon 10 10370
Protoss_Nexus 1 8317
Protoss_Robotics_Facility 1 8718
Protoss_Observatory 1 9989
10370
