Protoss_Gateway 4 10519
Protoss_Assimilator 1 2821
Protoss_Zealot 1 3458
Protoss_Cybernetics_Core 1 4545
Protoss_Dragoon 9 10600
Protoss_Nexus 2 9307
Protoss_Robotics_Facility 1 9027
Protoss_Observatory 1 9675
Protoss_Observer 1 10520
10600
