Protoss_Gateway 4 9651
Protoss_Assimilator 2 9879
Protoss_Cybernetics_Core 1 3755
Protoss_Zealot 1 3642
Protoss_Dragoon 11 10704
Protoss_Nexus 1 7762
Protoss_Robotics_Facility 1 8055
Protoss_Observatory 1 8727
Protoss_Observer 2 10398
10704
