Protoss_Gateway 2 8642
Protoss_Assimilator 1 2781
Protoss_Cybernetics_Core 1 3739
Protoss_Dragoon 9 10498
Protoss_Zealot 1 5334
Protoss_Robotics_Facility 1 6065
Protoss_Observatory 1 6661
Protoss_Observer 3 8820
Protoss_Nexus 1 8729
10498
