Protoss_Nexus 1 4365
Protoss_Gateway 4 10733
Protoss_Assimilator 2 6943
Protoss_Cybernetics_Core 1 5042
Protoss_Zealot 1 5108
Protoss_Dragoon 7 10720
Protoss_Citadel_of_Adun 1 7712
Protoss_Robotics_Facility 1 8408
Protoss_Templar_Archives 1 8697
Protoss_Shuttle 2 9681
Protoss_Observatory 1 9186
Protoss_Dark_Templar 2 9622
Protoss_Forge 1 10185
Protoss_Observer 1 10284
10733
