Protoss_Assimilator 2 8724
Protoss_Gateway 2 7857
Protoss_Cybernetics_Core 1 4169
Protoss_Zealot 1 4158
Protoss_Dragoon 6 10604
Protoss_Nexus 1 7828
Protoss_Citadel_of_Adun 1 7361
Protoss_Robotics_Facility 1 8573
Protoss_Templar_Archives 1 8483
Protoss_Shuttle 1 9561
Protoss_Dark_Templar 2 9594
Protoss_Observatory 2 9911
Protoss_Stargate 1 10463
Protoss_Observer 1 10164
10604
