Protoss_Gateway 3 8499
Protoss_Assimilator 2 9002
Protoss_Cybernetics_Core 1 3831
Protoss_Dragoon 10 10382
Protoss_Nexus 1 7618
Protoss_Robotics_Facility 1 8288
Protoss_Observatory 1 8923
Protoss_Citadel_of_Adun 1 9396
Protoss_Observer 1 9696
Protoss_Templar_Archives 1 10615
Protoss_Zealot 1 10382
10615
