Protoss_Assimilator 2 10410
Protoss_Gateway 4 10318
Protoss_Cybernetics_Core 1 4159
Protoss_Zealot 1 4150
Protoss_Dragoon 6 10406
Protoss_Citadel_of_Adun 1 5853
Protoss_Robotics_Facility 1 6656
Protoss_Templar_Archives 1 6845
Protoss_Shuttle 1 7645
Protoss_Dark_Templar 4 8464
Protoss_Nexus 1 9781
Protoss_Observatory 1 8723
Protoss_Observer 1 9592
10410
