Protoss_Gateway 4 9501
Protoss_Assimilator 1 2986
Protoss_Cybernetics_Core 1 3789
Protoss_Zealot 1 3682
Protoss_Dragoon 11 10450
Protoss_Nexus 1 7844
Protoss_Robotics_Facility 1 8147
Protoss_Observatory 1 8843
Protoss_Observer 2 10552
Protoss_Citadel_of_Adun 1 10852
10852
