Protoss_Gateway 4 10373
Protoss_Assimilator 2 8717
Protoss_Cybernetics_Core 1 3845
Protoss_Dragoon 8 10356
Protoss_Nexus 1 7886
Protoss_Robotics_Facility 1 7476
Protoss_Observatory 1 8021
Protoss_Citadel_of_Adun 1 8841
Protoss_Observer 2 10090
Protoss_Stargate 1 9988
Protoss_Templar_Archives 1 10055
10373
