Protoss_Gateway 2 6813
Protoss_Assimilator 1 3000
Protoss_Cybernetics_Core 1 4072
Protoss_Robotics_Facility 1 5427
Protoss_Dragoon 7 10133
Protoss_Observatory 1 6051
Protoss_Observer 2 7350
Protoss_Zealot 2 7660
Protoss_Shuttle 1 8507
Protoss_Robotics_Support_Bay 1 9016
10133
