Protoss_Gateway 4 9784
Protoss_Assimilator 1 2820
Protoss_Cybernetics_Core 1 3738
Protoss_Robotics_Facility 1 5212
Protoss_Dragoon 8 10730
Protoss_Observatory 1 5836
Protoss_Observer 4 10218
Protoss_Nexus 2 10199
10730
