Protoss_Gateway 3 8361
Protoss_Assimilator 2 9889
Protoss_Cybernetics_Core 1 3741
Protoss_Dragoon 11 10042
Protoss_Nexus 2 11611
Protoss_Robotics_Facility 1 8095
Protoss_Observatory 1 8781
Protoss_Observer 2 10068
11611
