Protoss_Gateway 2 5679
Protoss_Assimilator 2 9882
Protoss_Cybernetics_Core 1 4073
Protoss_Nexus 1 5903
Protoss_Dragoon 13 10286
Protoss_Robotics_Facility 1 8767
Protoss_Observatory 1 9679
Protoss_Shuttle 1 10201
10286
