Protoss_Gateway 2 5010
Protoss_Assimilator 1 2971
Protoss_Zealot 4 9314
Protoss_Cybernetics_Core 1 4566
Protoss_Dragoon 8 10066
Protoss_Nexus 1 8751
Protoss_Robotics_Facility 1 8633
Protoss_Shuttle 1 9781
Protoss_Robotics_Support_Bay 1 9585
Protoss_Reaver 1 10832
10832
