Protoss_Gateway 2 6838
Protoss_Assimilator 1 2810
Protoss_Zealot 1 3564
Protoss_Cybernetics_Core 1 4477
Protoss_Dragoon 13 10746
Protoss_Robotics_Facility 1 6855
Protoss_Observatory 1 7487
Protoss_Observer 2 9874
Protoss_Nexus 1 11689
11689
