Protoss_Gateway 2 9053
Protoss_Assimilator 1 3018
Protoss_Cybernetics_Core 1 3875
Protoss_Zealot 2 9182
Protoss_Dragoon 6 9984
Protoss_Nexus 1 7243
Protoss_Robotics_Facility 1 7072
Protoss_Shuttle 1 8223
Protoss_Robotics_Support_Bay 1 8227
Protoss_Reaver 1 9352
Protoss_Observatory 1 9163
Protoss_Observer 1 9956
9984
