Protoss_Gateway 4 9164
Protoss_Assimilator 1 2762
Protoss_Cybernetics_Core 1 3695
Protoss_Dragoon 10 10498
Protoss_Robotics_Facility 1 6764
Protoss_Nexus 1 8652
Protoss_Observatory 1 7351
Protoss_Observer 1 8110
Protoss_Shuttle 1 9925
10498
