Protoss_Gateway 1 3015
Protoss_Assimilator 1 3257
Protoss_Zealot 2 5398
Protoss_Cybernetics_Core 1 5095
Protoss_Robotics_Facility 1 6652
Protoss_Dragoon 2 7848
Protoss_Observatory 1 7206
Protoss_Shuttle 1 7667
Protoss_Forge 1 7489
Protoss_Observer 1 8270
Protoss_Robotics_Support_Bay 1 8171
Protoss_Reaver 1 9351
Protoss_Photon_Cannon 1 9487
9487
