Protoss_Gateway 4 9911
Protoss_Assimilator 2 9146
Protoss_Cybernetics_Core 1 3723
Protoss_Zealot 1 3676
Protoss_Citadel_of_Adun 1 4723
Protoss_Dragoon 7 10266
Protoss_Templar_Archives 1 5740
Protoss_Dark_Templar 1 6574
Protoss_Nexus 1 7931
Protoss_Robotics_Facility 1 7913
Protoss_Observatory 1 8532
Protoss_Observer 2 10034
10266
