Protoss_Gateway 5 10350
Protoss_Assimilator 2 8844
Protoss_Cybernetics_Core 1 3833
Protoss_Dragoon 7 9354
Protoss_Nexus 1 7543
Protoss_Robotics_Facility 1 7243
Protoss_Observatory 1 7931
Protoss_Citadel_of_Adun 1 8723
Protoss_Observer 1 8752
Protoss_Templar_Archives 1 10145
Protoss_Zealot 3 10570
10570
