Protoss_Gateway 4 10573
Protoss_Assimilator 1 2939
Protoss_Cybernetics_Core 1 3786
Protoss_Zealot 1 3790
Protoss_Citadel_of_Adun 1 4855
Protoss_Dragoon 7 9876
Protoss_Templar_Archives 1 5901
Protoss_Dark_Templar 2 6744
Protoss_Nexus 1 8493
Protoss_Robotics_Facility 1 9009
Protoss_Observatory 1 9831
10573
