Protoss_Gateway 2 10809
Protoss_Assimilator 1 3083
Protoss_Cybernetics_Core 1 3913
Protoss_Zealot 1 3896
Protoss_Robotics_Facility 1 5570
Protoss_Dragoon 6 10642
Protoss_Shuttle 1 6563
Protoss_Robotics_Support_Bay 1 6470
Protoss_Reaver 1 7916
Protoss_Observatory 1 8022
Protoss_Observer 2 9796
Protoss_Nexus 1 11162
11162
