Protoss_Gateway 2 6374
Protoss_Assimilator 1 2957
Protoss_Zealot 2 4558
Protoss_Cybernetics_Core 1 4505
Protoss_Dragoon 10 9904
Protoss_Nexus 1 8878
Protoss_Robotics_Facility 1 9716
9904
