Protoss_Nexus 1 4411
Protoss_Gateway 2 5163
Protoss_Assimilator 2 8122
Protoss_Cybernetics_Core 1 4989
Protoss_Zealot 1 5120
Protoss_Dragoon 11 9994
Protoss_Robotics_Facility 1 8247
Protoss_Citadel_of_Adun 1 9253
Protoss_Shuttle 1 9305
Protoss_Robotics_Support_Bay 1 9561
Protoss_Templar_Archives 1 10291
Protoss_Stargate 1 10574
Protoss_Reaver 1 10694
10694
