Protoss_Gateway 2 5711
Protoss_Nexus 2 9122
Protoss_Zealot 1 3724
Protoss_Assimilator 2 7647
Protoss_Cybernetics_Core 1 5034
Protoss_Dragoon 7 9543
Protoss_Robotics_Facility 1 8019
Protoss_Observatory 1 8723
Protoss_Observer 2 10028
Protoss_Citadel_of_Adun 1 9925
Protoss_Forge 1 9693
Protoss_Stargate 1 10753
Protoss_Photon_Cannon 1 10743
10753
