Protoss_Gateway 3 7705
Protoss_Assimilator 1 2844
Protoss_Cybernetics_Core 1 3866
Protoss_Zealot 1 3784
Protoss_Dragoon 13 10390
Protoss_Robotics_Facility 1 7316
Protoss_Observatory 1 8133
Protoss_Observer 2 9540
10390
