Protoss_Gateway 2 9451
Protoss_Assimilator 1 3114
Protoss_Cybernetics_Core 1 4128
Protoss_Dragoon 7 10593
Protoss_Robotics_Facility 1 6054
Protoss_Shuttle 2 10887
Protoss_Robotics_Support_Bay 1 6831
Protoss_Reaver 1 8098
Protoss_Observatory 1 7624
Protoss_Observer 1 8973
10887
