Protoss_Nexus 1 4505
Protoss_Gateway 4 10494
Protoss_Assimilator 2 7346
Protoss_Cybernetics_Core 1 4967
Protoss_Zealot 1 5356
Protoss_Dragoon 12 10514
Protoss_Robotics_Facility 1 8717
Protoss_Observatory 1 9487
Protoss_Citadel_of_Adun 1 10035
Protoss_Observer 1 10320
10514
