Protoss_Gateway 3 10774
Protoss_Assimilator 1 2947
Protoss_Cybernetics_Core 1 4153
Protoss_Zealot 2 8208
Protoss_Dragoon 7 10663
Protoss_Robotics_Facility 1 6862
Protoss_Shuttle 1 7877
Protoss_Robotics_Support_Bay 1 7831
Protoss_Reaver 1 9011
Protoss_Observatory 1 9124
Protoss_Observer 1 9813
10774
