Protoss_Assimilator 3 8561
Protoss_Gateway 2 6509
Protoss_Zealot 3 5510
Protoss_Nexus 1 6595
Protoss_Cybernetics_Core 1 6199
Protoss_Dragoon 8 9604
Protoss_Stargate 2 10954
Protoss_Fleet_Beacon 1 10483
10954
