Protoss_Gateway 2 7701
Protoss_Assimilator 1 2959
Protoss_Cybernetics_Core 1 3980
Protoss_Dragoon 10 10623
Protoss_Robotics_Facility 1 6492
Protoss_Observatory 1 7069
Protoss_Observer 3 10195
Protoss_Shuttle 1 9592
Protoss_Nexus 1 11235
11235
