Protoss_Gateway 2 8334
Protoss_Assimilator 1 3030
Protoss_Cybernetics_Core 1 3795
Protoss_Zealot 2 10080
Protoss_Dragoon 9 10676
Protoss_Nexus 1 8039
Protoss_Robotics_Facility 1 8293
Protoss_Shuttle 1 9299
Protoss_Robotics_Support_Bay 1 9226
Protoss_Reaver 1 10490
Protoss_Observatory 1 10281
10676
