Protoss_Gateway 4 10057
Protoss_Assimilator 2 8874
Protoss_Cybernetics_Core 1 3987
Protoss_Dragoon 5 10048
Protoss_Nexus 1 7778
Protoss_Citadel_of_Adun 1 7082
Protoss_Templar_Archives 1 8138
Protoss_Stargate 1 8549
Protoss_Dark_Templar 1 9110
Protoss_Arbiter_Tribunal 1 9588
10057
