Protoss_Nexus 2 10599
Protoss_Gateway 2 5035
Protoss_Assimilator 1 3962
Protoss_Cybernetics_Core 1 4946
Protoss_Zealot 2 9105
Protoss_Dragoon 10 10132
Protoss_Robotics_Facility 1 9504
Protoss_Shuttle 1 10511
10599
