Protoss_Gateway 1 2849
Protoss_Assimilator 1 3127
Protoss_Cybernetics_Core 1 3986
Protoss_Robotics_Facility 1 5442
Protoss_Dragoon 4 10560
Protoss_Shuttle 1 6507
Protoss_Robotics_Support_Bay 1 6676
Protoss_Reaver 2 9686
Protoss_Zealot 3 9808
Protoss_Nexus 1 11681
Protoss_Observatory 1 10339
11681
