Protoss_Gateway 3 9658
Protoss_Assimilator 2 9908
Protoss_Cybernetics_Core 1 3882
Protoss_Dragoon 9 9636
Protoss_Nexus 1 9167
Protoss_Robotics_Facility 1 9167
Protoss_Citadel_of_Adun 1 10122
Protoss_Observatory 1 9853
10122
