Protoss_Gateway 3 7498
Protoss_Assimilator 1 3073
Protoss_Cybernetics_Core 1 3973
Protoss_Nexus 1 6356
Protoss_Dragoon 9 9476
Protoss_Zealot 4 10078
Protoss_Robotics_Facility 1 10376
10376
