Protoss_Gateway 3 10539
Protoss_Assimilator 1 2862
Protoss_Cybernetics_Core 1 4117
Protoss_Dragoon 9 9720
Protoss_Nexus 1 8805
Protoss_Robotics_Facility 1 9296
Protoss_Observatory 1 9902
Protoss_Citadel_of_Adun 1 10823
10823
