Protoss_Gateway 2 5755
Protoss_Assimilator 1 2972
Protoss_Cybernetics_Core 1 3911
Protoss_Dragoon 6 7706
Protoss_Citadel_of_Adun 1 6414
Protoss_Templar_Archives 1 7649
Protoss_Dark_Templar 3 9240
Protoss_Nexus 1 10197
Protoss_Robotics_Facility 1 10697
10697
