Protoss_Gateway 3 6337
Protoss_Assimilator 2 4547
Protoss_Cybernetics_Core 1 3780
Protoss_Dragoon 5 7198
Protoss_Nexus 2 10873
Protoss_Robotics_Facility 1 9029
Protoss_Citadel_of_Adun 1 9406
Protoss_Shuttle 1 10013
Protoss_Robotics_Support_Bay 1 9932
Protoss_Templar_Archives 1 10634
10873
