Protoss_Nexus 1 4349
Protoss_Gateway 2 8125
Protoss_Assimilator 2 6203
Protoss_Cybernetics_Core 1 4883
Protoss_Zealot 2 5700
Protoss_Dragoon 10 10684
Protoss_Citadel_of_Adun 1 7822
Protoss_Robotics_Facility 1 8869
Protoss_Templar_Archives 1 8991
Protoss_Stargate 1 9223
Protoss_Observatory 1 9505
Protoss_Dark_Templar 1 9932
Protoss_Arbiter_Tribunal 1 10253
Protoss_Observer 1 10242
10684
