Protoss_Nexus 2 9695
Protoss_Gateway 3 9146
Protoss_Assimilator 3 6547
Protoss_Cybernetics_Core 1 5019
Protoss_Dragoon 7 10622
Protoss_Citadel_of_Adun 1 6321
Protoss_Robotics_Facility 1 10447
Protoss_Templar_Archives 1 10325
Protoss_Stargate 1 10573
10622
