Protoss_Gateway 2 4480
Protoss_Assimilator 1 2866
Protoss_Cybernetics_Core 1 3835
Protoss_Dragoon 10 9832
Protoss_Robotics_Facility 1 7945
Protoss_Observatory 1 8620
Protoss_Zealot 2 9080
Protoss_Observer 1 9572
Protoss_Nexus 1 11402
Protoss_Robotics_Support_Bay 1 10319
11402
