Protoss_Nexus 1 4439
Protoss_Gateway 5 10075
Protoss_Assimilator 2 5334
Protoss_Cybernetics_Core 1 5107
Protoss_Dragoon 8 10240
Protoss_Robotics_Facility 1 7415
Protoss_Citadel_of_Adun 1 7725
Protoss_Observatory 1 7993
Protoss_Templar_Archives 1 8785
Protoss_Observer 4 10500
Protoss_Stargate 1 9147
Protoss_Dark_Templar 2 9994
10500
