Protoss_Gateway 2 7637
Protoss_Assimilator 1 3070
Protoss_Cybernetics_Core 1 3919
Protoss_Dragoon 10 10478
Protoss_Nexus 2 10865
Protoss_Robotics_Facility 1 7775
Protoss_Observatory 1 8519
Protoss_Observer 2 10544
Protoss_Citadel_of_Adun 1 10806
10865
