Protoss_Gateway 4 10891
Protoss_Assimilator 2 10172
Protoss_Cybernetics_Core 1 3943
Protoss_Dragoon 8 8998
Protoss_Nexus 1 7837
Protoss_Citadel_of_Adun 1 8729
Protoss_Templar_Archives 1 10045
10891
