Protoss_Gateway 1 2927
Protoss_Assimilator 1 3198
Protoss_Cybernetics_Core 1 4094
Protoss_Dragoon 4 10473
Protoss_Robotics_Facility 1 5937
Protoss_Shuttle 1 7622
Protoss_Robotics_Support_Bay 1 7246
Protoss_Nexus 1 8915
Protoss_Reaver 3 10780
10780
