Protoss_Gateway 1 3007
Protoss_Assimilator 1 2955
Protoss_Cybernetics_Core 1 4024
Protoss_Dragoon 6 10076
Protoss_Robotics_Facility 1 6569
Protoss_Zealot 2 7686
Protoss_Shuttle 1 7551
Protoss_Observatory 1 7189
Protoss_Robotics_Support_Bay 1 7878
Protoss_Observer 2 10094
Protoss_Reaver 1 9295
Protoss_Nexus 1 10969
10969
