Protoss_Gateway 2 8767
Protoss_Assimilator 2 9460
Protoss_Cybernetics_Core 1 3867
Protoss_Zealot 1 3726
Protoss_Dragoon 7 10350
Protoss_Citadel_of_Adun 1 6239
Protoss_Templar_Archives 1 7294
Protoss_Dark_Templar 1 8174
Protoss_Nexus 1 9383
Protoss_Stargate 1 9846
10350
