Protoss_Gateway 3 8339
Protoss_Assimilator 1 3093
Protoss_Cybernetics_Core 1 4273
Protoss_Dragoon 10 10198
Protoss_Robotics_Facility 1 7386
Protoss_Nexus 1 8973
Protoss_Observatory 1 7995
Protoss_Observer 2 9330
Protoss_Robotics_Support_Bay 1 9299
Protoss_Zealot 2 10292
Protoss_Reaver 1 10570
10570
