Protoss_Gateway 2 3359
Protoss_Zealot 8 6108
Protoss_Forge 1 4795
Protoss_Photon_Cannon 4 8841
Protoss_Nexus 1 8849
Protoss_Assimilator 1 7968
Protoss_Cybernetics_Core 1 9427
Protoss_Citadel_of_Adun 1 10716
10716
