Protoss_Gateway 3 10734
Protoss_Assimilator 2 8123
Protoss_Cybernetics_Core 1 3903
Protoss_Dragoon 9 10248
Protoss_Nexus 1 8249
Protoss_Citadel_of_Adun 1 8502
Protoss_Robotics_Facility 1 9557
Protoss_Templar_Archives 1 10074
Protoss_Stargate 1 10692
Protoss_Observatory 1 10218
10734
