Protoss_Gateway 2 5897
Protoss_Assimilator 1 3086
Protoss_Cybernetics_Core 1 3875
Protoss_Dragoon 5 8314
Protoss_Nexus 1 8110
Protoss_Zealot 2 7204
Protoss_Robotics_Facility 1 8275
Protoss_Robotics_Support_Bay 1 8844
Protoss_Shuttle 1 9563
Protoss_Observatory 1 9380
Protoss_Reaver 1 10614
10614
