Protoss_Gateway 2 6328
Protoss_Assimilator 1 3358
Protoss_Zealot 3 4962
Protoss_Cybernetics_Core 1 4581
Protoss_Dragoon 10 10438
Protoss_Robotics_Facility 2 8743
Protoss_Nexus 1 8993
Protoss_Observatory 1 9375
Protoss_Observer 1 10102
10438
