Protoss_Gateway 2 6357
Protoss_Assimilator 3 10572
Protoss_Cybernetics_Core 1 4183
Protoss_Dragoon 8 10076
Protoss_Nexus 2 10585
Protoss_Robotics_Facility 1 8824
Protoss_Observatory 1 9455
Protoss_Observer 1 10206
Protoss_Citadel_of_Adun 1 10704
10704
