Protoss_Gateway 3 10635
Protoss_Assimilator 1 2777
Protoss_Cybernetics_Core 1 3730
Protoss_Dragoon 11 10724
Protoss_Nexus 2 9671
Protoss_Robotics_Facility 1 8503
Protoss_Observatory 1 9193
Protoss_Observer 2 10504
10724
