Protoss_Gateway 2 6241
Protoss_Assimilator 2 9750
Protoss_Zealot 1 3527
Protoss_Cybernetics_Core 1 4714
Protoss_Dragoon 9 10243
Protoss_Nexus 1 9099
Protoss_Robotics_Facility 1 8651
Protoss_Stargate 1 9826
Protoss_Observatory 1 9270
Protoss_Observer 2 10562
10562
