Protoss_Gateway 2 7948
Protoss_Assimilator 1 3145
Protoss_Zealot 1 3648
Protoss_Cybernetics_Core 1 4180
Protoss_Dragoon 6 10588
Protoss_Robotics_Facility 1 5932
Protoss_Shuttle 1 6947
Protoss_Robotics_Support_Bay 1 6561
Protoss_Reaver 2 9661
Protoss_Observatory 1 7981
Protoss_Observer 1 10403
10588
