Protoss_Gateway 2 6749
Protoss_Assimilator 1 2930
Protoss_Cybernetics_Core 1 3879
Protoss_Dragoon 6 9103
Protoss_Robotics_Facility 1 5920
Protoss_Zealot 1 6508
Protoss_Shuttle 1 7097
Protoss_Observatory 1 6908
Protoss_Robotics_Support_Bay 1 7337
Protoss_Reaver 2 9846
9846
