Protoss_Gateway 2 9847
Protoss_Assimilator 1 2897
Protoss_Cybernetics_Core 1 3749
Protoss_Dragoon 8 10684
Protoss_Robotics_Facility 1 6065
Protoss_Shuttle 1 7077
Protoss_Robotics_Support_Bay 1 6738
Protoss_Reaver 2 10408
Protoss_Observatory 1 9922
10684
