Protoss_Gateway 1 2715
Protoss_Assimilator 1 2794
Protoss_Cybernetics_Core 1 3741
Protoss_Dragoon 6 10170
Protoss_Robotics_Facility 1 6501
Protoss_Observatory 1 7090
Protoss_Nexus 1 8852
Protoss_Observer 2 8374
Protoss_Robotics_Support_Bay 1 8245
Protoss_Zealot 2 9176
Protoss_Shuttle 1 9289
Protoss_Reaver 1 10340
10340
