Protoss_Gateway 4 10279
Protoss_Assimilator 1 2872
Protoss_Cybernetics_Core 1 3708
Protoss_Nexus 2 10233
Protoss_Dragoon 8 8628
Protoss_Robotics_Facility 1 7962
Protoss_Observatory 1 8710
Protoss_Observer 2 10012
Protoss_Citadel_of_Adun 1 10836
10836
