Protoss_Gateway 6 10781
Protoss_Assimilator 1 2850
Protoss_Cybernetics_Core 1 3931
Protoss_Dragoon 9 10676
Protoss_Nexus 2 8403
Protoss_Robotics_Facility 1 8550
Protoss_Observatory 1 9234
Protoss_Observer 1 9952
Protoss_Citadel_of_Adun 1 10604
10781
