Protoss_Nexus 2 10280
Protoss_Gateway 4 10101
Protoss_Assimilator 1 3894
Protoss_Cybernetics_Core 1 4948
Protoss_Zealot 1 4940
Protoss_Dragoon 9 10360
Protoss_Robotics_Facility 1 7596
Protoss_Observatory 1 8223
Protoss_Observer 3 10282
10360
