Protoss_Gateway 4 10203
Protoss_Assimilator 2 9380
Protoss_Zealot 2 4082
Protoss_Cybernetics_Core 1 4554
Protoss_Dragoon 7 10642
Protoss_Nexus 1 8023
Protoss_Robotics_Facility 1 7789
Protoss_Citadel_of_Adun 1 8305
Protoss_Observatory 1 8364
Protoss_Observer 2 10170
Protoss_Templar_Archives 1 9925
10642
