Protoss_Gateway 2 6953
Protoss_Assimilator 1 3028
Protoss_Cybernetics_Core 1 3961
Protoss_Dragoon 12 10308
Protoss_Robotics_Facility 1 6571
Protoss_Observatory 1 7213
Protoss_Observer 1 8010
Protoss_Nexus 1 10884
10884
