Protoss_Gateway 2 10395
Protoss_Assimilator 1 3071
Protoss_Cybernetics_Core 1 4026
Protoss_Dragoon 2 10068
Protoss_Robotics_Facility 1 5727
Protoss_Shuttle 1 6982
Protoss_Robotics_Support_Bay 1 6607
Protoss_Zealot 2 8033
Protoss_Reaver 2 9516
Protoss_Observatory 1 8088
Protoss_Nexus 1 10020
10395
