Protoss_Gateway 3 9568
Protoss_Assimilator 1 3027
Protoss_Cybernetics_Core 1 3892
Protoss_Dragoon 8 10003
Protoss_Robotics_Facility 1 7482
Protoss_Zealot 4 9189
Protoss_Shuttle 1 8562
Protoss_Observatory 1 8434
Protoss_Observer 3 10369
10369
