Protoss_Gateway 3 10027
Protoss_Assimilator 1 2760
Protoss_Zealot 2 4377
Protoss_Cybernetics_Core 1 4699
Protoss_Dragoon 9 9314
Protoss_Robotics_Facility 1 7861
Protoss_Observatory 1 8416
Protoss_Observer 2 9932
Protoss_Nexus 1 10621
10621
