Protoss_Gateway 4 10591
Protoss_Assimilator 1 2891
Protoss_Cybernetics_Core 1 3807
Protoss_Dragoon 9 9020
Protoss_Nexus 1 7969
Protoss_Robotics_Facility 1 8344
Protoss_Shuttle 1 9347
Protoss_Zealot 2 9957
Protoss_Observatory 1 9709
Protoss_Citadel_of_Adun 1 10784
10784
