Protoss_Gateway 4 10565
Protoss_Assimilator 1 2841
Protoss_Cybernetics_Core 1 3771
Protoss_Dragoon 12 9676
Protoss_Nexus 1 9275
Protoss_Robotics_Facility 1 8875
Protoss_Observatory 1 9475
Protoss_Observer 1 10156
10565
