Protoss_Gateway 3 7439
Protoss_Assimilator 2 8799
Protoss_Cybernetics_Core 1 3859
Protoss_Dragoon 9 10186
Protoss_Nexus 1 7486
Protoss_Robotics_Facility 1 7185
Protoss_Observatory 1 7970
Protoss_Observer 3 10460
Protoss_Citadel_of_Adun 1 9316
Protoss_Templar_Archives 1 10402
Protoss_Stargate 1 10676
10676
