Protoss_Gateway 1 2884
Protoss_Assimilator 1 2928
Protoss_Cybernetics_Core 1 3910
Protoss_Dragoon 7 9760
Protoss_Robotics_Facility 2 7090
Protoss_Shuttle 1 8257
Protoss_Robotics_Support_Bay 1 7989
Protoss_Reaver 2 10360
Protoss_Nexus 1 11603
11603
