Protoss_Gateway 3 6949
Protoss_Assimilator 1 3097
Protoss_Cybernetics_Core 1 3983
Protoss_Dragoon 6 10132
Protoss_Citadel_of_Adun 1 6199
Protoss_Templar_Archives 1 7185
Protoss_Dark_Templar 5 9260
Protoss_Nexus 1 9911
10132
