Protoss_Gateway 3 8791
Protoss_Assimilator 1 2875
Protoss_Cybernetics_Core 1 4048
Protoss_Robotics_Facility 1 5342
Protoss_Dragoon 8 9672
Protoss_Shuttle 1 6352
Protoss_Observatory 1 6234
Protoss_Observer 4 8901
Protoss_Zealot 3 10274
10274
