Protoss_Gateway 2 8430
Protoss_Assimilator 1 2907
Protoss_Cybernetics_Core 1 3869
Protoss_Dragoon 6 10423
Protoss_Robotics_Facility 1 5747
Protoss_Shuttle 1 6737
Protoss_Observatory 1 6394
Protoss_Robotics_Support_Bay 1 6638
Protoss_Observer 1 7340
Protoss_Reaver 2 9606
10423
