Protoss_Gateway 2 4365
Protoss_Assimilator 2 3603
Protoss_Zealot 10 7563
Protoss_Cybernetics_Core 1 8114
Protoss_Robotics_Facility 1 9536
Protoss_Dragoon 4 10153
Protoss_Shuttle 1 10537
10537
