Protoss_Assimilator 1 2231
Protoss_Gateway 2 6490
Protoss_Cybernetics_Core 1 4153
Protoss_Citadel_of_Adun 1 5179
Protoss_Robotics_Facility 1 5909
Protoss_Templar_Archives 1 6186
Protoss_Dragoon 6 10266
Protoss_Shuttle 1 7179
Protoss_Dark_Templar 2 7476
Protoss_Observatory 1 7413
Protoss_Observer 3 10198
Protoss_Nexus 1 11049
11049
