Protoss_Gateway 2 6549
Protoss_Assimilator 2 10024
Protoss_Cybernetics_Core 1 3929
Protoss_Dragoon 10 10254
Protoss_Nexus 1 8383
Protoss_Robotics_Facility 1 8867
Protoss_Zealot 2 9406
Protoss_Observatory 1 9451
Protoss_Shuttle 1 10079
Protoss_Observer 1 10220
10254
