Protoss_Gateway 2 6748
Protoss_Assimilator 1 2999
Protoss_Cybernetics_Core 1 4059
Protoss_Robotics_Facility 1 5395
Protoss_Zealot 3 9308
Protoss_Observatory 1 5946
Protoss_Dragoon 8 10388
Protoss_Observer 4 8758
Protoss_Shuttle 1 9659
Protoss_Nexus 1 11311
11311
