Protoss_Assimilator 3 4060
Protoss_Gateway 2 6744
Protoss_Zealot 1 4093
Protoss_Cybernetics_Core 1 5276
Protoss_Dragoon 10 10543
Protoss_Robotics_Facility 1 8477
Protoss_Shuttle 1 9612
Protoss_Robotics_Support_Bay 1 9441
Protoss_Reaver 1 10663
10663
