Protoss_Gateway 3 10753
Protoss_Assimilator 2 3220
Protoss_Cybernetics_Core 1 4237
Protoss_Dragoon 9 10258
Protoss_Robotics_Facility 1 7312
Protoss_Observatory 1 8153
Protoss_Observer 3 10568
Protoss_Nexus 1 10495
10753
