Protoss_Gateway 3 10636
Protoss_Assimilator 1 2834
Protoss_Cybernetics_Core 1 3979
Protoss_Dragoon 10 10708
Protoss_Robotics_Facility 1 7679
Protoss_Nexus 2 11248
Protoss_Observatory 1 8230
Protoss_Observer 2 9868
11248
