Protoss_Gateway 3 8093
Protoss_Assimilator 1 3165
Protoss_Cybernetics_Core 1 4035
Protoss_Dragoon 11 10443
Protoss_Robotics_Facility 1 6893
Protoss_Observatory 1 7968
Protoss_Observer 2 9485
Protoss_Nexus 1 11131
11131
