Protoss_Gateway 3 7399
Protoss_Assimilator 1 3216
Protoss_Cybernetics_Core 1 4465
Protoss_Dragoon 10 9498
Protoss_Citadel_of_Adun 1 8830
Protoss_Templar_Archives 1 9849
Protoss_Zealot 3 10221
10221
