Protoss_Gateway 3 9545
Protoss_Assimilator 1 2812
Protoss_Cybernetics_Core 1 3844
Protoss_Dragoon 8 10708
Protoss_Robotics_Facility 1 5678
Protoss_Zealot 2 6728
Protoss_Shuttle 1 6667
Protoss_Robotics_Support_Bay 1 6371
Protoss_Reaver 1 7751
Protoss_Observatory 1 7860
Protoss_Observer 1 8898
Protoss_Citadel_of_Adun 1 10556
10708
