Protoss_Gateway 1 3154
Protoss_Assimilator 1 3132
Protoss_Cybernetics_Core 1 4241
Protoss_Dragoon 5 10698
Protoss_Robotics_Facility 1 7037
Protoss_Shuttle 1 8097
Protoss_Zealot 1 7992
Protoss_Robotics_Support_Bay 1 7856
Protoss_Reaver 1 9148
Protoss_Nexus 2 11363
Protoss_Observatory 1 10217
11363
