Protoss_Gateway 2 6268
Protoss_Assimilator 1 2973
Protoss_Cybernetics_Core 1 3893
Protoss_Dragoon 11 10464
Protoss_Nexus 1 6901
Protoss_Robotics_Facility 1 7965
Protoss_Observatory 1 8525
Protoss_Observer 1 9202
10464
