Protoss_Gateway 2 4366
Protoss_Assimilator 2 10493
Protoss_Cybernetics_Core 1 3922
Protoss_Dragoon 12 10248
Protoss_Nexus 1 8640
Protoss_Robotics_Facility 1 8514
Protoss_Observatory 1 9075
Protoss_Observer 2 10485
10493
