Protoss_Gateway 3 10854
Protoss_Assimilator 1 3024
Protoss_Zealot 2 8848
Protoss_Cybernetics_Core 1 5101
Protoss_Dragoon 4 8204
Protoss_Stargate 1 7095
Protoss_Citadel_of_Adun 1 7651
Protoss_Scout 1 8390
Protoss_Templar_Archives 1 8828
Protoss_Dark_Templar 3 10453
Protoss_Nexus 1 11350
11350
