Protoss_Gateway 2 6824
Protoss_Assimilator 2 3406
Protoss_Cybernetics_Core 1 4260
Protoss_Citadel_of_Adun 1 5349
Protoss_Dragoon 2 10638
Protoss_Templar_Archives 1 6437
Protoss_Dark_Templar 5 10238
Protoss_Robotics_Facility 1 8117
Protoss_Zealot 1 7578
Protoss_Nexus 1 10905
Protoss_Shuttle 1 10177
10905
