Protoss_Gateway 3 10014
Protoss_Assimilator 1 2995
Protoss_Cybernetics_Core 1 3859
Protoss_Dragoon 10 9450
Protoss_Nexus 1 9465
Protoss_Robotics_Facility 1 9846
Protoss_Zealot 4 10285
Protoss_Observatory 1 10405
10405
