Protoss_Gateway 5 10874
Protoss_Assimilator 1 3009
Protoss_Cybernetics_Core 1 3964
Protoss_Dragoon 8 10308
Protoss_Nexus 1 9115
Protoss_Robotics_Facility 1 9029
Protoss_Observatory 1 9689
Protoss_Observer 1 10393
10874
