Protoss_Gateway 3 9664
Protoss_Assimilator 1 2990
Protoss_Cybernetics_Core 1 4041
Protoss_Dragoon 11 10153
Protoss_Nexus 1 9440
Protoss_Robotics_Facility 1 9092
Protoss_Observatory 1 9946
10153
