Protoss_Gateway 2 6915
Protoss_Assimilator 1 2956
Protoss_Cybernetics_Core 1 3789
Protoss_Dragoon 8 9463
Protoss_Robotics_Facility 1 6922
Protoss_Observatory 1 7523
Protoss_Observer 3 9950
Protoss_Nexus 2 11555
11555
