Protoss_Gateway 2 5709
Protoss_Assimilator 3 4610
Protoss_Cybernetics_Core 1 4131
Protoss_Dragoon 8 8504
Protoss_Citadel_of_Adun 1 7933
Protoss_Templar_Archives 1 8955
Protoss_Dark_Templar 2 9950
Protoss_Nexus 1 10900
Protoss_Robotics_Facility 1 10895
10900
