Protoss_Gateway 2 7079
Protoss_Assimilator 1 3134
Protoss_Cybernetics_Core 1 3991
Protoss_Dragoon 7 10383
Protoss_Robotics_Facility 1 6753
Protoss_Shuttle 1 7747
Protoss_Robotics_Support_Bay 1 7941
Protoss_Reaver 1 9076
Protoss_Zealot 2 9288
Protoss_Observatory 1 9099
Protoss_Observer 1 9823
10383
