Protoss_Gateway 2 7008
Protoss_Assimilator 1 2941
Protoss_Cybernetics_Core 1 3900
Protoss_Dragoon 11 10725
Protoss_Robotics_Facility 1 6657
Protoss_Observatory 1 7372
Protoss_Observer 2 9263
Protoss_Nexus 1 10856
10856
