Protoss_Gateway 2 6483
Protoss_Assimilator 1 3133
Protoss_Cybernetics_Core 1 4135
Protoss_Dragoon 10 10668
Protoss_Citadel_of_Adun 1 5830
Protoss_Nexus 1 8460
Protoss_Robotics_Facility 1 10789
10789
