Protoss_Gateway 3 9270
Protoss_Assimilator 2 9968
Protoss_Cybernetics_Core 1 4276
Protoss_Dragoon 8 10625
Protoss_Citadel_of_Adun 1 7149
Protoss_Templar_Archives 1 8144
Protoss_Nexus 1 9410
Protoss_Dark_Templar 2 8998
Protoss_Stargate 1 10548
Protoss_Zealot 1 10465
10625
