Protoss_Gateway 2 6849
Protoss_Assimilator 1 2915
Protoss_Cybernetics_Core 1 4064
Protoss_Dragoon 7 9418
Protoss_Robotics_Facility 1 5947
Protoss_Observatory 1 6861
Protoss_Observer 2 10458
Protoss_Nexus 1 10000
10458
