Protoss_Gateway 3 8376
Protoss_Assimilator 1 2916
Protoss_Cybernetics_Core 1 3904
Protoss_Dragoon 11 9530
Protoss_Robotics_Facility 1 6724
Protoss_Observatory 1 7326
Protoss_Observer 1 8068
Protoss_Shuttle 1 10312
Protoss_Zealot 3 10223
10312
