Protoss_Gateway 2 4499
Protoss_Assimilator 1 3095
Protoss_Cybernetics_Core 1 4118
Protoss_Dragoon 10 8840
Protoss_Robotics_Facility 1 7967
Protoss_Observatory 1 8651
Protoss_Shuttle 1 9382
Protoss_Zealot 4 10510
Protoss_Robotics_Support_Bay 1 9717
Protoss_Observer 1 9985
10510
