Protoss_Gateway 2 6647
Protoss_Assimilator 1 3190
Protoss_Cybernetics_Core 1 3874
Protoss_Dragoon 7 10215
Protoss_Robotics_Facility 1 5982
Protoss_Shuttle 1 7192
Protoss_Robotics_Support_Bay 1 7241
Protoss_Zealot 2 7763
Protoss_Reaver 1 8446
Protoss_Observatory 1 8557
Protoss_Observer 1 9248
10215
