Protoss_Gateway 2 10814
Protoss_Assimilator 2 10201
Protoss_Cybernetics_Core 1 3724
Protoss_Dragoon 5 7736
Protoss_Nexus 1 7971
Protoss_Stargate 2 8898
Protoss_Zealot 2 9020
Protoss_Fleet_Beacon 1 9666
Protoss_Carrier 2 11956
11956
