Protoss_Gateway 4 10739
Protoss_Assimilator 1 3062
Protoss_Cybernetics_Core 1 3901
Protoss_Dragoon 9 9303
Protoss_Nexus 2 10968
Protoss_Robotics_Facility 1 9116
Protoss_Observatory 1 9737
Protoss_Observer 1 10573
10968
