Protoss_Gateway 3 8665
Protoss_Assimilator 1 3280
Protoss_Cybernetics_Core 1 4195
Protoss_Dragoon 9 10383
Protoss_Nexus 1 8135
Protoss_Robotics_Facility 1 9746
Protoss_Observatory 1 10388
10388
