Protoss_Gateway 2 7449
Protoss_Assimilator 1 3055
Protoss_Cybernetics_Core 1 3979
Protoss_Dragoon 10 10283
Protoss_Robotics_Facility 1 7114
Protoss_Observatory 1 7744
Protoss_Nexus 1 9995
Protoss_Observer 2 10390
10390
