Protoss_Gateway 2 6794
Protoss_Assimilator 1 2902
Protoss_Cybernetics_Core 1 3986
Protoss_Dragoon 9 9350
Protoss_Robotics_Facility 1 5701
Protoss_Observatory 1 6718
Protoss_Observer 1 7408
Protoss_Nexus 1 10992
Protoss_Stargate 2 10468
10992
