Protoss_Gateway 2 6488
Protoss_Assimilator 1 3035
Protoss_Cybernetics_Core 1 4054
Protoss_Dragoon 10 10235
Protoss_Robotics_Facility 1 5778
Protoss_Observatory 1 6431
Protoss_Observer 2 8863
Protoss_Nexus 1 10001
Protoss_Shuttle 1 10607
10607
