Protoss_Gateway 2 6933
Protoss_Assimilator 1 3246
Protoss_Cybernetics_Core 1 4151
Protoss_Robotics_Facility 1 5548
Protoss_Dragoon 6 9946
Protoss_Observatory 1 6093
Protoss_Observer 1 6920
Protoss_Shuttle 2 8933
Protoss_Nexus 1 11530
11530
