Protoss_Gateway 2 6772
Protoss_Assimilator 1 2870
Protoss_Cybernetics_Core 1 3873
Protoss_Dragoon 7 9058
Protoss_Robotics_Facility 1 6274
Protoss_Observatory 1 6824
Protoss_Observer 2 8948
Protoss_Nexus 1 9579
Protoss_Zealot 4 10262
Protoss_Shuttle 1 10187
10262
