Protoss_Gateway 2 6166
Protoss_Assimilator 1 3054
Protoss_Cybernetics_Core 1 3814
Protoss_Dragoon 8 9623
Protoss_Nexus 1 7997
Protoss_Zealot 5 10225
Protoss_Robotics_Facility 1 8237
Protoss_Observatory 1 9017
10225
