Protoss_Gateway 4 10795
Protoss_Assimilator 1 2905
Protoss_Cybernetics_Core 1 3843
Protoss_Dragoon 12 10535
Protoss_Nexus 1 8001
Protoss_Zealot 1 7848
Protoss_Robotics_Facility 1 9891
10795
