Protoss_Gateway 1 2875
Protoss_Assimilator 1 3108
Protoss_Cybernetics_Core 1 4139
Protoss_Robotics_Facility 1 5594
Protoss_Zealot 1 5123
Protoss_Dragoon 6 10742
Protoss_Robotics_Support_Bay 1 6156
Protoss_Reaver 1 7411
Protoss_Shuttle 2 10882
Protoss_Observatory 1 8613
Protoss_Nexus 1 11460
11460
