Protoss_Gateway 2 6486
Protoss_Assimilator 1 3170
Protoss_Cybernetics_Core 1 4057
Protoss_Dragoon 7 10433
Protoss_Citadel_of_Adun 1 8002
Protoss_Templar_Archives 1 9104
Protoss_Stargate 1 9353
Protoss_Nexus 1 10442
Protoss_Arbiter_Tribunal 1 10501
10501
