Protoss_Gateway 3 10418
Protoss_Assimilator 1 3075
Protoss_Cybernetics_Core 1 4017
Protoss_Dragoon 10 10358
Protoss_Robotics_Facility 1 8218
Protoss_Observatory 1 8963
Protoss_Nexus 1 10425
Protoss_Observer 2 10313
10425
