Protoss_Gateway 2 5357
Protoss_Assimilator 1 3055
Protoss_Zealot 2 4628
Protoss_Cybernetics_Core 1 4724
Protoss_Dragoon 11 9922
Protoss_Robotics_Facility 1 8184
Protoss_Observatory 1 8928
Protoss_Observer 2 10260
Protoss_Nexus 1 11655
11655
