Protoss_Nexus 1 4870
Protoss_Gateway 3 7264
Protoss_Assimilator 1 4687
Protoss_Cybernetics_Core 1 5574
Protoss_Zealot 6 9928
Protoss_Dragoon 7 10093
Protoss_Robotics_Facility 1 9517
Protoss_Observatory 1 10341
10341
