Protoss_Gateway 2 7799
Protoss_Assimilator 1 3165
Protoss_Cybernetics_Core 1 4075
Protoss_Zealot 1 4093
Protoss_Dragoon 9 9938
Protoss_Robotics_Facility 1 7502
Protoss_Observatory 1 8056
Protoss_Observer 2 10233
10233
