Protoss_Gateway 3 9480
Protoss_Assimilator 1 2928
Protoss_Cybernetics_Core 1 4046
Protoss_Robotics_Facility 1 5401
Protoss_Dragoon 9 10572
Protoss_Observatory 1 5961
Protoss_Observer 3 9574
Protoss_Shuttle 1 7595
Protoss_Nexus 1 9745
Protoss_Robotics_Support_Bay 1 10044
10572
