Protoss_Gateway 4 10409
Protoss_Assimilator 2 9912
Protoss_Cybernetics_Core 1 3879
Protoss_Dragoon 5 10510
Protoss_Zealot 1 5315
Protoss_Citadel_of_Adun 1 5811
Protoss_Templar_Archives 1 7064
Protoss_Dark_Templar 5 9758
Protoss_Nexus 1 9215
10510
