Protoss_Gateway 4 10729
Protoss_Assimilator 1 3197
Protoss_Cybernetics_Core 1 3877
Protoss_Dragoon 11 9917
Protoss_Nexus 1 6770
Protoss_Robotics_Facility 1 9764
Protoss_Observatory 1 10395
Protoss_Zealot 1 10593
10729
