Protoss_Gateway 4 10721
Protoss_Assimilator 1 3171
Protoss_Cybernetics_Core 1 4259
Protoss_Dragoon 8 9618
Protoss_Zealot 2 7453
Protoss_Nexus 1 10045
Protoss_Citadel_of_Adun 1 9428
Protoss_Robotics_Facility 1 10457
10721
