Protoss_Gateway 3 9329
Protoss_Assimilator 1 3126
Protoss_Cybernetics_Core 1 4129
Protoss_Dragoon 9 10584
Protoss_Robotics_Facility 1 5967
Protoss_Observatory 1 6573
Protoss_Observer 2 7936
Protoss_Shuttle 1 10001
10584
