Protoss_Gateway 2 8257
Protoss_Assimilator 1 2829
Protoss_Cybernetics_Core 1 3784
Protoss_Dragoon 7 10353
Protoss_Robotics_Facility 1 5773
Protoss_Zealot 2 6973
Protoss_Shuttle 1 6882
Protoss_Robotics_Support_Bay 1 6558
Protoss_Reaver 2 9741
Protoss_Observatory 1 8371
Protoss_Observer 2 10183
10353
