Protoss_Gateway 2 5394
Protoss_Assimilator 1 3120
Protoss_Cybernetics_Core 1 3982
Protoss_Dragoon 8 8658
Protoss_Citadel_of_Adun 2 7842
Protoss_Templar_Archives 1 8874
Protoss_Nexus 1 10463
Protoss_Dark_Templar 2 9793
Protoss_Zealot 2 10493
10493
