Protoss_Gateway 3 8979
Protoss_Assimilator 1 2920
Protoss_Cybernetics_Core 1 3889
Protoss_Dragoon 7 10308
Protoss_Citadel_of_Adun 1 6349
Protoss_Templar_Archives 1 7415
Protoss_Zealot 1 7308
Protoss_Dark_Templar 3 9223
Protoss_Robotics_Facility 1 9142
Protoss_Shuttle 1 10572
10572
