Protoss_Gateway 2 9186
Protoss_Assimilator 1 3072
Protoss_Cybernetics_Core 1 3964
Protoss_Dragoon 4 8833
Protoss_Robotics_Facility 1 5647
Protoss_Zealot 2 8078
Protoss_Shuttle 1 6712
Protoss_Observatory 1 6383
Protoss_Robotics_Support_Bay 1 6931
Protoss_Observer 2 8970
Protoss_Reaver 1 8366
Protoss_Nexus 1 11115
11115
