Protoss_Gateway 3 8785
Protoss_Assimilator 1 3231
Protoss_Cybernetics_Core 1 4353
Protoss_Dragoon 10 10323
Protoss_Nexus 1 7983
Protoss_Robotics_Facility 1 7802
Protoss_Observatory 1 8472
Protoss_Observer 2 9858
Protoss_Citadel_of_Adun 1 10044
10323
