Protoss_Gateway 2 4375
Protoss_Assimilator 1 3044
Protoss_Cybernetics_Core 1 3844
Protoss_Dragoon 7 7613
Protoss_Zealot 3 8303
Protoss_Citadel_of_Adun 1 7149
Protoss_Templar_Archives 1 8219
Protoss_Dark_Templar 2 9148
Protoss_Nexus 1 10890
10890
