Protoss_Gateway 2 4825
Protoss_Assimilator 1 2842
Protoss_Cybernetics_Core 1 3872
Protoss_Dragoon 7 7933
Protoss_Citadel_of_Adun 1 6461
Protoss_Templar_Archives 1 7664
Protoss_Dark_Templar 4 10117
Protoss_Zealot 1 9365
Protoss_Nexus 1 11330
Protoss_Robotics_Facility 1 11112
11330
