Protoss_Gateway 2 5409
Protoss_Assimilator 1 2850
Protoss_Cybernetics_Core 1 3824
Protoss_Dragoon 11 10702
Protoss_Robotics_Facility 1 7682
Protoss_Shuttle 1 8857
Protoss_Nexus 1 10023
Protoss_Robotics_Support_Bay 1 8807
Protoss_Reaver 1 9941
Protoss_Observatory 1 9949
10702
