Protoss_Gateway 2 7950
Protoss_Assimilator 1 3126
Protoss_Cybernetics_Core 1 4143
Protoss_Robotics_Facility 1 5555
Protoss_Dragoon 7 9602
Protoss_Shuttle 1 6541
Protoss_Observatory 1 6296
Protoss_Observer 3 8900
9602
