Protoss_Gateway 2 6647
Protoss_Assimilator 1 3178
Protoss_Cybernetics_Core 1 4007
Protoss_Zealot 1 4043
Protoss_Dragoon 11 9973
Protoss_Robotics_Facility 1 9087
Protoss_Observatory 1 9641
Protoss_Observer 1 10328
10328
