Protoss_Gateway 3 9718
Protoss_Assimilator 1 3150
Protoss_Cybernetics_Core 1 3999
Protoss_Dragoon 10 10695
Protoss_Nexus 1 8385
Protoss_Shield_Battery 1 7904
Protoss_Robotics_Facility 1 9202
Protoss_Observatory 1 9855
Protoss_Observer 1 10573
10695
