Protoss_Gateway 2 6709
Protoss_Assimilator 1 3131
Protoss_Cybernetics_Core 1 4055
Protoss_Dragoon 6 10510
Protoss_Citadel_of_Adun 1 6451
Protoss_Templar_Archives 1 7504
Protoss_Zealot 1 7643
Protoss_Dark_Templar 4 9758
Protoss_Nexus 1 10519
10519
