Protoss_Gateway 3 10435
Protoss_Assimilator 1 3135
Protoss_Zealot 1 3963
Protoss_Cybernetics_Core 1 4344
Protoss_Dragoon 6 10103
Protoss_Robotics_Facility 1 7114
Protoss_Shuttle 1 8217
Protoss_Robotics_Support_Bay 1 8479
Protoss_Nexus 1 10895
Protoss_Reaver 1 10391
Protoss_Observatory 1 10132
10895
