Protoss_Gateway 2 4464
Protoss_Assimilator 1 2985
Protoss_Cybernetics_Core 1 3945
Protoss_Dragoon 3 5718
Protoss_Citadel_of_Adun 1 6433
Protoss_Robotics_Facility 1 7417
Protoss_Templar_Archives 1 7464
Protoss_Shuttle 1 8437
Protoss_Dark_Templar 6 10483
10483
