Protoss_Gateway 5 10379
Protoss_Assimilator 1 3116
Protoss_Cybernetics_Core 1 3960
Protoss_Dragoon 9 10533
Protoss_Nexus 1 8148
Protoss_Zealot 2 10443
Protoss_Robotics_Facility 1 8707
Protoss_Observatory 1 9286
Protoss_Citadel_of_Adun 1 10233
Protoss_Observer 1 10338
10533
