Protoss_Assimilator 1 2664
Protoss_Gateway 2 6943
Protoss_Cybernetics_Core 1 4540
Protoss_Dragoon 4 7692
Protoss_Robotics_Facility 1 6381
Protoss_Observatory 1 7063
Protoss_Zealot 1 7774
Protoss_Observer 3 10530
Protoss_Citadel_of_Adun 1 8183
Protoss_Shuttle 1 8769
Protoss_Templar_Archives 1 9214
Protoss_Forge 1 9114
Protoss_Dark_Templar 2 10090
Protoss_Nexus 1 11575
11575
