Protoss_Assimilator 1 1988
Protoss_Gateway 2 7211
Protoss_Cybernetics_Core 1 4332
Protoss_Dragoon 6 10358
Protoss_Citadel_of_Adun 1 6780
Protoss_Templar_Archives 1 7804
Protoss_Dark_Templar 2 8815
Protoss_Nexus 1 10150
Protoss_Robotics_Facility 1 10153
10358
