Protoss_Gateway 4 10259
Protoss_Assimilator 1 2807
Protoss_Shield_Battery 1 3371
Protoss_Cybernetics_Core 1 3904
Protoss_Dragoon 10 9828
Protoss_Robotics_Facility 1 6488
Protoss_Observatory 1 7145
Protoss_Observer 2 8490
Protoss_Nexus 1 9605
Protoss_Zealot 2 10583
10583
