Protoss_Gateway 4 10074
Protoss_Assimilator 1 3010
Protoss_Cybernetics_Core 1 3934
Protoss_Dragoon 10 9554
Protoss_Nexus 1 9092
Protoss_Robotics_Facility 1 9275
Protoss_Observatory 1 9944
10074
