Protoss_Gateway 2 7094
Protoss_Assimilator 1 2985
Protoss_Zealot 2 4090
Protoss_Cybernetics_Core 1 4022
Protoss_Dragoon 9 10523
Protoss_Citadel_of_Adun 2 7378
Protoss_Templar_Archives 1 8409
Protoss_Dark_Templar 2 9268
Protoss_Nexus 1 10908
10908
