Protoss_Gateway 3 10402
Protoss_Assimilator 1 3047
Protoss_Cybernetics_Core 1 4196
Protoss_Dragoon 12 10548
Protoss_Robotics_Facility 1 6147
Protoss_Observatory 1 6716
Protoss_Observer 2 8025
Protoss_Nexus 1 10225
10548
