Protoss_Gateway 3 10031
Protoss_Assimilator 1 3177
Protoss_Cybernetics_Core 1 4177
Protoss_Dragoon 11 10723
Protoss_Robotics_Facility 1 6078
Protoss_Observatory 1 6896
Protoss_Observer 2 8873
Protoss_Nexus 1 9950
10723
