Protoss_Gateway 2 6459
Protoss_Assimilator 1 3022
Protoss_Cybernetics_Core 1 3980
Protoss_Dragoon 8 10253
Protoss_Citadel_of_Adun 1 6152
Protoss_Templar_Archives 1 7249
Protoss_Zealot 1 7318
Protoss_Dark_Templar 2 8158
Protoss_Nexus 1 9885
Protoss_Robotics_Facility 1 10361
10361
