Protoss_Gateway 2 6623
Protoss_Assimilator 1 2915
Protoss_Cybernetics_Core 1 3874
Protoss_Dragoon 8 10195
Protoss_Citadel_of_Adun 1 6415
Protoss_Templar_Archives 1 7559
Protoss_Zealot 1 7408
Protoss_Dark_Templar 2 8498
Protoss_Nexus 1 10070
Protoss_Stargate 1 10687
10687
