Protoss_Gateway 2 8620
Protoss_Assimilator 2 3273
Protoss_Cybernetics_Core 1 4184
Protoss_Dragoon 5 10488
Protoss_Robotics_Facility 1 5947
Protoss_Shuttle 1 6992
Protoss_Robotics_Support_Bay 1 6774
Protoss_Reaver 1 8043
Protoss_Observatory 1 8119
Protoss_Nexus 1 10680
Protoss_Observer 1 9643
Protoss_Forge 1 9874
10680
