Protoss_Gateway 4 10776
Protoss_Assimilator 1 2917
Protoss_Cybernetics_Core 1 4152
Protoss_Dragoon 10 10284
Protoss_Nexus 1 8833
Protoss_Robotics_Facility 1 9023
Protoss_Observatory 1 9705
Protoss_Observer 1 10464
10776
