Protoss_Assimilator 1 2359
Protoss_Gateway 2 5973
Protoss_Cybernetics_Core 1 3967
Protoss_Dragoon 6 10722
Protoss_Citadel_of_Adun 1 5122
Protoss_Robotics_Facility 1 5868
Protoss_Templar_Archives 1 6314
Protoss_Shuttle 1 6953
Protoss_Dark_Templar 3 7964
Protoss_Observatory 1 7392
Protoss_Observer 1 8354
Protoss_Nexus 1 10417
10722
