Protoss_Gateway 4 10701
Protoss_Assimilator 1 3072
Protoss_Cybernetics_Core 1 4187
Protoss_Dragoon 8 10254
Protoss_Robotics_Facility 1 5813
Protoss_Observatory 1 6963
Protoss_Nexus 2 10413
Protoss_Observer 2 8400
10701
