Protoss_Gateway 2 10500
Protoss_Assimilator 1 3050
Protoss_Cybernetics_Core 1 4043
Protoss_Zealot 2 7288
Protoss_Dragoon 6 10155
Protoss_Robotics_Facility 1 5853
Protoss_Shuttle 1 6972
Protoss_Robotics_Support_Bay 1 6726
Protoss_Reaver 1 8023
Protoss_Observatory 1 7862
Protoss_Observer 2 10273
Protoss_Nexus 1 10765
10765
