Protoss_Gateway 2 6724
Protoss_Assimilator 1 2996
Protoss_Zealot 1 3493
Protoss_Cybernetics_Core 1 4639
Protoss_Citadel_of_Adun 1 5681
Protoss_Dragoon 6 10003
Protoss_Templar_Archives 1 6684
Protoss_Dark_Templar 2 7563
Protoss_Nexus 1 9628
Protoss_Robotics_Facility 1 9191
Protoss_Shuttle 1 10257
Protoss_Robotics_Support_Bay 1 10411
10411
