Protoss_Gateway 2 3499
Protoss_Zealot 6 8208
Protoss_Assimilator 1 4286
Protoss_Cybernetics_Core 1 5111
Protoss_Dragoon 5 8363
Protoss_Citadel_of_Adun 1 7666
Protoss_Templar_Archives 1 8872
Protoss_Dark_Templar 2 9718
Protoss_Robotics_Facility 1 10969
10969
