Protoss_Gateway 2 7500
Protoss_Assimilator 1 2989
Protoss_Cybernetics_Core 1 3749
Protoss_Dragoon 8 10570
Protoss_Robotics_Facility 1 6631
Protoss_Shuttle 1 7637
Protoss_Robotics_Support_Bay 1 7636
Protoss_Reaver 1 8796
Protoss_Observatory 1 8669
Protoss_Nexus 1 10562
Protoss_Observer 1 9543
10570
