Protoss_Gateway 2 4299
Protoss_Assimilator 1 2961
Protoss_Cybernetics_Core 1 3819
Protoss_Dragoon 8 10113
Protoss_Zealot 2 9803
Protoss_Robotics_Facility 1 7442
Protoss_Shuttle 1 8442
Protoss_Nexus 1 9960
Protoss_Robotics_Support_Bay 1 8834
Protoss_Reaver 1 10036
Protoss_Observatory 1 9741
10113
