Protoss_Gateway 2 6532
Protoss_Assimilator 1 3111
Protoss_Cybernetics_Core 1 4123
Protoss_Dragoon 8 10458
Protoss_Robotics_Facility 1 6182
Protoss_Observatory 1 6745
Protoss_Observer 2 8035
Protoss_Nexus 1 10549
Protoss_Citadel_of_Adun 1 10732
10732
