Protoss_Nexus 1 4517
Protoss_Gateway 3 6979
Protoss_Assimilator 1 3986
Protoss_Cybernetics_Core 1 5107
Protoss_Zealot 2 7824
Protoss_Dragoon 9 8904
Protoss_Robotics_Facility 1 8200
Protoss_Observatory 1 9253
Protoss_Observer 1 10294
10294
