Protoss_Gateway 2 10482
Protoss_Assimilator 1 3160
Protoss_Cybernetics_Core 1 4098
Protoss_Dragoon 5 10138
Protoss_Robotics_Facility 1 7182
Protoss_Robotics_Support_Bay 1 7741
Protoss_Shuttle 1 8197
Protoss_Zealot 2 8883
Protoss_Reaver 1 9248
Protoss_Nexus 1 10650
Protoss_Observatory 1 9556
Protoss_Observer 1 10253
10650
