Protoss_Gateway 3 10559
Protoss_Assimilator 1 3322
Protoss_Cybernetics_Core 1 4148
Protoss_Dragoon 7 8840
Protoss_Robotics_Facility 1 6152
Protoss_Observatory 1 7103
Protoss_Observer 2 9443
Protoss_Nexus 1 10356
Protoss_Citadel_of_Adun 1 10030
10559
