Protoss_Gateway 1 2979
Protoss_Assimilator 1 3215
Protoss_Cybernetics_Core 1 4656
Protoss_Zealot 1 4983
Protoss_Robotics_Facility 1 6195
Protoss_Dragoon 7 10377
Protoss_Shuttle 1 7207
Protoss_Robotics_Support_Bay 1 7536
Protoss_Reaver 2 10996
Protoss_Observatory 1 8715
Protoss_Observer 1 9558
10996
