Protoss_Gateway 3 10822
Protoss_Assimilator 1 3110
Protoss_Cybernetics_Core 1 4008
Protoss_Dragoon 6 8540
Protoss_Robotics_Facility 1 5877
Protoss_Observatory 1 6524
Protoss_Observer 4 10145
Protoss_Nexus 2 11597
11597
