Protoss_Gateway 3 9513
Protoss_Assimilator 1 3215
Protoss_Cybernetics_Core 1 4058
Protoss_Dragoon 7 10573
Protoss_Citadel_of_Adun 1 6452
Protoss_Templar_Archives 1 7444
Protoss_Nexus 1 9230
Protoss_Dark_Templar 2 9213
10573
