Protoss_Gateway 3 9619
Protoss_Assimilator 1 3142
Protoss_Cybernetics_Core 1 4011
Protoss_Dragoon 12 10513
Protoss_Nexus 1 8991
Protoss_Robotics_Facility 1 8670
Protoss_Observatory 1 9233
Protoss_Observer 1 10113
10513
