Protoss_Gateway 1 2849
Protoss_Assimilator 1 3065
Protoss_Cybernetics_Core 1 3955
Protoss_Zealot 1 3858
Protoss_Dragoon 6 9038
Protoss_Robotics_Facility 1 7342
Protoss_Shuttle 1 8597
Protoss_Robotics_Support_Bay 1 8152
Protoss_Reaver 2 10700
10700
