Protoss_Gateway 4 10055
Protoss_Assimilator 1 3082
Protoss_Cybernetics_Core 1 3955
Protoss_Dragoon 8 9454
Protoss_Robotics_Facility 1 6861
Protoss_Observatory 1 7487
Protoss_Observer 3 9438
Protoss_Nexus 1 9761
Protoss_Shuttle 1 10339
10339
