Protoss_Gateway 4 10172
Protoss_Assimilator 1 3052
Protoss_Cybernetics_Core 1 4072
Protoss_Dragoon 13 10453
Protoss_Nexus 1 8125
Protoss_Robotics_Facility 1 8295
Protoss_Observatory 1 8946
Protoss_Observer 2 10393
10453
