Protoss_Nexus 2 11042
Protoss_Gateway 3 9992
Protoss_Assimilator 1 4298
Protoss_Cybernetics_Core 1 5329
Protoss_Zealot 3 9928
Protoss_Dragoon 5 8343
Protoss_Forge 1 7075
Protoss_Photon_Cannon 3 10739
Protoss_Robotics_Facility 1 9968
11042
