Protoss_Gateway 4 10205
Protoss_Assimilator 1 3173
Protoss_Cybernetics_Core 1 4181
Protoss_Dragoon 10 10398
Protoss_Robotics_Facility 1 7090
Protoss_Shuttle 1 8082
Protoss_Robotics_Support_Bay 1 7665
Protoss_Observatory 1 7726
Protoss_Reaver 1 9236
Protoss_Observer 2 10553
10553
