Protoss_Gateway 2 6181
Protoss_Assimilator 1 3186
Protoss_Zealot 6 10085
Protoss_Cybernetics_Core 1 5326
Protoss_Dragoon 5 9483
Protoss_Robotics_Facility 1 8022
Protoss_Shuttle 1 9212
Protoss_Robotics_Support_Bay 1 9019
Protoss_Reaver 1 10521
10521
