Protoss_Gateway 2 5674
Protoss_Assimilator 1 3075
Protoss_Cybernetics_Core 1 3989
Protoss_Dragoon 7 10728
Protoss_Citadel_of_Adun 1 7109
Protoss_Robotics_Facility 1 7867
Protoss_Zealot 1 8193
Protoss_Templar_Archives 1 8880
Protoss_Shuttle 1 9477
Protoss_Observatory 1 9179
Protoss_Dark_Templar 2 9828
Protoss_Nexus 1 11461
Protoss_Observer 1 10378
11461
