Protoss_Gateway 3 8923
Protoss_Assimilator 1 3210
Protoss_Cybernetics_Core 1 4207
Protoss_Dragoon 9 9982
Protoss_Citadel_of_Adun 1 6406
Protoss_Nexus 2 11576
Protoss_Robotics_Facility 1 8052
Protoss_Observatory 1 8828
Protoss_Observer 1 9553
11576
