Protoss_Gateway 4 10675
Protoss_Assimilator 2 3299
Protoss_Zealot 2 4793
Protoss_Cybernetics_Core 1 4744
Protoss_Dragoon 9 10728
Protoss_Nexus 1 9712
Protoss_Robotics_Facility 1 10284
10728
