Protoss_Nexus 2 9470
Protoss_Gateway 3 10119
Protoss_Assimilator 1 3945
Protoss_Cybernetics_Core 1 4948
Protoss_Zealot 1 5283
Protoss_Dragoon 7 10248
Protoss_Robotics_Facility 1 9727
Protoss_Observatory 1 10306
10306
