Protoss_Gateway 5 9284
Protoss_Assimilator 1 3085
Protoss_Cybernetics_Core 1 3921
Protoss_Dragoon 10 10408
Protoss_Nexus 1 9095
Protoss_Robotics_Facility 1 8788
Protoss_Observatory 1 9359
Protoss_Observer 1 10138
Protoss_Citadel_of_Adun 1 10784
10784
