Protoss_Gateway 2 6530
Protoss_Assimilator 2 3130
Protoss_Cybernetics_Core 1 4089
Protoss_Zealot 1 4098
Protoss_Dragoon 6 8288
Protoss_Citadel_of_Adun 1 7114
Protoss_Templar_Archives 1 8120
Protoss_Dark_Templar 4 10038
Protoss_Nexus 1 11200
11200
