Protoss_Gateway 2 6785
Protoss_Zealot 3 5864
Protoss_Assimilator 1 4760
Protoss_Cybernetics_Core 1 5879
Protoss_Dragoon 7 10494
Protoss_Robotics_Facility 1 9426
Protoss_Nexus 1 10883
Protoss_Observatory 1 9998
10883
