Protoss_Gateway 2 7290
Protoss_Assimilator 1 3127
Protoss_Zealot 5 10405
Protoss_Cybernetics_Core 1 4969
Protoss_Dragoon 2 6698
Protoss_Citadel_of_Adun 1 6405
Protoss_Robotics_Facility 1 7276
Protoss_Templar_Archives 1 7517
Protoss_Shuttle 1 8272
Protoss_Dark_Templar 5 10548
Protoss_Nexus 1 10645
10645
