Protoss_Gateway 2 6710
Protoss_Assimilator 1 3130
Protoss_Cybernetics_Core 1 4144
Protoss_Dragoon 7 10230
Protoss_Robotics_Facility 1 6890
Protoss_Shuttle 1 8027
Protoss_Robotics_Support_Bay 1 8094
Protoss_Zealot 2 8313
Protoss_Reaver 1 9401
Protoss_Observatory 1 9554
10230
