Protoss_Gateway 3 7569
Protoss_Assimilator 1 3226
Protoss_Cybernetics_Core 1 4380
Protoss_Dragoon 11 10343
Protoss_Robotics_Facility 1 6972
Protoss_Observatory 1 7632
Protoss_Observer 3 9808
Protoss_Nexus 1 10775
10775
