Protoss_Gateway 4 10218
Protoss_Assimilator 1 3144
Protoss_Cybernetics_Core 1 3994
Protoss_Dragoon 10 10333
Protoss_Nexus 1 9700
Protoss_Zealot 1 8953
Protoss_Robotics_Facility 1 10057
10333
