Protoss_Gateway 1 2794
Protoss_Assimilator 1 3024
Protoss_Cybernetics_Core 1 3934
Protoss_Dragoon 6 10178
Protoss_Robotics_Facility 1 5497
Protoss_Shuttle 1 6497
Protoss_Robotics_Support_Bay 1 6303
Protoss_Reaver 2 8973
Protoss_Zealot 2 9013
Protoss_Observatory 1 8586
Protoss_Nexus 1 10720
Protoss_Observer 2 10318
10720
