Protoss_Gateway 3 9674
Protoss_Assimilator 1 3013
Protoss_Cybernetics_Core 1 3982
Protoss_Dragoon 13 10548
Protoss_Nexus 1 9695
Protoss_Robotics_Facility 1 9378
Protoss_Observatory 1 10049
10548
