Protoss_Gateway 2 3485
Protoss_Zealot 6 9183
Protoss_Assimilator 1 5221
Protoss_Cybernetics_Core 1 5724
Protoss_Dragoon 8 10687
Protoss_Nexus 1 9086
Protoss_Robotics_Facility 1 9563
Protoss_Observatory 1 10319
10687
