Protoss_Gateway 2 6705
Protoss_Assimilator 1 2871
Protoss_Cybernetics_Core 1 3813
Protoss_Dragoon 7 10169
Protoss_Robotics_Facility 1 5667
Protoss_Observatory 1 6373
Protoss_Observer 1 7088
Protoss_Shuttle 1 8447
Protoss_Zealot 4 9417
Protoss_Nexus 1 10703
10703
