Protoss_Gateway 3 9540
Protoss_Assimilator 2 10050
Protoss_Cybernetics_Core 1 3934
Protoss_Dragoon 11 9878
Protoss_Nexus 1 7620
Protoss_Robotics_Facility 1 8270
Protoss_Observatory 1 8957
Protoss_Observer 2 10250
10250
