Protoss_Assimilator 1 2398
Protoss_Gateway 1 3109
Protoss_Cybernetics_Core 1 4097
Protoss_Robotics_Facility 1 5450
Protoss_Dragoon 3 9798
Protoss_Shuttle 1 6431
Protoss_Robotics_Support_Bay 1 6123
Protoss_Observatory 1 6244
Protoss_Observer 3 9625
Protoss_Nexus 1 8642
Protoss_Reaver 1 9021
9798
