Protoss_Gateway 3 9025
Protoss_Assimilator 1 3050
Protoss_Cybernetics_Core 1 3939
Protoss_Dragoon 13 10733
Protoss_Nexus 1 8882
Protoss_Robotics_Facility 1 8927
Protoss_Observatory 1 10104
10733
