Protoss_Gateway 3 10746
Protoss_Assimilator 1 2968
Protoss_Cybernetics_Core 1 3867
Protoss_Dragoon 8 10072
Protoss_Robotics_Facility 1 5603
Protoss_Observatory 1 6246
Protoss_Observer 3 8924
Protoss_Nexus 1 8514
10746
