Protoss_Gateway 3 10636
Protoss_Assimilator 1 2910
Protoss_Cybernetics_Core 1 3885
Protoss_Dragoon 4 10405
Protoss_Citadel_of_Adun 1 5659
Protoss_Templar_Archives 1 6760
Protoss_Dark_Templar 5 9641
Protoss_Nexus 1 9210
Protoss_Robotics_Facility 1 10874
10874
