Protoss_Gateway 2 6420
Protoss_Assimilator 1 2840
Protoss_Cybernetics_Core 1 3867
Protoss_Dragoon 8 9138
Protoss_Nexus 1 8093
Protoss_Zealot 3 10148
Protoss_Robotics_Facility 1 8490
Protoss_Shuttle 1 9507
Protoss_Observatory 1 9147
Protoss_Robotics_Support_Bay 1 9431
Protoss_Reaver 1 10560
10560
