Protoss_Gateway 3 10674
Protoss_Assimilator 1 3054
Protoss_Cybernetics_Core 1 3971
Protoss_Dragoon 9 10058
Protoss_Nexus 1 9113
Protoss_Zealot 3 10368
Protoss_Robotics_Facility 1 9393
Protoss_Observatory 1 9979
10674
