Protoss_Gateway 4 10855
Protoss_Assimilator 1 3025
Protoss_Cybernetics_Core 1 3841
Protoss_Dragoon 8 10512
Protoss_Nexus 1 8253
Protoss_Zealot 1 7660
Protoss_Robotics_Facility 1 8411
Protoss_Shuttle 1 9419
Protoss_Robotics_Support_Bay 1 9325
Protoss_Observatory 1 9588
Protoss_Observer 1 10282
10855
