Protoss_Gateway 3 8349
Protoss_Assimilator 1 2955
Protoss_Cybernetics_Core 1 3967
Protoss_Zealot 2 7643
Protoss_Dragoon 9 10363
Protoss_Robotics_Facility 1 6312
Protoss_Observatory 1 6895
Protoss_Observer 2 8520
Protoss_Nexus 1 10910
10910
