Protoss_Gateway 2 6705
Protoss_Assimilator 1 3094
Protoss_Cybernetics_Core 1 3909
Protoss_Dragoon 10 10330
Protoss_Nexus 1 8518
Protoss_Zealot 1 7686
Protoss_Robotics_Facility 1 9587
10330
