Protoss_Gateway 3 10711
Protoss_Assimilator 1 2790
Protoss_Cybernetics_Core 1 3784
Protoss_Dragoon 8 10298
Protoss_Robotics_Facility 1 6727
Protoss_Observatory 1 7271
Protoss_Observer 2 10293
Protoss_Nexus 1 9424
Protoss_Zealot 4 9228
Protoss_Shuttle 1 9192
10711
