Protoss_Assimilator 1 2219
Protoss_Gateway 3 7724
Protoss_Cybernetics_Core 1 4144
Protoss_Dragoon 6 10646
Protoss_Robotics_Facility 1 5639
Protoss_Observatory 1 6213
Protoss_Citadel_of_Adun 1 6698
Protoss_Observer 1 7012
Protoss_Shuttle 3 10005
Protoss_Zealot 6 9446
Protoss_Robotics_Support_Bay 1 9019
10646
