Protoss_Gateway 2 6739
Protoss_Assimilator 1 2853
Protoss_Cybernetics_Core 1 3805
Protoss_Dragoon 9 10484
Protoss_Nexus 1 7061
Protoss_Forge 1 6622
Protoss_Photon_Cannon 2 8955
Protoss_Zealot 2 10326
Protoss_Robotics_Facility 1 10491
10491
