Protoss_Gateway 2 5414
Protoss_Assimilator 1 3155
Protoss_Cybernetics_Core 1 4044
Protoss_Zealot 3 9398
Protoss_Dragoon 6 8053
Protoss_Robotics_Facility 1 7910
Protoss_Robotics_Support_Bay 1 8546
Protoss_Shuttle 1 9047
Protoss_Reaver 1 10098
Protoss_Nexus 1 11494
11494
