Protoss_Gateway 4 10190
Protoss_Assimilator 1 3101
Protoss_Cybernetics_Core 1 3919
Protoss_Dragoon 11 10523
Protoss_Nexus 1 7958
Protoss_Robotics_Facility 1 8632
Protoss_Observatory 1 9291
Protoss_Observer 1 10048
Protoss_Citadel_of_Adun 1 10437
10523
