Protoss_Gateway 3 6929
Protoss_Assimilator 1 3265
Protoss_Zealot 3 7602
Protoss_Cybernetics_Core 1 4894
Protoss_Dragoon 5 9744
Protoss_Citadel_of_Adun 1 6267
Protoss_Templar_Archives 1 7457
Protoss_Dark_Templar 3 8520
Protoss_Nexus 1 11367
11367
