Protoss_Gateway 3 9395
Protoss_Assimilator 1 2936
Protoss_Cybernetics_Core 1 3899
Protoss_Dragoon 12 10725
Protoss_Robotics_Facility 1 6675
Protoss_Observatory 1 7227
Protoss_Observer 2 8520
Protoss_Nexus 1 10485
Protoss_Zealot 1 10580
10725
