Protoss_Gateway 2 9465
Protoss_Assimilator 1 3183
Protoss_Cybernetics_Core 1 4046
Protoss_Dragoon 6 10454
Protoss_Robotics_Facility 1 6034
Protoss_Zealot 2 6512
Protoss_Shuttle 2 9173
Protoss_Robotics_Support_Bay 1 7143
Protoss_Reaver 1 8270
Protoss_Observatory 1 9347
Protoss_Observer 1 10082
10454
