Protoss_Gateway 2 4345
Protoss_Assimilator 2 10110
Protoss_Cybernetics_Core 1 3835
Protoss_Dragoon 7 9796
Protoss_Citadel_of_Adun 1 6354
Protoss_Templar_Archives 1 7452
Protoss_Nexus 1 9935
Protoss_Dark_Templar 1 9044
10110
