Protoss_Assimilator 1 2385
Protoss_Gateway 1 3011
Protoss_Cybernetics_Core 1 4009
Protoss_Dragoon 8 10728
Protoss_Robotics_Facility 1 5785
Protoss_Shuttle 1 6832
Protoss_Robotics_Support_Bay 1 6721
Protoss_Reaver 2 8973
Protoss_Nexus 1 10615
Protoss_Observatory 1 10321
10728
