Protoss_Gateway 4 10880
Protoss_Assimilator 1 2836
Protoss_Cybernetics_Core 1 3909
Protoss_Dragoon 10 9968
Protoss_Nexus 1 7984
Protoss_Robotics_Facility 1 9782
Protoss_Observatory 1 10326
10880
