Protoss_Gateway 2 6984
Protoss_Assimilator 1 3083
Protoss_Cybernetics_Core 1 3997
Protoss_Dragoon 5 9840
Protoss_Citadel_of_Adun 1 6448
Protoss_Robotics_Facility 1 7044
Protoss_Templar_Archives 1 7454
Protoss_Shuttle 1 8025
Protoss_Dark_Templar 4 9050
Protoss_Nexus 1 11559
11559
