Protoss_Gateway 2 6448
Protoss_Assimilator 1 3071
Protoss_Zealot 1 3538
Protoss_Cybernetics_Core 1 4133
Protoss_Dragoon 11 10306
Protoss_Robotics_Facility 1 8358
Protoss_Observatory 1 9065
Protoss_Nexus 1 10788
Protoss_Observer 2 10370
10788
