Protoss_Gateway 4 10013
Protoss_Assimilator 1 3111
Protoss_Cybernetics_Core 1 4047
Protoss_Dragoon 10 9395
Protoss_Nexus 1 9492
Protoss_Zealot 2 9997
Protoss_Robotics_Facility 1 10807
10807
