Protoss_Gateway 2 7075
Protoss_Assimilator 1 3124
Protoss_Cybernetics_Core 1 4246
Protoss_Dragoon 8 9726
Protoss_Citadel_of_Adun 2 9706
Protoss_Robotics_Facility 1 8002
Protoss_Observatory 1 8687
Protoss_Shuttle 1 9157
9726
