Protoss_Gateway 3 8021
Protoss_Assimilator 1 2923
Protoss_Cybernetics_Core 1 3807
Protoss_Citadel_of_Adun 1 4888
Protoss_Dragoon 1 4806
Protoss_Templar_Archives 1 5874
Protoss_Dark_Templar 11 10664
Protoss_Nexus 1 10733
Protoss_Forge 1 9953
10733
