Protoss_Gateway 2 9324
Protoss_Assimilator 1 3235
Protoss_Zealot 1 3708
Protoss_Cybernetics_Core 1 4386
Protoss_Dragoon 7 10312
Protoss_Robotics_Facility 1 6462
Protoss_Shuttle 1 7987
Protoss_Robotics_Support_Bay 1 7636
Protoss_Reaver 1 9038
Protoss_Observatory 1 9712
10312
