Protoss_Gateway 3 10571
Protoss_Assimilator 1 3059
Protoss_Zealot 1 3510
Protoss_Cybernetics_Core 1 4757
Protoss_Dragoon 11 10626
Protoss_Nexus 1 9269
Protoss_Robotics_Facility 2 9883
Protoss_Observatory 1 9971
10626
