Protoss_Gateway 1 2933
Protoss_Assimilator 1 3045
Protoss_Cybernetics_Core 1 3980
Protoss_Zealot 2 7688
Protoss_Robotics_Facility 1 5742
Protoss_Dragoon 4 9463
Protoss_Robotics_Support_Bay 1 6291
Protoss_Shield_Battery 1 6452
Protoss_Shuttle 2 9091
Protoss_Reaver 2 10781
Protoss_Nexus 1 11335
11335
