Protoss_Gateway 3 10625
Protoss_Assimilator 1 2989
Protoss_Cybernetics_Core 1 3960
Protoss_Dragoon 7 10538
Protoss_Robotics_Facility 1 6577
Protoss_Shuttle 1 7572
Protoss_Robotics_Support_Bay 1 7336
Protoss_Zealot 2 8508
Protoss_Reaver 1 8677
Protoss_Observatory 1 8769
Protoss_Observer 1 9828
10625
