Protoss_Gateway 3 10400
Protoss_Assimilator 1 3055
Protoss_Cybernetics_Core 1 4079
Protoss_Dragoon 2 5838
Protoss_Citadel_of_Adun 1 5391
Protoss_Templar_Archives 1 6443
Protoss_Dark_Templar 8 10093
Protoss_Nexus 1 9865
10400
