Protoss_Gateway 2 4322
Protoss_Assimilator 1 2823
Protoss_Cybernetics_Core 1 3857
Protoss_Dragoon 9 9470
Protoss_Robotics_Facility 1 7285
Protoss_Zealot 2 7536
Protoss_Robotics_Support_Bay 1 8737
Protoss_Shuttle 1 9331
Protoss_Reaver 1 10382
Protoss_Observatory 1 10060
10382
