Protoss_Gateway 2 5561
Protoss_Assimilator 1 3105
Protoss_Cybernetics_Core 1 3988
Protoss_Dragoon 10 9998
Protoss_Citadel_of_Adun 1 6952
Protoss_Nexus 2 11493
Protoss_Robotics_Facility 1 9514
Protoss_Observatory 1 10208
11493
