Protoss_Gateway 3 9003
Protoss_Assimilator 1 2782
Protoss_Cybernetics_Core 1 3713
Protoss_Dragoon 9 8948
Protoss_Nexus 1 9036
Protoss_Zealot 5 9870
Protoss_Citadel_of_Adun 1 10493
10493
