Protoss_Gateway 3 8699
Protoss_Assimilator 1 3085
Protoss_Cybernetics_Core 1 4145
Protoss_Dragoon 9 9753
Protoss_Robotics_Facility 1 8333
Protoss_Zealot 2 8953
Protoss_Observatory 1 8895
Protoss_Observer 1 9973
Protoss_Nexus 1 11565
11565
