Protoss_Gateway 2 8603
Protoss_Assimilator 1 2981
Protoss_Cybernetics_Core 1 3837
Protoss_Dragoon 8 10728
Protoss_Robotics_Facility 1 5567
Protoss_Shuttle 1 6555
Protoss_Robotics_Support_Bay 1 6201
Protoss_Reaver 1 7642
Protoss_Observatory 1 7929
Protoss_Observer 1 8682
Protoss_Nexus 1 11234
11234
