Protoss_Gateway 3 6879
Protoss_Assimilator 1 3084
Protoss_Cybernetics_Core 1 3973
Protoss_Dragoon 8 9186
Protoss_Zealot 4 8904
Protoss_Citadel_of_Adun 1 8885
Protoss_Templar_Archives 1 9888
Protoss_Nexus 1 11159
Protoss_Dark_Templar 2 10724
11159
