Protoss_Gateway 2 6609
Protoss_Assimilator 1 2815
Protoss_Cybernetics_Core 1 3777
Protoss_Dragoon 12 10678
Protoss_Robotics_Facility 1 6137
Protoss_Observatory 1 6757
Protoss_Observer 4 10018
Protoss_Nexus 1 10195
10678
