Protoss_Gateway 3 8472
Protoss_Assimilator 2 9408
Protoss_Cybernetics_Core 1 3979
Protoss_Dragoon 11 10642
Protoss_Nexus 1 7937
Protoss_Robotics_Facility 1 9059
Protoss_Zealot 1 8556
Protoss_Stargate 1 10567
Protoss_Observatory 1 10137
10642
