Protoss_Gateway 2 6893
Protoss_Assimilator 1 3030
Protoss_Cybernetics_Core 1 3944
Protoss_Dragoon 9 9609
Protoss_Robotics_Facility 1 6912
Protoss_Zealot 3 10293
Protoss_Observatory 1 7871
Protoss_Observer 1 8713
Protoss_Citadel_of_Adun 1 9020
Protoss_Shuttle 1 10037
Protoss_Templar_Archives 2 10339
10339
