Protoss_Gateway 2 8239
Protoss_Assimilator 1 3032
Protoss_Cybernetics_Core 1 4017
Protoss_Dragoon 10 10184
Protoss_Robotics_Facility 1 7134
Protoss_Observatory 1 7725
Protoss_Observer 3 10232
Protoss_Nexus 1 10935
10935
