Protoss_Gateway 2 8234
Protoss_Assimilator 1 3147
Protoss_Cybernetics_Core 1 3979
Protoss_Dragoon 6 10613
Protoss_Robotics_Facility 1 5842
Protoss_Shuttle 1 6832
Protoss_Robotics_Support_Bay 1 6776
Protoss_Reaver 2 9171
Protoss_Nexus 1 11486
11486
