Protoss_Gateway 1 2769
Protoss_Assimilator 1 2840
Protoss_Cybernetics_Core 1 3819
Protoss_Zealot 2 6018
Protoss_Robotics_Facility 1 5246
Protoss_Dragoon 5 10170
Protoss_Shuttle 3 10877
Protoss_Robotics_Support_Bay 1 6136
Protoss_Reaver 2 8443
Protoss_Observatory 1 9226
Protoss_Observer 1 9958
10877
