Protoss_Gateway 2 6784
Protoss_Assimilator 1 2856
Protoss_Cybernetics_Core 1 3845
Protoss_Dragoon 9 10063
Protoss_Robotics_Facility 1 6678
Protoss_Observatory 1 7281
Protoss_Observer 3 10098
Protoss_Nexus 2 9451
10098
