Protoss_Gateway 3 9954
Protoss_Assimilator 1 2971
Protoss_Cybernetics_Core 1 3975
Protoss_Dragoon 9 9974
Protoss_Robotics_Facility 1 7814
Protoss_Nexus 2 11557
Protoss_Observatory 1 8353
Protoss_Observer 2 9722
11557
