Protoss_Gateway 4 10844
Protoss_Assimilator 1 3145
Protoss_Cybernetics_Core 1 3908
Protoss_Dragoon 9 10200
Protoss_Nexus 1 8328
Protoss_Robotics_Facility 1 8592
Protoss_Observatory 1 9291
Protoss_Observer 1 10173
10844
