Protoss_Gateway 2 4463
Protoss_Assimilator 1 2972
Protoss_Cybernetics_Core 1 3809
Protoss_Dragoon 8 10663
Protoss_Nexus 2 10645
Protoss_Robotics_Facility 1 9244
Protoss_Shuttle 1 10612
Protoss_Robotics_Support_Bay 1 10212
10663
