Protoss_Gateway 2 4553
Protoss_Assimilator 1 2894
Protoss_Cybernetics_Core 1 3931
Protoss_Dragoon 5 7242
Protoss_Citadel_of_Adun 1 6903
Protoss_Templar_Archives 1 8195
Protoss_Robotics_Facility 1 8677
Protoss_Zealot 2 8796
Protoss_Nexus 1 10095
Protoss_Shuttle 1 9669
Protoss_Dark_Templar 2 9804
Protoss_Observatory 1 9918
Protoss_Observer 1 10596
10596
