Protoss_Gateway 2 9059
Protoss_Assimilator 1 3060
Protoss_Cybernetics_Core 1 4107
Protoss_Zealot 1 4228
Protoss_Dragoon 8 10408
Protoss_Robotics_Facility 1 7692
Protoss_Nexus 1 9265
Protoss_Observatory 1 8371
Protoss_Observer 1 9108
10408
