Protoss_Gateway 3 10122
Protoss_Assimilator 1 2918
Protoss_Cybernetics_Core 1 3841
Protoss_Dragoon 8 9172
Protoss_Robotics_Facility 1 7538
Protoss_Observatory 1 8125
Protoss_Observer 2 10420
Protoss_Nexus 1 10432
Protoss_Citadel_of_Adun 1 10104
10432
