Protoss_Nexus 1 4465
Protoss_Gateway 3 10319
Protoss_Assimilator 2 8578
Protoss_Cybernetics_Core 1 5071
Protoss_Zealot 4 9908
Protoss_Dragoon 10 10703
Protoss_Stargate 2 10382
Protoss_Fleet_Beacon 1 10064
10703
