Protoss_Gateway 2 7663
Protoss_Assimilator 2 3472
Protoss_Zealot 5 9083
Protoss_Cybernetics_Core 1 4574
Protoss_Dragoon 2 6170
Protoss_Robotics_Facility 1 7127
Protoss_Shuttle 1 8122
Protoss_Observatory 1 7843
Protoss_Robotics_Support_Bay 1 8605
Protoss_Reaver 2 10853
10853
