Protoss_Gateway 2 4293
Protoss_Assimilator 1 3160
Protoss_Cybernetics_Core 1 3878
Protoss_Dragoon 12 10062
Protoss_Nexus 1 9317
Protoss_Robotics_Facility 1 9541
Protoss_Observatory 1 10434
10434
