Protoss_Gateway 2 5672
Protoss_Assimilator 1 2887
Protoss_Cybernetics_Core 1 3971
Protoss_Dragoon 8 8346
Protoss_Robotics_Facility 1 7511
Protoss_Observatory 1 8135
Protoss_Shuttle 1 8827
Protoss_Zealot 6 10176
Protoss_Observer 1 9430
10176
