Protoss_Gateway 1 2769
Protoss_Assimilator 2 9326
Protoss_Cybernetics_Core 1 3928
Protoss_Dragoon 3 6484
Protoss_Stargate 2 9426
Protoss_Scout 2 8733
Protoss_Nexus 1 9133
Protoss_Air_Weapons_1 1 8291
Protoss_Fleet_Beacon 1 9453
Protoss_Carrier 2 12023
12023
