Protoss_Gateway 2 5667
Protoss_Assimilator 1 3021
Protoss_Cybernetics_Core 1 3881
Protoss_Dragoon 12 10246
Protoss_Nexus 2 10772
Protoss_Robotics_Facility 1 9105
Protoss_Observatory 1 9836
Protoss_Observer 1 10522
10772
