Protoss_Gateway 1 2907
Protoss_Assimilator 1 3001
Protoss_Cybernetics_Core 1 3899
Protoss_Zealot 4 9326
Protoss_Robotics_Facility 1 5625
Protoss_Dragoon 3 7404
Protoss_Shuttle 1 6865
Protoss_Robotics_Support_Bay 1 6871
Protoss_Reaver 3 10388
10388
