Protoss_Gateway 2 4617
Protoss_Assimilator 1 3064
Protoss_Cybernetics_Core 1 3994
Protoss_Dragoon 11 10526
Protoss_Citadel_of_Adun 1 7095
Protoss_Zealot 1 7570
Protoss_Templar_Archives 1 8081
Protoss_Dark_Templar 2 9382
10526
