Protoss_Gateway 2 7045
Protoss_Assimilator 1 3018
Protoss_Cybernetics_Core 1 4035
Protoss_Dragoon 8 9196
Protoss_Robotics_Facility 1 6925
Protoss_Observatory 1 7469
Protoss_Observer 2 8876
Protoss_Nexus 2 11049
Protoss_Zealot 2 10158
Protoss_Shuttle 1 10845
11049
