Protoss_Gateway 2 6669
Protoss_Assimilator 1 3353
Protoss_Cybernetics_Core 1 4204
Protoss_Dragoon 2 5888
Protoss_Citadel_of_Adun 1 5639
Protoss_Templar_Archives 1 7009
Protoss_Dark_Templar 4 8615
Protoss_Nexus 1 10428
Protoss_Robotics_Facility 1 10560
10560
