Protoss_Gateway 2 7172
Protoss_Assimilator 1 3133
Protoss_Cybernetics_Core 1 4124
Protoss_Dragoon 6 10674
Protoss_Citadel_of_Adun 1 6526
Protoss_Templar_Archives 1 7524
Protoss_Dark_Templar 4 9278
Protoss_Nexus 1 9780
10674
