Protoss_Assimilator 2 3489
Protoss_Gateway 3 10335
Protoss_Cybernetics_Core 1 4429
Protoss_Dragoon 6 8035
Protoss_Shield_Battery 2 7541
Protoss_Citadel_of_Adun 1 7559
Protoss_Templar_Archives 1 8663
Protoss_Dark_Templar 4 10335
Protoss_Forge 1 9661
10335
