Protoss_Gateway 2 6900
Protoss_Assimilator 1 2946
Protoss_Cybernetics_Core 1 3816
Protoss_Dragoon 10 10012
Protoss_Robotics_Facility 1 6883
Protoss_Observatory 1 7513
Protoss_Observer 4 10540
Protoss_Nexus 2 10537
10540
