Protoss_Gateway 2 10808
Protoss_Assimilator 1 3026
Protoss_Cybernetics_Core 1 4059
Protoss_Dragoon 3 7000
Protoss_Robotics_Facility 1 6769
Protoss_Forge 1 6866
Protoss_Shuttle 1 7812
Protoss_Photon_Cannon 1 7730
Protoss_Robotics_Support_Bay 1 7693
Protoss_Reaver 2 9915
10808
