Protoss_Gateway 3 9650
Protoss_Assimilator 1 2931
Protoss_Cybernetics_Core 1 3906
Protoss_Dragoon 9 9564
Protoss_Nexus 1 9165
Protoss_Robotics_Facility 1 9391
Protoss_Shuttle 1 10631
Protoss_Robotics_Support_Bay 1 10357
10631
