Protoss_Gateway 2 6393
Protoss_Assimilator 1 3221
Protoss_Zealot 1 3588
Protoss_Cybernetics_Core 1 4874
Protoss_Dragoon 8 9633
Protoss_Nexus 1 9852
Protoss_Robotics_Facility 1 9787
Protoss_Shuttle 1 10867
10867
