Protoss_Gateway 2 6409
Protoss_Assimilator 2 3530
Protoss_Zealot 2 4868
Protoss_Cybernetics_Core 1 4787
Protoss_Dragoon 10 10508
Protoss_Nexus 1 10035
Protoss_Robotics_Facility 1 9997
10508
