Protoss_Gateway 1 2802
Protoss_Assimilator 1 3320
Protoss_Zealot 2 7212
Protoss_Cybernetics_Core 1 4481
Protoss_Robotics_Facility 1 5773
Protoss_Dragoon 5 10708
Protoss_Shuttle 1 6783
Protoss_Robotics_Support_Bay 1 6893
Protoss_Reaver 1 8042
Protoss_Observatory 1 7818
Protoss_Observer 2 9248
Protoss_Nexus 2 11602
11602
