Protoss_Gateway 3 10564
Protoss_Assimilator 1 3471
Protoss_Cybernetics_Core 1 4244
Protoss_Dragoon 9 10370
Protoss_Robotics_Facility 1 6898
Protoss_Observatory 1 7686
Protoss_Observer 4 10309
Protoss_Nexus 1 10110
10564
