Protoss_Gateway 1 2875
Protoss_Assimilator 1 3057
Protoss_Cybernetics_Core 1 3994
Protoss_Dragoon 7 10623
Protoss_Zealot 1 6308
Protoss_Robotics_Facility 1 7057
Protoss_Shuttle 1 8067
Protoss_Robotics_Support_Bay 1 7838
Protoss_Reaver 1 9118
Protoss_Nexus 1 10360
Protoss_Observatory 1 9169
Protoss_Observer 1 10433
10623
