Protoss_Gateway 2 8182
Protoss_Assimilator 1 2838
Protoss_Cybernetics_Core 1 4024
Protoss_Robotics_Facility 1 5350
Protoss_Dragoon 2 5835
Protoss_Shuttle 1 6342
Protoss_Robotics_Support_Bay 1 6196
Protoss_Zealot 2 7408
Protoss_Reaver 2 8491
Protoss_Citadel_of_Adun 1 7592
Protoss_Templar_Archives 1 9014
Protoss_Dark_Templar 1 10243
10243
