Protoss_Gateway 3 9883
Protoss_Assimilator 2 9799
Protoss_Cybernetics_Core 1 3904
Protoss_Dragoon 7 9378
Protoss_Robotics_Facility 1 7780
Protoss_Zealot 2 7508
Protoss_Nexus 1 9580
Protoss_Observatory 1 8388
Protoss_Observer 2 9758
9883
