Protoss_Gateway 2 5559
Protoss_Assimilator 2 10187
Protoss_Cybernetics_Core 1 3893
Protoss_Dragoon 5 7513
Protoss_Citadel_of_Adun 1 7249
Protoss_Zealot 1 7178
Protoss_Robotics_Facility 2 11163
Protoss_Templar_Archives 1 8279
Protoss_Nexus 1 9706
Protoss_Dark_Templar 1 9243
Protoss_Stargate 1 10053
11163
