Protoss_Nexus 1 4970
Protoss_Gateway 3 8424
Protoss_Assimilator 2 8374
Protoss_Zealot 9 10390
Protoss_Cybernetics_Core 1 5684
Protoss_Dragoon 4 8518
Protoss_Citadel_of_Adun 1 7934
Protoss_Templar_Archives 1 8974
Protoss_Dark_Templar 2 10702
10702
