Protoss_Gateway 2 5114
Protoss_Assimilator 1 3092
Protoss_Zealot 2 4443
Protoss_Cybernetics_Core 1 4519
Protoss_Dragoon 11 9863
Protoss_Nexus 1 9623
Protoss_Robotics_Facility 1 9697
Protoss_Observatory 1 10420
10420
