Protoss_Gateway 2 3497
Protoss_Zealot 3 4268
Protoss_Assimilator 1 4420
Protoss_Cybernetics_Core 1 5304
Protoss_Dragoon 7 10743
Protoss_Nexus 1 9334
Protoss_Robotics_Facility 1 9167
Protoss_Shuttle 1 10172
Protoss_Robotics_Support_Bay 1 9746
10743
