Protoss_Gateway 2 5624
Protoss_Assimilator 1 3017
Protoss_Cybernetics_Core 1 3911
Protoss_Dragoon 7 9838
Protoss_Robotics_Facility 1 7721
Protoss_Zealot 4 8653
Protoss_Shuttle 1 8842
Protoss_Observatory 1 8654
Protoss_Observer 1 9445
Protoss_Nexus 1 11220
11220
