Protoss_Gateway 4 10531
Protoss_Assimilator 1 3090
Protoss_Cybernetics_Core 1 4044
Protoss_Dragoon 8 10548
Protoss_Robotics_Facility 1 5837
Protoss_Observatory 1 6566
Protoss_Observer 5 10245
Protoss_Nexus 1 10690
10690
