Protoss_Gateway 3 8774
Protoss_Assimilator 1 3225
Protoss_Zealot 2 4928
Protoss_Cybernetics_Core 1 4774
Protoss_Dragoon 10 10480
Protoss_Robotics_Facility 1 6742
Protoss_Observatory 1 7336
Protoss_Observer 2 8790
10480
