Protoss_Gateway 3 10383
Protoss_Assimilator 1 3003
Protoss_Cybernetics_Core 1 3812
Protoss_Dragoon 9 9894
Protoss_Robotics_Facility 1 5665
Protoss_Observatory 1 6253
Protoss_Observer 2 9842
Protoss_Nexus 2 10694
Protoss_Shuttle 1 10837
10837
