Protoss_Nexus 2 10334
Protoss_Gateway 5 10589
Protoss_Zealot 8 7390
Protoss_Assimilator 1 5486
Protoss_Cybernetics_Core 1 6573
Protoss_Dragoon 6 9795
Protoss_Robotics_Facility 1 10352
Protoss_Citadel_of_Adun 1 10259
10589
