Protoss_Gateway 2 9139
Protoss_Assimilator 1 3078
Protoss_Cybernetics_Core 1 3969
Protoss_Dragoon 4 10553
Protoss_Robotics_Facility 1 5824
Protoss_Shuttle 1 6827
Protoss_Observatory 1 6517
Protoss_Robotics_Support_Bay 1 6586
Protoss_Observer 2 10252
Protoss_Reaver 2 9648
10553
