Protoss_Gateway 4 9885
Protoss_Assimilator 1 2960
Protoss_Cybernetics_Core 1 3884
Protoss_Dragoon 11 9574
Protoss_Robotics_Facility 1 8004
Protoss_Nexus 1 9740
Protoss_Observatory 1 8593
Protoss_Observer 1 9283
Protoss_Shuttle 1 10327
Protoss_Zealot 2 10343
10343
