Protoss_Gateway 3 10708
Protoss_Assimilator 1 2792
Protoss_Cybernetics_Core 1 3729
Protoss_Dragoon 10 10184
Protoss_Nexus 2 10363
Protoss_Robotics_Facility 1 8772
Protoss_Observatory 1 9342
Protoss_Shuttle 1 9981
10708
