Protoss_Gateway 2 10271
Protoss_Assimilator 1 3045
Protoss_Cybernetics_Core 1 3934
Protoss_Dragoon 8 10445
Protoss_Robotics_Facility 1 6977
Protoss_Observatory 1 7568
Protoss_Nexus 1 9106
Protoss_Observer 1 8428
Protoss_Robotics_Support_Bay 1 8641
Protoss_Shuttle 1 9329
Protoss_Reaver 1 10380
10445
