Protoss_Gateway 2 4584
Protoss_Assimilator 1 3085
Protoss_Cybernetics_Core 1 4064
Protoss_Dragoon 8 10373
Protoss_Zealot 1 6818
Protoss_Nexus 2 10550
Protoss_Robotics_Facility 1 10337
10550
