Protoss_Gateway 2 7074
Protoss_Assimilator 1 2974
Protoss_Cybernetics_Core 1 3765
Protoss_Dragoon 9 10574
Protoss_Robotics_Facility 1 6647
Protoss_Observatory 1 7264
Protoss_Nexus 3 11721
Protoss_Observer 1 8258
Protoss_Shuttle 1 9981
Protoss_Robotics_Support_Bay 1 9727
11721
