Protoss_Gateway 3 9779
Protoss_Assimilator 1 3140
Protoss_Cybernetics_Core 1 4129
Protoss_Dragoon 9 10698
Protoss_Robotics_Facility 1 7231
Protoss_Observatory 1 7888
Protoss_Nexus 1 9921
Protoss_Observer 3 10183
10698
