Protoss_Gateway 3 9779
Protoss_Assimilator 1 3151
Protoss_Cybernetics_Core 1 4144
Protoss_Dragoon 11 10673
Protoss_Robotics_Facility 1 6930
Protoss_Observatory 1 7501
Protoss_Observer 4 10490
Protoss_Nexus 1 10104
10673
