Protoss_Gateway 2 7243
Protoss_Assimilator 1 3052
Protoss_Cybernetics_Core 1 4092
Protoss_Dragoon 8 9088
Protoss_Robotics_Facility 1 7006
Protoss_Observatory 1 7756
Protoss_Observer 3 9928
Protoss_Nexus 2 11652
11652
