Protoss_Gateway 2 6414
Protoss_Assimilator 1 3150
Protoss_Cybernetics_Core 1 4264
Protoss_Dragoon 8 8858
Protoss_Robotics_Facility 1 7270
Protoss_Observatory 1 8017
Protoss_Observer 3 10163
Protoss_Nexus 1 10315
10315
