Protoss_Gateway 3 7706
Protoss_Assimilator 1 2780
Protoss_Cybernetics_Core 1 3905
Protoss_Dragoon 12 10603
Protoss_Nexus 2 11560
Protoss_Robotics_Facility 1 8701
Protoss_Observatory 1 9251
Protoss_Observer 2 10535
11560
