Protoss_Gateway 2 7107
Protoss_Assimilator 1 2882
Protoss_Cybernetics_Core 1 3834
Protoss_Dragoon 12 10578
Protoss_Robotics_Facility 1 6467
Protoss_Observatory 1 7091
Protoss_Observer 2 9118
Protoss_Nexus 1 11508
11508
