Protoss_Gateway 3 7629
Protoss_Assimilator 1 2960
Protoss_Cybernetics_Core 1 3904
Protoss_Dragoon 11 9933
Protoss_Nexus 2 11693
Protoss_Robotics_Facility 1 9250
Protoss_Observatory 1 10000
11693
