Protoss_Gateway 6 10629
Protoss_Assimilator 1 3041
Protoss_Cybernetics_Core 1 3882
Protoss_Dragoon 9 9383
Protoss_Nexus 1 8191
Protoss_Robotics_Facility 1 8420
Protoss_Observatory 1 9070
Protoss_Observer 2 10380
10629
