Protoss_Nexus 2 10971
Protoss_Gateway 3 10632
Protoss_Assimilator 2 6075
Protoss_Cybernetics_Core 1 4991
Protoss_Zealot 3 9360
Protoss_Citadel_of_Adun 1 6017
Protoss_Dragoon 5 10282
Protoss_Robotics_Facility 1 6914
Protoss_Shuttle 1 8031
Protoss_Robotics_Support_Bay 1 7973
Protoss_Reaver 1 9268
Protoss_Observatory 1 8733
10971
