Protoss_Gateway 2 4325
Protoss_Assimilator 1 2861
Protoss_Cybernetics_Core 1 3751
Protoss_Dragoon 9 10464
Protoss_Citadel_of_Adun 1 6731
Protoss_Templar_Archives 1 7761
Protoss_Zealot 2 7878
Protoss_Dark_Templar 2 8630
Protoss_Nexus 1 10220
10464
