Protoss_Gateway 3 9698
Protoss_Assimilator 1 2980
Protoss_Cybernetics_Core 1 4473
Protoss_Zealot 2 6373
Protoss_Robotics_Facility 1 5857
Protoss_Dragoon 8 10548
Protoss_Robotics_Support_Bay 1 6466
Protoss_Shuttle 1 7037
Protoss_Reaver 1 8088
10548
