Protoss_Gateway 3 9550
Protoss_Assimilator 1 3142
Protoss_Cybernetics_Core 1 4079
Protoss_Dragoon 11 10558
Protoss_Robotics_Facility 1 7090
Protoss_Nexus 1 9178
Protoss_Observatory 1 8017
Protoss_Observer 3 10032
10558
