Protoss_Gateway 3 7919
Protoss_Assimilator 1 3075
Protoss_Zealot 3 8693
Protoss_Cybernetics_Core 1 4821
Protoss_Dragoon 10 10635
Protoss_Nexus 1 7915
Protoss_Robotics_Facility 1 8862
Protoss_Observatory 1 9440
Protoss_Observer 1 10408
10635
