Protoss_Gateway 2 6494
Protoss_Assimilator 1 2919
Protoss_Cybernetics_Core 1 3809
Protoss_Dragoon 12 10445
Protoss_Robotics_Facility 1 5598
Protoss_Observatory 1 6198
Protoss_Shuttle 1 7087
Protoss_Nexus 1 9560
Protoss_Robotics_Support_Bay 1 9117
Protoss_Reaver 1 10956
10956
