Protoss_Gateway 2 4305
Protoss_Assimilator 1 2877
Protoss_Cybernetics_Core 1 3834
Protoss_Dragoon 9 10438
Protoss_Robotics_Facility 1 7186
Protoss_Shuttle 2 9132
Protoss_Robotics_Support_Bay 1 8070
Protoss_Reaver 1 9316
Protoss_Observatory 1 8961
Protoss_Nexus 1 10935
Protoss_Observer 1 9920
10935
