Protoss_Assimilator 2 7186
Protoss_Gateway 2 9186
Protoss_Zealot 7 9202
Protoss_Nexus 1 7769
Protoss_Forge 1 7113
Protoss_Photon_Cannon 5 10045
Protoss_Cybernetics_Core 1 8459
Protoss_Dragoon 3 10272
10272
