Protoss_Gateway 4 9679
Protoss_Assimilator 1 2810
Protoss_Cybernetics_Core 1 3779
Protoss_Dragoon 8 10678
Protoss_Nexus 2 9607
Protoss_Robotics_Facility 1 7598
Protoss_Observatory 1 8146
Protoss_Observer 3 10548
Protoss_Citadel_of_Adun 1 9249
Protoss_Zealot 1 9698
10678
