Protoss_Gateway 4 10171
Protoss_Assimilator 1 2970
Protoss_Cybernetics_Core 1 3919
Protoss_Dragoon 8 9413
Protoss_Robotics_Facility 1 6612
Protoss_Observatory 1 7156
Protoss_Observer 2 9283
Protoss_Nexus 1 9675
Protoss_Shuttle 1 10417
Protoss_Zealot 2 10278
10417
