Protoss_Gateway 3 9565
Protoss_Assimilator 1 2995
Protoss_Cybernetics_Core 1 3963
Protoss_Dragoon 8 9118
Protoss_Robotics_Facility 1 6616
Protoss_Observatory 1 7202
Protoss_Observer 2 8742
Protoss_Nexus 1 9652
Protoss_Zealot 5 10322
10322
