Protoss_Nexus 1 4533
Protoss_Gateway 4 9700
Protoss_Assimilator 1 4015
Protoss_Cybernetics_Core 1 5125
Protoss_Zealot 1 5382
Protoss_Dragoon 11 10530
Protoss_Robotics_Facility 1 8467
Protoss_Shuttle 1 9523
10530
