Protoss_Gateway 2 6094
Protoss_Assimilator 1 2847
Protoss_Cybernetics_Core 1 3953
Protoss_Dragoon 9 9588
Protoss_Nexus 2 11347
Protoss_Robotics_Facility 1 9276
Protoss_Shuttle 1 10413
Protoss_Robotics_Support_Bay 1 10350
11347
