Protoss_Gateway 3 9459
Protoss_Assimilator 1 2980
Protoss_Cybernetics_Core 1 3879
Protoss_Dragoon 14 10623
Protoss_Robotics_Facility 1 7136
Protoss_Observatory 1 8108
Protoss_Observer 2 9465
10623
