Protoss_Gateway 1 2864
Protoss_Assimilator 1 3130
Protoss_Cybernetics_Core 1 4159
Protoss_Robotics_Facility 1 5661
Protoss_Dragoon 2 10723
Protoss_Zealot 3 8993
Protoss_Shuttle 1 6882
Protoss_Robotics_Support_Bay 1 6577
Protoss_Reaver 3 11041
Protoss_Nexus 1 11278
11278
