Protoss_Gateway 3 8754
Protoss_Assimilator 2 10442
Protoss_Cybernetics_Core 1 3969
Protoss_Dragoon 8 10013
Protoss_Nexus 1 7486
Protoss_Robotics_Facility 1 7712
Protoss_Observatory 1 10083
10442
