Protoss_Gateway 2 5803
Protoss_Assimilator 1 3211
Protoss_Cybernetics_Core 1 4287
Protoss_Dragoon 8 10432
Protoss_Nexus 2 10199
Protoss_Zealot 1 9502
Protoss_Robotics_Facility 1 10529
10529
