Protoss_Gateway 4 10807
Protoss_Assimilator 1 2980
Protoss_Cybernetics_Core 1 3882
Protoss_Dragoon 8 10602
Protoss_Zealot 2 5452
Protoss_Nexus 2 9942
Protoss_Robotics_Facility 1 10211
10807
