Protoss_Gateway 2 4725
Protoss_Assimilator 1 3077
Protoss_Cybernetics_Core 1 3908
Protoss_Dragoon 7 8683
Protoss_Zealot 4 9373
Protoss_Nexus 1 9217
Protoss_Citadel_of_Adun 1 9499
Protoss_Robotics_Facility 1 10491
Protoss_Templar_Archives 1 10706
10706
