Protoss_Nexus 2 11386
Protoss_Gateway 4 8434
Protoss_Assimilator 2 9500
Protoss_Cybernetics_Core 1 5139
Protoss_Dragoon 12 10658
Protoss_Zealot 1 6640
Protoss_Robotics_Facility 1 8381
Protoss_Observatory 1 9019
Protoss_Observer 1 10313
11386
