Protoss_Gateway 3 10140
Protoss_Assimilator 1 2835
Protoss_Cybernetics_Core 1 3894
Protoss_Dragoon 8 10288
Protoss_Robotics_Facility 1 6517
Protoss_Observatory 1 7194
Protoss_Observer 1 7883
Protoss_Nexus 1 9565
Protoss_Zealot 4 9348
Protoss_Shuttle 1 9362
10288
