Protoss_Gateway 3 10828
Protoss_Assimilator 1 3050
Protoss_Cybernetics_Core 1 3835
Protoss_Zealot 1 3716
Protoss_Dragoon 10 10500
Protoss_Nexus 1 8973
Protoss_Robotics_Facility 1 9392
Protoss_Observatory 1 10156
10828
