Protoss_Gateway 3 10387
Protoss_Assimilator 1 3086
Protoss_Cybernetics_Core 1 4015
Protoss_Dragoon 6 8743
Protoss_Nexus 1 7845
Protoss_Robotics_Facility 1 8489
Protoss_Shuttle 1 9642
Protoss_Robotics_Support_Bay 1 9384
Protoss_Reaver 1 10693
10693
