Protoss_Gateway 4 9844
Protoss_Assimilator 2 8893
Protoss_Cybernetics_Core 1 3879
Protoss_Dragoon 8 9403
Protoss_Citadel_of_Adun 1 6435
Protoss_Stargate 1 7298
Protoss_Templar_Archives 1 7593
Protoss_Nexus 1 8780
Protoss_Arbiter_Tribunal 1 8759
Protoss_Arbiter 1 11590
Protoss_Zealot 3 10328
11590
