Protoss_Gateway 4 10231
Protoss_Assimilator 1 3065
Protoss_Cybernetics_Core 1 4024
Protoss_Dragoon 10 10543
Protoss_Nexus 1 8092
Protoss_Robotics_Facility 1 8027
Protoss_Observatory 1 8861
Protoss_Zealot 1 9168
Protoss_Observer 2 10228
10543
