Protoss_Gateway 4 9721
Protoss_Assimilator 1 3065
Protoss_Cybernetics_Core 1 3922
Protoss_Dragoon 7 9378
Protoss_Nexus 1 7695
Protoss_Zealot 7 10188
Protoss_Citadel_of_Adun 1 9133
10188
