Protoss_Gateway 2 5579
Protoss_Assimilator 1 2975
Protoss_Cybernetics_Core 1 3855
Protoss_Dragoon 4 6603
Protoss_Citadel_of_Adun 1 6328
Protoss_Templar_Archives 1 7367
Protoss_Zealot 3 8850
Protoss_Dark_Templar 5 9893
Protoss_Nexus 1 11039
Protoss_Robotics_Facility 1 11117
11117
