Protoss_Gateway 2 3594
Protoss_Zealot 4 7305
Protoss_Assimilator 1 4660
Protoss_Cybernetics_Core 1 5804
Protoss_Dragoon 10 10540
Protoss_Nexus 1 9300
Protoss_Robotics_Facility 1 9857
10540
