Protoss_Assimilator 1 2420
Protoss_Gateway 5 10724
Protoss_Cybernetics_Core 1 4189
Protoss_Robotics_Facility 1 5482
Protoss_Dragoon 7 10065
Protoss_Shuttle 1 6632
Protoss_Observatory 1 6260
Protoss_Observer 3 8439
Protoss_Nexus 1 10232
Protoss_Citadel_of_Adun 1 9795
10724
