Protoss_Gateway 3 9267
Protoss_Assimilator 1 2812
Protoss_Cybernetics_Core 1 3882
Protoss_Dragoon 11 9662
Protoss_Nexus 1 7805
Protoss_Robotics_Facility 1 8097
Protoss_Observatory 1 9777
9777
