Protoss_Gateway 4 9179
Protoss_Assimilator 2 10161
Protoss_Cybernetics_Core 1 3852
Protoss_Dragoon 9 10694
Protoss_Robotics_Facility 1 6634
Protoss_Nexus 2 11544
Protoss_Observatory 1 7385
Protoss_Observer 3 9304
Protoss_Zealot 1 10448
11544
