Protoss_Gateway 2 5903
Protoss_Assimilator 1 3013
Protoss_Cybernetics_Core 1 3859
Protoss_Dragoon 14 10501
Protoss_Robotics_Facility 1 8889
Protoss_Observatory 1 9427
Protoss_Observer 1 10118
10501
