Protoss_Gateway 3 8874
Protoss_Assimilator 2 9437
Protoss_Cybernetics_Core 1 3747
Protoss_Dragoon 5 6364
Protoss_Nexus 1 8723
Protoss_Citadel_of_Adun 1 8135
Protoss_Robotics_Facility 1 9124
Protoss_Templar_Archives 1 9127
Protoss_Shuttle 1 10109
Protoss_Dark_Templar 3 10018
Protoss_Observatory 1 10055
10109
