Protoss_Gateway 2 4689
Protoss_Assimilator 1 2983
Protoss_Cybernetics_Core 1 4129
Protoss_Dragoon 5 6780
Protoss_Robotics_Facility 1 8167
Protoss_Zealot 4 8566
Protoss_Shuttle 1 9153
Protoss_Robotics_Support_Bay 1 8848
Protoss_Reaver 1 10204
10204
