Protoss_Gateway 4 9792
Protoss_Assimilator 2 8048
Protoss_Cybernetics_Core 1 3776
Protoss_Dragoon 7 8598
Protoss_Nexus 1 7814
Protoss_Robotics_Facility 1 7988
Protoss_Citadel_of_Adun 1 8074
Protoss_Templar_Archives 1 9339
Protoss_Shuttle 1 10017
Protoss_Dark_Templar 3 10468
Protoss_Stargate 1 10631
10631
