Protoss_Gateway 4 10738
Protoss_Assimilator 1 2935
Protoss_Cybernetics_Core 1 3723
Protoss_Dragoon 8 9148
Protoss_Robotics_Facility 1 5848
Protoss_Observatory 1 6791
Protoss_Observer 1 7644
Protoss_Nexus 2 11164
11164
