Protoss_Gateway 3 8997
Protoss_Assimilator 1 2996
Protoss_Cybernetics_Core 1 3967
Protoss_Zealot 5 9198
Protoss_Dragoon 7 10110
Protoss_Robotics_Facility 1 7222
Protoss_Observatory 1 7801
Protoss_Shuttle 1 8455
Protoss_Observer 2 10278
10278
