Protoss_Gateway 3 10393
Protoss_Assimilator 1 2932
Protoss_Cybernetics_Core 1 3862
Protoss_Zealot 3 7794
Protoss_Dragoon 5 9898
Protoss_Citadel_of_Adun 2 6623
Protoss_Templar_Archives 1 7645
Protoss_Dark_Templar 2 8620
Protoss_Robotics_Facility 1 9489
Protoss_Nexus 1 10709
Protoss_Observatory 1 10259
10709
