Protoss_Gateway 3 10675
Protoss_Assimilator 1 2954
Protoss_Cybernetics_Core 1 3848
Protoss_Dragoon 6 10064
Protoss_Robotics_Facility 1 6742
Protoss_Zealot 2 9312
Protoss_Shuttle 1 7929
Protoss_Robotics_Support_Bay 1 7524
Protoss_Reaver 1 8980
Protoss_Observatory 1 8850
Protoss_Observer 2 10534
Protoss_Nexus 1 11389
11389
