Protoss_Gateway 2 8633
Protoss_Assimilator 1 3145
Protoss_Cybernetics_Core 1 4249
Protoss_Dragoon 7 9583
Protoss_Robotics_Facility 1 6818
Protoss_Shuttle 1 7862
Protoss_Observatory 1 7526
Protoss_Observer 2 9233
Protoss_Robotics_Support_Bay 1 8636
Protoss_Reaver 1 10491
10491
