Protoss_Gateway 5 10674
Protoss_Assimilator 1 2881
Protoss_Cybernetics_Core 1 3770
Protoss_Dragoon 11 10143
Protoss_Nexus 2 10903
Protoss_Robotics_Facility 1 8932
Protoss_Observatory 1 9482
Protoss_Observer 1 10198
10903
