Protoss_Gateway 1 2776
Protoss_Assimilator 1 2939
Protoss_Cybernetics_Core 1 3860
Protoss_Robotics_Facility 1 5282
Protoss_Zealot 1 4850
Protoss_Dragoon 5 10550
Protoss_Shuttle 1 6263
Protoss_Robotics_Support_Bay 1 5957
Protoss_Reaver 2 8366
Protoss_Observatory 1 8346
Protoss_Observer 1 9450
10550
