Protoss_Gateway 2 4408
Protoss_Assimilator 1 3032
Protoss_Cybernetics_Core 1 3859
Protoss_Dragoon 8 10273
Protoss_Robotics_Facility 1 7043
Protoss_Zealot 6 9521
Protoss_Shuttle 1 8152
Protoss_Nexus 1 11720
11720
