Protoss_Gateway 3 10195
Protoss_Assimilator 1 2792
Protoss_Cybernetics_Core 1 3785
Protoss_Dragoon 10 10312
Protoss_Robotics_Facility 1 6695
Protoss_Observatory 1 7318
Protoss_Observer 4 10326
Protoss_Nexus 1 10279
10326
