Protoss_Assimilator 1 2330
Protoss_Gateway 2 7278
Protoss_Cybernetics_Core 1 4005
Protoss_Dragoon 2 6248
Protoss_Robotics_Facility 1 5932
Protoss_Citadel_of_Adun 1 6074
Protoss_Templar_Archives 1 7231
Protoss_Observatory 1 7105
Protoss_Zealot 3 9533
Protoss_Observer 1 7793
Protoss_Dark_Templar 1 8183
Protoss_Shuttle 1 8694
Protoss_High_Templar 1 8908
9533
