Protoss_Gateway 2 9441
Protoss_Assimilator 1 3039
Protoss_Cybernetics_Core 1 3961
Protoss_Zealot 2 8040
Protoss_Dragoon 6 10408
Protoss_Robotics_Facility 1 5825
Protoss_Observatory 1 6409
Protoss_Shuttle 1 7159
Protoss_Robotics_Support_Bay 1 7299
Protoss_Observer 2 10024
Protoss_Reaver 1 9272
Protoss_Nexus 1 11159
11159
