Protoss_Gateway 3 8955
Protoss_Assimilator 1 3029
Protoss_Cybernetics_Core 1 3834
Protoss_Dragoon 13 10703
Protoss_Nexus 1 8697
Protoss_Robotics_Facility 1 8755
Protoss_Observatory 1 9488
Protoss_Observer 1 10178
10703
