Protoss_Gateway 2 6968
Protoss_Assimilator 1 2816
Protoss_Cybernetics_Core 1 3769
Protoss_Dragoon 6 10608
Protoss_Citadel_of_Adun 1 6114
Protoss_Templar_Archives 1 7114
Protoss_Dark_Templar 6 9873
Protoss_Nexus 2 11280
11280
