Protoss_Nexus 2 10825
Protoss_Gateway 3 7233
Protoss_Assimilator 1 3920
Protoss_Cybernetics_Core 1 5014
Protoss_Dragoon 8 10213
Protoss_Robotics_Facility 1 8124
Protoss_Zealot 2 7763
Protoss_Shuttle 1 9162
Protoss_Robotics_Support_Bay 1 9023
Protoss_Reaver 1 10266
Protoss_Observatory 1 10187
10825
