Protoss_Gateway 2 4663
Protoss_Assimilator 1 2880
Protoss_Cybernetics_Core 1 3811
Protoss_Dragoon 10 10118
Protoss_Zealot 3 7883
Protoss_Nexus 2 10570
Protoss_Robotics_Facility 1 10362
10570
