Protoss_Gateway 3 9929
Protoss_Assimilator 1 2824
Protoss_Cybernetics_Core 1 3880
Protoss_Dragoon 8 9432
Protoss_Robotics_Facility 1 7171
Protoss_Shuttle 1 8395
Protoss_Robotics_Support_Bay 1 7971
Protoss_Zealot 4 10496
Protoss_Reaver 2 10516
10516
