Protoss_Gateway 2 8033
Protoss_Assimilator 1 3201
Protoss_Cybernetics_Core 1 4253
Protoss_Dragoon 7 10422
Protoss_Robotics_Facility 1 5866
Protoss_Zealot 2 6302
Protoss_Shuttle 1 6857
Protoss_Robotics_Support_Bay 1 6531
Protoss_Reaver 1 7908
Protoss_Observatory 1 7781
Protoss_Observer 1 8633
10422
