Protoss_Gateway 2 6635
Protoss_Assimilator 1 3030
Protoss_Cybernetics_Core 1 3974
Protoss_Dragoon 9 10732
Protoss_Citadel_of_Adun 1 5415
Protoss_Templar_Archives 1 6401
Protoss_Zealot 2 9054
Protoss_Dark_Templar 2 7492
10732
