Protoss_Gateway 4 10273
Protoss_Assimilator 1 2972
Protoss_Cybernetics_Core 1 3849
Protoss_Dragoon 10 9918
Protoss_Nexus 1 8191
Protoss_Robotics_Facility 1 8346
Protoss_Observatory 1 9063
Protoss_Observer 1 10116
Protoss_Citadel_of_Adun 1 10511
10511
