Protoss_Gateway 3 10631
Protoss_Assimilator 1 2813
Protoss_Cybernetics_Core 1 3849
Protoss_Dragoon 10 10108
Protoss_Robotics_Facility 1 6730
Protoss_Observatory 1 7271
Protoss_Observer 3 9260
Protoss_Nexus 2 11009
11009
