Protoss_Gateway 2 6495
Protoss_Nexus 1 5275
Protoss_Assimilator 1 4224
Protoss_Cybernetics_Core 1 5370
Protoss_Zealot 9 10318
Protoss_Dragoon 7 10728
Protoss_Shield_Battery 1 6801
10728
