Protoss_Gateway 3 9433
Protoss_Assimilator 1 2977
Protoss_Cybernetics_Core 1 4031
Protoss_Dragoon 11 10384
Protoss_Robotics_Facility 1 6947
Protoss_Observatory 1 7506
Protoss_Nexus 1 9258
Protoss_Observer 2 9004
Protoss_Shuttle 1 10261
Protoss_Robotics_Support_Bay 1 9888
10384
