Protoss_Gateway 2 6240
Protoss_Assimilator 2 3471
Protoss_Cybernetics_Core 1 4575
Protoss_Dragoon 6 8288
Protoss_Citadel_of_Adun 1 7595
Protoss_Templar_Archives 1 8679
Protoss_Dark_Templar 4 10293
10293
