Protoss_Gateway 2 4329
Protoss_Assimilator 1 2837
Protoss_Cybernetics_Core 1 3764
Protoss_Dragoon 7 9456
Protoss_Citadel_of_Adun 1 6015
Protoss_Zealot 1 6200
Protoss_Templar_Archives 1 7085
Protoss_Dark_Templar 5 10404
10404
