Protoss_Gateway 1 2783
Protoss_Assimilator 1 2868
Protoss_Cybernetics_Core 1 3903
Protoss_Dragoon 6 10402
Protoss_Robotics_Facility 1 5817
Protoss_Shuttle 1 6859
Protoss_Robotics_Support_Bay 1 6631
Protoss_Zealot 2 7860
Protoss_Reaver 2 9045
10402
