Protoss_Gateway 2 6930
Protoss_Assimilator 1 2830
Protoss_Cybernetics_Core 1 3787
Protoss_Dragoon 10 9906
Protoss_Robotics_Facility 1 6547
Protoss_Observatory 1 7115
Protoss_Observer 2 8398
Protoss_Nexus 1 9777
9906
