Protoss_Nexus 2 10685
Protoss_Gateway 3 7107
Protoss_Assimilator 2 9668
Protoss_Cybernetics_Core 1 5099
Protoss_Zealot 5 8767
Protoss_Dragoon 6 8165
Protoss_Robotics_Facility 1 8361
Protoss_Shuttle 1 9667
Protoss_Robotics_Support_Bay 1 9244
Protoss_Citadel_of_Adun 1 10468
Protoss_Reaver 1 10991
10991
