Protoss_Gateway 3 10118
Protoss_Assimilator 1 2954
Protoss_Cybernetics_Core 1 3749
Protoss_Dragoon 9 10180
Protoss_Nexus 2 10130
Protoss_Robotics_Facility 1 9939
Protoss_Citadel_of_Adun 1 10073
10180
