Protoss_Gateway 4 10885
Protoss_Assimilator 1 2825
Protoss_Cybernetics_Core 1 3881
Protoss_Zealot 1 3703
Protoss_Dragoon 11 10660
Protoss_Robotics_Facility 1 7292
Protoss_Observatory 1 7861
Protoss_Nexus 2 10710
Protoss_Observer 2 9150
10885
