Protoss_Gateway 3 9300
Protoss_Assimilator 1 2840
Protoss_Cybernetics_Core 1 3809
Protoss_Zealot 1 3713
Protoss_Dragoon 8 10298
Protoss_Nexus 2 10735
Protoss_Robotics_Facility 1 8287
Protoss_Observatory 1 8909
Protoss_Observer 1 9758
10735
