Protoss_Gateway 3 8003
Protoss_Assimilator 1 3080
Protoss_Cybernetics_Core 1 4130
Protoss_Robotics_Facility 1 5522
Protoss_Dragoon 8 10178
Protoss_Observatory 1 6222
Protoss_Observer 3 8338
Protoss_Citadel_of_Adun 1 9426
Protoss_Templar_Archives 1 10659
Protoss_Shuttle 1 10872
10872
