Protoss_Nexus 1 4557
Protoss_Gateway 2 5634
Protoss_Assimilator 2 8757
Protoss_Cybernetics_Core 1 4955
Protoss_Dragoon 8 8878
Protoss_Robotics_Facility 1 8853
Protoss_Stargate 1 9535
Protoss_Observatory 1 9464
Protoss_Fleet_Beacon 1 10548
10548
