Protoss_Nexus 1 4498
Protoss_Gateway 6 10569
Protoss_Assimilator 2 9083
Protoss_Cybernetics_Core 1 5129
Protoss_Zealot 5 9863
Protoss_Dragoon 7 9085
Protoss_Robotics_Facility 1 8252
Protoss_Observatory 1 8801
Protoss_Observer 2 10090
Protoss_Citadel_of_Adun 1 10508
10569
