Protoss_Gateway 2 5241
Protoss_Assimilator 1 2954
Protoss_Cybernetics_Core 1 3831
Protoss_Dragoon 4 9522
Protoss_Citadel_of_Adun 1 6679
Protoss_Robotics_Facility 1 7351
Protoss_Templar_Archives 1 7751
Protoss_Shuttle 1 8451
Protoss_Dark_Templar 3 9340
Protoss_Nexus 1 10199
10199
