Protoss_Gateway 2 4206
Protoss_Assimilator 1 2840
Protoss_Cybernetics_Core 1 3765
Protoss_Dragoon 5 6764
Protoss_Citadel_of_Adun 1 6487
Protoss_Zealot 1 6414
Protoss_Templar_Archives 1 7500
Protoss_Dark_Templar 4 10044
Protoss_Nexus 1 10137
Protoss_Robotics_Facility 1 9907
Protoss_Shuttle 1 10889
10889
