Protoss_Gateway 2 6283
Protoss_Assimilator 1 3162
Protoss_Cybernetics_Core 1 4142
Protoss_Dragoon 9 10734
Protoss_Robotics_Facility 1 6239
Protoss_Observatory 1 6834
Protoss_Observer 2 8352
Protoss_Nexus 1 10729
Protoss_Citadel_of_Adun 1 10471
10734
