Protoss_Gateway 2 4593
Protoss_Assimilator 1 3048
Protoss_Cybernetics_Core 1 3993
Protoss_Dragoon 10 10550
Protoss_Nexus 2 10101
Protoss_Robotics_Facility 1 9727
Protoss_Shuttle 1 10761
Protoss_Robotics_Support_Bay 1 10417
10761
