Protoss_Nexus 2 10374
Protoss_Gateway 4 10869
Protoss_Assimilator 2 9733
Protoss_Zealot 2 5478
Protoss_Cybernetics_Core 1 5602
Protoss_Dragoon 13 10443
Protoss_Citadel_of_Adun 1 9823
10869
