Protoss_Gateway 2 9025
Protoss_Assimilator 1 2934
Protoss_Cybernetics_Core 1 3855
Protoss_Zealot 4 9746
Protoss_Dragoon 7 10498
Protoss_Nexus 1 8195
Protoss_Robotics_Facility 1 7945
Protoss_Observatory 1 8539
Protoss_Observer 2 9820
10498
