Protoss_Gateway 2 7521
Protoss_Assimilator 1 2990
Protoss_Cybernetics_Core 1 4032
Protoss_Zealot 1 3958
Protoss_Dragoon 6 9593
Protoss_Robotics_Facility 1 7209
Protoss_Shield_Battery 1 7881
9593
