Protoss_Nexus 1 4680
Protoss_Gateway 3 7399
Protoss_Assimilator 2 9881
Protoss_Cybernetics_Core 1 5279
Protoss_Zealot 5 10013
Protoss_Dragoon 8 9948
Protoss_Robotics_Facility 1 7222
Protoss_Shield_Battery 1 7736
Protoss_Shuttle 1 9787
Protoss_Robotics_Support_Bay 1 9471
Protoss_Reaver 1 10838
10838
