Protoss_Gateway 3 10869
Protoss_Assimilator 1 3015
Protoss_Cybernetics_Core 1 4001
Protoss_Dragoon 8 10198
Protoss_Robotics_Facility 1 8317
Protoss_Nexus 1 9935
Protoss_Shuttle 1 9462
Protoss_Robotics_Support_Bay 1 9341
Protoss_Observatory 1 9386
Protoss_Zealot 2 10173
Protoss_Reaver 1 10726
10869
