Protoss_Assimilator 3 4388
Protoss_Gateway 2 6256
Protoss_Cybernetics_Core 1 4449
Protoss_Dragoon 10 10572
Protoss_Nexus 1 9061
Protoss_Robotics_Facility 1 9226
Protoss_Observatory 1 9791
10572
