Protoss_Gateway 4 10712
Protoss_Assimilator 1 3031
Protoss_Cybernetics_Core 1 3969
Protoss_Dragoon 10 9993
Protoss_Nexus 1 8032
Protoss_Robotics_Facility 1 8767
Protoss_Observatory 1 9494
Protoss_Observer 1 10258
10712
