Protoss_Gateway 2 7739
Protoss_Assimilator 1 2870
Protoss_Cybernetics_Core 1 4017
Protoss_Dragoon 3 6758
Protoss_Robotics_Facility 1 5960
Protoss_Citadel_of_Adun 1 6858
Protoss_Templar_Archives 1 7889
Protoss_Dark_Templar 4 9500
Protoss_Shuttle 1 8977
Protoss_Nexus 1 11195
Protoss_Observatory 1 10226
11195
