Protoss_Gateway 3 10087
Protoss_Assimilator 1 3011
Protoss_Cybernetics_Core 1 3818
Protoss_Dragoon 9 10522
Protoss_Nexus 2 10492
Protoss_Robotics_Facility 1 7547
Protoss_Observatory 1 8764
Protoss_Observer 2 10046
Protoss_Citadel_of_Adun 1 10790
10790
