Protoss_Gateway 3 9661
Protoss_Assimilator 1 2910
Protoss_Cybernetics_Core 1 3838
Protoss_Dragoon 13 10498
Protoss_Robotics_Facility 1 8445
Protoss_Nexus 1 9330
Protoss_Observatory 1 9040
Protoss_Observer 2 10345
10498
