Protoss_Gateway 4 10492
Protoss_Assimilator 1 3040
Protoss_Cybernetics_Core 1 4026
Protoss_Dragoon 7 9782
Protoss_Nexus 1 7885
Protoss_Robotics_Facility 1 8307
Protoss_Zealot 5 10578
Protoss_Observatory 1 9024
Protoss_Citadel_of_Adun 1 9626
Protoss_Observer 2 10325
Protoss_Templar_Archives 1 10799
10799
