Protoss_Gateway 2 3280
Protoss_Zealot 14 8493
Protoss_Forge 1 4363
Protoss_Photon_Cannon 4 6090
Protoss_Assimilator 1 7446
Protoss_Cybernetics_Core 1 8519
Protoss_Dragoon 4 10458
10458
