Protoss_Gateway 3 8095
Protoss_Assimilator 1 3040
Protoss_Zealot 7 10593
Protoss_Cybernetics_Core 1 4874
Protoss_Dragoon 11 9970
Protoss_Robotics_Facility 1 7412
Protoss_Observatory 1 7975
Protoss_Observer 2 9413
Protoss_Shuttle 1 10497
10593
