Protoss_Gateway 3 9739
Protoss_Assimilator 1 2896
Protoss_Cybernetics_Core 1 3829
Protoss_Dragoon 11 10598
Protoss_Nexus 2 11265
Protoss_Robotics_Facility 1 9396
Protoss_Observatory 1 9998
11265
