Protoss_Gateway 4 10880
Protoss_Assimilator 2 9930
Protoss_Cybernetics_Core 1 3884
Protoss_Dragoon 9 10313
Protoss_Nexus 2 10433
Protoss_Robotics_Facility 1 8257
Protoss_Observatory 1 8907
Protoss_Observer 2 10265
10880
