Protoss_Gateway 3 10768
Protoss_Assimilator 1 2995
Protoss_Cybernetics_Core 1 3983
Protoss_Dragoon 7 10193
Protoss_Robotics_Facility 1 7487
Protoss_Nexus 3 10070
Protoss_Observatory 1 8821
Protoss_Observer 2 10490
10768
