Protoss_Gateway 3 9481
Protoss_Assimilator 1 2800
Protoss_Cybernetics_Core 1 3724
Protoss_Dragoon 9 10356
Protoss_Zealot 2 7134
Protoss_Citadel_of_Adun 1 6655
Protoss_Templar_Archives 1 7659
Protoss_Dark_Templar 2 8672
Protoss_Nexus 1 9977
10356
