Protoss_Gateway 1 2780
Protoss_Assimilator 1 2830
Protoss_Cybernetics_Core 1 3817
Protoss_Dragoon 7 10390
Protoss_Robotics_Facility 1 6652
Protoss_Shuttle 1 7647
Protoss_Observatory 1 7271
Protoss_Observer 2 8852
Protoss_Nexus 1 9990
10390
