Protoss_Gateway 5 10477
Protoss_Assimilator 1 2936
Protoss_Cybernetics_Core 1 3859
Protoss_Dragoon 10 9462
Protoss_Robotics_Facility 1 6847
Protoss_Observatory 1 7466
Protoss_Observer 2 8755
Protoss_Citadel_of_Adun 1 10309
Protoss_Zealot 2 10118
10477
