Protoss_Gateway 3 9220
Protoss_Assimilator 1 3188
Protoss_Cybernetics_Core 1 4188
Protoss_Zealot 1 4792
Protoss_Dragoon 9 10182
Protoss_Robotics_Facility 1 7237
Protoss_Nexus 2 11563
Protoss_Observatory 1 7867
Protoss_Observer 1 8568
11563
