Protoss_Gateway 4 10477
Protoss_Assimilator 1 2863
Protoss_Cybernetics_Core 1 3810
Protoss_Dragoon 8 9573
Protoss_Nexus 2 9979
Protoss_Robotics_Facility 1 8512
Protoss_Observatory 1 9076
Protoss_Observer 1 10363
10477
