Protoss_Gateway 2 10406
Protoss_Assimilator 1 2910
Protoss_Cybernetics_Core 1 3878
Protoss_Dragoon 5 10048
Protoss_Robotics_Facility 1 5736
Protoss_Zealot 3 7154
Protoss_Shuttle 1 6721
Protoss_Robotics_Support_Bay 1 6498
Protoss_Reaver 1 7824
Protoss_Nexus 1 9769
Protoss_Observatory 1 9207
Protoss_Observer 1 10098
10406
