Protoss_Gateway 4 9718
Protoss_Zealot 2 4966
Protoss_Nexus 2 9431
Protoss_Assimilator 2 8786
Protoss_Forge 1 5612
Protoss_Cybernetics_Core 1 6577
Protoss_Photon_Cannon 1 6772
Protoss_Dragoon 4 10568
Protoss_Citadel_of_Adun 1 7779
Protoss_Templar_Archives 1 8959
Protoss_Dark_Templar 2 10098
10568
