Protoss_Gateway 4 7474
Protoss_Assimilator 1 3103
Protoss_Cybernetics_Core 1 4065
Protoss_Dragoon 3 8313
Protoss_Citadel_of_Adun 1 5241
Protoss_Templar_Archives 1 6250
Protoss_Dark_Templar 4 9373
Protoss_Robotics_Facility 1 8187
Protoss_Shuttle 1 9407
9407
