Protoss_Assimilator 1 2442
Protoss_Gateway 4 10476
Protoss_Cybernetics_Core 1 4204
Protoss_Dragoon 11 10708
Protoss_Robotics_Facility 1 5693
Protoss_Observatory 1 6564
Protoss_Observer 3 10238
Protoss_Nexus 1 10487
10708
