Protoss_Gateway 3 10242
Protoss_Assimilator 1 3150
Protoss_Cybernetics_Core 1 4010
Protoss_Dragoon 10 10268
Protoss_Robotics_Facility 1 6042
Protoss_Observatory 1 6591
Protoss_Observer 2 7931
Protoss_Shuttle 1 10177
Protoss_Zealot 1 10108
10268
