Protoss_Gateway 2 5699
Protoss_Zealot 3 8990
Protoss_Nexus 1 5345
Protoss_Cybernetics_Core 1 5011
Protoss_Assimilator 2 7415
Protoss_Dragoon 8 10210
Protoss_Robotics_Facility 1 9441
10210
