Protoss_Gateway 3 4409
Protoss_Assimilator 1 2995
Protoss_Cybernetics_Core 1 3884
Protoss_Dragoon 8 10205
Protoss_Nexus 1 7875
Protoss_Robotics_Facility 1 8717
Protoss_Zealot 3 10535
Protoss_Observatory 1 9452
Protoss_Observer 1 10273
10535
