Protoss_Gateway 3 8204
Protoss_Assimilator 1 3000
Protoss_Cybernetics_Core 1 4179
Protoss_Dragoon 11 9957
Protoss_Nexus 1 7971
Protoss_Robotics_Facility 1 7605
Protoss_Observatory 1 8903
Protoss_Observer 2 10190
10190
