Protoss_Gateway 3 10590
Protoss_Assimilator 1 2840
Protoss_Cybernetics_Core 1 4074
Protoss_Dragoon 12 10624
Protoss_Robotics_Facility 1 6547
Protoss_Observatory 1 7125
Protoss_Observer 2 8428
Protoss_Nexus 1 10027
Protoss_Shuttle 1 10507
10624
