Protoss_Gateway 1 2723
Protoss_Assimilator 3 8170
Protoss_Zealot 6 6788
Protoss_Nexus 1 6962
Protoss_Forge 1 6266
Protoss_Photon_Cannon 1 7287
Protoss_Cybernetics_Core 1 8700
Protoss_Robotics_Facility 1 10148
Protoss_Dragoon 2 10644
10644
