Protoss_Nexus 2 10159
Protoss_Gateway 5 10488
Protoss_Assimilator 1 4241
Protoss_Cybernetics_Core 1 5538
Protoss_Dragoon 7 9408
Protoss_Robotics_Facility 1 8167
Protoss_Observatory 1 8947
Protoss_Shuttle 1 9942
Protoss_Forge 1 10275
Protoss_Citadel_of_Adun 1 10689
10689
