Protoss_Gateway 3 7069
Protoss_Assimilator 1 3029
Protoss_Cybernetics_Core 1 3977
Protoss_Dragoon 13 10428
Protoss_Robotics_Facility 1 6733
Protoss_Observatory 1 7350
Protoss_Observer 1 8700
Protoss_Nexus 1 11037
11037
