Protoss_Gateway 4 9456
Protoss_Nexus 1 5051
Protoss_Assimilator 2 10394
Protoss_Cybernetics_Core 1 4863
Protoss_Zealot 1 4954
Protoss_Dragoon 9 10476
Protoss_Robotics_Facility 1 8478
Protoss_Observatory 1 9140
Protoss_Shuttle 1 9593
Protoss_Robotics_Support_Bay 1 9918
Protoss_Observer 1 10196
10476
