Protoss_Gateway 2 7149
Protoss_Assimilator 1 2986
Protoss_Cybernetics_Core 1 3919
Protoss_Dragoon 4 10722
Protoss_Robotics_Facility 1 6713
Protoss_Nexus 2 11591
Protoss_Observatory 1 7379
Protoss_Shuttle 1 8489
Protoss_Robotics_Support_Bay 1 8452
Protoss_Reaver 1 9632
Protoss_Zealot 2 9666
Protoss_Observer 1 10236
11591
