Protoss_Assimilator 1 2398
Protoss_Gateway 3 7473
Protoss_Cybernetics_Core 1 4081
Protoss_Dragoon 11 9438
Protoss_Robotics_Facility 1 6437
Protoss_Observatory 1 7129
Protoss_Observer 1 7910
Protoss_Citadel_of_Adun 1 8271
Protoss_Nexus 1 10880
Protoss_Templar_Archives 1 10194
10880
