Protoss_Gateway 2 9556
Protoss_Zealot 6 6159
Protoss_Assimilator 1 4416
Protoss_Cybernetics_Core 1 5834
Protoss_Citadel_of_Adun 1 7000
Protoss_Dragoon 3 8328
Protoss_Templar_Archives 1 8156
Protoss_Nexus 1 9988
Protoss_Dark_Templar 2 9832
Protoss_Stargate 1 10347
10347
