Protoss_Gateway 2 6629
Protoss_Assimilator 1 3048
Protoss_Cybernetics_Core 1 3900
Protoss_Dragoon 6 10348
Protoss_Citadel_of_Adun 1 5229
Protoss_Templar_Archives 1 6239
Protoss_Dark_Templar 3 8240
Protoss_Zealot 1 7690
Protoss_Nexus 1 9990
Protoss_Forge 1 10579
10579
