Protoss_Gateway 2 7083
Protoss_Assimilator 2 8235
Protoss_Cybernetics_Core 1 3765
Protoss_Dragoon 6 10606
Protoss_Nexus 1 7441
Protoss_Robotics_Facility 1 7749
Protoss_Shuttle 1 8773
Protoss_Robotics_Support_Bay 1 8630
Protoss_Zealot 3 9914
Protoss_Reaver 1 9984
Protoss_Observatory 1 10080
10606
