Protoss_Nexus 1 4588
Protoss_Gateway 3 7609
Protoss_Assimilator 1 4005
Protoss_Zealot 1 4818
Protoss_Cybernetics_Core 1 5187
Protoss_Dragoon 13 10688
Protoss_Robotics_Facility 1 8880
Protoss_Citadel_of_Adun 1 8901
10688
