Protoss_Gateway 3 9909
Protoss_Assimilator 1 2989
Protoss_Cybernetics_Core 1 3873
Protoss_Dragoon 11 10068
Protoss_Citadel_of_Adun 1 6194
Protoss_Robotics_Facility 1 6857
Protoss_Observatory 1 7763
Protoss_Observer 3 9715
Protoss_Nexus 2 10864
10864
