Protoss_Gateway 3 9149
Protoss_Assimilator 2 9814
Protoss_Cybernetics_Core 1 3750
Protoss_Dragoon 8 10598
Protoss_Robotics_Facility 1 6535
Protoss_Shuttle 1 7597
Protoss_Robotics_Support_Bay 1 7282
Protoss_Nexus 1 9029
Protoss_Reaver 1 8648
Protoss_Observatory 1 8901
Protoss_Observer 1 9640
10598
