Protoss_Gateway 3 8629
Protoss_Zealot 1 3536
Protoss_Assimilator 2 9708
Protoss_Cybernetics_Core 1 4551
Protoss_Dragoon 9 10332
Protoss_Nexus 1 8605
Protoss_Robotics_Facility 1 9476
10332
