Protoss_Gateway 4 9950
Protoss_Assimilator 1 3100
Protoss_Cybernetics_Core 1 4095
Protoss_Dragoon 4 8823
Protoss_Robotics_Facility 1 6052
Protoss_Observatory 1 6746
Protoss_Observer 3 9383
Protoss_Nexus 1 8930
Protoss_Zealot 3 10078
Protoss_Shuttle 1 10284
10284
