Protoss_Gateway 4 10799
Protoss_Assimilator 1 3014
Protoss_Cybernetics_Core 1 3899
Protoss_Dragoon 7 9176
Protoss_Robotics_Facility 1 7066
Protoss_Observatory 1 7607
Protoss_Nexus 2 11199
Protoss_Observer 2 8946
11199
