Protoss_Gateway 2 4517
Protoss_Assimilator 1 3072
Protoss_Cybernetics_Core 1 3973
Protoss_Dragoon 9 9408
Protoss_Zealot 2 7128
Protoss_Robotics_Facility 1 8927
Protoss_Shuttle 1 9979
Protoss_Robotics_Support_Bay 1 9641
9979
