Protoss_Nexus 1 4443
Protoss_Gateway 4 10296
Protoss_Assimilator 2 8773
Protoss_Cybernetics_Core 1 4997
Protoss_Zealot 5 9904
Protoss_Dragoon 10 9272
Protoss_Robotics_Facility 1 8324
Protoss_Observatory 1 9324
10296
