Protoss_Gateway 2 4624
Protoss_Assimilator 1 2822
Protoss_Cybernetics_Core 1 3723
Protoss_Dragoon 11 9488
Protoss_Zealot 2 6828
Protoss_Robotics_Facility 1 8875
Protoss_Shuttle 1 9897
Protoss_Robotics_Support_Bay 1 9812
Protoss_Observatory 1 10130
Protoss_Reaver 1 10948
10948
