Protoss_Gateway 2 5229
Protoss_Assimilator 1 2972
Protoss_Cybernetics_Core 1 4105
Protoss_Dragoon 2 6288
Protoss_Citadel_of_Adun 1 6079
Protoss_Robotics_Facility 1 7072
Protoss_Templar_Archives 1 7109
Protoss_Shuttle 1 8062
Protoss_Dark_Templar 8 10738
10738
