Protoss_Gateway 2 4341
Protoss_Assimilator 1 2847
Protoss_Cybernetics_Core 1 3843
Protoss_Dragoon 10 10056
Protoss_Zealot 2 8162
Protoss_Nexus 1 9197
Protoss_Robotics_Facility 1 9141
Protoss_Shuttle 1 10355
Protoss_Robotics_Support_Bay 1 10130
10355
