Protoss_Gateway 2 6942
Protoss_Assimilator 1 3007
Protoss_Cybernetics_Core 1 3939
Protoss_Dragoon 10 10196
Protoss_Robotics_Facility 1 6667
Protoss_Observatory 1 7269
Protoss_Observer 2 9938
Protoss_Nexus 1 9841
10196
