Protoss_Gateway 2 4241
Protoss_Assimilator 1 2967
Protoss_Cybernetics_Core 1 3765
Protoss_Dragoon 5 9326
Protoss_Robotics_Facility 1 7037
Protoss_Zealot 5 8104
Protoss_Shuttle 1 8021
Protoss_Robotics_Support_Bay 1 7858
Protoss_Reaver 1 9144
Protoss_Nexus 1 11132
11132
