Protoss_Gateway 4 10773
Protoss_Assimilator 1 3015
Protoss_Cybernetics_Core 1 4022
Protoss_Dragoon 8 9372
Protoss_Robotics_Facility 1 6558
Protoss_Observatory 1 7131
Protoss_Observer 5 10350
Protoss_Nexus 2 10951
Protoss_Citadel_of_Adun 1 10853
10951
