Protoss_Gateway 5 10615
Protoss_Assimilator 1 3053
Protoss_Cybernetics_Core 1 3925
Protoss_Dragoon 8 10648
Protoss_Robotics_Facility 1 6874
Protoss_Observatory 1 7441
Protoss_Observer 3 9348
Protoss_Nexus 2 10761
10761
