Protoss_Gateway 3 7803
Protoss_Assimilator 1 2845
Protoss_Cybernetics_Core 1 3808
Protoss_Dragoon 11 10184
Protoss_Nexus 1 7717
Protoss_Robotics_Facility 1 8987
Protoss_Zealot 1 10048
Protoss_Shuttle 1 10375
Protoss_Observatory 1 9947
10375
