Protoss_Gateway 3 7553
Protoss_Assimilator 1 3029
Protoss_Cybernetics_Core 1 3943
Protoss_Dragoon 10 10660
Protoss_Nexus 1 7897
Protoss_Zealot 3 9596
Protoss_Robotics_Facility 1 9445
Protoss_Observatory 1 10049
10660
