Protoss_Gateway 2 7978
Protoss_Assimilator 1 2830
Protoss_Cybernetics_Core 1 3867
Protoss_Dragoon 6 9312
Protoss_Nexus 2 11411
Protoss_Robotics_Facility 1 7757
Protoss_Shuttle 1 8737
Protoss_Observatory 1 8322
Protoss_Robotics_Support_Bay 1 8466
Protoss_Observer 1 9340
Protoss_Reaver 1 10437
Protoss_Zealot 2 10432
11411
