Protoss_Gateway 2 5309
Protoss_Assimilator 1 2840
Protoss_Cybernetics_Core 1 3869
Protoss_Dragoon 8 9223
Protoss_Robotics_Facility 1 7337
Protoss_Shuttle 1 8327
Protoss_Robotics_Support_Bay 1 8081
Protoss_Reaver 2 10916
Protoss_Zealot 2 10143
10916
