Protoss_Assimilator 2 10506
Protoss_Gateway 2 6914
Protoss_Cybernetics_Core 1 4217
Protoss_Dragoon 5 10170
Protoss_Robotics_Facility 1 6595
Protoss_Citadel_of_Adun 1 6445
Protoss_Templar_Archives 1 7433
Protoss_Shuttle 1 7771
Protoss_Dark_Templar 3 9032
Protoss_Observatory 1 8581
Protoss_Nexus 1 10491
Protoss_Observer 1 9370
10506
