Protoss_Gateway 2 9152
Protoss_Assimilator 1 2939
Protoss_Cybernetics_Core 1 4021
Protoss_Dragoon 7 10313
Protoss_Robotics_Facility 1 5858
Protoss_Shuttle 1 6857
Protoss_Observatory 1 6916
Protoss_Robotics_Support_Bay 1 7380
Protoss_Observer 2 10414
Protoss_Reaver 2 9810
10414
