Protoss_Gateway 4 9941
Protoss_Assimilator 1 3063
Protoss_Cybernetics_Core 1 4000
Protoss_Dragoon 8 9028
Protoss_Nexus 1 7705
Protoss_Robotics_Facility 1 8625
Protoss_Shuttle 1 9655
Protoss_Robotics_Support_Bay 1 9531
Protoss_Reaver 1 10706
10706
