Protoss_Gateway 2 4295
Protoss_Assimilator 1 2929
Protoss_Cybernetics_Core 1 3713
Protoss_Dragoon 8 10448
Protoss_Nexus 1 8043
Protoss_Robotics_Facility 1 7925
Protoss_Shuttle 1 9003
Protoss_Robotics_Support_Bay 1 8637
Protoss_Reaver 1 10164
Protoss_Observatory 1 10414
10448
