Protoss_Gateway 5 10434
Protoss_Assimilator 1 2910
Protoss_Cybernetics_Core 1 3964
Protoss_Dragoon 7 10623
Protoss_Zealot 1 7360
Protoss_Nexus 2 10133
Protoss_Robotics_Facility 1 9827
10623
