Protoss_Gateway 5 10851
Protoss_Assimilator 2 9503
Protoss_Cybernetics_Core 1 3753
Protoss_Dragoon 4 6844
Protoss_Citadel_of_Adun 1 6104
Protoss_Templar_Archives 1 7123
Protoss_Nexus 2 10253
Protoss_Dark_Templar 2 8758
Protoss_Robotics_Facility 1 8787
Protoss_Observatory 1 9744
10851
