Protoss_Gateway 2 6811
Protoss_Assimilator 1 2838
Protoss_Cybernetics_Core 1 3931
Protoss_Dragoon 8 8520
Protoss_Robotics_Facility 1 6452
Protoss_Observatory 1 7027
Protoss_Observer 1 7720
Protoss_Nexus 1 9859
Protoss_Shuttle 1 9225
Protoss_Robotics_Support_Bay 1 9189
Protoss_Reaver 1 10430
Protoss_Zealot 2 10250
10430
