Protoss_Gateway 4 10434
Protoss_Assimilator 1 2804
Protoss_Cybernetics_Core 1 3815
Protoss_Zealot 1 3770
Protoss_Dragoon 9 10600
Protoss_Robotics_Facility 1 6959
Protoss_Observatory 1 7552
Protoss_Nexus 2 11738
Protoss_Observer 2 9176
11738
