Protoss_Gateway 2 10226
Protoss_Assimilator 2 9046
Protoss_Cybernetics_Core 1 3831
Protoss_Dragoon 5 8616
Protoss_Nexus 2 11748
Protoss_Robotics_Facility 1 7311
Protoss_Shuttle 1 8489
Protoss_Robotics_Support_Bay 1 8083
Protoss_Reaver 1 9778
Protoss_Observatory 1 9437
Protoss_Zealot 1 9972
Protoss_Observer 1 10382
11748
