Protoss_Gateway 4 10437
Protoss_Assimilator 1 2798
Protoss_Cybernetics_Core 1 3773
Protoss_Dragoon 11 10592
Protoss_Nexus 1 8906
Protoss_Robotics_Facility 1 8788
Protoss_Observatory 1 9335
Protoss_Observer 1 10016
10592
