Protoss_Gateway 2 6450
Protoss_Assimilator 2 9960
Protoss_Cybernetics_Core 1 3798
Protoss_Dragoon 9 10588
Protoss_Citadel_of_Adun 1 5881
Protoss_Templar_Archives 1 6890
Protoss_Dark_Templar 2 7738
Protoss_Nexus 1 9104
Protoss_Robotics_Facility 1 10392
10588
