Protoss_Gateway 4 10641
Protoss_Assimilator 2 10073
Protoss_Cybernetics_Core 1 3802
Protoss_Dragoon 10 9630
Protoss_Nexus 1 7669
Protoss_Robotics_Facility 1 7778
Protoss_Observatory 1 8333
Protoss_Observer 1 9012
10641
