Protoss_Gateway 1 2918
Protoss_Assimilator 1 2996
Protoss_Cybernetics_Core 1 3933
Protoss_Zealot 2 7262
Protoss_Robotics_Facility 1 5348
Protoss_Dragoon 5 10720
Protoss_Shuttle 1 6427
Protoss_Robotics_Support_Bay 1 6159
Protoss_Reaver 1 7478
Protoss_Observatory 1 8321
Protoss_Observer 3 10206
Protoss_Nexus 1 11175
11175
