Protoss_Assimilator 2 6696
Protoss_Gateway 4 10494
Protoss_Zealot 3 8294
Protoss_Forge 1 4724
Protoss_Photon_Cannon 5 10722
Protoss_Nexus 2 8639
Protoss_Cybernetics_Core 1 8167
Protoss_Citadel_of_Adun 1 9270
Protoss_Dragoon 1 9162
Protoss_Templar_Archives 1 10604
10722
