Protoss_Gateway 2 5689
Protoss_Assimilator 1 2813
Protoss_Cybernetics_Core 1 3818
Protoss_Dragoon 9 9466
Protoss_Robotics_Facility 1 6958
Protoss_Shuttle 1 7979
Protoss_Robotics_Support_Bay 1 7581
Protoss_Observatory 1 8444
Protoss_Reaver 1 9216
Protoss_Nexus 1 11004
Protoss_Observer 1 10078
11004
