Protoss_Gateway 2 4559
Protoss_Assimilator 1 2802
Protoss_Cybernetics_Core 1 3950
Protoss_Dragoon 9 10068
Protoss_Nexus 1 8444
Protoss_Robotics_Facility 1 8541
Protoss_Citadel_of_Adun 1 8655
Protoss_Forge 1 9236
Protoss_Observatory 1 9562
Protoss_Observer 1 10260
10260
