Protoss_Gateway 2 5013
Protoss_Assimilator 1 3410
Protoss_Zealot 5 10116
Protoss_Cybernetics_Core 1 4668
Protoss_Dragoon 10 9274
Protoss_Nexus 1 10699
Protoss_Citadel_of_Adun 1 10348
10699
