Protoss_Nexus 1 4435
Protoss_Gateway 5 9364
Protoss_Assimilator 1 4044
Protoss_Cybernetics_Core 1 4989
Protoss_Dragoon 16 10736
Protoss_Robotics_Facility 1 8323
Protoss_Zealot 2 9704
10736
