Protoss_Nexus 1 4429
Protoss_Gateway 4 9831
Protoss_Assimilator 2 8223
Protoss_Cybernetics_Core 1 4943
Protoss_Zealot 1 5114
Protoss_Dragoon 12 10060
Protoss_Robotics_Facility 1 9325
Protoss_Observatory 1 9936
10060
