Protoss_Nexus 2 9714
Protoss_Gateway 2 5689
Protoss_Assimilator 2 9539
Protoss_Cybernetics_Core 1 5127
Protoss_Dragoon 9 10026
Protoss_Robotics_Facility 1 8596
Protoss_Citadel_of_Adun 1 9748
Protoss_Observatory 1 9311
10026
