Protoss_Gateway 3 8365
Protoss_Assimilator 2 9917
Protoss_Cybernetics_Core 1 3751
Protoss_Dragoon 12 10450
Protoss_Nexus 1 7543
Protoss_Robotics_Facility 1 8117
Protoss_Observatory 1 8715
Protoss_Observer 2 9998
Protoss_Citadel_of_Adun 1 10149
10450
