Protoss_Gateway 2 4925
Protoss_Assimilator 1 3065
Protoss_Cybernetics_Core 1 3944
Protoss_Dragoon 7 10462
Protoss_Robotics_Facility 1 7310
Protoss_Nexus 1 8707
Protoss_Shuttle 1 8291
Protoss_Robotics_Support_Bay 1 8013
Protoss_Reaver 1 9838
Protoss_Zealot 2 9520
Protoss_Observatory 1 9452
Protoss_Observer 1 10442
10462
