Protoss_Assimilator 5 8552
Protoss_Gateway 3 10757
Protoss_Cybernetics_Core 1 4427
Protoss_Dragoon 9 10194
Protoss_Nexus 1 8211
Protoss_Robotics_Facility 1 8822
Protoss_Observatory 1 9439
Protoss_Citadel_of_Adun 1 9947
Protoss_Observer 1 10152
10757
