Protoss_Gateway 4 10032
Protoss_Assimilator 1 2830
Protoss_Cybernetics_Core 1 3751
Protoss_Zealot 2 6502
Protoss_Dragoon 6 10280
Protoss_Robotics_Facility 1 5188
Protoss_Shuttle 1 6215
Protoss_Robotics_Support_Bay 1 6004
Protoss_Reaver 1 7306
Protoss_Nexus 1 9456
Protoss_Observatory 1 8245
Protoss_Observer 1 9872
10280
