Protoss_Nexus 2 11021
Protoss_Gateway 2 5727
Protoss_Assimilator 1 4113
Protoss_Cybernetics_Core 1 5121
Protoss_Zealot 5 9894
Protoss_Dragoon 8 10702
Protoss_Robotics_Facility 1 9404
Protoss_Observatory 1 10148
11021
