Protoss_Gateway 2 6825
Protoss_Assimilator 2 9565
Protoss_Cybernetics_Core 1 3843
Protoss_Zealot 3 9206
Protoss_Citadel_of_Adun 2 5901
Protoss_Dragoon 4 10040
Protoss_Templar_Archives 1 7012
Protoss_Dark_Templar 2 8016
Protoss_Nexus 1 9555
Protoss_Stargate 1 9302
Protoss_Arbiter_Tribunal 1 10499
10499
