Protoss_Gateway 4 10672
Protoss_Assimilator 1 2967
Protoss_Cybernetics_Core 1 3909
Protoss_Dragoon 9 10002
Protoss_Nexus 1 8655
Protoss_Robotics_Facility 1 8614
Protoss_Observatory 1 9215
Protoss_Observer 2 10506
10672
