Protoss_Gateway 2 6672
Protoss_Assimilator 1 2778
Protoss_Cybernetics_Core 1 3717
Protoss_Dragoon 10 10384
Protoss_Robotics_Facility 1 6416
Protoss_Observatory 1 6990
Protoss_Nexus 2 10403
Protoss_Observer 3 10290
10403
