Protoss_Gateway 2 7538
Protoss_Assimilator 1 2835
Protoss_Cybernetics_Core 1 3948
Protoss_Zealot 1 3828
Protoss_Dragoon 9 10164
Protoss_Nexus 1 8291
Protoss_Robotics_Facility 1 8940
Protoss_Observatory 1 9685
Protoss_Shuttle 1 10417
Protoss_Robotics_Support_Bay 1 10339
10417
