Protoss_Nexus 2 11237
Protoss_Gateway 2 5773
Protoss_Assimilator 1 3929
Protoss_Cybernetics_Core 1 4977
Protoss_Zealot 2 5650
Protoss_Dragoon 9 10508
Protoss_Robotics_Facility 1 9669
Protoss_Observatory 1 10321
11237
