Protoss_Gateway 4 10468
Protoss_Assimilator 1 2956
Protoss_Zealot 2 4350
Protoss_Cybernetics_Core 1 4471
Protoss_Dragoon 11 10534
Protoss_Nexus 1 8378
Protoss_Robotics_Facility 1 8099
Protoss_Observatory 1 8667
Protoss_Observer 2 10532
10534
