Protoss_Gateway 3 7269
Protoss_Assimilator 1 2906
Protoss_Cybernetics_Core 1 3833
Protoss_Dragoon 9 9282
Protoss_Nexus 1 7439
Protoss_Robotics_Facility 1 7070
Protoss_Observatory 1 7795
Protoss_Observer 2 9340
Protoss_Zealot 3 9884
Protoss_Shuttle 1 10349
10349
