Protoss_Gateway 2 8686
Protoss_Assimilator 1 3084
Protoss_Cybernetics_Core 1 3972
Protoss_Zealot 1 3852
Protoss_Dragoon 9 10528
Protoss_Robotics_Facility 1 6709
Protoss_Observatory 1 7249
Protoss_Nexus 1 9031
Protoss_Observer 2 8806
Protoss_Robotics_Support_Bay 1 8792
Protoss_Shuttle 1 9917
10528
