Protoss_Gateway 2 8625
Protoss_Assimilator 1 2798
Protoss_Cybernetics_Core 1 3764
Protoss_Zealot 1 4182
Protoss_Robotics_Facility 1 5459
Protoss_Dragoon 6 10744
Protoss_Shuttle 2 10435
Protoss_Robotics_Support_Bay 1 6050
Protoss_Reaver 1 7596
Protoss_Observatory 1 8691
Protoss_Nexus 1 10406
Protoss_Observer 1 9376
10744
