Protoss_Nexus 1 4469
Protoss_Gateway 4 9046
Protoss_Assimilator 2 6980
Protoss_Cybernetics_Core 1 4993
Protoss_Dragoon 12 10014
Protoss_Robotics_Facility 1 8525
Protoss_Observatory 1 9169
Protoss_Observer 2 10544
10544
