Protoss_Gateway 3 10583
Protoss_Assimilator 1 2869
Protoss_Zealot 2 4302
Protoss_Cybernetics_Core 1 4363
Protoss_Dragoon 8 10606
Protoss_Robotics_Facility 1 7372
Protoss_Nexus 1 9074
Protoss_Observatory 1 7913
Protoss_Observer 2 9586
Protoss_Citadel_of_Adun 1 8963
Protoss_Templar_Archives 1 10529
10606
