Protoss_Gateway 2 3590
Protoss_Zealot 11 9090
Protoss_Forge 1 5442
Protoss_Assimilator 1 6755
Protoss_Photon_Cannon 4 9292
Protoss_Cybernetics_Core 1 9172
Protoss_Dragoon 2 10066
10066
