Protoss_Gateway 4 10152
Protoss_Assimilator 2 8626
Protoss_Cybernetics_Core 1 3717
Protoss_Dragoon 8 9530
Protoss_Nexus 2 9783
Protoss_Robotics_Facility 1 9361
Protoss_Citadel_of_Adun 1 9507
Protoss_Observatory 1 9917
Protoss_Observer 1 10594
10594
