Protoss_Gateway 1 2776
Protoss_Assimilator 1 2950
Protoss_Cybernetics_Core 1 3878
Protoss_Dragoon 6 9592
Protoss_Nexus 2 9536
Protoss_Robotics_Facility 1 7993
Protoss_Shuttle 1 9319
Protoss_Robotics_Support_Bay 1 9520
Protoss_Zealot 1 10194
Protoss_Reaver 1 10670
Protoss_Observatory 1 10346
10670
