Protoss_Gateway 2 8963
Protoss_Zealot 5 8480
Protoss_Assimilator 1 3539
Protoss_Cybernetics_Core 1 4618
Protoss_Dragoon 6 10496
Protoss_Robotics_Facility 1 6536
Protoss_Shuttle 1 7551
Protoss_Robotics_Support_Bay 1 7417
Protoss_Reaver 1 8638
Protoss_Observatory 1 8584
Protoss_Observer 1 9266
Protoss_Nexus 1 11177
11177
