Protoss_Nexus 2 11650
Protoss_Gateway 5 9730
Protoss_Assimilator 2 7055
Protoss_Cybernetics_Core 1 5028
Protoss_Zealot 4 9672
Protoss_Dragoon 5 8287
Protoss_Robotics_Facility 1 7415
Protoss_Shuttle 1 8579
Protoss_Observatory 2 9894
Protoss_Observer 1 10586
11650
