Protoss_Gateway 4 10108
Protoss_Assimilator 1 2882
Protoss_Zealot 1 3528
Protoss_Nexus 2 9722
Protoss_Cybernetics_Core 1 5143
Protoss_Dragoon 11 10746
Protoss_Robotics_Facility 1 9572
Protoss_Forge 1 10570
10746
