Protoss_Gateway 4 9689
Protoss_Assimilator 2 10174
Protoss_Zealot 2 4380
Protoss_Cybernetics_Core 1 4375
Protoss_Dragoon 8 9952
Protoss_Robotics_Facility 1 6903
Protoss_Observatory 1 7475
Protoss_Observer 3 10450
Protoss_Nexus 1 9413
10450
