Protoss_Gateway 3 9777
Protoss_Assimilator 1 3030
Protoss_Cybernetics_Core 1 3871
Protoss_Dragoon 5 10672
Protoss_Robotics_Facility 1 5647
Protoss_Shuttle 1 6647
Protoss_Robotics_Support_Bay 1 6333
Protoss_Zealot 2 7696
Protoss_Reaver 2 8904
Protoss_Observatory 1 9680
Protoss_Nexus 1 11495
Protoss_Observer 1 10456
11495
