Protoss_Gateway 3 10363
Protoss_Assimilator 1 3069
Protoss_Cybernetics_Core 1 4070
Protoss_Dragoon 4 10654
Protoss_Citadel_of_Adun 1 6330
Protoss_Templar_Archives 1 7341
Protoss_Zealot 1 7194
Protoss_Dark_Templar 7 10612
Protoss_Nexus 1 10691
10691
