Protoss_Gateway 4 10759
Protoss_Assimilator 2 9727
Protoss_Cybernetics_Core 1 3773
Protoss_Dragoon 11 10300
Protoss_Nexus 1 8653
Protoss_Robotics_Facility 1 8753
Protoss_Observatory 1 9429
Protoss_Citadel_of_Adun 1 9962
Protoss_Observer 1 10110
10759
