Protoss_Gateway 4 8609
Protoss_Assimilator 1 2949
Protoss_Cybernetics_Core 1 3867
Protoss_Dragoon 10 10550
Protoss_Robotics_Facility 1 6889
Protoss_Nexus 1 8407
Protoss_Observatory 1 7475
Protoss_Observer 4 10156
Protoss_Zealot 2 10366
10550
