Protoss_Gateway 2 6534
Protoss_Assimilator 1 3006
Protoss_Cybernetics_Core 1 3879
Protoss_Dragoon 7 9934
Protoss_Robotics_Facility 1 6566
Protoss_Shuttle 1 7567
Protoss_Robotics_Support_Bay 1 7148
Protoss_Zealot 1 7310
Protoss_Reaver 1 8618
Protoss_Nexus 1 10091
Protoss_Observatory 1 9012
Protoss_Observer 1 9696
10091
