Protoss_Gateway 2 9747
Protoss_Assimilator 1 2912
Protoss_Cybernetics_Core 1 3867
Protoss_Zealot 1 3842
Protoss_Robotics_Facility 1 5340
Protoss_Dragoon 4 10464
Protoss_Robotics_Support_Bay 1 5903
Protoss_Shuttle 1 6795
Protoss_Reaver 1 7846
Protoss_Observatory 1 8133
Protoss_Observer 1 8996
Protoss_Nexus 1 11638
11638
