Protoss_Gateway 2 9158
Protoss_Assimilator 1 2902
Protoss_Cybernetics_Core 1 3833
Protoss_Zealot 1 3790
Protoss_Dragoon 9 10344
Protoss_Nexus 1 7893
Protoss_Robotics_Facility 1 8253
Protoss_Shuttle 1 9637
Protoss_Robotics_Support_Bay 1 9990
10344
