Protoss_Gateway 3 5249
Protoss_Assimilator 2 4258
Protoss_Zealot 6 6780
Protoss_Cybernetics_Core 1 6546
Protoss_Citadel_of_Adun 1 7573
Protoss_Robotics_Facility 1 8027
Protoss_Dragoon 2 7894
Protoss_Templar_Archives 1 8679
Protoss_Shuttle 1 9129
Protoss_Dark_Templar 4 10342
Protoss_Nexus 1 11039
11039
