Protoss_Gateway 2 8810
Protoss_Assimilator 1 2897
Protoss_Cybernetics_Core 1 3735
Protoss_Zealot 1 3730
Protoss_Dragoon 8 9740
Protoss_Robotics_Facility 1 6587
Protoss_Observatory 1 7172
Protoss_Nexus 2 11521
Protoss_Observer 5 10406
11521
