Protoss_Gateway 3 9681
Protoss_Assimilator 1 3001
Protoss_Cybernetics_Core 1 3920
Protoss_Nexus 1 7095
Protoss_Dragoon 8 9364
Protoss_Robotics_Facility 1 9048
Protoss_Zealot 2 10184
Protoss_Shuttle 1 10495
Protoss_Observatory 1 10127
10495
