Protoss_Gateway 2 8027
Protoss_Assimilator 1 2799
Protoss_Cybernetics_Core 1 3649
Protoss_Dragoon 7 8918
Protoss_Robotics_Facility 1 6373
Protoss_Observatory 1 7005
Protoss_Nexus 1 8695
Protoss_Observer 2 8667
Protoss_Shuttle 1 9670
Protoss_Robotics_Support_Bay 1 9347
Protoss_Reaver 1 10763
Protoss_Zealot 2 10348
10763
