Protoss_Gateway 3 9165
Protoss_Assimilator 2 8533
Protoss_Cybernetics_Core 1 3806
Protoss_Nexus 1 6854
Protoss_Dragoon 9 10216
Protoss_Robotics_Facility 1 6959
Protoss_Observatory 1 7756
Protoss_Observer 3 10496
Protoss_Citadel_of_Adun 1 9780
Protoss_Zealot 1 10478
10496
