Protoss_Gateway 2 8528
Protoss_Assimilator 2 8319
Protoss_Cybernetics_Core 1 3729
Protoss_Dragoon 5 9894
Protoss_Citadel_of_Adun 1 5939
Protoss_Templar_Archives 1 6976
Protoss_Nexus 1 8359
Protoss_Dark_Templar 1 7810
Protoss_Stargate 2 10152
Protoss_Fleet_Beacon 1 9453
Protoss_Carrier 1 11875
11875
