Protoss_Gateway 2 7115
Protoss_Assimilator 1 3073
Protoss_Cybernetics_Core 1 3977
Protoss_Zealot 1 3846
Protoss_Dragoon 10 10262
Protoss_Robotics_Facility 1 7275
Protoss_Shuttle 1 8351
Protoss_Robotics_Support_Bay 1 8801
Protoss_Observatory 1 9119
Protoss_Reaver 1 9960
Protoss_Observer 1 10564
10564
