Protoss_Gateway 3 9264
Protoss_Assimilator 1 2962
Protoss_Cybernetics_Core 1 3917
Protoss_Dragoon 11 10604
Protoss_Zealot 2 6546
Protoss_Nexus 1 8429
Protoss_Robotics_Facility 1 8879
Protoss_Observatory 1 9931
10604
