Protoss_Gateway 1 2956
Protoss_Assimilator 1 3091
Protoss_Cybernetics_Core 1 3996
Protoss_Zealot 2 6890
Protoss_Robotics_Facility 1 5630
Protoss_Dragoon 5 10080
Protoss_Shuttle 1 6727
Protoss_Robotics_Support_Bay 1 6460
Protoss_Reaver 1 7778
Protoss_Nexus 1 9909
Protoss_Observatory 1 10271
10271
