Protoss_Gateway 3 8477
Protoss_Assimilator 1 2804
Protoss_Cybernetics_Core 1 3767
Protoss_Zealot 1 3744
Protoss_Dragoon 8 9316
Protoss_Nexus 2 11125
Protoss_Robotics_Facility 1 8196
Protoss_Observatory 1 9077
Protoss_Observer 2 10382
11125
