Protoss_Gateway 2 7723
Protoss_Assimilator 2 10286
Protoss_Cybernetics_Core 1 3755
Protoss_Dragoon 10 10620
Protoss_Robotics_Facility 1 6439
Protoss_Nexus 2 10509
Protoss_Observatory 1 7192
Protoss_Observer 4 10100
10620
