Protoss_Gateway 2 8061
Protoss_Assimilator 2 9152
Protoss_Cybernetics_Core 1 4081
Protoss_Dragoon 10 10656
Protoss_Nexus 1 8069
Protoss_Robotics_Facility 1 8981
Protoss_Stargate 1 10019
Protoss_Observatory 1 9689
Protoss_Observer 1 10388
10656
