Protoss_Gateway 2 8617
Protoss_Assimilator 2 10115
Protoss_Cybernetics_Core 1 3750
Protoss_Dragoon 4 8266
Protoss_Nexus 2 10785
Protoss_Robotics_Facility 1 7416
Protoss_Citadel_of_Adun 1 7691
Protoss_Observatory 1 8048
Protoss_Templar_Archives 1 9059
Protoss_Observer 1 9028
Protoss_Shuttle 1 9517
Protoss_Dark_Templar 2 9946
10785
