Protoss_Nexus 2 11139
Protoss_Gateway 2 5213
Protoss_Assimilator 1 3952
Protoss_Cybernetics_Core 1 5059
Protoss_Zealot 1 5246
Protoss_Dragoon 8 9376
Protoss_Robotics_Facility 1 9225
Protoss_Shuttle 1 10629
11139
