Protoss_Nexus 2 10134
Protoss_Gateway 5 10867
Protoss_Assimilator 2 6477
Protoss_Cybernetics_Core 1 5123
Protoss_Zealot 2 9982
Protoss_Dragoon 8 10698
Protoss_Robotics_Facility 1 7877
Protoss_Observatory 1 8457
Protoss_Observer 1 9694
Protoss_Citadel_of_Adun 1 10060
Protoss_Forge 1 9833
Protoss_Shuttle 1 10595
10867
