Protoss_Gateway 2 7652
Protoss_Assimilator 1 3003
Protoss_Zealot 1 3586
Protoss_Cybernetics_Core 1 4296
Protoss_Dragoon 6 10058
Protoss_Citadel_of_Adun 1 6501
Protoss_Robotics_Facility 1 7684
Protoss_Templar_Archives 1 7535
Protoss_Dark_Templar 3 9306
Protoss_Shuttle 1 8879
Protoss_Observatory 1 8588
Protoss_Observer 2 10318
10318
