Protoss_Gateway 1 2723
Protoss_Assimilator 1 2892
Protoss_Cybernetics_Core 1 3754
Protoss_Zealot 4 9900
Protoss_Dragoon 6 8696
Protoss_Robotics_Facility 1 6751
Protoss_Shuttle 1 7739
Protoss_Robotics_Support_Bay 1 7333
Protoss_Reaver 2 9842
Protoss_Observatory 1 9585
Protoss_Nexus 1 11422
Protoss_Observer 1 10446
11422
