Protoss_Gateway 4 10849
Protoss_Assimilator 2 9268
Protoss_Cybernetics_Core 1 3821
Protoss_Dragoon 9 10432
Protoss_Robotics_Facility 1 6885
Protoss_Nexus 1 8351
Protoss_Observatory 1 7552
Protoss_Observer 3 9456
Protoss_Citadel_of_Adun 1 8676
Protoss_Templar_Archives 1 10261
10849
