Protoss_Gateway 2 7541
Protoss_Assimilator 1 2836
Protoss_Cybernetics_Core 1 3736
Protoss_Zealot 2 8500
Protoss_Dragoon 8 10368
Protoss_Nexus 1 7031
Protoss_Robotics_Facility 1 6907
Protoss_Shuttle 1 8011
Protoss_Robotics_Support_Bay 1 8150
Protoss_Reaver 1 9278
Protoss_Observatory 1 9150
Protoss_Observer 1 9968
10368
