Protoss_Gateway 4 10205
Protoss_Assimilator 1 2819
Protoss_Cybernetics_Core 1 3757
Protoss_Dragoon 12 10220
Protoss_Nexus 1 6286
Protoss_Zealot 1 8162
Protoss_Robotics_Facility 1 9245
Protoss_Shuttle 1 10615
10615
