Protoss_Gateway 2 9677
Protoss_Assimilator 2 10307
Protoss_Cybernetics_Core 1 3714
Protoss_Zealot 1 3764
Protoss_Dragoon 7 9856
Protoss_Robotics_Facility 1 7176
Protoss_Observatory 1 8025
Protoss_Nexus 1 9408
Protoss_Observer 2 9306
Protoss_Citadel_of_Adun 1 9235
Protoss_Templar_Archives 1 10225
Protoss_Shuttle 1 10299
10307
