Protoss_Gateway 2 4329
Protoss_Assimilator 1 2818
Protoss_Cybernetics_Core 1 3753
Protoss_Dragoon 9 9132
Protoss_Robotics_Facility 1 8017
Protoss_Shuttle 1 9001
Protoss_Robotics_Support_Bay 1 8575
Protoss_Zealot 3 9748
Protoss_Reaver 1 10054
Protoss_Observatory 1 9997
Protoss_Nexus 1 11791
11791
