Protoss_Gateway 2 6761
Protoss_Zealot 7 7448
Protoss_Forge 1 3926
Protoss_Photon_Cannon 3 5828
Protoss_Assimilator 1 5800
Protoss_Cybernetics_Core 1 7417
Protoss_Dragoon 4 9638
Protoss_Citadel_of_Adun 1 9845
9845
