Protoss_Gateway 2 8459
Protoss_Assimilator 1 2770
Protoss_Zealot 3 4594
Protoss_Cybernetics_Core 1 4732
Protoss_Dragoon 9 10388
Protoss_Nexus 1 7935
Protoss_Robotics_Facility 1 8057
Protoss_Shuttle 1 9879
Protoss_Robotics_Support_Bay 1 9742
Protoss_Reaver 1 10930
Protoss_Observatory 1 10441
10930
