Protoss_Gateway 2 8860
Protoss_Assimilator 2 9135
Protoss_Cybernetics_Core 1 3886
Protoss_Dragoon 10 10746
Protoss_Robotics_Facility 1 6639
Protoss_Nexus 1 8845
Protoss_Observatory 1 7585
Protoss_Observer 3 9768
Protoss_Citadel_of_Adun 1 9272
10746
