Protoss_Gateway 3 10771
Protoss_Assimilator 1 2776
Protoss_Cybernetics_Core 1 3803
Protoss_Zealot 1 3680
Protoss_Dragoon 10 10726
Protoss_Robotics_Facility 1 6381
Protoss_Observatory 1 6920
Protoss_Nexus 1 8729
Protoss_Observer 2 8260
Protoss_Shuttle 1 9161
Protoss_Robotics_Support_Bay 1 9212
Protoss_Reaver 1 10470
10771
