Protoss_Gateway 2 7285
Protoss_Assimilator 2 8764
Protoss_Cybernetics_Core 1 3729
Protoss_Dragoon 7 10162
Protoss_Nexus 1 7433
Protoss_Robotics_Facility 1 7165
Protoss_Shuttle 1 8311
Protoss_Robotics_Support_Bay 1 8329
Protoss_Reaver 1 9480
Protoss_Zealot 2 9160
Protoss_Observatory 1 9127
Protoss_Citadel_of_Adun 1 10019
Protoss_Observer 1 10084
Protoss_Stargate 1 10944
10944
