Protoss_Gateway 3 10538
Protoss_Assimilator 1 3018
Protoss_Cybernetics_Core 1 3858
Protoss_Nexus 2 7696
Protoss_Dragoon 9 10004
Protoss_Robotics_Facility 1 9345
Protoss_Observatory 1 9999
10538
