Protoss_Gateway 2 9913
Protoss_Assimilator 1 2970
Protoss_Cybernetics_Core 1 3839
Protoss_Dragoon 6 10376
Protoss_Robotics_Facility 1 6613
Protoss_Shuttle 1 7631
Protoss_Robotics_Support_Bay 1 7560
Protoss_Nexus 1 9277
Protoss_Reaver 1 8800
Protoss_Observatory 1 8635
Protoss_Observer 2 10296
10376
