Protoss_Gateway 2 6163
Protoss_Assimilator 1 3007
Protoss_Cybernetics_Core 1 3923
Protoss_Dragoon 11 10256
Protoss_Nexus 1 8903
Protoss_Robotics_Facility 1 9430
Protoss_Citadel_of_Adun 1 9244
10256
