Protoss_Gateway 3 10706
Protoss_Assimilator 1 2840
Protoss_Cybernetics_Core 1 3799
Protoss_Dragoon 9 10510
Protoss_Nexus 2 10579
Protoss_Robotics_Facility 1 8141
Protoss_Observatory 1 9002
Protoss_Observer 2 10444
10706
