Protoss_Gateway 2 7902
Protoss_Assimilator 2 10017
Protoss_Cybernetics_Core 1 3715
Protoss_Zealot 2 8838
Protoss_Dragoon 8 10692
Protoss_Nexus 1 7745
Protoss_Robotics_Facility 1 7827
Protoss_Shuttle 1 8811
Protoss_Robotics_Support_Bay 1 8893
Protoss_Observatory 1 9371
Protoss_Reaver 1 10028
Protoss_Citadel_of_Adun 1 10404
10692
