Protoss_Gateway 4 9697
Protoss_Assimilator 1 2797
Protoss_Cybernetics_Core 1 3745
Protoss_Zealot 1 3664
Protoss_Dragoon 12 10702
Protoss_Nexus 1 8355
Protoss_Robotics_Facility 1 8471
Protoss_Observatory 1 9154
Protoss_Observer 2 10444
10702
