Protoss_Gateway 2 7489
Protoss_Assimilator 3 3728
Protoss_Zealot 2 4660
Protoss_Cybernetics_Core 1 4629
Protoss_Nexus 1 6745
Protoss_Dragoon 10 10632
Protoss_Robotics_Facility 1 9247
Protoss_Forge 1 9445
10632
