Protoss_Gateway 4 9429
Protoss_Assimilator 2 9866
Protoss_Cybernetics_Core 1 3717
Protoss_Zealot 1 3720
Protoss_Dragoon 9 9802
Protoss_Nexus 1 7742
Protoss_Robotics_Facility 1 7839
Protoss_Observatory 1 8410
Protoss_Observer 2 9738
Protoss_Citadel_of_Adun 1 10289
Protoss_Shuttle 1 10729
10729
