Protoss_Gateway 2 5594
Protoss_Zealot 2 3968
Protoss_Assimilator 1 3716
Protoss_Cybernetics_Core 1 5069
Protoss_Dragoon 6 9793
Protoss_Nexus 1 9850
Protoss_Citadel_of_Adun 1 9179
Protoss_Templar_Archives 1 10196
Protoss_Robotics_Facility 1 11126
11126
