Protoss_Nexus 1 4388
Protoss_Gateway 2 5189
Protoss_Assimilator 2 9716
Protoss_Cybernetics_Core 1 5033
Protoss_Zealot 3 10352
Protoss_Dragoon 7 9750
Protoss_Robotics_Facility 1 8268
Protoss_Shuttle 1 9325
Protoss_Observatory 1 9055
Protoss_Robotics_Support_Bay 1 9113
Protoss_Observer 1 10062
10352
