Protoss_Gateway 2 10229
Protoss_Assimilator 1 3098
Protoss_Cybernetics_Core 1 4059
Protoss_Dragoon 4 9828
Protoss_Robotics_Facility 1 6219
Protoss_Shuttle 1 7271
Protoss_Robotics_Support_Bay 1 6845
Protoss_Reaver 2 9374
Protoss_Zealot 1 8140
Protoss_Observatory 1 8714
Protoss_Nexus 1 10625
Protoss_Observer 1 9978
10625
