Protoss_Gateway 1 2773
Protoss_Assimilator 1 2843
Protoss_Cybernetics_Core 1 3787
Protoss_Dragoon 6 10368
Protoss_Robotics_Facility 1 6576
Protoss_Shuttle 1 7561
Protoss_Robotics_Support_Bay 1 7327
Protoss_Reaver 1 8612
Protoss_Zealot 1 8320
Protoss_Observatory 1 8278
Protoss_Nexus 1 10201
Protoss_Observer 2 9818
10368
