Protoss_Gateway 3 10813
Protoss_Assimilator 1 2762
Protoss_Cybernetics_Core 1 3745
Protoss_Dragoon 10 10368
Protoss_Robotics_Facility 1 6343
Protoss_Observatory 1 6897
Protoss_Nexus 1 8519
Protoss_Observer 2 8196
Protoss_Shuttle 1 9147
Protoss_Robotics_Support_Bay 1 8803
Protoss_Reaver 1 10248
10813
