Protoss_Gateway 4 9484
Protoss_Assimilator 2 9354
Protoss_Cybernetics_Core 1 3883
Protoss_Dragoon 6 9900
Protoss_Citadel_of_Adun 1 6020
Protoss_Templar_Archives 1 7135
Protoss_Nexus 1 8269
Protoss_Dark_Templar 2 9770
Protoss_Robotics_Facility 1 9227
Protoss_Observatory 1 10353
10353
