Protoss_Gateway 2 7514
Protoss_Assimilator 1 3193
Protoss_Zealot 3 4712
Protoss_Cybernetics_Core 1 4841
Protoss_Dragoon 3 7198
Protoss_Citadel_of_Adun 1 6919
Protoss_Templar_Archives 1 7967
Protoss_Robotics_Facility 1 8314
Protoss_Dark_Templar 4 9611
Protoss_Shuttle 1 9301
Protoss_Observatory 1 9783
Protoss_Observer 1 10508
10508
