Protoss_Nexus 2 11145
Protoss_Gateway 2 5345
Protoss_Assimilator 1 3874
Protoss_Cybernetics_Core 1 5093
Protoss_Zealot 1 5314
Protoss_Dragoon 10 10454
Protoss_Robotics_Facility 1 11017
11145
