Protoss_Gateway 2 9467
Protoss_Assimilator 1 3239
Protoss_Zealot 4 8724
Protoss_Cybernetics_Core 1 4562
Protoss_Dragoon 7 10610
Protoss_Robotics_Facility 1 6674
Protoss_Shuttle 1 7659
Protoss_Robotics_Support_Bay 1 7679
Protoss_Reaver 1 8814
Protoss_Nexus 1 9821
Protoss_Observatory 1 9954
10610
