Protoss_Gateway 2 6027
Protoss_Assimilator 1 3022
Protoss_Cybernetics_Core 1 3868
Protoss_Dragoon 11 10226
Protoss_Robotics_Facility 1 7673
Protoss_Robotics_Support_Bay 1 8511
Protoss_Zealot 2 8722
Protoss_Shuttle 1 9421
Protoss_Reaver 1 10472
10472
