Protoss_Gateway 2 4207
Protoss_Assimilator 1 2840
Protoss_Cybernetics_Core 1 3809
Protoss_Dragoon 11 10596
Protoss_Nexus 1 7921
Protoss_Robotics_Facility 1 9805
Protoss_Observatory 1 10380
10596
