Protoss_Gateway 2 6080
Protoss_Assimilator 2 4330
Protoss_Cybernetics_Core 1 3878
Protoss_Dragoon 11 10019
Protoss_Nexus 2 11443
Protoss_Robotics_Facility 1 9099
Protoss_Observatory 1 9737
Protoss_Observer 1 10558
11443
