Protoss_Gateway 2 6228
Protoss_Assimilator 1 3033
Protoss_Cybernetics_Core 1 3836
Protoss_Dragoon 10 9638
Protoss_Robotics_Facility 1 7123
Protoss_Observatory 1 8147
Protoss_Zealot 1 8596
Protoss_Observer 2 9790
Protoss_Nexus 1 10805
10805
