Protoss_Assimilator 3 8223
Protoss_Gateway 4 10150
Protoss_Zealot 3 6230
Protoss_Nexus 1 6347
Protoss_Cybernetics_Core 1 6321
Protoss_Dragoon 9 10460
Protoss_Robotics_Facility 1 10231
Protoss_Citadel_of_Adun 1 10573
10573
