Protoss_Nexus 1 4300
Protoss_Gateway 2 10770
Protoss_Assimilator 1 3812
Protoss_Cybernetics_Core 1 4760
Protoss_Zealot 1 4572
Protoss_Dragoon 6 10037
Protoss_Robotics_Facility 1 10255
10770
