Protoss_Assimilator 3 8253
Protoss_Gateway 4 10146
Protoss_Nexus 1 5505
Protoss_Cybernetics_Core 1 5488
Protoss_Zealot 2 7930
Protoss_Dragoon 11 10660
Protoss_Citadel_of_Adun 1 7565
Protoss_Robotics_Facility 1 10679
10679
