Protoss_Gateway 6 10327
Protoss_Assimilator 1 2852
Protoss_Cybernetics_Core 1 3853
Protoss_Dragoon 6 10302
Protoss_Nexus 2 10086
Protoss_Robotics_Facility 1 7715
Protoss_Shuttle 1 8713
Protoss_Robotics_Support_Bay 1 8511
Protoss_Reaver 1 9764
Protoss_Observatory 1 10015
10327
