Protoss_Gateway 2 7480
Protoss_Assimilator 2 9957
Protoss_Cybernetics_Core 1 3957
Protoss_Dragoon 8 9932
Protoss_Nexus 1 8000
Protoss_Citadel_of_Adun 1 7978
Protoss_Robotics_Facility 1 8913
Protoss_Templar_Archives 1 9379
Protoss_Observatory 1 9595
Protoss_Dark_Templar 1 10242
Protoss_Observer 1 10288
10288
