Protoss_Gateway 2 9724
Protoss_Assimilator 2 9066
Protoss_Cybernetics_Core 1 4037
Protoss_Dragoon 4 7888
Protoss_Nexus 1 8038
Protoss_Citadel_of_Adun 1 7674
Protoss_Robotics_Facility 1 8263
Protoss_Templar_Archives 1 8864
Protoss_Observatory 1 8862
Protoss_Shuttle 1 9562
Protoss_Dark_Templar 3 10573
Protoss_Observer 1 10165
10573
