Protoss_Gateway 2 6487
Protoss_Zealot 3 4794
Protoss_Assimilator 1 3560
Protoss_Cybernetics_Core 1 4627
Protoss_Dragoon 11 10638
Protoss_Nexus 1 9179
Protoss_Robotics_Facility 1 9133
Protoss_Shuttle 1 10149
Protoss_Robotics_Support_Bay 1 9973
10638
