Protoss_Gateway 2 5478
Protoss_Assimilator 1 2780
Protoss_Cybernetics_Core 1 3701
Protoss_Zealot 3 10506
Protoss_Dragoon 10 9894
Protoss_Nexus 1 9081
Protoss_Robotics_Facility 1 9157
Protoss_Shuttle 1 10235
Protoss_Robotics_Support_Bay 1 9919
10506
