Protoss_Gateway 2 5769
Protoss_Zealot 2 4936
Protoss_Nexus 2 11056
Protoss_Assimilator 2 7231
Protoss_Cybernetics_Core 1 5053
Protoss_Dragoon 9 10342
Protoss_Robotics_Facility 1 8231
Protoss_Observatory 1 8899
Protoss_Observer 2 10438
Protoss_Citadel_of_Adun 1 10279
11056
