Protoss_Gateway 2 10683
Protoss_Assimilator 1 3144
Protoss_Cybernetics_Core 1 4159
Protoss_Dragoon 6 10506
Protoss_Robotics_Facility 1 6845
Protoss_Nexus 1 8422
Protoss_Shuttle 1 7843
Protoss_Robotics_Support_Bay 1 7753
Protoss_Zealot 2 9396
Protoss_Reaver 2 10270
10683
