Protoss_Gateway 1 2767
Protoss_Assimilator 1 2841
Protoss_Zealot 2 4134
Protoss_Cybernetics_Core 1 4030
Protoss_Dragoon 8 10625
Protoss_Nexus 1 8290
Protoss_Robotics_Facility 1 9292
Protoss_Shuttle 1 10446
10625
