Protoss_Assimilator 1 2443
Protoss_Gateway 2 7510
Protoss_Cybernetics_Core 1 4227
Protoss_Zealot 1 4238
Protoss_Dragoon 10 9944
Protoss_Nexus 1 7611
Protoss_Robotics_Facility 1 8227
Protoss_Observatory 1 8989
Protoss_Observer 2 10282
10282
