Protoss_Gateway 4 10248
Protoss_Assimilator 1 2988
Protoss_Cybernetics_Core 1 3959
Protoss_Dragoon 9 10406
Protoss_Citadel_of_Adun 1 6623
Protoss_Templar_Archives 1 7610
Protoss_Nexus 1 9222
Protoss_Dark_Templar 2 8460
Protoss_Stargate 1 10940
10940
