Protoss_Gateway 1 2793
Protoss_Assimilator 1 2941
Protoss_Cybernetics_Core 1 3794
Protoss_Zealot 2 8626
Protoss_Dragoon 6 10616
Protoss_Robotics_Facility 1 6835
Protoss_Shuttle 1 7817
Protoss_Robotics_Support_Bay 1 7697
Protoss_Reaver 1 8980
Protoss_Observatory 2 9465
Protoss_Observer 2 10442
10616
