Protoss_Gateway 3 10793
Protoss_Assimilator 2 9736
Protoss_Cybernetics_Core 1 3844
Protoss_Zealot 3 10268
Protoss_Dragoon 6 9378
Protoss_Nexus 1 8075
Protoss_Robotics_Facility 1 8047
Protoss_Citadel_of_Adun 1 8873
Protoss_Observatory 1 8645
Protoss_Observer 2 9974
Protoss_Templar_Archives 1 9897
Protoss_Stargate 1 10516
10793
