Protoss_Gateway 2 10176
Protoss_Assimilator 1 2926
Protoss_Cybernetics_Core 1 3771
Protoss_Dragoon 6 10338
Protoss_Robotics_Facility 1 6535
Protoss_Nexus 1 8607
Protoss_Shuttle 1 8129
Protoss_Robotics_Support_Bay 1 8170
Protoss_Zealot 2 9354
Protoss_Reaver 1 9452
Protoss_Observatory 1 9951
10338
