Protoss_Gateway 2 4441
Protoss_Assimilator 1 2862
Protoss_Cybernetics_Core 1 3919
Protoss_Dragoon 7 7922
Protoss_Citadel_of_Adun 1 7385
Protoss_Robotics_Facility 1 9083
Protoss_Templar_Archives 1 8880
Protoss_Dark_Templar 3 10738
Protoss_Nexus 1 11210
Protoss_Shuttle 1 10571
11210
