Protoss_Nexus 1 4415
Protoss_Gateway 4 8773
Protoss_Assimilator 2 6685
Protoss_Cybernetics_Core 1 5143
Protoss_Zealot 3 10062
Protoss_Dragoon 10 10063
Protoss_Robotics_Facility 1 8059
Protoss_Observatory 1 8646
Protoss_Shuttle 1 9519
Protoss_Observer 1 10122
10122
