Protoss_Gateway 3 9010
Protoss_Assimilator 1 2838
Protoss_Cybernetics_Core 1 3751
Protoss_Dragoon 6 10270
Protoss_Citadel_of_Adun 1 5684
Protoss_Robotics_Facility 1 6495
Protoss_Templar_Archives 1 6995
Protoss_Zealot 1 6960
Protoss_Shuttle 1 7581
Protoss_Dark_Templar 3 8612
Protoss_Nexus 1 10845
Protoss_Observatory 1 10166
10845
