Protoss_Gateway 3 8105
Protoss_Assimilator 1 2932
Protoss_Cybernetics_Core 1 3734
Protoss_Dragoon 12 10144
Protoss_Nexus 1 7175
Protoss_Robotics_Facility 1 7575
Protoss_Observatory 1 8169
Protoss_Observer 2 10288
10288
