Protoss_Gateway 2 9631
Protoss_Assimilator 2 9176
Protoss_Cybernetics_Core 1 3923
Protoss_Zealot 1 4008
Protoss_Dragoon 5 8822
Protoss_Nexus 2 11616
Protoss_Robotics_Facility 1 7656
Protoss_Citadel_of_Adun 1 8088
Protoss_Shuttle 1 8805
Protoss_Templar_Archives 1 9322
Protoss_Dark_Templar 1 10172
11616
