Protoss_Gateway 2 8617
Protoss_Assimilator 1 2794
Protoss_Zealot 1 3452
Protoss_Cybernetics_Core 1 3980
Protoss_Dragoon 7 10384
Protoss_Citadel_of_Adun 1 5203
Protoss_Templar_Archives 1 6232
Protoss_Dark_Templar 2 7918
Protoss_Nexus 1 8653
Protoss_Robotics_Facility 1 10188
10384
