Protoss_Gateway 2 6555
Protoss_Assimilator 1 2826
Protoss_Cybernetics_Core 1 3745
Protoss_Zealot 1 3772
Protoss_Dragoon 13 10700
Protoss_Robotics_Facility 1 6670
Protoss_Observatory 1 7263
Protoss_Observer 2 10478
Protoss_Nexus 1 10939
10939
