Protoss_Gateway 1 2709
Protoss_Assimilator 1 2942
Protoss_Cybernetics_Core 1 3772
Protoss_Zealot 1 3772
Protoss_Dragoon 6 10240
Protoss_Robotics_Facility 1 6595
Protoss_Shuttle 1 7573
Protoss_Robotics_Support_Bay 1 7601
Protoss_Reaver 1 8728
Protoss_Nexus 1 9973
Protoss_Observatory 1 8707
Protoss_Observer 2 10038
10240
