Protoss_Gateway 3 10235
Protoss_Assimilator 2 8794
Protoss_Cybernetics_Core 1 3779
Protoss_Dragoon 11 10319
Protoss_Robotics_Facility 1 6490
Protoss_Nexus 1 7989
Protoss_Observatory 1 7127
Protoss_Observer 2 8460
10319
