Protoss_Nexus 2 10240
Protoss_Gateway 4 10828
Protoss_Assimilator 2 8656
Protoss_Cybernetics_Core 1 4967
Protoss_Zealot 1 4814
Protoss_Dragoon 10 10174
Protoss_Citadel_of_Adun 1 8423
Protoss_Robotics_Facility 1 9883
Protoss_Templar_Archives 1 9934
10828
