Protoss_Gateway 1 2716
Protoss_Assimilator 1 2756
Protoss_Cybernetics_Core 1 3701
Protoss_Zealot 2 8784
Protoss_Dragoon 6 10352
Protoss_Robotics_Facility 1 6592
Protoss_Shuttle 1 7573
Protoss_Robotics_Support_Bay 1 7466
Protoss_Nexus 1 9185
Protoss_Reaver 1 8716
Protoss_Observatory 1 8976
Protoss_Observer 2 10334
10352
