Protoss_Gateway 2 8575
Protoss_Assimilator 1 2916
Protoss_Cybernetics_Core 1 3859
Protoss_Dragoon 10 10308
Protoss_Robotics_Facility 1 6953
Protoss_Nexus 1 8785
Protoss_Observatory 1 7571
Protoss_Observer 3 9654
10308
