Protoss_Gateway 3 10700
Protoss_Assimilator 1 3021
Protoss_Cybernetics_Core 1 3894
Protoss_Dragoon 6 10724
Protoss_Robotics_Facility 1 5593
Protoss_Zealot 2 6854
Protoss_Shuttle 1 6579
Protoss_Robotics_Support_Bay 1 6285
Protoss_Reaver 1 7996
Protoss_Observatory 1 8425
Protoss_Observer 2 10340
Protoss_Nexus 1 11293
11293
