Protoss_Gateway 2 5973
Protoss_Assimilator 2 9927
Protoss_Cybernetics_Core 1 3871
Protoss_Citadel_of_Adun 1 4961
Protoss_Dragoon 8 10686
Protoss_Templar_Archives 1 6347
Protoss_Dark_Templar 3 9810
Protoss_Nexus 1 10753
Protoss_Stargate 1 10601
10753
