Protoss_Nexus 2 10541
Protoss_Gateway 4 10506
Protoss_Assimilator 1 3906
Protoss_Cybernetics_Core 1 4861
Protoss_Zealot 1 5096
Protoss_Dragoon 3 6970
Protoss_Citadel_of_Adun 1 7427
Protoss_Robotics_Facility 1 8710
Protoss_Templar_Archives 1 8428
Protoss_Dark_Templar 2 9398
Protoss_Shuttle 1 9705
Protoss_Observatory 1 9576
Protoss_Observer 1 10308
10541
