Protoss_Nexus 1 4473
Protoss_Gateway 3 9791
Protoss_Assimilator 2 8398
Protoss_Cybernetics_Core 1 5030
Protoss_Zealot 1 5002
Protoss_Dragoon 10 9864
Protoss_Robotics_Facility 1 8366
Protoss_Observatory 1 9221
Protoss_Observer 2 10544
Protoss_Citadel_of_Adun 1 10528
10544
