Protoss_Gateway 2 6725
Protoss_Assimilator 2 9803
Protoss_Cybernetics_Core 1 3755
Protoss_Zealot 1 3716
Protoss_Dragoon 8 10288
Protoss_Citadel_of_Adun 1 5912
Protoss_Robotics_Facility 1 6878
Protoss_Templar_Archives 1 6913
Protoss_Shuttle 1 7865
Protoss_Dark_Templar 3 9354
Protoss_Nexus 1 10021
Protoss_Observatory 1 9125
Protoss_Observer 1 10262
10288
