Protoss_Gateway 2 6655
Protoss_Assimilator 2 9516
Protoss_Cybernetics_Core 1 3762
Protoss_Robotics_Facility 1 5335
Protoss_Dragoon 8 10428
Protoss_Observatory 1 6027
Protoss_Zealot 1 6498
Protoss_Observer 2 7888
Protoss_Nexus 1 9433
Protoss_Citadel_of_Adun 1 8936
Protoss_Templar_Archives 1 9944
10428
