Protoss_Nexus 1 4469
Protoss_Gateway 4 8501
Protoss_Assimilator 2 7521
Protoss_Cybernetics_Core 1 4975
Protoss_Dragoon 11 9710
Protoss_Robotics_Facility 1 7988
Protoss_Zealot 1 7820
Protoss_Observatory 1 8581
Protoss_Observer 2 9888
Protoss_Robotics_Support_Bay 1 9801
9888
