Protoss_Gateway 2 6732
Protoss_Assimilator 1 2792
Protoss_Cybernetics_Core 1 3755
Protoss_Zealot 1 3634
Protoss_Dragoon 6 10710
Protoss_Citadel_of_Adun 1 5482
Protoss_Robotics_Facility 1 6682
Protoss_Templar_Archives 1 6975
Protoss_Shuttle 2 10407
Protoss_Dark_Templar 3 9958
Protoss_Observatory 1 8001
Protoss_Observer 1 8708
Protoss_Nexus 1 10402
10710
