Protoss_Gateway 2 6894
Protoss_Assimilator 2 9784
Protoss_Cybernetics_Core 1 3819
Protoss_Dragoon 7 10580
Protoss_Robotics_Facility 1 5983
Protoss_Citadel_of_Adun 1 6215
Protoss_Templar_Archives 1 7205
Protoss_Shuttle 1 7527
Protoss_Dark_Templar 4 9014
Protoss_Nexus 1 9743
Protoss_Stargate 1 9667
10580
