Protoss_Gateway 2 8574
Protoss_Assimilator 1 2732
Protoss_Cybernetics_Core 1 3712
Protoss_Zealot 3 8924
Protoss_Dragoon 5 10554
Protoss_Robotics_Facility 1 6569
Protoss_Shuttle 1 7553
Protoss_Robotics_Support_Bay 1 8004
Protoss_Observatory 1 8056
Protoss_Reaver 1 9134
Protoss_Nexus 2 11557
Protoss_Observer 1 9738
11557
