Protoss_Gateway 3 9577
Protoss_Assimilator 2 8693
Protoss_Cybernetics_Core 1 4018
Protoss_Dragoon 6 10608
Protoss_Citadel_of_Adun 1 6458
Protoss_Nexus 1 8421
Protoss_Templar_Archives 1 7775
Protoss_Robotics_Facility 1 8932
Protoss_Dark_Templar 3 10380
Protoss_Observatory 1 9611
Protoss_Stargate 1 10437
Protoss_Observer 1 10420
10608
