Protoss_Gateway 9 6963
Protoss_Assimilator 1 5056
Protoss_Cybernetics_Core 1 6237
Protoss_Dragoon 2 7834
Protoss_Zealot 2 8718
Protoss_Citadel_of_Adun 1 8504
Protoss_Robotics_Facility 1 9122
Protoss_Nexus 1 10511
Protoss_Templar_Archives 1 9739
Protoss_Shuttle 1 10205
Protoss_Dark_Templar 2 10586
10586
