Protoss_Nexus 1 4514
Protoss_Gateway 2 9869
Protoss_Assimilator 2 6371
Protoss_Cybernetics_Core 1 5074
Protoss_Stargate 2 6658
Protoss_Forge 1 6691
Protoss_Corsair 4 8228
Protoss_Photon_Cannon 3 8607
Protoss_Dragoon 2 9843
Protoss_Robotics_Facility 1 9672
Protoss_Robotics_Support_Bay 1 10262
Protoss_Shuttle 1 10787
10787
