Protoss_Gateway 2 6799
Protoss_Assimilator 1 2970
Protoss_Cybernetics_Core 1 3883
Protoss_Dragoon 8 9072
Protoss_Robotics_Facility 1 6689
Protoss_Observatory 1 7688
Protoss_Observer 1 8832
Protoss_Nexus 2 11091
Protoss_Shuttle 1 9733
Protoss_Robotics_Support_Bay 1 10107
Protoss_Zealot 2 10490
11091
