Protoss_Gateway 3 9080
Protoss_Assimilator 1 2854
Protoss_Cybernetics_Core 1 3797
Protoss_Dragoon 10 10700
Protoss_Robotics_Facility 1 5612
Protoss_Observatory 1 6352
Protoss_Observer 4 9818
Protoss_Nexus 2 10791
10791
