Protoss_Assimilator 1 2446
Protoss_Gateway 3 9014
Protoss_Cybernetics_Core 1 4044
Protoss_Robotics_Facility 1 5827
Protoss_Dragoon 10 10745
Protoss_Shuttle 2 10362
Protoss_Observatory 1 7297
Protoss_Observer 3 9312
Protoss_Robotics_Support_Bay 1 8148
10745
