Protoss_Gateway 3 8680
Protoss_Assimilator 1 3022
Protoss_Cybernetics_Core 1 3865
Protoss_Zealot 1 3790
Protoss_Dragoon 10 9712
Protoss_Nexus 1 8069
Protoss_Robotics_Facility 1 10572
10572
