Protoss_Gateway 4 10396
Protoss_Assimilator 1 2794
Protoss_Cybernetics_Core 1 3722
Protoss_Dragoon 7 10320
Protoss_Nexus 2 10058
Protoss_Robotics_Facility 1 8091
Protoss_Observatory 1 8673
Protoss_Observer 2 9954
10396
