Protoss_Gateway 2 6537
Protoss_Assimilator 3 7010
Protoss_Zealot 3 5956
Protoss_Nexus 2 10990
Protoss_Cybernetics_Core 1 6046
Protoss_Dragoon 5 8830
Protoss_Robotics_Facility 1 8159
Protoss_Shuttle 1 9173
Protoss_Observatory 1 8857
Protoss_Robotics_Support_Bay 1 9181
Protoss_Observer 1 9776
Protoss_Reaver 1 10884
10990
