Protoss_Gateway 2 7139
Protoss_Assimilator 2 8742
Protoss_Cybernetics_Core 1 3913
Protoss_Dragoon 8 10194
Protoss_Nexus 1 7448
Protoss_Robotics_Facility 1 7763
Protoss_Citadel_of_Adun 1 8777
Protoss_Observatory 1 8393
Protoss_Observer 2 9676
Protoss_Templar_Archives 1 10878
10878
