Protoss_Gateway 2 8310
Protoss_Assimilator 2 8098
Protoss_Cybernetics_Core 1 3723
Protoss_Zealot 1 3668
Protoss_Dragoon 9 10406
Protoss_Nexus 1 7039
Protoss_Robotics_Facility 1 7707
Protoss_Observatory 1 8493
Protoss_Observer 2 9834
Protoss_Citadel_of_Adun 1 9711
Protoss_Stargate 1 10529
Protoss_Templar_Archives 1 10722
10722
