Protoss_Gateway 3 9899
Protoss_Assimilator 2 3491
Protoss_Zealot 2 4733
Protoss_Cybernetics_Core 1 4729
Protoss_Dragoon 6 10233
Protoss_Robotics_Facility 1 7672
Protoss_Nexus 1 9351
Protoss_Observatory 1 8222
Protoss_Observer 2 9730
10233
