Protoss_Gateway 2 8621
Protoss_Assimilator 1 2846
Protoss_Cybernetics_Core 1 3685
Protoss_Zealot 1 3648
Protoss_Dragoon 6 8796
Protoss_Robotics_Facility 1 6413
Protoss_Observatory 1 6955
Protoss_Nexus 1 8805
Protoss_Observer 2 8240
Protoss_Shuttle 1 9279
Protoss_Robotics_Support_Bay 1 9186
Protoss_Reaver 1 10364
10364
