Protoss_Gateway 1 2893
Protoss_Assimilator 1 2910
Protoss_Cybernetics_Core 1 3909
Protoss_Robotics_Facility 1 5379
Protoss_Dragoon 4 10023
Protoss_Shuttle 1 6377
Protoss_Robotics_Support_Bay 1 6164
Protoss_Reaver 2 8480
Protoss_Observatory 1 8650
Protoss_Observer 1 9383
Protoss_Nexus 1 10825
10825
