Protoss_Gateway 3 10694
Protoss_Assimilator 1 2958
Protoss_Cybernetics_Core 1 3905
Protoss_Dragoon 10 10554
Protoss_Nexus 2 10492
Protoss_Robotics_Facility 1 9153
Protoss_Observatory 1 10047
Protoss_Citadel_of_Adun 1 10509
10694
