Protoss_Gateway 3 10477
Protoss_Assimilator 2 3317
Protoss_Cybernetics_Core 1 4173
Protoss_Zealot 1 4784
Protoss_Dragoon 7 9486
Protoss_Nexus 1 9305
Protoss_Robotics_Facility 1 9407
Protoss_Shuttle 1 10607
Protoss_Robotics_Support_Bay 1 10351
10607
