Protoss_Gateway 2 8591
Protoss_Assimilator 1 2924
Protoss_Cybernetics_Core 1 3869
Protoss_Dragoon 8 10732
Protoss_Robotics_Facility 1 5585
Protoss_Shuttle 1 6563
Protoss_Robotics_Support_Bay 1 6247
Protoss_Zealot 2 7554
Protoss_Reaver 1 7831
Protoss_Observatory 1 7668
Protoss_Observer 2 9037
Protoss_Nexus 1 11711
11711
