Protoss_Gateway 2 6590
Protoss_Assimilator 1 3215
Protoss_Cybernetics_Core 1 4185
Protoss_Dragoon 9 9618
Protoss_Robotics_Facility 1 7522
Protoss_Observatory 1 8160
Protoss_Observer 2 9490
Protoss_Shuttle 1 10391
10391
