Protoss_Nexus 2 11369
Protoss_Gateway 4 8289
Protoss_Assimilator 2 7347
Protoss_Zealot 2 5663
Protoss_Cybernetics_Core 1 5665
Protoss_Dragoon 9 10743
Protoss_Robotics_Facility 1 9137
Protoss_Observatory 1 10194
11369
