Protoss_Gateway 4 9451
Protoss_Assimilator 2 10462
Protoss_Cybernetics_Core 1 4092
Protoss_Dragoon 8 10043
Protoss_Nexus 1 8232
Protoss_Robotics_Facility 1 8523
Protoss_Observatory 1 9214
Protoss_Shuttle 1 9817
Protoss_Robotics_Support_Bay 1 10142
Protoss_Zealot 1 10368
Protoss_Observer 1 10420
10462
