Protoss_Gateway 2 10031
Protoss_Assimilator 1 3062
Protoss_Cybernetics_Core 1 4605
Protoss_Zealot 2 9098
Protoss_Dragoon 4 10608
Protoss_Robotics_Facility 1 6897
Protoss_Shuttle 1 7889
Protoss_Robotics_Support_Bay 1 7795
Protoss_Reaver 1 8940
Protoss_Nexus 2 11707
Protoss_Observatory 1 9256
Protoss_Observer 2 10536
11707
