Protoss_Gateway 2 5717
Protoss_Assimilator 1 3014
Protoss_Zealot 3 5324
Protoss_Cybernetics_Core 1 4737
Protoss_Dragoon 10 10676
Protoss_Robotics_Facility 1 8374
Protoss_Observatory 1 9038
Protoss_Nexus 2 11519
Protoss_Observer 2 10578
11519
