Protoss_Gateway 2 4286
Protoss_Assimilator 1 2778
Protoss_Cybernetics_Core 1 3715
Protoss_Dragoon 13 10502
Protoss_Robotics_Facility 1 6859
Protoss_Shuttle 1 7841
Protoss_Robotics_Support_Bay 1 8057
Protoss_Zealot 2 8610
Protoss_Reaver 1 9204
10502
