Protoss_Gateway 3 10252
Protoss_Assimilator 1 3019
Protoss_Cybernetics_Core 1 4112
Protoss_Dragoon 10 10337
Protoss_Citadel_of_Adun 1 6690
Protoss_Templar_Archives 1 7732
Protoss_Dark_Templar 2 8833
Protoss_Nexus 1 10985
10985
