Protoss_Gateway 1 2781
Protoss_Assimilator 1 2964
Protoss_Cybernetics_Core 1 3785
Protoss_Zealot 3 9236
Protoss_Dragoon 4 7043
Protoss_Robotics_Facility 1 7065
Protoss_Nexus 2 11598
Protoss_Shuttle 1 8457
Protoss_Robotics_Support_Bay 1 8189
Protoss_Reaver 1 9669
Protoss_Observatory 1 9481
Protoss_Observer 1 10273
11598
