Protoss_Gateway 2 5409
Protoss_Assimilator 1 2937
Protoss_Cybernetics_Core 1 3951
Protoss_Dragoon 6 7328
Protoss_Citadel_of_Adun 1 6961
Protoss_Templar_Archives 1 7989
Protoss_Zealot 2 8108
Protoss_Dark_Templar 4 10258
Protoss_Nexus 1 10515
10515
