Protoss_Gateway 3 10856
Protoss_Assimilator 1 2904
Protoss_Cybernetics_Core 1 4030
Protoss_Dragoon 6 8474
Protoss_Nexus 2 10897
Protoss_Robotics_Facility 1 8412
Protoss_Shuttle 1 9419
Protoss_Observatory 1 9019
Protoss_Robotics_Support_Bay 1 9240
Protoss_Reaver 1 10470
Protoss_Zealot 2 10350
10897
