Protoss_Gateway 2 4316
Protoss_Assimilator 1 2940
Protoss_Cybernetics_Core 1 3829
Protoss_Dragoon 15 10726
Protoss_Robotics_Facility 1 9369
Protoss_Nexus 1 10732
Protoss_Observatory 1 9987
10732
