Protoss_Gateway 3 8361
Protoss_Assimilator 1 2811
Protoss_Cybernetics_Core 1 3971
Protoss_Zealot 4 9996
Protoss_Dragoon 9 9394
Protoss_Robotics_Facility 1 7084
Protoss_Observatory 1 7795
Protoss_Observer 2 10336
Protoss_Shuttle 1 9733
10336
