Protoss_Gateway 3 8241
Protoss_Assimilator 2 9334
Protoss_Cybernetics_Core 1 3761
Protoss_Dragoon 13 10568
Protoss_Nexus 1 7369
Protoss_Robotics_Facility 1 7423
Protoss_Observatory 1 8172
Protoss_Observer 2 9624
10568
