Protoss_Gateway 3 8556
Protoss_Assimilator 2 9709
Protoss_Cybernetics_Core 1 3965
Protoss_Dragoon 11 10520
Protoss_Nexus 1 7883
Protoss_Robotics_Facility 1 8201
Protoss_Observatory 1 8861
Protoss_Observer 2 10318
Protoss_Citadel_of_Adun 1 9979
10520
