Protoss_Gateway 2 9229
Protoss_Assimilator 1 2919
Protoss_Cybernetics_Core 1 3985
Protoss_Dragoon 9 10556
Protoss_Nexus 1 8266
Protoss_Robotics_Facility 1 9355
Protoss_Observatory 1 9930
10556
