Protoss_Gateway 2 10851
Protoss_Assimilator 1 2964
Protoss_Cybernetics_Core 1 3911
Protoss_Dragoon 6 10560
Protoss_Robotics_Facility 1 5884
Protoss_Shuttle 1 6873
Protoss_Robotics_Support_Bay 1 6561
Protoss_Nexus 1 8627
Protoss_Reaver 2 9938
Protoss_Observatory 1 7790
Protoss_Observer 2 10542
10851
