Protoss_Gateway 2 6839
Protoss_Assimilator 1 2966
Protoss_Zealot 3 4826
Protoss_Cybernetics_Core 1 4819
Protoss_Dragoon 9 9908
Protoss_Nexus 2 11624
Protoss_Robotics_Facility 1 9857
11624
