Protoss_Gateway 3 8990
Protoss_Nexus 1 5210
Protoss_Assimilator 2 7357
Protoss_Cybernetics_Core 1 5147
Protoss_Forge 1 5451
Protoss_Dragoon 4 10643
Protoss_Photon_Cannon 1 6535
Protoss_Citadel_of_Adun 1 7307
Protoss_Templar_Archives 1 8332
Protoss_Dark_Templar 3 10248
Protoss_Robotics_Facility 1 10006
Protoss_Stargate 1 10175
10643
