Protoss_Gateway 3 9471
Protoss_Assimilator 1 2748
Protoss_Cybernetics_Core 1 3675
Protoss_Zealot 1 3668
Protoss_Dragoon 11 10300
Protoss_Nexus 1 7953
Protoss_Robotics_Facility 1 8342
Protoss_Observatory 1 8897
Protoss_Observer 2 10182
10300
