Protoss_Gateway 1 2829
Protoss_Zealot 3 4748
Protoss_Assimilator 1 3675
Protoss_Cybernetics_Core 1 4689
Protoss_Dragoon 6 10673
Protoss_Robotics_Facility 1 6347
Protoss_Shuttle 1 7412
Protoss_Robotics_Support_Bay 1 7166
Protoss_Reaver 3 10620
Protoss_Nexus 1 11087
Protoss_Observatory 1 9967
11087
