Protoss_Gateway 3 10017
Protoss_Assimilator 1 2888
Protoss_Cybernetics_Core 1 3857
Protoss_Dragoon 10 10467
Protoss_Robotics_Facility 1 5982
Protoss_Robotics_Support_Bay 1 6466
Protoss_Shuttle 1 6932
Protoss_Reaver 1 7956
Protoss_Observatory 1 9448
Protoss_Nexus 2 11415
Protoss_Observer 1 10433
11415
