Protoss_Gateway 2 8655
Protoss_Assimilator 3 9181
Protoss_Cybernetics_Core 1 4099
Protoss_Dragoon 5 8664
Protoss_Nexus 1 8761
Protoss_Robotics_Facility 1 8689
Protoss_Citadel_of_Adun 1 9470
Protoss_Stargate 1 10236
Protoss_Observatory 1 9877
Protoss_Observer 1 10558
10558
