Protoss_Gateway 3 10875
Protoss_Assimilator 1 2806
Protoss_Cybernetics_Core 1 3807
Protoss_Dragoon 7 10688
Protoss_Nexus 2 10725
Protoss_Robotics_Facility 1 7502
Protoss_Robotics_Support_Bay 1 8093
Protoss_Shuttle 1 9001
Protoss_Zealot 2 8972
Protoss_Reaver 1 10160
Protoss_Observatory 1 10248
10875
