Protoss_Gateway 7 10894
Protoss_Assimilator 1 2923
Protoss_Cybernetics_Core 1 3857
Protoss_Dragoon 6 9346
Protoss_Robotics_Facility 1 6517
Protoss_Nexus 1 8239
Protoss_Shuttle 1 7611
Protoss_Robotics_Support_Bay 1 8094
Protoss_Reaver 2 10278
Protoss_Shield_Battery 1 10207
10894
