Protoss_Gateway 2 5671
Protoss_Assimilator 1 3270
Protoss_Cybernetics_Core 1 4169
Protoss_Dragoon 12 10403
Protoss_Citadel_of_Adun 1 6898
Protoss_Templar_Archives 1 7923
Protoss_Nexus 1 9914
Protoss_Robotics_Facility 1 10225
10403
