Protoss_Gateway 2 6428
Protoss_Assimilator 1 2904
Protoss_Zealot 2 4644
Protoss_Cybernetics_Core 1 4785
Protoss_Dragoon 12 10676
Protoss_Robotics_Facility 1 9498
Protoss_Nexus 1 10441
Protoss_Observatory 1 10393
10676
