Protoss_Gateway 3 10825
Protoss_Assimilator 1 2904
Protoss_Cybernetics_Core 1 3851
Protoss_Dragoon 6 10312
Protoss_Robotics_Facility 1 5553
Protoss_Shuttle 2 10757
Protoss_Zealot 2 7488
Protoss_Observatory 1 6674
Protoss_Observer 1 7358
Protoss_Robotics_Support_Bay 1 7309
Protoss_Reaver 1 8538
Protoss_Nexus 1 10300
10825
