Protoss_Gateway 4 9302
Protoss_Assimilator 2 9707
Protoss_Cybernetics_Core 1 3769
Protoss_Dragoon 12 10153
Protoss_Nexus 1 8225
Protoss_Robotics_Facility 1 8687
Protoss_Observatory 1 9428
Protoss_Citadel_of_Adun 1 10111
Protoss_Observer 1 10333
10333
