Protoss_Gateway 3 9793
Protoss_Assimilator 2 9719
Protoss_Cybernetics_Core 1 3898
Protoss_Dragoon 7 10638
Protoss_Citadel_of_Adun 1 5174
Protoss_Templar_Archives 1 6199
Protoss_Dark_Templar 4 8045
Protoss_Nexus 1 9377
10638
