Protoss_Gateway 2 8156
Protoss_Assimilator 1 2844
Protoss_Cybernetics_Core 1 3836
Protoss_Robotics_Facility 1 5366
Protoss_Dragoon 8 10124
Protoss_Observatory 1 6172
Protoss_Observer 2 7544
Protoss_Nexus 1 8431
Protoss_Shuttle 1 8601
Protoss_Robotics_Support_Bay 1 8619
Protoss_Reaver 1 9910
10124
