Protoss_Gateway 2 7184
Protoss_Assimilator 1 3123
Protoss_Cybernetics_Core 1 3919
Protoss_Zealot 1 3910
Protoss_Dragoon 10 10462
Protoss_Robotics_Facility 1 6790
Protoss_Observatory 1 7639
Protoss_Observer 2 8920
Protoss_Robotics_Support_Bay 1 9115
Protoss_Shuttle 1 9821
Protoss_Reaver 1 10872
10872
