Protoss_Gateway 4 9961
Protoss_Assimilator 1 2910
Protoss_Cybernetics_Core 1 3738
Protoss_Dragoon 10 10134
Protoss_Nexus 2 11776
Protoss_Robotics_Facility 1 8096
Protoss_Observatory 1 8635
Protoss_Observer 2 9920
11776
