Protoss_Gateway 4 9633
Protoss_Assimilator 1 2961
Protoss_Cybernetics_Core 1 3799
Protoss_Dragoon 12 10568
Protoss_Nexus 1 8031
Protoss_Robotics_Facility 1 8722
Protoss_Observatory 1 9356
Protoss_Observer 1 10260
10568
