Protoss_Gateway 2 3886
Protoss_Zealot 11 10397
Protoss_Assimilator 1 5116
Protoss_Cybernetics_Core 1 6882
Protoss_Dragoon 6 9870
Protoss_Robotics_Facility 1 8986
Protoss_Shuttle 1 10167
10397
