Protoss_Gateway 2 6074
Protoss_Zealot 4 5648
Protoss_Assimilator 1 3961
Protoss_Cybernetics_Core 1 5369
Protoss_Dragoon 9 10130
Protoss_Nexus 1 10152
Protoss_Robotics_Facility 1 10762
10762
