Protoss_Zealot 23 10488
Protoss_Gateway 2 8449
Protoss_Assimilator 1 3065
Protoss_Cybernetics_Core 1 4019
Protoss_Dragoon 6 9333
Protoss_Robotics_Facility 1 7197
Protoss_Observatory 1 8370
Protoss_Observer 1 9223
10488
