Protoss_Gateway 3 10795
Protoss_Assimilator 1 2876
Protoss_Cybernetics_Core 1 3908
Protoss_Dragoon 9 10190
Protoss_Robotics_Facility 1 6780
Protoss_Observatory 1 7382
Protoss_Observer 3 9970
Protoss_Nexus 2 10876
10876
