Protoss_Gateway 2 5818
Protoss_Assimilator 1 2958
Protoss_Cybernetics_Core 1 3897
Protoss_Dragoon 4 10144
Protoss_Citadel_of_Adun 1 5180
Protoss_Templar_Archives 1 6171
Protoss_Zealot 1 6198
Protoss_Dark_Templar 5 8680
Protoss_Nexus 1 10411
Protoss_Robotics_Facility 1 10430
10430
