Protoss_Gateway 4 10629
Protoss_Assimilator 1 3057
Protoss_Cybernetics_Core 1 3953
Protoss_Dragoon 5 10025
Protoss_Citadel_of_Adun 2 6004
Protoss_Zealot 1 6433
Protoss_Templar_Archives 1 6994
Protoss_Dark_Templar 3 10030
Protoss_Nexus 1 9195
Protoss_Robotics_Facility 1 10185
10629
