Protoss_Gateway 2 8331
Protoss_Assimilator 1 2928
Protoss_Zealot 3 4777
Protoss_Cybernetics_Core 1 5559
Protoss_Dragoon 4 10448
Protoss_Robotics_Facility 1 7221
Protoss_Citadel_of_Adun 1 7224
Protoss_Templar_Archives 1 8234
Protoss_Shuttle 1 8342
Protoss_Observatory 1 8709
Protoss_Dark_Templar 3 9955
Protoss_Observer 1 9533
Protoss_Forge 1 10218
10448
