Protoss_Gateway 2 7062
Protoss_Assimilator 1 3032
Protoss_Cybernetics_Core 1 4017
Protoss_Dragoon 7 9284
Protoss_Robotics_Facility 1 6732
Protoss_Observatory 1 7533
Protoss_Observer 1 8262
Protoss_Nexus 1 10285
Protoss_Shuttle 1 9619
Protoss_Robotics_Support_Bay 1 9716
Protoss_Reaver 1 10848
Protoss_Zealot 1 10486
10848
