Protoss_Gateway 3 9646
Protoss_Zealot 15 8577
Protoss_Forge 1 5551
Protoss_Photon_Cannon 2 10061
Protoss_Assimilator 1 8575
Protoss_Cybernetics_Core 1 9105
Protoss_Citadel_of_Adun 1 10119
Protoss_Dragoon 1 10382
10382
