Protoss_Gateway 2 8289
Protoss_Assimilator 1 3009
Protoss_Cybernetics_Core 1 3843
Protoss_Dragoon 8 9486
Protoss_Nexus 1 7863
Protoss_Robotics_Facility 1 8047
Protoss_Shuttle 1 9237
Protoss_Robotics_Support_Bay 1 9391
Protoss_Observatory 1 9900
Protoss_Zealot 2 10396
Protoss_Reaver 1 10852
10852
