Protoss_Gateway 4 10285
Protoss_Assimilator 1 2984
Protoss_Cybernetics_Core 1 3921
Protoss_Dragoon 6 10660
Protoss_Robotics_Facility 1 6742
Protoss_Shuttle 1 7815
Protoss_Robotics_Support_Bay 1 7519
Protoss_Zealot 1 7928
Protoss_Reaver 1 8866
Protoss_Nexus 1 9995
Protoss_Observatory 1 8827
Protoss_Observer 2 10136
10660
