Protoss_Gateway 3 10883
Protoss_Assimilator 1 2814
Protoss_Cybernetics_Core 1 3727
Protoss_Dragoon 6 8948
Protoss_Nexus 1 8427
Protoss_Robotics_Facility 1 8205
Protoss_Shuttle 1 9507
Protoss_Robotics_Support_Bay 1 9472
Protoss_Zealot 2 10120
Protoss_Reaver 1 10628
10883
