Protoss_Gateway 3 9261
Protoss_Assimilator 1 3012
Protoss_Cybernetics_Core 1 4019
Protoss_Dragoon 7 9498
Protoss_Nexus 2 11056
Protoss_Robotics_Facility 1 7482
Protoss_Observatory 1 8156
Protoss_Observer 2 10034
Protoss_Zealot 2 10188
11056
