Protoss_Gateway 3 10741
Protoss_Assimilator 1 2819
Protoss_Cybernetics_Core 1 3753
Protoss_Dragoon 9 9960
Protoss_Nexus 2 9451
Protoss_Robotics_Facility 1 9267
Protoss_Observatory 1 9932
10741
