Protoss_Gateway 2 3149
Protoss_Zealot 11 8546
Protoss_Assimilator 1 5329
Protoss_Forge 1 5377
Protoss_Cybernetics_Core 1 6768
Protoss_Photon_Cannon 4 8266
Protoss_Dragoon 4 10334
Protoss_Robotics_Facility 1 10229
Protoss_Nexus 1 11120
11120
