Protoss_Gateway 3 8049
Protoss_Assimilator 1 3086
Protoss_Cybernetics_Core 1 3910
Protoss_Dragoon 14 10557
Protoss_Robotics_Facility 1 6727
Protoss_Observatory 1 7291
Protoss_Observer 3 9338
10557
