Protoss_Gateway 3 9720
Protoss_Assimilator 1 2940
Protoss_Cybernetics_Core 1 3898
Protoss_Dragoon 8 9330
Protoss_Robotics_Facility 1 6673
Protoss_Observatory 1 7221
Protoss_Nexus 1 9012
Protoss_Observer 2 8560
Protoss_Citadel_of_Adun 1 9022
Protoss_Zealot 3 10590
10590
