Protoss_Nexus 1 4445
Protoss_Gateway 4 8937
Protoss_Assimilator 2 7783
Protoss_Cybernetics_Core 1 4986
Protoss_Zealot 2 8888
Protoss_Dragoon 9 10212
Protoss_Robotics_Facility 1 8102
Protoss_Observatory 1 8654
Protoss_Shuttle 1 9117
Protoss_Robotics_Support_Bay 1 9530
Protoss_Observer 1 9720
Protoss_Stargate 1 10499
Protoss_Reaver 1 10770
10770
