Protoss_Gateway 3 8552
Protoss_Assimilator 1 2887
Protoss_Cybernetics_Core 1 3856
Protoss_Dragoon 13 10746
Protoss_Nexus 1 8261
Protoss_Shield_Battery 1 9540
Protoss_Robotics_Facility 1 10679
10746
