Protoss_Gateway 4 10691
Protoss_Assimilator 1 2802
Protoss_Cybernetics_Core 1 3729
Protoss_Dragoon 7 8140
Protoss_Nexus 1 8455
Protoss_Robotics_Facility 1 8433
Protoss_Citadel_of_Adun 1 8845
Protoss_Zealot 4 9848
Protoss_Shuttle 1 9709
Protoss_Templar_Archives 2 10067
Protoss_Observatory 1 9835
Protoss_Observer 1 10524
10691
