Protoss_Gateway 4 10877
Protoss_Assimilator 1 3140
Protoss_Zealot 1 3560
Protoss_Cybernetics_Core 1 4611
Protoss_Dragoon 9 10632
Protoss_Nexus 2 10987
Protoss_Robotics_Facility 1 8141
Protoss_Observatory 1 8869
Protoss_Observer 2 10414
10987
