Protoss_Nexus 2 10467
Protoss_Gateway 2 5668
Protoss_Assimilator 2 7820
Protoss_Cybernetics_Core 1 4977
Protoss_Dragoon 3 7040
Protoss_Citadel_of_Adun 2 6846
Protoss_Zealot 2 7642
Protoss_Templar_Archives 1 8009
Protoss_Dark_Templar 5 10358
Protoss_Robotics_Facility 1 10308
10467
