Protoss_Gateway 3 10493
Protoss_Assimilator 2 9594
Protoss_Cybernetics_Core 1 4037
Protoss_Dragoon 6 10564
Protoss_Citadel_of_Adun 1 6299
Protoss_Robotics_Facility 1 7289
Protoss_Templar_Archives 1 7299
Protoss_Nexus 1 8745
Protoss_Dark_Templar 2 8138
Protoss_Shuttle 1 8423
Protoss_Observatory 1 8519
Protoss_Observer 1 10162
10564
