Protoss_Gateway 2 4459
Protoss_Assimilator 1 2938
Protoss_Cybernetics_Core 1 3883
Protoss_Dragoon 8 9244
Protoss_Nexus 1 9317
Protoss_Citadel_of_Adun 1 8709
Protoss_Robotics_Facility 1 9396
Protoss_Templar_Archives 1 9770
Protoss_Shuttle 1 10499
Protoss_Dark_Templar 1 10634
10634
