Protoss_Gateway 3 10549
Protoss_Assimilator 1 2924
Protoss_Cybernetics_Core 1 3766
Protoss_Dragoon 12 10078
Protoss_Nexus 1 10219
Protoss_Citadel_of_Adun 1 10056
Protoss_Robotics_Facility 1 10659
10659
