Protoss_Nexus 1 4554
Protoss_Gateway 4 10265
Protoss_Assimilator 2 7025
Protoss_Cybernetics_Core 1 4927
Protoss_Zealot 1 5238
Protoss_Dragoon 4 7298
Protoss_Citadel_of_Adun 1 6811
Protoss_Templar_Archives 1 7821
Protoss_Stargate 1 8859
Protoss_Dark_Templar 4 9642
Protoss_Arbiter_Tribunal 1 9965
10265
