Protoss_Gateway 4 10873
Protoss_Assimilator 1 2816
Protoss_Cybernetics_Core 1 3829
Protoss_Dragoon 5 10678
Protoss_Robotics_Facility 1 6461
Protoss_Shuttle 1 7707
Protoss_Robotics_Support_Bay 1 7338
Protoss_Zealot 2 8310
Protoss_Reaver 1 8908
Protoss_Nexus 1 10521
Protoss_Observatory 1 9387
Protoss_Observer 1 10572
10873
