Protoss_Nexus 1 5152
Protoss_Assimilator 1 4261
Protoss_Gateway 6 10516
Protoss_Cybernetics_Core 2 10037
Protoss_Zealot 3 7948
Protoss_Dragoon 4 8700
Protoss_Citadel_of_Adun 1 7414
Protoss_Templar_Archives 1 8605
Protoss_Shield_Battery 1 8494
Protoss_Dark_Templar 4 10435
10516
