Protoss_Gateway 2 6496
Protoss_Assimilator 1 2896
Protoss_Cybernetics_Core 1 3903
Protoss_Dragoon 11 10198
Protoss_Robotics_Facility 1 8293
Protoss_Robotics_Support_Bay 1 8996
Protoss_Reaver 1 10321
10321
