Protoss_Gateway 5 10730
Protoss_Assimilator 2 9041
Protoss_Cybernetics_Core 1 3960
Protoss_Dragoon 9 9693
Protoss_Nexus 1 9410
Protoss_Robotics_Facility 1 9314
Protoss_Observatory 1 9899
Protoss_Citadel_of_Adun 1 10576
Protoss_Observer 1 10588
10730
