Protoss_Gateway 3 10233
Protoss_Assimilator 1 3013
Protoss_Zealot 3 4824
Protoss_Cybernetics_Core 1 4741
Protoss_Dragoon 9 10248
Protoss_Nexus 2 9457
Protoss_Robotics_Facility 1 9551
Protoss_Observatory 1 10359
10359
