Protoss_Gateway 3 10492
Protoss_Assimilator 1 3018
Protoss_Cybernetics_Core 1 3839
Protoss_Dragoon 7 10634
Protoss_Zealot 2 6592
Protoss_Citadel_of_Adun 1 6103
Protoss_Templar_Archives 1 7137
Protoss_Dark_Templar 4 9124
Protoss_Nexus 1 9805
10634
