Protoss_Gateway 2 4331
Protoss_Assimilator 2 10193
Protoss_Cybernetics_Core 1 4945
Protoss_Zealot 1 4788
Protoss_Dragoon 6 8938
Protoss_Nexus 1 9339
Protoss_Citadel_of_Adun 1 8822
Protoss_Templar_Archives 1 9905
Protoss_Dark_Templar 2 10744
10744
