Protoss_Gateway 2 7111
Protoss_Assimilator 2 4067
Protoss_Zealot 2 4204
Protoss_Cybernetics_Core 1 5126
Protoss_Dragoon 7 10580
Protoss_Nexus 2 11299
Protoss_Citadel_of_Adun 1 7945
Protoss_Templar_Archives 1 8943
Protoss_Robotics_Facility 1 9965
Protoss_Dark_Templar 2 9784
11299
