Protoss_Gateway 2 3211
Protoss_Zealot 2 3970
Protoss_Assimilator 1 4301
Protoss_Cybernetics_Core 1 5077
Protoss_Dragoon 10 10356
Protoss_Nexus 1 8884
Protoss_Robotics_Facility 1 10182
10356
