Protoss_Gateway 4 10134
Protoss_Assimilator 1 2830
Protoss_Cybernetics_Core 1 3749
Protoss_Dragoon 8 8642
Protoss_Robotics_Facility 1 6554
Protoss_Observatory 1 7169
Protoss_Observer 1 7950
Protoss_Citadel_of_Adun 1 9046
Protoss_Nexus 1 10367
Protoss_Templar_Archives 1 10068
Protoss_Shuttle 1 10383
10383
