Protoss_Gateway 2 10026
Protoss_Assimilator 1 3003
Protoss_Cybernetics_Core 1 3954
Protoss_Dragoon 7 10482
Protoss_Robotics_Facility 1 6577
Protoss_Zealot 2 7406
Protoss_Shuttle 1 7561
Protoss_Robotics_Support_Bay 1 7149
Protoss_Reaver 1 8612
Protoss_Nexus 1 9867
Protoss_Observatory 1 8854
Protoss_Observer 1 10270
10482
