Protoss_Nexus 2 9677
Protoss_Gateway 4 9867
Protoss_Assimilator 1 3870
Protoss_Cybernetics_Core 1 4989
Protoss_Zealot 1 5134
Protoss_Dragoon 11 10712
Protoss_Robotics_Facility 1 9472
Protoss_Observatory 1 10051
10712
