Protoss_Gateway 3 7169
Protoss_Zealot 4 4573
Protoss_Assimilator 2 9234
Protoss_Cybernetics_Core 1 5747
Protoss_Nexus 1 7130
Protoss_Dragoon 12 10350
Protoss_Shield_Battery 1 8910
10350
