Protoss_Gateway 3 9599
Protoss_Assimilator 1 2949
Protoss_Zealot 1 3410
Protoss_Cybernetics_Core 1 4165
Protoss_Dragoon 8 10476
Protoss_Robotics_Facility 1 6761
Protoss_Nexus 1 8607
Protoss_Shuttle 1 8265
Protoss_Robotics_Support_Bay 1 8143
Protoss_Reaver 1 9316
Protoss_Observatory 1 9212
Protoss_Observer 1 10126
10476
