Protoss_Nexus 2 10127
Protoss_Gateway 2 5574
Protoss_Assimilator 1 4189
Protoss_Cybernetics_Core 1 5103
Protoss_Dragoon 9 10178
Protoss_Zealot 2 9154
Protoss_Robotics_Facility 1 10117
10178
