Protoss_Gateway 2 6550
Protoss_Assimilator 1 2838
Protoss_Cybernetics_Core 1 3764
Protoss_Zealot 1 3780
Protoss_Dragoon 4 10454
Protoss_Citadel_of_Adun 1 5323
Protoss_Robotics_Facility 1 6253
Protoss_Templar_Archives 1 6918
Protoss_Shuttle 1 7609
Protoss_Dark_Templar 3 8552
Protoss_Observatory 1 7951
Protoss_Nexus 2 11179
Protoss_Observer 2 10554
11179
