Protoss_Gateway 1 2757
Protoss_Assimilator 1 2851
Protoss_Cybernetics_Core 1 3888
Protoss_Dragoon 6 9194
Protoss_Robotics_Facility 1 6737
Protoss_Observatory 1 7306
Protoss_Nexus 2 11129
Protoss_Observer 3 9302
Protoss_Forge 2 10057
Protoss_Citadel_of_Adun 1 10730
11129
