Protoss_Gateway 3 10494
Protoss_Nexus 1 5779
Protoss_Zealot 2 5214
Protoss_Assimilator 2 6721
Protoss_Cybernetics_Core 1 6166
Protoss_Dragoon 9 10114
Protoss_Robotics_Facility 1 9065
Protoss_Observatory 1 9669
10494
