Protoss_Gateway 2 7387
Protoss_Assimilator 1 2985
Protoss_Cybernetics_Core 1 3911
Protoss_Dragoon 9 9686
Protoss_Robotics_Facility 1 6940
Protoss_Shuttle 1 7989
Protoss_Observatory 1 7901
Protoss_Observer 2 10414
Protoss_Robotics_Support_Bay 1 8547
Protoss_Reaver 1 9810
Protoss_Nexus 1 11479
11479
