Protoss_Nexus 1 4599
Protoss_Gateway 2 4748
Protoss_Assimilator 2 8595
Protoss_Cybernetics_Core 1 5285
Protoss_Zealot 1 5316
Protoss_Dragoon 10 10088
Protoss_Robotics_Facility 1 8521
Protoss_Observatory 1 9211
Protoss_Observer 1 9950
Protoss_Stargate 1 10722
10722
