Protoss_Gateway 2 8909
Protoss_Assimilator 2 9151
Protoss_Cybernetics_Core 1 4199
Protoss_Dragoon 7 10494
Protoss_Nexus 2 11491
Protoss_Citadel_of_Adun 1 7247
Protoss_Templar_Archives 1 8285
Protoss_Stargate 1 9397
Protoss_Dark_Templar 1 9122
11491
