Protoss_Gateway 5 10125
Protoss_Assimilator 1 2917
Protoss_Cybernetics_Core 1 3741
Protoss_Dragoon 8 10284
Protoss_Nexus 2 10359
Protoss_Robotics_Facility 1 8344
Protoss_Observatory 1 8918
Protoss_Zealot 3 10146
Protoss_Observer 2 10202
Protoss_Citadel_of_Adun 1 10677
10677
