Protoss_Gateway 3 10412
Protoss_Assimilator 1 2755
Protoss_Cybernetics_Core 1 3710
Protoss_Dragoon 9 10664
Protoss_Nexus 1 8326
Protoss_Robotics_Facility 1 8110
Protoss_Shuttle 1 9101
Protoss_Robotics_Support_Bay 1 9035
Protoss_Reaver 1 10288
Protoss_Observatory 1 10165
10664
