Protoss_Gateway 2 6273
Protoss_Assimilator 1 2865
Protoss_Cybernetics_Core 1 3826
Protoss_Dragoon 8 10172
Protoss_Robotics_Facility 1 6103
Protoss_Observatory 1 6666
Protoss_Observer 2 8230
Protoss_Nexus 2 11730
Protoss_Shuttle 1 9493
Protoss_Robotics_Support_Bay 1 9616
11730
