Protoss_Assimilator 3 6722
Protoss_Gateway 4 9509
Protoss_Zealot 6 10006
Protoss_Nexus 2 11449
Protoss_Cybernetics_Core 1 6495
Protoss_Dragoon 4 10216
Protoss_Citadel_of_Adun 1 8276
Protoss_Templar_Archives 1 9974
11449
