Protoss_Gateway 1 2892
Protoss_Assimilator 1 3056
Protoss_Zealot 2 7802
Protoss_Cybernetics_Core 1 4848
Protoss_Dragoon 5 10290
Protoss_Robotics_Facility 1 7033
Protoss_Robotics_Support_Bay 1 7577
Protoss_Shuttle 1 8275
Protoss_Reaver 2 10378
10378
