Protoss_Assimilator 2 8804
Protoss_Gateway 2 8179
Protoss_Cybernetics_Core 1 4187
Protoss_Dragoon 5 8518
Protoss_Nexus 2 11665
Protoss_Citadel_of_Adun 1 7216
Protoss_Robotics_Facility 1 8234
Protoss_Templar_Archives 1 8415
Protoss_Shuttle 1 9335
Protoss_High_Templar 4 10724
11665
