Protoss_Gateway 2 5673
Protoss_Nexus 2 10645
Protoss_Assimilator 2 7433
Protoss_Cybernetics_Core 1 5135
Protoss_Zealot 1 5664
Protoss_Dragoon 9 10036
Protoss_Robotics_Facility 1 8195
Protoss_Observatory 1 8765
Protoss_Observer 2 10148
10645
