Protoss_Gateway 2 4191
Protoss_Assimilator 3 8385
Protoss_Zealot 7 7244
Protoss_Nexus 1 7039
Protoss_Cybernetics_Core 1 7133
Protoss_Dragoon 6 10120
Protoss_Robotics_Facility 1 10183
10183
