Protoss_Gateway 2 7057
Protoss_Assimilator 1 2785
Protoss_Cybernetics_Core 1 3892
Protoss_Dragoon 8 10170
Protoss_Robotics_Facility 1 6102
Protoss_Shuttle 1 7313
Protoss_Observatory 1 7109
Protoss_Robotics_Support_Bay 1 7667
Protoss_Observer 1 7916
Protoss_Reaver 1 8966
Protoss_Nexus 1 10469
10469
