Protoss_Nexus 2 9643
Protoss_Gateway 2 5253
Protoss_Assimilator 2 9919
Protoss_Cybernetics_Core 1 5041
Protoss_Zealot 1 5232
Protoss_Dragoon 10 9832
Protoss_Robotics_Facility 1 9187
Protoss_Shuttle 1 10179
Protoss_Robotics_Support_Bay 1 9955
Protoss_Observatory 1 10413
10413
