Protoss_Gateway 4 10771
Protoss_Assimilator 2 9401
Protoss_Cybernetics_Core 1 3953
Protoss_Dragoon 6 10452
Protoss_Nexus 2 10926
Protoss_Citadel_of_Adun 1 7251
Protoss_Zealot 2 8074
Protoss_Templar_Archives 1 8497
Protoss_Dark_Templar 2 9700
10926
