Protoss_Forge 1 2971
Protoss_Photon_Cannon 6 8755
Protoss_Gateway 2 10246
Protoss_Assimilator 2 9827
Protoss_Cybernetics_Core 1 6810
Protoss_Nexus 1 8347
Protoss_Zealot 1 7238
Protoss_Citadel_of_Adun 1 8234
Protoss_Dragoon 2 8903
Protoss_Templar_Archives 1 9529
10246
