Protoss_Assimilator 2 4933
Protoss_Gateway 2 6842
Protoss_Zealot 2 5246
Protoss_Nexus 1 5956
Protoss_Cybernetics_Core 1 6028
Protoss_Dragoon 6 9408
Protoss_Shield_Battery 1 7505
Protoss_Robotics_Facility 1 9038
Protoss_Shuttle 1 10051
Protoss_Robotics_Support_Bay 1 9916
10051
