Protoss_Gateway 4 10002
Protoss_Assimilator 1 2828
Protoss_Cybernetics_Core 1 3791
Protoss_Dragoon 8 10478
Protoss_Nexus 2 8362
Protoss_Robotics_Facility 1 8121
Protoss_Observatory 1 8685
Protoss_Observer 1 9682
10478
