Protoss_Gateway 2 4285
Protoss_Assimilator 2 9662
Protoss_Cybernetics_Core 1 3804
Protoss_Dragoon 6 8200
Protoss_Nexus 1 8040
Protoss_Citadel_of_Adun 1 7425
Protoss_Robotics_Facility 1 8213
Protoss_Templar_Archives 1 8623
Protoss_Shuttle 1 9339
Protoss_Dark_Templar 4 10284
Protoss_Observatory 1 10342
10342
