Protoss_Gateway 3 10825
Protoss_Assimilator 1 2922
Protoss_Cybernetics_Core 1 3900
Protoss_Zealot 1 3836
Protoss_Citadel_of_Adun 1 5198
Protoss_Dragoon 6 10404
Protoss_Templar_Archives 1 6185
Protoss_Dark_Templar 2 7766
Protoss_Nexus 1 8607
Protoss_Robotics_Facility 1 8734
Protoss_Shuttle 1 10025
Protoss_Observatory 1 10073
10825
