Protoss_Gateway 2 7035
Protoss_Assimilator 1 2962
Protoss_Zealot 4 10366
Protoss_Cybernetics_Core 1 4766
Protoss_Dragoon 6 9516
Protoss_Robotics_Facility 1 6205
Protoss_Observatory 1 6812
Protoss_Observer 3 8712
Protoss_Nexus 1 9684
Protoss_Shuttle 1 10033
Protoss_Robotics_Support_Bay 1 9693
10366
