Protoss_Assimilator 3 9634
Protoss_Gateway 2 6132
Protoss_Zealot 2 4758
Protoss_Cybernetics_Core 1 5464
Protoss_Nexus 2 10287
Protoss_Dragoon 7 9624
Protoss_Robotics_Facility 1 10163
10287
