Protoss_Gateway 1 2723
Protoss_Assimilator 1 2938
Protoss_Cybernetics_Core 1 3877
Protoss_Dragoon 5 10446
Protoss_Robotics_Facility 1 5804
Protoss_Zealot 2 7320
Protoss_Shuttle 1 6789
Protoss_Robotics_Support_Bay 1 6569
Protoss_Reaver 1 7840
Protoss_Nexus 1 9427
Protoss_Observatory 1 8553
Protoss_Observer 1 9236
10446
