Protoss_Gateway 3 10076
Protoss_Assimilator 1 3173
Protoss_Cybernetics_Core 1 4341
Protoss_Dragoon 9 10373
Protoss_Robotics_Facility 1 7835
Protoss_Observatory 1 8542
Protoss_Nexus 1 10326
Protoss_Observer 2 10360
Protoss_Forge 1 10398
10398
