Protoss_Gateway 2 5020
Protoss_Assimilator 1 3071
Protoss_Cybernetics_Core 1 4084
Protoss_Dragoon 7 8183
Protoss_Robotics_Facility 1 8268
Protoss_Observatory 1 8996
Protoss_Nexus 1 10400
Protoss_Zealot 2 9583
Protoss_Observer 1 9698
Protoss_Shuttle 1 10692
10692
