Protoss_Gateway 2 10531
Protoss_Assimilator 1 3208
Protoss_Zealot 2 7930
Protoss_Cybernetics_Core 1 4921
Protoss_Dragoon 6 10464
Protoss_Robotics_Facility 1 6688
Protoss_Shuttle 1 7701
Protoss_Robotics_Support_Bay 1 7355
Protoss_Reaver 2 10882
Protoss_Observatory 1 9080
Protoss_Nexus 1 10913
Protoss_Observer 1 9764
10913
