Protoss_Gateway 3 8976
Protoss_Assimilator 1 3000
Protoss_Cybernetics_Core 1 3956
Protoss_Dragoon 12 10618
Protoss_Nexus 1 7805
Protoss_Robotics_Facility 1 8153
Protoss_Observatory 1 9319
Protoss_Observer 1 10002
10618
