Protoss_Gateway 2 10893
Protoss_Assimilator 1 2959
Protoss_Zealot 3 8228
Protoss_Cybernetics_Core 1 4599
Protoss_Dragoon 6 10728
Protoss_Robotics_Facility 1 6517
Protoss_Shuttle 2 10845
Protoss_Robotics_Support_Bay 1 7247
Protoss_Reaver 1 8564
Protoss_Observatory 1 8610
Protoss_Nexus 1 10349
Protoss_Observer 1 9532
10893
