Protoss_Gateway 3 9158
Protoss_Assimilator 1 2827
Protoss_Cybernetics_Core 1 3873
Protoss_Dragoon 8 10154
Protoss_Robotics_Facility 1 6466
Protoss_Observatory 1 7062
Protoss_Nexus 1 9439
Protoss_Observer 3 9756
Protoss_Shuttle 1 9505
10154
