Protoss_Gateway 2 5679
Protoss_Assimilator 2 10188
Protoss_Cybernetics_Core 1 3912
Protoss_Citadel_of_Adun 1 4931
Protoss_Dragoon 6 10518
Protoss_Templar_Archives 1 6036
Protoss_Dark_Templar 4 7896
Protoss_Nexus 1 9347
Protoss_Stargate 1 9436
10518
