Protoss_Gateway 2 5709
Protoss_Assimilator 1 3001
Protoss_Cybernetics_Core 1 3946
Protoss_Dragoon 8 10462
Protoss_Citadel_of_Adun 1 5154
Protoss_Templar_Archives 1 6203
Protoss_Dark_Templar 2 7042
Protoss_Nexus 2 10887
10887
