Protoss_Gateway 2 6912
Protoss_Assimilator 1 2989
Protoss_Cybernetics_Core 1 3907
Protoss_Dragoon 11 10580
Protoss_Robotics_Facility 1 6914
Protoss_Shuttle 1 7897
Protoss_Robotics_Support_Bay 1 8041
Protoss_Reaver 2 10466
10580
