Protoss_Gateway 3 9754
Protoss_Assimilator 2 9989
Protoss_Zealot 1 3514
Protoss_Cybernetics_Core 1 4634
Protoss_Dragoon 9 10746
Protoss_Citadel_of_Adun 1 5699
Protoss_Templar_Archives 1 6690
Protoss_Nexus 1 8087
Protoss_Dark_Templar 1 7520
Protoss_Robotics_Facility 1 8570
Protoss_Observatory 1 9151
Protoss_Observer 1 9832
10746
