Protoss_Gateway 2 7796
Protoss_Assimilator 1 2931
Protoss_Zealot 2 4618
Protoss_Cybernetics_Core 1 4749
Protoss_Dragoon 5 8876
Protoss_Nexus 2 11704
Protoss_Citadel_of_Adun 1 7125
Protoss_Robotics_Facility 1 8498
Protoss_Templar_Archives 1 8570
Protoss_Dark_Templar 2 9628
Protoss_Shuttle 1 9881
Protoss_Observatory 1 9500
Protoss_Observer 1 10484
11704
