Protoss_Gateway 4 10305
Protoss_Assimilator 1 3019
Protoss_Cybernetics_Core 1 3903
Protoss_Dragoon 9 9648
Protoss_Robotics_Facility 1 6806
Protoss_Observatory 1 7414
Protoss_Nexus 1 8964
Protoss_Observer 3 10238
Protoss_Shuttle 1 10705
10705
