Protoss_Gateway 2 4337
Protoss_Assimilator 2 10313
Protoss_Cybernetics_Core 1 3783
Protoss_Zealot 1 4218
Protoss_Dragoon 8 10668
Protoss_Nexus 2 9779
Protoss_Robotics_Facility 1 7965
Protoss_Observatory 1 8671
Protoss_Observer 2 9950
Protoss_Robotics_Support_Bay 1 10019
10668
