Protoss_Gateway 2 3491
Protoss_Zealot 5 4898
Protoss_Assimilator 2 10543
Protoss_Cybernetics_Core 1 5551
Protoss_Dragoon 8 10502
Protoss_Robotics_Facility 1 7975
Protoss_Nexus 1 9391
Protoss_Observatory 1 8552
Protoss_Observer 2 9898
10543
