Protoss_Gateway 2 5765
Protoss_Assimilator 1 2822
Protoss_Cybernetics_Core 1 3806
Protoss_Dragoon 8 10262
Protoss_Robotics_Facility 1 5542
Protoss_Observatory 1 6712
Protoss_Observer 2 10442
Protoss_Shuttle 1 8329
Protoss_Robotics_Support_Bay 1 8547
Protoss_Zealot 2 9066
Protoss_Reaver 1 9838
Protoss_Nexus 1 10913
Protoss_Citadel_of_Adun 1 10642
10913
