Protoss_Gateway 2 10619
Protoss_Assimilator 1 2925
Protoss_Cybernetics_Core 1 3987
Protoss_Dragoon 8 10568
Protoss_Robotics_Facility 1 5708
Protoss_Shuttle 1 6699
Protoss_Robotics_Support_Bay 1 6391
Protoss_Reaver 1 7912
Protoss_Observatory 1 7775
Protoss_Observer 2 9118
Protoss_Nexus 1 11011
11011
