Protoss_Gateway 4 10580
Protoss_Assimilator 1 2921
Protoss_Cybernetics_Core 1 3824
Protoss_Dragoon 5 10262
Protoss_Robotics_Facility 1 6526
Protoss_Observatory 1 7067
Protoss_Nexus 1 8742
Protoss_Observer 2 10306
Protoss_Robotics_Support_Bay 1 7719
Protoss_Shuttle 1 8649
Protoss_Zealot 2 9466
Protoss_Reaver 1 9700
10580
