Protoss_Gateway 2 9213
Protoss_Assimilator 1 2964
Protoss_Cybernetics_Core 1 3904
Protoss_Dragoon 8 10226
Protoss_Robotics_Facility 1 6598
Protoss_Observatory 1 7153
Protoss_Nexus 1 8932
Protoss_Observer 1 7846
Protoss_Robotics_Support_Bay 1 7956
Protoss_Shuttle 1 9885
Protoss_Reaver 1 10944
10944
