Protoss_Gateway 2 3309
Protoss_Zealot 14 9566
Protoss_Forge 1 4098
Protoss_Photon_Cannon 4 8312
Protoss_Assimilator 1 8556
Protoss_Cybernetics_Core 1 9430
Protoss_Dragoon 2 10428
10428
