Protoss_Gateway 4 10021
Protoss_Assimilator 2 9982
Protoss_Cybernetics_Core 1 3956
Protoss_Zealot 1 4164
Protoss_Dragoon 6 10476
Protoss_Citadel_of_Adun 2 10159
Protoss_Nexus 2 10393
Protoss_Robotics_Facility 1 8095
Protoss_Observatory 1 8661
Protoss_Observer 2 9998
10476
