Protoss_Gateway 2 7488
Protoss_Assimilator 1 2955
Protoss_Cybernetics_Core 1 3914
Protoss_Dragoon 9 9462
Protoss_Robotics_Facility 1 7009
Protoss_Shuttle 1 7995
Protoss_Observatory 1 7965
Protoss_Observer 1 8650
Protoss_Robotics_Support_Bay 1 8961
Protoss_Reaver 1 10090
Protoss_Zealot 1 10116
Protoss_Nexus 1 11768
11768
