Protoss_Gateway 2 6861
Protoss_Assimilator 1 3032
Protoss_Cybernetics_Core 1 3980
Protoss_Dragoon 12 10564
Protoss_Robotics_Facility 1 6662
Protoss_Shuttle 1 7707
Protoss_Observatory 1 7392
Protoss_Observer 2 10120
Protoss_Nexus 1 10950
Protoss_Forge 1 10129
10950
