Protoss_Gateway 1 2723
Protoss_Assimilator 1 2935
Protoss_Cybernetics_Core 1 3877
Protoss_Dragoon 7 9436
Protoss_Robotics_Facility 1 6742
Protoss_Observatory 1 7411
Protoss_Robotics_Support_Bay 1 7523
Protoss_Observer 1 8116
Protoss_Nexus 2 11483
Protoss_Shuttle 1 9743
Protoss_Zealot 1 10038
11483
