Protoss_Gateway 2 6895
Protoss_Assimilator 1 3016
Protoss_Cybernetics_Core 1 3864
Protoss_Zealot 1 3800
Protoss_Dragoon 10 10474
Protoss_Robotics_Facility 1 6707
Protoss_Observatory 1 7317
Protoss_Observer 2 8848
Protoss_Nexus 1 10911
Protoss_Shuttle 1 10167
Protoss_Robotics_Support_Bay 1 10425
10911
