Protoss_Gateway 2 8836
Protoss_Assimilator 1 2848
Protoss_Cybernetics_Core 1 3714
Protoss_Dragoon 10 10442
Protoss_Robotics_Facility 1 6589
Protoss_Nexus 1 8529
Protoss_Observatory 1 7234
Protoss_Observer 2 8514
Protoss_Shuttle 1 9415
Protoss_Robotics_Support_Bay 1 9407
Protoss_Reaver 1 10558
10558
