Protoss_Gateway 4 10037
Protoss_Assimilator 1 3083
Protoss_Cybernetics_Core 1 3984
Protoss_Nexus 2 9611
Protoss_Dragoon 10 10160
Protoss_Robotics_Facility 1 9396
Protoss_Observatory 1 10070
10160
