Protoss_Gateway 6 10823
Protoss_Assimilator 1 2976
Protoss_Cybernetics_Core 1 3805
Protoss_Dragoon 6 9786
Protoss_Robotics_Facility 1 6647
Protoss_Observatory 1 7213
Protoss_Nexus 2 10063
Protoss_Observer 3 9140
10823
