Protoss_Gateway 2 8524
Protoss_Assimilator 1 2790
Protoss_Cybernetics_Core 1 3916
Protoss_Dragoon 8 10224
Protoss_Robotics_Facility 1 6486
Protoss_Observatory 1 7061
Protoss_Observer 1 7766
Protoss_Nexus 1 9165
Protoss_Shuttle 1 8841
Protoss_Robotics_Support_Bay 1 8837
Protoss_Zealot 1 9306
Protoss_Reaver 1 10138
10224
