Protoss_Gateway 3 8656
Protoss_Assimilator 1 3105
Protoss_Cybernetics_Core 1 4084
Protoss_Dragoon 5 8467
Protoss_Robotics_Facility 2 7766
Protoss_Observatory 1 8330
Protoss_Observer 1 9223
Protoss_Zealot 3 9838
Protoss_Shuttle 1 10152
10152
