Protoss_Gateway 4 10845
Protoss_Assimilator 1 2704
Protoss_Cybernetics_Core 1 3763
Protoss_Dragoon 10 10470
Protoss_Nexus 2 10255
Protoss_Robotics_Facility 1 7235
Protoss_Observatory 1 7945
Protoss_Observer 3 10110
10845
