Protoss_Nexus 2 11321
Protoss_Gateway 3 9129
Protoss_Assimilator 2 7940
Protoss_Cybernetics_Core 1 4824
Protoss_Zealot 3 8880
Protoss_Dragoon 8 9632
Protoss_Robotics_Facility 2 8750
Protoss_Shuttle 1 9879
Protoss_Robotics_Support_Bay 1 9514
Protoss_Reaver 1 10930
11321
