Protoss_Gateway 3 5076
Protoss_Assimilator 1 4408
Protoss_Cybernetics_Core 1 5983
Protoss_Zealot 2 5774
Protoss_Dragoon 8 10368
Protoss_Nexus 1 9959
Protoss_Robotics_Facility 1 10496
Protoss_Stargate 1 11020
11020
