Protoss_Nexus 2 9223
Protoss_Gateway 6 10339
Protoss_Assimilator 1 3943
Protoss_Cybernetics_Core 1 4921
Protoss_Zealot 1 5064
Protoss_Dragoon 10 10018
Protoss_Robotics_Facility 1 9453
Protoss_Observatory 1 10215
10339
