Protoss_Gateway 2 8962
Protoss_Assimilator 1 2937
Protoss_Cybernetics_Core 1 3889
Protoss_Dragoon 7 10366
Protoss_Robotics_Facility 1 6691
Protoss_Nexus 1 8601
Protoss_Observatory 1 7476
Protoss_Observer 1 8176
Protoss_Robotics_Support_Bay 1 8645
Protoss_Shuttle 1 9545
Protoss_Reaver 1 10596
10596
