Protoss_Gateway 3 10765
Protoss_Assimilator 2 10384
Protoss_Cybernetics_Core 1 3929
Protoss_Dragoon 9 10192
Protoss_Nexus 1 8068
Protoss_Robotics_Facility 1 8398
Protoss_Observatory 1 9191
Protoss_Shuttle 1 9891
Protoss_Observer 2 10500
10765
