Protoss_Gateway 2 7114
Protoss_Assimilator 1 3042
Protoss_Zealot 3 9344
Protoss_Cybernetics_Core 1 4637
Protoss_Dragoon 9 10096
Protoss_Robotics_Facility 1 7075
Protoss_Observatory 1 7660
Protoss_Observer 1 8380
Protoss_Shuttle 1 9599
Protoss_Nexus 1 11647
11647
