Protoss_Gateway 2 5451
Protoss_Assimilator 2 10178
Protoss_Cybernetics_Core 1 3751
Protoss_Dragoon 10 10200
Protoss_Nexus 1 8419
Protoss_Robotics_Facility 1 9037
Protoss_Citadel_of_Adun 1 9323
Protoss_Shuttle 1 10095
Protoss_Robotics_Support_Bay 1 10177
Protoss_Templar_Archives 1 10794
10794
