Protoss_Gateway 3 7229
Protoss_Assimilator 1 3166
Protoss_Zealot 10 9224
Protoss_Cybernetics_Core 1 4915
Protoss_Dragoon 2 9514
Protoss_Citadel_of_Adun 1 6172
Protoss_Templar_Archives 1 9258
Protoss_Dark_Templar 3 10266
10266
