Protoss_Gateway 2 8775
Protoss_Assimilator 2 3177
Protoss_Cybernetics_Core 1 4229
Protoss_Dragoon 9 10448
Protoss_Nexus 1 8103
Protoss_Robotics_Facility 1 8386
Protoss_Observatory 1 9475
Protoss_Observer 1 10160
10448
