Protoss_Gateway 3 8400
Protoss_Assimilator 1 2949
Protoss_Cybernetics_Core 1 3959
Protoss_Dragoon 6 9693
Protoss_Robotics_Facility 1 6771
Protoss_Observatory 1 7499
Protoss_Observer 1 8183
Protoss_Zealot 4 9358
Protoss_Shuttle 1 9084
9693
