Protoss_Gateway 3 9891
Protoss_Assimilator 1 2847
Protoss_Cybernetics_Core 1 3843
Protoss_Dragoon 11 10356
Protoss_Robotics_Facility 1 6495
Protoss_Observatory 1 7185
Protoss_Observer 1 8338
Protoss_Nexus 1 9805
10356
