Protoss_Gateway 2 6641
Protoss_Assimilator 2 9425
Protoss_Cybernetics_Core 1 4027
Protoss_Dragoon 4 7744
Protoss_Citadel_of_Adun 1 6393
Protoss_Templar_Archives 1 7419
Protoss_Zealot 1 7210
Protoss_Dark_Templar 2 8496
Protoss_Nexus 2 11606
11606
