Protoss_Gateway 2 10895
Protoss_Assimilator 1 3000
Protoss_Cybernetics_Core 1 4051
Protoss_Dragoon 6 10096
Protoss_Robotics_Facility 1 6752
Protoss_Shuttle 1 7745
Protoss_Robotics_Support_Bay 1 7570
Protoss_Zealot 2 8640
Protoss_Reaver 2 10020
Protoss_Observatory 1 8512
Protoss_Nexus 1 10495
10895
