Protoss_Gateway 4 10637
Protoss_Assimilator 1 2892
Protoss_Cybernetics_Core 1 3814
Protoss_Dragoon 9 10614
Protoss_Nexus 2 11165
Protoss_Citadel_of_Adun 1 6941
Protoss_Robotics_Facility 1 8047
Protoss_Templar_Archives 1 8146
Protoss_Shuttle 1 9073
Protoss_Dark_Templar 2 9190
Protoss_Observatory 1 9046
Protoss_Observer 1 10034
11165
