Protoss_Gateway 1 2825
Protoss_Assimilator 1 2953
Protoss_Cybernetics_Core 1 4042
Protoss_Dragoon 6 9538
Protoss_Robotics_Facility 1 6653
Protoss_Shuttle 1 7693
Protoss_Observatory 1 7623
Protoss_Robotics_Support_Bay 1 7965
Protoss_Observer 2 10164
Protoss_Reaver 1 9376
Protoss_Zealot 1 10140
10164
