Protoss_Gateway 3 8101
Protoss_Zealot 2 5194
Protoss_Assimilator 1 4184
Protoss_Cybernetics_Core 1 5442
Protoss_Dragoon 7 9906
Protoss_Robotics_Facility 1 8093
Protoss_Observatory 1 8635
Protoss_Nexus 1 10547
Protoss_Observer 2 9966
Protoss_Shuttle 1 10437
Protoss_Robotics_Support_Bay 1 10213
10547
