Protoss_Nexus 1 4594
Protoss_Gateway 2 5174
Protoss_Assimilator 1 3926
Protoss_Cybernetics_Core 1 5030
Protoss_Zealot 4 10440
Protoss_Dragoon 9 10398
Protoss_Robotics_Facility 1 7751
Protoss_Shuttle 1 8735
Protoss_Robotics_Support_Bay 1 8543
Protoss_Reaver 1 9836
Protoss_Observatory 1 9576
10440
