Protoss_Gateway 3 10184
Protoss_Assimilator 2 8766
Protoss_Cybernetics_Core 1 4130
Protoss_Dragoon 6 10404
Protoss_Nexus 1 7481
Protoss_Robotics_Facility 1 7579
Protoss_Shuttle 1 8645
Protoss_Observatory 1 8415
Protoss_Robotics_Support_Bay 1 8497
Protoss_Zealot 2 9606
Protoss_Reaver 1 10044
10404
