Protoss_Gateway 2 7295
Protoss_Assimilator 1 2851
Protoss_Cybernetics_Core 1 3895
Protoss_Dragoon 6 9938
Protoss_Citadel_of_Adun 1 6559
Protoss_Robotics_Facility 1 7270
Protoss_Templar_Archives 1 8199
Protoss_Shuttle 1 8771
Protoss_Dark_Templar 2 9176
Protoss_Observatory 1 9380
Protoss_Zealot 1 9714
Protoss_Observer 1 10110
Protoss_Nexus 1 11693
11693
