Protoss_Gateway 2 6906
Protoss_Assimilator 1 3062
Protoss_Cybernetics_Core 1 4037
Protoss_Dragoon 10 10358
Protoss_Robotics_Facility 1 6873
Protoss_Observatory 1 7458
Protoss_Observer 2 8878
Protoss_Nexus 1 9687
Protoss_Shuttle 1 9903
Protoss_Robotics_Support_Bay 1 9543
Protoss_Reaver 1 10958
10958
