Protoss_Gateway 4 10720
Protoss_Assimilator 1 3103
Protoss_Cybernetics_Core 1 4003
Protoss_Dragoon 8 8880
Protoss_Robotics_Facility 1 6853
Protoss_Observatory 1 7612
Protoss_Observer 1 8338
Protoss_Shuttle 1 9459
Protoss_Nexus 1 10629
Protoss_Robotics_Support_Bay 1 9485
Protoss_Zealot 2 9852
Protoss_Reaver 1 11008
11008
