Protoss_Gateway 2 7550
Protoss_Assimilator 1 2824
Protoss_Zealot 2 4592
Protoss_Cybernetics_Core 1 4579
Protoss_Dragoon 6 9336
Protoss_Robotics_Facility 1 7063
Protoss_Observatory 1 7629
Protoss_Observer 2 8910
Protoss_Nexus 1 9908
Protoss_Shuttle 1 9811
Protoss_Robotics_Support_Bay 1 9687
Protoss_Reaver 1 10862
10862
