Protoss_Gateway 3 10787
Protoss_Assimilator 1 2840
Protoss_Cybernetics_Core 1 3748
Protoss_Dragoon 4 8764
Protoss_Robotics_Facility 1 6393
Protoss_Citadel_of_Adun 1 7097
Protoss_Observatory 1 6983
Protoss_Nexus 1 8723
Protoss_Zealot 1 7650
Protoss_Observer 1 7778
Protoss_Templar_Archives 1 8601
Protoss_Shuttle 1 9333
Protoss_Dark_Templar 4 10604
10787
