Protoss_Gateway 3 8149
Protoss_Assimilator 1 2770
Protoss_Cybernetics_Core 1 3791
Protoss_Robotics_Facility 1 5157
Protoss_Shuttle 1 6147
Protoss_Dragoon 10 10693
Protoss_Observatory 1 7963
Protoss_Observer 2 9255
Protoss_Nexus 1 10935
10935
