Protoss_Nexus 1 4641
Protoss_Gateway 5 10546
Protoss_Assimilator 1 4125
Protoss_Cybernetics_Core 1 5445
Protoss_Zealot 4 10444
Protoss_Dragoon 13 10448
Protoss_Robotics_Facility 1 8767
Protoss_Shuttle 1 9957
Protoss_Observatory 1 10276
10546
