Protoss_Assimilator 3 4711
Protoss_Gateway 2 8764
Protoss_Cybernetics_Core 1 4263
Protoss_Dragoon 10 10670
Protoss_Nexus 2 11187
Protoss_Robotics_Facility 1 8357
Protoss_Observatory 1 8930
Protoss_Observer 2 10268
11187
