Protoss_Gateway 1 2729
Protoss_Assimilator 1 2826
Protoss_Cybernetics_Core 1 3801
Protoss_Zealot 1 3756
Protoss_Dragoon 8 10188
Protoss_Robotics_Facility 1 7572
Protoss_Shuttle 1 8601
Protoss_Robotics_Support_Bay 1 8349
Protoss_Observatory 1 8629
Protoss_Reaver 1 9652
Protoss_Observer 1 10280
10280
