Protoss_Gateway 3 10323
Protoss_Assimilator 1 2810
Protoss_Cybernetics_Core 1 3822
Protoss_Dragoon 6 8612
Protoss_Robotics_Facility 1 6686
Protoss_Shuttle 1 7793
Protoss_Robotics_Support_Bay 1 7452
Protoss_Nexus 1 9377
Protoss_Reaver 1 9616
Protoss_Zealot 2 9816
10323
