Protoss_Gateway 3 9289
Protoss_Assimilator 2 9606
Protoss_Cybernetics_Core 1 3784
Protoss_Dragoon 9 10464
Protoss_Nexus 1 7008
Protoss_Robotics_Facility 1 7244
Protoss_Observatory 1 7999
Protoss_Shuttle 1 8701
Protoss_Observer 1 9304
Protoss_Robotics_Support_Bay 1 9314
Protoss_Reaver 1 10438
Protoss_Zealot 2 10564
10564
