Protoss_Gateway 2 5599
Protoss_Assimilator 1 3020
Protoss_Cybernetics_Core 1 3888
Protoss_Dragoon 12 10452
Protoss_Nexus 1 8615
Protoss_Robotics_Facility 1 8226
Protoss_Shuttle 1 9341
Protoss_Robotics_Support_Bay 1 9068
Protoss_Reaver 1 10392
10452
