Protoss_Gateway 2 4587
Protoss_Assimilator 1 3058
Protoss_Cybernetics_Core 1 3936
Protoss_Dragoon 7 9852
Protoss_Nexus 2 9260
Protoss_Citadel_of_Adun 1 8805
Protoss_Templar_Archives 1 10038
Protoss_Stargate 1 10423
10423
