Protoss_Gateway 2 10530
Protoss_Zealot 5 8614
Protoss_Assimilator 2 9889
Protoss_Nexus 1 8524
Protoss_Forge 1 7379
Protoss_Cybernetics_Core 1 8277
Protoss_Photon_Cannon 2 9019
Protoss_Citadel_of_Adun 1 9540
Protoss_Robotics_Facility 1 10391
Protoss_Templar_Archives 1 10673
10673
