Protoss_Gateway 5 10531
Protoss_Assimilator 1 2913
Protoss_Cybernetics_Core 1 3698
Protoss_Dragoon 6 6628
Protoss_Nexus 2 9229
Protoss_Citadel_of_Adun 1 8797
Protoss_Templar_Archives 1 9868
10531
