Protoss_Gateway 2 5021
Protoss_Assimilator 1 3376
Protoss_Cybernetics_Core 1 4185
Protoss_Dragoon 7 9590
Protoss_Nexus 2 9504
Protoss_Forge 2 8861
Protoss_Robotics_Facility 1 10827
10827
