Protoss_Gateway 2 8250
Protoss_Assimilator 1 2782
Protoss_Cybernetics_Core 1 3762
Protoss_Dragoon 10 10099
Protoss_Nexus 1 7761
Protoss_Robotics_Facility 1 7817
Protoss_Observatory 1 8539
Protoss_Observer 3 10551
10551
