Protoss_Nexus 1 4469
Protoss_Gateway 2 5262
Protoss_Assimilator 2 7421
Protoss_Cybernetics_Core 1 4995
Protoss_Dragoon 11 10058
Protoss_Robotics_Facility 1 8045
Protoss_Shuttle 1 9067
Protoss_Observatory 2 9914
Protoss_Robotics_Support_Bay 1 8777
Protoss_Reaver 1 10118
10118
