Protoss_Gateway 2 8551
Protoss_Assimilator 2 9363
Protoss_Cybernetics_Core 1 3631
Protoss_Dragoon 10 10662
Protoss_Robotics_Facility 1 6588
Protoss_Shuttle 1 7571
Protoss_Robotics_Support_Bay 1 7349
Protoss_Observatory 1 7664
Protoss_Reaver 1 8622
Protoss_Observer 3 10489
Protoss_Nexus 1 11645
11645
