Protoss_Gateway 3 10033
Protoss_Assimilator 1 2998
Protoss_Cybernetics_Core 1 3892
Protoss_Dragoon 6 10550
Protoss_Robotics_Facility 1 6618
Protoss_Shuttle 1 7747
Protoss_Robotics_Support_Bay 1 7310
Protoss_Zealot 1 7918
Protoss_Reaver 1 8798
Protoss_Nexus 1 9841
Protoss_Observatory 1 8644
Protoss_Observer 1 9840
10550
