Protoss_Gateway 3 8219
Protoss_Assimilator 1 2895
Protoss_Cybernetics_Core 1 3946
Protoss_Dragoon 10 9812
Protoss_Nexus 1 7590
Protoss_Robotics_Facility 1 7511
Protoss_Observatory 1 8083
Protoss_Observer 2 9366
9812
