Protoss_Gateway 4 9847
Protoss_Zealot 1 3322
Protoss_Assimilator 1 4303
Protoss_Cybernetics_Core 1 5551
Protoss_Dragoon 10 10262
Protoss_Nexus 1 9193
Protoss_Robotics_Facility 1 9900
10262
