Protoss_Gateway 2 5563
Protoss_Assimilator 2 8397
Protoss_Cybernetics_Core 1 4173
Protoss_Dragoon 5 9756
Protoss_Nexus 1 7397
Protoss_Robotics_Facility 1 7312
Protoss_Stargate 2 10961
Protoss_Observatory 1 8082
Protoss_Fleet_Beacon 1 8949
Protoss_Zealot 4 10548
Protoss_Observer 1 9618
Protoss_Carrier 1 11505
11505
