Protoss_Gateway 4 10283
Protoss_Assimilator 1 2854
Protoss_Cybernetics_Core 1 3804
Protoss_Dragoon 7 9706
Protoss_Robotics_Facility 1 5453
Protoss_Observatory 1 6134
Protoss_Nexus 2 10427
Protoss_Observer 3 8162
10427
