Protoss_Gateway 2 10569
Protoss_Assimilator 1 2967
Protoss_Cybernetics_Core 1 3904
Protoss_Dragoon 7 10572
Protoss_Robotics_Facility 1 5549
Protoss_Shuttle 2 10279
Protoss_Robotics_Support_Bay 1 6475
Protoss_Zealot 2 7278
Protoss_Reaver 1 7654
Protoss_Observatory 1 8053
Protoss_Nexus 1 9907
Protoss_Observer 1 8824
10572
