Protoss_Nexus 1 4565
Protoss_Gateway 4 10266
Protoss_Assimilator 2 7205
Protoss_Zealot 2 5700
Protoss_Cybernetics_Core 1 5666
Protoss_Dragoon 9 10486
Protoss_Forge 1 8032
Protoss_Robotics_Facility 1 8869
Protoss_Photon_Cannon 1 9092
Protoss_Citadel_of_Adun 1 9724
Protoss_Observatory 1 9442
Protoss_Observer 1 10146
Protoss_Templar_Archives 1 10783
10783
