Protoss_Gateway 4 10116
Protoss_Nexus 1 5029
Protoss_Assimilator 2 7096
Protoss_Cybernetics_Core 1 5247
Protoss_Zealot 3 9990
Protoss_Dragoon 8 9386
Protoss_Robotics_Facility 1 8591
Protoss_Observatory 1 9191
Protoss_Stargate 2 10677
Protoss_Observer 1 9878
Protoss_Fleet_Beacon 1 10859
Protoss_Shuttle 1 10881
10881
