Protoss_Nexus 1 4559
Protoss_Gateway 3 10183
Protoss_Assimilator 2 8124
Protoss_Cybernetics_Core 1 4961
Protoss_Zealot 1 5352
Protoss_Dragoon 12 10252
Protoss_Robotics_Facility 1 8076
Protoss_Shuttle 1 9081
Protoss_Robotics_Support_Bay 1 9291
Protoss_Reaver 1 10638
Protoss_Stargate 1 10975
10975
