Protoss_Gateway 2 5392
Protoss_Assimilator 1 3021
Protoss_Cybernetics_Core 1 3956
Protoss_Dragoon 10 10452
Protoss_Nexus 1 7923
Protoss_Robotics_Facility 1 7680
Protoss_Shuttle 1 8675
Protoss_Robotics_Support_Bay 1 8916
Protoss_Observatory 1 9718
10452
