Protoss_Assimilator 1 2353
Protoss_Gateway 3 10559
Protoss_Cybernetics_Core 1 4161
Protoss_Robotics_Facility 1 5480
Protoss_Dragoon 6 9858
Protoss_Shuttle 1 6467
Protoss_Robotics_Support_Bay 1 7404
Protoss_Forge 1 7654
Protoss_Photon_Cannon 1 8525
Protoss_Reaver 1 9326
Protoss_Nexus 1 10957
10957
