Protoss_Gateway 2 6946
Protoss_Assimilator 1 2946
Protoss_Cybernetics_Core 1 3722
Protoss_Dragoon 3 6424
Protoss_Robotics_Facility 1 6639
Protoss_Citadel_of_Adun 1 6456
Protoss_Templar_Archives 1 7467
Protoss_Shuttle 1 7647
Protoss_Robotics_Support_Bay 1 7288
Protoss_Dark_Templar 4 9764
Protoss_Reaver 2 10120
Protoss_Nexus 1 10691
10691
