Protoss_Gateway 2 4281
Protoss_Assimilator 1 2893
Protoss_Cybernetics_Core 1 3726
Protoss_Dragoon 11 9740
Protoss_Robotics_Facility 1 8474
Protoss_Nexus 2 11615
Protoss_Observatory 1 9041
Protoss_Observer 1 10316
11615
