Protoss_Gateway 3 10597
Protoss_Assimilator 2 9414
Protoss_Cybernetics_Core 1 3959
Protoss_Dragoon 10 10492
Protoss_Nexus 1 6522
Protoss_Robotics_Facility 1 7621
Protoss_Observatory 1 8165
Protoss_Observer 2 9624
Protoss_Shuttle 1 10553
Protoss_Robotics_Support_Bay 1 10155
Protoss_Zealot 2 10484
10597
