Protoss_Gateway 2 6623
Protoss_Assimilator 1 2804
Protoss_Cybernetics_Core 1 3838
Protoss_Dragoon 10 10098
Protoss_Robotics_Facility 1 6151
Protoss_Observatory 1 6750
Protoss_Observer 2 8032
Protoss_Nexus 1 9981
10098
