Protoss_Gateway 2 6801
Protoss_Assimilator 1 3075
Protoss_Cybernetics_Core 1 4033
Protoss_Dragoon 10 10433
Protoss_Robotics_Facility 1 5837
Protoss_Observatory 1 6458
Protoss_Observer 2 8113
Protoss_Nexus 1 10330
10433
