Protoss_Gateway 2 8877
Protoss_Assimilator 1 2922
Protoss_Cybernetics_Core 1 3803
Protoss_Dragoon 8 10450
Protoss_Robotics_Facility 1 6562
Protoss_Observatory 1 7107
Protoss_Observer 3 9074
Protoss_Nexus 1 9223
Protoss_Shuttle 1 9393
Protoss_Robotics_Support_Bay 1 8988
Protoss_Reaver 1 10444
10450
