Protoss_Gateway 2 6740
Protoss_Assimilator 1 2862
Protoss_Cybernetics_Core 1 3848
Protoss_Dragoon 8 10244
Protoss_Robotics_Facility 1 6511
Protoss_Observatory 1 7157
Protoss_Nexus 2 10616
Protoss_Observer 2 8710
Protoss_Shuttle 1 9611
Protoss_Robotics_Support_Bay 1 9489
Protoss_Reaver 1 10662
Protoss_Zealot 2 10470
10662
