Protoss_Nexus 1 4391
Protoss_Gateway 2 5039
Protoss_Assimilator 2 8496
Protoss_Cybernetics_Core 1 4919
Protoss_Zealot 2 9090
Protoss_Dragoon 9 10122
Protoss_Robotics_Facility 1 7843
Protoss_Shuttle 1 8841
Protoss_Robotics_Support_Bay 1 8618
Protoss_Reaver 1 10020
10122
