Protoss_Gateway 2 5075
Protoss_Assimilator 2 9313
Protoss_Cybernetics_Core 1 3726
Protoss_Dragoon 12 9718
Protoss_Nexus 1 8914
Protoss_Citadel_of_Adun 1 9138
Protoss_Templar_Archives 1 10585
Protoss_Robotics_Facility 1 10980
10980
