Protoss_Gateway 3 8707
Protoss_Zealot 4 5354
Protoss_Assimilator 1 4256
Protoss_Cybernetics_Core 1 5387
Protoss_Dragoon 9 10496
Protoss_Nexus 1 10135
Protoss_Robotics_Facility 1 9885
Protoss_Observatory 1 10427
10496
