Protoss_Gateway 1 2833
Protoss_Assimilator 1 2953
Protoss_Cybernetics_Core 1 3872
Protoss_Zealot 3 8496
Protoss_Dragoon 6 10000
Protoss_Robotics_Facility 1 6799
Protoss_Shuttle 1 7779
Protoss_Robotics_Support_Bay 1 7602
Protoss_Reaver 1 8830
Protoss_Observatory 1 8332
Protoss_Observer 2 10107
Protoss_Nexus 1 11088
11088
