Protoss_Gateway 3 9139
Protoss_Assimilator 1 2884
Protoss_Zealot 2 9180
Protoss_Cybernetics_Core 1 4031
Protoss_Robotics_Facility 1 5377
Protoss_Dragoon 9 10684
Protoss_Observatory 1 6117
Protoss_Observer 2 7866
Protoss_Nexus 1 8679
10684
