Protoss_Gateway 2 6982
Protoss_Assimilator 1 2974
Protoss_Cybernetics_Core 1 3903
Protoss_Zealot 3 10362
Protoss_Dragoon 8 9352
Protoss_Robotics_Facility 1 6619
Protoss_Observatory 1 7209
Protoss_Observer 2 8992
Protoss_Nexus 1 10110
Protoss_Shuttle 1 10049
Protoss_Robotics_Support_Bay 1 10091
10362
