Protoss_Gateway 2 5479
Protoss_Zealot 2 3912
Protoss_Assimilator 1 4331
Protoss_Cybernetics_Core 1 5226
Protoss_Dragoon 7 10124
Protoss_Robotics_Facility 1 8308
Protoss_Nexus 1 9995
Protoss_Observatory 1 9290
Protoss_Observer 1 10094
Protoss_Robotics_Support_Bay 1 10202
10202
