Protoss_Gateway 2 10695
Protoss_Assimilator 1 2784
Protoss_Cybernetics_Core 1 3751
Protoss_Dragoon 6 9976
Protoss_Robotics_Facility 1 5406
Protoss_Shuttle 1 6409
Protoss_Robotics_Support_Bay 1 6454
Protoss_Reaver 4 10766
Protoss_Nexus 1 10149
10766
