Protoss_Gateway 4 10575
Protoss_Assimilator 2 10035
Protoss_Cybernetics_Core 1 3880
Protoss_Dragoon 3 6236
Protoss_Citadel_of_Adun 1 6237
Protoss_Robotics_Facility 1 6601
Protoss_Templar_Archives 1 7290
Protoss_Shuttle 1 7601
Protoss_Dark_Templar 6 10052
Protoss_Nexus 1 9904
10575
