Protoss_Gateway 2 5481
Protoss_Assimilator 1 2959
Protoss_Cybernetics_Core 1 3885
Protoss_Dragoon 10 10112
Protoss_Nexus 2 9530
Protoss_Robotics_Facility 1 9307
Protoss_Shuttle 1 10377
Protoss_Robotics_Support_Bay 1 10086
Protoss_Observatory 1 10130
10377
