Protoss_Nexus 1 4967
Protoss_Gateway 4 10706
Protoss_Assimilator 2 8485
Protoss_Cybernetics_Core 1 5278
Protoss_Zealot 1 5048
Protoss_Dragoon 8 9975
Protoss_Robotics_Facility 1 7197
Protoss_Observatory 1 7828
Protoss_Observer 1 8658
Protoss_Robotics_Support_Bay 1 10319
10706
