Protoss_Nexus 1 4369
Protoss_Gateway 4 9981
Protoss_Assimilator 2 7025
Protoss_Cybernetics_Core 1 5003
Protoss_Dragoon 13 10310
Protoss_Robotics_Facility 1 8281
Protoss_Observatory 1 9046
Protoss_Observer 2 10406
Protoss_Citadel_of_Adun 1 10886
10886
