Protoss_Gateway 2 6437
Protoss_Assimilator 1 2959
Protoss_Cybernetics_Core 1 3930
Protoss_Dragoon 7 8537
Protoss_Robotics_Facility 1 6631
Protoss_Observatory 1 7361
Protoss_Observer 2 8656
Protoss_Nexus 2 10423
Protoss_Shuttle 1 9821
Protoss_Robotics_Support_Bay 1 9565
Protoss_Reaver 1 10872
10872
