Protoss_Assimilator 2 4667
Protoss_Gateway 2 6567
Protoss_Zealot 3 5720
Protoss_Cybernetics_Core 1 5185
Protoss_Nexus 1 6761
Protoss_Dragoon 9 10100
Protoss_Robotics_Facility 1 10039
10100
