Protoss_Gateway 2 7877
Protoss_Assimilator 1 2864
Protoss_Cybernetics_Core 1 3909
Protoss_Dragoon 8 10536
Protoss_Robotics_Facility 1 6423
Protoss_Nexus 2 10557
Protoss_Observatory 1 7095
Protoss_Observer 3 9220
10557
