Protoss_Nexus 2 11197
Protoss_Gateway 2 5813
Protoss_Assimilator 2 8768
Protoss_Cybernetics_Core 1 4987
Protoss_Zealot 2 7432
Protoss_Dragoon 8 9180
Protoss_Robotics_Facility 1 7671
Protoss_Observatory 1 8252
Protoss_Observer 2 9640
11197
