Protoss_Gateway 2 9027
Protoss_Assimilator 1 3050
Protoss_Zealot 2 4140
Protoss_Cybernetics_Core 1 4193
Protoss_Dragoon 6 9998
Protoss_Robotics_Facility 1 6953
Protoss_Observatory 1 7497
Protoss_Nexus 1 9199
Protoss_Observer 2 8946
Protoss_Citadel_of_Adun 1 8747
Protoss_Shuttle 1 9675
Protoss_Templar_Archives 1 9783
Protoss_Dark_Templar 1 10670
10670
