Protoss_Gateway 2 8452
Protoss_Assimilator 1 2792
Protoss_Cybernetics_Core 1 3751
Protoss_Zealot 1 3712
Protoss_Dragoon 8 9340
Protoss_Robotics_Facility 1 7087
Protoss_Nexus 2 11465
Protoss_Observatory 1 7756
Protoss_Observer 4 10383
11465
