Protoss_Gateway 3 8772
Protoss_Assimilator 1 2906
Protoss_Cybernetics_Core 1 3758
Protoss_Dragoon 11 10634
Protoss_Zealot 1 5192
Protoss_Robotics_Facility 1 6314
Protoss_Observatory 1 6955
Protoss_Nexus 2 11449
Protoss_Observer 5 10458
11449
