Protoss_Gateway 2 6777
Protoss_Assimilator 1 2962
Protoss_Cybernetics_Core 1 4109
Protoss_Dragoon 12 10364
Protoss_Forge 1 7978
Protoss_Nexus 1 9973
Protoss_Photon_Cannon 2 10253
10364
