Protoss_Gateway 3 6883
Protoss_Assimilator 1 2926
Protoss_Cybernetics_Core 1 3725
Protoss_Zealot 4 10546
Protoss_Dragoon 3 6038
Protoss_Citadel_of_Adun 1 5570
Protoss_Templar_Archives 1 6561
Protoss_Dark_Templar 10 10682
10682
