Protoss_Gateway 2 9683
Protoss_Assimilator 2 9684
Protoss_Cybernetics_Core 1 4061
Protoss_Dragoon 8 10182
Protoss_Nexus 1 7795
Protoss_Robotics_Facility 1 8365
Protoss_Observatory 1 8919
Protoss_Robotics_Support_Bay 1 9313
Protoss_Citadel_of_Adun 1 9823
Protoss_Observer 1 9600
Protoss_Shuttle 1 10529
10529
