Protoss_Gateway 2 8059
Protoss_Assimilator 2 9428
Protoss_Zealot 2 4298
Protoss_Cybernetics_Core 1 4530
Protoss_Dragoon 8 9930
Protoss_Nexus 1 8213
Protoss_Robotics_Facility 1 7981
Protoss_Shuttle 1 8993
Protoss_Observatory 1 8595
Protoss_Robotics_Support_Bay 1 9136
Protoss_Observer 1 9596
Protoss_Reaver 1 11012
11012
