Protoss_Gateway 4 10325
Protoss_Assimilator 1 2964
Protoss_Cybernetics_Core 1 3905
Protoss_Zealot 1 3976
Protoss_Dragoon 9 10534
Protoss_Robotics_Facility 1 6725
Protoss_Nexus 1 8960
Protoss_Observatory 1 7744
Protoss_Observer 4 10412
10534
