Protoss_Forge 1 2740
Protoss_Photon_Cannon 4 5814
Protoss_Gateway 2 7576
Protoss_Assimilator 2 10588
Protoss_Cybernetics_Core 1 6414
Protoss_Zealot 3 10568
Protoss_Dragoon 6 9966
Protoss_Nexus 1 9751
10588
