Protoss_Gateway 3 10341
Protoss_Assimilator 2 10312
Protoss_Cybernetics_Core 1 3947
Protoss_Dragoon 7 9786
Protoss_Robotics_Facility 1 6923
Protoss_Nexus 1 8687
Protoss_Shuttle 1 8133
Protoss_Robotics_Support_Bay 1 8156
Protoss_Reaver 1 9430
Protoss_Observatory 1 9146
Protoss_Observer 1 10034
10341
