Protoss_Gateway 2 7175
Protoss_Assimilator 1 2751
Protoss_Cybernetics_Core 1 3655
Protoss_Dragoon 7 10724
Protoss_Robotics_Facility 1 6708
Protoss_Shuttle 1 7719
Protoss_Nexus 2 11607
Protoss_Robotics_Support_Bay 1 7766
Protoss_Reaver 1 8962
Protoss_Observatory 1 8634
Protoss_Zealot 2 8844
Protoss_Observer 2 10168
11607
