Protoss_Gateway 2 8485
Protoss_Assimilator 1 2982
Protoss_Cybernetics_Core 1 3931
Protoss_Dragoon 8 10000
Protoss_Robotics_Facility 1 5644
Protoss_Observatory 1 6437
Protoss_Shuttle 1 7185
Protoss_Observer 3 8992
Protoss_Robotics_Support_Bay 1 9055
Protoss_Nexus 1 10771
10771
