Protoss_Gateway 2 5775
Protoss_Assimilator 1 2998
Protoss_Zealot 3 4856
Protoss_Cybernetics_Core 1 4921
Protoss_Dragoon 3 7116
Protoss_Robotics_Facility 1 7105
Protoss_Citadel_of_Adun 1 7555
Protoss_Templar_Archives 1 8565
Protoss_Shuttle 1 8585
Protoss_Dark_Templar 4 10158
Protoss_Nexus 1 11397
11397
