Protoss_Gateway 3 8761
Protoss_Assimilator 1 2980
Protoss_Cybernetics_Core 1 3863
Protoss_Zealot 1 3886
Protoss_Dragoon 7 9992
Protoss_Nexus 2 11505
Protoss_Robotics_Facility 1 8242
Protoss_Observatory 1 8874
Protoss_Observer 2 10194
11505
