Protoss_Assimilator 2 3472
Protoss_Gateway 2 5840
Protoss_Cybernetics_Core 1 4500
Protoss_Dragoon 10 10262
Protoss_Nexus 2 11512
Protoss_Robotics_Facility 1 10994
Protoss_Citadel_of_Adun 1 10882
11512
