Protoss_Gateway 5 10447
Protoss_Assimilator 1 2846
Protoss_Cybernetics_Core 1 3835
Protoss_Robotics_Facility 1 5245
Protoss_Dragoon 8 10280
Protoss_Observatory 1 6209
Protoss_Observer 4 9066
Protoss_Nexus 2 9361
10447
