Protoss_Gateway 2 8159
Protoss_Assimilator 2 9938
Protoss_Cybernetics_Core 1 4151
Protoss_Zealot 2 10040
Protoss_Dragoon 7 10176
Protoss_Nexus 1 7861
Protoss_Robotics_Facility 1 7977
Protoss_Shuttle 1 9005
Protoss_Observatory 1 8638
Protoss_Robotics_Support_Bay 1 9387
Protoss_Observer 1 9608
Protoss_Reaver 1 10764
10764
