Protoss_Gateway 2 6265
Protoss_Assimilator 1 2968
Protoss_Cybernetics_Core 1 3921
Protoss_Zealot 4 10144
Protoss_Dragoon 8 9836
Protoss_Robotics_Facility 1 7419
Protoss_Observatory 1 8154
Protoss_Observer 1 9002
Protoss_Nexus 1 10713
Protoss_Shuttle 1 10481
10713
