Protoss_Gateway 2 3447
Protoss_Zealot 2 4214
Protoss_Assimilator 1 4391
Protoss_Cybernetics_Core 1 5460
Protoss_Dragoon 8 10032
Protoss_Robotics_Facility 1 9409
Protoss_Nexus 1 10131
Protoss_Robotics_Support_Bay 1 10064
Protoss_Shuttle 1 10767
10767
