Protoss_Gateway 3 10627
Protoss_Zealot 4 9114
Protoss_Assimilator 1 3719
Protoss_Cybernetics_Core 1 4473
Protoss_Dragoon 6 10112
Protoss_Nexus 1 7269
Protoss_Robotics_Facility 1 7371
Protoss_Shuttle 1 8389
Protoss_Robotics_Support_Bay 1 8223
Protoss_Reaver 1 9440
Protoss_Observatory 1 9204
Protoss_Observer 1 10044
10627
