Protoss_Gateway 1 2763
Protoss_Assimilator 1 2952
Protoss_Zealot 1 3476
Protoss_Cybernetics_Core 1 4137
Protoss_Robotics_Facility 1 5481
Protoss_Dragoon 6 9988
Protoss_Shuttle 1 6467
Protoss_Robotics_Support_Bay 1 6485
Protoss_Reaver 2 10340
Protoss_Observatory 1 7692
Protoss_Observer 2 9252
Protoss_Nexus 1 11551
11551
