Protoss_Gateway 2 6415
Protoss_Assimilator 2 9284
Protoss_Forge 1 4867
Protoss_Cybernetics_Core 1 5359
Protoss_Dragoon 6 9744
Protoss_Nexus 1 7835
Protoss_Citadel_of_Adun 1 8089
Protoss_Robotics_Facility 1 8779
Protoss_Templar_Archives 1 9485
Protoss_Robotics_Support_Bay 1 10061
Protoss_Shield_Battery 1 10093
Protoss_Dark_Templar 2 10550
10550
