Protoss_Gateway 2 7527
Protoss_Assimilator 1 3068
Protoss_Cybernetics_Core 1 3921
Protoss_Dragoon 10 10262
Protoss_Robotics_Facility 1 7233
Protoss_Observatory 1 7858
Protoss_Observer 2 10204
Protoss_Nexus 1 9954
10262
