Protoss_Gateway 3 10888
Protoss_Assimilator 1 3078
Protoss_Cybernetics_Core 1 4159
Protoss_Zealot 1 4184
Protoss_Dragoon 9 10088
Protoss_Nexus 1 10175
Protoss_Robotics_Facility 1 9675
Protoss_Citadel_of_Adun 1 9638
Protoss_Templar_Archives 1 10653
Protoss_Observatory 1 10267
10888
