Protoss_Gateway 3 9505
Protoss_Assimilator 1 2906
Protoss_Cybernetics_Core 1 3892
Protoss_Dragoon 9 10392
Protoss_Robotics_Facility 1 6507
Protoss_Observatory 1 7397
Protoss_Nexus 1 9034
Protoss_Observer 1 8176
10392
