Protoss_Gateway 2 9878
Protoss_Assimilator 1 2819
Protoss_Cybernetics_Core 1 3757
Protoss_Dragoon 5 9098
Protoss_Robotics_Facility 1 6648
Protoss_Shuttle 1 7639
Protoss_Robotics_Support_Bay 1 7438
Protoss_Reaver 2 9742
Protoss_Nexus 2 11538
11538
