Protoss_Gateway 4 9159
Protoss_Assimilator 3 3499
Protoss_Zealot 1 3718
Protoss_Cybernetics_Core 1 4677
Protoss_Nexus 2 7479
Protoss_Dragoon 12 10688
Protoss_Robotics_Facility 1 10274
10688
