Protoss_Gateway 2 8844
Protoss_Assimilator 1 3018
Protoss_Cybernetics_Core 1 3927
Protoss_Zealot 3 9676
Protoss_Dragoon 8 10688
Protoss_Nexus 1 7984
Protoss_Robotics_Facility 1 8196
Protoss_Shuttle 1 9291
Protoss_Robotics_Support_Bay 1 9220
Protoss_Reaver 1 10466
10688
