Protoss_Assimilator 3 9962
Protoss_Gateway 3 10876
Protoss_Cybernetics_Core 1 4618
Protoss_Dragoon 6 8876
Protoss_Nexus 1 8744
Protoss_Robotics_Facility 1 8761
Protoss_Citadel_of_Adun 1 9635
Protoss_Observatory 1 9559
Protoss_Stargate 1 10228
Protoss_Observer 1 10252
Protoss_Templar_Archives 1 10757
10876
