Protoss_Gateway 4 10053
Protoss_Assimilator 1 2855
Protoss_Cybernetics_Core 1 3827
Protoss_Dragoon 12 10093
Protoss_Nexus 1 9305
Protoss_Robotics_Facility 1 9547
Protoss_Observatory 1 10132
Protoss_Citadel_of_Adun 1 10872
10872
