Protoss_Gateway 2 10299
Protoss_Assimilator 1 2847
Protoss_Cybernetics_Core 1 3813
Protoss_Dragoon 5 7960
Protoss_Robotics_Facility 1 6759
Protoss_Shuttle 1 7743
Protoss_Robotics_Support_Bay 1 7560
Protoss_Reaver 1 8794
Protoss_Zealot 1 8692
Protoss_Nexus 2 11055
Protoss_Observatory 1 9025
Protoss_Observer 2 10310
11055
