Protoss_Gateway 2 6067
Protoss_Assimilator 1 3156
Protoss_Cybernetics_Core 1 4163
Protoss_Zealot 1 4074
Protoss_Dragoon 11 10690
Protoss_Nexus 1 8207
Protoss_Robotics_Facility 1 8857
Protoss_Shuttle 1 10625
Protoss_Robotics_Support_Bay 1 10279
10690
