Protoss_Nexus 1 4341
Protoss_Gateway 2 5047
Protoss_Assimilator 1 3856
Protoss_Cybernetics_Core 1 4809
Protoss_Zealot 1 5088
Protoss_Dragoon 10 10198
Protoss_Robotics_Facility 1 9121
Protoss_Observatory 1 10361
10361
