Protoss_Gateway 1 2778
Protoss_Assimilator 1 2785
Protoss_Cybernetics_Core 1 3767
Protoss_Zealot 2 7900
Protoss_Dragoon 6 10104
Protoss_Robotics_Facility 1 6459
Protoss_Shuttle 1 7461
Protoss_Robotics_Support_Bay 1 7329
Protoss_Reaver 1 8668
Protoss_Observatory 1 8877
Protoss_Nexus 1 10664
Protoss_Observer 1 10062
10664
