Protoss_Gateway 2 6104
Protoss_Assimilator 1 3045
Protoss_Cybernetics_Core 1 3919
Protoss_Dragoon 6 8373
Protoss_Citadel_of_Adun 1 7049
Protoss_Templar_Archives 1 8184
Protoss_Dark_Templar 2 9278
Protoss_Nexus 1 11095
Protoss_Robotics_Facility 1 11171
11171
