Protoss_Gateway 5 10851
Protoss_Assimilator 1 2898
Protoss_Cybernetics_Core 1 3935
Protoss_Dragoon 8 10138
Protoss_Robotics_Facility 1 5607
Protoss_Observatory 1 6210
Protoss_Nexus 2 10787
Protoss_Observer 2 7608
10851
