Protoss_Gateway 3 9321
Protoss_Assimilator 2 9196
Protoss_Cybernetics_Core 1 3900
Protoss_Dragoon 7 10322
Protoss_Nexus 1 7771
Protoss_Robotics_Facility 1 8156
Protoss_Citadel_of_Adun 1 8953
Protoss_Observatory 1 8711
Protoss_Observer 1 9530
Protoss_Templar_Archives 1 9949
Protoss_Stargate 1 10304
Protoss_Zealot 2 10158
10322
