Protoss_Gateway 2 7379
Protoss_Assimilator 2 10286
Protoss_Cybernetics_Core 1 3731
Protoss_Dragoon 9 10632
Protoss_Nexus 1 7451
Protoss_Robotics_Facility 1 7283
Protoss_Shuttle 1 8443
Protoss_Robotics_Support_Bay 1 8273
Protoss_Observatory 1 9228
Protoss_Reaver 1 10274
10632
