Protoss_Gateway 3 9120
Protoss_Assimilator 1 3033
Protoss_Cybernetics_Core 1 4234
Protoss_Dragoon 9 10334
Protoss_Robotics_Facility 1 5627
Protoss_Shuttle 1 6742
Protoss_Observatory 1 6418
Protoss_Observer 4 10510
10510
