Protoss_Gateway 2 10447
Protoss_Assimilator 1 2986
Protoss_Cybernetics_Core 1 3923
Protoss_Dragoon 5 10702
Protoss_Robotics_Facility 1 6381
Protoss_Shuttle 1 7593
Protoss_Robotics_Support_Bay 1 7288
Protoss_Reaver 1 8644
Protoss_Zealot 1 8880
Protoss_Nexus 1 10399
10702
