Protoss_Gateway 2 7345
Protoss_Assimilator 1 2866
Protoss_Cybernetics_Core 1 3707
Protoss_Dragoon 9 10644
Protoss_Robotics_Facility 1 6759
Protoss_Zealot 4 8606
Protoss_Shuttle 1 7789
Protoss_Observatory 1 7763
Protoss_Observer 1 9120
Protoss_Nexus 1 11383
11383
