Protoss_Assimilator 3 8580
Protoss_Gateway 3 10837
Protoss_Zealot 3 6192
Protoss_Nexus 1 6073
Protoss_Cybernetics_Core 1 6253
Protoss_Dragoon 9 10334
Protoss_Robotics_Facility 1 9452
Protoss_Shuttle 1 10461
Protoss_Robotics_Support_Bay 1 10227
10837
