Protoss_Gateway 2 9056
Protoss_Assimilator 1 3074
Protoss_Cybernetics_Core 1 4030
Protoss_Dragoon 6 10396
Protoss_Stargate 1 6544
Protoss_Fleet_Beacon 1 7691
Protoss_Carrier 1 10015
Protoss_Robotics_Facility 1 9841
Protoss_Nexus 1 11699
11699
