Protoss_Gateway 3 10584
Protoss_Assimilator 1 2924
Protoss_Cybernetics_Core 1 3883
Protoss_Zealot 3 9952
Protoss_Dragoon 8 10704
Protoss_Nexus 1 8027
Protoss_Robotics_Facility 1 7706
Protoss_Shuttle 1 8701
Protoss_Robotics_Support_Bay 1 8770
Protoss_Reaver 1 9966
Protoss_Observatory 1 9945
10704
