Protoss_Nexus 1 4789
Protoss_Gateway 3 9321
Protoss_Assimilator 1 4426
Protoss_Cybernetics_Core 1 5254
Protoss_Zealot 4 10166
Protoss_Dragoon 7 9362
Protoss_Robotics_Facility 1 8529
Protoss_Robotics_Support_Bay 1 9317
Protoss_Shuttle 1 10103
10166
