Protoss_Gateway 5 9386
Protoss_Assimilator 2 9768
Protoss_Cybernetics_Core 1 4019
Protoss_Dragoon 8 10422
Protoss_Robotics_Facility 1 6792
Protoss_Observatory 1 7381
Protoss_Nexus 1 8961
Protoss_Observer 5 10596
10596
