Protoss_Gateway 2 8209
Protoss_Assimilator 1 2892
Protoss_Cybernetics_Core 1 3793
Protoss_Zealot 3 9934
Protoss_Dragoon 10 10736
Protoss_Nexus 1 7967
Protoss_Robotics_Facility 1 8031
Protoss_Shuttle 1 9069
Protoss_Robotics_Support_Bay 1 9083
Protoss_Reaver 1 10434
Protoss_Observatory 1 9930
10736
