Protoss_Nexus 2 9758
Protoss_Gateway 4 9548
Protoss_Assimilator 2 9282
Protoss_Cybernetics_Core 1 5071
Protoss_Zealot 1 5238
Protoss_Dragoon 8 9636
Protoss_Robotics_Facility 1 8271
Protoss_Observatory 1 9008
Protoss_Observer 2 10408
10408
