Protoss_Gateway 4 9792
Protoss_Assimilator 1 2818
Protoss_Cybernetics_Core 1 3788
Protoss_Dragoon 8 10626
Protoss_Nexus 2 9787
Protoss_Robotics_Facility 1 8024
Protoss_Observatory 1 8718
Protoss_Observer 2 10426
10626
