Protoss_Gateway 3 10444
Protoss_Nexus 1 5192
Protoss_Assimilator 1 4128
Protoss_Cybernetics_Core 1 4824
Protoss_Zealot 1 5043
Protoss_Dragoon 10 10173
Protoss_Robotics_Facility 1 8559
Protoss_Robotics_Support_Bay 1 9211
Protoss_Shuttle 1 9922
Protoss_Reaver 1 10976
10976
