Protoss_Gateway 2 8803
Protoss_Assimilator 1 3130
Protoss_Cybernetics_Core 1 4028
Protoss_Zealot 1 3898
Protoss_Dragoon 6 10258
Protoss_Robotics_Facility 1 6921
Protoss_Observatory 1 7562
Protoss_Nexus 1 9197
Protoss_Observer 2 9188
Protoss_Shuttle 1 9717
Protoss_Robotics_Support_Bay 1 9916
10258
