Protoss_Gateway 4 10637
Protoss_Assimilator 2 9179
Protoss_Cybernetics_Core 1 3872
Protoss_Dragoon 9 9870
Protoss_Robotics_Facility 1 6758
Protoss_Nexus 1 8686
Protoss_Observatory 1 7408
Protoss_Observer 3 9504
Protoss_Citadel_of_Adun 1 9052
Protoss_Templar_Archives 1 10367
Protoss_Stargate 1 10621
10637
