Protoss_Gateway 2 6174
Protoss_Assimilator 1 3088
Protoss_Cybernetics_Core 1 4024
Protoss_Dragoon 7 10700
Protoss_Robotics_Facility 1 7156
Protoss_Zealot 4 8738
Protoss_Shuttle 1 8275
Protoss_Observatory 1 8151
Protoss_Observer 2 9744
Protoss_Nexus 2 11239
11239
