Protoss_Gateway 4 10687
Protoss_Assimilator 1 2940
Protoss_Zealot 5 10048
Protoss_Cybernetics_Core 1 3974
Protoss_Citadel_of_Adun 1 4965
Protoss_Dragoon 1 4920
Protoss_Templar_Archives 1 6070
Protoss_Dark_Templar 7 9238
Protoss_Nexus 1 9379
10687
