Protoss_Gateway 4 8945
Protoss_Nexus 1 4954
Protoss_Zealot 4 10462
Protoss_Assimilator 1 4134
Protoss_Cybernetics_Core 1 5193
Protoss_Dragoon 11 10278
Protoss_Robotics_Facility 1 8198
Protoss_Observatory 1 8792
Protoss_Observer 1 9508
10462
