Protoss_Gateway 3 8547
Protoss_Assimilator 1 2840
Protoss_Cybernetics_Core 1 3879
Protoss_Dragoon 6 8180
Protoss_Robotics_Facility 1 6469
Protoss_Observatory 1 7096
Protoss_Citadel_of_Adun 1 7689
Protoss_Observer 3 10130
Protoss_Zealot 8 10488
10488
