Protoss_Nexus 1 4419
Protoss_Gateway 4 9673
Protoss_Assimilator 2 8157
Protoss_Zealot 5 9928
Protoss_Cybernetics_Core 1 5203
Protoss_Dragoon 7 9326
Protoss_Robotics_Facility 1 7854
Protoss_Observatory 1 8575
Protoss_Observer 3 10456
10456
