Protoss_Gateway 2 8099
Protoss_Assimilator 1 3060
Protoss_Cybernetics_Core 1 3956
Protoss_Zealot 1 3836
Protoss_Dragoon 6 9020
Protoss_Nexus 1 7661
Protoss_Citadel_of_Adun 1 7759
Protoss_Robotics_Facility 1 8861
Protoss_Templar_Archives 1 8863
Protoss_Shuttle 1 9841
Protoss_Dark_Templar 2 9842
9842
