Protoss_Gateway 3 8422
Protoss_Assimilator 1 2839
Protoss_Cybernetics_Core 1 3824
Protoss_Zealot 1 3668
Protoss_Dragoon 11 10426
Protoss_Nexus 1 7737
Protoss_Robotics_Facility 1 7871
Protoss_Observatory 1 8740
Protoss_Observer 2 10232
10426
