Protoss_Gateway 2 4909
Protoss_Assimilator 1 2748
Protoss_Zealot 1 3426
Protoss_Cybernetics_Core 1 4546
Protoss_Dragoon 12 10322
Protoss_Nexus 1 9141
Protoss_Robotics_Facility 1 9589
Protoss_Observatory 1 10237
10322
