Protoss_Gateway 2 6510
Protoss_Assimilator 2 9819
Protoss_Zealot 3 4724
Protoss_Cybernetics_Core 1 4594
Protoss_Citadel_of_Adun 1 5807
Protoss_Dragoon 9 10514
Protoss_Nexus 1 9055
Protoss_Robotics_Facility 1 9179
Protoss_Observatory 1 9749
10514
