Protoss_Gateway 4 10089
Protoss_Assimilator 1 2830
Protoss_Cybernetics_Core 1 3759
Protoss_Dragoon 11 10080
Protoss_Nexus 1 7803
Protoss_Zealot 1 7834
Protoss_Robotics_Facility 1 9864
10089
