Protoss_Gateway 3 8207
Protoss_Assimilator 1 2840
Protoss_Cybernetics_Core 1 3914
Protoss_Robotics_Facility 1 5221
Protoss_Dragoon 9 9908
Protoss_Observatory 1 6077
Protoss_Observer 3 8850
Protoss_Nexus 1 8122
9908
