Protoss_Nexus 1 4326
Protoss_Gateway 4 8816
Protoss_Assimilator 2 7122
Protoss_Cybernetics_Core 1 4853
Protoss_Zealot 3 9844
Protoss_Dragoon 14 10656
Protoss_Robotics_Facility 1 8382
Protoss_Citadel_of_Adun 1 8962
Protoss_Observatory 1 8951
Protoss_Observer 2 10362
Protoss_Stargate 1 10207
Protoss_Templar_Archives 1 10159
10656
