Protoss_Assimilator 1 2976
Protoss_Gateway 2 10089
Protoss_Cybernetics_Core 1 4269
Protoss_Zealot 1 4100
Protoss_Dragoon 6 10656
Protoss_Nexus 2 8935
Protoss_Robotics_Facility 1 8987
Protoss_Observatory 1 10124
10656
