Protoss_Gateway 4 9837
Protoss_Assimilator 1 2952
Protoss_Cybernetics_Core 1 3859
Protoss_Dragoon 10 10024
Protoss_Robotics_Facility 1 6540
Protoss_Observatory 1 7079
Protoss_Observer 2 8362
Protoss_Nexus 1 9859
Protoss_Citadel_of_Adun 1 9773
Protoss_Shuttle 1 10521
10521
