Protoss_Gateway 3 10837
Protoss_Assimilator 2 10167
Protoss_Cybernetics_Core 1 3767
Protoss_Dragoon 7 10166
Protoss_Citadel_of_Adun 1 5813
Protoss_Templar_Archives 1 6839
Protoss_Dark_Templar 4 8590
Protoss_Nexus 1 9307
10837
