Protoss_Nexus 1 4313
Protoss_Gateway 4 10720
Protoss_Assimilator 2 7135
Protoss_Cybernetics_Core 1 4940
Protoss_Zealot 4 9874
Protoss_Dragoon 8 9240
Protoss_Robotics_Facility 1 7929
Protoss_Shuttle 1 8941
Protoss_Robotics_Support_Bay 1 8852
Protoss_Reaver 1 10056
Protoss_Observatory 1 10058
Protoss_Citadel_of_Adun 1 10806
10806
