Protoss_Nexus 1 4881
Protoss_Forge 1 4030
Protoss_Photon_Cannon 7 9896
Protoss_Gateway 3 9699
Protoss_Assimilator 2 7618
Protoss_Cybernetics_Core 1 7089
Protoss_Citadel_of_Adun 1 8302
Protoss_Templar_Archives 1 9291
Protoss_Dark_Templar 3 10532
10532
