Protoss_Gateway 6 10503
Protoss_Assimilator 1 2766
Protoss_Cybernetics_Core 1 3854
Protoss_Zealot 1 3724
Protoss_Dragoon 9 10686
Protoss_Nexus 1 8706
Protoss_Robotics_Facility 1 8696
Protoss_Observatory 1 9392
Protoss_Observer 1 10206
10686
