Protoss_Gateway 2 4690
Protoss_Assimilator 2 10080
Protoss_Cybernetics_Core 1 3805
Protoss_Dragoon 6 10166
Protoss_Citadel_of_Adun 1 5726
Protoss_Zealot 1 5664
Protoss_Robotics_Facility 1 7014
Protoss_Templar_Archives 1 6885
Protoss_Dark_Templar 3 10460
Protoss_Shuttle 1 8009
Protoss_Nexus 1 9207
Protoss_Stargate 1 8981
Protoss_Arbiter_Tribunal 1 10566
10566
