Protoss_Nexus 2 11547
Protoss_Gateway 4 9311
Protoss_Assimilator 2 6970
Protoss_Cybernetics_Core 1 5059
Protoss_Zealot 2 5192
Protoss_Dragoon 8 9444
Protoss_Robotics_Facility 2 9555
Protoss_Citadel_of_Adun 1 8958
Protoss_Observatory 1 10126
11547
