Protoss_Gateway 4 10134
Protoss_Assimilator 1 3037
Protoss_Cybernetics_Core 1 4085
Protoss_Dragoon 12 10747
Protoss_Robotics_Facility 1 6695
Protoss_Observatory 1 7266
Protoss_Observer 2 10523
Protoss_Citadel_of_Adun 1 10169
10747
