Protoss_Gateway 2 7428
Protoss_Assimilator 2 10066
Protoss_Zealot 2 4218
Protoss_Cybernetics_Core 1 4259
Protoss_Dragoon 11 10728
Protoss_Robotics_Facility 1 6847
Protoss_Nexus 1 8929
Protoss_Observatory 1 7961
Protoss_Observer 2 9602
Protoss_Citadel_of_Adun 1 9455
10728
