Protoss_Gateway 2 10795
Protoss_Assimilator 1 2860
Protoss_Cybernetics_Core 1 3877
Protoss_Zealot 3 9834
Protoss_Dragoon 6 8990
Protoss_Robotics_Facility 1 6609
Protoss_Observatory 1 7294
Protoss_Nexus 1 8927
Protoss_Observer 1 8088
Protoss_Shuttle 1 8989
Protoss_Robotics_Support_Bay 1 8977
Protoss_Reaver 1 10154
10795
