Protoss_Gateway 2 6619
Protoss_Assimilator 1 2792
Protoss_Cybernetics_Core 1 3665
Protoss_Dragoon 8 10168
Protoss_Robotics_Facility 1 6299
Protoss_Observatory 1 6956
Protoss_Observer 2 10472
Protoss_Nexus 2 11791
Protoss_Zealot 4 9252
Protoss_Shuttle 1 9319
11791
