Protoss_Gateway 2 10734
Protoss_Assimilator 2 10453
Protoss_Cybernetics_Core 1 3753
Protoss_Dragoon 7 10530
Protoss_Robotics_Facility 1 6411
Protoss_Observatory 1 6953
Protoss_Nexus 1 8675
Protoss_Observer 2 10444
Protoss_Zealot 1 7722
Protoss_Shuttle 1 8561
Protoss_Robotics_Support_Bay 1 8694
Protoss_Reaver 1 9840
10734
