Protoss_Nexus 2 11491
Protoss_Gateway 2 6446
Protoss_Assimilator 2 7008
Protoss_Cybernetics_Core 1 4656
Protoss_Zealot 1 4468
Protoss_Dragoon 10 9966
Protoss_Robotics_Facility 1 8133
Protoss_Citadel_of_Adun 1 8722
Protoss_Observatory 1 8759
Protoss_Observer 2 10052
Protoss_Stargate 1 10034
Protoss_Templar_Archives 1 9947
11491
