Protoss_Assimilator 1 2341
Protoss_Gateway 2 7814
Protoss_Cybernetics_Core 1 4081
Protoss_Dragoon 7 10572
Protoss_Citadel_of_Adun 1 6027
Protoss_Robotics_Facility 1 7049
Protoss_Templar_Archives 1 7379
Protoss_Shuttle 1 8051
Protoss_Dark_Templar 4 10678
Protoss_Nexus 1 10405
Protoss_Observatory 1 9261
Protoss_Observer 1 10570
10678
