Protoss_Gateway 3 9224
Protoss_Assimilator 1 2976
Protoss_Cybernetics_Core 1 3831
Protoss_Dragoon 10 10484
Protoss_Robotics_Facility 1 6590
Protoss_Observatory 1 7158
Protoss_Nexus 1 8876
Protoss_Observer 3 9064
10484
