Protoss_Nexus 1 4385
Protoss_Gateway 4 8009
Protoss_Assimilator 1 3882
Protoss_Cybernetics_Core 1 4915
Protoss_Zealot 1 5272
Protoss_Dragoon 16 10380
Protoss_Robotics_Facility 1 10079
10380
