Protoss_Gateway 2 8467
Protoss_Assimilator 2 9610
Protoss_Cybernetics_Core 1 3789
Protoss_Zealot 2 9630
Protoss_Dragoon 6 8792
Protoss_Nexus 1 7980
Protoss_Robotics_Facility 1 8173
Protoss_Shuttle 1 9279
Protoss_Robotics_Support_Bay 1 9115
Protoss_Reaver 1 10330
Protoss_Observatory 1 10256
10330
