Protoss_Nexus 2 11281
Protoss_Gateway 2 5143
Protoss_Assimilator 2 7678
Protoss_Cybernetics_Core 1 4982
Protoss_Zealot 3 10432
Protoss_Dragoon 8 9216
Protoss_Robotics_Facility 1 7889
Protoss_Shuttle 1 8873
Protoss_Robotics_Support_Bay 2 8825
Protoss_Reaver 1 9962
Protoss_Observatory 1 9446
Protoss_Observer 1 10566
11281
