Protoss_Gateway 4 9954
Protoss_Assimilator 1 2814
Protoss_Zealot 1 3456
Protoss_Cybernetics_Core 1 4319
Protoss_Dragoon 11 10578
Protoss_Robotics_Facility 1 6289
Protoss_Nexus 1 8195
Protoss_Observatory 1 7245
Protoss_Observer 3 9378
10578
