Protoss_Gateway 3 10143
Protoss_Assimilator 1 2872
Protoss_Zealot 2 4488
Protoss_Cybernetics_Core 1 4291
Protoss_Dragoon 11 10544
Protoss_Robotics_Facility 1 6824
Protoss_Observatory 1 7361
Protoss_Observer 2 9240
Protoss_Nexus 1 10351
10544
