Protoss_Gateway 4 10250
Protoss_Assimilator 1 2767
Protoss_Cybernetics_Core 1 3802
Protoss_Dragoon 4 7752
Protoss_Nexus 1 7425
Protoss_Robotics_Facility 1 7299
Protoss_Shuttle 1 8435
Protoss_Robotics_Support_Bay 1 8273
Protoss_Zealot 2 8772
Protoss_Reaver 1 9486
Protoss_Observatory 1 9257
Protoss_Citadel_of_Adun 1 9901
Protoss_Observer 1 10090
Protoss_Templar_Archives 1 10885
10885
