Protoss_Gateway 3 8961
Protoss_Assimilator 1 2943
Protoss_Cybernetics_Core 1 3762
Protoss_Dragoon 10 10528
Protoss_Nexus 1 7435
Protoss_Robotics_Facility 1 7455
Protoss_Observatory 1 8273
Protoss_Observer 2 9556
Protoss_Citadel_of_Adun 1 10045
10528
