Protoss_Gateway 2 9823
Protoss_Assimilator 1 2876
Protoss_Cybernetics_Core 1 3729
Protoss_Zealot 1 3664
Protoss_Dragoon 8 10652
Protoss_Robotics_Facility 1 6667
Protoss_Shuttle 1 7651
Protoss_Robotics_Support_Bay 1 7254
Protoss_Reaver 2 10668
Protoss_Nexus 1 9977
Protoss_Observatory 1 8669
Protoss_Observer 2 10122
10668
