Protoss_Gateway 2 5457
Protoss_Assimilator 1 2925
Protoss_Cybernetics_Core 1 3776
Protoss_Zealot 3 9656
Protoss_Dragoon 8 10708
Protoss_Nexus 1 7822
Protoss_Robotics_Facility 1 7651
Protoss_Shuttle 1 8817
Protoss_Robotics_Support_Bay 1 8946
Protoss_Reaver 1 10072
Protoss_Observatory 1 9672
10708
