Protoss_Gateway 3 5728
Protoss_Assimilator 2 4271
Protoss_Zealot 2 5494
Protoss_Cybernetics_Core 1 5547
Protoss_Dragoon 6 8718
Protoss_Nexus 2 11321
Protoss_Robotics_Facility 1 8751
Protoss_Shuttle 1 9821
Protoss_Robotics_Support_Bay 1 9804
Protoss_Observatory 1 10271
Protoss_Reaver 1 10938
11321
