Protoss_Gateway 2 10456
Protoss_Assimilator 1 3140
Protoss_Cybernetics_Core 1 4054
Protoss_Dragoon 5 10078
Protoss_Stargate 1 7111
Protoss_Scout 1 8405
Protoss_Fleet_Beacon 1 8639
Protoss_Carrier 1 11006
Protoss_Shield_Battery 1 10338
11006
