Protoss_Gateway 2 9760
Protoss_Assimilator 1 2973
Protoss_Zealot 3 4876
Protoss_Cybernetics_Core 1 4709
Protoss_Dragoon 7 10722
Protoss_Robotics_Facility 1 7938
Protoss_Nexus 1 9227
Protoss_Observatory 1 8565
Protoss_Observer 1 9268
10722
