Protoss_Gateway 2 7353
Protoss_Assimilator 1 3131
Protoss_Cybernetics_Core 1 4158
Protoss_Dragoon 8 10153
Protoss_Robotics_Facility 2 10876
Protoss_Citadel_of_Adun 1 7234
Protoss_Templar_Archives 1 8262
Protoss_Dark_Templar 2 9158
10876
