Protoss_Nexus 2 11527
Protoss_Gateway 2 5491
Protoss_Assimilator 2 7594
Protoss_Cybernetics_Core 1 5126
Protoss_Dragoon 11 10176
Protoss_Robotics_Facility 1 8013
Protoss_Shuttle 1 9005
Protoss_Observatory 1 8683
Protoss_Robotics_Support_Bay 1 9427
Protoss_Observer 2 10490
Protoss_Reaver 1 10970
11527
