Protoss_Gateway 3 8595
Protoss_Assimilator 1 2752
Protoss_Cybernetics_Core 1 3788
Protoss_Dragoon 8 9604
Protoss_Robotics_Facility 1 6790
Protoss_Nexus 2 11415
Protoss_Observatory 1 7398
Protoss_Observer 4 10130
11415
