Protoss_Gateway 2 5802
Protoss_Assimilator 2 9624
Protoss_Cybernetics_Core 1 4021
Protoss_Zealot 1 4036
Protoss_Dragoon 10 10292
Protoss_Nexus 1 9090
Protoss_Citadel_of_Adun 1 9180
Protoss_Templar_Archives 1 10625
Protoss_Robotics_Facility 1 11143
11143
