Protoss_Nexus 2 11006
Protoss_Gateway 2 5123
Protoss_Assimilator 1 3874
Protoss_Cybernetics_Core 1 4857
Protoss_Zealot 2 5170
Protoss_Dragoon 7 9450
Protoss_Robotics_Facility 1 9432
Protoss_Observatory 1 10055
11006
