Protoss_Gateway 3 9237
Protoss_Zealot 2 4922
Protoss_Nexus 1 5391
Protoss_Assimilator 2 7636
Protoss_Cybernetics_Core 1 5027
Protoss_Dragoon 11 10454
Protoss_Robotics_Facility 1 7729
Protoss_Observatory 1 8297
Protoss_Observer 3 10208
Protoss_Citadel_of_Adun 1 10107
10454
