Protoss_Nexus 1 4341
Protoss_Gateway 2 5119
Protoss_Assimilator 2 8807
Protoss_Cybernetics_Core 1 4975
Protoss_Zealot 1 5048
Protoss_Dragoon 12 10524
Protoss_Robotics_Facility 1 9017
Protoss_Shuttle 1 10059
Protoss_Robotics_Support_Bay 1 9761
10524
