Protoss_Nexus 1 4341
Protoss_Gateway 4 10005
Protoss_Assimilator 2 7684
Protoss_Cybernetics_Core 1 4913
Protoss_Zealot 1 5022
Protoss_Dragoon 6 7848
Protoss_Citadel_of_Adun 1 7485
Protoss_Robotics_Facility 1 8915
Protoss_Templar_Archives 1 9197
Protoss_Shuttle 1 9975
Protoss_Dark_Templar 2 10040
Protoss_Stargate 1 10380
Protoss_Observatory 1 9839
10380
