Protoss_Gateway 2 5553
Protoss_Assimilator 1 2937
Protoss_Cybernetics_Core 1 3819
Protoss_Zealot 1 3740
Protoss_Dragoon 10 10048
Protoss_Nexus 1 9045
Protoss_Robotics_Facility 1 8969
Protoss_Observatory 1 9578
Protoss_Observer 1 10416
10416
