Protoss_Gateway 2 7683
Protoss_Assimilator 1 3028
Protoss_Cybernetics_Core 1 3918
Protoss_Dragoon 9 10338
Protoss_Robotics_Facility 1 7292
Protoss_Observatory 1 7851
Protoss_Observer 2 9740
Protoss_Shuttle 1 9447
Protoss_Zealot 2 9434
Protoss_Nexus 1 11550
11550
