Protoss_Gateway 3 8671
Protoss_Assimilator 2 10586
Protoss_Zealot 1 3392
Protoss_Cybernetics_Core 1 3951
Protoss_Dragoon 12 10622
Protoss_Nexus 1 8373
Protoss_Robotics_Facility 1 8163
Protoss_Observatory 1 8892
Protoss_Observer 2 10180
10622
