Protoss_Gateway 2 8414
Protoss_Assimilator 1 3040
Protoss_Cybernetics_Core 2 9978
Protoss_Zealot 3 10006
Protoss_Robotics_Facility 1 5527
Protoss_Dragoon 2 6490
Protoss_Shuttle 1 6513
Protoss_Robotics_Support_Bay 1 6419
Protoss_Reaver 2 8878
10006
