Protoss_Gateway 4 10781
Protoss_Assimilator 1 2758
Protoss_Cybernetics_Core 1 3673
Protoss_Dragoon 12 10138
Protoss_Nexus 2 10928
Protoss_Robotics_Facility 1 7965
Protoss_Observatory 1 8635
Protoss_Observer 3 10516
10928
