Protoss_Gateway 2 7877
Protoss_Assimilator 1 3086
Protoss_Cybernetics_Core 1 4104
Protoss_Dragoon 7 8833
Protoss_Robotics_Facility 1 7201
Protoss_Observatory 1 7772
Protoss_Observer 1 8508
Protoss_Citadel_of_Adun 1 8927
Protoss_Shuttle 1 9507
Protoss_Zealot 4 10065
10065
