Protoss_Gateway 3 9797
Protoss_Assimilator 1 3070
Protoss_Cybernetics_Core 1 3949
Protoss_Dragoon 12 10264
Protoss_Robotics_Facility 1 7812
Protoss_Observatory 1 8436
Protoss_Observer 1 9173
10264
