Protoss_Gateway 4 10861
Protoss_Assimilator 1 2795
Protoss_Cybernetics_Core 1 3755
Protoss_Robotics_Facility 1 5187
Protoss_Dragoon 9 9285
Protoss_Shuttle 1 6227
Protoss_Observatory 1 6103
Protoss_Observer 3 9728
Protoss_Nexus 1 10780
10861
