Protoss_Gateway 3 9674
Protoss_Assimilator 1 3029
Protoss_Cybernetics_Core 1 3814
Protoss_Zealot 1 3868
Protoss_Dragoon 9 10723
Protoss_Robotics_Facility 1 7795
Protoss_Nexus 1 9600
Protoss_Observatory 1 8451
Protoss_Observer 3 10417
10723
