Protoss_Gateway 2 8953
Protoss_Assimilator 1 3091
Protoss_Cybernetics_Core 1 4147
Protoss_Robotics_Facility 1 5698
Protoss_Zealot 3 9927
Protoss_Dragoon 5 9798
Protoss_Shuttle 1 6692
Protoss_Observatory 1 6400
Protoss_Robotics_Support_Bay 1 6829
Protoss_Observer 1 7295
Protoss_Reaver 1 8345
9927
