Protoss_Gateway 2 6913
Protoss_Assimilator 1 3075
Protoss_Cybernetics_Core 1 4104
Protoss_Robotics_Facility 1 5629
Protoss_Dragoon 9 10088
Protoss_Observatory 1 6258
Protoss_Observer 5 10503
Protoss_Shuttle 1 9181
10503
