Protoss_Gateway 3 9979
Protoss_Assimilator 1 3075
Protoss_Cybernetics_Core 1 3924
Protoss_Dragoon 7 10225
Protoss_Robotics_Facility 1 7246
Protoss_Shuttle 1 8547
Protoss_Nexus 1 9779
Protoss_Observatory 1 8742
Protoss_Observer 1 9698
10225
