Protoss_Gateway 2 7704
Protoss_Assimilator 1 3065
Protoss_Cybernetics_Core 1 3959
Protoss_Dragoon 11 10615
Protoss_Robotics_Facility 1 6747
Protoss_Observatory 1 7465
Protoss_Observer 1 8168
Protoss_Nexus 1 10365
10615
