Protoss_Gateway 2 9053
Protoss_Assimilator 1 3000
Protoss_Cybernetics_Core 1 3854
Protoss_Dragoon 5 10033
Protoss_Robotics_Facility 1 5736
Protoss_Shuttle 1 6727
Protoss_Robotics_Support_Bay 1 6507
Protoss_Zealot 2 7593
Protoss_Reaver 1 7804
Protoss_Observatory 1 7575
Protoss_Observer 1 8501
Protoss_Nexus 1 11573
11573
