Protoss_Gateway 3 8054
Protoss_Assimilator 1 2905
Protoss_Cybernetics_Core 1 3875
Protoss_Robotics_Facility 1 5287
Protoss_Dragoon 10 10678
Protoss_Shuttle 1 6277
Protoss_Observatory 1 6164
Protoss_Observer 1 6913
10678
