Protoss_Gateway 2 6861
Protoss_Assimilator 1 3057
Protoss_Cybernetics_Core 1 4054
Protoss_Dragoon 8 8668
Protoss_Robotics_Facility 1 9127
Protoss_Nexus 1 10430
Protoss_Shuttle 1 10192
10430
