Protoss_Gateway 2 9834
Protoss_Assimilator 2 3573
Protoss_Cybernetics_Core 1 4399
Protoss_Dragoon 2 6000
Protoss_Robotics_Facility 1 6937
Protoss_Forge 1 6655
Protoss_Photon_Cannon 1 7617
Protoss_Shuttle 1 7932
Protoss_Zealot 2 8643
Protoss_Robotics_Support_Bay 1 7933
Protoss_Reaver 1 9071
Protoss_Citadel_of_Adun 1 9427
9834
