Protoss_Gateway 3 9687
Protoss_Assimilator 1 3126
Protoss_Cybernetics_Core 1 4014
Protoss_Dragoon 7 9235
Protoss_Robotics_Facility 1 5912
Protoss_Observatory 1 6461
Protoss_Observer 2 9098
Protoss_Shuttle 1 8602
Protoss_Citadel_of_Adun 1 9723
Protoss_Zealot 2 9837
Protoss_Templar_Archives 1 10774
10774
