Protoss_Gateway 3 10287
Protoss_Assimilator 1 2961
Protoss_Cybernetics_Core 1 3829
Protoss_Dragoon 9 8555
Protoss_Citadel_of_Adun 1 7741
Protoss_Templar_Archives 1 8749
Protoss_Dark_Templar 2 9598
Protoss_Nexus 1 10771
Protoss_Zealot 2 10408
10771
