Protoss_Gateway 3 8621
Protoss_Assimilator 1 2875
Protoss_Cybernetics_Core 1 4011
Protoss_Dragoon 12 10669
Protoss_Robotics_Facility 1 6122
Protoss_Shuttle 1 7112
Protoss_Observatory 1 6721
Protoss_Observer 1 7715
Protoss_Shield_Battery 1 9122
Protoss_Citadel_of_Adun 1 10225
10669
