Protoss_Gateway 2 4409
Protoss_Assimilator 1 2820
Protoss_Cybernetics_Core 1 3900
Protoss_Dragoon 7 9370
Protoss_Robotics_Facility 1 7497
Protoss_Zealot 4 8618
Protoss_Observatory 1 8061
Protoss_Shuttle 1 8522
Protoss_Observer 1 9125
9370
