Protoss_Gateway 4 10462
Protoss_Assimilator 1 2811
Protoss_Cybernetics_Core 1 3749
Protoss_Dragoon 6 10108
Protoss_Robotics_Facility 1 6992
Protoss_Observatory 1 7804
Protoss_Nexus 2 9895
Protoss_Citadel_of_Adun 1 8654
Protoss_Observer 2 9978
Protoss_Templar_Archives 1 9858
10462
