Protoss_Gateway 3 8738
Protoss_Assimilator 1 2915
Protoss_Cybernetics_Core 1 3970
Protoss_Dragoon 13 10555
Protoss_Robotics_Facility 1 6462
Protoss_Shuttle 1 7452
Protoss_Observatory 1 7073
Protoss_Observer 2 10108
Protoss_Shield_Battery 1 8626
10555
