Protoss_Gateway 3 8934
Protoss_Assimilator 1 2884
Protoss_Cybernetics_Core 1 3834
Protoss_Robotics_Facility 1 5297
Protoss_Dragoon 9 10453
Protoss_Observatory 1 5861
Protoss_Shuttle 1 6477
Protoss_Observer 3 8868
10453
