Protoss_Gateway 1 2939
Protoss_Assimilator 1 3234
Protoss_Cybernetics_Core 1 4234
Protoss_Dragoon 3 6808
Protoss_Robotics_Facility 1 6072
Protoss_Shuttle 1 7452
Protoss_Robotics_Support_Bay 1 7189
Protoss_Zealot 2 8560
Protoss_Reaver 2 9626
Protoss_Observatory 1 9112
Protoss_Observer 1 10230
10230
