Protoss_Gateway 2 6219
Protoss_Assimilator 1 2995
Protoss_Cybernetics_Core 1 4144
Protoss_Dragoon 9 9139
Protoss_Robotics_Facility 1 9544
Protoss_Nexus 1 10716
Protoss_Zealot 2 9888
Protoss_Observatory 1 10101
Protoss_Shuttle 1 10692
10716
