Protoss_Gateway 2 6164
Protoss_Assimilator 2 3445
Protoss_Cybernetics_Core 1 4349
Protoss_Zealot 2 10138
Protoss_Dragoon 5 10258
Protoss_Nexus 1 9655
Protoss_Robotics_Facility 1 10492
10492
