Protoss_Gateway 2 6542
Protoss_Assimilator 1 3043
Protoss_Cybernetics_Core 1 4099
Protoss_Zealot 1 3998
Protoss_Dragoon 5 9243
Protoss_Robotics_Facility 1 5752
Protoss_Robotics_Support_Bay 1 6861
Protoss_Reaver 1 8076
Protoss_Nexus 2 11221
Protoss_Observatory 1 8389
Protoss_Observer 1 10393
11221
