Protoss_Gateway 2 6894
Protoss_Assimilator 1 2942
Protoss_Cybernetics_Core 1 3904
Protoss_Dragoon 7 8644
Protoss_Robotics_Facility 1 5973
Protoss_Observatory 1 6529
Protoss_Observer 2 7838
Protoss_Nexus 2 11161
Protoss_Citadel_of_Adun 1 10609
11161
