Protoss_Gateway 3 7144
Protoss_Assimilator 1 3114
Protoss_Cybernetics_Core 1 4006
Protoss_Dragoon 8 9252
Protoss_Robotics_Facility 1 5839
Protoss_Observatory 1 6531
Protoss_Observer 2 8542
Protoss_Nexus 2 11379
11379
