Protoss_Gateway 2 9289
Protoss_Assimilator 1 3119
Protoss_Cybernetics_Core 1 3949
Protoss_Dragoon 8 10583
Protoss_Robotics_Facility 1 5467
Protoss_Zealot 2 6552
Protoss_Shuttle 1 6517
Protoss_Nexus 1 9477
Protoss_Observatory 1 8214
Protoss_Citadel_of_Adun 1 9180
Protoss_Observer 1 9043
Protoss_Templar_Archives 1 10491
10583
