Protoss_Gateway 3 10646
Protoss_Assimilator 1 3172
Protoss_Cybernetics_Core 1 4204
Protoss_Dragoon 9 10175
Protoss_Robotics_Facility 1 6717
Protoss_Observatory 1 7316
Protoss_Observer 2 8718
Protoss_Nexus 1 10100
10646
