Protoss_Gateway 3 10319
Protoss_Assimilator 1 3170
Protoss_Cybernetics_Core 1 4197
Protoss_Dragoon 10 10332
Protoss_Robotics_Facility 1 6587
Protoss_Observatory 1 7146
Protoss_Observer 2 9183
Protoss_Shuttle 1 10467
10467
