Protoss_Gateway 2 7617
Protoss_Assimilator 1 3075
Protoss_Cybernetics_Core 1 3944
Protoss_Dragoon 6 10068
Protoss_Stargate 1 7001
Protoss_Fleet_Beacon 1 8124
Protoss_Carrier 1 10431
Protoss_Robotics_Facility 1 10163
10431
