Protoss_Gateway 2 6787
Protoss_Assimilator 1 3149
Protoss_Cybernetics_Core 1 4166
Protoss_Dragoon 9 9513
Protoss_Robotics_Facility 1 6737
Protoss_Observatory 1 7403
Protoss_Observer 2 9032
Protoss_Shuttle 1 9699
Protoss_Nexus 1 11115
11115
