Protoss_Gateway 3 10875
Protoss_Assimilator 1 3075
Protoss_Cybernetics_Core 1 3935
Protoss_Zealot 3 10148
Protoss_Dragoon 6 8333
Protoss_Robotics_Facility 1 6968
Protoss_Observatory 1 7591
Protoss_Observer 2 8890
Protoss_Nexus 1 10728
Protoss_Shuttle 1 10232
10875
