Protoss_Gateway 2 7264
Protoss_Assimilator 1 2885
Protoss_Cybernetics_Core 1 3930
Protoss_Dragoon 10 10228
Protoss_Robotics_Facility 1 6708
Protoss_Observatory 1 7345
Protoss_Observer 2 8640
10228
