Protoss_Gateway 2 6911
Protoss_Assimilator 1 3080
Protoss_Cybernetics_Core 1 4160
Protoss_Dragoon 11 10738
Protoss_Robotics_Facility 1 7442
Protoss_Observatory 1 8256
Protoss_Observer 2 9655
Protoss_Nexus 1 10451
10738
