Protoss_Gateway 1 2898
Protoss_Assimilator 1 3067
Protoss_Cybernetics_Core 1 4034
Protoss_Dragoon 7 10308
Protoss_Robotics_Facility 1 5847
Protoss_Zealot 1 5623
Protoss_Observatory 1 6421
Protoss_Observer 2 8654
Protoss_Shuttle 2 10457
Protoss_Nexus 1 10930
10930
