Protoss_Gateway 1 3042
Protoss_Assimilator 1 3102
Protoss_Cybernetics_Core 1 4044
Protoss_Dragoon 2 7627
Protoss_Robotics_Facility 1 5923
Protoss_Zealot 2 6875
Protoss_Robotics_Support_Bay 1 6552
Protoss_Shuttle 1 7007
Protoss_Reaver 1 8131
8131
