Protoss_Gateway 2 10869
Protoss_Assimilator 1 3197
Protoss_Cybernetics_Core 1 4104
Protoss_Dragoon 4 10428
Protoss_Robotics_Facility 1 5936
Protoss_Shuttle 1 6932
Protoss_Robotics_Support_Bay 1 6706
Protoss_Reaver 2 9101
Protoss_Observatory 1 8851
Protoss_Nexus 1 10735
Protoss_Observer 1 9705
10869
