Protoss_Gateway 2 8586
Protoss_Assimilator 1 3314
Protoss_Zealot 5 9528
Protoss_Cybernetics_Core 1 4844
Protoss_Dragoon 3 10363
Protoss_Robotics_Facility 1 6562
Protoss_Shuttle 1 7567
Protoss_Robotics_Support_Bay 1 7360
Protoss_Reaver 2 9670
10363
