Protoss_Gateway 3 8547
Protoss_Assimilator 1 3015
Protoss_Cybernetics_Core 1 3938
Protoss_Dragoon 9 9963
Protoss_Nexus 2 10643
Protoss_Robotics_Facility 1 10687
Protoss_Citadel_of_Adun 1 10619
10687
