Protoss_Gateway 2 6802
Protoss_Assimilator 1 3031
Protoss_Cybernetics_Core 1 3864
Protoss_Robotics_Facility 1 5412
Protoss_Dragoon 10 10648
Protoss_Observatory 1 6151
Protoss_Observer 4 10068
Protoss_Nexus 2 11176
11176
