Protoss_Gateway 1 2814
Protoss_Assimilator 1 2905
Protoss_Cybernetics_Core 1 3828
Protoss_Zealot 1 4123
Protoss_Dragoon 6 8773
Protoss_Robotics_Facility 1 7787
Protoss_Citadel_of_Adun 1 7987
Protoss_Shuttle 1 8882
Protoss_Templar_Archives 1 9162
Protoss_Dark_Templar 1 10003
Protoss_Robotics_Support_Bay 1 10315
10315
