Protoss_Gateway 2 7362
Protoss_Assimilator 1 2952
Protoss_Cybernetics_Core 1 3989
Protoss_Dragoon 7 9037
Protoss_Robotics_Facility 1 6106
Protoss_Observatory 1 6766
Protoss_Observer 2 8298
Protoss_Nexus 1 10515
Protoss_Citadel_of_Adun 1 10007
Protoss_Zealot 2 9973
10515
