Protoss_Gateway 2 6726
Protoss_Assimilator 1 3008
Protoss_Cybernetics_Core 1 3863
Protoss_Robotics_Facility 1 5312
Protoss_Dragoon 11 10217
Protoss_Observatory 1 5911
Protoss_Observer 3 9893
Protoss_Nexus 1 10781
10781
