Protoss_Gateway 2 9990
Protoss_Assimilator 1 3060
Protoss_Cybernetics_Core 1 3973
Protoss_Robotics_Facility 1 5462
Protoss_Dragoon 5 9764
Protoss_Shuttle 1 6457
Protoss_Robotics_Support_Bay 1 6301
Protoss_Reaver 2 10731
Protoss_Zealot 1 7313
Protoss_Observatory 1 8186
Protoss_Observer 1 9563
10731
