Protoss_Gateway 2 7209
Protoss_Assimilator 1 3027
Protoss_Cybernetics_Core 1 4003
Protoss_Dragoon 11 10350
Protoss_Robotics_Facility 1 5694
Protoss_Observatory 1 6333
Protoss_Observer 2 7878
Protoss_Nexus 1 11174
11174
