Protoss_Gateway 2 5654
Protoss_Assimilator 1 3311
Protoss_Cybernetics_Core 1 4154
Protoss_Zealot 1 4028
Protoss_Dragoon 5 9938
Protoss_Citadel_of_Adun 1 5391
Protoss_Templar_Archives 1 6579
Protoss_Dark_Templar 4 8590
Protoss_Robotics_Facility 1 9802
9938
