Protoss_Gateway 3 8308
Protoss_Assimilator 1 3024
Protoss_Cybernetics_Core 1 3849
Protoss_Robotics_Facility 1 5368
Protoss_Dragoon 8 10498
Protoss_Shuttle 1 6357
Protoss_Observatory 1 6036
Protoss_Observer 6 10594
Protoss_Nexus 1 11394
11394
