Protoss_Gateway 2 9187
Protoss_Assimilator 1 3043
Protoss_Cybernetics_Core 1 3967
Protoss_Dragoon 3 8543
Protoss_Stargate 2 6437
Protoss_Scout 2 7865
Protoss_Zealot 1 7743
Protoss_Shield_Battery 1 8258
9187
