Protoss_Gateway 3 7109
Protoss_Assimilator 1 3004
Protoss_Cybernetics_Core 1 4039
Protoss_Robotics_Facility 1 5417
Protoss_Dragoon 6 8700
Protoss_Observatory 1 6026
Protoss_Observer 4 10013
Protoss_Nexus 2 11505
11505
