Protoss_Gateway 2 7114
Protoss_Assimilator 1 2939
Protoss_Cybernetics_Core 1 4064
Protoss_Dragoon 6 10003
Protoss_Robotics_Facility 1 5792
Protoss_Robotics_Support_Bay 1 6436
Protoss_Shuttle 1 7527
Protoss_Reaver 1 8578
Protoss_Nexus 1 10325
Protoss_Observatory 1 9676
10325
