Protoss_Gateway 4 10757
Protoss_Assimilator 1 3165
Protoss_Cybernetics_Core 1 4079
Protoss_Dragoon 6 9483
Protoss_Robotics_Facility 1 7037
Protoss_Citadel_of_Adun 1 8121
Protoss_Observatory 1 7696
Protoss_Observer 1 8443
Protoss_Nexus 1 10256
Protoss_Templar_Archives 1 9600
Protoss_Shuttle 1 10452
10757
