Protoss_Gateway 2 8422
Protoss_Assimilator 1 2928
Protoss_Cybernetics_Core 1 3860
Protoss_Dragoon 7 9278
Protoss_Robotics_Facility 1 6280
Protoss_Observatory 1 6831
Protoss_Observer 3 10073
Protoss_Nexus 2 11262
Protoss_Citadel_of_Adun 1 9857
Protoss_Zealot 2 10433
11262
