Protoss_Gateway 2 6679
Protoss_Assimilator 1 2875
Protoss_Cybernetics_Core 1 3962
Protoss_Dragoon 10 10588
Protoss_Robotics_Facility 1 5962
Protoss_Observatory 1 6774
Protoss_Observer 4 10093
Protoss_Nexus 2 11203
11203
