Protoss_Gateway 2 9344
Protoss_Assimilator 1 2973
Protoss_Cybernetics_Core 1 4034
Protoss_Zealot 3 10368
Protoss_Dragoon 7 9717
Protoss_Robotics_Facility 1 7187
Protoss_Shuttle 2 10511
Protoss_Robotics_Support_Bay 1 8153
Protoss_Reaver 1 9608
Protoss_Citadel_of_Adun 1 10029
10511
