Protoss_Gateway 3 8682
Protoss_Assimilator 1 3112
Protoss_Cybernetics_Core 1 4172
Protoss_Zealot 4 10518
Protoss_Dragoon 8 9698
Protoss_Nexus 1 8490
Protoss_Robotics_Facility 1 9023
Protoss_Observatory 1 9956
Protoss_Shuttle 1 10442
10518
