Protoss_Gateway 2 8513
Protoss_Assimilator 1 2940
Protoss_Cybernetics_Core 1 3945
Protoss_Robotics_Facility 1 5413
Protoss_Dragoon 3 7208
Protoss_Observatory 1 6059
Protoss_Shuttle 1 6722
Protoss_Observer 3 8529
Protoss_Zealot 4 9873
Protoss_Robotics_Support_Bay 1 8602
Protoss_Nexus 1 10555
Protoss_Reaver 1 10291
10555
