Protoss_Gateway 2 6704
Protoss_Assimilator 1 2832
Protoss_Cybernetics_Core 1 3899
Protoss_Dragoon 7 10324
Protoss_Robotics_Facility 1 5818
Protoss_Observatory 1 6371
Protoss_Observer 3 9858
Protoss_Nexus 1 9909
Protoss_Shuttle 1 10759
10759
