Protoss_Gateway 3 10379
Protoss_Assimilator 1 3040
Protoss_Cybernetics_Core 1 4151
Protoss_Dragoon 8 9983
Protoss_Robotics_Facility 1 7209
Protoss_Observatory 1 8495
Protoss_Nexus 1 10421
Protoss_Observer 1 9308
Protoss_Shuttle 1 10209
10421
