Protoss_Gateway 3 6679
Protoss_Assimilator 1 3132
Protoss_Zealot 7 10498
Protoss_Cybernetics_Core 1 4781
Protoss_Dragoon 7 8519
Protoss_Citadel_of_Adun 1 8876
Protoss_Templar_Archives 1 10028
Protoss_Robotics_Facility 1 10757
10757
