Protoss_Gateway 1 2810
Protoss_Assimilator 1 2902
Protoss_Cybernetics_Core 1 3846
Protoss_Robotics_Facility 1 5263
Protoss_Dragoon 4 9816
Protoss_Zealot 2 6404
Protoss_Shuttle 1 6385
Protoss_Robotics_Support_Bay 1 6409
Protoss_Reaver 3 9650
9816
