Protoss_Gateway 3 9999
Protoss_Nexus 1 5356
Protoss_Zealot 2 5268
Protoss_Assimilator 1 4875
Protoss_Cybernetics_Core 1 6101
Protoss_Dragoon 8 10065
Protoss_Shield_Battery 1 7557
10065
