Protoss_Gateway 2 5902
Protoss_Assimilator 1 3243
Protoss_Cybernetics_Core 1 4208
Protoss_Zealot 3 8623
Protoss_Dragoon 12 10658
Protoss_Nexus 1 10420
Protoss_Robotics_Facility 1 10748
10748
