Protoss_Gateway 3 8879
Protoss_Assimilator 1 3220
Protoss_Cybernetics_Core 1 3989
Protoss_Dragoon 8 10426
Protoss_Robotics_Facility 1 7272
Protoss_Zealot 4 9388
Protoss_Shuttle 1 8565
Protoss_Observatory 1 8171
Protoss_Observer 1 9241
Protoss_Citadel_of_Adun 1 9801
10426
