Protoss_Gateway 2 6100
Protoss_Assimilator 1 2930
Protoss_Cybernetics_Core 1 3734
Protoss_Zealot 3 10193
Protoss_Dragoon 7 7998
Protoss_Citadel_of_Adun 1 7627
Protoss_Templar_Archives 1 8649
Protoss_Robotics_Facility 1 9077
Protoss_Dark_Templar 2 9528
Protoss_Shuttle 1 10222
10222
