Protoss_Gateway 2 5398
Protoss_Assimilator 1 2875
Protoss_Cybernetics_Core 1 3874
Protoss_Dragoon 6 8048
Protoss_Robotics_Facility 1 6407
Protoss_Observatory 1 7026
Protoss_Citadel_of_Adun 1 7746
Protoss_Observer 1 8113
Protoss_Zealot 2 8650
Protoss_Templar_Archives 1 9202
Protoss_Nexus 1 10944
Protoss_Dark_Templar 2 10193
10944
