Protoss_Gateway 2 7204
Protoss_Assimilator 1 3030
Protoss_Cybernetics_Core 1 3948
Protoss_Dragoon 8 10213
Protoss_Robotics_Facility 1 6707
Protoss_Observatory 1 7302
Protoss_Observer 3 10443
Protoss_Nexus 2 10635
10635
