Protoss_Gateway 2 6799
Protoss_Assimilator 1 3086
Protoss_Cybernetics_Core 1 3939
Protoss_Dragoon 3 6415
Protoss_Citadel_of_Adun 1 6152
Protoss_Templar_Archives 1 7196
Protoss_Zealot 1 7017
Protoss_Dark_Templar 6 10108
Protoss_Nexus 1 9963
10108
