Protoss_Gateway 2 5396
Protoss_Assimilator 1 2992
Protoss_Cybernetics_Core 1 3999
Protoss_Dragoon 12 10563
Protoss_Robotics_Facility 1 8747
Protoss_Observatory 1 9337
Protoss_Nexus 1 10925
10925
