Protoss_Gateway 3 10484
Protoss_Assimilator 1 3080
Protoss_Cybernetics_Core 1 4029
Protoss_Dragoon 12 10362
Protoss_Nexus 1 8260
Protoss_Robotics_Facility 1 7978
Protoss_Observatory 1 8684
Protoss_Observer 1 9773
10484
