Protoss_Gateway 2 9659
Protoss_Assimilator 1 3100
Protoss_Cybernetics_Core 1 4049
Protoss_Dragoon 5 10668
Protoss_Robotics_Facility 1 5822
Protoss_Shuttle 1 6812
Protoss_Robotics_Support_Bay 1 6656
Protoss_Reaver 1 7874
Protoss_Zealot 1 7598
Protoss_Observatory 1 7611
Protoss_Nexus 1 9860
Protoss_Observer 3 10293
10668
