Protoss_Gateway 2 6836
Protoss_Assimilator 1 3083
Protoss_Cybernetics_Core 1 4222
Protoss_Dragoon 7 9028
Protoss_Robotics_Facility 1 5982
Protoss_Observatory 1 6868
Protoss_Observer 2 9313
Protoss_Zealot 1 7723
Protoss_Shuttle 1 8554
Protoss_Robotics_Support_Bay 1 8548
Protoss_Reaver 1 10363
Protoss_Nexus 1 11207
11207
