Protoss_Gateway 1 2864
Protoss_Assimilator 1 3106
Protoss_Cybernetics_Core 1 4084
Protoss_Dragoon 4 10092
Protoss_Robotics_Facility 1 5852
Protoss_Zealot 2 6665
Protoss_Shuttle 2 10732
Protoss_Robotics_Support_Bay 1 6841
Protoss_Reaver 2 9333
Protoss_Nexus 1 10599
10732
