Protoss_Nexus 1 4661
Protoss_Gateway 3 8206
Protoss_Assimilator 1 4530
Protoss_Zealot 8 10568
Protoss_Cybernetics_Core 1 6389
Protoss_Dragoon 2 8873
Protoss_Citadel_of_Adun 1 8270
Protoss_Forge 2 8198
Protoss_Photon_Cannon 3 10090
Protoss_Templar_Archives 1 9534
Protoss_Dark_Templar 1 10403
10568
