Protoss_Gateway 5 10770
Protoss_Assimilator 1 3125
Protoss_Cybernetics_Core 1 4101
Protoss_Dragoon 9 10730
Protoss_Robotics_Facility 1 5958
Protoss_Observatory 1 6626
Protoss_Observer 2 8026
Protoss_Nexus 1 9638
Protoss_Shuttle 1 9141
10770
