Protoss_Gateway 2 7234
Protoss_Assimilator 1 3210
Protoss_Cybernetics_Core 1 4145
Protoss_Dragoon 8 10413
Protoss_Robotics_Facility 1 6818
Protoss_Observatory 1 7462
Protoss_Nexus 1 9350
Protoss_Observer 2 8790
Protoss_Shuttle 1 9787
Protoss_Robotics_Support_Bay 1 9566
Protoss_Reaver 1 10838
10838
