Protoss_Gateway 4 10833
Protoss_Assimilator 1 2961
Protoss_Zealot 1 3632
Protoss_Cybernetics_Core 1 4281
Protoss_Dragoon 8 9794
Protoss_Robotics_Facility 1 8053
Protoss_Observatory 1 8683
Protoss_Nexus 1 10233
Protoss_Observer 2 9970
10833
