Protoss_Gateway 2 6151
Protoss_Assimilator 1 3037
Protoss_Cybernetics_Core 1 3904
Protoss_Dragoon 7 8403
Protoss_Robotics_Facility 1 7244
Protoss_Observatory 1 7851
Protoss_Observer 2 9190
Protoss_Nexus 1 10343
Protoss_Shuttle 1 9782
Protoss_Zealot 2 9923
10343
