Protoss_Gateway 4 10587
Protoss_Assimilator 1 3249
Protoss_Zealot 4 10154
Protoss_Cybernetics_Core 1 4708
Protoss_Dragoon 9 10248
Protoss_Robotics_Facility 1 7273
Protoss_Observatory 1 7833
Protoss_Observer 2 9162
Protoss_Nexus 1 10118
10587
