Protoss_Assimilator 1 2383
Protoss_Gateway 1 3044
Protoss_Cybernetics_Core 1 4119
Protoss_Dragoon 5 9705
Protoss_Robotics_Facility 1 5686
Protoss_Shuttle 1 6697
Protoss_Robotics_Support_Bay 1 6446
Protoss_Reaver 3 10495
Protoss_Observatory 1 7362
Protoss_Observer 1 9445
10495
