Protoss_Gateway 3 7247
Protoss_Assimilator 1 3080
Protoss_Cybernetics_Core 1 3974
Protoss_Dragoon 9 9636
Protoss_Nexus 1 7768
Protoss_Zealot 1 7804
Protoss_Robotics_Facility 1 10385
Protoss_Citadel_of_Adun 1 10663
10663
