Protoss_Gateway 2 6057
Protoss_Assimilator 1 3026
Protoss_Cybernetics_Core 1 4110
Protoss_Dragoon 4 6937
Protoss_Citadel_of_Adun 1 7465
Protoss_Zealot 4 8503
Protoss_Robotics_Facility 1 8467
Protoss_Templar_Archives 1 8518
Protoss_Shuttle 1 9542
Protoss_Dark_Templar 4 10658
Protoss_Nexus 1 11285
11285
