Protoss_Gateway 2 7234
Protoss_Assimilator 1 2999
Protoss_Cybernetics_Core 1 3934
Protoss_Dragoon 9 9968
Protoss_Citadel_of_Adun 2 10625
Protoss_Robotics_Facility 1 6353
Protoss_Observatory 1 6906
Protoss_Observer 2 8961
Protoss_Nexus 1 10208
10625
