Protoss_Gateway 3 7932
Protoss_Assimilator 1 3243
Protoss_Zealot 2 4063
Protoss_Cybernetics_Core 1 4156
Protoss_Dragoon 12 10255
Protoss_Citadel_of_Adun 1 9497
Protoss_Templar_Archives 1 10519
10519
