Protoss_Gateway 1 3006
Protoss_Assimilator 1 3154
Protoss_Cybernetics_Core 1 4209
Protoss_Dragoon 6 10053
Protoss_Robotics_Facility 1 7230
Protoss_Shuttle 1 8262
Protoss_Zealot 1 8168
Protoss_Robotics_Support_Bay 1 8276
Protoss_Reaver 1 9476
Protoss_Observatory 1 9155
Protoss_Observer 1 10492
10492
