Protoss_Gateway 2 7673
Protoss_Assimilator 1 2913
Protoss_Cybernetics_Core 1 3993
Protoss_Robotics_Facility 1 5421
Protoss_Dragoon 9 10032
Protoss_Observatory 1 6077
Protoss_Observer 2 9498
10032
