Protoss_Gateway 1 2716
Protoss_Zealot 3 4878
Protoss_Assimilator 1 3645
Protoss_Cybernetics_Core 1 4734
Protoss_Robotics_Facility 1 6247
Protoss_Dragoon 6 10525
Protoss_Robotics_Support_Bay 1 6874
Protoss_Reaver 3 10743
Protoss_Observatory 1 7626
Protoss_Nexus 1 9090
Protoss_Observer 1 8625
10743
