Protoss_Gateway 3 6049
Protoss_Assimilator 1 3146
Protoss_Cybernetics_Core 1 3997
Protoss_Dragoon 12 10090
Protoss_Robotics_Facility 1 7469
Protoss_Observatory 1 8073
Protoss_Nexus 1 9585
Protoss_Observer 2 10084
10090
