Protoss_Gateway 3 10745
Protoss_Assimilator 1 3035
Protoss_Cybernetics_Core 1 3890
Protoss_Dragoon 5 10663
Protoss_Citadel_of_Adun 1 5179
Protoss_Templar_Archives 1 6277
Protoss_Dark_Templar 6 8723
Protoss_Nexus 1 10170
Protoss_Forge 1 9273
10745
