Protoss_Gateway 2 5463
Protoss_Assimilator 1 2873
Protoss_Cybernetics_Core 1 3769
Protoss_Dragoon 11 10366
Protoss_Nexus 1 8816
Protoss_Robotics_Facility 1 9251
Protoss_Observatory 1 9890
10366
