Protoss_Gateway 2 4719
Protoss_Assimilator 1 2995
Protoss_Cybernetics_Core 1 3964
Protoss_Dragoon 10 9163
Protoss_Nexus 1 9283
Protoss_Citadel_of_Adun 1 9268
Protoss_Templar_Archives 1 10781
10781
