Protoss_Gateway 3 10349
Protoss_Assimilator 1 2983
Protoss_Cybernetics_Core 1 3970
Protoss_Dragoon 8 10028
Protoss_Zealot 2 6763
Protoss_Nexus 1 8760
Protoss_Robotics_Facility 1 8768
Protoss_Observatory 1 9428
Protoss_Observer 1 10128
10349
