Protoss_Gateway 2 9384
Protoss_Assimilator 1 3040
Protoss_Zealot 1 3668
Protoss_Cybernetics_Core 1 4609
Protoss_Dragoon 7 10418
Protoss_Robotics_Facility 1 6155
Protoss_Shuttle 1 7147
Protoss_Robotics_Support_Bay 1 7096
Protoss_Reaver 2 9283
Protoss_Observatory 1 9111
Protoss_Nexus 1 11064
Protoss_Observer 1 10563
11064
