Protoss_Gateway 2 5585
Protoss_Assimilator 2 9761
Protoss_Cybernetics_Core 1 3872
Protoss_Dragoon 10 10355
Protoss_Robotics_Facility 1 7730
Protoss_Zealot 1 7418
Protoss_Observatory 1 8390
Protoss_Nexus 1 10140
Protoss_Observer 2 9998
Protoss_Stargate 1 10424
10424
