Protoss_Gateway 2 6413
Protoss_Assimilator 1 2880
Protoss_Cybernetics_Core 1 4106
Protoss_Dragoon 9 10170
Protoss_Robotics_Facility 1 5716
Protoss_Observatory 1 6447
Protoss_Observer 3 10380
Protoss_Nexus 2 11460
11460
