Protoss_Gateway 1 2884
Protoss_Assimilator 1 3130
Protoss_Cybernetics_Core 1 4088
Protoss_Dragoon 7 9616
Protoss_Robotics_Facility 1 6837
Protoss_Shuttle 1 7832
Protoss_Observatory 1 7508
Protoss_Robotics_Support_Bay 1 8196
Protoss_Observer 1 8435
Protoss_Reaver 2 10618
10618
