Protoss_Gateway 2 4371
Protoss_Assimilator 1 2956
Protoss_Cybernetics_Core 1 3880
Protoss_Dragoon 11 10004
Protoss_Nexus 1 8208
Protoss_Robotics_Facility 1 8413
Protoss_Observatory 1 8996
Protoss_Observer 2 10386
10386
