Protoss_Gateway 2 3449
Protoss_Zealot 7 6068
Protoss_Assimilator 1 4564
Protoss_Cybernetics_Core 1 5950
Protoss_Dragoon 6 8810
Protoss_Citadel_of_Adun 1 7722
Protoss_Templar_Archives 1 9084
Protoss_Dark_Templar 2 10008
Protoss_Nexus 1 11352
11352
