Protoss_Gateway 2 5855
Protoss_Assimilator 1 3105
Protoss_Zealot 2 9868
Protoss_Cybernetics_Core 1 4850
Protoss_Dragoon 8 10418
Protoss_Robotics_Facility 1 7178
Protoss_Observatory 1 7731
Protoss_Observer 3 10438
Protoss_Nexus 1 10509
10509
