Protoss_Gateway 3 9205
Protoss_Assimilator 1 3035
Protoss_Cybernetics_Core 1 4194
Protoss_Robotics_Facility 1 5562
Protoss_Dragoon 7 10048
Protoss_Observatory 1 6119
Protoss_Observer 2 8312
Protoss_Shuttle 2 10272
Protoss_Nexus 1 11729
11729
