Protoss_Gateway 3 7341
Protoss_Assimilator 2 9511
Protoss_Cybernetics_Core 1 3761
Protoss_Dragoon 8 10653
Protoss_Robotics_Facility 1 6711
Protoss_Observatory 1 7405
Protoss_Observer 2 8700
Protoss_Nexus 1 9315
Protoss_Zealot 3 9113
Protoss_Shuttle 1 10095
10653
