Protoss_Gateway 4 10215
Protoss_Assimilator 1 2946
Protoss_Cybernetics_Core 1 3794
Protoss_Dragoon 11 10428
Protoss_Robotics_Facility 1 6632
Protoss_Observatory 1 7181
Protoss_Observer 2 9563
Protoss_Nexus 1 10191
10428
