Protoss_Gateway 4 10359
Protoss_Assimilator 1 2765
Protoss_Cybernetics_Core 1 3830
Protoss_Dragoon 3 5543
Protoss_Robotics_Facility 1 6882
Protoss_Zealot 3 10125
Protoss_Citadel_of_Adun 1 7339
Protoss_Observatory 1 7616
Protoss_Templar_Archives 1 8662
Protoss_Shuttle 1 8827
Protoss_Nexus 1 10078
Protoss_Dark_Templar 3 10265
10359
