Protoss_Gateway 2 5769
Protoss_Assimilator 1 3117
Protoss_Cybernetics_Core 1 4172
Protoss_Dragoon 11 10584
Protoss_Robotics_Facility 1 7015
Protoss_Observatory 1 7739
Protoss_Observer 2 9322
Protoss_Nexus 1 9969
10584
