Protoss_Gateway 2 5758
Protoss_Forge 1 3605
Protoss_Zealot 2 4228
Protoss_Assimilator 1 4258
Protoss_Photon_Cannon 1 4520
Protoss_Cybernetics_Core 1 5289
Protoss_Dragoon 11 10432
Protoss_Robotics_Facility 1 9273
Protoss_Shuttle 1 10625
10625
