Protoss_Gateway 2 8585
Protoss_Assimilator 1 3145
Protoss_Cybernetics_Core 1 4161
Protoss_Dragoon 6 9199
Protoss_Robotics_Facility 1 7236
Protoss_Observatory 1 7965
Protoss_Citadel_of_Adun 1 8441
Protoss_Observer 1 9113
9199
