Protoss_Gateway 2 5309
Protoss_Assimilator 2 10405
Protoss_Cybernetics_Core 1 3855
Protoss_Dragoon 10 9708
Protoss_Zealot 1 7802
Protoss_Nexus 1 9408
Protoss_Robotics_Facility 1 9539
Protoss_Shuttle 1 10852
10852
