Protoss_Gateway 4 9965
Protoss_Assimilator 1 2983
Protoss_Cybernetics_Core 1 4033
Protoss_Dragoon 11 10276
Protoss_Nexus 1 7945
Protoss_Robotics_Facility 1 8645
Protoss_Observatory 1 9284
10276
