Protoss_Gateway 2 6783
Protoss_Assimilator 1 3022
Protoss_Cybernetics_Core 1 3943
Protoss_Dragoon 11 10634
Protoss_Robotics_Facility 1 5699
Protoss_Observatory 1 6342
Protoss_Observer 3 10086
Protoss_Nexus 2 11502
11502
