Protoss_Gateway 4 9907
Protoss_Assimilator 2 10001
Protoss_Cybernetics_Core 1 4021
Protoss_Dragoon 11 10532
Protoss_Nexus 1 8172
Protoss_Robotics_Facility 1 8318
Protoss_Observatory 1 8977
Protoss_Observer 1 9874
10532
