Protoss_Gateway 2 5900
Protoss_Assimilator 1 3075
Protoss_Cybernetics_Core 1 4011
Protoss_Dragoon 5 10035
Protoss_Citadel_of_Adun 1 6539
Protoss_Zealot 3 7300
Protoss_Templar_Archives 1 7645
Protoss_Nexus 1 9306
Protoss_Dark_Templar 4 9345
Protoss_Robotics_Facility 1 10646
10646
