Protoss_Gateway 2 5544
Protoss_Assimilator 1 2996
Protoss_Cybernetics_Core 1 3953
Protoss_Dragoon 4 6660
Protoss_Citadel_of_Adun 1 7181
Protoss_Zealot 2 7262
Protoss_Templar_Archives 1 8216
Protoss_Robotics_Facility 1 8718
Protoss_Dark_Templar 3 10084
Protoss_Nexus 1 10607
Protoss_Shuttle 1 9821
Protoss_Observatory 1 10039
10607
