Protoss_Gateway 4 10859
Protoss_Zealot 3 7223
Protoss_Assimilator 1 3785
Protoss_Cybernetics_Core 1 4959
Protoss_Dragoon 3 7328
Protoss_Citadel_of_Adun 1 6124
Protoss_Templar_Archives 1 7119
Protoss_Dark_Templar 6 10540
Protoss_Robotics_Facility 1 9135
Protoss_Shuttle 1 10532
10859
