Protoss_Gateway 2 3508
Protoss_Zealot 9 10544
Protoss_Assimilator 1 4079
Protoss_Cybernetics_Core 1 5189
Protoss_Dragoon 4 7082
Protoss_Citadel_of_Adun 1 7719
Protoss_Templar_Archives 1 8757
Protoss_High_Templar 2 10558
Protoss_Forge 1 9756
10558
