Protoss_Gateway 2 6294
Protoss_Assimilator 1 2970
Protoss_Zealot 3 8040
Protoss_Cybernetics_Core 1 4234
Protoss_Dragoon 8 10418
Protoss_Nexus 1 9995
Protoss_Robotics_Facility 1 10109
10418
