Protoss_Gateway 1 2839
Protoss_Assimilator 1 3255
Protoss_Zealot 3 5673
Protoss_Cybernetics_Core 1 5503
Protoss_Robotics_Facility 1 6828
Protoss_Dragoon 2 7285
Protoss_Citadel_of_Adun 1 7204
Protoss_Robotics_Support_Bay 1 7546
Protoss_Shuttle 1 7997
Protoss_Templar_Archives 1 8399
Protoss_Reaver 2 10100
Protoss_Dark_Templar 2 10260
10260
