Protoss_Gateway 3 8265
Protoss_Assimilator 1 2870
Protoss_Cybernetics_Core 1 3826
Protoss_Dragoon 11 9260
Protoss_Robotics_Facility 1 7909
Protoss_Zealot 5 10546
Protoss_Observatory 1 8510
Protoss_Observer 1 9200
Protoss_Shuttle 1 10265
Protoss_Nexus 1 11481
11481
