Protoss_Gateway 2 4229
Protoss_Assimilator 1 2939
Protoss_Cybernetics_Core 1 3819
Protoss_Dragoon 13 10116
Protoss_Zealot 2 6650
Protoss_Nexus 1 10017
Protoss_Robotics_Facility 1 10615
10615
