Protoss_Gateway 4 10204
Protoss_Assimilator 1 3020
Protoss_Cybernetics_Core 1 3833
Protoss_Dragoon 12 10670
Protoss_Nexus 1 8635
Protoss_Robotics_Facility 1 8345
Protoss_Observatory 1 8941
Protoss_Observer 2 10240
10670
