Protoss_Gateway 2 7014
Protoss_Assimilator 1 3125
Protoss_Cybernetics_Core 1 4159
Protoss_Dragoon 10 9593
Protoss_Robotics_Facility 1 6813
Protoss_Observatory 1 7644
Protoss_Observer 2 8940
Protoss_Nexus 2 11509
11509
