Protoss_Gateway 2 6704
Protoss_Assimilator 1 3077
Protoss_Cybernetics_Core 1 3984
Protoss_Dragoon 8 9440
Protoss_Robotics_Facility 1 6652
Protoss_Observatory 1 7202
Protoss_Observer 2 8525
Protoss_Nexus 1 9340
Protoss_Shuttle 1 8977
Protoss_Robotics_Support_Bay 1 8773
Protoss_Reaver 1 10186
Protoss_Zealot 2 10042
10186
