Protoss_Gateway 2 5981
Protoss_Zealot 5 9998
Protoss_Assimilator 1 4386
Protoss_Cybernetics_Core 1 5177
Protoss_Dragoon 9 9396
Protoss_Robotics_Facility 1 9277
Protoss_Shuttle 1 10292
Protoss_Robotics_Support_Bay 1 9873
10292
