Protoss_Gateway 2 8920
Protoss_Assimilator 1 2908
Protoss_Cybernetics_Core 1 4102
Protoss_Dragoon 5 10370
Protoss_Robotics_Facility 1 5887
Protoss_Shuttle 1 6873
Protoss_Robotics_Support_Bay 1 6491
Protoss_Zealot 2 7714
Protoss_Reaver 2 9334
Protoss_Nexus 1 11047
Protoss_Observatory 1 9951
11047
