Protoss_Nexus 2 10512
Protoss_Gateway 3 7846
Protoss_Assimilator 2 10576
Protoss_Cybernetics_Core 1 5005
Protoss_Zealot 1 5503
Protoss_Dragoon 8 8993
Protoss_Robotics_Facility 1 8487
Protoss_Shuttle 1 9517
Protoss_Robotics_Support_Bay 1 9266
Protoss_Observatory 1 9604
Protoss_Reaver 1 10568
10576
