Protoss_Gateway 3 10888
Protoss_Assimilator 1 3220
Protoss_Cybernetics_Core 1 4214
Protoss_Dragoon 11 10218
Protoss_Robotics_Facility 1 8062
Protoss_Nexus 1 9860
Protoss_Observatory 1 8696
Protoss_Observer 2 10025
10888
