Protoss_Gateway 3 10391
Protoss_Assimilator 1 3002
Protoss_Cybernetics_Core 1 3870
Protoss_Dragoon 7 10230
Protoss_Nexus 2 10874
Protoss_Robotics_Facility 1 9008
Protoss_Observatory 1 9766
10874
