Protoss_Gateway 2 4372
Protoss_Assimilator 1 2968
Protoss_Cybernetics_Core 1 3807
Protoss_Dragoon 9 8496
Protoss_Robotics_Facility 1 7767
Protoss_Shuttle 1 8921
Protoss_Robotics_Support_Bay 1 8655
Protoss_Reaver 1 9972
Protoss_Zealot 2 9886
9972
