Protoss_Nexus 1 4445
Protoss_Gateway 2 6100
Protoss_Assimilator 1 3797
Protoss_Cybernetics_Core 1 4845
Protoss_Zealot 1 4940
Protoss_Dragoon 10 9922
Protoss_Robotics_Facility 1 8365
Protoss_Observatory 1 9125
Protoss_Observer 1 9880
9922
