Protoss_Gateway 3 9277
Protoss_Assimilator 2 10084
Protoss_Cybernetics_Core 1 3789
Protoss_Dragoon 11 10612
Protoss_Robotics_Facility 1 6501
Protoss_Observatory 1 7092
Protoss_Observer 4 10298
Protoss_Nexus 1 9041
Protoss_Citadel_of_Adun 1 9175
Protoss_Templar_Archives 1 10410
10612
