Protoss_Gateway 5 9166
Protoss_Assimilator 2 9766
Protoss_Cybernetics_Core 1 3998
Protoss_Dragoon 8 9380
Protoss_Nexus 1 8872
Protoss_Robotics_Facility 1 9023
Protoss_Observatory 1 9777
Protoss_Zealot 3 10200
Protoss_Shuttle 1 10795
10795
