Protoss_Gateway 2 6389
Protoss_Assimilator 2 9990
Protoss_Cybernetics_Core 1 3799
Protoss_Dragoon 7 9930
Protoss_Citadel_of_Adun 1 5945
Protoss_Robotics_Facility 1 6473
Protoss_Templar_Archives 1 6974
Protoss_Zealot 3 10078
Protoss_Shuttle 2 10227
Protoss_Dark_Templar 2 7958
Protoss_Nexus 1 9995
Protoss_Observatory 1 9140
Protoss_Robotics_Support_Bay 1 9971
Protoss_Forge 1 10526
10526
