Protoss_Forge 1 3384
Protoss_Photon_Cannon 6 9646
Protoss_Nexus 2 11535
Protoss_Assimilator 1 6383
Protoss_Gateway 1 6966
Protoss_Cybernetics_Core 1 8035
Protoss_Stargate 2 9260
Protoss_Scout 2 10550
11535
