Protoss_Gateway 2 9528
Protoss_Assimilator 1 3072
Protoss_Zealot 3 10460
Protoss_Cybernetics_Core 1 4559
Protoss_Dragoon 6 9886
Protoss_Robotics_Facility 1 6829
Protoss_Observatory 1 7395
Protoss_Nexus 1 9085
Protoss_Observer 2 8686
Protoss_Shuttle 1 9587
Protoss_Robotics_Support_Bay 1 9199
Protoss_Reaver 1 10698
10698
