Protoss_Gateway 2 5477
Protoss_Assimilator 1 2926
Protoss_Cybernetics_Core 1 3819
Protoss_Dragoon 9 10224
Protoss_Robotics_Facility 1 7897
Protoss_Zealot 2 7892
Protoss_Shuttle 1 8929
Protoss_Robotics_Support_Bay 1 8667
Protoss_Reaver 1 10230
10230
