Protoss_Gateway 2 6084
Protoss_Assimilator 1 2934
Protoss_Cybernetics_Core 1 3974
Protoss_Zealot 1 4598
Protoss_Citadel_of_Adun 1 5353
Protoss_Robotics_Facility 1 6160
Protoss_Templar_Archives 1 6529
Protoss_Shuttle 1 7167
Protoss_Dark_Templar 4 8803
Protoss_Forge 1 7537
Protoss_Photon_Cannon 2 9803
Protoss_Dragoon 4 10533
Protoss_Observatory 1 9902
10533
