Protoss_Gateway 2 7754
Protoss_Assimilator 1 3200
Protoss_Cybernetics_Core 1 4169
Protoss_Dragoon 9 10670
Protoss_Robotics_Facility 1 7357
Protoss_Shuttle 1 8417
Protoss_Zealot 4 9045
Protoss_Observatory 1 8757
Protoss_Observer 1 9713
Protoss_Nexus 1 11385
11385
