Protoss_Gateway 2 4369
Protoss_Assimilator 1 3005
Protoss_Cybernetics_Core 1 3943
Protoss_Dragoon 12 10013
Protoss_Nexus 1 9637
Protoss_Zealot 2 8858
Protoss_Robotics_Facility 1 10038
10038
