Protoss_Gateway 3 10292
Protoss_Assimilator 1 3071
Protoss_Cybernetics_Core 1 3986
Protoss_Dragoon 1 4828
Protoss_Robotics_Facility 1 6001
Protoss_Nexus 1 7700
Protoss_Observatory 1 6572
Protoss_Observer 1 7293
Protoss_Forge 1 7303
Protoss_Zealot 3 9553
Protoss_Shuttle 1 8220
Protoss_Photon_Cannon 4 9939
10292
