Protoss_Gateway 2 5289
Protoss_Assimilator 1 3244
Protoss_Zealot 2 4618
Protoss_Cybernetics_Core 1 4614
Protoss_Dragoon 11 10643
Protoss_Nexus 2 10107
Protoss_Robotics_Facility 1 10726
10726
