Protoss_Gateway 2 5298
Protoss_Assimilator 1 2918
Protoss_Zealot 3 4656
Protoss_Cybernetics_Core 1 4935
Protoss_Dragoon 10 10160
Protoss_Nexus 1 9748
Protoss_Robotics_Facility 1 10149
10160
