Protoss_Gateway 3 10826
Protoss_Assimilator 1 2998
Protoss_Cybernetics_Core 1 3839
Protoss_Dragoon 8 10744
Protoss_Robotics_Facility 1 6675
Protoss_Observatory 1 7238
Protoss_Observer 2 8620
Protoss_Nexus 1 9449
Protoss_Zealot 4 9166
Protoss_Shuttle 1 9689
10826
