Protoss_Gateway 3 10702
Protoss_Assimilator 1 2975
Protoss_Cybernetics_Core 1 3917
Protoss_Dragoon 11 10423
Protoss_Robotics_Facility 1 6675
Protoss_Observatory 1 7236
Protoss_Observer 3 10580
Protoss_Nexus 1 9975
Protoss_Shuttle 1 9977
10702
