Protoss_Gateway 2 3815
Protoss_Zealot 19 10787
Protoss_Forge 1 7548
Protoss_Assimilator 1 7576
Protoss_Cybernetics_Core 1 9007
Protoss_Photon_Cannon 1 8812
Protoss_Citadel_of_Adun 1 10146
10787
