Protoss_Forge 1 3026
Protoss_Photon_Cannon 6 10608
Protoss_Nexus 1 6893
Protoss_Gateway 1 5918
Protoss_Assimilator 2 7747
Protoss_Cybernetics_Core 1 7394
Protoss_Zealot 2 8191
Protoss_Robotics_Facility 1 8996
Protoss_Stargate 1 9333
Protoss_Robotics_Support_Bay 1 9113
Protoss_Corsair 2 10571
Protoss_Reaver 2 11663
11663
