Protoss_Gateway 2 3951
Protoss_Zealot 13 8527
Protoss_Assimilator 1 6697
Protoss_Cybernetics_Core 1 8449
Protoss_Stargate 1 9867
Protoss_Dragoon 1 9685
Protoss_Citadel_of_Adun 1 10257
Protoss_Forge 1 10095
Protoss_Corsair 1 10285
10285
