Protoss_Forge 1 3315
Protoss_Nexus 1 6357
Protoss_Photon_Cannon 1 4763
Protoss_Gateway 4 10075
Protoss_Assimilator 2 7918
Protoss_Cybernetics_Core 1 6912
Protoss_Zealot 12 10833
Protoss_Citadel_of_Adun 1 8156
Protoss_Dragoon 1 8586
Protoss_Robotics_Facility 1 10705
Protoss_Templar_Archives 1 10381
Protoss_Ground_Weapons_1 1 9911
10833
