Protoss_Forge 1 3144
Protoss_Nexus 1 6308
Protoss_Gateway 5 10354
Protoss_Photon_Cannon 2 6443
Protoss_Assimilator 2 8816
Protoss_Zealot 11 10938
Protoss_Cybernetics_Core 1 7761
Protoss_Citadel_of_Adun 1 8863
Protoss_Stargate 1 9445
Protoss_Corsair 1 9866
Protoss_Templar_Archives 1 10707
10938
