Protoss_Forge 1 3622
Protoss_Photon_Cannon 4 10631
Protoss_Nexus 1 6628
Protoss_Gateway 2 11388
Protoss_Assimilator 2 8249
Protoss_Zealot 6 10258
Protoss_Cybernetics_Core 1 7395
Protoss_Dragoon 1 8141
Protoss_Stargate 1 8910
Protoss_Corsair 2 10426
Protoss_Citadel_of_Adun 1 10363
Protoss_Templar_Archives 1 11380
11388
