Protoss_Nexus 1 5577
Protoss_Forge 1 4738
Protoss_Gateway 4 11220
Protoss_Assimilator 2 7676
Protoss_Photon_Cannon 5 10041
Protoss_Cybernetics_Core 1 7137
Protoss_Zealot 3 9765
Protoss_Dragoon 2 8641
Protoss_Stargate 1 8607
Protoss_Citadel_of_Adun 1 9325
Protoss_Corsair 2 9617
Protoss_Templar_Archives 1 10889
11220
