Protoss_Gateway 2 8966
Protoss_Assimilator 2 10952
Protoss_Zealot 4 7811
Protoss_Cybernetics_Core 1 5082
Protoss_Stargate 1 6333
Protoss_Dragoon 1 6155
Protoss_Citadel_of_Adun 1 6804
Protoss_Corsair 1 6741
Protoss_Forge 1 7013
Protoss_Templar_Archives 1 7959
Protoss_Dark_Templar 1 8711
Protoss_Photon_Cannon 2 10131
Protoss_Nexus 1 11370
Protoss_High_Templar 2 10405
11370
