Protoss_Gateway 3 9391
Protoss_Assimilator 1 2209
Protoss_Cybernetics_Core 1 2841
Protoss_Dragoon 7 9709
Protoss_Robotics_Facility 1 4278
Protoss_Shuttle 1 5567
Protoss_Robotics_Support_Bay 1 5712
Protoss_Reaver 2 7693
Protoss_Scarab 6 9943
9943
