Protoss_Gateway 2 4234
Protoss_Zealot 14 10171
Protoss_Assimilator 1 6607
Protoss_Cybernetics_Core 1 7985
Protoss_Dragoon 2 10781
Protoss_Robotics_Facility 1 10406
Protoss_Shuttle 1 11287
11287
