Protoss_Forge 1 3118
Protoss_Photon_Cannon 2 4633
Protoss_Nexus 1 7343
Protoss_Gateway 4 9608
Protoss_Assimilator 1 5968
Protoss_Zealot 7 10529
Protoss_Cybernetics_Core 1 7218
10529
