Protoss_Gateway 2 3945
Protoss_Zealot 10 7017
Protoss_Assimilator 1 6055
Protoss_Cybernetics_Core 1 8085
Protoss_Dragoon 6 11107
Protoss_Robotics_Facility 1 9915
Protoss_Shuttle 1 10721
Protoss_Robotics_Support_Bay 1 10310
11107
