Protoss_Nexus 1 5547
Protoss_Forge 1 4359
Protoss_Photon_Cannon 4 10127
Protoss_Gateway 4 8813
Protoss_Assimilator 2 7456
Protoss_Cybernetics_Core 1 6974
Protoss_Zealot 10 10647
Protoss_Citadel_of_Adun 1 8149
Protoss_Dragoon 1 8715
Protoss_Templar_Archives 1 10731
10731
