Protoss_Gateway 1 3119
Protoss_Zealot 3 5725
Protoss_Assimilator 1 4618
Protoss_Cybernetics_Core 1 5796
Protoss_Dragoon 1 6745
Protoss_Stargate 1 7305
Protoss_Robotics_Facility 1 8461
Protoss_Corsair 2 10363
Protoss_Shuttle 1 9685
10363
