Protoss_Gateway 1 3225
Protoss_Zealot 3 4951
Protoss_Assimilator 1 4172
Protoss_Cybernetics_Core 1 5802
Protoss_Stargate 1 7031
Protoss_Forge 1 6377
Protoss_Photon_Cannon 4 9906
Protoss_Corsair 3 9393
Protoss_Robotics_Facility 1 8620
Protoss_Citadel_of_Adun 1 9651
Protoss_Nexus 1 12261
Protoss_Robotics_Support_Bay 1 10341
12261
