Protoss_Gateway 2 7513
Protoss_Assimilator 1 3407
Protoss_Zealot 8 10371
Protoss_Cybernetics_Core 1 5143
Protoss_Stargate 1 6500
Protoss_Citadel_of_Adun 1 6661
Protoss_Corsair 1 6916
Protoss_Templar_Archives 1 7763
Protoss_Dark_Templar 2 8621
Protoss_High_Templar 1 9431
10371
