Protoss_Forge 1 3038
Protoss_Photon_Cannon 8 10824
Protoss_Nexus 2 11883
Protoss_Assimilator 3 8158
Protoss_Gateway 1 7066
Protoss_Cybernetics_Core 1 8116
Protoss_Zealot 2 9518
Protoss_Citadel_of_Adun 1 10165
Protoss_Templar_Archives 1 11322
11883
