Protoss_Nexus 1 5621
Protoss_Forge 1 4043
Protoss_Photon_Cannon 2 9959
Protoss_Gateway 1 5703
Protoss_Assimilator 2 6881
Protoss_Zealot 4 8765
Protoss_Cybernetics_Core 1 7152
Protoss_Stargate 1 8395
Protoss_Dragoon 1 8253
Protoss_Robotics_Facility 1 9059
Protoss_Corsair 1 9203
Protoss_Shuttle 1 9903
Protoss_Robotics_Support_Bay 1 9381
9959
