Protoss_Forge 1 3045
Protoss_Photon_Cannon 3 9911
Protoss_Nexus 1 6363
Protoss_Gateway 2 9955
Protoss_Assimilator 2 7302
Protoss_Zealot 3 7663
Protoss_Cybernetics_Core 1 7419
Protoss_Stargate 1 8748
Protoss_Dragoon 2 9638
Protoss_Citadel_of_Adun 1 8852
Protoss_Templar_Archives 1 9883
Protoss_Corsair 2 10126
Protoss_High_Templar 2 10876
10876
