Protoss_Forge 1 3280
Protoss_Photon_Cannon 3 7517
Protoss_Nexus 1 7338
Protoss_Gateway 3 9769
Protoss_Assimilator 2 7828
Protoss_Cybernetics_Core 1 7358
Protoss_Zealot 1 7116
Protoss_Stargate 1 8660
Protoss_Dragoon 1 8241
Protoss_Citadel_of_Adun 1 9153
Protoss_Corsair 3 10456
Protoss_Templar_Archives 1 10171
Protoss_Dark_Templar 3 10976
10976
