Protoss_Forge 1 3407
Protoss_Photon_Cannon 2 10487
Protoss_Nexus 1 6916
Protoss_Gateway 2 11419
Protoss_Assimilator 2 6018
Protoss_Zealot 2 7061
Protoss_Cybernetics_Core 1 7125
Protoss_Stargate 1 8505
Protoss_Dragoon 2 9749
Protoss_Robotics_Facility 1 9534
Protoss_Corsair 4 10887
Protoss_Robotics_Support_Bay 1 9641
Protoss_Reaver 1 11195
11419
