Protoss_Forge 1 3266
Protoss_Nexus 1 6323
Protoss_Gateway 1 5533
Protoss_Photon_Cannon 3 9825
Protoss_Assimilator 2 7044
Protoss_Zealot 2 7236
Protoss_Cybernetics_Core 1 7258
Protoss_Dragoon 1 8401
Protoss_Stargate 2 9160
Protoss_Robotics_Facility 1 10309
Protoss_Corsair 4 10301
10309
