Protoss_Gateway 1 3463
Protoss_Assimilator 1 3578
Protoss_Cybernetics_Core 1 4649
Protoss_Zealot 2 5763
Protoss_Stargate 1 6060
Protoss_Citadel_of_Adun 1 6773
Protoss_Corsair 1 6701
Protoss_Dragoon 1 7356
Protoss_Templar_Archives 1 7959
Protoss_Dark_Templar 1 8771
Protoss_Forge 1 8627
Protoss_High_Templar 2 10666
Protoss_Photon_Cannon 2 10903
Protoss_Nexus 1 12008
12008
