Protoss_Gateway 3 11385
Protoss_Zealot 10 10501
Protoss_Forge 1 4357
Protoss_Nexus 1 7933
Protoss_Photon_Cannon 2 7283
Protoss_Assimilator 2 8334
Protoss_Cybernetics_Core 1 8510
Protoss_Stargate 1 9946
Protoss_Citadel_of_Adun 1 10304
Protoss_Corsair 1 10357
11385
