Protoss_Gateway 2 3686
Protoss_Zealot 12 10305
Protoss_Assimilator 2 9515
Protoss_Nexus 1 8987
Protoss_Forge 1 7293
Protoss_Cybernetics_Core 1 8462
Protoss_Photon_Cannon 2 11090
Protoss_Citadel_of_Adun 1 9535
Protoss_Stargate 1 10102
Protoss_Corsair 1 10553
11090
