Protoss_Forge 1 3273
Protoss_Photon_Cannon 10 10667
Protoss_Nexus 2 9398
Protoss_Gateway 1 5668
Protoss_Assimilator 2 8085
Protoss_Zealot 2 8176
Protoss_Cybernetics_Core 1 8027
Protoss_Stargate 2 10438
Protoss_Corsair 2 10591
Protoss_Robotics_Facility 1 11788
11788
