Protoss_Forge 1 3757
Protoss_Nexus 1 6275
Protoss_Photon_Cannon 4 9786
Protoss_Gateway 3 10955
Protoss_Assimilator 2 8269
Protoss_Cybernetics_Core 1 7577
Protoss_Zealot 7 10871
Protoss_Stargate 1 8927
Protoss_Citadel_of_Adun 1 9119
Protoss_Corsair 2 10043
Protoss_Templar_Archives 1 10276
10955
