Protoss_Nexus 1 5823
Protoss_Gateway 1 4768
Protoss_Forge 1 4668
Protoss_Photon_Cannon 1 5603
Protoss_Zealot 4 10706
Protoss_Assimilator 1 5828
Protoss_Cybernetics_Core 1 7667
Protoss_Robotics_Facility 1 11355
11355
