Protoss_Nexus 1 5656
Protoss_Forge 1 4067
Protoss_Gateway 1 5293
Protoss_Assimilator 2 7279
Protoss_Photon_Cannon 6 11114
Protoss_Cybernetics_Core 1 6502
Protoss_Zealot 2 7095
Protoss_Stargate 1 7741
Protoss_Robotics_Facility 1 8882
Protoss_Dragoon 1 8721
Protoss_Corsair 4 10617
Protoss_Shuttle 1 10103
Protoss_Robotics_Support_Bay 1 9542
11114
