Protoss_Gateway 2 4081
Protoss_Zealot 9 6776
Protoss_Forge 1 7064
Protoss_Photon_Cannon 6 10873
Protoss_Nexus 1 10121
Protoss_Assimilator 2 10422
Protoss_Cybernetics_Core 1 9135
Protoss_Stargate 1 10629
10873
