Protoss_Forge 1 3196
Protoss_Nexus 1 6254
Protoss_Photon_Cannon 2 5277
Protoss_Gateway 2 9860
Protoss_Assimilator 2 7631
Protoss_Cybernetics_Core 1 6998
Protoss_Zealot 3 9167
Protoss_Stargate 1 8451
Protoss_Citadel_of_Adun 1 8963
Protoss_Corsair 2 10075
Protoss_Templar_Archives 1 10055
10075
