Protoss_Gateway 2 3685
Protoss_Zealot 17 9551
Protoss_Assimilator 1 6161
Protoss_Cybernetics_Core 1 9261
Protoss_Forge 1 9741
Protoss_Stargate 1 10892
Protoss_Photon_Cannon 1 10755
Protoss_Citadel_of_Adun 1 11437
11437
