Protoss_Gateway 1 1607
Protoss_Zealot 6 7137
Protoss_Assimilator 1 3618
Protoss_Cybernetics_Core 1 4703
Protoss_Dragoon 1 6385
Protoss_Stargate 1 6907
Protoss_Forge 1 8994
8994
