Protoss_Nexus 1 5828
Protoss_Forge 1 4217
Protoss_Photon_Cannon 4 9812
Protoss_Gateway 3 8833
Protoss_Assimilator 2 7186
Protoss_Zealot 5 10896
Protoss_Cybernetics_Core 1 7378
Protoss_Citadel_of_Adun 1 8449
Protoss_Dragoon 1 8567
Protoss_Templar_Archives 1 9565
Protoss_High_Templar 3 10671
10896
