Protoss_Gateway 2 4045
Protoss_Zealot 9 8521
Protoss_Assimilator 1 4612
Protoss_Cybernetics_Core 1 5817
Protoss_Dragoon 1 6566
Protoss_Stargate 1 7466
Protoss_Corsair 1 7961
Protoss_Forge 1 8369
Protoss_Photon_Cannon 1 9714
Protoss_Citadel_of_Adun 1 10241
10241
