Protoss_Forge 1 3639
Protoss_Photon_Cannon 3 9848
Protoss_Nexus 2 8713
Protoss_Gateway 1 6678
Protoss_Assimilator 2 8074
Protoss_Cybernetics_Core 1 8265
Protoss_Zealot 4 10576
Protoss_Stargate 1 9721
Protoss_Robotics_Facility 1 10461
Protoss_Corsair 2 10861
Protoss_Robotics_Support_Bay 1 10588
10861
