Protoss_Gateway 3 8657
Protoss_Assimilator 1 3177
Protoss_Cybernetics_Core 1 4351
Protoss_Stargate 1 5649
Protoss_Zealot 16 10837
Protoss_Dragoon 1 5405
Protoss_Corsair 2 6947
Protoss_Citadel_of_Adun 1 6946
10837
