Protoss_Gateway 2 8493
Protoss_Assimilator 1 3597
Protoss_Cybernetics_Core 1 4645
Protoss_Stargate 1 5926
Protoss_Zealot 3 10847
Protoss_Scout 1 7455
Protoss_Citadel_of_Adun 1 8388
10847
