Protoss_Gateway 3 11291
Protoss_Assimilator 1 3284
Protoss_Cybernetics_Core 1 4371
Protoss_Zealot 5 10601
Protoss_Stargate 1 5884
Protoss_Dragoon 1 5693
Protoss_Corsair 2 7103
Protoss_Citadel_of_Adun 1 7242
Protoss_Templar_Archives 1 8567
Protoss_Forge 1 8562
Protoss_Dark_Templar 1 9307
Protoss_Photon_Cannon 1 9771
Protoss_High_Templar 1 10089
11291
