Protoss_Gateway 1 3484
Protoss_Assimilator 1 3317
Protoss_Zealot 4 8541
Protoss_Cybernetics_Core 1 5570
Protoss_Stargate 1 7424
Protoss_Dragoon 1 7286
Protoss_Forge 1 7146
Protoss_Corsair 2 10386
Protoss_Nexus 2 11663
Protoss_Citadel_of_Adun 1 9660
Protoss_Photon_Cannon 2 10305
11663
