Protoss_Nexus 1 6006
Protoss_Forge 1 4361
Protoss_Gateway 4 8709
Protoss_Assimilator 2 10326
Protoss_Photon_Cannon 2 10990
Protoss_Cybernetics_Core 1 6652
Protoss_Zealot 14 10655
Protoss_Citadel_of_Adun 1 7873
Protoss_Templar_Archives 1 10683
10990
