Protoss_Gateway 3 10729
Protoss_Zealot 4 6977
Protoss_Assimilator 2 9710
Protoss_Cybernetics_Core 1 5349
Protoss_Stargate 1 6648
Protoss_Dragoon 1 6465
Protoss_Forge 1 7176
Protoss_Corsair 1 7273
Protoss_Photon_Cannon 1 8805
Protoss_Nexus 1 10627
Protoss_Citadel_of_Adun 1 9447
Protoss_Templar_Archives 1 10530
10729
