Protoss_Forge 1 3491
Protoss_Photon_Cannon 2 5307
Protoss_Nexus 1 6767
Protoss_Gateway 3 11055
Protoss_Assimilator 3 10161
Protoss_Zealot 7 10763
Protoss_Cybernetics_Core 1 9217
Protoss_Dragoon 1 10251
Protoss_Citadel_of_Adun 1 10569
11055
