Protoss_Forge 1 2807
Protoss_Photon_Cannon 7 11061
Protoss_Nexus 2 11717
Protoss_Gateway 1 6306
Protoss_Assimilator 2 8157
Protoss_Cybernetics_Core 1 7312
Protoss_Dragoon 4 10735
Protoss_Stargate 1 8726
Protoss_Corsair 3 10677
11717
