Protoss_Forge 1 3361
Protoss_Photon_Cannon 8 10498
Protoss_Nexus 1 7078
Protoss_Gateway 3 11362
Protoss_Assimilator 2 10421
Protoss_Zealot 5 10696
Protoss_Cybernetics_Core 1 8014
Protoss_Citadel_of_Adun 1 9008
Protoss_Templar_Archives 1 10003
Protoss_Dark_Templar 1 11021
11362
