Protoss_Forge 1 3545
Protoss_Photon_Cannon 7 10841
Protoss_Nexus 2 11677
Protoss_Gateway 2 9123
Protoss_Zealot 3 7997
Protoss_Assimilator 2 8983
Protoss_Cybernetics_Core 1 8249
Protoss_Dragoon 1 9021
Protoss_Stargate 1 9901
Protoss_Corsair 1 10373
Protoss_Citadel_of_Adun 1 11359
11677
