Protoss_Gateway 1 3348
Protoss_Assimilator 1 3193
Protoss_Cybernetics_Core 1 4423
Protoss_Stargate 1 5706
Protoss_Dragoon 1 5541
Protoss_Corsair 4 9096
Protoss_Robotics_Facility 1 7528
Protoss_Forge 1 7277
Protoss_Shuttle 1 8351
Protoss_Photon_Cannon 3 10228
Protoss_Robotics_Support_Bay 1 8417
Protoss_Zealot 1 9871
Protoss_Reaver 1 10611
10611
