Protoss_Forge 1 3000
Protoss_Photon_Cannon 8 11050
Protoss_Nexus 1 7343
Protoss_Gateway 4 11163
Protoss_Assimilator 2 9091
Protoss_Zealot 4 10233
Protoss_Cybernetics_Core 1 8435
Protoss_Stargate 1 9668
Protoss_Citadel_of_Adun 1 9674
Protoss_Corsair 1 10086
Protoss_Templar_Archives 1 10732
11163
