Protoss_Gateway 2 10223
Protoss_Assimilator 1 3393
Protoss_Zealot 2 5021
Protoss_Cybernetics_Core 1 5298
Protoss_Dragoon 5 10360
Protoss_Stargate 1 7184
Protoss_Corsair 1 7616
Protoss_Robotics_Facility 1 8768
Protoss_Shuttle 1 9576
Protoss_Observatory 1 8935
Protoss_Observer 1 9998
10360
