Protoss_Nexus 1 5603
Protoss_Forge 1 4245
Protoss_Gateway 1 5533
Protoss_Assimilator 2 6948
Protoss_Photon_Cannon 2 6328
Protoss_Cybernetics_Core 1 7027
Protoss_Zealot 5 10831
Protoss_Stargate 1 8416
Protoss_Robotics_Facility 1 9409
Protoss_Dragoon 1 9093
Protoss_Corsair 3 10070
Protoss_Shuttle 1 10231
Protoss_Robotics_Support_Bay 1 9821
Protoss_Reaver 1 11373
Protoss_Citadel_of_Adun 1 11222
11373
