Protoss_Forge 1 3448
Protoss_Nexus 1 6366
Protoss_Gateway 4 9017
Protoss_Assimilator 2 10448
Protoss_Photon_Cannon 1 5477
Protoss_Zealot 14 10871
Protoss_Cybernetics_Core 1 7103
Protoss_Citadel_of_Adun 1 8173
Protoss_Templar_Archives 1 10498
10871
