Protoss_Forge 1 3266
Protoss_Nexus 1 6223
Protoss_Gateway 3 9239
Protoss_Photon_Cannon 2 6078
Protoss_Assimilator 2 7728
Protoss_Zealot 9 10731
Protoss_Cybernetics_Core 1 7333
Protoss_Citadel_of_Adun 1 8620
Protoss_Stargate 2 10918
Protoss_Corsair 1 10841
10918
