Protoss_Gateway 1 3466
Protoss_Assimilator 1 3528
Protoss_Zealot 4 8531
Protoss_Cybernetics_Core 1 5388
Protoss_Dragoon 1 6243
Protoss_Robotics_Facility 1 8018
Protoss_Forge 1 7718
Protoss_Shuttle 1 8836
Protoss_Robotics_Support_Bay 1 8204
Protoss_Reaver 1 10922
10922
