Protoss_Forge 1 3118
Protoss_Photon_Cannon 2 5073
Protoss_Nexus 1 6438
Protoss_Gateway 5 10910
Protoss_Assimilator 1 6225
Protoss_Zealot 10 10731
Protoss_Cybernetics_Core 1 7403
Protoss_Citadel_of_Adun 1 8808
10910
