Protoss_Forge 2 4857
Protoss_Nexus 1 5881
Protoss_Gateway 3 9987
Protoss_Assimilator 2 7941
Protoss_Photon_Cannon 4 10268
Protoss_Zealot 4 9203
Protoss_Cybernetics_Core 1 7101
Protoss_Dragoon 1 7857
Protoss_Stargate 1 8411
Protoss_Citadel_of_Adun 1 8450
Protoss_Corsair 1 8915
Protoss_Templar_Archives 1 9618
Protoss_Dark_Templar 1 10433
Protoss_High_Templar 2 10865
10865
