Protoss_Gateway 2 7884
Protoss_Assimilator 1 3482
Protoss_Cybernetics_Core 1 4628
Protoss_Zealot 10 9615
Protoss_Dragoon 1 5893
Protoss_Citadel_of_Adun 1 7049
Protoss_Templar_Archives 1 9398
Protoss_Forge 1 9805
Protoss_High_Templar 2 10457
Protoss_Photon_Cannon 1 11130
11130
