Protoss_Forge 1 3365
Protoss_Nexus 1 6158
Protoss_Photon_Cannon 4 10878
Protoss_Gateway 3 9641
Protoss_Assimilator 2 7121
Protoss_Cybernetics_Core 1 7323
Protoss_Zealot 3 8989
Protoss_Stargate 1 8603
Protoss_Citadel_of_Adun 1 8763
Protoss_Corsair 3 10547
Protoss_Templar_Archives 1 9835
Protoss_Dark_Templar 2 10901
10901
