Protoss_Gateway 3 8026
Protoss_Zealot 11 10858
Protoss_Assimilator 1 4928
Protoss_Cybernetics_Core 1 6313
Protoss_Citadel_of_Adun 1 7366
Protoss_Dragoon 1 7181
Protoss_Templar_Archives 1 8771
Protoss_Dark_Templar 2 10346
Protoss_High_Templar 2 10836
10858
