Protoss_Gateway 2 10659
Protoss_Assimilator 1 3503
Protoss_Zealot 3 8931
Protoss_Cybernetics_Core 1 5363
Protoss_Robotics_Facility 1 6854
Protoss_Dragoon 4 10111
Protoss_Shuttle 1 7731
Protoss_Robotics_Support_Bay 1 7373
Protoss_Reaver 2 10121
Protoss_Scarab 6 9975
10659
