Protoss_Forge 1 2950
Protoss_Nexus 1 6456
Protoss_Photon_Cannon 5 10502
Protoss_Gateway 3 9423
Protoss_Assimilator 2 6820
Protoss_Cybernetics_Core 1 7634
Protoss_Robotics_Facility 1 9136
Protoss_Stargate 1 9008
Protoss_Citadel_of_Adun 1 9273
Protoss_Robotics_Support_Bay 1 9400
Protoss_Corsair 2 10511
Protoss_Reaver 1 11006
Protoss_Templar_Archives 1 11151
11151
