Protoss_Assimilator 1 2652
Protoss_Forge 1 3108
Protoss_Gateway 2 5513
Protoss_Photon_Cannon 3 10029
Protoss_Zealot 15 10049
Protoss_Cybernetics_Core 1 7175
Protoss_Citadel_of_Adun 1 8169
Protoss_Ground_Weapons_1 1 6941
Protoss_Templar_Archives 1 10761
10761
