Protoss_Forge 1 3263
Protoss_Photon_Cannon 3 10833
Protoss_Nexus 1 7004
Protoss_Gateway 4 9541
Protoss_Assimilator 2 7319
Protoss_Zealot 2 7811
Protoss_Cybernetics_Core 1 7403
Protoss_Citadel_of_Adun 1 8441
Protoss_Dragoon 1 8676
Protoss_Templar_Archives 1 9653
Protoss_Dark_Templar 2 10451
Protoss_High_Templar 2 10441
Protoss_Robotics_Facility 1 11863
11863
