Protoss_Forge 1 2990
Protoss_Nexus 1 6448
Protoss_Photon_Cannon 6 10418
Protoss_Gateway 3 11078
Protoss_Assimilator 2 8644
Protoss_Zealot 4 9236
Protoss_Cybernetics_Core 1 8483
Protoss_Stargate 1 9801
Protoss_Citadel_of_Adun 1 10183
Protoss_Corsair 2 10818
Protoss_Templar_Archives 1 11353
11353
