Protoss_Forge 2 10913
Protoss_Photon_Cannon 9 9699
Protoss_Nexus 1 6601
Protoss_Gateway 1 5823
Protoss_Assimilator 2 7330
Protoss_Zealot 2 7579
Protoss_Cybernetics_Core 1 7535
Protoss_Stargate 1 8853
Protoss_Robotics_Facility 1 9737
Protoss_Corsair 1 9749
Protoss_Robotics_Support_Bay 1 9875
Protoss_Reaver 1 11379
11379
