Protoss_Forge 2 4453
Protoss_Nexus 1 5729
Protoss_Gateway 3 11044
Protoss_Photon_Cannon 3 11109
Protoss_Assimilator 2 8255
Protoss_Zealot 5 10006
Protoss_Cybernetics_Core 1 6927
Protoss_Stargate 1 8351
Protoss_Dragoon 1 8129
Protoss_Corsair 3 10596
Protoss_Citadel_of_Adun 1 9831
Protoss_Templar_Archives 1 10821
11109
