Protoss_Gateway 3 11171
Protoss_Assimilator 1 3336
Protoss_Zealot 3 8586
Protoss_Cybernetics_Core 1 4827
Protoss_Stargate 1 6571
Protoss_Dragoon 2 8706
Protoss_Scout 1 8296
Protoss_Forge 1 7783
Protoss_Photon_Cannon 2 10379
Protoss_Nexus 1 12207
Protoss_Citadel_of_Adun 1 11123
12207
