Protoss_Forge 1 2962
Protoss_Photon_Cannon 3 6568
Protoss_Nexus 1 7288
Protoss_Gateway 2 9128
Protoss_Assimilator 2 8916
Protoss_Cybernetics_Core 1 7327
Protoss_Zealot 5 10605
Protoss_Dragoon 1 8086
Protoss_Citadel_of_Adun 1 8609
Protoss_Templar_Archives 1 10328
10605
