Protoss_Forge 1 4037
Protoss_Photon_Cannon 4 10353
Protoss_Nexus 1 6981
Protoss_Gateway 4 9849
Protoss_Assimilator 1 6082
Protoss_Zealot 10 10868
Protoss_Cybernetics_Core 1 7393
Protoss_Dragoon 1 8216
Protoss_Citadel_of_Adun 1 8902
10868
