Protoss_Gateway 2 9429
Protoss_Assimilator 1 3383
Protoss_Zealot 3 6693
Protoss_Cybernetics_Core 1 5194
Protoss_Stargate 1 6619
Protoss_Dragoon 1 6181
Protoss_Citadel_of_Adun 1 6837
Protoss_Corsair 1 7121
Protoss_Templar_Archives 1 7878
Protoss_Forge 1 7906
Protoss_Dark_Templar 1 8821
Protoss_Photon_Cannon 3 10777
Protoss_Nexus 1 11521
Protoss_High_Templar 2 10541
11521
