Protoss_Gateway 2 4083
Protoss_Zealot 8 10191
Protoss_Assimilator 1 5700
Protoss_Forge 1 6855
Protoss_Cybernetics_Core 1 7987
Protoss_Photon_Cannon 1 8238
Protoss_Dragoon 1 8771
Protoss_Citadel_of_Adun 1 9032
10191
