Protoss_Gateway 4 10638
Protoss_Forge 1 3576
Protoss_Zealot 11 10766
Protoss_Photon_Cannon 3 8483
Protoss_Nexus 1 7964
Protoss_Assimilator 2 9799
Protoss_Cybernetics_Core 1 7829
Protoss_Dragoon 1 8583
Protoss_Citadel_of_Adun 1 9776
10766
