Protoss_Forge 1 3875
Protoss_Nexus 1 6266
Protoss_Photon_Cannon 6 10717
Protoss_Gateway 1 6183
Protoss_Assimilator 2 7381
Protoss_Cybernetics_Core 1 7325
Protoss_Zealot 2 7621
Protoss_Stargate 2 11045
Protoss_Robotics_Facility 1 9485
Protoss_Corsair 3 10827
Protoss_Robotics_Support_Bay 1 9573
Protoss_Reaver 1 11381
11381
