Protoss_Forge 1 3036
Protoss_Nexus 1 6312
Protoss_Gateway 4 10665
Protoss_Photon_Cannon 4 11150
Protoss_Assimilator 2 7576
Protoss_Zealot 3 8465
Protoss_Cybernetics_Core 1 6946
Protoss_Dragoon 1 7779
Protoss_Stargate 1 8332
Protoss_Citadel_of_Adun 1 8590
Protoss_Corsair 2 9629
Protoss_Templar_Archives 1 9773
Protoss_Robotics_Facility 1 11643
Protoss_Dark_Templar 1 10937
11643
