Protoss_Forge 1 2997
Protoss_Photon_Cannon 8 11115
Protoss_Nexus 1 6611
Protoss_Gateway 2 9251
Protoss_Assimilator 2 7772
Protoss_Zealot 2 8465
Protoss_Cybernetics_Core 1 7113
Protoss_Stargate 1 8427
Protoss_Citadel_of_Adun 1 8746
Protoss_Corsair 3 10933
Protoss_Templar_Archives 1 9843
Protoss_High_Templar 2 10751
11115
