Protoss_Gateway 1 3131
Protoss_Assimilator 2 10220
Protoss_Zealot 3 4860
Protoss_Cybernetics_Core 1 5808
Protoss_Dragoon 1 6556
Protoss_Forge 1 6893
Protoss_Photon_Cannon 3 9789
Protoss_Nexus 1 10525
10525
