Protoss_Forge 1 2936
Protoss_Photon_Cannon 4 10608
Protoss_Nexus 1 7363
Protoss_Gateway 5 11410
Protoss_Assimilator 2 9063
Protoss_Cybernetics_Core 1 7421
Protoss_Zealot 8 10726
Protoss_Citadel_of_Adun 1 8670
Protoss_Dragoon 1 8578
Protoss_Templar_Archives 1 10376
Protoss_High_Templar 2 11131
11410
