Protoss_Gateway 2 8794
Protoss_Assimilator 1 3423
Protoss_Zealot 3 9076
Protoss_Cybernetics_Core 1 5359
Protoss_Dragoon 1 6111
Protoss_Stargate 1 6905
Protoss_Citadel_of_Adun 1 7499
Protoss_Corsair 1 7321
Protoss_Templar_Archives 1 8699
Protoss_Nexus 1 11428
Protoss_Dark_Templar 1 10346
11428
