Protoss_Gateway 3 7745
Protoss_Assimilator 1 3383
Protoss_Zealot 11 10091
Protoss_Cybernetics_Core 1 5213
Protoss_Dragoon 1 6201
Protoss_Citadel_of_Adun 1 7141
Protoss_Templar_Archives 1 8442
Protoss_Forge 1 9277
Protoss_High_Templar 4 10427
Protoss_Archon 1 9788
Protoss_Photon_Cannon 1 10553
Protoss_Nexus 1 12652
12652
