Protoss_Forge 1 3053
Protoss_Nexus 1 6261
Protoss_Gateway 5 11073
Protoss_Photon_Cannon 2 6474
Protoss_Assimilator 2 10791
Protoss_Zealot 10 10686
Protoss_Cybernetics_Core 1 7311
Protoss_Citadel_of_Adun 1 8475
Protoss_Templar_Archives 1 10471
11073
