Protoss_Gateway 2 3653
Protoss_Zealot 11 9796
Protoss_Assimilator 1 5752
Protoss_Cybernetics_Core 1 7657
Protoss_Stargate 1 8990
Protoss_Dragoon 1 8841
Protoss_Citadel_of_Adun 1 9566
Protoss_Corsair 1 9411
9796
