Protoss_Forge 1 3309
Protoss_Nexus 1 6035
Protoss_Photon_Cannon 6 11178
Protoss_Gateway 2 9599
Protoss_Assimilator 2 8936
Protoss_Cybernetics_Core 1 6736
Protoss_Zealot 3 9691
Protoss_Stargate 1 8124
Protoss_Citadel_of_Adun 1 8346
Protoss_Corsair 3 10187
Protoss_Templar_Archives 1 9501
Protoss_Dark_Templar 2 10707
11178
