Protoss_Forge 1 3145
Protoss_Nexus 1 6128
Protoss_Gateway 1 5653
Protoss_Photon_Cannon 2 6054
Protoss_Assimilator 1 6299
Protoss_Zealot 3 10221
Protoss_Cybernetics_Core 1 7216
10221
