Protoss_Assimilator 1 2691
Protoss_Forge 1 3187
Protoss_Photon_Cannon 3 9525
Protoss_Gateway 3 5894
Protoss_Zealot 13 9547
Protoss_Ground_Weapons_1 1 7021
Protoss_Nexus 2 11133
11133
