Protoss_Gateway 1 3051
Protoss_Zealot 11 9865
Protoss_Forge 1 4551
Protoss_Photon_Cannon 3 10259
Protoss_Nexus 1 9385
Protoss_Assimilator 2 9661
Protoss_Cybernetics_Core 1 9409
Protoss_Citadel_of_Adun 1 11081
Protoss_Dragoon 1 10895
11081
