Protoss_Forge 1 3427
Protoss_Nexus 1 6307
Protoss_Photon_Cannon 3 9714
Protoss_Gateway 1 5417
Protoss_Zealot 5 10521
Protoss_Assimilator 1 6329
Protoss_Cybernetics_Core 1 7843
Protoss_Stargate 1 9735
Protoss_Corsair 1 10151
Protoss_Citadel_of_Adun 1 10993
10993
