Protoss_Forge 1 2952
Protoss_Nexus 1 6238
Protoss_Photon_Cannon 3 10993
Protoss_Gateway 4 9871
Protoss_Assimilator 2 8800
Protoss_Zealot 13 10637
Protoss_Cybernetics_Core 1 7286
Protoss_Citadel_of_Adun 1 8342
Protoss_Dragoon 1 8151
Protoss_Templar_Archives 1 10539
10993
