Protoss_Gateway 2 8493
Protoss_Assimilator 1 3468
Protoss_Zealot 8 10646
Protoss_Cybernetics_Core 1 5253
Protoss_Stargate 1 6788
Protoss_Dragoon 1 6716
Protoss_Citadel_of_Adun 1 7671
Protoss_Corsair 1 7211
Protoss_Templar_Archives 1 9219
Protoss_Nexus 1 11590
Protoss_Dark_Templar 1 10276
Protoss_Forge 1 10583
11590
