Protoss_Forge 1 3645
Protoss_Nexus 1 6203
Protoss_Photon_Cannon 4 11148
Protoss_Gateway 3 10605
Protoss_Assimilator 2 8270
Protoss_Zealot 2 10407
Protoss_Cybernetics_Core 1 7801
Protoss_Dragoon 1 8573
Protoss_Stargate 1 9254
Protoss_Citadel_of_Adun 1 9290
Protoss_Corsair 1 9665
Protoss_Templar_Archives 1 10432
11148
