Protoss_Forge 1 3107
Protoss_Photon_Cannon 3 11117
Protoss_Nexus 1 6477
Protoss_Gateway 3 10455
Protoss_Assimilator 2 6893
Protoss_Zealot 5 10513
Protoss_Cybernetics_Core 1 8247
Protoss_Citadel_of_Adun 1 9256
Protoss_Templar_Archives 1 11115
11117
