Protoss_Gateway 2 3863
Protoss_Zealot 14 10071
Protoss_Assimilator 1 6107
Protoss_Cybernetics_Core 1 7055
Protoss_Citadel_of_Adun 1 8053
Protoss_Dragoon 1 7966
Protoss_Nexus 1 11268
Protoss_Templar_Archives 1 10033
Protoss_Forge 1 10388
Protoss_High_Templar 2 10961
11268
