Protoss_Gateway 1 3217
Protoss_Zealot 5 8475
Protoss_Forge 1 4039
Protoss_Photon_Cannon 5 11184
Protoss_Nexus 1 8160
Protoss_Assimilator 2 8033
Protoss_Cybernetics_Core 1 7692
Protoss_Stargate 1 9453
Protoss_Robotics_Facility 1 10343
Protoss_Corsair 2 10705
Protoss_Dragoon 1 10185
Protoss_Robotics_Support_Bay 1 10575
11184
