Protoss_Gateway 2 3715
Protoss_Zealot 13 7809
Protoss_Nexus 1 10413
Protoss_Assimilator 1 8962
Protoss_Forge 1 9237
Protoss_Cybernetics_Core 1 10187
Protoss_Photon_Cannon 2 10762
Protoss_Stargate 1 11505
11505
