Protoss_Forge 1 2971
Protoss_Photon_Cannon 4 10661
Protoss_Gateway 4 11361
Protoss_Nexus 1 7487
Protoss_Zealot 7 10753
Protoss_Assimilator 2 8678
Protoss_Cybernetics_Core 1 7301
Protoss_Citadel_of_Adun 1 8404
Protoss_Dragoon 1 8835
Protoss_Templar_Archives 1 10368
11361
