Protoss_Forge 1 3490
Protoss_Nexus 1 6307
Protoss_Photon_Cannon 5 11160
Protoss_Gateway 1 5467
Protoss_Assimilator 2 6833
Protoss_Zealot 6 10435
Protoss_Cybernetics_Core 2 10321
Protoss_Stargate 1 8528
Protoss_Dragoon 1 8275
Protoss_Citadel_of_Adun 1 8880
11160
