Protoss_Forge 1 2851
Protoss_Photon_Cannon 6 10067
Protoss_Nexus 1 7058
Protoss_Gateway 4 9846
Protoss_Assimilator 1 6451
Protoss_Cybernetics_Core 1 7718
Protoss_Zealot 13 10957
Protoss_Citadel_of_Adun 1 8852
Protoss_Dragoon 1 9005
Protoss_Templar_Archives 1 11190
11190
