Protoss_Gateway 4 10194
Protoss_Zealot 6 10646
Protoss_Assimilator 1 4208
Protoss_Cybernetics_Core 1 5488
Protoss_Stargate 1 6895
Protoss_Corsair 1 7391
Protoss_Dragoon 1 7706
Protoss_Robotics_Facility 1 8698
Protoss_Citadel_of_Adun 1 9009
Protoss_Observatory 1 8805
Protoss_Templar_Archives 1 10041
Protoss_Shuttle 1 11076
Protoss_Observer 1 10818
Protoss_Dark_Templar 1 11151
11151
