Protoss_Nexus 1 5643
Protoss_Gateway 4 9211
Protoss_Forge 1 4785
Protoss_Photon_Cannon 2 5777
Protoss_Zealot 14 10955
Protoss_Assimilator 2 6736
Protoss_Cybernetics_Core 1 7734
Protoss_Citadel_of_Adun 1 8953
Protoss_Templar_Archives 1 10819
10955
