Protoss_Nexus 1 5563
Protoss_Forge 1 4105
Protoss_Gateway 5 8453
Protoss_Photon_Cannon 1 5428
Protoss_Assimilator 2 9346
Protoss_Zealot 14 10283
Protoss_Cybernetics_Core 1 6761
Protoss_Citadel_of_Adun 1 7747
Protoss_Templar_Archives 1 10686
Protoss_Ground_Weapons_1 1 9697
10686
