Protoss_Forge 1 3233
Protoss_Nexus 1 6255
Protoss_Photon_Cannon 2 5524
Protoss_Gateway 5 10960
Protoss_Assimilator 1 5727
Protoss_Cybernetics_Core 1 7211
Protoss_Zealot 12 10953
Protoss_Citadel_of_Adun 1 8445
Protoss_Dragoon 1 8253
Protoss_Templar_Archives 1 11277
11277
