Protoss_Forge 1 3473
Protoss_Nexus 1 5983
Protoss_Photon_Cannon 3 6027
Protoss_Gateway 3 11166
Protoss_Assimilator 3 9820
Protoss_Zealot 5 10285
Protoss_Cybernetics_Core 1 9658
Protoss_Citadel_of_Adun 1 10704
11166
