Protoss_Forge 1 3350
Protoss_Photon_Cannon 4 9687
Protoss_Nexus 1 6579
Protoss_Gateway 1 6085
Protoss_Assimilator 2 7342
Protoss_Cybernetics_Core 1 7162
Protoss_Zealot 4 9975
Protoss_Dragoon 1 7899
Protoss_Stargate 1 8600
Protoss_Robotics_Facility 1 9345
Protoss_Corsair 2 10239
Protoss_Citadel_of_Adun 1 10123
Protoss_Shuttle 1 10221
Protoss_Robotics_Support_Bay 1 9742
Protoss_Templar_Archives 1 11172
11172
