Protoss_Nexus 1 5633
Protoss_Forge 1 4061
Protoss_Photon_Cannon 2 5099
Protoss_Gateway 1 5827
Protoss_Zealot 3 8605
Protoss_Assimilator 2 7658
Protoss_Cybernetics_Core 1 7842
8605
