Protoss_Gateway 2 3904
Protoss_Zealot 13 10601
Protoss_Assimilator 1 6523
Protoss_Cybernetics_Core 1 7871
Protoss_Forge 1 8417
Protoss_Stargate 1 9436
Protoss_Citadel_of_Adun 1 9645
Protoss_Corsair 2 10856
10856
