Protoss_Gateway 3 10440
Protoss_Assimilator 1 3259
Protoss_Zealot 5 6691
Protoss_Cybernetics_Core 1 5329
Protoss_Stargate 1 6934
Protoss_Dragoon 7 11183
Protoss_Corsair 1 7539
11183
