Protoss_Nexus 1 5628
Protoss_Forge 1 4031
Protoss_Photon_Cannon 8 11003
Protoss_Gateway 4 9370
Protoss_Assimilator 2 7523
Protoss_Cybernetics_Core 1 7774
Protoss_Citadel_of_Adun 1 8759
Protoss_Dragoon 1 8577
Protoss_Zealot 1 9197
Protoss_Templar_Archives 1 9862
Protoss_High_Templar 4 10655
11003
