Protoss_Gateway 1 3383
Protoss_Assimilator 1 3559
Protoss_Zealot 3 5638
Protoss_Cybernetics_Core 1 5264
Protoss_Stargate 1 6538
Protoss_Robotics_Facility 1 7801
Protoss_Scout 1 8166
Protoss_Dragoon 3 10931
Protoss_Shuttle 1 8711
Protoss_Robotics_Support_Bay 1 8278
Protoss_Reaver 2 11316
11316
