Protoss_Gateway 2 3893
Protoss_Zealot 14 10186
Protoss_Assimilator 1 6804
Protoss_Forge 1 7420
Protoss_Photon_Cannon 1 9568
Protoss_Cybernetics_Core 1 10223
Protoss_Citadel_of_Adun 1 11296
11296
