Protoss_Nexus 1 5659
Protoss_Gateway 3 10473
Protoss_Assimilator 2 8198
Protoss_Forge 1 5046
Protoss_Zealot 4 8509
Protoss_Photon_Cannon 2 8171
Protoss_Cybernetics_Core 1 6895
Protoss_Citadel_of_Adun 1 8142
Protoss_Templar_Archives 1 9215
Protoss_Dark_Templar 2 10023
Protoss_High_Templar 2 10775
10775
