Protoss_Forge 1 2879
Protoss_Photon_Cannon 4 10819
Protoss_Nexus 1 6961
Protoss_Gateway 1 5879
Protoss_Assimilator 2 7807
Protoss_Zealot 2 9665
Protoss_Cybernetics_Core 1 7147
Protoss_Stargate 1 8670
Protoss_Dragoon 1 8711
Protoss_Robotics_Facility 1 9972
Protoss_Corsair 1 9117
Protoss_Shuttle 1 10775
Protoss_Robotics_Support_Bay 1 10142
10819
