Protoss_Forge 1 3277
Protoss_Photon_Cannon 6 7534
Protoss_Nexus 1 7648
Protoss_Gateway 2 10708
Protoss_Assimilator 2 8886
Protoss_Zealot 2 9717
Protoss_Cybernetics_Core 1 8163
Protoss_Stargate 1 9408
Protoss_Citadel_of_Adun 1 9627
Protoss_Corsair 2 10419
Protoss_Templar_Archives 1 10664
10708
