Protoss_Gateway 4 9752
Protoss_Zealot 15 10941
Protoss_Forge 1 5954
Protoss_Photon_Cannon 1 7421
Protoss_Nexus 1 9973
Protoss_Assimilator 1 8568
Protoss_Cybernetics_Core 1 10118
Protoss_Citadel_of_Adun 1 11139
11139
