Protoss_Forge 1 2994
Protoss_Photon_Cannon 3 5974
Protoss_Nexus 1 6958
Protoss_Gateway 3 10775
Protoss_Assimilator 2 8108
Protoss_Zealot 5 10776
Protoss_Cybernetics_Core 1 7790
Protoss_Stargate 1 9120
Protoss_Citadel_of_Adun 1 9792
Protoss_Corsair 2 10576
Protoss_Templar_Archives 1 10915
10915
