Protoss_Forge 1 3056
Protoss_Nexus 1 6140
Protoss_Photon_Cannon 2 5080
Protoss_Gateway 1 5641
Protoss_Assimilator 2 8725
Protoss_Zealot 3 9165
Protoss_Cybernetics_Core 1 7350
Protoss_Stargate 1 8657
Protoss_Robotics_Facility 1 9325
Protoss_Corsair 1 9107
Protoss_Shuttle 1 10141
Protoss_Robotics_Support_Bay 1 9559
Protoss_Reaver 1 11297
Protoss_Citadel_of_Adun 1 11397
11397
