Protoss_Gateway 2 11095
Protoss_Zealot 9 10051
Protoss_Assimilator 1 4049
Protoss_Forge 1 5364
Protoss_Cybernetics_Core 1 7473
Protoss_Citadel_of_Adun 1 8734
Protoss_Photon_Cannon 5 10415
Protoss_Templar_Archives 1 9878
Protoss_Ground_Weapons_1 1 9083
Protoss_Robotics_Facility 1 11793
Protoss_Dark_Templar 1 11175
11793
