Protoss_Forge 1 3172
Protoss_Nexus 1 6105
Protoss_Photon_Cannon 6 11087
Protoss_Gateway 1 5898
Protoss_Zealot 2 9437
Protoss_Assimilator 2 8955
Protoss_Cybernetics_Core 1 8771
Protoss_Stargate 1 10108
Protoss_Robotics_Facility 1 10971
Protoss_Corsair 1 10533
11087
