Protoss_Gateway 2 3775
Protoss_Zealot 10 10355
Protoss_Shield_Battery 1 5168
Protoss_Nexus 1 9341
Protoss_Forge 1 7909
Protoss_Assimilator 1 8217
Protoss_Photon_Cannon 2 9588
10355
