Protoss_Forge 1 3257
Protoss_Photon_Cannon 5 11026
Protoss_Nexus 1 7361
Protoss_Gateway 4 11293
Protoss_Assimilator 2 7273
Protoss_Cybernetics_Core 1 7386
Protoss_Zealot 3 9143
Protoss_Stargate 1 8634
Protoss_Dragoon 1 8157
Protoss_Citadel_of_Adun 1 8758
Protoss_Corsair 1 9053
Protoss_Templar_Archives 1 9805
Protoss_Dark_Templar 1 10543
Protoss_High_Templar 1 11183
11293
