Protoss_Nexus 1 5719
Protoss_Forge 1 4191
Protoss_Gateway 2 9183
Protoss_Assimilator 2 7064
Protoss_Photon_Cannon 2 10820
Protoss_Zealot 3 7518
Protoss_Cybernetics_Core 1 7183
Protoss_Stargate 1 8456
Protoss_Dragoon 1 8360
Protoss_Citadel_of_Adun 1 8633
Protoss_Corsair 3 10321
Protoss_Templar_Archives 1 9674
Protoss_Robotics_Facility 1 10241
Protoss_Dark_Templar 2 10667
10820
