Protoss_Forge 1 3253
Protoss_Photon_Cannon 6 10500
Protoss_Nexus 1 6794
Protoss_Gateway 3 11303
Protoss_Assimilator 2 7854
Protoss_Cybernetics_Core 1 7191
Protoss_Zealot 6 10749
Protoss_Stargate 2 9061
Protoss_Citadel_of_Adun 1 9314
Protoss_Corsair 2 10437
Protoss_Templar_Archives 1 10402
11303
