Protoss_Forge 1 2977
Protoss_Photon_Cannon 3 6462
Protoss_Nexus 1 7469
Protoss_Gateway 3 9520
Protoss_Zealot 11 10937
Protoss_Cybernetics_Core 1 7339
Protoss_Assimilator 2 9161
Protoss_Citadel_of_Adun 1 8744
Protoss_Templar_Archives 1 11203
11203
