Protoss_Nexus 1 6037
Protoss_Forge 1 4812
Protoss_Photon_Cannon 8 10904
Protoss_Gateway 1 6475
Protoss_Assimilator 2 8371
Protoss_Cybernetics_Core 1 7690
Protoss_Zealot 2 9465
Protoss_Stargate 1 9214
Protoss_Dragoon 2 9975
Protoss_Citadel_of_Adun 1 9568
Protoss_Corsair 2 10387
Protoss_Templar_Archives 1 10682
10904
