Protoss_Forge 1 2899
Protoss_Photon_Cannon 4 11111
Protoss_Nexus 1 6881
Protoss_Gateway 2 9777
Protoss_Assimilator 2 7454
Protoss_Zealot 5 9224
Protoss_Cybernetics_Core 1 7279
Protoss_Stargate 1 8572
Protoss_Citadel_of_Adun 1 8914
Protoss_Corsair 2 9645
Protoss_Templar_Archives 1 9964
Protoss_Robotics_Facility 1 11215
Protoss_Dark_Templar 2 10727
11215
