Protoss_Forge 1 3173
Protoss_Photon_Cannon 2 5810
Protoss_Nexus 2 12769
Protoss_Gateway 2 8838
Protoss_Assimilator 2 7047
Protoss_Zealot 2 7329
Protoss_Cybernetics_Core 1 7233
Protoss_Stargate 1 8471
Protoss_Citadel_of_Adun 1 8509
Protoss_Corsair 4 10794
Protoss_Templar_Archives 1 9505
Protoss_Dark_Templar 2 10447
12769
