Protoss_Gateway 2 9840
Protoss_Zealot 8 9956
Protoss_Assimilator 1 5938
Protoss_Cybernetics_Core 1 6728
Protoss_Stargate 1 8308
Protoss_Citadel_of_Adun 1 9047
Protoss_Corsair 1 8726
Protoss_Forge 1 9580
Protoss_Templar_Archives 1 10235
Protoss_Photon_Cannon 1 10748
Protoss_Dark_Templar 2 11051
11051
