Protoss_Gateway 2 3831
Protoss_Zealot 8 6161
Protoss_Assimilator 1 5791
Protoss_Cybernetics_Core 1 7057
Protoss_Stargate 1 8327
Protoss_Corsair 1 8737
Protoss_Nexus 1 11033
Protoss_Forge 1 9453
Protoss_Citadel_of_Adun 1 10636
Protoss_Photon_Cannon 1 11135
11135
