Protoss_Forge 1 2933
Protoss_Nexus 1 6392
Protoss_Gateway 1 5270
Protoss_Photon_Cannon 8 9814
Protoss_Assimilator 2 7154
Protoss_Zealot 3 8833
Protoss_Cybernetics_Core 1 6983
Protoss_Stargate 1 8238
Protoss_Robotics_Facility 1 9271
Protoss_Corsair 2 10571
Protoss_Robotics_Support_Bay 1 9464
Protoss_Shuttle 1 10285
Protoss_Reaver 1 11427
Protoss_Citadel_of_Adun 1 11213
11427
