Protoss_Forge 1 3022
Protoss_Photon_Cannon 2 4899
Protoss_Nexus 1 6915
Protoss_Gateway 2 9465
Protoss_Assimilator 2 7899
Protoss_Cybernetics_Core 1 6857
Protoss_Zealot 3 8359
Protoss_Stargate 1 8172
Protoss_Citadel_of_Adun 1 8601
Protoss_Corsair 3 10771
Protoss_Templar_Archives 1 9623
Protoss_Robotics_Facility 1 10320
Protoss_Dark_Templar 2 10497
Protoss_Shuttle 1 11167
11167
