Protoss_Forge 1 3041
Protoss_Photon_Cannon 6 10904
Protoss_Nexus 1 6981
Protoss_Gateway 3 10615
Protoss_Assimilator 2 8139
Protoss_Zealot 3 7999
Protoss_Cybernetics_Core 1 7181
Protoss_Stargate 1 8516
Protoss_Citadel_of_Adun 1 8724
Protoss_Corsair 2 10475
Protoss_Templar_Archives 1 10099
Protoss_High_Templar 1 11023
Protoss_Dark_Templar 1 11067
11067
