Protoss_Forge 1 3156
Protoss_Photon_Cannon 12 10535
Protoss_Nexus 1 8225
Protoss_Gateway 1 7067
Protoss_Zealot 2 9949
Protoss_Assimilator 2 9122
Protoss_Cybernetics_Core 1 9783
Protoss_Stargate 1 11658
11658
