Protoss_Gateway 3 10945
Protoss_Assimilator 1 3378
Protoss_Zealot 9 10791
Protoss_Cybernetics_Core 1 5178
Protoss_Stargate 1 6743
Protoss_Dragoon 1 6595
Protoss_Forge 1 6964
Protoss_Corsair 1 7481
Protoss_Photon_Cannon 2 10361
Protoss_Nexus 1 10841
Protoss_Citadel_of_Adun 1 9970
10945
