Protoss_Gateway 3 11186
Protoss_Zealot 10 7265
Protoss_Nexus 1 9805
Protoss_Forge 1 8134
Protoss_Photon_Cannon 3 10883
Protoss_Cybernetics_Core 1 10355
Protoss_Assimilator 1 9991
11186
