Protoss_Forge 3 4852
Protoss_Nexus 1 6019
Protoss_Gateway 3 10454
Protoss_Photon_Cannon 2 11197
Protoss_Assimilator 2 7802
Protoss_Zealot 6 10451
Protoss_Cybernetics_Core 1 7869
Protoss_Stargate 1 9141
Protoss_Dragoon 1 8759
Protoss_Citadel_of_Adun 1 9218
Protoss_Corsair 1 9549
Protoss_Templar_Archives 1 10583
11197
