Protoss_Forge 1 3097
Protoss_Nexus 1 6124
Protoss_Photon_Cannon 2 5096
Protoss_Gateway 3 9384
Protoss_Assimilator 2 7312
Protoss_Zealot 6 9885
Protoss_Cybernetics_Core 1 7313
Protoss_Dragoon 1 8113
Protoss_Citadel_of_Adun 1 8533
Protoss_Templar_Archives 1 10155
Protoss_Robotics_Facility 1 11254
Protoss_Dark_Templar 2 10903
Protoss_High_Templar 2 10969
11254
