Protoss_Nexus 1 5737
Protoss_Gateway 5 11399
Protoss_Forge 1 4921
Protoss_Assimilator 2 7522
Protoss_Zealot 6 10705
Protoss_Photon_Cannon 1 5931
Protoss_Cybernetics_Core 1 7251
Protoss_Stargate 1 8507
Protoss_Citadel_of_Adun 1 8622
Protoss_Corsair 3 10535
Protoss_Templar_Archives 1 9671
Protoss_Dark_Templar 1 10921
11399
