Protoss_Gateway 5 10332
Protoss_Nexus 1 5881
Protoss_Forge 1 4423
Protoss_Photon_Cannon 2 10440
Protoss_Assimilator 1 6326
Protoss_Cybernetics_Core 1 7176
Protoss_Zealot 8 10111
Protoss_Stargate 1 8593
Protoss_Dragoon 1 9031
Protoss_Corsair 1 9136
Protoss_Citadel_of_Adun 1 10007
10440
