Protoss_Forge 1 3153
Protoss_Nexus 1 6318
Protoss_Gateway 3 10231
Protoss_Photon_Cannon 2 5873
Protoss_Zealot 9 10791
Protoss_Assimilator 2 7828
Protoss_Cybernetics_Core 1 8033
Protoss_Stargate 1 9370
Protoss_Citadel_of_Adun 1 9239
Protoss_Corsair 1 9847
Protoss_Templar_Archives 1 11171
11171
