Protoss_Gateway 3 10729
Protoss_Assimilator 1 3143
Protoss_Zealot 9 10619
Protoss_Cybernetics_Core 1 4849
Protoss_Stargate 1 6403
Protoss_Corsair 2 7433
Protoss_Citadel_of_Adun 1 8365
Protoss_Templar_Archives 1 9513
Protoss_Forge 1 9693
10729
