Protoss_Nexus 1 5718
Protoss_Gateway 4 10714
Protoss_Forge 1 4758
Protoss_Assimilator 2 6841
Protoss_Photon_Cannon 3 10788
Protoss_Zealot 8 10793
Protoss_Cybernetics_Core 1 7213
Protoss_Stargate 1 8455
Protoss_Citadel_of_Adun 1 8297
Protoss_Templar_Archives 1 9301
Protoss_Corsair 1 8945
Protoss_Robotics_Facility 1 10767
Protoss_Dark_Templar 2 10217
10793
