Protoss_Forge 1 3427
Protoss_Nexus 1 6372
Protoss_Gateway 2 10225
Protoss_Photon_Cannon 4 10915
Protoss_Assimilator 2 8503
Protoss_Zealot 3 9039
Protoss_Cybernetics_Core 1 7791
Protoss_Stargate 1 9055
Protoss_Citadel_of_Adun 1 9263
Protoss_Corsair 2 10279
Protoss_Templar_Archives 1 10279
Protoss_Dark_Templar 2 11089
11089
