Protoss_Forge 1 3459
Protoss_Nexus 1 6444
Protoss_Photon_Cannon 4 10876
Protoss_Gateway 3 10583
Protoss_Zealot 5 9191
Protoss_Assimilator 2 8926
Protoss_Cybernetics_Core 1 8121
Protoss_Citadel_of_Adun 1 9271
Protoss_Templar_Archives 1 10333
Protoss_Dark_Templar 1 11139
11139
