Protoss_Forge 1 3154
Protoss_Nexus 1 6103
Protoss_Photon_Cannon 6 10017
Protoss_Gateway 1 5835
Protoss_Assimilator 2 7275
Protoss_Cybernetics_Core 1 7298
Protoss_Zealot 4 9715
Protoss_Stargate 1 8691
Protoss_Robotics_Facility 1 9319
Protoss_Dragoon 1 9105
Protoss_Corsair 2 9999
Protoss_Shuttle 1 10933
Protoss_Robotics_Support_Bay 1 10277
10933
