Protoss_Forge 1 3690
Protoss_Nexus 1 6111
Protoss_Photon_Cannon 2 9515
Protoss_Gateway 4 10109
Protoss_Assimilator 2 10317
Protoss_Zealot 16 10821
Protoss_Cybernetics_Core 1 7939
Protoss_Dragoon 1 8975
Protoss_Citadel_of_Adun 1 9275
Protoss_Templar_Archives 1 10460
10821
