Protoss_Nexus 1 5796
Protoss_Gateway 1 4721
Protoss_Forge 1 4935
Protoss_Zealot 3 8825
Protoss_Photon_Cannon 6 10693
Protoss_Assimilator 2 7790
Protoss_Cybernetics_Core 1 7535
Protoss_Stargate 1 8793
Protoss_Citadel_of_Adun 1 9076
Protoss_Corsair 3 10587
Protoss_Templar_Archives 1 10143
Protoss_Dark_Templar 1 10953
10953
