Protoss_Forge 1 3185
Protoss_Photon_Cannon 3 10352
Protoss_Nexus 1 6633
Protoss_Gateway 5 11375
Protoss_Assimilator 2 7043
Protoss_Cybernetics_Core 1 7105
Protoss_Zealot 3 10359
Protoss_Stargate 1 8331
Protoss_Citadel_of_Adun 1 8261
Protoss_Dragoon 1 8211
Protoss_Corsair 1 8757
Protoss_Templar_Archives 1 9597
Protoss_Robotics_Facility 1 10686
Protoss_High_Templar 3 11187
11375
