Protoss_Forge 1 2805
Protoss_Nexus 1 6189
Protoss_Gateway 3 10090
Protoss_Zealot 11 10677
Protoss_Photon_Cannon 4 8199
Protoss_Assimilator 2 9226
Protoss_Cybernetics_Core 1 8552
Protoss_Citadel_of_Adun 1 9744
Protoss_Templar_Archives 1 11200
11200
