Protoss_Forge 1 3141
Protoss_Gateway 2 11325
Protoss_Photon_Cannon 2 10820
Protoss_Zealot 6 10131
Protoss_Nexus 1 7548
Protoss_Assimilator 2 6825
Protoss_Cybernetics_Core 1 6897
Protoss_Stargate 1 8445
Protoss_Citadel_of_Adun 1 8451
Protoss_Corsair 4 10755
Protoss_Templar_Archives 1 10349
Protoss_Dark_Templar 1 11109
11325
