Protoss_Forge 1 3246
Protoss_Photon_Cannon 2 5183
Protoss_Nexus 1 6609
Protoss_Gateway 6 9618
Protoss_Assimilator 2 10342
Protoss_Cybernetics_Core 1 7331
Protoss_Zealot 14 10801
Protoss_Dragoon 1 8399
Protoss_Citadel_of_Adun 1 8672
10801
