Protoss_Forge 1 2952
Protoss_Photon_Cannon 3 11073
Protoss_Nexus 1 7076
Protoss_Gateway 3 10016
Protoss_Assimilator 2 7672
Protoss_Cybernetics_Core 1 6985
Protoss_Zealot 8 10565
Protoss_Stargate 1 8645
Protoss_Citadel_of_Adun 1 9242
Protoss_Corsair 1 9217
Protoss_Templar_Archives 1 10845
11073
