Protoss_Nexus 1 5948
Protoss_Forge 1 4453
Protoss_Photon_Cannon 6 11046
Protoss_Gateway 1 6130
Protoss_Assimilator 2 7478
Protoss_Zealot 2 7248
Protoss_Cybernetics_Core 1 7383
Protoss_Stargate 1 8717
Protoss_Robotics_Facility 2 10673
Protoss_Corsair 1 9276
Protoss_Shuttle 1 10961
Protoss_Robotics_Support_Bay 1 10421
11046
