Protoss_Gateway 1 3447
Protoss_Zealot 11 10643
Protoss_Nexus 1 7616
Protoss_Assimilator 2 10895
Protoss_Forge 1 6861
Protoss_Cybernetics_Core 1 7786
Protoss_Photon_Cannon 3 9894
Protoss_Stargate 1 9483
Protoss_Citadel_of_Adun 1 10284
Protoss_Corsair 1 9913
10895
