Protoss_Forge 1 2853
Protoss_Photon_Cannon 4 10841
Protoss_Nexus 1 6894
Protoss_Gateway 1 5980
Protoss_Assimilator 2 9294
Protoss_Zealot 4 9675
Protoss_Cybernetics_Core 1 8845
Protoss_Stargate 1 10251
Protoss_Citadel_of_Adun 1 10465
Protoss_Corsair 1 10707
10841
