Protoss_Forge 1 3417
Protoss_Photon_Cannon 2 4607
Protoss_Nexus 1 6875
Protoss_Gateway 6 9476
Protoss_Assimilator 2 7521
Protoss_Cybernetics_Core 1 6836
Protoss_Zealot 13 10865
Protoss_Dragoon 1 7631
Protoss_Citadel_of_Adun 1 8465
Protoss_Stargate 1 9204
Protoss_Templar_Archives 1 10698
10865
