Protoss_Forge 1 3332
Protoss_Nexus 1 6155
Protoss_Photon_Cannon 2 5085
Protoss_Gateway 4 10613
Protoss_Assimilator 2 10240
Protoss_Zealot 9 10939
Protoss_Cybernetics_Core 1 8365
Protoss_Dragoon 1 9141
Protoss_Citadel_of_Adun 1 9482
Protoss_Templar_Archives 1 10963
10963
