Protoss_Forge 1 3085
Protoss_Photon_Cannon 6 11140
Protoss_Nexus 1 7453
Protoss_Gateway 1 6363
Protoss_Zealot 5 10245
Protoss_Assimilator 2 8171
Protoss_Cybernetics_Core 1 8971
Protoss_Stargate 1 10238
Protoss_Robotics_Facility 1 11077
Protoss_Corsair 1 10727
11140
