Protoss_Forge 1 3252
Protoss_Photon_Cannon 2 4783
Protoss_Nexus 1 7384
Protoss_Gateway 1 6089
Protoss_Assimilator 2 8013
Protoss_Cybernetics_Core 1 7257
Protoss_Zealot 3 8546
Protoss_Stargate 1 8543
Protoss_Robotics_Facility 1 9672
Protoss_Corsair 4 10875
Protoss_Robotics_Support_Bay 1 9866
Protoss_Shuttle 1 10771
Protoss_Citadel_of_Adun 1 11278
11278
