Protoss_Nexus 1 5753
Protoss_Forge 1 4237
Protoss_Photon_Cannon 7 10582
Protoss_Gateway 1 6913
Protoss_Assimilator 2 10839
Protoss_Cybernetics_Core 1 8427
Protoss_Zealot 4 9905
Protoss_Stargate 2 9806
Protoss_Corsair 4 10891
10891
