Protoss_Forge 1 3321
Protoss_Photon_Cannon 2 4919
Protoss_Nexus 1 6915
Protoss_Gateway 1 5752
Protoss_Assimilator 2 7074
Protoss_Cybernetics_Core 1 6792
Protoss_Zealot 3 9847
Protoss_Stargate 1 8161
Protoss_Corsair 1 8575
Protoss_Citadel_of_Adun 1 9119
9847
