Protoss_Forge 2 4619
Protoss_Nexus 1 6119
Protoss_Gateway 3 9093
Protoss_Photon_Cannon 2 10353
Protoss_Assimilator 2 7175
Protoss_Zealot 3 8097
Protoss_Cybernetics_Core 1 7458
Protoss_Citadel_of_Adun 1 8638
10353
