Protoss_Forge 1 3383
Protoss_Photon_Cannon 3 9223
Protoss_Nexus 1 6637
Protoss_Gateway 1 5798
Protoss_Assimilator 2 6842
Protoss_Cybernetics_Core 1 6841
Protoss_Zealot 1 7013
Protoss_Stargate 1 8088
Protoss_Robotics_Facility 1 8891
Protoss_Corsair 4 10859
Protoss_Shuttle 1 9785
Protoss_Robotics_Support_Bay 1 9109
Protoss_Reaver 1 11075
11075
