Protoss_Forge 1 3203
Protoss_Photon_Cannon 2 7342
Protoss_Nexus 1 6773
Protoss_Gateway 2 10053
Protoss_Assimilator 2 7373
Protoss_Zealot 4 9289
Protoss_Cybernetics_Core 1 7153
Protoss_Stargate 1 8546
Protoss_Dragoon 1 8093
Protoss_Citadel_of_Adun 1 8915
Protoss_Corsair 3 10245
Protoss_Templar_Archives 1 9901
Protoss_Dark_Templar 2 10881
Protoss_Robotics_Facility 1 11490
11490
