Protoss_Forge 1 3217
Protoss_Photon_Cannon 2 5425
Protoss_Nexus 1 6705
Protoss_Gateway 1 6190
Protoss_Assimilator 2 7112
Protoss_Zealot 4 8985
Protoss_Cybernetics_Core 1 7269
Protoss_Stargate 1 8635
Protoss_Robotics_Facility 1 9209
Protoss_Corsair 3 10605
Protoss_Shuttle 1 10051
Protoss_Robotics_Support_Bay 1 9400
Protoss_Reaver 1 11193
11193
