Protoss_Forge 3 10514
Protoss_Photon_Cannon 4 7021
Protoss_Nexus 1 7294
Protoss_Gateway 1 6449
Protoss_Assimilator 2 8477
Protoss_Cybernetics_Core 1 8005
Protoss_Zealot 4 10433
Protoss_Stargate 1 9619
Protoss_Citadel_of_Adun 2 11086
Protoss_Dragoon 1 9897
Protoss_Corsair 1 10461
11086
