Protoss_Forge 1 3181
Protoss_Photon_Cannon 2 4311
Protoss_Nexus 1 7373
Protoss_Gateway 2 10349
Protoss_Assimilator 2 8469
Protoss_Zealot 5 10123
Protoss_Cybernetics_Core 1 7417
Protoss_Stargate 1 8684
Protoss_Citadel_of_Adun 1 9119
10349
