Protoss_Forge 1 3153
Protoss_Photon_Cannon 3 6540
Protoss_Gateway 2 6901
Protoss_Nexus 1 7537
Protoss_Assimilator 3 7938
Protoss_Cybernetics_Core 1 7941
Protoss_Zealot 2 9689
Protoss_Stargate 1 9203
Protoss_Dragoon 1 8861
Protoss_Robotics_Facility 1 10425
Protoss_Corsair 3 10923
Protoss_Shuttle 1 11243
11243
