Protoss_Nexus 1 5839
Protoss_Forge 1 4407
Protoss_Gateway 1 5859
Protoss_Photon_Cannon 2 10138
Protoss_Assimilator 2 6945
Protoss_Zealot 5 10415
Protoss_Cybernetics_Core 1 7675
Protoss_Stargate 1 8922
Protoss_Citadel_of_Adun 1 9140
Protoss_Dragoon 1 9537
Protoss_Corsair 1 9335
Protoss_Templar_Archives 1 10301
Protoss_Dark_Templar 1 11107
11107
