Protoss_Forge 1 3195
Protoss_Photon_Cannon 3 10910
Protoss_Nexus 1 6649
Protoss_Gateway 4 10355
Protoss_Assimilator 2 7520
Protoss_Cybernetics_Core 1 7148
Protoss_Zealot 2 8055
Protoss_Stargate 1 8477
Protoss_Citadel_of_Adun 1 8879
Protoss_Corsair 1 8897
Protoss_Templar_Archives 1 9889
Protoss_Dark_Templar 1 10649
Protoss_High_Templar 2 10813
10910
