Protoss_Forge 1 3146
Protoss_Photon_Cannon 3 10142
Protoss_Nexus 1 6909
Protoss_Gateway 4 11368
Protoss_Assimilator 2 7066
Protoss_Cybernetics_Core 1 7050
Protoss_Stargate 1 8427
Protoss_Zealot 2 8635
Protoss_Citadel_of_Adun 1 8710
Protoss_Corsair 3 10081
Protoss_Templar_Archives 1 9706
Protoss_Dark_Templar 2 10529
11368
