Protoss_Nexus 2 12663
Protoss_Forge 1 4299
Protoss_Gateway 3 9840
Protoss_Assimilator 2 6845
Protoss_Photon_Cannon 2 8739
Protoss_Zealot 6 10025
Protoss_Cybernetics_Core 1 6843
Protoss_Stargate 1 8113
Protoss_Dragoon 1 7793
Protoss_Citadel_of_Adun 1 8629
Protoss_Corsair 1 8995
Protoss_Templar_Archives 1 9855
Protoss_Robotics_Facility 1 11273
Protoss_High_Templar 2 10761
Protoss_Dark_Templar 1 10867
12663
