Protoss_Forge 1 3345
Protoss_Nexus 1 6161
Protoss_Photon_Cannon 3 11089
Protoss_Gateway 5 11246
Protoss_Assimilator 2 8775
Protoss_Zealot 8 9907
Protoss_Cybernetics_Core 1 7731
Protoss_Citadel_of_Adun 1 8803
Protoss_Templar_Archives 1 11131
11246
