Protoss_Gateway 4 7994
Protoss_Assimilator 1 3499
Protoss_Zealot 3 5486
Protoss_Cybernetics_Core 1 5674
Protoss_Dragoon 9 10431
Protoss_Robotics_Facility 1 10602
Protoss_Forge 1 10575
10602
