Protoss_Forge 1 3475
Protoss_Photon_Cannon 6 8929
Protoss_Nexus 1 6643
Protoss_Gateway 1 6164
Protoss_Assimilator 1 5864
Protoss_Zealot 2 7283
Protoss_Cybernetics_Core 1 7398
Protoss_Dragoon 2 9936
Protoss_Stargate 1 11323
11323
