Protoss_Gateway 2 7682
Protoss_Assimilator 1 3393
Protoss_Zealot 8 8839
Protoss_Cybernetics_Core 1 5413
Protoss_Dragoon 1 6331
Protoss_Citadel_of_Adun 1 7014
Protoss_Templar_Archives 1 8613
Protoss_Forge 1 9272
Protoss_High_Templar 3 10595
Protoss_Photon_Cannon 1 10416
Protoss_Dark_Templar 1 10609
Protoss_Archon 1 10035
Protoss_Robotics_Facility 1 11777
11777
