Protoss_Gateway 3 9677
Protoss_Zealot 8 7983
Protoss_Assimilator 1 4572
Protoss_Cybernetics_Core 1 6245
Protoss_Stargate 1 7812
Protoss_Dragoon 9 11173
Protoss_Citadel_of_Adun 1 8337
Protoss_Corsair 1 8223
11173
