Protoss_Gateway 3 11117
Protoss_Assimilator 1 3545
Protoss_Cybernetics_Core 1 4395
Protoss_Zealot 5 9685
Protoss_Stargate 1 5810
Protoss_Dragoon 1 5645
Protoss_Corsair 2 8031
Protoss_Forge 1 6582
Protoss_Citadel_of_Adun 1 8341
Protoss_Robotics_Facility 1 10574
11117
