Protoss_Forge 1 3726
Protoss_Photon_Cannon 2 9505
Protoss_Nexus 1 6857
Protoss_Gateway 4 11044
Protoss_Assimilator 2 8484
Protoss_Zealot 6 10771
Protoss_Cybernetics_Core 1 7411
Protoss_Stargate 1 8964
11044
