Protoss_Forge 1 3696
Protoss_Photon_Cannon 4 9790
Protoss_Nexus 1 6915
Protoss_Gateway 1 5757
Protoss_Assimilator 2 8366
Protoss_Cybernetics_Core 1 6953
Protoss_Zealot 3 8811
Protoss_Stargate 1 8214
Protoss_Robotics_Facility 1 9425
Protoss_Corsair 3 10406
Protoss_Robotics_Support_Bay 1 9960
Protoss_Reaver 1 11465
11465
