Protoss_Forge 1 3131
Protoss_Photon_Cannon 2 4177
Protoss_Nexus 1 7206
Protoss_Gateway 4 9603
Protoss_Assimilator 2 9741
Protoss_Cybernetics_Core 1 7143
Protoss_Zealot 10 10543
Protoss_Citadel_of_Adun 1 8305
Protoss_Templar_Archives 1 11338
11338
