Protoss_Forge 1 3235
Protoss_Photon_Cannon 2 4363
Protoss_Nexus 1 6809
Protoss_Gateway 6 9839
Protoss_Assimilator 2 7834
Protoss_Cybernetics_Core 1 7077
Protoss_Zealot 7 10369
Protoss_Dragoon 1 7925
Protoss_Citadel_of_Adun 1 8545
Protoss_Templar_Archives 1 10672
10672
