Protoss_Forge 1 3317
Protoss_Nexus 1 6097
Protoss_Photon_Cannon 3 8224
Protoss_Gateway 3 11192
Protoss_Zealot 3 7519
Protoss_Assimilator 2 8816
Protoss_Cybernetics_Core 1 8734
Protoss_Citadel_of_Adun 1 10083
Protoss_Dragoon 2 11189
Protoss_Templar_Archives 1 11383
11383
