Protoss_Forge 1 3745
Protoss_Nexus 1 6095
Protoss_Photon_Cannon 4 9827
Protoss_Gateway 5 10944
Protoss_Assimilator 2 7326
Protoss_Cybernetics_Core 1 7072
Protoss_Zealot 3 8787
Protoss_Stargate 1 8311
Protoss_Citadel_of_Adun 1 8561
Protoss_Corsair 1 8747
Protoss_Templar_Archives 1 9615
Protoss_High_Templar 1 10381
Protoss_Dark_Templar 2 10413
10944
