Protoss_Forge 1 3546
Protoss_Photon_Cannon 3 10682
Protoss_Nexus 1 6499
Protoss_Gateway 1 5353
Protoss_Assimilator 2 6980
Protoss_Cybernetics_Core 1 6756
Protoss_Zealot 4 9667
Protoss_Stargate 1 8317
Protoss_Dragoon 1 8553
Protoss_Corsair 3 10249
Protoss_Robotics_Facility 1 10737
10737
