Protoss_Forge 1 3045
Protoss_Photon_Cannon 3 9005
Protoss_Nexus 1 6591
Protoss_Gateway 3 10555
Protoss_Assimilator 2 7169
Protoss_Zealot 3 9611
Protoss_Cybernetics_Core 1 7275
Protoss_Stargate 1 8697
Protoss_Citadel_of_Adun 1 8913
Protoss_Corsair 1 9261
Protoss_Templar_Archives 1 9967
Protoss_Dark_Templar 1 10819
10819
