Protoss_Forge 1 3174
Protoss_Nexus 1 6278
Protoss_Photon_Cannon 2 5201
Protoss_Gateway 3 7808
Protoss_Zealot 11 10126
Protoss_Assimilator 2 9635
Protoss_Cybernetics_Core 1 9449
Protoss_Citadel_of_Adun 1 10488
Protoss_Robotics_Facility 1 11585
11585
