Protoss_Nexus 1 5988
Protoss_Forge 1 4593
Protoss_Gateway 3 10162
Protoss_Photon_Cannon 3 8828
Protoss_Assimilator 2 6766
Protoss_Cybernetics_Core 1 7846
Protoss_Stargate 1 9106
Protoss_Citadel_of_Adun 1 8906
Protoss_Corsair 2 10119
Protoss_Templar_Archives 1 10077
Protoss_Dark_Templar 1 10963
Protoss_High_Templar 1 10981
Protoss_Dragoon 1 10995
10995
