Protoss_Gateway 3 11012
Protoss_Zealot 9 8621
Protoss_Assimilator 1 4565
Protoss_Forge 1 5048
Protoss_Photon_Cannon 1 6630
Protoss_Cybernetics_Core 1 8258
Protoss_Dragoon 5 11086
Protoss_Citadel_of_Adun 1 10033
Protoss_Ground_Weapons_1 1 9136
11086
