Protoss_Gateway 2 11069
Protoss_Zealot 12 10855
Protoss_Forge 1 4231
Protoss_Nexus 1 8053
Protoss_Photon_Cannon 2 10537
Protoss_Assimilator 2 8310
Protoss_Cybernetics_Core 1 7872
Protoss_Stargate 1 9535
Protoss_Citadel_of_Adun 1 9752
Protoss_Corsair 1 9977
11069
