Protoss_Forge 1 2967
Protoss_Photon_Cannon 4 11087
Protoss_Nexus 1 6933
Protoss_Gateway 2 10582
Protoss_Assimilator 2 8385
Protoss_Zealot 3 8149
Protoss_Cybernetics_Core 1 8301
Protoss_Dragoon 1 9205
Protoss_Stargate 1 9758
Protoss_Citadel_of_Adun 1 9837
Protoss_Corsair 2 10773
Protoss_Templar_Archives 1 10951
11087
