Protoss_Gateway 3 6873
Protoss_Assimilator 1 3325
Protoss_Zealot 19 10955
Protoss_Cybernetics_Core 1 5357
Protoss_Dragoon 1 6337
Protoss_Citadel_of_Adun 1 7172
Protoss_Templar_Archives 1 10431
Protoss_Forge 1 10737
10955
