Protoss_Forge 1 3399
Protoss_Photon_Cannon 4 10913
Protoss_Nexus 2 12020
Protoss_Gateway 1 6500
Protoss_Assimilator 2 8115
Protoss_Zealot 3 9597
Protoss_Cybernetics_Core 1 7943
Protoss_Stargate 1 9203
Protoss_Robotics_Facility 1 10209
Protoss_Corsair 3 10949
Protoss_Robotics_Support_Bay 1 10399
12020
