Protoss_Forge 1 3278
Protoss_Photon_Cannon 1 4268
Protoss_Nexus 1 6598
Protoss_Gateway 4 11006
Protoss_Assimilator 2 7083
Protoss_Cybernetics_Core 1 6839
Protoss_Zealot 4 10955
Protoss_Stargate 1 8256
Protoss_Citadel_of_Adun 1 8558
Protoss_Corsair 1 8717
Protoss_Templar_Archives 1 9545
Protoss_Dark_Templar 3 10365
11006
