Protoss_Nexus 1 5616
Protoss_Gateway 1 4801
Protoss_Forge 1 4655
Protoss_Photon_Cannon 1 5583
Protoss_Assimilator 2 7003
Protoss_Zealot 5 9039
Protoss_Cybernetics_Core 1 7224
9039
