Protoss_Forge 1 3225
Protoss_Photon_Cannon 2 4641
Protoss_Nexus 1 7295
Protoss_Gateway 4 10085
Protoss_Zealot 15 10919
Protoss_Assimilator 2 9384
Protoss_Cybernetics_Core 1 7792
Protoss_Citadel_of_Adun 1 8873
Protoss_Templar_Archives 1 11005
11005
