Protoss_Gateway 2 9662
Protoss_Zealot 6 9561
Protoss_Assimilator 1 4402
Protoss_Cybernetics_Core 1 5421
Protoss_Stargate 1 7643
Protoss_Dragoon 1 7373
Protoss_Citadel_of_Adun 1 8276
Protoss_Corsair 1 8127
Protoss_Forge 1 8467
Protoss_Templar_Archives 1 9346
Protoss_Dark_Templar 2 10805
10805
