Protoss_Nexus 1 5789
Protoss_Gateway 6 11106
Protoss_Forge 1 4727
Protoss_Assimilator 2 7183
Protoss_Photon_Cannon 2 7968
Protoss_Zealot 6 9201
Protoss_Cybernetics_Core 1 7532
Protoss_Stargate 1 8856
Protoss_Citadel_of_Adun 1 8797
Protoss_Templar_Archives 1 9785
Protoss_Corsair 1 9793
Protoss_Dark_Templar 2 10533
Protoss_High_Templar 1 11003
Protoss_Ground_Weapons_1 1 9811
11106
