Protoss_Forge 1 3009
Protoss_Nexus 1 6285
Protoss_Gateway 4 11077
Protoss_Photon_Cannon 4 10573
Protoss_Assimilator 2 7731
Protoss_Cybernetics_Core 1 6720
Protoss_Zealot 2 8183
Protoss_Stargate 1 8001
Protoss_Citadel_of_Adun 1 8460
Protoss_Corsair 4 10925
Protoss_Templar_Archives 1 9575
Protoss_High_Templar 1 10455
11077
