Protoss_Forge 1 2881
Protoss_Photon_Cannon 1 4704
Protoss_Nexus 1 6582
Protoss_Gateway 3 10387
Protoss_Assimilator 2 7736
Protoss_Zealot 6 10386
Protoss_Cybernetics_Core 1 6738
Protoss_Stargate 1 8031
Protoss_Citadel_of_Adun 1 9489
Protoss_Dragoon 1 9874
Protoss_Templar_Archives 1 10525
10525
