Protoss_Forge 1 3500
Protoss_Photon_Cannon 2 4497
Protoss_Nexus 1 7402
Protoss_Gateway 3 10827
Protoss_Assimilator 2 8335
Protoss_Zealot 7 10819
Protoss_Cybernetics_Core 1 7267
Protoss_Stargate 1 8517
Protoss_Robotics_Facility 1 9515
Protoss_Corsair 2 10795
Protoss_Shuttle 1 10409
10827
