Protoss_Forge 1 2989
Protoss_Nexus 1 6253
Protoss_Gateway 1 5247
Protoss_Photon_Cannon 5 10967
Protoss_Zealot 3 8289
Protoss_Assimilator 2 7533
Protoss_Cybernetics_Core 1 7057
Protoss_Stargate 2 9443
Protoss_Citadel_of_Adun 1 9467
Protoss_Corsair 5 10925
Protoss_Templar_Archives 1 10741
10967
