Protoss_Forge 1 3248
Protoss_Nexus 1 6156
Protoss_Photon_Cannon 1 4723
Protoss_Gateway 4 10077
Protoss_Assimilator 2 6922
Protoss_Cybernetics_Core 1 6515
Protoss_Zealot 7 10567
Protoss_Stargate 1 7839
Protoss_Citadel_of_Adun 1 8347
Protoss_Corsair 1 8311
Protoss_Templar_Archives 1 9621
Protoss_Dark_Templar 1 10681
Protoss_High_Templar 1 10681
10681
