Protoss_Forge 1 3105
Protoss_Nexus 1 5947
Protoss_Photon_Cannon 4 9471
Protoss_Gateway 2 11273
Protoss_Assimilator 2 7851
Protoss_Cybernetics_Core 1 7203
Protoss_Zealot 3 10637
Protoss_Stargate 1 8477
Protoss_Robotics_Facility 1 9335
Protoss_Dragoon 2 9811
Protoss_Corsair 1 8921
Protoss_Citadel_of_Adun 1 9857
Protoss_Robotics_Support_Bay 1 9589
Protoss_Reaver 1 11091
Protoss_Templar_Archives 1 10990
11273
