Protoss_Forge 1 3157
Protoss_Photon_Cannon 3 6153
Protoss_Nexus 1 6483
Protoss_Gateway 4 10864
Protoss_Assimilator 2 7565
Protoss_Cybernetics_Core 1 7453
Protoss_Zealot 2 9256
Protoss_Stargate 1 8694
Protoss_Dragoon 1 8301
Protoss_Citadel_of_Adun 1 9072
Protoss_Corsair 2 9740
Protoss_Templar_Archives 1 10072
Protoss_Dark_Templar 2 10826
10864
