Protoss_Gateway 2 9908
Protoss_Assimilator 1 3593
Protoss_Zealot 6 10426
Protoss_Cybernetics_Core 1 5473
Protoss_Dragoon 1 6221
Protoss_Stargate 1 7061
Protoss_Robotics_Facility 1 8228
Protoss_Corsair 2 8271
Protoss_Forge 1 7908
Protoss_Shuttle 1 9221
Protoss_Photon_Cannon 1 9457
10426
