Protoss_Forge 1 3493
Protoss_Photon_Cannon 4 11095
Protoss_Nexus 1 6382
Protoss_Gateway 3 10521
Protoss_Assimilator 2 7664
Protoss_Zealot 5 10825
Protoss_Cybernetics_Core 1 7405
Protoss_Stargate 1 8729
Protoss_Citadel_of_Adun 1 9407
Protoss_Corsair 1 9209
Protoss_Templar_Archives 1 10445
11095
