Protoss_Forge 1 3145
Protoss_Nexus 1 6345
Protoss_Photon_Cannon 4 6191
Protoss_Gateway 3 10706
Protoss_Assimilator 2 7738
Protoss_Cybernetics_Core 1 8369
Protoss_Zealot 3 9865
Protoss_Stargate 1 9601
Protoss_Citadel_of_Adun 1 9386
Protoss_Dragoon 1 9353
Protoss_Templar_Archives 1 10464
Protoss_Corsair 2 10871
10871
