Protoss_Forge 1 3079
Protoss_Nexus 1 6523
Protoss_Gateway 1 5185
Protoss_Assimilator 2 6855
Protoss_Photon_Cannon 1 5716
Protoss_Cybernetics_Core 1 6433
Protoss_Zealot 4 10757
Protoss_Stargate 1 7925
Protoss_Dragoon 1 7675
Protoss_Robotics_Facility 1 8856
Protoss_Corsair 5 10889
Protoss_Shuttle 1 9785
Protoss_Robotics_Support_Bay 1 9181
Protoss_Reaver 1 11195
Protoss_Observatory 1 10576
11195
