Protoss_Nexus 1 5707
Protoss_Forge 1 4101
Protoss_Photon_Cannon 3 7629
Protoss_Gateway 1 6015
Protoss_Assimilator 2 7245
Protoss_Cybernetics_Core 1 7017
Protoss_Zealot 3 10201
Protoss_Stargate 1 8329
Protoss_Dragoon 1 8039
Protoss_Robotics_Facility 1 9488
Protoss_Corsair 4 10545
Protoss_Shuttle 1 10301
Protoss_Robotics_Support_Bay 1 9836
Protoss_Reaver 1 11443
11443
