Protoss_Forge 1 3712
Protoss_Nexus 1 6083
Protoss_Photon_Cannon 2 5103
Protoss_Gateway 4 11300
Protoss_Assimilator 2 8318
Protoss_Zealot 4 10579
Protoss_Cybernetics_Core 1 7641
Protoss_Stargate 1 8942
Protoss_Dragoon 1 8955
Protoss_Citadel_of_Adun 1 9719
Protoss_Corsair 2 9955
Protoss_Templar_Archives 1 10797
11300
