Protoss_Forge 1 2874
Protoss_Photon_Cannon 5 10721
Protoss_Nexus 1 7297
Protoss_Gateway 1 6235
Protoss_Assimilator 2 8220
Protoss_Zealot 6 10631
Protoss_Cybernetics_Core 1 7711
Protoss_Stargate 1 9033
Protoss_Citadel_of_Adun 1 8998
Protoss_Corsair 1 9445
Protoss_Templar_Archives 1 10483
10721
