Protoss_Gateway 2 11042
Protoss_Zealot 10 10917
Protoss_Assimilator 1 3935
Protoss_Cybernetics_Core 1 5294
Protoss_Dragoon 1 6181
Protoss_Stargate 1 6861
Protoss_Forge 1 6351
Protoss_Citadel_of_Adun 1 7326
Protoss_Corsair 1 7271
Protoss_Photon_Cannon 1 8447
Protoss_Nexus 1 11107
Protoss_Robotics_Facility 1 10695
Protoss_Templar_Archives 1 11411
11411
