Protoss_Forge 2 9425
Protoss_Nexus 1 6393
Protoss_Gateway 3 9837
Protoss_Assimilator 2 7454
Protoss_Photon_Cannon 2 10266
Protoss_Cybernetics_Core 1 6564
Protoss_Zealot 1 6883
Protoss_Dragoon 1 7357
Protoss_Stargate 1 7915
Protoss_Citadel_of_Adun 1 8227
Protoss_Corsair 1 8391
Protoss_Templar_Archives 1 9357
Protoss_Dark_Templar 1 10275
Protoss_High_Templar 2 10621
Protoss_Robotics_Facility 1 11526
11526
