Protoss_Forge 1 3253
Protoss_Photon_Cannon 6 11037
Protoss_Nexus 1 6743
Protoss_Gateway 3 10517
Protoss_Assimilator 2 8563
Protoss_Zealot 3 7455
Protoss_Cybernetics_Core 1 6999
Protoss_Dragoon 2 8085
Protoss_Stargate 1 8314
Protoss_Citadel_of_Adun 1 8671
Protoss_Corsair 1 8919
Protoss_Templar_Archives 1 10145
Protoss_Dark_Templar 2 10933
11037
