Protoss_Forge 1 3130
Protoss_Photon_Cannon 2 10293
Protoss_Nexus 1 6365
Protoss_Gateway 2 9494
Protoss_Assimilator 2 7115
Protoss_Zealot 6 9301
Protoss_Cybernetics_Core 1 7037
Protoss_Stargate 1 8385
Protoss_Citadel_of_Adun 1 8855
Protoss_Corsair 3 10205
Protoss_Templar_Archives 1 10051
10293
