Protoss_Forge 2 4753
Protoss_Nexus 2 12119
Protoss_Gateway 4 11227
Protoss_Photon_Cannon 2 9897
Protoss_Assimilator 2 7981
Protoss_Zealot 3 8791
Protoss_Cybernetics_Core 1 7161
Protoss_Dragoon 1 7905
Protoss_Stargate 1 8588
Protoss_Citadel_of_Adun 1 8371
Protoss_Templar_Archives 1 9413
Protoss_Corsair 3 10501
Protoss_Dark_Templar 2 10513
12119
