Protoss_Nexus 1 5737
Protoss_Gateway 3 11313
Protoss_Assimilator 2 7884
Protoss_Zealot 7 10395
Protoss_Forge 1 5561
Protoss_Cybernetics_Core 1 6833
Protoss_Photon_Cannon 1 7556
Protoss_Stargate 1 8369
Protoss_Robotics_Facility 1 8766
Protoss_Corsair 3 10033
Protoss_Dragoon 1 9075
Protoss_Shuttle 1 9861
Protoss_Citadel_of_Adun 1 9872
Protoss_Robotics_Support_Bay 1 9646
Protoss_Templar_Archives 1 11031
Protoss_Reaver 1 11351
11351
