Protoss_Gateway 1 3349
Protoss_Assimilator 2 10950
Protoss_Zealot 2 4568
Protoss_Cybernetics_Core 1 5447
Protoss_Stargate 1 6677
Protoss_Dragoon 1 6293
Protoss_Citadel_of_Adun 1 6983
Protoss_Corsair 1 7127
Protoss_Templar_Archives 1 7971
Protoss_Forge 1 7775
Protoss_Dark_Templar 2 9467
Protoss_Photon_Cannon 3 10709
Protoss_Robotics_Facility 1 9815
Protoss_Nexus 1 11797
Protoss_High_Templar 1 10254
Protoss_Observatory 1 9914
Protoss_Observer 1 10733
11797
