Protoss_Gateway 5 10631
Protoss_Zealot 12 10545
Protoss_Forge 1 5121
Protoss_Photon_Cannon 3 9515
Protoss_Nexus 1 8141
Protoss_Assimilator 2 8648
Protoss_Cybernetics_Core 1 7609
Protoss_Citadel_of_Adun 1 9245
Protoss_Dragoon 1 9615
Protoss_Templar_Archives 1 11231
11231
