Protoss_Forge 1 3398
Protoss_Photon_Cannon 3 10098
Protoss_Nexus 1 7227
Protoss_Gateway 4 10670
Protoss_Assimilator 2 8421
Protoss_Cybernetics_Core 1 7241
Protoss_Zealot 2 7527
Protoss_Stargate 1 8513
Protoss_Dragoon 3 10727
Protoss_Robotics_Facility 1 9713
Protoss_Corsair 2 10007
Protoss_Shuttle 1 11325
Protoss_Robotics_Support_Bay 1 10651
11325
