Protoss_Nexus 1 5693
Protoss_Gateway 1 4563
Protoss_Forge 1 4687
Protoss_Zealot 7 10459
Protoss_Assimilator 2 9743
Protoss_Photon_Cannon 2 7027
Protoss_Cybernetics_Core 1 7783
Protoss_Stargate 1 9117
Protoss_Citadel_of_Adun 1 9413
Protoss_Corsair 1 9549
Protoss_Templar_Archives 1 11231
11231
