Protoss_Nexus 1 5716
Protoss_Gateway 4 10709
Protoss_Forge 1 4868
Protoss_Assimilator 2 6175
Protoss_Photon_Cannon 3 9327
Protoss_Cybernetics_Core 1 6193
Protoss_Stargate 1 7604
Protoss_Zealot 2 8917
Protoss_Citadel_of_Adun 1 7777
Protoss_Corsair 2 8809
Protoss_Templar_Archives 1 9059
Protoss_Dark_Templar 2 9903
Protoss_High_Templar 2 10655
10709
