Protoss_Assimilator 1 2838
Protoss_Gateway 1 3631
Protoss_Cybernetics_Core 1 4734
Protoss_Stargate 1 6015
Protoss_Robotics_Facility 1 6954
Protoss_Corsair 4 9891
Protoss_Forge 1 7369
Protoss_Shuttle 2 9157
Protoss_Photon_Cannon 1 8502
Protoss_Dragoon 1 8613
Protoss_Robotics_Support_Bay 1 8773
Protoss_Air_Weapons_1 1 8399
Protoss_Reaver 1 10299
10299
