Protoss_Forge 1 3549
Protoss_Nexus 1 6034
Protoss_Photon_Cannon 6 10791
Protoss_Gateway 5 10418
Protoss_Assimilator 2 8352
Protoss_Cybernetics_Core 1 6790
Protoss_Zealot 5 10155
Protoss_Stargate 1 8027
Protoss_Corsair 1 8443
Protoss_Robotics_Facility 1 9703
Protoss_Robotics_Support_Bay 1 9861
Protoss_Reaver 1 11405
Protoss_Dragoon 1 11095
11405
