Protoss_Forge 1 3039
Protoss_Photon_Cannon 2 8935
Protoss_Nexus 1 6535
Protoss_Gateway 3 10792
Protoss_Assimilator 2 6665
Protoss_Zealot 3 9837
Protoss_Cybernetics_Core 1 6548
Protoss_Stargate 1 7979
Protoss_Dragoon 1 8237
Protoss_Citadel_of_Adun 1 8890
Protoss_Corsair 3 10419
Protoss_Templar_Archives 1 10089
Protoss_Dark_Templar 1 10829
10829
