Protoss_Forge 1 3179
Protoss_Photon_Cannon 2 4298
Protoss_Nexus 1 6834
Protoss_Gateway 1 5873
Protoss_Assimilator 1 5669
Protoss_Cybernetics_Core 1 6913
Protoss_Zealot 3 7829
Protoss_Stargate 1 8538
8538
