Protoss_Forge 1 3368
Protoss_Nexus 1 6195
Protoss_Photon_Cannon 2 8964
Protoss_Gateway 4 11297
Protoss_Assimilator 2 9734
Protoss_Zealot 3 10255
Protoss_Cybernetics_Core 1 7871
Protoss_Citadel_of_Adun 1 9511
Protoss_Dragoon 1 9589
Protoss_Templar_Archives 1 10527
11297
