Protoss_Forge 1 3156
Protoss_Photon_Cannon 7 10279
Protoss_Nexus 2 12805
Protoss_Gateway 1 6571
Protoss_Assimilator 2 10718
Protoss_Zealot 3 10501
Protoss_Cybernetics_Core 1 9459
Protoss_Stargate 1 11005
12805
