Protoss_Forge 1 3173
Protoss_Nexus 1 6061
Protoss_Photon_Cannon 2 5084
Protoss_Gateway 5 11217
Protoss_Assimilator 2 10432
Protoss_Zealot 9 10879
Protoss_Cybernetics_Core 1 7331
Protoss_Stargate 1 8592
Protoss_Dragoon 1 8989
Protoss_Citadel_of_Adun 1 9233
Protoss_Corsair 3 10365
11217
