Protoss_Forge 1 3056
Protoss_Nexus 1 6231
Protoss_Gateway 3 9263
Protoss_Photon_Cannon 4 9841
Protoss_Assimilator 2 7307
Protoss_Cybernetics_Core 1 7010
Protoss_Zealot 1 6901
Protoss_Citadel_of_Adun 1 8379
Protoss_Stargate 1 8699
Protoss_Templar_Archives 1 9399
Protoss_Corsair 3 10799
Protoss_Dark_Templar 4 10963
10963
