Protoss_Nexus 2 12583
Protoss_Gateway 2 8549
Protoss_Forge 1 4720
Protoss_Assimilator 2 6662
Protoss_Photon_Cannon 5 11039
Protoss_Cybernetics_Core 1 6131
Protoss_Zealot 1 6185
Protoss_Stargate 1 7643
Protoss_Dragoon 1 7343
Protoss_Citadel_of_Adun 1 8088
Protoss_Corsair 3 9559
Protoss_Templar_Archives 1 9201
Protoss_Dark_Templar 2 9975
Protoss_High_Templar 2 10727
12583
