Protoss_Gateway 4 10619
Protoss_Zealot 8 10857
Protoss_Nexus 1 7347
Protoss_Assimilator 1 5731
Protoss_Cybernetics_Core 1 6533
Protoss_Stargate 1 7949
Protoss_Dragoon 1 8487
Protoss_Forge 1 8257
Protoss_Corsair 1 8383
Protoss_Citadel_of_Adun 1 10304
10857
