Protoss_Forge 1 2893
Protoss_Photon_Cannon 2 4486
Protoss_Nexus 1 7113
Protoss_Gateway 3 10363
Protoss_Assimilator 2 7613
Protoss_Cybernetics_Core 1 7364
Protoss_Zealot 4 10176
Protoss_Stargate 1 9199
Protoss_Citadel_of_Adun 1 9739
Protoss_Corsair 2 10846
Protoss_Templar_Archives 1 10803
10846
