Protoss_Forge 1 3171
Protoss_Photon_Cannon 4 11198
Protoss_Nexus 1 6708
Protoss_Gateway 3 11068
Protoss_Assimilator 2 8342
Protoss_Zealot 6 10337
Protoss_Cybernetics_Core 1 7154
Protoss_Stargate 1 8706
Protoss_Citadel_of_Adun 1 9280
Protoss_Dragoon 1 9223
Protoss_Corsair 1 9121
Protoss_Templar_Archives 1 10465
11198
