Protoss_Nexus 2 11326
Protoss_Gateway 4 10539
Protoss_Forge 2 10928
Protoss_Assimilator 2 8879
Protoss_Photon_Cannon 1 6060
Protoss_Cybernetics_Core 1 6858
Protoss_Zealot 10 10415
Protoss_Dragoon 1 7721
Protoss_Citadel_of_Adun 1 8151
Protoss_Templar_Archives 1 10117
Protoss_Ground_Weapons_1 1 9751
11326
