Protoss_Gateway 2 8097
Protoss_Assimilator 1 3694
Protoss_Zealot 9 10362
Protoss_Forge 1 5008
Protoss_Photon_Cannon 1 6303
Protoss_Cybernetics_Core 1 7108
Protoss_Citadel_of_Adun 1 8471
Protoss_Ground_Weapons_1 1 8876
Protoss_Templar_Archives 1 11413
11413
