Protoss_Forge 1 2940
Protoss_Nexus 1 6103
Protoss_Photon_Cannon 2 5573
Protoss_Gateway 5 11302
Protoss_Assimilator 2 7256
Protoss_Cybernetics_Core 1 7205
Protoss_Zealot 3 9382
Protoss_Stargate 1 8452
Protoss_Citadel_of_Adun 1 8767
Protoss_Dragoon 1 8870
Protoss_Corsair 1 8859
Protoss_Templar_Archives 1 9879
Protoss_High_Templar 2 10771
11302
