Protoss_Forge 1 3158
Protoss_Photon_Cannon 6 10751
Protoss_Nexus 1 7753
Protoss_Gateway 3 10633
Protoss_Assimilator 2 8389
Protoss_Cybernetics_Core 1 7681
Protoss_Zealot 5 10597
Protoss_Stargate 1 8979
Protoss_Citadel_of_Adun 1 9312
Protoss_Corsair 2 10027
Protoss_Templar_Archives 1 10303
Protoss_Dark_Templar 1 11041
11041
