Protoss_Forge 1 3251
Protoss_Nexus 1 6377
Protoss_Gateway 1 5433
Protoss_Assimilator 2 6783
Protoss_Photon_Cannon 4 10325
Protoss_Cybernetics_Core 1 6525
Protoss_Zealot 2 8729
Protoss_Stargate 1 8006
Protoss_Dragoon 1 7747
Protoss_Robotics_Facility 1 8994
Protoss_Corsair 4 10479
Protoss_Robotics_Support_Bay 1 9404
Protoss_Citadel_of_Adun 1 10799
10799
