Protoss_Forge 1 3125
Protoss_Nexus 1 5998
Protoss_Gateway 4 8845
Protoss_Photon_Cannon 1 5538
Protoss_Assimilator 2 9791
Protoss_Zealot 17 10937
Protoss_Cybernetics_Core 1 6693
Protoss_Stargate 1 7946
Protoss_Citadel_of_Adun 1 8456
Protoss_Corsair 1 8501
Protoss_Templar_Archives 1 10757
10937
