Protoss_Gateway 3 11410
Protoss_Assimilator 1 3178
Protoss_Cybernetics_Core 1 4315
Protoss_Zealot 7 8511
Protoss_Stargate 1 5695
Protoss_Corsair 1 6207
Protoss_Citadel_of_Adun 1 8552
Protoss_Forge 1 8851
Protoss_Templar_Archives 1 9558
Protoss_Photon_Cannon 1 9927
11410
