Protoss_Forge 1 2797
Protoss_Nexus 1 6228
Protoss_Photon_Cannon 2 8647
Protoss_Gateway 3 6945
Protoss_Assimilator 1 5864
Protoss_Zealot 13 10519
Protoss_Cybernetics_Core 1 8237
Protoss_Stargate 1 9779
Protoss_Citadel_of_Adun 1 10004
Protoss_Corsair 2 10945
10945
