Protoss_Gateway 3 6746
Protoss_Assimilator 2 8176
Protoss_Zealot 11 8709
Protoss_Forge 1 4287
Protoss_Photon_Cannon 2 10748
Protoss_Ground_Weapons_1 1 8016
Protoss_Nexus 1 11458
Protoss_Cybernetics_Core 1 10507
11458
