Protoss_Forge 1 3702
Protoss_Nexus 1 6071
Protoss_Photon_Cannon 2 5684
Protoss_Gateway 4 10576
Protoss_Assimilator 2 7436
Protoss_Cybernetics_Core 1 7411
Protoss_Zealot 4 10959
Protoss_Stargate 1 8674
Protoss_Citadel_of_Adun 1 8597
Protoss_Dragoon 1 9143
Protoss_Corsair 2 10369
Protoss_Templar_Archives 1 9828
Protoss_High_Templar 2 11195
11195
