Protoss_Forge 1 3467
Protoss_Photon_Cannon 4 9315
Protoss_Nexus 1 6837
Protoss_Gateway 3 10953
Protoss_Assimilator 2 7238
Protoss_Cybernetics_Core 1 7083
Protoss_Zealot 6 10647
Protoss_Citadel_of_Adun 1 8783
Protoss_Templar_Archives 1 9912
10953
