Protoss_Nexus 1 5778
Protoss_Forge 1 4393
Protoss_Photon_Cannon 2 6493
Protoss_Gateway 3 7132
Protoss_Assimilator 2 9692
Protoss_Zealot 9 9271
Protoss_Cybernetics_Core 1 9293
Protoss_Citadel_of_Adun 1 10412
10412
