Protoss_Forge 1 3199
Protoss_Nexus 1 6115
Protoss_Photon_Cannon 6 10995
Protoss_Gateway 6 10747
Protoss_Zealot 4 9069
Protoss_Assimilator 2 7746
Protoss_Cybernetics_Core 1 8028
Protoss_Citadel_of_Adun 1 9168
Protoss_Templar_Archives 1 10158
Protoss_High_Templar 4 11069
11069
