Protoss_Gateway 2 3828
Protoss_Zealot 13 10734
Protoss_Assimilator 1 6288
Protoss_Cybernetics_Core 1 7600
Protoss_Forge 1 7886
Protoss_Stargate 1 8843
Protoss_Dragoon 1 8461
Protoss_Photon_Cannon 2 9398
Protoss_Citadel_of_Adun 1 9285
10734
