Protoss_Forge 1 3667
Protoss_Nexus 1 6282
Protoss_Gateway 1 5695
Protoss_Photon_Cannon 2 10448
Protoss_Assimilator 2 6847
Protoss_Cybernetics_Core 1 6760
Protoss_Zealot 1 6557
Protoss_Stargate 1 8073
10448
