Protoss_Nexus 1 2863
Protoss_Gateway 1 3715
Protoss_Assimilator 1 4368
Protoss_Forge 1 4712
Protoss_Zealot 3 6968
Protoss_Photon_Cannon 4 6513
Protoss_Cybernetics_Core 1 7113
7113
