Protoss_Forge 1 3446
Protoss_Photon_Cannon 4 10728
Protoss_Nexus 1 6549
Protoss_Gateway 4 11394
Protoss_Assimilator 2 8298
Protoss_Zealot 6 9759
Protoss_Cybernetics_Core 1 8198
Protoss_Stargate 1 9552
Protoss_Citadel_of_Adun 1 9543
Protoss_Corsair 2 10939
Protoss_Templar_Archives 1 10835
11394
