Protoss_Forge 1 3845
Protoss_Photon_Cannon 3 6805
Protoss_Nexus 1 7603
Protoss_Gateway 4 10683
Protoss_Assimilator 2 10911
Protoss_Cybernetics_Core 1 7519
Protoss_Zealot 7 10537
Protoss_Stargate 1 8861
Protoss_Citadel_of_Adun 1 8952
Protoss_Corsair 1 9269
Protoss_Templar_Archives 1 11304
11304
