Protoss_Gateway 2 10317
Protoss_Assimilator 1 3293
Protoss_Zealot 6 9831
Protoss_Cybernetics_Core 1 5829
Protoss_Dragoon 1 6591
Protoss_Stargate 1 7239
Protoss_Citadel_of_Adun 1 8263
10317
