Protoss_Nexus 1 5537
Protoss_Forge 1 3905
Protoss_Gateway 2 5638
Protoss_Assimilator 2 8525
Protoss_Zealot 11 10311
Protoss_Photon_Cannon 2 10046
Protoss_Cybernetics_Core 1 8128
Protoss_Stargate 2 9870
Protoss_Citadel_of_Adun 1 9642
Protoss_Corsair 2 10631
Protoss_Templar_Archives 1 11317
11317
