Protoss_Forge 1 3013
Protoss_Photon_Cannon 6 11127
Protoss_Nexus 1 6538
Protoss_Gateway 4 10399
Protoss_Assimilator 2 8479
Protoss_Zealot 8 10235
Protoss_Cybernetics_Core 1 7515
Protoss_Citadel_of_Adun 1 8568
Protoss_Templar_Archives 1 10142
Protoss_High_Templar 2 11055
Protoss_Dark_Templar 1 11077
11127
