Protoss_Forge 1 3125
Protoss_Photon_Cannon 5 10407
Protoss_Nexus 1 6607
Protoss_Gateway 3 10985
Protoss_Assimilator 2 7975
Protoss_Zealot 4 9043
Protoss_Cybernetics_Core 1 7114
Protoss_Stargate 1 8357
Protoss_Dragoon 1 7929
Protoss_Citadel_of_Adun 1 9120
Protoss_Corsair 3 10009
Protoss_Templar_Archives 1 10389
Protoss_Dark_Templar 2 11165
11165
