Protoss_Gateway 3 11278
Protoss_Assimilator 1 3645
Protoss_Zealot 11 10511
Protoss_Cybernetics_Core 1 6602
Protoss_Citadel_of_Adun 1 7802
Protoss_Dragoon 1 7730
Protoss_Templar_Archives 1 10193
Protoss_Forge 1 10921
11278
