Protoss_Assimilator 1 2735
Protoss_Forge 1 3549
Protoss_Gateway 3 6243
Protoss_Photon_Cannon 2 9683
Protoss_Zealot 8 8141
Protoss_Cybernetics_Core 1 8332
Protoss_Ground_Weapons_1 1 7276
Protoss_Dragoon 6 11106
11106
