Protoss_Gateway 2 3936
Protoss_Zealot 11 9429
Protoss_Assimilator 1 5695
Protoss_Cybernetics_Core 1 7131
Protoss_Citadel_of_Adun 1 8349
Protoss_Dragoon 1 8217
Protoss_Templar_Archives 1 9597
Protoss_Forge 1 9720
Protoss_Dark_Templar 1 10387
Protoss_Photon_Cannon 1 11067
11067
