Protoss_Gateway 2 8140
Protoss_Zealot 10 10351
Protoss_Forge 1 5372
Protoss_Photon_Cannon 2 9959
Protoss_Nexus 1 8479
Protoss_Assimilator 1 7068
Protoss_Cybernetics_Core 1 9062
Protoss_Robotics_Facility 1 10837
Protoss_Citadel_of_Adun 1 10450
Protoss_Dragoon 1 11128
11128
