Protoss_Forge 1 3131
Protoss_Nexus 1 6041
Protoss_Photon_Cannon 2 5009
Protoss_Gateway 6 11437
Protoss_Assimilator 2 7346
Protoss_Cybernetics_Core 1 6929
Protoss_Zealot 3 10185
Protoss_Stargate 1 8275
Protoss_Citadel_of_Adun 1 8391
Protoss_Dragoon 1 8423
Protoss_Corsair 2 9387
Protoss_Templar_Archives 1 9659
Protoss_High_Templar 2 10491
11437
