Protoss_Forge 1 3128
Protoss_Nexus 1 6011
Protoss_Photon_Cannon 2 5335
Protoss_Gateway 4 10263
Protoss_Assimilator 2 7053
Protoss_Zealot 5 10581
Protoss_Cybernetics_Core 1 7059
Protoss_Dragoon 1 7863
Protoss_Stargate 1 8419
Protoss_Citadel_of_Adun 1 8564
Protoss_Corsair 1 8925
Protoss_Templar_Archives 1 9874
Protoss_High_Templar 2 11117
11117
