Protoss_Gateway 2 9939
Protoss_Zealot 3 4985
Protoss_Nexus 1 7539
Protoss_Forge 1 6351
Protoss_Assimilator 1 6430
Protoss_Cybernetics_Core 1 7538
Protoss_Photon_Cannon 7 10605
Protoss_Dragoon 4 10706
10706
