Protoss_Gateway 2 9174
Protoss_Zealot 8 9686
Protoss_Assimilator 1 4534
Protoss_Forge 1 5071
Protoss_Photon_Cannon 2 11037
Protoss_Cybernetics_Core 1 7636
Protoss_Dragoon 1 8406
Protoss_Citadel_of_Adun 1 8662
Protoss_Templar_Archives 1 9815
Protoss_Ground_Weapons_1 1 9246
Protoss_High_Templar 2 10581
11037
