Protoss_Forge 1 3208
Protoss_Photon_Cannon 5 10692
Protoss_Nexus 1 6841
Protoss_Gateway 3 10672
Protoss_Assimilator 2 9021
Protoss_Cybernetics_Core 1 6718
Protoss_Zealot 4 9819
Protoss_Stargate 1 8223
Protoss_Citadel_of_Adun 1 8691
Protoss_Corsair 3 10345
Protoss_Templar_Archives 1 9817
Protoss_High_Templar 2 11009
11009
