Protoss_Forge 1 3257
Protoss_Photon_Cannon 6 8389
Protoss_Nexus 1 6745
Protoss_Gateway 2 9281
Protoss_Assimilator 2 9297
Protoss_Zealot 7 10913
Protoss_Cybernetics_Core 1 9206
Protoss_Stargate 1 10581
Protoss_Citadel_of_Adun 1 11265
11265
