Protoss_Gateway 3 10134
Protoss_Zealot 9 9817
Protoss_Assimilator 2 5099
Protoss_Cybernetics_Core 1 6389
Protoss_Stargate 1 7785
Protoss_Citadel_of_Adun 1 8112
Protoss_Corsair 1 8725
Protoss_Templar_Archives 1 9560
Protoss_Forge 1 9381
Protoss_Dark_Templar 2 10959
10959
