Protoss_Forge 1 3569
Protoss_Nexus 1 6104
Protoss_Photon_Cannon 4 10746
Protoss_Gateway 1 6003
Protoss_Assimilator 2 8646
Protoss_Zealot 3 9411
Protoss_Cybernetics_Core 1 7477
Protoss_Stargate 1 9714
Protoss_Citadel_of_Adun 1 10019
Protoss_Corsair 1 10147
Protoss_Templar_Archives 1 11253
11253
