Protoss_Forge 1 2995
Protoss_Photon_Cannon 3 9453
Protoss_Nexus 1 7053
Protoss_Gateway 4 10141
Protoss_Assimilator 2 7021
Protoss_Cybernetics_Core 1 7043
Protoss_Zealot 3 8987
Protoss_Dragoon 2 11077
Protoss_Citadel_of_Adun 1 8355
Protoss_Templar_Archives 1 9343
Protoss_Dark_Templar 2 11051
Protoss_High_Templar 2 11135
11135
