Protoss_Gateway 1 3332
Protoss_Zealot 7 10245
Protoss_Nexus 1 7021
Protoss_Assimilator 1 5558
Protoss_Cybernetics_Core 1 6665
Protoss_Forge 1 6401
Protoss_Stargate 1 7897
Protoss_Dragoon 1 7665
Protoss_Photon_Cannon 2 10441
Protoss_Corsair 2 10501
10501
