Protoss_Forge 1 3133
Protoss_Photon_Cannon 4 10928
Protoss_Nexus 1 7011
Protoss_Gateway 3 11434
Protoss_Assimilator 2 8291
Protoss_Zealot 7 10629
Protoss_Cybernetics_Core 1 7982
Protoss_Stargate 1 9473
Protoss_Citadel_of_Adun 1 9749
Protoss_Corsair 2 10775
11434
