Protoss_Gateway 2 4170
Protoss_Zealot 7 10946
Protoss_Assimilator 1 4767
Protoss_Cybernetics_Core 1 5958
Protoss_Dragoon 1 6841
Protoss_Stargate 1 7661
Protoss_Citadel_of_Adun 1 7870
Protoss_Forge 1 8756
10946
