Protoss_Forge 1 3286
Protoss_Photon_Cannon 4 9649
Protoss_Nexus 1 7015
Protoss_Gateway 3 11434
Protoss_Assimilator 2 7572
Protoss_Zealot 5 10413
Protoss_Cybernetics_Core 1 7501
Protoss_Stargate 1 8754
Protoss_Dragoon 1 8495
Protoss_Corsair 2 10005
Protoss_Citadel_of_Adun 1 9994
Protoss_Templar_Archives 1 11072
11434
