Protoss_Gateway 2 8748
Protoss_Assimilator 1 3432
Protoss_Zealot 6 8656
Protoss_Cybernetics_Core 1 5763
Protoss_Dragoon 1 6576
Protoss_Citadel_of_Adun 1 7008
Protoss_Templar_Archives 1 8200
Protoss_Dark_Templar 1 8951
Protoss_Forge 1 8992
Protoss_Robotics_Facility 1 10502
Protoss_Photon_Cannon 2 10398
Protoss_High_Templar 2 10746
10746
