Protoss_Gateway 2 9630
Protoss_Zealot 12 10896
Protoss_Forge 1 3851
Protoss_Photon_Cannon 3 5307
Protoss_Assimilator 1 5317
Protoss_Cybernetics_Core 1 8150
Protoss_Dragoon 1 8901
Protoss_Citadel_of_Adun 1 9228
Protoss_Ground_Weapons_1 1 9896
10896
