Protoss_Forge 1 3076
Protoss_Photon_Cannon 3 10937
Protoss_Nexus 1 8039
Protoss_Gateway 2 7188
Protoss_Assimilator 1 7020
Protoss_Zealot 11 10636
Protoss_Cybernetics_Core 1 10418
Protoss_Citadel_of_Adun 1 11408
11408
