Protoss_Nexus 1 5705
Protoss_Forge 1 4209
Protoss_Gateway 2 10842
Protoss_Photon_Cannon 7 10413
Protoss_Assimilator 2 7547
Protoss_Zealot 4 9177
Protoss_Cybernetics_Core 1 6847
Protoss_Stargate 1 8250
Protoss_Citadel_of_Adun 1 8593
Protoss_Dragoon 1 8665
Protoss_Corsair 4 10619
Protoss_Templar_Archives 1 10013
Protoss_High_Templar 1 11025
Protoss_Dark_Templar 1 11153
11153
