Protoss_Forge 1 3182
Protoss_Photon_Cannon 4 10987
Protoss_Nexus 1 6887
Protoss_Gateway 2 10215
Protoss_Assimilator 2 8197
Protoss_Zealot 6 10921
Protoss_Cybernetics_Core 1 7050
Protoss_Stargate 1 8578
Protoss_Citadel_of_Adun 1 8537
Protoss_Corsair 2 9975
Protoss_Templar_Archives 1 11017
11017
