Protoss_Forge 1 3476
Protoss_Nexus 1 6111
Protoss_Photon_Cannon 5 11095
Protoss_Gateway 3 8606
Protoss_Assimilator 2 7345
Protoss_Zealot 11 10485
Protoss_Cybernetics_Core 1 6979
Protoss_Dragoon 2 9363
Protoss_Citadel_of_Adun 1 8175
Protoss_Templar_Archives 1 10248
11095
