Protoss_Gateway 2 6979
Protoss_Assimilator 1 3463
Protoss_Zealot 10 10435
Protoss_Cybernetics_Core 1 4869
Protoss_Dragoon 1 5675
Protoss_Citadel_of_Adun 1 6271
Protoss_Templar_Archives 1 8085
Protoss_High_Templar 4 9923
Protoss_Nexus 1 11395
Protoss_Forge 1 9613
Protoss_Archon 2 10014
Protoss_Photon_Cannon 2 11046
11395
