Protoss_Forge 1 3350
Protoss_Nexus 1 6155
Protoss_Photon_Cannon 4 10933
Protoss_Gateway 3 10625
Protoss_Assimilator 2 8868
Protoss_Zealot 4 10305
Protoss_Cybernetics_Core 1 7804
Protoss_Stargate 1 9086
Protoss_Dragoon 1 8785
Protoss_Citadel_of_Adun 1 9288
Protoss_Corsair 1 9495
Protoss_Templar_Archives 1 10392
Protoss_Dark_Templar 1 11147
Protoss_High_Templar 1 11147
11147
