Protoss_Forge 1 2861
Protoss_Photon_Cannon 4 10957
Protoss_Nexus 1 7197
Protoss_Gateway 2 9914
Protoss_Assimilator 2 8025
Protoss_Cybernetics_Core 1 7152
Protoss_Zealot 4 9681
Protoss_Dragoon 1 7965
Protoss_Stargate 1 8548
Protoss_Citadel_of_Adun 1 9046
Protoss_Corsair 2 10731
Protoss_Templar_Archives 1 10397
10957
