Protoss_Forge 1 3425
Protoss_Photon_Cannon 4 10543
Protoss_Nexus 1 6929
Protoss_Gateway 3 9816
Protoss_Assimilator 2 8298
Protoss_Cybernetics_Core 1 6773
Protoss_Zealot 7 10915
Protoss_Citadel_of_Adun 1 7831
Protoss_Dragoon 1 7945
Protoss_Templar_Archives 1 9463
Protoss_High_Templar 2 10249
Protoss_Dark_Templar 1 10573
Protoss_Robotics_Facility 1 11643
11643
