Protoss_Forge 1 3089
Protoss_Photon_Cannon 4 11149
Protoss_Nexus 1 6783
Protoss_Gateway 4 9680
Protoss_Assimilator 2 8270
Protoss_Zealot 7 9969
Protoss_Cybernetics_Core 1 7070
Protoss_Dragoon 1 7995
Protoss_Citadel_of_Adun 1 8546
Protoss_Templar_Archives 1 10038
Protoss_High_Templar 1 10777
11149
