Protoss_Gateway 2 4050
Protoss_Zealot 10 8695
Protoss_Assimilator 1 5619
Protoss_Cybernetics_Core 1 7019
Protoss_Citadel_of_Adun 1 8308
Protoss_Stargate 1 8926
Protoss_Dragoon 1 8523
Protoss_Templar_Archives 1 9561
Protoss_Corsair 1 9345
Protoss_Forge 1 9602
Protoss_Nexus 1 12225
Protoss_Dark_Templar 2 11063
12225
