Protoss_Forge 1 3616
Protoss_Nexus 1 6263
Protoss_Photon_Cannon 6 11088
Protoss_Gateway 1 5699
Protoss_Zealot 4 9197
Protoss_Assimilator 2 10371
Protoss_Cybernetics_Core 1 8120
Protoss_Stargate 1 9439
Protoss_Dragoon 1 10039
Protoss_Corsair 2 10579
Protoss_Robotics_Facility 1 11294
11294
