Protoss_Forge 1 3459
Protoss_Photon_Cannon 6 11145
Protoss_Nexus 1 7195
Protoss_Gateway 4 10691
Protoss_Assimilator 2 7863
Protoss_Zealot 5 10609
Protoss_Cybernetics_Core 1 8035
Protoss_Citadel_of_Adun 1 9083
Protoss_Dragoon 1 9075
Protoss_Templar_Archives 1 10189
11145
