Protoss_Forge 1 2999
Protoss_Photon_Cannon 5 10911
Protoss_Nexus 1 6686
Protoss_Gateway 1 5455
Protoss_Zealot 3 8183
Protoss_Assimilator 2 7883
Protoss_Cybernetics_Core 1 7836
Protoss_Stargate 2 10901
Protoss_Robotics_Facility 1 10311
Protoss_Corsair 2 10435
10911
