Protoss_Assimilator 1 2768
Protoss_Gateway 1 3758
Protoss_Cybernetics_Core 1 4766
Protoss_Stargate 1 6023
Protoss_Robotics_Facility 1 6803
Protoss_Corsair 6 10435
Protoss_Shuttle 1 7891
Protoss_Forge 1 7934
Protoss_Photon_Cannon 2 10827
Protoss_Nexus 1 11754
Protoss_Air_Weapons_1 1 9681
11754
