Protoss_Gateway 1 3553
Protoss_Assimilator 1 3513
Protoss_Zealot 8 10551
Protoss_Cybernetics_Core 1 5223
Protoss_Robotics_Facility 1 7112
Protoss_Dragoon 1 6576
Protoss_Shuttle 2 11321
Protoss_Robotics_Support_Bay 1 7492
Protoss_Shield_Battery 1 7973
Protoss_Reaver 2 10280
Protoss_Citadel_of_Adun 1 10182
Protoss_Scarab 3 9890
11321
