Protoss_Forge 1 3433
Protoss_Photon_Cannon 4 10981
Protoss_Nexus 1 7157
Protoss_Gateway 3 10907
Protoss_Assimilator 2 8565
Protoss_Zealot 1 7589
Protoss_Cybernetics_Core 1 8445
Protoss_Stargate 1 9673
Protoss_Citadel_of_Adun 1 9940
Protoss_Corsair 2 10813
Protoss_Templar_Archives 1 11109
11109
