Protoss_Gateway 2 4053
Protoss_Zealot 7 8286
Protoss_Assimilator 1 5756
Protoss_Cybernetics_Core 1 6777
Protoss_Dragoon 1 7531
Protoss_Stargate 1 8627
Protoss_Citadel_of_Adun 1 9132
Protoss_Corsair 1 9046
Protoss_Forge 1 9391
Protoss_Templar_Archives 1 10251
Protoss_Nexus 1 12623
Protoss_Photon_Cannon 1 11108
12623
