Protoss_Forge 1 3043
Protoss_Photon_Cannon 6 11166
Protoss_Nexus 1 7453
Protoss_Gateway 3 9948
Protoss_Assimilator 2 7557
Protoss_Cybernetics_Core 1 8158
Protoss_Zealot 3 9859
Protoss_Citadel_of_Adun 1 9216
Protoss_Dragoon 1 9289
Protoss_Templar_Archives 1 10257
Protoss_High_Templar 2 11073
Protoss_Dark_Templar 1 11083
11166
