Protoss_Forge 1 3125
Protoss_Photon_Cannon 6 10760
Protoss_Nexus 1 6647
Protoss_Gateway 4 11350
Protoss_Assimilator 2 8265
Protoss_Cybernetics_Core 1 7258
Protoss_Zealot 4 10261
Protoss_Stargate 1 8493
Protoss_Citadel_of_Adun 1 8573
Protoss_Corsair 1 8925
Protoss_Templar_Archives 1 10754
11350
