Protoss_Forge 2 4174
Protoss_Nexus 1 5830
Protoss_Photon_Cannon 7 10331
Protoss_Gateway 2 10381
Protoss_Assimilator 2 7848
Protoss_Zealot 5 10331
Protoss_Cybernetics_Core 1 7485
Protoss_Stargate 1 8898
Protoss_Citadel_of_Adun 1 9629
Protoss_Corsair 1 9321
Protoss_Templar_Archives 1 11007
11007
