Protoss_Gateway 2 3798
Protoss_Zealot 11 8943
Protoss_Assimilator 1 5396
Protoss_Forge 1 5863
Protoss_Photon_Cannon 2 10209
Protoss_Cybernetics_Core 1 8278
Protoss_Stargate 1 9963
Protoss_Dragoon 2 10461
Protoss_Corsair 1 10381
Protoss_Citadel_of_Adun 1 11143
Protoss_Ground_Weapons_1 1 9811
11143
