Protoss_Gateway 2 8025
Protoss_Assimilator 1 3316
Protoss_Zealot 9 10927
Protoss_Cybernetics_Core 1 5050
Protoss_Dragoon 1 5805
Protoss_Stargate 1 6454
Protoss_Citadel_of_Adun 1 6675
Protoss_Corsair 3 8499
Protoss_Templar_Archives 1 8167
Protoss_Dark_Templar 1 8971
Protoss_Forge 1 9595
10927
