Protoss_Forge 1 3335
Protoss_Nexus 1 6099
Protoss_Photon_Cannon 2 4981
Protoss_Assimilator 2 7068
Protoss_Gateway 2 10207
Protoss_Zealot 5 9573
Protoss_Cybernetics_Core 1 6823
Protoss_Dragoon 1 7563
Protoss_Stargate 1 8239
Protoss_Citadel_of_Adun 1 9084
Protoss_Corsair 4 10623
Protoss_Templar_Archives 1 10194
Protoss_Dark_Templar 2 10979
10979
