Protoss_Gateway 2 6856
Protoss_Zealot 5 7833
Protoss_Assimilator 1 4035
Protoss_Cybernetics_Core 1 5259
Protoss_Dragoon 1 6011
Protoss_Citadel_of_Adun 1 6529
Protoss_Templar_Archives 1 7715
Protoss_Nexus 1 10055
Protoss_High_Templar 4 10277
Protoss_Forge 1 8697
Protoss_Archon 1 8757
Protoss_Photon_Cannon 6 11119
11119
