Protoss_Gateway 2 4120
Protoss_Zealot 11 10101
Protoss_Assimilator 1 5285
Protoss_Forge 1 7249
Protoss_Cybernetics_Core 1 8039
Protoss_Citadel_of_Adun 1 9033
Protoss_Photon_Cannon 3 11178
Protoss_Templar_Archives 1 10082
Protoss_High_Templar 2 10943
11178
