Protoss_Forge 1 4004
Protoss_Nexus 1 6497
Protoss_Photon_Cannon 6 8941
Protoss_Gateway 4 10608
Protoss_Assimilator 2 7493
Protoss_Cybernetics_Core 1 7772
Protoss_Stargate 1 9583
Protoss_Corsair 2 10691
Protoss_Citadel_of_Adun 1 10572
Protoss_Dragoon 2 10731
10731
