Protoss_Forge 1 2857
Protoss_Photon_Cannon 6 9746
Protoss_Nexus 1 7300
Protoss_Gateway 1 6089
Protoss_Assimilator 2 8168
Protoss_Cybernetics_Core 1 7115
Protoss_Zealot 3 8775
Protoss_Stargate 1 8481
Protoss_Robotics_Facility 1 9651
Protoss_Corsair 3 10343
Protoss_Shuttle 1 10525
Protoss_Robotics_Support_Bay 1 9971
10525
