Protoss_Forge 1 2953
Protoss_Nexus 1 6405
Protoss_Gateway 5 10320
Protoss_Photon_Cannon 2 5609
Protoss_Assimilator 2 7944
Protoss_Cybernetics_Core 1 6851
Protoss_Zealot 9 10777
Protoss_Citadel_of_Adun 1 8796
Protoss_Stargate 1 9085
Protoss_Corsair 2 10811
Protoss_Templar_Archives 1 10583
10811
