Protoss_Forge 1 3854
Protoss_Nexus 1 6398
Protoss_Photon_Cannon 8 11097
Protoss_Gateway 3 10853
Protoss_Assimilator 2 7963
Protoss_Cybernetics_Core 1 7591
Protoss_Zealot 5 10153
Protoss_Stargate 1 8881
Protoss_Citadel_of_Adun 1 9568
Protoss_Corsair 3 10647
Protoss_Templar_Archives 1 10566
11097
