Protoss_Forge 1 3024
Protoss_Nexus 1 6061
Protoss_Photon_Cannon 4 9986
Protoss_Gateway 2 10670
Protoss_Assimilator 2 9583
Protoss_Zealot 5 10827
Protoss_Cybernetics_Core 1 7730
Protoss_Stargate 1 8963
Protoss_Citadel_of_Adun 1 8923
Protoss_Dragoon 1 9133
Protoss_Corsair 1 9535
Protoss_Templar_Archives 1 10504
10827
