Protoss_Forge 1 3526
Protoss_Nexus 1 6146
Protoss_Photon_Cannon 3 9893
Protoss_Gateway 4 10728
Protoss_Assimilator 2 7249
Protoss_Cybernetics_Core 1 6653
Protoss_Zealot 7 10025
Protoss_Stargate 1 8133
Protoss_Citadel_of_Adun 1 8640
Protoss_Corsair 2 9801
Protoss_Templar_Archives 1 9757
10728
