Protoss_Forge 1 3223
Protoss_Photon_Cannon 2 6265
Protoss_Nexus 1 7023
Protoss_Gateway 4 8725
Protoss_Assimilator 1 5936
Protoss_Zealot 13 10655
Protoss_Cybernetics_Core 1 7897
Protoss_Citadel_of_Adun 1 9996
10655
