Protoss_Gateway 2 9938
Protoss_Assimilator 1 3310
Protoss_Zealot 7 10481
Protoss_Cybernetics_Core 1 5157
Protoss_Stargate 1 6419
Protoss_Dragoon 1 6177
Protoss_Citadel_of_Adun 1 6779
Protoss_Corsair 1 6855
Protoss_Templar_Archives 1 7927
Protoss_Forge 1 8091
Protoss_Dark_Templar 2 9439
Protoss_Photon_Cannon 3 11094
Protoss_Nexus 1 12698
12698
