Protoss_Forge 2 10776
Protoss_Photon_Cannon 5 10901
Protoss_Nexus 1 6885
Protoss_Gateway 2 9095
Protoss_Assimilator 2 7561
Protoss_Cybernetics_Core 1 6725
Protoss_Zealot 5 9691
Protoss_Stargate 1 7963
Protoss_Citadel_of_Adun 1 8605
Protoss_Corsair 3 10553
Protoss_Templar_Archives 1 10513
10901
