Protoss_Forge 1 2865
Protoss_Photon_Cannon 6 10343
Protoss_Nexus 1 6661
Protoss_Gateway 2 11377
Protoss_Zealot 4 7883
Protoss_Assimilator 2 8237
Protoss_Cybernetics_Core 1 8110
Protoss_Stargate 1 9397
Protoss_Citadel_of_Adun 1 9732
Protoss_Corsair 1 9849
Protoss_Templar_Archives 1 10765
11377
