Protoss_Forge 2 4505
Protoss_Nexus 1 5901
Protoss_Gateway 5 11436
Protoss_Photon_Cannon 6 11045
Protoss_Assimilator 2 7017
Protoss_Zealot 8 10927
Protoss_Cybernetics_Core 1 6639
Protoss_Stargate 1 7936
Protoss_Citadel_of_Adun 1 8037
Protoss_Templar_Archives 1 9090
Protoss_Corsair 1 8657
Protoss_High_Templar 4 11109
11436
