Protoss_Gateway 2 3905
Protoss_Zealot 15 9971
Protoss_Assimilator 1 6769
Protoss_Cybernetics_Core 1 9135
Protoss_Forge 1 8848
Protoss_Stargate 1 10416
Protoss_Dragoon 1 10093
Protoss_Citadel_of_Adun 1 10881
10881
