Protoss_Forge 1 3430
Protoss_Nexus 1 6126
Protoss_Photon_Cannon 4 10981
Protoss_Gateway 4 10892
Protoss_Assimilator 2 7728
Protoss_Cybernetics_Core 1 7061
Protoss_Zealot 3 9199
Protoss_Dragoon 1 7821
Protoss_Stargate 1 8322
Protoss_Citadel_of_Adun 1 8423
Protoss_Corsair 2 9489
Protoss_Templar_Archives 1 9454
Protoss_Dark_Templar 2 10525
10981
