Protoss_Forge 1 3138
Protoss_Photon_Cannon 3 10332
Protoss_Nexus 1 6948
Protoss_Gateway 1 5807
Protoss_Assimilator 2 7500
Protoss_Cybernetics_Core 1 6803
Protoss_Zealot 1 6407
Protoss_Stargate 1 8033
Protoss_Dragoon 2 9741
Protoss_Robotics_Facility 1 9341
Protoss_Corsair 4 10837
Protoss_Shuttle 1 10211
Protoss_Robotics_Support_Bay 1 9694
Protoss_Reaver 1 11353
11353
