Protoss_Forge 1 3128
Protoss_Nexus 1 6165
Protoss_Gateway 3 9871
Protoss_Photon_Cannon 1 5553
Protoss_Assimilator 2 7078
Protoss_Zealot 5 10787
Protoss_Cybernetics_Core 1 6629
Protoss_Stargate 1 8063
Protoss_Dragoon 1 7781
Protoss_Citadel_of_Adun 1 8470
Protoss_Corsair 2 9467
Protoss_Templar_Archives 1 9497
Protoss_High_Templar 2 10299
10787
