Protoss_Gateway 1 3320
Protoss_Assimilator 2 10860
Protoss_Zealot 3 6609
Protoss_Cybernetics_Core 1 5290
Protoss_Stargate 1 6526
Protoss_Dragoon 1 6097
Protoss_Citadel_of_Adun 1 6801
Protoss_Corsair 1 7073
Protoss_Templar_Archives 1 8058
Protoss_Forge 1 8167
Protoss_Dark_Templar 1 9003
Protoss_Nexus 1 11149
Protoss_High_Templar 2 10737
Protoss_Photon_Cannon 3 10911
11149
