Protoss_Gateway 2 3863
Protoss_Zealot 15 9366
Protoss_Assimilator 1 6647
Protoss_Cybernetics_Core 1 9333
Protoss_Forge 1 9736
Protoss_Dragoon 2 10461
Protoss_Photon_Cannon 1 10857
10857
