Protoss_Forge 1 2981
Protoss_Photon_Cannon 6 10921
Protoss_Nexus 1 7287
Protoss_Gateway 4 10581
Protoss_Assimilator 2 7846
Protoss_Zealot 3 9575
Protoss_Cybernetics_Core 1 7519
Protoss_Citadel_of_Adun 1 8689
Protoss_Dragoon 1 9029
Protoss_Templar_Archives 1 9919
Protoss_High_Templar 2 11015
11015
