Protoss_Gateway 1 3335
Protoss_Assimilator 1 3353
Protoss_Zealot 5 7427
Protoss_Cybernetics_Core 1 5187
Protoss_Stargate 1 6506
Protoss_Dragoon 1 6313
Protoss_Corsair 3 8649
Protoss_Citadel_of_Adun 1 7442
Protoss_Templar_Archives 1 8554
Protoss_Forge 1 8478
Protoss_Dark_Templar 2 10406
Protoss_Photon_Cannon 2 10778
Protoss_Nexus 1 12206
Protoss_High_Templar 1 11177
12206
