Protoss_Forge 1 3284
Protoss_Photon_Cannon 4 10351
Protoss_Nexus 1 6639
Protoss_Gateway 1 5428
Protoss_Assimilator 2 8083
Protoss_Zealot 4 8549
Protoss_Cybernetics_Core 1 6983
Protoss_Stargate 1 8537
Protoss_Corsair 3 10581
Protoss_Robotics_Facility 1 10393
Protoss_Observatory 1 10511
Protoss_Robotics_Support_Bay 1 10670
10670
