Protoss_Gateway 1 3113
Protoss_Zealot 10 10370
Protoss_Assimilator 1 4467
Protoss_Forge 1 5858
Protoss_Cybernetics_Core 1 7673
Protoss_Citadel_of_Adun 1 8683
Protoss_Dragoon 1 9858
Protoss_Photon_Cannon 2 10638
Protoss_Templar_Archives 1 11083
Protoss_Ground_Weapons_1 1 9661
11083
