Protoss_Forge 1 3335
Protoss_Photon_Cannon 6 10448
Protoss_Nexus 1 7077
Protoss_Gateway 3 11145
Protoss_Assimilator 2 8205
Protoss_Cybernetics_Core 1 6887
Protoss_Zealot 4 10359
Protoss_Stargate 1 8401
Protoss_Citadel_of_Adun 1 9043
Protoss_Corsair 3 10831
Protoss_Templar_Archives 1 10443
11145
