Protoss_Forge 2 4475
Protoss_Nexus 1 6093
Protoss_Gateway 2 11143
Protoss_Photon_Cannon 2 5731
Protoss_Zealot 5 10489
Protoss_Assimilator 2 9047
Protoss_Cybernetics_Core 1 8487
Protoss_Stargate 1 9967
Protoss_Citadel_of_Adun 1 10445
Protoss_Corsair 1 10385
11143
