Protoss_Gateway 2 7550
Protoss_Assimilator 1 3343
Protoss_Zealot 7 8201
Protoss_Cybernetics_Core 1 5218
Protoss_Citadel_of_Adun 1 6760
Protoss_Templar_Archives 1 8457
Protoss_Forge 1 9021
Protoss_High_Templar 4 11031
Protoss_Archon 1 9589
Protoss_Nexus 1 12108
Protoss_Dark_Templar 1 10481
Protoss_Photon_Cannon 2 10883
12108
