Protoss_Forge 1 3130
Protoss_Photon_Cannon 4 11178
Protoss_Nexus 1 6971
Protoss_Gateway 3 11135
Protoss_Assimilator 2 7946
Protoss_Zealot 3 10333
Protoss_Cybernetics_Core 1 6955
Protoss_Stargate 1 8296
Protoss_Citadel_of_Adun 1 8809
Protoss_Dragoon 1 8861
Protoss_Corsair 3 10199
Protoss_Templar_Archives 1 10577
11178
