Protoss_Gateway 1 3601
Protoss_Assimilator 1 3826
Protoss_Zealot 3 5496
Protoss_Cybernetics_Core 1 5630
Protoss_Citadel_of_Adun 1 6956
Protoss_Dragoon 1 6896
Protoss_Forge 1 7113
Protoss_Templar_Archives 1 8086
Protoss_Photon_Cannon 3 10748
Protoss_Nexus 1 11168
Protoss_High_Templar 2 10993
11168
