Protoss_Forge 1 3178
Protoss_Photon_Cannon 5 9767
Protoss_Nexus 1 6433
Protoss_Gateway 4 8757
Protoss_Assimilator 1 5806
Protoss_Zealot 13 10561
Protoss_Cybernetics_Core 1 7140
Protoss_Dragoon 1 7989
Protoss_Citadel_of_Adun 1 8406
10561
