Protoss_Gateway 2 4093
Protoss_Zealot 9 7736
Protoss_Assimilator 1 5128
Protoss_Cybernetics_Core 1 6138
Protoss_Stargate 1 8073
Protoss_Citadel_of_Adun 1 8583
Protoss_Corsair 2 9178
Protoss_Templar_Archives 1 9643
Protoss_Dark_Templar 2 10426
Protoss_Nexus 1 12817
12817
