Protoss_Nexus 1 5760
Protoss_Gateway 3 8830
Protoss_Forge 1 4595
Protoss_Assimilator 2 9565
Protoss_Photon_Cannon 3 9911
Protoss_Cybernetics_Core 1 6037
Protoss_Zealot 10 10559
Protoss_Dragoon 1 7067
Protoss_Stargate 1 7585
Protoss_Citadel_of_Adun 1 8416
Protoss_Corsair 4 10635
Protoss_Templar_Archives 1 10928
10928
