Protoss_Nexus 1 5991
Protoss_Forge 1 4488
Protoss_Gateway 3 11147
Protoss_Photon_Cannon 4 10287
Protoss_Assimilator 2 6951
Protoss_Cybernetics_Core 1 7078
Protoss_Zealot 5 9709
Protoss_Stargate 1 8368
Protoss_Citadel_of_Adun 1 8479
Protoss_Templar_Archives 1 9627
Protoss_Corsair 2 9845
11147
