Protoss_Gateway 2 3907
Protoss_Zealot 12 8697
Protoss_Nexus 1 9885
Protoss_Assimilator 1 8508
Protoss_Cybernetics_Core 1 9773
Protoss_Stargate 1 11028
Protoss_Forge 1 10504
11028
