Protoss_Gateway 3 10135
Protoss_Zealot 11 9915
Protoss_Assimilator 1 6476
Protoss_Forge 1 7343
Protoss_Cybernetics_Core 1 8664
Protoss_Photon_Cannon 1 8971
Protoss_Citadel_of_Adun 1 9875
10135
