Protoss_Forge 3 5271
Protoss_Nexus 1 5948
Protoss_Gateway 3 10304
Protoss_Assimilator 1 5889
Protoss_Zealot 12 10733
Protoss_Photon_Cannon 2 10329
Protoss_Cybernetics_Core 1 8429
Protoss_Stargate 1 10014
Protoss_Citadel_of_Adun 1 9897
Protoss_Corsair 1 10785
10785
