Protoss_Gateway 1 3363
Protoss_Assimilator 1 3393
Protoss_Zealot 4 8189
Protoss_Cybernetics_Core 1 5173
Protoss_Dragoon 1 5981
Protoss_Stargate 1 6826
Protoss_Citadel_of_Adun 1 6945
Protoss_Corsair 1 7385
Protoss_Templar_Archives 1 8095
Protoss_Forge 1 8501
Protoss_Dark_Templar 1 9141
Protoss_Photon_Cannon 4 10496
Protoss_High_Templar 2 10645
10645
