Protoss_Gateway 2 10595
Protoss_Assimilator 1 3415
Protoss_Zealot 5 10437
Protoss_Cybernetics_Core 1 5471
Protoss_Dragoon 1 6223
Protoss_Robotics_Facility 1 7213
Protoss_Forge 1 7517
Protoss_Shuttle 1 8033
Protoss_Robotics_Support_Bay 1 7747
Protoss_Citadel_of_Adun 1 8563
Protoss_Reaver 1 9239
Protoss_Templar_Archives 1 9681
Protoss_Photon_Cannon 2 10813
Protoss_High_Templar 1 10715
10813
