Protoss_Gateway 1 3533
Protoss_Assimilator 1 3578
Protoss_Cybernetics_Core 1 4756
Protoss_Zealot 3 6346
Protoss_Stargate 1 6102
Protoss_Corsair 1 6701
Protoss_Forge 1 7198
Protoss_Citadel_of_Adun 1 8470
Protoss_Photon_Cannon 4 10451
Protoss_Nexus 1 10906
Protoss_Robotics_Facility 1 11651
11651
