Protoss_Gateway 3 9675
Protoss_Assimilator 1 3490
Protoss_Zealot 12 10501
Protoss_Cybernetics_Core 1 5345
Protoss_Stargate 1 6591
Protoss_Forge 1 6335
Protoss_Citadel_of_Adun 1 7378
Protoss_Corsair 2 7779
Protoss_Templar_Archives 1 11050
11050
