Protoss_Gateway 2 7525
Protoss_Zealot 8 9473
Protoss_Assimilator 1 4110
Protoss_Cybernetics_Core 1 5339
Protoss_Dragoon 1 6155
Protoss_Citadel_of_Adun 1 6731
Protoss_Templar_Archives 1 7772
Protoss_Forge 1 8481
Protoss_High_Templar 3 11053
Protoss_Archon 1 9079
Protoss_Photon_Cannon 3 10039
Protoss_Dark_Templar 2 10315
11053
