Protoss_Forge 1 3164
Protoss_Photon_Cannon 2 4373
Protoss_Nexus 1 7020
Protoss_Gateway 1 6105
Protoss_Assimilator 2 8397
Protoss_Zealot 6 10717
Protoss_Cybernetics_Core 1 7267
Protoss_Stargate 1 8583
Protoss_Dragoon 1 8167
Protoss_Citadel_of_Adun 1 8685
Protoss_Corsair 1 9253
Protoss_Templar_Archives 1 10606
10717
