Protoss_Forge 1 3079
Protoss_Photon_Cannon 2 5288
Protoss_Nexus 1 6634
Protoss_Gateway 2 9167
Protoss_Assimilator 2 7858
Protoss_Cybernetics_Core 1 7065
Protoss_Zealot 9 10623
Protoss_Stargate 1 8317
Protoss_Citadel_of_Adun 1 8634
Protoss_Corsair 3 10791
Protoss_Templar_Archives 1 10418
10791
