Protoss_Gateway 2 7773
Protoss_Assimilator 1 3486
Protoss_Zealot 8 9416
Protoss_Cybernetics_Core 1 5398
Protoss_Dragoon 1 6156
Protoss_Citadel_of_Adun 1 7232
Protoss_Templar_Archives 1 8778
Protoss_Forge 1 9283
Protoss_Dark_Templar 1 9992
Protoss_High_Templar 2 10925
Protoss_Photon_Cannon 1 10406
10925
