Protoss_Forge 1 3199
Protoss_Photon_Cannon 3 11052
Protoss_Nexus 1 6853
Protoss_Gateway 1 5995
Protoss_Assimilator 2 7092
Protoss_Cybernetics_Core 1 6985
Protoss_Zealot 6 10591
Protoss_Dragoon 1 7749
Protoss_Stargate 1 8398
Protoss_Robotics_Facility 1 9166
Protoss_Corsair 3 10015
Protoss_Robotics_Support_Bay 1 9303
Protoss_Reaver 1 10987
11052
