Protoss_Forge 1 3357
Protoss_Photon_Cannon 4 6581
Protoss_Nexus 1 6997
Protoss_Gateway 2 10054
Protoss_Assimilator 2 7863
Protoss_Zealot 6 10559
Protoss_Cybernetics_Core 1 7767
Protoss_Stargate 1 9015
Protoss_Dragoon 1 8753
Protoss_Citadel_of_Adun 1 9372
Protoss_Corsair 3 10919
10919
