Protoss_Forge 1 3139
Protoss_Nexus 2 12795
Protoss_Photon_Cannon 3 10711
Protoss_Gateway 3 9057
Protoss_Assimilator 2 7467
Protoss_Cybernetics_Core 1 6615
Protoss_Zealot 3 10321
Protoss_Stargate 1 7855
Protoss_Citadel_of_Adun 1 7776
Protoss_Corsair 2 9067
Protoss_Templar_Archives 1 8978
Protoss_Dark_Templar 2 9907
12795
