Protoss_Gateway 2 6363
Protoss_Assimilator 1 3860
Protoss_Forge 1 4025
Protoss_Photon_Cannon 3 11039
Protoss_Zealot 11 9091
Protoss_Cybernetics_Core 1 8028
Protoss_Citadel_of_Adun 1 9240
Protoss_Ground_Weapons_1 1 8336
Protoss_Templar_Archives 1 10702
11039
