Protoss_Forge 1 3161
Protoss_Nexus 1 6180
Protoss_Gateway 4 9515
Protoss_Photon_Cannon 2 5861
Protoss_Assimilator 2 7559
Protoss_Zealot 13 10905
Protoss_Cybernetics_Core 1 7319
Protoss_Stargate 1 8653
Protoss_Dragoon 1 8317
Protoss_Citadel_of_Adun 1 8715
Protoss_Templar_Archives 1 10025
10905
