Protoss_Gateway 1 3003
Protoss_Zealot 4 10441
Protoss_Assimilator 1 4784
Protoss_Forge 1 5634
Protoss_Photon_Cannon 3 10099
Protoss_Cybernetics_Core 1 7030
Protoss_Dragoon 2 10766
Protoss_Stargate 1 8511
Protoss_Robotics_Facility 1 9566
Protoss_Corsair 1 8976
Protoss_Shuttle 1 10436
Protoss_Robotics_Support_Bay 1 10053
Protoss_Ground_Weapons_1 1 9876
Protoss_Reaver 1 11578
11578
