Protoss_Gateway 4 11217
Protoss_Zealot 10 10393
Protoss_Nexus 1 7709
Protoss_Assimilator 1 6476
Protoss_Cybernetics_Core 1 7973
Protoss_Dragoon 2 9089
Protoss_Citadel_of_Adun 1 9203
Protoss_Templar_Archives 1 10554
Protoss_Forge 1 10488
11217
