Protoss_Assimilator 1 2750
Protoss_Gateway 1 3621
Protoss_Cybernetics_Core 1 4689
Protoss_Dragoon 3 10999
Protoss_Stargate 1 6040
Protoss_Corsair 6 10439
Protoss_Robotics_Facility 1 7716
Protoss_Forge 1 7377
Protoss_Shuttle 1 8985
Protoss_Photon_Cannon 1 9117
Protoss_Air_Weapons_1 1 8701
Protoss_Nexus 1 12230
12230
