Protoss_Forge 1 2915
Protoss_Nexus 1 6193
Protoss_Gateway 3 9905
Protoss_Photon_Cannon 2 6259
Protoss_Assimilator 2 7437
Protoss_Cybernetics_Core 1 6285
Protoss_Zealot 2 9245
Protoss_Stargate 1 7889
Protoss_Citadel_of_Adun 1 8137
Protoss_Dragoon 1 8193
Protoss_Corsair 2 9529
Protoss_Templar_Archives 1 9338
Protoss_Dark_Templar 1 10087
Protoss_High_Templar 1 10653
10653
