Protoss_Gateway 2 3997
Protoss_Zealot 7 8491
Protoss_Assimilator 1 5086
Protoss_Cybernetics_Core 2 6155
Protoss_Forge 1 6285
Protoss_Photon_Cannon 3 9101
Protoss_Citadel_of_Adun 1 8569
Protoss_Templar_Archives 1 9611
Protoss_Dark_Templar 2 10363
Protoss_Robotics_Facility 1 11509
11509
