Protoss_Assimilator 1 2759
Protoss_Gateway 1 3724
Protoss_Cybernetics_Core 1 4711
Protoss_Stargate 1 5947
Protoss_Dragoon 2 7273
Protoss_Robotics_Facility 1 7214
Protoss_Corsair 6 10601
Protoss_Shuttle 1 8013
Protoss_Forge 1 8196
Protoss_Photon_Cannon 2 10235
10601
