Protoss_Gateway 1 3338
Protoss_Assimilator 1 3466
Protoss_Zealot 4 10436
Protoss_Cybernetics_Core 1 5325
Protoss_Dragoon 1 6151
Protoss_Robotics_Facility 1 7591
Protoss_Forge 1 7568
Protoss_Robotics_Support_Bay 1 8021
Protoss_Reaver 1 9541
10436
