Protoss_Gateway 3 10549
Protoss_Assimilator 1 3446
Protoss_Cybernetics_Core 1 4722
Protoss_Stargate 1 5984
Protoss_Forge 1 5473
Protoss_Photon_Cannon 1 6452
Protoss_Corsair 1 6401
Protoss_Zealot 7 10686
Protoss_Citadel_of_Adun 1 7951
Protoss_Templar_Archives 1 10809
10809
