Protoss_Nexus 1 6263
Protoss_Forge 1 4664
Protoss_Gateway 3 9873
Protoss_Photon_Cannon 6 10287
Protoss_Assimilator 2 8458
Protoss_Cybernetics_Core 1 7260
Protoss_Zealot 6 10561
Protoss_Stargate 1 8800
Protoss_Citadel_of_Adun 1 8822
Protoss_Corsair 2 10307
Protoss_Templar_Archives 1 10696
10696
