Protoss_Forge 1 3229
Protoss_Nexus 1 6119
Protoss_Photon_Cannon 6 10634
Protoss_Gateway 4 11331
Protoss_Assimilator 2 7375
Protoss_Cybernetics_Core 1 6558
Protoss_Zealot 4 10015
Protoss_Stargate 1 7893
Protoss_Dragoon 1 7505
Protoss_Citadel_of_Adun 1 8191
Protoss_Corsair 1 8719
Protoss_Templar_Archives 1 9699
Protoss_Dark_Templar 2 10567
11331
