Protoss_Forge 1 3499
Protoss_Nexus 1 6230
Protoss_Photon_Cannon 4 10592
Protoss_Gateway 3 10991
Protoss_Assimilator 2 8019
Protoss_Zealot 3 8851
Protoss_Cybernetics_Core 1 6907
Protoss_Dragoon 1 8339
Protoss_Citadel_of_Adun 1 9057
Protoss_Templar_Archives 1 10310
Protoss_Dark_Templar 1 11175
Protoss_High_Templar 1 11185
11185
