Protoss_Forge 1 3578
Protoss_Photon_Cannon 5 7544
Protoss_Nexus 1 8368
Protoss_Gateway 4 10677
Protoss_Assimilator 2 8720
Protoss_Cybernetics_Core 1 8189
Protoss_Zealot 4 10653
Protoss_Citadel_of_Adun 1 9356
Protoss_Templar_Archives 1 10346
Protoss_Dark_Templar 2 11111
11111
