Protoss_Forge 2 4995
Protoss_Nexus 1 5919
Protoss_Gateway 3 10435
Protoss_Assimilator 2 7710
Protoss_Photon_Cannon 3 10448
Protoss_Zealot 5 9911
Protoss_Cybernetics_Core 1 7041
Protoss_Stargate 1 8468
Protoss_Citadel_of_Adun 1 9238
Protoss_Corsair 3 10901
Protoss_Templar_Archives 1 10239
Protoss_High_Templar 1 11115
11115
