Protoss_Forge 1 3264
Protoss_Photon_Cannon 7 10714
Protoss_Nexus 1 7348
Protoss_Gateway 3 7033
Protoss_Zealot 14 10931
Protoss_Assimilator 2 10378
Protoss_Cybernetics_Core 1 11258
11258
