Protoss_Forge 1 3336
Protoss_Photon_Cannon 2 4556
Protoss_Nexus 1 7049
Protoss_Gateway 4 9983
Protoss_Assimilator 2 7058
Protoss_Cybernetics_Core 1 6889
Protoss_Stargate 1 8146
Protoss_Citadel_of_Adun 1 8366
Protoss_Corsair 1 8571
Protoss_Templar_Archives 1 9386
Protoss_Dark_Templar 2 10287
Protoss_High_Templar 4 11067
Protoss_Zealot 1 10947
11067
