Protoss_Nexus 1 5864
Protoss_Forge 1 4423
Protoss_Photon_Cannon 7 8578
Protoss_Assimilator 1 7004
Protoss_Gateway 4 10791
Protoss_Zealot 2 8601
Protoss_Cybernetics_Core 1 9628
Protoss_Dragoon 2 10391
10791
