Protoss_Gateway 2 4051
Protoss_Zealot 13 10389
Protoss_Forge 1 6170
Protoss_Photon_Cannon 3 11015
Protoss_Nexus 1 9775
Protoss_Assimilator 1 8401
Protoss_Cybernetics_Core 1 9179
Protoss_Citadel_of_Adun 1 10277
Protoss_Templar_Archives 1 11424
11424
