Protoss_Forge 1 3449
Protoss_Photon_Cannon 6 10184
Protoss_Nexus 1 7174
Protoss_Gateway 3 11085
Protoss_Assimilator 2 8221
Protoss_Cybernetics_Core 1 7525
Protoss_Zealot 1 7449
Protoss_Stargate 1 8778
Protoss_Citadel_of_Adun 1 9468
Protoss_Corsair 3 10615
Protoss_Templar_Archives 1 10640
11085
