Protoss_Gateway 1 3392
Protoss_Zealot 8 10539
Protoss_Nexus 1 6938
Protoss_Assimilator 2 10266
Protoss_Cybernetics_Core 1 6335
Protoss_Forge 1 6251
Protoss_Photon_Cannon 2 8346
Protoss_Stargate 1 7913
Protoss_Corsair 2 9279
Protoss_Citadel_of_Adun 1 11168
11168
