Protoss_Gateway 2 9984
Protoss_Zealot 6 7068
Protoss_Forge 1 5298
Protoss_Photon_Cannon 4 7800
Protoss_Nexus 1 10823
Protoss_Assimilator 2 10228
Protoss_Cybernetics_Core 1 11245
11245
