Protoss_Forge 1 2874
Protoss_Nexus 1 5943
Protoss_Photon_Cannon 4 10863
Protoss_Gateway 4 10064
Protoss_Assimilator 2 7971
Protoss_Zealot 5 9911
Protoss_Cybernetics_Core 1 6761
Protoss_Stargate 1 8053
Protoss_Citadel_of_Adun 1 7934
Protoss_Corsair 1 8461
Protoss_Templar_Archives 1 9803
Protoss_High_Templar 2 10659
Protoss_Dark_Templar 1 10753
10863
