Protoss_Forge 1 3661
Protoss_Nexus 1 6163
Protoss_Photon_Cannon 2 6897
Protoss_Gateway 2 10191
Protoss_Assimilator 2 7199
Protoss_Cybernetics_Core 1 6870
Protoss_Stargate 1 8216
Protoss_Zealot 2 10135
Protoss_Citadel_of_Adun 1 9061
Protoss_Corsair 3 10061
Protoss_Templar_Archives 1 10113
Protoss_Dark_Templar 1 10943
Protoss_High_Templar 1 10977
10977
