Protoss_Gateway 2 3665
Protoss_Zealot 14 8619
Protoss_Assimilator 1 6019
Protoss_Cybernetics_Core 1 7629
Protoss_Dragoon 2 8943
Protoss_Stargate 1 9554
Protoss_Citadel_of_Adun 1 9520
Protoss_Forge 1 9665
Protoss_Corsair 2 10667
Protoss_Templar_Archives 1 10559
Protoss_Photon_Cannon 1 10837
10837
