Protoss_Nexus 1 5782
Protoss_Gateway 6 11341
Protoss_Forge 1 4673
Protoss_Assimilator 2 7644
Protoss_Photon_Cannon 2 8381
Protoss_Cybernetics_Core 1 6165
Protoss_Zealot 5 10321
Protoss_Stargate 1 7913
Protoss_Citadel_of_Adun 1 8732
Protoss_Corsair 2 9105
Protoss_Templar_Archives 1 9817
Protoss_Dark_Templar 1 11171
11341
