Protoss_Forge 1 3149
Protoss_Nexus 1 6406
Protoss_Photon_Cannon 4 11089
Protoss_Gateway 2 9812
Protoss_Assimilator 2 7581
Protoss_Zealot 6 9467
Protoss_Cybernetics_Core 1 6815
Protoss_Stargate 1 8186
Protoss_Citadel_of_Adun 1 8522
Protoss_Corsair 1 8859
Protoss_Templar_Archives 1 9684
Protoss_Dark_Templar 2 10571
11089
