Protoss_Nexus 1 5785
Protoss_Forge 1 4631
Protoss_Gateway 3 10970
Protoss_Photon_Cannon 3 7004
Protoss_Assimilator 2 7785
Protoss_Zealot 3 9367
Protoss_Cybernetics_Core 1 7703
Protoss_Stargate 1 8937
Protoss_Dragoon 1 8653
Protoss_Citadel_of_Adun 1 9347
Protoss_Corsair 3 10735
Protoss_Templar_Archives 1 10354
Protoss_Dark_Templar 1 11139
11139
