Protoss_Nexus 1 5695
Protoss_Gateway 6 11339
Protoss_Forge 1 4808
Protoss_Photon_Cannon 4 9891
Protoss_Assimilator 2 7196
Protoss_Zealot 5 9597
Protoss_Cybernetics_Core 1 6482
Protoss_Stargate 1 7991
Protoss_Dragoon 1 7791
Protoss_Citadel_of_Adun 1 8431
Protoss_Corsair 1 8419
Protoss_Templar_Archives 1 9518
Protoss_Dark_Templar 1 10439
Protoss_High_Templar 2 10481
11339
