Protoss_Forge 1 2851
Protoss_Nexus 1 6021
Protoss_Gateway 4 9607
Protoss_Assimilator 2 6597
Protoss_Photon_Cannon 5 11120
Protoss_Cybernetics_Core 1 6466
Protoss_Citadel_of_Adun 1 7569
Protoss_Dragoon 1 7621
Protoss_Templar_Archives 1 8560
Protoss_Zealot 3 10933
Protoss_Dark_Templar 2 9305
Protoss_High_Templar 6 10821
Protoss_Archon 1 10218
11120
