Protoss_Forge 1 3427
Protoss_Nexus 1 6017
Protoss_Photon_Cannon 2 8275
Protoss_Gateway 3 9473
Protoss_Assimilator 2 8609
Protoss_Cybernetics_Core 1 6822
Protoss_Zealot 8 10387
Protoss_Dragoon 1 7693
Protoss_Stargate 1 8200
Protoss_Citadel_of_Adun 1 8924
Protoss_Corsair 1 8969
10387
