Protoss_Gateway 2 3824
Protoss_Zealot 11 9701
Protoss_Assimilator 1 5573
Protoss_Cybernetics_Core 1 6906
Protoss_Stargate 1 8178
Protoss_Citadel_of_Adun 1 8409
Protoss_Forge 1 8318
Protoss_Corsair 1 8601
Protoss_Templar_Archives 1 11071
Protoss_Nexus 1 12589
12589
