Protoss_Gateway 2 3928
Protoss_Zealot 12 8756
Protoss_Forge 1 5250
Protoss_Photon_Cannon 3 10546
Protoss_Assimilator 1 7398
Protoss_Cybernetics_Core 1 8603
Protoss_Citadel_of_Adun 1 9923
Protoss_Dragoon 2 10071
Protoss_Templar_Archives 1 11378
11378
