Protoss_Gateway 2 4003
Protoss_Zealot 10 8861
Protoss_Assimilator 1 5013
Protoss_Cybernetics_Core 1 6134
Protoss_Stargate 1 7529
Protoss_Dragoon 1 7081
Protoss_Corsair 1 7946
Protoss_Citadel_of_Adun 1 8559
Protoss_Forge 1 8509
Protoss_Templar_Archives 1 9975
Protoss_Photon_Cannon 3 10553
Protoss_High_Templar 2 11161
11161
