Protoss_Gateway 3 8674
Protoss_Assimilator 1 3443
Protoss_Cybernetics_Core 1 4503
Protoss_Zealot 7 9816
Protoss_Stargate 1 5910
Protoss_Citadel_of_Adun 1 6344
Protoss_Corsair 1 6326
Protoss_Templar_Archives 1 7808
Protoss_Dark_Templar 2 9181
9816
