Protoss_Forge 1 3385
Protoss_Nexus 1 6227
Protoss_Assimilator 2 7491
Protoss_Gateway 1 5581
Protoss_Photon_Cannon 6 11093
Protoss_Cybernetics_Core 1 7045
Protoss_Zealot 5 10299
Protoss_Dragoon 1 7809
Protoss_Stargate 1 8385
Protoss_Robotics_Facility 1 9412
Protoss_Corsair 3 10191
Protoss_Robotics_Support_Bay 1 9839
Protoss_Reaver 1 11333
11333
