Protoss_Forge 1 3327
Protoss_Photon_Cannon 3 11012
Protoss_Nexus 1 6859
Protoss_Gateway 1 5708
Protoss_Assimilator 2 7931
Protoss_Cybernetics_Core 1 6745
Protoss_Zealot 4 9873
Protoss_Stargate 1 7977
Protoss_Citadel_of_Adun 1 8251
Protoss_Corsair 3 10153
Protoss_Templar_Archives 1 9740
11012
