Protoss_Forge 1 3853
Protoss_Nexus 1 6338
Protoss_Photon_Cannon 5 9477
Protoss_Gateway 2 10548
Protoss_Assimilator 2 7558
Protoss_Cybernetics_Core 1 7463
Protoss_Zealot 2 8161
Protoss_Stargate 1 8783
Protoss_Corsair 3 10548
Protoss_Dragoon 1 10251
Protoss_Robotics_Facility 1 11177
11177
