Protoss_Gateway 2 3774
Protoss_Zealot 8 8361
Protoss_Forge 1 6051
Protoss_Photon_Cannon 7 11126
Protoss_Nexus 1 9068
Protoss_Assimilator 2 10714
Protoss_Cybernetics_Core 1 9626
Protoss_Citadel_of_Adun 1 11349
Protoss_Dragoon 1 11186
11349
