Protoss_Forge 1 3751
Protoss_Nexus 1 5961
Protoss_Photon_Cannon 5 10177
Protoss_Gateway 1 5701
Protoss_Assimilator 3 8631
Protoss_Cybernetics_Core 1 6736
Protoss_Zealot 5 10485
Protoss_Stargate 1 8043
Protoss_Corsair 4 10361
Protoss_Robotics_Facility 1 9755
Protoss_Robotics_Support_Bay 1 10011
Protoss_Reaver 1 11583
11583
