Protoss_Forge 1 3200
Protoss_Photon_Cannon 6 11027
Protoss_Nexus 1 6277
Protoss_Gateway 3 10627
Protoss_Assimilator 2 7068
Protoss_Cybernetics_Core 1 6824
Protoss_Zealot 4 9729
Protoss_Stargate 1 8314
Protoss_Citadel_of_Adun 1 8548
Protoss_Corsair 1 8723
Protoss_Templar_Archives 1 9653
Protoss_High_Templar 1 10571
11027
