Protoss_Gateway 2 7593
Protoss_Assimilator 1 3458
Protoss_Zealot 10 10796
Protoss_Forge 2 9792
Protoss_Cybernetics_Core 1 6369
Protoss_Citadel_of_Adun 1 7501
Protoss_Templar_Archives 1 9395
Protoss_Ground_Weapons_1 1 8491
Protoss_High_Templar 2 10171
Protoss_Photon_Cannon 1 10890
Protoss_Archon 1 10285
10890
