Protoss_Forge 1 3508
Protoss_Nexus 1 6060
Protoss_Photon_Cannon 6 10681
Protoss_Gateway 1 5913
Protoss_Assimilator 2 7759
Protoss_Cybernetics_Core 1 7722
Protoss_Zealot 2 9227
Protoss_Stargate 1 8967
Protoss_Dragoon 1 8601
Protoss_Robotics_Facility 1 10075
Protoss_Corsair 2 10033
Protoss_Robotics_Support_Bay 1 10577
10681
