Protoss_Forge 1 3015
Protoss_Photon_Cannon 7 10765
Protoss_Nexus 1 6725
Protoss_Gateway 1 5756
Protoss_Assimilator 2 7976
Protoss_Cybernetics_Core 1 8412
Protoss_Zealot 4 10549
Protoss_Stargate 2 10489
Protoss_Citadel_of_Adun 2 10427
Protoss_Corsair 1 10907
Protoss_Templar_Archives 1 11421
11421
