Protoss_Forge 1 3724
Protoss_Nexus 1 5963
Protoss_Photon_Cannon 3 10162
Protoss_Gateway 3 8963
Protoss_Assimilator 2 7036
Protoss_Zealot 7 10113
Protoss_Cybernetics_Core 1 6872
Protoss_Stargate 1 8301
Protoss_Citadel_of_Adun 1 9075
Protoss_Corsair 3 10439
Protoss_Templar_Archives 1 10755
10755
