Protoss_Gateway 2 10405
Protoss_Zealot 8 10275
Protoss_Nexus 1 6913
Protoss_Forge 1 5513
Protoss_Cybernetics_Core 1 6809
Protoss_Assimilator 2 7571
Protoss_Photon_Cannon 2 8622
Protoss_Dragoon 1 7701
Protoss_Stargate 1 8846
Protoss_Citadel_of_Adun 1 9604
Protoss_Corsair 3 10899
Protoss_Templar_Archives 1 10824
10899
