Protoss_Forge 1 3545
Protoss_Nexus 1 6264
Protoss_Photon_Cannon 5 10159
Protoss_Gateway 1 5801
Protoss_Assimilator 3 9575
Protoss_Zealot 3 9435
Protoss_Cybernetics_Core 1 7309
Protoss_Stargate 1 8715
Protoss_Dragoon 1 8629
Protoss_Corsair 3 10397
Protoss_Citadel_of_Adun 1 9739
10397
