Protoss_Forge 1 3563
Protoss_Photon_Cannon 6 9798
Protoss_Nexus 1 8247
Protoss_Gateway 2 11167
Protoss_Assimilator 2 8478
Protoss_Cybernetics_Core 1 7987
Protoss_Zealot 3 9469
Protoss_Stargate 1 9401
Protoss_Robotics_Facility 1 10279
Protoss_Corsair 2 10479
Protoss_Robotics_Support_Bay 1 10543
11167
