Protoss_Nexus 1 5750
Protoss_Gateway 3 8971
Protoss_Forge 1 4862
Protoss_Photon_Cannon 7 10739
Protoss_Zealot 6 10083
Protoss_Assimilator 3 8994
Protoss_Cybernetics_Core 1 7025
Protoss_Stargate 1 8673
Protoss_Citadel_of_Adun 1 9228
Protoss_Corsair 3 10585
10739
