Protoss_Forge 1 3037
Protoss_Nexus 1 6235
Protoss_Gateway 4 10265
Protoss_Photon_Cannon 3 10763
Protoss_Assimilator 2 7211
Protoss_Cybernetics_Core 1 6445
Protoss_Zealot 4 9115
Protoss_Stargate 1 7813
Protoss_Citadel_of_Adun 1 8337
Protoss_Corsair 2 9807
Protoss_Templar_Archives 1 9473
Protoss_Dark_Templar 1 10295
Protoss_High_Templar 1 10593
10763
