Protoss_Gateway 5 10282
Protoss_Zealot 6 9235
Protoss_Nexus 1 7045
Protoss_Assimilator 1 5675
Protoss_Cybernetics_Core 1 7868
Protoss_Dragoon 3 10735
Protoss_Forge 1 9019
Protoss_Photon_Cannon 4 11157
11157
