Protoss_Forge 1 3226
Protoss_Photon_Cannon 5 10900
Protoss_Nexus 1 7053
Protoss_Gateway 4 10700
Protoss_Assimilator 2 8043
Protoss_Cybernetics_Core 1 6932
Protoss_Zealot 3 10769
Protoss_Dragoon 1 7831
Protoss_Citadel_of_Adun 1 8353
Protoss_Templar_Archives 1 9497
Protoss_High_Templar 3 10991
10991
