Protoss_Gateway 3 10927
Protoss_Zealot 12 10789
Protoss_Assimilator 1 7689
Protoss_Cybernetics_Core 1 8439
Protoss_Nexus 1 10921
Protoss_Citadel_of_Adun 1 9593
Protoss_Dragoon 2 10087
Protoss_Forge 1 10085
10927
