Protoss_Forge 1 3051
Protoss_Nexus 1 6415
Protoss_Gateway 1 5473
Protoss_Photon_Cannon 4 10061
Protoss_Assimilator 2 8569
Protoss_Cybernetics_Core 1 6828
Protoss_Zealot 2 8225
Protoss_Stargate 1 8155
Protoss_Corsair 3 10661
Protoss_Robotics_Facility 1 10026
Protoss_Robotics_Support_Bay 1 10319
Protoss_Shuttle 1 11263
11263
