Protoss_Gateway 2 4102
Protoss_Zealot 9 8776
Protoss_Assimilator 1 5897
Protoss_Cybernetics_Core 1 6700
Protoss_Dragoon 5 10481
Protoss_Robotics_Facility 1 9234
Protoss_Shuttle 1 10046
Protoss_Robotics_Support_Bay 1 9668
Protoss_Reaver 1 11431
11431
