Protoss_Forge 1 2909
Protoss_Photon_Cannon 4 9182
Protoss_Nexus 1 7611
Protoss_Gateway 4 11326
Protoss_Assimilator 2 7569
Protoss_Zealot 2 7695
Protoss_Cybernetics_Core 1 7524
Protoss_Stargate 1 8789
Protoss_Citadel_of_Adun 1 8831
Protoss_Dragoon 1 8725
Protoss_Corsair 2 10474
Protoss_Templar_Archives 1 9871
Protoss_Dark_Templar 2 10739
11326
