Protoss_Forge 1 3635
Protoss_Nexus 1 6303
Protoss_Photon_Cannon 2 5761
Protoss_Gateway 6 11163
Protoss_Assimilator 2 7164
Protoss_Cybernetics_Core 1 7103
Protoss_Stargate 1 8356
Protoss_Citadel_of_Adun 1 8447
Protoss_Corsair 2 9377
Protoss_Templar_Archives 1 9555
Protoss_High_Templar 3 11075
Protoss_Dark_Templar 1 11079
11163
