Protoss_Gateway 1 3379
Protoss_Assimilator 1 3460
Protoss_Zealot 5 10587
Protoss_Cybernetics_Core 1 4581
Protoss_Robotics_Facility 1 6223
Protoss_Shuttle 1 7031
Protoss_Robotics_Support_Bay 1 6348
Protoss_Dragoon 1 7145
Protoss_Reaver 2 10787
Protoss_Stargate 1 9081
Protoss_Nexus 1 10853
Protoss_Corsair 2 10879
Protoss_Scarab 8 9995
Protoss_Forge 1 10423
10879
