Protoss_Forge 1 3265
Protoss_Photon_Cannon 2 4407
Protoss_Nexus 1 6957
Protoss_Gateway 3 10333
Protoss_Assimilator 2 8514
Protoss_Cybernetics_Core 1 6800
Protoss_Zealot 9 10929
Protoss_Stargate 1 8157
Protoss_Corsair 3 9847
Protoss_Citadel_of_Adun 1 9190
Protoss_Templar_Archives 1 10559
Protoss_Ground_Weapons_1 1 9771
10929
