Protoss_Forge 1 3528
Protoss_Nexus 1 6163
Protoss_Photon_Cannon 3 10150
Protoss_Gateway 4 11215
Protoss_Assimilator 2 6623
Protoss_Cybernetics_Core 1 6733
Protoss_Zealot 7 9763
Protoss_Stargate 1 7961
Protoss_Citadel_of_Adun 1 8328
Protoss_Corsair 1 8371
Protoss_Templar_Archives 1 9453
Protoss_Dark_Templar 2 10605
11215
