Protoss_Forge 1 3077
Protoss_Nexus 1 6262
Protoss_Gateway 4 10828
Protoss_Photon_Cannon 3 10516
Protoss_Assimilator 2 8155
Protoss_Cybernetics_Core 1 7105
Protoss_Zealot 9 10673
Protoss_Stargate 1 8647
Protoss_Citadel_of_Adun 1 8899
Protoss_Corsair 1 9057
Protoss_Templar_Archives 1 10855
10855
