Protoss_Forge 1 3212
Protoss_Photon_Cannon 4 7489
Protoss_Nexus 1 7253
Protoss_Gateway 4 10907
Protoss_Assimilator 2 8439
Protoss_Zealot 3 8795
Protoss_Cybernetics_Core 1 8301
Protoss_Stargate 1 10069
Protoss_Citadel_of_Adun 1 10292
Protoss_Corsair 1 10553
10907
