Protoss_Gateway 2 3729
Protoss_Zealot 17 10831
Protoss_Nexus 1 9753
Protoss_Assimilator 2 10390
Protoss_Forge 1 9158
Protoss_Cybernetics_Core 1 10153
Protoss_Photon_Cannon 1 10093
Protoss_Stargate 1 11433
11433
