Protoss_Forge 1 3011
Protoss_Photon_Cannon 3 6173
Protoss_Gateway 2 9351
Protoss_Zealot 7 10849
Protoss_Nexus 1 9379
Protoss_Assimilator 2 9946
Protoss_Cybernetics_Core 1 8956
Protoss_Stargate 1 10405
Protoss_Dragoon 2 10337
Protoss_Citadel_of_Adun 1 11113
11113
