Protoss_Forge 1 3611
Protoss_Nexus 1 6015
Protoss_Photon_Cannon 2 4927
Protoss_Gateway 3 10460
Protoss_Assimilator 2 7737
Protoss_Cybernetics_Core 1 6805
Protoss_Zealot 8 10701
Protoss_Stargate 1 8037
Protoss_Citadel_of_Adun 1 8706
Protoss_Corsair 2 9051
Protoss_Robotics_Facility 1 10714
Protoss_Templar_Archives 1 11263
11263
