Protoss_Forge 1 3553
Protoss_Nexus 1 6146
Protoss_Photon_Cannon 3 10119
Protoss_Gateway 4 11375
Protoss_Assimilator 2 6944
Protoss_Cybernetics_Core 1 6543
Protoss_Zealot 7 10619
Protoss_Stargate 1 7915
Protoss_Citadel_of_Adun 1 8229
Protoss_Corsair 4 10329
Protoss_Templar_Archives 1 10643
11375
