Protoss_Forge 1 3198
Protoss_Photon_Cannon 4 10380
Protoss_Nexus 1 7503
Protoss_Gateway 1 6375
Protoss_Assimilator 2 7685
Protoss_Cybernetics_Core 1 7651
Protoss_Zealot 1 7219
Protoss_Stargate 1 8878
Protoss_Dragoon 1 8543
Protoss_Corsair 3 10553
Protoss_Robotics_Facility 1 10669
10669
