Protoss_Gateway 3 10832
Protoss_Zealot 10 9237
Protoss_Assimilator 1 4989
Protoss_Cybernetics_Core 1 6190
Protoss_Stargate 1 7503
Protoss_Dragoon 1 7321
Protoss_Citadel_of_Adun 1 8107
Protoss_Corsair 1 7973
Protoss_Templar_Archives 1 9552
Protoss_High_Templar 2 10387
Protoss_Nexus 1 12835
12835
