Protoss_Forge 1 2912
Protoss_Photon_Cannon 7 10934
Protoss_Nexus 1 6169
Protoss_Gateway 2 9903
Protoss_Assimilator 2 7161
Protoss_Cybernetics_Core 1 6853
Protoss_Zealot 3 8302
Protoss_Stargate 1 8096
Protoss_Citadel_of_Adun 1 8798
Protoss_Corsair 3 9743
Protoss_Templar_Archives 1 9953
10934
