Protoss_Gateway 1 3209
Protoss_Assimilator 1 3110
Protoss_Zealot 5 7575
Protoss_Cybernetics_Core 1 4402
Protoss_Stargate 1 5694
Protoss_Dragoon 1 5335
Protoss_Corsair 2 7723
Protoss_Citadel_of_Adun 1 7037
Protoss_Templar_Archives 1 8183
Protoss_Forge 1 8237
Protoss_Dark_Templar 2 10193
Protoss_Nexus 1 11643
11643
