Protoss_Forge 1 3760
Protoss_Nexus 1 6161
Protoss_Photon_Cannon 2 5053
Protoss_Gateway 3 9745
Protoss_Assimilator 2 7106
Protoss_Cybernetics_Core 1 6745
Protoss_Zealot 10 10955
Protoss_Dragoon 1 7631
Protoss_Stargate 1 8243
Protoss_Citadel_of_Adun 1 8535
Protoss_Corsair 3 9859
Protoss_Templar_Archives 1 10577
10955
