Protoss_Gateway 2 4006
Protoss_Zealot 12 10035
Protoss_Assimilator 1 5737
Protoss_Cybernetics_Core 1 7373
Protoss_Stargate 1 8877
Protoss_Forge 1 8774
Protoss_Corsair 1 9337
Protoss_Photon_Cannon 3 10830
Protoss_Citadel_of_Adun 2 11434
Protoss_Dragoon 2 10951
11434
