Protoss_Forge 1 3158
Protoss_Nexus 1 6163
Protoss_Photon_Cannon 5 10510
Protoss_Gateway 1 5406
Protoss_Assimilator 2 7883
Protoss_Cybernetics_Core 1 6614
Protoss_Zealot 6 10297
Protoss_Stargate 1 8181
Protoss_Citadel_of_Adun 1 8885
Protoss_Corsair 1 9251
10510
