Protoss_Forge 1 2945
Protoss_Photon_Cannon 5 9820
Protoss_Nexus 1 7777
Protoss_Gateway 1 6603
Protoss_Assimilator 3 8482
Protoss_Zealot 4 9529
Protoss_Cybernetics_Core 1 8100
Protoss_Stargate 1 9910
Protoss_Citadel_of_Adun 1 10204
10204
