Protoss_Nexus 1 5837
Protoss_Forge 1 4513
Protoss_Gateway 2 9166
Protoss_Photon_Cannon 7 10571
Protoss_Assimilator 2 6759
Protoss_Zealot 2 7151
Protoss_Cybernetics_Core 1 7469
Protoss_Stargate 1 8758
Protoss_Citadel_of_Adun 1 8586
Protoss_Corsair 3 10703
Protoss_Templar_Archives 1 9887
Protoss_Dark_Templar 2 10673
Protoss_High_Templar 1 10707
10707
