Protoss_Nexus 1 5667
Protoss_Forge 1 3915
Protoss_Photon_Cannon 3 8841
Protoss_Gateway 1 5663
Protoss_Zealot 5 10931
Protoss_Cybernetics_Core 1 7135
Protoss_Assimilator 2 9518
Protoss_Stargate 1 11078
Protoss_Citadel_of_Adun 1 11222
11222
