Protoss_Forge 1 3272
Protoss_Nexus 1 6217
Protoss_Gateway 4 10101
Protoss_Photon_Cannon 1 5704
Protoss_Assimilator 2 6989
Protoss_Cybernetics_Core 1 6826
Protoss_Zealot 1 6583
Protoss_Stargate 1 8088
Protoss_Dragoon 8 11089
Protoss_Robotics_Facility 1 9201
Protoss_Corsair 1 8521
Protoss_Shuttle 1 10007
Protoss_Robotics_Support_Bay 1 9645
Protoss_Reaver 1 11167
11167
