Protoss_Forge 1 3889
Protoss_Nexus 1 6068
Protoss_Gateway 3 9794
Protoss_Photon_Cannon 2 10008
Protoss_Assimilator 2 7477
Protoss_Cybernetics_Core 1 6463
Protoss_Zealot 3 7679
Protoss_Stargate 1 7851
Protoss_Citadel_of_Adun 1 8325
Protoss_Corsair 3 10129
Protoss_Templar_Archives 1 9535
Protoss_Dark_Templar 3 11169
Protoss_High_Templar 1 10809
11169
