Protoss_Forge 1 3562
Protoss_Nexus 1 6125
Protoss_Photon_Cannon 3 8689
Protoss_Gateway 3 10966
Protoss_Assimilator 2 9137
Protoss_Zealot 4 10947
Protoss_Cybernetics_Core 1 6644
Protoss_Stargate 1 8229
Protoss_Dragoon 1 8323
Protoss_Citadel_of_Adun 1 8811
Protoss_Corsair 4 10833
Protoss_Templar_Archives 1 11047
11047
