Protoss_Forge 1 3620
Protoss_Nexus 1 6059
Protoss_Photon_Cannon 4 10281
Protoss_Gateway 3 10351
Protoss_Assimilator 2 8057
Protoss_Cybernetics_Core 1 6979
Protoss_Zealot 4 10889
Protoss_Stargate 1 8205
Protoss_Dragoon 1 8041
Protoss_Citadel_of_Adun 1 8962
Protoss_Corsair 3 10363
Protoss_Templar_Archives 1 10077
Protoss_Dark_Templar 1 10843
10889
