Protoss_Forge 1 3157
Protoss_Nexus 1 6131
Protoss_Gateway 3 10121
Protoss_Photon_Cannon 6 11061
Protoss_Assimilator 2 6515
Protoss_Cybernetics_Core 1 6536
Protoss_Zealot 3 9435
Protoss_Stargate 1 7911
Protoss_Dragoon 1 7457
Protoss_Citadel_of_Adun 1 7923
Protoss_Corsair 2 8923
Protoss_Templar_Archives 1 9623
Protoss_Dark_Templar 1 10635
Protoss_High_Templar 2 11097
11097
