Protoss_Nexus 1 5909
Protoss_Gateway 4 7796
Protoss_Forge 1 4915
Protoss_Photon_Cannon 2 6057
Protoss_Zealot 15 10131
Protoss_Assimilator 2 10240
Protoss_Cybernetics_Core 1 9625
Protoss_Stargate 1 10999
10999
