Protoss_Forge 1 3189
Protoss_Nexus 1 6406
Protoss_Photon_Cannon 4 11080
Protoss_Gateway 3 10604
Protoss_Assimilator 2 7335
Protoss_Cybernetics_Core 1 6803
Protoss_Zealot 5 10639
Protoss_Stargate 1 8149
Protoss_Citadel_of_Adun 1 8875
Protoss_Dragoon 1 8811
Protoss_Corsair 1 9133
Protoss_Templar_Archives 1 10989
11080
