Protoss_Forge 1 3611
Protoss_Photon_Cannon 5 11085
Protoss_Nexus 1 7311
Protoss_Gateway 2 9185
Protoss_Assimilator 2 7356
Protoss_Cybernetics_Core 1 7260
Protoss_Zealot 3 8565
Protoss_Dragoon 1 8003
Protoss_Stargate 1 8585
Protoss_Citadel_of_Adun 1 8635
Protoss_Corsair 3 10607
Protoss_Templar_Archives 1 9694
Protoss_Dark_Templar 2 10455
11085
