Protoss_Forge 1 3119
Protoss_Photon_Cannon 2 4407
Protoss_Nexus 1 6936
Protoss_Gateway 2 10775
Protoss_Assimilator 2 7341
Protoss_Zealot 2 7491
Protoss_Cybernetics_Core 1 7296
Protoss_Stargate 1 8954
Protoss_Dragoon 1 8777
Protoss_Citadel_of_Adun 1 9200
Protoss_Corsair 2 10581
Protoss_Robotics_Facility 1 10558
Protoss_Templar_Archives 1 10703
10775
