Protoss_Forge 1 3255
Protoss_Photon_Cannon 2 4435
Protoss_Nexus 1 7019
Protoss_Gateway 3 8881
Protoss_Assimilator 2 8946
Protoss_Cybernetics_Core 1 6970
Protoss_Zealot 11 10797
Protoss_Citadel_of_Adun 1 8410
Protoss_Templar_Archives 1 10228
10797
