Protoss_Forge 1 3383
Protoss_Nexus 1 6159
Protoss_Photon_Cannon 4 9499
Protoss_Gateway 4 11411
Protoss_Assimilator 2 7403
Protoss_Cybernetics_Core 1 7276
Protoss_Zealot 1 7145
Protoss_Citadel_of_Adun 1 8565
Protoss_Stargate 1 8948
Protoss_Corsair 3 10569
Protoss_Templar_Archives 1 10116
Protoss_Dark_Templar 2 10907
11411
