Protoss_Gateway 2 8872
Protoss_Assimilator 1 3291
Protoss_Cybernetics_Core 1 4333
Protoss_Zealot 3 6345
Protoss_Stargate 1 5575
Protoss_Citadel_of_Adun 1 6193
Protoss_Corsair 2 7441
Protoss_Templar_Archives 1 7429
Protoss_Forge 1 7926
Protoss_Dark_Templar 1 8251
Protoss_Photon_Cannon 2 11090
Protoss_High_Templar 3 10963
11090
