Protoss_Forge 2 8529
Protoss_Photon_Cannon 3 6053
Protoss_Gateway 4 10945
Protoss_Zealot 8 10859
Protoss_Assimilator 1 6181
Protoss_Cybernetics_Core 1 7436
Protoss_Stargate 1 8780
Protoss_Dragoon 1 8495
Protoss_Citadel_of_Adun 1 9309
Protoss_Corsair 1 9355
10945
