Protoss_Forge 1 3485
Protoss_Photon_Cannon 7 11195
Protoss_Nexus 1 6863
Protoss_Gateway 3 9152
Protoss_Assimilator 2 8961
Protoss_Cybernetics_Core 1 6736
Protoss_Zealot 5 9997
Protoss_Citadel_of_Adun 1 8036
Protoss_Dragoon 1 7867
Protoss_Templar_Archives 1 10135
Protoss_Dark_Templar 1 11079
Protoss_High_Templar 2 11095
11195
