Protoss_Gateway 2 3937
Protoss_Zealot 9 10861
Protoss_Assimilator 1 4941
Protoss_Cybernetics_Core 1 6568
Protoss_Citadel_of_Adun 1 7604
Protoss_Dragoon 1 7486
Protoss_Templar_Archives 1 8662
Protoss_Forge 1 9359
Protoss_High_Templar 2 11016
Protoss_Photon_Cannon 1 10298
11016
