Protoss_Gateway 2 10089
Protoss_Zealot 5 8896
Protoss_Nexus 1 7079
Protoss_Assimilator 1 6318
Protoss_Cybernetics_Core 1 6963
Protoss_Dragoon 2 9796
Protoss_Forge 1 7674
Protoss_Robotics_Facility 1 9613
Protoss_Photon_Cannon 2 10124
Protoss_Shuttle 1 10441
Protoss_Robotics_Support_Bay 1 9873
Protoss_Reaver 1 11583
11583
