Protoss_Forge 1 3280
Protoss_Nexus 1 6163
Protoss_Photon_Cannon 3 10280
Protoss_Gateway 4 11382
Protoss_Assimilator 2 7032
Protoss_Cybernetics_Core 1 7055
Protoss_Zealot 4 9913
Protoss_Dragoon 1 7937
Protoss_Stargate 1 8476
Protoss_Citadel_of_Adun 1 9131
Protoss_Corsair 1 8913
Protoss_Templar_Archives 1 10202
Protoss_Dark_Templar 2 11015
11382
