Protoss_Gateway 2 10299
Protoss_Zealot 6 7983
Protoss_Assimilator 2 10350
Protoss_Cybernetics_Core 1 5120
Protoss_Stargate 1 6359
Protoss_Dragoon 1 6039
Protoss_Corsair 3 8403
Protoss_Citadel_of_Adun 1 7673
Protoss_Templar_Archives 1 8725
Protoss_Dark_Templar 2 10375
Protoss_Nexus 1 11411
Protoss_High_Templar 1 11127
11411
