Protoss_Nexus 1 5651
Protoss_Forge 1 4265
Protoss_Gateway 3 10581
Protoss_Photon_Cannon 4 10511
Protoss_Assimilator 2 7091
Protoss_Zealot 8 10959
Protoss_Cybernetics_Core 1 7090
Protoss_Stargate 1 8481
Protoss_Citadel_of_Adun 1 9117
Protoss_Corsair 3 10299
Protoss_Templar_Archives 1 10225
10959
