Protoss_Forge 1 2913
Protoss_Photon_Cannon 3 8954
Protoss_Nexus 1 7039
Protoss_Gateway 3 11077
Protoss_Assimilator 2 7899
Protoss_Cybernetics_Core 1 6894
Protoss_Zealot 8 10811
Protoss_Stargate 1 8505
Protoss_Citadel_of_Adun 1 8715
Protoss_Corsair 1 8943
Protoss_Templar_Archives 1 10608
11077
