Protoss_Forge 1 2920
Protoss_Photon_Cannon 5 8813
Protoss_Nexus 1 7403
Protoss_Gateway 1 6439
Protoss_Assimilator 1 6225
Protoss_Cybernetics_Core 1 7567
Protoss_Zealot 1 7541
Protoss_Citadel_of_Adun 1 8641
Protoss_Dragoon 1 8473
8813
