Protoss_Forge 1 3636
Protoss_Nexus 1 6245
Protoss_Photon_Cannon 4 9307
Protoss_Gateway 4 11299
Protoss_Assimilator 1 5204
Protoss_Zealot 4 10311
Protoss_Cybernetics_Core 1 8335
Protoss_Stargate 1 10063
Protoss_Dragoon 1 9731
Protoss_Citadel_of_Adun 1 10434
Protoss_Corsair 1 10657
11299
