Protoss_Forge 1 3656
Protoss_Photon_Cannon 5 10469
Protoss_Nexus 1 7051
Protoss_Gateway 1 5864
Protoss_Assimilator 2 8155
Protoss_Cybernetics_Core 1 6889
Protoss_Zealot 3 9799
Protoss_Stargate 2 9750
Protoss_Dragoon 1 7913
Protoss_Citadel_of_Adun 1 9089
Protoss_Corsair 4 10835
Protoss_Robotics_Facility 1 11627
11627
