Protoss_Forge 1 3336
Protoss_Photon_Cannon 4 10422
Protoss_Nexus 1 6983
Protoss_Gateway 2 8885
Protoss_Assimilator 2 8837
Protoss_Cybernetics_Core 1 6795
Protoss_Zealot 6 10419
Protoss_Stargate 1 8209
Protoss_Dragoon 1 7979
Protoss_Corsair 3 10365
Protoss_Citadel_of_Adun 1 9705
Protoss_Templar_Archives 1 11087
11087
