Protoss_Forge 1 3206
Protoss_Nexus 1 6184
Protoss_Gateway 5 10281
Protoss_Assimilator 2 8855
Protoss_Photon_Cannon 3 8335
Protoss_Cybernetics_Core 1 6235
Protoss_Stargate 1 7519
Protoss_Zealot 6 10855
Protoss_Corsair 2 9049
Protoss_Citadel_of_Adun 1 8813
10855
