Protoss_Forge 1 3370
Protoss_Photon_Cannon 6 10480
Protoss_Nexus 1 7270
Protoss_Gateway 2 9289
Protoss_Assimilator 2 10941
Protoss_Zealot 9 10825
Protoss_Cybernetics_Core 1 7703
Protoss_Stargate 1 9034
Protoss_Citadel_of_Adun 1 8902
Protoss_Corsair 1 9543
10941
