Protoss_Forge 1 3325
Protoss_Photon_Cannon 7 10892
Protoss_Nexus 1 7197
Protoss_Gateway 3 11004
Protoss_Assimilator 2 7509
Protoss_Zealot 3 8291
Protoss_Cybernetics_Core 1 7275
Protoss_Stargate 1 8629
Protoss_Citadel_of_Adun 1 8493
Protoss_Corsair 1 9047
Protoss_Templar_Archives 1 9683
Protoss_Dark_Templar 1 10503
11004
