Protoss_Forge 1 3325
Protoss_Photon_Cannon 3 5893
Protoss_Nexus 1 7351
Protoss_Gateway 1 6463
Protoss_Zealot 2 8053
Protoss_Assimilator 2 10850
Protoss_Cybernetics_Core 1 11197
11197
