Protoss_Forge 1 2994
Protoss_Nexus 1 6067
Protoss_Gateway 3 9512
Protoss_Assimilator 2 7427
Protoss_Photon_Cannon 8 10991
Protoss_Zealot 2 6391
Protoss_Cybernetics_Core 1 6511
Protoss_Dragoon 1 7257
Protoss_Stargate 1 7843
Protoss_Citadel_of_Adun 1 8199
Protoss_Corsair 2 9227
Protoss_Templar_Archives 1 9248
Protoss_Dark_Templar 1 10003
Protoss_High_Templar 2 10731
10991
