Protoss_Forge 1 3396
Protoss_Photon_Cannon 6 8368
Protoss_Nexus 1 7259
Protoss_Gateway 3 11002
Protoss_Assimilator 2 9681
Protoss_Cybernetics_Core 1 7328
Protoss_Zealot 3 8291
Protoss_Stargate 1 9598
Protoss_Citadel_of_Adun 1 9845
Protoss_Corsair 1 10067
Protoss_Templar_Archives 1 11145
11145
