Protoss_Forge 1 3105
Protoss_Nexus 1 6258
Protoss_Photon_Cannon 2 5137
Protoss_Gateway 4 10197
Protoss_Assimilator 2 7706
Protoss_Cybernetics_Core 1 7365
Protoss_Zealot 6 10725
Protoss_Stargate 1 8811
Protoss_Dragoon 1 8479
Protoss_Citadel_of_Adun 1 9455
Protoss_Corsair 2 10079
10725
