Protoss_Forge 1 3137
Protoss_Photon_Cannon 3 10702
Protoss_Nexus 1 6930
Protoss_Gateway 4 10459
Protoss_Assimilator 2 7085
Protoss_Cybernetics_Core 1 6817
Protoss_Zealot 2 8843
Protoss_Stargate 1 8153
Protoss_Dragoon 1 7971
Protoss_Citadel_of_Adun 1 8601
Protoss_Corsair 1 8733
Protoss_Templar_Archives 1 9627
Protoss_High_Templar 3 11067
11067
