Protoss_Gateway 2 3739
Protoss_Zealot 8 7761
Protoss_Assimilator 1 5807
Protoss_Cybernetics_Core 1 6905
Protoss_Stargate 1 8200
Protoss_Forge 1 8194
Protoss_Corsair 1 8717
Protoss_Robotics_Facility 1 9937
Protoss_Photon_Cannon 2 10271
Protoss_Robotics_Support_Bay 1 10457
Protoss_Nexus 1 12813
12813
