Protoss_Gateway 2 3938
Protoss_Zealot 17 10508
Protoss_Assimilator 1 5260
Protoss_Cybernetics_Core 1 7766
Protoss_Stargate 1 9177
Protoss_Dragoon 1 8736
Protoss_Robotics_Facility 1 9994
Protoss_Corsair 1 9711
10508
