Protoss_Forge 1 3544
Protoss_Photon_Cannon 5 10344
Protoss_Nexus 1 6665
Protoss_Gateway 3 11238
Protoss_Assimilator 2 7843
Protoss_Cybernetics_Core 1 7046
Protoss_Zealot 3 8413
Protoss_Stargate 1 8411
Protoss_Citadel_of_Adun 1 8701
Protoss_Corsair 1 8837
Protoss_Templar_Archives 1 9777
Protoss_High_Templar 2 10583
11238
