Protoss_Gateway 1 3437
Protoss_Zealot 8 10105
Protoss_Nexus 1 6991
Protoss_Forge 1 5412
Protoss_Photon_Cannon 3 7925
Protoss_Assimilator 2 9682
Protoss_Cybernetics_Core 1 9771
Protoss_Stargate 1 11266
Protoss_Robotics_Facility 1 11823
11823
