Protoss_Forge 1 3497
Protoss_Photon_Cannon 1 4443
Protoss_Nexus 1 6493
Protoss_Gateway 2 10361
Protoss_Assimilator 2 6971
Protoss_Zealot 4 8817
Protoss_Cybernetics_Core 1 7145
Protoss_Stargate 1 8677
Protoss_Citadel_of_Adun 1 8731
Protoss_Corsair 2 10143
Protoss_Templar_Archives 1 9835
Protoss_Robotics_Facility 1 10663
Protoss_Dark_Templar 2 11177
11177
