Protoss_Forge 1 3105
Protoss_Photon_Cannon 2 6190
Protoss_Nexus 1 6913
Protoss_Gateway 1 6105
Protoss_Assimilator 2 7397
Protoss_Cybernetics_Core 1 7212
Protoss_Zealot 2 8669
Protoss_Stargate 1 8500
Protoss_Robotics_Facility 1 9541
Protoss_Corsair 4 10883
Protoss_Dragoon 1 9661
Protoss_Shuttle 1 10505
Protoss_Robotics_Support_Bay 1 9943
10883
