Protoss_Gateway 1 3269
Protoss_Assimilator 1 3190
Protoss_Zealot 3 5495
Protoss_Cybernetics_Core 1 5333
Protoss_Stargate 1 6586
Protoss_Dragoon 2 7597
Protoss_Citadel_of_Adun 1 6995
Protoss_Corsair 3 8523
Protoss_Templar_Archives 1 8061
Protoss_Forge 1 8251
Protoss_Dark_Templar 1 9037
Protoss_Nexus 1 11377
Protoss_High_Templar 1 9959
Protoss_Photon_Cannon 1 11169
11377
