Protoss_Forge 1 3414
Protoss_Photon_Cannon 2 4377
Protoss_Nexus 1 6901
Protoss_Gateway 2 8625
Protoss_Assimilator 2 7580
Protoss_Cybernetics_Core 1 6720
Protoss_Zealot 8 10700
Protoss_Stargate 1 7951
Protoss_Corsair 4 10315
Protoss_Citadel_of_Adun 1 9172
Protoss_Templar_Archives 1 11366
11366
