Protoss_Forge 1 3609
Protoss_Photon_Cannon 2 4792
Protoss_Nexus 1 6806
Protoss_Gateway 3 10929
Protoss_Assimilator 2 8325
Protoss_Cybernetics_Core 1 6748
Protoss_Zealot 6 10407
Protoss_Stargate 1 8096
Protoss_Citadel_of_Adun 1 8657
Protoss_Corsair 4 10499
Protoss_Templar_Archives 1 10134
Protoss_Dark_Templar 2 11041
11041
