Protoss_Forge 1 3141
Protoss_Nexus 1 6119
Protoss_Photon_Cannon 3 8083
Protoss_Gateway 1 6231
Protoss_Assimilator 2 7211
Protoss_Cybernetics_Core 1 7373
Protoss_Zealot 2 8799
Protoss_Stargate 2 9329
Protoss_Corsair 5 10603
Protoss_Citadel_of_Adun 1 10777
10777
