Protoss_Forge 1 3229
Protoss_Nexus 1 6259
Protoss_Photon_Cannon 4 10495
Protoss_Gateway 4 10189
Protoss_Assimilator 1 5573
Protoss_Cybernetics_Core 1 6760
Protoss_Zealot 11 10957
Protoss_Stargate 1 8067
Protoss_Citadel_of_Adun 1 8479
Protoss_Corsair 2 9293
10957
