Protoss_Gateway 2 4139
Protoss_Zealot 8 9265
Protoss_Assimilator 1 4987
Protoss_Cybernetics_Core 1 6025
Protoss_Stargate 1 7418
Protoss_Citadel_of_Adun 1 7795
Protoss_Corsair 1 7829
Protoss_Forge 1 8115
Protoss_Photon_Cannon 2 9671
Protoss_Templar_Archives 1 9503
Protoss_Nexus 1 12180
12180
