Protoss_Nexus 1 5991
Protoss_Forge 1 4657
Protoss_Gateway 3 8931
Protoss_Photon_Cannon 6 11067
Protoss_Assimilator 2 6882
Protoss_Cybernetics_Core 1 6961
Protoss_Citadel_of_Adun 1 7984
Protoss_Templar_Archives 1 9056
Protoss_Zealot 3 10943
Protoss_High_Templar 4 10847
Protoss_Dark_Templar 1 10345
Protoss_Archon 1 10183
11067
