Protoss_Gateway 4 9908
Protoss_Zealot 9 10121
Protoss_Assimilator 1 4549
Protoss_Cybernetics_Core 1 5841
Protoss_Forge 1 5902
Protoss_Stargate 1 7338
Protoss_Corsair 1 7916
Protoss_Photon_Cannon 3 10494
Protoss_Citadel_of_Adun 1 10099
Protoss_Ground_Weapons_1 1 9891
10494
