Protoss_Nexus 1 5899
Protoss_Forge 1 4625
Protoss_Gateway 4 9957
Protoss_Photon_Cannon 2 10750
Protoss_Assimilator 2 7575
Protoss_Cybernetics_Core 1 6956
Protoss_Zealot 2 7215
Protoss_Dragoon 8 11135
Protoss_Stargate 1 9103
Protoss_Corsair 2 10417
11135
