Protoss_Forge 1 3536
Protoss_Nexus 1 6289
Protoss_Photon_Cannon 4 10733
Protoss_Assimilator 3 8175
Protoss_Gateway 3 10290
Protoss_Cybernetics_Core 1 6957
Protoss_Zealot 6 9871
Protoss_Stargate 1 8208
Protoss_Citadel_of_Adun 1 8545
Protoss_Corsair 3 10904
10904
