Protoss_Forge 1 3446
Protoss_Photon_Cannon 5 9311
Protoss_Nexus 1 7073
Protoss_Gateway 4 10733
Protoss_Assimilator 2 7289
Protoss_Zealot 5 9629
Protoss_Cybernetics_Core 1 7215
Protoss_Stargate 1 8441
Protoss_Citadel_of_Adun 1 8730
Protoss_Corsair 2 9519
Protoss_Templar_Archives 1 9949
Protoss_Dark_Templar 2 10745
10745
