Protoss_Nexus 1 5769
Protoss_Forge 1 4345
Protoss_Gateway 5 11194
Protoss_Photon_Cannon 4 10732
Protoss_Assimilator 2 6859
Protoss_Cybernetics_Core 1 6772
Protoss_Zealot 3 9961
Protoss_Dragoon 1 7541
Protoss_Stargate 1 8161
Protoss_Citadel_of_Adun 1 8700
Protoss_Corsair 1 8611
Protoss_Templar_Archives 1 9732
Protoss_High_Templar 2 10499
Protoss_Dark_Templar 1 10551
11194
