Protoss_Forge 1 3208
Protoss_Photon_Cannon 4 10973
Protoss_Nexus 1 6901
Protoss_Gateway 3 11109
Protoss_Assimilator 2 9218
Protoss_Cybernetics_Core 1 6813
Protoss_Zealot 8 10209
Protoss_Stargate 1 8070
Protoss_Citadel_of_Adun 1 8295
Protoss_Corsair 5 10559
Protoss_Templar_Archives 1 11352
11352
