Protoss_Forge 1 3015
Protoss_Photon_Cannon 4 6033
Protoss_Nexus 1 7474
Protoss_Gateway 3 10403
Protoss_Assimilator 2 8459
Protoss_Cybernetics_Core 1 7852
Protoss_Zealot 5 10283
Protoss_Stargate 1 9556
Protoss_Citadel_of_Adun 1 9799
Protoss_Corsair 2 10653
Protoss_Templar_Archives 1 10873
10873
