Protoss_Gateway 2 10459
Protoss_Assimilator 1 3417
Protoss_Zealot 3 5223
Protoss_Cybernetics_Core 1 5381
Protoss_Dragoon 5 10773
Protoss_Robotics_Facility 1 7248
Protoss_Robotics_Support_Bay 1 7435
Protoss_Reaver 2 11031
Protoss_Nexus 1 10263
Protoss_Shuttle 1 9763
11031
