Protoss_Gateway 2 4054
Protoss_Zealot 13 9970
Protoss_Assimilator 1 5543
Protoss_Cybernetics_Core 1 6273
Protoss_Citadel_of_Adun 1 7516
Protoss_Dragoon 2 7731
Protoss_Forge 1 9678
Protoss_Photon_Cannon 1 10698
Protoss_Templar_Archives 1 11074
11074
