Protoss_Forge 1 2881
Protoss_Photon_Cannon 12 11105
Protoss_Nexus 1 7263
Protoss_Gateway 1 6437
Protoss_Assimilator 1 6324
Protoss_Cybernetics_Core 1 9211
Protoss_Zealot 1 9413
Protoss_Stargate 1 10573
11105
