Protoss_Forge 1 3553
Protoss_Nexus 1 6227
Protoss_Gateway 5 10665
Protoss_Assimilator 2 8142
Protoss_Photon_Cannon 2 10623
Protoss_Cybernetics_Core 1 6355
Protoss_Zealot 3 9809
Protoss_Dragoon 1 7165
Protoss_Stargate 1 7921
Protoss_Citadel_of_Adun 1 7963
Protoss_Corsair 2 9135
Protoss_Templar_Archives 1 9175
Protoss_High_Templar 1 10619
Protoss_Dark_Templar 1 10651
10665
