Protoss_Forge 1 3385
Protoss_Photon_Cannon 5 10353
Protoss_Nexus 1 7223
Protoss_Gateway 1 6131
Protoss_Assimilator 2 6799
Protoss_Cybernetics_Core 1 7151
Protoss_Zealot 4 10023
Protoss_Stargate 2 9423
Protoss_Dragoon 1 7917
Protoss_Robotics_Facility 1 9139
Protoss_Corsair 4 10615
Protoss_Robotics_Support_Bay 1 9744
Protoss_Reaver 1 11231
11231
