Protoss_Gateway 2 11137
Protoss_Assimilator 1 3394
Protoss_Zealot 4 8241
Protoss_Cybernetics_Core 1 5262
Protoss_Dragoon 1 6086
Protoss_Robotics_Facility 1 7499
Protoss_Shuttle 1 8331
Protoss_Robotics_Support_Bay 1 7716
Protoss_Reaver 2 10525
Protoss_Citadel_of_Adun 1 9853
Protoss_Forge 1 10269
Protoss_Templar_Archives 1 11161
11161
