Protoss_Gateway 1 3253
Protoss_Zealot 8 9901
Protoss_Assimilator 1 3913
Protoss_Cybernetics_Core 1 4903
Protoss_Stargate 1 6345
Protoss_Robotics_Facility 1 7403
Protoss_Corsair 1 6931
Protoss_Forge 1 7488
Protoss_Robotics_Support_Bay 1 7603
Protoss_Photon_Cannon 2 9398
Protoss_Reaver 1 9121
Protoss_Scarab 4 9001
Protoss_Shield_Battery 1 9974
Protoss_Shuttle 1 11306
11306
