Protoss_Gateway 5 11323
Protoss_Zealot 10 9849
Protoss_Nexus 1 7623
Protoss_Assimilator 2 9370
Protoss_Cybernetics_Core 1 7186
Protoss_Forge 1 7190
Protoss_Stargate 1 8441
Protoss_Photon_Cannon 3 10209
Protoss_Citadel_of_Adun 1 8978
Protoss_Corsair 1 9091
Protoss_Templar_Archives 1 10111
11323
