Protoss_Forge 1 3091
Protoss_Photon_Cannon 5 10527
Protoss_Nexus 1 6696
Protoss_Gateway 3 10846
Protoss_Assimilator 2 7771
Protoss_Cybernetics_Core 1 7615
Protoss_Zealot 3 10131
Protoss_Stargate 1 8946
Protoss_Dragoon 1 8541
Protoss_Citadel_of_Adun 1 9473
Protoss_Corsair 1 9355
Protoss_Templar_Archives 1 11178
11178
