Protoss_Forge 1 3439
Protoss_Nexus 1 6789
Protoss_Photon_Cannon 6 10311
Protoss_Gateway 4 10783
Protoss_Zealot 3 8821
Protoss_Assimilator 2 9105
Protoss_Cybernetics_Core 1 10037
Protoss_Dragoon 3 10871
10871
