Protoss_Forge 1 3285
Protoss_Photon_Cannon 3 10905
Protoss_Nexus 1 7245
Protoss_Gateway 3 9035
Protoss_Assimilator 2 9695
Protoss_Zealot 9 10911
Protoss_Cybernetics_Core 1 7434
Protoss_Dragoon 1 8175
Protoss_Citadel_of_Adun 1 8601
Protoss_Stargate 2 11163
11163
