Protoss_Gateway 2 4058
Protoss_Zealot 11 10396
Protoss_Assimilator 1 5956
Protoss_Cybernetics_Core 1 7063
Protoss_Forge 1 7677
Protoss_Photon_Cannon 2 11094
Protoss_Dragoon 1 9591
11094
