Protoss_Forge 1 3488
Protoss_Nexus 1 6311
Protoss_Photon_Cannon 4 10647
Protoss_Gateway 3 9735
Protoss_Assimilator 2 7270
Protoss_Zealot 3 10909
Protoss_Cybernetics_Core 1 7616
Protoss_Stargate 2 9590
Protoss_Citadel_of_Adun 1 9070
Protoss_Corsair 4 10883
Protoss_Templar_Archives 1 11013
11013
