Protoss_Gateway 1 3396
Protoss_Forge 1 3615
Protoss_Assimilator 2 10952
Protoss_Photon_Cannon 2 5691
Protoss_Cybernetics_Core 1 5312
Protoss_Dragoon 1 6075
Protoss_Stargate 1 6935
Protoss_Corsair 1 7599
Protoss_Zealot 2 10465
Protoss_Nexus 1 11153
Protoss_Citadel_of_Adun 1 10815
11153
