Protoss_Gateway 2 3645
Protoss_Zealot 9 9895
Protoss_Assimilator 1 5060
Protoss_Cybernetics_Core 1 6617
Protoss_Stargate 1 8307
Protoss_Dragoon 1 8211
Protoss_Citadel_of_Adun 1 8765
Protoss_Corsair 1 9137
Protoss_Forge 1 10127
10127
