Protoss_Forge 1 3198
Protoss_Nexus 1 6436
Protoss_Gateway 1 5427
Protoss_Assimilator 2 6995
Protoss_Photon_Cannon 3 10110
Protoss_Cybernetics_Core 1 6621
Protoss_Zealot 5 10339
Protoss_Stargate 1 7952
Protoss_Dragoon 1 7773
Protoss_Robotics_Facility 1 8997
Protoss_Corsair 4 10343
Protoss_Robotics_Support_Bay 1 9159
Protoss_Reaver 1 10839
10839
