Protoss_Forge 1 3068
Protoss_Nexus 1 6528
Protoss_Photon_Cannon 10 10666
Protoss_Gateway 3 9640
Protoss_Assimilator 2 7715
Protoss_Cybernetics_Core 1 7433
Protoss_Zealot 2 7966
Protoss_Citadel_of_Adun 1 8771
Protoss_Templar_Archives 1 9842
Protoss_High_Templar 2 10606
10666
