Protoss_Gateway 1 3328
Protoss_Forge 1 3708
Protoss_Zealot 4 8186
Protoss_Photon_Cannon 4 10755
Protoss_Nexus 1 9009
Protoss_Assimilator 1 7211
Protoss_Cybernetics_Core 1 8388
Protoss_Dragoon 2 10211
Protoss_Stargate 1 10183
Protoss_Citadel_of_Adun 1 10902
Protoss_Corsair 1 10611
10902
