Protoss_Forge 1 3438
Protoss_Nexus 1 6317
Protoss_Gateway 4 10781
Protoss_Photon_Cannon 5 10969
Protoss_Assimilator 2 7053
Protoss_Cybernetics_Core 1 6793
Protoss_Zealot 2 9269
Protoss_Stargate 1 8391
Protoss_Citadel_of_Adun 1 8571
Protoss_Corsair 1 8827
Protoss_Templar_Archives 1 9865
10969
