Protoss_Forge 1 3566
Protoss_Nexus 1 6138
Protoss_Photon_Cannon 3 11103
Protoss_Gateway 3 9641
Protoss_Assimilator 2 7835
Protoss_Cybernetics_Core 1 6751
Protoss_Zealot 7 10377
Protoss_Stargate 1 7977
Protoss_Corsair 4 10197
Protoss_Citadel_of_Adun 1 9074
Protoss_Templar_Archives 1 11035
11103
