Protoss_Forge 1 3595
Protoss_Nexus 1 6175
Protoss_Photon_Cannon 2 9272
Protoss_Gateway 2 9027
Protoss_Assimilator 2 7395
Protoss_Cybernetics_Core 1 6446
Protoss_Zealot 4 9137
Protoss_Stargate 1 7673
Protoss_Dragoon 1 7257
Protoss_Citadel_of_Adun 1 7967
Protoss_Corsair 1 8313
Protoss_Templar_Archives 1 10864
10864
