Protoss_Gateway 2 11019
Protoss_Assimilator 1 3489
Protoss_Zealot 6 9241
Protoss_Forge 1 7681
Protoss_Photon_Cannon 1 8633
Protoss_Cybernetics_Core 1 9443
Protoss_Citadel_of_Adun 1 10618
Protoss_Dragoon 1 10386
11019
