Protoss_Forge 2 10941
Protoss_Nexus 1 6105
Protoss_Photon_Cannon 6 10016
Protoss_Gateway 2 8826
Protoss_Assimilator 2 7462
Protoss_Cybernetics_Core 1 7042
Protoss_Zealot 5 10215
Protoss_Stargate 1 8409
Protoss_Citadel_of_Adun 1 8539
Protoss_Corsair 2 9949
Protoss_Templar_Archives 1 10001
Protoss_Dark_Templar 2 10767
10941
