Protoss_Gateway 2 11287
Protoss_Assimilator 1 3200
Protoss_Zealot 9 10499
Protoss_Cybernetics_Core 1 4918
Protoss_Dragoon 1 5685
Protoss_Stargate 1 6499
Protoss_Corsair 5 10655
Protoss_Nexus 1 9596
Protoss_Forge 1 8659
Protoss_Citadel_of_Adun 1 10364
11287
