Protoss_Gateway 2 6757
Protoss_Assimilator 1 2363
Protoss_Zealot 5 7226
Protoss_Cybernetics_Core 1 3821
Protoss_Stargate 1 4901
Protoss_Dragoon 1 5336
Protoss_Citadel_of_Adun 1 5657
Protoss_Forge 1 8071
8071
