Protoss_Forge 1 3255
Protoss_Photon_Cannon 4 10893
Protoss_Nexus 1 6558
Protoss_Gateway 1 5468
Protoss_Assimilator 2 6698
Protoss_Zealot 5 10111
Protoss_Cybernetics_Core 1 6688
Protoss_Stargate 2 9351
Protoss_Robotics_Facility 1 9018
Protoss_Corsair 4 9990
Protoss_Robotics_Support_Bay 1 9348
Protoss_Reaver 1 10966
10966
