Protoss_Gateway 6 11286
Protoss_Zealot 5 10749
Protoss_Nexus 1 6915
Protoss_Assimilator 2 6644
Protoss_Cybernetics_Core 1 6179
Protoss_Stargate 1 7461
Protoss_Citadel_of_Adun 1 7789
Protoss_Forge 1 7777
Protoss_Corsair 1 7885
Protoss_Templar_Archives 1 8799
Protoss_Photon_Cannon 1 9027
Protoss_Dark_Templar 2 9771
Protoss_High_Templar 2 10553
11286
