Protoss_Nexus 1 5727
Protoss_Gateway 4 11087
Protoss_Forge 1 4436
Protoss_Photon_Cannon 1 5368
Protoss_Assimilator 2 7237
Protoss_Cybernetics_Core 1 6261
Protoss_Zealot 9 10389
Protoss_Dragoon 1 7027
Protoss_Stargate 1 7687
Protoss_Citadel_of_Adun 1 8419
Protoss_Corsair 2 8927
Protoss_Templar_Archives 1 10321
11087
