Protoss_Forge 1 3265
Protoss_Photon_Cannon 5 11034
Protoss_Nexus 1 7184
Protoss_Gateway 2 9147
Protoss_Assimilator 2 9160
Protoss_Cybernetics_Core 1 7102
Protoss_Zealot 9 10499
Protoss_Stargate 1 8360
Protoss_Citadel_of_Adun 1 8777
Protoss_Corsair 4 10901
Protoss_Templar_Archives 1 10450
Protoss_Dragoon 2 11021
11034
