Protoss_Forge 1 3429
Protoss_Photon_Cannon 3 10896
Protoss_Nexus 1 6990
Protoss_Gateway 4 10345
Protoss_Assimilator 2 7669
Protoss_Zealot 3 8919
Protoss_Cybernetics_Core 1 7283
Protoss_Stargate 1 8609
Protoss_Dragoon 1 8261
Protoss_Citadel_of_Adun 1 8883
Protoss_Corsair 2 10483
Protoss_Templar_Archives 1 9901
Protoss_High_Templar 4 11087
11087
