Protoss_Forge 1 3280
Protoss_Nexus 1 6141
Protoss_Photon_Cannon 3 9863
Protoss_Gateway 2 8354
Protoss_Assimilator 2 10111
Protoss_Cybernetics_Core 1 7024
Protoss_Zealot 9 10775
Protoss_Stargate 1 8323
Protoss_Citadel_of_Adun 1 8535
Protoss_Corsair 2 10315
10775
