Protoss_Forge 1 3543
Protoss_Photon_Cannon 3 10139
Protoss_Nexus 1 6889
Protoss_Gateway 2 9508
Protoss_Assimilator 2 9023
Protoss_Cybernetics_Core 1 6826
Protoss_Zealot 6 10591
Protoss_Dragoon 1 7709
Protoss_Stargate 1 8513
Protoss_Citadel_of_Adun 1 9007
Protoss_Corsair 4 10931
Protoss_Templar_Archives 1 10605
10931
