Protoss_Gateway 1 1811
Protoss_Zealot 5 7991
Protoss_Assimilator 1 3011
Protoss_Cybernetics_Core 1 3892
Protoss_Robotics_Facility 1 4953
Protoss_Dragoon 1 5255
Protoss_Stargate 1 5950
Protoss_Shuttle 1 6267
Protoss_Robotics_Support_Bay 1 6625
Protoss_Corsair 4 9819
Protoss_Reaver 1 7263
Protoss_Forge 1 7669
Protoss_Photon_Cannon 3 9625
Protoss_Scarab 4 9825
9825
