Protoss_Gateway 2 3882
Protoss_Zealot 9 8536
Protoss_Assimilator 1 5456
Protoss_Cybernetics_Core 1 7002
Protoss_Dragoon 2 7761
Protoss_Citadel_of_Adun 1 8086
Protoss_Templar_Archives 1 9483
Protoss_High_Templar 2 10541
10541
