Protoss_Gateway 2 4137
Protoss_Zealot 9 10571
Protoss_Assimilator 1 4598
Protoss_Cybernetics_Core 1 6218
Protoss_Stargate 1 7693
Protoss_Dragoon 1 7501
Protoss_Citadel_of_Adun 1 8278
Protoss_Corsair 1 8296
Protoss_Forge 1 8522
Protoss_Photon_Cannon 1 10828
10828
