Protoss_Forge 1 3122
Protoss_Photon_Cannon 3 10909
Protoss_Nexus 1 7016
Protoss_Gateway 2 9862
Protoss_Assimilator 2 7733
Protoss_Cybernetics_Core 1 7088
Protoss_Zealot 7 10499
Protoss_Stargate 1 8522
Protoss_Corsair 3 10667
Protoss_Citadel_of_Adun 1 9519
10909
