Protoss_Gateway 1 3163
Protoss_Zealot 9 9186
Protoss_Assimilator 1 4663
Protoss_Cybernetics_Core 1 6353
Protoss_Stargate 1 7818
Protoss_Citadel_of_Adun 1 8314
Protoss_Corsair 1 8236
Protoss_Templar_Archives 1 9463
Protoss_Dark_Templar 2 10973
Protoss_Nexus 1 12213
Protoss_Forge 1 10586
12213
