Protoss_Forge 1 3119
Protoss_Photon_Cannon 4 10974
Protoss_Nexus 1 6849
Protoss_Gateway 2 11377
Protoss_Assimilator 2 7917
Protoss_Zealot 4 9913
Protoss_Cybernetics_Core 1 7677
Protoss_Stargate 1 9119
Protoss_Citadel_of_Adun 1 9193
Protoss_Corsair 2 10793
Protoss_Templar_Archives 1 10806
11377
