Protoss_Forge 1 3246
Protoss_Photon_Cannon 2 4317
Protoss_Nexus 1 6839
Protoss_Gateway 3 9784
Protoss_Assimilator 2 8593
Protoss_Zealot 10 10917
Protoss_Cybernetics_Core 1 7275
Protoss_Citadel_of_Adun 1 8509
Protoss_Dragoon 1 8411
Protoss_Stargate 2 11228
11228
