Protoss_Forge 1 2966
Protoss_Photon_Cannon 4 10446
Protoss_Nexus 2 10811
Protoss_Gateway 1 6308
Protoss_Assimilator 2 8153
Protoss_Cybernetics_Core 1 7348
Protoss_Zealot 5 10281
Protoss_Stargate 2 9930
Protoss_Corsair 4 10601
10811
