Protoss_Forge 1 3131
Protoss_Photon_Cannon 2 5191
Protoss_Nexus 1 6547
Protoss_Gateway 4 10030
Protoss_Assimilator 2 7297
Protoss_Cybernetics_Core 1 6774
Protoss_Zealot 5 10597
Protoss_Stargate 1 8165
Protoss_Citadel_of_Adun 1 8447
Protoss_Corsair 2 9177
Protoss_Templar_Archives 1 10690
10690
