Protoss_Nexus 1 5805
Protoss_Gateway 4 9827
Protoss_Forge 1 4874
Protoss_Assimilator 2 10890
Protoss_Zealot 10 10215
Protoss_Photon_Cannon 5 10883
Protoss_Cybernetics_Core 1 6901
Protoss_Citadel_of_Adun 1 8204
Protoss_Dragoon 1 8277
Protoss_Templar_Archives 1 10173
10890
