Protoss_Forge 1 3650
Protoss_Nexus 1 6287
Protoss_Gateway 2 8625
Protoss_Photon_Cannon 2 11192
Protoss_Assimilator 2 8328
Protoss_Zealot 7 10279
Protoss_Cybernetics_Core 1 6576
Protoss_Stargate 1 7988
Protoss_Citadel_of_Adun 1 8289
Protoss_Corsair 1 8445
Protoss_Templar_Archives 1 10161
Protoss_Dark_Templar 2 11121
11192
