Protoss_Forge 1 3584
Protoss_Nexus 1 5981
Protoss_Photon_Cannon 4 11189
Protoss_Gateway 4 10510
Protoss_Assimilator 2 6632
Protoss_Cybernetics_Core 1 6697
Protoss_Zealot 1 6829
Protoss_Stargate 1 8002
Protoss_Citadel_of_Adun 1 8629
Protoss_Corsair 3 9621
Protoss_Templar_Archives 1 9691
Protoss_Dark_Templar 2 10515
11189
