Protoss_Forge 1 2936
Protoss_Photon_Cannon 3 5219
Protoss_Nexus 1 7741
Protoss_Gateway 1 6773
Protoss_Zealot 3 10609
Protoss_Assimilator 2 10141
Protoss_Cybernetics_Core 1 10207
Protoss_Stargate 1 11459
11459
