Protoss_Gateway 2 7072
Protoss_Assimilator 1 3360
Protoss_Zealot 7 9183
Protoss_Cybernetics_Core 1 5519
Protoss_Dragoon 1 6359
Protoss_Citadel_of_Adun 1 6814
Protoss_Templar_Archives 1 7807
Protoss_High_Templar 4 10223
Protoss_Archon 1 8839
Protoss_Forge 1 9606
Protoss_Nexus 1 11583
Protoss_Photon_Cannon 3 11174
11583
