Protoss_Forge 1 3646
Protoss_Nexus 1 6095
Protoss_Gateway 4 11084
Protoss_Photon_Cannon 2 9341
Protoss_Assimilator 2 8838
Protoss_Cybernetics_Core 1 6183
Protoss_Zealot 7 9347
Protoss_Stargate 1 7423
Protoss_Citadel_of_Adun 1 7963
Protoss_Corsair 3 9009
Protoss_Templar_Archives 1 10223
11084
