Protoss_Gateway 1 1872
Protoss_Zealot 4 5793
Protoss_Assimilator 1 2998
Protoss_Cybernetics_Core 1 3770
Protoss_Robotics_Facility 1 4814
Protoss_Dragoon 1 5041
Protoss_Stargate 1 5694
Protoss_Shuttle 1 6255
Protoss_Robotics_Support_Bay 1 6675
Protoss_Corsair 5 9999
Protoss_Reaver 1 7373
Protoss_Forge 1 7837
Protoss_Photon_Cannon 3 9742
Protoss_Scarab 1 9974
9999
