Protoss_Forge 1 3333
Protoss_Photon_Cannon 6 10581
Protoss_Nexus 1 7167
Protoss_Gateway 3 10697
Protoss_Assimilator 2 8181
Protoss_Cybernetics_Core 1 7345
Protoss_Zealot 4 9641
Protoss_Stargate 1 8769
Protoss_Citadel_of_Adun 1 9262
Protoss_Corsair 3 10599
10697
