Protoss_Forge 1 3461
Protoss_Nexus 1 6143
Protoss_Photon_Cannon 5 10733
Protoss_Gateway 1 5257
Protoss_Assimilator 2 9317
Protoss_Cybernetics_Core 1 6241
Protoss_Zealot 5 9831
Protoss_Stargate 1 7469
Protoss_Dragoon 1 7873
Protoss_Corsair 3 10951
Protoss_Robotics_Facility 1 10759
10951
