Protoss_Assimilator 1 2887
Protoss_Gateway 1 3758
Protoss_Cybernetics_Core 1 4758
Protoss_Robotics_Facility 1 6243
Protoss_Dragoon 1 5546
Protoss_Zealot 2 6731
Protoss_Shuttle 1 7046
Protoss_Robotics_Support_Bay 1 6678
Protoss_Citadel_of_Adun 1 8066
Protoss_Reaver 2 10846
Protoss_Forge 1 8078
Protoss_Photon_Cannon 3 11127
Protoss_Templar_Archives 1 9590
Protoss_High_Templar 1 10336
11127
