Protoss_Gateway 2 6634
Protoss_Assimilator 1 3091
Protoss_Zealot 7 9581
Protoss_Cybernetics_Core 1 5214
Protoss_Dragoon 1 5989
Protoss_Citadel_of_Adun 1 6359
Protoss_Templar_Archives 1 7355
Protoss_High_Templar 2 8103
Protoss_Forge 1 8189
Protoss_Dark_Templar 2 8859
Protoss_Archon 1 8187
Protoss_Photon_Cannon 2 9393
Protoss_Nexus 1 12653
12653
