Protoss_Gateway 3 9221
Protoss_Assimilator 1 3468
Protoss_Zealot 2 5011
Protoss_Cybernetics_Core 1 5273
Protoss_Dragoon 8 11076
Protoss_Robotics_Facility 1 7223
Protoss_Shuttle 1 8031
Protoss_Robotics_Support_Bay 1 7378
Protoss_Reaver 2 10225
11076
