Protoss_Gateway 1 3243
Protoss_Assimilator 2 10591
Protoss_Zealot 5 7123
Protoss_Cybernetics_Core 1 5013
Protoss_Stargate 1 6250
Protoss_Dragoon 1 5857
Protoss_Citadel_of_Adun 1 6731
Protoss_Corsair 3 10893
Protoss_Templar_Archives 1 7827
Protoss_Forge 1 8163
Protoss_Dark_Templar 1 8597
Protoss_Photon_Cannon 2 9164
Protoss_Nexus 1 11251
Protoss_High_Templar 1 10813
11251
