Protoss_Forge 1 3151
Protoss_Photon_Cannon 3 10194
Protoss_Nexus 1 6559
Protoss_Gateway 3 10115
Protoss_Assimilator 2 7610
Protoss_Cybernetics_Core 1 6891
Protoss_Zealot 7 10531
Protoss_Stargate 1 8148
Protoss_Citadel_of_Adun 1 8461
Protoss_Corsair 1 8565
Protoss_Templar_Archives 1 9623
Protoss_High_Templar 2 10903
10903
