Protoss_Gateway 2 3623
Protoss_Zealot 11 10215
Protoss_Nexus 2 10562
Protoss_Assimilator 2 10298
Protoss_Forge 1 8007
Protoss_Photon_Cannon 2 10873
Protoss_Cybernetics_Core 1 9404
Protoss_Stargate 1 10714
Protoss_Robotics_Facility 1 11699
11699
