Protoss_Gateway 1 3466
Protoss_Zealot 10 10731
Protoss_Forge 1 5371
Protoss_Photon_Cannon 4 10058
Protoss_Nexus 1 9778
Protoss_Assimilator 1 9501
Protoss_Cybernetics_Core 1 11071
11071
