Protoss_Forge 1 3612
Protoss_Nexus 1 6304
Protoss_Gateway 4 10259
Protoss_Assimilator 2 8437
Protoss_Photon_Cannon 5 11164
Protoss_Cybernetics_Core 1 6696
Protoss_Zealot 9 10015
Protoss_Dragoon 1 7443
Protoss_Citadel_of_Adun 1 7864
Protoss_Templar_Archives 1 9824
Protoss_Ground_Weapons_1 1 9557
Protoss_Dark_Templar 2 10857
Protoss_High_Templar 2 11141
11164
