Protoss_Forge 1 3611
Protoss_Nexus 1 6200
Protoss_Photon_Cannon 3 10701
Protoss_Gateway 2 9333
Protoss_Assimilator 2 6609
Protoss_Cybernetics_Core 1 6421
Protoss_Zealot 6 10039
Protoss_Stargate 1 7775
Protoss_Citadel_of_Adun 1 8270
Protoss_Corsair 2 8959
Protoss_Templar_Archives 1 10151
Protoss_Dark_Templar 2 11011
11011
