Protoss_Gateway 1 3371
Protoss_Assimilator 1 3370
Protoss_Zealot 3 5170
Protoss_Cybernetics_Core 1 5305
Protoss_Dragoon 6 11161
Protoss_Robotics_Facility 1 7486
Protoss_Shuttle 1 8291
Protoss_Robotics_Support_Bay 1 8017
Protoss_Reaver 2 10791
Protoss_Forge 1 8935
11161
