Protoss_Gateway 2 7448
Protoss_Forge 1 4047
Protoss_Zealot 11 10891
Protoss_Photon_Cannon 3 8073
Protoss_Nexus 1 8318
Protoss_Assimilator 2 10942
Protoss_Cybernetics_Core 1 10003
10942
