Protoss_Forge 1 3249
Protoss_Photon_Cannon 5 10603
Protoss_Nexus 1 6887
Protoss_Gateway 3 8830
Protoss_Assimilator 2 7088
Protoss_Zealot 7 10603
Protoss_Cybernetics_Core 1 6828
Protoss_Citadel_of_Adun 1 7929
Protoss_Dragoon 1 7775
Protoss_Templar_Archives 1 9275
Protoss_High_Templar 4 11069
Protoss_Dark_Templar 1 10869
Protoss_Archon 1 10342
11069
