Protoss_Forge 1 3098
Protoss_Nexus 1 6314
Protoss_Photon_Cannon 2 10636
Protoss_Gateway 4 9179
Protoss_Assimilator 2 9539
Protoss_Cybernetics_Core 1 7059
Protoss_Zealot 12 10611
Protoss_Citadel_of_Adun 1 8221
Protoss_Stargate 1 10017
Protoss_Templar_Archives 1 10723
Protoss_Corsair 1 10741
10741
