Protoss_Gateway 2 3870
Protoss_Zealot 12 10613
Protoss_Nexus 2 12241
Protoss_Assimilator 1 6501
Protoss_Cybernetics_Core 1 7429
Protoss_Stargate 1 8776
Protoss_Dragoon 1 8455
Protoss_Forge 1 8791
Protoss_Corsair 2 9821
Protoss_Photon_Cannon 3 11127
12241
