Protoss_Forge 1 2930
Protoss_Photon_Cannon 3 7989
Protoss_Nexus 1 7193
Protoss_Gateway 3 10127
Protoss_Assimilator 2 8639
Protoss_Zealot 7 10727
Protoss_Cybernetics_Core 1 7392
Protoss_Stargate 1 8787
Protoss_Dragoon 1 8519
Protoss_Corsair 2 9939
Protoss_Citadel_of_Adun 1 10669
10727
