Protoss_Forge 2 10623
Protoss_Photon_Cannon 7 10666
Protoss_Nexus 1 6431
Protoss_Gateway 2 9524
Protoss_Assimilator 2 6771
Protoss_Cybernetics_Core 1 6283
Protoss_Zealot 10 10715
Protoss_Stargate 1 7693
Protoss_Corsair 2 8801
Protoss_Citadel_of_Adun 1 8745
10715
