Protoss_Gateway 2 3775
Protoss_Zealot 9 8799
Protoss_Assimilator 1 5147
Protoss_Cybernetics_Core 1 6149
Protoss_Stargate 1 7396
Protoss_Dragoon 1 7375
Protoss_Citadel_of_Adun 1 7894
Protoss_Corsair 1 7835
Protoss_Templar_Archives 1 10047
Protoss_Forge 1 9717
10047
