Protoss_Nexus 1 5703
Protoss_Gateway 2 8538
Protoss_Assimilator 2 6543
Protoss_Zealot 10 9839
Protoss_Cybernetics_Core 1 6418
Protoss_Stargate 1 7649
Protoss_Citadel_of_Adun 1 7774
Protoss_Corsair 1 8121
Protoss_Templar_Archives 1 9314
Protoss_Forge 1 9425
Protoss_High_Templar 2 10681
Protoss_Photon_Cannon 3 11150
11150
