Protoss_Gateway 2 11046
Protoss_Zealot 10 10249
Protoss_Forge 1 5362
Protoss_Nexus 1 8003
Protoss_Assimilator 2 8167
Protoss_Photon_Cannon 3 10578
Protoss_Cybernetics_Core 1 7559
Protoss_Stargate 1 9337
Protoss_Robotics_Facility 1 10334
Protoss_Corsair 2 10481
Protoss_Robotics_Support_Bay 1 10572
Protoss_Shuttle 1 11331
11331
