Protoss_Forge 1 3324
Protoss_Photon_Cannon 4 9421
Protoss_Nexus 1 6705
Protoss_Gateway 1 6245
Protoss_Assimilator 2 6881
Protoss_Cybernetics_Core 1 7231
Protoss_Stargate 1 8542
Protoss_Zealot 3 9671
Protoss_Robotics_Facility 1 9119
Protoss_Corsair 3 10597
Protoss_Robotics_Support_Bay 1 9234
Protoss_Reaver 1 10823
10823
