Protoss_Forge 1 3538
Protoss_Photon_Cannon 3 10409
Protoss_Nexus 1 7035
Protoss_Gateway 3 9747
Protoss_Assimilator 2 8104
Protoss_Cybernetics_Core 1 7166
Protoss_Zealot 8 10679
Protoss_Stargate 1 8669
Protoss_Citadel_of_Adun 1 8851
Protoss_Corsair 2 9871
10679
