Protoss_Gateway 2 10862
Protoss_Zealot 7 10431
Protoss_Nexus 1 6673
Protoss_Assimilator 2 6439
Protoss_Cybernetics_Core 1 6185
Protoss_Stargate 1 7483
Protoss_Dragoon 1 7469
Protoss_Forge 1 7577
Protoss_Corsair 4 10507
Protoss_Citadel_of_Adun 1 8737
Protoss_Photon_Cannon 3 10633
10862
