Protoss_Gateway 2 9284
Protoss_Assimilator 2 9581
Protoss_Cybernetics_Core 1 4525
Protoss_Zealot 2 5149
Protoss_Stargate 1 5818
Protoss_Citadel_of_Adun 1 6162
Protoss_Dragoon 2 6793
Protoss_Corsair 1 6371
Protoss_Templar_Archives 1 7511
Protoss_Nexus 1 9835
Protoss_Dark_Templar 2 9111
Protoss_Forge 1 9193
Protoss_High_Templar 2 10117
Protoss_Photon_Cannon 2 10694
Protoss_Archon 1 10303
10694
