Protoss_Forge 1 3321
Protoss_Nexus 1 6071
Protoss_Photon_Cannon 2 9617
Protoss_Gateway 5 10815
Protoss_Assimilator 2 6725
Protoss_Cybernetics_Core 1 6485
Protoss_Zealot 3 9079
Protoss_Stargate 1 7785
Protoss_Dragoon 1 7545
Protoss_Citadel_of_Adun 1 8344
Protoss_Corsair 2 8897
Protoss_Templar_Archives 1 9359
Protoss_Dark_Templar 1 10129
10815
