Protoss_Gateway 2 9759
Protoss_Zealot 11 10383
Protoss_Nexus 1 6773
Protoss_Assimilator 2 8111
Protoss_Cybernetics_Core 1 6823
Protoss_Forge 1 7126
Protoss_Stargate 1 8173
Protoss_Citadel_of_Adun 1 8873
Protoss_Corsair 2 9437
Protoss_Photon_Cannon 2 11028
Protoss_Templar_Archives 1 11026
11028
