Protoss_Gateway 2 8763
Protoss_Zealot 9 10617
Protoss_Assimilator 1 4383
Protoss_Cybernetics_Core 1 5400
Protoss_Dragoon 1 6163
Protoss_Stargate 1 6988
Protoss_Forge 1 6607
Protoss_Corsair 1 7405
Protoss_Citadel_of_Adun 1 8631
Protoss_Photon_Cannon 1 9887
10617
