Protoss_Forge 1 3376
Protoss_Photon_Cannon 3 10982
Protoss_Nexus 1 7219
Protoss_Gateway 2 9706
Protoss_Assimilator 2 7530
Protoss_Cybernetics_Core 1 7130
Protoss_Zealot 2 8219
Protoss_Stargate 1 8379
Protoss_Citadel_of_Adun 1 8470
Protoss_Corsair 2 9637
Protoss_Robotics_Facility 1 10001
Protoss_Templar_Archives 1 9857
Protoss_Shuttle 1 10833
Protoss_Dark_Templar 2 10761
10982
