Protoss_Forge 1 3156
Protoss_Photon_Cannon 4 10769
Protoss_Nexus 1 6542
Protoss_Gateway 2 9967
Protoss_Assimilator 2 8436
Protoss_Cybernetics_Core 1 7279
Protoss_Zealot 4 10347
Protoss_Stargate 1 8598
Protoss_Dragoon 1 8557
Protoss_Citadel_of_Adun 1 9187
Protoss_Corsair 3 10381
Protoss_Templar_Archives 1 11063
11063
