Protoss_Gateway 4 10925
Protoss_Zealot 9 10723
Protoss_Assimilator 1 5090
Protoss_Cybernetics_Core 1 6159
Protoss_Stargate 1 7419
Protoss_Forge 1 7109
Protoss_Citadel_of_Adun 1 7937
Protoss_Photon_Cannon 4 9534
Protoss_Corsair 2 8645
Protoss_Templar_Archives 1 9514
10925
