Protoss_Gateway 2 7286
Protoss_Assimilator 1 3149
Protoss_Zealot 4 10379
Protoss_Cybernetics_Core 1 4623
Protoss_Stargate 1 5936
Protoss_Dragoon 7 9641
Protoss_Corsair 5 10451
Protoss_Citadel_of_Adun 1 10451
10451
