Protoss_Forge 1 3059
Protoss_Nexus 1 6468
Protoss_Photon_Cannon 3 11195
Protoss_Gateway 3 9344
Protoss_Assimilator 2 9511
Protoss_Zealot 6 10951
Protoss_Cybernetics_Core 1 7910
Protoss_Stargate 1 9440
Protoss_Dragoon 1 9186
Protoss_Citadel_of_Adun 1 10541
11195
