Protoss_Forge 1 3057
Protoss_Photon_Cannon 2 10773
Protoss_Nexus 1 6655
Protoss_Gateway 4 10552
Protoss_Assimilator 2 7934
Protoss_Cybernetics_Core 1 6660
Protoss_Zealot 8 10955
Protoss_Stargate 1 7911
Protoss_Citadel_of_Adun 1 8239
Protoss_Corsair 4 10559
10955
