Protoss_Forge 1 3338
Protoss_Photon_Cannon 4 10874
Protoss_Nexus 1 6760
Protoss_Gateway 1 5989
Protoss_Assimilator 2 7883
Protoss_Zealot 3 9069
Protoss_Cybernetics_Core 1 7774
Protoss_Dragoon 1 8557
Protoss_Stargate 2 10444
Protoss_Corsair 3 10879
Protoss_Robotics_Facility 1 11113
11113
