Protoss_Gateway 1 3299
Protoss_Zealot 5 7937
Protoss_Assimilator 1 4046
Protoss_Cybernetics_Core 1 4953
Protoss_Stargate 1 6314
Protoss_Dragoon 1 6039
Protoss_Forge 1 6318
Protoss_Corsair 3 10477
Protoss_Photon_Cannon 5 11023
Protoss_Nexus 1 10561
Protoss_Robotics_Facility 1 10231
11023
