Protoss_Gateway 2 3787
Protoss_Zealot 13 8656
Protoss_Assimilator 1 6161
Protoss_Cybernetics_Core 1 8274
Protoss_Citadel_of_Adun 1 9268
Protoss_Dragoon 1 9071
Protoss_Forge 1 9254
Protoss_Templar_Archives 1 10352
Protoss_Dark_Templar 1 11111
11111
