Protoss_Nexus 1 5939
Protoss_Gateway 3 10988
Protoss_Assimilator 2 6556
Protoss_Cybernetics_Core 1 5868
Protoss_Stargate 1 7169
Protoss_Robotics_Facility 1 8578
Protoss_Corsair 2 8326
Protoss_Forge 1 7938
Protoss_Dragoon 3 10526
Protoss_Robotics_Support_Bay 1 8713
Protoss_Reaver 2 11268
11268
