Protoss_Gateway 2 4071
Protoss_Zealot 7 8016
Protoss_Assimilator 1 4570
Protoss_Cybernetics_Core 1 5802
Protoss_Dragoon 1 6606
Protoss_Citadel_of_Adun 1 6984
Protoss_Templar_Archives 1 9006
Protoss_Forge 1 8914
Protoss_High_Templar 3 11151
Protoss_Photon_Cannon 4 11154
11154
