Protoss_Gateway 2 9388
Protoss_Assimilator 1 3175
Protoss_Cybernetics_Core 1 4413
Protoss_Zealot 11 10105
Protoss_Stargate 1 6067
Protoss_Corsair 3 7811
Protoss_Citadel_of_Adun 1 9025
Protoss_Robotics_Facility 1 10410
Protoss_Shuttle 1 11239
Protoss_Robotics_Support_Bay 1 10695
11239
