Protoss_Forge 1 3183
Protoss_Photon_Cannon 4 9653
Protoss_Nexus 1 6991
Protoss_Gateway 3 11374
Protoss_Assimilator 2 8607
Protoss_Cybernetics_Core 1 7007
Protoss_Zealot 4 9963
Protoss_Stargate 1 8381
Protoss_Citadel_of_Adun 1 8267
Protoss_Corsair 3 10909
Protoss_Templar_Archives 1 10011
Protoss_Dark_Templar 1 11109
11374
