Protoss_Gateway 1 3411
Protoss_Assimilator 1 3354
Protoss_Zealot 5 8196
Protoss_Cybernetics_Core 1 5399
Protoss_Dragoon 1 6241
Protoss_Citadel_of_Adun 1 6599
Protoss_Robotics_Facility 1 7512
Protoss_Shuttle 1 8331
Protoss_Templar_Archives 1 8341
Protoss_Forge 1 7993
Protoss_Robotics_Support_Bay 1 8138
Protoss_Photon_Cannon 2 11054
Protoss_Reaver 2 10698
Protoss_High_Templar 2 10653
Protoss_Scarab 1 9717
11054
