Protoss_Nexus 1 5963
Protoss_Forge 1 4493
Protoss_Gateway 4 8990
Protoss_Photon_Cannon 7 10747
Protoss_Zealot 10 10369
Protoss_Cybernetics_Core 1 7407
Protoss_Assimilator 2 7293
Protoss_Citadel_of_Adun 1 8710
Protoss_Templar_Archives 1 9823
Protoss_High_Templar 3 11199
11199
