Protoss_Gateway 2 4102
Protoss_Zealot 9 9336
Protoss_Assimilator 1 4598
Protoss_Cybernetics_Core 1 6129
Protoss_Stargate 1 7544
Protoss_Citadel_of_Adun 1 8054
Protoss_Dragoon 1 8281
Protoss_Forge 1 9629
Protoss_Nexus 1 12108
12108
