Protoss_Gateway 2 3935
Protoss_Zealot 15 9789
Protoss_Forge 1 6397
Protoss_Nexus 1 9604
Protoss_Photon_Cannon 1 8257
Protoss_Assimilator 2 10716
Protoss_Cybernetics_Core 1 9491
Protoss_Stargate 1 11032
11032
