Protoss_Forge 1 3587
Protoss_Gateway 1 4744
Protoss_Photon_Cannon 2 4827
Protoss_Assimilator 2 9635
Protoss_Cybernetics_Core 1 6102
Protoss_Stargate 1 7375
Protoss_Dragoon 1 7095
Protoss_Nexus 1 9445
Protoss_Corsair 5 10657
Protoss_Citadel_of_Adun 1 8744
Protoss_Zealot 2 10407
Protoss_Templar_Archives 1 9856
Protoss_Dark_Templar 1 10733
10733
