Protoss_Forge 1 2901
Protoss_Photon_Cannon 4 10195
Protoss_Nexus 1 6951
Protoss_Gateway 3 11115
Protoss_Assimilator 2 7673
Protoss_Cybernetics_Core 1 7153
Protoss_Zealot 4 10527
Protoss_Stargate 1 8611
Protoss_Dragoon 1 8341
Protoss_Citadel_of_Adun 1 9020
Protoss_Corsair 2 9791
Protoss_Templar_Archives 1 10086
Protoss_Dark_Templar 1 10997
11115
