Protoss_Nexus 1 5781
Protoss_Gateway 4 10037
Protoss_Forge 1 4625
Protoss_Assimilator 2 6885
Protoss_Photon_Cannon 2 8207
Protoss_Cybernetics_Core 1 6473
Protoss_Zealot 6 10649
Protoss_Dragoon 1 7243
Protoss_Stargate 1 7897
Protoss_Citadel_of_Adun 1 8301
Protoss_Corsair 1 8433
Protoss_Templar_Archives 1 9391
Protoss_High_Templar 2 10137
Protoss_Archon 1 10394
10649
