Protoss_Forge 2 3563
Protoss_Photon_Cannon 3 6043
Protoss_Gateway 2 9964
Protoss_Zealot 2 8803
Protoss_Nexus 1 9256
Protoss_Assimilator 2 8661
Protoss_Cybernetics_Core 1 8367
Protoss_Stargate 1 9979
Protoss_Citadel_of_Adun 1 10248
Protoss_Corsair 1 10393
Protoss_Templar_Archives 1 11355
11355
