Protoss_Forge 1 3592
Protoss_Nexus 1 6164
Protoss_Photon_Cannon 4 11016
Protoss_Gateway 4 10924
Protoss_Assimilator 2 7062
Protoss_Cybernetics_Core 1 6863
Protoss_Stargate 1 8123
Protoss_Citadel_of_Adun 1 8177
Protoss_Dragoon 1 8333
Protoss_Corsair 2 9709
Protoss_Templar_Archives 1 9545
Protoss_Zealot 2 10605
Protoss_High_Templar 2 10777
11016
