Protoss_Forge 1 3336
Protoss_Photon_Cannon 2 4415
Protoss_Nexus 1 6773
Protoss_Gateway 2 10562
Protoss_Assimilator 2 7471
Protoss_Cybernetics_Core 1 6683
Protoss_Zealot 5 9907
Protoss_Stargate 1 8007
Protoss_Corsair 4 10441
Protoss_Citadel_of_Adun 1 9100
Protoss_Templar_Archives 2 10341
10562
