Protoss_Gateway 4 9689
Protoss_Assimilator 1 3393
Protoss_Zealot 5 6795
Protoss_Cybernetics_Core 1 4897
Protoss_Stargate 1 6125
Protoss_Dragoon 11 11011
Protoss_Scout 1 7497
Protoss_Nexus 1 9479
11011
