Protoss_Forge 1 3243
Protoss_Photon_Cannon 2 4649
Protoss_Nexus 1 7781
Protoss_Gateway 3 7609
Protoss_Zealot 15 10583
Protoss_Assimilator 1 9157
Protoss_Cybernetics_Core 1 10036
10583
