Protoss_Forge 2 8873
Protoss_Nexus 1 6185
Protoss_Photon_Cannon 4 10958
Protoss_Gateway 3 11400
Protoss_Assimilator 2 9483
Protoss_Zealot 4 8879
Protoss_Cybernetics_Core 1 7025
Protoss_Stargate 1 8538
Protoss_Corsair 3 10589
Protoss_Citadel_of_Adun 1 9823
Protoss_Templar_Archives 1 11005
11400
