Protoss_Forge 1 3681
Protoss_Nexus 1 6129
Protoss_Photon_Cannon 2 11071
Protoss_Gateway 4 9464
Protoss_Zealot 5 10441
Protoss_Assimilator 2 7779
Protoss_Cybernetics_Core 2 7787
Protoss_Stargate 1 8665
Protoss_Citadel_of_Adun 1 9184
Protoss_Corsair 2 9859
Protoss_Templar_Archives 1 10467
11071
