Protoss_Gateway 2 4203
Protoss_Zealot 13 10747
Protoss_Assimilator 1 5357
Protoss_Cybernetics_Core 1 7049
Protoss_Citadel_of_Adun 1 8046
Protoss_Templar_Archives 1 9459
Protoss_High_Templar 2 10225
Protoss_Forge 1 10075
Protoss_Nexus 1 12437
12437
