Protoss_Gateway 1 3289
Protoss_Zealot 4 7312
Protoss_Assimilator 2 10402
Protoss_Cybernetics_Core 1 5016
Protoss_Stargate 1 6267
Protoss_Dragoon 1 5953
Protoss_Forge 1 6323
Protoss_Corsair 4 10819
Protoss_Photon_Cannon 5 11144
Protoss_Nexus 1 10555
Protoss_Robotics_Facility 1 10099
Protoss_Robotics_Support_Bay 1 10310
11144
