Protoss_Gateway 3 11019
Protoss_Zealot 8 9480
Protoss_Forge 2 8499
Protoss_Photon_Cannon 4 9485
Protoss_Assimilator 1 8087
Protoss_Cybernetics_Core 1 10433
Protoss_Dragoon 1 11179
11179
