Protoss_Forge 1 3554
Protoss_Nexus 1 6163
Protoss_Photon_Cannon 3 11055
Protoss_Gateway 1 5791
Protoss_Assimilator 2 7435
Protoss_Cybernetics_Core 1 6849
Protoss_Zealot 6 10102
Protoss_Stargate 1 8122
Protoss_Robotics_Facility 1 9447
Protoss_Corsair 4 10646
Protoss_Robotics_Support_Bay 1 9539
Protoss_Shuttle 1 10453
11055
