Protoss_Forge 1 2847
Protoss_Nexus 1 6029
Protoss_Photon_Cannon 3 10684
Protoss_Gateway 2 9228
Protoss_Assimilator 2 7088
Protoss_Zealot 2 7675
Protoss_Cybernetics_Core 1 6811
Protoss_Stargate 1 8152
Protoss_Citadel_of_Adun 1 8467
Protoss_Corsair 3 9919
Protoss_Templar_Archives 1 9553
Protoss_Dark_Templar 2 10301
Protoss_High_Templar 2 11129
11129
