Protoss_Gateway 2 10860
Protoss_Zealot 9 9857
Protoss_Nexus 1 7011
Protoss_Forge 1 5549
Protoss_Assimilator 2 9375
Protoss_Photon_Cannon 4 10921
Protoss_Cybernetics_Core 1 8971
Protoss_Stargate 1 10197
Protoss_Citadel_of_Adun 1 10263
Protoss_Corsair 1 10613
Protoss_Templar_Archives 1 11301
11301
