Protoss_Forge 1 3801
Protoss_Photon_Cannon 4 10641
Protoss_Nexus 1 6985
Protoss_Gateway 2 8973
Protoss_Assimilator 2 7602
Protoss_Cybernetics_Core 1 7147
Protoss_Zealot 8 10933
Protoss_Stargate 1 8516
Protoss_Citadel_of_Adun 1 8520
Protoss_Corsair 3 10885
Protoss_Templar_Archives 1 11018
11018
