Protoss_Nexus 1 5859
Protoss_Forge 1 4241
Protoss_Gateway 4 11426
Protoss_Photon_Cannon 3 10483
Protoss_Assimilator 2 7285
Protoss_Zealot 10 10465
Protoss_Cybernetics_Core 1 7059
Protoss_Stargate 1 8360
Protoss_Citadel_of_Adun 1 8493
Protoss_Corsair 1 8891
Protoss_Templar_Archives 1 10289
Protoss_High_Templar 2 11179
11426
