Protoss_Gateway 2 9745
Protoss_Assimilator 2 9717
Protoss_Zealot 4 6894
Protoss_Cybernetics_Core 1 4799
Protoss_Stargate 1 6081
Protoss_Dragoon 1 5697
Protoss_Citadel_of_Adun 1 6786
Protoss_Corsair 3 10827
Protoss_Templar_Archives 1 8025
Protoss_Forge 1 7687
Protoss_Nexus 1 10453
Protoss_Dark_Templar 1 8923
Protoss_Photon_Cannon 2 9689
Protoss_High_Templar 3 10841
10841
