Protoss_Forge 1 3791
Protoss_Photon_Cannon 3 10501
Protoss_Nexus 1 7069
Protoss_Gateway 2 10125
Protoss_Assimilator 2 7252
Protoss_Cybernetics_Core 1 7052
Protoss_Zealot 7 10627
Protoss_Stargate 1 8355
Protoss_Citadel_of_Adun 1 8743
Protoss_Corsair 2 10053
Protoss_Templar_Archives 1 11385
11385
