Protoss_Forge 1 3243
Protoss_Photon_Cannon 4 10104
Protoss_Nexus 1 6470
Protoss_Gateway 2 9690
Protoss_Assimilator 2 7699
Protoss_Zealot 9 10955
Protoss_Cybernetics_Core 1 6924
Protoss_Stargate 1 8186
Protoss_Citadel_of_Adun 1 8649
Protoss_Corsair 3 10369
10955
