Protoss_Forge 1 3222
Protoss_Nexus 1 6239
Protoss_Photon_Cannon 3 10821
Protoss_Gateway 3 9033
Protoss_Assimilator 2 7743
Protoss_Cybernetics_Core 1 6531
Protoss_Stargate 1 7797
Protoss_Zealot 4 9529
Protoss_Citadel_of_Adun 1 7971
Protoss_Corsair 2 9449
Protoss_Templar_Archives 1 9624
Protoss_High_Templar 2 10477
Protoss_Dark_Templar 1 11051
11051
