Protoss_Forge 1 3209
Protoss_Nexus 2 11137
Protoss_Photon_Cannon 3 10936
Protoss_Gateway 1 5420
Protoss_Assimilator 2 7662
Protoss_Zealot 2 8023
Protoss_Cybernetics_Core 1 7584
Protoss_Robotics_Facility 1 9127
Protoss_Stargate 1 8994
Protoss_Corsair 2 10255
Protoss_Robotics_Support_Bay 1 9400
Protoss_Reaver 1 11027
11137
