Protoss_Gateway 3 9468
Protoss_Forge 1 3643
Protoss_Zealot 9 10656
Protoss_Photon_Cannon 6 8633
Protoss_Nexus 1 8883
Protoss_Assimilator 1 8584
Protoss_Cybernetics_Core 1 10786
10786
