Protoss_Forge 1 3584
Protoss_Photon_Cannon 3 11017
Protoss_Nexus 1 6959
Protoss_Gateway 3 9985
Protoss_Assimilator 2 9704
Protoss_Cybernetics_Core 1 6961
Protoss_Zealot 8 10813
Protoss_Stargate 1 8245
Protoss_Dragoon 1 8159
Protoss_Citadel_of_Adun 1 8866
Protoss_Corsair 2 10103
11017
