Protoss_Gateway 2 3521
Protoss_Zealot 14 10781
Protoss_Assimilator 1 4673
Protoss_Cybernetics_Core 1 7040
Protoss_Stargate 1 8320
Protoss_Citadel_of_Adun 1 8977
Protoss_Corsair 2 9351
Protoss_Forge 1 9148
Protoss_Templar_Archives 1 10071
Protoss_Dark_Templar 1 10865
10865
