Protoss_Forge 1 3607
Protoss_Photon_Cannon 4 11181
Protoss_Nexus 1 6954
Protoss_Gateway 2 9583
Protoss_Assimilator 2 7913
Protoss_Cybernetics_Core 1 6878
Protoss_Zealot 6 10485
Protoss_Stargate 1 8426
Protoss_Citadel_of_Adun 1 8914
Protoss_Corsair 1 8853
Protoss_Templar_Archives 1 10556
11181
