Protoss_Forge 1 3299
Protoss_Nexus 1 6039
Protoss_Photon_Cannon 5 7955
Protoss_Gateway 1 6209
Protoss_Zealot 5 10504
Protoss_Cybernetics_Core 1 9136
Protoss_Assimilator 2 8927
Protoss_Stargate 2 11191
11191
