Protoss_Forge 1 2879
Protoss_Nexus 1 6329
Protoss_Photon_Cannon 3 10151
Protoss_Gateway 2 9726
Protoss_Assimilator 3 8763
Protoss_Cybernetics_Core 1 6665
Protoss_Zealot 6 10475
Protoss_Dragoon 1 7469
Protoss_Stargate 1 7957
Protoss_Citadel_of_Adun 1 8047
Protoss_Corsair 4 10255
Protoss_Templar_Archives 1 9614
Protoss_Dark_Templar 1 10637
10637
