Protoss_Forge 1 2969
Protoss_Nexus 1 6251
Protoss_Photon_Cannon 3 10589
Protoss_Gateway 2 8301
Protoss_Assimilator 2 8261
Protoss_Zealot 11 10771
Protoss_Cybernetics_Core 1 7085
Protoss_Citadel_of_Adun 1 8073
Protoss_Stargate 2 10144
Protoss_Templar_Archives 1 10409
10771
