Protoss_Nexus 1 5917
Protoss_Forge 1 4223
Protoss_Photon_Cannon 2 5256
Protoss_Gateway 4 10267
Protoss_Assimilator 2 7554
Protoss_Cybernetics_Core 1 7355
Protoss_Stargate 1 8583
Protoss_Zealot 10 10935
Protoss_Citadel_of_Adun 1 8925
Protoss_Corsair 1 9049
Protoss_Templar_Archives 1 10949
10949
