Protoss_Forge 1 3085
Protoss_Nexus 1 6203
Protoss_Photon_Cannon 2 9332
Protoss_Gateway 2 10016
Protoss_Assimilator 2 8773
Protoss_Zealot 4 10755
Protoss_Cybernetics_Core 1 7319
Protoss_Stargate 1 8650
Protoss_Dragoon 2 10181
Protoss_Citadel_of_Adun 1 8850
Protoss_Corsair 3 10710
Protoss_Templar_Archives 1 10409
10755
