Protoss_Forge 1 3221
Protoss_Photon_Cannon 5 10934
Protoss_Nexus 1 6887
Protoss_Gateway 3 10230
Protoss_Assimilator 2 8084
Protoss_Cybernetics_Core 1 7279
Protoss_Zealot 7 10763
Protoss_Stargate 1 8663
Protoss_Citadel_of_Adun 1 8867
Protoss_Corsair 2 9791
Protoss_Templar_Archives 1 10724
10934
