Protoss_Forge 1 3252
Protoss_Photon_Cannon 3 10108
Protoss_Nexus 1 7081
Protoss_Gateway 3 10015
Protoss_Assimilator 2 7224
Protoss_Cybernetics_Core 1 7029
Protoss_Zealot 4 10037
Protoss_Stargate 1 8291
Protoss_Citadel_of_Adun 1 8629
Protoss_Corsair 2 9749
Protoss_Templar_Archives 1 9623
Protoss_Dark_Templar 1 10403
10403
