Protoss_Forge 1 3483
Protoss_Photon_Cannon 3 10215
Protoss_Nexus 1 7113
Protoss_Gateway 3 9099
Protoss_Assimilator 2 7741
Protoss_Zealot 5 9187
Protoss_Cybernetics_Core 1 7129
Protoss_Citadel_of_Adun 1 8143
Protoss_Stargate 3 11231
Protoss_Dragoon 1 10081
Protoss_Corsair 2 10771
11231
