Protoss_Gateway 2 3692
Protoss_Zealot 9 7611
Protoss_Nexus 2 12134
Protoss_Assimilator 1 6441
Protoss_Cybernetics_Core 1 7589
Protoss_Stargate 1 9247
Protoss_Citadel_of_Adun 1 9128
Protoss_Forge 1 9135
Protoss_Corsair 2 10687
Protoss_Templar_Archives 1 10356
Protoss_Photon_Cannon 2 10725
Protoss_Dark_Templar 1 11193
12134
