Protoss_Forge 1 3253
Protoss_Photon_Cannon 3 10784
Protoss_Nexus 1 7015
Protoss_Gateway 1 5832
Protoss_Assimilator 2 6875
Protoss_Cybernetics_Core 1 6873
Protoss_Zealot 4 9653
Protoss_Stargate 2 9123
Protoss_Citadel_of_Adun 1 8412
Protoss_Corsair 7 10915
Protoss_Templar_Archives 1 10467
10915
