Protoss_Gateway 2 3873
Protoss_Zealot 11 8396
Protoss_Assimilator 1 6093
Protoss_Cybernetics_Core 1 7027
Protoss_Stargate 1 8793
Protoss_Dragoon 1 8501
Protoss_Robotics_Facility 1 10012
Protoss_Corsair 1 9391
Protoss_Forge 1 9976
Protoss_Robotics_Support_Bay 1 10137
Protoss_Shuttle 1 10861
Protoss_Photon_Cannon 1 11023
11023
