Protoss_Forge 1 3576
Protoss_Photon_Cannon 2 4554
Protoss_Nexus 1 7111
Protoss_Gateway 2 9097
Protoss_Assimilator 2 7624
Protoss_Zealot 8 10923
Protoss_Cybernetics_Core 1 7213
Protoss_Stargate 1 8472
Protoss_Dragoon 1 8089
Protoss_Citadel_of_Adun 1 8956
Protoss_Corsair 2 9695
Protoss_Templar_Archives 1 10553
10923
