Protoss_Forge 1 3094
Protoss_Photon_Cannon 4 10932
Protoss_Nexus 1 6967
Protoss_Gateway 2 9248
Protoss_Assimilator 2 7475
Protoss_Cybernetics_Core 1 6824
Protoss_Zealot 4 9405
Protoss_Stargate 1 8102
Protoss_Citadel_of_Adun 1 8533
Protoss_Corsair 2 9803
Protoss_Templar_Archives 1 9667
Protoss_High_Templar 2 10791
10932
