Protoss_Forge 1 3548
Protoss_Nexus 1 6116
Protoss_Photon_Cannon 6 11175
Protoss_Gateway 2 10085
Protoss_Assimilator 2 7882
Protoss_Zealot 4 10051
Protoss_Cybernetics_Core 1 7414
Protoss_Stargate 1 8675
Protoss_Citadel_of_Adun 1 9069
Protoss_Corsair 3 10603
Protoss_Dragoon 2 10975
11175
