Protoss_Forge 1 3064
Protoss_Nexus 1 6063
Protoss_Photon_Cannon 1 4691
Protoss_Gateway 4 10604
Protoss_Assimilator 2 7629
Protoss_Zealot 11 10942
Protoss_Cybernetics_Core 1 7250
Protoss_Stargate 1 8515
Protoss_Citadel_of_Adun 1 8697
Protoss_Corsair 1 8925
10942
