Protoss_Forge 1 2979
Protoss_Nexus 1 6326
Protoss_Gateway 3 10310
Protoss_Assimilator 2 8135
Protoss_Photon_Cannon 1 5715
Protoss_Cybernetics_Core 1 6687
Protoss_Zealot 6 10319
Protoss_Stargate 1 7925
Protoss_Corsair 4 10193
Protoss_Citadel_of_Adun 1 8989
Protoss_Templar_Archives 1 10050
10319
