Protoss_Forge 1 3442
Protoss_Photon_Cannon 3 11084
Protoss_Nexus 1 6511
Protoss_Gateway 2 10821
Protoss_Assimilator 2 9169
Protoss_Cybernetics_Core 1 7506
Protoss_Zealot 2 9095
Protoss_Stargate 1 8778
Protoss_Dragoon 1 8353
Protoss_Corsair 1 9199
Protoss_Citadel_of_Adun 1 9825
Protoss_Templar_Archives 1 10908
11084
