Protoss_Forge 1 3448
Protoss_Nexus 1 5999
Protoss_Photon_Cannon 4 11049
Protoss_Gateway 2 10675
Protoss_Assimilator 3 7917
Protoss_Cybernetics_Core 1 6816
Protoss_Stargate 1 8055
Protoss_Zealot 5 10723
Protoss_Corsair 5 10949
Protoss_Citadel_of_Adun 1 9385
11049
