Protoss_Gateway 2 2473
Protoss_Zealot 9 5926
Protoss_Nexus 1 6828
Protoss_Assimilator 1 7211
Protoss_Forge 1 7533
Protoss_Cybernetics_Core 1 8477
Protoss_Photon_Cannon 1 8513
8513
