Protoss_Forge 1 3411
Protoss_Photon_Cannon 3 10935
Protoss_Nexus 1 6733
Protoss_Gateway 4 10868
Protoss_Assimilator 2 10779
Protoss_Cybernetics_Core 1 6863
Protoss_Zealot 9 10671
Protoss_Stargate 1 8190
Protoss_Citadel_of_Adun 1 8843
Protoss_Corsair 1 8683
Protoss_Templar_Archives 1 10821
10935
