Protoss_Gateway 2 8047
Protoss_Assimilator 1 3568
Protoss_Zealot 3 5183
Protoss_Cybernetics_Core 1 5366
Protoss_Dragoon 9 11053
Protoss_Stargate 1 6975
Protoss_Corsair 4 10111
11053
