Protoss_Gateway 2 3893
Protoss_Zealot 12 7983
Protoss_Assimilator 1 5441
Protoss_Cybernetics_Core 1 7672
Protoss_Stargate 2 9457
Protoss_Dragoon 2 8825
Protoss_Forge 1 8920
Protoss_Corsair 4 10801
Protoss_Photon_Cannon 2 10849
10849
