Protoss_Forge 1 3404
Protoss_Photon_Cannon 5 10479
Protoss_Nexus 1 7729
Protoss_Gateway 2 9664
Protoss_Assimilator 2 8445
Protoss_Cybernetics_Core 1 7646
Protoss_Zealot 7 10877
Protoss_Stargate 1 8903
Protoss_Citadel_of_Adun 1 9152
Protoss_Corsair 2 10707
Protoss_Templar_Archives 1 11026
11026
