Protoss_Forge 1 3487
Protoss_Nexus 1 6041
Protoss_Photon_Cannon 2 10446
Protoss_Gateway 2 9387
Protoss_Assimilator 2 7012
Protoss_Cybernetics_Core 1 6285
Protoss_Zealot 4 8419
Protoss_Stargate 1 7529
Protoss_Citadel_of_Adun 1 7885
Protoss_Corsair 4 10851
Protoss_Templar_Archives 1 8968
Protoss_Dark_Templar 2 10297
Protoss_High_Templar 1 11049
11049
