Protoss_Forge 1 3061
Protoss_Nexus 1 6459
Protoss_Gateway 4 8843
Protoss_Photon_Cannon 2 9818
Protoss_Assimilator 1 5618
Protoss_Zealot 5 9919
Protoss_Cybernetics_Core 1 6739
Protoss_Dragoon 8 10769
Protoss_Citadel_of_Adun 1 10721
Protoss_Ground_Weapons_1 1 9975
10769
