Protoss_Forge 2 9515
Protoss_Nexus 1 6017
Protoss_Photon_Cannon 2 8060
Protoss_Gateway 2 10289
Protoss_Assimilator 2 6999
Protoss_Cybernetics_Core 1 6269
Protoss_Zealot 4 10563
Protoss_Stargate 1 7503
Protoss_Corsair 5 10601
Protoss_Citadel_of_Adun 1 9276
Protoss_Templar_Archives 1 10467
Protoss_Robotics_Facility 1 11844
11844
