Protoss_Forge 2 10292
Protoss_Nexus 1 6183
Protoss_Photon_Cannon 2 5137
Protoss_Gateway 3 9501
Protoss_Assimilator 2 7559
Protoss_Cybernetics_Core 1 6840
Protoss_Zealot 10 10839
Protoss_Stargate 1 8111
Protoss_Citadel_of_Adun 1 8783
Protoss_Corsair 2 9635
Protoss_Templar_Archives 1 10844
10844
