Protoss_Forge 1 3696
Protoss_Nexus 1 6007
Protoss_Gateway 4 8594
Protoss_Assimilator 2 8257
Protoss_Photon_Cannon 4 11053
Protoss_Cybernetics_Core 1 6133
Protoss_Zealot 11 10726
Protoss_Citadel_of_Adun 1 8029
Protoss_Dragoon 1 9765
Protoss_Templar_Archives 1 10258
Protoss_Ground_Weapons_1 1 9429
11053
