Protoss_Forge 1 3073
Protoss_Nexus 1 6031
Protoss_Photon_Cannon 2 9596
Protoss_Gateway 5 11122
Protoss_Assimilator 2 8696
Protoss_Zealot 6 10843
Protoss_Cybernetics_Core 1 6963
Protoss_Stargate 1 8254
Protoss_Citadel_of_Adun 1 8645
Protoss_Corsair 1 8701
Protoss_Templar_Archives 1 9900
Protoss_Dark_Templar 1 10919
11122
