Protoss_Forge 1 3196
Protoss_Nexus 1 6265
Protoss_Photon_Cannon 1 4669
Protoss_Gateway 6 11088
Protoss_Assimilator 2 6733
Protoss_Cybernetics_Core 1 6546
Protoss_Zealot 4 8669
Protoss_Citadel_of_Adun 1 7663
Protoss_Templar_Archives 1 9003
Protoss_Dark_Templar 4 10611
Protoss_High_Templar 1 11027
11088
