Protoss_Nexus 1 5905
Protoss_Forge 1 4297
Protoss_Photon_Cannon 4 10664
Protoss_Gateway 2 9925
Protoss_Assimilator 2 8444
Protoss_Cybernetics_Core 1 7186
Protoss_Zealot 6 10455
Protoss_Stargate 1 8697
Protoss_Citadel_of_Adun 1 8824
Protoss_Corsair 1 9123
Protoss_Templar_Archives 1 11295
11295
