Protoss_Forge 1 3427
Protoss_Photon_Cannon 2 10891
Protoss_Nexus 1 6697
Protoss_Gateway 4 11014
Protoss_Assimilator 2 7562
Protoss_Zealot 4 9091
Protoss_Cybernetics_Core 1 7451
Protoss_Citadel_of_Adun 1 8642
Protoss_Templar_Archives 1 9687
Protoss_Dark_Templar 4 11189
11189
