Protoss_Forge 1 3673
Protoss_Nexus 1 6087
Protoss_Photon_Cannon 3 8925
Protoss_Gateway 6 11318
Protoss_Assimilator 2 6988
Protoss_Cybernetics_Core 1 6795
Protoss_Zealot 8 10933
Protoss_Stargate 1 8043
Protoss_Citadel_of_Adun 1 8626
Protoss_Corsair 2 9731
11318
