Protoss_Gateway 2 3968
Protoss_Zealot 15 10865
Protoss_Assimilator 1 7431
Protoss_Nexus 1 9531
Protoss_Forge 1 8068
Protoss_Cybernetics_Core 1 8865
Protoss_Photon_Cannon 4 10402
Protoss_Stargate 1 11018
11018
