Protoss_Forge 1 3555
Protoss_Nexus 1 6163
Protoss_Photon_Cannon 5 11121
Protoss_Gateway 4 10195
Protoss_Assimilator 2 8233
Protoss_Zealot 6 10535
Protoss_Cybernetics_Core 1 7422
Protoss_Stargate 1 8656
Protoss_Citadel_of_Adun 1 9232
Protoss_Corsair 1 9073
11121
