Protoss_Gateway 2 3853
Protoss_Zealot 7 9025
Protoss_Nexus 2 12549
Protoss_Assimilator 1 5549
Protoss_Cybernetics_Core 1 6651
Protoss_Stargate 1 8085
Protoss_Dragoon 1 7841
Protoss_Corsair 2 9163
Protoss_Forge 1 9343
Protoss_Photon_Cannon 2 10385
Protoss_Citadel_of_Adun 1 10582
12549
