Protoss_Forge 1 3135
Protoss_Nexus 1 6186
Protoss_Photon_Cannon 1 4785
Protoss_Gateway 4 10978
Protoss_Assimilator 2 8060
Protoss_Zealot 8 10543
Protoss_Cybernetics_Core 1 7152
Protoss_Dragoon 1 7891
Protoss_Stargate 1 8418
Protoss_Citadel_of_Adun 1 9040
Protoss_Corsair 1 8925
Protoss_Templar_Archives 1 10379
Protoss_Dark_Templar 1 11135
11135
