Protoss_Forge 1 3401
Protoss_Nexus 1 6239
Protoss_Photon_Cannon 2 10837
Protoss_Gateway 3 9437
Protoss_Assimilator 2 8154
Protoss_Cybernetics_Core 1 6459
Protoss_Zealot 11 10847
Protoss_Stargate 1 7763
Protoss_Dragoon 1 7577
Protoss_Citadel_of_Adun 1 8099
Protoss_Corsair 2 9105
10847
