Protoss_Forge 1 3277
Protoss_Nexus 1 6165
Protoss_Photon_Cannon 3 9445
Protoss_Assimilator 2 7985
Protoss_Gateway 3 10783
Protoss_Cybernetics_Core 1 7347
Protoss_Zealot 7 10807
Protoss_Stargate 1 8622
Protoss_Citadel_of_Adun 1 9126
Protoss_Corsair 3 10623
Protoss_Templar_Archives 1 10993
10993
