Protoss_Forge 1 3033
Protoss_Photon_Cannon 6 11191
Protoss_Nexus 1 7145
Protoss_Gateway 1 6025
Protoss_Assimilator 2 8140
Protoss_Zealot 3 10475
Protoss_Cybernetics_Core 1 7285
Protoss_Stargate 1 8588
Protoss_Corsair 2 10237
Protoss_Robotics_Facility 1 10478
Protoss_Robotics_Support_Bay 1 10579
11191
