Protoss_Forge 1 3099
Protoss_Photon_Cannon 5 10706
Protoss_Nexus 1 6807
Protoss_Gateway 1 5715
Protoss_Assimilator 2 8125
Protoss_Zealot 6 10677
Protoss_Cybernetics_Core 2 8085
Protoss_Dragoon 1 8881
Protoss_Stargate 1 9633
Protoss_Citadel_of_Adun 1 10255
Protoss_Corsair 2 10677
10706
