Protoss_Forge 1 3259
Protoss_Photon_Cannon 3 10080
Protoss_Nexus 1 6757
Protoss_Gateway 2 9502
Protoss_Assimilator 2 7306
Protoss_Cybernetics_Core 1 6855
Protoss_Zealot 3 9341
Protoss_Stargate 1 8165
Protoss_Citadel_of_Adun 1 8600
Protoss_Dragoon 1 8633
Protoss_Corsair 4 10737
Protoss_Templar_Archives 1 9659
Protoss_Dark_Templar 2 10545
10737
