Protoss_Forge 1 3735
Protoss_Nexus 1 6463
Protoss_Photon_Cannon 3 10956
Protoss_Gateway 2 8971
Protoss_Assimilator 2 7329
Protoss_Cybernetics_Core 1 6978
Protoss_Zealot 5 9949
Protoss_Stargate 1 8283
Protoss_Citadel_of_Adun 1 8676
Protoss_Corsair 1 8751
Protoss_Templar_Archives 1 9683
Protoss_High_Templar 2 10791
10956
