Protoss_Forge 1 3084
Protoss_Photon_Cannon 5 11071
Protoss_Nexus 1 6692
Protoss_Gateway 4 11438
Protoss_Assimilator 2 7703
Protoss_Cybernetics_Core 1 6512
Protoss_Zealot 8 10793
Protoss_Stargate 1 7865
Protoss_Citadel_of_Adun 1 8490
Protoss_Corsair 2 9061
Protoss_Templar_Archives 1 10262
11438
