Protoss_Forge 1 3240
Protoss_Photon_Cannon 2 4516
Protoss_Nexus 1 7107
Protoss_Gateway 3 10916
Protoss_Assimilator 2 8199
Protoss_Cybernetics_Core 1 6939
Protoss_Zealot 7 10549
Protoss_Stargate 1 8382
Protoss_Citadel_of_Adun 1 9035
Protoss_Corsair 3 10435
Protoss_Ground_Weapons_1 1 9955
10916
