Protoss_Forge 1 3657
Protoss_Nexus 1 6147
Protoss_Photon_Cannon 2 5083
Protoss_Gateway 4 9329
Protoss_Assimilator 2 10234
Protoss_Cybernetics_Core 1 7051
Protoss_Zealot 15 10849
Protoss_Stargate 1 8296
Protoss_Citadel_of_Adun 1 8497
Protoss_Corsair 1 8713
Protoss_Templar_Archives 1 10981
10981
