Protoss_Forge 1 2859
Protoss_Photon_Cannon 2 4270
Protoss_Nexus 1 6773
Protoss_Gateway 4 9309
Protoss_Assimilator 2 10644
Protoss_Zealot 15 10919
Protoss_Cybernetics_Core 1 6827
Protoss_Stargate 1 8095
Protoss_Citadel_of_Adun 1 8251
Protoss_Corsair 1 8533
10919
