Protoss_Forge 1 3203
Protoss_Photon_Cannon 2 4352
Protoss_Nexus 1 6869
Protoss_Assimilator 3 7904
Protoss_Gateway 4 9529
Protoss_Cybernetics_Core 1 7056
Protoss_Zealot 8 10165
Protoss_Citadel_of_Adun 1 8113
Protoss_Templar_Archives 1 9170
Protoss_High_Templar 4 11084
11084
