Protoss_Gateway 3 10514
Protoss_Assimilator 1 3258
Protoss_Zealot 6 8803
Protoss_Cybernetics_Core 1 4997
Protoss_Stargate 1 6278
Protoss_Citadel_of_Adun 1 6703
Protoss_Corsair 1 7023
Protoss_Dragoon 1 7327
Protoss_Templar_Archives 1 8806
Protoss_Dark_Templar 2 9793
Protoss_Forge 1 10115
Protoss_High_Templar 1 10911
10911
