Protoss_Nexus 1 5976
Protoss_Forge 1 4250
Protoss_Gateway 1 5396
Protoss_Photon_Cannon 2 5675
Protoss_Assimilator 2 7242
Protoss_Zealot 4 10111
Protoss_Cybernetics_Core 1 7261
Protoss_Dragoon 1 8307
Protoss_Stargate 2 9579
Protoss_Robotics_Facility 1 9457
Protoss_Corsair 4 10921
Protoss_Shuttle 1 10779
Protoss_Robotics_Support_Bay 1 10132
10921
