Protoss_Forge 1 3401
Protoss_Nexus 2 10239
Protoss_Photon_Cannon 2 5045
Protoss_Gateway 1 5707
Protoss_Assimilator 2 8745
Protoss_Cybernetics_Core 1 6840
Protoss_Zealot 6 10929
Protoss_Stargate 1 8078
Protoss_Corsair 4 10887
Protoss_Robotics_Facility 1 10369
Protoss_Shuttle 1 11203
Protoss_Robotics_Support_Bay 1 10632
11203
