Protoss_Forge 1 3217
Protoss_Photon_Cannon 2 4701
Protoss_Nexus 2 12715
Protoss_Gateway 3 10924
Protoss_Assimilator 2 7078
Protoss_Cybernetics_Core 1 6971
Protoss_Zealot 3 9661
Protoss_Stargate 1 8317
Protoss_Dragoon 1 7921
Protoss_Citadel_of_Adun 1 8773
Protoss_Corsair 3 10521
Protoss_Templar_Archives 1 9858
Protoss_Dark_Templar 2 11145
12715
