Protoss_Gateway 2 8134
Protoss_Assimilator 1 3447
Protoss_Zealot 11 10903
Protoss_Cybernetics_Core 1 5347
Protoss_Stargate 1 6608
Protoss_Dragoon 4 8289
Protoss_Corsair 6 9719
10903
