Protoss_Forge 1 4001
Protoss_Photon_Cannon 5 10989
Protoss_Nexus 1 6891
Protoss_Gateway 2 7521
Protoss_Assimilator 2 9349
Protoss_Cybernetics_Core 1 7191
Protoss_Zealot 11 10739
Protoss_Citadel_of_Adun 1 8269
Protoss_Stargate 2 10602
10989
