Protoss_Forge 1 3798
Protoss_Nexus 1 6165
Protoss_Photon_Cannon 2 5477
Protoss_Gateway 3 9195
Protoss_Assimilator 2 6390
Protoss_Zealot 10 10469
Protoss_Cybernetics_Core 1 7475
Protoss_Citadel_of_Adun 1 8467
Protoss_Templar_Archives 1 10122
Protoss_High_Templar 2 10891
10891
