Protoss_Forge 1 3409
Protoss_Nexus 1 6217
Protoss_Photon_Cannon 2 10728
Protoss_Gateway 3 11414
Protoss_Assimilator 2 9355
Protoss_Cybernetics_Core 1 6837
Protoss_Zealot 10 10357
Protoss_Stargate 1 8207
Protoss_Citadel_of_Adun 1 8770
Protoss_Corsair 1 8749
Protoss_Templar_Archives 1 10658
11414
