Protoss_Gateway 1 3349
Protoss_Assimilator 1 3200
Protoss_Cybernetics_Core 1 4473
Protoss_Zealot 4 7241
Protoss_Dragoon 1 5215
Protoss_Stargate 1 5825
Protoss_Corsair 4 10571
Protoss_Robotics_Facility 1 8439
Protoss_Forge 2 9020
Protoss_Shuttle 1 9243
Protoss_Photon_Cannon 2 10253
Protoss_Robotics_Support_Bay 1 9451
Protoss_Reaver 1 11027
11027
