Protoss_Forge 1 3614
Protoss_Photon_Cannon 4 9863
Protoss_Nexus 1 7188
Protoss_Gateway 2 10712
Protoss_Assimilator 2 7352
Protoss_Zealot 2 9405
Protoss_Cybernetics_Core 1 7523
Protoss_Stargate 2 9342
Protoss_Citadel_of_Adun 1 9317
Protoss_Corsair 5 10933
Protoss_Templar_Archives 1 10878
10933
