Protoss_Forge 1 3454
Protoss_Photon_Cannon 3 8835
Protoss_Nexus 1 6908
Protoss_Gateway 3 10619
Protoss_Assimilator 2 9773
Protoss_Cybernetics_Core 1 7015
Protoss_Zealot 7 10627
Protoss_Stargate 1 8369
Protoss_Corsair 1 8875
Protoss_Citadel_of_Adun 1 9713
10627
