Protoss_Gateway 2 3931
Protoss_Zealot 15 9231
Protoss_Assimilator 1 6011
Protoss_Cybernetics_Core 1 7380
Protoss_Stargate 1 8900
Protoss_Forge 1 8838
Protoss_Corsair 2 10223
Protoss_Photon_Cannon 1 9887
Protoss_Robotics_Facility 1 10920
Protoss_Citadel_of_Adun 1 11315
11315
