Protoss_Nexus 1 5705
Protoss_Forge 1 4380
Protoss_Gateway 1 5729
Protoss_Photon_Cannon 3 10574
Protoss_Assimilator 2 6602
Protoss_Zealot 5 10579
Protoss_Cybernetics_Core 1 7040
Protoss_Stargate 2 9358
Protoss_Robotics_Facility 1 9130
Protoss_Corsair 5 10909
Protoss_Citadel_of_Adun 1 9720
Protoss_Shuttle 1 9957
Protoss_Robotics_Support_Bay 1 9380
Protoss_Reaver 1 11223
11223
