Protoss_Forge 1 3225
Protoss_Nexus 1 6263
Protoss_Gateway 3 8689
Protoss_Photon_Cannon 5 10550
Protoss_Assimilator 2 6113
Protoss_Cybernetics_Core 1 6900
Protoss_Stargate 1 8123
Protoss_Citadel_of_Adun 1 8273
Protoss_Corsair 3 10537
Protoss_Templar_Archives 1 9377
Protoss_High_Templar 2 10165
10550
