Protoss_Forge 1 3708
Protoss_Nexus 1 6289
Protoss_Photon_Cannon 7 8975
Protoss_Gateway 4 10703
Protoss_Assimilator 2 9424
Protoss_Cybernetics_Core 1 8669
Protoss_Zealot 3 10393
Protoss_Stargate 1 9926
Protoss_Citadel_of_Adun 1 10117
Protoss_Corsair 1 10471
10703
