Protoss_Forge 1 3348
Protoss_Photon_Cannon 3 10985
Protoss_Nexus 1 6669
Protoss_Gateway 1 5520
Protoss_Assimilator 2 9517
Protoss_Zealot 4 10507
Protoss_Cybernetics_Core 1 8393
Protoss_Dragoon 1 9323
Protoss_Stargate 1 9835
Protoss_Citadel_of_Adun 1 10660
Protoss_Corsair 2 10907
10985
