Protoss_Forge 1 3305
Protoss_Photon_Cannon 4 10745
Protoss_Nexus 1 6825
Protoss_Gateway 2 9329
Protoss_Assimilator 2 7509
Protoss_Cybernetics_Core 1 6781
Protoss_Zealot 3 7815
Protoss_Stargate 1 8034
Protoss_Citadel_of_Adun 1 8597
Protoss_Corsair 3 10911
Protoss_Templar_Archives 1 9868
Protoss_Dragoon 2 10491
Protoss_High_Templar 1 11027
11027
