Protoss_Forge 1 3641
Protoss_Photon_Cannon 3 10787
Protoss_Nexus 1 6915
Protoss_Gateway 3 9755
Protoss_Assimilator 2 7191
Protoss_Cybernetics_Core 1 7364
Protoss_Zealot 10 10919
Protoss_Stargate 1 8708
Protoss_Citadel_of_Adun 1 8859
Protoss_Corsair 2 9739
10919
