Protoss_Gateway 2 3719
Protoss_Zealot 7 5715
Protoss_Nexus 1 8701
Protoss_Assimilator 1 7102
Protoss_Forge 1 7444
Protoss_Cybernetics_Core 1 8638
Protoss_Photon_Cannon 3 10336
Protoss_Dragoon 4 10161
Protoss_Stargate 1 9954
Protoss_Corsair 1 10369
10369
