Protoss_Forge 1 3048
Protoss_Photon_Cannon 1 4054
Protoss_Nexus 1 6489
Protoss_Gateway 4 9953
Protoss_Assimilator 2 7908
Protoss_Zealot 7 10953
Protoss_Cybernetics_Core 1 6860
Protoss_Stargate 1 8115
Protoss_Citadel_of_Adun 1 8334
Protoss_Corsair 1 8623
Protoss_Templar_Archives 1 9517
Protoss_High_Templar 2 10545
10953
