Protoss_Forge 1 3572
Protoss_Nexus 1 6231
Protoss_Photon_Cannon 3 10832
Protoss_Gateway 3 11327
Protoss_Assimilator 2 8041
Protoss_Zealot 5 10577
Protoss_Cybernetics_Core 1 7097
Protoss_Stargate 1 8995
Protoss_Citadel_of_Adun 1 9533
Protoss_Dragoon 1 9463
Protoss_Corsair 3 10925
11327
