Protoss_Forge 1 3215
Protoss_Photon_Cannon 2 9179
Protoss_Nexus 1 6457
Protoss_Gateway 3 11353
Protoss_Assimilator 2 7241
Protoss_Zealot 11 10933
Protoss_Cybernetics_Core 1 6903
Protoss_Citadel_of_Adun 1 8075
Protoss_Stargate 1 10519
Protoss_Templar_Archives 1 10367
Protoss_Ground_Weapons_1 1 9973
11353
