Protoss_Forge 1 3507
Protoss_Photon_Cannon 4 10582
Protoss_Nexus 1 6907
Protoss_Gateway 2 9147
Protoss_Assimilator 2 7163
Protoss_Zealot 6 10005
Protoss_Cybernetics_Core 1 6867
Protoss_Stargate 1 8273
Protoss_Dragoon 1 8035
Protoss_Corsair 3 10571
Protoss_Citadel_of_Adun 1 9222
Protoss_Templar_Archives 1 11199
11199
