Protoss_Forge 1 3232
Protoss_Photon_Cannon 3 10465
Protoss_Nexus 1 6967
Protoss_Gateway 3 10147
Protoss_Assimilator 2 7486
Protoss_Cybernetics_Core 1 6801
Protoss_Zealot 8 10681
Protoss_Stargate 1 8273
Protoss_Dragoon 1 8085
Protoss_Citadel_of_Adun 1 9044
Protoss_Corsair 4 10893
Protoss_Templar_Archives 1 10341
10893
