Protoss_Forge 1 3557
Protoss_Nexus 1 6103
Protoss_Photon_Cannon 3 10380
Protoss_Gateway 2 11133
Protoss_Assimilator 2 7613
Protoss_Cybernetics_Core 1 6806
Protoss_Zealot 7 10763
Protoss_Stargate 1 8151
Protoss_Corsair 4 10497
Protoss_Citadel_of_Adun 1 9851
11133
