Protoss_Forge 1 3113
Protoss_Photon_Cannon 4 9568
Protoss_Nexus 1 7462
Protoss_Gateway 1 6393
Protoss_Assimilator 2 8214
Protoss_Cybernetics_Core 1 7610
Protoss_Zealot 3 9101
Protoss_Stargate 2 9874
Protoss_Dragoon 1 8589
Protoss_Corsair 4 10673
Protoss_Citadel_of_Adun 1 10264
10673
