Protoss_Forge 1 3689
Protoss_Nexus 1 6191
Protoss_Photon_Cannon 4 10985
Protoss_Gateway 3 9653
Protoss_Assimilator 1 6475
Protoss_Cybernetics_Core 1 7493
Protoss_Zealot 9 10907
Protoss_Citadel_of_Adun 1 8886
10985
