Protoss_Forge 1 3240
Protoss_Photon_Cannon 2 4617
Protoss_Nexus 1 7175
Protoss_Gateway 3 10851
Protoss_Assimilator 2 7325
Protoss_Cybernetics_Core 1 6997
Protoss_Zealot 6 10951
Protoss_Stargate 1 8225
Protoss_Corsair 4 10511
Protoss_Citadel_of_Adun 1 9245
Protoss_Templar_Archives 1 10707
10951
