Protoss_Forge 1 3225
Protoss_Nexus 1 6097
Protoss_Photon_Cannon 3 10884
Protoss_Gateway 2 10595
Protoss_Assimilator 2 8561
Protoss_Zealot 4 9939
Protoss_Cybernetics_Core 1 6753
Protoss_Dragoon 1 7577
Protoss_Stargate 1 8697
Protoss_Citadel_of_Adun 1 9207
Protoss_Corsair 3 10417
10884
