Protoss_Forge 1 2902
Protoss_Photon_Cannon 5 10853
Protoss_Nexus 1 7160
Protoss_Gateway 2 11346
Protoss_Assimilator 1 6034
Protoss_Zealot 3 9217
Protoss_Cybernetics_Core 1 8874
Protoss_Stargate 1 10261
Protoss_Citadel_of_Adun 2 10860
11346
