Protoss_Forge 1 3267
Protoss_Photon_Cannon 2 4595
Protoss_Nexus 1 7005
Protoss_Gateway 3 9643
Protoss_Assimilator 2 7593
Protoss_Cybernetics_Core 1 6901
Protoss_Zealot 6 10267
Protoss_Stargate 1 8245
Protoss_Citadel_of_Adun 1 8528
Protoss_Dragoon 1 9073
Protoss_Corsair 3 10495
Protoss_Templar_Archives 1 9864
Protoss_Dark_Templar 2 11109
11109
