Protoss_Forge 1 3327
Protoss_Nexus 1 6123
Protoss_Photon_Cannon 2 5025
Protoss_Gateway 3 10539
Protoss_Assimilator 2 7683
Protoss_Cybernetics_Core 1 7213
Protoss_Zealot 5 10443
Protoss_Dragoon 1 8123
Protoss_Stargate 1 8604
Protoss_Citadel_of_Adun 1 8951
Protoss_Corsair 3 10779
Protoss_Templar_Archives 1 10633
10779
