Protoss_Gateway 2 3702
Protoss_Zealot 9 10045
Protoss_Forge 1 5856
Protoss_Nexus 1 8405
Protoss_Assimilator 2 9069
Protoss_Photon_Cannon 2 7986
Protoss_Cybernetics_Core 1 8582
Protoss_Stargate 1 9899
Protoss_Citadel_of_Adun 1 10402
Protoss_Corsair 1 10379
10402
