Protoss_Gateway 2 3815
Protoss_Zealot 9 9729
Protoss_Forge 1 5175
Protoss_Photon_Cannon 6 10613
Protoss_Nexus 1 8949
Protoss_Assimilator 2 10865
Protoss_Cybernetics_Core 1 9606
Protoss_Stargate 1 11205
Protoss_Citadel_of_Adun 1 11214
11214
