Protoss_Forge 1 3205
Protoss_Photon_Cannon 3 10266
Protoss_Nexus 1 6940
Protoss_Gateway 3 10757
Protoss_Assimilator 2 8489
Protoss_Cybernetics_Core 1 6933
Protoss_Zealot 5 10551
Protoss_Stargate 1 8321
Protoss_Citadel_of_Adun 1 8823
Protoss_Dragoon 1 8933
Protoss_Corsair 3 10417
Protoss_Templar_Archives 1 10429
10757
