Protoss_Forge 1 3474
Protoss_Photon_Cannon 1 4407
Protoss_Nexus 1 6619
Protoss_Gateway 2 9364
Protoss_Assimilator 2 7548
Protoss_Cybernetics_Core 1 6559
Protoss_Zealot 4 10439
Protoss_Stargate 1 7957
Protoss_Citadel_of_Adun 1 8431
Protoss_Dragoon 1 8723
Protoss_Corsair 3 10549
Protoss_Templar_Archives 1 9967
10549
