Protoss_Forge 2 10948
Protoss_Photon_Cannon 2 4604
Protoss_Nexus 1 7053
Protoss_Gateway 3 9931
Protoss_Assimilator 2 7791
Protoss_Cybernetics_Core 1 6919
Protoss_Zealot 8 10589
Protoss_Stargate 1 8195
Protoss_Corsair 2 10177
Protoss_Citadel_of_Adun 1 9407
10948
