Protoss_Gateway 2 8849
Protoss_Assimilator 1 3369
Protoss_Zealot 13 10605
Protoss_Cybernetics_Core 1 5249
Protoss_Dragoon 1 6015
Protoss_Stargate 1 6772
Protoss_Citadel_of_Adun 1 7293
Protoss_Corsair 1 7235
Protoss_Forge 1 8128
Protoss_Templar_Archives 1 9391
Protoss_Photon_Cannon 1 10557
Protoss_Nexus 1 12509
Protoss_Dark_Templar 2 11121
12509
