Protoss_Forge 1 3310
Protoss_Nexus 1 6133
Protoss_Photon_Cannon 1 4739
Protoss_Gateway 4 9043
Protoss_Assimilator 2 6561
Protoss_Cybernetics_Core 1 6415
Protoss_Zealot 15 10901
Protoss_Stargate 1 7792
Protoss_Citadel_of_Adun 1 8107
Protoss_Corsair 2 9067
Protoss_Templar_Archives 1 11119
11119
