Protoss_Forge 1 3246
Protoss_Nexus 1 6199
Protoss_Gateway 4 10240
Protoss_Photon_Cannon 2 10623
Protoss_Assimilator 2 6380
Protoss_Cybernetics_Core 1 6581
Protoss_Zealot 2 8276
Protoss_Stargate 1 7837
Protoss_Citadel_of_Adun 1 7909
Protoss_Dragoon 1 7743
Protoss_Corsair 4 10373
Protoss_Templar_Archives 1 8987
Protoss_Dark_Templar 2 10167
Protoss_High_Templar 2 11195
11195
