Protoss_Forge 1 3026
Protoss_Nexus 1 6111
Protoss_Gateway 3 10841
Protoss_Photon_Cannon 4 9625
Protoss_Assimilator 2 8063
Protoss_Zealot 3 9547
Protoss_Cybernetics_Core 1 6647
Protoss_Stargate 1 7996
Protoss_Dragoon 1 8057
Protoss_Corsair 4 10825
Protoss_Robotics_Facility 1 10095
Protoss_Robotics_Support_Bay 1 10339
Protoss_Observatory 1 10470
10841
