Protoss_Gateway 2 8697
Protoss_Forge 1 3640
Protoss_Zealot 13 10611
Protoss_Photon_Cannon 2 10531
Protoss_Nexus 1 7390
Protoss_Assimilator 2 9719
Protoss_Cybernetics_Core 1 7106
Protoss_Citadel_of_Adun 1 9045
Protoss_Templar_Archives 1 10107
10611
