Protoss_Forge 1 3399
Protoss_Nexus 1 6455
Protoss_Photon_Cannon 4 10637
Protoss_Gateway 4 10354
Protoss_Assimilator 2 8374
Protoss_Cybernetics_Core 1 7302
Protoss_Zealot 4 10936
Protoss_Citadel_of_Adun 1 8514
Protoss_Dragoon 2 9869
Protoss_Templar_Archives 1 9685
Protoss_Dark_Templar 1 10621
Protoss_High_Templar 2 10999
10999
