Protoss_Forge 1 3088
Protoss_Photon_Cannon 4 10859
Protoss_Nexus 1 6971
Protoss_Gateway 1 5863
Protoss_Assimilator 2 8189
Protoss_Zealot 6 10783
Protoss_Cybernetics_Core 1 7162
Protoss_Stargate 1 8665
Protoss_Dragoon 1 8465
Protoss_Citadel_of_Adun 1 9156
Protoss_Corsair 2 9779
Protoss_Templar_Archives 1 10461
10859
