Protoss_Forge 1 3253
Protoss_Photon_Cannon 6 10955
Protoss_Nexus 1 6868
Protoss_Gateway 3 9577
Protoss_Assimilator 2 8458
Protoss_Cybernetics_Core 1 6751
Protoss_Zealot 6 10103
Protoss_Stargate 1 8053
Protoss_Dragoon 1 7831
Protoss_Citadel_of_Adun 1 8541
Protoss_Corsair 1 8599
Protoss_Templar_Archives 1 10102
Protoss_Dark_Templar 1 11175
Protoss_High_Templar 1 11189
11189
