Protoss_Nexus 1 5740
Protoss_Gateway 6 11198
Protoss_Forge 1 4699
Protoss_Assimilator 2 7400
Protoss_Photon_Cannon 1 5699
Protoss_Cybernetics_Core 1 6377
Protoss_Zealot 4 10697
Protoss_Stargate 1 7843
Protoss_Dragoon 1 7379
Protoss_Citadel_of_Adun 1 8239
Protoss_Corsair 1 8255
Protoss_Templar_Archives 1 9454
Protoss_Dark_Templar 1 10203
Protoss_High_Templar 2 10613
11198
