Protoss_Nexus 1 5759
Protoss_Forge 1 4181
Protoss_Gateway 1 4965
Protoss_Photon_Cannon 4 10295
Protoss_Assimilator 1 5432
Protoss_Cybernetics_Core 1 6303
Protoss_Zealot 3 9675
Protoss_Stargate 1 8289
Protoss_Dragoon 1 9113
Protoss_Corsair 3 10387
Protoss_Citadel_of_Adun 1 11315
11315
