Protoss_Forge 1 3165
Protoss_Nexus 1 6356
Protoss_Photon_Cannon 3 10292
Protoss_Gateway 2 9649
Protoss_Assimilator 2 7361
Protoss_Cybernetics_Core 1 7013
Protoss_Zealot 3 9861
Protoss_Stargate 1 8361
Protoss_Dragoon 1 8105
Protoss_Citadel_of_Adun 1 8885
Protoss_Corsair 3 10131
Protoss_Templar_Archives 1 9871
Protoss_Dark_Templar 2 10757
10757
