Protoss_Assimilator 1 2762
Protoss_Gateway 1 3827
Protoss_Cybernetics_Core 1 4818
Protoss_Stargate 1 6190
Protoss_Robotics_Facility 1 7392
Protoss_Robotics_Support_Bay 1 8044
Protoss_Shield_Battery 1 10639
10639
