Protoss_Gateway 1 3266
Protoss_Assimilator 1 3130
Protoss_Cybernetics_Core 1 4251
Protoss_Zealot 6 10479
Protoss_Dragoon 2 5799
Protoss_Stargate 1 5669
Protoss_Corsair 4 9715
Protoss_Forge 1 7158
Protoss_Nexus 1 10620
Protoss_Photon_Cannon 4 11089
Protoss_Citadel_of_Adun 1 9959
11089
