Protoss_Forge 1 3285
Protoss_Nexus 1 6146
Protoss_Photon_Cannon 3 10949
Protoss_Gateway 3 9527
Protoss_Assimilator 2 7210
Protoss_Cybernetics_Core 1 6845
Protoss_Zealot 4 9828
Protoss_Stargate 1 8117
Protoss_Citadel_of_Adun 1 8295
Protoss_Corsair 3 10485
Protoss_Dragoon 1 9316
Protoss_Templar_Archives 1 9745
Protoss_Dark_Templar 3 10670
10949
