Protoss_Forge 1 3228
Protoss_Nexus 1 5977
Protoss_Photon_Cannon 3 9592
Protoss_Gateway 4 10964
Protoss_Assimilator 2 7220
Protoss_Cybernetics_Core 1 7240
Protoss_Zealot 7 10767
Protoss_Stargate 1 8511
Protoss_Citadel_of_Adun 1 8549
Protoss_Corsair 2 9703
10964
