Protoss_Gateway 2 3891
Protoss_Zealot 18 10653
Protoss_Nexus 1 9363
Protoss_Assimilator 1 8272
Protoss_Forge 1 9040
Protoss_Photon_Cannon 2 11129
Protoss_Cybernetics_Core 1 10711
11129
