Protoss_Forge 1 2927
Protoss_Nexus 1 5977
Protoss_Photon_Cannon 7 11037
Protoss_Gateway 2 8733
Protoss_Assimilator 2 7780
Protoss_Cybernetics_Core 1 6798
Protoss_Zealot 5 9533
Protoss_Stargate 1 8253
Protoss_Citadel_of_Adun 1 8877
Protoss_Corsair 3 10423
Protoss_Templar_Archives 1 10588
11037
