Protoss_Gateway 4 10344
Protoss_Zealot 10 10451
Protoss_Forge 1 4047
Protoss_Nexus 1 7262
Protoss_Photon_Cannon 4 11134
Protoss_Assimilator 2 7889
Protoss_Cybernetics_Core 1 7176
Protoss_Stargate 1 8498
Protoss_Citadel_of_Adun 1 9137
Protoss_Corsair 1 8911
Protoss_Templar_Archives 1 10685
11134
