Protoss_Forge 1 3474
Protoss_Photon_Cannon 4 10960
Protoss_Nexus 1 6683
Protoss_Gateway 3 10895
Protoss_Assimilator 2 8723
Protoss_Cybernetics_Core 1 6948
Protoss_Dragoon 1 7685
Protoss_Stargate 1 8377
Protoss_Citadel_of_Adun 1 8443
Protoss_Zealot 2 8895
Protoss_Corsair 3 10611
Protoss_Templar_Archives 1 9603
Protoss_Dark_Templar 1 10615
10960
