Protoss_Gateway 2 3789
Protoss_Zealot 11 7327
Protoss_Nexus 1 8572
Protoss_Assimilator 2 9232
Protoss_Forge 1 7682
Protoss_Cybernetics_Core 1 8989
Protoss_Photon_Cannon 3 11119
Protoss_Dragoon 1 9763
Protoss_Stargate 1 10647
Protoss_Citadel_of_Adun 1 10754
11119
