Protoss_Gateway 2 7508
Protoss_Assimilator 1 3494
Protoss_Zealot 12 10043
Protoss_Cybernetics_Core 1 5229
Protoss_Stargate 1 6703
Protoss_Corsair 1 7119
Protoss_Citadel_of_Adun 1 8050
Protoss_Forge 1 8517
Protoss_Templar_Archives 1 9889
Protoss_Photon_Cannon 2 11007
Protoss_Dark_Templar 1 10867
11007
