Protoss_Forge 1 3073
Protoss_Photon_Cannon 2 5805
Protoss_Nexus 1 6409
Protoss_Gateway 4 11079
Protoss_Assimilator 2 7754
Protoss_Zealot 8 10455
Protoss_Cybernetics_Core 1 7527
Protoss_Stargate 1 8796
Protoss_Citadel_of_Adun 1 8803
Protoss_Corsair 2 9863
Protoss_Templar_Archives 1 10545
11079
