Protoss_Gateway 1 3348
Protoss_Assimilator 1 3206
Protoss_Zealot 5 8171
Protoss_Cybernetics_Core 1 5263
Protoss_Dragoon 2 6857
Protoss_Stargate 1 6976
Protoss_Citadel_of_Adun 1 7776
Protoss_Corsair 3 8861
Protoss_Templar_Archives 1 8873
Protoss_Forge 1 8665
Protoss_Dark_Templar 1 9661
Protoss_Photon_Cannon 2 10952
Protoss_High_Templar 1 10479
Protoss_Nexus 1 12329
12329
