Protoss_Forge 1 2905
Protoss_Photon_Cannon 2 7909
Protoss_Nexus 1 6427
Protoss_Gateway 3 9718
Protoss_Assimilator 2 6650
Protoss_Cybernetics_Core 1 6355
Protoss_Stargate 1 7749
Protoss_Zealot 7 10431
Protoss_Citadel_of_Adun 1 8497
Protoss_Corsair 2 8865
Protoss_Templar_Archives 1 10863
10863
