Protoss_Forge 2 9035
Protoss_Nexus 1 5961
Protoss_Photon_Cannon 6 10048
Protoss_Gateway 4 10857
Protoss_Assimilator 2 6751
Protoss_Cybernetics_Core 1 6632
Protoss_Dragoon 1 7505
Protoss_Citadel_of_Adun 1 8256
Protoss_Zealot 5 10181
Protoss_Templar_Archives 1 9986
Protoss_High_Templar 2 11081
Protoss_Dark_Templar 1 10975
11081
