Protoss_Forge 1 3300
Protoss_Photon_Cannon 2 10889
Protoss_Nexus 1 6729
Protoss_Gateway 2 10198
Protoss_Assimilator 2 7143
Protoss_Cybernetics_Core 1 6627
Protoss_Zealot 2 7971
Protoss_Stargate 1 8135
Protoss_Citadel_of_Adun 1 8496
Protoss_Corsair 2 9649
Protoss_Templar_Archives 1 9734
Protoss_Robotics_Facility 1 10367
Protoss_Dark_Templar 2 11031
Protoss_Shuttle 1 11249
11249
