Protoss_Forge 1 3263
Protoss_Nexus 1 5993
Protoss_Gateway 3 10095
Protoss_Photon_Cannon 4 11200
Protoss_Assimilator 2 7299
Protoss_Cybernetics_Core 1 6333
Protoss_Zealot 4 10671
Protoss_Stargate 1 7571
Protoss_Citadel_of_Adun 1 8125
Protoss_Corsair 4 10655
Protoss_Templar_Archives 1 9208
Protoss_Dark_Templar 1 9973
Protoss_High_Templar 1 9987
11200
