Protoss_Forge 1 3554
Protoss_Photon_Cannon 5 10082
Protoss_Nexus 1 6715
Protoss_Gateway 2 11393
Protoss_Assimilator 2 7587
Protoss_Zealot 9 10645
Protoss_Cybernetics_Core 1 6477
Protoss_Stargate 1 7819
Protoss_Citadel_of_Adun 1 8505
Protoss_Corsair 4 10529
Protoss_Templar_Archives 1 11304
11393
