Protoss_Forge 1 3326
Protoss_Photon_Cannon 3 11098
Protoss_Nexus 1 6798
Protoss_Gateway 5 10673
Protoss_Assimilator 1 5699
Protoss_Cybernetics_Core 1 6667
Protoss_Zealot 11 10657
Protoss_Citadel_of_Adun 1 7935
Protoss_Templar_Archives 1 10000
11098
