Protoss_Forge 1 3196
Protoss_Nexus 1 6157
Protoss_Photon_Cannon 2 5061
Protoss_Gateway 3 10874
Protoss_Assimilator 2 7911
Protoss_Zealot 6 10651
Protoss_Cybernetics_Core 1 7819
Protoss_Stargate 1 9057
Protoss_Citadel_of_Adun 1 9371
Protoss_Corsair 1 9519
Protoss_Templar_Archives 1 10625
10874
