Protoss_Forge 1 3340
Protoss_Nexus 1 6247
Protoss_Gateway 4 9181
Protoss_Photon_Cannon 1 5370
Protoss_Assimilator 2 6875
Protoss_Zealot 4 8041
Protoss_Cybernetics_Core 1 6737
Protoss_Stargate 1 8337
Protoss_Corsair 2 10715
Protoss_Dragoon 8 10831
10831
