Protoss_Nexus 1 5943
Protoss_Forge 1 4309
Protoss_Gateway 5 11077
Protoss_Photon_Cannon 5 11119
Protoss_Assimilator 2 8406
Protoss_Zealot 10 10781
Protoss_Cybernetics_Core 1 7320
Protoss_Citadel_of_Adun 1 8423
Protoss_Stargate 1 8756
Protoss_Corsair 1 9337
11119
