Protoss_Forge 1 3266
Protoss_Nexus 1 6293
Protoss_Photon_Cannon 5 10823
Protoss_Gateway 4 9845
Protoss_Assimilator 2 8418
Protoss_Cybernetics_Core 1 7146
Protoss_Zealot 7 10829
Protoss_Citadel_of_Adun 1 8287
Protoss_Dragoon 1 8831
Protoss_Templar_Archives 1 9443
Protoss_High_Templar 2 10525
Protoss_Dark_Templar 2 11047
11047
