Protoss_Gateway 2 6982
Protoss_Assimilator 1 3322
Protoss_Zealot 7 9949
Protoss_Cybernetics_Core 1 5058
Protoss_Dragoon 6 10827
Protoss_Robotics_Facility 1 6755
Protoss_Shuttle 1 7553
Protoss_Robotics_Support_Bay 1 7111
Protoss_Reaver 2 10311
Protoss_Scarab 4 9868
10827
