Protoss_Forge 1 3209
Protoss_Photon_Cannon 6 10980
Protoss_Nexus 1 6825
Protoss_Gateway 4 10885
Protoss_Assimilator 2 7998
Protoss_Cybernetics_Core 1 6929
Protoss_Zealot 3 9557
Protoss_Stargate 1 8260
Protoss_Corsair 1 8705
Protoss_Citadel_of_Adun 1 9363
Protoss_Templar_Archives 1 10361
Protoss_High_Templar 2 11121
11121
