Protoss_Forge 1 3239
Protoss_Nexus 1 6119
Protoss_Gateway 4 11411
Protoss_Photon_Cannon 8 11054
Protoss_Assimilator 2 10297
Protoss_Cybernetics_Core 1 6280
Protoss_Zealot 12 10511
Protoss_Citadel_of_Adun 1 8146
Protoss_Templar_Archives 1 9537
Protoss_Ground_Weapons_1 1 9875
11411
