Protoss_Forge 1 3187
Protoss_Nexus 1 6162
Protoss_Photon_Cannon 2 5137
Protoss_Gateway 2 8264
Protoss_Assimilator 2 7608
Protoss_Zealot 11 10819
Protoss_Cybernetics_Core 1 7139
Protoss_Stargate 1 8866
Protoss_Citadel_of_Adun 1 8936
Protoss_Corsair 1 9321
10819
