Protoss_Forge 1 3513
Protoss_Photon_Cannon 8 11105
Protoss_Nexus 1 7021
Protoss_Gateway 1 5719
Protoss_Assimilator 2 9457
Protoss_Zealot 3 9163
Protoss_Cybernetics_Core 1 8405
Protoss_Stargate 1 9697
Protoss_Corsair 1 10167
Protoss_Citadel_of_Adun 1 11184
11184
