Protoss_Gateway 3 10881
Protoss_Assimilator 1 3651
Protoss_Zealot 6 10556
Protoss_Forge 1 4793
Protoss_Cybernetics_Core 1 6455
Protoss_Stargate 1 7774
Protoss_Citadel_of_Adun 1 7673
Protoss_Templar_Archives 1 8673
Protoss_Corsair 1 8226
Protoss_High_Templar 2 10933
Protoss_Dark_Templar 1 9521
Protoss_Ground_Weapons_1 1 8521
Protoss_Photon_Cannon 3 11123
11123
