Protoss_Forge 1 3301
Protoss_Photon_Cannon 2 4899
Protoss_Nexus 1 6894
Protoss_Gateway 4 10941
Protoss_Assimilator 2 6926
Protoss_Cybernetics_Core 1 6819
Protoss_Zealot 8 10605
Protoss_Stargate 1 8161
Protoss_Citadel_of_Adun 1 8637
Protoss_Corsair 2 9273
Protoss_Templar_Archives 1 10652
10941
