Protoss_Forge 1 3249
Protoss_Photon_Cannon 1 4183
Protoss_Nexus 1 6702
Protoss_Gateway 4 10056
Protoss_Assimilator 2 6146
Protoss_Zealot 2 7139
Protoss_Cybernetics_Core 1 6903
Protoss_Dragoon 11 11139
Protoss_Stargate 1 10799
11139
