Protoss_Forge 1 3301
Protoss_Photon_Cannon 3 10592
Protoss_Nexus 1 6900
Protoss_Gateway 4 11265
Protoss_Assimilator 2 7017
Protoss_Cybernetics_Core 1 6941
Protoss_Zealot 7 10429
Protoss_Stargate 1 8230
Protoss_Citadel_of_Adun 1 8740
Protoss_Corsair 1 8669
Protoss_Templar_Archives 1 10382
11265
