Protoss_Forge 1 3537
Protoss_Photon_Cannon 3 10785
Protoss_Nexus 1 6971
Protoss_Gateway 2 11133
Protoss_Assimilator 2 7732
Protoss_Cybernetics_Core 1 7069
Protoss_Zealot 7 10949
Protoss_Stargate 1 8311
Protoss_Citadel_of_Adun 1 9303
Protoss_Corsair 4 10853
Protoss_Templar_Archives 1 10479
11133
