Protoss_Forge 1 3500
Protoss_Nexus 1 6055
Protoss_Photon_Cannon 4 10875
Protoss_Gateway 1 5685
Protoss_Assimilator 2 8120
Protoss_Cybernetics_Core 1 7262
Protoss_Stargate 1 8529
Protoss_Zealot 3 10745
Protoss_Citadel_of_Adun 1 9393
Protoss_Corsair 4 10931
10931
