Protoss_Forge 1 3063
Protoss_Nexus 1 6525
Protoss_Gateway 2 10679
Protoss_Photon_Cannon 8 11181
Protoss_Assimilator 2 8037
Protoss_Cybernetics_Core 1 6799
Protoss_Zealot 3 8185
Protoss_Stargate 1 8089
Protoss_Citadel_of_Adun 1 8386
Protoss_Corsair 3 10243
Protoss_Templar_Archives 1 9611
Protoss_Dark_Templar 1 10399
11181
