Protoss_Gateway 2 10809
Protoss_Assimilator 1 3416
Protoss_Zealot 3 7149
Protoss_Cybernetics_Core 1 5164
Protoss_Stargate 1 6602
Protoss_Citadel_of_Adun 1 6499
Protoss_Dragoon 1 6487
Protoss_Corsair 1 7013
Protoss_Templar_Archives 1 7608
Protoss_Forge 1 7479
Protoss_Dark_Templar 1 8705
Protoss_Photon_Cannon 4 10956
Protoss_High_Templar 2 10489
Protoss_Nexus 1 11851
Psionic_Storm 1 9931
11851
