Protoss_Forge 1 3129
Protoss_Photon_Cannon 3 10805
Protoss_Nexus 1 6769
Protoss_Gateway 4 9789
Protoss_Assimilator 2 7579
Protoss_Zealot 10 10781
Protoss_Cybernetics_Core 1 6821
Protoss_Stargate 1 8131
Protoss_Citadel_of_Adun 1 8295
Protoss_Templar_Archives 1 10518
10805
