Protoss_Forge 1 3109
Protoss_Photon_Cannon 2 9789
Protoss_Nexus 1 6665
Protoss_Gateway 4 11071
Protoss_Assimilator 2 7157
Protoss_Cybernetics_Core 1 6503
Protoss_Zealot 7 10275
Protoss_Stargate 1 7731
Protoss_Dragoon 1 7545
Protoss_Citadel_of_Adun 1 8506
Protoss_Corsair 2 8986
Protoss_Templar_Archives 1 10338
11071
