Protoss_Forge 1 3676
Protoss_Photon_Cannon 3 10985
Protoss_Nexus 1 6529
Protoss_Assimilator 2 8427
Protoss_Gateway 3 10578
Protoss_Zealot 12 10753
Protoss_Cybernetics_Core 1 7079
Protoss_Stargate 1 8364
Protoss_Citadel_of_Adun 1 8827
Protoss_Corsair 3 10357
10985
