Protoss_Forge 1 2819
Protoss_Photon_Cannon 2 5735
Protoss_Nexus 1 7240
Protoss_Gateway 2 10258
Protoss_Assimilator 2 8793
Protoss_Cybernetics_Core 1 7389
Protoss_Zealot 4 9549
Protoss_Stargate 1 8639
Protoss_Citadel_of_Adun 1 8548
Protoss_Corsair 1 9249
Protoss_Templar_Archives 1 9993
Protoss_Robotics_Facility 1 11138
Protoss_Dark_Templar 2 11057
11138
