Protoss_Forge 1 3299
Protoss_Photon_Cannon 3 10791
Protoss_Nexus 1 7111
Protoss_Gateway 2 6925
Protoss_Assimilator 2 8833
Protoss_Zealot 9 9807
Protoss_Cybernetics_Core 1 8300
Protoss_Stargate 1 9660
Protoss_Citadel_of_Adun 1 9715
Protoss_Corsair 1 10271
Protoss_Templar_Archives 1 10836
Protoss_Dragoon 2 10667
10836
