Protoss_Forge 2 4623
Protoss_Nexus 1 6100
Protoss_Gateway 3 9836
Protoss_Photon_Cannon 2 8381
Protoss_Assimilator 2 7378
Protoss_Zealot 9 10851
Protoss_Cybernetics_Core 1 7082
Protoss_Stargate 1 8343
Protoss_Corsair 2 9915
Protoss_Dragoon 1 9133
Protoss_Citadel_of_Adun 1 9407
Protoss_Templar_Archives 1 10867
10867
