Protoss_Forge 1 3206
Protoss_Photon_Cannon 2 11060
Protoss_Nexus 1 7014
Protoss_Gateway 3 10239
Protoss_Assimilator 2 8037
Protoss_Cybernetics_Core 1 6803
Protoss_Zealot 8 10935
Protoss_Stargate 1 8119
Protoss_Citadel_of_Adun 1 8653
Protoss_Corsair 2 9241
Protoss_Templar_Archives 1 9867
Protoss_Dark_Templar 2 11163
11163
