Protoss_Forge 2 4219
Protoss_Nexus 1 5849
Protoss_Gateway 2 9033
Protoss_Photon_Cannon 5 10727
Protoss_Assimilator 2 7181
Protoss_Cybernetics_Core 1 6901
Protoss_Zealot 3 9575
Protoss_Stargate 1 8335
Protoss_Citadel_of_Adun 1 8455
Protoss_Corsair 3 10187
Protoss_Templar_Archives 1 9647
Protoss_High_Templar 1 10447
Protoss_Dark_Templar 1 10851
10851
