Protoss_Forge 1 3339
Protoss_Photon_Cannon 5 7209
Protoss_Nexus 1 8380
Protoss_Gateway 3 11256
Protoss_Assimilator 2 8847
Protoss_Zealot 4 10623
Protoss_Cybernetics_Core 1 8515
Protoss_Dragoon 1 9495
Protoss_Robotics_Facility 1 10378
Protoss_Citadel_of_Adun 1 10719
Protoss_Shuttle 1 11187
Protoss_Robotics_Support_Bay 1 10615
11256
