Protoss_Forge 1 3056
Protoss_Photon_Cannon 5 9009
Protoss_Nexus 1 6603
Protoss_Gateway 5 11071
Protoss_Assimilator 2 10091
Protoss_Zealot 8 10881
Protoss_Cybernetics_Core 1 8107
Protoss_Dragoon 1 8847
Protoss_Citadel_of_Adun 1 9481
11071
