Protoss_Gateway 2 10487
Protoss_Assimilator 1 3433
Protoss_Cybernetics_Core 1 4685
Protoss_Zealot 2 6851
Protoss_Stargate 1 6042
Protoss_Dragoon 3 9006
Protoss_Robotics_Facility 1 7733
Protoss_Corsair 1 7376
10487
