Protoss_Forge 1 2902
Protoss_Photon_Cannon 3 4511
Protoss_Nexus 1 7533
Protoss_Gateway 2 11343
Protoss_Assimilator 1 7377
Protoss_Zealot 2 9797
Protoss_Cybernetics_Core 1 9235
Protoss_Stargate 1 10465
Protoss_Citadel_of_Adun 1 10930
Protoss_Dragoon 1 10745
Protoss_Corsair 1 10917
11343
