Protoss_Forge 1 3278
Protoss_Photon_Cannon 4 11006
Protoss_Nexus 1 6713
Protoss_Gateway 1 5676
Protoss_Assimilator 2 9478
Protoss_Cybernetics_Core 1 6805
Protoss_Zealot 2 9158
Protoss_Stargate 2 9608
Protoss_Scout 3 11201
11201
