Protoss_Gateway 2 3955
Protoss_Zealot 12 10343
Protoss_Nexus 2 9754
Protoss_Assimilator 1 7627
Protoss_Forge 1 8035
Protoss_Photon_Cannon 5 10949
Protoss_Cybernetics_Core 1 10103
10949
