Protoss_Forge 1 3779
Protoss_Nexus 1 6342
Protoss_Photon_Cannon 6 10899
Protoss_Gateway 2 10035
Protoss_Assimilator 2 7893
Protoss_Zealot 7 10463
Protoss_Cybernetics_Core 1 7334
Protoss_Stargate 1 8663
Protoss_Citadel_of_Adun 1 8645
Protoss_Corsair 2 9893
Protoss_Templar_Archives 1 9994
Protoss_Dark_Templar 2 11095
11095
