Protoss_Gateway 1 3483
Protoss_Assimilator 1 3283
Protoss_Cybernetics_Core 1 4574
Protoss_Forge 1 4811
Protoss_Stargate 1 6233
Protoss_Photon_Cannon 3 8401
Protoss_Corsair 2 8026
Protoss_Zealot 3 10526
10526
