Protoss_Forge 1 3240
Protoss_Nexus 1 6103
Protoss_Photon_Cannon 2 6936
Protoss_Gateway 3 10270
Protoss_Assimilator 1 5151
Protoss_Zealot 8 10915
Protoss_Cybernetics_Core 1 8425
Protoss_Stargate 1 9688
Protoss_Citadel_of_Adun 1 9625
Protoss_Corsair 1 10159
10915
