Protoss_Gateway 1 1893
Protoss_Assimilator 1 2378
Protoss_Forge 1 2867
Protoss_Cybernetics_Core 1 3823
Protoss_Photon_Cannon 1 4258
Protoss_Dragoon 1 5006
Protoss_Robotics_Facility 1 6017
Protoss_Observatory 1 7631
7631
