Protoss_Gateway 1 3372
Protoss_Assimilator 1 3403
Protoss_Zealot 5 9901
Protoss_Cybernetics_Core 1 6238
Protoss_Forge 1 6501
Protoss_Dragoon 1 7061
Protoss_Citadel_of_Adun 1 7518
Protoss_Photon_Cannon 2 9358
Protoss_Templar_Archives 1 8836
Protoss_Nexus 1 11223
Protoss_High_Templar 2 11153
11223
