Protoss_Forge 1 3452
Protoss_Photon_Cannon 3 10699
Protoss_Nexus 1 6273
Protoss_Gateway 3 11385
Protoss_Assimilator 2 8467
Protoss_Zealot 6 10495
Protoss_Cybernetics_Core 1 7039
Protoss_Stargate 1 8489
Protoss_Dragoon 1 8369
Protoss_Citadel_of_Adun 1 8978
Protoss_Corsair 1 9517
Protoss_Templar_Archives 1 10317
11385
