Protoss_Gateway 1 3264
Protoss_Forge 1 3354
Protoss_Zealot 5 10721
Protoss_Photon_Cannon 8 11130
Protoss_Nexus 1 7341
Protoss_Assimilator 2 8389
Protoss_Cybernetics_Core 1 7311
Protoss_Stargate 1 8638
Protoss_Corsair 3 10495
Protoss_Citadel_of_Adun 1 10243
Protoss_Shield_Battery 1 10259
11130
