Protoss_Gateway 2 7513
Protoss_Forge 1 2373
Protoss_Zealot 5 9011
Protoss_Photon_Cannon 3 8183
Protoss_Nexus 1 4675
Protoss_Assimilator 2 7029
Protoss_Cybernetics_Core 1 6197
Protoss_Stargate 1 7186
Protoss_Citadel_of_Adun 1 7643
Protoss_Corsair 1 8663
9011
