Protoss_Gateway 3 9325
Protoss_Forge 1 3353
Protoss_Zealot 6 10049
Protoss_Photon_Cannon 7 10571
Protoss_Nexus 1 7395
Protoss_Assimilator 2 7165
Protoss_Cybernetics_Core 1 7358
Protoss_Citadel_of_Adun 1 8608
Protoss_Templar_Archives 1 11275
11275
