Protoss_Gateway 1 3676
Protoss_Nexus 1 6279
Protoss_Zealot 5 9419
Protoss_Assimilator 1 5144
Protoss_Cybernetics_Core 1 6217
Protoss_Forge 1 6806
Protoss_Dragoon 1 7429
Protoss_Stargate 1 8179
Protoss_Photon_Cannon 4 9902
Protoss_Corsair 3 10867
10867
