Protoss_Gateway 5 11224
Protoss_Forge 1 3380
Protoss_Zealot 4 8599
Protoss_Photon_Cannon 4 10899
Protoss_Nexus 1 7290
Protoss_Assimilator 2 7118
Protoss_Cybernetics_Core 1 6957
Protoss_Citadel_of_Adun 1 8099
Protoss_Templar_Archives 1 9399
Protoss_High_Templar 4 11103
Protoss_Dark_Templar 1 10585
11224
