Protoss_Gateway 2 8566
Protoss_Forge 1 3737
Protoss_Zealot 7 10405
Protoss_Photon_Cannon 2 7451
Protoss_Nexus 1 8741
Protoss_Assimilator 2 10009
Protoss_Cybernetics_Core 1 8838
Protoss_Dragoon 1 9613
Protoss_Stargate 1 10183
Protoss_Citadel_of_Adun 1 10397
Protoss_Corsair 1 10701
10701
