Protoss_Gateway 2 4055
Protoss_Zealot 11 9353
Protoss_Forge 1 5719
Protoss_Assimilator 1 6461
Protoss_Photon_Cannon 1 7665
Protoss_Cybernetics_Core 1 8939
Protoss_Dragoon 1 9689
Protoss_Citadel_of_Adun 1 10453
10453
