Protoss_Gateway 2 7414
Protoss_Assimilator 1 3498
Protoss_Zealot 8 9883
Protoss_Cybernetics_Core 1 5367
Protoss_Dragoon 1 6201
Protoss_Citadel_of_Adun 1 7987
Protoss_Nexus 1 10635
Protoss_Templar_Archives 1 9497
Protoss_High_Templar 2 10809
10809
