Protoss_Gateway 2 7729
Protoss_Assimilator 1 3434
Protoss_Zealot 5 7206
Protoss_Cybernetics_Core 1 5833
Protoss_Citadel_of_Adun 1 6967
Protoss_Forge 1 8668
Protoss_Nexus 1 12198
12198
