Protoss_Gateway 1 3342
Protoss_Assimilator 1 3218
Protoss_Cybernetics_Core 1 4452
Protoss_Forge 1 4836
Protoss_Stargate 1 5983
Protoss_Photon_Cannon 3 8294
Protoss_Corsair 1 6401
Protoss_Robotics_Facility 1 9988
9988
