Protoss_Forge 1 2877
Protoss_Photon_Cannon 5 9587
Protoss_Nexus 1 6763
Protoss_Gateway 3 11188
Protoss_Assimilator 2 7340
Protoss_Zealot 3 9395
Protoss_Cybernetics_Core 1 7282
Protoss_Dragoon 2 11013
Protoss_Stargate 1 8643
Protoss_Citadel_of_Adun 1 9427
Protoss_Corsair 4 10915
Protoss_Templar_Archives 1 10521
11188
