Protoss_Forge 1 3139
Protoss_Photon_Cannon 4 11025
Protoss_Nexus 1 6982
Protoss_Gateway 3 11155
Protoss_Assimilator 2 8261
Protoss_Zealot 4 10277
Protoss_Cybernetics_Core 1 7835
Protoss_Stargate 1 9569
Protoss_Corsair 2 10849
Protoss_Citadel_of_Adun 1 10867
11155
