Protoss_Forge 1 2981
Protoss_Photon_Cannon 7 10902
Protoss_Nexus 1 6681
Protoss_Gateway 1 5619
Protoss_Assimilator 1 5444
Protoss_Zealot 5 9571
Protoss_Cybernetics_Core 1 6731
Protoss_Stargate 1 8179
Protoss_Corsair 3 10477
Protoss_Citadel_of_Adun 1 9314
10902
