Protoss_Nexus 1 5791
Protoss_Forge 1 4205
Protoss_Photon_Cannon 3 10803
Protoss_Gateway 2 9622
Protoss_Assimilator 2 6981
Protoss_Cybernetics_Core 1 6927
Protoss_Zealot 4 9401
Protoss_Stargate 1 8226
Protoss_Dragoon 1 8013
Protoss_Citadel_of_Adun 1 8717
Protoss_Corsair 4 10727
Protoss_Templar_Archives 1 9724
Protoss_Dark_Templar 2 10499
10803
