Protoss_Gateway 2 3779
Protoss_Zealot 9 9466
Protoss_Assimilator 1 5811
Protoss_Cybernetics_Core 1 6650
Protoss_Citadel_of_Adun 1 7865
Protoss_Dragoon 1 7786
Protoss_Forge 1 7855
Protoss_Photon_Cannon 2 10673
Protoss_Templar_Archives 1 9681
Protoss_Dark_Templar 1 10601
Protoss_High_Templar 1 10606
10673
