Protoss_Gateway 2 6828
Protoss_Assimilator 1 3624
Protoss_Zealot 5 10918
Protoss_Cybernetics_Core 1 5483
Protoss_Citadel_of_Adun 1 6763
Protoss_Templar_Archives 1 7768
Protoss_Forge 1 7588
Protoss_Dark_Templar 2 8546
Protoss_Nexus 1 11201
Protoss_High_Templar 2 9596
Protoss_Photon_Cannon 2 10250
Protoss_Archon 1 9723
11201
