Protoss_Forge 1 3169
Protoss_Nexus 1 6168
Protoss_Gateway 3 8970
Protoss_Assimilator 2 10341
Protoss_Photon_Cannon 2 10463
Protoss_Zealot 14 10757
Protoss_Cybernetics_Core 1 6649
Protoss_Stargate 1 8214
Protoss_Citadel_of_Adun 1 8410
Protoss_Corsair 1 8643
Protoss_Ground_Weapons_1 1 9813
Protoss_Templar_Archives 1 11265
11265
