Protoss_Gateway 2 3888
Protoss_Assimilator 1 4067
Protoss_Zealot 9 10226
Protoss_Cybernetics_Core 1 5364
Protoss_Stargate 1 6724
Protoss_Dragoon 1 6661
Protoss_Citadel_of_Adun 1 7133
Protoss_Corsair 1 7156
10226
