Protoss_Gateway 2 11061
Protoss_Assimilator 1 3488
Protoss_Zealot 9 10688
Protoss_Cybernetics_Core 1 5158
Protoss_Dragoon 1 6571
Protoss_Robotics_Facility 1 7510
Protoss_Robotics_Support_Bay 1 7615
Protoss_Shuttle 1 8336
Protoss_Reaver 1 9521
Protoss_Forge 1 9523
Protoss_Citadel_of_Adun 1 10791
Protoss_Photon_Cannon 1 11156
11156
