Protoss_Gateway 2 3938
Protoss_Zealot 12 9356
Protoss_Assimilator 1 7028
Protoss_Cybernetics_Core 1 8293
Protoss_Stargate 1 9597
Protoss_Dragoon 1 9351
Protoss_Citadel_of_Adun 1 10249
Protoss_Corsair 2 10618
Protoss_Forge 1 10815
10815
