Protoss_Forge 1 3234
Protoss_Nexus 1 6293
Protoss_Photon_Cannon 10 11163
Protoss_Gateway 1 5909
Protoss_Assimilator 2 10173
Protoss_Zealot 4 8806
Protoss_Cybernetics_Core 1 7458
Protoss_Robotics_Facility 1 9575
Protoss_Citadel_of_Adun 1 9627
Protoss_Templar_Archives 1 10813
Protoss_Robotics_Support_Bay 1 10403
Protoss_Stargate 1 11549
11549
