Protoss_Gateway 4 9049
Protoss_Zealot 13 10841
Protoss_Forge 1 4808
Protoss_Photon_Cannon 3 10998
Protoss_Nexus 1 8850
Protoss_Assimilator 2 10495
Protoss_Cybernetics_Core 1 8155
Protoss_Citadel_of_Adun 1 9190
10998
