Protoss_Gateway 2 6976
Protoss_Assimilator 1 3532
Protoss_Zealot 8 8231
Protoss_Cybernetics_Core 1 5328
Protoss_Citadel_of_Adun 1 6462
Protoss_Templar_Archives 1 8103
Protoss_Forge 1 8018
Protoss_Dark_Templar 1 8911
Protoss_Photon_Cannon 5 11142
Protoss_High_Templar 4 10776
Protoss_Archon 1 9836
11142
