Protoss_Forge 1 2913
Protoss_Nexus 1 7089
Protoss_Photon_Cannon 3 5858
Protoss_Gateway 2 8561
Protoss_Assimilator 2 7374
Protoss_Cybernetics_Core 1 7729
Protoss_Zealot 10 10917
Protoss_Citadel_of_Adun 1 8718
Protoss_Templar_Archives 1 9790
10917
