Protoss_Gateway 2 8408
Protoss_Assimilator 1 3635
Protoss_Cybernetics_Core 1 4612
Protoss_Zealot 8 10816
Protoss_Stargate 1 6028
Protoss_Forge 1 5658
Protoss_Dragoon 1 6256
Protoss_Photon_Cannon 1 6628
Protoss_Corsair 1 6676
Protoss_Citadel_of_Adun 1 7904
10816
