Protoss_Gateway 2 3983
Protoss_Zealot 10 10813
Protoss_Assimilator 1 5005
Protoss_Cybernetics_Core 1 6924
Protoss_Citadel_of_Adun 1 7971
Protoss_Dragoon 1 7781
Protoss_Templar_Archives 1 9458
Protoss_High_Templar 2 10301
Protoss_Forge 1 10166
Protoss_Archon 1 10386
Protoss_Photon_Cannon 1 11138
11138
