Protoss_Gateway 2 6922
Protoss_Assimilator 1 3350
Protoss_Zealot 8 10176
Protoss_Cybernetics_Core 1 5218
Protoss_Dragoon 1 5966
Protoss_Citadel_of_Adun 1 6645
Protoss_Templar_Archives 1 7924
Protoss_High_Templar 4 9656
Protoss_Forge 1 9045
Protoss_Archon 2 9718
Protoss_Photon_Cannon 1 10494
Protoss_Nexus 1 12788
12788
