Protoss_Gateway 1 3393
Protoss_Assimilator 1 3433
Protoss_Zealot 5 8326
Protoss_Cybernetics_Core 1 5233
Protoss_Dragoon 1 6046
Protoss_Citadel_of_Adun 1 7383
Protoss_Forge 1 7303
Protoss_Templar_Archives 1 8604
Protoss_Photon_Cannon 5 11103
Protoss_High_Templar 2 10118
Protoss_Nexus 1 11703
Protoss_Dark_Templar 1 10870
Psionic_Storm 1 9991
11703
