Protoss_Forge 1 3389
Protoss_Photon_Cannon 4 6404
Protoss_Nexus 1 7828
Protoss_Gateway 1 6964
Protoss_Assimilator 2 9318
Protoss_Zealot 5 10311
Protoss_Cybernetics_Core 1 8415
Protoss_Citadel_of_Adun 1 9548
Protoss_Robotics_Facility 1 10847
Protoss_Templar_Archives 1 11107
11107
