Protoss_Gateway 3 8203
Protoss_Zealot 10 8966
Protoss_Assimilator 1 6153
Protoss_Cybernetics_Core 1 7008
Protoss_Nexus 1 9117
Protoss_Forge 1 8578
Protoss_Photon_Cannon 1 9557
Protoss_Citadel_of_Adun 1 10083
Protoss_Templar_Archives 1 11113
Protoss_Robotics_Facility 1 11783
11783
