Protoss_Gateway 2 6737
Protoss_Assimilator 1 3578
Protoss_Cybernetics_Core 1 4668
Protoss_Zealot 11 9555
Protoss_Citadel_of_Adun 1 5833
Protoss_Templar_Archives 1 9097
Protoss_Dark_Templar 2 10476
Protoss_Nexus 1 12862
12862
