Protoss_Gateway 2 7354
Protoss_Assimilator 1 3344
Protoss_Zealot 9 9609
Protoss_Cybernetics_Core 1 5224
Protoss_Dragoon 1 6066
Protoss_Citadel_of_Adun 1 6651
Protoss_Templar_Archives 1 8361
Protoss_High_Templar 3 10471
Protoss_Forge 1 9930
10471
