Protoss_Gateway 2 7928
Protoss_Assimilator 1 3543
Protoss_Zealot 6 8351
Protoss_Cybernetics_Core 1 5526
Protoss_Dragoon 1 6538
Protoss_Citadel_of_Adun 1 7502
Protoss_Templar_Archives 1 8563
Protoss_Forge 1 8823
Protoss_High_Templar 4 10526
Protoss_Nexus 1 11838
Protoss_Archon 1 9515
Protoss_Photon_Cannon 3 11047
11838
