Protoss_Forge 1 3276
Protoss_Nexus 1 6311
Protoss_Gateway 3 8803
Protoss_Photon_Cannon 6 11011
Protoss_Assimilator 2 10027
Protoss_Zealot 10 10469
Protoss_Cybernetics_Core 1 7895
Protoss_Citadel_of_Adun 1 9027
Protoss_Robotics_Facility 1 10874
11011
