Protoss_Forge 2 4471
Protoss_Photon_Cannon 4 5931
Protoss_Nexus 1 7193
Protoss_Assimilator 2 8257
Protoss_Gateway 1 6994
Protoss_Cybernetics_Core 1 8641
Protoss_Stargate 1 10376
10376
