Protoss_Forge 1 2999
Protoss_Nexus 1 6338
Protoss_Photon_Cannon 2 5803
Protoss_Gateway 5 9740
Protoss_Assimilator 2 10385
Protoss_Zealot 12 10956
Protoss_Cybernetics_Core 1 7658
Protoss_Dragoon 1 8646
Protoss_Citadel_of_Adun 1 8958
Protoss_Templar_Archives 1 11306
11306
