Protoss_Gateway 2 10670
Protoss_Assimilator 2 10800
Protoss_Zealot 2 5041
Protoss_Cybernetics_Core 1 5120
Protoss_Stargate 1 6385
Protoss_Citadel_of_Adun 1 6576
Protoss_Corsair 1 6816
Protoss_Dragoon 1 7166
Protoss_Templar_Archives 1 7781
Protoss_Dark_Templar 2 9481
Protoss_Nexus 1 10422
Protoss_Forge 1 8788
Protoss_Photon_Cannon 1 10133
Protoss_High_Templar 1 11116
11116
