Protoss_Forge 1 2983
Protoss_Nexus 1 6494
Protoss_Gateway 3 9138
Protoss_Photon_Cannon 2 11117
Protoss_Assimilator 2 8935
Protoss_Cybernetics_Core 1 6729
Protoss_Zealot 9 10387
Protoss_Citadel_of_Adun 1 8036
Protoss_Dragoon 1 7983
Protoss_Templar_Archives 1 10685
Protoss_Ground_Weapons_1 1 9995
11117
