Protoss_Gateway 2 3948
Protoss_Zealot 14 10401
Protoss_Assimilator 1 6960
Protoss_Forge 1 7808
Protoss_Nexus 1 11073
Protoss_Cybernetics_Core 1 10178
Protoss_Photon_Cannon 1 10288
11073
