Protoss_Forge 1 3092
Protoss_Photon_Cannon 5 10205
Protoss_Gateway 1 5368
Protoss_Nexus 1 7866
Protoss_Assimilator 2 10781
Protoss_Zealot 4 10856
Protoss_Cybernetics_Core 1 7759
Protoss_Stargate 1 9182
Protoss_Dragoon 1 9296
Protoss_Corsair 1 9606
Protoss_Citadel_of_Adun 1 11270
11270
