Protoss_Forge 1 3365
Protoss_Nexus 1 6343
Protoss_Photon_Cannon 7 9728
Protoss_Gateway 1 5933
Protoss_Assimilator 2 9677
Protoss_Cybernetics_Core 1 6991
Protoss_Zealot 4 10656
Protoss_Stargate 1 8290
Protoss_Corsair 3 9910
Protoss_Citadel_of_Adun 1 9728
Protoss_Templar_Archives 1 11118
11118
