Protoss_Gateway 3 9029
Protoss_Zealot 13 10605
Protoss_Assimilator 1 5650
Protoss_Cybernetics_Core 1 6584
Protoss_Nexus 1 9521
Protoss_Citadel_of_Adun 1 8576
Protoss_Forge 1 10491
10605
