Protoss_Gateway 2 4219
Protoss_Zealot 8 6883
Protoss_Forge 1 4767
Protoss_Photon_Cannon 3 9333
Protoss_Assimilator 1 6466
Protoss_Cybernetics_Core 1 7807
Protoss_Stargate 2 9775
Protoss_Corsair 2 10537
10537
