Protoss_Forge 1 3079
Protoss_Nexus 1 6188
Protoss_Gateway 5 9618
Protoss_Photon_Cannon 2 10783
Protoss_Assimilator 2 9698
Protoss_Zealot 13 10261
Protoss_Cybernetics_Core 1 6975
Protoss_Citadel_of_Adun 1 7990
Protoss_Dragoon 1 7876
Protoss_Templar_Archives 1 10239
Protoss_Ground_Weapons_1 1 9816
Protoss_High_Templar 1 11196
11196
