Protoss_Gateway 3 11357
Protoss_Assimilator 1 3380
Protoss_Zealot 4 7733
Protoss_Cybernetics_Core 1 5279
Protoss_Stargate 1 6657
Protoss_Citadel_of_Adun 1 6965
Protoss_Dragoon 1 6885
Protoss_Corsair 1 7127
Protoss_Templar_Archives 1 8039
Protoss_Forge 1 8035
Protoss_Photon_Cannon 3 11071
Protoss_Dark_Templar 1 9215
Protoss_High_Templar 2 10769
11357
