Protoss_Gateway 2 3870
Protoss_Zealot 9 7491
Protoss_Shield_Battery 1 3910
Protoss_Assimilator 1 8140
Protoss_Forge 1 8463
Protoss_Cybernetics_Core 1 9783
Protoss_Photon_Cannon 2 11181
Protoss_Citadel_of_Adun 1 10833
11181
