Protoss_Gateway 1 3354
Protoss_Assimilator 1 3435
Protoss_Forge 1 3937
Protoss_Photon_Cannon 2 8452
Protoss_Cybernetics_Core 1 5902
Protoss_Dragoon 1 6641
Protoss_Ground_Weapons_1 1 8689
Protoss_Zealot 1 10043
10043
