Protoss_Gateway 1 3470
Protoss_Assimilator 1 3483
Protoss_Zealot 7 10341
Protoss_Cybernetics_Core 1 5418
Protoss_Stargate 1 6764
Protoss_Dragoon 1 6644
Protoss_Corsair 4 10071
Protoss_Nexus 1 10671
Protoss_Forge 2 9563
Protoss_Citadel_of_Adun 1 10223
Protoss_Templar_Archives 1 11338
11338
