Protoss_Gateway 1 3255
Protoss_Assimilator 1 3364
Protoss_Zealot 4 8396
Protoss_Cybernetics_Core 1 5272
Protoss_Dragoon 1 6026
Protoss_Stargate 1 6867
Protoss_Forge 1 6915
Protoss_Corsair 1 7341
Protoss_Photon_Cannon 3 10953
Protoss_Citadel_of_Adun 1 8398
Protoss_Robotics_Facility 1 9899
Protoss_Templar_Archives 1 9778
Protoss_Nexus 1 11548
Protoss_Robotics_Support_Bay 1 10085
Protoss_Dark_Templar 1 10696
11548
