Protoss_Gateway 2 9641
Protoss_Assimilator 1 3436
Protoss_Zealot 3 6721
Protoss_Cybernetics_Core 1 5293
Protoss_Dragoon 1 6036
Protoss_Robotics_Facility 1 7555
Protoss_Citadel_of_Adun 1 7832
Protoss_Shuttle 1 8366
Protoss_Robotics_Support_Bay 1 7703
Protoss_Reaver 2 10569
Protoss_Templar_Archives 1 9763
Protoss_Forge 1 10108
Protoss_High_Templar 1 10521
Protoss_Photon_Cannon 2 11063
11063
