Protoss_Gateway 2 3783
Protoss_Zealot 11 7636
Protoss_Forge 1 7168
Protoss_Photon_Cannon 3 9183
Protoss_Assimilator 1 8555
Protoss_Cybernetics_Core 1 9812
Protoss_Stargate 1 11107
11107
