Protoss_Gateway 2 3811
Protoss_Zealot 13 8953
Protoss_Forge 1 6780
Protoss_Assimilator 1 7870
Protoss_Photon_Cannon 3 10290
Protoss_Cybernetics_Core 1 9018
Protoss_Stargate 1 10504
Protoss_Citadel_of_Adun 1 11014
Protoss_Corsair 1 10943
11014
