Protoss_Gateway 3 6793
Protoss_Zealot 17 10826
Protoss_Nexus 1 6678
Protoss_Assimilator 1 7686
Protoss_Cybernetics_Core 1 9342
Protoss_Citadel_of_Adun 1 10560
Protoss_Forge 1 10158
Protoss_Photon_Cannon 1 11129
11129
