Protoss_Gateway 2 3863
Protoss_Zealot 12 9721
Protoss_Assimilator 1 6926
Protoss_Cybernetics_Core 1 7961
Protoss_Stargate 1 9239
Protoss_Dragoon 2 9926
Protoss_Corsair 1 9756
Protoss_Citadel_of_Adun 1 10755
Protoss_Forge 1 10625
10755
