Protoss_Gateway 2 4147
Protoss_Zealot 9 9366
Protoss_Assimilator 1 5099
Protoss_Cybernetics_Core 1 6138
Protoss_Forge 1 6022
Protoss_Citadel_of_Adun 1 7818
Protoss_Templar_Archives 1 9258
Protoss_Photon_Cannon 2 10288
Protoss_High_Templar 2 10511
Protoss_Ground_Weapons_1 1 9756
Protoss_Nexus 1 12863
12863
