Protoss_Nexus 1 5668
Protoss_Forge 1 4164
Protoss_Photon_Cannon 6 11198
Protoss_Gateway 2 7148
Protoss_Assimilator 2 7284
Protoss_Zealot 9 10541
Protoss_Cybernetics_Core 1 8222
Protoss_Stargate 1 9531
Protoss_Citadel_of_Adun 1 9459
Protoss_Corsair 1 9946
Protoss_Templar_Archives 1 10453
11198
