Protoss_Gateway 2 4232
Protoss_Zealot 10 8971
Protoss_Assimilator 1 4958
Protoss_Cybernetics_Core 1 6128
Protoss_Forge 1 6265
Protoss_Dragoon 1 6906
Protoss_Citadel_of_Adun 1 7725
Protoss_Templar_Archives 1 8911
Protoss_Photon_Cannon 2 10498
Protoss_Dark_Templar 1 10431
Protoss_Nexus 1 12571
Protoss_High_Templar 2 11183
12571
