Protoss_Gateway 2 3991
Protoss_Zealot 8 9945
Protoss_Assimilator 1 5200
Protoss_Cybernetics_Core 1 6343
Protoss_Stargate 1 7765
Protoss_Corsair 1 8183
Protoss_Nexus 1 12682
12682
