Protoss_Gateway 2 4000
Protoss_Zealot 13 10531
Protoss_Assimilator 1 4788
Protoss_Cybernetics_Core 1 6852
Protoss_Citadel_of_Adun 1 7920
Protoss_Dragoon 1 8451
Protoss_Templar_Archives 1 8963
Protoss_Forge 1 8686
Protoss_High_Templar 2 9993
Protoss_Photon_Cannon 1 10891
10891
