Protoss_Forge 2 4486
Protoss_Nexus 1 6034
Protoss_Photon_Cannon 4 10935
Protoss_Gateway 6 8833
Protoss_Assimilator 1 5997
Protoss_Cybernetics_Core 1 7203
Protoss_Zealot 16 10851
Protoss_Citadel_of_Adun 1 8369
Protoss_Dragoon 1 9011
10935
