Protoss_Gateway 2 8018
Protoss_Assimilator 1 3498
Protoss_Zealot 8 9986
Protoss_Cybernetics_Core 1 6177
Protoss_Stargate 1 7621
Protoss_Dragoon 1 7346
Protoss_Corsair 1 8036
Protoss_Citadel_of_Adun 1 8694
Protoss_Templar_Archives 1 9944
Protoss_Forge 1 9613
Protoss_Dark_Templar 2 11096
11096
