Protoss_Forge 1 3043
Protoss_Photon_Cannon 8 11172
Protoss_Nexus 1 8353
Protoss_Gateway 4 11043
Protoss_Assimilator 2 10126
Protoss_Zealot 5 10699
Protoss_Cybernetics_Core 1 9636
Protoss_Citadel_of_Adun 1 10633
11172
