Protoss_Gateway 2 7334
Protoss_Assimilator 1 3578
Protoss_Zealot 6 8131
Protoss_Cybernetics_Core 1 5288
Protoss_Dragoon 1 6156
Protoss_Citadel_of_Adun 1 6768
Protoss_Templar_Archives 1 8929
Protoss_Forge 1 9124
Protoss_High_Templar 3 10546
Protoss_Nexus 1 11803
Protoss_Archon 1 9955
Protoss_Dark_Templar 1 10706
11803
