Protoss_Gateway 2 7056
Protoss_Assimilator 1 3526
Protoss_Zealot 9 9701
Protoss_Cybernetics_Core 1 5471
Protoss_Dragoon 1 6221
Protoss_Forge 1 6205
Protoss_Citadel_of_Adun 1 7950
Protoss_Stargate 2 10063
Protoss_Photon_Cannon 1 10421
Protoss_Corsair 3 10951
10951
