Protoss_Forge 1 3549
Protoss_Photon_Cannon 10 10588
Protoss_Nexus 1 6979
Protoss_Gateway 3 9563
Protoss_Assimilator 2 7922
Protoss_Cybernetics_Core 1 7278
Protoss_Citadel_of_Adun 1 8278
Protoss_Dragoon 1 8371
Protoss_Templar_Archives 1 9288
Protoss_High_Templar 3 11166
Protoss_Dark_Templar 1 10771
11166
