Protoss_Forge 1 3359
Protoss_Photon_Cannon 2 4363
Protoss_Nexus 1 7368
Protoss_Gateway 1 6548
Protoss_Assimilator 2 7918
Protoss_Zealot 3 8370
Protoss_Cybernetics_Core 1 7999
Protoss_Robotics_Facility 1 9486
Protoss_Stargate 1 9707
Protoss_Dragoon 1 9921
Protoss_Shuttle 1 10636
Protoss_Robotics_Support_Bay 1 9938
10636
