Protoss_Gateway 3 8143
Protoss_Assimilator 1 3382
Protoss_Zealot 11 10216
Protoss_Cybernetics_Core 1 5343
Protoss_Stargate 1 7173
Protoss_Citadel_of_Adun 1 7317
Protoss_Corsair 1 8276
Protoss_Nexus 1 11749
Protoss_Templar_Archives 1 10478
11749
