Protoss_Forge 1 3766
Protoss_Nexus 1 6286
Protoss_Photon_Cannon 7 10865
Protoss_Gateway 5 11383
Protoss_Assimilator 2 7609
Protoss_Zealot 2 6765
Protoss_Cybernetics_Core 1 6707
Protoss_Citadel_of_Adun 1 7871
Protoss_Templar_Archives 1 8952
Protoss_Dragoon 1 9337
Protoss_High_Templar 2 9709
Protoss_Dark_Templar 1 10089
Protoss_Robotics_Facility 1 11281
11383
