Protoss_Assimilator 1 2793
Protoss_Gateway 1 3668
Protoss_Cybernetics_Core 1 4663
Protoss_Stargate 1 5950
Protoss_Robotics_Facility 1 6548
Protoss_Citadel_of_Adun 1 6601
Protoss_Corsair 1 6371
Protoss_Shuttle 1 7356
Protoss_Templar_Archives 1 7728
Protoss_Forge 1 7648
Protoss_High_Templar 2 9961
Protoss_Nexus 1 10523
Protoss_Photon_Cannon 5 10999
Protoss_Dark_Templar 1 10713
Psionic_Storm 1 9911
10999
