Protoss_Nexus 1 5841
Protoss_Forge 1 4237
Protoss_Photon_Cannon 5 10799
Protoss_Gateway 3 8573
Protoss_Assimilator 1 5669
Protoss_Zealot 12 10595
Protoss_Cybernetics_Core 1 7685
Protoss_Citadel_of_Adun 1 8791
Protoss_Stargate 2 10628
Protoss_Corsair 1 10697
Protoss_Robotics_Facility 1 11862
11862
