Protoss_Gateway 2 8938
Protoss_Assimilator 1 3523
Protoss_Zealot 5 9106
Protoss_Cybernetics_Core 1 5499
Protoss_Citadel_of_Adun 1 6606
Protoss_Dragoon 1 6501
Protoss_Robotics_Facility 1 7927
Protoss_Shuttle 1 9116
Protoss_Robotics_Support_Bay 1 8686
Protoss_Reaver 1 10258
10258
