Protoss_Forge 1 3816
Protoss_Nexus 1 6358
Protoss_Photon_Cannon 3 10173
Protoss_Gateway 1 5703
Protoss_Assimilator 2 8149
Protoss_Cybernetics_Core 1 7020
Protoss_Zealot 2 8351
Protoss_Dragoon 1 7776
Protoss_Stargate 1 8423
Protoss_Corsair 4 10736
Protoss_Robotics_Facility 1 9976
Protoss_Robotics_Support_Bay 3 10264
Protoss_Shuttle 1 11001
11001
