Protoss_Assimilator 1 2787
Protoss_Gateway 1 3870
Protoss_Cybernetics_Core 1 4857
Protoss_Stargate 1 6108
Protoss_Dragoon 1 5845
Protoss_Robotics_Facility 1 7393
Protoss_Corsair 2 7157
Protoss_Shuttle 1 8195
Protoss_Robotics_Support_Bay 1 7826
Protoss_Reaver 3 11647
Protoss_Nexus 1 11222
Protoss_Forge 1 10804
11647
