Protoss_Nexus 1 5983
Protoss_Forge 1 4907
Protoss_Photon_Cannon 8 10373
Protoss_Assimilator 2 7846
Protoss_Gateway 3 10173
Protoss_Cybernetics_Core 1 8286
Protoss_Stargate 2 9691
Protoss_Citadel_of_Adun 1 9619
Protoss_Corsair 3 10756
Protoss_Templar_Archives 1 10823
10823
