Protoss_Gateway 2 4535
Protoss_Zealot 15 9289
Protoss_Assimilator 1 7350
Protoss_Cybernetics_Core 1 8594
Protoss_Forge 1 8585
Protoss_Citadel_of_Adun 1 9626
Protoss_Templar_Archives 1 10709
Protoss_Photon_Cannon 2 11145
Protoss_Nexus 1 12549
12549
