Protoss_Forge 1 3098
Protoss_Nexus 1 6197
Protoss_Photon_Cannon 4 11176
Protoss_Gateway 5 9993
Protoss_Assimilator 2 10750
Protoss_Zealot 13 10835
Protoss_Cybernetics_Core 1 8241
Protoss_Citadel_of_Adun 1 9239
Protoss_Templar_Archives 1 11216
11216
