Protoss_Nexus 1 5713
Protoss_Gateway 4 9553
Protoss_Assimilator 2 9682
Protoss_Forge 1 5138
Protoss_Photon_Cannon 1 6138
Protoss_Zealot 10 10061
Protoss_Cybernetics_Core 1 7551
Protoss_Citadel_of_Adun 1 8624
Protoss_Dragoon 1 8536
Protoss_Templar_Archives 1 10381
Protoss_Ground_Weapons_1 1 9561
Protoss_High_Templar 2 11151
11151
