Protoss_Gateway 1 3410
Protoss_Assimilator 1 3813
Protoss_Zealot 2 6866
Protoss_Cybernetics_Core 1 5213
Protoss_Dragoon 1 5961
Protoss_Stargate 1 6673
Protoss_Robotics_Facility 1 7722
Protoss_Corsair 2 9601
Protoss_Forge 1 7952
Protoss_Shuttle 1 8601
Protoss_Shield_Battery 1 8003
Protoss_Robotics_Support_Bay 1 8064
Protoss_Photon_Cannon 4 11118
Protoss_Reaver 1 9743
Protoss_Nexus 1 11914
11914
