Protoss_Forge 1 1912
Protoss_Nexus 1 3248
Protoss_Photon_Cannon 2 4208
Protoss_Gateway 1 4780
Protoss_Assimilator 1 4967
Protoss_Cybernetics_Core 1 5800
Protoss_Zealot 1 6566
6566
