Protoss_Forge 1 3145
Protoss_Nexus 1 6347
Protoss_Photon_Cannon 2 5390
Protoss_Gateway 5 10063
Protoss_Assimilator 2 10301
Protoss_Cybernetics_Core 1 7581
Protoss_Zealot 11 10891
Protoss_Citadel_of_Adun 1 8760
Protoss_Templar_Archives 1 10951
10951
