Protoss_Gateway 1 3508
Protoss_Assimilator 1 3288
Protoss_Zealot 6 8767
Protoss_Cybernetics_Core 1 6267
Protoss_Dragoon 1 7051
Protoss_Citadel_of_Adun 1 7529
Protoss_Forge 1 7675
Protoss_Templar_Archives 1 8601
Protoss_Dark_Templar 1 9609
Protoss_Photon_Cannon 1 10083
Protoss_High_Templar 2 11113
Protoss_Nexus 1 12448
12448
