Protoss_Gateway 1 3323
Protoss_Assimilator 1 3354
Protoss_Zealot 3 6541
Protoss_Cybernetics_Core 1 5048
Protoss_Dragoon 1 5821
Protoss_Stargate 1 6821
Protoss_Citadel_of_Adun 1 6985
Protoss_Corsair 1 7261
Protoss_Templar_Archives 1 8149
Protoss_Forge 1 7838
Protoss_Photon_Cannon 3 10510
Protoss_Dark_Templar 1 9016
Protoss_Nexus 1 11518
Protoss_High_Templar 2 10806
Psionic_Storm 1 9721
11518
