Protoss_Nexus 1 5713
Protoss_Forge 1 4391
Protoss_Photon_Cannon 3 6705
Protoss_Gateway 5 10032
Protoss_Assimilator 2 8382
Protoss_Zealot 9 10687
Protoss_Cybernetics_Core 1 7608
Protoss_Citadel_of_Adun 1 8903
10687
