Protoss_Forge 1 3190
Protoss_Photon_Cannon 7 10633
Protoss_Nexus 1 7048
Protoss_Gateway 2 9874
Protoss_Assimilator 1 5900
Protoss_Zealot 5 9521
Protoss_Cybernetics_Core 1 7338
Protoss_Citadel_of_Adun 1 8393
Protoss_Dragoon 1 8311
Protoss_Templar_Archives 1 9518
Protoss_Dark_Templar 2 10821
10821
