Protoss_Forge 2 6493
Protoss_Assimilator 2 6030
Protoss_Photon_Cannon 3 10623
Protoss_Gateway 2 9028
Protoss_Zealot 2 9631
Protoss_Cybernetics_Core 1 9978
Protoss_Citadel_of_Adun 1 11063
11063
