Protoss_Gateway 2 3927
Protoss_Zealot 7 9121
Protoss_Assimilator 1 4923
Protoss_Forge 1 5742
Protoss_Cybernetics_Core 1 6857
Protoss_Photon_Cannon 4 11146
Protoss_Citadel_of_Adun 1 7849
Protoss_Templar_Archives 1 9426
Protoss_High_Templar 2 10173
Protoss_Nexus 1 12227
Protoss_Ground_Weapons_1 1 9459
12227
