Protoss_Gateway 3 9941
Protoss_Assimilator 1 3388
Protoss_Zealot 4 6916
Protoss_Cybernetics_Core 1 5916
Protoss_Dragoon 10 10993
Protoss_Forge 1 7400
Protoss_Citadel_of_Adun 1 10766
10993
