Protoss_Gateway 1 3548
Protoss_Assimilator 2 10717
Protoss_Cybernetics_Core 1 4713
Protoss_Robotics_Facility 1 6553
Protoss_Dragoon 1 6076
Protoss_Zealot 1 7041
Protoss_Robotics_Support_Bay 1 6812
Protoss_Reaver 2 11066
Protoss_Shuttle 1 9133
Protoss_Stargate 1 10453
Protoss_Nexus 1 11965
11965
