Protoss_Gateway 2 3995
Protoss_Zealot 17 10203
Protoss_Nexus 1 9095
Protoss_Forge 1 8099
Protoss_Assimilator 1 8446
Protoss_Photon_Cannon 2 10688
Protoss_Cybernetics_Core 1 10087
Protoss_Stargate 1 11653
11653
