Protoss_Forge 1 3388
Protoss_Photon_Cannon 2 4481
Protoss_Nexus 1 7160
Protoss_Gateway 3 9144
Protoss_Assimilator 1 5944
Protoss_Cybernetics_Core 1 7008
Protoss_Zealot 1 9266
9266
