Protoss_Forge 1 3193
Protoss_Photon_Cannon 5 10994
Protoss_Nexus 1 7479
Protoss_Gateway 4 11060
Protoss_Assimilator 3 9642
Protoss_Cybernetics_Core 1 7449
Protoss_Citadel_of_Adun 1 8533
Protoss_Zealot 8 10257
Protoss_Robotics_Facility 1 11835
11835
