Protoss_Forge 1 3226
Protoss_Photon_Cannon 7 10505
Protoss_Nexus 1 7618
Protoss_Gateway 1 6548
Protoss_Assimilator 2 8569
Protoss_Zealot 3 10401
Protoss_Cybernetics_Core 1 7668
Protoss_Dragoon 2 9551
Protoss_Citadel_of_Adun 1 8983
Protoss_Templar_Archives 1 11043
11043
