Protoss_Gateway 2 8031
Protoss_Assimilator 1 3409
Protoss_Zealot 7 10001
Protoss_Cybernetics_Core 1 5238
Protoss_Dragoon 1 6391
Protoss_Stargate 1 7093
Protoss_Corsair 1 8081
Protoss_Shield_Battery 1 8607
Protoss_Forge 1 10215
10215
