Protoss_Forge 2 8528
Protoss_Photon_Cannon 4 9704
Protoss_Nexus 1 6939
Protoss_Gateway 4 10588
Protoss_Assimilator 1 6074
Protoss_Cybernetics_Core 1 7197
Protoss_Zealot 10 10541
Protoss_Dragoon 1 7966
Protoss_Citadel_of_Adun 1 8308
Protoss_Templar_Archives 1 11173
11173
