Protoss_Forge 1 2895
Protoss_Photon_Cannon 4 10945
Protoss_Nexus 1 7306
Protoss_Gateway 1 6173
Protoss_Assimilator 2 7634
Protoss_Zealot 2 7321
Protoss_Cybernetics_Core 1 7340
Protoss_Stargate 2 10603
Protoss_Robotics_Facility 1 9858
Protoss_Corsair 3 10896
Protoss_Robotics_Support_Bay 1 10018
Protoss_Shuttle 1 10821
10945
