Protoss_Forge 1 3348
Protoss_Photon_Cannon 8 11098
Protoss_Nexus 1 7309
Protoss_Gateway 1 6557
Protoss_Assimilator 2 8713
Protoss_Zealot 6 10279
Protoss_Cybernetics_Core 1 7564
Protoss_Citadel_of_Adun 1 9010
Protoss_Templar_Archives 1 9999
Protoss_High_Templar 1 10757
Protoss_Dark_Templar 1 10865
11098
