Protoss_Gateway 2 3928
Protoss_Zealot 10 8341
Protoss_Assimilator 1 7082
Protoss_Cybernetics_Core 1 8496
Protoss_Forge 1 8610
Protoss_Citadel_of_Adun 1 9499
Protoss_Photon_Cannon 2 10115
Protoss_Templar_Archives 1 10719
10719
