Protoss_Gateway 2 4008
Protoss_Zealot 18 9667
Protoss_Assimilator 1 7093
Protoss_Cybernetics_Core 1 8433
Protoss_Citadel_of_Adun 1 9459
Protoss_Templar_Archives 1 10658
Protoss_Forge 1 10559
10658
