Protoss_Gateway 2 4086
Protoss_Zealot 10 10661
Protoss_Assimilator 1 5237
Protoss_Cybernetics_Core 1 6736
Protoss_Citadel_of_Adun 1 7731
Protoss_Templar_Archives 1 8939
Protoss_Forge 1 9033
Protoss_High_Templar 3 10909
Protoss_Nexus 1 11827
Protoss_Photon_Cannon 2 10611
Protoss_Archon 1 10048
11827
