Protoss_Gateway 1 3363
Protoss_Assimilator 1 3699
Protoss_Zealot 3 5666
Protoss_Cybernetics_Core 1 5368
Protoss_Citadel_of_Adun 1 6432
Protoss_Dragoon 1 6508
Protoss_Forge 1 6718
Protoss_Templar_Archives 1 7673
Protoss_Photon_Cannon 3 10635
Protoss_Dark_Templar 2 9241
Protoss_Nexus 1 11648
Protoss_High_Templar 1 11036
11648
