Protoss_Nexus 1 5444
Protoss_Forge 1 3857
Protoss_Photon_Cannon 4 9249
Protoss_Gateway 1 5513
Protoss_Assimilator 2 7620
Protoss_Zealot 5 9149
Protoss_Cybernetics_Core 1 6673
Protoss_Stargate 1 8021
Protoss_Robotics_Facility 2 10908
Protoss_Corsair 3 10849
Protoss_Robotics_Support_Bay 1 9216
Protoss_Reaver 1 10949
10949
