Protoss_Assimilator 1 2730
Protoss_Forge 1 3397
Protoss_Gateway 3 6179
Protoss_Photon_Cannon 4 10625
Protoss_Zealot 8 8185
Protoss_Ground_Weapons_1 1 7385
Protoss_Cybernetics_Core 1 9185
Protoss_Dragoon 3 9961
Protoss_Stargate 1 10783
10783
