Protoss_Gateway 1 3358
Protoss_Assimilator 1 3472
Protoss_Cybernetics_Core 1 4528
Protoss_Zealot 3 8011
Protoss_Stargate 1 5913
Protoss_Corsair 4 10111
Protoss_Robotics_Facility 1 7775
Protoss_Forge 1 7824
Protoss_Shuttle 1 8651
Protoss_Photon_Cannon 2 10059
Protoss_Robotics_Support_Bay 1 8661
Protoss_Reaver 2 11286
Protoss_Nexus 1 12843
12843
