Protoss_Gateway 2 4188
Protoss_Zealot 15 10276
Protoss_Assimilator 1 7197
Protoss_Cybernetics_Core 1 8413
Protoss_Citadel_of_Adun 1 10036
Protoss_Nexus 1 11601
Protoss_Templar_Archives 1 11188
11601
