Protoss_Gateway 2 9811
Protoss_Assimilator 1 3453
Protoss_Cybernetics_Core 1 4571
Protoss_Zealot 4 8241
Protoss_Citadel_of_Adun 1 6210
Protoss_Forge 1 6506
Protoss_Dragoon 2 7571
Protoss_Templar_Archives 1 8383
Protoss_Photon_Cannon 2 10280
Protoss_Dark_Templar 1 9121
Protoss_High_Templar 2 10625
Protoss_Nexus 1 12721
12721
