Protoss_Forge 1 3612
Protoss_Photon_Cannon 7 11121
Protoss_Nexus 1 7271
Protoss_Gateway 1 6247
Protoss_Assimilator 2 8594
Protoss_Cybernetics_Core 1 7265
Protoss_Zealot 6 10267
Protoss_Stargate 1 8675
Protoss_Citadel_of_Adun 1 8988
Protoss_Corsair 2 9847
Protoss_Templar_Archives 1 11215
11215
