Protoss_Forge 1 3207
Protoss_Photon_Cannon 7 11110
Protoss_Gateway 2 10609
Protoss_Zealot 6 10801
Protoss_Nexus 1 8068
Protoss_Assimilator 2 9083
Protoss_Cybernetics_Core 1 8094
Protoss_Citadel_of_Adun 1 9149
Protoss_Templar_Archives 1 10327
Protoss_High_Templar 1 11171
11171
