Protoss_Gateway 1 3523
Protoss_Assimilator 1 3583
Protoss_Zealot 4 7326
Protoss_Cybernetics_Core 1 5859
Protoss_Stargate 1 7149
Protoss_Dragoon 1 6751
Protoss_Citadel_of_Adun 1 7659
Protoss_Corsair 1 7566
Protoss_Templar_Archives 1 8781
Protoss_Dark_Templar 1 9541
Protoss_Nexus 1 11418
Protoss_Forge 1 10228
Protoss_High_Templar 1 10516
Protoss_Photon_Cannon 1 11170
11418
