Protoss_Forge 1 3074
Protoss_Photon_Cannon 4 10488
Protoss_Nexus 1 6613
Protoss_Gateway 3 8908
Protoss_Zealot 11 10396
Protoss_Assimilator 2 8748
Protoss_Cybernetics_Core 1 8505
Protoss_Citadel_of_Adun 1 9558
Protoss_Templar_Archives 1 10588
10588
