Protoss_Forge 1 3133
Protoss_Photon_Cannon 3 5583
Protoss_Nexus 1 7008
Protoss_Gateway 4 8993
Protoss_Assimilator 2 10942
Protoss_Zealot 13 10746
Protoss_Cybernetics_Core 1 8093
Protoss_Citadel_of_Adun 1 9288
Protoss_Templar_Archives 1 10843
10942
