Protoss_Gateway 1 3483
Protoss_Assimilator 1 3533
Protoss_Zealot 3 5841
Protoss_Cybernetics_Core 1 5970
Protoss_Forge 1 7057
Protoss_Dragoon 2 8889
Protoss_Photon_Cannon 1 9558
9558
