Protoss_Forge 1 3265
Protoss_Nexus 1 6150
Protoss_Photon_Cannon 5 11157
Protoss_Gateway 3 10438
Protoss_Assimilator 2 8309
Protoss_Zealot 9 10403
Protoss_Cybernetics_Core 1 6875
Protoss_Citadel_of_Adun 1 8217
Protoss_Dragoon 1 8423
Protoss_Templar_Archives 1 10134
11157
