Protoss_Gateway 1 3356
Protoss_Assimilator 1 3383
Protoss_Zealot 7 8929
Protoss_Cybernetics_Core 1 6117
Protoss_Stargate 2 7811
Protoss_Dragoon 1 7121
Protoss_Citadel_of_Adun 1 8193
Protoss_Corsair 1 8221
Protoss_Forge 1 8617
Protoss_Templar_Archives 1 9335
Protoss_Nexus 1 11908
Protoss_Dark_Templar 1 10393
Protoss_Photon_Cannon 2 10950
Protoss_High_Templar 1 11151
11908
