Protoss_Forge 1 3754
Protoss_Photon_Cannon 6 9954
Protoss_Nexus 1 7983
Protoss_Gateway 1 6961
Protoss_Assimilator 2 8268
Protoss_Cybernetics_Core 1 8103
Protoss_Zealot 2 8528
Protoss_Stargate 1 9388
Protoss_Robotics_Facility 1 10338
Protoss_Corsair 2 10468
Protoss_Shuttle 1 11206
Protoss_Robotics_Support_Bay 1 10668
11206
