Protoss_Gateway 2 8682
Protoss_Zealot 7 7443
Protoss_Assimilator 1 4516
Protoss_Cybernetics_Core 1 6723
Protoss_Stargate 1 8102
Protoss_Dragoon 2 9193
Protoss_Citadel_of_Adun 1 8551
Protoss_Forge 1 8439
Protoss_Corsair 3 10409
Protoss_Templar_Archives 1 9671
Protoss_Photon_Cannon 4 11142
11142
