Protoss_Forge 1 3187
Protoss_Photon_Cannon 6 10063
Protoss_Nexus 1 8405
Protoss_Gateway 2 11245
Protoss_Assimilator 2 8616
Protoss_Cybernetics_Core 1 8200
Protoss_Zealot 4 10545
Protoss_Citadel_of_Adun 1 9528
Protoss_Templar_Archives 1 10523
11245
