Protoss_Gateway 2 10731
Protoss_Zealot 8 9774
Protoss_Nexus 1 7395
Protoss_Forge 1 5736
Protoss_Photon_Cannon 4 7461
Protoss_Assimilator 2 10713
Protoss_Cybernetics_Core 1 9695
Protoss_Citadel_of_Adun 1 10793
10793
