Protoss_Forge 1 3566
Protoss_Photon_Cannon 2 4566
Protoss_Nexus 1 7375
Protoss_Gateway 4 10167
Protoss_Assimilator 2 9959
Protoss_Zealot 9 10813
Protoss_Cybernetics_Core 1 7450
Protoss_Citadel_of_Adun 1 8590
Protoss_Dragoon 1 8406
Protoss_Templar_Archives 1 10400
10813
