Protoss_Forge 1 2965
Protoss_Photon_Cannon 5 9615
Protoss_Nexus 2 12707
Protoss_Gateway 1 5847
Protoss_Assimilator 2 7073
Protoss_Cybernetics_Core 1 6833
Protoss_Zealot 1 6585
Protoss_Stargate 1 8123
Protoss_Robotics_Facility 1 9226
Protoss_Corsair 2 9991
Protoss_Shuttle 1 10143
Protoss_Robotics_Support_Bay 1 10235
12707
