Protoss_Forge 1 2978
Protoss_Photon_Cannon 9 10504
Protoss_Nexus 1 9010
Protoss_Assimilator 1 7713
Protoss_Gateway 2 11094
Protoss_Zealot 3 10496
Protoss_Cybernetics_Core 1 9648
Protoss_Citadel_of_Adun 1 11023
11094
