Protoss_Nexus 1 5778
Protoss_Forge 1 4163
Protoss_Photon_Cannon 5 11200
Protoss_Gateway 4 9378
Protoss_Assimilator 2 7516
Protoss_Cybernetics_Core 1 8975
Protoss_Zealot 7 9951
Protoss_Citadel_of_Adun 1 10091
Protoss_Templar_Archives 1 11104
11200
