Protoss_Forge 1 3326
Protoss_Photon_Cannon 4 10733
Protoss_Nexus 1 7059
Protoss_Gateway 2 9153
Protoss_Assimilator 1 6289
Protoss_Zealot 5 10515
Protoss_Cybernetics_Core 1 7429
Protoss_Dragoon 1 8325
10733
