Protoss_Gateway 2 3902
Protoss_Zealot 8 7763
Protoss_Assimilator 1 4793
Protoss_Forge 1 5473
Protoss_Cybernetics_Core 1 6720
Protoss_Citadel_of_Adun 1 7793
Protoss_Dragoon 1 8106
Protoss_Photon_Cannon 5 10943
Protoss_Templar_Archives 1 9265
Protoss_Nexus 1 12088
Protoss_High_Templar 2 10526
Protoss_Ground_Weapons_1 1 9306
12088
