Protoss_Gateway 1 3173
Protoss_Assimilator 2 10703
Protoss_Zealot 3 6388
Protoss_Cybernetics_Core 1 5123
Protoss_Dragoon 1 5876
Protoss_Stargate 1 6836
Protoss_Citadel_of_Adun 1 7361
Protoss_Forge 1 6983
Protoss_Corsair 1 7306
Protoss_Photon_Cannon 4 10774
Protoss_Templar_Archives 1 8375
Protoss_Dark_Templar 1 9191
Protoss_Robotics_Facility 1 10123
Protoss_Nexus 1 11783
Protoss_Robotics_Support_Bay 1 10252
11783
