Protoss_Forge 1 2988
Protoss_Nexus 1 6502
Protoss_Photon_Cannon 2 5275
Protoss_Gateway 5 10636
Protoss_Assimilator 1 6454
Protoss_Zealot 11 10571
Protoss_Cybernetics_Core 1 7939
Protoss_Citadel_of_Adun 1 9005
Protoss_Dragoon 1 8795
10636
