Protoss_Assimilator 1 2732
Protoss_Gateway 1 3826
Protoss_Cybernetics_Core 1 4817
Protoss_Stargate 2 6537
Protoss_Corsair 9 10495
Protoss_Forge 1 7709
Protoss_Photon_Cannon 1 8641
Protoss_Air_Weapons_1 1 8355
Protoss_Robotics_Facility 1 10559
Protoss_Shuttle 1 11361
11361
