Protoss_Forge 1 3162
Protoss_Photon_Cannon 4 6144
Protoss_Nexus 1 8743
Protoss_Assimilator 1 7190
Protoss_Gateway 2 8835
Protoss_Cybernetics_Core 1 9556
Protoss_Zealot 6 10747
Protoss_Citadel_of_Adun 1 10791
10791
