Protoss_Forge 1 3105
Protoss_Nexus 1 6433
Protoss_Photon_Cannon 4 11139
Protoss_Gateway 3 9229
Protoss_Assimilator 2 9600
Protoss_Zealot 9 10521
Protoss_Cybernetics_Core 1 7399
Protoss_Citadel_of_Adun 1 8435
Protoss_Dragoon 1 8749
11139
