Protoss_Forge 1 3139
Protoss_Nexus 1 6268
Protoss_Gateway 4 8648
Protoss_Photon_Cannon 5 11119
Protoss_Assimilator 2 8813
Protoss_Zealot 11 10436
Protoss_Cybernetics_Core 1 7760
Protoss_Citadel_of_Adun 1 8793
Protoss_Templar_Archives 1 10198
11119
