Protoss_Forge 1 3316
Protoss_Nexus 1 6062
Protoss_Photon_Cannon 8 10583
Protoss_Gateway 1 5906
Protoss_Assimilator 2 8682
Protoss_Zealot 5 9585
Protoss_Cybernetics_Core 1 7697
Protoss_Dragoon 1 8471
Protoss_Citadel_of_Adun 1 9052
Protoss_Templar_Archives 1 10150
Protoss_Dark_Templar 1 11101
11101
