Protoss_Gateway 2 8360
Protoss_Assimilator 1 3476
Protoss_Zealot 9 10948
Protoss_Cybernetics_Core 1 6358
Protoss_Dragoon 1 7106
Protoss_Citadel_of_Adun 1 7637
Protoss_Robotics_Facility 1 9098
Protoss_Templar_Archives 1 8754
Protoss_Dark_Templar 2 9661
Protoss_Shuttle 1 10021
Protoss_High_Templar 2 10436
Protoss_Forge 1 10700
10948
