Protoss_Gateway 2 7348
Protoss_Assimilator 1 3429
Protoss_Zealot 5 9573
Protoss_Cybernetics_Core 1 5293
Protoss_Stargate 1 6614
Protoss_Dragoon 1 6456
Protoss_Citadel_of_Adun 1 6898
Protoss_Robotics_Facility 1 8118
Protoss_Templar_Archives 1 8308
Protoss_Shuttle 1 8926
Protoss_Dark_Templar 2 9061
Protoss_Forge 1 8913
Protoss_Nexus 1 12238
Protoss_Photon_Cannon 2 11123
Protoss_High_Templar 1 10681
12238
