Protoss_Forge 1 4023
Protoss_Nexus 1 6560
Protoss_Photon_Cannon 5 10848
Protoss_Gateway 4 9078
Protoss_Assimilator 2 9942
Protoss_Cybernetics_Core 1 6983
Protoss_Zealot 8 10836
Protoss_Citadel_of_Adun 1 8346
Protoss_Dragoon 1 8271
Protoss_Templar_Archives 1 10240
Protoss_High_Templar 2 11036
11036
