Protoss_Gateway 2 10991
Protoss_Zealot 7 10101
Protoss_Assimilator 1 4116
Protoss_Cybernetics_Core 1 5443
Protoss_Stargate 1 6823
Protoss_Dragoon 1 6900
Protoss_Forge 1 6868
Protoss_Citadel_of_Adun 1 7543
Protoss_Corsair 2 8341
Protoss_Photon_Cannon 3 10471
Protoss_Nexus 1 11348
Protoss_Templar_Archives 1 10099
Protoss_Dark_Templar 1 10976
11348
