Protoss_Forge 1 3527
Protoss_Photon_Cannon 5 9662
Protoss_Gateway 3 10886
Protoss_Nexus 1 7578
Protoss_Assimilator 2 10715
Protoss_Zealot 3 10091
Protoss_Cybernetics_Core 1 8458
Protoss_Stargate 1 9723
Protoss_Corsair 2 10836
Protoss_Citadel_of_Adun 1 11075
11075
