Protoss_Gateway 2 11210
Protoss_Assimilator 1 3453
Protoss_Zealot 5 10351
Protoss_Cybernetics_Core 1 5818
Protoss_Dragoon 1 6571
Protoss_Robotics_Facility 1 7603
Protoss_Forge 1 7575
Protoss_Robotics_Support_Bay 1 7732
Protoss_Shuttle 1 8541
Protoss_Reaver 1 9683
Protoss_Photon_Cannon 3 11097
Protoss_Citadel_of_Adun 1 10642
11210
