Protoss_Gateway 2 3971
Protoss_Zealot 8 8739
Protoss_Assimilator 1 6753
Protoss_Forge 1 7053
Protoss_Photon_Cannon 2 10705
Protoss_Cybernetics_Core 1 8913
Protoss_Dragoon 1 9785
10705
