Protoss_Forge 1 3163
Protoss_Photon_Cannon 4 9606
Protoss_Nexus 1 7383
Protoss_Gateway 5 11423
Protoss_Assimilator 2 8587
Protoss_Zealot 7 10441
Protoss_Cybernetics_Core 1 7878
Protoss_Citadel_of_Adun 1 8963
Protoss_Templar_Archives 1 10637
11423
