Protoss_Forge 1 3198
Protoss_Nexus 1 6484
Protoss_Photon_Cannon 3 7054
Protoss_Gateway 3 11279
Protoss_Assimilator 2 9189
Protoss_Zealot 9 10759
Protoss_Cybernetics_Core 1 8161
Protoss_Citadel_of_Adun 1 9172
Protoss_Dragoon 1 9043
Protoss_Templar_Archives 1 10603
11279
