Protoss_Forge 1 3040
Protoss_Nexus 1 6358
Protoss_Photon_Cannon 2 5243
Protoss_Gateway 4 9303
Protoss_Assimilator 2 10223
Protoss_Zealot 7 9916
Protoss_Cybernetics_Core 1 7923
Protoss_Citadel_of_Adun 1 8923
Protoss_Dragoon 1 8696
Protoss_Templar_Archives 1 10568
10568
