Protoss_Forge 1 3438
Protoss_Photon_Cannon 2 4443
Protoss_Nexus 1 6943
Protoss_Gateway 1 6045
Protoss_Assimilator 1 5728
Protoss_Cybernetics_Core 1 7049
Protoss_Zealot 3 8411
Protoss_Stargate 1 8387
8411
