Protoss_Gateway 4 9843
Protoss_Zealot 9 7179
Protoss_Nexus 1 8737
Protoss_Assimilator 3 10191
Protoss_Cybernetics_Core 1 8119
Protoss_Dragoon 6 11071
Protoss_Forge 1 10465
11071
