Protoss_Forge 1 2927
Protoss_Photon_Cannon 6 11020
Protoss_Nexus 1 7107
Protoss_Gateway 3 8789
Protoss_Assimilator 2 10553
Protoss_Zealot 9 9893
Protoss_Cybernetics_Core 1 7310
Protoss_Citadel_of_Adun 1 8449
Protoss_Templar_Archives 1 10477
11020
