Protoss_Gateway 2 3672
Protoss_Zealot 15 9483
Protoss_Nexus 1 10361
Protoss_Forge 1 8702
Protoss_Assimilator 1 8809
Protoss_Photon_Cannon 2 10039
Protoss_Cybernetics_Core 1 10994
10994
