Protoss_Forge 1 3175
Protoss_Nexus 1 6390
Protoss_Photon_Cannon 3 10620
Protoss_Gateway 3 9478
Protoss_Assimilator 2 9181
Protoss_Zealot 8 10676
Protoss_Cybernetics_Core 1 7814
Protoss_Dragoon 1 8733
Protoss_Citadel_of_Adun 1 9138
10676
