Protoss_Gateway 3 8321
Protoss_Zealot 12 10581
Protoss_Assimilator 1 5023
Protoss_Cybernetics_Core 1 6031
Protoss_Dragoon 1 7066
Protoss_Stargate 1 8251
Protoss_Corsair 1 9646
10581
