Protoss_Nexus 1 5908
Protoss_Forge 1 4499
Protoss_Photon_Cannon 2 11105
Protoss_Gateway 4 11037
Protoss_Assimilator 2 8785
Protoss_Zealot 11 10596
Protoss_Cybernetics_Core 1 7080
Protoss_Citadel_of_Adun 1 8113
Protoss_Dragoon 1 8713
Protoss_Templar_Archives 1 9418
Protoss_High_Templar 2 10953
11105
