Protoss_Nexus 1 5461
Protoss_Forge 1 3911
Protoss_Photon_Cannon 5 11102
Protoss_Gateway 5 11065
Protoss_Assimilator 2 9402
Protoss_Zealot 13 10869
Protoss_Cybernetics_Core 1 7499
Protoss_Citadel_of_Adun 1 8562
Protoss_Dragoon 1 8931
Protoss_Templar_Archives 1 10597
11102
