Protoss_Gateway 2 3688
Protoss_Zealot 14 10701
Protoss_Nexus 1 8648
Protoss_Forge 1 7373
Protoss_Photon_Cannon 1 8313
Protoss_Assimilator 2 9908
Protoss_Cybernetics_Core 1 9478
Protoss_Citadel_of_Adun 1 10958
10958
