Protoss_Gateway 2 4093
Protoss_Zealot 12 9013
Protoss_Assimilator 1 5853
Protoss_Cybernetics_Core 1 7537
Protoss_Forge 1 7817
Protoss_Dragoon 1 8501
Protoss_Photon_Cannon 3 10593
Protoss_Robotics_Facility 1 10363
Protoss_Citadel_of_Adun 1 10219
Protoss_Templar_Archives 1 11223
Protoss_Observatory 1 10664
11223
