Protoss_Gateway 2 8817
Protoss_Assimilator 1 3438
Protoss_Zealot 3 5055
Protoss_Cybernetics_Core 1 6059
Protoss_Stargate 1 7303
Protoss_Citadel_of_Adun 1 7198
Protoss_Dragoon 1 7256
Protoss_Corsair 1 7721
Protoss_Templar_Archives 1 8493
Protoss_Forge 1 8653
Protoss_Dark_Templar 2 9571
Protoss_High_Templar 2 10323
Protoss_Nexus 1 12108
12108
