Protoss_Forge 1 2981
Protoss_Nexus 1 6143
Protoss_Photon_Cannon 2 5308
Protoss_Gateway 4 9875
Protoss_Assimilator 2 7489
Protoss_Zealot 7 10586
Protoss_Cybernetics_Core 1 8121
Protoss_Citadel_of_Adun 1 9262
Protoss_Templar_Archives 1 10502
Protoss_Dragoon 1 10926
Protoss_Robotics_Facility 1 11852
11852
