Protoss_Gateway 2 8687
Protoss_Assimilator 1 3378
Protoss_Zealot 4 7571
Protoss_Cybernetics_Core 1 4609
Protoss_Stargate 1 5913
Protoss_Dragoon 1 5556
Protoss_Corsair 1 6341
Protoss_Citadel_of_Adun 1 7513
Protoss_Templar_Archives 1 8593
Protoss_Forge 1 8602
Protoss_Dark_Templar 2 9446
Protoss_High_Templar 2 11191
Protoss_Nexus 1 12583
Protoss_Photon_Cannon 1 11128
12583
