Protoss_Gateway 2 3758
Protoss_Zealot 12 10756
Protoss_Nexus 1 8496
Protoss_Forge 1 7087
Protoss_Photon_Cannon 2 8428
Protoss_Assimilator 2 9833
Protoss_Cybernetics_Core 1 9773
Protoss_Citadel_of_Adun 1 11153
11153
