Protoss_Nexus 1 6107
Protoss_Gateway 3 5968
Protoss_Zealot 16 10306
Protoss_Assimilator 2 9500
Protoss_Forge 1 7413
Protoss_Cybernetics_Core 1 9198
Protoss_Photon_Cannon 1 9283
Protoss_Stargate 1 10837
Protoss_Citadel_of_Adun 1 10668
10837
