Protoss_Forge 1 2979
Protoss_Photon_Cannon 4 10495
Protoss_Nexus 1 6968
Protoss_Gateway 1 6168
Protoss_Assimilator 2 7593
Protoss_Zealot 4 8502
Protoss_Cybernetics_Core 1 7625
Protoss_Stargate 1 8938
Protoss_Citadel_of_Adun 1 8858
Protoss_Corsair 3 10611
Protoss_Robotics_Facility 1 10491
Protoss_Shuttle 1 11316
11316
