Protoss_Forge 1 3038
Protoss_Nexus 2 11733
Protoss_Photon_Cannon 3 10843
Protoss_Gateway 2 10556
Protoss_Assimilator 2 8368
Protoss_Zealot 3 9601
Protoss_Cybernetics_Core 1 7534
Protoss_Citadel_of_Adun 1 8603
Protoss_Dragoon 1 8453
Protoss_Templar_Archives 1 9732
Protoss_Dark_Templar 1 10481
11733
