Protoss_Nexus 1 5687
Protoss_Forge 1 4269
Protoss_Photon_Cannon 2 5600
Protoss_Gateway 3 8448
Protoss_Assimilator 2 7153
Protoss_Cybernetics_Core 1 7453
Protoss_Zealot 12 10696
Protoss_Citadel_of_Adun 1 8568
Protoss_Templar_Archives 1 10137
Protoss_Dark_Templar 2 10976
10976
