Protoss_Forge 2 9878
Protoss_Photon_Cannon 5 11012
Protoss_Assimilator 2 8273
Protoss_Gateway 1 7148
Protoss_Zealot 1 7666
Protoss_Cybernetics_Core 1 8588
Protoss_Dragoon 1 9376
Protoss_Stargate 1 9878
Protoss_Citadel_of_Adun 1 9978
Protoss_Corsair 1 10326
Protoss_Templar_Archives 1 11308
11308
