Protoss_Forge 1 3822
Protoss_Nexus 1 6224
Protoss_Photon_Cannon 6 11088
Protoss_Gateway 1 5983
Protoss_Assimilator 1 6268
Protoss_Zealot 5 9916
Protoss_Cybernetics_Core 1 9430
Protoss_Robotics_Facility 1 11538
11538
