Protoss_Gateway 1 3447
Protoss_Zealot 4 7913
Protoss_Assimilator 1 4227
Protoss_Cybernetics_Core 1 5475
Protoss_Stargate 1 6720
Protoss_Dragoon 1 6407
Protoss_Citadel_of_Adun 1 7133
Protoss_Corsair 1 7139
Protoss_Templar_Archives 1 8568
Protoss_Nexus 1 10815
Protoss_Dark_Templar 1 9365
Protoss_Forge 1 9849
Protoss_High_Templar 1 10331
Protoss_Photon_Cannon 2 11071
11071
