Protoss_Forge 1 2118
Protoss_Nexus 1 3557
Protoss_Photon_Cannon 2 4548
Protoss_Gateway 2 5671
Protoss_Assimilator 1 6498
Protoss_Zealot 7 9036
Protoss_Cybernetics_Core 1 7699
9036
