Protoss_Nexus 2 9582
Protoss_Forge 2 9194
Protoss_Photon_Cannon 5 10415
Protoss_Gateway 3 6057
Protoss_Zealot 12 9334
Protoss_Assimilator 1 10546
Protoss_Cybernetics_Core 1 11401
11401
