Protoss_Gateway 1 3460
Protoss_Assimilator 1 3466
Protoss_Cybernetics_Core 1 4483
Protoss_Zealot 7 10375
Protoss_Stargate 1 5796
Protoss_Corsair 1 6207
Protoss_Scout 1 7309
Protoss_Dragoon 1 6905
Protoss_Nexus 1 11667
Protoss_Citadel_of_Adun 1 10601
11667
