Protoss_Nexus 1 5733
Protoss_Forge 1 4148
Protoss_Photon_Cannon 1 5088
Protoss_Gateway 3 8358
Protoss_Assimilator 2 9758
Protoss_Zealot 11 10362
Protoss_Cybernetics_Core 1 7680
Protoss_Dragoon 1 8516
Protoss_Citadel_of_Adun 1 8859
Protoss_Templar_Archives 1 9858
Protoss_Ground_Weapons_1 1 9836
10362
