Protoss_Forge 1 3349
Protoss_Photon_Cannon 4 10595
Protoss_Nexus 1 7220
Protoss_Gateway 2 9893
Protoss_Assimilator 2 8873
Protoss_Cybernetics_Core 1 7571
Protoss_Dragoon 1 8309
Protoss_Citadel_of_Adun 1 8681
Protoss_Zealot 3 10113
Protoss_Stargate 2 10632
Protoss_Templar_Archives 1 10843
10843
