Protoss_Forge 1 2931
Protoss_Photon_Cannon 5 11169
Protoss_Nexus 1 6497
Protoss_Gateway 4 8742
Protoss_Assimilator 2 10440
Protoss_Zealot 16 10697
Protoss_Cybernetics_Core 1 6594
Protoss_Citadel_of_Adun 1 7847
Protoss_Templar_Archives 1 9631
Protoss_High_Templar 2 10571
Protoss_Ground_Weapons_1 1 9725
11169
