Protoss_Gateway 2 6532
Protoss_Assimilator 1 2394
Protoss_Zealot 7 8931
Protoss_Cybernetics_Core 1 4128
Protoss_Robotics_Facility 1 5358
Protoss_Dragoon 2 6336
Protoss_Robotics_Support_Bay 1 7063
Protoss_Shield_Battery 1 7179
8931
