Protoss_Gateway 1 3351
Protoss_Assimilator 1 3398
Protoss_Zealot 3 5536
Protoss_Cybernetics_Core 1 5513
Protoss_Dragoon 1 6378
Protoss_Stargate 1 6958
Protoss_Citadel_of_Adun 1 7218
Protoss_Corsair 1 7601
Protoss_Templar_Archives 1 8213
Protoss_Forge 1 8434
Protoss_Dark_Templar 1 9001
Protoss_Photon_Cannon 5 11193
Protoss_High_Templar 2 10553
Protoss_Nexus 1 11643
Psionic_Storm 1 9671
11643
