Protoss_Forge 1 3230
Protoss_Photon_Cannon 2 9642
Protoss_Nexus 1 6793
Protoss_Gateway 1 5638
Protoss_Assimilator 1 5753
Protoss_Zealot 7 10488
Protoss_Cybernetics_Core 1 8143
Protoss_Stargate 1 9380
Protoss_Dragoon 1 9226
10488
