Protoss_Gateway 2 8171
Protoss_Assimilator 1 3461
Protoss_Zealot 11 10323
Protoss_Cybernetics_Core 1 5559
Protoss_Stargate 1 6966
Protoss_Dragoon 1 7017
Protoss_Citadel_of_Adun 1 7941
Protoss_Corsair 1 7787
Protoss_Templar_Archives 1 9873
Protoss_Forge 1 9951
Protoss_High_Templar 2 10635
Protoss_Photon_Cannon 3 11128
11128
