Protoss_Nexus 1 5864
Protoss_Gateway 4 8589
Protoss_Forge 1 5211
Protoss_Zealot 15 10507
Protoss_Assimilator 1 5669
Protoss_Photon_Cannon 1 6228
Protoss_Cybernetics_Core 1 7168
Protoss_Citadel_of_Adun 1 8401
10507
