Protoss_Assimilator 1 2553
Protoss_Gateway 1 3833
Protoss_Cybernetics_Core 1 4851
Protoss_Stargate 1 6138
Protoss_Dragoon 2 6708
Protoss_Corsair 5 9878
Protoss_Forge 1 8659
9878
