Protoss_Gateway 5 10921
Protoss_Zealot 14 10516
Protoss_Nexus 1 8572
Protoss_Forge 1 7705
Protoss_Assimilator 1 7780
Protoss_Photon_Cannon 2 8838
Protoss_Cybernetics_Core 1 9444
Protoss_Citadel_of_Adun 1 10464
Protoss_Stargate 1 10812
10921
