Protoss_Forge 1 3100
Protoss_Photon_Cannon 5 11042
Protoss_Gateway 1 4746
Protoss_Nexus 1 7295
Protoss_Assimilator 2 6885
Protoss_Cybernetics_Core 1 6674
Protoss_Stargate 2 10883
Protoss_Corsair 4 10419
Protoss_Robotics_Facility 1 10374
Protoss_Shuttle 1 11279
11279
