Protoss_Gateway 4 10706
Protoss_Zealot 10 10887
Protoss_Assimilator 1 4423
Protoss_Forge 1 4711
Protoss_Nexus 1 8207
Protoss_Photon_Cannon 2 7207
Protoss_Cybernetics_Core 1 8103
Protoss_Citadel_of_Adun 1 9225
Protoss_Dragoon 1 9093
10887
