Protoss_Forge 1 3052
Protoss_Photon_Cannon 4 11115
Protoss_Nexus 1 6621
Protoss_Gateway 4 9820
Protoss_Assimilator 2 9619
Protoss_Cybernetics_Core 1 6845
Protoss_Zealot 8 10811
Protoss_Citadel_of_Adun 1 8844
11115
