Protoss_Forge 1 3478
Protoss_Photon_Cannon 6 10547
Protoss_Nexus 1 6867
Protoss_Gateway 2 11264
Protoss_Zealot 5 10461
Protoss_Assimilator 1 6693
Protoss_Cybernetics_Core 1 8847
Protoss_Citadel_of_Adun 1 10034
Protoss_Dragoon 1 9949
Protoss_Templar_Archives 1 11179
11264
