Protoss_Forge 1 3259
Protoss_Nexus 1 6583
Protoss_Photon_Cannon 3 11054
Protoss_Gateway 4 8922
Protoss_Assimilator 2 9685
Protoss_Cybernetics_Core 1 7025
Protoss_Zealot 13 10645
Protoss_Citadel_of_Adun 1 8068
Protoss_Templar_Archives 1 10689
11054
