Protoss_Gateway 1 3419
Protoss_Assimilator 2 10813
Protoss_Zealot 3 5731
Protoss_Cybernetics_Core 1 5315
Protoss_Stargate 1 6932
Protoss_Dragoon 1 6666
Protoss_Citadel_of_Adun 1 7299
Protoss_Corsair 1 7376
Protoss_Forge 1 7724
Protoss_Templar_Archives 1 8298
Protoss_Photon_Cannon 4 10820
Protoss_Dark_Templar 1 9116
Protoss_Nexus 1 11258
Protoss_High_Templar 2 11033
11258
