Protoss_Forge 1 3322
Protoss_Photon_Cannon 5 10703
Protoss_Nexus 1 6884
Protoss_Gateway 3 8870
Protoss_Assimilator 2 7888
Protoss_Cybernetics_Core 1 7424
Protoss_Zealot 6 10121
Protoss_Citadel_of_Adun 1 8669
Protoss_Dragoon 1 8796
Protoss_Templar_Archives 1 9742
Protoss_Robotics_Facility 1 11042
Protoss_High_Templar 2 10501
11042
