Protoss_Gateway 1 3291
Protoss_Assimilator 1 3175
Protoss_Cybernetics_Core 1 4492
Protoss_Zealot 5 9319
Protoss_Dragoon 1 5323
Protoss_Stargate 1 6343
Protoss_Corsair 1 6837
Protoss_Citadel_of_Adun 1 8252
Protoss_Templar_Archives 1 9355
Protoss_Forge 1 9246
Protoss_Dark_Templar 1 10161
Protoss_Photon_Cannon 1 10379
Protoss_High_Templar 1 11171
11171
