Protoss_Nexus 1 5668
Protoss_Forge 1 4344
Protoss_Gateway 4 8093
Protoss_Assimilator 2 9464
Protoss_Photon_Cannon 2 10832
Protoss_Cybernetics_Core 1 6883
Protoss_Citadel_of_Adun 1 7903
Protoss_Zealot 11 9836
Protoss_Templar_Archives 1 9649
Protoss_High_Templar 2 10941
Protoss_Ground_Weapons_1 1 9971
10941
