Protoss_Forge 1 3353
Protoss_Photon_Cannon 6 6369
Protoss_Nexus 1 7984
Protoss_Gateway 4 10658
Protoss_Assimilator 1 6688
Protoss_Cybernetics_Core 1 7898
Protoss_Zealot 8 10663
Protoss_Dragoon 1 8929
Protoss_Citadel_of_Adun 1 9788
Protoss_Templar_Archives 1 11245
11245
