Protoss_Gateway 2 4111
Protoss_Zealot 11 10183
Protoss_Assimilator 1 4648
Protoss_Cybernetics_Core 1 6074
Protoss_Citadel_of_Adun 1 7247
Protoss_Templar_Archives 1 8580
Protoss_Forge 1 8348
Protoss_Photon_Cannon 2 10005
Protoss_High_Templar 4 11126
Protoss_Archon 1 9767
11126
