Protoss_Forge 1 3048
Protoss_Photon_Cannon 9 10733
Protoss_Nexus 1 6195
Protoss_Gateway 3 11342
Protoss_Assimilator 2 8556
Protoss_Zealot 3 7919
Protoss_Cybernetics_Core 1 8085
Protoss_Citadel_of_Adun 1 9222
Protoss_Templar_Archives 1 10430
11342
