Protoss_Assimilator 1 3085
Protoss_Gateway 2 9672
Protoss_Cybernetics_Core 1 4763
Protoss_Dragoon 9 10926
Protoss_Robotics_Facility 1 6399
Protoss_Observatory 1 6611
Protoss_Observer 1 7391
Protoss_Shuttle 1 8491
Protoss_Forge 1 9093
Protoss_Shield_Battery 1 9151
Protoss_Photon_Cannon 1 10033
Protoss_Citadel_of_Adun 1 11164
11164
