Protoss_Forge 1 3075
Protoss_Nexus 1 6283
Protoss_Photon_Cannon 4 10397
Protoss_Assimilator 2 6531
Protoss_Gateway 3 9385
Protoss_Zealot 7 9921
Protoss_Cybernetics_Core 1 7620
Protoss_Citadel_of_Adun 1 8748
Protoss_Templar_Archives 1 10110
Protoss_High_Templar 2 11081
11081
