Protoss_Forge 1 3113
Protoss_Nexus 1 6611
Protoss_Photon_Cannon 6 11058
Protoss_Assimilator 2 7008
Protoss_Gateway 3 9553
Protoss_Cybernetics_Core 1 8528
Protoss_Zealot 10 10680
Protoss_Citadel_of_Adun 1 9878
11058
