Protoss_Nexus 1 5703
Protoss_Forge 2 8263
Protoss_Photon_Cannon 5 10925
Protoss_Assimilator 2 6705
Protoss_Gateway 3 8420
Protoss_Cybernetics_Core 1 9385
Protoss_Zealot 6 10013
Protoss_Citadel_of_Adun 1 10573
Protoss_Robotics_Facility 1 11340
11340
