Protoss_Forge 1 3153
Protoss_Nexus 1 6383
Protoss_Photon_Cannon 3 10470
Protoss_Gateway 4 10370
Protoss_Assimilator 2 7284
Protoss_Cybernetics_Core 1 7511
Protoss_Citadel_of_Adun 1 8568
Protoss_Robotics_Facility 1 10009
Protoss_Templar_Archives 1 9954
Protoss_Zealot 1 10291
Protoss_Observatory 1 10238
Protoss_High_Templar 2 11056
11056
