Protoss_Forge 1 3366
Protoss_Photon_Cannon 5 11198
Protoss_Nexus 1 7055
Protoss_Gateway 3 10629
Protoss_Zealot 4 10696
Protoss_Assimilator 2 8966
Protoss_Cybernetics_Core 1 9928
Protoss_Citadel_of_Adun 1 11059
11198
