Protoss_Gateway 3 8119
Protoss_Assimilator 1 3503
Protoss_Zealot 3 5303
Protoss_Cybernetics_Core 1 5454
Protoss_Stargate 1 6781
Protoss_Dragoon 8 9811
Protoss_Corsair 1 7216
9811
