Protoss_Forge 1 3816
Protoss_Photon_Cannon 6 10928
Protoss_Nexus 1 7723
Protoss_Assimilator 2 7087
Protoss_Gateway 3 11311
Protoss_Cybernetics_Core 1 7883
Protoss_Zealot 2 8008
Protoss_Citadel_of_Adun 1 8948
Protoss_Dragoon 1 8856
Protoss_Templar_Archives 1 10008
Protoss_High_Templar 2 10891
11311
