Protoss_Forge 1 3747
Protoss_Nexus 1 6394
Protoss_Photon_Cannon 1 4845
Protoss_Gateway 3 8978
Protoss_Assimilator 2 9488
Protoss_Zealot 11 10656
Protoss_Cybernetics_Core 1 7460
Protoss_Citadel_of_Adun 1 8524
Protoss_Templar_Archives 1 9975
Protoss_Ground_Weapons_1 1 9606
Protoss_High_Templar 2 10955
10955
