Protoss_Forge 1 3203
Protoss_Nexus 1 6233
Protoss_Gateway 4 10123
Protoss_Photon_Cannon 1 5349
Protoss_Assimilator 2 8420
Protoss_Zealot 10 10701
Protoss_Cybernetics_Core 1 6707
Protoss_Citadel_of_Adun 1 7827
Protoss_Dragoon 1 8106
Protoss_Templar_Archives 1 9841
Protoss_Robotics_Facility 1 11508
Protoss_High_Templar 2 11016
11508
