Protoss_Gateway 1 3339
Protoss_Assimilator 1 3377
Protoss_Zealot 3 5275
Protoss_Cybernetics_Core 1 5537
Protoss_Stargate 1 6782
Protoss_Citadel_of_Adun 1 6932
Protoss_Dragoon 1 7049
Protoss_Corsair 1 7253
Protoss_Forge 1 7597
Protoss_Templar_Archives 1 8205
Protoss_Dark_Templar 1 8985
8985
