Protoss_Gateway 3 8842
Protoss_Assimilator 1 3370
Protoss_Zealot 9 9643
Protoss_Cybernetics_Core 1 5392
Protoss_Citadel_of_Adun 1 6483
Protoss_Dragoon 2 11059
Protoss_Templar_Archives 1 9755
Protoss_Forge 1 10012
Protoss_High_Templar 2 10543
Protoss_Photon_Cannon 2 11073
11073
