Protoss_Gateway 2 4263
Protoss_Zealot 9 10253
Protoss_Assimilator 1 4696
Protoss_Cybernetics_Core 1 6526
Protoss_Forge 1 6545
Protoss_Stargate 1 7805
Protoss_Dragoon 1 7431
Protoss_Citadel_of_Adun 1 8115
Protoss_Scout 1 9391
Protoss_Templar_Archives 1 10569
Protoss_Photon_Cannon 1 10978
10978
