Protoss_Gateway 4 10460
Protoss_Zealot 5 8846
Protoss_Forge 1 4153
Protoss_Photon_Cannon 2 6371
Protoss_Nexus 1 7968
Protoss_Assimilator 2 9436
Protoss_Cybernetics_Core 1 7942
Protoss_Citadel_of_Adun 1 9101
Protoss_Dragoon 1 9801
Protoss_Templar_Archives 1 11288
11288
