Protoss_Forge 1 3024
Protoss_Nexus 1 6233
Protoss_Photon_Cannon 7 10923
Protoss_Gateway 3 10463
Protoss_Zealot 6 10110
Protoss_Assimilator 2 10838
Protoss_Cybernetics_Core 1 8093
Protoss_Citadel_of_Adun 1 9308
Protoss_Templar_Archives 1 11009
11009
