Protoss_Forge 1 3160
Protoss_Photon_Cannon 2 4544
Protoss_Nexus 1 6906
Protoss_Gateway 1 5831
Protoss_Assimilator 2 8213
Protoss_Zealot 1 6396
Protoss_Cybernetics_Core 1 7202
8213
