Protoss_Forge 1 3312
Protoss_Nexus 1 6397
Protoss_Gateway 4 10088
Protoss_Assimilator 2 8125
Protoss_Photon_Cannon 2 9218
Protoss_Zealot 7 10861
Protoss_Cybernetics_Core 1 6801
Protoss_Citadel_of_Adun 1 7873
Protoss_Templar_Archives 1 9718
Protoss_High_Templar 2 10773
Protoss_Dark_Templar 1 10736
10861
