Protoss_Forge 1 3147
Protoss_Photon_Cannon 3 10964
Protoss_Nexus 1 7446
Protoss_Gateway 4 10076
Protoss_Assimilator 2 8472
Protoss_Zealot 8 10391
Protoss_Cybernetics_Core 1 7470
Protoss_Citadel_of_Adun 1 8663
Protoss_Templar_Archives 1 10560
10964
