Protoss_Nexus 1 5794
Protoss_Gateway 2 10128
Protoss_Forge 1 4818
Protoss_Assimilator 2 7351
Protoss_Photon_Cannon 5 10144
Protoss_Zealot 5 10670
Protoss_Cybernetics_Core 1 7173
Protoss_Citadel_of_Adun 1 8266
Protoss_Stargate 1 8974
Protoss_Templar_Archives 1 9549
Protoss_Corsair 1 9526
Protoss_Ground_Weapons_1 1 9991
10670
