Protoss_Forge 1 3486
Protoss_Photon_Cannon 2 9800
Protoss_Nexus 1 6628
Protoss_Assimilator 2 10159
Protoss_Gateway 4 9338
Protoss_Cybernetics_Core 1 7103
Protoss_Zealot 12 10551
Protoss_Citadel_of_Adun 1 8188
Protoss_Dragoon 1 8151
Protoss_Ground_Armor_1 1 9791
Protoss_Templar_Archives 1 11244
11244
