Protoss_Nexus 1 5815
Protoss_Forge 1 4158
Protoss_Photon_Cannon 4 10859
Protoss_Gateway 4 9798
Protoss_Assimilator 2 7863
Protoss_Zealot 8 10396
Protoss_Cybernetics_Core 1 7483
Protoss_Dragoon 1 8286
Protoss_Citadel_of_Adun 1 9180
Protoss_Templar_Archives 1 10243
Protoss_Dark_Templar 1 11136
11136
