Protoss_Gateway 2 4097
Protoss_Zealot 12 9971
Protoss_Assimilator 1 4650
Protoss_Cybernetics_Core 1 6392
Protoss_Dragoon 1 7231
Protoss_Stargate 1 7863
Protoss_Citadel_of_Adun 1 8355
Protoss_Corsair 1 8396
Protoss_Forge 1 9618
Protoss_Templar_Archives 1 10699
10699
