Protoss_Nexus 1 5760
Protoss_Forge 1 4243
Protoss_Gateway 3 10819
Protoss_Photon_Cannon 8 10489
Protoss_Assimilator 2 8001
Protoss_Zealot 4 8611
Protoss_Cybernetics_Core 1 7768
Protoss_Citadel_of_Adun 1 8808
Protoss_Templar_Archives 1 10278
Protoss_High_Templar 2 11036
Protoss_Ground_Weapons_1 1 9916
11036
