Protoss_Gateway 3 7942
Protoss_Zealot 18 10471
Protoss_Assimilator 1 4503
Protoss_Cybernetics_Core 1 5503
Protoss_Citadel_of_Adun 1 6839
Protoss_Dragoon 1 6646
Protoss_Templar_Archives 1 10014
10471
