Protoss_Forge 1 2896
Protoss_Nexus 1 5973
Protoss_Photon_Cannon 1 4613
Protoss_Gateway 6 9940
Protoss_Assimilator 1 5661
Protoss_Zealot 10 10671
Protoss_Cybernetics_Core 1 6426
Protoss_Stargate 1 7928
Protoss_Dragoon 3 10723
Protoss_Corsair 2 8708
Protoss_Citadel_of_Adun 1 10180
10723
