Protoss_Forge 2 10908
Protoss_Photon_Cannon 4 9131
Protoss_Nexus 1 6623
Protoss_Gateway 4 10967
Protoss_Assimilator 2 7853
Protoss_Zealot 1 6811
Protoss_Cybernetics_Core 1 7608
Protoss_Dragoon 2 10151
Protoss_Stargate 1 8998
Protoss_Robotics_Facility 2 11098
Protoss_Scout 1 10476
11098
