Protoss_Forge 1 3033
Protoss_Nexus 1 6118
Protoss_Photon_Cannon 4 10808
Protoss_Gateway 3 8780
Protoss_Assimilator 2 8596
Protoss_Zealot 7 10213
Protoss_Cybernetics_Core 1 7318
Protoss_Citadel_of_Adun 1 8413
Protoss_Templar_Archives 1 9840
Protoss_High_Templar 3 11055
11055
