Protoss_Nexus 1 5760
Protoss_Gateway 1 4691
Protoss_Forge 1 4568
Protoss_Photon_Cannon 7 11106
Protoss_Assimilator 1 5434
Protoss_Zealot 7 10933
Protoss_Cybernetics_Core 1 6718
Protoss_Citadel_of_Adun 1 7791
Protoss_Templar_Archives 1 10708
11106
