Protoss_Gateway 2 3973
Protoss_Zealot 9 9226
Protoss_Assimilator 2 10318
Protoss_Forge 1 6430
Protoss_Cybernetics_Core 1 7430
Protoss_Citadel_of_Adun 1 8484
Protoss_Nexus 1 10717
Protoss_Photon_Cannon 3 10947
Protoss_Templar_Archives 1 10103
Protoss_High_Templar 2 10896
10947
