Protoss_Forge 1 3363
Protoss_Photon_Cannon 5 10943
Protoss_Nexus 1 7008
Protoss_Gateway 4 9608
Protoss_Assimilator 2 8954
Protoss_Zealot 9 10816
Protoss_Cybernetics_Core 1 8170
Protoss_Citadel_of_Adun 1 9911
Protoss_Dragoon 1 10391
10943
