Protoss_Nexus 1 5933
Protoss_Gateway 3 10303
Protoss_Forge 1 4753
Protoss_Photon_Cannon 6 10483
Protoss_Zealot 7 9866
Protoss_Assimilator 2 9376
Protoss_Cybernetics_Core 1 8336
Protoss_Stargate 1 9930
Protoss_Corsair 1 10351
Protoss_Dragoon 2 11071
Protoss_Citadel_of_Adun 1 11256
11256
