Protoss_Forge 1 2996
Protoss_Photon_Cannon 2 5783
Protoss_Nexus 1 6720
Protoss_Gateway 6 10381
Protoss_Assimilator 1 5720
Protoss_Cybernetics_Core 1 6926
Protoss_Zealot 12 10841
Protoss_Citadel_of_Adun 1 8125
Protoss_Dragoon 1 8756
Protoss_Templar_Archives 1 10878
10878
