Protoss_Nexus 1 5725
Protoss_Gateway 4 8782
Protoss_Assimilator 1 4477
Protoss_Forge 1 4788
Protoss_Cybernetics_Core 1 5878
Protoss_Photon_Cannon 1 5857
Protoss_Zealot 15 10815
Protoss_Citadel_of_Adun 1 7072
Protoss_Templar_Archives 1 9974
Protoss_Ground_Weapons_1 1 8913
Protoss_Robotics_Facility 1 11401
Protoss_High_Templar 2 11081
11401
