Protoss_Forge 1 3482
Protoss_Photon_Cannon 4 7679
Protoss_Nexus 1 6991
Protoss_Gateway 3 10048
Protoss_Zealot 7 10941
Protoss_Assimilator 2 9713
Protoss_Cybernetics_Core 1 9709
Protoss_Citadel_of_Adun 1 10874
Protoss_Dragoon 2 11096
11096
