Protoss_Nexus 1 5688
Protoss_Gateway 4 8821
Protoss_Forge 1 4648
Protoss_Assimilator 2 9575
Protoss_Photon_Cannon 1 5627
Protoss_Zealot 14 10717
Protoss_Cybernetics_Core 1 6402
Protoss_Citadel_of_Adun 1 7518
Protoss_Templar_Archives 1 9535
Protoss_High_Templar 2 10523
Protoss_Ground_Weapons_1 1 9557
Protoss_Robotics_Facility 1 11854
11854
