Protoss_Gateway 1 3463
Protoss_Assimilator 2 4723
Protoss_Zealot 7 10393
Protoss_Cybernetics_Core 1 5998
Protoss_Stargate 1 7504
Protoss_Dragoon 1 7161
Protoss_Citadel_of_Adun 1 7601
Protoss_Forge 1 10033
10393
