Protoss_Nexus 1 5667
Protoss_Gateway 2 9888
Protoss_Forge 1 4683
Protoss_Photon_Cannon 5 11093
Protoss_Assimilator 2 6673
Protoss_Cybernetics_Core 1 6671
Protoss_Zealot 5 9963
Protoss_Stargate 2 9299
Protoss_Citadel_of_Adun 1 8115
Protoss_Corsair 6 10633
Protoss_Shield_Battery 1 10356
11093
