Protoss_Nexus 1 5916
Protoss_Forge 1 4516
Protoss_Photon_Cannon 5 7178
Protoss_Gateway 4 10833
Protoss_Assimilator 2 8932
Protoss_Zealot 8 10871
Protoss_Cybernetics_Core 1 9340
Protoss_Stargate 1 10578
Protoss_Citadel_of_Adun 1 10658
10871
