Protoss_Forge 1 3150
Protoss_Nexus 1 6280
Protoss_Gateway 4 9728
Protoss_Photon_Cannon 2 5731
Protoss_Assimilator 2 8073
Protoss_Cybernetics_Core 1 6751
Protoss_Zealot 7 10911
Protoss_Citadel_of_Adun 1 8345
Protoss_Templar_Archives 1 9410
Protoss_High_Templar 4 10831
Protoss_Archon 1 10345
10911
