Protoss_Nexus 1 5853
Protoss_Gateway 3 8208
Protoss_Assimilator 2 8793
Protoss_Cybernetics_Core 1 6108
Protoss_Forge 1 5863
Protoss_Photon_Cannon 1 6873
Protoss_Citadel_of_Adun 1 7503
Protoss_Zealot 13 10661
Protoss_Templar_Archives 1 10062
Protoss_Ground_Weapons_1 1 9586
10661
