Protoss_Nexus 1 5701
Protoss_Forge 1 4239
Protoss_Photon_Cannon 7 10863
Protoss_Gateway 2 10564
Protoss_Assimilator 2 8552
Protoss_Zealot 7 10275
Protoss_Cybernetics_Core 1 7780
Protoss_Stargate 1 9032
Protoss_Citadel_of_Adun 1 9699
Protoss_Corsair 2 10875
10875
