Protoss_Forge 1 3328
Protoss_Photon_Cannon 5 10950
Protoss_Nexus 1 6783
Protoss_Gateway 2 9254
Protoss_Assimilator 2 9007
Protoss_Zealot 5 9311
Protoss_Cybernetics_Core 1 7088
Protoss_Citadel_of_Adun 1 8296
Protoss_Templar_Archives 1 9578
Protoss_Dark_Templar 2 10451
10950
