Protoss_Forge 2 10043
Protoss_Nexus 1 6218
Protoss_Photon_Cannon 1 5188
Protoss_Gateway 4 8908
Protoss_Assimilator 2 7073
Protoss_Zealot 13 10896
Protoss_Cybernetics_Core 1 7185
Protoss_Citadel_of_Adun 1 8204
10896
