Protoss_Forge 1 3273
Protoss_Nexus 1 6113
Protoss_Photon_Cannon 6 10928
Protoss_Gateway 2 9850
Protoss_Assimilator 2 8691
Protoss_Zealot 3 9155
Protoss_Cybernetics_Core 1 7646
Protoss_Dragoon 1 8473
Protoss_Citadel_of_Adun 1 8769
Protoss_Templar_Archives 1 9776
Protoss_Dark_Templar 1 10515
Protoss_High_Templar 1 10589
10928
