Protoss_Forge 1 3912
Protoss_Nexus 1 6368
Protoss_Photon_Cannon 5 10708
Protoss_Gateway 3 10803
Protoss_Assimilator 2 7954
Protoss_Zealot 3 9083
Protoss_Cybernetics_Core 1 7612
Protoss_Dragoon 1 8571
Protoss_Citadel_of_Adun 1 9098
10803
