Protoss_Assimilator 2 5740
Protoss_Gateway 1 3764
Protoss_Cybernetics_Core 1 4791
Protoss_Stargate 3 10986
Protoss_Corsair 10 10670
Protoss_Dragoon 1 6726
Protoss_Forge 1 8354
Protoss_Shield_Battery 1 8195
Protoss_Photon_Cannon 1 9288
Protoss_Air_Weapons_1 1 8366
10986
