Protoss_Forge 1 3285
Protoss_Photon_Cannon 4 10328
Protoss_Nexus 1 7043
Protoss_Gateway 2 9728
Protoss_Assimilator 2 6924
Protoss_Cybernetics_Core 1 6906
Protoss_Zealot 2 8601
Protoss_Dragoon 1 7761
Protoss_Stargate 1 8443
Protoss_Citadel_of_Adun 1 8838
Protoss_Corsair 2 9458
Protoss_Templar_Archives 1 10083
Protoss_Dark_Templar 2 11171
11171
