Protoss_Forge 1 3049
Protoss_Nexus 1 6131
Protoss_Photon_Cannon 3 9611
Protoss_Gateway 5 10351
Protoss_Assimilator 2 9175
Protoss_Zealot 7 10225
Protoss_Cybernetics_Core 1 8383
Protoss_Dragoon 1 9713
Protoss_Citadel_of_Adun 1 10134
10351
