Protoss_Forge 1 3112
Protoss_Photon_Cannon 4 9269
Protoss_Nexus 1 7354
Protoss_Gateway 3 10820
Protoss_Assimilator 2 9263
Protoss_Cybernetics_Core 1 7299
Protoss_Zealot 7 9897
Protoss_Citadel_of_Adun 1 8335
Protoss_Templar_Archives 1 10213
Protoss_High_Templar 2 10983
10983
