Protoss_Forge 1 3152
Protoss_Nexus 1 6208
Protoss_Gateway 2 10680
Protoss_Assimilator 2 7228
Protoss_Photon_Cannon 4 8963
Protoss_Cybernetics_Core 1 6776
Protoss_Zealot 3 10281
Protoss_Dragoon 1 7851
Protoss_Citadel_of_Adun 1 8170
10680
