Protoss_Gateway 2 3829
Protoss_Zealot 7 8396
Protoss_Nexus 1 8168
Protoss_Assimilator 2 10448
Protoss_Forge 1 6813
Protoss_Cybernetics_Core 1 7608
Protoss_Stargate 1 8975
Protoss_Photon_Cannon 3 10728
Protoss_Corsair 2 10561
Protoss_Citadel_of_Adun 1 10048
10728
