Protoss_Forge 2 10894
Protoss_Nexus 1 6403
Protoss_Photon_Cannon 3 10580
Protoss_Assimilator 1 5300
Protoss_Gateway 4 10699
Protoss_Zealot 7 9920
Protoss_Cybernetics_Core 1 7390
Protoss_Dragoon 1 8188
Protoss_Citadel_of_Adun 1 8493
Protoss_Ground_Weapons_1 1 9711
10894
