Protoss_Nexus 1 5801
Protoss_Forge 2 10168
Protoss_Gateway 3 9594
Protoss_Photon_Cannon 8 11193
Protoss_Assimilator 2 7267
Protoss_Cybernetics_Core 1 6939
Protoss_Zealot 3 9401
Protoss_Stargate 1 8253
Protoss_Dragoon 1 7817
Protoss_Citadel_of_Adun 1 8735
Protoss_Corsair 2 9525
Protoss_Templar_Archives 1 9751
Protoss_Robotics_Facility 1 11200
Protoss_Dark_Templar 3 10817
11200
