Protoss_Forge 1 3413
Protoss_Nexus 1 6124
Protoss_Photon_Cannon 8 10794
Protoss_Gateway 3 10678
Protoss_Assimilator 2 8150
Protoss_Cybernetics_Core 1 6988
Protoss_Zealot 2 8571
Protoss_Dragoon 1 7901
Protoss_Citadel_of_Adun 1 8398
Protoss_Templar_Archives 1 9958
Protoss_High_Templar 2 10916
10916
