Protoss_Forge 1 3576
Protoss_Nexus 1 6145
Protoss_Photon_Cannon 3 10160
Protoss_Gateway 3 9086
Protoss_Assimilator 2 7338
Protoss_Cybernetics_Core 1 6541
Protoss_Zealot 5 10363
Protoss_Citadel_of_Adun 1 7607
Protoss_Dragoon 1 7723
Protoss_Templar_Archives 1 8879
Protoss_Dark_Templar 1 9785
Protoss_High_Templar 2 9851
Protoss_Archon 1 10028
Protoss_Robotics_Facility 1 11541
11541
