Protoss_Forge 2 4273
Protoss_Nexus 1 6028
Protoss_Photon_Cannon 3 6478
Protoss_Gateway 4 11087
Protoss_Assimilator 1 7505
Protoss_Zealot 8 10548
Protoss_Cybernetics_Core 1 8790
Protoss_Citadel_of_Adun 1 9987
11087
