Protoss_Gateway 1 3254
Protoss_Assimilator 1 3581
Protoss_Zealot 3 5903
Protoss_Cybernetics_Core 1 5433
Protoss_Stargate 1 6978
Protoss_Dragoon 1 6791
Protoss_Corsair 2 8083
8083
