Protoss_Forge 1 3851
Protoss_Nexus 1 6380
Protoss_Photon_Cannon 4 9573
Protoss_Gateway 2 9233
Protoss_Assimilator 2 7160
Protoss_Cybernetics_Core 1 7010
Protoss_Zealot 1 6795
Protoss_Stargate 1 8268
Protoss_Citadel_of_Adun 1 8309
Protoss_Templar_Archives 1 9327
Protoss_Corsair 3 10437
Protoss_Dark_Templar 4 11051
Protoss_Robotics_Facility 1 11277
11277
