Protoss_Forge 1 3075
Protoss_Nexus 1 6182
Protoss_Gateway 4 10273
Protoss_Assimilator 2 10134
Protoss_Photon_Cannon 1 6171
Protoss_Zealot 9 10309
Protoss_Cybernetics_Core 1 7239
Protoss_Dragoon 1 7987
Protoss_Citadel_of_Adun 1 8281
Protoss_Templar_Archives 1 10552
10552
