Protoss_Forge 1 3288
Protoss_Photon_Cannon 2 9576
Protoss_Nexus 1 6779
Protoss_Gateway 3 10073
Protoss_Assimilator 2 7059
Protoss_Cybernetics_Core 1 6887
Protoss_Zealot 1 6755
Protoss_Stargate 1 8144
Protoss_Citadel_of_Adun 1 8541
Protoss_Corsair 2 9161
Protoss_Templar_Archives 1 9636
Protoss_Dark_Templar 1 10507
Protoss_High_Templar 2 10931
Protoss_Robotics_Facility 1 11890
11890
