Protoss_Forge 1 2998
Protoss_Photon_Cannon 3 10503
Protoss_Nexus 1 6867
Protoss_Gateway 3 9788
Protoss_Assimilator 2 8116
Protoss_Zealot 9 10556
Protoss_Cybernetics_Core 1 7388
Protoss_Citadel_of_Adun 1 8513
Protoss_Templar_Archives 1 9978
10556
