Protoss_Forge 1 3236
Protoss_Nexus 1 6380
Protoss_Gateway 4 10924
Protoss_Photon_Cannon 2 10460
Protoss_Assimilator 2 9139
Protoss_Zealot 10 10726
Protoss_Cybernetics_Core 1 6638
Protoss_Citadel_of_Adun 1 7713
Protoss_Dragoon 1 9521
Protoss_Templar_Archives 1 10984
Protoss_Ground_Weapons_1 1 9726
10984
