Protoss_Gateway 1 1940
Protoss_Assimilator 1 2787
Protoss_Zealot 5 7151
Protoss_Cybernetics_Core 1 3438
Protoss_Stargate 1 5023
Protoss_Citadel_of_Adun 1 5516
Protoss_Corsair 1 6261
7151
