Protoss_Forge 1 2845
Protoss_Photon_Cannon 3 5881
Protoss_Nexus 1 6935
Protoss_Assimilator 2 10153
Protoss_Gateway 3 8985
Protoss_Zealot 11 10943
Protoss_Cybernetics_Core 1 8383
Protoss_Citadel_of_Adun 1 9408
Protoss_Dragoon 1 9227
Protoss_Templar_Archives 1 10853
10943
