Protoss_Forge 1 2974
Protoss_Photon_Cannon 2 5379
Protoss_Nexus 1 6676
Protoss_Gateway 3 9793
Protoss_Assimilator 2 7856
Protoss_Zealot 7 10871
Protoss_Cybernetics_Core 1 7431
Protoss_Stargate 1 9185
Protoss_Citadel_of_Adun 1 9477
Protoss_Corsair 2 10227
Protoss_Templar_Archives 1 10477
10871
