Protoss_Gateway 3 11214
Protoss_Forge 1 3856
Protoss_Zealot 9 10766
Protoss_Photon_Cannon 2 8137
Protoss_Nexus 1 7864
Protoss_Assimilator 2 8024
Protoss_Cybernetics_Core 1 7403
Protoss_Stargate 1 8888
Protoss_Corsair 2 10156
Protoss_Citadel_of_Adun 1 10381
11214
