Protoss_Gateway 2 4925
Protoss_Assimilator 1 3348
Protoss_Cybernetics_Core 1 4478
Protoss_Stargate 1 6030
Protoss_Zealot 10 10906
Protoss_Citadel_of_Adun 1 6814
Protoss_Corsair 1 6551
Protoss_Templar_Archives 1 8008
Protoss_Robotics_Facility 1 9129
Protoss_Dark_Templar 2 8791
Protoss_Forge 1 8658
Protoss_Nexus 1 11792
Protoss_Photon_Cannon 1 10583
11792
