Protoss_Forge 1 3144
Protoss_Photon_Cannon 4 10995
Protoss_Nexus 1 6788
Protoss_Gateway 4 9977
Protoss_Assimilator 2 8497
Protoss_Cybernetics_Core 1 7232
Protoss_Zealot 2 9113
Protoss_Citadel_of_Adun 1 8608
Protoss_Templar_Archives 1 9775
Protoss_High_Templar 4 10931
10995
