Protoss_Forge 1 3210
Protoss_Nexus 1 6378
Protoss_Photon_Cannon 2 10097
Protoss_Gateway 1 5840
Protoss_Assimilator 2 7952
Protoss_Cybernetics_Core 1 7174
Protoss_Zealot 3 9336
Protoss_Robotics_Facility 1 8843
Protoss_Stargate 1 8893
Protoss_Dragoon 1 8736
Protoss_Shuttle 1 9826
Protoss_Corsair 3 10681
Protoss_Robotics_Support_Bay 1 9688
Protoss_Reaver 1 11391
11391
