Protoss_Forge 1 3296
Protoss_Nexus 1 6233
Protoss_Gateway 3 9849
Protoss_Assimilator 2 6849
Protoss_Photon_Cannon 4 10926
Protoss_Cybernetics_Core 1 6559
Protoss_Zealot 1 6521
Protoss_Dragoon 1 7339
Protoss_Stargate 1 7930
Protoss_Citadel_of_Adun 1 8317
Protoss_Corsair 2 8987
10926
