Protoss_Gateway 2 10662
Protoss_Assimilator 1 3511
Protoss_Zealot 2 5196
Protoss_Cybernetics_Core 1 5336
Protoss_Stargate 1 6725
Protoss_Dragoon 1 6656
Protoss_Corsair 1 7151
Protoss_Citadel_of_Adun 1 7808
Protoss_Forge 1 8016
Protoss_Templar_Archives 1 9458
Protoss_Photon_Cannon 1 9563
Protoss_Nexus 1 12257
Protoss_Dark_Templar 1 10591
12257
