Protoss_Forge 1 3158
Protoss_Nexus 1 6568
Protoss_Gateway 4 8963
Protoss_Photon_Cannon 1 5303
Protoss_Assimilator 2 8934
Protoss_Zealot 11 10246
Protoss_Cybernetics_Core 1 6945
Protoss_Citadel_of_Adun 1 8080
Protoss_Templar_Archives 1 10432
Protoss_Ground_Weapons_1 1 9981
10432
