Protoss_Forge 1 3105
Protoss_Photon_Cannon 2 9315
Protoss_Nexus 1 6612
Protoss_Gateway 3 10723
Protoss_Assimilator 2 9379
Protoss_Zealot 3 10026
Protoss_Cybernetics_Core 1 8748
Protoss_Stargate 1 10227
Protoss_Citadel_of_Adun 1 10302
Protoss_Templar_Archives 1 11383
11383
