Protoss_Gateway 2 3914
Protoss_Zealot 9 10709
Protoss_Nexus 2 8967
Protoss_Forge 1 7467
Protoss_Photon_Cannon 2 8914
Protoss_Assimilator 2 9939
Protoss_Cybernetics_Core 1 9967
Protoss_Stargate 1 11321
11321
