Protoss_Forge 1 3465
Protoss_Photon_Cannon 2 5228
Protoss_Nexus 1 6425
Protoss_Gateway 1 5789
Protoss_Assimilator 2 7375
Protoss_Zealot 4 10777
Protoss_Cybernetics_Core 1 7067
Protoss_Dragoon 1 7903
Protoss_Stargate 1 8609
10777
