Protoss_Forge 1 3604
Protoss_Nexus 1 6275
Protoss_Photon_Cannon 2 10159
Protoss_Gateway 2 10733
Protoss_Assimilator 2 8161
Protoss_Zealot 4 9625
Protoss_Cybernetics_Core 1 7744
Protoss_Dragoon 1 8511
Protoss_Stargate 1 9096
Protoss_Citadel_of_Adun 1 9522
Protoss_Corsair 2 10385
Protoss_Templar_Archives 1 10656
10733
