Protoss_Nexus 1 5993
Protoss_Forge 1 4363
Protoss_Gateway 6 11162
Protoss_Photon_Cannon 2 10962
Protoss_Assimilator 2 7714
Protoss_Zealot 10 10863
Protoss_Cybernetics_Core 1 7290
Protoss_Citadel_of_Adun 1 8569
Protoss_Templar_Archives 1 10135
Protoss_Dark_Templar 1 11091
11162
