Protoss_Gateway 2 4037
Protoss_Zealot 16 10623
Protoss_Assimilator 1 4343
Protoss_Cybernetics_Core 1 6023
Protoss_Stargate 1 7258
Protoss_Dragoon 1 6826
Protoss_Corsair 1 7736
Protoss_Nexus 1 11888
Protoss_Forge 1 10644
11888
