Protoss_Gateway 1 3498
Protoss_Assimilator 1 3520
Protoss_Zealot 2 5376
Protoss_Cybernetics_Core 1 5500
Protoss_Citadel_of_Adun 1 6758
Protoss_Dragoon 1 6661
Protoss_Forge 1 7179
Protoss_Templar_Archives 1 7918
Protoss_Photon_Cannon 3 11073
Protoss_High_Templar 3 10799
Protoss_Nexus 1 12235
12235
