Protoss_Gateway 3 10288
Protoss_Assimilator 1 3423
Protoss_Zealot 3 7980
Protoss_Cybernetics_Core 1 5166
Protoss_Dragoon 7 11036
Protoss_Citadel_of_Adun 1 7191
Protoss_Robotics_Facility 1 7929
Protoss_Shuttle 1 8736
Protoss_Robotics_Support_Bay 1 8039
Protoss_Reaver 1 9878
11036
