Protoss_Gateway 2 3573
Protoss_Zealot 11 7273
Protoss_Nexus 1 9819
Protoss_Assimilator 2 9782
Protoss_Cybernetics_Core 1 9111
Protoss_Forge 1 9265
Protoss_Stargate 1 10433
Protoss_Dragoon 1 10197
Protoss_Photon_Cannon 2 10699
Protoss_Corsair 1 10859
10859
