Protoss_Nexus 2 12129
Protoss_Gateway 3 5319
Protoss_Zealot 9 9293
Protoss_Assimilator 2 8317
Protoss_Forge 1 6868
Protoss_Cybernetics_Core 1 8102
Protoss_Photon_Cannon 4 11028
Protoss_Citadel_of_Adun 1 10366
12129
