Protoss_Forge 1 3015
Protoss_Photon_Cannon 5 11018
Protoss_Nexus 2 11073
Protoss_Gateway 1 5793
Protoss_Zealot 5 10368
Protoss_Cybernetics_Core 1 7060
Protoss_Assimilator 2 9363
Protoss_Citadel_of_Adun 1 10130
Protoss_Stargate 1 11452
11452
