Protoss_Forge 1 3482
Protoss_Nexus 1 6275
Protoss_Gateway 4 8903
Protoss_Assimilator 2 9671
Protoss_Photon_Cannon 1 5734
Protoss_Zealot 16 10731
Protoss_Cybernetics_Core 1 6889
Protoss_Citadel_of_Adun 1 7940
Protoss_Ground_Weapons_1 1 9871
10731
