Protoss_Forge 1 3139
Protoss_Nexus 1 6401
Protoss_Gateway 2 10261
Protoss_Assimilator 2 7210
Protoss_Photon_Cannon 3 10414
Protoss_Cybernetics_Core 1 6879
Protoss_Zealot 2 10709
Protoss_Stargate 1 8274
Protoss_Robotics_Facility 1 9608
Protoss_Corsair 2 9407
Protoss_Dragoon 1 9701
Protoss_Robotics_Support_Bay 1 9759
Protoss_Reaver 1 11313
11313
