Protoss_Forge 1 3220
Protoss_Photon_Cannon 2 5352
Protoss_Nexus 1 6598
Protoss_Gateway 4 9786
Protoss_Assimilator 2 10348
Protoss_Zealot 9 10776
Protoss_Cybernetics_Core 1 7160
Protoss_Citadel_of_Adun 1 8262
Protoss_Dragoon 1 8988
Protoss_Templar_Archives 1 10811
10811
