Protoss_Nexus 1 6073
Protoss_Forge 1 4683
Protoss_Gateway 3 9043
Protoss_Photon_Cannon 4 10048
Protoss_Assimilator 2 7553
Protoss_Cybernetics_Core 1 7012
Protoss_Zealot 6 10156
Protoss_Stargate 1 8358
Protoss_Citadel_of_Adun 1 8569
Protoss_Corsair 3 10636
Protoss_Templar_Archives 1 10820
10820
