Protoss_Forge 1 3488
Protoss_Nexus 1 6313
Protoss_Photon_Cannon 4 11200
Protoss_Gateway 3 9668
Protoss_Assimilator 2 9629
Protoss_Zealot 8 10223
Protoss_Cybernetics_Core 1 7421
Protoss_Citadel_of_Adun 1 8478
Protoss_Dragoon 1 8241
Protoss_Templar_Archives 1 10268
11200
