Protoss_Forge 1 3152
Protoss_Nexus 2 12704
Protoss_Gateway 4 9259
Protoss_Photon_Cannon 1 5383
Protoss_Assimilator 2 8973
Protoss_Cybernetics_Core 1 6701
Protoss_Zealot 8 9986
Protoss_Dragoon 1 7521
Protoss_Citadel_of_Adun 1 8188
Protoss_Templar_Archives 1 10014
Protoss_High_Templar 2 11136
Protoss_Ground_Weapons_1 1 9961
12704
