Protoss_Forge 1 3365
Protoss_Nexus 1 6467
Protoss_Photon_Cannon 5 10803
Protoss_Gateway 2 10658
Protoss_Assimilator 2 7735
Protoss_Zealot 2 10177
Protoss_Cybernetics_Core 1 6890
Protoss_Stargate 1 8271
Protoss_Robotics_Facility 1 9325
Protoss_Corsair 3 9957
Protoss_Citadel_of_Adun 1 9632
Protoss_Templar_Archives 1 10802
10803
