Protoss_Gateway 2 7332
Protoss_Zealot 12 9692
Protoss_Assimilator 1 4043
Protoss_Cybernetics_Core 1 5395
Protoss_Dragoon 1 6421
Protoss_Citadel_of_Adun 1 6834
Protoss_Templar_Archives 1 9726
Protoss_Dark_Templar 2 10886
Protoss_Forge 1 10763
10886
