Protoss_Forge 1 2855
Protoss_Photon_Cannon 6 7959
Protoss_Nexus 1 8263
Protoss_Gateway 1 7268
Protoss_Assimilator 2 9535
Protoss_Zealot 4 9743
Protoss_Cybernetics_Core 1 8709
Protoss_Stargate 1 10076
Protoss_Citadel_of_Adun 1 10715
10715
