Protoss_Forge 1 3197
Protoss_Photon_Cannon 5 10556
Protoss_Nexus 1 6701
Protoss_Gateway 4 11211
Protoss_Assimilator 2 7846
Protoss_Zealot 5 9441
Protoss_Cybernetics_Core 1 7211
Protoss_Citadel_of_Adun 1 8226
Protoss_Templar_Archives 1 9296
Protoss_High_Templar 5 11107
11211
