Protoss_Forge 1 3071
Protoss_Photon_Cannon 2 10658
Protoss_Nexus 1 6603
Protoss_Gateway 5 11291
Protoss_Assimilator 2 6914
Protoss_Cybernetics_Core 1 6665
Protoss_Zealot 11 10739
Protoss_Stargate 1 8092
Protoss_Corsair 2 9159
Protoss_Citadel_of_Adun 1 9255
Protoss_Shield_Battery 1 10420
11291
