Protoss_Forge 1 3449
Protoss_Photon_Cannon 4 9427
Protoss_Nexus 1 6601
Protoss_Gateway 3 11407
Protoss_Zealot 6 10807
Protoss_Assimilator 2 7747
Protoss_Cybernetics_Core 1 8297
Protoss_Stargate 1 9601
Protoss_Citadel_of_Adun 1 9948
Protoss_Corsair 1 10023
Protoss_Robotics_Facility 1 11520
11520
