Protoss_Forge 1 2859
Protoss_Nexus 1 6019
Protoss_Photon_Cannon 4 10896
Protoss_Gateway 4 8866
Protoss_Assimilator 2 8885
Protoss_Cybernetics_Core 1 7136
Protoss_Zealot 11 10199
Protoss_Citadel_of_Adun 1 8175
Protoss_Dragoon 1 7985
Protoss_Templar_Archives 1 9892
Protoss_High_Templar 2 10703
10896
