Protoss_Forge 1 2831
Protoss_Nexus 1 5968
Protoss_Photon_Cannon 9 10349
Protoss_Gateway 1 6068
Protoss_Assimilator 2 7921
Protoss_Zealot 4 9635
Protoss_Cybernetics_Core 1 7545
Protoss_Dragoon 1 10477
10477
