Protoss_Gateway 2 3639
Protoss_Zealot 9 9983
Protoss_Assimilator 2 7218
Protoss_Nexus 1 8491
Protoss_Forge 1 6958
Protoss_Cybernetics_Core 1 8507
Protoss_Photon_Cannon 2 8955
Protoss_Citadel_of_Adun 1 10081
Protoss_Templar_Archives 1 11113
11113
