Protoss_Gateway 3 11366
Protoss_Assimilator 1 3502
Protoss_Cybernetics_Core 1 4595
Protoss_Zealot 7 10389
Protoss_Stargate 1 6072
Protoss_Corsair 2 7295
Protoss_Citadel_of_Adun 1 7389
11366
