Protoss_Nexus 1 6129
Protoss_Forge 1 4505
Protoss_Gateway 3 9009
Protoss_Photon_Cannon 1 5447
Protoss_Assimilator 2 7221
Protoss_Cybernetics_Core 1 6585
Protoss_Zealot 2 7741
Protoss_Stargate 1 7825
Protoss_Citadel_of_Adun 1 8027
Protoss_Corsair 2 8873
Protoss_Templar_Archives 1 9162
Protoss_Dark_Templar 3 9923
Protoss_Robotics_Facility 1 11183
11183
