Protoss_Gateway 2 3534
Protoss_Zealot 5 9523
Protoss_Assimilator 1 4842
Protoss_Cybernetics_Core 1 5821
Protoss_Dragoon 1 6563
Protoss_Forge 1 6619
Protoss_Robotics_Facility 1 8033
Protoss_Photon_Cannon 3 10331
Protoss_Shuttle 1 8835
Protoss_Robotics_Support_Bay 1 8249
Protoss_Reaver 1 9977
Protoss_Stargate 1 10050
Protoss_Corsair 1 10459
Protoss_Scarab 1 9931
10459
