Protoss_Forge 1 3333
Protoss_Photon_Cannon 3 11097
Protoss_Nexus 1 6679
Protoss_Gateway 3 9479
Protoss_Assimilator 2 7996
Protoss_Zealot 9 10221
Protoss_Cybernetics_Core 1 6705
Protoss_Citadel_of_Adun 1 7932
Protoss_Templar_Archives 1 9195
Protoss_Dark_Templar 1 11055
Protoss_High_Templar 2 11063
Protoss_Ground_Weapons_1 1 9993
11097
