Protoss_Forge 1 3504
Protoss_Photon_Cannon 1 4522
Protoss_Nexus 1 6361
Protoss_Gateway 5 9338
Protoss_Assimilator 2 9296
Protoss_Cybernetics_Core 1 6757
Protoss_Zealot 14 10903
Protoss_Citadel_of_Adun 1 7880
Protoss_Dragoon 1 8035
Protoss_Templar_Archives 1 10813
Protoss_Ground_Weapons_1 1 9811
10903
