Protoss_Forge 1 3269
Protoss_Nexus 1 6063
Protoss_Photon_Cannon 3 10894
Protoss_Gateway 4 11254
Protoss_Assimilator 2 9150
Protoss_Zealot 12 10425
Protoss_Cybernetics_Core 1 8331
Protoss_Citadel_of_Adun 1 9395
Protoss_Templar_Archives 1 11049
Protoss_Robotics_Facility 1 11661
11661
