Protoss_Forge 1 4057
Protoss_Nexus 1 6503
Protoss_Photon_Cannon 7 11033
Protoss_Gateway 1 6884
Protoss_Assimilator 2 7835
Protoss_Cybernetics_Core 1 7889
Protoss_Zealot 4 10603
Protoss_Stargate 1 9187
Protoss_Citadel_of_Adun 1 10202
Protoss_Corsair 2 10419
Protoss_Templar_Archives 1 11271
11271
