Protoss_Forge 1 3438
Protoss_Nexus 1 6313
Protoss_Photon_Cannon 2 6433
Protoss_Gateway 4 10184
Protoss_Assimilator 2 8497
Protoss_Zealot 7 10636
Protoss_Cybernetics_Core 1 7846
Protoss_Stargate 1 9145
Protoss_Citadel_of_Adun 1 9479
Protoss_Corsair 3 10770
Protoss_Templar_Archives 1 10835
10835
