Protoss_Gateway 1 3523
Protoss_Assimilator 1 3613
Protoss_Zealot 4 8176
Protoss_Cybernetics_Core 1 5473
Protoss_Stargate 1 6748
Protoss_Dragoon 1 6671
Protoss_Corsair 1 7166
Protoss_Citadel_of_Adun 1 8160
Protoss_Templar_Archives 1 9218
Protoss_Nexus 1 11607
Protoss_Dark_Templar 2 10898
11607
