Protoss_Nexus 1 5957
Protoss_Forge 1 4368
Protoss_Photon_Cannon 3 6108
Protoss_Gateway 6 10075
Protoss_Assimilator 1 6330
Protoss_Cybernetics_Core 1 7431
Protoss_Zealot 9 10636
Protoss_Citadel_of_Adun 1 8539
Protoss_Stargate 1 9953
Protoss_Templar_Archives 1 11208
11208
