Protoss_Forge 1 2969
Protoss_Photon_Cannon 9 10908
Protoss_Nexus 1 6843
Protoss_Gateway 3 10367
Protoss_Assimilator 2 9098
Protoss_Cybernetics_Core 1 7175
Protoss_Zealot 3 9061
Protoss_Citadel_of_Adun 1 8182
Protoss_Templar_Archives 1 9822
Protoss_High_Templar 2 11146
11146
