Protoss_Gateway 2 3763
Protoss_Zealot 12 10536
Protoss_Assimilator 1 5608
Protoss_Cybernetics_Core 1 7045
Protoss_Dragoon 2 8946
Protoss_Citadel_of_Adun 1 8534
Protoss_Forge 1 8236
10536
