Protoss_Forge 2 4634
Protoss_Nexus 1 6011
Protoss_Gateway 4 11390
Protoss_Photon_Cannon 5 10568
Protoss_Assimilator 2 7753
Protoss_Zealot 5 10821
Protoss_Cybernetics_Core 1 6976
Protoss_Citadel_of_Adun 1 8218
Protoss_Templar_Archives 1 9335
Protoss_High_Templar 3 11046
Protoss_Dark_Templar 1 10351
Protoss_Robotics_Facility 1 11471
Protoss_Ground_Weapons_1 1 9901
11471
