Protoss_Nexus 2 12774
Protoss_Forge 1 4183
Protoss_Photon_Cannon 2 5448
Protoss_Gateway 1 5923
Protoss_Assimilator 2 7148
Protoss_Cybernetics_Core 1 7118
Protoss_Robotics_Facility 1 8683
Protoss_Stargate 1 9123
Protoss_Shuttle 1 9486
Protoss_Robotics_Support_Bay 1 8914
Protoss_Dragoon 1 9521
Protoss_Corsair 1 9546
Protoss_Reaver 2 11680
12774
