Protoss_Gateway 2 3933
Protoss_Zealot 9 8353
Protoss_Nexus 1 8638
Protoss_Assimilator 2 10217
Protoss_Cybernetics_Core 1 7693
Protoss_Forge 1 8089
Protoss_Photon_Cannon 1 9029
Protoss_Citadel_of_Adun 1 9999
Protoss_Dragoon 2 10541
10541
