Protoss_Nexus 1 5698
Protoss_Forge 1 4043
Protoss_Photon_Cannon 4 10675
Protoss_Gateway 1 5864
Protoss_Assimilator 2 6943
Protoss_Cybernetics_Core 1 6908
Protoss_Zealot 1 6816
Protoss_Dragoon 1 7676
Protoss_Stargate 1 9483
Protoss_Robotics_Facility 2 11075
Protoss_Corsair 2 10558
Protoss_Shuttle 1 11341
11341
