Protoss_Forge 2 4568
Protoss_Nexus 1 6018
Protoss_Gateway 2 10990
Protoss_Photon_Cannon 6 10653
Protoss_Assimilator 2 6723
Protoss_Cybernetics_Core 1 6638
Protoss_Zealot 3 9068
Protoss_Stargate 1 7978
Protoss_Dragoon 1 7711
Protoss_Robotics_Facility 1 9023
Protoss_Corsair 2 10776
10990
