Protoss_Gateway 2 3977
Protoss_Zealot 8 7771
Protoss_Assimilator 1 5637
Protoss_Cybernetics_Core 1 6803
Protoss_Stargate 1 8108
Protoss_Dragoon 1 7736
Protoss_Citadel_of_Adun 1 8648
Protoss_Forge 1 8510
Protoss_Templar_Archives 1 9815
Protoss_Nexus 1 11558
Protoss_Photon_Cannon 2 11139
Protoss_Dark_Templar 1 10636
Protoss_High_Templar 1 10671
11558
