Protoss_Forge 1 3082
Protoss_Photon_Cannon 4 11047
Protoss_Gateway 2 10569
Protoss_Zealot 4 10411
Protoss_Assimilator 1 5999
Protoss_Cybernetics_Core 1 7011
Protoss_Stargate 1 8393
Protoss_Nexus 1 9843
Protoss_Dragoon 1 8325
Protoss_Corsair 1 9007
Protoss_Citadel_of_Adun 1 9620
Protoss_Templar_Archives 1 10667
11047
