Protoss_Nexus 1 5798
Protoss_Forge 1 4401
Protoss_Gateway 1 5191
Protoss_Assimilator 2 6504
Protoss_Photon_Cannon 1 5398
Protoss_Cybernetics_Core 1 6303
Protoss_Zealot 2 8146
Protoss_Stargate 1 7585
Protoss_Dragoon 1 7226
8146
