Protoss_Forge 1 3647
Protoss_Nexus 1 6193
Protoss_Photon_Cannon 1 4875
Protoss_Gateway 4 9356
Protoss_Assimilator 2 10837
Protoss_Zealot 14 10865
Protoss_Cybernetics_Core 1 6938
Protoss_Citadel_of_Adun 1 8007
Protoss_Dragoon 1 9441
Protoss_Templar_Archives 1 10975
10975
