Protoss_Forge 1 3324
Protoss_Nexus 1 6343
Protoss_Photon_Cannon 4 10413
Protoss_Gateway 1 5978
Protoss_Assimilator 2 7344
Protoss_Zealot 5 9715
Protoss_Cybernetics_Core 1 7263
Protoss_Stargate 1 8686
Protoss_Citadel_of_Adun 1 8815
Protoss_Dragoon 1 8601
Protoss_Corsair 2 9946
Protoss_Templar_Archives 1 11093
11093
