Protoss_Forge 1 3357
Protoss_Photon_Cannon 2 4445
Protoss_Nexus 1 7118
Protoss_Gateway 4 11380
Protoss_Assimilator 2 7689
Protoss_Cybernetics_Core 1 7278
Protoss_Zealot 4 9533
Protoss_Stargate 1 8630
Protoss_Dragoon 1 8340
Protoss_Citadel_of_Adun 1 8796
Protoss_Corsair 3 10250
Protoss_Templar_Archives 1 9837
Protoss_Dark_Templar 2 10656
11380
