Protoss_Forge 1 3168
Protoss_Photon_Cannon 4 9133
Protoss_Nexus 1 6968
Protoss_Gateway 4 10683
Protoss_Assimilator 2 8627
Protoss_Zealot 8 10933
Protoss_Cybernetics_Core 1 7993
Protoss_Citadel_of_Adun 1 9173
Protoss_Dragoon 1 9316
Protoss_Templar_Archives 1 10625
10933
