Protoss_Forge 1 3772
Protoss_Nexus 1 6289
Protoss_Photon_Cannon 3 7048
Protoss_Gateway 3 10515
Protoss_Zealot 5 9660
Protoss_Assimilator 2 8183
Protoss_Cybernetics_Core 1 7852
Protoss_Citadel_of_Adun 1 9687
10515
