Protoss_Forge 1 3599
Protoss_Nexus 1 6192
Protoss_Photon_Cannon 4 10298
Protoss_Gateway 2 8456
Protoss_Assimilator 2 7772
Protoss_Zealot 8 10781
Protoss_Cybernetics_Core 1 7543
Protoss_Citadel_of_Adun 1 8653
Protoss_Dragoon 1 8511
Protoss_Stargate 2 10379
Protoss_Corsair 2 10866
Protoss_Ground_Weapons_1 1 9896
10866
