Protoss_Nexus 1 5879
Protoss_Forge 1 4281
Protoss_Photon_Cannon 2 7064
Protoss_Assimilator 2 5933
Protoss_Gateway 1 7009
Protoss_Zealot 4 10691
Protoss_Cybernetics_Core 1 8358
Protoss_Citadel_of_Adun 1 9473
10691
