Protoss_Forge 1 3369
Protoss_Photon_Cannon 7 11029
Protoss_Nexus 1 6884
Protoss_Assimilator 2 8055
Protoss_Gateway 3 10583
Protoss_Cybernetics_Core 1 7274
Protoss_Zealot 1 6947
Protoss_Stargate 1 8528
Protoss_Corsair 3 10371
Protoss_Citadel_of_Adun 1 9523
Protoss_Templar_Archives 1 10548
11029
