Protoss_Forge 1 3029
Protoss_Nexus 2 11389
Protoss_Assimilator 2 6546
Protoss_Gateway 1 5871
Protoss_Photon_Cannon 7 11060
Protoss_Zealot 1 6557
Protoss_Cybernetics_Core 1 7169
Protoss_Stargate 1 8597
Protoss_Robotics_Facility 1 9316
Protoss_Corsair 1 9055
Protoss_Robotics_Support_Bay 1 9486
Protoss_Reaver 1 11325
11389
