Protoss_Gateway 1 3291
Protoss_Assimilator 1 3149
Protoss_Zealot 3 6277
Protoss_Cybernetics_Core 1 4970
Protoss_Dragoon 1 5765
Protoss_Stargate 1 6496
Protoss_Citadel_of_Adun 1 6893
Protoss_Corsair 5 10461
Protoss_Templar_Archives 1 7885
Protoss_Forge 1 7878
Protoss_Dark_Templar 1 9191
Protoss_Photon_Cannon 2 10345
Protoss_Nexus 1 11607
Protoss_High_Templar 2 10899
11607
