Protoss_Nexus 1 5848
Protoss_Forge 1 4323
Protoss_Gateway 4 10725
Protoss_Photon_Cannon 4 9052
Protoss_Assimilator 2 7070
Protoss_Cybernetics_Core 1 6641
Protoss_Zealot 2 8071
Protoss_Stargate 1 7928
Protoss_Dragoon 1 7559
Protoss_Citadel_of_Adun 1 8393
Protoss_Corsair 4 10413
Protoss_Templar_Archives 1 9493
Protoss_Dark_Templar 2 10251
10725
