Protoss_Nexus 1 5717
Protoss_Forge 1 4223
Protoss_Gateway 3 10508
Protoss_Assimilator 2 6687
Protoss_Photon_Cannon 8 11172
Protoss_Cybernetics_Core 1 6313
Protoss_Stargate 1 7636
Protoss_Dragoon 1 7207
Protoss_Citadel_of_Adun 1 7751
Protoss_Corsair 2 8943
Protoss_Templar_Archives 1 8952
Protoss_Robotics_Facility 1 10221
Protoss_Dark_Templar 1 9781
Protoss_High_Templar 1 10533
11172
