Protoss_Gateway 2 3701
Protoss_Zealot 10 6796
Protoss_Nexus 1 9198
Protoss_Assimilator 2 9955
Protoss_Cybernetics_Core 1 8328
Protoss_Forge 1 8197
Protoss_Stargate 1 9678
Protoss_Photon_Cannon 3 11108
Protoss_Citadel_of_Adun 1 10377
Protoss_Corsair 1 10271
11108
