Protoss_Forge 1 3203
Protoss_Nexus 1 6178
Protoss_Photon_Cannon 8 11123
Protoss_Gateway 4 10693
Protoss_Assimilator 2 6606
Protoss_Cybernetics_Core 1 6690
Protoss_Zealot 5 9426
Protoss_Citadel_of_Adun 1 7805
Protoss_Templar_Archives 1 9183
Protoss_High_Templar 2 10116
Protoss_Archon 1 10352
Protoss_Ground_Weapons_1 1 9931
11123
