Protoss_Gateway 2 4070
Protoss_Zealot 15 10947
Protoss_Assimilator 1 4413
Protoss_Cybernetics_Core 1 5578
Protoss_Dragoon 1 6386
Protoss_Citadel_of_Adun 1 6767
Protoss_Forge 1 8153
Protoss_Templar_Archives 1 10432
10947
