Protoss_Forge 1 3146
Protoss_Nexus 1 6422
Protoss_Gateway 2 9815
Protoss_Photon_Cannon 3 8698
Protoss_Assimilator 2 7619
Protoss_Zealot 4 10486
Protoss_Cybernetics_Core 1 7573
Protoss_Dragoon 1 8346
Protoss_Stargate 2 9400
Protoss_Citadel_of_Adun 1 9705
Protoss_Corsair 5 10760
Protoss_Templar_Archives 1 10783
10783
