Protoss_Gateway 2 7739
Protoss_Assimilator 1 3524
Protoss_Zealot 6 8425
Protoss_Cybernetics_Core 1 5724
Protoss_Dragoon 1 6691
Protoss_Citadel_of_Adun 1 7332
Protoss_Templar_Archives 1 8807
Protoss_Forge 1 9213
Protoss_High_Templar 2 10478
10478
