Protoss_Forge 1 3478
Protoss_Photon_Cannon 8 10588
Protoss_Nexus 1 8935
Protoss_Gateway 2 11142
Protoss_Assimilator 2 9763
Protoss_Zealot 3 10651
Protoss_Cybernetics_Core 1 9546
Protoss_Citadel_of_Adun 1 10635
11142
