Protoss_Forge 1 3100
Protoss_Nexus 1 6608
Protoss_Photon_Cannon 1 5326
Protoss_Assimilator 1 5757
Protoss_Gateway 6 10880
Protoss_Zealot 10 10730
Protoss_Cybernetics_Core 1 7443
Protoss_Citadel_of_Adun 1 8593
10880
