Protoss_Gateway 3 8504
Protoss_Assimilator 1 3700
Protoss_Zealot 9 10541
Protoss_Cybernetics_Core 1 5324
Protoss_Dragoon 1 6116
Protoss_Stargate 1 6728
Protoss_Citadel_of_Adun 1 7080
Protoss_Corsair 1 7816
Protoss_Templar_Archives 1 10108
10541
