Protoss_Gateway 1 3348
Protoss_Assimilator 1 3393
Protoss_Zealot 4 7266
Protoss_Cybernetics_Core 1 5688
Protoss_Dragoon 2 8986
Protoss_Stargate 1 7343
Protoss_Citadel_of_Adun 1 7463
Protoss_Corsair 5 10498
Protoss_Templar_Archives 1 8675
Protoss_Forge 1 8348
Protoss_Photon_Cannon 3 10397
Protoss_Dark_Templar 1 10791
10791
