Protoss_Gateway 3 11310
Protoss_Zealot 13 10421
Protoss_Forge 2 8632
Protoss_Photon_Cannon 1 6878
Protoss_Nexus 1 9558
Protoss_Assimilator 2 10204
Protoss_Cybernetics_Core 1 10407
11310
