Protoss_Forge 1 2908
Protoss_Photon_Cannon 3 5688
Protoss_Nexus 1 7222
Protoss_Gateway 3 9513
Protoss_Assimilator 2 10465
Protoss_Zealot 9 10683
Protoss_Cybernetics_Core 1 7394
Protoss_Citadel_of_Adun 1 8610
Protoss_Dragoon 1 8511
Protoss_Templar_Archives 1 10867
10867
