Protoss_Gateway 4 10230
Protoss_Zealot 16 10891
Protoss_Assimilator 1 5584
Protoss_Cybernetics_Core 1 6448
Protoss_Citadel_of_Adun 1 7535
Protoss_Dragoon 1 7476
Protoss_Templar_Archives 1 9363
Protoss_High_Templar 2 10838
10891
