Protoss_Forge 1 3472
Protoss_Photon_Cannon 5 11076
Protoss_Nexus 1 6583
Protoss_Gateway 1 5888
Protoss_Assimilator 2 7193
Protoss_Cybernetics_Core 1 6903
Protoss_Zealot 3 10591
Protoss_Stargate 1 8321
Protoss_Corsair 4 10791
Protoss_Robotics_Facility 1 10784
11076
