Protoss_Gateway 2 3887
Protoss_Zealot 9 10757
Protoss_Assimilator 2 10913
Protoss_Nexus 1 9329
Protoss_Forge 2 8052
Protoss_Cybernetics_Core 1 8821
Protoss_Photon_Cannon 2 10307
Protoss_Citadel_of_Adun 1 9874
10913
