Protoss_Forge 1 2954
Protoss_Photon_Cannon 4 9675
Protoss_Nexus 1 7488
Protoss_Gateway 4 10885
Protoss_Assimilator 2 7961
Protoss_Zealot 2 7451
Protoss_Cybernetics_Core 1 7854
Protoss_Citadel_of_Adun 1 8924
Protoss_Templar_Archives 1 10111
Protoss_High_Templar 2 10896
Protoss_Robotics_Facility 1 11693
11693
