Protoss_Forge 1 3430
Protoss_Nexus 1 6466
Protoss_Photon_Cannon 2 10514
Protoss_Gateway 3 9328
Protoss_Assimilator 2 9519
Protoss_Cybernetics_Core 1 7114
Protoss_Zealot 11 10948
Protoss_Citadel_of_Adun 1 8709
Protoss_Templar_Archives 1 10153
Protoss_Robotics_Facility 1 11603
11603
