Protoss_Forge 1 3265
Protoss_Nexus 1 6363
Protoss_Photon_Cannon 5 11097
Protoss_Gateway 3 11216
Protoss_Assimilator 2 8648
Protoss_Zealot 4 10901
Protoss_Cybernetics_Core 1 7814
Protoss_Citadel_of_Adun 1 8991
Protoss_Templar_Archives 1 10418
11216
