Protoss_Forge 1 3237
Protoss_Photon_Cannon 3 10226
Protoss_Nexus 1 6638
Protoss_Gateway 3 10981
Protoss_Assimilator 2 9066
Protoss_Zealot 6 10261
Protoss_Cybernetics_Core 1 6908
Protoss_Citadel_of_Adun 1 8256
Protoss_Templar_Archives 1 10200
Protoss_High_Templar 2 11103
11103
