Protoss_Forge 1 3174
Protoss_Photon_Cannon 5 10400
Protoss_Nexus 1 7603
Protoss_Gateway 2 10263
Protoss_Assimilator 2 8905
Protoss_Cybernetics_Core 1 7774
Protoss_Zealot 2 8051
Protoss_Stargate 1 9058
Protoss_Citadel_of_Adun 1 9143
Protoss_Corsair 3 10893
Protoss_Templar_Archives 1 10430
10893
