Protoss_Forge 1 3075
Protoss_Photon_Cannon 6 11185
Protoss_Gateway 4 11097
Protoss_Nexus 1 8188
Protoss_Zealot 3 7710
Protoss_Assimilator 2 9396
Protoss_Cybernetics_Core 1 8644
Protoss_Citadel_of_Adun 1 9638
Protoss_Templar_Archives 1 10652
11185
