Protoss_Forge 1 3056
Protoss_Photon_Cannon 4 7152
Protoss_Gateway 1 6039
Protoss_Nexus 1 8183
Protoss_Assimilator 2 8434
Protoss_Zealot 6 10408
Protoss_Cybernetics_Core 1 8033
Protoss_Stargate 1 9490
Protoss_Citadel_of_Adun 2 10793
Protoss_Corsair 2 10513
Protoss_Templar_Archives 1 11258
11258
