Protoss_Gateway 3 10957
Protoss_Zealot 11 9321
Protoss_Forge 1 6786
Protoss_Photon_Cannon 1 7755
Protoss_Nexus 2 11913
Protoss_Assimilator 2 10788
Protoss_Cybernetics_Core 1 10057
11913
