Protoss_Forge 1 2937
Protoss_Nexus 1 6177
Protoss_Photon_Cannon 5 10718
Protoss_Assimilator 2 9183
Protoss_Gateway 4 11103
Protoss_Cybernetics_Core 1 7498
Protoss_Zealot 9 10171
Protoss_Citadel_of_Adun 1 8577
Protoss_Templar_Archives 1 10341
Protoss_High_Templar 1 11131
11131
