Protoss_Gateway 2 4005
Protoss_Zealot 12 9373
Protoss_Assimilator 1 4979
Protoss_Cybernetics_Core 1 6461
Protoss_Citadel_of_Adun 1 7617
Protoss_Templar_Archives 1 8733
Protoss_High_Templar 2 10215
10215
