Protoss_Forge 1 3318
Protoss_Photon_Cannon 5 11164
Protoss_Nexus 1 6744
Protoss_Gateway 2 9584
Protoss_Assimilator 2 7394
Protoss_Zealot 6 10576
Protoss_Cybernetics_Core 1 6842
Protoss_Dragoon 1 7996
Protoss_Citadel_of_Adun 2 9008
Protoss_Stargate 1 10206
Protoss_Templar_Archives 1 10085
Protoss_Corsair 1 10636
Protoss_High_Templar 2 10911
11164
