Protoss_Gateway 2 3643
Protoss_Zealot 9 6918
Protoss_Forge 1 5278
Protoss_Photon_Cannon 3 10768
Protoss_Nexus 2 10843
Protoss_Assimilator 2 10409
Protoss_Cybernetics_Core 1 10222
10843
