Protoss_Nexus 2 12753
Protoss_Forge 1 4351
Protoss_Photon_Cannon 1 5408
Protoss_Gateway 4 8988
Protoss_Assimilator 2 8623
Protoss_Zealot 12 10433
Protoss_Cybernetics_Core 1 7772
Protoss_Citadel_of_Adun 1 8773
Protoss_Templar_Archives 1 10786
12753
