Protoss_Gateway 4 11255
Protoss_Zealot 14 10591
Protoss_Nexus 1 8277
Protoss_Forge 1 6739
Protoss_Assimilator 1 7058
Protoss_Photon_Cannon 1 7673
Protoss_Cybernetics_Core 1 8353
Protoss_Citadel_of_Adun 1 9551
11255
