Protoss_Gateway 2 3942
Protoss_Zealot 5 6466
Protoss_Assimilator 1 4565
Protoss_Cybernetics_Core 1 6080
Protoss_Forge 1 6266
Protoss_Nexus 1 10873
Protoss_Photon_Cannon 3 10752
10873
