Protoss_Forge 2 8751
Protoss_Nexus 1 5984
Protoss_Photon_Cannon 2 6300
Protoss_Gateway 4 11129
Protoss_Assimilator 2 8636
Protoss_Zealot 5 10941
Protoss_Cybernetics_Core 1 7856
Protoss_Citadel_of_Adun 1 9027
Protoss_Dragoon 1 10271
11129
