Protoss_Gateway 2 3999
Protoss_Zealot 4 7176
Protoss_Assimilator 1 4520
Protoss_Forge 1 5041
Protoss_Cybernetics_Core 1 6576
Protoss_Citadel_of_Adun 1 7635
Protoss_Ground_Weapons_1 1 8966
Protoss_Photon_Cannon 1 10383
10383
