Protoss_Forge 2 10558
Protoss_Nexus 1 6198
Protoss_Photon_Cannon 2 10085
Protoss_Gateway 4 9173
Protoss_Assimilator 2 7108
Protoss_Zealot 13 10283
Protoss_Cybernetics_Core 1 6685
Protoss_Citadel_of_Adun 1 7873
Protoss_Templar_Archives 1 10913
Protoss_Ground_Weapons_1 1 9891
10913
