Protoss_Forge 1 3208
Protoss_Photon_Cannon 5 10918
Protoss_Nexus 1 7643
Protoss_Gateway 4 9208
Protoss_Assimilator 2 9483
Protoss_Cybernetics_Core 1 7813
Protoss_Zealot 10 10421
Protoss_Citadel_of_Adun 1 8899
Protoss_Dragoon 1 10261
Protoss_Templar_Archives 1 10642
10918
