Protoss_Forge 1 3356
Protoss_Photon_Cannon 4 10646
Protoss_Nexus 2 11078
Protoss_Gateway 1 6368
Protoss_Assimilator 2 7522
Protoss_Cybernetics_Core 1 7481
Protoss_Zealot 1 7211
Protoss_Stargate 1 8803
Protoss_Robotics_Facility 1 9583
Protoss_Corsair 1 9381
Protoss_Robotics_Support_Bay 1 9683
Protoss_Reaver 1 11211
11211
