Protoss_Gateway 2 4088
Protoss_Zealot 10 10761
Protoss_Assimilator 1 4645
Protoss_Cybernetics_Core 1 5858
Protoss_Dragoon 1 6761
Protoss_Citadel_of_Adun 1 7613
Protoss_Forge 1 8113
Protoss_Photon_Cannon 2 10093
Protoss_Templar_Archives 1 10898
10898
