Protoss_Gateway 2 9976
Protoss_Zealot 4 5977
Protoss_Assimilator 1 4141
Protoss_Cybernetics_Core 1 5360
Protoss_Stargate 1 6809
Protoss_Dragoon 1 6819
Protoss_Citadel_of_Adun 1 7509
Protoss_Forge 1 7215
Protoss_Corsair 1 7427
Protoss_Templar_Archives 1 8499
Protoss_Photon_Cannon 5 11019
Protoss_Dark_Templar 1 9431
Protoss_Nexus 1 12103
12103
