Protoss_Forge 1 3980
Protoss_Nexus 1 6067
Protoss_Photon_Cannon 2 5827
Protoss_Gateway 2 9986
Protoss_Assimilator 2 6752
Protoss_Zealot 4 10577
Protoss_Cybernetics_Core 1 7868
Protoss_Citadel_of_Adun 1 9117
Protoss_Templar_Archives 1 10481
10577
