Protoss_Forge 2 4679
Protoss_Nexus 1 5933
Protoss_Gateway 4 10303
Protoss_Photon_Cannon 2 5909
Protoss_Zealot 3 7201
Protoss_Assimilator 2 7455
Protoss_Cybernetics_Core 1 7587
Protoss_Dragoon 8 10617
Protoss_Robotics_Facility 1 10663
Protoss_Citadel_of_Adun 1 10403
10663
