Protoss_Forge 1 3191
Protoss_Photon_Cannon 6 11105
Protoss_Nexus 1 6909
Protoss_Gateway 1 5763
Protoss_Assimilator 2 8263
Protoss_Cybernetics_Core 1 6766
Protoss_Zealot 3 7889
Protoss_Stargate 2 10388
Protoss_Corsair 4 10801
Protoss_Robotics_Facility 1 10143
11105
