Protoss_Gateway 2 3907
Protoss_Zealot 8 6429
Protoss_Assimilator 1 5997
Protoss_Cybernetics_Core 1 8062
Protoss_Dragoon 3 10809
Protoss_Stargate 1 10153
Protoss_Forge 1 9878
Protoss_Photon_Cannon 1 10861
10861
