Protoss_Forge 1 3566
Protoss_Photon_Cannon 2 5325
Protoss_Nexus 1 6599
Protoss_Gateway 6 10545
Protoss_Assimilator 2 7602
Protoss_Cybernetics_Core 1 7132
Protoss_Zealot 6 10661
Protoss_Stargate 1 8520
Protoss_Dragoon 1 8317
Protoss_Citadel_of_Adun 1 9218
Protoss_Corsair 1 9113
Protoss_Robotics_Facility 1 11836
11836
