Protoss_Forge 1 3282
Protoss_Nexus 1 6313
Protoss_Photon_Cannon 2 10132
Protoss_Gateway 4 9744
Protoss_Assimilator 2 8331
Protoss_Zealot 15 10928
Protoss_Cybernetics_Core 1 7824
Protoss_Citadel_of_Adun 1 8943
Protoss_Templar_Archives 1 10493
Protoss_Ground_Weapons_1 1 9996
10928
