Protoss_Forge 1 3499
Protoss_Nexus 1 6203
Protoss_Photon_Cannon 2 9014
Protoss_Gateway 4 11309
Protoss_Assimilator 2 7889
Protoss_Zealot 4 9073
Protoss_Cybernetics_Core 1 7202
Protoss_Dragoon 2 8688
Protoss_Stargate 1 8683
Protoss_Citadel_of_Adun 1 9579
11309
