Protoss_Gateway 2 11408
Protoss_Assimilator 1 3420
Protoss_Zealot 3 5275
Protoss_Cybernetics_Core 1 5379
Protoss_Dragoon 1 6441
Protoss_Stargate 1 7116
Protoss_Citadel_of_Adun 1 7403
Protoss_Scout 1 8641
Protoss_Templar_Archives 1 8521
Protoss_Forge 1 8636
Protoss_Dark_Templar 1 9271
Protoss_Photon_Cannon 1 9583
Protoss_Nexus 1 12513
Protoss_High_Templar 1 10966
12513
