Protoss_Nexus 1 5919
Protoss_Forge 1 4353
Protoss_Photon_Cannon 3 7103
Protoss_Gateway 4 9468
Protoss_Assimilator 2 8668
Protoss_Zealot 9 10681
Protoss_Cybernetics_Core 1 7726
Protoss_Citadel_of_Adun 1 8757
Protoss_Dragoon 1 8666
Protoss_Templar_Archives 1 10639
10681
