Protoss_Gateway 2 2416
Protoss_Zealot 9 7226
Protoss_Assimilator 1 5199
Protoss_Cybernetics_Core 1 5881
Protoss_Citadel_of_Adun 1 7366
Protoss_Forge 1 8136
Protoss_Templar_Archives 1 8408
8408
