Protoss_Gateway 2 3705
Protoss_Zealot 7 8041
Protoss_Nexus 1 9158
Protoss_Assimilator 2 10319
Protoss_Forge 1 8378
Protoss_Cybernetics_Core 1 9328
Protoss_Photon_Cannon 4 11096
Protoss_Stargate 1 10603
11096
