Protoss_Forge 1 3051
Protoss_Nexus 1 6239
Protoss_Gateway 3 11080
Protoss_Photon_Cannon 12 11083
Protoss_Assimilator 2 6832
Protoss_Zealot 1 6119
Protoss_Cybernetics_Core 1 6902
Protoss_Citadel_of_Adun 1 7918
Protoss_Templar_Archives 1 8983
Protoss_Dark_Templar 1 9743
Protoss_High_Templar 2 10505
11083
