Protoss_Forge 2 10276
Protoss_Nexus 1 6183
Protoss_Photon_Cannon 4 10404
Protoss_Gateway 3 11174
Protoss_Assimilator 2 7223
Protoss_Zealot 3 8763
Protoss_Cybernetics_Core 1 7296
Protoss_Stargate 1 8527
Protoss_Citadel_of_Adun 1 8809
Protoss_Corsair 3 10737
Protoss_Templar_Archives 1 9867
Protoss_Dark_Templar 2 10733
11174
