Protoss_Forge 2 10827
Protoss_Nexus 1 6309
Protoss_Photon_Cannon 2 5192
Protoss_Gateway 4 9517
Protoss_Assimilator 2 7499
Protoss_Zealot 11 10881
Protoss_Cybernetics_Core 1 7567
Protoss_Citadel_of_Adun 1 8705
Protoss_Templar_Archives 1 11263
11263
