Protoss_Forge 1 2939
Protoss_Photon_Cannon 3 10361
Protoss_Nexus 1 6973
Protoss_Gateway 1 5815
Protoss_Assimilator 2 8747
Protoss_Cybernetics_Core 1 6835
Protoss_Zealot 4 10475
Protoss_Stargate 1 8239
Protoss_Dragoon 1 8075
Protoss_Citadel_of_Adun 1 9103
Protoss_Corsair 4 10871
Protoss_Templar_Archives 1 10222
10871
