Protoss_Forge 1 3280
Protoss_Nexus 1 6211
Protoss_Gateway 4 10225
Protoss_Assimilator 2 7421
Protoss_Zealot 9 10919
Protoss_Cybernetics_Core 1 6527
Protoss_Photon_Cannon 1 6833
Protoss_Stargate 1 7949
Protoss_Citadel_of_Adun 1 8348
Protoss_Corsair 2 9057
Protoss_Robotics_Facility 1 11892
11892
