Protoss_Forge 1 3135
Protoss_Photon_Cannon 3 10645
Protoss_Nexus 1 6992
Protoss_Gateway 4 9803
Protoss_Assimilator 1 5755
Protoss_Zealot 11 10457
Protoss_Cybernetics_Core 1 6987
Protoss_Citadel_of_Adun 1 8143
10645
