Protoss_Gateway 1 3377
Protoss_Assimilator 1 3550
Protoss_Zealot 5 10687
Protoss_Cybernetics_Core 1 5465
Protoss_Stargate 1 6730
Protoss_Dragoon 1 6487
Protoss_Citadel_of_Adun 1 7183
Protoss_Forge 1 7293
Protoss_Templar_Archives 1 8270
Protoss_Photon_Cannon 8 10809
Protoss_High_Templar 2 10161
10809
