Protoss_Forge 1 3251
Protoss_Nexus 1 6368
Protoss_Gateway 5 10358
Protoss_Photon_Cannon 3 11174
Protoss_Assimilator 2 7667
Protoss_Zealot 12 10742
Protoss_Cybernetics_Core 1 7407
Protoss_Citadel_of_Adun 1 8610
Protoss_Templar_Archives 1 11072
11174
