Protoss_Forge 1 3150
Protoss_Photon_Cannon 4 7254
Protoss_Nexus 1 7467
Protoss_Gateway 2 11329
Protoss_Zealot 6 10778
Protoss_Assimilator 2 9094
Protoss_Cybernetics_Core 1 8790
Protoss_Stargate 1 10193
Protoss_Citadel_of_Adun 1 10491
Protoss_Corsair 1 10621
11329
