Protoss_Forge 1 3856
Protoss_Nexus 1 6251
Protoss_Photon_Cannon 4 10673
Protoss_Gateway 4 9089
Protoss_Assimilator 2 7519
Protoss_Cybernetics_Core 1 7231
Protoss_Zealot 2 7611
Protoss_Citadel_of_Adun 1 8369
Protoss_Templar_Archives 1 9395
Protoss_Dragoon 1 9779
Protoss_High_Templar 5 10929
10929
