Protoss_Nexus 1 5887
Protoss_Forge 2 9729
Protoss_Photon_Cannon 4 11028
Protoss_Gateway 3 9658
Protoss_Assimilator 2 8429
Protoss_Zealot 5 9636
Protoss_Cybernetics_Core 1 8683
Protoss_Citadel_of_Adun 1 9767
Protoss_Dragoon 1 9778
11028
