Protoss_Gateway 1 3193
Protoss_Zealot 6 7755
Protoss_Nexus 1 7018
Protoss_Assimilator 1 5307
Protoss_Cybernetics_Core 1 6859
Protoss_Stargate 1 8258
Protoss_Citadel_of_Adun 1 8363
Protoss_Forge 1 8227
Protoss_Corsair 4 10653
Protoss_Templar_Archives 1 9355
Protoss_Photon_Cannon 8 11018
11018
