Protoss_Forge 1 3165
Protoss_Nexus 1 5985
Protoss_Photon_Cannon 3 11090
Protoss_Gateway 3 9615
Protoss_Assimilator 1 5632
Protoss_Cybernetics_Core 1 6783
Protoss_Zealot 8 10433
Protoss_Dragoon 1 8037
Protoss_Citadel_of_Adun 1 9253
Protoss_Templar_Archives 1 10966
11090
