Protoss_Gateway 2 3876
Protoss_Zealot 9 10251
Protoss_Assimilator 1 5473
Protoss_Cybernetics_Core 2 7726
Protoss_Stargate 1 8185
Protoss_Dragoon 1 7763
Protoss_Citadel_of_Adun 1 8417
Protoss_Forge 1 8523
Protoss_Corsair 1 8815
Protoss_Templar_Archives 1 9665
Protoss_Photon_Cannon 2 11105
Protoss_Dark_Templar 1 10415
11105
