Protoss_Forge 1 3314
Protoss_Photon_Cannon 2 5075
Protoss_Nexus 1 6469
Protoss_Gateway 1 6036
Protoss_Assimilator 2 7521
Protoss_Cybernetics_Core 1 7153
Protoss_Zealot 2 10889
10889
