Protoss_Nexus 1 5787
Protoss_Forge 1 4451
Protoss_Gateway 4 11208
Protoss_Assimilator 2 6484
Protoss_Photon_Cannon 5 10843
Protoss_Cybernetics_Core 1 6835
Protoss_Zealot 3 9373
Protoss_Stargate 1 8413
Protoss_Citadel_of_Adun 1 8202
Protoss_Dragoon 1 8235
Protoss_Corsair 3 10611
Protoss_Templar_Archives 1 9588
Protoss_Dark_Templar 2 10365
Protoss_High_Templar 2 11117
11208
