Protoss_Forge 1 3657
Protoss_Nexus 1 6413
Protoss_Photon_Cannon 2 5291
Protoss_Gateway 2 10072
Protoss_Assimilator 2 8653
Protoss_Zealot 5 10865
Protoss_Cybernetics_Core 1 7733
Protoss_Dragoon 1 9063
Protoss_Citadel_of_Adun 1 9583
Protoss_Stargate 2 10731
10865
