Protoss_Forge 1 3128
Protoss_Photon_Cannon 3 8380
Protoss_Nexus 1 6427
Protoss_Gateway 2 9139
Protoss_Assimilator 2 7079
Protoss_Cybernetics_Core 1 7447
Protoss_Zealot 3 10458
10458
