Protoss_Forge 1 3321
Protoss_Nexus 1 6329
Protoss_Photon_Cannon 7 11129
Protoss_Gateway 4 11011
Protoss_Assimilator 2 7653
Protoss_Cybernetics_Core 1 7505
Protoss_Zealot 7 10181
Protoss_Citadel_of_Adun 1 8735
Protoss_Templar_Archives 1 10315
11129
