Protoss_Forge 1 3263
Protoss_Photon_Cannon 6 10568
Protoss_Nexus 1 6901
Protoss_Gateway 2 10111
Protoss_Assimilator 2 8421
Protoss_Zealot 2 6863
Protoss_Cybernetics_Core 1 7201
Protoss_Stargate 1 8455
Protoss_Citadel_of_Adun 1 8684
Protoss_Corsair 1 8873
Protoss_Templar_Archives 1 9967
Protoss_Dark_Templar 1 10743
10743
