Protoss_Forge 2 8956
Protoss_Photon_Cannon 3 9995
Protoss_Gateway 2 11009
Protoss_Assimilator 1 6586
Protoss_Zealot 3 10871
Protoss_Cybernetics_Core 1 7617
Protoss_Stargate 1 8974
Protoss_Citadel_of_Adun 1 9230
Protoss_Corsair 2 10021
Protoss_Templar_Archives 1 11084
11084
