Protoss_Gateway 3 9738
Protoss_Zealot 12 9561
Protoss_Assimilator 1 4648
Protoss_Cybernetics_Core 1 6077
Protoss_Citadel_of_Adun 1 7111
Protoss_Dragoon 1 7036
Protoss_Templar_Archives 1 9379
Protoss_High_Templar 2 10681
Protoss_Dark_Templar 1 10976
10976
