Protoss_Forge 1 3238
Protoss_Nexus 1 6203
Protoss_Photon_Cannon 4 10421
Protoss_Gateway 4 11273
Protoss_Assimilator 2 7766
Protoss_Cybernetics_Core 1 6946
Protoss_Zealot 4 10286
Protoss_Stargate 1 8325
Protoss_Citadel_of_Adun 1 8498
Protoss_Corsair 2 9541
Protoss_Templar_Archives 1 10845
11273
