Protoss_Gateway 2 9338
Protoss_Assimilator 2 9788
Protoss_Zealot 6 9711
Protoss_Cybernetics_Core 1 5083
Protoss_Stargate 1 6307
Protoss_Dragoon 1 5851
Protoss_Citadel_of_Adun 1 6538
Protoss_Forge 1 6357
Protoss_Corsair 2 7809
Protoss_Templar_Archives 1 7621
Protoss_Photon_Cannon 3 10147
Protoss_Dark_Templar 1 8377
Protoss_High_Templar 1 10271
Protoss_Nexus 1 12515
12515
