Protoss_Gateway 3 9355
Protoss_Assimilator 2 5284
Protoss_Cybernetics_Core 1 4609
Protoss_Zealot 3 7261
Protoss_Stargate 1 5928
Protoss_Dragoon 6 10699
Protoss_Corsair 1 6347
10699
