Protoss_Assimilator 1 2147
Protoss_Gateway 1 3485
Protoss_Cybernetics_Core 1 4623
Protoss_Stargate 2 6213
Protoss_Corsair 9 10639
Protoss_Forge 1 7993
Protoss_Photon_Cannon 2 9430
Protoss_Air_Weapons_1 1 9081
10639
