Protoss_Forge 2 9827
Protoss_Nexus 1 6395
Protoss_Photon_Cannon 9 11194
Protoss_Gateway 4 11027
Protoss_Assimilator 2 8617
Protoss_Zealot 2 7835
Protoss_Cybernetics_Core 1 7791
Protoss_Citadel_of_Adun 1 8934
Protoss_Dragoon 1 8718
Protoss_Templar_Archives 1 10109
Protoss_High_Templar 1 11127
11194
