Protoss_Forge 2 9694
Protoss_Photon_Cannon 5 6398
Protoss_Nexus 1 7049
Protoss_Gateway 3 10859
Protoss_Assimilator 2 10667
Protoss_Zealot 4 10811
Protoss_Cybernetics_Core 1 9560
Protoss_Citadel_of_Adun 1 10568
10859
