Protoss_Forge 1 3255
Protoss_Photon_Cannon 4 9258
Protoss_Nexus 1 6727
Protoss_Gateway 2 11010
Protoss_Assimilator 2 7339
Protoss_Cybernetics_Core 1 6539
Protoss_Zealot 2 7845
Protoss_Stargate 1 7791
Protoss_Corsair 4 10571
Protoss_Citadel_of_Adun 1 8911
Protoss_Templar_Archives 1 9946
Protoss_Dark_Templar 1 11079
11079
