Protoss_Forge 2 9253
Protoss_Nexus 1 6148
Protoss_Photon_Cannon 3 10674
Protoss_Gateway 4 10527
Protoss_Assimilator 2 7371
Protoss_Cybernetics_Core 1 7295
Protoss_Zealot 5 10099
Protoss_Stargate 1 8589
Protoss_Citadel_of_Adun 1 8659
Protoss_Dragoon 1 8787
Protoss_Corsair 1 9005
Protoss_Templar_Archives 1 9823
10674
