Protoss_Forge 1 3460
Protoss_Photon_Cannon 3 5230
Protoss_Nexus 1 7393
Protoss_Gateway 3 9789
Protoss_Assimilator 3 10571
Protoss_Zealot 6 10449
Protoss_Cybernetics_Core 1 7360
Protoss_Stargate 1 8625
Protoss_Citadel_of_Adun 1 8876
Protoss_Dragoon 1 8891
Protoss_Corsair 2 9663
10571
