Protoss_Forge 1 3073
Protoss_Nexus 1 6385
Protoss_Gateway 5 10802
Protoss_Photon_Cannon 1 5621
Protoss_Assimilator 2 7671
Protoss_Zealot 11 10945
Protoss_Cybernetics_Core 1 6775
Protoss_Dragoon 1 7517
Protoss_Stargate 1 8244
Protoss_Corsair 1 8657
Protoss_Citadel_of_Adun 1 9693
Protoss_Templar_Archives 1 11402
11402
