Protoss_Forge 2 9606
Protoss_Nexus 1 6058
Protoss_Photon_Cannon 4 9543
Protoss_Gateway 4 11399
Protoss_Assimilator 2 7272
Protoss_Cybernetics_Core 1 6890
Protoss_Zealot 5 9309
Protoss_Stargate 1 8197
Protoss_Citadel_of_Adun 1 8619
Protoss_Corsair 1 8703
Protoss_Templar_Archives 1 9667
Protoss_Dark_Templar 1 10421
Protoss_High_Templar 1 11199
11399
