Protoss_Forge 2 10264
Protoss_Photon_Cannon 2 11040
Protoss_Nexus 1 6659
Protoss_Gateway 4 10172
Protoss_Assimilator 2 7728
Protoss_Cybernetics_Core 1 6643
Protoss_Zealot 3 9103
Protoss_Stargate 1 8033
Protoss_Citadel_of_Adun 1 8508
Protoss_Dragoon 1 8591
Protoss_Corsair 1 8509
Protoss_Templar_Archives 1 9517
Protoss_Dark_Templar 3 11075
Protoss_High_Templar 2 11017
11075
