Protoss_Forge 1 3663
Protoss_Nexus 1 6361
Protoss_Photon_Cannon 2 5191
Protoss_Gateway 4 9960
Protoss_Assimilator 2 7708
Protoss_Cybernetics_Core 1 7009
Protoss_Zealot 4 9099
Protoss_Stargate 1 8430
Protoss_Dragoon 8 10935
Protoss_Corsair 4 10895
10935
