Protoss_Gateway 2 3588
Protoss_Zealot 15 9125
Protoss_Assimilator 1 6617
Protoss_Cybernetics_Core 1 7993
Protoss_Forge 1 8589
Protoss_Stargate 1 9747
Protoss_Photon_Cannon 1 9759
Protoss_Corsair 1 10167
Protoss_Nexus 1 12838
12838
