Protoss_Forge 1 3053
Protoss_Photon_Cannon 3 11114
Protoss_Nexus 1 7013
Protoss_Gateway 3 9815
Protoss_Assimilator 2 10585
Protoss_Zealot 10 10499
Protoss_Cybernetics_Core 1 6950
Protoss_Stargate 1 8505
Protoss_Citadel_of_Adun 1 8921
Protoss_Corsair 1 9289
11114
