Protoss_Forge 1 3023
Protoss_Photon_Cannon 3 10737
Protoss_Nexus 1 6881
Protoss_Gateway 2 9467
Protoss_Assimilator 2 8299
Protoss_Zealot 7 10881
Protoss_Cybernetics_Core 1 7025
Protoss_Dragoon 1 7855
Protoss_Stargate 1 8729
Protoss_Citadel_of_Adun 1 8945
Protoss_Corsair 3 10673
Protoss_Templar_Archives 1 10643
10881
