Protoss_Nexus 1 5367
Protoss_Forge 1 3773
Protoss_Gateway 4 11273
Protoss_Photon_Cannon 3 10367
Protoss_Assimilator 2 7676
Protoss_Zealot 9 10213
Protoss_Cybernetics_Core 1 6571
Protoss_Stargate 1 7978
Protoss_Corsair 3 10327
Protoss_Citadel_of_Adun 1 9140
Protoss_Templar_Archives 1 11027
11273
