Protoss_Nexus 2 11361
Protoss_Forge 1 4707
Protoss_Photon_Cannon 5 11090
Protoss_Gateway 3 8838
Protoss_Assimilator 2 10594
Protoss_Cybernetics_Core 1 7039
Protoss_Zealot 12 10941
Protoss_Citadel_of_Adun 1 8165
Protoss_Templar_Archives 1 11164
11361
