Protoss_Forge 1 3969
Protoss_Photon_Cannon 5 10482
Protoss_Nexus 1 7925
Protoss_Gateway 1 6607
Protoss_Assimilator 2 9521
Protoss_Zealot 5 10147
Protoss_Cybernetics_Core 1 8376
Protoss_Stargate 1 9622
Protoss_Corsair 2 10805
Protoss_Robotics_Facility 1 11347
11347
