Protoss_Forge 1 2980
Protoss_Nexus 1 6117
Protoss_Photon_Cannon 1 5145
Protoss_Gateway 4 10039
Protoss_Assimilator 2 7432
Protoss_Zealot 4 9337
Protoss_Cybernetics_Core 1 7058
Protoss_Stargate 1 8719
Protoss_Citadel_of_Adun 1 8587
Protoss_Corsair 2 9763
Protoss_Templar_Archives 1 10109
Protoss_Dragoon 3 11073
Protoss_Ground_Weapons_1 1 9919
11073
