Protoss_Forge 1 3096
Protoss_Photon_Cannon 9 11074
Protoss_Nexus 1 7000
Protoss_Gateway 4 11118
Protoss_Assimilator 1 6366
Protoss_Zealot 4 9901
Protoss_Cybernetics_Core 1 7957
Protoss_Stargate 1 9958
Protoss_Citadel_of_Adun 1 10333
Protoss_Corsair 1 10491
11118
