Protoss_Forge 1 3145
Protoss_Photon_Cannon 4 10305
Protoss_Nexus 1 6997
Protoss_Gateway 3 9528
Protoss_Assimilator 1 5615
Protoss_Zealot 7 10533
Protoss_Cybernetics_Core 1 7081
Protoss_Dragoon 1 8013
Protoss_Stargate 1 8771
Protoss_Citadel_of_Adun 1 9100
Protoss_Corsair 1 9189
10533
