Protoss_Forge 2 10867
Protoss_Photon_Cannon 5 10986
Protoss_Nexus 1 6535
Protoss_Gateway 3 10403
Protoss_Assimilator 2 7020
Protoss_Cybernetics_Core 1 6883
Protoss_Zealot 5 10253
Protoss_Stargate 1 8515
Protoss_Citadel_of_Adun 1 8894
Protoss_Corsair 2 9653
Protoss_Templar_Archives 1 9891
Protoss_Dark_Templar 1 10825
10986
