Protoss_Forge 1 3200
Protoss_Photon_Cannon 3 9491
Protoss_Nexus 1 6824
Protoss_Gateway 4 10444
Protoss_Assimilator 2 7892
Protoss_Cybernetics_Core 1 7137
Protoss_Zealot 5 10507
Protoss_Stargate 1 8363
Protoss_Dragoon 1 8627
Protoss_Citadel_of_Adun 1 9257
Protoss_Corsair 2 10645
10645
