Protoss_Nexus 1 5447
Protoss_Forge 1 3751
Protoss_Photon_Cannon 1 4692
Protoss_Gateway 4 11185
Protoss_Assimilator 2 6407
Protoss_Cybernetics_Core 1 6397
Protoss_Zealot 3 7317
Protoss_Stargate 2 8005
Protoss_Citadel_of_Adun 1 8234
Protoss_Corsair 7 10033
Protoss_Templar_Archives 1 9419
Protoss_Dark_Templar 1 10653
11185
