Protoss_Forge 1 3287
Protoss_Photon_Cannon 4 9294
Protoss_Nexus 1 6497
Protoss_Gateway 2 10595
Protoss_Assimilator 2 6800
Protoss_Cybernetics_Core 1 6899
Protoss_Zealot 5 9923
Protoss_Stargate 1 8197
Protoss_Corsair 3 10709
Protoss_Citadel_of_Adun 1 9697
Protoss_Templar_Archives 1 10857
10857
