Protoss_Gateway 1 3256
Protoss_Forge 1 3598
Protoss_Zealot 12 10585
Protoss_Photon_Cannon 9 9991
Protoss_Nexus 1 9675
Protoss_Assimilator 1 7911
Protoss_Cybernetics_Core 1 9517
Protoss_Citadel_of_Adun 1 11230
11230
