Protoss_Forge 1 3236
Protoss_Nexus 1 6182
Protoss_Gateway 2 9102
Protoss_Photon_Cannon 3 10547
Protoss_Assimilator 2 7882
Protoss_Zealot 9 10927
Protoss_Cybernetics_Core 1 6565
Protoss_Stargate 1 8309
Protoss_Citadel_of_Adun 1 8541
Protoss_Corsair 4 10779
Protoss_Templar_Archives 1 10926
10927
