Protoss_Forge 1 3357
Protoss_Photon_Cannon 7 10984
Protoss_Nexus 1 8049
Protoss_Gateway 2 9879
Protoss_Assimilator 2 9113
Protoss_Cybernetics_Core 1 8165
Protoss_Zealot 6 10931
Protoss_Stargate 1 9391
Protoss_Citadel_of_Adun 1 10217
Protoss_Corsair 1 9823
10984
