Protoss_Forge 1 3496
Protoss_Nexus 1 6083
Protoss_Photon_Cannon 2 11125
Protoss_Gateway 4 10799
Protoss_Assimilator 2 7112
Protoss_Cybernetics_Core 1 6477
Protoss_Zealot 3 9181
Protoss_Stargate 1 7714
Protoss_Dragoon 1 7581
Protoss_Citadel_of_Adun 1 8239
Protoss_Corsair 3 9549
Protoss_Templar_Archives 1 9407
Protoss_Dark_Templar 2 10199
Protoss_High_Templar 2 10951
11125
