Protoss_Forge 1 3388
Protoss_Photon_Cannon 1 4356
Protoss_Nexus 1 6393
Protoss_Gateway 4 9106
Protoss_Assimilator 2 9068
Protoss_Cybernetics_Core 1 6643
Protoss_Zealot 13 10205
Protoss_Citadel_of_Adun 1 7813
Protoss_Stargate 2 11283
11283
