Protoss_Forge 1 3254
Protoss_Nexus 1 6242
Protoss_Photon_Cannon 3 10406
Protoss_Gateway 2 9206
Protoss_Assimilator 2 7303
Protoss_Cybernetics_Core 1 6963
Protoss_Zealot 7 10539
Protoss_Stargate 1 8224
Protoss_Citadel_of_Adun 1 8603
Protoss_Corsair 4 10729
Protoss_Templar_Archives 1 10949
10949
