Protoss_Nexus 1 5735
Protoss_Gateway 4 9515
Protoss_Assimilator 1 4510
Protoss_Forge 1 5078
Protoss_Zealot 14 10531
Protoss_Photon_Cannon 3 11020
Protoss_Cybernetics_Core 1 6515
Protoss_Stargate 1 7753
Protoss_Corsair 2 10513
Protoss_Citadel_of_Adun 1 8836
11020
