Protoss_Nexus 1 5391
Protoss_Forge 1 3743
Protoss_Photon_Cannon 3 7033
Protoss_Gateway 2 10517
Protoss_Assimilator 2 7215
Protoss_Cybernetics_Core 1 6297
Protoss_Zealot 4 10635
Protoss_Stargate 2 8387
Protoss_Corsair 8 10787
Protoss_Citadel_of_Adun 1 10161
10787
