Protoss_Nexus 1 5761
Protoss_Forge 1 4103
Protoss_Assimilator 1 4660
Protoss_Gateway 4 8237
Protoss_Photon_Cannon 1 5819
Protoss_Cybernetics_Core 1 6331
Protoss_Zealot 17 10621
Protoss_Citadel_of_Adun 1 7564
Protoss_Stargate 2 10500
Protoss_Ground_Weapons_1 1 9305
Protoss_Corsair 2 10909
10909
