Protoss_Forge 1 3565
Protoss_Nexus 1 6001
Protoss_Photon_Cannon 1 4613
Protoss_Gateway 2 10608
Protoss_Assimilator 2 6698
Protoss_Cybernetics_Core 1 6339
Protoss_Zealot 4 8383
Protoss_Stargate 2 9316
Protoss_Citadel_of_Adun 1 8031
Protoss_Corsair 7 10869
Protoss_Templar_Archives 1 9101
Protoss_Dark_Templar 2 10663
10869
