Protoss_Nexus 1 5439
Protoss_Forge 1 3767
Protoss_Photon_Cannon 4 10327
Protoss_Gateway 1 5333
Protoss_Assimilator 2 6649
Protoss_Cybernetics_Core 1 6350
Protoss_Zealot 3 7503
Protoss_Stargate 1 7598
Protoss_Robotics_Facility 1 8791
Protoss_Corsair 5 10629
Protoss_Robotics_Support_Bay 1 8932
Protoss_Citadel_of_Adun 1 9934
Protoss_Shuttle 1 10259
Protoss_Templar_Archives 1 10945
Protoss_Reaver 1 11555
11555
