Protoss_Forge 1 3115
Protoss_Nexus 1 6146
Protoss_Gateway 4 9926
Protoss_Assimilator 1 5119
Protoss_Photon_Cannon 5 10091
Protoss_Cybernetics_Core 1 6452
Protoss_Zealot 14 10841
Protoss_Citadel_of_Adun 1 7466
10841
