Protoss_Forge 1 3470
Protoss_Photon_Cannon 1 4460
Protoss_Nexus 1 6591
Protoss_Gateway 2 5693
Protoss_Assimilator 2 10521
Protoss_Zealot 15 10857
Protoss_Cybernetics_Core 1 7519
Protoss_Stargate 1 8797
Protoss_Corsair 3 10667
Protoss_Citadel_of_Adun 1 10338
10857
