Protoss_Forge 2 4728
Protoss_Nexus 1 5812
Protoss_Gateway 4 9088
Protoss_Assimilator 2 9107
Protoss_Cybernetics_Core 1 5992
Protoss_Photon_Cannon 2 10115
Protoss_Zealot 15 10910
Protoss_Stargate 1 7495
Protoss_Corsair 2 10545
Protoss_Citadel_of_Adun 1 8718
10910
