Protoss_Forge 1 3196
Protoss_Photon_Cannon 3 11198
Protoss_Nexus 1 9279
Protoss_Gateway 1 8527
Protoss_Assimilator 2 9917
Protoss_Cybernetics_Core 1 9513
Protoss_Zealot 2 9837
Protoss_Stargate 1 10874
Protoss_Dragoon 1 10409
11198
