Protoss_Forge 1 3065
Protoss_Photon_Cannon 2 9753
Protoss_Nexus 1 6355
Protoss_Gateway 2 11367
Protoss_Assimilator 2 7559
Protoss_Cybernetics_Core 1 6425
Protoss_Zealot 4 9307
Protoss_Stargate 1 7775
Protoss_Citadel_of_Adun 1 8351
Protoss_Corsair 4 10333
Protoss_Templar_Archives 1 9443
Protoss_Dark_Templar 1 10287
Protoss_Arbiter_Tribunal 1 10673
11367
