Protoss_Nexus 1 5445
Protoss_Forge 1 3847
Protoss_Photon_Cannon 2 9971
Protoss_Gateway 3 11347
Protoss_Assimilator 2 10344
Protoss_Cybernetics_Core 1 6469
Protoss_Zealot 8 10829
Protoss_Stargate 1 8102
Protoss_Corsair 4 10591
Protoss_Citadel_of_Adun 1 9279
11347
