Protoss_Forge 1 3276
Protoss_Photon_Cannon 3 10813
Protoss_Nexus 1 6993
Protoss_Gateway 4 10152
Protoss_Assimilator 2 9857
Protoss_Cybernetics_Core 1 6905
Protoss_Zealot 9 10093
Protoss_Citadel_of_Adun 1 7956
Protoss_Dragoon 3 11137
11137
