Protoss_Forge 1 3530
Protoss_Photon_Cannon 2 4860
Protoss_Nexus 1 6975
Protoss_Gateway 4 10917
Protoss_Assimilator 2 8109
Protoss_Zealot 10 10931
Protoss_Cybernetics_Core 1 7085
Protoss_Stargate 1 8311
Protoss_Citadel_of_Adun 1 8831
Protoss_Corsair 2 9537
10931
