Protoss_Forge 1 3043
Protoss_Photon_Cannon 9 10549
Protoss_Nexus 1 6735
Protoss_Gateway 3 8892
Protoss_Assimilator 2 8713
Protoss_Zealot 5 8309
Protoss_Cybernetics_Core 1 6851
Protoss_Citadel_of_Adun 1 7967
Protoss_Templar_Archives 1 9337
Protoss_High_Templar 3 10943
Protoss_Dark_Templar 1 10111
Protoss_Archon 1 10379
10943
