Protoss_Forge 1 3256
Protoss_Photon_Cannon 3 10817
Protoss_Nexus 1 9331
Protoss_Gateway 1 8353
Protoss_Assimilator 1 8284
Protoss_Zealot 2 10347
Protoss_Cybernetics_Core 1 9921
10817
