Protoss_Forge 1 3585
Protoss_Nexus 1 6157
Protoss_Photon_Cannon 3 10736
Protoss_Gateway 4 11280
Protoss_Assimilator 2 8627
Protoss_Zealot 8 10413
Protoss_Cybernetics_Core 1 6749
Protoss_Stargate 1 8202
Protoss_Citadel_of_Adun 1 8721
Protoss_Corsair 2 9599
Protoss_Templar_Archives 1 11352
11352
