Protoss_Forge 1 3250
Protoss_Photon_Cannon 9 7626
Protoss_Nexus 1 9543
Protoss_Gateway 1 8571
Protoss_Assimilator 2 10614
Protoss_Cybernetics_Core 1 9927
Protoss_Dragoon 1 10671
Protoss_Stargate 1 11165
11165
