Protoss_Forge 1 3256
Protoss_Photon_Cannon 3 10149
Protoss_Nexus 1 7045
Protoss_Gateway 4 11367
Protoss_Assimilator 2 7385
Protoss_Cybernetics_Core 1 6933
Protoss_Zealot 3 8575
Protoss_Stargate 1 8268
Protoss_Dragoon 1 8063
Protoss_Citadel_of_Adun 1 8768
Protoss_Corsair 3 10145
Protoss_Templar_Archives 1 9858
Protoss_Dark_Templar 2 10613
11367
