Protoss_Gateway 2 3907
Protoss_Zealot 12 10217
Protoss_Assimilator 1 5643
Protoss_Cybernetics_Core 1 7050
Protoss_Forge 1 7483
Protoss_Stargate 1 8705
Protoss_Photon_Cannon 3 10940
Protoss_Citadel_of_Adun 1 9240
Protoss_Corsair 2 9747
10940
