Protoss_Gateway 2 4035
Protoss_Zealot 10 8109
Protoss_Assimilator 1 5423
Protoss_Cybernetics_Core 1 6933
Protoss_Stargate 1 8175
Protoss_Citadel_of_Adun 1 8141
Protoss_Corsair 1 8587
Protoss_Templar_Archives 1 9397
Protoss_Nexus 1 11441
Protoss_Forge 1 9703
Protoss_Dark_Templar 1 10371
Protoss_Photon_Cannon 2 10897
Protoss_High_Templar 1 11103
11441
