Protoss_Forge 2 4693
Protoss_Nexus 1 5904
Protoss_Gateway 2 8061
Protoss_Assimilator 2 7791
Protoss_Photon_Cannon 2 10055
Protoss_Cybernetics_Core 1 6251
Protoss_Zealot 8 10429
Protoss_Stargate 1 7703
Protoss_Corsair 3 10671
Protoss_Citadel_of_Adun 1 8707
10671
