Protoss_Forge 1 3387
Protoss_Photon_Cannon 4 9925
Protoss_Nexus 1 7043
Protoss_Gateway 1 6002
Protoss_Assimilator 2 7030
Protoss_Zealot 3 9127
Protoss_Cybernetics_Core 1 7036
Protoss_Stargate 1 8361
Protoss_Dragoon 1 8153
Protoss_Robotics_Facility 1 9643
Protoss_Corsair 4 10925
Protoss_Robotics_Support_Bay 1 9807
10925
