Protoss_Forge 1 3496
Protoss_Photon_Cannon 4 10936
Protoss_Nexus 1 6993
Protoss_Gateway 1 6085
Protoss_Assimilator 2 7219
Protoss_Zealot 6 9802
Protoss_Cybernetics_Core 1 7081
Protoss_Stargate 2 9276
Protoss_Corsair 6 10853
Protoss_Citadel_of_Adun 1 10941
10941
