Protoss_Nexus 1 5569
Protoss_Forge 1 3957
Protoss_Photon_Cannon 2 9825
Protoss_Gateway 3 8548
Protoss_Assimilator 3 9445
Protoss_Cybernetics_Core 1 6435
Protoss_Zealot 12 10555
Protoss_Stargate 1 7945
Protoss_Citadel_of_Adun 1 8208
Protoss_Corsair 4 10685
Protoss_Ground_Weapons_1 1 9681
10685
