Protoss_Forge 1 2942
Protoss_Photon_Cannon 3 9771
Protoss_Nexus 1 6333
Protoss_Gateway 4 10883
Protoss_Assimilator 2 7238
Protoss_Zealot 4 8093
Protoss_Cybernetics_Core 1 6963
Protoss_Stargate 1 8349
Protoss_Citadel_of_Adun 1 8451
Protoss_Corsair 1 9043
Protoss_Templar_Archives 1 9615
Protoss_Dark_Templar 1 10373
Protoss_High_Templar 1 11125
11125
