Protoss_Gateway 2 3955
Protoss_Zealot 10 10957
Protoss_Forge 1 5691
Protoss_Nexus 1 8933
Protoss_Photon_Cannon 2 9186
Protoss_Assimilator 2 8179
Protoss_Cybernetics_Core 1 8455
Protoss_Stargate 1 9805
Protoss_Citadel_of_Adun 1 10095
Protoss_Corsair 1 10231
Protoss_Templar_Archives 1 11089
11089
