Protoss_Forge 1 3645
Protoss_Photon_Cannon 4 10098
Protoss_Nexus 1 6977
Protoss_Gateway 3 11234
Protoss_Assimilator 2 7754
Protoss_Zealot 3 10535
Protoss_Cybernetics_Core 1 7104
Protoss_Stargate 1 8599
Protoss_Dragoon 2 9087
Protoss_Citadel_of_Adun 1 9149
Protoss_Corsair 3 10651
Protoss_Templar_Archives 1 10262
Protoss_Dark_Templar 1 11009
11234
