Protoss_Forge 1 3330
Protoss_Nexus 1 6308
Protoss_Gateway 4 10171
Protoss_Assimilator 2 6729
Protoss_Photon_Cannon 3 10915
Protoss_Cybernetics_Core 1 6341
Protoss_Zealot 4 9157
Protoss_Stargate 1 7675
Protoss_Citadel_of_Adun 1 8070
Protoss_Dragoon 1 7895
Protoss_Corsair 4 10709
Protoss_Templar_Archives 1 9162
Protoss_Dark_Templar 1 10013
10915
