Protoss_Forge 1 2921
Protoss_Photon_Cannon 3 10084
Protoss_Nexus 1 7094
Protoss_Gateway 5 9999
Protoss_Assimilator 3 10958
Protoss_Zealot 11 10789
Protoss_Cybernetics_Core 1 7273
Protoss_Stargate 1 8779
Protoss_Dragoon 1 8459
Protoss_Citadel_of_Adun 1 9206
10958
