Protoss_Forge 1 3412
Protoss_Photon_Cannon 3 10037
Protoss_Nexus 1 6343
Protoss_Gateway 4 10921
Protoss_Assimilator 2 8323
Protoss_Cybernetics_Core 1 6361
Protoss_Zealot 4 8783
Protoss_Stargate 1 7593
Protoss_Citadel_of_Adun 1 8025
Protoss_Corsair 3 10173
Protoss_Templar_Archives 1 9321
Protoss_High_Templar 2 11049
11049
