Protoss_Forge 1 3555
Protoss_Nexus 1 6145
Protoss_Photon_Cannon 3 10438
Protoss_Gateway 2 8522
Protoss_Assimilator 2 9701
Protoss_Cybernetics_Core 1 7317
Protoss_Zealot 9 10735
Protoss_Stargate 1 8581
Protoss_Citadel_of_Adun 1 9048
Protoss_Corsair 2 9899
Protoss_Templar_Archives 1 11289
11289
