Protoss_Forge 1 3278
Protoss_Nexus 1 6118
Protoss_Photon_Cannon 2 10631
Protoss_Gateway 3 9808
Protoss_Assimilator 2 7801
Protoss_Zealot 8 10729
Protoss_Cybernetics_Core 1 6993
Protoss_Stargate 1 8328
Protoss_Citadel_of_Adun 1 8827
Protoss_Corsair 2 9981
Protoss_Templar_Archives 1 10543
10729
