Protoss_Forge 1 3233
Protoss_Photon_Cannon 7 11110
Protoss_Nexus 1 7037
Protoss_Gateway 1 5921
Protoss_Assimilator 2 7583
Protoss_Cybernetics_Core 1 6956
Protoss_Zealot 4 9321
Protoss_Stargate 1 8208
Protoss_Citadel_of_Adun 1 8587
Protoss_Dragoon 1 8803
Protoss_Corsair 2 9983
Protoss_Templar_Archives 1 9673
Protoss_High_Templar 1 10587
11110
