Protoss_Forge 1 3077
Protoss_Photon_Cannon 5 8626
Protoss_Nexus 1 6708
Protoss_Gateway 6 11343
Protoss_Assimilator 2 7659
Protoss_Cybernetics_Core 1 6823
Protoss_Zealot 4 10447
Protoss_Stargate 1 8213
Protoss_Citadel_of_Adun 1 8533
Protoss_Corsair 1 8683
Protoss_Templar_Archives 1 9805
Protoss_Robotics_Facility 1 11173
Protoss_High_Templar 2 10551
Protoss_Dark_Templar 1 10629
11343
