Protoss_Forge 1 3147
Protoss_Nexus 1 6037
Protoss_Photon_Cannon 3 10955
Protoss_Gateway 1 5556
Protoss_Assimilator 2 9166
Protoss_Zealot 4 10121
Protoss_Cybernetics_Core 1 7081
Protoss_Stargate 1 8908
Protoss_Corsair 2 10187
10955
