Protoss_Forge 1 3134
Protoss_Nexus 1 6081
Protoss_Photon_Cannon 1 4765
Protoss_Gateway 5 10927
Protoss_Assimilator 2 5990
Protoss_Cybernetics_Core 1 6313
Protoss_Zealot 1 6431
Protoss_Stargate 1 7687
Protoss_Citadel_of_Adun 1 8032
Protoss_Corsair 2 8783
Protoss_Templar_Archives 1 9033
Protoss_Dark_Templar 2 10657
Protoss_High_Templar 2 10609
10927
