Protoss_Forge 1 3490
Protoss_Nexus 1 6065
Protoss_Photon_Cannon 4 9323
Protoss_Gateway 4 11073
Protoss_Assimilator 2 8487
Protoss_Cybernetics_Core 1 6799
Protoss_Zealot 6 10321
Protoss_Stargate 1 8275
Protoss_Dragoon 1 8303
Protoss_Citadel_of_Adun 1 8904
Protoss_Corsair 1 8761
Protoss_Templar_Archives 1 10525
11073
