Protoss_Forge 2 10002
Protoss_Photon_Cannon 4 9615
Protoss_Nexus 1 7256
Protoss_Gateway 2 10754
Protoss_Assimilator 2 7696
Protoss_Zealot 4 9779
Protoss_Cybernetics_Core 1 7495
Protoss_Stargate 1 8791
Protoss_Citadel_of_Adun 1 9535
10754
