Protoss_Forge 1 3424
Protoss_Photon_Cannon 5 11098
Protoss_Nexus 1 7517
Protoss_Gateway 2 10830
Protoss_Assimilator 2 7739
Protoss_Zealot 4 10659
Protoss_Cybernetics_Core 1 8714
Protoss_Dragoon 1 9545
Protoss_Citadel_of_Adun 1 9924
Protoss_Templar_Archives 1 11097
11098
