Protoss_Nexus 1 5737
Protoss_Forge 1 4126
Protoss_Photon_Cannon 5 10577
Protoss_Gateway 3 10247
Protoss_Assimilator 2 7746
Protoss_Cybernetics_Core 1 7870
Protoss_Zealot 4 10525
Protoss_Stargate 1 9467
Protoss_Citadel_of_Adun 1 9950
Protoss_Corsair 2 10795
Protoss_Templar_Archives 1 10947
10947
