Protoss_Forge 1 3231
Protoss_Nexus 1 6193
Protoss_Gateway 5 10245
Protoss_Assimilator 2 10706
Protoss_Photon_Cannon 3 8891
Protoss_Zealot 4 10861
Protoss_Cybernetics_Core 1 6879
Protoss_Dragoon 10 11149
Protoss_Robotics_Facility 1 11470
11470
