Protoss_Forge 2 4629
Protoss_Nexus 1 5781
Protoss_Gateway 3 11137
Protoss_Assimilator 2 7267
Protoss_Photon_Cannon 3 10611
Protoss_Cybernetics_Core 1 6466
Protoss_Zealot 8 10913
Protoss_Stargate 1 7789
Protoss_Dragoon 1 7667
Protoss_Citadel_of_Adun 1 8649
Protoss_Corsair 2 9377
Protoss_Templar_Archives 1 10259
11137
