Protoss_Forge 1 3328
Protoss_Nexus 1 6135
Protoss_Photon_Cannon 2 8813
Protoss_Gateway 4 9717
Protoss_Assimilator 2 7201
Protoss_Cybernetics_Core 1 6992
Protoss_Zealot 11 10907
Protoss_Stargate 1 8219
Protoss_Dragoon 1 7789
Protoss_Citadel_of_Adun 1 8543
Protoss_Corsair 1 8629
10907
