Protoss_Gateway 3 10845
Protoss_Zealot 9 10953
Protoss_Nexus 1 6731
Protoss_Forge 1 5183
Protoss_Photon_Cannon 2 7663
Protoss_Assimilator 2 8109
Protoss_Cybernetics_Core 1 9084
Protoss_Citadel_of_Adun 1 10102
Protoss_Templar_Archives 1 11165
11165
