Protoss_Forge 1 2930
Protoss_Photon_Cannon 3 4977
Protoss_Nexus 1 7169
Protoss_Gateway 3 9844
Protoss_Assimilator 2 7182
Protoss_Cybernetics_Core 1 6969
Protoss_Zealot 6 9833
Protoss_Citadel_of_Adun 1 8048
Protoss_Stargate 1 8715
Protoss_Corsair 3 10903
Protoss_Templar_Archives 1 10745
10903
