Protoss_Gateway 3 11412
Protoss_Zealot 11 10689
Protoss_Nexus 1 7130
Protoss_Forge 1 5636
Protoss_Photon_Cannon 5 9303
Protoss_Assimilator 2 10410
Protoss_Cybernetics_Core 1 8065
Protoss_Dragoon 2 10789
Protoss_Robotics_Facility 1 10279
Protoss_Shield_Battery 1 9242
Protoss_Citadel_of_Adun 1 10716
Protoss_Stargate 1 11058
11412
