Protoss_Forge 1 3177
Protoss_Nexus 1 6351
Protoss_Gateway 4 9243
Protoss_Assimilator 2 8974
Protoss_Zealot 10 10661
Protoss_Photon_Cannon 4 10651
Protoss_Cybernetics_Core 1 6772
Protoss_Dragoon 1 7631
Protoss_Citadel_of_Adun 1 7975
Protoss_Templar_Archives 1 9931
Protoss_High_Templar 2 10869
Protoss_Dark_Templar 1 10879
Protoss_Ground_Weapons_1 1 9783
10879
