Protoss_Forge 1 3025
Protoss_Photon_Cannon 3 7500
Protoss_Nexus 1 7371
Protoss_Gateway 5 9940
Protoss_Assimilator 2 7995
Protoss_Cybernetics_Core 1 7663
Protoss_Zealot 12 10875
Protoss_Citadel_of_Adun 1 8657
Protoss_Templar_Archives 1 10442
10875
