Protoss_Forge 1 3193
Protoss_Photon_Cannon 4 9391
Protoss_Nexus 1 6897
Protoss_Gateway 2 10745
Protoss_Assimilator 2 7803
Protoss_Cybernetics_Core 1 6743
Protoss_Zealot 3 9861
Protoss_Stargate 1 8119
Protoss_Corsair 3 9977
Protoss_Citadel_of_Adun 1 10101
Protoss_Templar_Archives 1 11195
11195
