Protoss_Gateway 3 10316
Protoss_Zealot 11 10819
Protoss_Nexus 1 7054
Protoss_Forge 1 5524
Protoss_Photon_Cannon 2 7735
Protoss_Assimilator 2 8090
Protoss_Cybernetics_Core 1 8496
Protoss_Stargate 1 9772
Protoss_Citadel_of_Adun 1 9713
Protoss_Dragoon 1 9487
Protoss_Corsair 1 10197
Protoss_Templar_Archives 1 10775
10819
