Protoss_Forge 2 6428
Protoss_Photon_Cannon 5 7494
Protoss_Gateway 2 8568
Protoss_Assimilator 1 6198
Protoss_Zealot 2 9265
Protoss_Cybernetics_Core 1 9622
Protoss_Robotics_Facility 1 11149
Protoss_Dragoon 1 10541
11149
