Protoss_Forge 1 3073
Protoss_Nexus 1 6033
Protoss_Photon_Cannon 2 5036
Protoss_Gateway 2 9994
Protoss_Assimilator 2 7396
Protoss_Cybernetics_Core 1 6783
Protoss_Zealot 7 10663
Protoss_Stargate 1 8029
Protoss_Dragoon 1 7873
Protoss_Corsair 4 10313
Protoss_Citadel_of_Adun 1 9286
Protoss_Templar_Archives 1 10591
10663
