Protoss_Forge 1 3703
Protoss_Nexus 1 6147
Protoss_Photon_Cannon 2 11071
Protoss_Gateway 2 8661
Protoss_Assimilator 2 6785
Protoss_Cybernetics_Core 1 6455
Protoss_Zealot 10 10699
Protoss_Stargate 1 7793
Protoss_Citadel_of_Adun 1 8267
Protoss_Corsair 1 8415
Protoss_Templar_Archives 1 10187
11071
