Protoss_Forge 1 3283
Protoss_Photon_Cannon 2 4453
Protoss_Nexus 1 7478
Protoss_Gateway 3 9972
Protoss_Assimilator 2 7749
Protoss_Zealot 6 10571
Protoss_Cybernetics_Core 1 7783
Protoss_Stargate 1 9163
Protoss_Citadel_of_Adun 1 9112
Protoss_Corsair 3 10865
Protoss_Templar_Archives 1 10292
Protoss_Dark_Templar 2 11146
11146
