Protoss_Forge 1 3375
Protoss_Photon_Cannon 2 8441
Protoss_Nexus 1 6427
Protoss_Gateway 2 8031
Protoss_Assimilator 2 7877
Protoss_Cybernetics_Core 1 6533
Protoss_Zealot 10 10829
Protoss_Stargate 1 7856
Protoss_Citadel_of_Adun 1 7851
Protoss_Corsair 3 10481
10829
