Protoss_Gateway 1 3286
Protoss_Assimilator 1 3278
Protoss_Zealot 4 7203
Protoss_Cybernetics_Core 1 4913
Protoss_Stargate 1 6225
Protoss_Dragoon 1 6071
Protoss_Corsair 1 6773
Protoss_Citadel_of_Adun 1 7433
Protoss_Forge 1 7717
Protoss_Templar_Archives 1 8472
Protoss_Photon_Cannon 3 10116
Protoss_Dark_Templar 2 10031
Protoss_Nexus 1 12369
Protoss_High_Templar 1 10867
12369
