Protoss_Forge 1 2953
Protoss_Nexus 1 6103
Protoss_Photon_Cannon 4 10592
Protoss_Gateway 3 10101
Protoss_Assimilator 2 7322
Protoss_Zealot 8 10645
Protoss_Cybernetics_Core 1 7126
Protoss_Stargate 1 8508
Protoss_Citadel_of_Adun 1 9133
Protoss_Corsair 3 10473
10645
