Protoss_Forge 1 2803
Protoss_Nexus 1 5895
Protoss_Photon_Cannon 2 4825
Protoss_Gateway 4 9312
Protoss_Assimilator 2 9268
Protoss_Zealot 13 10820
Protoss_Cybernetics_Core 1 7300
Protoss_Citadel_of_Adun 1 8399
Protoss_Templar_Archives 1 10170
10820
