Protoss_Forge 1 3112
Protoss_Nexus 1 6285
Protoss_Gateway 4 10839
Protoss_Assimilator 2 7313
Protoss_Photon_Cannon 3 10019
Protoss_Cybernetics_Core 1 6433
Protoss_Zealot 5 10663
Protoss_Stargate 1 7817
Protoss_Citadel_of_Adun 1 8372
Protoss_Corsair 2 9195
Protoss_Templar_Archives 1 9391
Protoss_High_Templar 2 10941
10941
