Protoss_Forge 1 3574
Protoss_Photon_Cannon 3 10936
Protoss_Nexus 1 6920
Protoss_Gateway 4 10491
Protoss_Assimilator 2 6778
Protoss_Cybernetics_Core 1 6719
Protoss_Zealot 4 9633
Protoss_Stargate 1 7990
Protoss_Dragoon 1 8217
Protoss_Corsair 2 9078
Protoss_Citadel_of_Adun 1 8915
Protoss_Templar_Archives 1 9901
Protoss_High_Templar 2 10745
10936
