Protoss_Forge 1 2971
Protoss_Photon_Cannon 5 11188
Protoss_Nexus 1 7149
Protoss_Gateway 3 9105
Protoss_Assimilator 2 8393
Protoss_Cybernetics_Core 1 7101
Protoss_Zealot 6 9963
Protoss_Citadel_of_Adun 1 8214
Protoss_Dragoon 1 8165
Protoss_Templar_Archives 1 9744
Protoss_High_Templar 2 10569
Protoss_Dark_Templar 1 10805
11188
