Protoss_Forge 1 3714
Protoss_Nexus 1 6175
Protoss_Photon_Cannon 3 10796
Protoss_Gateway 4 11292
Protoss_Assimilator 2 8208
Protoss_Cybernetics_Core 1 6977
Protoss_Zealot 3 9299
Protoss_Stargate 1 8283
Protoss_Corsair 2 9661
Protoss_Citadel_of_Adun 1 9547
Protoss_Templar_Archives 1 10581
11292
