Protoss_Forge 1 3194
Protoss_Photon_Cannon 5 10402
Protoss_Nexus 1 6389
Protoss_Gateway 1 5753
Protoss_Assimilator 2 7889
Protoss_Zealot 4 10239
Protoss_Cybernetics_Core 1 6829
Protoss_Dragoon 1 7715
Protoss_Stargate 1 8257
Protoss_Corsair 4 10559
Protoss_Citadel_of_Adun 1 9361
Protoss_Templar_Archives 1 10793
10793
