Protoss_Forge 1 3343
Protoss_Photon_Cannon 2 4315
Protoss_Nexus 1 7141
Protoss_Gateway 1 6079
Protoss_Assimilator 1 5856
Protoss_Zealot 3 8509
Protoss_Cybernetics_Core 1 7318
8509
