Protoss_Forge 1 2843
Protoss_Photon_Cannon 3 10793
Protoss_Nexus 1 7065
Protoss_Gateway 2 10390
Protoss_Assimilator 2 10034
Protoss_Cybernetics_Core 1 6909
Protoss_Zealot 5 9359
Protoss_Stargate 1 8461
Protoss_Citadel_of_Adun 1 8431
Protoss_Corsair 1 8941
Protoss_Templar_Archives 1 9947
Protoss_Robotics_Facility 1 11135
Protoss_Dark_Templar 1 10843
11135
