Protoss_Forge 1 3157
Protoss_Nexus 1 6311
Protoss_Photon_Cannon 7 10645
Protoss_Gateway 1 5825
Protoss_Assimilator 2 9463
Protoss_Cybernetics_Core 1 6851
Protoss_Stargate 1 8090
Protoss_Robotics_Facility 1 9290
Protoss_Corsair 3 10521
Protoss_Shuttle 1 10193
Protoss_Robotics_Support_Bay 1 9769
Protoss_Reaver 1 11565
11565
