Protoss_Forge 1 3228
Protoss_Nexus 1 6137
Protoss_Photon_Cannon 1 4752
Protoss_Gateway 2 10170
Protoss_Assimilator 2 7797
Protoss_Cybernetics_Core 1 6535
Protoss_Zealot 8 10955
Protoss_Stargate 1 8106
Protoss_Corsair 3 10387
Protoss_Citadel_of_Adun 1 9529
Protoss_Templar_Archives 1 10701
10955
