Protoss_Gateway 3 10344
Protoss_Zealot 12 10710
Protoss_Assimilator 1 4497
Protoss_Cybernetics_Core 1 5747
Protoss_Dragoon 1 6661
Protoss_Stargate 1 7362
Protoss_Forge 1 6902
Protoss_Corsair 1 7896
Protoss_Citadel_of_Adun 1 8906
Protoss_Templar_Archives 1 10868
10868
