Protoss_Forge 1 3019
Protoss_Photon_Cannon 2 6148
Protoss_Nexus 1 9162
Protoss_Gateway 3 11059
Protoss_Assimilator 2 8941
Protoss_Zealot 3 10709
Protoss_Cybernetics_Core 1 9085
Protoss_Stargate 1 10384
Protoss_Citadel_of_Adun 1 10317
Protoss_Corsair 1 10857
11059
