Protoss_Gateway 1 3335
Protoss_Zealot 11 10751
Protoss_Nexus 1 7273
Protoss_Assimilator 2 9615
Protoss_Forge 2 6662
Protoss_Cybernetics_Core 1 8638
Protoss_Photon_Cannon 2 9040
Protoss_Stargate 1 9957
Protoss_Dragoon 1 9637
Protoss_Citadel_of_Adun 1 10655
Protoss_Corsair 1 10441
10751
