Protoss_Gateway 2 4127
Protoss_Zealot 11 10772
Protoss_Assimilator 1 4542
Protoss_Cybernetics_Core 1 5546
Protoss_Stargate 1 7051
Protoss_Dragoon 1 7141
Protoss_Corsair 1 7466
Protoss_Citadel_of_Adun 1 8245
Protoss_Templar_Archives 1 9238
10772
