Protoss_Forge 1 3595
Protoss_Nexus 1 6160
Protoss_Photon_Cannon 2 11057
Protoss_Gateway 2 9671
Protoss_Assimilator 2 7301
Protoss_Cybernetics_Core 1 6591
Protoss_Zealot 10 10803
Protoss_Stargate 1 7975
Protoss_Citadel_of_Adun 1 8487
Protoss_Corsair 1 8385
Protoss_Templar_Archives 1 10057
Protoss_Robotics_Facility 1 10792
11057
