Protoss_Nexus 1 5551
Protoss_Forge 1 4090
Protoss_Gateway 1 5421
Protoss_Photon_Cannon 2 10363
Protoss_Assimilator 2 7222
Protoss_Zealot 8 10391
Protoss_Cybernetics_Core 1 7061
Protoss_Stargate 1 8564
Protoss_Robotics_Facility 1 9355
Protoss_Corsair 4 10839
Protoss_Shuttle 1 10171
Protoss_Robotics_Support_Bay 1 9599
Protoss_Reaver 1 11313
11313
