Protoss_Forge 2 9001
Protoss_Photon_Cannon 3 9951
Protoss_Gateway 3 9757
Protoss_Assimilator 1 5385
Protoss_Cybernetics_Core 1 6755
Protoss_Zealot 7 10837
Protoss_Dragoon 1 7501
Protoss_Stargate 1 8081
Protoss_Citadel_of_Adun 1 8195
Protoss_Corsair 1 8495
Protoss_Templar_Archives 1 10391
10837
