Protoss_Gateway 2 9420
Protoss_Assimilator 1 3371
Protoss_Zealot 7 10286
Protoss_Forge 1 4768
Protoss_Cybernetics_Core 1 6694
Protoss_Stargate 1 7943
Protoss_Dragoon 1 7561
Protoss_Citadel_of_Adun 1 8242
Protoss_Corsair 1 8366
Protoss_Templar_Archives 1 9891
Protoss_Photon_Cannon 2 10273
Protoss_Ground_Weapons_1 1 8826
Protoss_Robotics_Facility 1 11553
Protoss_High_Templar 1 10861
11553
