Protoss_Forge 1 3046
Protoss_Nexus 1 6097
Protoss_Photon_Cannon 3 10280
Protoss_Gateway 2 9805
Protoss_Assimilator 2 8317
Protoss_Cybernetics_Core 1 6869
Protoss_Zealot 9 10931
Protoss_Stargate 1 8201
Protoss_Citadel_of_Adun 1 8273
Protoss_Corsair 3 10593
10931
