Protoss_Gateway 2 3963
Protoss_Zealot 10 9571
Protoss_Forge 1 6109
Protoss_Photon_Cannon 4 10933
Protoss_Assimilator 1 6914
Protoss_Cybernetics_Core 1 7768
Protoss_Citadel_of_Adun 1 9086
Protoss_Stargate 2 10909
Protoss_Corsair 1 10446
10933
