Protoss_Forge 1 3382
Protoss_Nexus 1 6176
Protoss_Gateway 1 5118
Protoss_Photon_Cannon 3 9215
Protoss_Assimilator 2 7486
Protoss_Cybernetics_Core 1 6491
Protoss_Zealot 1 6283
Protoss_Stargate 2 11030
Protoss_Robotics_Facility 1 9304
Protoss_Corsair 4 10605
Protoss_Shuttle 1 10165
Protoss_Robotics_Support_Bay 1 9934
Protoss_Reaver 1 11635
11635
