Protoss_Forge 1 3251
Protoss_Photon_Cannon 2 4559
Protoss_Nexus 1 7146
Protoss_Gateway 1 6115
Protoss_Assimilator 2 7645
Protoss_Cybernetics_Core 1 7163
Protoss_Zealot 7 10793
Protoss_Stargate 1 8407
Protoss_Robotics_Facility 1 9750
Protoss_Corsair 3 10223
Protoss_Robotics_Support_Bay 1 10020
10793
