Protoss_Nexus 1 5657
Protoss_Forge 1 4027
Protoss_Gateway 1 5297
Protoss_Photon_Cannon 3 10336
Protoss_Assimilator 2 7124
Protoss_Zealot 7 10807
Protoss_Cybernetics_Core 1 6795
Protoss_Stargate 2 8681
Protoss_Corsair 7 10639
Protoss_Citadel_of_Adun 1 9131
Protoss_Templar_Archives 1 11337
11337
