Protoss_Nexus 1 5898
Protoss_Gateway 1 4913
Protoss_Assimilator 2 6231
Protoss_Cybernetics_Core 1 5953
Protoss_Stargate 2 7748
Protoss_Forge 1 7557
Protoss_Corsair 8 10486
Protoss_Photon_Cannon 3 10393
Protoss_Robotics_Facility 1 10882
10882
