Protoss_Forge 1 3565
Protoss_Nexus 1 6257
Protoss_Photon_Cannon 5 11044
Protoss_Gateway 3 10031
Protoss_Assimilator 2 6980
Protoss_Cybernetics_Core 1 6884
Protoss_Stargate 1 8124
Protoss_Zealot 4 9275
Protoss_Citadel_of_Adun 1 8436
Protoss_Corsair 4 10501
Protoss_Templar_Archives 1 9445
Protoss_Dark_Templar 1 10205
Protoss_High_Templar 2 10841
11044
