Protoss_Forge 1 3927
Protoss_Nexus 1 6309
Protoss_Photon_Cannon 4 10655
Protoss_Gateway 1 5678
Protoss_Assimilator 2 8629
Protoss_Zealot 7 10174
Protoss_Cybernetics_Core 1 6713
Protoss_Stargate 1 8345
Protoss_Citadel_of_Adun 1 8885
Protoss_Corsair 3 10911
Protoss_Templar_Archives 1 10248
10911
