Protoss_Nexus 1 5801
Protoss_Forge 1 4255
Protoss_Photon_Cannon 3 6225
Protoss_Gateway 1 6409
Protoss_Assimilator 2 9315
Protoss_Zealot 5 10743
Protoss_Cybernetics_Core 1 9033
Protoss_Stargate 2 11638
Protoss_Citadel_of_Adun 1 10778
11638
