Protoss_Forge 1 3303
Protoss_Photon_Cannon 2 4404
Protoss_Nexus 1 7225
Protoss_Gateway 6 10805
Protoss_Assimilator 2 7001
Protoss_Cybernetics_Core 1 7165
Protoss_Zealot 3 9107
Protoss_Citadel_of_Adun 1 8224
Protoss_Dragoon 1 8251
Protoss_Templar_Archives 1 9249
Protoss_Dark_Templar 2 10243
Protoss_High_Templar 2 11175
11175
