Protoss_Forge 1 3380
Protoss_Photon_Cannon 3 6439
Protoss_Nexus 1 7143
Protoss_Gateway 4 10979
Protoss_Assimilator 1 5791
Protoss_Cybernetics_Core 1 7943
Protoss_Citadel_of_Adun 1 9091
Protoss_Zealot 5 10837
Protoss_Dragoon 1 9639
10979
