Protoss_Forge 1 3182
Protoss_Nexus 1 6059
Protoss_Gateway 2 8401
Protoss_Photon_Cannon 2 10920
Protoss_Assimilator 2 7295
Protoss_Cybernetics_Core 1 6075
Protoss_Stargate 1 7415
Protoss_Zealot 9 10365
Protoss_Citadel_of_Adun 2 8695
Protoss_Corsair 3 10603
Protoss_Templar_Archives 1 9679
Protoss_High_Templar 1 11165
11165
