Protoss_Gateway 1 2949
Protoss_Zealot 5 7033
Protoss_Assimilator 1 4327
Protoss_Cybernetics_Core 1 6300
Protoss_Stargate 1 7656
Protoss_Dragoon 1 8195
Protoss_Corsair 4 10629
Protoss_Citadel_of_Adun 1 9435
Protoss_Templar_Archives 1 10460
Protoss_Forge 1 9997
Protoss_Photon_Cannon 1 11189
11189
