Protoss_Forge 1 3592
Protoss_Nexus 1 6176
Protoss_Photon_Cannon 3 10721
Protoss_Gateway 2 9758
Protoss_Assimilator 2 7413
Protoss_Cybernetics_Core 1 7341
Protoss_Zealot 6 10791
Protoss_Stargate 1 8573
Protoss_Citadel_of_Adun 1 8777
Protoss_Corsair 2 9687
Protoss_Templar_Archives 1 10422
10791
