Protoss_Forge 1 3089
Protoss_Photon_Cannon 5 10444
Protoss_Nexus 1 6897
Protoss_Gateway 3 10129
Protoss_Assimilator 2 7600
Protoss_Cybernetics_Core 1 6769
Protoss_Zealot 9 10669
Protoss_Stargate 1 8012
Protoss_Corsair 1 8423
Protoss_Citadel_of_Adun 1 9055
Protoss_Templar_Archives 1 10510
10669
