Protoss_Nexus 1 5633
Protoss_Gateway 2 4969
Protoss_Zealot 14 10941
Protoss_Forge 1 6143
Protoss_Assimilator 2 8816
Protoss_Photon_Cannon 3 9223
Protoss_Cybernetics_Core 1 8422
Protoss_Stargate 1 10048
Protoss_Citadel_of_Adun 1 10506
Protoss_Corsair 1 10505
10941
