Protoss_Forge 1 2994
Protoss_Nexus 2 10998
Protoss_Photon_Cannon 3 10319
Protoss_Assimilator 2 6874
Protoss_Gateway 1 6148
Protoss_Cybernetics_Core 1 7222
Protoss_Zealot 1 7066
Protoss_Robotics_Facility 1 8820
Protoss_Stargate 1 9047
Protoss_Shuttle 1 9781
Protoss_Corsair 2 10456
Protoss_Robotics_Support_Bay 1 9403
10998
