Protoss_Forge 2 6939
Protoss_Photon_Cannon 8 11155
Protoss_Nexus 1 6773
Protoss_Assimilator 2 8449
Protoss_Gateway 2 8924
Protoss_Zealot 6 10716
Protoss_Cybernetics_Core 1 8045
Protoss_Citadel_of_Adun 1 9291
Protoss_Dragoon 1 9166
Protoss_Templar_Archives 1 10628
11155
