Protoss_Nexus 1 5721
Protoss_Forge 1 4088
Protoss_Gateway 3 8913
Protoss_Photon_Cannon 1 5348
Protoss_Assimilator 1 5327
Protoss_Zealot 6 9406
Protoss_Cybernetics_Core 1 6797
Protoss_Citadel_of_Adun 1 7793
Protoss_Ground_Weapons_1 1 9621
9621
