Protoss_Forge 1 3319
Protoss_Nexus 1 6152
Protoss_Gateway 4 9625
Protoss_Assimilator 2 7535
Protoss_Photon_Cannon 2 10295
Protoss_Cybernetics_Core 1 6408
Protoss_Zealot 10 10841
Protoss_Dragoon 1 7267
Protoss_Citadel_of_Adun 1 7601
Protoss_Templar_Archives 1 9995
Protoss_Dark_Templar 2 11119
11119
