Protoss_Gateway 2 3972
Protoss_Zealot 10 8613
Protoss_Assimilator 1 5573
Protoss_Cybernetics_Core 1 7393
Protoss_Forge 1 7765
Protoss_Photon_Cannon 1 9474
Protoss_Citadel_of_Adun 1 10450
10450
