Protoss_Forge 1 3040
Protoss_Photon_Cannon 5 10918
Protoss_Nexus 1 6695
Protoss_Gateway 3 8616
Protoss_Assimilator 2 9283
Protoss_Cybernetics_Core 1 7185
Protoss_Zealot 9 9796
Protoss_Citadel_of_Adun 1 8368
Protoss_Templar_Archives 1 9913
Protoss_High_Templar 2 10716
Protoss_Dark_Templar 1 10826
10918
