Protoss_Nexus 1 6080
Protoss_Forge 1 4518
Protoss_Gateway 4 10554
Protoss_Photon_Cannon 2 11123
Protoss_Assimilator 2 6998
Protoss_Zealot 7 10396
Protoss_Cybernetics_Core 1 6948
Protoss_Stargate 1 8213
Protoss_Citadel_of_Adun 1 8269
Protoss_Dragoon 1 8876
Protoss_Corsair 2 10051
Protoss_Templar_Archives 1 10903
Protoss_Robotics_Facility 1 11693
11693
