Protoss_Forge 1 3177
Protoss_Photon_Cannon 3 10698
Protoss_Nexus 1 7073
Protoss_Gateway 4 11163
Protoss_Assimilator 2 9358
Protoss_Cybernetics_Core 1 6908
Protoss_Zealot 10 10301
Protoss_Citadel_of_Adun 1 8019
Protoss_Templar_Archives 1 10554
11163
