Protoss_Gateway 2 8367
Protoss_Assimilator 1 3608
Protoss_Zealot 5 8796
Protoss_Cybernetics_Core 1 5396
Protoss_Stargate 1 6661
Protoss_Dragoon 1 7118
Protoss_Corsair 2 8261
Protoss_Citadel_of_Adun 1 8119
Protoss_Templar_Archives 1 9314
Protoss_Forge 1 9118
Protoss_Dark_Templar 2 10106
Protoss_Photon_Cannon 2 11093
Protoss_Nexus 1 12455
Protoss_High_Templar 2 10891
12455
