Protoss_Nexus 1 5964
Protoss_Forge 1 4378
Protoss_Photon_Cannon 2 8853
Protoss_Gateway 5 11362
Protoss_Assimilator 1 5777
Protoss_Zealot 5 10706
Protoss_Cybernetics_Core 1 8105
Protoss_Citadel_of_Adun 1 9319
Protoss_Robotics_Facility 1 11053
11362
