Protoss_Forge 1 3035
Protoss_Photon_Cannon 4 10778
Protoss_Nexus 1 6758
Protoss_Gateway 4 9861
Protoss_Assimilator 2 8056
Protoss_Zealot 7 10756
Protoss_Cybernetics_Core 1 7585
Protoss_Stargate 1 9368
Protoss_Dragoon 1 9046
Protoss_Corsair 1 9786
Protoss_Citadel_of_Adun 1 11303
11303
