Protoss_Forge 1 3386
Protoss_Photon_Cannon 2 4504
Protoss_Nexus 1 6845
Protoss_Gateway 3 10067
Protoss_Assimilator 2 8073
Protoss_Zealot 5 9787
Protoss_Cybernetics_Core 1 7367
Protoss_Stargate 1 8610
Protoss_Citadel_of_Adun 1 8930
Protoss_Corsair 2 10205
Protoss_Templar_Archives 1 9935
Protoss_Dark_Templar 3 10907
10907
