Protoss_Nexus 1 6058
Protoss_Forge 1 4593
Protoss_Photon_Cannon 2 5983
Protoss_Assimilator 2 9243
Protoss_Gateway 3 9225
Protoss_Cybernetics_Core 1 7944
Protoss_Zealot 11 10960
Protoss_Citadel_of_Adun 1 9119
Protoss_Templar_Archives 1 11179
Protoss_Robotics_Facility 1 11753
11753
