Protoss_Gateway 2 6416
Protoss_Assimilator 1 3534
Protoss_Zealot 6 8161
Protoss_Cybernetics_Core 1 5713
Protoss_Citadel_of_Adun 1 7220
Protoss_Dragoon 1 7236
Protoss_Templar_Archives 1 8545
Protoss_Forge 1 8749
Protoss_Dark_Templar 1 9361
Protoss_High_Templar 3 10616
Protoss_Photon_Cannon 2 10143
10616
