Protoss_Forge 1 3099
Protoss_Photon_Cannon 3 11154
Protoss_Nexus 1 7112
Protoss_Gateway 4 9354
Protoss_Assimilator 2 10108
Protoss_Cybernetics_Core 1 6988
Protoss_Zealot 10 10526
Protoss_Citadel_of_Adun 1 8589
Protoss_Templar_Archives 1 10928
11154
