Protoss_Forge 2 8979
Protoss_Photon_Cannon 6 11146
Protoss_Nexus 1 6989
Protoss_Gateway 2 9350
Protoss_Assimilator 2 7859
Protoss_Cybernetics_Core 1 6793
Protoss_Zealot 4 9605
Protoss_Stargate 1 8084
Protoss_Citadel_of_Adun 1 8596
Protoss_Corsair 2 9122
Protoss_Templar_Archives 1 9721
Protoss_Dark_Templar 2 10495
11146
