Protoss_Forge 1 2284
Protoss_Nexus 1 3570
Protoss_Photon_Cannon 1 4046
Protoss_Gateway 1 4559
Protoss_Assimilator 2 5901
Protoss_Zealot 2 6446
Protoss_Cybernetics_Core 1 5639
Protoss_Robotics_Facility 1 7278
7278
