Protoss_Forge 1 3115
Protoss_Nexus 1 6211
Protoss_Gateway 3 9866
Protoss_Assimilator 2 8022
Protoss_Zealot 10 10431
Protoss_Cybernetics_Core 1 6247
Protoss_Photon_Cannon 1 6329
Protoss_Stargate 1 7620
Protoss_Corsair 2 8777
Protoss_Citadel_of_Adun 1 8923
Protoss_Robotics_Facility 1 11232
Protoss_Templar_Archives 1 11240
11240
