Protoss_Nexus 1 5751
Protoss_Forge 1 4329
Protoss_Photon_Cannon 4 10957
Protoss_Gateway 4 10227
Protoss_Assimilator 2 9515
Protoss_Zealot 9 10779
Protoss_Cybernetics_Core 1 7329
Protoss_Citadel_of_Adun 1 8544
Protoss_Templar_Archives 1 9720
10957
