Protoss_Gateway 3 10085
Protoss_Zealot 13 10916
Protoss_Nexus 1 7393
Protoss_Forge 1 6194
Protoss_Photon_Cannon 2 7586
Protoss_Assimilator 1 9223
Protoss_Cybernetics_Core 1 10619
10916
