Protoss_Forge 1 3401
Protoss_Photon_Cannon 4 11069
Protoss_Nexus 1 7519
Protoss_Gateway 3 9618
Protoss_Assimilator 2 7937
Protoss_Cybernetics_Core 1 7593
Protoss_Zealot 3 10556
Protoss_Citadel_of_Adun 1 8618
Protoss_Stargate 1 9601
Protoss_Dragoon 1 9211
Protoss_Templar_Archives 1 9968
Protoss_Corsair 2 10658
Protoss_High_Templar 2 11016
11069
