Protoss_Gateway 1 3251
Protoss_Zealot 9 10381
Protoss_Forge 1 4711
Protoss_Photon_Cannon 3 9997
Protoss_Nexus 1 10235
Protoss_Assimilator 1 8589
Protoss_Cybernetics_Core 1 9995
Protoss_Dragoon 1 10833
10833
