Protoss_Forge 1 3014
Protoss_Photon_Cannon 1 4619
Protoss_Gateway 1 5129
Protoss_Zealot 9 10585
Protoss_Assimilator 1 5929
Protoss_Cybernetics_Core 1 8311
Protoss_Stargate 1 9873
Protoss_Citadel_of_Adun 1 10495
Protoss_Corsair 1 10299
10585
