Protoss_Gateway 3 8375
Protoss_Assimilator 1 3228
Protoss_Zealot 11 10289
Protoss_Cybernetics_Core 1 6325
Protoss_Dragoon 2 10507
Protoss_Stargate 1 7651
Protoss_Corsair 3 9665
Protoss_Citadel_of_Adun 1 10215
10507
