Protoss_Forge 1 3190
Protoss_Photon_Cannon 8 11030
Protoss_Nexus 1 6640
Protoss_Gateway 1 6271
Protoss_Assimilator 2 8237
Protoss_Zealot 5 9247
Protoss_Cybernetics_Core 1 7478
Protoss_Citadel_of_Adun 1 8855
Protoss_Templar_Archives 1 9928
Protoss_High_Templar 1 10679
11030
