Protoss_Forge 1 3245
Protoss_Photon_Cannon 5 10803
Protoss_Nexus 1 6941
Protoss_Gateway 5 11410
Protoss_Assimilator 2 7667
Protoss_Cybernetics_Core 1 6783
Protoss_Zealot 2 7039
Protoss_Citadel_of_Adun 1 7929
Protoss_Templar_Archives 1 9075
Protoss_Dark_Templar 2 9915
Protoss_High_Templar 2 10667
11410
