Protoss_Forge 1 3493
Protoss_Nexus 1 6139
Protoss_Photon_Cannon 4 10239
Protoss_Gateway 2 9337
Protoss_Assimilator 2 8095
Protoss_Cybernetics_Core 1 6771
Protoss_Zealot 6 10465
Protoss_Stargate 1 8201
Protoss_Dragoon 1 7957
Protoss_Citadel_of_Adun 1 8744
Protoss_Corsair 2 9641
Protoss_Templar_Archives 1 10872
10872
