Protoss_Gateway 2 7293
Protoss_Assimilator 1 3528
Protoss_Zealot 7 10635
Protoss_Cybernetics_Core 1 5372
Protoss_Dragoon 1 6161
Protoss_Citadel_of_Adun 1 6618
Protoss_Templar_Archives 1 8604
Protoss_High_Templar 3 10123
Protoss_Forge 1 9219
Protoss_Archon 1 9454
Protoss_Nexus 1 12796
12796
