Protoss_Forge 1 3189
Protoss_Photon_Cannon 3 10535
Protoss_Nexus 1 6961
Protoss_Gateway 3 10553
Protoss_Assimilator 2 7319
Protoss_Cybernetics_Core 1 6959
Protoss_Zealot 5 9867
Protoss_Dragoon 1 7713
Protoss_Stargate 1 8401
Protoss_Citadel_of_Adun 1 9207
Protoss_Corsair 2 9453
Protoss_Templar_Archives 1 10255
10553
