Protoss_Forge 1 3109
Protoss_Nexus 1 6388
Protoss_Gateway 4 9411
Protoss_Photon_Cannon 1 5348
Protoss_Assimilator 2 8002
Protoss_Zealot 8 10551
Protoss_Cybernetics_Core 1 6728
Protoss_Citadel_of_Adun 1 8084
Protoss_Dragoon 1 8658
Protoss_Templar_Archives 1 9763
Protoss_High_Templar 2 10721
10721
