Protoss_Forge 1 3279
Protoss_Photon_Cannon 4 10521
Protoss_Nexus 1 6731
Protoss_Gateway 2 11321
Protoss_Assimilator 2 7493
Protoss_Cybernetics_Core 1 7079
Protoss_Stargate 2 9674
Protoss_Corsair 5 10569
Protoss_Citadel_of_Adun 1 10059
Protoss_Templar_Archives 1 11125
11321
