Protoss_Forge 1 3911
Protoss_Nexus 1 6226
Protoss_Photon_Cannon 4 9639
Protoss_Gateway 3 10516
Protoss_Assimilator 3 10569
Protoss_Cybernetics_Core 1 6982
Protoss_Zealot 3 9259
Protoss_Stargate 1 8313
Protoss_Citadel_of_Adun 1 8488
Protoss_Corsair 4 10755
Protoss_Templar_Archives 1 9525
Protoss_Dark_Templar 1 10427
10755
