Protoss_Forge 1 3464
Protoss_Nexus 1 6729
Protoss_Assimilator 2 7969
Protoss_Gateway 2 6313
Protoss_Photon_Cannon 2 8925
Protoss_Cybernetics_Core 1 7403
Protoss_Zealot 5 9733
Protoss_Dragoon 2 8321
Protoss_Citadel_of_Adun 1 8843
Protoss_Robotics_Facility 1 10305
Protoss_Templar_Archives 1 9979
Protoss_Dark_Templar 2 10761
Protoss_Shuttle 1 11121
Protoss_Ground_Weapons_1 1 9826
11121
