Protoss_Forge 1 3681
Protoss_Photon_Cannon 6 10062
Protoss_Nexus 1 7010
Protoss_Gateway 4 10691
Protoss_Assimilator 2 7267
Protoss_Cybernetics_Core 1 7060
Protoss_Zealot 2 8429
Protoss_Dragoon 1 7807
Protoss_Stargate 1 8626
Protoss_Citadel_of_Adun 1 8855
Protoss_Corsair 2 9645
Protoss_Templar_Archives 1 9916
Protoss_High_Templar 2 10673
10691
