Protoss_Forge 1 3669
Protoss_Nexus 1 6105
Protoss_Photon_Cannon 7 11188
Protoss_Gateway 2 10041
Protoss_Zealot 6 8831
Protoss_Assimilator 2 7912
Protoss_Cybernetics_Core 1 7601
Protoss_Stargate 1 8845
Protoss_Citadel_of_Adun 1 9167
Protoss_Corsair 3 10717
Protoss_Templar_Archives 1 10580
11188
