Protoss_Gateway 1 3278
Protoss_Assimilator 1 3545
Protoss_Zealot 3 5291
Protoss_Cybernetics_Core 1 5488
Protoss_Stargate 1 6776
Protoss_Dragoon 1 6596
Protoss_Citadel_of_Adun 1 7210
Protoss_Corsair 1 7206
Protoss_Templar_Archives 1 8208
Protoss_Forge 1 7883
Protoss_Dark_Templar 1 8961
Protoss_Photon_Cannon 3 11148
Protoss_Nexus 1 11694
Protoss_High_Templar 2 10916
11694
