Protoss_Nexus 1 5827
Protoss_Forge 1 4119
Protoss_Photon_Cannon 2 5321
Protoss_Gateway 6 11013
Protoss_Assimilator 2 8585
Protoss_Zealot 6 10931
Protoss_Cybernetics_Core 1 7273
Protoss_Dragoon 1 8423
Protoss_Stargate 1 9073
Protoss_Citadel_of_Adun 1 9545
Protoss_Corsair 1 9495
11013
