Protoss_Nexus 1 6033
Protoss_Gateway 2 9416
Protoss_Assimilator 2 6709
Protoss_Cybernetics_Core 1 6469
Protoss_Zealot 2 9627
Protoss_Stargate 1 7714
Protoss_Dragoon 1 7829
Protoss_Citadel_of_Adun 1 8249
Protoss_Corsair 4 10413
Protoss_Templar_Archives 1 9242
Protoss_Forge 1 9350
Protoss_Dark_Templar 2 10253
Protoss_Photon_Cannon 2 11193
11193
