Protoss_Gateway 2 8562
Protoss_Zealot 5 9269
Protoss_Assimilator 1 4177
Protoss_Cybernetics_Core 1 5551
Protoss_Stargate 1 6952
Protoss_Dragoon 1 6987
Protoss_Citadel_of_Adun 1 7439
Protoss_Corsair 2 10649
Protoss_Templar_Archives 1 8844
Protoss_Forge 1 9062
Protoss_Dark_Templar 1 9609
Protoss_Photon_Cannon 1 9999
Protoss_High_Templar 1 10393
Protoss_Nexus 1 12680
12680
