Protoss_Forge 1 3332
Protoss_Nexus 1 6259
Protoss_Photon_Cannon 3 8975
Protoss_Gateway 4 10338
Protoss_Assimilator 2 7380
Protoss_Cybernetics_Core 1 7023
Protoss_Zealot 1 6819
Protoss_Dragoon 1 7767
Protoss_Stargate 1 8495
Protoss_Citadel_of_Adun 1 8732
Protoss_Corsair 1 8909
Protoss_Templar_Archives 1 9821
Protoss_Dark_Templar 2 10641
Protoss_Robotics_Facility 1 11775
11775
