Protoss_Forge 1 2981
Protoss_Photon_Cannon 2 9447
Protoss_Nexus 1 6356
Protoss_Gateway 3 10825
Protoss_Assimilator 2 7745
Protoss_Cybernetics_Core 1 6315
Protoss_Zealot 4 9833
Protoss_Dragoon 1 7273
Protoss_Stargate 2 10752
Protoss_Corsair 3 10653
Protoss_Robotics_Facility 1 9975
Protoss_Robotics_Support_Bay 1 10069
Protoss_Reaver 1 11621
11621
