Protoss_Gateway 1 3321
Protoss_Assimilator 1 3253
Protoss_Zealot 8 9173
Protoss_Cybernetics_Core 1 5177
Protoss_Dragoon 1 5985
Protoss_Stargate 1 6740
Protoss_Citadel_of_Adun 1 7182
Protoss_Corsair 1 7339
Protoss_Templar_Archives 1 8671
Protoss_Forge 1 8599
Protoss_Dark_Templar 2 10197
Protoss_Photon_Cannon 3 10559
Protoss_High_Templar 1 10987
10987
