Protoss_Forge 1 2931
Protoss_Photon_Cannon 6 11051
Protoss_Gateway 1 5935
Protoss_Nexus 1 7781
Protoss_Assimilator 2 7991
Protoss_Cybernetics_Core 1 8395
Protoss_Zealot 2 10377
Protoss_Stargate 1 9791
Protoss_Dragoon 1 9525
Protoss_Citadel_of_Adun 1 10103
Protoss_Corsair 1 10355
Protoss_Templar_Archives 1 11150
11150
