Protoss_Forge 1 3145
Protoss_Photon_Cannon 2 4794
Protoss_Nexus 1 7594
Protoss_Gateway 4 11342
Protoss_Assimilator 2 10380
Protoss_Cybernetics_Core 1 7438
Protoss_Dragoon 1 8191
Protoss_Zealot 10 10830
Protoss_Citadel_of_Adun 1 8798
Protoss_Templar_Archives 1 10480
11342
