Protoss_Gateway 1 3406
Protoss_Zealot 3 7479
Protoss_Assimilator 1 4227
Protoss_Cybernetics_Core 1 5521
Protoss_Dragoon 1 6259
Protoss_Stargate 1 6867
Protoss_Forge 1 6955
Protoss_Corsair 1 7317
Protoss_Photon_Cannon 3 10919
Protoss_Nexus 1 11167
11167
