Protoss_Forge 1 3146
Protoss_Photon_Cannon 3 8240
Protoss_Gateway 2 11396
Protoss_Nexus 1 6951
Protoss_Assimilator 2 9809
Protoss_Zealot 5 10409
Protoss_Cybernetics_Core 1 7490
Protoss_Stargate 1 9715
Protoss_Dragoon 1 9415
Protoss_Citadel_of_Adun 1 10098
Protoss_Corsair 1 10421
Protoss_Templar_Archives 1 11194
11396
