Protoss_Gateway 3 11075
Protoss_Assimilator 1 3410
Protoss_Cybernetics_Core 1 4443
Protoss_Zealot 3 6765
Protoss_Citadel_of_Adun 1 5878
Protoss_Templar_Archives 1 6907
Protoss_Stargate 1 7624
Protoss_Dark_Templar 4 10215
Protoss_Corsair 1 8175
11075
