Protoss_Forge 1 2809
Protoss_Nexus 1 6099
Protoss_Gateway 3 8437
Protoss_Photon_Cannon 2 8595
Protoss_Assimilator 2 10637
Protoss_Zealot 13 10519
Protoss_Cybernetics_Core 1 6848
Protoss_Citadel_of_Adun 1 7917
Protoss_Templar_Archives 1 9875
10637
