Protoss_Gateway 2 6899
Protoss_Assimilator 2 10939
Protoss_Zealot 7 8027
Protoss_Cybernetics_Core 1 5257
Protoss_Dragoon 1 5997
Protoss_Citadel_of_Adun 1 6520
Protoss_Templar_Archives 1 8232
Protoss_Forge 1 8647
Protoss_High_Templar 4 9909
Protoss_Archon 1 9241
Protoss_Nexus 1 11738
Protoss_Photon_Cannon 4 10636
11738
