Protoss_Forge 1 3321
Protoss_Nexus 1 6420
Protoss_Gateway 3 10076
Protoss_Photon_Cannon 2 5903
Protoss_Assimilator 2 7049
Protoss_Cybernetics_Core 1 7045
Protoss_Zealot 3 9863
Protoss_Stargate 1 8351
Protoss_Citadel_of_Adun 1 8951
Protoss_Corsair 3 10313
Protoss_Dragoon 1 9181
Protoss_Templar_Archives 1 9953
Protoss_Dark_Templar 1 10773
Protoss_High_Templar 2 10879
10879
