Protoss_Forge 1 3717
Protoss_Nexus 1 6081
Protoss_Photon_Cannon 2 4967
Protoss_Gateway 4 10562
Protoss_Zealot 5 10477
Protoss_Assimilator 2 8526
Protoss_Cybernetics_Core 1 8272
Protoss_Stargate 1 9513
Protoss_Dragoon 1 9051
Protoss_Citadel_of_Adun 1 9797
Protoss_Corsair 2 10549
Protoss_Templar_Archives 1 10809
10809
