Protoss_Forge 1 2271
Protoss_Photon_Cannon 2 4077
Protoss_Nexus 1 3761
Protoss_Gateway 1 4673
Protoss_Assimilator 1 4996
Protoss_Cybernetics_Core 1 5742
Protoss_Zealot 3 7675
7675
