Protoss_Forge 1 3375
Protoss_Nexus 1 6386
Protoss_Gateway 6 10957
Protoss_Assimilator 2 7877
Protoss_Photon_Cannon 2 7190
Protoss_Cybernetics_Core 1 6683
Protoss_Zealot 5 9765
Protoss_Citadel_of_Adun 1 8227
Protoss_Templar_Archives 1 9542
Protoss_Robotics_Facility 1 11617
11617
