Protoss_Forge 1 3470
Protoss_Nexus 1 6381
Protoss_Gateway 4 10366
Protoss_Assimilator 2 7685
Protoss_Photon_Cannon 2 6117
Protoss_Cybernetics_Core 1 6909
Protoss_Zealot 4 10113
Protoss_Stargate 1 8141
Protoss_Citadel_of_Adun 1 8707
Protoss_Dragoon 1 8795
Protoss_Corsair 1 8679
Protoss_Templar_Archives 1 10009
Protoss_Robotics_Facility 1 11317
Protoss_Dark_Templar 1 10955
Protoss_High_Templar 3 11163
11317
