Protoss_Forge 1 3731
Protoss_Photon_Cannon 8 9415
Protoss_Nexus 1 7491
Protoss_Gateway 2 11330
Protoss_Assimilator 2 7698
Protoss_Cybernetics_Core 1 7658
Protoss_Zealot 2 8127
Protoss_Stargate 2 10189
Protoss_Corsair 4 10755
11330
