Protoss_Forge 1 2896
Protoss_Photon_Cannon 3 9824
Protoss_Nexus 1 7018
Protoss_Gateway 2 9196
Protoss_Cybernetics_Core 1 6908
Protoss_Assimilator 2 8414
Protoss_Zealot 8 10395
Protoss_Stargate 1 8813
Protoss_Citadel_of_Adun 1 9537
Protoss_Corsair 1 9486
Protoss_Templar_Archives 1 11138
11138
