Protoss_Forge 1 3319
Protoss_Nexus 1 6085
Protoss_Photon_Cannon 3 11157
Protoss_Gateway 4 11234
Protoss_Assimilator 2 7234
Protoss_Cybernetics_Core 1 6917
Protoss_Stargate 1 8237
Protoss_Citadel_of_Adun 1 8503
Protoss_Corsair 3 9872
Protoss_Zealot 1 8931
Protoss_Templar_Archives 1 9523
Protoss_Dark_Templar 2 10587
11234
