Protoss_Forge 1 3215
Protoss_Photon_Cannon 2 5316
Protoss_Nexus 1 6656
Protoss_Gateway 4 11359
Protoss_Assimilator 1 5874
Protoss_Cybernetics_Core 1 7254
Protoss_Zealot 14 10916
Protoss_Citadel_of_Adun 1 8328
Protoss_Templar_Archives 1 10440
11359
