Protoss_Forge 1 3195
Protoss_Nexus 1 6127
Protoss_Photon_Cannon 1 4731
Protoss_Gateway 4 9345
Protoss_Assimilator 2 8165
Protoss_Zealot 14 10957
Protoss_Cybernetics_Core 1 7011
Protoss_Citadel_of_Adun 1 8587
Protoss_Templar_Archives 1 11261
11261
