Protoss_Nexus 1 5778
Protoss_Forge 1 4450
Protoss_Gateway 3 10743
Protoss_Assimilator 2 6913
Protoss_Photon_Cannon 2 6768
Protoss_Cybernetics_Core 1 6628
Protoss_Zealot 1 7171
Protoss_Stargate 2 9366
Protoss_Robotics_Facility 1 9218
Protoss_Citadel_of_Adun 1 9187
Protoss_Corsair 4 10036
Protoss_Templar_Archives 1 10341
Protoss_Dark_Templar 2 11116
11116
