Protoss_Nexus 1 5857
Protoss_Gateway 5 11098
Protoss_Forge 1 4903
Protoss_Photon_Cannon 4 9185
Protoss_Zealot 4 8613
Protoss_Assimilator 2 7623
Protoss_Cybernetics_Core 1 7261
Protoss_Dragoon 1 8037
Protoss_Stargate 1 8809
Protoss_Citadel_of_Adun 1 8914
Protoss_Corsair 1 9297
Protoss_Templar_Archives 1 9969
Protoss_Dark_Templar 1 10757
11098
