Protoss_Gateway 2 10994
Protoss_Assimilator 1 3601
Protoss_Zealot 6 9961
Protoss_Cybernetics_Core 1 4876
Protoss_Dragoon 1 5731
Protoss_Robotics_Facility 1 6894
Protoss_Forge 1 7050
Protoss_Shuttle 1 7717
Protoss_Robotics_Support_Bay 1 7599
Protoss_Reaver 2 10159
Protoss_Photon_Cannon 3 10623
Protoss_Citadel_of_Adun 1 11067
Protoss_Scarab 3 9860
11067
