Protoss_Gateway 2 9428
Protoss_Zealot 6 7467
Protoss_Assimilator 1 4405
Protoss_Cybernetics_Core 1 5671
Protoss_Stargate 1 6992
Protoss_Forge 1 6515
Protoss_Dragoon 1 7035
Protoss_Photon_Cannon 2 9989
Protoss_Citadel_of_Adun 1 9020
9989
