Protoss_Forge 1 3097
Protoss_Photon_Cannon 3 11101
Protoss_Nexus 1 7251
Protoss_Gateway 4 9313
Protoss_Assimilator 2 9275
Protoss_Zealot 11 10439
Protoss_Cybernetics_Core 1 7265
Protoss_Citadel_of_Adun 1 8265
Protoss_Dragoon 1 8209
Protoss_Templar_Archives 1 10565
11101
