Protoss_Nexus 1 5761
Protoss_Gateway 3 8611
Protoss_Forge 1 4597
Protoss_Assimilator 2 9185
Protoss_Photon_Cannon 2 7838
Protoss_Cybernetics_Core 1 6528
Protoss_Zealot 12 10803
Protoss_Dragoon 1 7417
Protoss_Citadel_of_Adun 1 7806
Protoss_Templar_Archives 1 10324
10803
