Protoss_Forge 1 3046
Protoss_Photon_Cannon 5 11090
Protoss_Nexus 1 6869
Protoss_Gateway 3 9755
Protoss_Assimilator 1 5375
Protoss_Zealot 7 10323
Protoss_Cybernetics_Core 1 7780
Protoss_Citadel_of_Adun 1 9116
Protoss_Dragoon 1 9801
Protoss_Templar_Archives 1 11197
11197
