Protoss_Forge 1 3272
Protoss_Nexus 1 6273
Protoss_Photon_Cannon 3 10137
Protoss_Gateway 1 5777
Protoss_Assimilator 2 7204
Protoss_Cybernetics_Core 1 7024
Protoss_Zealot 3 8581
10137
