Protoss_Forge 1 2907
Protoss_Photon_Cannon 2 4289
Protoss_Nexus 1 7127
Protoss_Gateway 4 11131
Protoss_Assimilator 2 7744
Protoss_Cybernetics_Core 1 7591
Protoss_Zealot 5 10077
Protoss_Stargate 1 9037
Protoss_Citadel_of_Adun 1 9302
Protoss_Corsair 1 9539
Protoss_Templar_Archives 1 10440
11131
