Protoss_Gateway 1 3363
Protoss_Assimilator 1 3173
Protoss_Zealot 8 8711
Protoss_Cybernetics_Core 1 5832
Protoss_Citadel_of_Adun 1 6973
Protoss_Templar_Archives 1 8372
Protoss_Forge 1 8565
Protoss_High_Templar 3 10721
Protoss_Photon_Cannon 4 10933
Psionic_Storm 1 9896
10933
