Protoss_Forge 1 2948
Protoss_Photon_Cannon 5 11129
Protoss_Nexus 1 6891
Protoss_Gateway 3 11070
Protoss_Zealot 5 9549
Protoss_Assimilator 2 9118
Protoss_Cybernetics_Core 1 8217
Protoss_Citadel_of_Adun 1 9397
Protoss_Templar_Archives 1 10423
Protoss_High_Templar 1 11183
11183
