Protoss_Forge 1 2928
Protoss_Photon_Cannon 4 10827
Protoss_Nexus 1 6371
Protoss_Gateway 4 10206
Protoss_Assimilator 2 6833
Protoss_Cybernetics_Core 1 7130
Protoss_Zealot 3 9265
Protoss_Stargate 1 8389
Protoss_Citadel_of_Adun 1 8421
Protoss_Corsair 1 8881
Protoss_Templar_Archives 1 9451
Protoss_Dark_Templar 1 10189
Protoss_High_Templar 3 11109
11109
