Protoss_Forge 1 3121
Protoss_Nexus 1 6038
Protoss_Photon_Cannon 4 9764
Protoss_Gateway 3 11100
Protoss_Assimilator 2 7987
Protoss_Zealot 6 10051
Protoss_Cybernetics_Core 1 7527
Protoss_Stargate 1 8770
Protoss_Citadel_of_Adun 1 9288
Protoss_Corsair 2 9835
Protoss_Templar_Archives 1 10431
11100
