Protoss_Forge 1 3355
Protoss_Nexus 1 6097
Protoss_Photon_Cannon 5 10329
Protoss_Gateway 2 11437
Protoss_Zealot 3 9011
Protoss_Assimilator 2 8869
Protoss_Cybernetics_Core 1 8579
Protoss_Stargate 1 9831
Protoss_Citadel_of_Adun 1 10009
Protoss_Corsair 1 10243
Protoss_Templar_Archives 1 11041
11437
