Protoss_Forge 1 2966
Protoss_Photon_Cannon 5 10348
Protoss_Nexus 2 12707
Protoss_Gateway 1 6179
Protoss_Assimilator 2 8151
Protoss_Cybernetics_Core 1 7261
Protoss_Zealot 2 7397
Protoss_Stargate 1 8600
Protoss_Corsair 3 10323
Protoss_Robotics_Facility 1 10492
12707
