Protoss_Forge 1 3272
Protoss_Nexus 1 6472
Protoss_Gateway 3 11289
Protoss_Photon_Cannon 3 9732
Protoss_Zealot 12 10597
Protoss_Assimilator 2 7826
Protoss_Cybernetics_Core 1 8668
Protoss_Citadel_of_Adun 1 9744
Protoss_Templar_Archives 1 10738
11289
