Protoss_Nexus 1 5919
Protoss_Gateway 5 10577
Protoss_Forge 1 4683
Protoss_Assimilator 2 6847
Protoss_Photon_Cannon 1 5687
Protoss_Zealot 2 6501
Protoss_Cybernetics_Core 1 6823
Protoss_Stargate 1 8099
Protoss_Citadel_of_Adun 1 8031
Protoss_Dragoon 1 7815
Protoss_Templar_Archives 1 9027
Protoss_Corsair 1 8659
Protoss_Dark_Templar 2 10619
Protoss_High_Templar 4 11137
11137
