Protoss_Gateway 2 7598
Protoss_Assimilator 1 3323
Protoss_Zealot 7 9527
Protoss_Cybernetics_Core 1 5075
Protoss_Dragoon 1 5835
Protoss_Citadel_of_Adun 1 6613
Protoss_Templar_Archives 1 7859
Protoss_High_Templar 4 10413
Protoss_Nexus 1 10931
Protoss_Archon 1 8812
Protoss_Forge 1 9772
Protoss_Photon_Cannon 2 10885
10931
