Protoss_Forge 1 3084
Protoss_Photon_Cannon 1 4187
Protoss_Nexus 1 6756
Protoss_Gateway 4 10523
Protoss_Assimilator 2 9416
Protoss_Zealot 10 10637
Protoss_Cybernetics_Core 1 6907
Protoss_Dragoon 1 7727
Protoss_Citadel_of_Adun 1 8081
Protoss_Templar_Archives 1 10068
10637
