Protoss_Forge 1 3411
Protoss_Nexus 1 6286
Protoss_Gateway 1 5433
Protoss_Assimilator 2 7369
Protoss_Photon_Cannon 3 9825
Protoss_Zealot 3 9819
Protoss_Cybernetics_Core 1 7364
Protoss_Dragoon 1 8329
Protoss_Stargate 1 8865
Protoss_Robotics_Facility 1 9637
Protoss_Corsair 3 10885
Protoss_Shuttle 1 10455
Protoss_Robotics_Support_Bay 1 10205
10885
