Protoss_Nexus 2 12034
Protoss_Gateway 2 8470
Protoss_Assimilator 2 6977
Protoss_Forge 1 5379
Protoss_Cybernetics_Core 1 6139
Protoss_Photon_Cannon 5 11021
Protoss_Zealot 2 8275
Protoss_Stargate 1 7410
Protoss_Dragoon 1 7431
Protoss_Citadel_of_Adun 1 7985
Protoss_Corsair 3 9163
Protoss_Templar_Archives 1 8975
Protoss_Dark_Templar 2 9903
Protoss_High_Templar 2 10655
12034
