Protoss_Forge 2 9414
Protoss_Photon_Cannon 3 10429
Protoss_Nexus 1 6499
Protoss_Gateway 5 11175
Protoss_Assimilator 2 8647
Protoss_Zealot 5 9479
Protoss_Cybernetics_Core 1 6897
Protoss_Citadel_of_Adun 1 8083
Protoss_Templar_Archives 1 9835
Protoss_High_Templar 2 10585
11175
