Protoss_Gateway 1 3399
Protoss_Assimilator 2 10069
Protoss_Cybernetics_Core 1 4483
Protoss_Stargate 1 5738
Protoss_Corsair 7 10057
Protoss_Nexus 1 9080
Protoss_Robotics_Facility 1 9073
Protoss_Shield_Battery 1 9369
Protoss_Robotics_Support_Bay 1 9568
Protoss_Shuttle 1 10876
10876
