Protoss_Forge 1 2973
Protoss_Photon_Cannon 2 4277
Protoss_Nexus 1 7015
Protoss_Gateway 1 5847
Protoss_Assimilator 2 9106
Protoss_Zealot 2 9023
Protoss_Cybernetics_Core 1 7177
Protoss_Dragoon 1 7945
Protoss_Stargate 1 8647
Protoss_Robotics_Facility 1 9787
Protoss_Corsair 1 9133
Protoss_Robotics_Support_Bay 1 10105
10105
