Protoss_Forge 1 2903
Protoss_Photon_Cannon 3 6533
Protoss_Nexus 1 7259
Protoss_Gateway 3 10286
Protoss_Assimilator 2 7704
Protoss_Cybernetics_Core 1 7331
Protoss_Zealot 5 9883
Protoss_Stargate 1 8733
Protoss_Citadel_of_Adun 1 8948
Protoss_Corsair 2 10071
Protoss_Templar_Archives 1 9976
Protoss_Dark_Templar 3 11043
11043
