Protoss_Forge 1 3487
Protoss_Photon_Cannon 2 5263
Protoss_Nexus 1 6570
Protoss_Gateway 5 10958
Protoss_Assimilator 2 7814
Protoss_Zealot 5 10759
Protoss_Cybernetics_Core 1 7641
Protoss_Stargate 1 8941
Protoss_Dragoon 1 8633
Protoss_Citadel_of_Adun 1 9188
Protoss_Corsair 1 9449
10958
