Protoss_Forge 1 2867
Protoss_Photon_Cannon 2 4483
Protoss_Gateway 1 4377
Protoss_Zealot 3 6919
Protoss_Assimilator 1 5205
Protoss_Cybernetics_Core 1 6609
Protoss_Stargate 1 7843
Protoss_Corsair 4 10907
Protoss_Nexus 1 10555
Protoss_Citadel_of_Adun 1 9362
10907
