Protoss_Gateway 1 3159
Protoss_Zealot 12 10831
Protoss_Nexus 1 7905
Protoss_Forge 1 7245
Protoss_Assimilator 2 9194
Protoss_Photon_Cannon 6 11034
Protoss_Cybernetics_Core 1 9357
Protoss_Stargate 1 10670
Protoss_Citadel_of_Adun 1 10840
11034
