Protoss_Forge 1 3318
Protoss_Nexus 1 6113
Protoss_Photon_Cannon 4 9721
Protoss_Gateway 4 11291
Protoss_Assimilator 2 7681
Protoss_Cybernetics_Core 1 6963
Protoss_Zealot 3 7959
Protoss_Stargate 1 8269
Protoss_Citadel_of_Adun 1 8605
Protoss_Corsair 3 10297
Protoss_Templar_Archives 1 9607
Protoss_Dark_Templar 2 10473
11291
