Protoss_Forge 1 3126
Protoss_Assimilator 1 3269
Protoss_Photon_Cannon 1 4177
Protoss_Gateway 2 5903
Protoss_Zealot 9 9079
Protoss_Cybernetics_Core 1 6543
Protoss_Citadel_of_Adun 1 7713
Protoss_Templar_Archives 1 8795
Protoss_Ground_Weapons_1 1 7737
Protoss_Dark_Templar 3 10761
10761
