Protoss_Nexus 1 5879
Protoss_Forge 1 4364
Protoss_Gateway 2 6089
Protoss_Zealot 7 10657
Protoss_Assimilator 2 9278
Protoss_Cybernetics_Core 1 7937
Protoss_Stargate 2 9929
10657
