Protoss_Gateway 3 11261
Protoss_Forge 1 3581
Protoss_Photon_Cannon 3 10487
Protoss_Nexus 1 7906
Protoss_Assimilator 2 7869
Protoss_Zealot 3 9363
Protoss_Cybernetics_Core 1 7487
Protoss_Stargate 1 8801
Protoss_Dragoon 1 8595
Protoss_Citadel_of_Adun 1 9524
Protoss_Corsair 3 10503
Protoss_Templar_Archives 1 10604
11261
