Protoss_Forge 1 2999
Protoss_Photon_Cannon 6 10819
Protoss_Nexus 2 9715
Protoss_Gateway 1 6663
Protoss_Assimilator 2 8647
Protoss_Cybernetics_Core 1 7729
Protoss_Zealot 4 9571
Protoss_Stargate 1 9015
Protoss_Dragoon 1 8647
Protoss_Citadel_of_Adun 1 9481
Protoss_Corsair 2 10191
Protoss_Templar_Archives 1 10573
10819
