Protoss_Forge 1 3093
Protoss_Photon_Cannon 5 10770
Protoss_Nexus 1 6643
Protoss_Gateway 2 10000
Protoss_Assimilator 2 7713
Protoss_Zealot 3 8513
Protoss_Cybernetics_Core 1 7569
Protoss_Stargate 1 8988
Protoss_Citadel_of_Adun 1 9382
Protoss_Corsair 2 10761
Protoss_Templar_Archives 1 10410
10770
