Protoss_Forge 1 3125
Protoss_Photon_Cannon 3 9691
Protoss_Nexus 1 6678
Protoss_Gateway 4 11276
Protoss_Assimilator 2 7387
Protoss_Cybernetics_Core 1 6803
Protoss_Zealot 4 10069
Protoss_Stargate 1 8390
Protoss_Citadel_of_Adun 1 8933
Protoss_Corsair 1 8931
Protoss_Templar_Archives 1 10033
Protoss_Robotics_Facility 1 10674
Protoss_Dark_Templar 1 10911
11276
