Protoss_Forge 1 3182
Protoss_Nexus 1 6066
Protoss_Gateway 1 5099
Protoss_Assimilator 2 6781
Protoss_Photon_Cannon 3 9200
Protoss_Cybernetics_Core 1 6309
Protoss_Zealot 3 10909
Protoss_Stargate 1 7661
Protoss_Dragoon 1 7291
Protoss_Robotics_Facility 1 8561
Protoss_Corsair 5 10771
Protoss_Shuttle 1 9589
Protoss_Robotics_Support_Bay 1 9156
Protoss_Reaver 1 10899
10909
