Protoss_Gateway 2 3993
Protoss_Zealot 11 10741
Protoss_Assimilator 1 5763
Protoss_Cybernetics_Core 1 7805
Protoss_Forge 1 8353
Protoss_Dragoon 4 9956
Protoss_Photon_Cannon 1 9799
10741
