Protoss_Nexus 1 5746
Protoss_Forge 1 4279
Protoss_Photon_Cannon 2 8628
Protoss_Gateway 1 5741
Protoss_Assimilator 2 6655
Protoss_Cybernetics_Core 1 6745
Protoss_Zealot 3 10741
Protoss_Stargate 1 7971
Protoss_Dragoon 1 7861
Protoss_Robotics_Facility 1 9111
Protoss_Corsair 4 10409
Protoss_Shuttle 1 9935
Protoss_Robotics_Support_Bay 1 9339
Protoss_Reaver 1 11077
11077
