Protoss_Forge 1 3146
Protoss_Photon_Cannon 5 10915
Protoss_Nexus 1 6455
Protoss_Gateway 1 6035
Protoss_Zealot 5 9667
Protoss_Assimilator 2 10584
Protoss_Cybernetics_Core 1 9311
Protoss_Stargate 1 10651
Protoss_Dragoon 1 10806
Protoss_Citadel_of_Adun 1 11433
11433
