Protoss_Forge 1 3668
Protoss_Photon_Cannon 4 10540
Protoss_Nexus 1 6897
Protoss_Gateway 1 5819
Protoss_Assimilator 2 8012
Protoss_Zealot 3 9201
Protoss_Cybernetics_Core 1 7304
Protoss_Stargate 1 8642
Protoss_Dragoon 1 8625
Protoss_Corsair 3 10495
Protoss_Robotics_Facility 1 10321
10540
