Protoss_Forge 1 3336
Protoss_Photon_Cannon 7 10383
Protoss_Nexus 1 6963
Protoss_Gateway 2 9968
Protoss_Assimilator 2 8029
Protoss_Zealot 2 7221
Protoss_Cybernetics_Core 1 6968
Protoss_Stargate 1 8293
Protoss_Citadel_of_Adun 1 8717
Protoss_Corsair 2 9583
Protoss_Templar_Archives 1 9725
Protoss_Dark_Templar 1 10615
10615
