Protoss_Gateway 2 7411
Protoss_Assimilator 1 3459
Protoss_Zealot 8 9567
Protoss_Cybernetics_Core 1 5687
Protoss_Dragoon 1 6665
Protoss_Citadel_of_Adun 1 6989
Protoss_Templar_Archives 1 7981
Protoss_Forge 1 8647
Protoss_High_Templar 4 10409
Protoss_Archon 1 9156
Protoss_Photon_Cannon 4 10626
Protoss_Nexus 1 12861
12861
