Protoss_Forge 1 3153
Protoss_Photon_Cannon 4 10074
Protoss_Nexus 1 7181
Protoss_Gateway 3 11257
Protoss_Assimilator 2 8230
Protoss_Cybernetics_Core 1 7083
Protoss_Zealot 5 10600
Protoss_Stargate 1 8443
Protoss_Citadel_of_Adun 1 8569
Protoss_Corsair 1 9365
Protoss_Robotics_Facility 1 10557
Protoss_Templar_Archives 1 10615
11257
