Protoss_Forge 2 9998
Protoss_Photon_Cannon 8 10923
Protoss_Gateway 2 10837
Protoss_Zealot 2 6093
Protoss_Nexus 1 7547
Protoss_Assimilator 1 5909
Protoss_Cybernetics_Core 1 7727
10923
