Protoss_Forge 1 3074
Protoss_Nexus 1 5983
Protoss_Photon_Cannon 3 7412
Protoss_Gateway 1 5711
Protoss_Assimilator 2 8993
Protoss_Zealot 4 10439
Protoss_Cybernetics_Core 1 6996
Protoss_Stargate 1 8912
Protoss_Dragoon 1 8559
Protoss_Corsair 3 10677
Protoss_Citadel_of_Adun 1 10722
10722
