Protoss_Gateway 3 11429
Protoss_Assimilator 1 3325
Protoss_Cybernetics_Core 1 4404
Protoss_Zealot 2 5003
Protoss_Dragoon 10 10909
Protoss_Stargate 1 7088
Protoss_Robotics_Facility 1 7793
Protoss_Shuttle 1 8751
Protoss_Robotics_Support_Bay 1 8558
Protoss_Reaver 1 10403
11429
