Protoss_Gateway 2 8541
Protoss_Assimilator 1 3417
Protoss_Zealot 2 5003
Protoss_Cybernetics_Core 1 5167
Protoss_Stargate 1 6463
Protoss_Dragoon 1 6283
Protoss_Citadel_of_Adun 1 7032
Protoss_Corsair 1 6903
Protoss_Forge 1 7493
Protoss_Templar_Archives 1 8071
Protoss_Dark_Templar 2 9299
Protoss_Photon_Cannon 3 11108
Protoss_Nexus 1 12009
Protoss_High_Templar 2 11001
12009
