Protoss_Gateway 2 9131
Protoss_Zealot 4 9297
Protoss_Assimilator 1 4050
Protoss_Cybernetics_Core 1 5422
Protoss_Stargate 1 6920
Protoss_Nexus 1 8708
Protoss_Citadel_of_Adun 1 7536
Protoss_Corsair 1 7355
Protoss_Forge 1 7829
Protoss_Templar_Archives 1 8718
Protoss_Photon_Cannon 3 10981
Protoss_Dark_Templar 2 10023
Protoss_High_Templar 2 10821
10981
