Protoss_Forge 1 3184
Protoss_Photon_Cannon 3 7139
Protoss_Nexus 1 6843
Protoss_Gateway 1 6057
Protoss_Assimilator 2 8949
Protoss_Zealot 6 10083
Protoss_Cybernetics_Core 1 8690
Protoss_Stargate 1 10037
Protoss_Citadel_of_Adun 1 10029
Protoss_Corsair 1 10445
Protoss_Templar_Archives 1 11215
Protoss_Dragoon 1 11053
11215
