Protoss_Forge 1 3709
Protoss_Photon_Cannon 4 10197
Protoss_Nexus 1 7131
Protoss_Gateway 1 6077
Protoss_Assimilator 2 7187
Protoss_Cybernetics_Core 1 7135
Protoss_Zealot 5 10761
Protoss_Dragoon 1 8163
Protoss_Stargate 1 9094
Protoss_Robotics_Facility 1 10141
Protoss_Corsair 3 10777
Protoss_Shuttle 1 11423
11423
