Protoss_Forge 1 3099
Protoss_Photon_Cannon 6 11173
Protoss_Nexus 1 6963
Protoss_Gateway 1 5905
Protoss_Assimilator 2 8210
Protoss_Cybernetics_Core 1 7010
Protoss_Zealot 5 10325
Protoss_Stargate 1 8363
Protoss_Robotics_Facility 1 9499
Protoss_Corsair 4 10871
Protoss_Shuttle 1 10407
11173
