Protoss_Forge 2 8948
Protoss_Photon_Cannon 3 10222
Protoss_Gateway 2 6454
Protoss_Assimilator 1 5053
Protoss_Cybernetics_Core 1 7449
Protoss_Zealot 3 8275
Protoss_Stargate 1 8686
Protoss_Citadel_of_Adun 1 8685
Protoss_Dragoon 1 9117
Protoss_Corsair 2 9934
Protoss_Templar_Archives 1 9697
Protoss_Dark_Templar 1 10439
Protoss_Nexus 1 12632
Protoss_High_Templar 1 11191
12632
