Protoss_Nexus 1 5709
Protoss_Forge 1 4372
Protoss_Gateway 4 10334
Protoss_Photon_Cannon 2 7077
Protoss_Assimilator 2 7311
Protoss_Cybernetics_Core 1 6797
Protoss_Stargate 1 8201
Protoss_Robotics_Facility 1 9161
Protoss_Zealot 1 8525
Protoss_Dragoon 6 11191
Protoss_Corsair 1 8621
Protoss_Shuttle 1 9999
Protoss_Robotics_Support_Bay 1 9708
Protoss_Reaver 1 11573
11573
