Protoss_Forge 1 2969
Protoss_Photon_Cannon 2 4397
Protoss_Nexus 1 6995
Protoss_Gateway 3 10256
Protoss_Assimilator 2 7895
Protoss_Zealot 5 10641
Protoss_Cybernetics_Core 1 7462
Protoss_Stargate 1 8701
Protoss_Citadel_of_Adun 1 9328
Protoss_Corsair 1 9167
Protoss_Templar_Archives 1 10363
Protoss_Robotics_Facility 1 11501
Protoss_Dark_Templar 1 11101
11501
