Protoss_Forge 1 3205
Protoss_Nexus 1 6081
Protoss_Gateway 4 11273
Protoss_Photon_Cannon 6 10813
Protoss_Assimilator 2 7191
Protoss_Cybernetics_Core 1 6397
Protoss_Zealot 5 10503
Protoss_Stargate 1 7775
Protoss_Dragoon 1 7533
Protoss_Corsair 2 9221
Protoss_Citadel_of_Adun 1 8955
Protoss_Templar_Archives 1 10361
Protoss_High_Templar 2 11161
11273
