Protoss_Forge 1 2982
Protoss_Photon_Cannon 2 10092
Protoss_Nexus 1 6593
Protoss_Gateway 4 9761
Protoss_Assimilator 2 9398
Protoss_Zealot 12 10887
Protoss_Cybernetics_Core 1 6974
Protoss_Citadel_of_Adun 1 8579
Protoss_Dragoon 1 9319
Protoss_Templar_Archives 1 10940
10940
