Protoss_Gateway 2 8386
Protoss_Assimilator 1 3415
Protoss_Zealot 10 8975
Protoss_Cybernetics_Core 1 5605
Protoss_Citadel_of_Adun 1 7117
Protoss_Templar_Archives 1 9139
Protoss_Forge 1 9533
Protoss_High_Templar 3 10809
Protoss_Dark_Templar 1 10057
Protoss_Photon_Cannon 1 10954
Protoss_Stargate 1 11563
11563
