Protoss_Forge 1 3029
Protoss_Photon_Cannon 2 5220
Protoss_Nexus 1 6547
Protoss_Gateway 1 5945
Protoss_Assimilator 2 8337
Protoss_Zealot 6 10383
Protoss_Cybernetics_Core 1 7397
Protoss_Citadel_of_Adun 1 9255
Protoss_Dragoon 1 9181
10383
