Protoss_Forge 1 3416
Protoss_Nexus 1 6447
Protoss_Gateway 4 10872
Protoss_Photon_Cannon 1 5665
Protoss_Zealot 14 10751
Protoss_Assimilator 2 7759
Protoss_Cybernetics_Core 1 7677
Protoss_Citadel_of_Adun 1 9171
Protoss_Templar_Archives 1 10525
Protoss_Robotics_Facility 1 11610
11610
