Protoss_Forge 1 3191
Protoss_Nexus 1 6469
Protoss_Gateway 4 10395
Protoss_Photon_Cannon 3 9258
Protoss_Assimilator 2 7489
Protoss_Cybernetics_Core 1 7331
Protoss_Zealot 8 10909
Protoss_Stargate 1 8653
Protoss_Citadel_of_Adun 1 9059
Protoss_Corsair 1 9077
Protoss_Templar_Archives 1 11319
11319
