Protoss_Forge 1 3253
Protoss_Photon_Cannon 3 8015
Protoss_Nexus 1 6445
Protoss_Gateway 5 11285
Protoss_Assimilator 2 9289
Protoss_Cybernetics_Core 1 6719
Protoss_Zealot 4 9421
Protoss_Stargate 1 8041
Protoss_Corsair 3 10897
Protoss_Dragoon 1 8933
Protoss_Citadel_of_Adun 1 9394
Protoss_Templar_Archives 1 10494
11285
