Protoss_Forge 2 9631
Protoss_Nexus 1 6108
Protoss_Photon_Cannon 5 11159
Protoss_Gateway 2 9364
Protoss_Assimilator 2 7357
Protoss_Cybernetics_Core 1 6959
Protoss_Zealot 3 9385
Protoss_Stargate 1 8219
Protoss_Citadel_of_Adun 1 8425
Protoss_Corsair 3 9891
Protoss_Templar_Archives 1 9467
Protoss_Dark_Templar 2 10307
11159
