Protoss_Forge 1 3129
Protoss_Photon_Cannon 3 10737
Protoss_Nexus 1 6879
Protoss_Gateway 4 9348
Protoss_Assimilator 2 10195
Protoss_Cybernetics_Core 1 6793
Protoss_Zealot 9 10391
Protoss_Citadel_of_Adun 1 7928
Protoss_Dragoon 1 7883
Protoss_Templar_Archives 1 10284
10737
