Protoss_Forge 1 3088
Protoss_Photon_Cannon 4 11177
Protoss_Nexus 1 6785
Protoss_Gateway 3 9136
Protoss_Assimilator 3 9365
Protoss_Cybernetics_Core 1 6677
Protoss_Zealot 8 10437
Protoss_Stargate 1 7988
Protoss_Citadel_of_Adun 1 8410
Protoss_Corsair 1 8521
Protoss_Templar_Archives 1 9653
Protoss_High_Templar 1 10869
11177
