Protoss_Nexus 1 5684
Protoss_Gateway 4 10583
Protoss_Forge 1 4551
Protoss_Assimilator 2 7768
Protoss_Photon_Cannon 4 9313
Protoss_Zealot 4 9647
Protoss_Cybernetics_Core 1 6501
Protoss_Stargate 1 8056
Protoss_Corsair 1 8479
Protoss_Citadel_of_Adun 1 9297
Protoss_Templar_Archives 1 10333
10583
