Protoss_Nexus 1 5659
Protoss_Gateway 5 11270
Protoss_Assimilator 2 7706
Protoss_Forge 1 4831
Protoss_Photon_Cannon 3 11039
Protoss_Cybernetics_Core 1 6866
Protoss_Zealot 3 8159
Protoss_Stargate 1 8182
Protoss_Citadel_of_Adun 1 8042
Protoss_Templar_Archives 1 9045
Protoss_Dragoon 1 9001
Protoss_Corsair 1 8903
Protoss_Dark_Templar 2 10003
Protoss_High_Templar 2 10755
11270
