Protoss_Forge 1 3384
Protoss_Photon_Cannon 2 4388
Protoss_Nexus 1 7101
Protoss_Gateway 5 10973
Protoss_Assimilator 2 9229
Protoss_Zealot 11 10347
Protoss_Cybernetics_Core 1 7232
Protoss_Citadel_of_Adun 1 8261
Protoss_Templar_Archives 1 10275
Protoss_High_Templar 2 11045
Protoss_Dark_Templar 1 11189
11189
