Protoss_Forge 1 3087
Protoss_Photon_Cannon 5 10833
Protoss_Nexus 1 6851
Protoss_Gateway 1 5697
Protoss_Assimilator 2 9567
Protoss_Zealot 6 10533
Protoss_Cybernetics_Core 1 7113
Protoss_Dragoon 1 8055
Protoss_Stargate 1 8625
Protoss_Citadel_of_Adun 1 9395
Protoss_Corsair 3 10887
10887
