Protoss_Forge 1 3716
Protoss_Nexus 1 6385
Protoss_Gateway 1 5650
Protoss_Photon_Cannon 3 10121
Protoss_Assimilator 2 6964
Protoss_Cybernetics_Core 1 6867
Protoss_Zealot 4 9609
Protoss_Stargate 2 10058
Protoss_Corsair 5 10709
Protoss_Citadel_of_Adun 1 10830
10830
