Protoss_Gateway 3 9724
Protoss_Forge 1 3248
Protoss_Photon_Cannon 6 10547
Protoss_Nexus 1 7609
Protoss_Assimilator 2 7797
Protoss_Cybernetics_Core 1 7587
Protoss_Zealot 3 10501
Protoss_Stargate 1 8865
Protoss_Citadel_of_Adun 1 9155
Protoss_Dragoon 1 9241
Protoss_Corsair 3 10625
Protoss_Templar_Archives 1 10154
Protoss_Dark_Templar 1 10907
10907
