Protoss_Nexus 1 5758
Protoss_Gateway 4 10608
Protoss_Forge 1 4754
Protoss_Assimilator 2 7965
Protoss_Photon_Cannon 1 5731
Protoss_Zealot 9 10861
Protoss_Cybernetics_Core 1 6664
Protoss_Stargate 1 7993
Protoss_Citadel_of_Adun 1 8081
Protoss_Corsair 2 9385
Protoss_Templar_Archives 1 9355
Protoss_Dark_Templar 2 10103
Protoss_High_Templar 2 10331
10861
