Protoss_Nexus 1 5798
Protoss_Forge 1 4488
Protoss_Gateway 6 11328
Protoss_Assimilator 2 6637
Protoss_Photon_Cannon 2 11134
Protoss_Cybernetics_Core 1 6267
Protoss_Zealot 3 8493
Protoss_Stargate 1 7628
Protoss_Dragoon 1 7299
Protoss_Citadel_of_Adun 1 8250
Protoss_Corsair 3 9671
Protoss_Templar_Archives 1 9385
Protoss_High_Templar 3 10893
11328
