Protoss_Gateway 1 3004
Protoss_Zealot 9 9757
Protoss_Forge 1 4600
Protoss_Photon_Cannon 3 11133
Protoss_Nexus 1 8805
Protoss_Assimilator 1 6974
Protoss_Cybernetics_Core 1 8327
Protoss_Stargate 1 9768
Protoss_Citadel_of_Adun 1 10619
Protoss_Corsair 2 10829
11133
