Protoss_Forge 1 2856
Protoss_Photon_Cannon 6 10947
Protoss_Nexus 1 6622
Protoss_Gateway 1 5721
Protoss_Assimilator 2 7473
Protoss_Cybernetics_Core 1 7039
Protoss_Zealot 3 8641
Protoss_Stargate 1 8453
Protoss_Robotics_Facility 1 9564
Protoss_Dragoon 1 8991
Protoss_Corsair 3 10518
Protoss_Shuttle 1 10697
10947
