Protoss_Forge 1 3117
Protoss_Nexus 1 5891
Protoss_Gateway 5 11371
Protoss_Assimilator 2 7383
Protoss_Cybernetics_Core 1 6018
Protoss_Photon_Cannon 3 10156
Protoss_Zealot 5 9995
Protoss_Stargate 1 7492
Protoss_Dragoon 1 7887
Protoss_Corsair 2 8662
Protoss_Citadel_of_Adun 1 8749
Protoss_Templar_Archives 1 9889
Protoss_Dark_Templar 2 10709
Protoss_Robotics_Facility 1 11877
11877
