Protoss_Forge 1 3082
Protoss_Nexus 1 6401
Protoss_Gateway 4 9704
Protoss_Photon_Cannon 2 5903
Protoss_Assimilator 2 10751
Protoss_Zealot 12 10751
Protoss_Cybernetics_Core 1 7771
Protoss_Citadel_of_Adun 1 8805
Protoss_Templar_Archives 1 11236
11236
