Protoss_Forge 1 3053
Protoss_Photon_Cannon 2 4439
Protoss_Nexus 1 6895
Protoss_Gateway 5 11235
Protoss_Assimilator 2 7764
Protoss_Zealot 7 10909
Protoss_Cybernetics_Core 1 7208
Protoss_Stargate 1 8597
Protoss_Citadel_of_Adun 1 9011
Protoss_Corsair 2 9693
11235
