Protoss_Forge 1 3220
Protoss_Photon_Cannon 4 10768
Protoss_Nexus 1 8209
Protoss_Gateway 1 7117
Protoss_Assimilator 3 10763
Protoss_Cybernetics_Core 1 8191
Protoss_Zealot 3 9085
Protoss_Stargate 1 9579
Protoss_Citadel_of_Adun 1 9823
Protoss_Dragoon 1 10337
Protoss_Corsair 1 10191
Protoss_Templar_Archives 1 11114
11114
