Protoss_Forge 1 3043
Protoss_Photon_Cannon 7 10913
Protoss_Nexus 1 6793
Protoss_Assimilator 2 9260
Protoss_Gateway 3 9233
Protoss_Cybernetics_Core 1 7245
Protoss_Zealot 10 10845
Protoss_Dragoon 1 7997
Protoss_Citadel_of_Adun 1 8595
Protoss_Templar_Archives 1 10354
Protoss_High_Templar 1 11129
11129
