Protoss_Forge 1 3048
Protoss_Photon_Cannon 7 10491
Protoss_Nexus 1 8621
Protoss_Gateway 1 7763
Protoss_Assimilator 2 9324
Protoss_Cybernetics_Core 1 8843
Protoss_Stargate 1 10099
Protoss_Citadel_of_Adun 1 9931
Protoss_Corsair 1 10519
Protoss_Templar_Archives 1 11237
11237
