Protoss_Forge 1 3297
Protoss_Photon_Cannon 5 9295
Protoss_Nexus 1 6843
Protoss_Gateway 1 5781
Protoss_Assimilator 2 7246
Protoss_Zealot 3 10395
Protoss_Cybernetics_Core 1 7339
Protoss_Dragoon 2 8937
Protoss_Stargate 1 8680
Protoss_Robotics_Facility 1 9519
Protoss_Corsair 4 10939
Protoss_Shuttle 1 10319
Protoss_Robotics_Support_Bay 1 10690
10939
