Protoss_Gateway 2 10482
Protoss_Assimilator 1 3330
Protoss_Zealot 7 10947
Protoss_Cybernetics_Core 1 4933
Protoss_Stargate 1 6159
Protoss_Dragoon 1 5727
Protoss_Citadel_of_Adun 1 6565
Protoss_Corsair 1 6615
Protoss_Templar_Archives 1 7723
Protoss_Forge 1 7765
Protoss_Dark_Templar 2 9601
Protoss_Photon_Cannon 2 10735
Protoss_Nexus 1 11103
Protoss_High_Templar 1 10375
11103
