Protoss_Forge 1 3269
Protoss_Nexus 1 6087
Protoss_Photon_Cannon 4 9702
Protoss_Gateway 4 11157
Protoss_Assimilator 2 7280
Protoss_Zealot 8 10563
Protoss_Cybernetics_Core 1 7013
Protoss_Stargate 1 8370
Protoss_Citadel_of_Adun 1 8897
Protoss_Corsair 4 10883
11157
