Protoss_Gateway 3 8235
Protoss_Assimilator 1 2530
Protoss_Zealot 12 9541
Protoss_Cybernetics_Core 1 3905
Protoss_Stargate 1 4911
Protoss_Forge 1 5375
Protoss_Citadel_of_Adun 1 5938
Protoss_Corsair 2 6819
Protoss_Templar_Archives 1 9610
9610
