Protoss_Forge 2 8978
Protoss_Photon_Cannon 4 10608
Protoss_Nexus 1 7150
Protoss_Gateway 1 6031
Protoss_Assimilator 2 7846
Protoss_Zealot 4 10063
Protoss_Cybernetics_Core 1 7614
Protoss_Stargate 1 9156
Protoss_Citadel_of_Adun 1 9186
Protoss_Corsair 1 9575
Protoss_Templar_Archives 1 10377
Protoss_Dark_Templar 1 11141
11141
