Protoss_Forge 1 3281
Protoss_Photon_Cannon 4 10989
Protoss_Nexus 1 6799
Protoss_Gateway 2 9631
Protoss_Assimilator 2 8290
Protoss_Zealot 6 10307
Protoss_Cybernetics_Core 1 7533
Protoss_Dragoon 1 8345
Protoss_Citadel_of_Adun 1 9006
Protoss_Stargate 1 9682
Protoss_Templar_Archives 1 9993
Protoss_Corsair 1 10173
Protoss_Dark_Templar 2 11149
11149
