Protoss_Nexus 1 5677
Protoss_Gateway 3 9273
Protoss_Forge 2 10791
Protoss_Assimilator 2 7168
Protoss_Photon_Cannon 4 10010
Protoss_Zealot 4 9631
Protoss_Cybernetics_Core 1 7105
Protoss_Dragoon 1 7859
Protoss_Stargate 1 8437
Protoss_Citadel_of_Adun 1 8516
Protoss_Corsair 1 9029
Protoss_Templar_Archives 1 9671
Protoss_Dark_Templar 1 10519
Protoss_High_Templar 2 10565
10791
