Protoss_Forge 1 3051
Protoss_Photon_Cannon 5 10189
Protoss_Nexus 1 6779
Protoss_Gateway 1 5595
Protoss_Assimilator 2 7493
Protoss_Zealot 2 9193
Protoss_Cybernetics_Core 1 8171
Protoss_Stargate 1 9412
Protoss_Robotics_Facility 1 9720
Protoss_Corsair 2 10901
Protoss_Shuttle 1 10881
Protoss_Robotics_Support_Bay 1 10471
10901
