Protoss_Forge 1 3114
Protoss_Nexus 1 6131
Protoss_Gateway 4 10763
Protoss_Assimilator 2 9528
Protoss_Photon_Cannon 1 5770
Protoss_Zealot 14 10743
Protoss_Cybernetics_Core 1 8318
Protoss_Citadel_of_Adun 1 9426
Protoss_Ground_Weapons_1 1 9499
Protoss_Templar_Archives 1 10970
10970
