Protoss_Forge 1 3481
Protoss_Photon_Cannon 4 9695
Protoss_Nexus 1 6583
Protoss_Gateway 2 9603
Protoss_Assimilator 3 8516
Protoss_Cybernetics_Core 1 6868
Protoss_Zealot 7 10933
Protoss_Stargate 1 8185
Protoss_Citadel_of_Adun 1 8460
Protoss_Corsair 2 10053
Protoss_Templar_Archives 1 9617
10933
