Protoss_Gateway 2 3940
Protoss_Zealot 15 10559
Protoss_Assimilator 1 6891
Protoss_Cybernetics_Core 1 8101
Protoss_Forge 1 8250
Protoss_Citadel_of_Adun 1 9383
Protoss_Photon_Cannon 2 10099
Protoss_Templar_Archives 1 11011
11011
