Protoss_Forge 1 3226
Protoss_Nexus 2 11668
Protoss_Photon_Cannon 3 6152
Protoss_Gateway 2 10869
Protoss_Assimilator 2 7967
Protoss_Zealot 2 7467
Protoss_Cybernetics_Core 1 7657
Protoss_Stargate 1 8996
Protoss_Citadel_of_Adun 1 9118
Protoss_Dragoon 1 8951
Protoss_Corsair 2 10579
Protoss_Templar_Archives 1 10720
11668
