Protoss_Gateway 2 8703
Protoss_Zealot 12 10732
Protoss_Nexus 1 7122
Protoss_Assimilator 2 9767
Protoss_Cybernetics_Core 1 6529
Protoss_Forge 1 6517
Protoss_Photon_Cannon 2 9840
Protoss_Stargate 1 8198
Protoss_Dragoon 1 8009
Protoss_Citadel_of_Adun 1 8573
Protoss_Corsair 1 8957
10732
