Protoss_Forge 1 3488
Protoss_Nexus 1 6185
Protoss_Photon_Cannon 4 10934
Protoss_Gateway 2 11249
Protoss_Assimilator 2 8255
Protoss_Cybernetics_Core 1 7374
Protoss_Zealot 5 10469
Protoss_Stargate 1 8875
Protoss_Dragoon 1 9181
Protoss_Corsair 3 10667
Protoss_Citadel_of_Adun 1 10358
Protoss_Templar_Archives 1 11345
11345
