Protoss_Forge 2 9166
Protoss_Photon_Cannon 3 7192
Protoss_Nexus 1 7033
Protoss_Gateway 5 11434
Protoss_Assimilator 2 8984
Protoss_Zealot 5 10521
Protoss_Cybernetics_Core 1 8297
Protoss_Stargate 1 9568
Protoss_Citadel_of_Adun 1 9398
Protoss_Corsair 1 9977
11434
