Protoss_Nexus 1 5745
Protoss_Forge 1 4070
Protoss_Photon_Cannon 3 10618
Protoss_Gateway 3 8757
Protoss_Assimilator 2 7788
Protoss_Cybernetics_Core 1 6951
Protoss_Zealot 11 10137
Protoss_Citadel_of_Adun 1 7939
Protoss_Templar_Archives 1 10097
Protoss_Robotics_Facility 1 11269
Protoss_High_Templar 2 10881
Protoss_Dark_Templar 1 10979
Protoss_Ground_Weapons_1 1 9869
11269
