Protoss_Forge 1 3629
Protoss_Photon_Cannon 6 10573
Protoss_Nexus 1 7589
Protoss_Gateway 1 6521
Protoss_Assimilator 2 6668
Protoss_Zealot 3 8806
Protoss_Cybernetics_Core 1 7848
Protoss_Stargate 1 9374
Protoss_Citadel_of_Adun 1 9221
Protoss_Corsair 2 10411
Protoss_Templar_Archives 1 10587
10587
