Protoss_Forge 1 3310
Protoss_Photon_Cannon 4 10217
Protoss_Nexus 1 7007
Protoss_Gateway 4 11415
Protoss_Assimilator 2 8997
Protoss_Zealot 3 8359
Protoss_Cybernetics_Core 1 7454
Protoss_Stargate 1 8826
Protoss_Citadel_of_Adun 1 8967
Protoss_Corsair 1 9279
Protoss_Templar_Archives 1 10007
Protoss_Dark_Templar 1 10769
11415
