Protoss_Forge 2 4352
Protoss_Nexus 1 5880
Protoss_Gateway 3 11025
Protoss_Photon_Cannon 3 10342
Protoss_Zealot 10 10783
Protoss_Assimilator 3 10341
Protoss_Cybernetics_Core 1 7342
Protoss_Stargate 1 8666
Protoss_Citadel_of_Adun 1 8997
Protoss_Dragoon 1 8919
Protoss_Corsair 3 10723
11025
