Protoss_Forge 1 3244
Protoss_Nexus 1 6157
Protoss_Photon_Cannon 4 9648
Protoss_Gateway 3 10083
Protoss_Assimilator 3 10187
Protoss_Cybernetics_Core 1 7450
Protoss_Zealot 6 10727
Protoss_Stargate 1 8827
Protoss_Dragoon 1 8429
Protoss_Citadel_of_Adun 1 9478
Protoss_Corsair 2 10587
Protoss_Templar_Archives 1 10593
10727
