Protoss_Forge 1 2999
Protoss_Nexus 1 6295
Protoss_Photon_Cannon 6 10873
Protoss_Gateway 1 5730
Protoss_Zealot 6 10921
Protoss_Assimilator 2 10186
Protoss_Cybernetics_Core 1 10512
10921
