Protoss_Forge 1 3007
Protoss_Nexus 1 6336
Protoss_Gateway 2 10827
Protoss_Assimilator 2 7393
Protoss_Photon_Cannon 4 10323
Protoss_Cybernetics_Core 1 6451
Protoss_Zealot 3 9591
Protoss_Dragoon 1 7393
Protoss_Stargate 1 7895
Protoss_Citadel_of_Adun 1 8338
Protoss_Corsair 2 9607
Protoss_Robotics_Facility 1 9847
Protoss_Templar_Archives 1 9603
Protoss_Shuttle 1 11057
Protoss_Robotics_Support_Bay 1 10423
11057
