Protoss_Forge 1 3235
Protoss_Photon_Cannon 4 11073
Protoss_Nexus 1 6503
Protoss_Gateway 4 10767
Protoss_Assimilator 2 7957
Protoss_Cybernetics_Core 1 6837
Protoss_Zealot 7 10189
Protoss_Stargate 1 8110
Protoss_Citadel_of_Adun 1 8320
Protoss_Corsair 1 8543
Protoss_Templar_Archives 1 10617
11073
