Protoss_Forge 1 3548
Protoss_Photon_Cannon 2 4693
Protoss_Nexus 1 7051
Protoss_Gateway 4 11276
Protoss_Assimilator 2 7558
Protoss_Cybernetics_Core 1 7287
Protoss_Zealot 2 8607
Protoss_Dragoon 1 8095
Protoss_Stargate 1 8718
Protoss_Citadel_of_Adun 1 8665
Protoss_Corsair 3 10783
Protoss_Templar_Archives 1 10531
11276
