Protoss_Gateway 3 10505
Protoss_Zealot 4 6753
Protoss_Nexus 1 6931
Protoss_Assimilator 2 7189
Protoss_Cybernetics_Core 1 6395
Protoss_Stargate 1 7668
Protoss_Citadel_of_Adun 1 7966
Protoss_Corsair 3 9355
Protoss_Forge 1 8315
Protoss_Templar_Archives 1 9140
Protoss_Photon_Cannon 4 10873
Protoss_Dark_Templar 1 10735
Protoss_High_Templar 1 11027
11027
