Protoss_Forge 1 3531
Protoss_Photon_Cannon 6 10724
Protoss_Gateway 3 11419
Protoss_Nexus 1 7477
Protoss_Assimilator 2 8085
Protoss_Zealot 3 9539
Protoss_Cybernetics_Core 1 7241
Protoss_Stargate 1 8549
Protoss_Citadel_of_Adun 1 9025
Protoss_Corsair 2 9623
Protoss_Dragoon 1 9805
Protoss_Templar_Archives 1 10458
11419
