Protoss_Gateway 2 3939
Protoss_Zealot 19 10853
Protoss_Nexus 1 9263
Protoss_Forge 1 7603
Protoss_Assimilator 2 10733
Protoss_Photon_Cannon 1 9556
Protoss_Cybernetics_Core 1 9866
Protoss_Stargate 1 11165
Protoss_Citadel_of_Adun 1 11119
11165
