Protoss_Forge 1 2971
Protoss_Photon_Cannon 3 10895
Protoss_Nexus 1 7333
Protoss_Gateway 6 10755
Protoss_Assimilator 2 8395
Protoss_Zealot 6 8603
Protoss_Cybernetics_Core 1 7517
Protoss_Stargate 1 8999
Protoss_Corsair 1 9563
Protoss_Dragoon 3 11183
11183
