Protoss_Forge 1 3104
Protoss_Photon_Cannon 3 6887
Protoss_Gateway 2 9547
Protoss_Nexus 2 10381
Protoss_Assimilator 2 10713
Protoss_Cybernetics_Core 1 6673
Protoss_Zealot 5 10361
Protoss_Stargate 1 8389
Protoss_Citadel_of_Adun 1 8571
Protoss_Corsair 1 8857
10713
