Protoss_Forge 1 3128
Protoss_Photon_Cannon 6 10809
Protoss_Nexus 1 7033
Protoss_Gateway 3 9289
Protoss_Assimilator 2 7466
Protoss_Cybernetics_Core 1 7104
Protoss_Zealot 1 6729
Protoss_Dragoon 1 7851
Protoss_Stargate 1 8907
Protoss_Citadel_of_Adun 1 9073
Protoss_Corsair 2 9961
Protoss_Templar_Archives 1 10163
Protoss_High_Templar 2 10991
Protoss_Dark_Templar 1 11133
11133
