Protoss_Forge 1 3729
Protoss_Nexus 1 6149
Protoss_Photon_Cannon 2 5107
Protoss_Gateway 2 8715
Protoss_Assimilator 2 7551
Protoss_Cybernetics_Core 1 6817
Protoss_Zealot 9 10819
Protoss_Stargate 1 8079
Protoss_Dragoon 1 7895
Protoss_Citadel_of_Adun 1 8565
Protoss_Corsair 4 10565
Protoss_Templar_Archives 1 11156
11156
