Protoss_Forge 1 3278
Protoss_Photon_Cannon 4 10243
Protoss_Nexus 1 6674
Protoss_Gateway 3 9707
Protoss_Assimilator 2 7401
Protoss_Cybernetics_Core 1 6802
Protoss_Zealot 3 7839
Protoss_Stargate 1 8126
Protoss_Citadel_of_Adun 1 8155
Protoss_Corsair 1 8655
Protoss_Templar_Archives 1 9306
Protoss_Robotics_Facility 1 10534
Protoss_High_Templar 2 10491
Protoss_Dark_Templar 1 10729
10729
