Protoss_Gateway 2 8354
Protoss_Assimilator 1 3293
Protoss_Zealot 6 9877
Protoss_Cybernetics_Core 1 5266
Protoss_Dragoon 3 8303
Protoss_Stargate 1 6928
Protoss_Corsair 3 9565
Protoss_Citadel_of_Adun 1 8970
Protoss_Templar_Archives 1 9980
Protoss_Forge 1 9516
Protoss_Photon_Cannon 1 10598
Protoss_Dark_Templar 2 10969
10969
