Protoss_Forge 1 3526
Protoss_Photon_Cannon 3 11107
Protoss_Nexus 1 7405
Protoss_Gateway 2 10723
Protoss_Assimilator 2 9072
Protoss_Zealot 4 9955
Protoss_Cybernetics_Core 1 7772
Protoss_Stargate 1 9016
Protoss_Citadel_of_Adun 1 8957
Protoss_Corsair 2 10653
Protoss_Templar_Archives 1 10304
11107
