Protoss_Gateway 2 4048
Protoss_Zealot 11 8691
Protoss_Assimilator 1 4950
Protoss_Cybernetics_Core 1 7458
Protoss_Citadel_of_Adun 1 8458
Protoss_Forge 1 8305
Protoss_Templar_Archives 1 9596
Protoss_Photon_Cannon 3 10599
Protoss_High_Templar 2 10446
Protoss_Nexus 1 12598
12598
