Protoss_Gateway 2 3961
Protoss_Zealot 13 10327
Protoss_Assimilator 1 6159
Protoss_Cybernetics_Core 1 8083
Protoss_Citadel_of_Adun 1 9193
Protoss_Dragoon 1 9217
Protoss_Stargate 1 9778
Protoss_Corsair 1 10229
Protoss_Templar_Archives 1 10933
Protoss_Forge 1 10734
10933
