Protoss_Gateway 2 6990
Protoss_Assimilator 1 3271
Protoss_Zealot 8 10015
Protoss_Cybernetics_Core 1 5385
Protoss_Citadel_of_Adun 1 6504
Protoss_Dragoon 1 6361
Protoss_Templar_Archives 1 7663
Protoss_High_Templar 4 10934
Protoss_Forge 1 8794
Protoss_Dark_Templar 2 9343
Protoss_Archon 1 8706
Protoss_Photon_Cannon 2 9996
10934
