Protoss_Nexus 1 5843
Protoss_Gateway 1 4703
Protoss_Forge 1 4909
Protoss_Assimilator 2 6716
Protoss_Photon_Cannon 2 10743
Protoss_Cybernetics_Core 1 6269
Protoss_Zealot 2 7713
Protoss_Dragoon 1 7017
Protoss_Stargate 1 7889
Protoss_Robotics_Facility 1 8970
Protoss_Corsair 5 10739
Protoss_Shuttle 1 9879
Protoss_Robotics_Support_Bay 1 9589
Protoss_Reaver 1 11089
11089
