Protoss_Nexus 1 5798
Protoss_Gateway 3 10652
Protoss_Forge 1 4890
Protoss_Assimilator 2 7184
Protoss_Photon_Cannon 2 9169
Protoss_Cybernetics_Core 1 6814
Protoss_Zealot 3 10235
Protoss_Stargate 1 8089
Protoss_Dragoon 1 7773
Protoss_Citadel_of_Adun 1 8571
Protoss_Corsair 4 10519
Protoss_Templar_Archives 1 9823
Protoss_Dark_Templar 1 10721
10721
