Protoss_Forge 1 3459
Protoss_Nexus 1 6239
Protoss_Photon_Cannon 1 4867
Protoss_Gateway 2 9536
Protoss_Assimilator 3 9980
Protoss_Cybernetics_Core 1 6893
Protoss_Stargate 1 8151
Protoss_Citadel_of_Adun 1 7969
Protoss_Dragoon 1 8229
Protoss_Corsair 4 10569
Protoss_Zealot 4 10089
Protoss_Templar_Archives 1 10129
Protoss_Dark_Templar 2 11099
11099
