Protoss_Nexus 1 5831
Protoss_Gateway 4 10355
Protoss_Forge 1 4712
Protoss_Assimilator 3 9403
Protoss_Photon_Cannon 1 5671
Protoss_Cybernetics_Core 1 6181
Protoss_Zealot 5 10639
Protoss_Dragoon 1 6997
Protoss_Stargate 1 7535
Protoss_Citadel_of_Adun 1 8355
Protoss_Corsair 2 8639
Protoss_Templar_Archives 1 9490
Protoss_Dark_Templar 1 10267
10639
