Protoss_Gateway 2 3747
Protoss_Zealot 15 10959
Protoss_Assimilator 1 5935
Protoss_Cybernetics_Core 1 7276
Protoss_Citadel_of_Adun 1 8311
Protoss_Templar_Archives 1 9563
Protoss_Forge 1 10251
10959
