Protoss_Forge 1 3245
Protoss_Photon_Cannon 2 4417
Protoss_Nexus 1 6983
Protoss_Gateway 2 9909
Protoss_Assimilator 2 7325
Protoss_Cybernetics_Core 1 7145
Protoss_Zealot 3 8311
Protoss_Stargate 1 8413
Protoss_Citadel_of_Adun 1 8380
Protoss_Corsair 3 10171
Protoss_Templar_Archives 1 9533
Protoss_Dark_Templar 2 10799
10799
