Protoss_Forge 1 3308
Protoss_Photon_Cannon 3 8345
Protoss_Nexus 1 6883
Protoss_Gateway 5 10622
Protoss_Assimilator 2 7212
Protoss_Cybernetics_Core 1 6541
Protoss_Zealot 10 10819
Protoss_Stargate 1 7812
Protoss_Citadel_of_Adun 1 8101
Protoss_Corsair 1 8241
10819
