Protoss_Forge 1 3551
Protoss_Nexus 1 6179
Protoss_Gateway 4 11365
Protoss_Photon_Cannon 2 10462
Protoss_Assimilator 2 10290
Protoss_Zealot 4 9585
Protoss_Cybernetics_Core 1 6393
Protoss_Dragoon 1 7377
Protoss_Stargate 1 8345
Protoss_Corsair 1 8789
Protoss_Citadel_of_Adun 1 9385
Protoss_Templar_Archives 1 10859
Protoss_Robotics_Facility 1 11670
11670
