Protoss_Forge 1 3392
Protoss_Photon_Cannon 2 4501
Protoss_Nexus 1 7173
Protoss_Gateway 4 11052
Protoss_Assimilator 2 8263
Protoss_Zealot 2 10835
Protoss_Cybernetics_Core 1 8210
Protoss_Stargate 1 9453
Protoss_Dragoon 1 9115
Protoss_Citadel_of_Adun 1 10296
Protoss_Corsair 1 9891
11052
