Protoss_Gateway 2 4290
Protoss_Zealot 6 8526
Protoss_Assimilator 1 5113
Protoss_Cybernetics_Core 1 6609
Protoss_Forge 1 6749
Protoss_Dragoon 1 7356
Protoss_Stargate 1 8071
Protoss_Citadel_of_Adun 1 8718
Protoss_Photon_Cannon 4 11173
Protoss_Nexus 1 12005
Protoss_Templar_Archives 1 10814
12005
