Protoss_Gateway 2 10551
Protoss_Zealot 10 10597
Protoss_Nexus 1 6744
Protoss_Assimilator 1 6281
Protoss_Cybernetics_Core 1 8500
Protoss_Stargate 1 9799
Protoss_Citadel_of_Adun 1 10339
Protoss_Corsair 1 10379
Protoss_Templar_Archives 1 11361
11361
