Protoss_Gateway 2 6050
Protoss_Assimilator 1 3316
Protoss_Zealot 13 9453
Protoss_Cybernetics_Core 1 4497
Protoss_Stargate 1 5775
Protoss_Dragoon 1 5491
Protoss_Corsair 1 6303
Protoss_Forge 1 8862
Protoss_Photon_Cannon 4 11151
Protoss_Nexus 1 12154
12154
