Protoss_Forge 2 7549
Protoss_Photon_Cannon 4 9261
Protoss_Gateway 2 5597
Protoss_Zealot 4 9893
Protoss_Nexus 1 9101
Protoss_Assimilator 2 10660
Protoss_Cybernetics_Core 1 8963
Protoss_Stargate 2 11000
Protoss_Dragoon 1 9951
Protoss_Corsair 1 10595
11000
