Protoss_Forge 1 3633
Protoss_Photon_Cannon 3 6596
Protoss_Nexus 1 6559
Protoss_Gateway 4 10973
Protoss_Zealot 6 10945
Protoss_Assimilator 2 8210
Protoss_Cybernetics_Core 1 7991
Protoss_Dragoon 1 8757
Protoss_Stargate 1 9595
Protoss_Citadel_of_Adun 1 10030
Protoss_Corsair 2 10725
10973
