Protoss_Forge 1 3835
Protoss_Photon_Cannon 5 10779
Protoss_Nexus 1 6743
Protoss_Gateway 2 10260
Protoss_Assimilator 2 8259
Protoss_Cybernetics_Core 1 6972
Protoss_Zealot 3 8661
Protoss_Stargate 1 8313
Protoss_Dragoon 1 8149
Protoss_Citadel_of_Adun 1 8591
Protoss_Corsair 2 9457
Protoss_Templar_Archives 1 10176
Protoss_Dark_Templar 2 11149
11149
