Protoss_Forge 1 3597
Protoss_Nexus 1 6191
Protoss_Photon_Cannon 2 5083
Protoss_Gateway 4 11373
Protoss_Assimilator 2 8493
Protoss_Zealot 3 9831
Protoss_Cybernetics_Core 1 7353
Protoss_Stargate 1 8699
Protoss_Citadel_of_Adun 1 8745
Protoss_Corsair 2 9977
Protoss_Templar_Archives 1 9828
Protoss_High_Templar 2 10759
11373
