Protoss_Forge 1 3159
Protoss_Nexus 1 5997
Protoss_Gateway 3 11186
Protoss_Assimilator 2 6736
Protoss_Photon_Cannon 3 10710
Protoss_Cybernetics_Core 1 6391
Protoss_Zealot 5 9881
Protoss_Stargate 1 7725
Protoss_Citadel_of_Adun 1 8131
Protoss_Corsair 5 10799
Protoss_Templar_Archives 1 9559
Protoss_Dark_Templar 1 10723
11186
