Protoss_Forge 1 2958
Protoss_Nexus 1 6025
Protoss_Photon_Cannon 2 6089
Protoss_Gateway 4 11307
Protoss_Assimilator 2 10012
Protoss_Zealot 5 9513
Protoss_Cybernetics_Core 1 7609
Protoss_Stargate 1 8855
Protoss_Citadel_of_Adun 1 9561
Protoss_Corsair 1 9317
11307
