Protoss_Gateway 3 9206
Protoss_Zealot 13 10391
Protoss_Nexus 1 6679
Protoss_Assimilator 2 8004
Protoss_Forge 1 5750
Protoss_Cybernetics_Core 1 6621
Protoss_Photon_Cannon 3 11083
Protoss_Stargate 1 7955
Protoss_Citadel_of_Adun 1 8254
Protoss_Corsair 2 10087
Protoss_Templar_Archives 1 10089
11083
