Protoss_Forge 1 2795
Protoss_Photon_Cannon 2 4191
Protoss_Nexus 1 6691
Protoss_Gateway 2 9129
Protoss_Assimilator 2 7837
Protoss_Cybernetics_Core 1 6645
Protoss_Zealot 10 10921
Protoss_Stargate 1 7911
Protoss_Corsair 3 9839
Protoss_Citadel_of_Adun 1 9009
Protoss_Templar_Archives 1 11300
11300
