Protoss_Gateway 2 3903
Protoss_Zealot 9 10851
Protoss_Nexus 2 11939
Protoss_Assimilator 1 5481
Protoss_Cybernetics_Core 1 6829
Protoss_Stargate 1 8142
Protoss_Dragoon 2 8121
Protoss_Citadel_of_Adun 1 8886
Protoss_Corsair 2 9227
Protoss_Forge 1 8930
Protoss_Photon_Cannon 1 10781
11939
