Protoss_Gateway 2 6582
Protoss_Assimilator 1 3184
Protoss_Cybernetics_Core 1 4323
Protoss_Zealot 11 9687
Protoss_Stargate 1 5555
Protoss_Dragoon 1 5805
Protoss_Corsair 1 5963
Protoss_Citadel_of_Adun 1 7802
Protoss_Templar_Archives 1 9573
Protoss_Dark_Templar 2 10577
10577
