Protoss_Forge 1 3269
Protoss_Nexus 1 6280
Protoss_Photon_Cannon 1 4807
Protoss_Gateway 5 11413
Protoss_Assimilator 2 10153
Protoss_Zealot 8 10477
Protoss_Cybernetics_Core 1 6999
Protoss_Stargate 1 8327
Protoss_Citadel_of_Adun 1 9057
Protoss_Corsair 1 9003
11413
