Protoss_Forge 1 3222
Protoss_Nexus 1 6077
Protoss_Photon_Cannon 2 9021
Protoss_Gateway 4 10185
Protoss_Assimilator 2 7355
Protoss_Zealot 5 9103
Protoss_Cybernetics_Core 1 6935
Protoss_Stargate 1 8400
Protoss_Citadel_of_Adun 1 8509
Protoss_Corsair 1 9057
Protoss_Templar_Archives 1 9709
Protoss_High_Templar 4 10931
10931
