Protoss_Gateway 2 3831
Protoss_Zealot 12 10401
Protoss_Nexus 1 7423
Protoss_Assimilator 1 5861
Protoss_Cybernetics_Core 1 7086
Protoss_Stargate 1 8379
Protoss_Dragoon 1 8171
Protoss_Forge 1 8379
Protoss_Corsair 3 10215
Protoss_Photon_Cannon 5 10937
10937
