Protoss_Forge 1 3088
Protoss_Photon_Cannon 3 4526
Protoss_Gateway 2 6224
Protoss_Zealot 10 9143
Protoss_Nexus 1 11426
Protoss_Assimilator 2 10506
Protoss_Cybernetics_Core 1 10810
11426
