Protoss_Forge 1 3661
Protoss_Nexus 1 6015
Protoss_Photon_Cannon 4 10581
Protoss_Gateway 4 10967
Protoss_Assimilator 2 6950
Protoss_Cybernetics_Core 1 6851
Protoss_Zealot 3 8790
Protoss_Stargate 1 8077
Protoss_Dragoon 1 7619
Protoss_Citadel_of_Adun 1 8379
Protoss_Corsair 3 9875
Protoss_Templar_Archives 1 9371
Protoss_Dark_Templar 2 10215
Protoss_High_Templar 2 11047
11047
