Protoss_Forge 1 3340
Protoss_Photon_Cannon 2 4629
Protoss_Nexus 1 7369
Protoss_Gateway 4 10297
Protoss_Assimilator 2 7661
Protoss_Cybernetics_Core 1 7029
Protoss_Zealot 10 10907
Protoss_Stargate 1 8316
Protoss_Citadel_of_Adun 1 8685
Protoss_Corsair 1 8839
Protoss_Templar_Archives 1 10551
10907
