Protoss_Gateway 2 3675
Protoss_Zealot 12 10806
Protoss_Assimilator 1 4867
Protoss_Cybernetics_Core 1 6077
Protoss_Stargate 1 7336
Protoss_Corsair 2 8387
Protoss_Nexus 1 9956
Protoss_Dragoon 2 9692
Protoss_Forge 1 9688
Protoss_Photon_Cannon 1 11080
Protoss_Citadel_of_Adun 1 11413
11413
