Protoss_Gateway 1 3331
Protoss_Assimilator 1 3327
Protoss_Zealot 6 7183
Protoss_Cybernetics_Core 1 5070
Protoss_Dragoon 1 5811
Protoss_Stargate 1 6563
Protoss_Citadel_of_Adun 1 6992
Protoss_Corsair 4 10319
Protoss_Templar_Archives 1 8291
Protoss_Forge 1 8806
Protoss_Dark_Templar 1 9247
Protoss_High_Templar 2 10815
Protoss_Photon_Cannon 1 10674
10815
