Protoss_Gateway 2 3863
Protoss_Zealot 10 10321
Protoss_Nexus 1 8721
Protoss_Assimilator 2 10749
Protoss_Cybernetics_Core 1 7847
Protoss_Stargate 1 9361
Protoss_Forge 1 8892
Protoss_Dragoon 2 10681
Protoss_Corsair 1 9997
Protoss_Photon_Cannon 2 11188
Protoss_Robotics_Facility 1 11791
11791
