Protoss_Forge 1 3256
Protoss_Photon_Cannon 8 10615
Protoss_Nexus 1 6968
Protoss_Gateway 2 10176
Protoss_Assimilator 2 10011
Protoss_Zealot 6 10677
Protoss_Cybernetics_Core 1 8235
Protoss_Citadel_of_Adun 1 9402
Protoss_Templar_Archives 1 10641
10677
