Protoss_Forge 1 3604
Protoss_Photon_Cannon 2 4655
Protoss_Nexus 1 6993
Protoss_Gateway 2 9479
Protoss_Assimilator 2 6982
Protoss_Cybernetics_Core 1 6905
Protoss_Zealot 3 9081
Protoss_Stargate 1 8225
Protoss_Citadel_of_Adun 1 8241
Protoss_Corsair 2 9819
Protoss_Templar_Archives 1 9263
Protoss_Dark_Templar 2 10227
Protoss_High_Templar 2 10979
10979
