Protoss_Forge 1 2882
Protoss_Photon_Cannon 5 10589
Protoss_Nexus 1 6977
Protoss_Gateway 4 11269
Protoss_Assimilator 2 7414
Protoss_Zealot 4 8384
Protoss_Cybernetics_Core 1 6920
Protoss_Citadel_of_Adun 1 7958
Protoss_Templar_Archives 1 8981
Protoss_High_Templar 4 10519
Protoss_Dark_Templar 1 10765
Protoss_Archon 1 10049
11269
