Protoss_Forge 1 3598
Protoss_Nexus 1 6166
Protoss_Photon_Cannon 3 8229
Protoss_Gateway 6 11187
Protoss_Assimilator 2 8083
Protoss_Cybernetics_Core 1 6778
Protoss_Zealot 6 10291
Protoss_Stargate 1 8019
Protoss_Citadel_of_Adun 1 8176
Protoss_Corsair 2 10841
Protoss_Templar_Archives 1 10419
11187
