Protoss_Forge 2 4750
Protoss_Gateway 2 6278
Protoss_Photon_Cannon 7 10975
Protoss_Nexus 1 7493
Protoss_Assimilator 2 7133
Protoss_Cybernetics_Core 1 7299
Protoss_Zealot 4 9041
Protoss_Stargate 1 8621
Protoss_Dragoon 1 8349
Protoss_Corsair 3 10597
Protoss_Robotics_Facility 1 10757
10975
