Protoss_Forge 1 3512
Protoss_Photon_Cannon 4 6869
Protoss_Nexus 1 7615
Protoss_Gateway 2 10945
Protoss_Assimilator 2 10517
Protoss_Cybernetics_Core 1 8941
Protoss_Zealot 4 10753
Protoss_Stargate 1 10223
Protoss_Citadel_of_Adun 1 10454
Protoss_Corsair 1 10643
10945
