Protoss_Gateway 2 9756
Protoss_Assimilator 1 3310
Protoss_Zealot 6 9485
Protoss_Cybernetics_Core 1 5420
Protoss_Stargate 1 6949
Protoss_Dragoon 1 6471
Protoss_Citadel_of_Adun 1 6958
Protoss_Corsair 2 7963
Protoss_Templar_Archives 1 8340
Protoss_Forge 1 8640
Protoss_Dark_Templar 2 11051
Protoss_Photon_Cannon 1 10156
Protoss_High_Templar 1 11049
11051
