Protoss_Gateway 2 3725
Protoss_Zealot 13 10774
Protoss_Assimilator 1 4230
Protoss_Cybernetics_Core 1 5165
Protoss_Stargate 1 6511
Protoss_Dragoon 1 6505
Protoss_Corsair 2 8125
Protoss_Nexus 1 10823
Protoss_Forge 1 9579
Protoss_Citadel_of_Adun 1 10584
Protoss_Photon_Cannon 1 11075
11075
