Protoss_Forge 1 3413
Protoss_Photon_Cannon 3 10267
Protoss_Nexus 1 6992
Protoss_Gateway 4 11302
Protoss_Assimilator 2 7893
Protoss_Cybernetics_Core 1 6851
Protoss_Zealot 4 9591
Protoss_Stargate 1 8148
Protoss_Dragoon 1 7949
Protoss_Citadel_of_Adun 1 8743
Protoss_Corsair 1 8569
Protoss_Templar_Archives 1 9877
Protoss_Dark_Templar 2 10727
11302
