Protoss_Forge 1 3160
Protoss_Photon_Cannon 2 4197
Protoss_Nexus 1 6811
Protoss_Gateway 3 9295
Protoss_Assimilator 2 7777
Protoss_Cybernetics_Core 1 6988
Protoss_Zealot 10 10927
Protoss_Citadel_of_Adun 1 8016
Protoss_Stargate 2 10881
10927
