Protoss_Forge 1 2925
Protoss_Nexus 1 6227
Protoss_Gateway 2 9541
Protoss_Assimilator 2 7203
Protoss_Photon_Cannon 2 9531
Protoss_Cybernetics_Core 1 6382
Protoss_Zealot 3 9109
Protoss_Stargate 1 7669
Protoss_Dragoon 1 7653
Protoss_Citadel_of_Adun 1 7999
Protoss_Corsair 4 10251
Protoss_Templar_Archives 1 9295
Protoss_Dark_Templar 2 10625
Protoss_Robotics_Facility 1 11733
11733
