Protoss_Forge 1 3236
Protoss_Photon_Cannon 5 11010
Protoss_Nexus 1 6429
Protoss_Gateway 2 9360
Protoss_Assimilator 2 8564
Protoss_Zealot 7 10395
Protoss_Cybernetics_Core 1 7375
Protoss_Stargate 1 8741
Protoss_Dragoon 1 8571
Protoss_Corsair 1 9157
Protoss_Citadel_of_Adun 1 10110
Protoss_Templar_Archives 1 11101
11101
