Protoss_Forge 1 3121
Protoss_Photon_Cannon 3 10117
Protoss_Nexus 1 6908
Protoss_Gateway 3 11257
Protoss_Assimilator 2 7474
Protoss_Cybernetics_Core 1 6777
Protoss_Zealot 7 10281
Protoss_Stargate 1 8073
Protoss_Citadel_of_Adun 1 8508
Protoss_Corsair 2 10555
Protoss_Templar_Archives 1 10483
11257
