Protoss_Forge 1 3403
Protoss_Photon_Cannon 3 10149
Protoss_Nexus 1 6967
Protoss_Gateway 4 10121
Protoss_Assimilator 2 7166
Protoss_Cybernetics_Core 1 6723
Protoss_Zealot 3 8961
Protoss_Stargate 1 8189
Protoss_Citadel_of_Adun 1 8332
Protoss_Corsair 1 8661
Protoss_Templar_Archives 1 9365
Protoss_High_Templar 4 10873
10873
