Protoss_Forge 1 3277
Protoss_Photon_Cannon 2 4570
Protoss_Nexus 1 6822
Protoss_Gateway 4 10903
Protoss_Assimilator 2 8008
Protoss_Cybernetics_Core 1 6791
Protoss_Zealot 8 10599
Protoss_Stargate 1 8070
Protoss_Dragoon 1 7961
Protoss_Corsair 3 10133
Protoss_Citadel_of_Adun 1 9231
Protoss_Templar_Archives 1 11331
11331
