Protoss_Forge 1 3487
Protoss_Nexus 1 6029
Protoss_Photon_Cannon 3 9706
Protoss_Gateway 1 5589
Protoss_Assimilator 2 7109
Protoss_Zealot 6 10941
Protoss_Cybernetics_Core 1 6793
Protoss_Stargate 1 8045
Protoss_Robotics_Facility 1 8896
Protoss_Corsair 5 10919
Protoss_Shuttle 1 9897
Protoss_Robotics_Support_Bay 1 9631
Protoss_Reaver 1 11245
Protoss_Citadel_of_Adun 1 11322
11322
