Protoss_Forge 1 3466
Protoss_Nexus 1 6191
Protoss_Photon_Cannon 4 10461
Protoss_Gateway 3 11409
Protoss_Assimilator 3 10417
Protoss_Cybernetics_Core 1 6893
Protoss_Zealot 4 9691
Protoss_Stargate 1 8225
Protoss_Citadel_of_Adun 1 8621
Protoss_Corsair 2 9727
Protoss_Templar_Archives 1 9803
Protoss_High_Templar 2 10671
11409
