Protoss_Gateway 2 3885
Protoss_Zealot 10 8091
Protoss_Nexus 2 9832
Protoss_Assimilator 2 9917
Protoss_Cybernetics_Core 1 8727
Protoss_Forge 1 8836
Protoss_Stargate 1 9961
Protoss_Photon_Cannon 1 9799
Protoss_Robotics_Facility 1 11193
Protoss_Corsair 1 10371
11193
