Protoss_Forge 1 3495
Protoss_Photon_Cannon 2 4505
Protoss_Nexus 1 7180
Protoss_Gateway 2 9290
Protoss_Assimilator 2 8029
Protoss_Cybernetics_Core 1 7002
Protoss_Zealot 8 10577
Protoss_Stargate 1 8386
Protoss_Citadel_of_Adun 1 8672
Protoss_Corsair 1 8825
Protoss_Templar_Archives 1 9901
Protoss_Robotics_Facility 1 10935
Protoss_Dark_Templar 1 11007
11007
