Protoss_Forge 1 3291
Protoss_Photon_Cannon 2 4628
Protoss_Nexus 1 7161
Protoss_Gateway 1 5935
Protoss_Assimilator 2 6950
Protoss_Cybernetics_Core 1 7000
Protoss_Zealot 1 6567
Protoss_Stargate 1 8310
Protoss_Dragoon 1 8065
Protoss_Robotics_Facility 1 9373
Protoss_Corsair 4 10763
Protoss_Robotics_Support_Bay 1 9642
Protoss_Reaver 1 11131
11131
