Protoss_Forge 1 3546
Protoss_Nexus 1 6182
Protoss_Photon_Cannon 3 10823
Protoss_Gateway 4 10721
Protoss_Assimilator 2 7175
Protoss_Cybernetics_Core 1 6823
Protoss_Zealot 4 9343
Protoss_Stargate 1 8201
Protoss_Dragoon 1 7897
Protoss_Citadel_of_Adun 1 8623
Protoss_Corsair 2 10491
Protoss_Templar_Archives 1 9740
Protoss_Dark_Templar 2 10531
10823
