Protoss_Forge 1 3282
Protoss_Nexus 1 6133
Protoss_Photon_Cannon 3 10325
Protoss_Gateway 2 8984
Protoss_Assimilator 2 6621
Protoss_Cybernetics_Core 1 6903
Protoss_Zealot 7 10555
Protoss_Stargate 1 8152
Protoss_Dragoon 1 7759
Protoss_Citadel_of_Adun 1 8470
Protoss_Corsair 3 10323
Protoss_Templar_Archives 1 10852
10852
