Protoss_Forge 1 3077
Protoss_Photon_Cannon 1 4161
Protoss_Nexus 1 6633
Protoss_Gateway 1 5505
Protoss_Assimilator 2 8347
Protoss_Zealot 6 10835
Protoss_Cybernetics_Core 1 7196
Protoss_Dragoon 1 8086
Protoss_Stargate 2 10887
Protoss_Robotics_Facility 1 9783
Protoss_Corsair 3 10605
Protoss_Shuttle 1 10785
Protoss_Robotics_Support_Bay 1 10275
10887
