Protoss_Forge 1 3581
Protoss_Nexus 1 6119
Protoss_Photon_Cannon 3 10236
Protoss_Gateway 3 11344
Protoss_Assimilator 2 7363
Protoss_Cybernetics_Core 1 6649
Protoss_Zealot 5 9781
Protoss_Stargate 1 7915
Protoss_Citadel_of_Adun 1 8788
Protoss_Corsair 5 10927
Protoss_Templar_Archives 1 9809
Protoss_Dark_Templar 2 10681
11344
