Protoss_Forge 1 3217
Protoss_Nexus 1 6257
Protoss_Photon_Cannon 2 5187
Protoss_Gateway 4 10568
Protoss_Assimilator 2 7835
Protoss_Cybernetics_Core 1 7064
Protoss_Zealot 4 8839
Protoss_Stargate 1 8331
Protoss_Citadel_of_Adun 1 8787
Protoss_Corsair 2 9535
Protoss_Templar_Archives 1 9878
10568
