Protoss_Forge 1 3592
Protoss_Nexus 1 6174
Protoss_Photon_Cannon 2 10368
Protoss_Gateway 4 11157
Protoss_Assimilator 2 6902
Protoss_Cybernetics_Core 1 6541
Protoss_Zealot 8 10783
Protoss_Stargate 1 7921
Protoss_Citadel_of_Adun 1 8637
Protoss_Corsair 3 9641
Protoss_Templar_Archives 1 10446
11157
