Protoss_Forge 1 3351
Protoss_Photon_Cannon 5 10418
Protoss_Nexus 1 6857
Protoss_Gateway 1 5711
Protoss_Assimilator 2 6912
Protoss_Cybernetics_Core 1 7075
Protoss_Zealot 2 7935
Protoss_Stargate 1 8409
Protoss_Citadel_of_Adun 1 8841
Protoss_Corsair 4 10717
Protoss_Templar_Archives 1 9947
Protoss_Dark_Templar 1 10903
10903
