Protoss_Forge 1 3377
Protoss_Photon_Cannon 4 10867
Protoss_Nexus 1 6959
Protoss_Gateway 4 11245
Protoss_Assimilator 2 8992
Protoss_Cybernetics_Core 1 6930
Protoss_Zealot 10 10883
Protoss_Dragoon 1 7701
Protoss_Citadel_of_Adun 2 8745
Protoss_Templar_Archives 1 10607
11245
