Protoss_Gateway 2 3923
Protoss_Zealot 14 9777
Protoss_Nexus 2 12157
Protoss_Assimilator 1 5789
Protoss_Cybernetics_Core 1 7081
Protoss_Stargate 1 8347
Protoss_Dragoon 1 7939
Protoss_Forge 1 8111
Protoss_Corsair 3 10311
Protoss_Photon_Cannon 6 11123
12157
