Protoss_Forge 1 3647
Protoss_Nexus 1 6089
Protoss_Photon_Cannon 3 10173
Protoss_Gateway 1 6032
Protoss_Assimilator 2 6933
Protoss_Cybernetics_Core 1 7017
Protoss_Zealot 3 8933
Protoss_Stargate 2 8665
Protoss_Corsair 7 10875
Protoss_Citadel_of_Adun 1 9947
Protoss_Templar_Archives 1 11009
11009
