Protoss_Forge 1 3235
Protoss_Nexus 1 6160
Protoss_Photon_Cannon 3 11008
Protoss_Gateway 3 10527
Protoss_Assimilator 2 7259
Protoss_Cybernetics_Core 1 6708
Protoss_Zealot 3 8987
Protoss_Stargate 1 7933
Protoss_Citadel_of_Adun 1 7986
Protoss_Corsair 5 10957
Protoss_Templar_Archives 1 9077
Protoss_Dark_Templar 2 10875
11008
