Protoss_Forge 1 3022
Protoss_Nexus 1 6137
Protoss_Gateway 2 11108
Protoss_Assimilator 3 7370
Protoss_Photon_Cannon 5 10911
Protoss_Zealot 6 9861
Protoss_Cybernetics_Core 1 6865
Protoss_Stargate 1 8229
Protoss_Dragoon 1 7993
Protoss_Citadel_of_Adun 1 8962
Protoss_Corsair 1 8933
Protoss_Templar_Archives 1 10018
Protoss_Dark_Templar 1 10789
11108
