Protoss_Gateway 2 3723
Protoss_Zealot 9 10587
Protoss_Nexus 1 8485
Protoss_Assimilator 1 6807
Protoss_Cybernetics_Core 1 7849
Protoss_Forge 1 7831
Protoss_Stargate 1 9296
Protoss_Photon_Cannon 4 11051
Protoss_Corsair 1 9737
Protoss_Citadel_of_Adun 1 10905
11051
