Protoss_Gateway 2 6793
Protoss_Assimilator 1 3312
Protoss_Cybernetics_Core 1 4313
Protoss_Zealot 15 10779
Protoss_Stargate 1 5649
Protoss_Dragoon 1 5385
Protoss_Corsair 1 6067
Protoss_Citadel_of_Adun 1 8316
Protoss_Forge 2 9091
Protoss_Templar_Archives 1 10329
Protoss_Dark_Templar 1 11107
11107
