Protoss_Forge 1 3559
Protoss_Nexus 1 6142
Protoss_Photon_Cannon 2 9559
Protoss_Gateway 2 10089
Protoss_Assimilator 2 7095
Protoss_Zealot 4 8553
Protoss_Cybernetics_Core 1 6969
Protoss_Stargate 1 8243
Protoss_Citadel_of_Adun 1 8774
Protoss_Dragoon 1 8873
Protoss_Corsair 4 10637
Protoss_Templar_Archives 1 10179
Protoss_Dark_Templar 2 10943
10943
