Protoss_Forge 1 3637
Protoss_Nexus 1 6083
Protoss_Photon_Cannon 4 10710
Protoss_Gateway 3 10779
Protoss_Assimilator 2 7164
Protoss_Zealot 3 7671
Protoss_Cybernetics_Core 1 7567
Protoss_Stargate 1 8880
Protoss_Dragoon 5 10881
Protoss_Corsair 3 10797
10881
