Protoss_Nexus 1 5809
Protoss_Gateway 4 10408
Protoss_Forge 1 4787
Protoss_Assimilator 2 9732
Protoss_Photon_Cannon 2 6278
Protoss_Zealot 9 10547
Protoss_Cybernetics_Core 1 7467
Protoss_Citadel_of_Adun 1 8694
Protoss_Dragoon 1 8477
Protoss_Templar_Archives 1 10102
10547
