Protoss_Forge 1 3192
Protoss_Photon_Cannon 3 10969
Protoss_Nexus 1 6429
Protoss_Gateway 1 5521
Protoss_Assimilator 2 8296
Protoss_Cybernetics_Core 1 6755
Protoss_Zealot 6 10909
Protoss_Stargate 1 8098
Protoss_Citadel_of_Adun 1 8896
Protoss_Corsair 3 10115
Protoss_Templar_Archives 1 9887
Protoss_Robotics_Facility 1 11811
11811
