Protoss_Forge 1 3061
Protoss_Nexus 1 6072
Protoss_Gateway 5 10822
Protoss_Photon_Cannon 3 9402
Protoss_Assimilator 2 7521
Protoss_Cybernetics_Core 1 6747
Protoss_Zealot 3 8985
Protoss_Citadel_of_Adun 1 7785
Protoss_Templar_Archives 1 8803
Protoss_High_Templar 2 10305
Protoss_Dark_Templar 1 10299
10822
