Protoss_Gateway 2 3908
Protoss_Zealot 4 8386
Protoss_Assimilator 1 4934
Protoss_Cybernetics_Core 1 6211
Protoss_Citadel_of_Adun 1 7424
Protoss_Dragoon 1 7241
Protoss_Templar_Archives 1 8639
Protoss_Forge 1 8305
Protoss_High_Templar 2 9411
Protoss_Photon_Cannon 6 11184
Protoss_Archon 1 9545
11184
