Protoss_Forge 1 3371
Protoss_Nexus 1 6507
Protoss_Gateway 1 5652
Protoss_Assimilator 2 6977
Protoss_Photon_Cannon 8 10837
Protoss_Cybernetics_Core 1 6738
Protoss_Zealot 4 10521
Protoss_Stargate 1 8031
Protoss_Citadel_of_Adun 1 8595
Protoss_Corsair 5 10941
Protoss_Robotics_Facility 1 11196
11196
