Protoss_Forge 1 3701
Protoss_Nexus 1 6149
Protoss_Photon_Cannon 2 10287
Protoss_Gateway 2 9805
Protoss_Assimilator 2 7134
Protoss_Cybernetics_Core 1 6605
Protoss_Zealot 3 8563
Protoss_Stargate 1 8079
Protoss_Citadel_of_Adun 1 8803
Protoss_Corsair 4 10625
Protoss_Templar_Archives 1 9835
Protoss_Dark_Templar 2 10603
10625
