Protoss_Forge 1 3272
Protoss_Photon_Cannon 4 11084
Protoss_Nexus 1 6717
Protoss_Gateway 2 9096
Protoss_Zealot 8 10342
Protoss_Assimilator 2 7544
Protoss_Cybernetics_Core 1 7303
Protoss_Stargate 1 8636
Protoss_Citadel_of_Adun 1 8726
Protoss_Corsair 3 10665
Protoss_Templar_Archives 1 10508
11084
