Protoss_Forge 1 3118
Protoss_Nexus 1 6183
Protoss_Gateway 3 10410
Protoss_Photon_Cannon 3 10149
Protoss_Assimilator 2 7644
Protoss_Cybernetics_Core 1 6507
Protoss_Zealot 7 10599
Protoss_Stargate 1 8119
Protoss_Citadel_of_Adun 1 8465
Protoss_Corsair 2 10259
Protoss_Templar_Archives 1 10576
10599
