Protoss_Nexus 1 5831
Protoss_Forge 1 4709
Protoss_Gateway 4 10661
Protoss_Photon_Cannon 3 10904
Protoss_Assimilator 2 6904
Protoss_Cybernetics_Core 1 6842
Protoss_Zealot 9 10531
Protoss_Stargate 1 8160
Protoss_Citadel_of_Adun 1 8680
Protoss_Corsair 2 9169
Protoss_Templar_Archives 1 10203
Protoss_Dark_Templar 2 10951
10951
