Protoss_Forge 1 3635
Protoss_Nexus 1 6269
Protoss_Photon_Cannon 2 10737
Protoss_Gateway 2 9560
Protoss_Assimilator 2 8271
Protoss_Cybernetics_Core 1 6883
Protoss_Zealot 8 10777
Protoss_Stargate 1 8206
Protoss_Citadel_of_Adun 1 8318
Protoss_Dragoon 1 8303
Protoss_Corsair 1 8911
10777
