Protoss_Forge 1 3549
Protoss_Nexus 1 6111
Protoss_Photon_Cannon 2 5275
Protoss_Gateway 2 10671
Protoss_Assimilator 2 6996
Protoss_Cybernetics_Core 1 6876
Protoss_Zealot 4 10359
Protoss_Stargate 1 8361
Protoss_Citadel_of_Adun 1 8717
Protoss_Corsair 3 10255
10671
