Protoss_Forge 1 2956
Protoss_Nexus 1 6141
Protoss_Gateway 4 8706
Protoss_Assimilator 2 10080
Protoss_Photon_Cannon 2 10123
Protoss_Cybernetics_Core 1 6373
Protoss_Zealot 11 10465
Protoss_Stargate 1 7750
Protoss_Corsair 2 8963
Protoss_Citadel_of_Adun 1 10199
10465
