Protoss_Forge 1 3208
Protoss_Photon_Cannon 2 10218
Protoss_Nexus 1 6600
Protoss_Gateway 2 9886
Protoss_Assimilator 2 6847
Protoss_Cybernetics_Core 1 6517
Protoss_Zealot 3 8939
Protoss_Stargate 1 7847
Protoss_Citadel_of_Adun 1 8704
Protoss_Corsair 4 10447
Protoss_Templar_Archives 1 9721
Protoss_Dark_Templar 2 10703
10703
