Protoss_Forge 1 3213
Protoss_Nexus 1 6301
Protoss_Gateway 4 9683
Protoss_Assimilator 2 7913
Protoss_Cybernetics_Core 1 6278
Protoss_Photon_Cannon 4 11095
Protoss_Zealot 10 10597
Protoss_Stargate 1 7726
Protoss_Citadel_of_Adun 1 8305
Protoss_Corsair 2 10739
11095
