Protoss_Forge 1 3323
Protoss_Photon_Cannon 2 10404
Protoss_Nexus 1 6461
Protoss_Gateway 4 10388
Protoss_Assimilator 2 6799
Protoss_Cybernetics_Core 1 6416
Protoss_Zealot 4 8987
Protoss_Stargate 1 7822
Protoss_Citadel_of_Adun 1 8135
Protoss_Corsair 3 9473
Protoss_Templar_Archives 1 9183
Protoss_Dark_Templar 2 9931
10404
