Protoss_Forge 1 3281
Protoss_Photon_Cannon 2 4369
Protoss_Nexus 1 6885
Protoss_Gateway 2 9343
Protoss_Assimilator 2 7981
Protoss_Cybernetics_Core 1 6711
Protoss_Zealot 9 10603
Protoss_Stargate 1 7973
Protoss_Corsair 2 9171
Protoss_Citadel_of_Adun 1 9153
Protoss_Templar_Archives 1 10595
10603
