Protoss_Forge 1 3266
Protoss_Photon_Cannon 3 9980
Protoss_Nexus 1 7136
Protoss_Assimilator 2 7283
Protoss_Gateway 2 9279
Protoss_Zealot 8 10671
Protoss_Cybernetics_Core 1 7326
Protoss_Stargate 1 8609
Protoss_Citadel_of_Adun 1 8611
Protoss_Corsair 1 9017
Protoss_Templar_Archives 1 10912
Protoss_Ground_Weapons_1 1 9953
10912
