Protoss_Nexus 1 5857
Protoss_Gateway 6 11419
Protoss_Forge 1 4577
Protoss_Assimilator 2 7013
Protoss_Photon_Cannon 3 10648
Protoss_Cybernetics_Core 1 6591
Protoss_Zealot 7 9849
Protoss_Stargate 1 7922
Protoss_Citadel_of_Adun 1 8187
Protoss_Corsair 1 8331
Protoss_Templar_Archives 1 9238
Protoss_High_Templar 4 11085
Protoss_Archon 1 10460
11419
