Protoss_Forge 1 3436
Protoss_Nexus 1 6129
Protoss_Photon_Cannon 2 5013
Protoss_Gateway 1 5780
Protoss_Assimilator 2 7124
Protoss_Cybernetics_Core 1 6923
Protoss_Zealot 4 10237
Protoss_Stargate 1 8319
Protoss_Dragoon 1 8077
Protoss_Robotics_Facility 1 9184
Protoss_Corsair 4 10831
Protoss_Shuttle 1 10215
Protoss_Robotics_Support_Bay 1 9651
10831
