Protoss_Forge 1 3452
Protoss_Nexus 1 6100
Protoss_Photon_Cannon 3 10112
Protoss_Gateway 4 11071
Protoss_Assimilator 2 7994
Protoss_Cybernetics_Core 1 6621
Protoss_Zealot 8 10865
Protoss_Stargate 1 8027
Protoss_Corsair 2 9085
Protoss_Citadel_of_Adun 1 9029
11071
