Protoss_Nexus 1 5617
Protoss_Gateway 1 4615
Protoss_Forge 1 4539
Protoss_Assimilator 2 7359
Protoss_Photon_Cannon 5 10175
Protoss_Cybernetics_Core 1 6627
Protoss_Zealot 3 9393
Protoss_Stargate 1 7865
Protoss_Corsair 5 10771
Protoss_Robotics_Facility 1 9852
Protoss_Shuttle 1 10665
Protoss_Robotics_Support_Bay 1 10133
10771
