Protoss_Forge 1 3399
Protoss_Photon_Cannon 4 7399
Protoss_Nexus 1 6867
Protoss_Gateway 1 5915
Protoss_Assimilator 2 10077
Protoss_Cybernetics_Core 1 9172
Protoss_Zealot 3 10357
Protoss_Stargate 1 10626
Protoss_Citadel_of_Adun 1 10874
10874
