Protoss_Forge 1 3632
Protoss_Nexus 1 6198
Protoss_Photon_Cannon 3 10461
Protoss_Gateway 4 11422
Protoss_Assimilator 2 7343
Protoss_Cybernetics_Core 1 6703
Protoss_Zealot 8 10875
Protoss_Stargate 1 7967
Protoss_Corsair 2 8992
Protoss_Citadel_of_Adun 1 9665
Protoss_Templar_Archives 1 11253
11422
