Protoss_Forge 1 3296
Protoss_Nexus 1 6103
Protoss_Photon_Cannon 2 10213
Protoss_Gateway 4 11430
Protoss_Assimilator 2 7317
Protoss_Cybernetics_Core 1 6243
Protoss_Zealot 4 8523
Protoss_Stargate 1 7763
Protoss_Citadel_of_Adun 1 8098
Protoss_Corsair 5 10769
Protoss_Templar_Archives 1 9209
Protoss_Dark_Templar 2 9983
11430
