Protoss_Forge 1 3257
Protoss_Nexus 1 6323
Protoss_Gateway 2 9459
Protoss_Assimilator 2 7537
Protoss_Photon_Cannon 2 10321
Protoss_Cybernetics_Core 1 6562
Protoss_Zealot 4 8725
Protoss_Stargate 1 7828
Protoss_Citadel_of_Adun 1 8209
Protoss_Corsair 4 10707
Protoss_Templar_Archives 1 9338
Protoss_Robotics_Facility 1 10621
Protoss_Dark_Templar 2 10415
10707
