Protoss_Nexus 1 5438
Protoss_Forge 1 3846
Protoss_Photon_Cannon 3 11102
Protoss_Gateway 4 10909
Protoss_Assimilator 2 6622
Protoss_Cybernetics_Core 1 6336
Protoss_Zealot 9 10699
Protoss_Stargate 1 7639
Protoss_Citadel_of_Adun 1 8341
Protoss_Corsair 3 10741
Protoss_Templar_Archives 1 10701
11102
