Protoss_Nexus 1 5665
Protoss_Forge 1 4394
Protoss_Gateway 2 10367
Protoss_Assimilator 2 7445
Protoss_Photon_Cannon 4 11018
Protoss_Cybernetics_Core 1 6327
Protoss_Zealot 7 10287
Protoss_Stargate 1 7565
Protoss_Citadel_of_Adun 1 8108
Protoss_Corsair 1 8045
Protoss_Templar_Archives 1 10217
Protoss_Dark_Templar 2 11175
11175
