Protoss_Forge 1 3173
Protoss_Photon_Cannon 3 10836
Protoss_Nexus 1 6841
Protoss_Gateway 2 9860
Protoss_Assimilator 2 6908
Protoss_Cybernetics_Core 1 6682
Protoss_Zealot 8 10501
Protoss_Stargate 1 7953
Protoss_Citadel_of_Adun 1 8768
Protoss_Corsair 4 10397
Protoss_Templar_Archives 1 11225
11225
