Protoss_Nexus 1 5785
Protoss_Gateway 1 4927
Protoss_Forge 1 4845
Protoss_Assimilator 2 7940
Protoss_Photon_Cannon 4 8951
Protoss_Zealot 4 9969
Protoss_Cybernetics_Core 1 7325
Protoss_Stargate 1 8617
Protoss_Dragoon 1 8265
Protoss_Robotics_Facility 1 9394
Protoss_Corsair 4 10881
Protoss_Shuttle 1 10217
Protoss_Robotics_Support_Bay 1 10510
10881
