Protoss_Nexus 1 5747
Protoss_Forge 1 4240
Protoss_Gateway 1 5236
Protoss_Photon_Cannon 3 10430
Protoss_Assimilator 2 6738
Protoss_Cybernetics_Core 1 6523
Protoss_Zealot 7 10693
Protoss_Stargate 1 7941
Protoss_Citadel_of_Adun 1 8525
Protoss_Corsair 4 10323
Protoss_Robotics_Facility 1 10277
Protoss_Robotics_Support_Bay 1 10371
10693
