Protoss_Gateway 2 9466
Protoss_Assimilator 1 3252
Protoss_Cybernetics_Core 1 4353
Protoss_Zealot 4 8201
Protoss_Stargate 1 5744
Protoss_Dragoon 1 5601
Protoss_Corsair 1 6191
Protoss_Citadel_of_Adun 1 7128
Protoss_Templar_Archives 1 8643
Protoss_Dark_Templar 1 9441
Protoss_Forge 1 9293
Protoss_Nexus 1 11605
Protoss_High_Templar 2 10481
Protoss_Photon_Cannon 3 11048
11605
