Protoss_Forge 1 3233
Protoss_Photon_Cannon 3 10418
Protoss_Nexus 1 6934
Protoss_Gateway 3 9582
Protoss_Assimilator 2 7418
Protoss_Zealot 7 10407
Protoss_Cybernetics_Core 1 6898
Protoss_Stargate 1 8198
Protoss_Citadel_of_Adun 1 8603
Protoss_Corsair 3 10567
Protoss_Templar_Archives 1 10207
10567
