Protoss_Forge 1 3301
Protoss_Photon_Cannon 1 4276
Protoss_Nexus 1 6599
Protoss_Gateway 4 11213
Protoss_Assimilator 2 8416
Protoss_Zealot 8 10359
Protoss_Cybernetics_Core 1 6900
Protoss_Stargate 1 8204
Protoss_Citadel_of_Adun 1 8625
Protoss_Corsair 3 9671
Protoss_Ground_Weapons_1 1 9925
11213
