Protoss_Forge 1 3377
Protoss_Photon_Cannon 3 5823
Protoss_Nexus 1 6899
Protoss_Gateway 4 10949
Protoss_Assimilator 2 7553
Protoss_Zealot 5 9423
Protoss_Cybernetics_Core 1 7432
Protoss_Stargate 1 8731
Protoss_Citadel_of_Adun 1 9254
Protoss_Corsair 1 9145
Protoss_Templar_Archives 1 10247
Protoss_High_Templar 2 11101
11101
