Protoss_Gateway 1 3343
Protoss_Assimilator 1 3376
Protoss_Zealot 7 10596
Protoss_Cybernetics_Core 1 5358
Protoss_Stargate 1 6647
Protoss_Corsair 2 8191
Protoss_Citadel_of_Adun 1 7783
Protoss_Forge 1 8824
Protoss_Nexus 1 11874
Protoss_Templar_Archives 1 11113
11874
