Protoss_Forge 1 3430
Protoss_Photon_Cannon 2 4687
Protoss_Nexus 1 7038
Protoss_Gateway 3 10425
Protoss_Assimilator 2 7602
Protoss_Zealot 5 10419
Protoss_Cybernetics_Core 1 6899
Protoss_Dragoon 1 7695
Protoss_Stargate 1 8355
Protoss_Citadel_of_Adun 1 9197
Protoss_Corsair 3 10765
10765
