Protoss_Forge 1 3300
Protoss_Photon_Cannon 2 4249
Protoss_Nexus 1 7082
Protoss_Gateway 4 11271
Protoss_Assimilator 2 7098
Protoss_Cybernetics_Core 1 6741
Protoss_Zealot 8 10663
Protoss_Stargate 1 8031
Protoss_Citadel_of_Adun 1 8499
Protoss_Corsair 2 9089
Protoss_Templar_Archives 1 10385
11271
