Protoss_Gateway 2 3701
Protoss_Zealot 11 10363
Protoss_Shield_Battery 1 6571
Protoss_Forge 1 6884
Protoss_Photon_Cannon 4 9774
Protoss_Assimilator 1 8608
Protoss_Cybernetics_Core 1 9767
Protoss_Stargate 1 11246
11246
