Protoss_Gateway 4 11365
Protoss_Zealot 7 9327
Protoss_Nexus 1 7366
Protoss_Assimilator 2 8345
Protoss_Cybernetics_Core 1 7375
Protoss_Forge 1 7339
Protoss_Stargate 1 8969
Protoss_Photon_Cannon 3 10754
Protoss_Dragoon 1 8815
Protoss_Citadel_of_Adun 1 9688
Protoss_Corsair 1 9475
Protoss_Templar_Archives 1 10705
11365
