Protoss_Forge 1 3296
Protoss_Photon_Cannon 3 4405
Protoss_Nexus 1 6957
Protoss_Gateway 4 10231
Protoss_Assimilator 2 7667
Protoss_Cybernetics_Core 1 6821
Protoss_Zealot 5 10681
Protoss_Stargate 1 8053
Protoss_Citadel_of_Adun 1 8643
Protoss_Corsair 1 8519
Protoss_Dragoon 1 8939
Protoss_Templar_Archives 1 9637
Protoss_Dark_Templar 1 10467
Protoss_High_Templar 2 11001
11001
