Protoss_Forge 1 3624
Protoss_Photon_Cannon 3 10676
Protoss_Nexus 1 7129
Protoss_Gateway 3 11186
Protoss_Assimilator 2 8023
Protoss_Cybernetics_Core 1 6908
Protoss_Zealot 8 10851
Protoss_Dragoon 1 7651
Protoss_Stargate 1 8369
Protoss_Citadel_of_Adun 1 9083
Protoss_Corsair 2 9503
Protoss_Templar_Archives 1 11121
11186
