Protoss_Forge 1 3621
Protoss_Photon_Cannon 2 10962
Protoss_Nexus 1 6627
Protoss_Gateway 3 8651
Protoss_Assimilator 2 7185
Protoss_Cybernetics_Core 1 6765
Protoss_Zealot 12 10583
Protoss_Dragoon 1 7509
Protoss_Citadel_of_Adun 1 8130
Protoss_Stargate 2 10806
Protoss_Ground_Weapons_1 1 9997
10962
