Protoss_Forge 1 3180
Protoss_Nexus 1 6169
Protoss_Gateway 2 9251
Protoss_Assimilator 2 6613
Protoss_Photon_Cannon 2 10086
Protoss_Zealot 10 10945
Protoss_Cybernetics_Core 1 6675
Protoss_Stargate 1 7937
Protoss_Citadel_of_Adun 1 8359
Protoss_Corsair 4 10767
10945
