Protoss_Forge 1 3612
Protoss_Nexus 1 6293
Protoss_Photon_Cannon 3 10297
Protoss_Gateway 3 8649
Protoss_Assimilator 2 9018
Protoss_Cybernetics_Core 1 6739
Protoss_Zealot 12 10813
Protoss_Citadel_of_Adun 1 8049
Protoss_Stargate 2 10087
Protoss_Corsair 2 10829
Protoss_Ground_Weapons_1 1 9921
10829
