Protoss_Forge 1 3259
Protoss_Nexus 1 6295
Protoss_Gateway 5 11014
Protoss_Assimilator 2 6766
Protoss_Photon_Cannon 2 9174
Protoss_Cybernetics_Core 1 6481
Protoss_Zealot 4 8601
Protoss_Stargate 1 7791
Protoss_Citadel_of_Adun 1 8035
Protoss_Corsair 1 8249
Protoss_Templar_Archives 1 9481
Protoss_High_Templar 4 10699
11014
