Protoss_Forge 1 3241
Protoss_Photon_Cannon 3 10526
Protoss_Nexus 1 6663
Protoss_Gateway 1 5589
Protoss_Assimilator 2 7356
Protoss_Zealot 4 9591
Protoss_Cybernetics_Core 1 7048
Protoss_Stargate 1 8436
Protoss_Dragoon 1 8243
Protoss_Corsair 4 10857
Protoss_Robotics_Facility 1 10230
10857
