Protoss_Forge 1 3088
Protoss_Photon_Cannon 3 10705
Protoss_Nexus 1 6467
Protoss_Gateway 2 9935
Protoss_Assimilator 2 7941
Protoss_Zealot 5 9657
Protoss_Cybernetics_Core 1 7602
Protoss_Stargate 1 8847
Protoss_Citadel_of_Adun 1 9188
Protoss_Corsair 2 10493
Protoss_Templar_Archives 1 10357
10705
