Protoss_Nexus 1 5632
Protoss_Forge 1 4029
Protoss_Photon_Cannon 4 10812
Protoss_Gateway 5 9971
Protoss_Assimilator 2 7023
Protoss_Cybernetics_Core 1 6852
Protoss_Zealot 3 8101
Protoss_Stargate 1 8119
Protoss_Citadel_of_Adun 1 8288
Protoss_Corsair 2 10537
Protoss_Templar_Archives 1 9323
Protoss_High_Templar 4 10441
Protoss_Archon 1 10444
10812
