Protoss_Gateway 3 6528
Protoss_Zealot 14 10925
Protoss_Assimilator 1 4026
Protoss_Cybernetics_Core 1 5883
Protoss_Citadel_of_Adun 1 6903
Protoss_Forge 1 6903
Protoss_Photon_Cannon 3 9568
Protoss_Templar_Archives 1 11093
11093
