Protoss_Forge 1 3492
Protoss_Nexus 1 6185
Protoss_Photon_Cannon 3 10535
Protoss_Gateway 1 5923
Protoss_Assimilator 2 6929
Protoss_Cybernetics_Core 1 7105
Protoss_Zealot 4 9359
Protoss_Stargate 1 8413
Protoss_Robotics_Facility 1 9210
Protoss_Corsair 4 10749
Protoss_Robotics_Support_Bay 1 9568
Protoss_Reaver 1 11207
11207
