Protoss_Gateway 2 4134
Protoss_Zealot 13 10036
Protoss_Assimilator 1 5143
Protoss_Cybernetics_Core 1 6984
Protoss_Forge 1 7780
Protoss_Photon_Cannon 2 9308
Protoss_Nexus 1 11624
Protoss_Citadel_of_Adun 1 10888
11624
