Protoss_Gateway 1 3225
Protoss_Zealot 8 10525
Protoss_Forge 1 3911
Protoss_Photon_Cannon 5 8579
Protoss_Assimilator 1 6631
Protoss_Cybernetics_Core 1 9811
Protoss_Citadel_of_Adun 1 10951
Protoss_Stargate 1 11529
11529
