Protoss_Gateway 1 3328
Protoss_Assimilator 1 3213
Protoss_Cybernetics_Core 1 4348
Protoss_Stargate 1 5593
Protoss_Corsair 2 6613
Protoss_Forge 1 6654
Protoss_Robotics_Facility 1 8018
Protoss_Photon_Cannon 2 11113
Protoss_Robotics_Support_Bay 1 8199
Protoss_Shuttle 1 8921
Protoss_Dragoon 2 10006
Protoss_Reaver 2 11115
Protoss_Nexus 1 11980
11980
