Protoss_Forge 1 3123
Protoss_Nexus 1 6329
Protoss_Photon_Cannon 2 10486
Protoss_Assimilator 2 9099
Protoss_Gateway 3 6988
Protoss_Zealot 17 10518
Protoss_Cybernetics_Core 1 9740
10518
