Protoss_Gateway 2 4048
Protoss_Zealot 13 7918
Protoss_Assimilator 1 7143
Protoss_Cybernetics_Core 1 8818
Protoss_Forge 1 8747
Protoss_Robotics_Facility 1 10319
Protoss_Dragoon 1 9801
Protoss_Citadel_of_Adun 1 10746
Protoss_Shuttle 1 11131
11131
