Protoss_Assimilator 1 2633
Protoss_Gateway 1 3805
Protoss_Cybernetics_Core 1 4819
Protoss_Stargate 2 10880
Protoss_Robotics_Facility 1 6528
Protoss_Corsair 7 10895
Protoss_Shuttle 1 7451
Protoss_Fleet_Beacon 1 8768
Protoss_Forge 1 8532
Protoss_Photon_Cannon 1 9571
10895
