Protoss_Gateway 2 4001
Protoss_Zealot 10 7526
Protoss_Assimilator 1 6225
Protoss_Nexus 1 10976
Protoss_Cybernetics_Core 1 9890
Protoss_Dragoon 1 10646
Protoss_Robotics_Facility 1 11513
Protoss_Stargate 1 11453
11513
