Protoss_Gateway 1 3377
Protoss_Assimilator 1 3402
Protoss_Zealot 8 9503
Protoss_Cybernetics_Core 1 5566
Protoss_Citadel_of_Adun 1 6682
Protoss_Forge 1 6595
Protoss_Templar_Archives 1 9350
Protoss_Photon_Cannon 3 10078
Protoss_High_Templar 2 11117
11117
