Protoss_Gateway 2 9048
Protoss_Assimilator 1 3362
Protoss_Cybernetics_Core 1 4436
Protoss_Robotics_Facility 1 6077
Protoss_Dragoon 3 8261
Protoss_Zealot 1 6188
Protoss_Shuttle 1 6891
Protoss_Observatory 1 6550
Protoss_Observer 2 8236
Protoss_Stargate 1 8345
Protoss_Corsair 4 10748
Protoss_Robotics_Support_Bay 1 8961
Protoss_Forge 1 9623
Protoss_Nexus 1 12595
Protoss_Reaver 1 11546
12595
