Protoss_Gateway 1 3294
Protoss_Forge 2 7802
Protoss_Zealot 6 10311
Protoss_Assimilator 1 4596
Protoss_Cybernetics_Core 1 5632
Protoss_Dragoon 1 6421
Protoss_Stargate 1 7851
Protoss_Corsair 2 8936
Protoss_Citadel_of_Adun 1 8856
Protoss_Photon_Cannon 2 10526
Protoss_Nexus 1 11483
Protoss_Templar_Archives 1 11081
Protoss_Shield_Battery 1 10473
11483
