Protoss_Gateway 1 3283
Protoss_Assimilator 2 4588
Protoss_Zealot 5 7591
Protoss_Cybernetics_Core 1 6193
Protoss_Stargate 1 7554
Protoss_Forge 1 7064
Protoss_Corsair 4 10846
Protoss_Citadel_of_Adun 1 8728
Protoss_Templar_Archives 1 9814
Protoss_Nexus 1 12133
Protoss_High_Templar 1 10561
Protoss_Photon_Cannon 1 10945
12133
