Protoss_Nexus 1 6018
Protoss_Forge 1 4394
Protoss_Photon_Cannon 6 11103
Protoss_Assimilator 2 7356
Protoss_Gateway 1 7224
Protoss_Cybernetics_Core 1 8428
Protoss_Stargate 1 9932
Protoss_Robotics_Facility 1 10469
Protoss_Corsair 1 10376
Protoss_Shuttle 1 11411
11411
