Protoss_Gateway 2 3928
Protoss_Zealot 5 7421
Protoss_Nexus 1 8462
Protoss_Assimilator 2 9388
Protoss_Cybernetics_Core 1 7547
Protoss_Stargate 1 9223
Protoss_Forge 1 8958
Protoss_Corsair 2 10416
Protoss_Photon_Cannon 3 10783
10783
