Protoss_Gateway 2 4161
Protoss_Zealot 17 10851
Protoss_Assimilator 1 7210
Protoss_Cybernetics_Core 1 8995
Protoss_Citadel_of_Adun 1 10047
Protoss_Dragoon 1 9858
Protoss_Templar_Archives 1 11188
11188
