Protoss_Gateway 1 3409
Protoss_Assimilator 1 3463
Protoss_Zealot 2 5231
Protoss_Cybernetics_Core 1 5134
Protoss_Stargate 1 6418
Protoss_Robotics_Facility 1 7076
Protoss_Dragoon 1 6551
Protoss_Corsair 2 10881
Protoss_Citadel_of_Adun 1 7792
Protoss_Robotics_Support_Bay 1 7383
Protoss_Forge 1 10398
10881
