Protoss_Gateway 2 3878
Protoss_Zealot 15 9781
Protoss_Forge 1 5816
Protoss_Photon_Cannon 3 10673
Protoss_Assimilator 1 8751
Protoss_Cybernetics_Core 1 9995
Protoss_Robotics_Facility 1 11895
11895
