Protoss_Gateway 2 4233
Protoss_Assimilator 1 4168
Protoss_Cybernetics_Core 1 5243
Protoss_Zealot 5 9013
Protoss_Stargate 1 6939
Protoss_Citadel_of_Adun 1 7373
Protoss_Dragoon 1 7436
9013
