Protoss_Assimilator 1 2743
Protoss_Gateway 1 3741
Protoss_Cybernetics_Core 1 4915
Protoss_Stargate 1 6158
Protoss_Robotics_Facility 1 6924
Protoss_Corsair 5 10651
Protoss_Shuttle 1 7731
Protoss_Robotics_Support_Bay 1 7187
Protoss_Reaver 2 11676
Protoss_Air_Weapons_1 1 8511
Protoss_Forge 1 9690
Protoss_Shield_Battery 1 9853
Protoss_Photon_Cannon 2 10750
Protoss_Nexus 1 12708
12708
