Protoss_Nexus 1 5859
Protoss_Gateway 1 4798
Protoss_Forge 1 4613
Protoss_Zealot 2 6273
Protoss_Photon_Cannon 2 7765
Protoss_Assimilator 2 7179
Protoss_Cybernetics_Core 1 7302
Protoss_Stargate 1 8643
8643
