Protoss_Gateway 2 7459
Protoss_Assimilator 1 3650
Protoss_Zealot 8 9786
Protoss_Cybernetics_Core 1 5631
Protoss_Shield_Battery 1 5619
Protoss_Dragoon 1 6541
Protoss_Stargate 1 7073
Protoss_Citadel_of_Adun 1 7642
Protoss_Corsair 1 7486
Protoss_Templar_Archives 1 10005
Protoss_Forge 1 9605
10005
