Protoss_Gateway 3 10341
Protoss_Assimilator 1 3520
Protoss_Zealot 2 5196
Protoss_Forge 1 5146
Protoss_Photon_Cannon 1 6159
Protoss_Cybernetics_Core 1 7093
Protoss_Stargate 1 8452
Protoss_Citadel_of_Adun 1 8267
Protoss_Dragoon 1 8071
Protoss_Corsair 3 10680
Protoss_Ground_Weapons_1 1 9011
10680
