Protoss_Gateway 2 10591
Protoss_Assimilator 1 3308
Protoss_Zealot 4 7878
Protoss_Cybernetics_Core 1 5044
Protoss_Stargate 1 6288
Protoss_Dragoon 1 6253
Protoss_Robotics_Facility 1 7708
Protoss_Shuttle 1 8611
Protoss_Robotics_Support_Bay 1 7903
Protoss_Reaver 1 9921
Protoss_Forge 1 9449
10591
