Protoss_Gateway 2 3865
Protoss_Zealot 7 5722
Protoss_Assimilator 1 6826
Protoss_Cybernetics_Core 1 7516
Protoss_Forge 1 8253
Protoss_Nexus 1 10661
Protoss_Photon_Cannon 3 10505
Protoss_Citadel_of_Adun 1 10403
10661
