Protoss_Forge 1 3092
Protoss_Photon_Cannon 5 9904
Protoss_Nexus 1 7333
Protoss_Gateway 3 9841
Protoss_Assimilator 1 7154
Protoss_Cybernetics_Core 1 8763
Protoss_Zealot 4 10451
Protoss_Citadel_of_Adun 1 9841
Protoss_Templar_Archives 1 11432
11432
