Protoss_Assimilator 1 2782
Protoss_Gateway 1 3700
Protoss_Cybernetics_Core 1 4698
Protoss_Dragoon 1 5446
Protoss_Stargate 1 5998
Protoss_Robotics_Facility 1 6826
Protoss_Corsair 3 8786
Protoss_Zealot 3 8665
Protoss_Robotics_Support_Bay 1 7827
Protoss_Reaver 1 10286
Protoss_Air_Weapons_1 1 9176
10286
