Protoss_Assimilator 1 2702
Protoss_Gateway 1 3708
Protoss_Cybernetics_Core 1 4704
Protoss_Dragoon 1 5456
Protoss_Stargate 2 9402
Protoss_Robotics_Facility 1 7123
Protoss_Corsair 5 10753
Protoss_Shuttle 1 7936
Protoss_Forge 1 8003
Protoss_Robotics_Support_Bay 1 8252
Protoss_Photon_Cannon 3 10554
Protoss_Reaver 1 11236
Protoss_Air_Weapons_1 1 9621
11236
