Protoss_Assimilator 1 2757
Protoss_Gateway 1 3828
Protoss_Cybernetics_Core 1 4848
Protoss_Stargate 1 6118
Protoss_Robotics_Facility 1 7151
Protoss_Corsair 4 9841
Protoss_Forge 1 7320
Protoss_Shuttle 1 8796
Protoss_Robotics_Support_Bay 1 8188
Protoss_Air_Weapons_1 1 8421
Protoss_Reaver 1 10871
10871
