Protoss_Gateway 2 4064
Protoss_Zealot 12 10896
Protoss_Assimilator 1 5787
Protoss_Forge 1 6078
Protoss_Photon_Cannon 5 10613
Protoss_Cybernetics_Core 1 8183
Protoss_Citadel_of_Adun 1 9538
Protoss_Dragoon 1 10031
10896
