Protoss_Assimilator 1 2748
Protoss_Gateway 1 3728
Protoss_Cybernetics_Core 1 4728
Protoss_Stargate 1 6043
Protoss_Dragoon 1 5611
Protoss_Robotics_Facility 1 7085
Protoss_Corsair 5 10741
Protoss_Zealot 2 8001
Protoss_Shuttle 1 8081
Protoss_Forge 1 8361
Protoss_Robotics_Support_Bay 1 9036
Protoss_Photon_Cannon 2 9920
Protoss_Reaver 1 10806
Protoss_Air_Weapons_1 1 9686
10806
