Protoss_Gateway 2 5438
Protoss_Assimilator 1 3734
Protoss_Zealot 14 10781
Protoss_Nexus 1 10413
Protoss_Forge 1 8684
Protoss_Cybernetics_Core 1 9569
Protoss_Photon_Cannon 1 9637
10781
