Protoss_Gateway 2 4055
Protoss_Zealot 4 7525
Protoss_Assimilator 1 4174
Protoss_Cybernetics_Core 1 5830
Protoss_Stargate 1 7055
Protoss_Citadel_of_Adun 1 7556
Protoss_Corsair 2 10609
Protoss_Forge 1 8787
Protoss_Photon_Cannon 1 11069
11069
