Protoss_Forge 1 3009
Protoss_Photon_Cannon 2 4383
Protoss_Nexus 1 7238
Protoss_Gateway 2 7928
Protoss_Assimilator 1 6866
Protoss_Zealot 3 8421
Protoss_Cybernetics_Core 1 8240
Protoss_Stargate 1 9685
9685
