Protoss_Gateway 1 3561
Protoss_Assimilator 1 3483
Protoss_Zealot 6 10031
Protoss_Cybernetics_Core 1 5449
Protoss_Stargate 1 6997
Protoss_Corsair 1 7416
Protoss_Nexus 1 11788
11788
