Protoss_Gateway 2 11109
Protoss_Assimilator 1 3528
Protoss_Zealot 3 7001
Protoss_Cybernetics_Core 1 5651
Protoss_Dragoon 1 6461
Protoss_Stargate 1 7115
Protoss_Citadel_of_Adun 1 7016
Protoss_Corsair 1 7536
Protoss_Forge 1 8305
Protoss_Photon_Cannon 1 9327
Protoss_Nexus 1 11945
11945
