Protoss_Gateway 2 9530
Protoss_Assimilator 2 10478
Protoss_Zealot 3 5526
Protoss_Cybernetics_Core 1 5668
Protoss_Citadel_of_Adun 1 6770
Protoss_Dragoon 1 6701
Protoss_Forge 1 7257
Protoss_Templar_Archives 1 7798
Protoss_Dark_Templar 1 8566
Protoss_Nexus 1 10843
Protoss_High_Templar 3 10376
Protoss_Photon_Cannon 3 10458
10843
