Protoss_Gateway 3 9687
Protoss_Assimilator 1 3559
Protoss_Cybernetics_Core 1 4696
Protoss_Zealot 11 10898
Protoss_Stargate 1 6067
Protoss_Forge 1 5609
Protoss_Corsair 2 7296
Protoss_Citadel_of_Adun 1 8348
Protoss_Ground_Weapons_1 1 9511
10898
