Protoss_Gateway 2 5943
Protoss_Assimilator 1 3906
Protoss_Zealot 3 6141
Protoss_Cybernetics_Core 1 5654
Protoss_Dragoon 1 6581
Protoss_Citadel_of_Adun 1 7145
Protoss_Stargate 1 8322
Protoss_Templar_Archives 1 8194
Protoss_Forge 1 8287
Protoss_Dark_Templar 1 9146
Protoss_Photon_Cannon 3 11073
Protoss_Corsair 1 9461
Protoss_High_Templar 2 10006
Protoss_Nexus 1 11797
11797
