Protoss_Gateway 2 4018
Protoss_Zealot 12 10626
Protoss_Assimilator 1 4966
Protoss_Cybernetics_Core 1 5986
Protoss_Dragoon 1 6771
Protoss_Stargate 1 7483
Protoss_Citadel_of_Adun 1 7748
Protoss_Corsair 1 7941
Protoss_Templar_Archives 1 10693
10693
