Protoss_Gateway 2 4003
Protoss_Assimilator 1 3910
Protoss_Zealot 5 6201
Protoss_Cybernetics_Core 1 7614
Protoss_Forge 1 7975
Protoss_Dragoon 4 10961
Protoss_Photon_Cannon 1 9285
10961
