Protoss_Gateway 2 4048
Protoss_Zealot 5 8481
Protoss_Assimilator 1 4276
Protoss_Cybernetics_Core 1 6128
Protoss_Robotics_Facility 1 8043
Protoss_Dragoon 4 9291
Protoss_Shuttle 1 9691
Protoss_Citadel_of_Adun 1 10049
Protoss_Robotics_Support_Bay 1 9598
Protoss_Reaver 1 11176
Protoss_Templar_Archives 1 11332
11332
