Protoss_Gateway 2 4175
Protoss_Zealot 13 10571
Protoss_Assimilator 1 5085
Protoss_Cybernetics_Core 1 7568
Protoss_Dragoon 1 8451
Protoss_Citadel_of_Adun 1 8893
Protoss_Templar_Archives 1 10543
Protoss_Forge 1 10428
10571
