Protoss_Nexus 1 5814
Protoss_Gateway 3 9597
Protoss_Forge 1 4676
Protoss_Photon_Cannon 6 11198
Protoss_Assimilator 1 6643
Protoss_Zealot 7 10941
Protoss_Cybernetics_Core 1 7769
Protoss_Stargate 1 9078
Protoss_Corsair 2 10386
Protoss_Citadel_of_Adun 1 10628
Protoss_Robotics_Facility 1 11798
11798
