Protoss_Forge 1 3167
Protoss_Photon_Cannon 5 10783
Protoss_Nexus 1 7028
Protoss_Gateway 1 7168
Protoss_Assimilator 2 8585
Protoss_Zealot 2 8711
Protoss_Cybernetics_Core 1 8628
Protoss_Dragoon 1 9443
Protoss_Robotics_Facility 1 10272
Protoss_Stargate 1 10348
Protoss_Robotics_Support_Bay 1 10437
Protoss_Corsair 1 10766
10783
