Protoss_Gateway 2 8873
Protoss_Zealot 8 10181
Protoss_Assimilator 1 4285
Protoss_Cybernetics_Core 1 5508
Protoss_Dragoon 1 7146
Protoss_Robotics_Facility 1 8083
Protoss_Citadel_of_Adun 1 7893
Protoss_Shuttle 1 9331
Protoss_Robotics_Support_Bay 1 8918
Protoss_Reaver 1 10473
10473
