Protoss_Gateway 2 3893
Protoss_Zealot 12 8571
Protoss_Assimilator 1 5648
Protoss_Cybernetics_Core 1 7828
Protoss_Citadel_of_Adun 1 8828
Protoss_Nexus 1 11538
Protoss_Templar_Archives 1 10523
Protoss_Forge 1 10820
11538
