Protoss_Gateway 3 10249
Protoss_Zealot 11 10851
Protoss_Forge 1 4688
Protoss_Photon_Cannon 3 10453
Protoss_Nexus 1 8698
Protoss_Assimilator 2 10608
Protoss_Cybernetics_Core 1 9298
Protoss_Citadel_of_Adun 1 10549
Protoss_Dragoon 1 10666
10851
