Protoss_Gateway 2 4247
Protoss_Zealot 11 9626
Protoss_Assimilator 1 5123
Protoss_Cybernetics_Core 1 6351
Protoss_Dragoon 5 11096
Protoss_Stargate 1 7916
Protoss_Citadel_of_Adun 1 8639
Protoss_Corsair 3 10321
11096
