Protoss_Nexus 1 5923
Protoss_Forge 1 4581
Protoss_Photon_Cannon 3 10743
Protoss_Gateway 4 10403
Protoss_Assimilator 2 7948
Protoss_Cybernetics_Core 1 7918
Protoss_Zealot 9 10766
Protoss_Dragoon 3 9780
Protoss_Citadel_of_Adun 1 10172
10766
