Protoss_Gateway 2 7590
Protoss_Assimilator 1 3448
Protoss_Zealot 9 10551
Protoss_Cybernetics_Core 1 5546
Protoss_Stargate 1 6862
Protoss_Dragoon 1 6748
Protoss_Citadel_of_Adun 1 7332
Protoss_Templar_Archives 1 9668
Protoss_Forge 1 9833
10551
