Protoss_Nexus 1 6119
Protoss_Forge 1 4741
Protoss_Assimilator 3 10139
Protoss_Photon_Cannon 1 5843
Protoss_Gateway 4 10458
Protoss_Zealot 15 10536
Protoss_Cybernetics_Core 1 7881
Protoss_Citadel_of_Adun 1 9122
Protoss_Templar_Archives 1 11211
11211
