Protoss_Gateway 3 9221
Protoss_Assimilator 1 3533
Protoss_Zealot 3 5251
Protoss_Cybernetics_Core 1 5416
Protoss_Robotics_Facility 1 7105
Protoss_Dragoon 12 10893
Protoss_Observatory 1 7352
Protoss_Observer 1 8311
10893
