Protoss_Gateway 2 7818
Protoss_Assimilator 1 3653
Protoss_Zealot 7 10892
Protoss_Cybernetics_Core 1 5203
Protoss_Citadel_of_Adun 1 6203
Protoss_Templar_Archives 1 8273
Protoss_Forge 1 8311
Protoss_High_Templar 2 9778
Protoss_Photon_Cannon 2 10296
10892
