Protoss_Gateway 3 8598
Protoss_Assimilator 1 3346
Protoss_Zealot 12 10276
Protoss_Cybernetics_Core 1 4923
Protoss_Stargate 1 6279
Protoss_Citadel_of_Adun 1 7148
Protoss_Corsair 1 6876
Protoss_Templar_Archives 1 11022
11022
