Protoss_Gateway 2 3879
Protoss_Zealot 17 10061
Protoss_Assimilator 1 6862
Protoss_Forge 1 8372
Protoss_Cybernetics_Core 1 10178
Protoss_Photon_Cannon 1 10603
Protoss_Citadel_of_Adun 1 11334
11334
