Protoss_Gateway 1 3281
Protoss_Assimilator 1 3474
Protoss_Zealot 8 10362
Protoss_Forge 1 5047
Protoss_Cybernetics_Core 1 6658
Protoss_Citadel_of_Adun 1 7653
Protoss_Dragoon 1 7493
Protoss_Robotics_Facility 1 9003
Protoss_Robotics_Support_Bay 1 9588
Protoss_Ground_Weapons_1 1 9651
10362
