Protoss_Gateway 4 9573
Protoss_Zealot 15 10851
Protoss_Nexus 1 8143
Protoss_Assimilator 1 6492
Protoss_Forge 1 6850
Protoss_Photon_Cannon 1 7914
Protoss_Cybernetics_Core 1 8540
Protoss_Citadel_of_Adun 1 9772
10851
