Protoss_Gateway 2 2543
Protoss_Zealot 12 8886
Protoss_Assimilator 1 4774
Protoss_Forge 1 5960
Protoss_Cybernetics_Core 1 6738
Protoss_Citadel_of_Adun 1 7825
Protoss_Dragoon 1 8181
8886
