Protoss_Gateway 2 4112
Protoss_Zealot 8 8761
Protoss_Assimilator 1 4938
Protoss_Cybernetics_Core 1 6110
Protoss_Dragoon 1 6911
Protoss_Citadel_of_Adun 1 7276
Protoss_Templar_Archives 1 9048
Protoss_Dark_Templar 2 10306
Protoss_Forge 1 9842
Protoss_High_Templar 2 10553
10553
