Protoss_Forge 1 3229
Protoss_Photon_Cannon 7 10661
Protoss_Gateway 2 6796
Protoss_Nexus 1 7858
Protoss_Assimilator 1 6573
Protoss_Zealot 10 10611
Protoss_Cybernetics_Core 1 8349
Protoss_Stargate 1 9596
Protoss_Corsair 2 10726
10726
