Protoss_Gateway 2 9323
Protoss_Forge 1 3571
Protoss_Zealot 9 10456
Protoss_Photon_Cannon 3 9875
Protoss_Assimilator 1 6730
Protoss_Cybernetics_Core 1 8380
Protoss_Dragoon 1 9211
Protoss_Citadel_of_Adun 1 10722
10722
