Protoss_Gateway 1 3368
Protoss_Assimilator 1 3203
Protoss_Cybernetics_Core 1 4425
Protoss_Stargate 1 5709
Protoss_Robotics_Facility 1 6629
Protoss_Corsair 8 10885
Protoss_Forge 1 6942
Protoss_Shuttle 1 7649
Protoss_Robotics_Support_Bay 1 7465
Protoss_Photon_Cannon 2 10614
Protoss_Reaver 1 10635
10885
