Protoss_Forge 1 3928
Protoss_Nexus 1 6503
Protoss_Photon_Cannon 5 10924
Protoss_Assimilator 1 9171
Protoss_Gateway 1 9696
Protoss_Cybernetics_Core 1 10703
Protoss_Zealot 1 10471
10924
