Protoss_Nexus 2 10672
Protoss_Forge 1 4439
Protoss_Assimilator 2 10749
Protoss_Gateway 1 6082
Protoss_Cybernetics_Core 1 7355
Protoss_Photon_Cannon 5 9808
Protoss_Stargate 1 8711
Protoss_Robotics_Facility 1 9306
Protoss_Corsair 2 10271
Protoss_Shuttle 2 11293
Protoss_Ground_Weapons_1 1 9311
11293
