Protoss_Gateway 2 3923
Protoss_Zealot 14 10131
Protoss_Assimilator 1 7598
Protoss_Forge 1 7636
Protoss_Photon_Cannon 2 8723
Protoss_Cybernetics_Core 1 9343
Protoss_Citadel_of_Adun 1 10586
10586
