Protoss_Gateway 2 8069
Protoss_Assimilator 1 3349
Protoss_Zealot 4 6443
Protoss_Cybernetics_Core 1 5151
Protoss_Stargate 1 6693
Protoss_Corsair 1 7111
Protoss_Dragoon 8 11026
Protoss_Robotics_Facility 1 8927
Protoss_Forge 1 8463
Protoss_Photon_Cannon 1 9658
Protoss_Shuttle 1 10531
Protoss_Robotics_Support_Bay 1 10198
11026
