Protoss_Gateway 1 3243
Protoss_Assimilator 1 3425
Protoss_Zealot 6 7671
Protoss_Cybernetics_Core 1 5552
Protoss_Stargate 1 6952
Protoss_Dragoon 1 6576
Protoss_Citadel_of_Adun 1 7456
Protoss_Scout 1 8371
Protoss_Forge 1 7908
Protoss_Templar_Archives 1 8598
Protoss_Photon_Cannon 4 11168
Protoss_Dark_Templar 1 9346
Protoss_High_Templar 1 10788
Protoss_Nexus 1 12703
12703
