Protoss_Gateway 3 9575
Protoss_Zealot 15 10556
Protoss_Assimilator 1 6243
Protoss_Cybernetics_Core 1 7482
Protoss_Citadel_of_Adun 1 8891
Protoss_Dragoon 1 8961
Protoss_Templar_Archives 1 10411
10556
