Protoss_Gateway 2 3583
Protoss_Zealot 7 5945
Protoss_Assimilator 1 5579
Protoss_Cybernetics_Core 1 7177
Protoss_Forge 1 7483
Protoss_Stargate 1 8640
Protoss_Photon_Cannon 2 9075
Protoss_Corsair 3 10701
10701
