Protoss_Gateway 2 4128
Protoss_Zealot 6 9079
Protoss_Assimilator 1 4519
Protoss_Forge 1 4857
Protoss_Photon_Cannon 1 5797
Protoss_Cybernetics_Core 1 6565
Protoss_Dragoon 1 7347
Protoss_Citadel_of_Adun 1 7706
Protoss_Ground_Weapons_1 1 9245
Protoss_Nexus 1 12308
12308
