Protoss_Gateway 2 4023
Protoss_Zealot 12 9308
Protoss_Cybernetics_Core 1 6118
Protoss_Assimilator 1 6213
Protoss_Dragoon 1 7486
Protoss_Citadel_of_Adun 1 8261
Protoss_Templar_Archives 1 10093
Protoss_Forge 1 9781
Protoss_Nexus 1 12118
12118
