Protoss_Forge 1 2878
Protoss_Nexus 1 6438
Protoss_Photon_Cannon 7 9414
Protoss_Gateway 3 10612
Protoss_Assimilator 2 10212
Protoss_Zealot 5 10566
Protoss_Cybernetics_Core 1 8494
Protoss_Citadel_of_Adun 1 9517
Protoss_Templar_Archives 1 11061
11061
