Protoss_Gateway 2 4030
Protoss_Zealot 14 10781
Protoss_Assimilator 1 5817
Protoss_Cybernetics_Core 1 7546
Protoss_Stargate 1 8906
Protoss_Citadel_of_Adun 1 9065
Protoss_Corsair 1 9321
Protoss_Forge 1 10483
10781
