Protoss_Gateway 2 4089
Protoss_Zealot 11 10396
Protoss_Assimilator 1 5004
Protoss_Cybernetics_Core 1 5915
Protoss_Forge 1 5773
Protoss_Dragoon 1 7041
Protoss_Citadel_of_Adun 1 8123
Protoss_Templar_Archives 1 9453
Protoss_Photon_Cannon 1 10110
Protoss_Ground_Weapons_1 1 9501
Protoss_Nexus 1 12735
12735
