Protoss_Forge 1 2948
Protoss_Nexus 1 6373
Protoss_Photon_Cannon 7 10907
Protoss_Gateway 1 5806
Protoss_Assimilator 2 7751
Protoss_Cybernetics_Core 2 7953
Protoss_Stargate 2 10406
Protoss_Robotics_Facility 1 9805
Protoss_Corsair 3 10731
Protoss_Robotics_Support_Bay 1 9924
Protoss_Reaver 1 11576
11576
