Protoss_Gateway 2 8047
Protoss_Zealot 9 9741
Protoss_Assimilator 1 4069
Protoss_Cybernetics_Core 1 5120
Protoss_Stargate 1 6487
Protoss_Dragoon 1 6171
Protoss_Citadel_of_Adun 1 6953
Protoss_Corsair 1 7016
Protoss_Forge 1 8595
Protoss_Templar_Archives 1 9662
Protoss_High_Templar 2 10866
10866
