Protoss_Gateway 2 3888
Protoss_Zealot 10 9211
Protoss_Forge 1 6418
Protoss_Photon_Cannon 4 10061
Protoss_Nexus 1 10093
Protoss_Assimilator 1 8533
Protoss_Cybernetics_Core 1 11008
11008
