Protoss_Gateway 2 3654
Protoss_Zealot 14 10636
Protoss_Assimilator 1 5303
Protoss_Cybernetics_Core 1 7288
Protoss_Forge 1 7659
Protoss_Dragoon 1 8056
Protoss_Citadel_of_Adun 1 8882
Protoss_Photon_Cannon 1 9613
Protoss_Templar_Archives 1 10883
10883
