Protoss_Gateway 2 3919
Protoss_Zealot 8 9491
Protoss_Forge 1 4618
Protoss_Photon_Cannon 4 10389
Protoss_Nexus 1 8408
Protoss_Assimilator 1 6956
Protoss_Cybernetics_Core 1 8455
Protoss_Stargate 1 9882
Protoss_Corsair 1 10601
10601
