Protoss_Gateway 2 3688
Protoss_Zealot 13 10416
Protoss_Forge 1 5128
Protoss_Photon_Cannon 2 7598
Protoss_Nexus 1 9903
Protoss_Assimilator 1 8548
Protoss_Cybernetics_Core 1 9868
Protoss_Stargate 1 11571
11571
