Protoss_Forge 1 3017
Protoss_Nexus 1 6518
Protoss_Photon_Cannon 7 8798
Protoss_Gateway 3 9519
Protoss_Zealot 9 10863
Protoss_Assimilator 1 8546
Protoss_Cybernetics_Core 1 10513
10863
