Protoss_Forge 1 3852
Protoss_Nexus 2 12655
Protoss_Photon_Cannon 3 10881
Protoss_Gateway 3 8521
Protoss_Assimilator 2 8274
Protoss_Cybernetics_Core 1 6503
Protoss_Zealot 2 8383
Protoss_Stargate 1 7873
Protoss_Citadel_of_Adun 1 8119
Protoss_Corsair 1 8521
Protoss_Templar_Archives 1 9409
Protoss_Dark_Templar 1 10195
Protoss_Robotics_Facility 1 11831
12655
