Protoss_Gateway 3 10755
Protoss_Assimilator 1 3393
Protoss_Zealot 10 10546
Protoss_Cybernetics_Core 1 5423
Protoss_Stargate 1 7053
Protoss_Dragoon 1 6741
Protoss_Forge 1 6971
Protoss_Corsair 1 7481
Protoss_Citadel_of_Adun 1 8593
Protoss_Photon_Cannon 1 10448
Protoss_Robotics_Facility 1 11826
11826
