Protoss_Gateway 1 3505
Protoss_Assimilator 1 3548
Protoss_Zealot 3 7066
Protoss_Cybernetics_Core 1 5391
Protoss_Robotics_Facility 1 6928
Protoss_Dragoon 1 6396
Protoss_Citadel_of_Adun 1 7688
Protoss_Robotics_Support_Bay 1 7060
Protoss_Reaver 1 8561
Protoss_Templar_Archives 1 8859
Protoss_Forge 1 8517
Protoss_Nexus 1 11281
Protoss_Shield_Battery 1 9208
Protoss_High_Templar 1 10116
Protoss_Photon_Cannon 3 11086
Protoss_Dark_Templar 1 10631
11281
