Protoss_Gateway 2 9887
Protoss_Zealot 3 5791
Protoss_Assimilator 1 4128
Protoss_Cybernetics_Core 1 7284
Protoss_Forge 1 7314
Protoss_Citadel_of_Adun 1 8396
Protoss_Photon_Cannon 2 11153
Protoss_Dragoon 1 8711
Protoss_Templar_Archives 1 9720
Protoss_Dark_Templar 2 10646
11153
