Protoss_Gateway 2 8488
Protoss_Assimilator 1 3418
Protoss_Zealot 3 6648
Protoss_Cybernetics_Core 1 5143
Protoss_Stargate 1 6467
Protoss_Dragoon 1 6136
Protoss_Corsair 1 6896
Protoss_Citadel_of_Adun 1 7413
Protoss_Templar_Archives 1 8413
Protoss_Forge 1 8580
Protoss_Dark_Templar 2 9246
Protoss_Nexus 1 11533
Protoss_Photon_Cannon 3 10457
Protoss_High_Templar 2 10516
11533
