Protoss_Forge 1 2973
Protoss_Photon_Cannon 4 10218
Protoss_Nexus 1 7330
Protoss_Gateway 2 8728
Protoss_Zealot 8 10791
Protoss_Assimilator 2 10296
Protoss_Cybernetics_Core 1 9013
Protoss_Citadel_of_Adun 1 10048
Protoss_Templar_Archives 1 11091
11091
