Protoss_Gateway 2 10089
Protoss_Assimilator 1 3488
Protoss_Zealot 6 8581
Protoss_Cybernetics_Core 1 5526
Protoss_Stargate 1 6903
Protoss_Dragoon 1 6531
Protoss_Corsair 1 7361
Protoss_Citadel_of_Adun 1 7893
Protoss_Forge 1 7530
Protoss_Photon_Cannon 1 8762
Protoss_Templar_Archives 1 9517
Protoss_Dark_Templar 2 10836
Protoss_High_Templar 1 11156
11156
