Protoss_Gateway 1 3347
Protoss_Assimilator 2 4286
Protoss_Zealot 4 6655
Protoss_Forge 1 4915
Protoss_Cybernetics_Core 1 6601
Protoss_Citadel_of_Adun 1 7686
Protoss_Dragoon 1 7497
Protoss_Photon_Cannon 3 10059
Protoss_Templar_Archives 1 8879
Protoss_High_Templar 3 11179
Protoss_Nexus 1 12385
12385
