Protoss_Gateway 1 3273
Protoss_Assimilator 1 3284
Protoss_Zealot 6 8007
Protoss_Cybernetics_Core 1 5495
Protoss_Dragoon 1 6291
Protoss_Stargate 1 6811
Protoss_Citadel_of_Adun 1 7090
Protoss_Corsair 1 7241
Protoss_Templar_Archives 1 8478
Protoss_Forge 1 8282
Protoss_Dark_Templar 1 9281
Protoss_Photon_Cannon 1 9585
Protoss_High_Templar 1 10236
Protoss_Nexus 1 12239
12239
