Protoss_Forge 1 3143
Protoss_Photon_Cannon 6 10666
Protoss_Nexus 1 7397
Protoss_Gateway 2 11194
Protoss_Assimilator 2 7657
Protoss_Zealot 4 9693
Protoss_Cybernetics_Core 1 8184
Protoss_Stargate 1 9554
Protoss_Citadel_of_Adun 1 9923
Protoss_Robotics_Facility 1 10582
Protoss_Corsair 1 9971
Protoss_Templar_Archives 1 11088
11194
