Protoss_Assimilator 1 2758
Protoss_Forge 1 3287
Protoss_Photon_Cannon 1 4534
Protoss_Gateway 3 6413
Protoss_Zealot 13 10472
Protoss_Ground_Weapons_1 1 7156
Protoss_Cybernetics_Core 1 8759
Protoss_Stargate 1 10607
10607
