Protoss_Forge 2 10383
Protoss_Nexus 1 6674
Protoss_Photon_Cannon 2 5843
Protoss_Assimilator 2 8506
Protoss_Gateway 4 10036
Protoss_Zealot 8 9913
Protoss_Cybernetics_Core 1 8171
Protoss_Citadel_of_Adun 1 9543
Protoss_Robotics_Facility 1 11809
11809
