Protoss_Gateway 2 7516
Protoss_Assimilator 1 3303
Protoss_Zealot 3 7391
Protoss_Cybernetics_Core 1 5201
Protoss_Citadel_of_Adun 1 6383
Protoss_Dragoon 1 6371
Protoss_Templar_Archives 1 7414
Protoss_Robotics_Facility 1 8868
Protoss_Dark_Templar 3 10231
Protoss_High_Templar 1 10246
10246
