Protoss_Gateway 2 4113
Protoss_Zealot 11 8851
Protoss_Assimilator 1 5024
Protoss_Cybernetics_Core 1 6657
Protoss_Citadel_of_Adun 1 7969
Protoss_Shield_Battery 1 7478
Protoss_Templar_Archives 1 9069
Protoss_Forge 1 9304
Protoss_Dark_Templar 1 9826
Protoss_High_Templar 2 10578
Protoss_Photon_Cannon 1 10243
10578
