Protoss_Gateway 1 3338
Protoss_Assimilator 2 10860
Protoss_Zealot 2 4991
Protoss_Cybernetics_Core 1 5163
Protoss_Stargate 1 6403
Protoss_Citadel_of_Adun 1 6353
Protoss_Dragoon 1 6921
Protoss_Corsair 1 6851
Protoss_Templar_Archives 1 7478
Protoss_Dark_Templar 2 9218
Protoss_Forge 1 8367
Protoss_Nexus 1 10579
Protoss_Photon_Cannon 3 10123
Protoss_High_Templar 2 10722
10860
