Protoss_Gateway 2 4078
Protoss_Zealot 5 5346
Protoss_Assimilator 1 4976
Protoss_Cybernetics_Core 1 6950
Protoss_Forge 1 7053
Protoss_Citadel_of_Adun 1 8455
Protoss_Nexus 1 11351
Protoss_Photon_Cannon 1 9866
11351
