Protoss_Forge 1 3343
Protoss_Nexus 1 6388
Protoss_Photon_Cannon 7 10788
Protoss_Gateway 1 5613
Protoss_Assimilator 2 8358
Protoss_Zealot 4 9216
Protoss_Cybernetics_Core 1 7473
Protoss_Citadel_of_Adun 1 8555
Protoss_Templar_Archives 1 9599
Protoss_High_Templar 1 10506
10788
