Protoss_Gateway 2 8616
Protoss_Assimilator 1 2347
Protoss_Cybernetics_Core 1 2918
Protoss_Zealot 2 4878
Protoss_Dragoon 1 4126
Protoss_Robotics_Facility 1 4433
Protoss_Shuttle 1 5801
Protoss_Robotics_Support_Bay 1 5928
Protoss_Reaver 2 7823
Protoss_Citadel_of_Adun 1 7148
Protoss_Forge 1 7343
Protoss_Photon_Cannon 1 8080
Protoss_Templar_Archives 1 8438
Protoss_Scarab 1 8898
8898
