Protoss_Nexus 1 5866
Protoss_Forge 1 4241
Protoss_Gateway 3 8197
Protoss_Assimilator 2 7245
Protoss_Photon_Cannon 7 11015
Protoss_Zealot 10 9359
Protoss_Cybernetics_Core 1 6731
Protoss_Citadel_of_Adun 1 7916
Protoss_Templar_Archives 1 8903
Protoss_High_Templar 3 10623
Protoss_Ground_Weapons_1 1 9727
11015
