Protoss_Forge 1 3106
Protoss_Nexus 1 6243
Protoss_Photon_Cannon 2 5739
Protoss_Gateway 5 9073
Protoss_Assimilator 2 7093
Protoss_Cybernetics_Core 1 7524
Protoss_Zealot 12 10556
Protoss_Citadel_of_Adun 1 9303
Protoss_Templar_Archives 1 10551
10556
