Protoss_Gateway 1 3466
Protoss_Assimilator 1 3463
Protoss_Zealot 4 7251
Protoss_Cybernetics_Core 1 5673
Protoss_Stargate 1 6903
Protoss_Citadel_of_Adun 1 7138
Protoss_Corsair 1 7321
Protoss_Templar_Archives 1 8133
Protoss_Dark_Templar 3 10751
Protoss_Forge 1 9670
Protoss_Nexus 1 11844
Protoss_Photon_Cannon 1 10890
11844
