Protoss_Nexus 1 5859
Protoss_Forge 1 4523
Protoss_Photon_Cannon 2 5823
Protoss_Gateway 4 8070
Protoss_Assimilator 2 8789
Protoss_Cybernetics_Core 1 7437
Protoss_Citadel_of_Adun 1 8528
Protoss_Dragoon 1 8347
Protoss_Zealot 12 10347
Protoss_Templar_Archives 1 10905
10905
