Protoss_Forge 1 3580
Protoss_Photon_Cannon 3 10331
Protoss_Nexus 2 11543
Protoss_Gateway 1 5917
Protoss_Assimilator 2 7789
Protoss_Cybernetics_Core 1 6948
Protoss_Stargate 1 8173
Protoss_Corsair 4 10563
Protoss_Robotics_Facility 1 10119
Protoss_Robotics_Support_Bay 1 10263
11543
