Protoss_Gateway 2 8067
Protoss_Assimilator 1 3258
Protoss_Zealot 3 7981
Protoss_Cybernetics_Core 1 5133
Protoss_Stargate 1 6460
Protoss_Dragoon 1 6266
Protoss_Citadel_of_Adun 1 7199
Protoss_Corsair 1 7011
Protoss_Templar_Archives 1 8283
Protoss_Forge 1 8771
Protoss_Dark_Templar 2 9041
Protoss_Nexus 1 11685
Protoss_High_Templar 2 10156
Protoss_Photon_Cannon 1 10874
11685
