Protoss_Forge 1 3010
Protoss_Photon_Cannon 5 11188
Protoss_Nexus 1 7331
Protoss_Gateway 4 10876
Protoss_Assimilator 2 8919
Protoss_Zealot 2 9301
Protoss_Cybernetics_Core 1 7645
Protoss_Citadel_of_Adun 1 9059
Protoss_Templar_Archives 1 10146
Protoss_High_Templar 1 11046
11188
