Protoss_Forge 1 3227
Protoss_Photon_Cannon 5 11076
Protoss_Nexus 1 6783
Protoss_Gateway 3 9499
Protoss_Assimilator 2 7768
Protoss_Cybernetics_Core 1 6668
Protoss_Zealot 1 6517
Protoss_Citadel_of_Adun 1 7947
Protoss_Dragoon 1 8661
Protoss_Templar_Archives 1 9130
Protoss_Dark_Templar 1 9949
Protoss_High_Templar 2 10303
Protoss_Robotics_Facility 1 11443
Protoss_Archon 1 10391
11443
