Protoss_Nexus 1 5727
Protoss_Forge 1 4273
Protoss_Photon_Cannon 2 8235
Protoss_Gateway 4 9029
Protoss_Assimilator 2 7658
Protoss_Cybernetics_Core 1 7117
Protoss_Zealot 7 10291
Protoss_Citadel_of_Adun 1 8317
Protoss_Robotics_Facility 1 11124
11124
