Protoss_Forge 1 3099
Protoss_Nexus 2 9549
Protoss_Gateway 1 5664
Protoss_Photon_Cannon 3 10919
Protoss_Assimilator 2 7027
Protoss_Cybernetics_Core 1 7107
Protoss_Stargate 1 8537
Protoss_Robotics_Facility 2 9933
Protoss_Zealot 1 8906
Protoss_Corsair 4 10947
Protoss_Robotics_Support_Bay 1 9865
Protoss_Shuttle 1 10586
10947
