Protoss_Forge 1 3434
Protoss_Photon_Cannon 2 11199
Protoss_Nexus 1 6595
Protoss_Gateway 4 9514
Protoss_Assimilator 2 10593
Protoss_Cybernetics_Core 1 6883
Protoss_Zealot 11 10793
Protoss_Citadel_of_Adun 1 8336
Protoss_Templar_Archives 1 10201
Protoss_Ground_Weapons_1 1 9763
11199
