Protoss_Forge 1 3578
Protoss_Photon_Cannon 8 10109
Protoss_Nexus 1 6935
Protoss_Gateway 1 6197
Protoss_Assimilator 2 8666
Protoss_Zealot 4 10419
Protoss_Cybernetics_Core 1 7887
Protoss_Stargate 1 9222
Protoss_Corsair 3 10953
Protoss_Citadel_of_Adun 1 11266
11266
