Protoss_Nexus 1 5765
Protoss_Forge 1 4258
Protoss_Gateway 2 7074
Protoss_Photon_Cannon 6 11182
Protoss_Assimilator 2 9440
Protoss_Zealot 10 10661
Protoss_Cybernetics_Core 1 7953
Protoss_Stargate 1 9326
Protoss_Citadel_of_Adun 1 9316
Protoss_Dragoon 1 9231
Protoss_Corsair 2 10456
11182
