Protoss_Forge 2 8954
Protoss_Nexus 1 6293
Protoss_Photon_Cannon 7 11189
Protoss_Gateway 4 11024
Protoss_Assimilator 2 9454
Protoss_Zealot 6 10669
Protoss_Cybernetics_Core 1 7557
Protoss_Citadel_of_Adun 1 9291
Protoss_Templar_Archives 1 10456
11189
