Protoss_Forge 1 3257
Protoss_Nexus 1 6309
Protoss_Photon_Cannon 4 10817
Protoss_Gateway 3 9438
Protoss_Assimilator 2 7369
Protoss_Zealot 1 6275
Protoss_Cybernetics_Core 1 7472
Protoss_Dragoon 1 8213
Protoss_Citadel_of_Adun 1 8497
Protoss_Templar_Archives 1 9487
Protoss_High_Templar 4 10985
Protoss_Dark_Templar 1 10259
Protoss_Robotics_Facility 1 11230
Protoss_Archon 1 10324
11230
