Protoss_Forge 1 3089
Protoss_Photon_Cannon 3 8806
Protoss_Nexus 1 6669
Protoss_Gateway 2 9458
Protoss_Assimilator 2 8941
Protoss_Zealot 5 10923
Protoss_Cybernetics_Core 1 7753
Protoss_Stargate 1 9067
Protoss_Dragoon 1 8717
Protoss_Citadel_of_Adun 1 9952
Protoss_Corsair 1 9487
10923
