Protoss_Nexus 1 5631
Protoss_Forge 1 3981
Protoss_Photon_Cannon 9 11135
Protoss_Gateway 3 7795
Protoss_Assimilator 2 9344
Protoss_Cybernetics_Core 1 6523
Protoss_Zealot 12 10216
Protoss_Citadel_of_Adun 1 7561
Protoss_Templar_Archives 1 9790
Protoss_High_Templar 2 10765
Protoss_Ground_Weapons_1 1 9625
11135
