Protoss_Forge 1 3446
Protoss_Photon_Cannon 3 8648
Protoss_Nexus 1 6619
Protoss_Gateway 2 9888
Protoss_Assimilator 2 6767
Protoss_Cybernetics_Core 1 6885
Protoss_Stargate 1 8157
Protoss_Citadel_of_Adun 1 8209
Protoss_Dragoon 1 8179
Protoss_Corsair 1 8569
Protoss_Templar_Archives 1 9634
Protoss_High_Templar 1 10801
10801
