Protoss_Forge 1 3303
Protoss_Nexus 1 6671
Protoss_Photon_Cannon 4 10922
Protoss_Gateway 4 10935
Protoss_Assimilator 2 8325
Protoss_Cybernetics_Core 1 7119
Protoss_Zealot 10 10275
Protoss_Citadel_of_Adun 1 8207
Protoss_Templar_Archives 1 9814
Protoss_High_Templar 2 11117
11117
