Protoss_Forge 1 2877
Protoss_Photon_Cannon 4 11075
Protoss_Nexus 1 6685
Protoss_Gateway 3 8911
Protoss_Assimilator 1 5586
Protoss_Zealot 12 10423
Protoss_Cybernetics_Core 1 7019
Protoss_Citadel_of_Adun 1 8296
Protoss_Templar_Archives 1 10668
11075
