Protoss_Forge 1 3602
Protoss_Photon_Cannon 6 11133
Protoss_Gateway 5 11148
Protoss_Nexus 1 7063
Protoss_Assimilator 2 7932
Protoss_Zealot 2 7143
Protoss_Cybernetics_Core 1 7839
Protoss_Stargate 1 9470
Protoss_Citadel_of_Adun 1 9652
Protoss_Corsair 2 10706
Protoss_Templar_Archives 1 10868
11148
