Protoss_Gateway 1 3414
Protoss_Assimilator 1 3534
Protoss_Zealot 4 7276
Protoss_Cybernetics_Core 1 5128
Protoss_Dragoon 1 6086
Protoss_Stargate 1 6878
Protoss_Citadel_of_Adun 1 7372
Protoss_Corsair 1 7496
Protoss_Templar_Archives 1 8363
Protoss_Forge 1 7918
Protoss_High_Templar 1 10851
10851
