Protoss_Forge 1 3268
Protoss_Photon_Cannon 2 9673
Protoss_Nexus 1 6829
Protoss_Gateway 2 9701
Protoss_Assimilator 2 7177
Protoss_Zealot 1 6187
Protoss_Cybernetics_Core 1 6906
Protoss_Stargate 1 8277
Protoss_Citadel_of_Adun 1 8441
Protoss_Corsair 3 10163
Protoss_Templar_Archives 1 9460
Protoss_Robotics_Facility 1 10013
Protoss_Dark_Templar 1 10335
Protoss_High_Templar 1 10555
Protoss_Shuttle 1 10835
10835
