Protoss_Gateway 2 11023
Protoss_Assimilator 1 3287
Protoss_Zealot 5 9257
Protoss_Cybernetics_Core 1 6317
Protoss_Stargate 1 7582
Protoss_Dragoon 1 7207
Protoss_Citadel_of_Adun 1 7889
Protoss_Forge 1 8116
Protoss_Corsair 1 8199
Protoss_Templar_Archives 1 9258
Protoss_Photon_Cannon 2 10325
Protoss_Dark_Templar 2 10957
Protoss_Robotics_Facility 1 10956
11023
