Protoss_Forge 1 2965
Protoss_Photon_Cannon 2 4306
Protoss_Nexus 1 7301
Protoss_Gateway 4 9365
Protoss_Assimilator 2 8081
Protoss_Zealot 10 10877
Protoss_Cybernetics_Core 1 7684
Protoss_Citadel_of_Adun 1 8809
Protoss_Templar_Archives 1 10475
Protoss_Robotics_Facility 1 11512
11512
