Protoss_Forge 1 3130
Protoss_Nexus 1 6278
Protoss_Gateway 2 9076
Protoss_Photon_Cannon 7 10428
Protoss_Assimilator 2 7175
Protoss_Zealot 4 7931
Protoss_Cybernetics_Core 1 6942
Protoss_Citadel_of_Adun 1 7976
Protoss_Templar_Archives 1 9104
Protoss_High_Templar 3 10751
10751
