Protoss_Forge 1 3429
Protoss_Nexus 1 6220
Protoss_Gateway 1 5443
Protoss_Assimilator 1 5241
Protoss_Photon_Cannon 1 5821
Protoss_Zealot 2 7917
Protoss_Cybernetics_Core 1 7229
Protoss_Stargate 2 9405
9405
