Protoss_Nexus 1 5681
Protoss_Gateway 3 11033
Protoss_Forge 1 4665
Protoss_Assimilator 2 7760
Protoss_Photon_Cannon 2 10735
Protoss_Zealot 8 10623
Protoss_Cybernetics_Core 1 7358
Protoss_Dragoon 1 8167
Protoss_Stargate 1 9027
Protoss_Citadel_of_Adun 1 8814
Protoss_Corsair 2 10741
Protoss_Templar_Archives 1 10115
Protoss_Ground_Weapons_1 1 9479
11033
