Protoss_Forge 1 3662
Protoss_Nexus 1 6232
Protoss_Photon_Cannon 3 10085
Protoss_Gateway 1 5559
Protoss_Assimilator 2 6887
Protoss_Cybernetics_Core 1 6821
Protoss_Stargate 1 8106
Protoss_Dragoon 1 7713
Protoss_Citadel_of_Adun 1 8442
Protoss_Zealot 1 8225
Protoss_Robotics_Facility 1 9957
10085
