Protoss_Forge 1 3273
Protoss_Photon_Cannon 3 11188
Protoss_Nexus 1 7638
Protoss_Gateway 3 9416
Protoss_Assimilator 2 9910
Protoss_Cybernetics_Core 1 7563
Protoss_Zealot 11 10881
Protoss_Citadel_of_Adun 1 8683
Protoss_Templar_Archives 1 11088
11188
