Protoss_Forge 1 3228
Protoss_Photon_Cannon 5 10813
Protoss_Nexus 1 7179
Protoss_Gateway 2 10059
Protoss_Assimilator 2 7547
Protoss_Cybernetics_Core 1 7141
Protoss_Zealot 3 8259
Protoss_Citadel_of_Adun 1 8176
Protoss_Templar_Archives 1 9528
Protoss_High_Templar 2 11025
11025
