Protoss_Nexus 1 5863
Protoss_Forge 1 4188
Protoss_Photon_Cannon 11 10773
Protoss_Gateway 1 6330
Protoss_Assimilator 2 7964
Protoss_Zealot 1 7051
Protoss_Cybernetics_Core 1 7938
Protoss_Stargate 1 9208
Protoss_Robotics_Facility 1 9838
Protoss_Corsair 2 10341
Protoss_Robotics_Support_Bay 1 9983
Protoss_Reaver 1 11531
11531
