Protoss_Gateway 3 11027
Protoss_Assimilator 1 3312
Protoss_Cybernetics_Core 1 4379
Protoss_Stargate 1 5719
Protoss_Forge 1 5285
Protoss_Photon_Cannon 3 10080
Protoss_Corsair 2 7086
Protoss_Zealot 6 9311
Protoss_Citadel_of_Adun 1 8207
Protoss_Templar_Archives 1 9330
Protoss_Dark_Templar 2 10381
Protoss_Ground_Weapons_1 1 9086
11027
