Protoss_Forge 1 3498
Protoss_Photon_Cannon 7 11091
Protoss_Nexus 1 7289
Protoss_Gateway 3 9401
Protoss_Assimilator 2 7877
Protoss_Zealot 1 6717
Protoss_Cybernetics_Core 1 7279
Protoss_Dragoon 1 8019
Protoss_Citadel_of_Adun 1 8274
Protoss_Templar_Archives 1 9646
Protoss_Dark_Templar 1 10391
Protoss_High_Templar 3 11171
11171
