Protoss_Forge 1 3291
Protoss_Photon_Cannon 3 10815
Protoss_Nexus 1 7193
Protoss_Gateway 3 10338
Protoss_Assimilator 2 7692
Protoss_Cybernetics_Core 1 7380
Protoss_Zealot 2 7508
Protoss_Stargate 1 8619
Protoss_Dragoon 1 8356
Protoss_Citadel_of_Adun 1 9146
Protoss_Corsair 3 10786
Protoss_Templar_Archives 1 10156
Protoss_Dark_Templar 2 10936
10936
