Protoss_Gateway 1 3487
Protoss_Assimilator 2 10532
Protoss_Zealot 4 6471
Protoss_Cybernetics_Core 1 6071
Protoss_Citadel_of_Adun 1 7107
Protoss_Dragoon 1 7313
Protoss_Templar_Archives 1 8119
Protoss_Dark_Templar 1 8859
Protoss_Forge 1 8666
Protoss_Nexus 1 10880
Protoss_High_Templar 2 10449
Protoss_Photon_Cannon 4 11151
11151
