Protoss_Nexus 1 5818
Protoss_Gateway 1 4887
Protoss_Assimilator 2 6808
Protoss_Cybernetics_Core 1 5992
Protoss_Stargate 1 7288
Protoss_Forge 1 7343
Protoss_Corsair 4 9846
Protoss_Robotics_Facility 2 11218
Protoss_Photon_Cannon 7 11059
Protoss_Robotics_Support_Bay 1 8998
Protoss_Reaver 1 10801
11218
