Protoss_Forge 1 3011
Protoss_Nexus 1 6263
Protoss_Gateway 4 10193
Protoss_Photon_Cannon 2 9680
Protoss_Assimilator 2 7113
Protoss_Zealot 7 10846
Protoss_Cybernetics_Core 1 6918
Protoss_Dragoon 1 7993
Protoss_Robotics_Facility 1 9178
Protoss_Citadel_of_Adun 1 9047
Protoss_Shuttle 1 10366
Protoss_Robotics_Support_Bay 1 9753
Protoss_Templar_Archives 1 10794
Protoss_Reaver 1 11508
11508
