Protoss_Gateway 1 3325
Protoss_Assimilator 1 3388
Protoss_Cybernetics_Core 1 4468
Protoss_Stargate 1 5803
Protoss_Dragoon 1 5573
Protoss_Corsair 5 10899
Protoss_Citadel_of_Adun 1 6943
Protoss_Forge 1 6905
Protoss_Nexus 1 9577
Protoss_Templar_Archives 1 8359
Protoss_Dark_Templar 1 9219
Protoss_Photon_Cannon 3 10902
10902
