Protoss_Nexus 1 5788
Protoss_Forge 1 4442
Protoss_Gateway 4 11338
Protoss_Assimilator 2 6698
Protoss_Cybernetics_Core 1 6535
Protoss_Photon_Cannon 1 6504
Protoss_Zealot 4 10611
Protoss_Stargate 1 8163
Protoss_Dragoon 1 7916
Protoss_Citadel_of_Adun 1 8337
Protoss_Corsair 4 10439
Protoss_Templar_Archives 1 9473
Protoss_Dark_Templar 2 10806
11338
