Protoss_Forge 1 3225
Protoss_Photon_Cannon 3 10350
Protoss_Nexus 1 6525
Protoss_Gateway 3 9687
Protoss_Assimilator 2 6906
Protoss_Cybernetics_Core 1 6884
Protoss_Zealot 5 9535
Protoss_Dragoon 1 7649
Protoss_Stargate 1 8237
Protoss_Citadel_of_Adun 1 8459
Protoss_Corsair 2 9301
Protoss_Templar_Archives 1 9488
Protoss_Dark_Templar 2 11199
Protoss_High_Templar 2 10639
11199
