Protoss_Forge 1 3167
Protoss_Photon_Cannon 6 10561
Protoss_Nexus 1 8508
Protoss_Gateway 4 9822
Protoss_Zealot 8 10956
Protoss_Assimilator 1 8873
Protoss_Cybernetics_Core 1 11329
11329
