Protoss_Nexus 1 6066
Protoss_Forge 1 4488
Protoss_Gateway 2 8708
Protoss_Photon_Cannon 1 5622
Protoss_Assimilator 2 7665
Protoss_Zealot 6 10436
Protoss_Cybernetics_Core 1 7433
Protoss_Citadel_of_Adun 1 8607
Protoss_Templar_Archives 1 10552
10552
