Protoss_Forge 1 3123
Protoss_Photon_Cannon 5 11037
Protoss_Nexus 1 6676
Protoss_Gateway 1 6365
Protoss_Assimilator 2 8864
Protoss_Zealot 4 10361
Protoss_Cybernetics_Core 1 8671
Protoss_Stargate 1 9944
Protoss_Citadel_of_Adun 2 10944
Protoss_Corsair 1 10406
11037
