Protoss_Nexus 1 5738
Protoss_Forge 1 4123
Protoss_Photon_Cannon 3 10664
Protoss_Gateway 3 10606
Protoss_Assimilator 2 7380
Protoss_Cybernetics_Core 1 6607
Protoss_Zealot 2 7911
Protoss_Stargate 1 7873
Protoss_Citadel_of_Adun 1 8162
Protoss_Corsair 2 8896
Protoss_Templar_Archives 1 10179
Protoss_Robotics_Facility 1 10757
Protoss_Dark_Templar 1 11011
Protoss_High_Templar 1 11041
11041
