Protoss_Assimilator 1 2813
Protoss_Gateway 1 3814
Protoss_Cybernetics_Core 1 4828
Protoss_Stargate 1 6075
Protoss_Dragoon 1 5646
Protoss_Robotics_Facility 1 6980
Protoss_Corsair 6 9830
Protoss_Forge 1 6666
Protoss_Shuttle 1 8351
Protoss_Photon_Cannon 3 10104
Protoss_Robotics_Support_Bay 1 9469
Protoss_Nexus 1 12168
Protoss_Reaver 1 11226
12168
